[{"job_id": "100003009054657", "location_code": "hk", "company": "Nutri Life Nutrition Consultancy Centre", "job_title": "Registered Dietitian", "description": "To cope with our further expansion, we sincerely invite high caliber candidates to join our team to grow with us together.\n\nJob Description:\n\nProvide nutritional consultation, including weight management, cholesterol, blood pressure, diabetes, gout, cancer and other chronic diseases.\nConduct and participate in health seminars, cooking classes and health promotion workshops\nAssist in research and preparation of nutrition articles\nConduct television and media interviews\n\nRequirements:\u00a0\n\nDegree holders / Master in Nutrition and Dietetics. Registered dietitian with recognized registration body.\nCustomer oriented, caring and empathetic\nExcellent communication and interpersonal skills\nExcellent analytical and presentation skills\nSelf-initiated and willing to work under pressure\nProficiency in spoken and written English and Cantonese. Proficiency in mandarin will be an advantage.\nComputer literate in MS Word, Excel, Photoshop, Powerpoint.\nExperience in providing nutritional and dietary consultation service is an advantage.\nNew graduates will also be considered.\nA rewarding remuneration package will be offer to the right candidate. Interested parties please apply by clicking the \u201cApply now\u201d button below with your present and expected salary.\n\n\nAll information received will be kept in strict confidential and only for employment-related purposes.", "employment_types": ["Full Time"], "selling_points": ["Provide nutritional and dietary advices", "Conduct health seminars and workshops", "Registered dietitian with recognized registration"], "locations": ["Tsim Sha Tsui"], "categories": ["Beauty Care / Health", "Nutritionist"], "post_time": "2022-01-17T16:02:09Z", "salary": {"currency": "HKD", "max": 34999, "min": 20000, "period": "monthly", "term": null}, "salary_visible": true, "title_keywords": ["dietitian"], "responsibilities": ["management"], "requirements": {"degrees": ["degree", "master"], "majors": [], "languages": ["cantonese", "english", "mandarin"], "language_level": ["advantage", "proficiency"], "hard_skills": ["excel", "photoshop", "powerpoint", "ms word"], "soft_skills": ["presentation skills", "communication and interpersonal skills", "work under pressure"], "languages_combined": [{"language": "cantonese", "language_level": []}, {"language": "english", "language_level": []}, {"language": "mandarin", "language_level": ["proficiency", "advantage"]}]}, "experience_required": {"duration": [], "field": []}}, {"job_id": "100003009052440", "location_code": "hk", "company": "Twin Wealth Biotech Limited", "job_title": "Sales & Marketing Executive", "description": "Responsibilities\n\nDrive sales to achieve company's assigned sales target;\nDevelop strategy and content for digital marketing & social media platforms across different markets and to evaluate effectiveness of different marketing campaigns;\nPerform sales analysis and gather market information for sales and marketing strategies' formulation;\nPlan & execute marketing activities for assigned product portfolio to increase brand awareness, expand customer base, engagement and achieve sales target;\nMonitor and maintain good relationship with existing distributors to maximize sales and profits;\nProactively develop new distribution channels to ensure continuous business growth and expand market coverage;\nManage internal designers & work closely with third parties for advertisements' production;\nMonitoring A&P expenditure & product budget;\nOrganize and support exhibitions, events & brand activities year-round\nSupport ad-hoc projects and marketing activities as assigned.\n\nRequirements\n\nUniversity degree holder in Marketing / Health Technology / Nutriology / Biology Chemistry or related discipline;\u00a0 candidate with science background is preferable\nExperience in digital marketing and social media marketing is a must\nCreative, detail oriented, outgoing and result-oriented with excellent interpersonal communication skill;\nProficiency in both spoken and written English and Chinese (Mandarin is an asset);\nAble to work under pressure with multi-tasking skill, willing to learn;\nHigh sense of responsibility, mature and self-initiative;\nExcellent PC skills;\n\nInterested parties please apply in full resume including current and expected salary by clicking\u00a0'Apply Now'.\u00a0To know more about\u00a0us, please visit our company website at\u00a0http://www.healthbank.com.hk.\n\nAll information received will be kept in strict confidence and only be used for employment-related purposes.", "employment_types": ["Full Time", "Permanent"], "selling_points": [], "locations": ["Central & Western Area"], "categories": ["Beauty Care / Health", "Nutritionist", "Marketing / Public Relations", "Marketing - Brand / Product Management", "Sales, CS & Business Devpt", "Sales - Sales Management"], "post_time": "2022-01-17T03:02:28Z", "salary": {"currency": null, "max": null, "min": null, "period": "monthly", "term": null}, "salary_visible": false, "title_keywords": ["sales & marketing executive"], "responsibilities": ["market information", "marketing strategies", "advertisements", "sales target", "social media platforms", "analysis", "monitor", "monitoring", "develop", "evaluate", "maintain good relationship", "budget", "digital marketing", "marketing campaigns", "plan", "drive sales", "ad-hoc projects"], "requirements": {"degrees": ["university degree"], "majors": ["chemistry", "biology", "marketing"], "languages": ["english", "chinese", "mandarin"], "language_level": ["proficiency"], "hard_skills": ["pc skills"], "soft_skills": ["outgoing", "multi-tasking skill", "interpersonal", "detail oriented", "communication skill", "willing to learn", "high sense of responsibility", "mature", "self-initiative", "creative", "result-oriented", "work under pressure"], "languages_combined": [{"language": "english", "language_level": ["proficiency"]}, {"language": "chinese", "language_level": ["proficiency"]}, {"language": "mandarin", "language_level": []}]}, "experience_required": {"duration": [], "field": ["social media", "marketing", "digital marketing"]}}, {"job_id": "100003009052928", "location_code": "hk", "company": "Haven of Hope Christian Service", "job_title": "Dietitian (Ref: PHS/DHCE/D/JDB)", "description": "Responsibilities:\nProvide Dietetic services to service users of the DHC Express Scheme,\u00a0 including direct assessment, treatment, program planning & implementation, be responsible for related documentation, communication & reporting;\nConduct primary health promotion, education talk & provide direct patient education & coaching;\nAs an active member of the multi-disciplinary team and primary healthcare resource hub to engage related service stakeholder and discipline for primary health & chronic disease management;\nProvide professional inputs in service planning and development of the Scheme;\nTo supervise supporting staff, as required\nRequirements:\nBachelor of Science in Dietetics plus internship and on list of Hong Kong Academy of Accredited Dietitian;\nPossess 5 years or above post-qualification experience in patient care related practice in dietetic service, preferable both in clinical setting or in community setting;\nGood interpersonal and problem-solving skills.\nPossess good communication and presentation skills\nProactive, mature and independent; possess good computer literacy\nPlease send full resume with expected salary and reference no. quoted to Haven of Hope Christian Service, Staff Engagement Department, 7 Haven of Hope Road, Tseung Kwan O, New Territories or via email by clicking \"Apply Now\", or via Whatsapp no. 6507 8148 (with reference no. quoted at the caption) on or before 5 February 2022. Only short-listed candidates will be notified.\n\n\nEnquiry: 2703 3227 (Phone); 6507 8148 (Whatsapp).\n\n\nFor details about our organization, please visit www.hohcs.org.hk.\n\n\nProspective employees are requested to undergo/submit Sexual Conviction Record Check for work relating to children or mentally incapacitated persons before employment. Data collected will be used for recruitment purpose only.\n\n\nThis advertisement should not be reproduced, in whole or in part, to other recruitment websites without our prior written permission.\n\n", "employment_types": ["Full Time", "Permanent"], "selling_points": [], "locations": ["Tseung Kwan O"], "categories": ["Beauty Care / Health", "Nutritionist", "Others", "Medical Services", "Others"], "post_time": "2022-01-17T04:34:23Z", "salary": {"currency": null, "max": null, "min": null, "period": "monthly", "term": null}, "salary_visible": false, "title_keywords": ["dietitian"], "responsibilities": ["reporting", "management", "related documentation", "implementation", "communication", "planning"], "requirements": {"degrees": ["bachelor"], "majors": ["science"], "languages": [], "language_level": [], "hard_skills": ["hope", "no", "plus", "whatsapp", "problem-solving skills"], "soft_skills": ["independent", "patient", "mature", "communication", "computer literacy", "presentation skills", "problem-solving skills", "proactive", "interpersonal"], "languages_combined": []}, "experience_required": {"duration": ["5 years"], "field": ["related", "post-qualification", "clinical"]}}, {"job_id": "100003009043843", "location_code": "hk", "company": "Amway Hong Kong Ltd", "job_title": "Nutritionist (Full-time )", "description": "Provide professional nutrition consultation and dietary advice to clients\nProvide excellent customer service, establish, and maintain excellent customer relationship\nIntroduce and detail health supplements and provide appropriate product suggestions and advices\nOrganize and conduct public health education, seminars and workshops\nConduct health supplement market research and assist in product development\nEmbrace company culture and core values and actively participate in CSR activities and volunteer work\nParticipate and support daily operations and work closely with other departments on different projects\nExciting opportunities to develop career based on interests and talents and equip with the skills and knowledge required for success\n\nRequirement\n\nDegree in Nutrition and / or Food science or other relevant disciplines\nAt least 3 years' working experience in healthcare / pharmaceutical industry is preferred. Experience in retail / service industry is an advantage\nExcellent command of both written & spoken English, Mandarin and Cantonese\nPleasant, out-going with strong communication, interpersonal & presentation skill\nAble to work independently and under pressure\nOn-job training will be provided\n\nWe offer competitive remuneration package to the right candidate. Interested parties please send your application together with a detailed resume, current & expected salary and availability by clicking the \"APPLY NOW\" button below.", "employment_types": ["Full Time", "Permanent"], "selling_points": [], "locations": ["Mong Kok"], "categories": ["Beauty Care / Health", "Nutritionist", "Others"], "post_time": "2022-01-13T02:08:41Z", "salary": {"currency": null, "max": null, "min": null, "period": "monthly", "term": null}, "salary_visible": false, "title_keywords": ["nutritionist"], "responsibilities": ["market research", "work closely with other departments", "develop", "communication", "daily operations", "maintain", "customer service"], "requirements": {"degrees": ["degree"], "majors": ["food science"], "languages": ["cantonese", "english", "mandarin"], "language_level": ["excellent"], "hard_skills": ["workshops", "presentation skill"], "soft_skills": ["presentation skill", "work independently", "under pressure", "pleasant", "communication", "customer service", "interpersonal"], "languages_combined": [{"language": "cantonese", "language_level": ["excellent"]}, {"language": "english", "language_level": ["excellent"]}, {"language": "mandarin", "language_level": ["excellent"]}]}, "experience_required": {"duration": ["at least 3 years"], "field": ["pharmaceutical", "healthcare", "retail", "service industry"]}}, {"job_id": "100003009044265", "location_code": "hk", "company": "Concord Alliance Limited", "job_title": "Nutritionist", "description": "An exciting opportunity has arisen for an experienced, enthusiastic and passionate Associate Medical Affairs Manager to join our Nutritional division. \u00a0\nResponsibilities:\nTake the lead for medical marketing activities aligned with company strategy and vision. Coordinate new product launch planning and execution of strategy. Perform key opinion leaders\u2019 management and engagement.\nPrepare promotional materials and activities review in compliance to company code of practice, local laws, regulations and guidelines.\nEnsure high quality scientific and medical information delivery on products and enquiries handling to add value to business through scientific based medical service and customer oriented service to sales force, external customers (physicians, dieticians and consumers) and correct tracking/reporting of enquiries and safety reports.\nSearch relevant scientific literature from a variety of sources, circulate and maintain a current awareness service of new literature deemed to be of high value and relevant.\nTrain and provide expertise support for medical and commercial personnel and develop and deliver quality presentations about product and disease\nDevelop, review and update operational SOPs. Operation budget update monthly to finance if needed.\nDevelop and deliver clinical study proposal when needed to support local HCP initiated studies in collaboration with internal and external customers.\nRequirements:\nBachelor of science in nutrition/food related discipline or life sciences.\nMinimum 5 years in health care industry with medical marketing responsibilities, preferably with experience in multinational nutrition company\nGood communication and interpersonal skill with high sensitivity in interacting with people of different backgrounds\nTeam work spirit and solution-based mindset\nStrategic thinking, result-oriented and able to positively influence others\nAbility to manage multiple priorities independently\nGood business acumen, customer-oriented with medical integrity\nGood at spoken and written English & Chinese and good presentation skills\nResponsible for carrying out day-to-day operations within limits of delegated responsibilities while ensuring medical affairs operations excellence.", "employment_types": ["Full Time", "Permanent"], "selling_points": ["Degree in Nutrition and / or Food science", "At least 3 years exp. in Health Care Industry", "Double Pay"], "locations": ["Tsim Sha Tsui"], "categories": ["Sciences, Lab, R&D", "Food Science", "Beauty Care / Health", "Nutritionist", "Medical Services", "Pharmaceutical"], "post_time": "2022-01-13T03:35:43Z", "salary": {"currency": null, "max": null, "min": null, "period": "monthly", "term": null}, "salary_visible": false, "title_keywords": ["nutritionist"], "responsibilities": ["regulations", "reporting", "management", "tracking", "internal and external customers", "guidelines", "review", "compliance", "quality", "presentations", "develop", "coordinate", "budget", "promotional materials", "reports", "maintain", "sops", "planning"], "requirements": {"degrees": ["bachelor"], "majors": ["science"], "languages": ["english", "chinese"], "language_level": ["good"], "hard_skills": ["acumen"], "soft_skills": ["independently", "strategic thinking", "responsible", "sensitivity", "integrity", "interpersonal skill", "communication", "customer-oriented", "presentation skills", "business acumen", "result-oriented"], "languages_combined": [{"language": "english", "language_level": ["good", "good"]}, {"language": "chinese", "language_level": ["good", "good"]}]}, "experience_required": {"duration": ["minimum 5 years"], "field": ["health care", "marketing", "medical"]}}, {"job_id": "100003009050347", "location_code": "hk", "company": "Abbott Laboratories Ltd.", "job_title": "Associate Medical Affairs Manager", "description": "Responsibilities:\n\nProvide professional nutrition and dietary consultation to the patients and monitor the progress through different health programs\nHandle customers\u2019 enquiries and advise suitable products/services in a professional manner\nConduct the related article & media writing, health talks, training, research & survey and other health programs, etc\nPlan and execute the health programs & strategies of the group\nManage customers\u2019 records\nAssist in any ad-hoc assignments\n\nRequirements:\n\nDegree or above in Nutrition, Dietetics or related disciplines\nWell-organized, detail-minded, flexible, proactive, able to work under pressure to meet deadlines\nIndependent, a team player with initiative and good communication and interpersonal skills\nGood command of Mandarin is highly preferred\nProficient PC skills of MS office and Chinese word processing\nShift duty is required (No night shift)\n\nInterested candidates please click\u00a0APPLY NOW\u00a0to send your CV with current and expected salaries to us; Only shortlisted candidate will be notified.\u00a0 Personal data collected by job applicants will be kept in strict confidence and used for recruitment purpose only.", "employment_types": ["Full Time", "Permanent"], "selling_points": [], "locations": ["Eastern Area"], "categories": ["Beauty Care / Health", "Nutritionist", "Medical Services", "Others", "Sciences, Lab, R&D", "Research & Development (R&D)"], "post_time": "2022-01-15T03:51:00Z", "salary": {"currency": null, "max": null, "min": null, "period": "monthly", "term": null}, "salary_visible": false, "title_keywords": ["associate", "manager"], "responsibilities": ["ad-hoc assignments", "monitor", "professional manner", "plan"], "requirements": {"degrees": ["degree or above"], "majors": ["related disciplines"], "languages": ["chinese", "mandarin"], "language_level": ["good command", "proficient"], "hard_skills": ["no", "pc skills", "chinese word processing", "ms office"], "soft_skills": ["detail-minded", "flexible", "independent", "well-organized", "team player", "communication and interpersonal skills", "meet deadlines", "proactive", "initiative", "work under pressure"], "languages_combined": [{"language": "chinese", "language_level": ["proficient"]}, {"language": "mandarin", "language_level": ["good command"]}]}, "experience_required": {"duration": [], "field": []}}, {"job_id": "100003009040878", "location_code": "hk", "company": "Luxmed Medical Group Limited", "job_title": "Nutritionist/ Registered Dietitian", "description": "Responsibilities\uff1a\n\nAssess customers\u2019 nutritional needs\nProvide professional consultations\nRecommend our customers with Company\u2019s comprehensive range of health and fitness products, food supplements, meal replacements and health equipment in our service centers.\n\nRequirements\uff1a\n\nDegree holder in Nutrition or equivalent\nAt least 1 year relevant experience in nutrition\u00a0consultation\nCustomer- oriented with pleasant and outgoing character\nFluent in Cantonese & English with excellent presentation skills\nFresh graduate is also welcomed\n\nComprehensive benefit scheme includes:\n\nDouble pay, discretionary bonus, quarterly incentive scheme, medical & life insurance, birthday & new-born purchase discount, staff purchase discount\u00a0\n\nInterested parties, please send your resume and expected salary to ahkhr @ amway.com.\n\nFor further information about Amway Hong Kong Limited, please visit the Company\u2019s web site:www.amway.com.hk.\n\nAll information provided will be treated in strict confidence and used for recruitment purposes only. All data of unsuccessful applications will be destroyed after 3 months.", "employment_types": ["Full Time", "Permanent"], "selling_points": ["Independent and initiative team player", "Good command of Mandarin is highly preferred", "Shift duty is required (No night shift)"], "locations": ["Tsim Sha Tsui"], "categories": ["Beauty Care / Health", "Nutritionist"], "post_time": "2022-01-12T03:10:36Z", "salary": {"currency": null, "max": null, "min": null, "period": "monthly", "term": null}, "salary_visible": false, "title_keywords": ["dietitian", "nutritionist"], "responsibilities": [], "requirements": {"degrees": ["fresh graduate", "degree holder"], "majors": [], "languages": ["cantonese", "english"], "language_level": ["excellent", "fluent"], "hard_skills": ["scheme"], "soft_skills": ["outgoing", "presentation skills", "comprehensive", "pleasant"], "languages_combined": [{"language": "cantonese", "language_level": ["fluent", "excellent"]}, {"language": "english", "language_level": ["fluent", "excellent"]}]}, "experience_required": {"duration": ["at least 1 year"], "field": ["relevant experience"]}}, {"job_id": "100003009041562", "location_code": "hk", "company": "Vigene", "job_title": "Vigene - Nutritionist \u71df\u990a\u5e2b / Health Advisor \u5065\u5eb7\u9867\u554f", "description": "Job Description:\n\nProvide professional nutritional and health consultations (including dietary and weight control) on achieving clients' needs\nProvide and maintain excellent client relationship\nIntroduce and suggest appropriate health supplements and treatments to clients\nEdit and revise nutrition related articles and leaflets\nAssist in company nutrition and health promotion training, activities, seminars and presentations\nPerform ad hoc duties assigned by Supervisor\n\nRequirements:\n\nDegree in Nutrition / Food Science or equivalent\n1 year or above work\u00a0experience in nutrition, dietary consultation or health supplement sales\nCustomer oriented, self-motivated with positive attitude\nAble to work both independently and as a team, and under pressure\nGood presentation, communication & interpersonal skills\nProficient in spoken and written English and Chinese\nProficient in MS Office\nRecent Nutrition graduates will also be considered\n\nWork Locations:\n\nMongkok/Tsim Sha Tsui/Causeway Bay/Admiralty (5 mins walk from MTR station)\n\nWork Hours:\n\n8 hours per day (Monday to Friday 12-9pm, Saturday 10am-7pm)\nOff on every Sunday, no shift work required\n\nBenefits:\n\nAnnual Leave 12 days or above, birthday leave\nBonus day off\nYear-end bonus and salary adjustment\nCompetitive incentive and commission scheme + bonus\nOvertime work allowance\nMedical benefits\nOn-job training\nExcellent career development opportunities\nStaff purchase discounts (health and skincare products)\nStaff referral bonus\n\nWe offer attractive salary package with excellent career development opportunities to the right candidates. Please send your full CV stating your availability, current and expected salary via\n\n\nWHATSAPP 95419788 (https://wa.me/85295419788)\nClick 'APPLY NOW'", "employment_types": ["Full Time", "Permanent"], "selling_points": ["Nutrition consultation, supplement recommendation", "1 year+ experience in nutrition / sales", "Nutrition fresh grad also considered"], "locations": ["Mong Kok"], "categories": ["Beauty Care / Health", "Athletics / Fitness / Sports & Recreation", "Nutritionist", "Others"], "post_time": "2022-01-12T04:02:13Z", "salary": {"currency": null, "max": null, "min": null, "period": "monthly", "term": null}, "salary_visible": false, "title_keywords": ["\u71df\u990a\u5e2b", "advisor", "nutritionist"], "responsibilities": ["ad hoc duties", "control", "leaflets", "presentations", "maintain"], "requirements": {"degrees": ["degree"], "majors": ["food science"], "languages": ["english", "chinese"], "language_level": ["proficient"], "hard_skills": ["ms office"], "soft_skills": ["self-motivated", "independently", "under pressure", "positive attitude", "communication", "interpersonal skills", "presentation"], "languages_combined": [{"language": "english", "language_level": ["proficient"]}, {"language": "chinese", "language_level": ["proficient"]}]}, "experience_required": {"duration": ["1 year"], "field": []}}, {"job_id": "100003009049883", "location_code": "hk", "company": "CK Life Sciences Limited", "job_title": "Manager, Technical Services (health supplement/product development/ regulatory affairs)", "description": "A Manager, Technical Services is now required as a result of business growth:\n\nResponsibilities:\n\u2022 Responsible for the product development of our health products (Adrien Gagnon) for Hong Kong, the Mainland & Asian markets;\n\u2022 Coordinate with the R&D team to develop product formulation/ modification and prepare documentation in order to cope with related registration requirements;\n\u2022 Provide technical advice and work closely with the commercial team on marketing / promotional materials and nutrition labels, etc.;\n\u2022 Develop regulatory strategy and communicate the regulatory trend and its business impact to management and cross-functional teammates;\n\u2022 Manage product registration and present registration dossiers to expedite the approval progress;\n\u2022 Monitor the quality of raw materials/ finished products / facilities to ensure the full compliance of audits and inspections by HK FEHC and CFS;\n\u2022 Provide professional assessment and analysis to our customer service team to settle customer\u2019s complaint;\n\u2022 Organize health talk to corporate associations and deliver new product & compliance training to the retailers, promoters and cross-functional teammates.\n\nRequirements:\n\u2022 A Master\u2019s / Bachelor\u2019s degree in Food & Nutritional Science, Pharmacy or other related discipline;\n\u2022 A minimum of 8 years\u2019 experience in R&D (health supplement and / or food), regulatory affairs and quality assurance;\n\u2022 Previous experience in Hong Kong, the Mainland & Asian markets is a plus;\n\u2022 Solid knowledge in regulatory submissions, policy and procedures;\n\u2022 Hands-on experience in GMP and ISO is an advantage;\n\u2022 Demonstrate advanced skills in report writing and documentation;\n\u2022 Decisive, attentive to details and with strong organizational skills;\n\u2022 Can work under pressure and a fast-paced working environment.\n\nThank you for your interest in a career with CK Life Sciences. Competitive compensation and benefits package will be offered to the right candidate. We operate a 5-day workweek, and our benefits cover retirement, health and life. Regular shuttle bus service is also provided with pick-ups and drop-offs at designated and convenient locations.\n\nTo apply for our position, you should write, enclosing a current resume to Chief Manager, Human Resources & Administration, CK Life Sciences Limited, 2 Dai Fu Street, Tai Po Industrial Estate, Hong Kong or by clicking the APPLY NOW button. For more company information, please visit www.ck-lifesciences.com.\n\nWe are an equal opportunity employer and welcome applications from all qualified candidates. Personal data collected will be treated in strictest confidence and handled confidentially by authorized personnel for recruitment-related purposes within the Group.", "employment_types": ["Full Time", "Permanent"], "selling_points": ["MSc /BSc in Food & Nutritional Science or Pharmacy", "8 years\u2019 experience in R&D(health supplement/food)", "5-day workweek"], "locations": ["Tai Po Area"], "categories": ["Sciences, Lab, R&D", "Food Science", "Beauty Care / Health", "Nutritionist", "Manufacturing", "Product Development / Management"], "post_time": "2022-01-14T09:23:24Z", "salary": {"currency": null, "max": null, "min": null, "period": "monthly", "term": null}, "salary_visible": false, "title_keywords": ["product development", "manager"], "responsibilities": ["management", "technical advice", "compliance", "coordinate with", "monitor", "quality", "develop", "audits", "analysis", "promotional materials", "customer service", "documentation"], "requirements": {"degrees": ["degree", "bachelor", "master"], "majors": ["science"], "languages": [], "language_level": [], "hard_skills": ["r&d", "plus", "documentation"], "soft_skills": ["organizational skills", "advanced", "attentive to details", "hands-on", "decisive", "work under pressure"], "languages_combined": []}, "experience_required": {"duration": ["minimum of 8 years"], "field": ["food", "regulatory affairs", "quality assurance"]}}, {"job_id": "100003009038355", "location_code": "hk", "company": "Puredia Corporation Limited", "job_title": "Global Business Development Executive or Associate", "description": "Do you want to work in a fast paced and dynamic team that aims to develop new and exciting nutraceutical products (e.g. supplements, beauty drinks, functional gummies) to our customers?\n\nDo you want to gain exposure and experience by cooperating with multinational companies like Nestle and Amway on new product development?\u00a0\u00a0\n\nDo you have strong experience in interpreting customer needs, nutraceutical trends, and commercial insights for formulating an innovative nutraceutical product?\u00a0\u00a0\n\nThen join Puredia ingredient sales team as a Global Business Development Executive or Associate today!\u00a0\n\nRoles & Responsibilities\n\nB2B Sales\nDriving sales by promoting our branded ingredients to brands and distributors to develop new nutraceutical products, such as supplements, beauty drinks, functional gummies, etc.\u00a0\nFollowing up on new enquiries from company\u2019s website, newsletter and LinkedIn connections.\u00a0\nDriving the entire sales funnel from initial partner engagement / product introduction to securing product development\nProviding feedback to management on ways to further improve and streamline the sales funnel and sales experience\nProviding feedback to management on market trends, competitive threats, existing gaps, and opportunities to deliver greater value to clients by extending company offerings\nAttending and exhibiting at global tradeshows and conferences to reach out to new customers. (Currently on hold due to COVID-19)\nGlobal Business Development Associate\n\n\nRequirements\n\nBachelor's degree in Food & Nutritional Science, Biomedical Science, Biological Science, Business Adminstration or related field\nMinimum 1 year experience in sales / business development related scope of work in nutraceutical, pharmaceutical or food and beverage industries.\u00a0\nFresh graduate is also welcomed.\nExcellent written and oral skills in English.\nGlobal Business Development Executive\n\nRequirements\n\nBachelor's degree in Food & Nutritional Science, Biomedical Science, Biological Science, Business Adminstration or related field\nMinimum 3 year experience in sales / business development related scope of work in nutraceutical, pharmaceutical or food and beverage industries.\u00a0\nExcellent written and oral skills in English.\nStrong experience working with international customers.\nExcellent project Management and problem solving skills.\nBenefits\n\nAttractive Commission Package\n5-day Work and Bank Holidays\nMedical Insurance\n10+ Days Annual Leave\nMultinational Exposure\nStaff Purchase Discount", "employment_types": ["Full Time"], "selling_points": [], "locations": ["Tsim Sha Tsui"], "categories": ["Sales, CS & Business Devpt", "Business Development", "Beauty Care / Health", "Nutritionist", "Account Servicing"], "post_time": "2022-01-11T06:42:32Z", "salary": {"currency": null, "max": null, "min": null, "period": "monthly", "term": null}, "salary_visible": false, "title_keywords": ["associate", "business development executive"], "responsibilities": ["management", "conferences", "website", "develop"], "requirements": {"degrees": ["degree", "bachelor", "fresh graduate"], "majors": ["biomedical science", "science", "business", "biological science"], "languages": ["english"], "language_level": ["excellent"], "hard_skills": ["project management", "problem solving skills"], "soft_skills": ["project management", "oral", "problem solving skills"], "languages_combined": [{"language": "english", "language_level": ["excellent", "excellent"]}]}, "experience_required": {"duration": ["minimum 3 year", "minimum 1 year"], "field": ["related", "pharmaceutical", "business development", "food"]}}, {"job_id": "100003009027508", "location_code": "hk", "company": "Hong Kong Sports Institute Ltd", "job_title": "SPORT NUTRITIONIST", "description": "Sport Nutritionist\n\nThe Hong Kong Sports Institute Limited (\u201cHKSI\u201d) is the Government\u2019s delivery agent of elite sports training systems. The HKSI\u2019s mission is to provide an environment in which sports talent can be identified, nurtured and developed to pursue excellence in the international sporting arena benchmarked at Major Games results. We are now inviting suitable candidates for the following vacancy:\n\nThe\u00a0Job\n\nReporting\u00a0to the Sport Nutrition and Monitoring Manager, the Sport Nutritionist will be responsible for the following duties:\n\nTo conduct individual nutritional and anthropometric and monitoring and advise on optimal nutritional and energy requirements for sports specific performance and health;\nTo\u00a0collaborate with allied ETSTD areas as appropriate to the ETSTD biopsychosocial operational model;\nTo\u00a0provide on-field support at local and overseas training and competitions;\nTo design and supervise the menu for athletes\u2019 food services and document the nutritional values;\nTo conduct nutrition education for groups by holding formal and informal discussion groups and lectures for athletes, parents and coaches;\nTo provide regular updates on sport nutrition information for the athletes and coaches based on international research and new developments;\u00a0\nTo participate in the annual ETSTD research programme;\nTo supervise junior staff;\nTo demonstrate an active commitment to personal professional development; and\nTo perform any other appropriate duties as assigned by supervisor.\n\u00a0\nThe\u00a0Requirements\nMaster or higher degree in Dietetics or a relevant discipline;\n5 or more years of working experience in nutrition, of which at least 3 years are in sports nutrition;\nProven experience in assisting the delivery of elite level sport nutrition programmes;\nExcellent interpersonal and communication skills;\nGood command in both spoken and written Chinese and English. Knowledge of Putonghua will be an advantage; and\nAwareness/ knowledge of Child Protection in sport and equal opportunity issues in the context of Hong Kong.\n\n[Applicants who have responded to the previous advertisements need not re-apply. Their applications are being considered accordingly.]\n\n\u00a0\nAPPLICATIONS\u00a0\n\nPlease send the completed\u00a0Application Form\u00a0with indication of expected salary to\u00a0The Human Resources Manager, Hong Kong Sports Institute Ltd, 25 Yuen Wo Road, Sha Tin, New Territories\u00a0or email:\u00a0hrdept @ hksi.org.hk. on or before 19 January 2022.Please quote reference no. JD-20220106-SN\u00a0 in the application.\n\nAppointment will be on a fixed term contract. General information is available at the website\u00a0http://www.hksi.org.hk.\nApplicants who are not invited for interview within six months may consider their applications unsuccessful.\n\u00a0\nAll applications will be treated in the strictest confidence. Data collected will be used for recruitment and other employment-related purposes only.\n\n\nTHE HKSI IS AN EQUAL OPPORTUNITIES EMPLOYER\u00a0\n\n\n\n", "employment_types": ["Full Time"], "selling_points": [], "locations": ["Shatin Area"], "categories": ["Beauty Care / Health", "Nutritionist"], "post_time": "2022-01-06T10:14:30Z", "salary": {"currency": null, "max": null, "min": null, "period": "monthly", "term": null}, "salary_visible": false, "title_keywords": ["nutritionist"], "responsibilities": ["collaborate with", "reporting", "monitoring", "design"], "requirements": {"degrees": ["degree", "master"], "majors": [], "languages": ["putonghua", "english", "chinese"], "language_level": ["advantage", "good command"], "hard_skills": ["no", "hksi"], "soft_skills": ["communication skills", "confidence", "interpersonal"], "languages_combined": [{"language": "putonghua", "language_level": ["advantage"]}, {"language": "english", "language_level": ["good command"]}, {"language": "chinese", "language_level": ["good command"]}]}, "experience_required": {"duration": ["at least 3 years"], "field": []}}, {"job_id": "100003009027877", "location_code": "hk", "company": "Nutri-Professional Physiotherapy & Health Care Centre", "job_title": "Nutritionist/Registered Dietitian", "description": "\nDuties:\n\nProvide professional nutritional & dietary consultation to clients.\nAssist in nutrition article & book writing, cooking demonstration, recipe development, media interviews, health seminars, research & survey and other health promotion activities.\n\n\n\nRequirements:\n\nUniversity Degree in Nutrition or Dietetics or equivalent. Possess professional qualification of registration.\nMinimum 1-2 years relevant experience in nutrition consultation and nutrition project coordination.\nProficiency in both spoken and written English & Chinese.\nResponsible, customer oriented, self-initiated.\n\n\n\nInterested party, please submit full C.V. with expected salary and availability to Ms. Wong by clicking \u201cAPPLY NOW\u201d or contact 2368 6689 (Ms. Wong) for more information.\n\n\n\nPersonal data collected will be used for recruitment purpose only.", "employment_types": ["Full Time", "Permanent"], "selling_points": ["Provide professional nutritional & dietary consult", "Assist in nutrition article & book writing", "University Degree in Nutrition or Dietetics"], "locations": ["Not Specified"], "categories": ["Beauty Care / Health", "Nutritionist", "Therapist", "Others"], "post_time": "2022-01-06T16:07:23Z", "salary": {"currency": null, "max": null, "min": null, "period": "monthly", "term": null}, "salary_visible": false, "title_keywords": ["dietitian", "nutritionist"], "responsibilities": [], "requirements": {"degrees": ["university degree"], "majors": [], "languages": ["english", "chinese"], "language_level": ["proficiency"], "hard_skills": ["c"], "soft_skills": ["coordination", "responsible"], "languages_combined": [{"language": "english", "language_level": ["proficiency"]}, {"language": "chinese", "language_level": ["proficiency"]}]}, "experience_required": {"duration": ["minimum 1-2 years"], "field": ["relevant experience"]}}, {"job_id": "100003009020432", "location_code": "hk", "company": "Endeavour Search Limited", "job_title": "Nutritionist (Product Training and Education, Pharmaceutical Firm)", "description": "Client\u00a0\n\nA new headcount for an expanding international pharmaceutical and skincare nutrition firm, excellent opportunity for nutritionist go in-house and support patient education and customer training programs for new product launch and consultation.\n\nResponsibilities\n\n\nRespond to Dr/Nurse/Internal staff customer enquiry and case/training support request \u00a0(both internal and external) and work towards resolving the stated problem or answering the inquiry. (About procedure, product information, product application)\nTypical training would be holding 1-1 or small group workshop\nDocument into cases, according to departmental procedures.\nDevelop and maintain training materials for internal use.\nDevelop into a subject matter expert on assigned product platforms and utilize your clinical background and experience to provide excellent application support to clinic customers\nInteract with multiple in-house groups by providing feedback on product issues and quality trends\nQualifications\nDegree in Nutrition/Science/Nursing\nProfessional communication skills (written and verbal),\nPassion for skincare product\nDerive satisfaction from assisting customers resolve their technical problems while helping the company achieve its product quality and customer satisfaction goals.\nInterested candidates, please forward your CV by jobsDB application system\u00a0For confidential discussion, please contact Kevin at 3956 1822", "employment_types": ["Full Time", "Permanent"], "selling_points": ["International Pharmaceutical Firm", "Pivotal Trainer Role", "20% -40% Bonus (No sales target, team work )"], "locations": ["Central & Western Area"], "categories": ["Beauty Care / Health", "Nutritionist"], "post_time": "2022-01-04T11:30:20Z", "salary": {"currency": null, "max": null, "min": null, "period": "monthly", "term": null}, "salary_visible": false, "title_keywords": ["nutritionist"], "responsibilities": ["workshop", "procedures", "subject matter expert", "quality", "develop", "communication", "maintain"], "requirements": {"degrees": ["degree"], "majors": ["science", "nursing"], "languages": [], "language_level": [], "hard_skills": ["small", "go"], "soft_skills": ["communication skills", "patient", "passion for"], "languages_combined": []}, "experience_required": {"duration": [], "field": ["clinic", "clinical"]}}, {"job_id": "100003009021154", "location_code": "hk", "company": "Prenetics Limited", "job_title": "Dietitian / Nutritionist / Health Coach", "description": "Founded in 2014, Prenetics is a major global diagnostics and genetic testing company with the mission to bring health closer to millions of people globally and decentralize healthcare by making the three pillars \u2014 Prevention, Diagnostics and Personalized Care \u2014 comprehensive and accessible to anyone, at anytime and anywhere. Prenetics is led by visionary entrepreneur,\u00a0Danny Yeung, with a team of over 800 employees and operations across 9 locations, including\u00a0United Kingdom,\u00a0Hong Kong,\u00a0India,\u00a0South Africa, and\u00a0Southeast Asia. Prenetics develops consumer genetic testing and early colorectal cancer screening; provides COVID-19 testing, rapid point of care and at-home diagnostic testing and medical genetic testing.\n\nMost recently, Prenetics made\u00a0international headlines to become the first Unicorn in Hong Kong to publicly list on the Nasdaq via merger with\u00a02021 Adrian Cheng's Artisan Acquisition Corp, valuing Prenetics at approximately US $1.7b.\n\nWe are looking for individuals with previous health coaching, life coaching, or weight loss coaching experience, but most importantly, we're looking for all-around tech savvy, intelligent, empathetic, and efficient people who have a commitment to helping Prenetics advance and deliver the digital health coaching craft. A professional health background is not required but an advantage.\n\nResponsibilities\n\nUse an individual\u2019s DNA profile to analyse his/her nutritional and lifestyle needs, and develop personalised and sustainable diet, exercise, or other wellness plans tailored to their goals.\nEmpower clients to take their health into their own hands by helping them understand their current health status, their motivations and ultimately create behavioural change.\nProvide remote digital health coaching using science-based therapeutic tools, including an evolving digital app as your main source of communication (includes texting and phone calls).\nEmpathize, connect, and partner with customers to ensure personal success and sustainability using various counseling techniques including, but not limited to motivational interviewing and customer-centered goal setting.\nCollaborate with and support Marketing and Business Development Teams in content creation and Health Team representation.\nDesign and deliver seminars, workshops, presentations with potential customers and client partners.\nPresent work progress at regular team meetings.\nParticipate in offline marketing events, with some of these events to be held on weekends.\nUphold company values and maintain a strong team dynamic including sharing your specific expertise with your teammates.\n\nOur ideal candidate will have\n\n\nBachelor\u2019s degree in Public Health, Nutrition, Nutrition & Dietetics is preferred, 1-3 year experience\nVery strong communication skills, both written and verbal, in both professional and casual forms in English and in Cantonese. Mandarin will be a plus.\nStrong presentation skills and presence\nFast learner and able to adapt to a constantly changing startup environment\nDemonstrated prior experience helping others lose weight, eat better or get active\nPreferred experience in telephonic health coaching or related role\nStrong organizational and time management skills\nHighly collaborative and able to work in a team environment\nProfessional license or certification will be an advantage: dietitians, nutritionists, nurses, therapists, social workers, trainers, health coaches, etc\n\nOur DNA is\u00a0P-R-E-N-E-T-I-C-S.\u00a0See what each word of our company name means:\n\nPassion\n\nYou love what you do and accomplish amazing result\nYou spread positivity, bring enthusiasm to work and inspire team members\nYou drive team toward specific goals, even when they seem unlikely or difficult\n\nResilience\n\nYou embrace changes and be able to drive through uncertainty, ambiguity and uncomfortable situations\nYou bounce back quickly from setbacks and challenges\nYou are persistent and determined to achieve the desired outcome\n\nEmpowerment\n\nYou trust others to play their positions well like an elite sports team\nYou foster a strong team spirit while encouraging others to take initiatives and risks\nYou create a space to allow team to grow and hold each other accountable\n\niNtegrity\n\nYou are trustworthy and lead by example\nYou are consistent in your message and action all the times\nYou deliver what you have promised\n\nEpic\n\nYou challenge your own comfort zone and always outperform yourself\nYou make meaningful and amazing impact to the world\nYou dare to take risks and you move fast\n\nTransparency\n\nYou are completely honest and committed to giving candid feedbacks, no matter how challenging it might be\nYou share ideas, knowledge and skills that empower others and create access to information with the wider team\nYou share wins and failures openly\n\nIngenuity\n\nYou make sound judgement and come up with solutions that are creative and smart. Copy when feasible\nYou challenge the status quo and question things that could be done differently for better. Modify the wheel if you can\u2019t change it\nYou think outside of the box and make value-based innovation\n\nCommunications\n\nYou articulate your thoughts and ideas effectively and respectfully\nYou know your audience and talk in a way they want to be told\nYou make sure communications happens, no matter where you are\n\nSelflessness\n\nYou put the needs of others before one's own and find ways in helping other to succeed\nYou focus on team wins than personal wins and share credits\nYou act in the company's best interest\nWe are Prenetics, our people make us who we are.", "employment_types": ["Full Time", "Permanent"], "selling_points": ["Attractive salary with career development", "Global digital health company", "Young and energetic working environment"], "locations": ["Quarry Bay"], "categories": ["Beauty Care / Health", "Athletics / Fitness / Sports & Recreation", "Nutritionist", "Others"], "post_time": "2022-01-05T03:15:49Z", "salary": {"currency": null, "max": null, "min": null, "period": "monthly", "term": null}, "salary_visible": false, "title_keywords": ["dietitian", "nutritionist"], "responsibilities": ["collaborate with", "marketing events", "management", "ideas", "operations", "teams", "design", "develop", "testing", "communication", "presentations", "maintain", "plans", "phone calls", "analyse"], "requirements": {"degrees": ["degree", "bachelor"], "majors": ["public health"], "languages": ["cantonese", "english", "mandarin"], "language_level": [], "hard_skills": ["plus", "no", "word", "presentations", "goal", "make", "dynamic", "c", "rapid", "workshops", "r", "focus"], "soft_skills": ["team spirit", "trustworthy", "persistent", "collaborative", "communication", "comprehensive", "visionary", "articulate", "focus", "efficient", "determined", "integrity", "committed", "honest", "creative", "fast learner", "ideal", "communication skills", "dynamic", "active", "time management skills", "organizational", "accountable", "presentation skills"], "languages_combined": [{"language": "cantonese", "language_level": []}, {"language": "english", "language_level": []}, {"language": "mandarin", "language_level": []}]}, "experience_required": {"duration": ["1-3 year"], "field": ["related", "digital", "tech"]}}, {"job_id": "100003009028652", "location_code": "hk", "company": "Abbott Laboratories Ltd.", "job_title": "Health Advisor", "description": "Responsibilities:\n\nTo handle product enquires and complaints in accordance with accurate product information, standard Q&A, internal compliance & code of conduct\nTo contact with prospective customers to build long term customer relationship, achieve retention & conversion through professional, ethical & high quality customer services\nTo fulfill sales orders from any possible channels\nTo prepare reports as requested by CRM Manager on analyses, customer feedback with recommended solution & market intelligence\nTo provide support in marketing events e.g. conference, health talk, exhibition and training\nTo develop and maintain accurate & timely customer records in CRM system\nRequirements:\n\nBachelor\u2019s Degree in Nutritional Science, Pharmaceutical or science related subject\n1 -2\u00a0years of experience in customer relationship management in Healthcare, FMCG or retail industry, experience in customer service preferred\nExcellent spoken and written communication skills in English, Putonghua and Cantonese\nProactive, polite and good telephone manner\nBe able to work under pressure, result-oriented and good team player\nComputer literacy in MS Office applications including Excel, Word and PowerPoint, MSCRM or any other CRM system preferable\nInterested parties, please send your profile with present and expected salary by clicking \"Apply Now\"\nPersonal data collected will be used for recruitment purposes only.", "employment_types": ["Full Time", "Permanent"], "selling_points": [], "locations": ["Eastern Area"], "categories": ["Sales, CS & Business Devpt", "Customer Service - Supervisor / Officer", "Beauty Care / Health", "Nutritionist", "Medical Services", "Pharmaceutical"], "post_time": "2022-01-07T19:19:42Z", "salary": {"currency": null, "max": null, "min": null, "period": "monthly", "term": null}, "salary_visible": false, "title_keywords": ["advisor"], "responsibilities": ["marketing events", "provide support", "compliance", "quality", "customer services", "develop", "maintain", "contact", "prepare reports"], "requirements": {"degrees": ["degree", "bachelor"], "majors": ["science"], "languages": ["cantonese", "putonghua", "english"], "language_level": ["excellent"], "hard_skills": ["excel", "word", "powerpoint", "ms office"], "soft_skills": ["communication skills", "good team player", "polite", "computer literacy", "customer service", "proactive", "telephone manner", "result-oriented", "work under pressure"], "languages_combined": [{"language": "cantonese", "language_level": ["excellent"]}, {"language": "putonghua", "language_level": ["excellent"]}, {"language": "english", "language_level": ["excellent"]}]}, "experience_required": {"duration": ["1 -2 years"], "field": ["retail industry", "healthcare", "management", "fmcg", "customer service"]}}, {"job_id": "100003009017132", "location_code": "hk", "company": "Caf\u00e9 de Coral Group Limited", "job_title": "Nutritionist (School Catering)", "description": "Responsibilities:\n\nDesign school menus and develop new products which fulfil the nutritional requirements of students\nAnalyze food nutrient content and propose improvement plans\nAssist in school visit activities; host nutritional talks and design health programs for schools\nEdit newsletter to share healthy and nutrition information to schools\nHandle ad-hoc project assigned by supervisor\u00a0\n\nRequirements:\n\nDegree holder in Nutrition, Food Science & Nutrition or related disciplines\n1-2 years\u2019relevant working experiences in food manufacturing industry\nPleasant, outgoing, self-motivated and able to work independently\nProficiency in MS Office including PowerPoint, Excel, Word, Outlook and Chinese Word Processing\nGood command of both written and spoken English and Chinese\u00a0\n\nInterested parties please send full resume with PRESENT & EXPECTED SALARY to Human Resources Department by clicking\u00a0\"APPLY NOW\"\n\n\nWe are an EQUAL OPPORTUNITIES EMPLOYER.\n\nAll information received will be kept in strict confidence and be used for employment-related purpose only.", "employment_types": ["Full Time", "Permanent"], "selling_points": ["Design school menus and develop new products", "host nutritional talks and design health programs", "5 days work; 15 days AL"], "locations": ["Shatin Area"], "categories": ["Hospitality / F & B", "Food & Beverage", "Beauty Care / Health", "Nutritionist", "Others"], "post_time": "2022-01-03T20:52:20Z", "salary": {"currency": null, "max": null, "min": null, "period": "monthly", "term": null}, "salary_visible": false, "title_keywords": ["nutritionist"], "responsibilities": ["ad-hoc", "plans", "design", "develop"], "requirements": {"degrees": ["degree holder"], "majors": ["related disciplines", "food science"], "languages": ["english", "chinese"], "language_level": ["proficiency", "good command"], "hard_skills": ["excel", "chinese word processing", "word", "powerpoint", "outlook", "ms office"], "soft_skills": ["outgoing", "self-motivated", "work independently", "pleasant"], "languages_combined": [{"language": "english", "language_level": ["good command"]}, {"language": "chinese", "language_level": ["proficiency", "good command"]}]}, "experience_required": {"duration": [], "field": ["food manufacturing industry"]}}, {"job_id": "100003009023150", "location_code": "hk", "company": "The Rosehip Specialist (HK) Limited", "job_title": "Marketing Supervisor (Pet Supplement Brand for Asia)", "description": "Job\u00a0Responsibilities\n\nResponsible for market development of the brand for the Asia Market\nAssist in developing online and offline promotion campaign in accordance to the brand strategy\nAnalyze business trends and conduct market research in achieving sales and market share targets\nCompile regular business reports and presentations for management's review\nProvide marketing supports to sales and operations team\nAny other ad hoc projects assigned by the Management\n\n\u00a0Requirements\n\nDegree / Diploma holder in Marketing, Business related discipline\nMinimum 2 years\u2019 solid experience in brand or product MKT in the field of Pet or FMCG sectors\nStrategic thinker with demonstrated experience in brand building and positioning\nCreative, people-oriented, dynamic with strong market sense\nStrong in communicating skill from different backgrounds and at all levels, both internally and externally\nComputer proficiency in Microsoft office, Word, Excel and PowerPoint is essential\nGood command of spoken and written English, Chinese and Mandarin", "employment_types": ["Full Time", "Permanent"], "selling_points": [], "locations": ["Tsim Sha Tsui"], "categories": ["Beauty Care / Health", "Nutritionist", "Sales, CS & Business Devpt", "Retail Sales", "E-commerce", "Marketing - Brand / Product Management"], "post_time": "2022-01-06T01:26:13Z", "salary": {"currency": null, "max": null, "min": null, "period": "monthly", "term": null}, "salary_visible": false, "title_keywords": ["supervisor"], "responsibilities": ["management", "operations", "conduct market research", "review", "developing", "presentations", "analyze business trends", "reports", "ad hoc projects"], "requirements": {"degrees": ["diploma holder", "degree"], "majors": ["business", "marketing"], "languages": ["english", "chinese", "mandarin"], "language_level": ["good command"], "hard_skills": ["excel", "microsoft office", "word", "powerpoint", "dynamic"], "soft_skills": ["strong market sense", "dynamic", "creative", "people-oriented"], "languages_combined": [{"language": "english", "language_level": ["good command"]}, {"language": "chinese", "language_level": ["good command"]}, {"language": "mandarin", "language_level": ["good command"]}]}, "experience_required": {"duration": ["minimum 2 years"], "field": ["fmcg", "brand"]}}, {"job_id": "100003009026810", "location_code": "hk", "company": "iOne Theory Limited", "job_title": "\u521d\u7d1a\u7f8e\u5f62\u5e2b/\u7f8e\u5f62\u5e2b", "description": "Job Responsibilities\n\nTake the ownership of the marketing plan development, and create effective promotion strategies to drive interest and new leads in various channel.\nManage the tactical execution of marketing campaigns, including sales offer, online/offline communication, digital content creation, etc.\nLead the team to formulate extra sales channel for promotion, including joint promotion, Marketing research, etc.\nOversee the implementation and budget of digital channel, including SEO/SEM, social media, etc\nUnderstand key marketing performance metrics and tracking tools to provide insights on channel strategies, forecast and competitor analysis\nAnalyze product performance and competitor\u2019s trends to uncover consumer behaviour\n\nJob Requirement\n\nDegree holder in Business or Marketing or related disciplines\nOver 2 years Digital Marketing experience and proven experience within Social Media\nWork experience in pet products market is definitely\u00a0an advantage\nFamiliar with Performance Marketing like SEO / SEM, Web Analytics and Facebook ad.\nExperience in building Digital teams KPI\u2019s processes\nExcellent planning and project management skills\nCreative, energetic, good interpersonal and communication skills\nExcellent command in English, Cantonese and Mandarin\nCandidate with less experienced will be considered as Assistant Marketing Manager", "employment_types": ["Full Time"], "selling_points": ["5 days work", "Performance bonus", "Ongoing training"], "locations": ["Central"], "categories": ["Beauty Care / Health", "Beautician", "Nutritionist", "Therapist"], "post_time": "2022-01-06T08:41:10Z", "salary": {"currency": null, "max": null, "min": null, "period": "monthly", "term": null}, "salary_visible": false, "title_keywords": [], "responsibilities": ["social media", "provide insights", "seo", "analysis", "budget", "implementation", "performance metrics", "communication", "marketing plan", "marketing research", "marketing campaigns", "sem", "forecast", "tracking"], "requirements": {"degrees": ["degree holder"], "majors": ["related disciplines", "business", "marketing"], "languages": ["cantonese", "english", "mandarin"], "language_level": ["excellent"], "hard_skills": ["seo", "project management", "sem", "web analytics", "facebook"], "soft_skills": ["communication skills", "creative", "project management skills", "web analytics", "energetic", "interpersonal"], "languages_combined": [{"language": "cantonese", "language_level": ["excellent"]}, {"language": "english", "language_level": ["excellent"]}, {"language": "mandarin", "language_level": ["excellent"]}]}, "experience_required": {"duration": ["2 years"], "field": ["social media", "digital marketing", "digital"]}}, {"job_id": "100003009019052", "location_code": "hk", "company": "Injoy Health Corporate Limited", "job_title": "Business Executive (Health Industry) e-Shops + Retail", "description": "Job Description\n\n\nDirect report to team leader for daily operations\u00a0\nAnalyze business trends and consumer insights and evaluate existing product categories on choices\nHandle sales and account\nDevelop and execute business development strategies for discovering and securing new business opportunities.\nCampaign management for marketing promotion\nLeading a team of 5+ part-time temporary promoter staffs to perform sales duties and offline promotion, across multiple locations\nAny other ad hoc projects\n\nRequirements\n\n\nHigher Diploma with 2 years of experience in Business, Journalism, Marketing, FMCG or Health Industry\nProficient in Chinese writing\nStrong marketing sense, logical thinking with excellent communication and project management skills\nIndependent, self-motivated, well organised and strong time management\nExperience in online shop\u00a0\nKnowledge in Google Analytics, social media ad placing is an advantage\nKnowledge in videoing editing, Adobe P.S & A.I is an advantage\nImmediate available is highly preferred\nFresh graduates with good attitude also welcomed", "employment_types": ["Full Time"], "selling_points": ["Experience in e-Shops operation (eg. HKTV Mall,)", "Work independently, Business & Marketing", "Able to communicate effectively"], "locations": ["Kwun Tong"], "categories": ["Sales, CS & Business Devpt", "Business Development", "Beauty Care / Health", "Nutritionist", "Marketing / Public Relations", "Digital Marketing"], "post_time": "2022-01-04T06:31:44Z", "salary": {"currency": null, "max": null, "min": null, "period": "monthly", "term": null}, "salary_visible": false, "title_keywords": ["business executive"], "responsibilities": ["product categories", "consumer insights", "business opportunities", "develop", "evaluate", "daily operations", "analyze business trends", "ad hoc projects", "campaign management", "report"], "requirements": {"degrees": ["diploma"], "majors": ["journalism", "business", "marketing"], "languages": ["chinese"], "language_level": ["proficient"], "hard_skills": ["project management", "adobe", "google analytics"], "soft_skills": ["self-motivated", "independent", "marketing sense", "project management skills", "communication", "organised", "time management"], "languages_combined": [{"language": "chinese", "language_level": ["proficient"]}]}, "experience_required": {"duration": ["2 years"], "field": ["fmcg", "business", "marketing"]}}, {"job_id": "100003009003158", "location_code": "hk", "company": "Chinese Essence Health Management Limited", "job_title": "Registered Dietitian / Nutritionist", "description": "Responsibilities:\n\nProvide professional nutrition and dietary consultation to the patients and monitor the progress\nCoordinate with doctors and clinical advisors to improve customers\u2019 lives\nTo assist in the planning and implementing of health promotion activities, seminars, presentations and product-selling strategies\nHandle nutrition-related enquiries and recommend our customers with Company\u2019s comprehensive range of health and fitness products, food supplements and other health services\nParticipate in health promotion activities and seminars\n\nRequirements:\n\nDegree holder in Nutrition, Dietetics or equivalent\nPreferably with 2 years of experience in nutrition consultation service\nEmbracing the philosophy of continuous improvement\nWell-organized, attentive, flexible, able to work under pressure to meet team goals\nCustomer oriented, excellent communication skills and sales experience will be an advantage\nProficiency in command of written and spoken English & Chinese\nExcellent work ethics, independent and self-motivated with positive attitude\nImmediate Available\n\nWe offer attractive compensation package plus career opportunities to the right candidates. Please send your detailed resume, with\u00a0latest\u00a0and\u00a0expected salary\u00a0to our Human Resources Department by clicking \"Apply Now\".\n\nAll data collected will be used for recruitment purpose only.", "employment_types": ["Full Time"], "selling_points": ["Attractive remuneration package includes", "2 yrs exp in nutrition consultation service", "Provide nutritional, dietary & health consultation"], "locations": ["Causeway Bay"], "categories": ["Beauty Care / Health", "Nutritionist", "Others", "Medical Services", "Others"], "post_time": "2021-12-28T08:20:27Z", "salary": {"currency": null, "max": null, "min": null, "period": "monthly", "term": null}, "salary_visible": false, "title_keywords": ["dietitian", "nutritionist"], "responsibilities": ["planning", "monitor", "presentations", "coordinate with"], "requirements": {"degrees": ["degree holder"], "majors": [], "languages": ["english", "chinese"], "language_level": ["proficiency"], "hard_skills": [], "soft_skills": ["attentive", "communication skills", "flexible", "self-motivated", "independent", "well-organized", "positive attitude", "work under pressure"], "languages_combined": [{"language": "english", "language_level": ["proficiency"]}, {"language": "chinese", "language_level": ["proficiency"]}]}, "experience_required": {"duration": ["2 years"], "field": []}}, {"job_id": "100003009004194", "location_code": "hk", "company": "UBaby HK Limited", "job_title": "Nutritionist", "description": "Responsibilities and Duties:\n-\u00a0\u00a0\u00a0\u00a0\u00a0\u00a0\u00a0\u00a0\u00a0 Prepare all marketing materials and compose written content relates to products\n-\u00a0\u00a0\u00a0\u00a0\u00a0\u00a0\u00a0\u00a0\u00a0 Assist in nutrition article and social media writing\n-\u00a0\u00a0\u00a0\u00a0\u00a0\u00a0\u00a0\u00a0\u00a0 Compose training materials and conduct regular training and health talk to our members\n-\u00a0\u00a0\u00a0\u00a0\u00a0\u00a0\u00a0\u00a0\u00a0 Assist in ad hoc marketing campaigns and events as assigned\n\nRequirement:\n-\u00a0\u00a0\u00a0\u00a0\u00a0\u00a0\u00a0\u00a0\u00a0 Degree holder in marketing with minimum 1 years working experience, former experience in FMCG and/ nutritional supplement industry is preferred\n-\u00a0\u00a0\u00a0\u00a0\u00a0\u00a0\u00a0\u00a0\u00a0 Good command of written English and Chinese; Fluency in Mandarin will be an advantage\n-\u00a0\u00a0\u00a0\u00a0\u00a0\u00a0\u00a0\u00a0\u00a0 Customer-oriented with pleasant, outgoing character with good presentation skill\n-\u00a0\u00a0\u00a0\u00a0\u00a0\u00a0\u00a0\u00a0\u00a0Proficient in design software, including Photoshop, Illustrator, Premiere\n\nInterested parties please e-mail your resume with available date, current and expected salary by clicking \"Apply Now\".\n\n", "employment_types": ["Contract"], "selling_points": [], "locations": ["Kowloon Bay"], "categories": ["Beauty Care / Health", "Nutritionist"], "post_time": "2021-12-29T02:34:04Z", "salary": {"currency": null, "max": null, "min": null, "period": "monthly", "term": null}, "salary_visible": false, "title_keywords": ["nutritionist"], "responsibilities": ["marketing materials", "social media", "ad hoc", "marketing campaigns"], "requirements": {"degrees": ["degree holder"], "majors": ["marketing"], "languages": ["english", "chinese", "mandarin"], "language_level": ["fluency", "advantage", "good command"], "hard_skills": ["presentation skill", "illustrator", "premiere", "photoshop"], "soft_skills": ["outgoing", "customer-oriented", "presentation skill", "pleasant"], "languages_combined": [{"language": "english", "language_level": ["good command"]}, {"language": "chinese", "language_level": ["good command"]}, {"language": "mandarin", "language_level": ["fluency", "advantage"]}]}, "experience_required": {"duration": ["minimum 1 years"], "field": ["marketing", "fmcg"]}}, {"job_id": "100003009002001", "location_code": "hk", "company": "Vigene", "job_title": "Vigene - Nutritionist \u71df\u990a\u5e2b/Health Advisor \u5065\u5eb7\u9867\u554f", "description": "Job Description:\n\nProvide professional nutritional and health consultations (including dietary and weight control) on achieving clients' needs\nProvide and maintain excellent client relationship\nIntroduce and suggest appropriate health supplements and treatments to clients\nEdit and revise nutrition related articles and leaflets\nAssist in company nutrition and health promotion training, activities, seminars and presentations\nPerform ad hoc duties assigned by Supervisor\n\nRequirements:\n\nDegree in Nutrition / Food Science or equivalent\n1 year or above work\u00a0experience in nutrition, dietary consultation or health supplement sales\nCustomer oriented, self-motivated with positive attitude\nAble to work both independently and as a team, and under pressure\nGood presentation, communication & interpersonal skills\nProficient in spoken and written English and Chinese\nProficient in MS Office\nRecent Nutrition graduates will also be considered\n\nWork Locations:\n\nMongkok/Tsim Sha Tsui/Causeway Bay/Admiralty (5 mins walk from MTR station)\n\nWork Hours:\n\n8 hours per day (Monday to Friday 12-9pm, Saturday 10am-7pm)\nOff on every Sunday, no shift work required\n\nBenefits:\n\nAnnual Leave 12 days or above, birthday leave\nBonus day off\nYear-end bonus and salary adjustment\nCompetitive incentive and commission scheme + bonus\nOvertime work allowance\nMedical benefits\nOn-job training\nExcellent career development opportunities\nStaff purchase discounts (health and skincare products)\nStaff referral bonus\n\nWe offer attractive salary package with excellent career development opportunities to the right candidates. Please send your full CV stating your availability, current and expected salary via\n\nWHATSAPP 95419788 (https://wa.me/85295419788)\nClick 'APPLY NOW'", "employment_types": ["Full Time", "Permanent"], "selling_points": ["Nutrition consultation, supplement recommendation", "1 year+ experience in nutrition / sales", "Nutrition fresh grad also considered"], "locations": ["Mong Kok"], "categories": ["Beauty Care / Health", "Athletics / Fitness / Sports & Recreation", "Nutritionist", "Others"], "post_time": "2021-12-28T03:31:51Z", "salary": {"currency": null, "max": null, "min": null, "period": "monthly", "term": null}, "salary_visible": false, "title_keywords": ["\u71df\u990a\u5e2b", "advisor", "nutritionist"], "responsibilities": ["ad hoc duties", "control", "leaflets", "presentations", "maintain"], "requirements": {"degrees": ["degree"], "majors": ["food science"], "languages": ["english", "chinese"], "language_level": ["proficient"], "hard_skills": ["ms office"], "soft_skills": ["self-motivated", "independently", "under pressure", "positive attitude", "communication", "interpersonal skills", "presentation"], "languages_combined": [{"language": "english", "language_level": ["proficient"]}, {"language": "chinese", "language_level": ["proficient"]}]}, "experience_required": {"duration": ["1 year"], "field": []}}, {"job_id": "100003009008683", "location_code": "hk", "company": "Pruvit (HK) Limited", "job_title": "Social Media Specialist", "description": "Social Media Specialist\n\nJob Responsibilities\n\n\u00a0\u00a0\u00a0Design the blue print for the social media development, make strategies to fulfil community expanding goals\n\n\n\u00a0\u00a0\u00a0Manage social media properties (Facebook, Instagram, Wechat etc.), including daily monitoring, posting, and content development\n\n\n\u00a0\u00a0\u00a0Lead on all social media content - from planning the approach to seeing through delivery\n\n\n\u00a0\u00a0\u00a0According to trending topics and social analytics, coordinate and implement social media marketing communications with responsibilities that include social media advertising and creating brand awareness\n\u00a0\u00a0\u00a0Monitor and evaluate results from social media campaigns, and consolidate these to improve strategies\n\n\n\u00a0\u00a0\u00a0Engage regularly with members on the social media community, provide value and building relationships with members\n\n\n\u00a0\u00a0\u00a0Measure the success of community-building activity to inform future initiatives, propose strategies to upgrade constantly\n\nJob Requirements\n\n\n\u2014MUST\n\n\u2022 Bachelor's degree in communications, language studies, marketing or media fields\n\n\u2022\u00a0\u00a0\u00a0Strong command of spoken and written English, Mandarin and Cantonese\n\n\u2022 Creative and passionate in lifestyle, health & fitness and photography\n\n--BETTER\n\n\u2022\u00a0\u00a0\u00a0Able to use app or software on graphic and video treatment\u2022\u00a0\u00a0\u00a0Proficient in production tools (Photoshop, illustrator, Adobe Premiere, Final Cut Pro, etc)\n\nIANG welcome!\n\nHere with Pr\u00fcvit, you will enjoy:\n\n\u2022\u00a0\u00a0\u00a0International community supports and first-hand training resources for personal development\n\u2022\u00a0\u00a0\u00a0Competitive compensations\n\u2022\u00a0\u00a0\u00a05 days work\n\u2022\u00a0\u00a0\u00a0Medical insurance\n\u2022\u00a0\u00a0\u00a0Double pay\n\nIf you are the one, do not hesitate to click the \u201cApply\u201d to send us your CV and covering letter.\n\nIn you covering letter, you should include:\n\n-Why you think you are suitable for the position;\n\n-What is it that you want to PR\u00dcV with social media\n\n-Your favourite facebook branding page in Asia (one to three choices)\n\n-One fun fact about yourself\n\nApplications without the covering letter will NOT be considered.", "employment_types": ["Full Time", "Permanent"], "selling_points": [], "locations": ["Hung Hom"], "categories": ["Media & Advertising", "Strategic Planning", "Beauty Care / Health", "Nutritionist", "E-commerce", "Marketing - Brand / Product Management"], "post_time": "2021-12-30T21:58:11Z", "salary": {"currency": null, "max": null, "min": null, "period": "monthly", "term": null}, "salary_visible": false, "title_keywords": ["social media specialist"], "responsibilities": ["social media", "communications with", "advertising", "social media campaigns", "monitor", "design", "coordinate", "evaluate", "social media content", "facebook", "daily monitoring", "planning"], "requirements": {"degrees": ["degree", "bachelor"], "majors": ["marketing", "communications"], "languages": ["cantonese", "english", "mandarin"], "language_level": [], "hard_skills": ["final cut pro", "fun", "illustrator", "adobe premiere", "facebook", "photoshop"], "soft_skills": ["passionate", "creative"], "languages_combined": [{"language": "cantonese", "language_level": []}, {"language": "english", "language_level": []}, {"language": "mandarin", "language_level": []}]}, "experience_required": {"duration": [], "field": []}}, {"job_id": "100003009042580", "location_code": "hk", "company": "FANCL (Fantastic Natural Cosmetics Limited)", "job_title": "Nutritionist", "description": "We are looking for passionate, dynamic and committed talents to work in our shops to provide integrated and professional nutrition, dietary, and health consultation service to our customers. He/ she will undergo extensive and well-organized training in the aspect of selling, service, product knowledge and shop management to fast track the career in the beauty and health industry.\n\nResponsibilities:\n\nAssess and analyze customers\u2019 nutritional needs so as to provide professional consultations and recommendations to them in our shops\nParticipate in health talks and events\nConduct internal staff training on professional health and product knowledge\nAssist in the planning and implementing of health promotion and product-selling strategies\n\nRequirements:\n\nDegree holders in Food Science, Nutrition, Dietetics or related disciplines\nAt least one year of experience in providing nutrition and dietary consultation services\nA pleasant manner, self-motivated, customer-oriented and willing to learn\nExcellent communication and interpersonal skills\nGood command of written and spoken English and Chinese. Spoken Mandarin will be an advantage\nRecent graduates will also be considered\n\nWe offer attractive remuneration package, employee benefits & staff caring items, including:\n\nHK$5,000 New Joiner Bonus\u00a0\nShift Duties\n7 days of holiday per month\n12 days of Annual Leave\u00a0 \u00a0 \u00a0 \u00a0 \u00a0 \u00a0 \u00a0 \u00a0 \u00a0 \u00a0 \u00a0 \u00a0 \u00a0 \u00a0 \u00a0\u00a0\nCompetitive Commission Payment\nGuaranteed Commission\nDiscretionary Bonus\nAttendance Bonus\nOvertime Work Allowance\nStaff Referral Bonus\u00a0\nMedical Benefits\nFree Product\u00a0 \u00a0 \u00a0 \u00a0 \u00a0 \u00a0 \u00a0 \u00a0 \u00a0 \u00a0 \u00a0 \u00a0 \u00a0 \u00a0 \u00a0 \u00a0 \u00a0 \u00a0 \u00a0 \u00a0\u00a0\nStaff Purchase Discounts\nOn-the-Job Training\nBirthday Gifts\u00a0 \u00a0 \u00a0 \u00a0 \u00a0 \u00a0 \u00a0 \u00a0 \u00a0 \u00a0 \u00a0 \u00a0 \u00a0 \u00a0 \u00a0 \u00a0 \u00a0 \u00a0\u00a0\nStaff Activities such as our Christmas Party, Annual Dinner, Birthday / Staff Gathering Parties etc\n\nFor interested applicants, please send your full r\u00e9sum\u00e9 with expected salary to \"Apply Now\" or below channels:\n\n1) Telephone\uff1a\u00a0\u00a0 3622 0766\n2) WhatsApp\uff1a\u00a0 \u00a06638 3569\u00a0\n3) Website\u00a0 \u00a0 \uff1a\u00a0\u00a0\u00a0http://www.fancl-hk.com/recruitment/zapplicationaddB.asp\n\nPlease also state your public examination results for internal reference purpose.\n\nPersonal data collected will be used for recruitment purposes only.", "employment_types": ["Full Time", "Permanent"], "selling_points": ["Nutritionist", "$5000 new staff bonus, 7 days off/mth, 12 paid AL", "Retail experiences. Fresh graduates are welcome"], "locations": ["Not Specified"], "categories": ["Beauty Care / Health", "Nutritionist", "Sales, CS & Business Devpt", "Retail Sales"], "post_time": "2022-01-12T08:04:05Z", "salary": {"currency": null, "max": null, "min": null, "period": "monthly", "term": null}, "salary_visible": false, "title_keywords": ["nutritionist"], "responsibilities": ["planning"], "requirements": {"degrees": ["degree"], "majors": ["related disciplines", "food science"], "languages": ["english", "chinese", "mandarin"], "language_level": ["advantage", "good command"], "hard_skills": [], "soft_skills": ["self-motivated", "willing to learn", "pleasant", "customer-oriented", "communication and interpersonal skills"], "languages_combined": [{"language": "english", "language_level": ["good command"]}, {"language": "chinese", "language_level": ["good command"]}, {"language": "mandarin", "language_level": ["advantage"]}]}, "experience_required": {"duration": ["at least one year"], "field": []}}, {"job_id": "100003009034382", "location_code": "hk", "company": "Twin Wealth Biotech Limited", "job_title": "Sales & Marketing Executive / Senior Sales & Marketing Executive", "description": "Responsibilities\n\nDrive sales to achieve company's assigned sales target;\nMonitor and maintain good relationship with existing distributors to maximize sales and profits;\nProactively develop new distribution channels to ensure continuous business growth and expand market coverage;\nPerform sales analysis and gather market information for sales and marketing strategies' fomulation;\nPlan & execute marketing activities for assigned product portfolio to increase brand awareness, expand customer base, engagement and achieve sales target;\nDevelop strategy and content for digital marketing & social media platforms across different markets and to evaluate effectiveness of different marketing campaigns;\nManage internal designers & work closely with third parties for advertisements' production;\nMonitoring A&P expenditure & product budget;\nOrganize and support exhibitions, events & brand activities year-round\nSupport ad-hoc projects and marketing activities as assigned.\n\nRequirements\n\nUniversity degree holder in Marketing / Health Technology / Nutriology / Biology Chemistry or related discipline;\u00a0 candidate with science background is preferable\nAt least 3 years' working experience in FMCG / Health Supplement / Skin Care Industry;\nExperience in brand management will be an advantage;\nExperience in digital marketing and social media marketing is a must\nProficiency in both spoken and written English and Chinese (Mandarin is an asset);\nCreative, detail oriented, outgoing and result-oriented with excellent interpersonal communication skill;\nAble to work under pressure with multi-tasking skill, willing to learn;\nHigh sense of responsibility, mature and self-initiative;\nExcellent PC skills;\nCandidate with more relevant experiences will be considered as Assistant Manager\n\nInterested parties please apply in full resume including current and expected salary by clicking\u00a0'Apply Now'.\u00a0To know more about\u00a0us, please visit our company website at\u00a0http://www.healthbank.com.hk.\n\nAll information received will be kept in strict confidence and only be used for employment-related purposes.", "employment_types": ["Full Time", "Permanent"], "selling_points": [], "locations": ["Central & Western Area"], "categories": ["Beauty Care / Health", "Nutritionist", "Marketing / Public Relations", "Marketing - Brand / Product Management", "Sales, CS & Business Devpt", "Sales - Sales Management"], "post_time": "2022-01-10T03:17:13Z", "salary": {"currency": null, "max": null, "min": null, "period": "monthly", "term": null}, "salary_visible": false, "title_keywords": ["senior sales & marketing executive", "sales & marketing executive"], "responsibilities": ["market information", "marketing strategies", "advertisements", "sales target", "analysis", "monitor", "social media platforms", "monitoring", "develop", "maintain good relationship", "evaluate", "budget", "digital marketing", "plan", "marketing campaigns", "drive sales", "ad-hoc projects"], "requirements": {"degrees": ["university degree"], "majors": ["chemistry", "biology", "marketing"], "languages": ["english", "chinese", "mandarin"], "language_level": ["proficiency"], "hard_skills": ["pc skills"], "soft_skills": ["outgoing", "multi-tasking skill", "interpersonal", "detail oriented", "communication skill", "willing to learn", "high sense of responsibility", "mature", "self-initiative", "creative", "result-oriented", "work under pressure"], "languages_combined": [{"language": "english", "language_level": ["proficiency"]}, {"language": "chinese", "language_level": ["proficiency"]}, {"language": "mandarin", "language_level": []}]}, "experience_required": {"duration": ["at least 3 years"], "field": ["social media", "management", "fmcg", "brand", "marketing", "digital marketing"]}}, {"job_id": "100003009023065", "location_code": "hk", "company": "The Rosehip Specialist (HK) Limited", "job_title": "Sales & Marketing Manager (Pet Supplement Brand for Asia)", "description": "Job Responsibilities\n\nTake the ownership of the marketing plan development, and create effective promotion strategies to drive interest and new leads in various channel.\nManage the tactical execution of marketing campaigns, including sales offer, online/offline communication, digital content creation, etc.\nLead the team to formulate extra sales channel for promotion, including joint promotion, Marketing research, etc.\nOversee the implementation and budget of digital channel, including SEO/SEM, social media, etc\nUnderstand key marketing performance metrics and tracking tools to provide insights on channel strategies, forecast and competitor analysis\nAnalyze product performance and competitor\u2019s trends to uncover consumer behaviour\n\nJob Requirement\n\nDegree holder in Business or Marketing or related disciplines\nOver 2 years Digital Marketing experience and proven experience within Social Media\nWork experience in pet products market is definitely\u00a0an advantage\nFamiliar with Performance Marketing like SEO / SEM, Web Analytics and Facebook ad.\nExperience in building Digital teams KPI\u2019s processes\nExcellent planning and project management skills\nCreative, energetic, good interpersonal and communication skills\nExcellent command in English, Cantonese and Mandarin\nCandidate with less experienced will be considered as Assistant Marketing Manager", "employment_types": ["Full Time", "Permanent"], "selling_points": [], "locations": ["Tsim Sha Tsui"], "categories": ["Beauty Care / Health", "Nutritionist", "Sales, CS & Business Devpt", "Retail Sales", "E-commerce", "Marketing - Brand / Product Management"], "post_time": "2022-01-06T01:29:12Z", "salary": {"currency": null, "max": null, "min": null, "period": "monthly", "term": null}, "salary_visible": false, "title_keywords": ["sales & marketing manager"], "responsibilities": ["social media", "provide insights", "seo", "analysis", "budget", "implementation", "performance metrics", "communication", "marketing plan", "marketing research", "marketing campaigns", "sem", "forecast", "tracking"], "requirements": {"degrees": ["degree holder"], "majors": ["related disciplines", "business", "marketing"], "languages": ["cantonese", "english", "mandarin"], "language_level": ["excellent"], "hard_skills": ["seo", "project management", "sem", "web analytics", "facebook"], "soft_skills": ["communication skills", "creative", "project management skills", "web analytics", "energetic", "interpersonal"], "languages_combined": [{"language": "cantonese", "language_level": ["excellent"]}, {"language": "english", "language_level": ["excellent"]}, {"language": "mandarin", "language_level": ["excellent"]}]}, "experience_required": {"duration": ["2 years"], "field": ["social media", "digital marketing", "digital"]}}, {"job_id": "100003009014533", "location_code": "hk", "company": "Haven of Hope Christian Service", "job_title": "Dietitian (Ref: NH/EHCCS/Diet/JDB)", "description": "Provide Dietetic services to elderly of the home care and residential home service, including conducting menu modification, home visits, direct assessment, treatment as well as coordinating health talk, workshops and programs;\nAs an active member of the multi-disciplinary team, provide professional inputs in care plan formulating;\nProvide education & coaching to the staff\nPlease send full resume with expected salary and reference no. quoted to Haven of Hope Christian Service, Staff Engagement Department, 7 Haven of Hope Road, Tseung Kwan O, New Territories or via email by clicking \"Apply Now\", or via Whatsapp no. 6507 8148 (with reference no. quoted at the caption) on or before 22 January 2022. Only short-listed candidates will be notified.\nEnquiry: 2703 3227 (Phone); 6507 8148 (Whatsapp).\nFor details about our organization, please visit www.hohcs.org.hk.\nProspective employees are requested to undergo/submit Sexual Conviction Record Check for work relating to children or mentally incapacitated persons before employment. Data collected will be used for recruitment purpose only.\nThis advertisement should not be reproduced, in whole or in part, to other recruitment websites without our prior written permission.", "employment_types": ["Full Time", "Permanent"], "selling_points": [], "locations": ["Tseung Kwan O"], "categories": ["Beauty Care / Health", "Nutritionist", "Others"], "post_time": "2022-01-03T03:38:45Z", "salary": {"currency": null, "max": null, "min": null, "period": "monthly", "term": null}, "salary_visible": false, "title_keywords": ["dietitian"], "responsibilities": ["recruitment", "plan", "data"], "requirements": {"degrees": [], "majors": [], "languages": [], "language_level": [], "hard_skills": ["workshops", "whatsapp", "no", "hope"], "soft_skills": ["active"], "languages_combined": []}, "experience_required": {"duration": [], "field": []}}, {"job_id": "100003009015701", "location_code": "hk", "company": "Slowood Limited", "job_title": "Merchandiser (Asia & China OEM)", "description": "We are looking for an individual who commit to promote sustainable lifestyle and help building a cleaner earth for our future generation. Cover letter with passionate on sustainable living is a must.\u00a0\n\nResponsibilities\u00a0\n\nPlan and execute purchase order, ensue inventory level is at best\u00a0 level\nMaintain good relationship with both local & existing oversea suppliers\nSourcing and develop product with factory to create new solution to reduce single use waste\nPerform QA check on Food and non Food daily essential items, ensure quality meet slowood value\nNegotiate with suppliers to achieve best pricing, quality and term\nManage and update ERP system, capable to manage big data on different CSV file\n\nSkill Requirements\n\nPassionate in promoting zero waste/ sustainable lifestyle\u00a0\nKnowledge / interest in health foods and / package-free / eco-conscious living.\nMinimum of 1 year\u2019s relevant experience in local and China OEM merchandising.\nCapable to handle ERP/ inventory management system\nPC knowledge: Advance Excel plus strong data analyzing & management skill\nGood command of both written and spoken English & Chinese, Mandarin is required\nMulti task, strong analytical\u00a0skills & detail minded person\n\nBenefit\n\nYear end bonus according to performance\n5 days per week (09:00 \u2013 18:00) (flexible working time )\nBank Holiday\nMPF\nMedical insurance\n\nWorking area\u00a0\n\nTsuenWan\u00a0\n\nApplication Method\n\nIf you do care about the nature and hope to build a strong bonding with a group of environment lovers, please don\u2019t hesitate to apply by sending your CV, availability and position interest to us.\n\nPersonal data provided will be used for recruitment purposes only.", "employment_types": ["Full Time"], "selling_points": ["experience in local and China OEM merchandising", "5 days work per week, fixable working hours", "Passionate in promoting zero waste lifestyle"], "locations": ["Tsuen Wan Area"], "categories": ["Beauty Care / Health", "Nutritionist", "Information Technology (IT)", "Product Management / Business Analyst", "Merchandising & Purchasing", "Procurement / Purchasing / Sourcing"], "post_time": "2022-01-03T07:25:46Z", "salary": {"currency": null, "max": null, "min": null, "period": "monthly", "term": null}, "salary_visible": false, "title_keywords": ["merchandiser"], "responsibilities": ["inventory", "quality", "big data", "develop", "maintain good relationship", "purchase", "plan"], "requirements": {"degrees": [], "majors": [], "languages": ["english", "chinese", "mandarin"], "language_level": ["good command"], "hard_skills": ["excel", "plus", "erp", "analytical skills", "pc knowledge"], "soft_skills": ["passionate", "capable", "analytical skills"], "languages_combined": [{"language": "english", "language_level": ["good command"]}, {"language": "chinese", "language_level": ["good command"]}, {"language": "mandarin", "language_level": ["good command"]}]}, "experience_required": {"duration": ["minimum of 1 year"], "field": ["merchandising", "relevant experience"]}}, {"job_id": "100003009002449", "location_code": "hk", "company": "Thanks Ai Hong Kong Limited", "job_title": "Marketing Executive", "description": "Responsibilities and Duties:\n-\u00a0\u00a0\u00a0\u00a0\u00a0\u00a0\u00a0\u00a0\u00a0 Prepare all marketing materials and compose written content relates to products\n-\u00a0\u00a0\u00a0\u00a0\u00a0\u00a0\u00a0\u00a0\u00a0 Assist in nutrition article and social media writing\n-\u00a0\u00a0\u00a0\u00a0\u00a0\u00a0\u00a0\u00a0\u00a0 Compose training materials and conduct regular training and health talk to our members\n-\u00a0\u00a0\u00a0\u00a0\u00a0\u00a0\u00a0\u00a0\u00a0 Assist in ad hoc marketing campaigns and events as assigned\n\nRequirement:\n-\u00a0\u00a0\u00a0\u00a0\u00a0\u00a0\u00a0\u00a0\u00a0 Degree holder in marketing with minimum 1 years working experience, former experience in FMCG and/ nutritional supplement industry is preferred\n-\u00a0\u00a0\u00a0\u00a0\u00a0\u00a0\u00a0\u00a0\u00a0 Good command of written English and Chinese; Fluency in Mandarin will be an advantage\n-\u00a0\u00a0\u00a0\u00a0\u00a0\u00a0\u00a0\u00a0\u00a0 Customer-oriented with pleasant, outgoing character with good presentation skill\n-\u00a0\u00a0\u00a0\u00a0\u00a0\u00a0\u00a0\u00a0\u00a0Proficient in design software, including Photoshop, Illustrator, Premiere\n\nInterested parties please e-mail your resume with available date, current and expected salary by clicking \"Apply Now\".\n\n", "employment_types": ["Full Time"], "selling_points": [], "locations": ["Tsim Sha Tsui"], "categories": ["Beauty Care / Health", "Nutritionist", "Marketing / Public Relations", "Marketing - Brand / Product Management"], "post_time": "2021-12-28T05:44:16Z", "salary": {"currency": null, "max": null, "min": null, "period": "monthly", "term": null}, "salary_visible": false, "title_keywords": ["marketing executive"], "responsibilities": ["marketing materials", "social media", "ad hoc", "marketing campaigns"], "requirements": {"degrees": ["degree holder"], "majors": ["marketing"], "languages": ["english", "chinese", "mandarin"], "language_level": ["fluency", "advantage", "good command"], "hard_skills": ["presentation skill", "illustrator", "premiere", "photoshop"], "soft_skills": ["outgoing", "customer-oriented", "presentation skill", "pleasant"], "languages_combined": [{"language": "english", "language_level": ["good command"]}, {"language": "chinese", "language_level": ["good command"]}, {"language": "mandarin", "language_level": ["fluency", "advantage"]}]}, "experience_required": {"duration": ["minimum 1 years"], "field": ["marketing", "fmcg"]}}, {"job_id": "100003008999290", "location_code": "hk", "company": "Haven of Hope Christian Service", "job_title": "Dietitian (Ref: NH/ Diet/JDB)", "description": "Provide Dietetic services to elderly of the home care and residential home service, including conducting menu modification, home visits, direct assessment, treatment as well as coordinating health talk, workshops and programs;\nAs an active member of the multi-disciplinary team, provide professional inputs in care plan formulating;\nProvide education & coaching to the staff\nPlease send full resume with expected salary and reference no. quoted to Haven of Hope Christian Service, Staff Engagement Department, 7 Haven of Hope Road, Tseung Kwan O, New Territories or via email by clicking \"Apply Now\", or via Whatsapp no. 6507 8148 (with reference no. quoted at the caption) on or before 15 January 2022. Only short-listed candidates will be notified.\nEnquiry: 2703 3227 (Phone); 6507 8148 (Whatsapp).\nFor details about our organization, please visit www.hohcs.org.hk.\nProspective employees are requested to undergo/submit Sexual Conviction Record Check for work relating to children or mentally incapacitated persons before employment. Data collected will be used for recruitment purpose only.\nThis advertisement should not be reproduced, in whole or in part, to other recruitment websites without our prior written permission.", "employment_types": ["Full Time", "Permanent"], "selling_points": [], "locations": ["Tseung Kwan O"], "categories": ["Beauty Care / Health", "Nutritionist", "Others"], "post_time": "2021-12-24T06:48:01Z", "salary": {"currency": null, "max": null, "min": null, "period": "monthly", "term": null}, "salary_visible": false, "title_keywords": ["dietitian"], "responsibilities": ["recruitment", "plan", "data"], "requirements": {"degrees": [], "majors": [], "languages": [], "language_level": [], "hard_skills": ["workshops", "whatsapp", "no", "hope"], "soft_skills": ["active"], "languages_combined": []}, "experience_required": {"duration": [], "field": []}}]