[{"job_id": "100003009052344", "location_code": "hk", "company": "Be Priceless Limited", "job_title": "Business Development and Operations Manager for Non-profit Educational Organization", "description": "Be Priceless\u00a0is a non-profit educational organization that aims to empower disadvantaged children and their communities to strengthen well-being and safety. We believe in a more equitable world where no child is left behind.\n\nWe are seeking a passionate candidate to be the Operations Manager who has extensive experienced in business and partnership development, and program management for non-profit organization or education entrepreneurship sector in Hong Kong.\u00a0 \u00a0 \u00a0 \u00a0 \u00a0 \u00a0 \u00a0 \u00a0\n\nBe Priceless is growing well and the Operations Manager will have a key role in driving the development of the programs, resources, as well as partnerships with trusted NGOs, schools, community groups and members.\n\nWe develop in depth evidence and best practice-based educational programs to build capacity, mindsets and practices of children, caregivers and care service providers to promote personal development, well-being (physical, mental and social health) and risk reduction (against violence, exploitation, health risks, disasters, etc).\u00a0\u00a0\n\nWe work by shared leadership and community-wide collaboration to create and deliver an impactful educational program. Our team comes from diverse technical and community backgrounds. For more information, please visit\u00a0www.bepriceless.org\n\nJob Highlight - Opportunities:\n\n\u00b7\u00a0\u00a0\u00a0\u00a0\u00a0Assist the founder with internal processes and monitor the growth of a transformative educational program that empowers and engages an all-of-city approach to strengthening children, youth and families' well-being and safety.\n\n\u00b7\u00a0\u00a0\u00a0\u00a0\u00a0Coordinate and collaborate with dynamic team of multicultural experts from diverse fields, community members, child and youth in empowering ways.\n\n\u00b7\u00a0\u00a0\u00a0\u00a0\u00a0\u00a0Positive, collaborative, nurturing organizational culture\n\nKey Jobs Responsibilities:\n\n\n\n-\u00a0 \u00a0 \u00a0 Direct report to founder\u00a0\n\n\n\u00b7\u00a0\u00a0\u00a0\u00a0\u00a0\u00a0Develop and implement business plans to generate resources and enhance outcomes and impacts.\n\n\u00b7\u00a0\u00a0\u00a0\u00a0\u00a0\u00a0Facilitate pursuit of opportunities for development and funding for Be Priceless by contributing to grant proposal development.\n\n\u00b7\u00a0\u00a0\u00a0\u00a0\u00a0\u00a0Drive and strengthen organization culture, mechanisms and actions for producing impact, collaboration, coordination, communication, accountability, quality control, team and program operations management.\n\n\u00b7\u00a0\u00a0\u00a0\u00a0\u00a0\u00a0Drive and manage all team operations and coordination.\n\n\u00b7\u00a0\u00a0\u00a0\u00a0\u00a0\u00a0Coordinate the planning, development, implementation, assessments and reporting of all educational and other organizational projects\n\n\u00b7\u00a0\u00a0\u00a0\u00a0\u00a0\u00a0Drive the child safeguarding and protection policy, protocol, monitoring and reporting mechanisms.\n\n\u00b7\u00a0\u00a0\u00a0\u00a0\u00a0\u00a0Work with and support the team, including optimizing operational aspects of the program.\n\n\u00b7\u00a0\u00a0\u00a0\u00a0\u00a0\u00a0Lead the initiatives to promote learning, well-being and safety of the team and the stakeholders we serve\n\n\u00b7\u00a0\u00a0\u00a0\u00a0\u00a0\u00a0Drive and strengthen community engagement\n\n\u00b7\u00a0\u00a0\u00a0\u00a0\u00a0\u00a0Develop strong program management to promote nurturing organization culture, effective impact achievement, multisectoral collaboration, accountability, including tools to strengthen the organization structure, process, work and future development;\n\n\u00b7\u00a0\u00a0\u00a0\u00a0\u00a0\u00a0Create and upkeep processes and team management that facilitate internal and external communication and collaborations from online tools, in-person participation, ongoing updates, to team and partners engagement;\u00a0\n\n\u00b7\u00a0\u00a0\u00a0\u00a0\u00a0\u00a0Facilitate and participate educational program planning, development, production, dissemination, evaluation and review.\n\nJob Requirement:\n\no\u00a0\u00a0Strong track record in business development and operation management role in non-profit sector, social entrepreneurship, or educational sector.\u00a0\n\no\u00a0 High level of competence, independence, integrity and accountability required.\n\no\u00a0\u00a0At least 3-5 years of experience in organization operations management.\u00a0\n\no\u00a0\u00a0Strong experience in working with other non-profit, social entrepreneur, or education sectors.\u00a0\n\n\u00b7\u00a0\u00a0\u00a0Passionate and dedicated in promoting child and youth learning, well-being and protection\n\n\u00b7\u00a0\u00a0\u00a0Adaptive, flexible, productive, efficient and collaborative\n\n\u00b7\u00a0\u00a0\u00a0Strong ethical and professional standard - including accountability, transparency.\n\n\u00b7\u00a0\u00a0\u00a0Strong\u00a0communication, leadership,\u00a0collaboration, coordination and problem solving skills.\n\n\u00b7\u00a0\u00a0\u00a0Strong productivity, organization and time management skills.\n\n\u00b7\u00a0\u00a0\u00a0Social media management proficiency\n\n\u00b7\u00a0\u00a0\u00a0Professional level written and spoken English is required\u00a0\n\n\u00b7\u00a0 Professional level written and spoken one or more of the following is required: Chinese, Nepali, Urdu, Hindi, Tagalog, or Bahasa.\n\n\u00b7\u00a0\u00a0\u00a0Regular background checks (including\u00a0Sexual\u00a0Conviction Record\u00a0Check\u00a0(SCRC)\u00a0and previous employment checks) and abiding to code of conduct including for child safeguarding-protection are an absolute requirements. We have continuous and rigorous monitoring of issues of concerns safety of children and other vulnerable individuals. We will investigate/ report where appropriate.\u00a0\u00a0\n\nPreferred experience/ skills:\u00a0\n\nDegree in education, psychology, social work or related field\nData management and analysis\nExperience in developing e-learning or other educational programs\u00a0\n\nLogistics:\u00a0Full-time, candidate must be in Hong Kong\n\nDuration: Long-term contract with 3 month probation.\n\nSalary: \u00a0Based on experience\n\nExpected\u00a0Start Date: immediately\n\nIf you are interested, please apply with\u00a0your full resume with cover letter as the front page, time availability and expected salary.", "employment_types": ["Full Time"], "selling_points": ["Development, Partnerships, Management, Leadership", "competitive salary, empowering, multi-sectoral", "Non-profit, social entrepreneur, education"], "locations": ["Central"], "categories": ["Education", "Others", "Public / Civil", "Social Services - Community / Non-profit Organization", "Management", "Top Executives (CEO, CFO, CTO, GM, MD etc.)"], "post_time": "2022-01-17T02:48:44Z", "salary": {"currency": "HKD", "max": 54999, "min": 45000, "period": "monthly", "term": null}, "salary_visible": true, "title_keywords": ["business development and operations manager"], "responsibilities": ["reporting", "management", "evaluation", "operations", "monitoring", "review", "implementation", "business plans", "develop", "communication", "coordinate", "planning", "coordination", "quality control", "support the team", "report"], "requirements": {"degrees": ["degree"], "majors": ["social work", "psychology"], "languages": ["english", "urdu", "hindi", "tagalog", "nepali", "chinese"], "language_level": [], "hard_skills": ["code", "problem solving skills", "analysis", "data management"], "soft_skills": ["passionate", "flexible", "productive", "efficient", "accountability", "time management skills", "integrity", "collaborative", "communication", "learning", "ethical", "coordination", "problem solving skills", "leadership"], "languages_combined": [{"language": "english", "language_level": []}, {"language": "urdu", "language_level": []}, {"language": "hindi", "language_level": []}, {"language": "tagalog", "language_level": []}, {"language": "nepali", "language_level": []}, {"language": "chinese", "language_level": []}]}, "experience_required": {"duration": ["at least 3-5 years"], "field": ["operations management", "developing", "education"]}}, {"job_id": "100003009053481", "location_code": "hk", "company": "\u7dad\u591a\u5229\u4e9e\u6559\u80b2\u6a5f\u69cb\u6709\u9650\u516c\u53f8", "job_title": "Operations and Admissions Assistant/Officer", "description": "The Operations and Admissions Assistant/Officer will assist to support with tasks related to daily school operations.\n\nJob Responsibilities\u00a0\n\nSchool operations related:\n\nTo assist with the central purchase orders of stationaries, gifts accessories, and printing of handbooks, staffs' /students cards, ensuring that purchasing/printing is carried out in accordance with the purchasing policy and guidelines.\nTo source new providers, manage and coordinate the arrangement of our extracurricular activities and the relevant contract renewal.\nTo liaise with outside extracurricular activities provides regarding availability, costs, group sizes, venues, contracts and code of conduct, etc.\u00a0\nTo communicate with the schools all matters pertaining to the extracurricular programme\nCompile statistics and data\nBe responsible for the booking of venue for organisation-wide events including graduation, sport days, staff annual dinner as well as other ad hoc events\nTo assist in school bus contract renewal\nTo work closely with Operation Manager and other departments/schools to provide support in the full range of operational tasks.\nSchool admissions-related:\u00a0\n\nProvide administrative support to the operations for the Admissions Team\nAdminister different kinds of communications materials and handle email inquiries from parent\nCommunicate with the administrative assistant of each campus to ensure the flow of admissions are in line\nVerify, print, and deliver all application forms for campuses\nManage the system with IT team\nRequirements:\n\nHolder of Bachelor's degree in any discipline\nMinimum 2 years' relevant experience, procurement experience is preferable.\nAbility to manage tight deadlines & competing workloads, and work within a changing environment\nSolid analytical skills with the ability to create cost analyses\nHave a service driver personality with good interpersonal, communication skills and problem-solving skills\nProficient in English and Chinese (verbal and written)\nComputer literary in Google and MS office suite ; specifically email, Word/Docs, Excel/Sheets.\nInterest parties please click \"APPLY\" and send Curriculum Vitae with full career details, salary history, availability, and expected salary.\u00a0", "employment_types": ["Full Time", "Permanent"], "selling_points": ["Bachelor's degree in any discipline", "Minimum 2 years of relevant experience", "Location : Wan Chai"], "locations": ["Wan Chai"], "categories": ["Admin & HR", "Clerical / Admin Staff", "Education", "Others"], "post_time": "2022-01-17T07:02:20Z", "salary": {"currency": null, "max": null, "min": null, "period": "monthly", "term": null}, "salary_visible": false, "title_keywords": ["operations", "officer", "assistant"], "responsibilities": ["communicate with", "provide support", "ad hoc", "data", "guidelines", "operations", "contracts", "operational tasks", "coordinate", "purchase", "booking", "liaise with", "provide administrative support", "costs"], "requirements": {"degrees": ["degree", "bachelor"], "majors": [], "languages": ["english", "chinese"], "language_level": ["proficient"], "hard_skills": ["excel", "word", "analytical skills", "problem-solving skills", "ms office"], "soft_skills": ["problem-solving skills", "communication skills", "interpersonal", "analytical skills"], "languages_combined": [{"language": "english", "language_level": ["proficient"]}, {"language": "chinese", "language_level": ["proficient"]}]}, "experience_required": {"duration": ["minimum 2 years"], "field": ["relevant experience", "procurement"]}}, {"job_id": "100003008990012", "location_code": "hk", "company": "Monkey Tree English Learning Center (Po Lam)", "job_title": "Admin Assistant / Administrator", "description": "This is a fast-paced, organised and multicultural team, you will be assigned to support our teachers and handle administrative and customer service duties.\u00a0\u00a0\u00a0 \u00a0\n\nThe candidate will be responsible for\n\nManage center operations and handle general administration work\nPerform high quality customer services at Front Desk\nPromote company\u2019s services & products to perspective customers\nHandle customers\u2019s enquiries & complaints\nProvide support for Center Manager & Teachers\n\n\nOur Requirements:\n\nPossess 1 to 3 years working experience in administration/customer service of educational industry will be highly recommended, DSE / Fresh Graduate also welcome\nFluent in both spoken and written English and Cantonese is a MUST.\u00a0 \u00a0\nLove kids and willing to take care of those in age 3-12 years old\u00a0\u00a0 \u00a0\nProficient in MS Word and Excel,\nWell-orangized is essential, detail-minded and multi-tasking skills\nService-oriented with good communication skills\nWilling to work on Saturdays\nDSE, Diploma/ Degree or above required\n\n\nBenefits include:\n\n5 day work week\nOff on all Public Holidays\nFriday Free Lunch\nBonus Scheme\nSales Commission\nMedical Scheme\n\n\nLocation - Po Lam \u2013 Tsueng Kwan O\n\nInterested parties please email us your resume with Expected SALARY as MUST.", "employment_types": ["Full Time"], "selling_points": ["Handle customers\u2019 enquiries & admin. work", "2 to 5 years working experience", "5 day work week, Medical Scheme, Bonus Scheme"], "locations": ["Tseung Kwan O"], "categories": ["Admin & HR", "Administration / Operation Manager", "Sales, CS & Business Devpt", "Customer Service - Supervisor / Officer", "Education", "Others"], "post_time": "2022-01-17T16:20:51Z", "salary": {"currency": null, "max": null, "min": null, "period": "monthly", "term": null}, "salary_visible": false, "title_keywords": ["admin assistant", "administrator"], "responsibilities": ["provide support", "operations", "quality", "customer services", "communication", "customer service", "customer service duties", "administration"], "requirements": {"degrees": ["fresh graduate", "diploma", "degree or above", "dse"], "majors": [], "languages": ["cantonese", "english"], "language_level": ["fluent"], "hard_skills": ["excel", "ms word"], "soft_skills": ["detail-minded", "communication skills", "responsible", "service-oriented", "customer service", "organised", "multi-tasking skills"], "languages_combined": [{"language": "cantonese", "language_level": ["fluent"]}, {"language": "english", "language_level": ["fluent"]}]}, "experience_required": {"duration": ["1 to 3 years"], "field": ["customer service", "administration"]}}, {"job_id": "100003009052538", "location_code": "hk", "company": "School of Continuing Education, HKBU", "job_title": "Programme Assistant (Ref. No.: PRSCE0037/21-22)", "description": "The appointee is expected to carry out general administrative duties for Division of Continuing and Professional Education. Major duties include: (a) assisting in the day-to-day operation of the programmes, including but not limited to class scheduling, examination arrangement, student record updating, and organisation of student activities; (b) liaising with internal and external parties (including staff, students and external bodies) and handling enquiries and complaints; (c) compiling information and figures and maintaining database / file records; and (d) providing supports to ad-hoc duties as assigned by the supervisor(s).\nMinimum Requirements:\n\u00a0(i) Holder of Higher Diploma or Associate Degree with preferably 2 years of related experience; OR (ii) with at least 5 passes in HKCEE including English Language (at least Grade C if Syllabus A/Level 2 from 2007) and Chinese Language (at least Level 2 from 2007), or at least 5 subjects attaining Level 2 in HKDSE including English Language and Chinese Language with more work experience;\nHolder of Bachelor\u2019s degree with at least 1 year of work experience will also be considered;\nEffective interpersonal and multi-tasking skills;\nAble to work under tight schedule;\nGood command of written and spoken English and Chinese; and\nProficient in MS Office applications (English and Chinese) and Excel.\nSalary will be commensurate with qualifications and experience.\nApplication Procedure:\nApplicants are invited to submit their applications at the HKBU e-Recruitment System (jobs.hkbu.edu.hk). Shortlisted candidates will be invited to sit for written test. Applicants not invited for interview 8 weeks after the closing date may consider their applications unsuccessful. Details of the University's Personal Information Collection Statement can be found at http://hro.hkbu.edu.hk/pics.\nThe School reserves the right not to make an appointment for the post advertised, and the appointment will be made according to the terms and conditions then applicable at the time of offer.\nClosing date: 31 January 2022", "employment_types": ["Full Time"], "selling_points": [], "locations": ["Tsim Sha Tsui"], "categories": ["Admin & HR", "Clerical / Admin Staff", "Receptionist", "Education", "Others"], "post_time": "2022-01-17T03:20:13Z", "salary": {"currency": null, "max": null, "min": null, "period": "monthly", "term": null}, "salary_visible": false, "title_keywords": ["assistant"], "responsibilities": ["maintaining", "internal and external parties", "liaising with", "scheduling", "administrative duties", "schedule", "database", "ad-hoc duties", "recruitment", "day-to-day operation"], "requirements": {"degrees": ["associate degree", "bachelor", "diploma", "degree", "hkdse"], "majors": [], "languages": ["english", "chinese"], "language_level": ["good command", "proficient"], "hard_skills": ["excel", "make", "c", "ms office"], "soft_skills": ["multi-tasking skills", "interpersonal", "organisation", "ad-hoc duties"], "languages_combined": [{"language": "english", "language_level": ["good command", "proficient"]}, {"language": "chinese", "language_level": ["good command", "proficient"]}]}, "experience_required": {"duration": ["2 years", "at least 1 year"], "field": ["related", "chinese language"]}}, {"job_id": "100003009054635", "location_code": "hk", "company": "The Hong Kong University of Science and Technology", "job_title": "Assistant Officer (Kellogg-HKUST EMBA Program)(Job ID: 7069)", "description": "\n\u5609\u8afe\u6492\u8056\u65b9\u6fdf\u5404\u66f8\u9662 St. Francis\u2019 Canossian College\nStudent Support Officer\nAssist the Counselling Department and support SEN students\nRequirements:\nHigher diploma or above, with relevant experience preferred.\nInterested parties are invited to send their applications, enclosing full resumes stating qualifications, career history, aspirations and contact numbers latest by 31 January 2022 to:\nThe Principal\nSt. Francis\u2019 Canossian College\n9 \u2013 13 Kennedy Road, Wanchai, Hong Kong\nOr via email to: Apply Now\nInformation/ Personal data collected will be used for employment purposes only.\nPlease specify the applied position on the envelope or in the email.\n\u5b78\u6821 / \u6a5f\u69cb\u57fa\u672c\u8cc7\u6599\n\u2022 \u62db\u8058\u5b78\u6821/\u6a5f\u69cb\u540d\u7a31 \u5609\u8afe\u6492\u8056\u65b9\u6fdf\u5404\u66f8\u9662\n\u2022 \u7533\u8acb\u806f\u7d61\u4eba \u5229\u5c0f\u59d0 Ms. Li\n\u2022 \u96fb\u8a71 25872700\n\u2022 \u50b3\u771f 25291758\n\u2022 \u96fb\u90f5 Apply Now\n\u2022 \u5730\u5740 9-13 Kennedy Road, Wan Chai, Hong Kong.\n\u2022 \u6a5f\u69cb\u985e\u5225 \u4e2d\u5b78\n\n", "employment_types": ["Full Time"], "selling_points": ["collating course materials", "managing databases; preparing mailings", "handling enquiries; managing classroom facilities"], "locations": ["Sai Kung"], "categories": ["Admin & HR", "Clerical / Admin Staff", "Education", "Others", "Information Technology (IT)", "Others"], "post_time": "2022-01-17T10:21:05Z", "salary": {"currency": null, "max": null, "min": null, "period": "monthly", "term": null}, "salary_visible": false, "title_keywords": ["assistant officer"], "responsibilities": [], "requirements": {"degrees": ["higher diploma or above"], "majors": [], "languages": [], "language_level": [], "hard_skills": [], "soft_skills": [], "languages_combined": []}, "experience_required": {"duration": [], "field": ["relevant experience"]}}, {"job_id": "100003009054998", "location_code": "hk", "company": "Forex Forest Limited", "job_title": "Course Assistant (Shift Duty)", "description": "Job Title:\u00a0\u00a0\u00a0\u00a0\u00a0\u00a0\u00a0\u00a0\u00a0\u00a0Assistant Officer (Kellogg-HKUST EMBA Program)\nDepartment:\u00a0\u00a0\u00a0\u00a0School of Business and Management\nJob ID:\u00a0 \u00a0 \u00a0 \u00a0 \u00a0 \u00a0 \u00a07069\n\nJob Posting Details\n\nThe Kellogg-HKUST EMBA Program team is looking for an individual for the position of Assistant Officer.\u00a0 The appointee will render administrative support to the Kellogg-HKUST Executive MBA Program team.\u00a0 Duties include collating course materials; managing databases; preparing mailings; handling enquiries; managing classroom facilities; and performing other duties as assigned.\n\nApplicants should have a higher diploma or an associate degree with at least 1-2 years of work experience.\u00a0 Degree holders are also welcome to apply.\u00a0 Candidates should have good communication and interpersonal skills, and knowledge in Microsoft Office.\u00a0 The ability to perform multi-tasks is preferred.\u00a0 A good command of written and spoken English and fluency in Cantonese are required.\u00a0 Working outside normal office hours and during weekends will be expected. (Duration: 2 years, renewable)\n\nStarting salary will be commensurate with qualifications and experience. \u00a0Fringe benefits including annual leave, medical and dental benefits will be provided.\u00a0 A gratuity will be payable upon successful completion of contract.\n\nApplication Procedure\nIn support of a green work environment, we accept applications submitted online only.\u00a0 To apply, please complete an online application form through the HKUST Careers website (https://hkustcareers.ust.hk) and return it online to the Human Resources Office on or before Monday, 31 January 2022.\u00a0 Applicants will receive an acknowledgement by email upon successful submission.\u00a0 We thank applicants for their interest, but advise that only shortlisted candidates will be notified of the result of the application.\n\n(Information provided by applicants will be used for recruitment and other employment-related purposes only.)\n\nHKUST is an equal opportunities employer and is committed to our core values of\ninclusiveness, diversity, and respect.", "employment_types": ["Full Time", "Permanent"], "selling_points": ["Finance Education", "Course Assistance, admin & clerical support", "Admin Clerk, Assistant Administrator"], "locations": ["Tsim Sha Tsui"], "categories": ["Admin & HR", "Clerical / Admin Staff", "Education", "Others"], "post_time": "2022-01-17T16:22:52Z", "salary": {"currency": null, "max": null, "min": null, "period": "monthly", "term": null}, "salary_visible": false, "title_keywords": ["assistant"], "responsibilities": ["management", "other duties", "administrative support", "communication", "databases"], "requirements": {"degrees": ["associate degree", "diploma", "degree"], "majors": [], "languages": ["cantonese", "english"], "language_level": ["fluency", "good command"], "hard_skills": ["id", "databases", "microsoft office"], "soft_skills": ["communication and interpersonal skills", "multi-tasks"], "languages_combined": [{"language": "cantonese", "language_level": ["good command"]}, {"language": "english", "language_level": ["fluency", "good command"]}]}, "experience_required": {"duration": ["at least 1-2 years"], "field": []}}, {"job_id": "100003009054974", "location_code": "hk", "company": "HKU SPACE Po Leung Kuk Stanley Ho Community College", "job_title": "Executive Assistant (various posts)  (Ref: VP/ft/22-01)", "description": "Job Duties:\n\n\u00a0\u00a0\u00a0\u00a0\u00a0\u00a0\u00a0 Provide clerical and administrative support\n\u00a0\u00a0\u00a0\u00a0\u00a0\u00a0\u00a0 Update and maintain various internal record\n\u00a0\u00a0\u00a0\u00a0\u00a0\u00a0\u00a0 Provide regular internal reports\n\u00a0\u00a0\u00a0\u00a0\u00a0\u00a0\u00a0 Handle customers' enquiries and business correspondence\u00a0\u00a0\n\u00a0\u00a0\u00a0\u00a0\u00a0\u00a0\u00a0 Assist in project coordination with suppliers including material sourcing, ordering and delivery follow-up\n\u00a0\u00a0\u00a0\u00a0\u00a0\u00a0\u00a0 Perform general reception duties\n\u00a0\u00a0\u00a0\u00a0\u00a0\u00a0\u00a0 Perform ad hoc tasks as assigned\n\nJob Requirements:\n\n\u00a0\u00a0\u00a0\u00a0\u00a0\u00a0\u00a0 Required to work on Saturday and Sunday\n\u00a0\u00a0\u00a0\u00a0\u00a0\u00a0\u00a0 Shift duty is required\n\u00a0\u00a0\u00a0\u00a0\u00a0\u00a0\u00a0 Form 5 or equivalent\n\u00a0\u00a0\u00a0\u00a0\u00a0\u00a0\u00a0 1 year of working experience\n\u00a0\u00a0\u00a0\u00a0\u00a0\u00a0\u00a0 Strong senses of responsibility, communication skills, self-motivated, attention to details, analytical mind & independent\n\u00a0\u00a0\u00a0\u00a0\u00a0\u00a0\u00a0 Proficiency in computer literacy, MS Office application and Chinese word Processing\u00a0\u00a0\n\nWe offer\u00a05-day work\u00a0with competitive remuneration and benefit packages to the right candidate.\u00a0Interested parties please send your application with\u00a0full resume, present and expected salary\u00a0by clicking \"Apply Now\".\u00a0", "employment_types": ["Full Time", "Contract"], "selling_points": ["administrative and secretariat support", "manage tuition fees payments and prepare reports", "process student records and data, arrange exam"], "locations": ["Causeway Bay"], "categories": ["Education", "Others"], "post_time": "2022-01-17T16:22:40Z", "salary": {"currency": null, "max": null, "min": null, "period": "monthly", "term": null}, "salary_visible": false, "title_keywords": ["executive assistant"], "responsibilities": ["project coordination", "administrative support", "ad hoc tasks", "maintain", "reports"], "requirements": {"degrees": ["form 5 or equivalent"], "majors": [], "languages": ["chinese"], "language_level": ["proficiency"], "hard_skills": ["chinese word processing", "ms office"], "soft_skills": ["communication skills", "self-motivated", "independent", "computer literacy", "analytical mind", "attention to details"], "languages_combined": [{"language": "chinese", "language_level": ["proficiency"]}]}, "experience_required": {"duration": ["1 year"], "field": []}}, {"job_id": "100003009051638", "location_code": "hk", "company": "China Vantage International Holdings Limited", "job_title": "Programme Administrative Assistant / Clerk (Full-time)", "description": "We are now inviting suitable candidate(s) to join us in the School of Nursing and Health Studies for the following post(s):\u00a0\n\nAssistant Manager (Ref: 220004O)\n\nMajor Duties and Responsibilities\n\nThe appointee shall mainly be responsible for the following:\n\nadministering and coordinating the development of programmes and courses offered by the School, and the accreditation/re-accreditation with professional bodies;\nhandling administrative duties involved in research, learning and teaching activities, as well as student related matters;\nplanning and coordinating various events and activities such as seminars and conferences;\ncoordinating the local/overseas clinical practicum of students;\nproof-reading and editing information and documents to meet the internal quality assurance standard;\nparticipating in general office administration, management and enhancement;\nproviding secretarial service to committees and meetings;\nsupervising supporting staff on day-to-day operations; and\nperforming any other duties as assigned.\u00a0\n\nCandidates\n\nCandidates should possess the following qualifications, experience and attributes:\n\na recognized degree with at least 2 years of relevant post-qualification experience. \u00a0More/Considerable relevant experience at supervisory level in a varieties of university administration is preferred;\nexcellent interpersonal, communication, organizational and analytical skills;\nattributes of coping with ambiguity and change;\nability to handle multiple tasks concurrently and work independently; and\nan excellent command of both written and spoken English and Chinese, preferably including Putonghua.\n\nCandidates may be invited to attend a written test.\u00a0\n\nTerms and Conditions for Appointment\n\nAn attractive remuneration package, including basic salary, an end-of-contract gratuity, and a discretionary incentive payment, where applicable, will be offered to the right candidates. Generous annual leave, staff-development sponsorships, medical and dental benefits, and life insurance coverage will also be provided.\u00a0\n\nTo Apply\n\nCandidates who are interested in joining us may submit their applications via the University\u2019s eRecruitment System.\u00a0\n\nhttps://hkmu.taleo.net/careersection/ex_full_time/jobapply.ftl?lang=en&job=220004O\u00a0\n\nClosing date of application: 31 January 2022\n\nThe personal data collected will be used for the purpose of considering your application for employment.\u00a0 For details, please refer to the \u201cPersonal Data (Privacy) Notice for Job Applicant\u201d on the University\u2019s website.\u00a0 If you are not contacted by the University within eight weeks from the closing date of application, you may assume that your application is unsuccessful.\u00a0\u00a0", "employment_types": ["Full Time"], "selling_points": ["Education", "Administrative Assistant", "Administration"], "locations": ["Causeway Bay"], "categories": ["Admin & HR", "Clerical / Admin Staff", "Education", "Others"], "post_time": "2022-01-16T16:37:01Z", "salary": {"currency": null, "max": null, "min": null, "period": "monthly", "term": null}, "salary_visible": false, "title_keywords": ["administrative assistant", "clerk"], "responsibilities": ["administration", "any other duties", "management", "supervising", "office administration", "quality", "day-to-day operations", "secretarial service", "communication", "conferences", "payment", "administrative duties", "editing", "planning"], "requirements": {"degrees": ["degree"], "majors": [], "languages": ["putonghua", "english", "chinese"], "language_level": ["excellent"], "hard_skills": ["basic", "analytical skills"], "soft_skills": ["work independently", "responsible", "organizational", "analytical skills", "communication", "handle multiple tasks", "learning", "interpersonal"], "languages_combined": [{"language": "putonghua", "language_level": ["excellent"]}, {"language": "english", "language_level": ["excellent"]}, {"language": "chinese", "language_level": ["excellent"]}]}, "experience_required": {"duration": ["at least 2 years"], "field": ["administration", "supervisory level", "post-qualification", "relevant experience"]}}, {"job_id": "100003009054683", "location_code": "hk", "company": "The Hong Kong University of Science and Technology", "job_title": "Assistant Manager (MBA Student Affairs) (Job ID: 7070)", "description": "Major Duties\n\nThe appointees will be required to\n\n-\u00a0 \u00a0provide administrative support to sub-degree programmes and functions relating to assessments, examinations and quality assurance;\n\n-\u00a0 \u00a0provide secretariat support to committees and meetings;\n\n-\u00a0 \u00a0support the administration of tuition fees payments;\n\n-\u00a0 \u00a0assist in preparing reports, processing and administering records and data;\n\n-\u00a0 \u00a0assist in the organisation of College events / activities and class scheduling; and\n\n-\u00a0 \u00a0perform other duties as assigned by supervisors.\n\nQualifications Required\n\nCandidates should have (i) a Bachelor\u2019s degree or a sub-degree with at least 2 years of administrative experience, preferably in tertiary education sector; (ii) self-motivated, meticulous, responsible, independent as well as a team player; (iii) good command of spoken and written English and Chinese; (iv) high proficiency in Microsoft Office (advanced knowledge in Excel is an advantage); and (v) good interpersonal, communication and organisation skills.\n\nRemuneration and Conditions of Service\n\nSalary will be commensurate with qualifications and experience. Fringe benefits include contract-end gratuity, medical benefits, and staff development sponsorship. Initial appointment will be on a fixed-term contract for up to two years. Re-engagement thereafter is subject to mutual agreement.\n\n\n\n\nApplication\n\nPlease send your full curriculum vitae (with your current and expected salary) by email or by post to HKU SPACE Po Leung Kuk Stanley Ho Community College, 18/F, 66 Leighton Road, Causeway Bay, Hong Kong. You should indicate the full title and the job reference number of the post you are applying for.\n\nAll applications will be treated in strict confidence. Only those who are shortlisted will be contacted. Applicants not contacted within eight weeks from the closing date may assume that their applications are unsuccessful. The College reserves the right not to fill the post(s) advertised.\n\nClosing date: 24 January 2022", "employment_types": ["Full Time"], "selling_points": ["MBA Student Engagement and Affairs", "Student Enrichment or Short Programs", "Special Programs"], "locations": ["Sai Kung"], "categories": ["Admin & HR", "Administration / Operation Manager", "Education", "Others"], "post_time": "2022-01-17T10:33:08Z", "salary": {"currency": null, "max": null, "min": null, "period": "monthly", "term": null}, "salary_visible": false, "title_keywords": ["assistant manager"], "responsibilities": ["perform other duties", "data", "quality", "communication", "scheduling", "payments", "preparing reports", "provide administrative support", "administration"], "requirements": {"degrees": ["degree", "bachelor"], "majors": [], "languages": ["english", "chinese"], "language_level": ["good command"], "hard_skills": ["excel", "processing", "microsoft office"], "soft_skills": ["meticulous", "self-motivated", "independent", "advanced", "responsible", "communication", "organisation", "team player", "interpersonal"], "languages_combined": [{"language": "english", "language_level": ["good command"]}, {"language": "chinese", "language_level": ["good command"]}]}, "experience_required": {"duration": ["at least 2 years"], "field": ["administrative", "education"]}}, {"job_id": "100003009054181", "location_code": "hk", "company": "Hong Kong Baptist University", "job_title": "Clerk (PR0396/21-22)", "description": "Requirement:\n-\u00a0Higher Diploma graduates or above\n-\u00a0Good command of written and spoken English and Chinese\n-\u00a0Proficient in PC applications on MS Word and Excel\n-\u00a0Good communication and inter-personal skills\n-\u00a0Pleasant disposition with excellent telephone and reception skills and manner\n-\u00a0Work in Causeway Bay\n-\u00a0Shift duty required\n-\u00a0Immediately available preferred\n-\u00a0Fresh graduates are also welcome\n\n\nResponsibility:\n- Provide supports to the Programme Administration\n- Administrative duties such as timetabling, exam invigilation, attendance etc\n- Receive, collate, distribute student coursework and prepare mark sheets\n- Maintain a good filing system and record management\n- Liaise with teachers with respect to curriculum and students progress\n- Handle phone calls including enquiries and requests from students\n- Ad hoc duties assigned by the supervisor", "employment_types": ["Full Time"], "selling_points": ["a higher diploma or an associate degree", "one year of relevant work experience", "proficiency in common computer applications"], "locations": ["Kowloon City"], "categories": ["Admin & HR", "Clerical / Admin Staff", "Others", "Education", "Others"], "post_time": "2022-01-17T08:41:45Z", "salary": {"currency": null, "max": null, "min": null, "period": "monthly", "term": null}, "salary_visible": false, "title_keywords": ["clerk"], "responsibilities": ["ad hoc duties", "attendance", "management", "maintain", "administrative duties", "liaise with", "phone calls", "administration"], "requirements": {"degrees": ["diploma"], "majors": [], "languages": ["english", "chinese"], "language_level": ["good command"], "hard_skills": ["ms word", "excel", "pc applications"], "soft_skills": ["communication", "inter-personal skills", "pleasant"], "languages_combined": [{"language": "english", "language_level": ["good command"]}, {"language": "chinese", "language_level": ["good command"]}]}, "experience_required": {"duration": [], "field": []}}, {"job_id": "100003009054581", "location_code": "hk", "company": "The Hong Kong University of Science and Technology", "job_title": "Assistant Manager (Admissions)(Job ID: 7068)", "description": "SCHOOL OF CHINESE MEDICINE\n\nClinical Division\n\nClerk (PR0396/21-22)\n\nDuties:\nhandle and check the daily income of the clinics;\nprepare invoice for payment;\nhandle petty cash reimbursement;\ncalculate part-time staff salary;\nprovide support to office administration, meetings and events;\nanswer internal and external enquires; and\nperform any other duties as assigned.\nRequirements:\n\na higher diploma or an associate degree;\nat least one year of relevant work experience;\nproficiency in common computer applications including MS Office, Excel and Chinese word processing;\ngood interpersonal skills and a strong sense of responsibility; and\nability to work independently and be self-motivated.\nImmediate availability will be an advantage.\n\nShortlisted candidates will be invited to attend a computer test.\n\nSalary will be commensurate with qualifications and experience.\n\nApplication Procedure:\n\nApplicants are invited to submit their applications at the HKBU e-Recruitment System (jobs.hkbu.edu.hk). Applicants not invited for interview 8 weeks after the closing date may consider their applications unsuccessful. Details of the University\u2019s Personal Information Collection Statement can be found at http://hro.hkbu.edu.hk/pics.\n\nThe University reserves the right not to make an appointment for the post advertised, and the appointment will be made according to the terms and conditions then applicable at the time of offer.\n\nClosing date: 29 January 2022", "employment_types": ["Full Time"], "selling_points": ["Candidates Retention & Expectation Setting", "Admissions Administration", "Project Management"], "locations": ["Sai Kung"], "categories": ["Admin & HR", "Administration / Operation Manager", "Education", "Others"], "post_time": "2022-01-17T10:06:16Z", "salary": {"currency": null, "max": null, "min": null, "period": "monthly", "term": null}, "salary_visible": false, "title_keywords": ["assistant manager"], "responsibilities": ["any other duties", "provide support", "invoice", "office administration", "payment"], "requirements": {"degrees": ["associate degree", "diploma"], "majors": [], "languages": ["chinese"], "language_level": ["proficiency"], "hard_skills": ["excel", "make", "chinese word processing", "ms office"], "soft_skills": ["work independently", "interpersonal skills", "self-motivated", "sense of responsibility"], "languages_combined": [{"language": "chinese", "language_level": ["proficiency"]}]}, "experience_required": {"duration": ["at least one year"], "field": []}}, {"job_id": "100003009054536", "location_code": "hk", "company": "The Hong Kong University of Science and Technology", "job_title": "Executive Assistant to Vice-President for Research and Development (Job ID: 7067)", "description": "The Diocesan Boys\u2019 School Foundation Limited is a registered charity, please visit our website for background details: http://www.dbs.edu.hk/dbsfoundation.\n\nMotivated and committed individuals are invited to apply for the post of Assistant Events Officer.\n\nJob Responsibilities\n\nAssist in handling event-related operation work, including venue reservation, food and beverage, programmes, invitation and registration, on-site hospitality / support and related administrative work;\nWork closely with the Events and Development Sub-Committee to execute a series of foundation and anniversary ceremonial events;\nAssist in processing event sponsorship, foundation souvenir/ publication orders, and issuance of receipt/ acknowledgement;\nHandle email/phone enquiry and provide donor/sponsor service;\nAssist in database management including data entry, regular update and report generation;\nProvide timely update on website / social media contents;\nLiaise and work closely with members of sub-committees, colleagues from other departments and external vendors/ suppliers;\nProvide secretarial support to Sub-Committees and working group meetings; and\nPerform other duties as assigned by the Chief Administrator.\n\n\u00a0Requirements\n\nHolder of Bachelor Degree;\nA minimum of 3 years working experience;\nGood manner, good communication skills, stable and responsible;\nProficient in MS Word, Excel, PowerPoint, Chinese word processing and internet; and\nExperience in managing data in computer system an advantage.\n\nFull personal particulars including educational background, working experience, current and expected salary (quoting reference: Application for the Position of Assistant Events Officer) should reach the Chief Administrator of Foundation Office, Diocesan Boys\u2019 School Foundation Limited, 131 Argyle Street, Kowloon, Hong Kong, or by email on or before 17 February 2022.\n\nAll information provided will be used for recruitment related purposes only.", "employment_types": ["Full Time"], "selling_points": ["planning and coordinating budgets and resources", "servicing committees", "preparing papers and reports"], "locations": ["Sai Kung"], "categories": ["Admin & HR", "Administration / Operation Manager", "Education", "Others"], "post_time": "2022-01-17T09:54:56Z", "salary": {"currency": null, "max": null, "min": null, "period": "monthly", "term": null}, "salary_visible": false, "title_keywords": ["vice president", "executive assistant"], "responsibilities": ["liaise", "social media", "management", "perform other duties", "administrative work", "data entry", "website", "secretarial support", "database", "contents", "publication", "report"], "requirements": {"degrees": ["degree", "bachelor"], "majors": [], "languages": ["chinese"], "language_level": ["proficient"], "hard_skills": ["excel", "chinese word processing", "powerpoint", "ms word"], "soft_skills": ["communication skills", "stable", "responsible"], "languages_combined": [{"language": "chinese", "language_level": ["proficient"]}]}, "experience_required": {"duration": ["minimum of 3 years"], "field": []}}, {"job_id": "100003009051689", "location_code": "hk", "company": "The University of Manchester Worldwide Limited", "job_title": "Operations Administrative Assistant", "description": "Job Title:\u00a0 \u00a0 \u00a0 \u00a0 \u00a0\u00a0Assistant Manager (Admissions)\nDepartment:\u00a0\u00a0\u00a0\u00a0School of Business and Management (MBA Programs)\nJob ID:\u00a0\u00a0\u00a0\u00a0\u00a0\u00a0\u00a0\u00a0\u00a0\u00a0\u00a0\u00a0\u00a07068\n\nJob Posting Details\n\nThe HKUST MBA Program Office is searching for an individual with strong organizational skills to fill the role of Assistant Manager (Admissions) in the Marketing & Admissions Team.\u00a0\n\nReporting to the Manager of Marketing & Admissions Team, the appointee will take part in the end-to-end candidate recruitment, admissions process management and yielding. \u00a0This role requires the exercise of independent judgement, strong administrative and excellent interpersonal skills with a focus in the following key areas:\u00a0\n\nCandidates Retention & Expectation Setting: Act as the dedicated admissions advisor and manage candidates\u2019 expectations during the pre-enrolment stage.\u00a0 Conduct personal consultations to guide the potential candidates during the admission process and achieve the team KPI in converting applicants to enrolled students.\nAdmissions Administration: Execute the University\u2019s guidelines and policies throughout the admission process.\u00a0 Manage the logistics of the entire admission process, including but not limited to handling application enquiries (phone & email); processing qualifications checking for offer issuance; scheduling interviews with potential candidates and internal interviewers; and providing regular reports on application and admission data.\nProject Management:\u00a0Conduct projects that cover different aspects of the admissions process as assigned to enhance operation efficiency and maintain partnership relations, such as system integration, AI Chabot and promotion scheme.\u00a0 \u00a0\n\nApplicants should have a bachelor\u2019s degree with at least 3 years of work experience.\u00a0 The ideal candidate should be a team player with excellent interpersonal & organizational skills.\u00a0 He/She should be proactive in problem-solving and have the capability to work under pressure and independently.\u00a0 Experience in managing CRM and admissions role is a plus.\u00a0 Prior background in global higher education is preferred but not compulsory. \u00a0Excellent communication skills and command of verbal and written English and Chinese (including Mandarin) are required.\u00a0 Occasional travel and working outside office hours including occasional weekends will be expected. (Duration: 2 years, renewable)\n\nStarting salary will be commensurate with qualifications and experience.\u00a0 Fringe benefits including annual leave, medical and dental benefits will be provided.\u00a0 A gratuity will be payable upon successful completion of contract.\n\nApplication Procedure\nIn support of a green work environment, we accept applications submitted online only.\u00a0 To apply, please complete an online application form through the HKUST Careers website (https://hkustcareers.ust.hk) and return it online to the Human Resources Office on or before Sunday, 6 February 2022.\u00a0 Applicants will receive an acknowledgement by email upon successful submission.\u00a0 We thank applicants for their interest, but advise that only shortlisted candidates will be notified of the result of the application.\n\n(Information provided by applicants will be used for recruitment and other employment-related purposes only.)\n\nHKUST is an equal opportunities employer and is committed to our core values of\ninclusiveness, diversity, and respect.", "employment_types": ["Full Time", "Contract"], "selling_points": ["H Dip or above, 3-5 yrs wk exp, Gd Eng, IT skills", "Mature, can-do, multi-task, creative, outgoing", "Int'l exposure, training, immediate, salary expect"], "locations": ["Causeway Bay"], "categories": ["Admin & HR", "Clerical / Admin Staff", "Education", "Others", "Marketing / Public Relations", "Public Relations - Event Management"], "post_time": "2022-01-16T21:50:48Z", "salary": {"currency": null, "max": null, "min": null, "period": "monthly", "term": null}, "salary_visible": false, "title_keywords": ["administrative assistant", "operations"], "responsibilities": ["reporting", "management", "data", "guidelines", "policies", "work under pressure", "checking", "communication", "scheduling", "project management", "maintain", "recruitment", "logistics", "reports", "administration"], "requirements": {"degrees": ["degree", "bachelor"], "majors": [], "languages": ["english", "chinese", "mandarin"], "language_level": ["excellent"], "hard_skills": ["plus", "ai", "id", "problem-solving", "scheme", "project management", "integration", "focus", "processing"], "soft_skills": ["organizational skills", "communication skills", "independently", "independent", "work under pressure", "problem-solving", "project management", "team player", "interpersonal skills", "focus", "proactive", "interpersonal", "ideal"], "languages_combined": [{"language": "english", "language_level": ["excellent"]}, {"language": "chinese", "language_level": ["excellent"]}, {"language": "mandarin", "language_level": ["excellent"]}]}, "experience_required": {"duration": ["at least 3 years"], "field": []}}, {"job_id": "100003009048140", "location_code": "hk", "company": "Monkey Tree English Learning Center", "job_title": "Center Manager (Education Center /W9Z/Ref No.J22001)", "description": "Job Title:\u00a0\u00a0\u00a0\u00a0\u00a0\u00a0\u00a0\u00a0\u00a0Executive Assistant to Vice-President for Research and Development\nDepartment:\u00a0 \u00a0 Office of the Vice-President for Research and Development\nJob ID:\u00a0\u00a0\u00a0\u00a0\u00a0\u00a0\u00a0\u00a0\u00a0\u00a0\u00a0\u00a0\u00a07067\n\nJob Posting Details\n\nThe appointee will assist the Vice-President for Research and Development (VPRD) in all aspects of administration related to the VPRD Office, including strategic planning; managing and overseeing the VPRDO; planning and coordinating budgets and resources; servicing committees; preparing papers and reports; reviewing and administering research-related policies, services and activities; managing special projects; and offering advice and acting on various duties under the auspices of VPRD. The appointee will also serve as a liaison person between VPRD and members of the University to ensure effective flow of communication and smooth implementation of policy and schemes.\n\nApplicants should have a bachelor\u2019s degree with at least 10 years of relevant work experience in the higher education sector. The ideal candidate should have a strong sense of responsibility and commitment, and be highly initiative, detail-oriented and multi-task oriented.\u00a0 He/She should possess excellent and demonstrable leadership; organizational, planning and interpersonal communication; and analytical and problem-solving skills.\u00a0 Excellent command of written and spoken English and Chinese (both Cantonese and Putonghua) is required. (Duration: 2 years, renewable)\n\nStarting salary will be commensurate with qualifications and experience. \u00a0Fringe benefits including annual leave, medical and dental benefits will be provided. \u00a0A gratuity will be payable upon successful completion of contract.\n\nApplication Procedure\nIn support of a green work environment, we accept applications submitted online only. \u00a0To apply, please complete an online application form through the HKUST Careers website (https://hkustcareers.ust.hk) and return it online to the Human Resources Office on or before\u00a0Monday, 31 January 2022.\u00a0 Applicants will receive an acknowledgement by email upon successful submission.\u00a0 We thank applicants for their interest, but advise that only shortlisted candidates will be notified of the result of the application.\n\n(Information provided by applicants will be used for recruitment and other employment-related purposes only.)\n\nHKUST is an equal opportunities employer and is committed to our core values of\ninclusiveness, diversity, and respect.", "employment_types": ["Full Time"], "selling_points": ["Fluent English and Mandarin Speaker", "Excellent promotional growth opportunities", "Attractive remuneration package"], "locations": ["Yau Tsim Mong Area"], "categories": ["Admin & HR", "Others", "Sales, CS & Business Devpt", "Customer Service - Manager", "Education", "Others"], "post_time": "2022-01-17T16:20:55Z", "salary": {"currency": null, "max": null, "min": null, "period": "monthly", "term": null}, "salary_visible": false, "title_keywords": ["manager"], "responsibilities": ["administration", "budgets", "strategic planning", "policies", "implementation", "communication", "reports", "planning"], "requirements": {"degrees": ["degree", "bachelor"], "majors": [], "languages": ["cantonese", "putonghua", "english", "chinese"], "language_level": ["excellent"], "hard_skills": ["id", "problem-solving skills"], "soft_skills": ["multi-task oriented", "sense of responsibility", "organizational", "detail-oriented", "communication", "smooth", "problem-solving skills", "interpersonal", "leadership", "initiative", "ideal"], "languages_combined": [{"language": "cantonese", "language_level": ["excellent"]}, {"language": "putonghua", "language_level": ["excellent"]}, {"language": "english", "language_level": ["excellent"]}, {"language": "chinese", "language_level": ["excellent"]}]}, "experience_required": {"duration": ["at least 10 years"], "field": ["education"]}}, {"job_id": "100003009054502", "location_code": "hk", "company": "The Hong Kong University of Science and Technology", "job_title": "Manager (Job ID: 7066)", "description": "Job Responsibility:\n\nHandle administrative tasks including record maintenance and follow-up & etc.\nEnsure administrative tasks delivered are in compliance with any regulatory requirements\nData Entry, Filing, Searching information\nOther office administration support\n\nRequirements:\n\nF.6 (HKDSE with 5 Subject Level 2 include Eng / Chinese / Maths)\n1 - 2 years clerical / administration / data entry working experiences.\nWith government (HKSAR) working experiences is an advantage\nEnglish Typing 30 WPM and Chinese Typing 25 WPM or above\nGood communications skills including MS Word, MS Excel and PowerPoint\nAble to work under pressure with careful mindset.\nGood communication skill in both written and spoken English and Cantonese\nImmediately available is highly preferred\n\nSalary Range from HK$11,000 to $12,900", "employment_types": ["Full Time"], "selling_points": ["providing administrative support", "preparing documents for meetings", "liaising with internal and external stakeholders"], "locations": ["Sai Kung"], "categories": ["Admin & HR", "Administration / Operation Manager", "Education", "Others"], "post_time": "2022-01-17T09:48:51Z", "salary": {"currency": null, "max": null, "min": null, "period": "monthly", "term": null}, "salary_visible": false, "title_keywords": ["manager"], "responsibilities": ["office administration support", "maintenance", "data entry", "regulatory requirements", "compliance", "administrative tasks"], "requirements": {"degrees": ["hkdse"], "majors": [], "languages": ["cantonese", "english", "chinese"], "language_level": ["good"], "hard_skills": ["ms excel", "typing", "powerpoint", "ms word"], "soft_skills": ["communication skill", "careful", "work under pressure"], "languages_combined": [{"language": "cantonese", "language_level": ["good"]}, {"language": "english", "language_level": ["good"]}, {"language": "chinese", "language_level": []}]}, "experience_required": {"duration": ["1 - 2 years"], "field": ["clerical", "administration"]}}, {"job_id": "100003009039163", "location_code": "hk", "company": "City University of Hong Kong", "job_title": "Executive Officer in the Student Development Services [Ref. B/506/03]", "description": "The appointee will be assigned to the Learning Centre Administration Section of the School to provide administrative and clerical support in the day-to-day operation. Duties include but not limited to: a) assisting in daily class operation and teaching equipment / centre facilities preparation; b) maintaining records, preparing reports, and performing administrative duties such as filing and photocopying; c) data inputting and compiling; d) providing frontline support for classes and counter services including enquiry handling; and e) coordinating and liaising with internal and external parties such as instructors, students and contractors. The appointee is also required to perform shift duty on weekday evenings.\nMinimum Requirements:\nHKCEE 5 passes including English Language (at least grade C if Syllabus A / Level 2 from 2007), or at least 5 subjects attaining Level 2 in HKDSE including English Language and Chinese Language, or Yi Jin graduates;\nAt least 2 years of relevant experience;\nGood communication and customer services skills;\nCompetency in computer software applications;\nKnowledge in basic operation and setup of audio-visual equipment is an advantage; and\nHolders of Associate Degree / Higher Diploma with less experience may also be considered.\nSalary will be commensurate with qualifications and experience.\nApplication Procedure:\nApplicants are invited to submit their applications at the HKBU e-Recruitment System (jobs.hkbu.edu.hk). Applicants not invited for interview 8 weeks after the closing date may consider their applications unsuccessful. Details of the University's Personal Information Collection Statement can be found at http://hro.hkbu.edu.hk/pics.\nThe School reserves the right not to make an appointment for the post advertised, and the appointment will be made according to the terms and conditions then applicable at the time of offer.\nClosing date: 24 January 2022", "employment_types": ["Full Time", "Contract"], "selling_points": ["A Bachelor\u2019s degree", "Relevant working experience", "Gratuity, leave, medical and dental schemes."], "locations": ["Wong Tai Sin Area"], "categories": ["Admin & HR", "Clerical / Admin Staff", "Personal / Executive Assistant", "Education", "Others"], "post_time": "2022-01-13T18:54:36Z", "salary": {"currency": null, "max": null, "min": null, "period": "monthly", "term": null}, "salary_visible": false, "title_keywords": ["executive officer"], "responsibilities": ["software", "maintaining", "data", "internal and external parties", "liaising with", "customer services", "communication", "administrative duties", "visual", "preparing reports", "administrative and clerical support", "recruitment", "audio", "setup", "day-to-day operation", "administration"], "requirements": {"degrees": ["associate degree", "diploma", "hkdse"], "majors": [], "languages": ["english", "chinese"], "language_level": [], "hard_skills": ["make", "c", "basic"], "soft_skills": ["communication", "learning", "customer services skills"], "languages_combined": [{"language": "english", "language_level": []}, {"language": "chinese", "language_level": []}]}, "experience_required": {"duration": ["at least 2 years"], "field": ["relevant experience"]}}, {"job_id": "100003009053187", "location_code": "hk", "company": "Diocesan Boys' School Foundation Limited", "job_title": "Administrative Assistant", "description": "This is a dynamic and demanding role and will involve considerable flexibility and the ability to prioritise tasks in order to deliver administrative support for the academic community within the Centre and wider community.\u00a0 The post holder\u2019s role will be to ensure effective and professional liaison and communication with academic, administrative and external customers at all levels, to facilitate the smooth running of day-to-day activities.\n\n\nKey Responsibilities\n\n\nTo provide efficient and professional services to stakeholders\nTo provide effective support in programme, event and office administration\nTo implement the admission and registration process\nTo support teaching and learning services\nTo maintain student records and its systems\nTo support and implement event plans and concepts\n20 days annual leave, 5 days work, fringe benefits and working with global teams.", "employment_types": ["Full Time"], "selling_points": ["Higher Diploma or Associate Degree or above", "Minimum 2 year working experience", "Business, accounting, computing studies discipline"], "locations": ["Mong Kok"], "categories": ["Education", "Others"], "post_time": "2022-01-17T16:20:59Z", "salary": {"currency": null, "max": null, "min": null, "period": "monthly", "term": null}, "salary_visible": false, "title_keywords": ["administrative assistant"], "responsibilities": ["administrative support", "office administration", "systems", "communication", "maintain student records", "plans"], "requirements": {"degrees": [], "majors": [], "languages": [], "language_level": [], "hard_skills": ["dynamic"], "soft_skills": ["efficient", "prioritise", "communication", "dynamic", "learning", "smooth"], "languages_combined": []}, "experience_required": {"duration": [], "field": []}}, {"job_id": "100003009052434", "location_code": "hk", "company": "Advance Resources Personnel Consultants Limited", "job_title": "Clerical Assistant (5 days, HKSAR Contract, $11-$13K)", "description": "\u00a0Responsibilities\n\nProvide professional consultation, such as introducing course details and proposing suitable course packages, to prospective customers\nMonitor students\u2019 progress, & communicate with customers to retain a clear understanding of their needs, as well as to maintain good customer relationship\nManage the center\u2019s class schedule to best satisfy students and teachers\nHandling walk-in inquiries, calls, and customer follow-ups\nMaintain the center\u2019s and classrooms\u2019 appearance as well as completeness to ensure a smooth working and teaching environment\nProvide assistance to teachers when needed\nSupervise and train fresh staff on course details, administrative procedures, etc.\n\nRequirements\n\nForm 7 graduate or above\nWell-mannered, and possess effective communication and interpersonal skills\nConfident, cheerful and proactive with a positive attitude\nAble to multi-task & work under pressure\nPossess a detail-oriented mind with excellent problem-solving skills\nComputer literate, especially in Microsoft Office (Word & Excel)\nFluent in Cantonese and English, Mandarin is an advantage\nWilling to work on Saturdays\nLove kids\nBenefits\noff on all Public Holidays\nCourse benefits for candidates with children\nComprehensive medical scheme\n5 days work week\n\nWorking Location: West 9 Zone\n\nInterested parties please email us your resume with expected salary.", "employment_types": ["Full Time", "Contract"], "selling_points": ["Clerical duty, data entry, filing, scanning", "office administration support, ad hoc support", "Contract position, 5 days work, public holiday"], "locations": ["Wan Chai Area"], "categories": ["Admin & HR", "Clerical / Admin Staff", "Others", "Education", "Others"], "post_time": "2022-01-17T03:09:51Z", "salary": {"currency": null, "max": null, "min": null, "period": "monthly", "term": null}, "salary_visible": false, "title_keywords": ["clerical assistant"], "responsibilities": ["communicate with", "monitor", "procedures", "maintain", "schedule", "provide assistance"], "requirements": {"degrees": [], "majors": [], "languages": ["cantonese", "english", "mandarin"], "language_level": ["advantage", "fluent"], "hard_skills": ["problem-solving skills", "word", "excel", "microsoft office"], "soft_skills": ["confident", "cheerful", "multi-task", "detail-oriented", "positive attitude", "communication and interpersonal skills", "problem-solving skills", "proactive", "work under pressure"], "languages_combined": [{"language": "cantonese", "language_level": ["fluent"]}, {"language": "english", "language_level": ["fluent"]}, {"language": "mandarin", "language_level": ["advantage"]}]}, "experience_required": {"duration": [], "field": []}}, {"job_id": "100003009033125", "location_code": "hk", "company": "\u5b78\u65af\u6559\u80b2", "job_title": "\u5168\u8077\u63a5\u5f85\u54e1 / Receptionist / \u5ba2\u6236\u52a9\u7406 / Customer Service Assistant *Recent Graduate will be considered*", "description": "(Ref. No.: S_AD_93_JB)\n\n\n\nJob duties:\n\nDevelop, manage and supervise the P-12 athletic sports program in line with the school\u2019s overall mission statement.\nEnsure continuity and progression in sporting opportunities across P - 12.\nManage sporting calendar\nSchedule practices, games, tournaments for all teams\nDistribute weekly facility schedule\nSelect coaching staff, along with supervision, development and communication with coaches.\nOrganize coaches\u2019 meetings at the beginning of each season to review expectations, guidelines, and rules of play.\nRepresent CAIS in all league and athletic associations including ISSFHK, HKSSF and PASS and attend all meetings. Lead the organisation of CAIS\u2019 participation in associated leagues.\nArrange officials, scorekeepers, timers for all home and away games\u00a0\nArrange transportation for all away competitions\nAssign staff cover for PE/Sports\nPrepare and verify athletic eligibility lists\nEnsure that student-athletes have turned in required forms/paperwork/fees\nOversee the distribution, collection, storage upkeep and replacement of school athletic uniforms\nOrder and distribute athletic apparel for coaches\nConvene at least 1 sport for all ISSFHK\u2019s 37 interscholastic teams\nUpdate school platforms with schedules and locations of all practices and competitions\nMaintain accurate records of team and school accomplishments\nSupervise all home competitions and act as the host to officials, volunteers, parents and visiting schools. Responsible for the preparation for home competitions.\nApplication of external facilities and fields with appropriate communication between vendors.\nPrepare and monitor athletic budget, completing administrative paperwork for operational spending of budget.\nOrder equipment and maintain a current inventory of all athletic equipment.\nDevelop student leaders through Lions Committee.\nPlan year-end athletic banquet with presentation of athletic awards.\nLiaise with staff, parents & advancement team to promote sport throughout the school community.\nPromote sporting vision & values to school community.\nMaintain a clear strategic plan for the athletic program in sport.\nLong term planning in terms of sports facilities and participation in international competitions.\n\nRequirements:\n\nBachelor\u2019s degree or higher, preferably relevant to Physical Education, Sport Administration or Kinesiology\nMinimum of two years of experience in sport administration\nNative proficiency in spoken and written English required\nPreferably holds a teaching certificate\n\nEffective Date of Employment\n\nThe starting date for this appointment is mid-August 2022. Initial contracts are normally 2 years in duration.\n\nApplication Details\n\nInterested parties please apply with full resume stating current and expected salary by clicking \u201cApply Now\u201d or by email to the Human Resources Department via our employment webpage at\u00a0www.caisbv.edu.hk.\n\nPlease quote the reference number of the post in your application.\n\nAll personal data submitted will be used for recruitment purposes only and all related information will be kept for up to 24 months.", "employment_types": ["Full Time"], "selling_points": ["\u61c9\u7b54\u5b78\u751f\u53ca\u5bb6\u9577\u67e5\u8a62", "\u8655\u7406\u88dc\u7fd2\u4e2d\u5fc3\u65e5\u5e38\u5927\u5c0f\u4e8b\u52d9", "\u4e94\u5929\u5de5\u4f5c\u65e5\u516c\u773e\u5047\u671f\u4f11\u606f"], "locations": ["Not Specified"], "categories": ["Admin & HR", "Clerical / Admin Staff", "Receptionist", "Education", "Others"], "post_time": "2022-01-16T21:50:09Z", "salary": {"currency": null, "max": null, "min": null, "period": "monthly", "term": null}, "salary_visible": false, "title_keywords": ["receptionist", "\u5ba2\u6236\u52a9\u7406", "customer service assistant"], "responsibilities": ["year-end", "guidelines", "schedules", "inventory", "review", "teams", "monitor", "budget", "develop", "communication", "maintain", "schedule", "plan", "liaise with", "planning"], "requirements": {"degrees": ["certificate", "degree", "bachelor"], "majors": [], "languages": ["english"], "language_level": ["native", "proficiency"], "hard_skills": [], "soft_skills": [], "languages_combined": [{"language": "english", "language_level": ["native", "proficiency"]}]}, "experience_required": {"duration": ["minimum of two years"], "field": ["administration"]}}, {"job_id": "100003009051733", "location_code": "hk", "company": "HKU SPACE Po Leung Kuk Stanley Ho Community College", "job_title": "Executive Assistants  (Ref: AP/ft/22-01)", "description": "Role and Responsibilities\n\nThe job scope of the lab technician involves assisting HOD/Science, supporting the Science department and the school in the following areas:\n\nManagement of science laboratories\nPack and organise the resources in the Science laboratories\nLabel and keep records of all existing and new Science resources and maintain loan records of these resources. Inform HOD if any resource needs to be replenished\nKeep records of consumables (to replenish when quantity is low).\u00a0 Monitor and maintain records of substances listed under Schedule 1 or Schedule 2 of the Control of Chemicals Ordinance (if applicable)\nLiaise with vendors and request for quotations for Science resources\nSource and make purchases for lab supplies and keep records of the expenditure\n\u00a0Monitor and maintain licences, warranties and maintenance contracts as necessary\n\u00a0Service and maintain equipment in good condition. Ensure that equipment like Microscopes are serviced once a year and are kept in a ready-to-use condition\n\u00a0Conduct audit of the inventory list as required by the Finance Department, at the end of every semester\n\u00a0\u00a0Ensure proper disposal of waste materials such as sharp waste objects and chemicals\n\u00a0Prepare and set up lab resources for teachers\u2019 demonstrations and students\u2019 use during science practical lessons\n\u00a0Prepare and set up the materials for Science Practical Assessments and Project Works\n\u00a0Set up lab resources for science enrichment activities, e.g. post-exam activities and during the Summer Programme\n\u00a0Ensure adherence to safe laboratory practices by staff and students. Report any incident to the Science HOD immediately\n\u00a0Maintain tidiness and cleanliness of laboratories\n\u00a0Take care of the plants and animals in the laboratories. Feed and maintain the habitats of the animals in the Science laboratories\n\u00a0Conduct technical training for staff as required\n\u00a0Liaise with Campus Management team to ensure that the Science laboratories are well-maintained\n\u00a0Liaise with Nurse on the validity of items in the first aid kit in the Science laboratories\nAdministrative support for science teachers\nAssist teachers in preparing materials and laboratory protocols for science programmes and students\u2019 projects\nAssist teachers in conducting demonstrations and hands-on activities/experiments\nCreate videos of Science activities/experiments\nSearch for and recommend web-based resources for teaching and learning purposes\nCollate feedback data from surveys on science activities and School Excellence Model-related surveys for review purposes\nAccompany students on learning journeys and field trips (when necessary)\nUpdate information and displays on the science notice board (when necessary)\nPrepare the schedule for the Science Practical Assessments and assist teachers in\u00a0\u00a0 invigilation\nAssist teachers in conducting make-up for students who miss the Science Practical Assessments\u00a0\nLogistical and administrative support for school and departmental events/programmes\nAssist the Science department in the implementation of programmes, e.g. hydroponics programme and student volunteer programme\nMaintain the hydroponic facilities and take care of the vegetables\nMaintain the Science planters and take care of the plants\nAssist in running school events such as Green Day, Family Fest, Summer Programme etc.\nAssist the Exam Committee in invigilation of students with special considerations\nAssist in Science examination paper marking sessions\nProvide logistical support to school and departments as necessary\u00a0\n\nRequirements\n\nDiploma / Degree holder in the study of Physics, Biology, Chemistry or Science subjects\nHave work experience in a school environment or laboratory is preferable\nFresh graduates will also be considered\nBe an effective communicator in oral and written English\nBe a good team player\n\nCompetitive remuneration and benefits will be offered to the suitable candidate.\nInterested parties, please send a cover letter, detailed resume including\u00a0availability, present and expected salary\u00a0either\u00a0by online application\u00a0or by post to the Human Resources Department at 23 Nam Long Shan Road, Aberdeen, Hong Kong.\u00a0 Only shortlisted candidates will be notified.\n\nAll personal data collected will be used for recruitment purposes only.", "employment_types": ["Full Time", "Contract"], "selling_points": ["programme promotion and liaison with schools", "student admission and office administration", "social media management and material publication"], "locations": ["Causeway Bay"], "categories": ["Education", "Others"], "post_time": "2022-01-16T21:51:16Z", "salary": {"currency": null, "max": null, "min": null, "period": "monthly", "term": null}, "salary_visible": false, "title_keywords": ["executive"], "responsibilities": ["management team", "management", "control", "maintenance", "administrative support", "data", "contracts", "inventory", "ensure adherence", "monitor", "audit", "review", "implementation", "school events", "maintain", "schedule", "liaise with", "report"], "requirements": {"degrees": ["diploma", "degree holder"], "majors": ["science", "biology", "chemistry", "physics"], "languages": ["english"], "language_level": [], "hard_skills": [], "soft_skills": ["good team player", "communicator", "oral"], "languages_combined": [{"language": "english", "language_level": []}]}, "experience_required": {"duration": [], "field": ["laboratory"]}}, {"job_id": "100003009053036", "location_code": "hk", "company": "Christian Alliance International School", "job_title": "Athletics Director (Non-Teaching Role)", "description": "Job Title:\u00a0\u00a0\u00a0\u00a0\u00a0\u00a0\u00a0\u00a0\u00a0\u00a0\u00a0\u00a0Manager\nDepartment:\u00a0\u00a0\u00a0\u00a0\u00a0\u00a0Office of the Vice-President for Research and Development\nJob ID:\u00a0\u00a0\u00a0\u00a0\u00a0\u00a0\u00a0\u00a0\u00a0\u00a0\u00a0\u00a0\u00a0\u00a0\u00a07066\n\nJob Posting Details\n\nThe appointee will provide support in all aspects of administration relating to research and development.\u00a0 Duties include but not limited to providing administrative support to functions under VPRDO, preparing documents for meetings and taking necessary follow-up actions, budgeting and accounting, liaising with internal and external stakeholders on research-related matters, managing and coordinating University-wide events and activities, supporting research committees/working groups, coordinating the nominations/applications for awards and honors, supporting investigation of suspected misconduct cases, and performing any other ad-hoc duties as assigned.\n\nApplicants should have a bachelor's degree with at least 7 years of work experience in the higher education sector.\u00a0 The ideal candidate should be a good team player with good organizational and communication skills, and be effective in multi-tasking work culture. Excellent command of written and spoken English and Chinese (both Cantonese and Putonghua) is required.\u00a0 Candidates with good understanding of research facilities management, grant administration and management, and proper committee secretarial servicing training is preferred. (Duration: 2 years, renewable)\n\nStarting salary will be commensurate with qualifications and experience. \u00a0Fringe benefits including annual leave, medical and dental benefits will be provided. \u00a0A gratuity will be payable upon successful completion of contract.\n\nApplication Procedure\nIn support of a green work environment, we accept applications submitted online only. \u00a0To apply, please complete an online application form through the HKUST Careers website (https://hkustcareers.ust.hk) and return it online to the Human Resources Office on or before\u00a0Monday, 31 January 2022.\u00a0 Applicants will receive an acknowledgement by email upon successful submission.\u00a0 We thank applicants for their interest, but advise that only shortlisted candidates will be notified of the result of the application.\n\n(Information provided by applicants will be used for recruitment and other employment-related purposes only.)\n\nHKUST is an equal opportunities employer and is committed to our core values of\ninclusiveness, diversity, and respect.", "employment_types": ["Full Time", "Contract"], "selling_points": ["Bachelor\u2019s degree or higher", "Minimum of two years of experience in sport admin", "Native proficiency in spoken and written English"], "locations": ["Lai Chi Kok"], "categories": ["Education", "Others"], "post_time": "2022-01-17T05:18:20Z", "salary": {"currency": null, "max": null, "min": null, "period": "monthly", "term": null}, "salary_visible": false, "title_keywords": ["director"], "responsibilities": ["provide support", "management", "administrative support", "budgeting", "liaising with", "investigation", "communication", "ad-hoc duties", "administration"], "requirements": {"degrees": ["degree", "bachelor"], "majors": [], "languages": ["cantonese", "putonghua", "english", "chinese"], "language_level": ["excellent"], "hard_skills": ["id", "facilities management"], "soft_skills": ["communication skills", "good team player", "organizational", "multi-tasking", "ad-hoc duties", "ideal"], "languages_combined": [{"language": "cantonese", "language_level": ["excellent"]}, {"language": "putonghua", "language_level": ["excellent"]}, {"language": "english", "language_level": ["excellent"]}, {"language": "chinese", "language_level": ["excellent"]}]}, "experience_required": {"duration": ["at least 7 years"], "field": ["education"]}}, {"job_id": "100003009046370", "location_code": "hk", "company": "Hong Kong Institute of Construction", "job_title": "Officer - Campus Administration, HKIC", "description": "Duties\nReporting to the Associate Director (Student Life and Resources), the appointee will be responsible for:\n\n\nPlanning and organizing student development programmes, activities and special projects to support and enhance student learning;\nProviding advice, support and training to Students\u2019 Union, student societies and student groups;\nServing as the Secretary for Student Orientation Working Group, coordinating the welcoming ceremony, orientation activities for new students, and the Student Orientation website;\nCoordinating the IT projects and providing support for SLR websites and social media;\nLiaising with different stakeholders for student development activities/programmes; and\nPerforming any other duties as assigned.\nThe appointee will be also required to work flexible hours on a need basis.\nRequirements\nA Bachelor\u2019s degree or an equivalent qualification, preferably with a postgraduate qualification;\nRelevant working experience in related fields, preferably in higher education or youth work;\nWorking knowledge of computer applications;\nOutgoing personality and ability to communicate with young people;\nGood problem solving skills, being resourceful and self-motivated; and\nGood command of written and spoken English and Chinese (including Putonghua).\n\nShortlisted candidates will be invited for a written test.\n\n(Those who have responded to the previous advertisement need not re-apply.)\n\n\nSalary and Conditions of Service\n\nRemuneration package will be highly competitive, commensurate with qualifications and experience.\u00a0 Appointment will be made on a fixed-term contract; fringe benefits include gratuity, leave, medical and dental schemes.\nInformation and Application\nFurther information on the post and the University is available at\u00a0http://www.cityu.edu.hk, or from the Human Resources Office, City University of Hong Kong, Tat Chee Avenue, Kowloon Tong, Hong Kong [Fax : 2788 1154 or 3442 0311].\u00a0\n\nTo apply, please submit an online application at\u00a0http://jobs.cityu.edu.hk. The closing date is\u00a028 January 2022.\u00a0 Applications will receive full consideration and only shortlisted applicants will be contacted.\u00a0 The University\u2019s privacy policy is available on the homepage.\n\nCity University of Hong Kong is an equal opportunity employer. We are committed to the principle of diversity. Personal data provided by applicants will be used for recruitment and other employment-related purposes.\n\nWorldwide recognition ranking #53 (QS survey 2022), and #4 among top 50 universities under age 50 (QS survey 2021); #1 in the World\u2019s Most International Universities (THE survey 2020); #1 in Engineering/Technology/Computer Sciences in Hong Kong (ARWU survey 2016); and #1 Business School in Asia-Pacific region (UT Dallas survey 2019).", "employment_types": ["Full Time", "Contract"], "selling_points": ["a recognised degree", "min. 3 years\u2019 post-qualification work experience", "oversee the daily operation of the Campus"], "locations": ["Not Specified"], "categories": ["Admin & HR", "Administration / Operation Manager", "Clerical / Admin Staff", "Education", "Others"], "post_time": "2022-01-13T10:46:17Z", "salary": {"currency": null, "max": null, "min": null, "period": null, "term": null}, "salary_visible": false, "title_keywords": ["officer"], "responsibilities": ["reporting", "social media", "any other duties", "website", "liaising with", "providing support", "planning"], "requirements": {"degrees": ["degree", "bachelor"], "majors": [], "languages": ["putonghua", "english", "chinese"], "language_level": ["good command"], "hard_skills": ["problem solving skills"], "soft_skills": ["outgoing personality", "problem solving skills", "self-motivated", "resourceful"], "languages_combined": [{"language": "putonghua", "language_level": ["good command"]}, {"language": "english", "language_level": ["good command"]}, {"language": "chinese", "language_level": ["good command"]}]}, "experience_required": {"duration": [], "field": ["related", "relevant working experience", "education"]}}, {"job_id": "100003009053227", "location_code": "hk", "company": "Singapore International School (Hong Kong)", "job_title": "Science Lab Assistant / Technician", "description": "(Ref: AO/EA (SCOM) 2022-01-14)\n\nResponsibilities:\n\nprovide administrative support to the School of Communication, including programme administration, functions and events, and new programme development;\ncreate and maintain contents on social media platforms;\nserve as secretary to committees and working groups; and\nassist in a wide spectrum of other school duties.\n\n\n\nApplicants should:\n\npossess a recognised degree, preferably in Journalism and Communication or related disciplines with 2 years of relevant work experience;\nhave a good command of written and spoken English and Chinese (including Putonghua);\nbe proficient in computer skills;\nbe a fast learner, meticulous, self-motivated, a good team player and be able to work independently with a strong sense of responsibility; and\npossess good interpersonal and communication skills.\n\nThe appointee may be required to work outside normal office hours.\u00a0 Applicants with work experience in the tertiary education sector and knowledge of social media platforms will be an advantage.\u00a0 Applicants with less experience will be considered for the post of Executive Assistant.\n\n\n\nSalary will\u00a0be commensurate with qualifications and experience.\u00a0 Applicants should send a full resume with expected salary by email via \"Apply Now\"\u00a0or by post to Human Resources Office, The Hang Seng University of Hong Kong, Hang Shin Link, Siu Lek Yuen, Shatin, N.T., Hong Kong on or before 30 January 2022.\u00a0 Please indicate the post applied for and mark 'Application - Confidential' and the reference number on the cover.\u00a0 The University reserves the right not to fill the position in this exercise.\n\nApplicants who are not invited to an interview within three months may consider their applications unsuccessful.\u00a0 All information received will be treated in strict confidence, and the data collected will be used for recruitment purposes only.\u00a0 The Personal Information Collection Statement will be provided upon request.\n\nThe Hang Seng University of Hong Kong, incorporated in Hong Kong with limited liability by guarantee, is an equal opportunity employer.", "employment_types": ["Full Time", "Permanent"], "selling_points": [], "locations": ["Aberdeen"], "categories": ["Education", "Others", "Sciences, Lab, R&D", "Laboratory"], "post_time": "2022-01-17T06:29:29Z", "salary": {"currency": null, "max": null, "min": null, "period": "monthly", "term": null}, "salary_visible": false, "title_keywords": ["technician", "assistant"], "responsibilities": ["data", "social media platforms", "communication", "maintain", "recruitment", "contents", "provide administrative support", "administration"], "requirements": {"degrees": ["degree"], "majors": ["journalism", "related disciplines"], "languages": ["putonghua", "english", "chinese"], "language_level": ["good command"], "hard_skills": ["computer skills"], "soft_skills": ["meticulous", "self-motivated", "good team player", "work independently", "communication skills", "confidence", "sense of responsibility", "communication", "fast learner", "interpersonal"], "languages_combined": [{"language": "putonghua", "language_level": ["good command"]}, {"language": "english", "language_level": ["good command"]}, {"language": "chinese", "language_level": ["good command"]}]}, "experience_required": {"duration": ["2 years"], "field": ["related", "social media", "education"]}}, {"job_id": "100003009053675", "location_code": "hk", "company": "Hong Kong Metropolitan University", "job_title": "Temporary/Part-time Clerk (Ref: 220004L)", "description": "The Diocesan Boys\u2019 School Foundation Limited is a registered charity, please visit our website for background details: http://www.dbs.edu.hk/dbsfoundation.\n\nMotivated and committed individuals are invited to apply for the post of Administrative Assistant.\n\nJob Responsibilities:\n\nTo attend to the day-to-day general administration including processing of daily incoming and outgoing documents and filing, handling souvenir orders and delivery\nAssist in processing payment and sponsorship, and issuance of receipt and acknowledgement\nTo assist in database management including data entry, regular update and report generation; and updating inventory record\nTo provide administrative support e.g. scheduling of meetings and on-site hospitality to Board, Committees and working group meetings\nTo assist and provide logistic and on-site support to internal and external fund raising events\nOther duties as assigned by the Chief Administrator of Foundation Office\nReport to Chief Administrator of Foundation Office\n\nRequirements:\n\nHolder of Higher Diploma or Associate Degree or above in business, accounting, computing studies or related discipline\nMinimum 2 year working experience\nGood manner, good communication skills, stable and responsible\nProficient in MS Word, Excel, PowerPoint and Chinese word processing, internet\n\nFull personal particulars including educational background, working experience, current and expected salary should reach the Chief Administrator of Foundation Office, Diocesan Boys\u2019 School Foundation Limited, 131 Argyle Street, Kowloon, Hong Kong, or by email on or before 17 February 2022.\n\nAll information provided will be used for recruitment related purposes only.", "employment_types": ["Part Time", "Temporary"], "selling_points": ["handling day-to-day operations of the School", "at least 5 subjects with Level 2 in HKDSE", "good computer skills"], "locations": ["Kowloon City"], "categories": ["Education", "Others"], "post_time": "2022-01-17T07:19:49Z", "salary": {"currency": null, "max": null, "min": null, "period": "monthly", "term": null}, "salary_visible": false, "title_keywords": ["part time clerk"], "responsibilities": ["management", "other duties", "data entry", "inventory record", "payment", "database", "provide administrative support", "report", "scheduling of meetings", "administration"], "requirements": {"degrees": ["diploma", "degree or above"], "majors": ["business", "accounting"], "languages": ["chinese"], "language_level": ["proficient"], "hard_skills": ["excel", "chinese word processing", "powerpoint", "ms word"], "soft_skills": ["communication skills", "stable", "responsible"], "languages_combined": [{"language": "chinese", "language_level": ["proficient"]}]}, "experience_required": {"duration": ["minimum 2 year"], "field": []}}, {"job_id": "100003009050764", "location_code": "hk", "company": "The Hang Seng University of Hong Kong", "job_title": "Assistant Officer / Executive Assistant \u2013 School of Communication  (Ref: AO/EA (SCOM) 2022-01-14)", "description": "RESEARCH OFFICE\n\nExecutive Officer (PR0256/21-22)\n\nThe Office is looking for a number of meticulous teamplayers. The candidate will perform the following duties:\n\nSupport the University\u2019s research initiatives and enhance its research culture and engagement;\nSupport the development of the interdisciplinary research labs and the hiring of labs\u2019 members;\nDevelop and enhance the existing websites and contribute in various social media platforms and external liaison;\nPromote research-related events/activities, including but not limited to talks, programmes, conferences, tour visits, interviews, symposiums and exhibitions, etc.;\nProvide support in forging industrial/academic partnerships;\nPromote research communication and publicity;\nProvide support in committee work; and\nCarry out ad hoc tasks as assigned.\nApplicants should possess:\n\nA recognised degree in Public Relations & Communications, Language Studies or related disciplines preferred;\nAt least four years of relevant experience;\nAn excellent command of written and spoken English and Chinese (including Putonghua), and relevant editing and multimedia production skills;\nProactivity, maturity, meticulousness, readiness to accept challenges, capability in multitasking and independence at work;\nStrong communication and interpersonal skills, good analytical ability and a strong sense of responsibility;\nAbility to work under tight timelines; and\nProficiency in a wide range of computing applications.\nInitial appointment will be offered on a fixed-term contract of 2 years. Re-appointment thereafter will be subject to mutual agreement.\n\nSalary will be commensurate with qualifications and experience.\n\nApplication Procedure:\n\nApplicants are invited to submit their applications at the HKBU e-Recruitment System (jobs.hkbu.edu.hk). Those not invited for interview 8 weeks after the closing date may consider their applications unsuccessful. Details of the University\u2019s Personal Information Collection Statement can be found at http://hro.hkbu.edu.hk/pics.\n\nThe University reserves the right not to make an appointment for the post advertised, and the appointment will be made according to the terms and conditions then applicable at the time of offer.\n\nClosing date: 27 January 2022", "employment_types": ["Full Time"], "selling_points": [], "locations": ["Shatin Area"], "categories": ["Education", "Others"], "post_time": "2022-01-14T11:18:26Z", "salary": {"currency": null, "max": null, "min": null, "period": "monthly", "term": null}, "salary_visible": false, "title_keywords": ["assistant officer", "executive assistant"], "responsibilities": ["provide support", "social media platforms", "ad hoc tasks", "develop", "communication", "conferences", "recruitment", "committee work", "editing"], "requirements": {"degrees": ["degree"], "majors": ["related disciplines", "communications"], "languages": ["putonghua", "english", "chinese"], "language_level": ["excellent"], "hard_skills": ["make", "multimedia"], "soft_skills": ["communication", "meticulous", "communication and interpersonal skills", "sense of responsibility"], "languages_combined": [{"language": "putonghua", "language_level": ["excellent"]}, {"language": "english", "language_level": ["excellent"]}, {"language": "chinese", "language_level": ["excellent"]}]}, "experience_required": {"duration": ["at least four years"], "field": ["relevant experience"]}}, {"job_id": "100003009054983", "location_code": "hk", "company": "Mathconcept Education Limited", "job_title": "\u6559\u6750\u7de8\u8f2f Courseware Editor", "description": "Job Responsibility:\n\nHandle administrative tasks including record maintenance and follow-up & etc.\nEnsure administrative tasks delivered are in compliance with any regulatory requirements\nData Entry, Filing, Searching information\nOther office administration support\n\nRequirements:\n\nF.6 (HKDSE with 5 Subject Level 2 include Eng / Chinese / Maths)\n1 - 2 years clerical / administration / data entry working experiences.\nWith government (HKSAR) working experiences is an advantage\nEnglish Typing 30 WPM and Chinese Typing 25 WPM or above\nGood communications skills including MS Word, MS Excel and PowerPoint\nAble to work under pressure with careful mindset.\nGood communication skill in both written and spoken English and Cantonese\nImmediately available is highly preferred\n\nSalary Range from HK$11,000 to $12,900\n", "employment_types": ["Full Time", "Permanent"], "selling_points": ["performance bonus + Transportation allowance", "Overseas travel allowance", "Medical Benefits + 5-day Work week"], "locations": ["Lai Chi Kok"], "categories": ["Education", "Others"], "post_time": "2022-01-17T16:22:45Z", "salary": {"currency": "HKD", "max": 19999, "min": 14000, "period": "monthly", "term": null}, "salary_visible": true, "title_keywords": ["courseware editor"], "responsibilities": ["office administration support", "maintenance", "data entry", "regulatory requirements", "compliance", "administrative tasks"], "requirements": {"degrees": ["hkdse"], "majors": [], "languages": ["cantonese", "english", "chinese"], "language_level": ["good"], "hard_skills": ["ms excel", "typing", "powerpoint", "ms word"], "soft_skills": ["communication skill", "careful", "work under pressure"], "languages_combined": [{"language": "cantonese", "language_level": ["good"]}, {"language": "english", "language_level": ["good"]}, {"language": "chinese", "language_level": []}]}, "experience_required": {"duration": ["1 - 2 years"], "field": ["clerical", "administration"]}}, {"job_id": "100003009055628", "location_code": "hk", "company": "The International Montessori Education Foundation Limited", "job_title": "Receptionist / Administrative Assistant (Mid-levels Campus)", "description": "IMS\u00a0is seeking a Receptionist / Administrative Assistant to welcome children and parents into the school.\n\nOur Receptionist /Administrative Assistant must have the following skills/qualifications:\n\n\nWarm personality, with love for children\nStrong language skills in written and spoken English and Chinese (Mandarin is a plus)\nGood computer skills.\u00a0 Knowledge of MS Office, in particular Excel will be an advantage\nCustomer service experience required\nExperience working in schools preferred\nSuperior inter-personal and communication skills\nGood team player and organized\n\nLocation:\u00a0Mid-levels Campus\n\nInterested parties please send full resume with availability\u00a0and expected salary by\u00a0clicking \"APPLY NOW\" below.\u00a0 Personal data collected will be used for recruitment purpose only.", "employment_types": ["Full Time", "Permanent"], "selling_points": [], "locations": ["Central"], "categories": ["Admin & HR", "Clerical / Admin Staff", "Education", "Others"], "post_time": "2022-01-18T02:48:45Z", "salary": {"currency": null, "max": null, "min": null, "period": "monthly", "term": null}, "salary_visible": false, "title_keywords": ["receptionist", "administrative assistant"], "responsibilities": ["communication", "customer service experience"], "requirements": {"degrees": [], "majors": [], "languages": ["english", "chinese", "mandarin"], "language_level": [], "hard_skills": ["excel", "plus", "computer skills", "ms office"], "soft_skills": ["communication skills", "good team player", "organized", "inter-personal", "customer service", "superior"], "languages_combined": [{"language": "english", "language_level": []}, {"language": "chinese", "language_level": []}, {"language": "mandarin", "language_level": []}]}, "experience_required": {"duration": [], "field": ["customer service"]}}, {"job_id": "100003009053540", "location_code": "hk", "company": "St. Francis' Canossian College", "job_title": "Student Support Officer", "description": "\n\u5609\u8afe\u6492\u8056\u65b9\u6fdf\u5404\u66f8\u9662 St. Francis\u2019 Canossian College\nStudent Support Officer\nAssist the Counselling Department and support SEN students\nRequirements:\nHigher diploma or above, with relevant experience preferred.\nInterested parties are invited to send their applications, enclosing full resumes stating qualifications, career history, aspirations and contact numbers latest by 31 January 2022 to:\nThe Principal\nSt. Francis\u2019 Canossian College\n9 \u2013 13 Kennedy Road, Wanchai, Hong Kong\nOr via email to: Apply Now\nInformation/ Personal data collected will be used for employment purposes only.\nPlease specify the applied position on the envelope or in the email.\n\u5b78\u6821 / \u6a5f\u69cb\u57fa\u672c\u8cc7\u6599\n\u2022 \u62db\u8058\u5b78\u6821/\u6a5f\u69cb\u540d\u7a31 \u5609\u8afe\u6492\u8056\u65b9\u6fdf\u5404\u66f8\u9662\n\u2022 \u7533\u8acb\u806f\u7d61\u4eba \u5229\u5c0f\u59d0 Ms. Li\n\u2022 \u96fb\u8a71 25872700\n\u2022 \u50b3\u771f 25291758\n\u2022 \u96fb\u90f5 Apply Now\n\u2022 \u5730\u5740 9-13 Kennedy Road, Wan Chai, Hong Kong.\n\u2022 \u6a5f\u69cb\u985e\u5225 \u4e2d\u5b78\n\n", "employment_types": ["Full Time"], "selling_points": [], "locations": ["Wan Chai"], "categories": ["Education", "Tutor / Instructor", "Others"], "post_time": "2022-01-17T07:07:39Z", "salary": {"currency": null, "max": null, "min": null, "period": "monthly", "term": null}, "salary_visible": false, "title_keywords": ["officer"], "responsibilities": [], "requirements": {"degrees": ["higher diploma or above"], "majors": [], "languages": [], "language_level": [], "hard_skills": [], "soft_skills": [], "languages_combined": []}, "experience_required": {"duration": [], "field": ["relevant experience"]}}, {"job_id": "100003009055231", "location_code": "hk", "company": "Hong Kong Metropolitan University", "job_title": "Assistant Manager (Ref: 220004O)", "description": "We are now inviting suitable candidate(s) to join us in the School of Nursing and Health Studies for the following post(s):\u00a0\n\nAssistant Manager (Ref: 220004O)\n\nMajor Duties and Responsibilities\n\nThe appointee shall mainly be responsible for the following:\n\nadministering and coordinating the development of programmes and courses offered by the School, and the accreditation/re-accreditation with professional bodies;\nhandling administrative duties involved in research, learning and teaching activities, as well as student related matters;\nplanning and coordinating various events and activities such as seminars and conferences;\ncoordinating the local/overseas clinical practicum of students;\nproof-reading and editing information and documents to meet the internal quality assurance standard;\nparticipating in general office administration, management and enhancement;\nproviding secretarial service to committees and meetings;\nsupervising supporting staff on day-to-day operations; and\nperforming any other duties as assigned.\u00a0\n\nCandidates\n\nCandidates should possess the following qualifications, experience and attributes:\n\na recognized degree with at least 2 years of relevant post-qualification experience. \u00a0More/Considerable relevant experience at supervisory level in a varieties of university administration is preferred;\nexcellent interpersonal, communication, organizational and analytical skills;\nattributes of coping with ambiguity and change;\nability to handle multiple tasks concurrently and work independently; and\nan excellent command of both written and spoken English and Chinese, preferably including Putonghua.\n\nCandidates may be invited to attend a written test.\u00a0\n\nTerms and Conditions for Appointment\n\nAn attractive remuneration package, including basic salary, an end-of-contract gratuity, and a discretionary incentive payment, where applicable, will be offered to the right candidates. Generous annual leave, staff-development sponsorships, medical and dental benefits, and life insurance coverage will also be provided.\u00a0\n\nTo Apply\n\nCandidates who are interested in joining us may submit their applications via the University\u2019s eRecruitment System.\u00a0\n\nhttps://hkmu.taleo.net/careersection/ex_full_time/jobapply.ftl?lang=en&job=220004O\u00a0\n\nClosing date of application: 31 January 2022\n\nThe personal data collected will be used for the purpose of considering your application for employment.\u00a0 For details, please refer to the \u201cPersonal Data (Privacy) Notice for Job Applicant\u201d on the University\u2019s website.\u00a0 If you are not contacted by the University within eight weeks from the closing date of application, you may assume that your application is unsuccessful.\u00a0\u00a0", "employment_types": ["Full Time", "Contract"], "selling_points": ["Administration and Coordination", "Gratuity and bonus", "Attractive medical, dental & life insurance"], "locations": ["Kowloon City"], "categories": ["Education", "Others"], "post_time": "2022-01-18T01:53:12Z", "salary": {"currency": null, "max": null, "min": null, "period": "monthly", "term": null}, "salary_visible": false, "title_keywords": ["assistant manager"], "responsibilities": ["administration", "any other duties", "management", "supervising", "office administration", "quality", "day-to-day operations", "secretarial service", "communication", "conferences", "payment", "administrative duties", "editing", "planning"], "requirements": {"degrees": ["degree"], "majors": [], "languages": ["putonghua", "english", "chinese"], "language_level": ["excellent"], "hard_skills": ["basic", "analytical skills"], "soft_skills": ["work independently", "responsible", "organizational", "analytical skills", "communication", "handle multiple tasks", "learning", "interpersonal"], "languages_combined": [{"language": "putonghua", "language_level": ["excellent"]}, {"language": "english", "language_level": ["excellent"]}, {"language": "chinese", "language_level": ["excellent"]}]}, "experience_required": {"duration": ["at least 2 years"], "field": ["administration", "supervisory level", "post-qualification", "relevant experience"]}}, {"job_id": "100003009055501", "location_code": "hk", "company": "The University of Hong Kong", "job_title": "Project Associate (2 posts)", "description": "The Diocesan Boys\u2019 School Foundation Limited is a registered charity, please visit our website for background details: http://www.dbs.edu.hk/dbsfoundation.\n\nMotivated and committed individuals are invited to apply for the post of Assistant Events Officer.\n\nJob Responsibilities\n\nAssist in handling event-related operation work, including venue reservation, food and beverage, programmes, invitation and registration, on-site hospitality / support and related administrative work;\nWork closely with the Events and Development Sub-Committee to execute a series of foundation and anniversary ceremonial events;\nAssist in processing event sponsorship, foundation souvenir/ publication orders, and issuance of receipt/ acknowledgement;\nHandle email/phone enquiry and provide donor/sponsor service;\nAssist in database management including data entry, regular update and report generation;\nProvide timely update on website / social media contents;\nLiaise and work closely with members of sub-committees, colleagues from other departments and external vendors/ suppliers;\nProvide secretarial support to Sub-Committees and working group meetings; and\nPerform other duties as assigned by the Chief Administrator.\n\n\u00a0Requirements\n\nHolder of Bachelor Degree;\nA minimum of 3 years working experience;\nGood manner, good communication skills, stable and responsible;\nProficient in MS Word, Excel, PowerPoint, Chinese word processing and internet; and\nExperience in managing data in computer system an advantage.\n\nFull personal particulars including educational background, working experience, current and expected salary (quoting reference: Application for the Position of Assistant Events Officer) should reach the Chief Administrator of Foundation Office, Diocesan Boys\u2019 School Foundation Limited, 131 Argyle Street, Kowloon, Hong Kong, or by email on or before 17 February 2022.\n\nAll information provided will be used for recruitment related purposes only.", "employment_types": ["Full Time"], "selling_points": ["Will assist in organizing events", "Perform any other duties as assigned", "Recognized Bachelor\u2019s degree in any discipline"], "locations": ["Pok Fu Lam"], "categories": ["Education", "Others", "Marketing / Public Relations", "Public Relations - Event Management", "Others"], "post_time": "2022-01-18T02:39:47Z", "salary": {"currency": null, "max": null, "min": null, "period": "monthly", "term": null}, "salary_visible": false, "title_keywords": ["associate"], "responsibilities": ["liaise", "social media", "management", "perform other duties", "administrative work", "data entry", "website", "secretarial support", "database", "contents", "publication", "report"], "requirements": {"degrees": ["degree", "bachelor"], "majors": [], "languages": ["chinese"], "language_level": ["proficient"], "hard_skills": ["excel", "chinese word processing", "powerpoint", "ms word"], "soft_skills": ["communication skills", "stable", "responsible"], "languages_combined": [{"language": "chinese", "language_level": ["proficient"]}]}, "experience_required": {"duration": ["minimum of 3 years"], "field": []}}, {"job_id": "100003009055612", "location_code": "hk", "company": "Advance Resources Personnel Consultants Limited", "job_title": "Clerical Assistant (5 days, HKSAR Contract, $11-$13K)", "description": "Job Responsibility:\n\nHandle administrative tasks including record maintenance and follow-up & etc.\nEnsure administrative tasks delivered are in compliance with any regulatory requirements\nData Entry, Filing, Searching information\nOther office administration support\n\nRequirements:\n\nF.6 (HKDSE with 5 Subject Level 2 include Eng / Chinese / Maths)\n1 - 2 years clerical / administration / data entry working experiences.\nWith government (HKSAR) working experiences is an advantage\nEnglish Typing 30 WPM and Chinese Typing 25 WPM or above\nGood communications skills including MS Word, MS Excel and PowerPoint\nAble to work under pressure with careful mindset.\nGood communication skill in both written and spoken English and Cantonese\nImmediately available is highly preferred\n\nSalary Range from HK$11,000 to $12,900", "employment_types": ["Full Time", "Contract"], "selling_points": ["Clerical duty, data entry, filing, scanning", "office administration support, ad hoc support", "Contract position, 5 days work, public holiday"], "locations": ["Wan Chai Area"], "categories": ["Admin & HR", "Clerical / Admin Staff", "Others", "Education", "Others"], "post_time": "2022-01-18T02:47:42Z", "salary": {"currency": null, "max": null, "min": null, "period": "monthly", "term": null}, "salary_visible": false, "title_keywords": ["clerical assistant"], "responsibilities": ["office administration support", "maintenance", "data entry", "regulatory requirements", "compliance", "administrative tasks"], "requirements": {"degrees": ["hkdse"], "majors": [], "languages": ["cantonese", "english", "chinese"], "language_level": ["good"], "hard_skills": ["ms excel", "typing", "powerpoint", "ms word"], "soft_skills": ["communication skill", "careful", "work under pressure"], "languages_combined": [{"language": "cantonese", "language_level": ["good"]}, {"language": "english", "language_level": ["good"]}, {"language": "chinese", "language_level": []}]}, "experience_required": {"duration": ["1 - 2 years"], "field": ["clerical", "administration"]}}, {"job_id": "100003009048482", "location_code": "hk", "company": "Hong Kong Baptist University", "job_title": "Executive Officer (PR0256/21-22)", "description": "RESEARCH OFFICE\n\nExecutive Officer (PR0256/21-22)\n\nThe Office is looking for a number of meticulous teamplayers. The candidate will perform the following duties:\n\nSupport the University\u2019s research initiatives and enhance its research culture and engagement;\nSupport the development of the interdisciplinary research labs and the hiring of labs\u2019 members;\nDevelop and enhance the existing websites and contribute in various social media platforms and external liaison;\nPromote research-related events/activities, including but not limited to talks, programmes, conferences, tour visits, interviews, symposiums and exhibitions, etc.;\nProvide support in forging industrial/academic partnerships;\nPromote research communication and publicity;\nProvide support in committee work; and\nCarry out ad hoc tasks as assigned.\nApplicants should possess:\n\nA recognised degree in Public Relations & Communications, Language Studies or related disciplines preferred;\nAt least four years of relevant experience;\nAn excellent command of written and spoken English and Chinese (including Putonghua), and relevant editing and multimedia production skills;\nProactivity, maturity, meticulousness, readiness to accept challenges, capability in multitasking and independence at work;\nStrong communication and interpersonal skills, good analytical ability and a strong sense of responsibility;\nAbility to work under tight timelines; and\nProficiency in a wide range of computing applications.\nInitial appointment will be offered on a fixed-term contract of 2 years. Re-appointment thereafter will be subject to mutual agreement.\n\nSalary will be commensurate with qualifications and experience.\n\nApplication Procedure:\n\nApplicants are invited to submit their applications at the HKBU e-Recruitment System (jobs.hkbu.edu.hk). Those not invited for interview 8 weeks after the closing date may consider their applications unsuccessful. Details of the University\u2019s Personal Information Collection Statement can be found at http://hro.hkbu.edu.hk/pics.\n\nThe University reserves the right not to make an appointment for the post advertised, and the appointment will be made according to the terms and conditions then applicable at the time of offer.\n\nClosing date: 27 January 2022", "employment_types": ["Full Time"], "selling_points": ["Support the University\u2019s research initiatives", "Contribute in various social media platforms", "Relevant editing and multimedia production skills"], "locations": ["Kowloon City"], "categories": ["Education", "Others", "Marketing / Public Relations", "Marketing - Marketing Communication", "Public Relations - Event Management"], "post_time": "2022-01-14T06:39:02Z", "salary": {"currency": null, "max": null, "min": null, "period": "monthly", "term": null}, "salary_visible": false, "title_keywords": ["executive officer"], "responsibilities": ["provide support", "social media platforms", "ad hoc tasks", "develop", "communication", "conferences", "recruitment", "committee work", "editing"], "requirements": {"degrees": ["degree"], "majors": ["related disciplines", "communications"], "languages": ["putonghua", "english", "chinese"], "language_level": ["excellent"], "hard_skills": ["make", "multimedia"], "soft_skills": ["communication", "meticulous", "communication and interpersonal skills", "sense of responsibility"], "languages_combined": [{"language": "putonghua", "language_level": ["excellent"]}, {"language": "english", "language_level": ["excellent"]}, {"language": "chinese", "language_level": ["excellent"]}]}, "experience_required": {"duration": ["at least four years"], "field": ["relevant experience"]}}, {"job_id": "100003009054527", "location_code": "hk", "company": "Hong Kong Federation of Education Workers Limited", "job_title": "\u9805\u76ee\u7d71\u7c4c\u4e3b\u4efb(\u5c08\u696d\u767c\u5c55\u90e8)", "description": "\u8077\u8cac \u00a0:\n\n\u61c9\u7b54\u5b78\u751f\u53ca\u5bb6\u9577\u67e5\u8a62\u53ca\u5b89\u6392\u8abf\u5802\n\u8655\u7406\u5831\u540d\u4e8b\u5b9c\n\u6574\u7406\u6587\u4ef6\u53ca\u6587\u66f8\u8655\u7406\n\u8655\u7406\u88dc\u7fd2\u4e2d\u5fc3\u65e5\u5e38\u5927\u5c0f\u4e8b\u52d9\n\n\u8077\u4f4d\u8981\u6c42 \u00a0:\n\n\u4e2d\u5b78\u7562\u696d\uff0c\u540c\u7b49\u5b78\u6b77\u6216\u4ee5\u4e0a\u7a0b\u5ea6\n\u61c2\u4e2d\u82f1\u6253\u5b57\uff0c\u719f\u8b58\u57fa\u672c\u96fb\u8166\u64cd\u4f5c\n\u7a4d\u6975\u9032\u53d6\uff0c\u7d30\u5fc3\uff0c\u5f85\u4eba\u6709\u79ae\uff0c\u6709\u8cac\u4efb\u611f\n\u5177\u76f8\u95dc\u5de5\u4f5c\u7d93\u9a57\u8005\u512a\u5148\n\n\u5de5\u4f5c\u6642\u9593 :\n\n\u4e94\u5929\u5de5\u4f5c\u65e5, \u8f2a\u4f11\n\u661f\u671f\u4e00\u81f3\u4e94\u00a0(12:00-21:00) \u53ca\u661f\u671f\u516d(09:00-19:00) 1\u5c0f\u6642\u5348\u98ef\u6642\u9593\n\u9022\u661f\u671f\u65e5\u53ca\u516c\u773e\u5047\u671f\u4f11\u606f\n\u5de5\u4f5c\u5730\u9ede: \u592a\u5b50/\u7063\u4ed4/\u6c99\u7530/\u8343\u7063/\u5143\u6717 (\u53ef\u6309\u5c45\u4f4f\u5730\u5340\u5b89\u6392)\n\n\n\u54e1\u5de5\u53ef\u4eab\u00a0:\u00a0\n\n\u52e4\u5de5\u734e\n\u5b9a\u671f\u54e1\u5de5\u6d3b\u52d5\u53ca\u805a\u9910\n\u52de\u5de5\u4fdd\u96aa\n\u91ab\u7642\u4fdd\u96aa\n\u6709\u85aa\u75c5\u5047\u3001\u5a5a\u5047\u3001\u4f8d\u7522\u5047\u3001\u751f\u65e5\u798f\u5229\n\u9022\u661f\u671f\u65e5\u53ca\u516c\u773e\u5047\u671f\u4f11\u606f\n\n\u6709\u8207\u8da3\u8005\u8acb\u628a\u5c65\u6b77\u8868\u96fb\u90f5\u7d66\u6211\u5011\uff0c\u6211\u5011\u6703\u81f4\u96fb\u76f8\u7d04\u9762\u8a66\u6642\u9593\u3002", "employment_types": ["Full Time"], "selling_points": [], "locations": ["Mong Kok"], "categories": ["Education", "Others", "Public / Civil", "Social Services - Community / Non-profit Organization"], "post_time": "2022-01-17T09:53:31Z", "salary": {"currency": null, "max": null, "min": null, "period": "monthly", "term": null}, "salary_visible": false, "title_keywords": [], "responsibilities": [], "requirements": {"degrees": [], "majors": [], "languages": [], "language_level": [], "hard_skills": [], "soft_skills": [], "languages_combined": []}, "experience_required": {"duration": [], "field": []}}, {"job_id": "100003009048056", "location_code": "hk", "company": "Hong Kong Baptist University", "job_title": "Executive Officer (PR0472/21-22)", "description": "Role & Responsibilities:\n\n\nDeliver lessons in IPC curriculum\u00a0in a structured and coordinated manner with due regard to the ability of the students and the curriculum targets of the particular year group\nEnsure attention is given to appropriate differentiation in lesson preparation and delivery\nDesign a relevant, challenging and rigorous curriculum in liaison with the Level Teachers\u00a0\nContribute to the formation of collaborative learning at all levels of school life\nCreate inquiry-based classrooms that develop critical thinking skills, knowledge and a range of skills within an environment based on trust and respect\nSelect relevant resources and digital tools to support and enhance learning\nDevelop appropriate assessment tasks, providing timely and effective feedback that enhances pupil\u2019s learning\nCommunicate effectively with pupils, parents and colleagues in a professional\u00a0manner\nProvide appropriate pastoral support as and when necessary\n\nRequirements:\n\n\nBachelor\u2019s degree in Education or a basic degree and a Post Graduate\u00a0Diploma/Certificate\u00a0in Education\u00a0\u00a0\nA minimum of 2 years working experience in teaching IPC\u00a0within an international school\u00a0setting\nInnovative and creative approach to providing an outstanding education in line with the IPC Curriculum\nProven record of outstanding teaching and learning, and have ability to inspire, challenge, support and empower students\u00a0towards excellence.\nPositive approach to professional development, particularly in the areas\u00a0of IPC and ICT\nProficiency in Google Classroom environment and familiarity with various education software and apps\u00a0\nAble to assess pupils\u2019 interests, needs and developments\nOpen, proactive, patient and caring\nSensitive to the demands of working in a cross-cultural setting\nExcellent interpersonal and communication skills\nMust be able to work legally in HK(HK permanent resident, Holder of relevant visa)\nFitness to work (Successful candidates will undergo a medical examination, and if there is a health problem, the employment may be canceled.)\n\nHow To Apply:\n\nInterested candidates please send your full CV by clicking \"Apply Now\".\u00a0 Only shortlisted candidates will be contacted.\n\n\n\n\nAll personal data collected will be used for recruitment purposes only and will be kept strictly confidential.", "employment_types": ["Full Time"], "selling_points": ["Administer Lab's projects and grants applications", "Coordinate Lab's engagement activities", "Possess a recognised relevant bachelor's degree"], "locations": ["Kowloon City"], "categories": ["Education", "Others", "Marketing / Public Relations", "Marketing - Direct Marketing", "Marketing - Marketing Communication"], "post_time": "2022-01-14T04:37:11Z", "salary": {"currency": null, "max": null, "min": null, "period": "monthly", "term": null}, "salary_visible": false, "title_keywords": ["executive officer"], "responsibilities": ["professional manner", "design", "develop"], "requirements": {"degrees": ["certificate", "diploma", "degree", "bachelor"], "majors": [], "languages": [], "language_level": [], "hard_skills": ["basic"], "soft_skills": ["communication skills", "creative", "innovative", "sensitive to", "learning", "patient", "proactive", "interpersonal", "positive"], "languages_combined": []}, "experience_required": {"duration": ["minimum of 2 years"], "field": ["teaching"]}}, {"job_id": "100003009048054", "location_code": "hk", "company": "The University of Hong Kong", "job_title": "Executive Assistant, Masters Programmes Administration (at the rank of Clerk II)", "description": "Major Duties\n\nThe appointee will be required to\n\n-\u00a0 \u00a0provide administrative support to student admission;\n\n-\u00a0 \u00a0liaise with secondary schools and various parties to organise promotional and engagement activities;\n\n-\u00a0 \u00a0prepare publicity materials;\n\n-\u00a0 \u00a0update College website content;\n\n-\u00a0 \u00a0manage and create content for social media platforms; and\n\n-\u00a0 \u00a0perform other administrative duties as assigned by the supervisors.\n\nQualifications Required\n\nCandidates should have (i) a Bachelor\u2019s degree or a sub-degree qualificationwith at least 2 years of office administrative experience; (ii) good presentation, organisational and interpersonal skills; (iii) good command of both spoken and written English and Chinese; (iv) ability to manage multiple tasks and work independently, (v) high proficiency in MS Excel; and (vi) preferably knowledge of Adobe Photoshop and/or Adobe Premiere\n\nRemuneration and Conditions of Service\n\nSalary will be commensurate with qualifications and experience. Fringe benefits include contract-end gratuity, medical benefits, and staff development sponsorship. Initial appointment will be on a fixed-term contract for up to two years. Re-engagement thereafter is subject to mutual agreement.\n\n\n\n\nApplication\n\nPlease send your full curriculum vitae (with your current and expected salary) by email\u00a0or by post to HKU SPACE Po Leung Kuk Stanley Ho Community College, 18/F, 66 Leighton Road, Causeway Bay, Hong Kong. You should indicate the full title and the reference number of the post you are applying for.\n\nAll applications will be treated in strict confidence. Only those who are shortlisted will be contacted. The College reserves the right not to fill the posts advertised.\n\nClosing date for application: 24 January 2022", "employment_types": ["Full Time"], "selling_points": ["processing of applications", "providing support for classes and examinations", "assisting in general office administration"], "locations": ["Aberdeen"], "categories": ["Education", "Others"], "post_time": "2022-01-14T04:37:05Z", "salary": {"currency": null, "max": null, "min": null, "period": "monthly", "term": null}, "salary_visible": false, "title_keywords": ["executive assistant", "clerk"], "responsibilities": ["social media platforms", "website", "liaise with", "administrative duties", "provide administrative support"], "requirements": {"degrees": ["degree", "bachelor"], "majors": [], "languages": ["english", "chinese"], "language_level": ["good command"], "hard_skills": ["ms excel", "adobe photoshop", "adobe premiere"], "soft_skills": ["work independently", "interpersonal skills", "presentation", "multiple tasks"], "languages_combined": [{"language": "english", "language_level": ["good command"]}, {"language": "chinese", "language_level": ["good command"]}]}, "experience_required": {"duration": ["at least 2 years"], "field": ["administrative"]}}, {"job_id": "100003009051163", "location_code": "hk", "company": "School of Continuing Education, HKBU", "job_title": "Part-time Helpers (Ref. No.: PRSCEP0046/21-22)", "description": "The applicant must possess\na\u00a0recognised degree;\na minimum of 3 years\u2019 post-qualification work experience in institutional administration, preferably in vocational training bodies, educational institutions, public bodies or sizable organisations;\nknowledge in construction and managerial accounting would be an advantage;\nstrong leadership, self-initiative and problem solving skills;\na high level of integrity and a strong sense of responsibility;\ngood communication and interpersonal skills;\na pro-active, resourceful and energetic character, and the ability to work independently with minimal supervision;\ngood knowledge and skills in Word, Excel, Powerpoint, English and Chinese word processing; and\na good command of both written and spoken English and Chinese.\n(Applicants who do not possess the required qualifications and / or experience may be considered for other positions within the organisation.)\nDuties include\nto oversee the daily operation of the Kowloon Bay Campus and lead the administration team to ensure smooth and effective operation;\nto initiate, plan, manage and implement new development initiatives and improvement initiatives;\nto assist the adoption of computerisation and carry out user acceptance test in system implementation;\nto assist in promoting construction training including the marketing of construction related courses to the general public and the stakeholders of the construction industry;\nto assist in obtaining qualifications recognition from local and overseas professional organisations, educational institutions and government authorities;\nto perform secretariat duties for related task forces, promotion events, seminars, conferences, and any other relevant activities;\nto prepare for the annual budget;\nto help maintain the Kowloon Bay Campus in a clean and tidy state of operation and help task the security guards and cleaners;\nto act as duty-in-charge during non-office hour operation; and\nto carry out any other duties as assigned from time to time by the Executive Director.\nApplications\nThe position is on a renewable fixed-term contract (subject to performance and operational needs) for a period of 2 years.\nPlease click the below \u201cApply Online\u201d to complete the application form and upload the updated curriculum vitae, the results of English and Chinese Language obtained in public examinations, current and expected salary together with a covering letter stating one\u2019s suitability for the job on or before\u00a027\u00a0January\u00a02022.", "employment_types": ["Part Time", "Temporary"], "selling_points": [], "locations": ["Kowloon City Area"], "categories": ["Admin & HR", "Clerical / Admin Staff", "Education", "Others", "Others", "Others"], "post_time": "2022-01-15T03:48:54Z", "salary": {"currency": null, "max": null, "min": null, "period": "hourly", "term": null}, "salary_visible": false, "title_keywords": [], "responsibilities": ["any other duties", "budget", "daily operation", "implementation", "communication", "conferences", "maintain", "plan", "administration"], "requirements": {"degrees": ["degree"], "majors": [], "languages": ["english", "chinese"], "language_level": ["good command", "good"], "hard_skills": ["clean", "excel", "chinese word processing", "word", "powerpoint", "system implementation", "problem solving skills"], "soft_skills": ["work independently", "resourceful", "sense of responsibility", "integrity", "smooth", "communication and interpersonal skills", "self-initiative", "organisation", "pro-active", "problem solving skills", "energetic", "leadership"], "languages_combined": [{"language": "english", "language_level": ["good command", "good", "good"]}, {"language": "chinese", "language_level": ["good command", "good", "good"]}]}, "experience_required": {"duration": ["minimum of 3 years"], "field": ["post-qualification", "training", "administration"]}}, {"job_id": "100003009047655", "location_code": "hk", "company": "Hong Kong Council for Accreditation of Academic and Vocational Qualifications", "job_title": "Assistant Registrar  [Ref: 2022/01/15/J]", "description": "RESEARCH OFFICE\nHong Kong Baptist University has been awarded funding under Job Creation Scheme 2.0 supported by the Government to create employment opportunities amidst the deteriorating economy due to the pandemic.\nThe Research Office now invites applications for the following position:\nExecutive Officer (PR0472/21-22)\nSupport research development in the six transdisciplinary laboratories\nAdminister Lab's projects and grants applications;\nCoordinate Lab's engagement activities;\nSupport Lab's development and coordinate internal and external collaborations; and\nSupport research website enhancement.\nApplicants should possess a recognised relevant bachelor's degree with relevant work experience. They should have good interpersonal, communication and organisational skills and a good command of written and spoken English and Chinese (including Putonghua).\nThe Office may appoint candidates to positions different from what they have applied for to suit its operational needs.\nThe appointment will be offered on a fixed-term contract of one year.\nApplication Procedure:\nApplicants are invited to submit their applications at the HKBU e-Recruitment System (jobs.hkbu.edu.hk). Those not invited for interview 8 weeks after submission of application may consider their applications unsuccessful. Details of the University's Personal Information Collection Statement can be found at http://hro.hkbu.edu.hk/pics.\nThe University reserves the right not to make an appointment for the post advertised, and the appointment will be made according to the terms and conditions applicable at the time of offer.\nReview of applications is ongoing until the position is filled.", "employment_types": ["Full Time", "Contract"], "selling_points": [], "locations": ["Siu Sai Wan"], "categories": ["Admin & HR", "Administration / Operation Manager", "Education", "Tutor / Instructor", "Others"], "post_time": "2022-01-14T03:39:55Z", "salary": {"currency": null, "max": null, "min": null, "period": "monthly", "term": null}, "salary_visible": false, "title_keywords": ["assistant"], "responsibilities": ["review", "website", "coordinate", "communication", "recruitment"], "requirements": {"degrees": ["degree", "bachelor"], "majors": [], "languages": ["putonghua", "english", "chinese"], "language_level": ["good command", "good"], "hard_skills": ["make", "scheme"], "soft_skills": ["communication", "organisational skills", "interpersonal"], "languages_combined": [{"language": "putonghua", "language_level": ["good command", "good"]}, {"language": "english", "language_level": ["good command", "good"]}, {"language": "chinese", "language_level": ["good command", "good"]}]}, "experience_required": {"duration": [], "field": []}}, {"job_id": "100003009053693", "location_code": "hk", "company": "Convey Telecom Engineering Limited", "job_title": "\u904b\u4f5c\u52a9\u7406", "description": "Executive Assistant, Masters Programmes Administration (at the rank of Clerk II) in the Faculty of Business and Economics (Ref.: 511563) (to commence as soon as possible, on a two-year fixed-term basis, with contract-end gratuity and University contribution to a retirement benefits scheme, totalling up to 10% of basic salary, with the possibility of renewal)\u00a0\u00a0\n\nApplicants should possess a Bachelor\u2019s degree, with at least 1-2 years\u2019 full-time work experience in the field of programme administration or a related field. \u00a0They should be proficient in both written and spoken English and Chinese (including Putonghua), with good organisational, communication, project management and problem-solving skills, and computer literacy; and must be able to work independently and under pressure. \u00a0They should be good team players, attentive to details, with the ability to multi-task. \u00a0They should also have a passion for working with students from all backgrounds and cultures.\n\nThe appointee will support the administration and operation of the Faculty\u2019s taught postgraduate programmes, including processing of applications, assisting in course arrangements such as taking attendance and Moodle management, providing support for classes and examinations, organising activities, assisting in general office administration, handling enquires, and performing other duties as assigned. \u00a0The appointee will work at the Faculty\u2019s Cyberport campus and may need to work outside normal office hours, including evenings and weekends. \u00a0Shortlisted candidates will be invited to attend a written test and an interview.\u00a0\n\nA highly competitive salary commensurate with qualifications and experience will be offered, in addition to annual leave and medical benefits.\u00a0\n\nThe University only accepts online application for the above post. \u00a0Applicants should apply online at the University\u2019s careers site (https://jobs.hku.hk) and upload an up-to-date C.V. Review of applications will commence as soon as possible and continue until February 4, 2022, or until the post is filled, whichever is earlier.\n\nThe University is an equal opportunities employer and\nis committed to equality, ethics, inclusivity, diversity and transparency", "employment_types": ["Full Time"], "selling_points": [], "locations": ["Wong Tai Sin Area"], "categories": ["Education", "Tutor / Instructor", "Others", "Others", "Others"], "post_time": "2022-01-17T07:21:49Z", "salary": {"currency": null, "max": null, "min": null, "period": "monthly", "term": null}, "salary_visible": false, "title_keywords": [], "responsibilities": ["attendance", "management", "other duties", "office administration", "communication", "project management", "providing support", "administration"], "requirements": {"degrees": ["degree", "bachelor"], "majors": [], "languages": ["putonghua", "english", "chinese"], "language_level": ["good", "proficient"], "hard_skills": ["basic", "scheme", "project management", "problem-solving skills", "processing"], "soft_skills": ["work independently", "under pressure", "multi-task", "attentive to details", "passion for", "communication", "project management", "computer literacy", "problem-solving skills"], "languages_combined": [{"language": "putonghua", "language_level": ["good"]}, {"language": "english", "language_level": ["proficient", "good"]}, {"language": "chinese", "language_level": ["proficient", "good"]}]}, "experience_required": {"duration": ["at least 1-2 years"], "field": ["related", "administration"]}}, {"job_id": "100003009051138", "location_code": "hk", "company": "Think.Math Group Limited", "job_title": "Centre Manager Trainee", "description": "We are now looking for a\u00a0Digital Marketing Specialist to join our team. Your\u00a0direct\u00a0responsibilities\u00a0include creating, managing and executing campaign and activations calendar that can build the brand awareness and drive impacts.Manage and create for our online platforms, e.g. website, Facebook, Instagram, WeChat, mobile app, and other digital platforms, as well as planning and execute all brand communications and media actions on all channels.\n\nMAIN RESPONSIBILITIES:\n\n\n\nCreating, managing and executing campaign and activations calendar that can build the brand awareness and drive impacts.\nManage and create content for our online platforms, e.g. website, Facebook, Instagram, WeChat, mobile app, and other digital platforms.\nPlanning and execute all brand communications and media actions on all channels.\nExplore new promotion or collaboration opportunities with relevant partners.\nSupervise all activities related to the brand. Ensuring that messaging and marketing activities are aligned with brand and company values.\nCome up with briefs, manage marketing agency or internal teams for development of brand campaigns and activations.\nManage the communications of third-party partners to drive the brand forward and work with brand influencers for driving the brand and audience reach.\nCollaborating with different teams such as Admissions, Faculty, Facilities, operations etc.\nMonitor the brand health and manage the brand tracking study and generate weekly, monthly performance reports and forecast predictions.\nKeep up on the changes in the industry with competitors and audience insights analysis.\n\nREQUIREMENTS:\n\nStrong project management skills with the ability to supervise multiple projects.\nHas knowledge executing the followings: campaign management, media activities, video production, photo shooting, and partners\u2019 communications management.\nExperience in brand health tracking, market research.\nProficiency with word processing, spreadsheet and presentation software (MS Office/Google)\nAbility to think strategically and come up with campaigns and activations ideas.\nBe an excellent team player, as well as keeping an open mind.\nStrong project management experience, across multiple teams and geographical.\nKnowledge in Adobe photoshop, illustrator, etc, will be an advantage.\nGood personality, positive attitude, able to work independently.\nExcellent command in written & spoken Cantonese and English.\nAt least 2 years of work experiences in the marketing sector, experience in the Education industry will be an advantage.\nProficiency in MS Office Application, Word, Excel, PowerPoint, Google Business Apps and all social media platform.\nCandidate with more experience will be considered for a senior position.\n\nWhy\u00a0IMS?\n\nYou want to have a job you\u2019re actually eager to come to every single day, with people that will inspire and challenge you. This is an outstanding opportunity to see your projects and efforts come to fruition, and feel real ownership on the job.\n\nPerks\n\nSunny space in beautiful Stanley with one of the best views in HK, you\u2019ll feel on holidays every single day!\nA fantastic work environment with lots of learning opportunities\nNot two days are the same when you work on education, prepare to be wowed, moved and inspired on a weekly basis\n\nLocation: Stanley Campus\n\nInterested parties please send full resume with availability\u00a0and expected salary by\u00a0clicking \"APPLY NOW\".\u00a0\n\nPersonal data collected will be used for recruitment purpose only.", "employment_types": ["Full Time", "Permanent"], "selling_points": ["5 days working", "Provide all round training, welcome fresh grad", "Great chance of promoting to be a partner"], "locations": ["Kowloon City"], "categories": ["Admin & HR", "Administration / Operation Manager", "Education", "Others"], "post_time": "2022-01-15T03:23:24Z", "salary": {"currency": null, "max": null, "min": null, "period": "monthly", "term": null}, "salary_visible": false, "title_keywords": ["centre manager", "trainee"], "responsibilities": ["tracking", "mobile app", "performance reports", "operations", "analysis", "teams", "website", "monitor", "executing", "forecast", "facebook", "planning"], "requirements": {"degrees": [], "majors": [], "languages": ["cantonese", "english"], "language_level": ["excellent"], "hard_skills": ["excel", "adobe photoshop", "word processing", "illustrator", "word", "powerpoint", "project management", "spreadsheet", "ms office"], "soft_skills": ["work independently", "project management skills", "positive attitude", "project management", "learning", "think strategically", "team player", "presentation"], "languages_combined": [{"language": "cantonese", "language_level": ["excellent"]}, {"language": "english", "language_level": ["excellent"]}]}, "experience_required": {"duration": ["at least 2 years"], "field": ["brand", "market research", "education", "project management", "marketing"]}}, {"job_id": "100003009051333", "location_code": "hk", "company": "Assurance Education Limited", "job_title": "Education Consultant, Full Time", "description": "The appointees will be required to provide clerical support to the instructors, students and staff in Learning Centres. Major duties include a) venue checking, audio video equipment setup and material preparation for classes; b) centre patrol; c) counter and reception duties; and d) any other office / operation duties as assigned.\nAppointment Period:\nAround 6 months (with possibility of further appointment)\nWorking Location:\nLearning Centres in Kowloon Tong, Tsimshatsui, Kwun Tong or Wan Chai\nWorking hours:\nMonday to Friday \u2013 6:00 pm onwards (4 to 5 hours)\nSaturday \u2013 9:00 am to 1:00 pm or 1:30 pm to 5:30 pm\nMinimum Requirements:\n\u00a0\u00a0\u00a0\u00a0\u00a0\u00a0\u00a0\u00a0\u00a0\u00a0 Completed secondary education or equivalent;\n\u00a0\u00a0\u00a0\u00a0\u00a0\u00a0\u00a0\u00a0\u00a0\u00a0 Basic knowledge in audio video equipment setup;\n\u00a0\u00a0\u00a0\u00a0\u00a0\u00a0\u00a0\u00a0\u00a0\u00a0 Proficiency in computer applications including Word (Chinese and English) and Excel, Chinese & English typing;\n\u00a0\u00a0\u00a0\u00a0\u00a0\u00a0\u00a0\u00a0\u00a0\u00a0 Good manner and customer service skills; and\n\u00a0\u00a0\u00a0\u00a0\u00a0\u00a0\u00a0\u00a0\u00a0\u00a0 Relevant work experience is preferred\nSalary : HK$50 per hour\n\n\n\nThose who have responded to the advertisement posted in Dec 2021 need not re-apply.\n\nApplication Procedure:\nApplicants are invited to submit their applications at the HKBU e-Recruitment System (jobs.hkbu.edu.hk). Applicants not invited for interview 8 weeks after the closing date may consider their applications unsuccessful. Details of the University's Personal Information Collection Statement can be found at http://hro.hkbu.edu.hk/pics.\nThe School reserves the right not to make an appointment for the post advertised, and the appointment will be made according to the terms and conditions then applicable at the time of offer.\nClosing date: 24 January 2022", "employment_types": ["Full Time"], "selling_points": ["Proficiency in English, Cantonese & Mandarin", "Degree holder, 1 year of experience", "Salary $15-17K, 5 days working"], "locations": ["Causeway Bay"], "categories": ["Admin & HR", "Personal / Executive Assistant", "Secretary", "Education", "Others"], "post_time": "2022-01-15T09:22:56Z", "salary": {"currency": "HKD", "max": 16999, "min": 14000, "period": "monthly", "term": null}, "salary_visible": true, "title_keywords": ["education consultant"], "responsibilities": ["provide clerical support", "audio", "checking", "setup"], "requirements": {"degrees": [], "majors": [], "languages": [], "language_level": [], "hard_skills": ["c"], "soft_skills": ["learning"], "languages_combined": []}, "experience_required": {"duration": [], "field": []}}, {"job_id": "100003009047465", "location_code": "hk", "company": "The Hong Kong Polytechnic University", "job_title": "Project Assistant / Project Administrative Assistant", "description": "Responsibilities\n\nThe appointee will be involved in accreditation and assessment exercises in vocational area, and conduct projects related to quality assurance of education and training programmes. Major duties may include conducting accreditation and assessment exercises; assisting in relevant research and consultancy work, liaison with institutions, government bureaux, and professional bodies; supporting the development of guidelines and procedures, and other internal and external development activities; and management of databases.\n\n\nRequirements\n\nApplicants should hold a first degree comparable to HKQF Level 5, preferably with a post-graduate qualification at HKQF Level 6 or above, with at least 5 years of post-qualification relevant work experience, preferably in education, training or quality assurance.\u00a0 We are looking for an individual who has a good understanding of the education system in Hong Kong; good analytical, project management, presentation, interpersonal and communication skills; and excellent written and spoken English and Chinese, including Putonghua.\u00a0 Being proactive, reflective, independent as well as a team player is essential. Possessing good ICT knowledge, understanding of international qualification standards and exposure to accreditation/quality assurance work in the vocational sector would be an advantage.\n\n\nConditions of Service and Application Procedures\n\nInitial appointment will normally be made on a two-year contract subject to renewal.\u00a0 We offer competitive salary commensurate with qualifications and experience, contract-end gratuity, plus fringe benefits including annual leave, medical and dental benefits.\u00a0\n\nApplicants are invited to apply by letter including a short narrative on how you can add value to HKCAAVQ together with your CV, and stating present and expected salary.\u00a0 Please send your application quoting the relevant reference number to the Assistant Executive Manager (Human Resources) either by Apply Now\u00a0or by post to HKCAAVQ, 10 Siu Sai Wan Road, Chai Wan, Hong Kong no later than 28 January 2022.\n\nPersonal data collected will be treated in the strictest confidence and only be used for recruitment purposes.\n\nFor more information on HKCAAVQ, please visit www.hkcaavq.edu.hk.", "employment_types": ["Full Time"], "selling_points": [], "locations": ["Not Specified"], "categories": ["Admin & HR", "Clerical / Admin Staff", "Personal / Executive Assistant", "Education", "Others"], "post_time": "2022-01-14T03:11:19Z", "salary": {"currency": null, "max": null, "min": null, "period": null, "term": null}, "salary_visible": false, "title_keywords": ["administrative assistant", "project assistant"], "responsibilities": ["management", "guidelines", "quality", "procedures", "databases"], "requirements": {"degrees": ["degree"], "majors": [], "languages": ["putonghua", "english", "chinese"], "language_level": ["excellent"], "hard_skills": ["no", "project management", "plus", "wan"], "soft_skills": ["communication skills", "confidence", "independent", "presentation", "project management", "team player", "proactive", "interpersonal"], "languages_combined": [{"language": "putonghua", "language_level": ["excellent"]}, {"language": "english", "language_level": ["excellent"]}, {"language": "chinese", "language_level": ["excellent"]}]}, "experience_required": {"duration": ["at least 5 years"], "field": ["post-qualification", "training", "education", "medical", "quality assurance"]}}, {"job_id": "100003009047881", "location_code": "hk", "company": "The University of Hong Kong", "job_title": "Clerk I/II (2 posts) (holding the functional title of Senior Executive Assistant/ Executive Assistan", "description": "Responsibilities\n\nProvide professional consultation, such as introducing course details and proposing suitable course packages, to prospective customers\nMaintain good customer relationship\nManage the centre\u2019s class schedule\nHandling walk-in inquiries, calls, and customer follow-ups\nMaintain the centre\u2019s appearance\nProvide assistance to teachers when needed\n\n\u00a0Requirements\n\nMust have passion towards young children.\nForm 6 graduate or above\nFresh graduates are welcome, but 1-2 years working experience preferred\nCheerful, caring, patient, responsible and initiative.\nAble to multi-task & work under pressure\nComputer literate, especially in Microsoft Office (Word & Excel)\nFluent in Cantonese and English, Mandarin is an advantage\n\nRemuneration packages\n\n5 days working & long lunch hour\nProvide all round training\nGreat chance of promoting to be a partner\n\nWorking hours\n\n5 days working per week (including Saturday)\n10:00am \u2013 7:30pm\u00a0(4 days between Monday-Friday) and\u00a09:00am \u2013 6:30pm (Saturday)", "employment_types": ["Full Time"], "selling_points": ["Applicants should possess a good Bachelor\u2019s degree", "at least 2 years\u2019 work experience", "in tertiary institutions or in the education"], "locations": ["Pok Fu Lam"], "categories": ["Education", "Others"], "post_time": "2022-01-14T04:07:17Z", "salary": {"currency": null, "max": null, "min": null, "period": "monthly", "term": null}, "salary_visible": false, "title_keywords": ["clerk", "senior executive assistant", "executive"], "responsibilities": ["maintain", "schedule", "provide assistance"], "requirements": {"degrees": [], "majors": [], "languages": ["cantonese", "english", "mandarin"], "language_level": ["advantage", "fluent"], "hard_skills": ["excel", "word", "microsoft office"], "soft_skills": ["cheerful", "multi-task", "responsible", "patient", "initiative", "work under pressure"], "languages_combined": [{"language": "cantonese", "language_level": ["fluent"]}, {"language": "english", "language_level": ["fluent"]}, {"language": "mandarin", "language_level": ["advantage"]}]}, "experience_required": {"duration": ["1-2 years"], "field": []}}, {"job_id": "100003009042763", "location_code": "hk", "company": "City University of Hong Kong", "job_title": "Executive Officer I/II in the Centre for Judicial Education and Research [Ref. B/512/03]", "description": "Job Description: Education Consultant\n\nOrganization\n\nAssurance aims to help students make blossom and make the most out of high school. Assurance is headquartered in Hong Kong and maintains offices in Shenzhen and Shanghai. All of our consultants are from top universities such as Wharton, Harvard, UPenn and UChicago. For more information, please visit www.assuranceedu.com.\n\nPosition\n\nEducation Consultant, Full Time\n\nLocation\n\nCauseway Bay\n\nHours\n\n5 days work week\nTuesday to Saturday\n9.30am to 6.30pm\n\nResponsibilities\n\nProvide administrative support\nHandle correspondence\nManage school application forms\nAssist in seminars and events\n\nRequirements\n\nFluency in Cantonese, English and Mandarin\nProficient in Word, Excel, and word processing in English & Chinese\n1 year of experience as administrative assistant/secretary\nDegree holder in any discipline\n\nCompensation\n\nWe offer a starting salary of $15000-$17,000/month. Please state your expected salary.\n\nApplication\n\nInterested parties please submit your resume and cover letter to Ms. Tiffany Cheung at admin @ AssuranceEDU.com\u00a0with \u201c[Name] Assurance Recruitment]\u201d in the email title. Please state your expected salary.", "employment_types": ["Full Time", "Contract"], "selling_points": ["Bachelor\u2019s degree", "Relevant working experience", "Gratuity, leave, medical and dental schemes"], "locations": ["Wong Tai Sin Area"], "categories": ["Admin & HR", "Clerical / Admin Staff", "Personal / Executive Assistant", "Education", "Others"], "post_time": "2022-01-13T18:54:36Z", "salary": {"currency": null, "max": null, "min": null, "period": "monthly", "term": null}, "salary_visible": false, "title_keywords": ["executive officer"], "responsibilities": ["provide administrative support"], "requirements": {"degrees": ["degree holder"], "majors": [], "languages": ["cantonese", "english", "chinese", "mandarin"], "language_level": ["fluency", "proficient"], "hard_skills": ["excel", "word processing", "word"], "soft_skills": [], "languages_combined": [{"language": "cantonese", "language_level": ["fluency"]}, {"language": "english", "language_level": ["fluency", "proficient"]}, {"language": "chinese", "language_level": ["fluency", "proficient"]}, {"language": "mandarin", "language_level": ["fluency"]}]}, "experience_required": {"duration": ["1 year"], "field": ["administrative"]}}, {"job_id": "100003009053550", "location_code": "hk", "company": "Champion Goal Education Limited", "job_title": "\u6559\u80b2\u4e2d\u5fc3\u8aa0\u8058\u5b78\u751f\u4e8b\u52d9\u52a9\u7406", "description": "Responsibilities:\n\nDevelop and edit courseware to support our continuous growth of businesses\nReview and update our existing courseware\nProvide pedagogical support to our centers\nPerform ad hoc duties as assigned by management \u00a0\u00a0\n\nRequirements:\n\nUniversity graduate or above in Mathematics or other Science subjects with strong Mathematical background\nExperiences or qualification in Mathematics Education is highly preferable\nGood computer knowledge\nGood communication and organization skills\nGood team player\nAble to work independently\nAttention to details", "employment_types": ["Full Time"], "selling_points": [], "locations": ["Sham Shui Po"], "categories": ["Education", "Tutor / Instructor", "Others", "Others", "Others"], "post_time": "2022-01-17T07:08:50Z", "salary": {"currency": null, "max": null, "min": null, "period": "monthly", "term": null}, "salary_visible": false, "title_keywords": [], "responsibilities": ["ad hoc duties", "management", "review", "develop"], "requirements": {"degrees": ["university graduate or above"], "majors": ["mathematics", "science"], "languages": [], "language_level": [], "hard_skills": [], "soft_skills": ["good team player", "work independently", "communication", "attention to details", "organization skills"], "languages_combined": []}, "experience_required": {"duration": [], "field": ["education"]}}, {"job_id": "100003009053601", "location_code": "hk", "company": "The Church of Christ in China Heep Woh Primary School", "job_title": "\u8cc7\u8a0a\u79d1\u6280\u6559\u5b78\u52a9\u7406 (\u5168\u8077)", "description": "We are looking for a number of enthusiastic people to be part of our admissions teams supporting our applicants and programme teams, working collaboratively in accordance with good customer care principles. Alongside processing applications and acting as a first point of contact for queries, you will also support admissions events (either on-campus or virtual), interviews, and confirmation.\n\nSuccessful candidates will have experience of working with administrative processes in a customer facing office environment. The roles require applicants who thrive in a busy team environment who enjoy interacting and supporting a wide range of people and who are flexible and responsive to customer needs. Strong organisational and accuracy skills are essential alongside the ability to adapt to changing systems and platforms and work and communicate successfully across, emails, face to face and virtual channels.\n\nJob responsibilities\n\nTo monitor, implement and converting all enquiries to meet the KPIs\nTo build relations with enquirers, follow up and conversion\nTo offer\u00a0 responsive and professional services to all enquirers\nTo provide responsive consultations with prospective students\n\nTo manage databases of enquirers efficiently and effectively\n\nTo proactively support the promotional campaigns\nTo plan, monitor and implement all recruitment related activities\n\nTo prepare, analyse, and recommend necessary recruitment reporting\n\nTo support Marketing team to prepare promotional materials\n20 days annual leave, 5 days work, fringe benefits\u00a0 and working with global teams.", "employment_types": ["Full Time"], "selling_points": [], "locations": ["Mong Kok"], "categories": ["Education", "Tutor / Instructor", "Others", "Others", "Others"], "post_time": "2022-01-17T07:13:26Z", "salary": {"currency": null, "max": null, "min": null, "period": "monthly", "term": null}, "salary_visible": false, "title_keywords": [], "responsibilities": ["reporting", "systems", "monitor", "teams", "promotional materials", "recruitment", "contact", "databases", "kpis", "plan", "administrative processes", "analyse"], "requirements": {"degrees": [], "majors": [], "languages": [], "language_level": [], "hard_skills": ["processing", "databases"], "soft_skills": ["flexible", "responsive", "enthusiastic"], "languages_combined": []}, "experience_required": {"duration": [], "field": ["administrative"]}}, {"job_id": "100003009052555", "location_code": "hk", "company": "LinkedU Overseas Education Limited", "job_title": "Academic Tutors (Part-Time/ Freelance)", "description": "Project Associate in the President\u2019s Office (2 posts) (Ref.:511632) (to commence as soon as possible for one year)\n\nApplicants should have a recognised Bachelor\u2019s degree in any discipline.\u00a0 They should be self-motivated with a strong sense of responsibility and positive attitude and be able to work independently and on a multi-tasking basis.\u00a0 They should also have a good command of written and spoken English and Chinese, as well as strong communication and interpersonal skills.\u00a0 A high level of computer proficiency would be an advantage.\n\nThe appointee(s) will assist in organizing events by coordinating with internal and external parties, preparing meeting documents, consolidating publicity materials, compiling data and providing on-site support, and will perform any other duties as assigned.\u00a0 Shortlisted candidates will be invited to attend a written test and an interview.\n\nApplicants should be Hong Kong residents and fresh graduates.\u00a0 Existing staff of the University need not apply.\n\nThe University only accepts online application for the above post(s).\u00a0 Applicants should apply online at the University's careers site (https://jobs.hku.hk) and upload an up-to-date C.V.\u00a0 Review of applications will commence as soon as possible and continue until February 28, 2022, or until the post is filled, whichever is earlier.\n\nThe University is an equal opportunities employer and\nis committed to equality, ethics, inclusivity, diversity and transparency", "employment_types": ["Part Time", "Freelance"], "selling_points": ["Competitive hourly rate", "Flexible working schedule", "Admissions experiences in top UK schools"], "locations": ["Central"], "categories": ["Education", "Tutor / Instructor", "Others"], "post_time": "2022-01-17T03:24:31Z", "salary": {"currency": null, "max": null, "min": null, "period": "hourly", "term": null}, "salary_visible": false, "title_keywords": [], "responsibilities": ["any other duties", "data", "review", "internal and external parties", "communication"], "requirements": {"degrees": ["degree", "bachelor"], "majors": [], "languages": ["english", "chinese"], "language_level": ["good command"], "hard_skills": ["c"], "soft_skills": ["self-motivated", "work independently", "sense of responsibility", "positive attitude", "committed", "multi-tasking", "communication and interpersonal skills"], "languages_combined": [{"language": "english", "language_level": ["good command"]}, {"language": "chinese", "language_level": ["good command"]}]}, "experience_required": {"duration": [], "field": []}}, {"job_id": "100003009052565", "location_code": "hk", "company": "LinkedU Overseas Education Limited", "job_title": "Consultant (UK Boarding School & University)", "description": "Clerk I/II (holding the functional title of Senior Executive Assistant/Executive Assistant) (2 posts) in the Faculty of Law (Ref.: 511489) (to commence as soon as possible, on a two-year fixed-term basis, with contract-end gratuity and University contribution to a retirement benefits scheme, totalling up to 10% of basic salary, with the possibility of renewal)\u00a0\u00a0\n\nApplicants should possess a good Bachelor\u2019s degree, with at least 2 years\u2019 work experience preferably in tertiary institutions or in the education sector.\u00a0\u00a0Non-degree holders with substantial relevant working experiences will also be considered.\u00a0 They must be a good team player; self-motivated with excellent organizational and interpersonal skills; attentive to details; able to work independently and under pressure to meet tight deadlines and able to prioritise multi-tasks efficiently. They should have a good command of written and spoken English and Chinese; and IT proficiency skills including MS Word and MS Excel.\u00a0 Knowledge of Putonghua would be an advantage but not a must.\u00a0 Those with less experience and/or lower qualification may be appointed as Clerk II.\u00a0\n\nThe appointees will provide administrative and clerical support to the Faculty Office, mainly in the area of postgraduate and/or undergraduate programmes and perform any other duties as assigned. \u00a0They will be responsible for handling admissions, examinations and student affairs, performing data entry, coordinating events and activities organized by the Faculty Office. Shortlisted candidates will be invited to attend a written test and an interview.\u00a0\n\nA highly competitive salary commensurate with qualifications and experience will be offered, in addition to annual leave and medical benefits.\u00a0\n\nThe University only accepts online application for the above post.\u00a0 Applicants should apply online at the University\u2019s careers site (https://jobs.hku.hk) and upload an up-\u00adto\u00ad-date C.V.\u00a0 Review of applications will commence as soon as possible and continue until\u00a0January 28, 2022, or until the post is filled, whichever is earlier.\u00a0\n\nThe University is committed to diversity and inclusivity. The Faculty of Arts\nexpressly encourages qualified persons from all genders to apply.", "employment_types": ["Full Time"], "selling_points": ["Fast-growing overseas education industry", "Opportunity to learn overseas property market", "Positive, growth-mindset with willingness to learn"], "locations": ["Central"], "categories": ["Education", "Others", "Sales, CS & Business Devpt", "Direct Sales"], "post_time": "2022-01-17T03:25:52Z", "salary": {"currency": null, "max": null, "min": null, "period": "monthly", "term": null}, "salary_visible": false, "title_keywords": ["consultant"], "responsibilities": ["any other duties", "performing data entry", "administrative and clerical support"], "requirements": {"degrees": ["degree", "bachelor"], "majors": [], "languages": ["putonghua", "english", "chinese"], "language_level": ["advantage", "good command"], "hard_skills": ["ms excel", "basic", "scheme", "ms word"], "soft_skills": ["organized", "good team player", "self-motivated", "work independently", "under pressure", "attentive to details", "meet tight deadlines", "multi-tasks", "organizational", "responsible", "prioritise", "interpersonal skills"], "languages_combined": [{"language": "putonghua", "language_level": ["advantage"]}, {"language": "english", "language_level": ["good command"]}, {"language": "chinese", "language_level": ["good command"]}]}, "experience_required": {"duration": ["at least 2 years"], "field": ["education"]}}, {"job_id": "100003009054059", "location_code": "hk", "company": "Hong Kong Baptist University", "job_title": "\u5ba2\u6236\u670d\u52d9\u4e3b\u7ba1 / \u5ba2\u6236\u670d\u52d9\u52a9\u7406 (\u4e2d\u91ab\u85e5\u8a3a\u6240) (PR0334/20-21)", "description": "Duties\nProvide administrative assistance to the Centre Director and maintain daily operation of the Centre;\nProvide assistance in the logistics arrangements of Centre\u2019s activities, including ceremonies/conferences/lecturers/seminars/visits;\nConduct market analysis;\nManage social media platforms and update website;\nDesign online/printing promotional materials;\nPrepare reports/speeches/web stories/write up for media publicity; and\nPerform any other duties as assigned.\nRequirements\n\nA Bachelor\u2019s degree with relevant working experience. Excellent command of written and spoken English and Chinese (including Putonghua); good organizational, communication and interpersonal skills; strong sense of responsibility with initiatives and ability to work independently are required. Prior experience in tertiary education institutions would be an advantage.\n\nCandidates with more than 5 years\u2019 relevant experience may be considered for appointment as Executive Officer I.\n\nShortlisted candidates will be invited for a written test.\n\nSalary and Conditions of Service\n\nRemuneration package will be highly competitive, commensurate with qualifications and experience.\u00a0 Appointment will be made on a fixed-term contract; fringe benefits include gratuity, leave, medical and dental schemes.\n\nInformation and Application\n\nFurther information on the posts and the University is available at\u00a0http://www.cityu.edu.hk, or from the Human Resources Office, City University of Hong Kong, Tat Chee Avenue, Kowloon Tong, Hong Kong [Fax : 2788 1154 or 3442 0311].\u00a0\n\nTo apply, please submit an online application at\u00a0http://jobs.cityu.edu.hk.\u00a0The closing date is 28 January 2022.\u00a0\u00a0Applications will receive full consideration and only shortlisted applicants will be contacted.\u00a0 The University\u2019s privacy policy is available on the homepage.\n\nCity University of Hong Kong is an equal opportunity employer. We are committed to the principle of diversity. Personal data provided by applicants will be used for recruitment and other employment-related purposes.\n\nWorldwide recognition ranking #53 (QS survey 2022), and #4 among top 50 universities under age 50 (QS survey 2021); #1 in the World\u2019s Most International Universities (THE survey 2020); #1 in Engineering/Technology/Computer Sciences in Hong Kong (ARWU survey 2016); and #1 Business School in Asia-Pacific region (UT Dallas survey 2019).", "employment_types": ["Full Time"], "selling_points": ["\u9808\u5b8c\u6210\u4e2d\u5b78\u8ab2\u7a0b", "\u8a3a\u6240\u5de5\u4f5c\u5982\u767b\u8a18\u3001\u63a5\u5f85\u3001\u8f38\u5165\u8655\u65b9\u3001\u6536\u8cbb\u3001\u8655\u7406\u75c5\u4eba\u8a18\u9304\u3001\u8f14\u52a9\u5354\u8abf\u898b\u7fd2\u5b78\u54e1\u3001\u5354\u52a9\u8655\u7406\u8a3a\u6240\u5167\u90e8\u4e00\u822c\u4e8b\u52d9\u53ca\u6587\u66f8", "\u63a5\u5f85\u53ca\u9867\u5ba2\u670d\u52d9\u5de5\u4f5c\u7d93\u9a57"], "locations": ["Kowloon City"], "categories": ["Education", "Others", "Medical Services", "Others", "Public / Civil", "Others"], "post_time": "2022-01-17T08:15:47Z", "salary": {"currency": null, "max": null, "min": null, "period": "monthly", "term": null}, "salary_visible": false, "title_keywords": ["\u5ba2\u6236\u670d\u52d9\u52a9\u7406"], "responsibilities": ["any other duties", "logistics arrangements", "daily operation", "social media platforms", "website", "design", "conferences", "maintain", "administrative assistance", "market analysis", "promotional materials", "prepare reports", "provide assistance"], "requirements": {"degrees": ["degree", "bachelor"], "majors": [], "languages": ["putonghua", "english", "chinese"], "language_level": ["excellent"], "hard_skills": [], "soft_skills": ["organizational", "work independently", "communication and interpersonal skills", "sense of responsibility"], "languages_combined": [{"language": "putonghua", "language_level": ["excellent"]}, {"language": "english", "language_level": ["excellent"]}, {"language": "chinese", "language_level": ["excellent"]}]}, "experience_required": {"duration": ["5 years"], "field": ["relevant experience", "relevant working experience", "education"]}}, {"job_id": "100003009050061", "location_code": "hk", "company": "The Hong Kong University of Science and Technology", "job_title": "Officer (Technical Support)(Job ID: 7064)", "description": "\n\u6559\u80b2\u4e2d\u5fc3\u8aa0\u8058\u5b78\u751f\u4e8b\u52d9\u52a9\u7406:\n\u5de5\u4f5c\u5730\u9ede: \u8354\u679d\u89d2\n\u5de5\u4f5c\u6642\u9593: \u661f\u671f\u4e00\u81f3\u4e94\u4e0a\u53489\u664215\u5206\u81f3\u4e0b\u53487\u664230\u5206\u53ca\u661f\u671f\u516d\u4e0a\u53489\u664215\u5206\u81f3\u4e0b\u53485\u664230\u5206, \u4f11\u606f\u65e5\u5b9a\u65bc\u661f\u671f\u4e00\u81f3\u516d\u5176\u4e2d\u4e00\u65e5\u53ca\u661f\u671f\u65e5\u3002\n\u4e94\u5929\u5de5\u4f5c,\u9280\u884c\u5047\u671f\u3002\n\u8077\u8cac:\n\u2022 \u5354\u52a9\u9ede\u540d\u53ca\u5b78\u751f\u9032\u51fa\u73ed\u623f;\n\u2022 \u5354\u52a9\u4e2d\u5fc3\u7d93\u7406\u8655\u7406\u4e00\u822c\u884c\u653f\u5de5\u4f5c;\n\u2022 \u5354\u52a9\u5176\u4ed6\u5de5\u4f5c\n\u8981\u6c42:\n\u2022 \u6709\u76f8\u95dc\u5de5\u4f5c\u7d93\u9a57\u5c07\u7372\u512a\u5148\u8003\u616e\n\u2022 \u61c2\u82f1\u8a9e\u53ca\u666e\u901a\u8a71\n\u2022 \u5c0d\u5de5\u4f5c\u6709\u71b1\u8aa0\u3001\u4e3b\u52d5\u6709\u79ae\u3001\u7a4d\u6975\u52e4\u596e\u3001\u5bcc\u8cac\u4efb\u5fc3\u3002\n\u53ef\u5373\u6642\u4e0a\u73ed\u512a\u5148\n\u6709\u610f\u8005\u8acb\u5c07\u500b\u4eba\u5c65\u6b77\u3001\u8981\u6c42\u85aa\u91d1\u3001\u53ef\u5230\u8077\u65e5\u671f\u96fb\u90f5\u81f3 Apply Now\n\u6c92\u6709\u8a3b\u660e\u8981\u6c42\u85aa\u91d1\u6055\u4e0d\u56de\u8986\n\n", "employment_types": ["Full Time"], "selling_points": ["Liaise with laboratory personnel", "Collect data, digitize records and maintain data", "Provide IT and AutoCAD support to the team"], "locations": ["Sai Kung"], "categories": ["Admin & HR", "Clerical / Admin Staff", "Education", "Others"], "post_time": "2022-01-14T09:42:36Z", "salary": {"currency": null, "max": null, "min": null, "period": "monthly", "term": null}, "salary_visible": false, "title_keywords": ["officer"], "responsibilities": [], "requirements": {"degrees": [], "majors": [], "languages": [], "language_level": [], "hard_skills": [], "soft_skills": [], "languages_combined": []}, "experience_required": {"duration": [], "field": []}}, {"job_id": "100003009043946", "location_code": "hk", "company": "HKU School of Professional & Continuing Education", "job_title": "Programme Executive in Chinese Medicine Subject Group in the College of Life Sciences and Technology", "description": "Role & Responsibilities:\n\n\nPlan and prepare well-structured, clearly presented lessons appropriate to the abilities of all Primary/Secondary students and the ESL curriculum being taught\nConduct co-teaching and planning with\u00a0the Classroom Teacher\nLiaise with the Class Teacher and Learning Support where a student may have special educational\u00a0needs and with the Counselling Team if a\u00a0student is experiencing pastoral difficulties\nPromote high standards in the use of English as the common language and help develop English for\u00a0Academic Progress (hothousing)\nUse fun and interactive approaches to help students improve their English oral skills\nAssess, record and monitor the progress of all students according to curriculum guidelines in order to provide\u00a0accurate information to class teachers and parents in a variety of forms, as and when necessary\nProvide high-quality, accurate, constructive and targeted information to parents at Parent Teacher Conferences, in\u00a0school reports, incidental meetings and communications\nBe involved in new responsibilities within the department as part of an ongoing process of professional\u00a0development\nMaintain order and discipline of classes\nUndertake other reasonable duties as requested by the ESL Co-ordinator, Mile Post Leader, Deputy Head or members of the Senior Leadership Team and any duties that the Principal deems necessary for the effective operation of the school\nExecute other non-teaching duties, such as preparing and improving teaching materials, \u00a0maintaining materials and resources as needed\nRequirements:\n\nBachelor\u2019s degree and a Post Graduate\u00a0Diploma/Certificate\u00a0in Education\u00a0\u00a0\nTeaching experience within an international school\u00a0setting preferred.\u00a0\nGood interpersonal, communication and presentation skills\nFamiliarity with the British National Curriculum of England ( plus Cambridge/IPC) \u00a0as appropriate\nProficiency in Google Classroom environment and familiarity with various educational software and apps\u00a0\nAble to assess pupils\u2019 interests, needs and developments\nOpen, proactive, patient and caring\nSensitive to the demands of working in a cross-cultural setting and a team player\nExcellent interpersonal and communication skills\u00a0\nParticipate positively in departmental meetings, follow policies and generally contributing to the effective and efficient running of the department\nMust be able to work legally in HK (HK permanent resident, holder of relevant visa)\n\nHOW TO APPLY:\nInterested candidates please send your full CV by clicking \"Apply Now\". Only shortlisted candidates will be contacted.\n\n\n\n\nAll personal data collected will be used for recruitment purposes only and will be kept strictly confidential.", "employment_types": ["Full Time", "Contract"], "selling_points": ["support programme management, development", "mentor and supervise subordinate staff", "liaise with external professional bodies"], "locations": ["Not Specified"], "categories": ["Admin & HR", "Clerical / Admin Staff", "Education", "Others", "Others", "Others"], "post_time": "2022-01-13T02:33:06Z", "salary": {"currency": null, "max": null, "min": null, "period": "monthly", "term": null}, "salary_visible": false, "title_keywords": ["executive"], "responsibilities": ["maintaining", "guidelines", "monitor", "quality", "develop", "conferences", "maintain", "reports", "plan", "liaise with", "teaching materials", "planning"], "requirements": {"degrees": ["certificate", "diploma", "degree", "bachelor"], "majors": [], "languages": [], "language_level": [], "hard_skills": ["plus"], "soft_skills": ["efficient", "communication skills", "communication", "presentation skills", "sensitive to", "patient", "team player", "proactive", "interpersonal"], "languages_combined": []}, "experience_required": {"duration": [], "field": ["teaching"]}}, {"job_id": "100003009052562", "location_code": "hk", "company": "LinkedU Overseas Education Limited", "job_title": "Wordpress Developer (Part-Time / Freelance)", "description": "\n\u00a0 \u2022 \u4e2d\u516d\u6216\u526f\u5b78\u4f4d\u7a0b\u5ea6\uff0c\u54c1\u683c\u7aef\u6b63\uff0c\u505a\u4e8b\u52e4\u5feb\n\u2022 \u826f\u597d\u4e2d\u82f1\u8a9e\u6e9d\u901a\u6280\u5de7\n\u2022 \u5354\u52a9\u652f\u63f4\u5b78\u751f\u904b\u7528\u5e73\u677f\u96fb\u8166\u7b49\u96fb\u5b50\u5b78\u7fd2\u5de5\u5177\n\u2022 \u5354\u52a9\u5b78\u6821\u6e96\u5099\u591a\u5a92\u9ad4\u8cc7\u8a0a\u53ca\u96fb\u5b50\u5b78\u7fd2\u6559\u6750\n\u2022 \u5354\u52a9\u96fb\u8166\u5668\u6750\u63a5\u99c1\u3001\u7dad\u8b77\u96fb\u8166\u8a2d\u5099\u53ca\u8edf\u4ef6\n\u2022 \u652f\u63f4\u6559\u5e2b\u5728\u61c9\u7528\u8cc7\u8a0a\u79d1\u6280\u65bc\u6559\u5b78\u53ca\u884c\u653f\u5de5\u4f5c\n\u2022 \u85aa\u91d1\u9762\u8b70\n\n", "employment_types": ["Part Time", "Temporary"], "selling_points": ["Proficient in Front-End & Back-End Web Programming", "Familiar with SEO is a plus", "fast-growing overseas education industry"], "locations": ["Central"], "categories": ["Education", "Others", "Information Technology (IT)", "IT - Webmaster / SEO", "Software Development"], "post_time": "2022-01-17T03:25:18Z", "salary": {"currency": null, "max": null, "min": null, "period": "hourly", "term": null}, "salary_visible": false, "title_keywords": ["developer"], "responsibilities": [], "requirements": {"degrees": [], "majors": [], "languages": [], "language_level": [], "hard_skills": [], "soft_skills": [], "languages_combined": []}, "experience_required": {"duration": [], "field": []}}, {"job_id": "100003009037558", "location_code": "hk", "company": "Hong Kong Examinations and Assessment Authority", "job_title": "Officer \u2013 Examinations Administration (Ref: IP/01/809)", "description": "\n\nProvide one-to-one tutorials focusing on UK Boarding School and G5 University admissions preparation\nTutors will be assigned to teach one or more subject case(s) depending on academic qualifications:\n(1) Clinical Sciences (Medicine, Dentistry, Physiotherapy, etc.);\n(2) Boarding School assessment (UKiset, CAT4, Common Entrance);\n(3) Interview training;\n(4) Law (LNAT, CLT);\n(5) Oxbridge admissions (test and interview preparation);\n(6) English proficiency test (IELTS)\nRequirements:\n\nGraduated from UK top boarding schools/ G5 Universities/ UK Medical/ Dental/ Law Schools\nProfound knowledge in UK university admissions tests such as LNAT, UCAT, etc.\nAt least Grade A/9 in GCSE/A-Level, or 7 in IB HL among science (Maths, Biology, Chemistry, etc.) and humanity subjects (economics, psychology, etc.)\nSound knowledge of the UK education system and pathway\nPassionate and patient in teaching students with high academic attainment\nExcellent communication skills and work ethics\nDeliver tutorial according to LINKEDU expectation\nAs a Leading Overseas Education Consultancy in Hong Kong, we are expanding our tutoring team to provide students with comprehensive admissions training for UK top boarding schools and prestigious universities. We are looking for academic qualified and driven tutors to join our energetic team.\n\nTo apply, please send your CV by clicking APPLY NOW. All information collected will be\u00a0handled under confidentiality and used for recruitment purposes only.", "employment_types": ["Full Time", "Contract"], "selling_points": [], "locations": ["Not Specified"], "categories": ["Admin & HR", "Clerical / Admin Staff", "Others", "Education", "Others"], "post_time": "2022-01-11T03:06:58Z", "salary": {"currency": null, "max": null, "min": null, "period": null, "term": null}, "salary_visible": false, "title_keywords": ["officer"], "responsibilities": ["communication", "recruitment"], "requirements": {"degrees": [], "majors": [], "languages": ["english"], "language_level": ["proficiency"], "hard_skills": [], "soft_skills": ["passionate", "communication skills", "comprehensive", "patient", "energetic", "driven"], "languages_combined": [{"language": "english", "language_level": ["proficiency"]}]}, "experience_required": {"duration": [], "field": []}}, {"job_id": "100003009051133", "location_code": "hk", "company": "NTK Academic Group Limited", "job_title": "Customer Service Representative", "description": "Job Description:\u00a0\n\nTeach Mathematics in small group of children from age 3-16 with material developed by the education center\nAssist to teach English class\nCommunicate with parents and follow up with students' progress based on their individual performance\nAssist to handle general administration.\n\nRequirement:\n\nDegree holder, fresh graduates will also be considered\nDedicated, mature, independent & with good communication skills\nFriendly, creative, patient & love working with young children\nPreferably to possess relevant teaching experience\nWilling to working on Saturdays\n\nWe offer:\n\n51/2 working days in a week\nPaid annual leave\nMedical Insurance\n\nFor interested parties, please send your resumes along with your expected salary and available date\n(All information provided will only be used for recruitment related purpose.)", "employment_types": ["Full Time", "Permanent"], "selling_points": ["5 days work, fixed schedule", "Discretionary Bonus, Monthly Incentive", "Excellent promotion opportunity"], "locations": ["Causeway Bay"], "categories": ["Sales, CS & Business Devpt", "Customer Service - Supervisor / Officer", "Education", "Others"], "post_time": "2022-01-15T03:10:47Z", "salary": {"currency": null, "max": null, "min": null, "period": "monthly", "term": null}, "salary_visible": false, "title_keywords": ["customer service representative"], "responsibilities": ["communicate with parents", "administration"], "requirements": {"degrees": ["degree holder"], "majors": [], "languages": [], "language_level": [], "hard_skills": [], "soft_skills": ["communication skills", "independent", "mature", "friendly", "patient", "creative"], "languages_combined": []}, "experience_required": {"duration": [], "field": ["teaching"]}}, {"job_id": "100003009042186", "location_code": "hk", "company": "Lingnan University", "job_title": "Institutional Advancement Officer (Post Ref.: 21/273)", "description": "Job Responsibilities:\nProviding professional advice to prospective\u00a0students and /or parents on the most appropriate\u00a0study paths\nManaging students\u2019 applications and related procedures, such as Visa applications\nParticipate\u00a0and provide support in seminars, exhibitions\u00a0and events\nRespond to students\u2019 and parents\u2019 enquiries\u00a0\nMaintain an overall understanding of the overseas property market and make internal referrals when necessary\n\nJob Requirements:\n\nCandidates with UK educational background are highly preferred\nThe successful candidate should have a general\u00a0understanding of the UK educational system\n1-2 years or above working experience in the overseas education industry or other consultancy role\nBusiness proficient English and Cantonese\u00a0\nGood communication\u00a0and interpersonal skills\nResponsible, Organised, and detailed-oriented\nSelf-motivated and customer oriented", "employment_types": ["Full Time", "Contract"], "selling_points": ["Handling donation transactions", "Assisting in/ organising fundraising activities", "Collecting and compiling data of donors"], "locations": ["Tuen Mun Area"], "categories": ["Education", "Others"], "post_time": "2022-01-13T02:26:03Z", "salary": {"currency": null, "max": null, "min": null, "period": "monthly", "term": null}, "salary_visible": false, "title_keywords": ["institutional advancement officer"], "responsibilities": ["provide support", "maintain", "procedures"], "requirements": {"degrees": [], "majors": [], "languages": ["cantonese", "english"], "language_level": ["proficient"], "hard_skills": [], "soft_skills": ["self-motivated", "responsible", "communication and interpersonal skills", "organised", "detailed"], "languages_combined": [{"language": "cantonese", "language_level": ["proficient"]}, {"language": "english", "language_level": ["proficient"]}]}, "experience_required": {"duration": ["1-2 years"], "field": ["education"]}}, {"job_id": "100003009050128", "location_code": "hk", "company": "HKUE Limited", "job_title": "Assistant Programme Manager (Business Programmes)", "description": "Job Title:\u00a0\u00a0\u00a0\u00a0\u00a0\u00a0\u00a0\u00a0\u00a0\u00a0Officer (Technical Support)\nDepartment:\u00a0 \u00a0 \u00a0Campus Management Office\nJob ID:\u00a0 \u00a0 \u00a0 \u00a0 \u00a0 \u00a0 \u00a0\u00a07064\n\nJob Posting Details\n\nThe Office is looking for a person eager to learn on-the-job to join the Laboratory Services team.\u00a0 The appointee will carry out data collection to assist in the planning and execution of installation and maintenance of laboratory provisions.\n\nMajor responsibilities include but are not limited to the following:\u00a0\n\nLiaise with laboratory personnel\nCollect data, digitize records and maintain databases of furniture and services layouts\nProvide IT and AutoCAD support to the team\nApplicants should have a bachelor\u2019s degree in science or engineering disciplines.\u00a0 A good command of both spoken and written English and Chinese (including Putonghua) and proficiency in computer literacy are required.\u00a0 Applicants should also be highly organized, self-motivated, a team player and able to work independently.\u00a0 Knowledge of AutoCAD is preferred. (Duration: 1 year)\n\nFringe benefits including annual leave, medical and dental benefits will be provided where applicable.\u00a0\n\nApplication Procedure\nIn support of a green work environment, we accept applications submitted online only.\u00a0 To apply, please complete an online application form through the HKUST Careers website (https://hkustcareers.ust.hk) and return it online to the Human Resources Office on or before Friday, 28 January 2022.\u00a0 Applicants will receive an acknowledgement by email upon successful submission.\u00a0 We thank applicants for their interest, but advise that only shortlisted candidates will be notified of the result of the application.\n\n(Information provided by applicants will be used for recruitment and other employment-related purposes only.)\n\nHKUST is an equal opportunities employer and is committed to our core values of\ninclusiveness, diversity, and respect.", "employment_types": ["Full Time", "Permanent"], "selling_points": [], "locations": ["Mong Kok"], "categories": ["Admin & HR", "Administration / Operation Manager", "Clerical / Admin Staff", "Education", "Others"], "post_time": "2022-01-14T09:49:34Z", "salary": {"currency": null, "max": null, "min": null, "period": "monthly", "term": null}, "salary_visible": false, "title_keywords": ["manager", "assistant"], "responsibilities": ["installation", "management", "maintenance", "data", "technical support", "maintain", "data collection", "databases", "liaise with", "planning"], "requirements": {"degrees": ["degree", "bachelor"], "majors": ["science", "engineering"], "languages": ["putonghua", "english", "chinese"], "language_level": ["proficiency", "good command"], "hard_skills": ["id", "databases", "maintenance", "autocad"], "soft_skills": ["organized", "self-motivated", "work independently", "eager to learn", "computer literacy", "team player"], "languages_combined": [{"language": "putonghua", "language_level": ["proficiency", "good command"]}, {"language": "english", "language_level": ["proficiency", "good command"]}, {"language": "chinese", "language_level": ["proficiency", "good command"]}]}, "experience_required": {"duration": [], "field": []}}, {"job_id": "100003009054460", "location_code": "hk", "company": "Malvern College Hong Kong Limited", "job_title": "Chinese Supply/Substitute Teacher (IB PYP) (Mar - Apr 2022)", "description": "Job Responsibilities:\n\nManage company\u2019s social media platform and other online marketing tools.\nDeveloping concepts, graphics and layouts for\u00a0online & offline advertising materials.\nCreating innovative\u00a0concepts in line with integrated marketing campaigns.\nCollaborating with other departments in advertising materials (posters, website or leaflet) and academic materials (notes or other publications)\nResponsible for any ad-hoc duties as assigned by Senior Management\nAssist to handle daily office administration duties\n\nRequirements:\n\nDiploma in Graphic Design or related disciplines\nInterested in education field\nGood sense of marketing and graphic design skills\nHands on knowledge in computer graphics or video editing software such as Illustrator, Photoshop or iMovie / Final Cut Pro\nMulti-tasking and able to work under tight schedule\nFresh graduates are also welcome\nEnthusiasm, patient and outspoken person with excellent communication andinterpersonal skills;\nPunctual, responsible and highly self-motivated individual\nAble to work as part of a team\n\nWe are offering:\u00a0\n\nMonthly salary of $13,000 or above (negotiable) with attractive bonus scheme and annual leave\nTraining regarding online marketing\nFlexible working hours that matches your own life commitments\nWorking hours: 5 days a week including Saturday; Monday \u2013 Friday 11am-7pm, Saturday 10am-6pm\n\nInterested parties, please click \"Apply Now\" and attach your cover letter and full resume. Data collected will be used for recruitment purposes only.\nFor further information about For You Education Ltd, please visit our website:\u00a0www.foryouedu.com.hk.", "employment_types": ["Temporary"], "selling_points": ["PYP Chinese, Registered/Permitted Teacher", "Native Chinese, Fluent English", "Supply/Substitute teaching"], "locations": ["Tai Po Area"], "categories": ["Education", "Teacher", "Others"], "post_time": "2022-01-17T09:39:09Z", "salary": {"currency": null, "max": null, "min": null, "period": "hourly", "term": null}, "salary_visible": false, "title_keywords": ["teacher"], "responsibilities": ["graphics", "social media", "advertising", "leaflet", "developing", "website", "marketing campaigns", "ad-hoc duties", "office administration duties", "senior management"], "requirements": {"degrees": ["diploma"], "majors": ["related disciplines", "graphic design"], "languages": [], "language_level": [], "hard_skills": ["graphics", "final cut pro", "illustrator", "scheme", "video editing", "photoshop"], "soft_skills": ["flexible", "self-motivated", "responsible", "interested in", "outspoken", "communication", "multi-tasking", "hands on", "patient"], "languages_combined": []}, "experience_required": {"duration": [], "field": []}}, {"job_id": "100003009046719", "location_code": "hk", "company": "Autism Partnership Foundation Limited", "job_title": "Service Administrative Executive", "description": "\n\nHandle new development & maintenance to the company's WordPress website and service portals\nImplement appropriate and tidy codes and test them in various environments, enhance and/or modify them if necessary\nCarry out testing, bug fixing and troubleshooting\nConduct WordPress performance test and tuning\nCustom WordPress theme and plugins\nMonitor the performance of the website\nJob Requirements:\n\nDegree holder in Web design, web development or related technical disciplines\nProficient in web development on WordPress with minimum 2 years hands-on experience\nProven experience and understanding of responsive design\nKnowledge of front-end technologies including CSS3, JavaScript, HTML5, and jQuery\nKnowledge of back-end integration such as database, JSON API integration\nFamiliar with SEO tracking code installation (eg. GTM, GA, Facebook Pixel, etc.) will be a plus\nGood command of written Chinese and English", "employment_types": ["Full Time", "Permanent"], "selling_points": [], "locations": ["Ngau Tau Kok"], "categories": ["Admin & HR", "Clerical / Admin Staff", "Education", "Others", "HR Supporting Staff"], "post_time": "2022-01-13T23:58:58Z", "salary": {"currency": null, "max": null, "min": null, "period": "monthly", "term": null}, "salary_visible": false, "title_keywords": ["administrative executive"], "responsibilities": ["installation", "seo", "maintenance", "troubleshooting", "website", "testing", "design", "monitor the performance", "database", "facebook", "tracking"], "requirements": {"degrees": ["degree holder"], "majors": ["web design"], "languages": ["english", "chinese"], "language_level": ["good command"], "hard_skills": ["web design", "web development", "plus", "seo", "maintenance", "jquery", "wordpress", "javascript", "integration", "code", "facebook", "codes"], "soft_skills": ["hands-on", "responsive", "troubleshooting"], "languages_combined": [{"language": "english", "language_level": ["good command"]}, {"language": "chinese", "language_level": ["good command"]}]}, "experience_required": {"duration": ["minimum 2 years"], "field": ["development", "design"]}}, {"job_id": "100003009039164", "location_code": "hk", "company": "Hong Kong College of Technology", "job_title": "Administration Officer", "description": "Job Duties:\n(under supervision)\n- To monitor and update school databases / website / social media platforms\n- To assist / coordinate in the production of school publications and printed materials\n- To assist in the planning of digital marketing / student recruitment campaign\n- To provide operational support to the School events such as programme seminars and exhibitions\n- To provide administrative / logistic / editorial support to Communication & Development Team\n\u00a0and perform any other duties as assigned\nRequirements :\n- Degree holder preferably with 1-2 year working experience (Fresh graduate / those with less \u00a0experience will be considered for appointment as Assistant Officer)\n- Detail-oriented, dynamic, open-minded with good command of English and Chinese\n- Proactive, independent and have strong sense of responsibility\n- With an appropriate level of IT skill, preferably with knowledge in design software (eg. Photoshop, InDesign, Canva, etc)\n- Interest in art and art education, knowledge in web design or web editorial work preferred\n- Immediate available is preferred\nThe appointment is basically on full-time on one-year term, and is to be renewed subject to mutual agreements and operational needs.\nInterested parties please apply with your full C.V. and a completed HKAS005 Job Application Form, and send it together with a covering letter indicating your view on art education, your expected salary, and your available date for assuming duty (if applicable) by mail to Human Resources Department, Hong Kong Arts Centre, 8/F, 2 Harbour Road, Wanchai, Hong Kong, or by email. Please quote reference.\nApplication form can be downloaded from Hong Kong Art School website at\u00a0www.hkas.edu.hk\u00a0(https://www.hkas.edu.hk/wp-content/uploads/HKAS005_Job_Application_Form.pdf)\u00a0or picked up directly from the Enrolment Office of the Hong Kong Art School, Room 819, 8/F, Youth Square, 238 Chai Wan Road, Chai Wan, Hong Kong, during office hours.\nThe closing date for application is\u00a025 January 2022.\nOnly shortlisted candidates will be contacted. We are an equal opportunities employer.", "employment_types": ["Full Time"], "selling_points": ["Secretary", "Education", "Administration"], "locations": ["Not Specified"], "categories": ["Admin & HR", "Secretary", "Education", "Others", "Professional Services", "Translation"], "post_time": "2022-01-11T08:53:49Z", "salary": {"currency": null, "max": null, "min": null, "period": "monthly", "term": null}, "salary_visible": false, "title_keywords": ["administration officer"], "responsibilities": ["any other duties", "operational support", "social media platforms", "monitor", "website", "school events", "coordinate", "communication", "digital marketing", "recruitment", "databases", "planning"], "requirements": {"degrees": ["fresh graduate", "degree holder"], "majors": [], "languages": ["english", "chinese"], "language_level": ["good command"], "hard_skills": ["web design", "web", "indesign", "dynamic", "photoshop"], "soft_skills": ["independent", "sense of responsibility", "open-minded", "detail-oriented", "dynamic", "proactive"], "languages_combined": [{"language": "english", "language_level": ["good command"]}, {"language": "chinese", "language_level": ["good command"]}]}, "experience_required": {"duration": ["1-2 year"], "field": []}}, {"job_id": "100003009053619", "location_code": "hk", "company": "Gotendo Beauty and Healthcare Group Limited", "job_title": "\u5e97\u52d9\u52a9\u7406", "description": "Job Title:\u00a0Mathematics Teacher\n\nJob\u00a0roles\u00a0and\u00a0responsibilities:\nTo carry out the professional duties of a teacher as circumstances may require and in accordance with the school's policies under the direction of the Head of Secondary. To be an effective professional who demonstrates thorough curriculum knowledge, can teach and assess effectively and take responsibility for professional development.\n\nPlanning, Teaching and Class Management:\n\nTeach allocated students by planning their teaching to achieve progression of learning through:\n\n\nidentifying clear teaching objectives and specifying how they will be taught and assessed;\nsetting tasks which challenge students and ensure high levels of interest;\nsetting appropriate expectations;\nsetting clear targets, building on prior attainment;\nbe aware of and make provision for students who are SEN, G&T or who have other particular individual needs;\nproviding clear structures for lessons maintaining pace, motivation and challenge;\nmaking effective use of assessment and ensure coverage of programmes of study;\nensuring effective teaching and best use of available time;\nmaintaining discipline in accordance with the school's procedures and encouraging good practice with regard to punctuality, behaviour, standards of work and homework;\nusing a variety of teaching methods to:\n1.match approach to content, structure information, present a set of key ideas and use appropriate vocabulary\n2.use effective questioning, listen carefully to students, give attention to errors and misconceptions\n3.select appropriate learning resources and develop study skills through library, ICT and other sources;\n\nensuring students acquire and consolidate knowledge, skills and understanding appropriate to mathematics and numeracy;\nevaluating own teaching critically to improve effectiveness;\nensuring the effective and efficient deployment of classroom support;\nliaise with the Head of Department to ensure the implementation of department policy and best practice.\nMonitoring, Assessment, Recording, Reporting:\n\nassess how well learning objectives have been achieved and use them to improve specific aspects of teaching;\nmark and monitor students' work and set targets for progress;\nassess and record students' progress systematically and keep records to check work is understood and completed, monitor strengths and weaknesses, inform planning and recognise the level at which the student is achieving;\nundertake assessment of students as requested by examination bodies, departmental and school procedures;\nprepare and present informative reports to parents;\nundertake assessment of students and participate in the school\u2019s system reporting to parents.\nPastoral Duties:\n\nbe a Form Tutor to an assigned group of students;\npromote the general progress and well-being of individual students;\nliaise with the Pastoral Head to ensure the implementation of the school's pastoral\u00a0system;\nregister students, accompany them to assemblies, encourage their full attendance at all lessons and their participation in other aspects of school life;\nalert appropriate staff to problems experienced by students and make recommendations as to how these may be resolved;\ncommunicate, as appropriate, with parents of students and persons or bodies outside the school concerned with the welfare of individual students, after consultation with appropriate staff;\nteach PSHE according to school policy.\nOther Professional Requirements:\n\noperate at all times within the stated policies and practices of the school;\nknow matheamtics to enable effective teaching;\ntake account of wider curriculum developments;\nestablish\u00a0effective working relationships and set a good example through their presentation and personal and professional conduct;\nendeavour to give every child the opportunity to reach their potential and meet high expectations;\ncontribute to the corporate life of the school through effective participation in meetings and management systems necessary to coordinate the management of the school;\ntake part in marketing and liaison activities such as Open Days, Parents Teacher Conference, Options and other events;\ntake responsibility for own professional development and duties in relation to school policies and practices;\nliaise effectively with parents and governors.\nto be aware of and abide by all the School\u2019s policies, in particular safeguarding.\nto perform such other duties as may be required by the Head of Secondary.\nThis job description may be reviewed at the end of the academic year or earlier if necessary. In addition it may be amended at any time after consultation with you.\n\n\nHow to apply:\nInterested candidates please send your full CV by clicking \"Apply Now\".\u00a0 Only shortlisted candidates will be contacted.\n\nAll personal data collected will be used for recruitment purposes only and will be kept strictly confidential.", "employment_types": ["Full Time"], "selling_points": [], "locations": ["Kwun Tong"], "categories": ["Education", "Tutor / Instructor", "Others", "Others", "Others"], "post_time": "2022-01-17T07:15:06Z", "salary": {"currency": null, "max": null, "min": null, "period": "monthly", "term": null}, "salary_visible": false, "title_keywords": [], "responsibilities": ["make recommendations", "reporting", "management", "attendance", "ideas", "maintaining", "policies", "monitoring", "procedures", "implementation", "monitor", "develop", "improve effectiveness", "reports", "liaise with", "planning"], "requirements": {"degrees": [], "majors": [], "languages": [], "language_level": [], "hard_skills": [], "soft_skills": ["presentation"], "languages_combined": []}, "experience_required": {"duration": [], "field": []}}, {"job_id": "100003009048525", "location_code": "hk", "company": "College of Professional and Continuing Education", "job_title": "Project Associate (two posts) [Appointment period: eighteen months]", "description": "In this role we would like you to use your best efforts to:\n\nHelp create a happy environment where children love to come and learn\nOffer high level of customer service at centre, over the phone and through email/messenger platforms\nBuild and maintain great relationships with students, parents, teachers and admin colleagues\nHandle enquiries from prospective and existing students\nBe responsible for general admin duties\nAssist in ad hoc tasks and assignments\nOffer general support to admin and teaching teams\n\nAlthough full training will be provided, to be successful in this role, you should ideally have the following: \u00a0\n\nDiploma/degree - preferred, this job is very suitable for fresh graduate, but more important is your ability to learn and a positive attitude\nGood written and spoken communication skills in English, Cantonese and Mandarin\nSound PC skills including MS Word and Excel\nProbably the most important skill for this role is your ability to communicate well with your colleagues, parents and students.\nThe ability to use own initiative and display flexibility when dealing with encountering the unexpected\nStrong organisational skills\nAbility to work positively and confidently within a team or independently\nA Detail-oriented approach\nA mature, responsible and sensible outlook\n\nYour efforts will be rewarded as follows:\u00a0\n\nMonthly medical allowance;\nMonthly lifestyle allowance;\nMonthly bonus;\nPerformance bonus;\nGratuity;\nFree courses/discounts for colleagues with children;\nExcellent prospects for promotion and management training.\n\nWorking Location: Kowloon or Hong Kong Island", "employment_types": ["Full Time"], "selling_points": [], "locations": ["Kowloon City"], "categories": ["Admin & HR", "Clerical / Admin Staff", "Education", "Others"], "post_time": "2022-01-14T06:45:14Z", "salary": {"currency": null, "max": null, "min": null, "period": "monthly", "term": null}, "salary_visible": false, "title_keywords": ["associate"], "responsibilities": ["management", "ad hoc tasks", "teams", "communication", "handle enquiries", "maintain", "customer service", "general support"], "requirements": {"degrees": ["diploma", "degree", "fresh graduate"], "majors": [], "languages": ["cantonese", "english", "mandarin"], "language_level": ["good"], "hard_skills": ["excel", "pc skills", "outlook", "ms word"], "soft_skills": ["communication skills", "independently", "responsible", "mature", "detail-oriented", "positive attitude", "customer service", "organisational skills", "initiative"], "languages_combined": [{"language": "cantonese", "language_level": ["good"]}, {"language": "english", "language_level": ["good"]}, {"language": "mandarin", "language_level": ["good"]}]}, "experience_required": {"duration": [], "field": []}}, {"job_id": "100003009053397", "location_code": "hk", "company": "Wong Shiu Chi Secondary School", "job_title": "\u516c\u6c11\u8207\u793e\u6703\u767c\u5c55\u79d1\u6559\u5b78\u52a9\u7406", "description": "\n\u8077\u8cac :\u4e00\u822c\u6587\u54e1\u6587\u66f8\u5de5\u4f5c,\u5305\u62ec\u8cc7\u6599\u8f38\u5165,\u6587\u4ef6\u5b58\u6a94,\u8907\u5370,\u7de8\u5236\u5831\u544a\u7b49\n\n\u8cc7\u6b77 :\u4e2d\u4e94\u7a0b\u5ea6; \u826f\u597d\u7cb5\u8a9e; \u4e00\u822c\u666e\u901a\u8a71; \u4e00\u822c\u82f1\u8a9e; \u61c2\u8b80\u5beb\u4e2d\u6587; \u61c2\u8b80\u5beb\u82f1\u6587; \u61c2MS Word; \u61c2MS Excel; \u61c2\u82f1\u6587\u6253\u5b57; \u61c2\u4e2d\u6587\u6253\u5b57; \u5177\u6709\u57fa\u672c\u96fb\u8166\u64cd\u4f5c\u77e5\u8b58; \u6709\u6587\u8077\u5de5\u4f5c\u7d93\u9a57\u512a\u5148\n\n\u5f85\u9047 :\u6bcf\u6708$13,000 - $15,000, \u661f\u671f\u4e00\u81f3\u4e94: \u4e0a\u53489\u6642\u81f3\u4e0b\u53486\u6642, \u6bcf\u9031\u5de5\u4f5c5\u5929\n\n\u7533\u8acb\u9808\u77e5 :\u6c42\u8077\u8005\u53ef\u50b3\u771f(21040202)\u6216\u96fb\u90f5(Apply Now)\u5c65\u6b77\u8868\u7d66SY SOLUTIONS LIMITED\u3002\u5982\u8981\u7d22\u53d6\u6536\u96c6\u500b\u4eba\u8cc7\u6599\u8072\u660e, \u8acb\u8207\u8449\u5c0f\u59d0(Fax/Email)\u806f\u7d61\u3002\n\n", "employment_types": ["Full Time"], "selling_points": [], "locations": ["Tai Po Area"], "categories": ["Education", "Tutor / Instructor", "Others", "Others", "Others"], "post_time": "2022-01-17T06:55:31Z", "salary": {"currency": null, "max": null, "min": null, "period": "monthly", "term": null}, "salary_visible": false, "title_keywords": [], "responsibilities": [], "requirements": {"degrees": [], "majors": [], "languages": [], "language_level": [], "hard_skills": ["excel", "word"], "soft_skills": [], "languages_combined": []}, "experience_required": {"duration": [], "field": []}}, {"job_id": "100003009050621", "location_code": "hk", "company": "The Independent Schools Foundation Academy Ltd", "job_title": "Administrative Assistant \u2013 Co-Curricular Activities Department (Ref: CCA/AA/20211101_ jdb)", "description": "Job Responsibilities:\n\nOversee the administrative matters, course management and coordination of the Programmes, to maintain an effective day-to-day operation of the programmes, such as student records, examinations, graduation matters, course materials and lectures preparation;\nReports to the Head of School regarding programme operation matters such as managing academic related tasks and student affairs;\nPriorities key tasks, allocating duties to academic & programme staff within the Institution and in accordance with Institution policies and procedures;\nAssist in reviewing and developing/ monitoring the implementation of policies and procedures;\nPlay a key part in implementation of the QA processes & Accreditation exercise;\nUndertake committee work in various meetings, committees and boards;\nDevelop and comply various programme related reports and statistics for management review;\nPerform any other duties as assigned by the Supervisor.\n\nJob Requirements:\n\nMinimum Bachelor Degree (preferably with post graduate degree) &/or Professional qualifications in related subject areas;\nMinimum 4 years working experience in higher education programmes &/or programme administration & management in which at least 2 years in a supervisory role;\nExcellent command in both written & spoken English and Chinese;\nDemonstrated ability to scope work, generate work plans and manage to deadlines;\nA good team leader with strong communication, interpersonal and analytical skills;\nSelf-motivated, organized, detail-oriented and capable in multi-tasking;\nPresentable, personable and patient personality;\nProficientin computer software applications, such as Microsoft Word, Excel and PowerPoint;\nExperience in managing programme management team and working with students will be a definite advantage;\nImmediate availability is highly preferred.\n\nPersonal data collected will be used for recruitment purpose only, and the collected data will also be considered for other suitable positions available in our Company.\n\nOnly short-listed candidates will be notified.\n\n\n", "employment_types": ["Full Time", "Permanent"], "selling_points": ["Minimum of 1 year of work experience", "Involve in the daily operation on department activ", "Render English-Chinese written translation duties"], "locations": ["Pok Fu Lam"], "categories": ["Admin & HR", "Clerical / Admin Staff", "Others", "Education", "Others"], "post_time": "2022-01-14T10:59:30Z", "salary": {"currency": null, "max": null, "min": null, "period": "monthly", "term": null}, "salary_visible": false, "title_keywords": ["administrative assistant"], "responsibilities": ["any other duties", "management", "policies", "monitoring", "procedures", "developing", "implementation", "student records", "develop", "management review", "maintain", "reports", "coordination", "committee work", "day-to-day operation"], "requirements": {"degrees": ["degree", "bachelor"], "majors": [], "languages": ["english", "chinese"], "language_level": ["excellent"], "hard_skills": ["excel", "microsoft word", "professional qualifications", "powerpoint", "analytical skills"], "soft_skills": ["organized", "self-motivated", "personable", "capable", "analytical skills", "communication", "detail-oriented", "multi-tasking", "presentable", "patient", "good team leader", "interpersonal"], "languages_combined": [{"language": "english", "language_level": ["excellent"]}, {"language": "chinese", "language_level": ["excellent"]}]}, "experience_required": {"duration": ["minimum 4 years", "at least 2 years"], "field": ["management", "supervisory", "education", "team", "administration"]}}, {"job_id": "100003009054863", "location_code": "hk", "company": "The Hong Kong Polytechnic University", "job_title": "Technical Assistant (two posts)", "description": "The Role\n\nTo join our PYP teaching team as a supply teacher in March to April 2022.\n\nMajor Responsibilities\n\nDeliver lessons and provide general educational support in Chinese subjects;\nEnsure attention is given to appropriate differentiation in lesson preparation and delivery;\nDesign a relevant, challenging and rigorous curriculum in liaison with the curriculum co-ordinator;\nContribute to the formation of collaborative learning at all levels of school life;\nCreate inquiry-based classrooms that develop critical thinking skills, knowledge and a range of skills within an environment based on trust and respect;\nSelect relevant resources and digital tools to support and enhance learning;\nDevelop appropriate assessment tasks, providing timely and effective feedback that enhances pupil\u2019s learning;\nCommunicate effectively with pupils, parents and colleagues in a professional manner;\nProvide appropriate pastoral support as and when necessary;\nUse assessment to guide instructions and evidence student learning; and\nCollect and organise\u00a0assessment\u00a0data for instruction and reporting.\nRequirements\n\nHolder of bachelor\u2019s degree in Chinese Language, Chinese Literature or relevant subject area;\nA recognised teaching qualification for the required age range (e.g. B.Ed., PGCE).\nExperience in teaching IB PYP Chinese.\nExcellent level of English;\nHolder of permanent HKID or dependent visa in Hong Kong.\nPlease send in application with a cover letter and full resume including your current and expected salaries addressed to the Human Resources Department, Malvern College Hong Kong by clicking 'Apply now'.\n\nPersonal data provided by job applicants will be treated in strict confidence and for recruitment purposes only. Please note that only shortlisted candidates will be invited for interviews. The final employment will be subject to pre-employment and child protection checks.", "employment_types": ["Full Time"], "selling_points": [], "locations": ["Not Specified"], "categories": ["Education", "Others", "Information Technology (IT)", "Support", "Others"], "post_time": "2022-01-17T12:06:45Z", "salary": {"currency": null, "max": null, "min": null, "period": null, "term": null}, "salary_visible": false, "title_keywords": ["technical assistant"], "responsibilities": ["reporting", "data", "professional manner", "design", "develop"], "requirements": {"degrees": ["degree", "bachelor"], "majors": [], "languages": ["english", "chinese"], "language_level": ["excellent"], "hard_skills": [], "soft_skills": ["confidence"], "languages_combined": [{"language": "english", "language_level": ["excellent"]}, {"language": "chinese", "language_level": []}]}, "experience_required": {"duration": [], "field": ["teaching"]}}, {"job_id": "100003009047572", "location_code": "hk", "company": "The University of Hong Kong", "job_title": "Senior Research Assistant (holding the functional title of Project Manager) (Ref.: 511355)", "description": "Autism Partnership Foundation (APF), a registered charitable organisation in Hong Kong, is committed to making a difference in the life of individuals with autism. APF aims to generate public awareness and knowledge about autism.\u00a0We advocate Applied Behaviour Analysis (ABA) treatment and intervention through diversified channels and settings, like direct treatments, community programmes of education and research.\u00a0For more details about APF, please visit: www.apf.org.hk or Facebook/APFHongKong\n\nTo cope with our expansion, we are looking for a high-calibre candidate to join us as our\u00a0\n\nService Administrative Executive\n\nKey Responsibilities:\n\n\nTo provide clerical and administrative support to ensure a smooth centre operations and learning environment\nTo manage our programmes schedules, workshops & outing activities arrangement\nTo handle all aspects of service programme applications and handle parents' enquires\nCreates and updates records for our service database\nTo provide support in all organisation events\nTo undertake ad-hoc duties as assigned\nKey Experiences:\n\nExperience in service administration for NGO\nHands-on programme administration experience including admission and registration, scheduling and coordinating activities with high attention to details required\nFront office experience is highly preferred\n\nThe ability to manage various stakeholders and manage their expectations\nThe Ideal Candidate:\n\nAssociate Degree holder or above in any disciplines\u00a0\u00a0\nAt least 2 years' solid experience in office administration and handling enquires\nGood command of written and spoken in both English and Chinese (Mandarin is an advantage)\nProficiency in MS Office and Chinese Word Processing\nA mature team player, good at multi-tasking and work under pressure\nResponsible, confident, cheerful and proactive with a positive attitude\nExcellent communication and interpersonal skills\nImmediate available is preferred\n\nInterested party please send your CV with your expected package (MUST). Only shortlisted candidates will be notified. All information provided will be treated in strict confidential and personal data will be used solely for recruitment purpose. Applicants who are not contacted within 4 weeks shall consider their applications unsuccessful and it will be kept for future reference. All unsuccessful applications will be destroyed within 6 months.", "employment_types": ["Full Time"], "selling_points": ["possess a MPhil degree or above", "1 year\u2019s post-qualification working experience", "coordinating school visits, liaising with teachers"], "locations": ["Not Specified"], "categories": ["Admin & HR", "Others", "Education", "Others", "Marketing / Public Relations", "Public Relations - Event Management"], "post_time": "2022-01-14T03:28:43Z", "salary": {"currency": null, "max": null, "min": null, "period": "monthly", "term": null}, "salary_visible": false, "title_keywords": ["project manager", "senior research assistant"], "responsibilities": ["provide support", "administrative support", "schedules", "operations", "analysis", "office administration", "work under pressure", "communication", "scheduling", "recruitment", "database", "ad-hoc duties", "facebook", "personal data", "administration"], "requirements": {"degrees": ["associate degree"], "majors": ["any disciplines"], "languages": ["english", "chinese", "mandarin"], "language_level": ["advantage", "proficiency", "good command"], "hard_skills": ["chinese word processing", "analysis", "workshops", "facebook", "ms office"], "soft_skills": ["confident", "cheerful", "responsible", "work under pressure", "mature", "positive attitude", "committed", "smooth", "learning", "hands-on", "multi-tasking", "organisation", "ad-hoc duties", "attention to details", "communication and interpersonal skills", "team player", "proactive", "ideal"], "languages_combined": [{"language": "english", "language_level": ["advantage", "good command"]}, {"language": "chinese", "language_level": ["advantage", "proficiency", "good command"]}, {"language": "mandarin", "language_level": ["advantage", "good command"]}]}, "experience_required": {"duration": ["at least 2 years"], "field": ["office administration", "administration"]}}, {"job_id": "100003009039119", "location_code": "hk", "company": "Hong Kong College of Technology", "job_title": "Senior Programme Administration Officer / Officer  (New joiner Bonus $10000)", "description": "Duties:\u00a0\n\nProvide secretarial service to academic and quality assurance committees;\nProvide administrative and logistic support to programme accreditation exercises and staff development functions / activities;\nAssist in internal audit and programme review exercises;\nAssist in entering data and updating information into database and ensure data accuracy; and\nAny other duties as assigned by supervisor(s).\u00a0\n\nRequirements:\n\nBachelor\u2019s degree or above, preferably in Language, Communications or related areas;\nAt least 4 years working experience, preferably in the tertiary education sector;\nSkills in Chinese Word Processing (\u5009\u9821\u6216\u901f\u6210), MS Office applications (including, Word, Excel and PowerPoint);\nGood command of written and spoken English and Chinese; and\nAble to work under pressure and tight schedule.\nWe endeavour to recruit and retain talents in the career that embraces growth and staff development, with voluntary employer contribution in MPF as well as flexible work arrangement where applicable and appropriate.\n\n\nInterested parties please send your full resume with your available date, present and expected salary and quote the Position and\u00a0Job Reference No. on the email subject.\u00a0\n\nTo know more about us, please visit our\u00a0website www.hkct.edu.hk\n\nPersonal data provided by the applicants will only be used for recruitment and employment-related purposes.\nWe are an equal opportunity employer.", "employment_types": ["Full Time"], "selling_points": ["Programme Administration", "Education", "supervision"], "locations": ["Not Specified"], "categories": ["Admin & HR", "Clerical / Admin Staff", "Education", "Others", "Public / Civil", "Social Services - Community / Non-profit Organization"], "post_time": "2022-01-11T08:46:10Z", "salary": {"currency": null, "max": null, "min": null, "period": "monthly", "term": null}, "salary_visible": false, "title_keywords": ["administration officer", "officer"], "responsibilities": ["any other duties", "internal audit", "programme review exercises", "quality", "logistic support", "ensure data accuracy", "secretarial service", "updating information", "staff development functions", "database", "entering data"], "requirements": {"degrees": ["degree or above", "bachelor"], "majors": ["communications"], "languages": ["english", "chinese"], "language_level": ["good command"], "hard_skills": ["excel", "chinese word processing", "word", "powerpoint", "ms office"], "soft_skills": ["flexible", "work under pressure"], "languages_combined": [{"language": "english", "language_level": ["good command"]}, {"language": "chinese", "language_level": ["good command"]}]}, "experience_required": {"duration": ["at least 4 years"], "field": ["education"]}}, {"job_id": "100003009049493", "location_code": "hk", "company": "The Hong Kong Institute Of Bankers", "job_title": "Head of Relationship Management (Training and Development)", "description": "\n\u8077\u8cac :\u4e00\u822c\u5e97\u52d9\u52a9\u7406\u5de5\u4f5c,\u76e4\u9ede\u5b58\u8ca8,\u66f4\u65b0\u5b58\u8ca8\u8a18\u9304,\u6574\u7406\u8ca8\u5009,\u8ca0\u8cac\u5009\u5eab\u65e5\u5e38\u7406\u8ca8\u53ca\u5009\u52d9\u5de5\u4f5c(\u5982\u51fa\u5165\u8ca8,\u5206\u8ca8,\u5305\u88dd\u5bc4\u8ca8\u7b49),\u57f7\u8ca8,\u6838\u5c0d\u8ca8\u7269\u8cc7\u6599,\u5b89\u6392\u7269\u6d41\u670d\u52d9\n\n\u8cc7\u6b77 :\u6c92\u6709\u5b78\u6b77\u8981\u6c42; \u826f\u597d\u7cb5\u8a9e; \u4e00\u822c\u666e\u901a\u8a71; \u61c2\u8b80\u5beb\u4e2d\u6587; \u6709\u8cac\u4efb\u5fc3\n\n\u5f85\u9047 :\u6bcf\u6708$11,000 - $15,000, \u6709\u52e4\u5de5\u734e, \u71df\u696d\u734e\u91d1 \u53ca\u5e74\u7d42\u734e\u91d1, \u4e0a\u534811\u6642\u81f3\u4e0b\u53488\u6642, \u6bcf\u9031\u5de5\u4f5c6\u5929,\u8f2a\u4f11, \u6bcf\u5929\u5de5\u4f5c 9 \u5c0f\u6642\n\n\u7533\u8acb\u9808\u77e5 :\u6c42\u8077\u8005\u53ef\u81f4\u96fb28891317\u8207\u5fa1\u6bbf\u5802\u85e5\u599d\u6709\u9650\u516c\u53f8\u85cd\u5c0f\u59d0\u806f\u7d61\u3002\n\n", "employment_types": ["Full Time", "Permanent"], "selling_points": ["Banking sector", "Training & Development", "HKIB professional qualifications"], "locations": ["Sheung Wan"], "categories": ["Banking / Finance", "Others", "Education", "Others", "Admin & HR", "Training & Development"], "post_time": "2022-01-14T08:45:00Z", "salary": {"currency": null, "max": null, "min": null, "period": "monthly", "term": null}, "salary_visible": false, "title_keywords": [], "responsibilities": [], "requirements": {"degrees": [], "majors": [], "languages": [], "language_level": [], "hard_skills": [], "soft_skills": [], "languages_combined": []}, "experience_required": {"duration": [], "field": []}}, {"job_id": "100003009050254", "location_code": "hk", "company": "IDP Education Limited", "job_title": "IELTS Invigilator - Part-time", "description": "School of Professional Education and Executive Development (SPEED)\n\nProject Associate (two posts) (Ref. 220114-01)\n[Appointment period: eighteen months]\n\nDuties\n\nThe appointees will assist the Project Coordinator in the Education Bureau (EDB) funded project - \u201cInternational Experiential Learning and Application: Global Work-Integrated Education (Global-WIE) and idea Generation Laboratory (iG-Lab)\u201d.\n\nThe appointees will (a) contribute to the planning and implementing activities related to student employability; (b) liaise and establish good relationships with local and overseas business partners, and participate in industry collaborations, such as recruitment talks and job referrals; (c) provide all-round support to students and fresh graduates, including but not limited to career advisory service and job referrals, and (d) perform any other duties as assigned.\n\nThe appointees may be required to work on shift duties as well as outdoor, on weekends and public holidays. They may take up assignments and work outside Hong Kong occasionally.\n\nQualifications\n\nApplicants should have the following qualifications and qualities:\n\n(a) a good honours degree, preferably in Business, Marketing or related disciplines; (b) at least three years of relevant work experience, preferably in industries of recruitment and event management; (c) good communication and interpersonal skills; (d) being an outgoing, positive and customer-oriented person; (e) be able to work independently and under pressure; (f) a good command of written and spoken English and Chinese, and (g) good computer knowledge in MS Office applications.\n\nApplicants with less experience will be considered for the post of Project Assistant.\n\nShortlisted candidates may be invited to sit for a written test.\n\nRemuneration\n\nSalary offered will be commensurate with qualifications and experience.\n\nApplication\n\nPlease complete the job application form which is available on http://www.cpce-polyu.edu.hk/chro/app_form/ and send it to the Human Resources Office, College of Professional and Continuing Education. For applicants who wish to provide a separate curriculum vitae, they should still complete the job application form for facilitating the recruitment process. Recruitment will continue until the positions are filled. Initial consideration of applications will commence in late Janurary 2022.\n\nFor enquiries/further information, please contact Mr Steve Hung at 3746 0737.\n\nNote: College of Professional and Continuing Education Limited is an affiliate of The Hong Kong Polytechnic University.", "employment_types": ["Part Time"], "selling_points": [], "locations": ["Not Specified"], "categories": ["Admin & HR", "Clerical / Admin Staff", "Education", "Others", "Sales, CS & Business Devpt", "Others"], "post_time": "2022-01-14T10:01:27Z", "salary": {"currency": null, "max": null, "min": null, "period": "hourly", "term": null}, "salary_visible": false, "title_keywords": [], "responsibilities": ["liaise", "any other duties", "management", "communication", "recruitment", "contact", "recruitment process", "planning"], "requirements": {"degrees": ["degree"], "majors": ["related disciplines", "business", "marketing"], "languages": ["english", "chinese"], "language_level": ["good command", "good"], "hard_skills": ["c", "ms office"], "soft_skills": ["outgoing", "work independently", "under pressure", "customer-oriented", "learning", "communication and interpersonal skills", "positive"], "languages_combined": [{"language": "english", "language_level": ["good command", "good"]}, {"language": "chinese", "language_level": ["good command", "good"]}]}, "experience_required": {"duration": ["at least three years"], "field": ["management", "recruitment"]}}, {"job_id": "100003009042506", "location_code": "hk", "company": "Hong Kong Institute of Construction", "job_title": "Officer - Student Recruitment", "description": "\n\u8077\u8cac :\u652f\u63f4\u516c\u6c11\u8207\u793e\u6703\u767c\u5c55\u79d1\u66a8\u901a\u8b58\u79d1\u53ca\u5b78\u6821\u884c\u653f\n\n\u8cc7\u6b77 :\u5c08\u4e0a\u6559\u80b2\uff1a\u5b78\u58eb\u5b78\u4f4d; \u826f\u597d\u7cb5\u8a9e; \u826f\u597d\u82f1\u8a9e; \u61c2\u8b80\u5beb\u4e2d\u6587; \u61c2\u8b80\u5beb\u82f1\u6587; \u61c2\u96fb\u8166\u6587\u66f8\u8655\u7406; \u5177\u5b78\u6821\u5de5\u4f5c\u7d93\u9a57\u512a\u5148\uff0c\u5177\u76f8\u95dc\u5b78\u6b77\u512a\u5148\n\n\u5f85\u9047 :\u6bcf\u6708$15,000 - $17,000, \u6709\u8d85\u6642\u5de5\u4f5c\u88dc\u5047, \u661f\u671f\u4e00\u81f3\u4e94: \u4e0a\u53488\u6642\u81f3\u4e0b\u53485\u6642, \u6bcf\u9031\u5de5\u4f5c5\u5929, \u6bcf\u5929\u5de5\u4f5c 9 \u5c0f\u6642, \u5348\u81b3\u6642\u9593:\u4e2d\u534812\u664235\u5206\u81f3\u4e0b\u53481\u664235\u5206\n\n\u7533\u8acb\u9808\u77e5 :\u6c42\u8077\u8005\u53ef\u50b3\u771f(26507256)\u6216\u96fb\u90f5(Apply Now)\u5c65\u6b77\u8868\u7d66\u738b\u8087\u679d\u4e2d\u5b78\u3002\u5982\u8981\u7d22\u53d6\u6536\u96c6\u500b\u4eba\u8cc7\u6599\u8072\u660e, \u8acb\u8207\u6881\u5148\u751f(Tel:26561270)\u806f\u7d61\u3002\n\n", "employment_types": ["Full Time", "Contract"], "selling_points": ["a recognised degree", "a minimum of 3 years\u2019 post-qualification work exp.", "plan and execute student recruitment events"], "locations": ["Not Specified"], "categories": ["Admin & HR", "Clerical / Admin Staff", "Education", "Others", "Marketing / Public Relations", "Marketing - General / Support"], "post_time": "2022-01-12T07:49:05Z", "salary": {"currency": null, "max": null, "min": null, "period": null, "term": null}, "salary_visible": false, "title_keywords": ["officer"], "responsibilities": [], "requirements": {"degrees": [], "majors": [], "languages": [], "language_level": [], "hard_skills": [], "soft_skills": [], "languages_combined": []}, "experience_required": {"duration": [], "field": []}}, {"job_id": "100003009050257", "location_code": "hk", "company": "IDP Education Limited", "job_title": "Examination Services Assistant (CS Focus)", "description": "JOCKEY CLUB DESIGN INSTITUTE FOR SOCIAL INNOVATION\nProject Assistant / Project Administrative Assistant (Ref. 22011312)\n[Appointment period: twelve months initially, with possibility of further appointment]\nJockey Club Design Institute for Social Innovation is a unit aims at providing an innovative and human-centred platform to envision a better life in the society, connecting people with passion and nurturing doers of all ages to innovate with collective wisdom to enable impactful action.\nDuties\nThe appointee will assist the project leader in the research project \u2013 \u201cPolyU Jockey Club Operation SoInno\u201d.\u00a0 He/She will be required to:\n(a)\u00a0\u00a0 \u00a0handle administrative and expense claims of the Unit;\n(b)\u00a0\u00a0 \u00a0assist in the preparation of reports and maintain database;\n(c)\u00a0\u00a0 \u00a0support a wide range of project activities;\n(d)\u00a0\u00a0 \u00a0assist in the regular updating of the Unit\u2019s website and other online promotion platforms; and\n(e)\u00a0\u00a0 \u00a0perform any other duties as assigned by the Director of Jockey Club Design Institute for Social Innovation or his delegates.\nThe appointee may be required to work occasionally outside normal office hours, including Saturdays and Sundays.\nQualifications\nApplicants for the Project Assistant post should have an honours degree or an equivalent qualification, preferably in Business Administration, Social Sciences or relevant disciplines with at least one year of relevant post-qualification experience. \u00a0\nApplicants for the Project Administrative Assistant post should have five passes in HKCEE including English Language (at least Grade C if Syllabus A; Level 2 if results are obtained from 2007 onwards), Chinese Language (Level 2 if results are obtained from 2007 onwards) and Mathematics; or a combination of results in five HKDSE subjects of Level 2 in New Senior Secondary subjects / \u201cAttained\u201d in Applied Learning subjects / Grade E in Other Language subjects, and the five subjects must include English Language, Chinese Language and Mathematics.\u00a0 He/She should have at least two years of relevant post-qualification experience.\nApplicants should also:\n(a)\u00a0\u00a0 \u00a0have good planning, administrative and organizational skills with high self-motivation;\n(b)\u00a0\u00a0 \u00a0be able to work independently and under pressure;\n(c)\u00a0\u00a0 \u00a0have a good command of both written and spoken English and Chinese;\n(d)\u00a0\u00a0 \u00a0have good interpersonal and communication skills as well as team spirit;\n(e)\u00a0\u00a0 \u00a0have good computer literacy, including the use of Internet, social media platforms, online meeting tools and MS Office applications, i.e. Chinese word processing, Excel, PowerPoint and Outlook; and\n(f)\u00a0\u00a0 \u00a0be competent in using the Adobe Illustrator or website Content Management System being an advantage.\nApplicants are invited to contact Ms Alice Law at tel no. 3400 3435 or email via \"Apply Now\" for further information.\nApplicants should submit a covering letter together with completed application form and curriculum vitae.\nRemuneration\nA highly competitive remuneration package will be offered.\u00a0 Applicants should state their current and expected salary in the application.\nApplication\nPlease send a completed application form by post to Human Resources Office, 13/F, Li Ka Shing Tower, The Hong Kong Polytechnic University, Hung Hom, Kowloon, Hong Kong or via email by clicking \"Apply Now\".\u00a0 Application forms can be downloaded from https://www.polyu.edu.hk/hro/careers/guidelines_and_forms/forms.\u00a0 If a separate curriculum vitae is to be provided, please still complete the application form which will help speed up the recruitment process.\u00a0 Consideration of applications will commence on 20 January 2022 until the position is filled.\u00a0 Applications should be addressed directly to Ms Alice Law (please state Jockey Club Design Institute for Social Innovation on the envelope).\u00a0 The University\u2019s Personal Information Collection Statement for recruitment can be found at https://www.polyu.edu.hk/hro/careers/guidelines_and_forms/pics_for_recruitment.\nPolyU is an equal opportunity employer committed to diversity and inclusivity.\u00a0 All qualified applicants will receive consideration for employment without regard to gender, ethnicity, nationality, family status or physical or mental disabilities.", "employment_types": ["Full Time", "Permanent"], "selling_points": [], "locations": ["Wan Chai"], "categories": ["Admin & HR", "Clerical / Admin Staff", "Education", "Others", "Others", "Student / Fresh Graduate / No Experience"], "post_time": "2022-01-14T10:02:11Z", "salary": {"currency": null, "max": null, "min": null, "period": "monthly", "term": null}, "salary_visible": false, "title_keywords": ["examination services assistant"], "responsibilities": ["administration", "any other duties", "management", "social media platforms", "website", "design", "communication", "maintain", "reports", "planning", "database", "contact", "recruitment", "recruitment process", "online promotion"], "requirements": {"degrees": ["degree", "hkdse"], "majors": ["mathematics", "business administration", "social sciences"], "languages": ["english", "chinese"], "language_level": ["good command"], "hard_skills": ["excel", "alice", "no", "chinese word processing", "powerpoint", "adobe illustrator", "c", "outlook", "ms office"], "soft_skills": ["organizational skills", "work independently", "communication skills", "under pressure", "team spirit", "competent", "computer literacy", "committed", "self-motivation", "learning", "innovative", "interpersonal"], "languages_combined": [{"language": "english", "language_level": ["good command"]}, {"language": "chinese", "language_level": ["good command"]}]}, "experience_required": {"duration": ["at least one year", "at least two years"], "field": ["post-qualification", "business administration"]}}, {"job_id": "100003009047896", "location_code": "hk", "company": "The English Schools Foundation", "job_title": "Assistant Administrator - ESF Hillside International Kindergarten", "description": "Job Duties & Accountabilities:\n\nTo drive and sustain the development of the Institute by promoting quality Professional Qualification Programmes, including Enhanced Competence Framework (ECF) and Certified Banker (CB), and also Continuing Development Programmes (CDP), with the aim to enhance the banking industry competency standard and elevate HKIB as the authoritative institute in setting such standard in Hong Kong and across region.\n\n\n\nFormulate strategies in the promoting and positioning of HKIB professional qualifications and also continuous professional development programmes\nDirect the product development of the Institute to support the continuous professional development of industry practitioners\nDrive the performance of the team by setting the strategic direction and formulating business strategies\nDevelop strategies in building collaboration with business partners / trainers to support the development of the Institute\nDrive digital learning strategy to enhance customer experience in using e-channel and flexi-learning platform\n\nJob Requirements:\n\nDegree holder in any discipline\nMinimum 12 years of experience preferably in training or front-line business functions with banking sector\nHolders of HKIB professional qualifications such as Certified Banker (CB) or other ECF qualifications are preferable\nExperience in banking product development or training & development will be an added advantage\nExceptional leadership skills and proven ability to manage multiple responsibilities in a fast-paced environment with critical deadlines\nExcellent interpersonal skills to work with people at all levels\nStrong project management, analytical and problem solving skills\nAble to establish network with senior executives within the industry\nEnergetic, self-motivated, resourceful, and result oriented\nExcellent command in both written and spoken English and Chinese\nInterested parties may send in your application together with a detailed resume stating your\u00a0present & expected salaries, date of availability\u00a0and contact phone number by clicking\u00a0\"Apply Now\"\nApplicants are welcomed to visit our website:\u00a0www.hkib.org\u00a0for further information about the institute.\n\n(All information provided will be treated in strict confidence and used solely for recruitment purposes)", "employment_types": ["Full Time", "Permanent"], "selling_points": ["To follow all administrative processes", "Grade 5, preferably A Levels", "Two year's administration"], "locations": ["Not Specified"], "categories": ["Admin & HR", "Clerical / Admin Staff", "Others", "Education", "Others"], "post_time": "2022-01-14T04:10:14Z", "salary": {"currency": null, "max": null, "min": null, "period": "monthly", "term": null}, "salary_visible": false, "title_keywords": ["administrator", "assistant"], "responsibilities": ["quality", "develop strategies", "banking"], "requirements": {"degrees": ["degree holder"], "majors": [], "languages": ["english", "chinese"], "language_level": ["excellent"], "hard_skills": ["project management", "problem solving skills", "professional qualifications"], "soft_skills": ["self-motivated", "resourceful", "fast-paced environment", "leadership skills", "project management", "analytical and problem solving skills", "result oriented", "interpersonal skills", "energetic"], "languages_combined": [{"language": "english", "language_level": ["excellent"]}, {"language": "chinese", "language_level": ["excellent"]}]}, "experience_required": {"duration": ["minimum 12 years"], "field": ["training", "development", "business", "banking sector", "banking", "product development"]}}, {"job_id": "100003009052294", "location_code": "hk", "company": "Tianda Institute", "job_title": "\u7814\u7a76\u54e1 Researcher (Full time or Part time)", "description": "DEPARTMENT OF REHABILITATION SCIENCES\nTechnical Assistant (two posts) (Ref. 22011717)\n[Appointment period: each for twelve months]\nDuties\nThe appointees will be required to:\n(a) provide support for teaching, research and service to the Department;\n(b) provide information update and maintenance of accounts for e-learning system;\n(c) perform housekeeping in classrooms and laboratories;\n(d) assist in the setting up, operation and maintenance of the computing, audio-visual and other teaching equipment; and\n(e) perform any other duties as assigned by the Head of Department or his delegates.\nThe appointees may be required to work outside normal office hours and on Saturdays and Sundays.\nQualifications\nApplicants should have:\n(a) five passes in HKCEE including English Language (at least Grade C if Syllabus A; Level 2 if results are obtained from 2007 onwards), Chinese Language (Level 2 if results are obtained from 2007 onwards) and Mathematics; or a combination of results in five HKDSE subjects of Level 2\u00a0in New Senior Secondary subjects / \"Attained\" in Applied Learning subjects / Grade E in Other Language subjects, and the five subjects must include English Language, Chinese Language and Mathematics;\n(b) good computer knowledge and experience in using application software such as MS Office, photo/video editing software and e-learning system, etc.; and\n(c) good interpersonal and communication skills.\nRemuneration\nA highly competitive remuneration package will be offered. Applicants should state their current and expected salary in the application.\nApplication\nPlease send a completed application form by post to Human Resources Office, 13/F, Li Ka Shing Tower, The Hong Kong Polytechnic University, Hung Hom, Kowloon, Hong Kong or via email by clicking \"Apply Now\".\u00a0 Application forms can be downloaded from https://www.polyu.edu.hk/hro/careers/guidelines_and_forms/forms.\u00a0 If\u00a0 a separate curriculum vitae is to be provided, please still complete the application form which will help speed up the recruitment process.\u00a0 Consideration of applications will commence on 30 January 2022 until the positions are filled. \u00a0The University\u2019s Personal Information Collection Statement for recruitment can be found at https://www.polyu.edu.hk/hro/careers/guidelines_and_forms/pics_for_recruitment.\nPolyU is an equal opportunity employer committed to diversity and inclusivity.\u00a0 All qualified applicants will receive consideration for employment without regard to gender, ethnicity, nationality, family status or physical or mental disabilities.", "employment_types": ["Full Time", "Permanent"], "selling_points": [], "locations": ["Central"], "categories": ["Media & Advertising", "Others", "Professional Services", "Business Analysis / Data Analysis", "Education", "Others"], "post_time": "2022-01-17T02:39:43Z", "salary": {"currency": null, "max": null, "min": null, "period": "monthly", "term": null}, "salary_visible": false, "title_keywords": ["researcher"], "responsibilities": ["any other duties", "rehabilitation", "provide support", "software", "maintenance", "housekeeping", "video editing", "communication", "recruitment", "visual", "recruitment process", "audio"], "requirements": {"degrees": ["hkdse"], "majors": ["mathematics"], "languages": ["english", "chinese"], "language_level": [], "hard_skills": ["video editing", "c", "maintenance", "ms office"], "soft_skills": ["communication skills", "learning", "interpersonal", "committed"], "languages_combined": [{"language": "english", "language_level": []}, {"language": "chinese", "language_level": []}]}, "experience_required": {"duration": [], "field": ["editing", "photo", "video"]}}, {"job_id": "100003009039248", "location_code": "hk", "company": "HKU School of Professional & Continuing Education", "job_title": "Executive Assistant II in the Registry Affairs Unit", "description": "Work type:\u00a0Full-time\nDepartment:\u00a0Faculty of Education (10000)\nCategories:\u00a0Research Support Staff\n\nSenior Research Assistant (holding the functional title of Project Manager) in the Faculty of Education\u00a0(Ref.: 511355) (to commence as soon as possible for 1 year, with the possibility of renewal)\u00a0\u00a0\n\nApplicants should possess a MPhil degree or above, with at least 1 year\u2019s post-qualification working experience.\u00a0 They should have a good command of written and spoken English and Chinese (including Cantonese), excellent research skills in qualitative research, experience in teaching biology, good time management skills, and the ability to work independently and as a team.\u00a0\u00a0\n\nThe appointee will work for a Quality Education Fund (QEF) project on biology teaching.\u00a0 He/She will be responsible for coordinating school visits, liaising with teachers on matters related to producing lesson videos, on-site directing and filming of the lessons, supporting the development and write-up of educative curriculum materials, organizing professional development workshops, plenary workshops and dissemination seminars, overseeing the production of educative curriculum materials and delivery to schools, collecting, analyzing and evaluating data on various components of the projects, and performing other duties as assigned.\u00a0\u00a0\n\nEnquiries about the post should be sent to Dr. Kennedy Chan at [via APPLY NOW].\u00a0\n\nA highly competitive salary commensurate with qualifications and experience will be offered, in addition to annual leave and medical benefits.\u00a0\n\nThe University only accepts online application for the above post. Applicants should apply online and upload an up-to-date C.V[via APPLY NOW].\u00a0 Review of applications will start as soon as possible and continue until\u00a0January 23, 2022, or until the post is filled, whichever is earlier.\n\nAdvertised:Dec 23, 2021 (HK Time)\nApplications close:Jan 23, 2022 (HK Time)", "employment_types": ["Full Time", "Contract"], "selling_points": ["the administration of CEF reimbursable courses", "process CEF applications, reimbursement claims", "maintain physical and electronic records"], "locations": ["Not Specified"], "categories": ["Admin & HR", "Clerical / Admin Staff", "Education", "Others", "Others", "Others"], "post_time": "2022-01-11T09:09:53Z", "salary": {"currency": null, "max": null, "min": null, "period": "monthly", "term": null}, "salary_visible": false, "title_keywords": ["executive assistant"], "responsibilities": ["management", "other duties", "data", "quality", "liaising with", "research support"], "requirements": {"degrees": ["degree or above"], "majors": [], "languages": ["cantonese", "english", "chinese"], "language_level": ["excellent", "good command", "good"], "hard_skills": ["workshops"], "soft_skills": ["time management skills", "work independently", "research skills", "responsible"], "languages_combined": [{"language": "cantonese", "language_level": ["good command", "good"]}, {"language": "english", "language_level": ["excellent", "good command", "good"]}, {"language": "chinese", "language_level": ["excellent", "good command", "good"]}]}, "experience_required": {"duration": ["at least 1 year"], "field": ["management", "research", "post-qualification", "teaching", "team"]}}, {"job_id": "100003009051187", "location_code": "hk", "company": "Mindset Asia Limited", "job_title": "General Manager - Learning Center", "description": "Duties:\u00a0\n\nProvide secretarial service to academic and quality assurance committees;\nProvide administrative and logistic support to programme accreditation exercises and staff development functions / activities;\nAssist in internal audit and programme review exercises;\nAssist in entering data and updating information into database and ensure data accuracy; and\nAny other duties as assigned by supervisor(s).\u00a0\n\nRequirements:\n\nBachelor\u2019s degree or above, preferably in Language, Communications or related areas;\nAt least 4 years working experience, preferably in the tertiary education sector;\nSkills in Chinese Word Processing (\u5009\u9821\u6216\u901f\u6210), MS Office applications (including, Word, Excel and PowerPoint);\nGood command of written and spoken English and Chinese; and\nAble to work under pressure and tight schedule.\nWe endeavour to recruit and retain talents in the career that embraces growth and staff development, with voluntary employer contribution in MPF as well as flexible work arrangement where applicable and appropriate.\n\n\nInterested parties please send your full resume with your available date, present and expected salary and quote the Position and\u00a0Job Reference No. on the email subject.\u00a0\n\nTo know more about us, please visit our\u00a0website www.hkct.edu.hk\n\nPersonal data provided by the applicants will only be used for recruitment and employment-related purposes.\nWe are an equal opportunity employer.", "employment_types": ["Full Time", "Permanent"], "selling_points": [], "locations": ["Not Specified"], "categories": ["Education", "Others", "Management", "General Management", "Admin & HR", "Training & Development"], "post_time": "2022-01-15T04:21:46Z", "salary": {"currency": null, "max": null, "min": null, "period": "monthly", "term": null}, "salary_visible": false, "title_keywords": ["general manager"], "responsibilities": ["any other duties", "internal audit", "programme review exercises", "quality", "logistic support", "ensure data accuracy", "secretarial service", "updating information", "staff development functions", "database", "entering data"], "requirements": {"degrees": ["degree or above", "bachelor"], "majors": ["communications"], "languages": ["english", "chinese"], "language_level": ["good command"], "hard_skills": ["excel", "chinese word processing", "word", "powerpoint", "ms office"], "soft_skills": ["flexible", "work under pressure"], "languages_combined": [{"language": "english", "language_level": ["good command"]}, {"language": "chinese", "language_level": ["good command"]}]}, "experience_required": {"duration": ["at least 4 years"], "field": ["education"]}}, {"job_id": "100003009045515", "location_code": "hk", "company": "Parsons Music Corporation", "job_title": "Administrator/ Assistant, Education", "description": "Full-time/Part-time Project Coordinator (at the rank of Executive Officer) in the Department of Psychiatry\u00a0(Ref.: 509252) (to commence as soon as possible for one-year, with the possibility of renewal subject to satisfactory performance)\u00a0\n\nApplicants should possess a good Bachelor\u2019s degree, preferably in social work, psychology, public health, nursing, or related disciplines. They should have an excellent command of written English with Level 5* or above in English Language in HKDSE, B or above in Use of English in HKALE, 5 or above in English Language in IB, or equivalent.\u00a0\n\nThe appointee will join the Psychosis Study and Intervention (PSI) Research Team which focuses on understanding how the human mind could under some conditions enter into a psychosis state, and how best to help people afflicted with psychotic experiences. \u00a0He/She will write up books, journals and media publications for the dissemination of research findings based on the guidance and requirements given by Professor Eric Chen, and perform other duties as assigned. \u00a0Working hours will be flexible.\u00a0 Those who have responded to the previous advertisement (Ref.: 508484) need not re-apply.\n\nA highly competitive salary commensurate with qualifications and experience will be offered, in addition to annual leave and medical benefits.\u00a0\n\nThe University only accepts online application for the above post. \u00a0Applicants should apply online and upload an up-to-date C.V.\u00a0 Closes February 12, 2022.", "employment_types": ["Full Time", "Permanent"], "selling_points": ["Tutors\u2019 and students\u2019 management", "3 years' relevant experience", "5-day work week"], "locations": ["Tsim Sha Tsui"], "categories": ["Admin & HR", "Clerical / Admin Staff", "Education", "Others", "Recruitment / Executive Search"], "post_time": "2022-01-13T07:59:42Z", "salary": {"currency": null, "max": null, "min": null, "period": "monthly", "term": null}, "salary_visible": false, "title_keywords": ["administrator", "assistant"], "responsibilities": ["guidance", "perform other duties"], "requirements": {"degrees": ["degree", "bachelor", "hkdse"], "majors": ["psychology", "social work", "related disciplines", "nursing", "public health"], "languages": ["english"], "language_level": ["excellent"], "hard_skills": [], "soft_skills": ["flexible"], "languages_combined": [{"language": "english", "language_level": ["excellent"]}]}, "experience_required": {"duration": [], "field": ["research team"]}}, {"job_id": "100003009053893", "location_code": "hk", "company": "MediParamedical Services Limited", "job_title": "\u8a3a\u6240\u52a9\u7406", "description": "\u8a3b\u518a\u6559\u80b2\u5fc3\u7406\u5b78\u5bb6\uff08\u534a\u8077\uff09/ Registered Educational Psychologist (Part-time)\n\n\u8077\u8cac\uff1a\n\n\u2022 \u5152\u7ae5\u548c\u9752\u5c11\u5e74\u5fc3\u7406\u8a55\u4f30\u3001\u6cbb\u7642\u53ca\u8a13\u7df4\n\n\u2022 \u63d0\u4f9b\u5bb6\u9577\u53ca\u6559\u5e2b\u54a8\u8a62\u53ca\u57f9\u8a13\n\n\u2022 \u6309\u9700\u8981\u65bc\u4e0a\u74b0\u6216\u5230\u6821\u5de5\u4f5c\n\n\n\n\n\u8981\u6c42\uff1a\n\n\u2022 \u9999\u6e2f\u5fc3\u7406\u5b78\u6703\u6559\u80b2\u5fc3\u7406\u5b78\u90e8\u6703\u54e1\n\n\u2022 \u6301\u6709\u6d77\u5916\u6216\u672c\u5730\u8a8d\u53ef\u6559\u80b2\u5fc3\u7406\u5b78\u78a9\u58eb\u6216\u4ee5\u4e0a\u5b78\u4f4d\n\n\u2022 2 \u5e74\u6216\u4ee5\u4e0a\u7d93\u9a57", "employment_types": ["Full Time"], "selling_points": [], "locations": ["Not Specified"], "categories": ["Education", "Tutor / Instructor", "Others", "Others", "Others"], "post_time": "2022-01-17T07:42:50Z", "salary": {"currency": null, "max": null, "min": null, "period": "monthly", "term": null}, "salary_visible": false, "title_keywords": ["\u8a3a\u6240\u52a9\u7406"], "responsibilities": [], "requirements": {"degrees": [], "majors": [], "languages": [], "language_level": [], "hard_skills": [], "soft_skills": [], "languages_combined": []}, "experience_required": {"duration": [], "field": []}}, {"job_id": "100003009029874", "location_code": "hk", "company": "The Hong Kong Medical Association", "job_title": "Assistant Executive Officer - Education (Contract)", "description": "\n\u8077\u8cac :\u8ca0\u8cac\u5de5\u5834\u53ca\u9662\u820d\u6e05\u6f54\u5de5\u4f5c;\u5354\u52a9\u55ae\u4f4d\u5916\u52e4\u5de5\u4f5c;\u5354\u52a9\u7167\u9867\u9662\u820d\u53ca\u5de5\u5834\u7684\u820d\u53cb/\u5de5\u53cb(1\u5e74\u5408\u7d04,\u6bcf\u5e74\u7e8c\u7d04)\n\n\u8cc7\u6b77 :\u5c0f\u516d\u7a0b\u5ea6; \u826f\u597d\u7cb5\u8a9e; \u61c2\u8b80\u5beb\u4e2d\u6587; \u5177\u6728\u5de5\u6216\u91d1\u5de5\u7d93\u9a57\u512a\u5148\n\n\u5f85\u9047 :\u6bcf\u6708$13,730, \u6709\u4f9b\u81b3\u98df, \u751f\u65e5\u5047, \u9580\u8a3a\u91ab\u7642, \u4f4f\u9662\u4fdd\u96aa \u53ca\u9032\u4fee\u6d25\u8cbc, \u661f\u671f\u4e00\u81f3\u4e94: \u4e0a\u53488\u6642\u534a\u81f3\u4e0b\u53485\u6642\u534a\u53ca\u661f\u671f\u516d: \u4e0a\u53489\u6642\u81f3\u4e0b\u53481\u6642, \u6bcf\u9031\u5de5\u4f5c5\u5929\u534a(48\u5c0f\u6642)\n\n\u7533\u8acb\u9808\u77e5 :\u53ef\u96fb\u90f5(Apply Now)\u6216\u90f5\u5bc4(\u65b0\u754c\u7c89\u5dba\u96cd\u76db\u82d1\u96cd\u8588\u95a3\u5730\u4e0b)\u5c65\u6b77\u8868\u7d66\u9999\u6e2f\u4e2d\u83ef\u57fa\u7763\u6559\u9752\u5e74\u6703,\u5982\u8981\u7d22\u53d6\u6536\u96c6\u500b\u4eba\u8cc7\u6599\u8072\u660e,\u8acb\u8207\u970d\u5148\u751f(Email/Post)\u806f\u7d61\n\n", "employment_types": ["Contract"], "selling_points": [], "locations": ["Wan Chai"], "categories": ["Education", "Others", "Management", "General Management"], "post_time": "2022-01-11T04:39:18Z", "salary": {"currency": null, "max": null, "min": null, "period": "monthly", "term": null}, "salary_visible": false, "title_keywords": ["assistant executive officer"], "responsibilities": [], "requirements": {"degrees": [], "majors": [], "languages": [], "language_level": [], "hard_skills": [], "soft_skills": [], "languages_combined": []}, "experience_required": {"duration": [], "field": []}}, {"job_id": "100003009040115", "location_code": "hk", "company": "Carmel School", "job_title": "Administrative Officer", "description": "Responsibilities:\n\nResponsible for the tutors\u2019 recruitment process\nTutors\u2019 and students\u2019 management: Plan, lead and execute different monitoring systems for quality improvement\nOffer general support to the education team and liaise with different parties for quality control\nHandle branches\u2019 enquiries and support their operations (the tutor\u2019s part)\nHandle any ad hoc tasks and assignments\n\u00a0Requirements:\nDegree holder with minimum\u00a03 years\u2019\u00a0relevant experience\nInstrumental music background is preferred\nStrong organizational and communication skills\nCandidate with less experience will be considered as Assistant.\nPlease send your CV with current and expected salary\u00a0via the system\u00a0or send it to the Human Resources Department of Parsons Music Limited at 8/F, Railway Plaza, No. 39 Chatham Road South, Tsimshatsui, Kowloon, Hong Kong.\n(Data collected will be used for recruitment purpose only.)", "employment_types": ["Full Time", "Permanent"], "selling_points": ["International school", "Minimum two years' working experience", "Event coordination / admissions / student service"], "locations": ["Shau Kei Wan"], "categories": ["Education", "Others"], "post_time": "2022-01-12T01:30:32Z", "salary": {"currency": null, "max": null, "min": null, "period": "monthly", "term": null}, "salary_visible": false, "title_keywords": ["administrative officer"], "responsibilities": ["management", "general support", "operations", "monitoring", "systems", "quality", "ad hoc tasks", "plan", "quality control", "liaise with", "recruitment process"], "requirements": {"degrees": ["degree holder"], "majors": [], "languages": [], "language_level": [], "hard_skills": ["no"], "soft_skills": ["communication skills", "organizational", "instrumental"], "languages_combined": []}, "experience_required": {"duration": ["minimum 3 years"], "field": ["relevant experience"]}}, {"job_id": "100003009046732", "location_code": "hk", "company": "American School Hong Kong", "job_title": "Learning Support Educational Assistant - Multiple Positions Available", "description": "Duties:\u00a0 The appointee will provide programme administrative support to the Chinese Medicine Subject Group and will perform the following duties:\nTo support programme management including quality assurance compliance, programme publicity, student admission, maintenance of student records, students and teaching staff support, and preparation of academic reports;\nTo assist the programme director/manager in programme development and validation, including proposal preparation and arrangement of academic meetings etc.\nTo liaise with internal units, and external professional bodies and institutions ;\nTo mentor and supervise subordinate staff;\nOther duties as assigned by the programme director/manager.\nRequirements:\u00a0 Candidates should possess a recognized degree with at least 4-5 years relevant administrative working experience.\u00a0 Preference will be given to candidates with programme management and publicity experience.\u00a0 Candidates should be independent, detail-minded, and able to work under pressure.\u00a0 They should have strong analytical, organizational and interpersonal skills, excellent command of written and spoken English and Chinese (including Putonghua), and good computer proficiency.\nTerms of Appointment:Salary placement will be commensurate with qualifications and experience.\u00a0 The contract will normally be for 2 years with the possibility of renewal subject to review.\u00a0 A contract-end gratuity (taxable) will be payable upon satisfactory completion of the contract.\u00a0 Medical and dental benefits, annual leave and the use of sports and library facilities will be provided where applicable.\u00a0 The School also provides staff development opportunities.\nApplications: \u00a0Please send application quoting the reference number to the Human Resources Unit, HKU SPACE, 7/F., T. T. Tsui Building, The University of Hong Kong, Pokfulam Road, Hong Kong.\u00a0 You may apply online or download an application form at http://hkuspace.hku.hk/jobs or request one by fax (852) 2540 3271.\nClosing Date for Applications: \u00a0\u00a0 27 January 2022\nThe information provided in an application will only be used for the purpose of consideration for appointment by HKU SPACE.\u00a0 Applicants not contacted within 8 weeks from the closing date may assume that their applications are unsuccessful.\u00a0 Unsuccessful applications will be kept for a maximum period of 24 months.", "employment_types": ["Full Time", "Contract"], "selling_points": ["International School Educational Assistant", "Competitive Compensation and Package", "Professional Growth Opportunity"], "locations": ["Tai Po Area"], "categories": ["Education", "Tutor / Instructor", "Others"], "post_time": "2022-01-14T00:08:07Z", "salary": {"currency": null, "max": null, "min": null, "period": "monthly", "term": null}, "salary_visible": false, "title_keywords": ["assistant"], "responsibilities": ["management", "maintenance", "administrative support", "other duties", "compliance", "quality", "review", "student records", "reports", "liaise with", "work under pressure"], "requirements": {"degrees": ["degree"], "majors": [], "languages": ["putonghua", "english", "chinese"], "language_level": ["excellent", "proficiency", "good"], "hard_skills": ["maintenance"], "soft_skills": ["detail-minded", "independent", "organizational", "interpersonal skills", "work under pressure"], "languages_combined": [{"language": "putonghua", "language_level": ["excellent", "proficiency", "good"]}, {"language": "english", "language_level": ["excellent", "proficiency", "good"]}, {"language": "chinese", "language_level": ["excellent", "proficiency", "good"]}]}, "experience_required": {"duration": ["at least 4-5 years"], "field": ["management", "administrative"]}}, {"job_id": "100003009053774", "location_code": "hk", "company": "Food Monster Limited", "job_title": "\u5e97\u52d9\u52a9\u7406", "description": "\n\u8077\u8cac :\u4e00\u822c\u8a3a\u6240\u5de5\u4f5c\uff0c\u9700\u5916\u51fa\u5de5\u4f5c\n\n\u8cc7\u6b77 :\u4e2d\u4e94\u7a0b\u5ea6; \u826f\u597d\u7cb5\u8a9e; \u826f\u597d\u82f1\u8a9e; \u61c2\u8b80\u5beb\u4e2d\u6587; \u61c2\u8b80\u5beb\u82f1\u6587; \u9700\u5177\u5099\u76f8\u95dc\u8a3c\u66f8\n\n\u5f85\u9047 :\u6bcf\u6708$12,000 - $14,000, \u6709\u91ab\u7642\u798f\u5229, \u4e0a\u53489\u6642\u81f3\u4e0b\u53486\u6642, \u6bcf\u9031\u5de5\u4f5c5\u5929,\u8f2a\u4f11, \u6bcf\u5929\u5de5\u4f5c 9 \u5c0f\u6642\n\n\u7533\u8acb\u9808\u77e5 :\u6c42\u8077\u8005\u53ef\u81f4\u96fb59049193\u8207\u91ab\u806f\u670d\u52d9\u6709\u9650\u516c\u53f8\u674e\u5c0f\u59d0\u806f\u7d61\u3002\n\n", "employment_types": ["Full Time"], "selling_points": [], "locations": ["Wong Tai Sin Area"], "categories": ["Education", "Tutor / Instructor", "Others", "Others", "Others"], "post_time": "2022-01-17T07:30:23Z", "salary": {"currency": null, "max": null, "min": null, "period": "monthly", "term": null}, "salary_visible": false, "title_keywords": [], "responsibilities": [], "requirements": {"degrees": [], "majors": [], "languages": [], "language_level": [], "hard_skills": [], "soft_skills": [], "languages_combined": []}, "experience_required": {"duration": [], "field": []}}, {"job_id": "100003009048211", "location_code": "hk", "company": "Lam Tai Fai College", "job_title": "\u6821\u5de5", "description": "As a\u00a0Centre Support Assistant, you directly report to the Senior Centre Director (Area) and take an active role in providing comprehensive support to you supervisor which includes but not limited to administrative support, data entry tasks, paperwork \u00a0and report preparation. Besides, you will carry out any special duties which assigned.\n\nResponsibilities:\n\n\nPerform internal co-ordination within Centres and Departments;\nProvide general administrative support and perform other ad-hoc duties requested by the supervisor;\nWorkweek and Workhours: Mon- Fri 10:00am- 7:00pm;\nWork Location: Kwun Tong & Jordan\n\n\nRequirements:\n\n\nPost-secondary educated with at least 1 year of working experience;\nExcellent computer skills;\nFriendly, outgoing and enthusiastic;\nFresh graduates are welcome.\n\nBenefits:\n\n\u00a0\u00a0 Medical Coverage (spouse included)\n\u00a0\u00a0 14 days annual leave\n\u00a0\u00a0 Bank holiday\n\u00a0\u00a0 OT pay\n\u00a0\u00a0 Study Sponsorship Programme\n\u00a0\u00a0 Study Leave and Exam Leave\n\u00a0\u00a0 Marriage Leave\n\u00a0\u00a0 Discretionary annual Bonus\n\u00a0\u00a0 Free English course\n\u00a0\u00a0 Full training provided\n\u00a0\u00a0 Dental Care Plan\n\u00a0\u00a0 Career progression opportunities within the organization\n\u00a0\u00a0 Modern, comfortable and attractive working environment\n\u00a0\u00a0 Staff activities and team building budget\n\nTo apply for this position, please send your application letter & resume with current and expected salary (MUST).\u00a0\n\n\n\nAll information received will be kept in strict confidence and for employment-related purposes only. Only short-listed applicants will be contacted for an interview. You may consider your application unsuccessful if you do not hear from us within six weeks from the closing date. Enquiries by telephone or other means regarding the receipt of your application or the progress of the recruitment exercise will not be entertained.\u00a0", "employment_types": ["Full Time"], "selling_points": [], "locations": ["Shatin Area"], "categories": ["Admin & HR", "Others", "Education", "Others", "Others", "Others"], "post_time": "2022-01-14T05:54:48Z", "salary": {"currency": null, "max": null, "min": null, "period": "monthly", "term": null}, "salary_visible": false, "title_keywords": [], "responsibilities": ["general administrative support", "ad-hoc duties"], "requirements": {"degrees": [], "majors": [], "languages": [], "language_level": [], "hard_skills": [], "soft_skills": [], "languages_combined": []}, "experience_required": {"duration": [], "field": []}}, {"job_id": "100003009053672", "location_code": "hk", "company": "SO-IN Yaumatei Education Centre (S.S.) Limited", "job_title": "\u6578\u5b78\u5c0e\u5e2b", "description": "\n\u4e3b\u8981\u8077\u8cac\uff1a\n\u8ca0\u8cac\u5eda\u85dd\u73ed\u524d\u7684\u6e96\u5099\u5de5\u4f5c (\u5305\u62ec\u98df\u6750\u53ca\u716e\u98df\u5eda\u5177\u7b49)\n\u2022 \u5354\u52a9\u8655\u7406\u65e5\u5e38\u71df\u904b\u4e8b\u52d9\u53ca\u8a2d\u5b9a\u98df\u8b5c\n\u2022 \u5354\u52a9\u8a02\u8cfc\u6216\u5916\u51fa\u8cfc\u8cb7\u98df\u6750\n\u2022 \u8f14\u52a9\u5eda\u85dd\u4e2d\u5fc3\u5c0e\u5e2b\u5728\u8ab2\u5802\u4e0a\u6307\u5c0e\u5b78\u54e1\n\u2022 \u63d0\u4f9b\u9867\u5ba2\u670d\u52d9\u53ca\u89e3\u7b54\u67e5\u8a62\n\u00a0 \u5165\u8077\u8981\u6c42\uff1a\n\u2022 \u4e2d\u5b78\u7a0b\u5ea6\u6216\u4ee5\u4e0a\n\u2022 \u71b1\u611b\u70f9\u98ea\n\u2022 \u6027\u683c\u958b\u6717\u3001\u89aa\u5207\u6709\u79ae\u3001\u614b\u5ea6\u8aa0\u61c7\n\u2022 \u80fd\u7368\u7acb\u5de5\u4f5c\n\u2022 \u6709\u5c08\u696d\u5eda\u85dd\u57f9\u8a13\u6216\u5eda\u623f\u5de5\u4f5c\u7d93\u9a57\u8005\u512a\u5148\u8003\u616e\n\n", "employment_types": ["Full Time"], "selling_points": [], "locations": ["Yau Ma Tei"], "categories": ["Education", "Tutor / Instructor", "Others", "Others", "Others"], "post_time": "2022-01-17T07:19:55Z", "salary": {"currency": null, "max": null, "min": null, "period": "monthly", "term": null}, "salary_visible": false, "title_keywords": [], "responsibilities": [], "requirements": {"degrees": [], "majors": [], "languages": [], "language_level": [], "hard_skills": [], "soft_skills": [], "languages_combined": []}, "experience_required": {"duration": [], "field": []}}, {"job_id": "100003009046224", "location_code": "hk", "company": "The Hong Kong University of Science and Technology", "job_title": "Assistant Officer (Building Maintenance) (Job ID: 7057)", "description": "Duties: The appointee will supervise a team to deliver a range of International and Professional examinations covering pre-during-post operations; assist in planning resources for the team, resolve any assessment /examinations irregularities and complaints; carry out the special arrangement for SEN candidates; assist in identifying improvement areas and propose changes to operation or procedures; communicate and coordinate with internal and external parties on the assessment/ examination operations with the objective of effectively administer various examinations/ assessments and contribute to ongoing operation and services improvement, and meeting the financial objectives within the given resources, timeline, relevant policies and guidelines of the International and Professional Examinations & Assessments Division and HKEAA.\nRequirements:\n(a)\u00a0\u00a0 \u00a0A Bachelor\u2019s degree in any discipline;\n(b)\u00a0\u00a0 \u00a0At least 5 years of experience in an administrative or operationally focused position or in the field of education or public sectors with at least two years in a supervisory position;\n(c)\u00a0\u00a0 \u00a0Knowledge of administration in a highly complex environment or examination operations desirable;\n(d)\u00a0\u00a0 \u00a0Interpersonal, organisational, problem solving and supervisory skills;\n(e)\u00a0\u00a0 \u00a0Hands-on experience with PC and system;\n(f)\u00a0\u00a0 \u00a0Experienced in customer service, complaint handling preferred;\n(g)\u00a0\u00a0 \u00a0Highly meticulous and ability to work under pressure and irregular hours; and\n(h)\u00a0\u00a0 \u00a0Proficiency in both written and spoken English and Chinese preferably including Putonghua.\nEmployment Terms:\u00a0 The remuneration package will be commensurate with qualifications and experience.\u00a0 Appointment will be on a fixed-term contract with contract-end-gratuity, MPF benefits, medical and dental care.\u00a0 Future employment may be offered on renewable contracts subject to performance and staffing needs.\nDate for Application Review: 21 January 2022\nApplications would be considered until the post is filled.\nApplication forms can be obtained from the HKEAA office on 13/F., Southorn Centre, 130 Hennessy Road, Wan Chai, Hong Kong or downloaded from the HKEAA website (www.hkeaa.edu.hk/tc/Career/general.html).\u00a0 Completed application forms should be returned to the Manager \u2013 Human Resources at the above address. Due to the secrecy nature of HKEAA's job duties, applicants invited for interview may be required to make a declaration of any conflict of interests. Applicants not notified within 10 weeks from the application review date should consider their applications unsuccessful.\nThe HKEAA is an equal opportunities employer and welcomes applications from all qualified candidates. Information provided relating to employment will be kept confidential and used only for processing applications. For details, please refer to the Policy Statement on Equal Opportunities and the Personal Information Collection Statement on the HKEAA website (www.hkeaa.edu.hk).", "employment_types": ["Full Time"], "selling_points": ["maintenance of building elements", "Carry out duties assigned for facilities", "Liaise with user departments, customers"], "locations": ["Sai Kung"], "categories": ["Admin & HR", "Clerical / Admin Staff", "Education", "Others", "Building & Construction", "Building / Construction / QS"], "post_time": "2022-01-13T10:01:14Z", "salary": {"currency": null, "max": null, "min": null, "period": "monthly", "term": null}, "salary_visible": false, "title_keywords": ["assistant officer"], "responsibilities": ["administration", "irregularities", "guidelines", "operations", "policies", "internal and external parties", "procedures", "coordinate with", "work under pressure", "customer service", "planning"], "requirements": {"degrees": ["degree", "bachelor"], "majors": [], "languages": ["putonghua", "english", "chinese"], "language_level": ["proficiency"], "hard_skills": ["problem solving", "pc", "c"], "soft_skills": ["meticulous", "focused", "problem solving", "hands-on", "customer service", "interpersonal", "work under pressure"], "languages_combined": [{"language": "putonghua", "language_level": ["proficiency"]}, {"language": "english", "language_level": ["proficiency"]}, {"language": "chinese", "language_level": ["proficiency"]}]}, "experience_required": {"duration": ["at least 5 years", "at least two years"], "field": ["supervisory", "administrative", "education"]}}, {"job_id": "100003009053755", "location_code": "hk", "company": "Creative Education Management Limited", "job_title": "Part time school tutor \u5230\u6821\u529f\u8ab2\u8f14\u5c0e\u73ed/\u8208\u8da3\u73ed/SEN \u6cbb\u7642\u5c0f\u7d44\u5c0e\u5e2b", "description": "Job responsibilities:\n\nProvides administrative and on-site support to Continuing Medical Education (CME) programmes;\nManages data filing system and reports for course administration;\nAssist in the publishing work for monthly magazine; and\nAssist in ad-hoc duties as assigned\nRequirements:\n\nUniversity graduate in Social Science or other relevant subjects with at least 1 year experience.\u00a0 Fresh graduate will also be considered;\nFamiliar with MS Office and social media platforms; and\nGood written and verbal communication skills;\nKnowledge in social media and meeting software (e.g Facebook and ZOOM)\u00a0 will be an added advantage\nImmediate available is preferred\n\nApplication letters in\u00a0BOTH\u00a0Chinese and English with full resume, present and expected salary and date available should be sent to Human Resources Team of the Hong Kong Medical Association.\n\n\n(Personal data collected for recruitment purpose only)", "employment_types": ["Full Time"], "selling_points": [], "locations": ["Not Specified"], "categories": ["Education", "Others", "Others", "Others"], "post_time": "2022-01-17T07:28:00Z", "salary": {"currency": null, "max": null, "min": null, "period": "monthly", "term": null}, "salary_visible": false, "title_keywords": ["tutor"], "responsibilities": ["administration", "reports", "ad-hoc duties", "data"], "requirements": {"degrees": ["university graduate", "fresh graduate"], "majors": ["science"], "languages": ["english", "chinese"], "language_level": [], "hard_skills": ["facebook", "ms office"], "soft_skills": ["communication skills"], "languages_combined": [{"language": "english", "language_level": []}, {"language": "chinese", "language_level": []}]}, "experience_required": {"duration": ["at least 1 year"], "field": []}}, {"job_id": "100003009046253", "location_code": "hk", "company": "The Hong Kong University of Science and Technology", "job_title": "Assistant Officer (Registry Systems)(Job ID: 7058)", "description": "Job Description: Media Studies Teacher\n\nJob roles and responsibilities:\n\nKorean International School is seeking an enthusiastic Media Studies Teacher to join our high achieving, student centred department. The successful candidate should be able to teach across all key stages. Experience teaching the UK curriculum IGCSE and A-levels would be preferred.\n\nPlan and develop exciting lessons to teach Media Studies to students from Year 7 to 13\nTake responsibility for secondary classes, in supporting, nurturing and taking a genuine interest in the holistic development of all students\nCreate inquiry-based classrooms that develop critical thinking skills, knowledge and a range of skills within an environment based on trust and respect\nReport to the Heads of Department and work closely with the Heads of School and other colleagues to ensure the effective delivery of the planned Media Studies curriculums\nTo assist the Heads of Department in maintaining and improving the standard within the department\nCreate high quality curriculum materials that cater for students of all abilities and needs\nTo assist in curriculum development within the department\nIntegrate technology into pedagogy to follow school wide learning initiatives\n\nRequirements for Media Studies teacher:\n\n\nMinimum of a Bachelor's degree in related subject and PGCE / PGDE or equivalent\u00a0\u00a0\nProven experience of teaching Media to A Level\u00a0\nMinimum of two years\u2019 UK curriculum teaching experience\nAbility to build rapport with students aged 11-18\nExcellent communication and presentation skills\nA creative and enthusiastic approach both in and out of the classroom\u00a0\u00a0\nExcellent IT and interpersonal communication skills to work closely with students and parents\nThis job description may be reviewed at the end of the academic year or earlier if necessary. In addition, it may be amended at any time after consultation with you.\n\n\u00a0How to apply:\n\nInterested candidates please send your full CV by clicking \"Apply Now\".\u00a0 Only shortlisted candidates will be contacted.\n\nAll personal data collected will be used for recruitment purposes only and will be kept strictly confidential.", "employment_types": ["Full Time"], "selling_points": ["implementing e-forms and approval workflows", "improving user experience on Registry\u2019s website", "liaising with users, staff, students"], "locations": ["Sai Kung"], "categories": ["Admin & HR", "Clerical / Admin Staff", "Education", "Others", "Information Technology (IT)", "Others"], "post_time": "2022-01-13T10:06:40Z", "salary": {"currency": null, "max": null, "min": null, "period": "monthly", "term": null}, "salary_visible": false, "title_keywords": ["assistant officer"], "responsibilities": ["maintaining", "quality", "develop", "plan", "report"], "requirements": {"degrees": ["degree", "bachelor"], "majors": [], "languages": [], "language_level": [], "hard_skills": [], "soft_skills": ["communication skills", "communication", "presentation skills", "enthusiastic", "creative", "interpersonal"], "languages_combined": []}, "experience_required": {"duration": ["minimum of two years"], "field": ["teaching", "media"]}}, {"job_id": "100003009043059", "location_code": "hk", "company": "Kaplan Financial (HK) Limited", "job_title": "Officer, Program Management", "description": "\n\u5de5\u4f5c\u5185\u5bb9:\n\u2022 \u5354\u52a9\u5e97\u8216\u65e5\u5e38\u904b\u4f5c\n\u2022 \u63d0\u4f9b\u512a\u8cea\u9867\u5ba2\u670d\u52d9\n\u2022 \u5354\u52a9\u9867\u5ba2\u9078\u8cfc\u5408\u9069\u7684\u8ca8\u54c1\n\u2022 \u4fdd\u6301\u8ca8\u5834\u6574\u9f4a\u6e05\u6f54\n\u5de5\u4f5c\u8981\u6c42:\n\u2022 \u5177\u76f8\u95dc\u5de5\u4f5c\u7d93\u9a57\u8005\u6703\u88ab\u512a\u5148\u8003\u616e\n\u2022 \u826f\u597d\u6e9d\u901a\u53ca\u4eba\u969b\u6280\u5de7\n\u2022 \u4e3b\u52d5\u71b1\u8aa0\n\u2022 \u4e2d\u6587\u8f38\u5165\u6cd5\n\u5de5\u4f5c\u985e\u578b: \u5168\u8077, \u9577\u671f\n\u85aa\u916c: \u9762\u8b70\n\u6642\u9593:\n\u2022 \u65e5\u73ed\n\u798f\u5229:\n\u2022 \u54e1\u5de5\u8cfc\u7269\u512a\u60e0\n\u2022 \u81b3\u98df\u88dc\u8cbc\n\u88dc\u5145\u85aa\u916c:\n\u2022 \u4f63\u91d1\n\u2022 \u8d85\u6642\u52a0\u73ed\u8cbb\n\u2022 \u52e4\u5de5\u734e\u91d1\nApply Now\n\n", "employment_types": ["Full Time", "Permanent"], "selling_points": ["5-day work week; Flexible Working Hour", "Excellent Career Development Opportunities", "Friendly working environment"], "locations": ["Wan Chai"], "categories": ["Admin & HR", "Clerical / Admin Staff", "Others", "Education", "Others"], "post_time": "2022-01-12T09:41:00Z", "salary": {"currency": null, "max": null, "min": null, "period": "monthly", "term": null}, "salary_visible": false, "title_keywords": ["officer"], "responsibilities": [], "requirements": {"degrees": [], "majors": [], "languages": [], "language_level": [], "hard_skills": [], "soft_skills": [], "languages_combined": []}, "experience_required": {"duration": [], "field": []}}, {"job_id": "100003009039959", "location_code": "hk", "company": "HKU SPACE Po Leung Kuk Stanley Ho Community College", "job_title": "Executive Officer  (Ref: SD/ft/22-01)", "description": "\n\u8077\u8cac :\u4e00\u822c\u6821\u5de5\u5de5\u4f5c, \u6821\u820d/\u5b78\u6821\u6e05\u6f54, \u4e00\u822c\u9ad4\u529b\u52de\u52d5\u8077\u52d9\uff0c\u642c\u904b\u50a2\u4fec\u96dc\u7269\u53ca\u5834\u5730\u64fa\u8a2d, \u5916\u52e4, \u4e00\u822c\u5eb6\u52d9\u5de5\u4f5c\n\n\u8cc7\u6b77 :\u5c0f\u4e00\u7a0b\u5ea6; 1\u5e74\u7d93\u9a57; \u826f\u597d\u7cb5\u8a9e; \u61c2\u8b80\u5beb\u4e2d\u6587\n\n\u5f85\u9047 :\u6bcf\u6708$12,000 - $13,000, \u6709\u91ab\u7642\u798f\u5229, \u661f\u671f\u4e00\u81f3\u4e94: \u4e0a\u53488\u6642\u81f3\u4e0b\u53486\u6642\u53ca\u661f\u671f\u516d: \u4e0a\u53489\u6642\u81f3\u4e0b\u53481\u6642, \u6bcf\u9031\u5de5\u4f5c5\u5929\u534a\n\n\u7533\u8acb\u9808\u77e5 :\u6c42\u8077\u8005\u53ef\u81f4\u96fb27861990\u8207\u6797\u5927\u8f1d\u4e2d\u5b78\u5510\u5148\u751f\u806f\u7d61\u3002\n\n", "employment_types": ["Full Time", "Contract"], "selling_points": ["administrative support to a student centre", "event planning and liaison with various parties", "management of social media platforms"], "locations": ["Causeway Bay"], "categories": ["Education", "Others"], "post_time": "2022-01-11T16:02:20Z", "salary": {"currency": null, "max": null, "min": null, "period": "monthly", "term": null}, "salary_visible": false, "title_keywords": ["executive officer"], "responsibilities": [], "requirements": {"degrees": [], "majors": [], "languages": [], "language_level": [], "hard_skills": [], "soft_skills": [], "languages_combined": []}, "experience_required": {"duration": [], "field": []}}, {"job_id": "100003009051995", "location_code": "hk", "company": "L & K Education Consultancy Limited", "job_title": "Senior / Education Consultant (UK) (5 days work week)", "description": "\n\u8077\u8cac :Conduct tutorial Class, S.1-S.6, Prepare Teaching Materials, Daily Administrative Work\n\n\u8cc7\u6b77 :\u5c08\u4e0a\u6559\u80b2\uff1a\u5b78\u58eb\u5b78\u4f4d; 1\u5e74\u7d93\u9a57; \u826f\u597d\u7cb5\u8a9e; \u826f\u597d\u666e\u901a\u8a71; \u826f\u597d\u82f1\u8a9e; \u61c2\u8b80\u5beb\u4e2d\u6587; \u61c2\u8b80\u5beb\u82f1\u6587; \u61c2Microsoft Office; \u5177\u6709\u4e00\u822c\u4e92\u806f\u7db2\u77e5\u8b58; \u61c2\u4e2d\u6587\u6253\u5b57\n\n\u5f85\u9047 :\u6bcf\u6708$13,000 - $19,000, \u6709\u91ab\u7642\u798f\u5229 \u53ca\u8868\u73fe\u734e\u91d1, \u4e8c,\u4e09,\u4e94: \u4e0a\u534810\u6642\u534a\u81f3\u4e0b\u53487\u664215\u5206,\u4e00,\u56db: \u4e0b\u53482\u6642\u81f3\u4e0b\u53487\u664215\u5206\u53ca\u661f\u671f\u516d: \u4e0a\u53489\u664215\u5206\u81f3\u4e0b\u53487\u664215\u5206, \u6bcf\u9031\u5de5\u4f5c5\u5929, \u6bcf\u5929\u5de5\u4f5c 5 - 10 \u5c0f\u6642\n\n\u7533\u8acb\u9808\u77e5 :\u6c42\u8077\u8005\u53ef\u96fb\u90f5(Apply Now)\u5c65\u6b77\u8868\u7d66\u6578\u7814\u6cb9\u9ebb\u5730\u6559\u80b2\u4e2d\u5fc3(\u4e2d\u5b78\u90e8)\u6709\u9650\u516c\u53f8\u3002\u5982\u8981\u7d22\u53d6\u6536\u96c6\u500b\u4eba\u8cc7\u6599\u8072\u660e, \u8acb\u8207\u674e\u5148\u751f(Email)\u806f\u7d61\u3002\n\n", "employment_types": ["Full Time"], "selling_points": ["Full-time (5 days work week)", "Education", "Study experience in UK / overseas"], "locations": ["Causeway Bay"], "categories": ["Education", "Others", "Sales, CS & Business Devpt", "Direct Sales"], "post_time": "2022-01-17T01:47:12Z", "salary": {"currency": null, "max": null, "min": null, "period": "monthly", "term": null}, "salary_visible": false, "title_keywords": ["education consultant"], "responsibilities": ["administrative work", "prepare teaching materials"], "requirements": {"degrees": [], "majors": [], "languages": [], "language_level": [], "hard_skills": [], "soft_skills": [], "languages_combined": []}, "experience_required": {"duration": [], "field": []}}, {"job_id": "100003009047497", "location_code": "hk", "company": "The University of Hong Kong", "job_title": "Research Assistant I/II (several posts) (Ref.: 511380)", "description": "Job Title:\u00a0 \u00a0 \u00a0 \u00a0\u00a0Assistant Officer (Building Maintenance)\nDepartment:\u00a0\u00a0Campus Management Office\nJob ID:\u00a0 \u00a0 \u00a0 \u00a0 \u00a0 \u00a07057\n\nJob Posting Details\n\nThe Building Maintenance Unit of the Campus Management Office is responsible for managing all aspects of building maintenance with an aim to provide a well-maintained, safe and sustainable environment for all campus users.\u00a0 We are looking for a high calibre candidate to join the Unit.\u00a0 The appointee will be responsible for the following:\nPlan, organize and execute works relating to repairs and maintenance of building elements, building improvement and construction activities on campus;\n\n\nCarry out duties assigned for facilities and property management and assist in event organization;\n\n\nLiaise with user departments, customers, contractors, statutory bodies, consultants, utilities companies and in-house office/sections on carrying out building facilities works and services;\n\n\n\u00a0Manage, monitor and inspect contractor/consultant performance and quality of work;\n\n\n\u00a0Ensure compliance with statutory and safety requirements; and\n\n\nPerform any responsibilities as assigned by senior management.\nApplicants should have a degree in building technology, construction, building surveying or related disciplines; or an associate degree/higher diploma/higher certificate in building technology, construction, building surveying or related disciplines with at least 1 year of relevant experience in building maintenance or building facilities management.\u00a0 Proficiency in written and spoken English and Chinese is a must and proficiency in Putonghua is preferred.\u00a0 Knowledge in AutoCAD is an advantage. (Duration: 1 year)\n\n(Applicants who have responded to the previous advertisement on 17 Dec 2021 need not re-apply.)\n\n\nFringe benefits including annual leave, medical and dental benefits will be provided where applicable.\n\nApplication Procedure\nIn support of a green work environment, we accept applications submitted online only.\u00a0 To apply, please complete an online application form through the HKUST Careers website (https://hkustcareers.ust.hk) and return it online to the Human Resources Office on or before Thursday, 27 January 2022.\u00a0 Applicants will receive an acknowledgement by email upon successful submission.\u00a0 We thank applicants for their interest, but advise that only shortlisted candidates will be notified of the result of the application.\n(Information provided by applicants will be used for recruitment and other employment-related purposes only.)\n\nHKUST is an equal opportunities employer and is committed to our core values of\ninclusiveness, diversity, and respect.", "employment_types": ["Full Time"], "selling_points": [], "locations": ["Not Specified"], "categories": ["Public / Civil", "Counseling", "Education", "Others", "Medical Services", "Others"], "post_time": "2022-01-14T03:20:24Z", "salary": {"currency": null, "max": null, "min": null, "period": "monthly", "term": null}, "salary_visible": false, "title_keywords": ["research assistant"], "responsibilities": ["management", "maintenance", "monitor", "quality", "ensure compliance", "plan", "liaise with", "senior management"], "requirements": {"degrees": ["higher certificate", "associate degree", "diploma", "degree"], "majors": ["related disciplines", "building surveying"], "languages": ["putonghua", "english", "chinese"], "language_level": ["proficiency"], "hard_skills": ["maintenance", "id", "facilities management", "safe", "autocad"], "soft_skills": ["responsible"], "languages_combined": [{"language": "putonghua", "language_level": ["proficiency"]}, {"language": "english", "language_level": ["proficiency"]}, {"language": "chinese", "language_level": ["proficiency"]}]}, "experience_required": {"duration": ["at least 1 year"], "field": ["management", "maintenance", "related", "relevant experience", "building surveying", "construction"]}}, {"job_id": "100003009041892", "location_code": "hk", "company": "Caritas Institute of Higher Education", "job_title": "Administrative Officer [Part Time] (Ref.: 22/10/BHM/AO)", "description": "Job Responsibilities:\n\n\u00a0\u00a0\u00a0\u00a0\u00a0\u00a0\u00a0\u00a0 Build and maintain strong relationship with existing clients\n\u00a0\u00a0\u00a0\u00a0\u00a0\u00a0\u00a0\u00a0 Answer enquiries from parents, students and referring agencies professionally\n\u00a0\u00a0\u00a0\u00a0\u00a0\u00a0\u00a0\u00a0 Understand clients\u2019 needs and provide suitable solutions\n\u00a0\u00a0\u00a0\u00a0\u00a0\u00a0\u00a0\u00a0 Provide after-sale services to enhance customer satisfaction\n\u00a0\u00a0\u00a0\u00a0\u00a0\u00a0\u00a0\u00a0 Introduce and follow up education programs\u00a0that base on students\u2019 needs and ability\u00a0to enhance continuous service\n\u00a0\u00a0\u00a0\u00a0\u00a0\u00a0\u00a0\u00a0 Assist \u00a0in ad hoc projects\n\n\u00a0Essential Qualities\n\n\u00a0\u00a0\u00a0\u00a0\u00a0\u00a0\u00a0\u00a0 Higher diploma or above in any discipline\n\u00a0\u00a0\u00a0\u00a0\u00a0\u00a0\u00a0\u00a0 Good command of spoken and written English, Cantonese and Mandarin\u00a0\n\u00a0\u00a0\u00a0\u00a0\u00a0\u00a0\u00a0\u00a0 Possess problem-solving skills\u00a0and good listening skills to tailor the best solution according to clients' needs\n\u00a0\u00a0\u00a0\u00a0\u00a0\u00a0\u00a0\u00a0 Able to prioritize and handle multiple tasks simultaneously\n\u00a0\u00a0\u00a0\u00a0\u00a0\u00a0\u00a0\u00a0 A good team player and good interpersonal skills\u00a0\n\u00a0\u00a0\u00a0\u00a0\u00a0\u00a0\u00a0\u00a0 Candidate with more experience will be considered as senior customer service representative\n\nWhat We Offer\n\n\u00a0\u00a0\u00a0\u00a0\u00a0\u00a0\u00a0\u00a0 5-day work week in a vibrant and multicultural work environment\n\u00a0\u00a0\u00a0\u00a0\u00a0\u00a0\u00a0\u00a0 Prime working location in the heart of Hong Kong\n\u00a0\u00a0\u00a0\u00a0\u00a0\u00a0\u00a0\u00a0 Comprehensive training and professional development program\n\u00a0\u00a0\u00a0\u00a0\u00a0\u00a0\u00a0\u00a0 Career advancement opportunities in a market leading organisation\n\u00a0\u00a0\u00a0\u00a0\u00a0\u00a0\u00a0\u00a0 Medical benefits and monthly wellness sponsorship for leisure activities\n\u00a0\u00a0\u00a0\u00a0\u00a0\u00a0\u00a0\u00a0 Competitive remuneration package and incentive schemes\n\nWorking location: Causeway Bay / Kowloon City\n\nInterested parties should send a detailed CV and cover letter with expected salary to our recruitment email.\n\nNote:\u00a0Shortlisted applicants will be\u00a0invited to interview by HR staff and interview details will be confirmed by NTK official email.", "employment_types": ["Contract"], "selling_points": [], "locations": ["Tseung Kwan O"], "categories": ["Admin & HR", "Clerical / Admin Staff", "Education", "Others", "Management", "General Management"], "post_time": "2022-01-12T04:35:27Z", "salary": {"currency": null, "max": null, "min": null, "period": "monthly", "term": null}, "salary_visible": false, "title_keywords": ["administrative officer"], "responsibilities": ["customer service", "maintain", "ad hoc projects"], "requirements": {"degrees": ["higher diploma or above"], "majors": [], "languages": ["cantonese", "english", "mandarin"], "language_level": ["good command"], "hard_skills": ["problem-solving skills"], "soft_skills": ["good team player", "able to prioritize", "handle multiple tasks", "customer service", "interpersonal skills", "problem-solving skills"], "languages_combined": [{"language": "cantonese", "language_level": ["good command"]}, {"language": "english", "language_level": ["good command"]}, {"language": "mandarin", "language_level": ["good command"]}]}, "experience_required": {"duration": [], "field": ["customer service"]}}, {"job_id": "100003009046533", "location_code": "hk", "company": "See You at the Top", "job_title": "Sales Officer / Manager", "description": "\n\u62db\u8058\u5230\u6821\u529f\u8ab2\u8f14\u5c0e\u73ed/\u8208\u8da3\u73ed/SEN \u6cbb\u7642\u5c0f\u7d44\u5c0e\u5e2b\n\u529f\u8ab2\u8f14\u5c0e\u73ed\uff1a\u6559\u6388\u5c0f\u5b78\u751f\u82f1\u6587\u548c\u6578\u5b78\uff0c\u5354\u52a9\u4ed6\u5011\u89e3\u6c7a\u5b78\u7fd2\u4e0a\u7684\u554f\u984c\u3002\n\u5404\u985e\u8208\u8da3\u73ed\uff1a\u82b1\u5f0f\u8df3\u7e69\u3001\u526a\u7d19\u3001\u6c99\u756b\u3001\u5e03\u85dd\u3001\u96dc\u800d\u3001\u82ac\u862d\u6728\u68cb\u3001\u4e2d\u570b\u821e\u3001\u9676\u85dd\u3001\u8edf\u5f0f\u98db\u6a19\u7b49\u7b49\nSEN\u6cbb\u7642\u5c0f\u7d44\uff1a\u611f\u7d71\u6cbb\u7642\u3001\u97f3\u6a02\u6cbb\u7642\u3001\u793e\u4ea4\u60c5\u7dd2\u3001\u5c08\u6ce8\u529b\u3001\u751f\u6daf\u898f\u5283\u5c0f\u7d44\u7b49\u7b49\n\u5de5\u4f5c\u8207\u5152\u7ae5\u6709\u95dc,\u6e96\u50f1\u54e1\u9700\u81ea\u9858\u9032\u884c\u300a\u6027\u7f6a\u884c\u5b9a\u7f6a\u7d00\u9304\u67e5\u6838\u300b\u3002\n\u6642\u9593\uff1a\u9022\u661f\u671f\u4e00\u81f3\u516d (\u5176\u4e2d1-3\u5929\u7686\u53ef) 14:00-18:00\u00a0\n\u85aa\u916c\uff1a\u00a0\n\u529f\u8ab2\u8f14\u5c0e\u73ed\uff1a$80-120/\u5c0f\u6642\n\u8208\u8da3\u73ed\u53caSEN\u6cbb\u7642\u5c0f\u7d44\uff1a\u9762\u898b\u5546\u8b70 (\u8996\u4e4e\u8cc7\u6b77)\n\u8981\u6c42\uff1a\u5927\u5c08\u7a0b\u5ea6\u6216\u4ee5\u4e0a\uff0c\u5b88\u6642\u3001\u76e1\u8cac\n\n", "employment_types": ["Full Time", "Part Time", "Permanent", "Freelance"], "selling_points": ["World renowned training - impacted >250 million", "Hard working & honest ones will get Good Income", "4-Day Week; 3-Week Annual Leave; Family Vacation"], "locations": ["Wan Chai Area"], "categories": ["Sales, CS & Business Devpt", "Business Development", "Education", "Others", "Marketing / Public Relations", "Marketing - General / Support"], "post_time": "2022-01-13T18:55:24Z", "salary": {"currency": "HKD", "max": 69999, "min": 25000, "period": "monthly", "term": null}, "salary_visible": true, "title_keywords": ["sales officer", "manager"], "responsibilities": [], "requirements": {"degrees": [], "majors": [], "languages": [], "language_level": [], "hard_skills": [], "soft_skills": [], "languages_combined": []}, "experience_required": {"duration": [], "field": []}}, {"job_id": "100003009043693", "location_code": "hk", "company": "Hong Kong Institute of Technology", "job_title": "Assistant Campus Counsellor", "description": "Lingnan University, a distinctive liberal arts institution in the Hong Kong Special Administrative Region, is committed to the provision of quality whole-person education by combining the best of Chinese and Western liberal arts traditions. It strives to pursue excellence in teaching, learning, scholarship and community engagement. With three academic Faculties, it offers a wide range of undergraduate degree programmes in arts, business and social sciences. Lingnan\u2019s liberal arts education is characterised by a broad-based interdisciplinary curriculum with specialised disciplinary studies; close student-staff relationship; a vibrant residential campus; ample global learning opportunities; active community engagement and multifarious workplace experience. The School of Graduate Studies also offers postgraduate programmes up to doctoral level in various disciplines and provides professional education for the wider society.\u00a0 Applications are now invited for the following post:\n\nInstitutional Advancement Officer\nOffice of Institutional Advancement and Alumni Affairs\u00a0\n(Post Ref.: 21/273)\n\nResponsibilities\nHandling donation transactions\nAssisting in organising fundraising activities, programmes and donor networking activities\nCollecting and compiling data of donors and maintaining donors\u2019 database\nAssisting in maintaining effective liaison and relationships with donors\nRequirements\nA recognized degree\nFluent in written and spoken English and Chinese (including Putonghua)\nGood organisation, communication and presentation skills\nAt least 1 year\u2019s work experience\nExperience in organising events/fundraising activities would be a definite advantage\nCandidates with less/more experience will also be considered for appointment at a relevant rank.\n\nSalary and Fringe Benefits\nThe rank and commencing salary will be commensurate with qualifications and experience.\u00a0 Fringe benefits, where applicable, include annual leave, medical and dental benefits, mandatory provident fund and gratuity.\n\nApplication Procedure\u00a0(online application only)\nPlease click \"Apply Now\" to submit your application. \u00a0Personal data collected will be used for recruitment purposes only.\n\nWe are an equal opportunities employer.\u00a0Review of applications will continue until the post is filled.\u00a0 Qualified candidates are advised to submit their applications early for consideration.\n\nThe University reserves the right not to make an appointment for the post advertised, or to fill the post by invitation or by search.\u00a0 We regret that only shortlisted candidates will be notified.", "employment_types": ["Full Time"], "selling_points": [], "locations": ["Lai Chi Kok"], "categories": ["Admin & HR", "Administration / Operation Manager", "Public / Civil", "Counseling", "Education", "Others"], "post_time": "2022-01-13T01:31:01Z", "salary": {"currency": null, "max": null, "min": null, "period": "monthly", "term": null}, "salary_visible": false, "title_keywords": ["assistant"], "responsibilities": ["database", "maintaining", "transactions", "data"], "requirements": {"degrees": ["degree"], "majors": [], "languages": ["putonghua", "english", "chinese"], "language_level": ["fluent"], "hard_skills": [], "soft_skills": ["communication", "presentation skills", "organisation"], "languages_combined": [{"language": "putonghua", "language_level": ["fluent"]}, {"language": "english", "language_level": ["fluent"]}, {"language": "chinese", "language_level": ["fluent"]}]}, "experience_required": {"duration": ["at least 1 year"], "field": []}}, {"job_id": "100003009054471", "location_code": "hk", "company": "Ed Pro Learning Centre Limited", "job_title": "Tutors (Math / Physics) - Full Time (Junior / Senior)", "description": "Job Title:\u00a0\u00a0\u00a0\u00a0\u00a0\u00a0\u00a0\u00a0\u00a0\u00a0Assistant Officer (Registry Systems)\nDepartment:\u00a0 \u00a0 \u00a0Academic Registry\nJob ID:\u00a0 \u00a0 \u00a0 \u00a0 \u00a0 \u00a0 \u00a0\u00a07058\n\nJob Posting Details\n\nThe Academic Registry is looking for an appointee to work in the Registry Systems team providing services to the University community.\n\nThe appointee will assist in various IT projects related to office digitalization and automation. Duties include:\n\n(a) implementing e-forms and approval workflows by using low-code development tools; supporting the existing e-form services as well as assisting users to automate their business processes;\n\n(b) improving user experience on Registry\u2019s website by employing technologies such as Chatbot;\n\n(c)\u00a0 installing, maintaining and troubleshooting various computer systems including desktop equipment and software, in particular PCs, Mac, mobile/tablet devices, Microsoft 365, Microsoft Office and other popular software;\n\n(d)\u00a0\u00a0 liaising with users, staff, students and other parties to solve IT or system-related problems; and\n\n(e)\u00a0\u00a0\u00a0 performing other duties as assigned.\n\nApplicants should either be fresh graduates with a bachelor\u2019s degree, or have an associate degree or higher diploma in information systems, information technology, computer science or other equivalent disciplines with at least 1 year of post-qualification relevant work experience.\u00a0 They should possess a logical and meticulous mind with good analytical and be detail-oriented, as well as effective communication skills with a good command of spoken and written English.\u00a0 Knowledge and experience in development tools such as Microsoft Power Platform will be an advantage. (Duration: 1 year)\n\nFringe benefits including annual leave, medical and dental benefits will be provided where applicable.\u00a0\u00a0\n\nApplication Procedure\nIn support of a green work environment, we accept applications submitted online only.\u00a0 To apply, please complete an online application form through the HKUST Careers website (https://hkustcareers.ust.hk) and return it online to the Human Resources Office on or before Friday, 11February 2022.\u00a0 Applicants will receive an acknowledgement by email upon successful submission.\u00a0 We thank applicants for their interest, but advise that only shortlisted candidates will be notified of the result of the application.\n\n(Information provided by applicants will be used for recruitment and other employment-related purposes only.)\n\nHKUST is an equal opportunities employer and is committed to our core values of\ninclusiveness, diversity, and respect.", "employment_types": ["Full Time"], "selling_points": [], "locations": ["Yau Ma Tei"], "categories": ["Education", "Teacher", "Tutor / Instructor", "Others"], "post_time": "2022-01-17T09:41:21Z", "salary": {"currency": null, "max": null, "min": null, "period": "monthly", "term": null}, "salary_visible": false, "title_keywords": ["junior"], "responsibilities": ["software", "maintaining", "other duties", "systems", "pcs", "user experience", "website", "troubleshooting", "computer systems", "liaising with", "communication", "installing"], "requirements": {"degrees": ["associate degree", "diploma", "degree", "bachelor"], "majors": ["computer science", "information technology"], "languages": ["english"], "language_level": ["good command", "good"], "hard_skills": ["microsoft office", "id", "computer systems", "mobile", "c", "code"], "soft_skills": ["communication skills", "meticulous", "troubleshooting", "detail-oriented"], "languages_combined": [{"language": "english", "language_level": ["good command", "good"]}]}, "experience_required": {"duration": ["at least 1 year"], "field": ["development", "post-qualification", "information technology"]}}, {"job_id": "100003009044518", "location_code": "hk", "company": "UBC Asia Pacific Regional Office Limited", "job_title": "Officer, Development & Alumni Engagement", "description": "Responsibilities:\nManaging training courses in Accountancy team, including the logistic of materials & classroom sessions, timetable scheduling, lecturer arrangements, the maintenance of student records & online learning platform, the handling of internal programme meeting and complaints etc.\nMaintaining a close communication with corporate clients, students, lecturers, external bodies, and examiners for building a good relationship\nWorking after regular office hours and/or at weekends/public holidays will be required occasionally\nSupporting the Marketing and Course Consultation Teams in event organizations\nRequirements:\nA degree holder with 2 years' post-qualification experience. Candidates with less experience will be considered as Assistant Officer,\u00a0Program Management\nRelevant administrative experience preferably in education setting\nCapable to manage large student population\nA good command of written and spoken English and Chinese\nProficiency in using computer applications including Microsoft Office\nGood organisational, communication, problem-solving and multi-tasking skills\nAbility to work independently and willingness to take up responsibilities\nKaplan helps individuals achieve their educational and career goals. ACTION NOW and send your application letter with full resume stating present and expected salary as well as availability to: Human Resources Department, Kaplan Hong Kong via \"Apply Now\" today!! Attractive remunerations will be offered to successful candidates!", "employment_types": ["Full Time"], "selling_points": [], "locations": ["Causeway Bay"], "categories": ["Education", "Others"], "post_time": "2022-01-13T18:55:02Z", "salary": {"currency": null, "max": null, "min": null, "period": "monthly", "term": null}, "salary_visible": false, "title_keywords": ["officer"], "responsibilities": ["maintaining", "maintenance", "teams", "student records", "communication", "scheduling", "good relationship"], "requirements": {"degrees": ["degree holder"], "majors": [], "languages": ["english", "chinese"], "language_level": ["good command"], "hard_skills": ["problem-solving", "microsoft office"], "soft_skills": ["work independently", "capable", "problem-solving", "communication", "multi-tasking skills"], "languages_combined": [{"language": "english", "language_level": ["good command"]}, {"language": "chinese", "language_level": ["good command"]}]}, "experience_required": {"duration": ["2 years"], "field": ["management", "administrative", "post-qualification", "education"]}}, {"job_id": "100003009047438", "location_code": "hk", "company": "The University of Hong Kong", "job_title": "Research Assistant I/II (Ref.: 511395)", "description": "Major Duties\n\nThe appointee will be required to\n\n-\u00a0 \u00a0provide administrative support to the Student Development Resource Centre;\n\n-\u00a0 \u00a0assist in daily centre operations and handle enquiries;\n\n-\u00a0 \u00a0liaise with internal and external parties in different fields and support the planning and organisation of functions, activities and events;\n\n-\u00a0 \u00a0manage and create content for social media platforms;\n\n-\u00a0 \u00a0contribute to the implementation of new projects; and\n\n-\u00a0 \u00a0perform other duties as assigned by supervisors.\n\nQualifications Required\n\nCandidates should have (i) a Bachelor\u2019s degree with at least 5 years of administrative experience, \u00a0preferably in Social Science, Social Administration, Youth Studies or related disciplines; (ii) good interpersonal skills and language proficiency; (iii) experience in organising student activities; (iv) ability to manage multiple tasks and work independently; and (iv) high proficiency in Microsoft Office (advanced knowledge in Excel is an advantage).\n\nCandidates with less experience will be considered for the position of Assistant Executive Officer.\n\nRemuneration and Conditions of Service\n\nSalary will be commensurate with qualifications and experience. Fringe benefits include contract-end gratuity, medical benefits, and staff development sponsorship. Initial appointment will be on a fixed-term contract for up to two years. Re-engagement thereafter is subject to mutual agreement.\n\nApplication\n\nPlease send your full curriculum vitae (with your current and expected salary) by email\u00a0or by post to HKU SPACE Po Leung Kuk Stanley Ho Community College, 18/F, 66 Leighton Road, Causeway Bay, Hong Kong. You should indicate the full title and job reference number of the post you are applying for.\n\nAll applications will be treated in strict confidence. Only those who are shortlisted will be contacted. The College reserves the right not to fill the posts advertised.\n\nClosing date:\u00a0 26 January 2022", "employment_types": ["Full Time"], "selling_points": ["possess a Bachelor\u2019s degree or above", "with experience in computer programming", "with experience in  data management"], "locations": ["Not Specified"], "categories": ["Education", "Others", "Information Technology (IT)", "Others", "Marketing / Public Relations", "Marketing - Market Research"], "post_time": "2022-01-14T03:05:54Z", "salary": {"currency": null, "max": null, "min": null, "period": "monthly", "term": null}, "salary_visible": false, "title_keywords": ["research assistant"], "responsibilities": ["administration", "perform other duties", "operations", "internal and external parties", "social media platforms", "implementation", "handle enquiries", "liaise with", "provide administrative support", "planning"], "requirements": {"degrees": ["degree", "bachelor"], "majors": ["related disciplines", "science"], "languages": [], "language_level": [], "hard_skills": ["excel", "microsoft office"], "soft_skills": ["work independently", "advanced", "multiple tasks", "interpersonal skills", "organisation"], "languages_combined": []}, "experience_required": {"duration": ["at least 5 years"], "field": ["related", "administrative", "administration"]}}, {"job_id": "100003009044386", "location_code": "hk", "company": "HKU School of Professional & Continuing Education", "job_title": "Temporary Research Assistant II in the College of Humanities and Law", "description": "Work type:\u00a0Full-time\nDepartment:\u00a0Department of Psychiatry (21500)\nCategories:\u00a0Research Support Staff\n\nResearch Assistant I/II (several posts) in the Department of Psychiatry\u00a0(Ref.: 511380) (to commence as soon as possible on a one-year temporary basis or two-year fixed-term basis, with the possibility of renewal subject to satisfactory performance)\n\nThis is an exciting opportunity for the appointee to join the multidisciplinary PSI team based at the Department of Psychiatry, University of Hong Kong. The PSI team, made up of enthusiastic and highly motivated researchers and clinicians, is internationally renowned for its\u00a0contribution towards clinical research in psychiatry and mental disorders. The Team\u2019s research provides significant insight and acts as an important informer for front-line mental health services.\n\nApplicants should possess a Bachelor\u2019s degree in psychology, social sciences,\u00a0or other healthcare-related disciplines. They should have an excellent command of written and spoken English and Chinese, the willingness to learn new skills, a strong commitment to high quality research, good organizational, communication, and interpersonal skills, and the ability to prioritize work and maintain a high level of effectiveness. The team is looking for an individual with high calibre to take part in clinical research projects with diverse interests, such as interventions and outcome measures of early psychotic disorders, or large-scale youth mental health assessments and services.\u00a0\n\nThe appointee will work closely with professional researchers and clinicians\u00a0to deliver and evaluate community assessments. He/She will also provide protocol-based interventions and\u00a0support to people with mental health difficulties.\u00a0 This position would be ideal for someone wanting to gain in research and interventions that target early onset mental disorders, and to be equipped with substantial clinical skills at the same time.\u00a0 Those who have responded to the previous advertisement (Ref.: 508724) need not re-apply.\n\nA highly competitive salary commensurate with qualifications and experience will be offered, in addition to annual leave and medical benefits. The appointment on fixed terms will attract a contract-end gratuity and University contribution to a retirement benefits scheme totalling up to 10% of basic salary.\n\nThe University only accepts online applications for the above posts. Applicants should apply online and upload an up-to-date C.V.\u00a0 Review of applications will start as soon as possible and continue until\u00a0February 28, 2022, or until the posts are filled, whichever is earlier.\n\nAdvertised:Dec 29, 2021 (HK Time)\nApplications close:Feb 28, 2022 (HK Time)", "employment_types": ["Temporary"], "selling_points": ["implementing the Education Bureau project", "co-ordinate with different parties", "lesson preparation, observation, evaluation"], "locations": ["Not Specified"], "categories": ["Admin & HR", "Others", "Education", "Others", "Others", "Others"], "post_time": "2022-01-13T03:56:32Z", "salary": {"currency": null, "max": null, "min": null, "period": "monthly", "term": null}, "salary_visible": false, "title_keywords": ["research assistant"], "responsibilities": ["research projects", "quality", "communication", "evaluate", "research support", "maintain"], "requirements": {"degrees": ["degree", "bachelor"], "majors": ["related disciplines", "psychology", "social sciences"], "languages": ["english", "chinese"], "language_level": ["excellent", "good"], "hard_skills": [], "soft_skills": ["organizational", "prioritize", "communication", "diverse", "motivated", "interpersonal skills", "enthusiastic", "ideal"], "languages_combined": [{"language": "english", "language_level": ["excellent", "good"]}, {"language": "chinese", "language_level": ["excellent", "good"]}]}, "experience_required": {"duration": [], "field": []}}, {"job_id": "100003009039588", "location_code": "hk", "company": "The Hong Kong University of Science and Technology", "job_title": "Assistant Officer (Executive Education Office)(Job ID: 7043)", "description": "Formerly known as Caritas Francis Hsu College (CFHC), Caritas Institute of Higher Education (CIHE) commenced its operations in 1985.\u00a0 At present, CIHE has five academic schools which are responsible for offering programmes that are pitched at Hong Kong Qualifications Framework (HKQF) from Level 4 to Level 6.\n\nThe Rita Tong Liu School of Business and Hospitality Management (the School) prides itself in offering professional education in various disciplines of business studies (in both full-time and part-time modes), providing students with learning experiences that are aligned closely with industry trends and market needs, especially in the area of economic, business and technological developments.\u00a0 Our BBA (Hons) Programme, with 4 streams, Accountancy (AC), Corporate Management and Governance (CMG), Hotel Management (HM), Marketing and Event Management (MEM), aims to provide students with professional development, sound education and positive life values.\u00a0 The School has received professional recognition by the Hong Kong Institute of Certified Public Accountants (HKICPA), Association of Chartered Certified Accountants (ACCA), CPA (Australia) and Hong Kong Chartered Governance Institute (HKCGI).\u00a0 Our graduates in BBA (Hons) Accountancy and Corporate Management and Governance are granted equivalent exemption status as students of other local universities. Besides, the School launched in 2020/21 a Top-up programme, namely Bachelor of Entrepreneurial Management (Honours) in Design Business (BEMDB). This interdisciplinary programme aims to nurture future entrepreneurs in the field of design business.\u00a0 BEMDB graduates are expected to become entrepreneurs in their own design businesses or in other project/brand/segment start-up positions in the design or creative industry.\u00a0\n\nThe School will launch the first CIHE\u2019s Master\u2019s programme (part-time mode) in January 2022, namely Master of Corporate Governance (MCG). It has been granted Collaborative Course Agreement (CCA) by HKCGI. Graduates of the programme will be eligible for full exemption from the examinations of Chartered Governance Qualifying Programme (CGQP). With a number of years of recognised work experience, they can apply for associate membership of both Company Secretaries and Corporate Governance Professionals.\u00a0\n\nDuties\n\nThe appointee will be responsible for (i) drafting and preparing discussion papers, proposals, correspondences and reports; (ii) serving as secretary to such committees as assigned; (iii) providing administrative support for teaching and learning; institutional review, programme validation, revalidation and accreditation; (iv) coordinating a team for administrative duties; (v) assisting in the two Institutions' functions; and (vi) undertaking such other duties as determined by the Supervisors.\n\nAppointment Criteria\n\nApplicants should have (a) a recognised Bachelor's degree; (b) a good command of written and spoken English and Chinese (including Putonghua); (c) proficiency in computer applications; (d) good organisational and communication skills; and (e) relevant work experience.\n\nApplication Deadline\n\nUntil the positions are filled\u00a0\n\nSalary will be commensurate with qualifications and experience. Interested parties are invited to submit (i) an application letter indicating expected salary; (ii) an updatedCV; and (iii) a duly completed application form (obtainable at https://www.cihe.edu.hk/en/career),to the Institute Secretariat, 10/F, 18 Chui Ling Road, Tseung Kwan O.Candidates not invited for interview within 2 months after the application deadline may assume their applications unsuccessful.", "employment_types": ["Full Time"], "selling_points": ["providing support to promotion activities", "program admission process", "Working beyond normal office hours may be required"], "locations": ["Sai Kung"], "categories": ["Admin & HR", "Clerical / Admin Staff", "Education", "Others", "Information Technology (IT)", "Others"], "post_time": "2022-01-11T10:09:51Z", "salary": {"currency": null, "max": null, "min": null, "period": "monthly", "term": null}, "salary_visible": false, "title_keywords": ["assistant officer", "executive"], "responsibilities": ["management", "other duties", "administrative support", "operations", "review", "design", "communication", "reports", "administrative duties", "computer applications"], "requirements": {"degrees": ["degree", "bachelor", "master"], "majors": ["business", "design"], "languages": ["putonghua", "english", "chinese"], "language_level": ["good command"], "hard_skills": ["acca", "hong kong institute of certified public accountants", "association of chartered certified accountants", "cpa", "c", "hkicpa"], "soft_skills": ["communication skills", "determined", "responsible", "collaborative", "learning", "creative", "positive"], "languages_combined": [{"language": "putonghua", "language_level": ["good command"]}, {"language": "english", "language_level": ["good command"]}, {"language": "chinese", "language_level": ["good command"]}]}, "experience_required": {"duration": [], "field": ["management", "business", "education"]}}, {"job_id": "100003009047484", "location_code": "hk", "company": "The University of Hong Kong", "job_title": "Research Assistant II (Ref.: 511333)", "description": "Sales Executive / Officer / Manager\u00a0(University Senior year also welcome)\n\nSalary: 25k to 40k (Officer) / 45k to 65k (Manager)\n\nLocation: Wanchai\n\n\nJob Highlights:\n\n4-day Work Week\n3-week Annual Leave\nHigh remuneration package\nFast Track Development Plan for Success\n\nCompany Overview:\n\nSee You at The Top\u00a0is a training and career enhancement start-up in Hong Kong.\nWe provide training, coaching, counselling to young graduates to shape them into leaders of tomorrow.\nOur parent company, Ziglar, has been operating in the USA for over 40 years and in China for\u00a0the past 17 years.\nWe are now launching in Hong Kong\nDiscover more on: www.syatt.org\n\nAre You:\n\nAffected by pandemic?\nHunting for more prosperous\u00a0career change?\nFresh graduate from university and not clear in career development?\nDSE Level or above, and not furthering your study?\nCapable to communicate effectively in Cantonese, Putonghua and English? (A Plus)\nHardworking and Honest? (A Must)\n\nJob Description:\n\nEnroll young people to our world-renowned\u00a0See You at The Top\u00a0seminar\nSupport seminar graduates securing a promising career path\nCandidate with good Online Sales & Management experience will be considered as Sales Manager\nPlease indicate job level applying - Executive, Officer or Manager", "employment_types": ["Full Time"], "selling_points": ["Applicants should possess a Bachelor\u2019s degree", "assist in clinical research on pregnancy", "have a good command of English and Cantonese"], "locations": ["Not Specified"], "categories": ["Education", "Others", "Marketing / Public Relations", "Marketing - Market Research", "Medical Services", "Others"], "post_time": "2022-01-14T03:16:05Z", "salary": {"currency": null, "max": null, "min": null, "period": "monthly", "term": null}, "salary_visible": false, "title_keywords": ["research assistant"], "responsibilities": ["plan"], "requirements": {"degrees": [], "majors": [], "languages": [], "language_level": [], "hard_skills": [], "soft_skills": [], "languages_combined": []}, "experience_required": {"duration": [], "field": []}}, {"job_id": "100003009043986", "location_code": "hk", "company": "Academic Asia UK Limited", "job_title": "Secretary", "description": "\u5de5\u4f5c\u8aaa\u660e:\n\n\u65bc\u672c\u4e2d\u5fc3\u6559\u6388\u6709\u95dc\u79d1\u76ee\uff0c\u53e6\u5916\u9700\u8981\u70ba\u8ab2\u7a0b\u6e96\u5099\u76f8\u95dc\u6559\u6750\n\u7121\u9700\u884c\u653f\u5de5\u4f5c\uff0c\u53ea\u9700\u5c08\u6ce8\u6559\u5b78\n\u516c\u53f8\u63d0\u4f9b\u624b\u63d0\u96fb\u8166\u4ee5\u914d\u5408\u79d1\u6280\u5316\u6559\u5b78\u6a21\u5f0f\n\u5b9a\u671f\u53c3\u8207\u5c08\u696d\u53ca\u7cfb\u7d71\u5316\u7684\u5728\u8077\u5c0e\u5e2b\u57f9\u8a13\n\n\u8981\u6c42:\n\n\u5927\u5b78\u6216\u4ee5\u4e0a\u7a0b\u5ea6\uff0c\u6b61\u8fce\u5927\u5b78\u7562\u696d\u751f\u61c9\u5fb5\uff0c\u6709\u7d93\u9a57\u8005\u512a\u5148\u8003\u616e\n\u672c\u79d1\u6210\u7e3e\u826f\u597d\n\u719f\u8b58\u516c\u958b\u8003\u8a66\uff0c\u6c7a\u5fc3\u65bc\u88dc\u7fd2\u754c\u767c\u5c55\n\u80fd\u517c\u6559\u5176\u4ed6\u79d1\u76ee\u8005\u512a\u5148\u8003\u616e\n\u5c65\u6b77\u9808\u5217\u660e\u5c31\u8b80\u4e2d\u5b78\u53ca\u5927\u5b78\u540d\u7a31\u53ca\u5b78\u7cfb(\u5217\u660e\u5e74\u4efd\u53ca\u6210\u7e3e)\n16 - 24K + Performance Bonus\uff0c\u53ef\u905450k \u4ee5\u4e0a\n\n\u5de5\u4f5c\u5730\u9ede:\n\n\u4f50\u6566\uff0f\u7063\u4ed4\n\n\u5176\u4ed6\u798f\u5229:\n\n\u5e74\u5047\u5341\u5929\u8d77\uff0c\u6709\u85aa\u75c5\u5047\uff0c\u751f\u65e5\u5047\u53ca\u91ab\u7642\u6d25\u8cbc\uff0c\u9280\u884c\u5047\u671f\n\n\u672c\u6821\u6210\u7acb\u65bc2012\u5e74\uff0c\u6df1\u53d7\u5b78\u751f\u53ca\u5bb6\u9577\u6b61\u8fce\uff0c\u5728\u6559\u80b2\u884c\u696d\u64c1\u6709\u826f\u597d\u5546\u8b7d\u3002\u5982\u61c9\u5fb5\u8005\u672c\u8eab\u5df2\u6709\u53ef\u89c0\u751f\u6e90(\u80fd\u5e36\u5b78\u751f\u52a0\u76df)\u00a0\uff0c\u5408\u4f5c\u6a21\u5f0f\u53ef\u53e6\u4f5c\u5546\u8b70\u00a0", "employment_types": ["Full Time", "Permanent"], "selling_points": ["Degree in any discipline", "3 years\u2019 working experience", "5-day work, attractive remuneration package"], "locations": ["Causeway Bay"], "categories": ["Admin & HR", "Administration / Operation Manager", "Secretary", "Education", "Others"], "post_time": "2022-01-13T02:41:27Z", "salary": {"currency": null, "max": null, "min": null, "period": "monthly", "term": null}, "salary_visible": false, "title_keywords": ["secretary"], "responsibilities": [], "requirements": {"degrees": [], "majors": [], "languages": [], "language_level": [], "hard_skills": [], "soft_skills": [], "languages_combined": []}, "experience_required": {"duration": [], "field": []}}, {"job_id": "100003009049430", "location_code": "hk", "company": "The University of Hong Kong", "job_title": "Project Associate (2 posts)", "description": "Responsibilities:\n\nExecuting strategies for young alumni and students programs;\nCoordinating communications which include social media, web content and other avenues to promote alumni activities;\nIdentifying volunteers, donors and advocates to advance the mission of the University\u2019s alumni and fundraising mandate;\nProviding high-level administrative support to senior UBC administrators; and\nSupporting specific fundraising duties, i.e. research, organize events, process donors\u2019 gifts and pledge for HK Foundation.\nRequirements:\n\nBachelor's degree or equivalent, preferably from the University of British Columbia:\u00a0 \u00a0 \u00a0\nAt least 5 years of relevant work experience;\nExcellent English writing and communication skills are required, and Cantonese and Mandarin will be an asset; and\nExperience with MS Office and website management software is expected.\nInterested candidates should submit their CV\u00a0and covering letter with expected salary and availability to Mei Mei Yiu, Director, Development & Alumni Engagement, UBC Asia Pacific Regional Office on or before Jan 31, 2022.", "employment_types": ["Full Time"], "selling_points": ["Applicants should be a fresh graduate", "a good command of written and spoken English", "good interpersonal and communication skills"], "locations": ["Pok Fu Lam"], "categories": ["Education", "Others"], "post_time": "2022-01-14T08:37:07Z", "salary": {"currency": null, "max": null, "min": null, "period": "monthly", "term": null}, "salary_visible": false, "title_keywords": ["associate"], "responsibilities": ["social media", "executing", "administrative support"], "requirements": {"degrees": ["degree", "bachelor"], "majors": [], "languages": ["cantonese", "english", "mandarin"], "language_level": ["excellent"], "hard_skills": ["ms office"], "soft_skills": ["communication skills"], "languages_combined": [{"language": "cantonese", "language_level": ["excellent"]}, {"language": "english", "language_level": ["excellent"]}, {"language": "mandarin", "language_level": ["excellent"]}]}, "experience_required": {"duration": ["at least 5 years"], "field": ["management"]}}, {"job_id": "100003009047665", "location_code": "hk", "company": "The University of Hong Kong", "job_title": "Research Assistant I/II (Ref.: 511352)", "description": "Monthly Salary Range:\u00a0\u00a0\u00a0\u00a0\u00a0\u00a0\u00a0 HK$20,155 \u2013 HK$25,565\nDuties:\u00a0 The appointee will assist the Project Leader in implementing the Education Bureau project related to Non-Chinese Speaking Students in Kindergarten. He/She will co-ordinate with different parties; provide and assist in school support services including lesson preparation, observation, evaluation and design teaching methods; support kindergarten teachers to teach non-Chinese speaking students to learn Chinese; provide support for home-school cooperation; organize learning community activities and seminars; and perform other duties as assigned.\nRequirements: Candidates should possess a bachelor\u2019s degree in Education, Chinese Language or equivalent. They should have good command of written and spoken English and Chinese (both Cantonese and Putonghua); good interpersonal and organizational skills; and be familiar with MS Office applications, including Word, Excel, PowerPoint, SPSS etc. They should also be self-motivated, responsible, and able to work independently and in a team. Teaching experience, especially in teaching Chinese as a second language, will be an advantage.\nTerms of Appointment: \u00a0Salary placement will be commensurate with qualifications and experience.\nApplications: \u00a0Please send application quoting the reference number to the Human Resources Unit, HKU SPACE, 7/F., T. T. Tsui Building, The University of Hong Kong, Pokfulam Road, Hong Kong.\u00a0 You may apply online or download an application form at http://hkuspace.hku.hk/jobs or request one by fax (852) 2540 3271.\nClosing Date for Applications: \u00a0\u00a0 20 January 2022\nThe information provided in an application will only be used for the purpose of consideration for appointment by HKU SPACE.\u00a0 Applicants not contacted within 8 weeks from the closing date may assume that their applications are unsuccessful.\u00a0 Unsuccessful applications will be kept for a maximum period of 24 months.", "employment_types": ["Full Time"], "selling_points": ["possess a Bachelor's degree or above", "assist in a community project", "manage research database"], "locations": ["Not Specified"], "categories": ["Professional Services", "Business Analysis / Data Analysis", "Education", "Others", "Public / Civil", "Others"], "post_time": "2022-01-14T03:41:08Z", "salary": {"currency": null, "max": null, "min": null, "period": "monthly", "term": null}, "salary_visible": false, "title_keywords": ["research assistant"], "responsibilities": ["provide support", "perform other duties", "co-ordinate with", "support services", "design", "evaluation"], "requirements": {"degrees": ["degree", "bachelor"], "majors": [], "languages": ["cantonese", "putonghua", "english", "chinese"], "language_level": ["advantage", "good command"], "hard_skills": ["excel", "word", "powerpoint", "ms office"], "soft_skills": ["organizational skills", "self-motivated", "work independently", "responsible", "learning", "interpersonal"], "languages_combined": [{"language": "cantonese", "language_level": ["good command"]}, {"language": "putonghua", "language_level": ["good command"]}, {"language": "english", "language_level": ["good command"]}, {"language": "chinese", "language_level": ["advantage", "good command"]}]}, "experience_required": {"duration": [], "field": ["teaching"]}}]