[{"job_id": "100003009053930", "location_code": "hk", "company": "Pacific Focus Consultancy Limited", "job_title": "HR & Administration, Officer", "description": "Our client is a reputable corporate bank and they are looking for a high calibre to join the HR & Admin department.\n\nResponsibilities:\n\nHR:\n\nTo provide full scope of efficient HR support and services to the company operations;\nReport to top management of the company and be responsible for full spectrum of Human Resources and Administration functions including recruitment & selection, compensation & benefits, training & development, employee relations and administration;\nReview company Human Resources policy and procedures to match with business demand and strategies;\nDrive annual compensation process including salary review, budgeting, incentive schemes to facilitate recruitment and retention program;\nCompile management reports and statistical analysis;\nLead or participate in ad hoc projects as required.\n\nAdmin:\n\nOversee various office administration functions, including facilities management, office supplies, document storage, fixed assets and inventory management\nManage office relocation, renovation projects, rental and lease agreements\nExecute office administration policies and procedures to ensure compliance with corporate requirements\nPrepare annual budget for office administration function and closely monitor operating expenditures\nAssist in appointment coordination and travel arrangement including arrangement of flights, hotel and transportation Schedule, coordinate, and organize events such as annual dinner, staff activities, meetings and conferences\nSupervise and review IT vendor service and performance\nRequirements:\n\nFluent / strong language skills in English and Chinese.\nAccounting knowledge would be appreciated\nWork experience around 1-2 years, fresh graduate is welcome.", "employment_types": ["Full Time", "Permanent"], "selling_points": ["5-day work week, great benefits", "International working platform", "Stable career development"], "locations": ["Central"], "categories": ["Admin & HR", "Administration / Operation Manager", "Banking / Finance", "Corporate Banking", "HR Supporting Staff"], "post_time": "2022-01-17T07:47:44Z", "salary": {"currency": null, "max": null, "min": null, "period": "monthly", "term": null}, "salary_visible": false, "title_keywords": ["officer", "hr"], "responsibilities": ["operations", "budgeting", "renovation", "budget", "inventory management", "administration", "office administration", "monitor", "conferences", "schedule", "report", "management", "office supplies", "review", "procedures", "policies", "hr", "analysis", "ensure compliance", "coordinate", "management reports", "recruitment", "ad hoc projects", "coordination", "travel arrangement"], "requirements": {"degrees": ["fresh graduate"], "majors": [], "languages": ["english", "chinese"], "language_level": ["fluent"], "hard_skills": [], "soft_skills": [], "languages_combined": [{"language": "english", "language_level": ["fluent"]}, {"language": "chinese", "language_level": ["fluent"]}]}, "experience_required": {"duration": ["1-2 years"], "field": []}}, {"job_id": "100003009053284", "location_code": "hk", "company": "OSMA Consulting Limited", "job_title": "Executive Assistant \uff08\u8463\u4e8b\u52a9\u7406\uff09", "description": "Our client is a reputable investment group with business lines across multiple industries in Asia. The high level seniors of this group are currently looking for qualified individual to assist on group's daily business and operation.\n\u6211\u4eec\u7684\u5ba2\u6237\u662f\u4e00\u5bb6\u58f0\u8a89\u5353\u8457\u7684\u6295\u8d44\u96c6\u56e2\uff0c\u4e1a\u52a1\u904d\u53ca\u4e9a\u6d32\u591a\u4e2a\u884c\u4e1a\u3002 \u8be5\u96c6\u56e2\u7684\u9ad8\u5c42\u76ee\u524d\u6b63\u5728\u5bfb\u627e\u5408\u683c\u7684\u4e2a\u4eba\u6765\u534f\u52a9\u96c6\u56e2\u7684\u65e5\u5e38\u4e1a\u52a1\u548c\u8fd0\u8425\u3002\n\nResponsibilities:\n-Coordination with internal departments (BD, IR, HR, etc) regarding daily operation;\u00a0\n-Liaising with various external parties (Clients' representatives or Guests) on business affairs;\n-Occasionally attend business meeting with senior management and take minutes ;\u00a0\n-Director's office administration work and back up other admin colleagues when needed;\n-Perform any other ad-hoc requests from management.\n\nQualifications:\n-Bachelor Degree or above;\n-Past experience in finance industry is a plus;\n-Mature and presentable;\n-Good command in English and Chinese.\n\n\n\u804c\u8d23\uff1a\n-\u4e0e\u5185\u90e8\u90e8\u95e8\uff08BD\u3001IR\u3001HR\u7b49\uff09\u5c31\u65e5\u5e38\u8fd0\u4f5c\u8fdb\u884c\u534f\u8c03\uff1b\n-\u5c31\u5546\u52a1\u4e8b\u5b9c\u4e0e\u5404\u79cd\u5916\u90e8\u5404\u65b9\uff08\u5ba2\u6237\u4ee3\u8868\u6216\u5ba2\u4eba\uff09\u8054\u7edc\uff1b\n-\u5076\u5c14\u53c2\u52a0\u4e0e\u9ad8\u7ea7\u7ba1\u7406\u4eba\u5458\u7684\u5546\u52a1\u4f1a\u8bae\u5e76\u505a\u4f1a\u8bae\u8bb0\u5f55\uff1b\n-\u4e3b\u7ba1\u529e\u516c\u5ba4\u884c\u653f\u5de5\u4f5c\uff0c\u5e76\u5728\u9700\u8981\u65f6\u652f\u6301\u5176\u4ed6\u884c\u653f\u540c\u4e8b\uff1b\n- \u6267\u884c\u6765\u81ea\u7ba1\u7406\u5c42\u7684\u4efb\u4f55\u5176\u4ed6\u4e34\u65f6\u8bf7\u6c42\u3002\n\n\u8d44\u683c\uff1a\n-\u672c\u79d1\u53ca\u4ee5\u4e0a\u5b66\u5386\uff1b\n-\u6709\u91d1\u878d\u884c\u4e1a\u7ecf\u9a8c\u8005\u4f18\u5148\uff1b\n-\u6210\u719f\u4e14\u6709\u8d23\u4efb\u5fc3\uff1b\n-\u826f\u597d\u7684\u4e2d\u82f1\u6587\u8868\u8fbe\u3002\n\n", "employment_types": ["Full Time"], "selling_points": ["Reputable investment group", "Excellent career exposure", "Attractive package"], "locations": ["Central"], "categories": ["Admin & HR", "Administration / Operation Manager", "Personal / Executive Assistant", "Secretary"], "post_time": "2022-01-17T06:47:02Z", "salary": {"currency": null, "max": null, "min": null, "period": "monthly", "term": null}, "salary_visible": false, "title_keywords": ["executive assistant"], "responsibilities": ["management", "hr", "external parties", "daily operation", "office administration work", "ad-hoc requests", "senior management"], "requirements": {"degrees": ["degree or above"], "majors": [], "languages": ["english", "chinese"], "language_level": [], "hard_skills": ["plus"], "soft_skills": ["presentable"], "languages_combined": [{"language": "english", "language_level": []}, {"language": "chinese", "language_level": []}]}, "experience_required": {"duration": [], "field": ["finance industry"]}}, {"job_id": "100003009054890", "location_code": "hk", "company": "Jobson Mores Limited", "job_title": "Insurance - Senior Manager, Office Administration (Over 500 employees)", "description": "We are currently seeking an Insurance -\u00a0Senior Manager, Office Administration for one one of the largest\u00a0insurance clients (over 500 internal staff).\u00a0\n\n\nRESPONSIBILITIES\n\nProvide full spectrum of clerical and administrative support for the Company\nPerform administrative duties, including general office support, procurement, insurance, facilities management, contract and documentations\nSupervise administration team to ensure smooth office operation\nAssist of the office renovation, office relocation and decoration projects\nCoordinate with contractors, suppliers and vendors, in order to monitor the progress\nHandle ad hoc projects as assigned\nREQUIREMENTS\n\n\nDiploma or above in Business Administration or other relevant disciplines\nMinimum 8 years' working experience in office administration\nWell organized, detail-minded, strong sense of responsible, independent and self-motivated, able to work under pressure\nStrong communication, interpersonal and presentation skills\nProficient in written and spoken Chinese and English\nGood command of computer literacy in Chinese word proceeding, MS Word, Excel and PowerPoint\nApply For This Job\n\nInterested candidate please\u00a0CLICK\u00a0apply button to apply online or send your resume in MS word format to\u00a0Jobson Mores Recruitment\n\nPlease note that only shortlisted candidate will be notified. All information will be treated in strict confidence and solely used for recruitment purposes.", "employment_types": ["Full Time"], "selling_points": ["Full Spectrum of Administrative Support", "Procurement, Contract and Documentations", "Mature, Self-motivated and Meticulous"], "locations": ["Tai Koo"], "categories": ["Admin & HR", "Administration / Operation Manager", "Clerical / Admin Staff", "Insurance", "Others"], "post_time": "2022-01-17T12:49:28Z", "salary": {"currency": null, "max": null, "min": null, "period": "monthly", "term": null}, "salary_visible": false, "title_keywords": ["senior manager"], "responsibilities": ["management", "administrative support", "renovation", "coordinate with", "office support", "monitor", "administrative duties", "ad hoc projects", "insurance", "administration"], "requirements": {"degrees": ["diploma or above"], "majors": ["business administration"], "languages": ["english", "chinese"], "language_level": ["good command", "proficient"], "hard_skills": ["chinese word proceeding", "excel", "powerpoint", "ms word"], "soft_skills": ["detail-minded", "self-motivated", "confidence", "independent", "responsible", "well organized", "communication", "computer literacy", "presentation skills", "interpersonal", "work under pressure"], "languages_combined": [{"language": "english", "language_level": ["proficient"]}, {"language": "chinese", "language_level": ["good command", "proficient"]}]}, "experience_required": {"duration": ["minimum 8 years"], "field": ["office administration"]}}, {"job_id": "100003009052623", "location_code": "hk", "company": "Sompo Insurance (Hong Kong) Company Limited", "job_title": "Senior Administration Officer", "description": "Responsibilities\n\n\nIn charge of office maintenance and repair coordination, insurance and licensing renewal, vendor management in a professional manner\nBeing the first contact point with building management office\nMonitor external contractors / service providers for effective maintenance of various systems\nResponsible for managing inventory and document storage\nAct as\u00a0the\u00a0project lead\u00a0for\u00a0office renovation and relocation\nAssist in planning and executing company events and functions (eg: Annual dinner, Christmas party & other staff activities)\nMonitor office expenditure and budgets to enhance cost efficiency\nPerform backup reception duties when necessary\nRequirements\nHolder of Diploma in any discipline\nMinimum of 5 years\u2019 relevant work experience in office administration with supervising a small team and monitoring outsourced contractors\nExposure in office relocation / renovation is\u00a0a must\nProactive with a can-do attitude, attention to details, a strong sense of responsibility\nAble to resolve problems independently\nImmediate availability would be a great advantage\n\nWe offer 5-day week and competitive remuneration package commensurate with qualification and experience.\u00a0 Please send full resume with details of current and expected salary to HR Department by clicking \"Apply Now\".\n\nPersonal data will be used for recruitment purpose only.", "employment_types": ["Full Time", "Permanent"], "selling_points": ["Provide office administration services", "Office relocation / renovation experience prefer", "Immediate available would be advantage"], "locations": ["Quarry Bay"], "categories": ["Admin & HR", "Administration / Operation Manager", "Clerical / Admin Staff", "Receptionist"], "post_time": "2022-01-17T03:35:10Z", "salary": {"currency": null, "max": null, "min": null, "period": "monthly", "term": null}, "salary_visible": false, "title_keywords": ["senior administration officer"], "responsibilities": ["budgets", "management", "cost", "maintenance", "inventory", "systems", "professional manner", "monitor", "renovation", "building management", "repair", "executing", "contact", "coordination", "insurance", "planning"], "requirements": {"degrees": ["diploma"], "majors": [], "languages": [], "language_level": [], "hard_skills": ["small"], "soft_skills": ["independently", "sense of responsibility", "can-do attitude", "attention to details", "proactive"], "languages_combined": []}, "experience_required": {"duration": ["minimum of 5 years"], "field": ["office administration", "team"]}}, {"job_id": "100003009052792", "location_code": "hk", "company": "Diesel Pacific Limited", "job_title": "Assistant Administration Manager - Shared Service", "description": "Responsibilities:\n\n\u00a0OFFICE ADMINISTRATION\n\nOversee a wide range of administrative functions\n\nSupervising administrative assistant and tea lady\nPreparation of office administration budgets review & approve various office expenses whilst manage within budget guidelines\nVendor management on external contracts\nManaging and implement office planning initiatives, monitor corresponding construction schedule\nProvide secretarial support to GM such as prepare expense claim and meeting logistic arrangement\nOrganizing logistics for both internal and external events\nBudget management including budget forecast and expenses control\nProvide administrative support to office team particularly business travel arrangement\nSupport reception as needed\n\n\u00a0SUPPORT TO RETAIL STORES\n\nOrganize Administrative work between stores and office\nSupport materials supplies to stores\n\n\u00a0OTHERS\n\nSupport company events and other ad-hoc projects assigned by manager\n\n\u00a0Requirements:\n\nBachelor's degree or above.\nAt least 5 years administrative experience\nExperience in sizable MNC company is preferred\nStrong supervisory, interpersonal and negotiation skills and able to work under pressure\nProficiency in both Cantonese, English and Mandarin\nLess experience will be considered as Senior Administration Officer\n\nInterested parties please state the apply position and send full resume via click\u00a0Apply Now\u00a0to send your resume with current & expected salary to us.\n\nInformation provided will be treated in strict confidence and only be used for recruitment purpose. The Company may refer suitable applicants to other vacancies within the associated Group of companies.\n\nDiesel Pacific Limited is part of the OTB Group. For all job opportunities within OTB Group visit\u00a0www.otb.net/en/otb-career/", "employment_types": ["Full Time", "Permanent"], "selling_points": ["At least 5 years administrative experience", "Oversee a wide range of administrative functions", "Organize Admin work between stores & office"], "locations": ["Causeway Bay"], "categories": ["Admin & HR", "Administration / Operation Manager"], "post_time": "2022-01-17T04:05:18Z", "salary": {"currency": null, "max": null, "min": null, "period": "monthly", "term": null}, "salary_visible": false, "title_keywords": ["assistant administration manager"], "responsibilities": ["supervising", "budget", "secretarial support", "provide administrative support", "control", "administrative work", "office administration", "contracts", "expenses", "monitor", "logistics", "schedule", "forecast", "management", "review", "budgets", "guidelines", "logistic arrangement", "travel arrangement", "planning"], "requirements": {"degrees": ["degree or above", "bachelor"], "majors": [], "languages": ["cantonese", "english", "mandarin"], "language_level": ["proficiency"], "hard_skills": [], "soft_skills": ["negotiation skills", "interpersonal", "work under pressure"], "languages_combined": [{"language": "cantonese", "language_level": ["proficiency"]}, {"language": "english", "language_level": ["proficiency"]}, {"language": "mandarin", "language_level": ["proficiency"]}]}, "experience_required": {"duration": ["at least 5 years"], "field": ["administrative", "administration"]}}, {"job_id": "100003009052549", "location_code": "hk", "company": "Sodexo (Hong Kong) Limited", "job_title": "Facilities Officer (Office)", "description": "Job Duties:\n\nUnder the reliever team to provide support in different office sites as scheduled\u00a0\nOversee daily routine facilities management and ensure the operation of office equipment and office environment are in good condition\nPerform logistics and administration support to the team, including but not limited to arrange ordering for office equipment and facilities, set up meeting rooms and manage access card for staff/visitors\nSupervise and monitor in house and outsourced teams with diverse trades to ensure the facilities services including customer relation, security, cleaning, and facilities maintenance and repair are delivered effectively and cost efficiently\nCoordinate minor project works e.g. renovation, relocation, moves etc.\u00a0\nEnsure vendors submit invoices in timely manner\nEnsure all work carried out in compliance with standards and Health & Safety Regulation\nReport to Account Manager for special feedback and key account management\nPerform other duties assigned by\u00a0Supervisor\n\nJob Requirements:\n\nHigher diploma holder in Facilities Management or Service related disciplines\nMinimum 5\u00a0years of working experience in Facilities Management\nStrong computer skills\nGood command of spoken and written English and Chinese\nProfessional appearance and demeanor, strong interpersonal skills and excellent communication skills\n\nPlace of Work and Working Hours:\n\nHong Kong Island (Monday to Friday, 9:00a.m. to 6:00p.m.)\n\nBenefits:\n\nPublic Holiday\nBirthday Leave\nMedical benefits\nA fun and lively working environment where you will be valued and developed\n\nWe offer competitive remuneration to the right candidates. Please apply with detailed resume and\u00a0salary expectation\u00a0to Human Resources Department, Sodexo (Hong Kong) Limited by clicking\u00a0Apply Now.\n\n*Personal data collected is for recruitment purposes only.", "employment_types": ["Full Time", "Permanent"], "selling_points": ["FM role in Corporate Office", "Report to Account Manager", "5-day work week"], "locations": ["Central"], "categories": ["Admin & HR", "Administration / Operation Manager", "Others", "Property / Real Estate", "Others"], "post_time": "2022-01-17T03:23:43Z", "salary": {"currency": null, "max": null, "min": null, "period": "monthly", "term": null}, "salary_visible": false, "title_keywords": ["officer"], "responsibilities": ["provide support", "management", "cost", "invoices", "maintenance", "perform other duties", "renovation", "monitor", "teams", "compliance", "coordinate", "repair", "logistics", "cleaning", "report", "administration"], "requirements": {"degrees": ["higher diploma holder"], "majors": ["related disciplines"], "languages": ["english", "chinese"], "language_level": ["good command"], "hard_skills": ["facilities management", "computer skills"], "soft_skills": ["communication skills", "interpersonal skills"], "languages_combined": [{"language": "english", "language_level": ["good command"]}, {"language": "chinese", "language_level": ["good command"]}]}, "experience_required": {"duration": ["minimum 5 years"], "field": ["management"]}}, {"job_id": "100003009054387", "location_code": "hk", "company": "China Road and Bridge Corporation", "job_title": "Administration Officer", "description": "Responsibilities :\n\n\u00a0\u00a0\u00a0\u00a0\u00a0\u00a0\u00a0\u00a0 Responsible for office administration works & documentation\u00a0management\u00a0of site office\n\nRequirements :\n\n\u00a0\u00a0\u00a0\u00a0\u00a0\u00a0\u00a0\u00a0 Form 5 graduate with HKCEE full cert, preferably have completed a post secondary; certificate programme on human resources management;\n\u00a0\u00a0\u00a0\u00a0\u00a0\u00a0\u00a0\u00a0 Minimum 5\u00a0years' administrative experience;\n\u00a0\u00a0\u00a0\u00a0\u00a0\u00a0\u00a0\u00a0 Site office experience is much preferred;\n\u00a0\u00a0\u00a0\u00a0\u00a0\u00a0\u00a0\u00a0 Good command of both spoken & written English, Chinese\n\u00a0\u00a0\u00a0\u00a0\u00a0\u00a0\u00a0\u00a0 Proficient in MS Office;\n\u00a0\u00a0\u00a0\u00a0\u00a0\u00a0\u00a0\u00a0 Working on site office\u00a0\n\u00a0\u00a0\u00a0\u00a0\u00a0\u00a0\u00a0\u00a0 Candidates with more experience will be considered as Senior Site Administrative Officer ; with less experience will be considered as Assistant Site Administrative Officer\n\u00a0\u00a0\u00a0\u00a0\u00a0\u00a0\u00a0\u00a0 Immediate available is highly preferred\nAn attractive remuneration package will be offered to the successful candidate. To apply for the above position, please send your application with full resume, current and expected salary and contact number to Human Resources Department - E-mail via clicking \"Apply Now\"", "employment_types": ["Full Time"], "selling_points": ["Form 5 graduate with HKCEE full cert", "Minimum 5 years' administrative experience", "Immediate available is highly preferred"], "locations": ["Others"], "categories": ["Admin & HR", "Administration / Operation Manager"], "post_time": "2022-01-17T09:20:01Z", "salary": {"currency": null, "max": null, "min": null, "period": "monthly", "term": null}, "salary_visible": false, "title_keywords": ["administration officer"], "responsibilities": ["documentation", "office administration", "management"], "requirements": {"degrees": ["certificate", "form 5"], "majors": [], "languages": ["english", "chinese"], "language_level": ["good command"], "hard_skills": ["ms office"], "soft_skills": [], "languages_combined": [{"language": "english", "language_level": ["good command"]}, {"language": "chinese", "language_level": ["good command"]}]}, "experience_required": {"duration": ["minimum 5 years"], "field": ["administrative"]}}, {"job_id": "100003009054502", "location_code": "hk", "company": "The Hong Kong University of Science and Technology", "job_title": "Manager (Job ID: 7066)", "description": "Job Title:\u00a0\u00a0\u00a0\u00a0\u00a0\u00a0\u00a0\u00a0\u00a0\u00a0\u00a0\u00a0Manager\nDepartment:\u00a0\u00a0\u00a0\u00a0\u00a0\u00a0Office of the Vice-President for Research and Development\nJob ID:\u00a0\u00a0\u00a0\u00a0\u00a0\u00a0\u00a0\u00a0\u00a0\u00a0\u00a0\u00a0\u00a0\u00a0\u00a07066\n\nJob Posting Details\n\nThe appointee will provide support in all aspects of administration relating to research and development.\u00a0 Duties include but not limited to providing administrative support to functions under VPRDO, preparing documents for meetings and taking necessary follow-up actions, budgeting and accounting, liaising with internal and external stakeholders on research-related matters, managing and coordinating University-wide events and activities, supporting research committees/working groups, coordinating the nominations/applications for awards and honors, supporting investigation of suspected misconduct cases, and performing any other ad-hoc duties as assigned.\n\nApplicants should have a bachelor's degree with at least 7 years of work experience in the higher education sector.\u00a0 The ideal candidate should be a good team player with good organizational and communication skills, and be effective in multi-tasking work culture. Excellent command of written and spoken English and Chinese (both Cantonese and Putonghua) is required.\u00a0 Candidates with good understanding of research facilities management, grant administration and management, and proper committee secretarial servicing training is preferred. (Duration: 2 years, renewable)\n\nStarting salary will be commensurate with qualifications and experience. \u00a0Fringe benefits including annual leave, medical and dental benefits will be provided. \u00a0A gratuity will be payable upon successful completion of contract.\n\nApplication Procedure\nIn support of a green work environment, we accept applications submitted online only. \u00a0To apply, please complete an online application form through the HKUST Careers website (https://hkustcareers.ust.hk) and return it online to the Human Resources Office on or before\u00a0Monday, 31 January 2022.\u00a0 Applicants will receive an acknowledgement by email upon successful submission.\u00a0 We thank applicants for their interest, but advise that only shortlisted candidates will be notified of the result of the application.\n\n(Information provided by applicants will be used for recruitment and other employment-related purposes only.)\n\nHKUST is an equal opportunities employer and is committed to our core values of\ninclusiveness, diversity, and respect.", "employment_types": ["Full Time"], "selling_points": ["providing administrative support", "preparing documents for meetings", "liaising with internal and external stakeholders"], "locations": ["Sai Kung"], "categories": ["Admin & HR", "Administration / Operation Manager", "Education", "Others"], "post_time": "2022-01-17T09:48:51Z", "salary": {"currency": null, "max": null, "min": null, "period": "monthly", "term": null}, "salary_visible": false, "title_keywords": ["manager"], "responsibilities": ["provide support", "management", "administrative support", "budgeting", "liaising with", "investigation", "communication", "ad-hoc duties", "administration"], "requirements": {"degrees": ["degree", "bachelor"], "majors": [], "languages": ["cantonese", "putonghua", "english", "chinese"], "language_level": ["excellent"], "hard_skills": ["id", "facilities management"], "soft_skills": ["communication skills", "good team player", "organizational", "multi-tasking", "ad-hoc duties", "ideal"], "languages_combined": [{"language": "cantonese", "language_level": ["excellent"]}, {"language": "putonghua", "language_level": ["excellent"]}, {"language": "english", "language_level": ["excellent"]}, {"language": "chinese", "language_level": ["excellent"]}]}, "experience_required": {"duration": ["at least 7 years"], "field": ["education"]}}, {"job_id": "100003009052740", "location_code": "hk", "company": "ADECCO", "job_title": "Executive Assistant (+Secretary) (+Administration)", "description": "Our client, a multinational oil and gas company,\u00a0is now looking for Executive Assistant (+Secretary) (+Administration)\n\nJob Responsibilities\n\n\u00a0\u00a0\u00a0\u00a0\u00a0\u00a0\u00a0\u00a0 Manage information flow in a timely and accurate manner\n\u00a0\u00a0\u00a0\u00a0\u00a0\u00a0\u00a0\u00a0 Manage executives\u2019 calendars and set up meetings\n\u00a0\u00a0\u00a0\u00a0\u00a0\u00a0\u00a0\u00a0 Make travel and accommodation arrangements\n\u00a0\u00a0\u00a0\u00a0\u00a0\u00a0\u00a0\u00a0 Rack daily expenses and prepare weekly, monthly or quarterly reports\n\u00a0\u00a0\u00a0\u00a0\u00a0\u00a0\u00a0\u00a0 Keepup with office supply inventory\n\u00a0\u00a0\u00a0\u00a0\u00a0\u00a0\u00a0\u00a0 Format information for internal and external communication\n\u00a0\u00a0\u00a0\u00a0\u00a0\u00a0\u00a0\u00a0 Take minutes during meetings\n\u00a0\u00a0\u00a0\u00a0\u00a0\u00a0\u00a0\u00a0 Screen and direct phone calls and distribute correspondence\n\u00a0\u00a0\u00a0\u00a0\u00a0\u00a0\u00a0\u00a0 Organize and maintain the office filing system\n\nJob Requirements\n\n\u00a0\u00a0\u00a0\u00a0\u00a0\u00a0\u00a0\u00a0 High School degree\n\u00a0\u00a0\u00a0\u00a0\u00a0\u00a0\u00a0\u00a0 Work experience as an Executive Assistant, Administrative Assistant or similar role\n\u00a0\u00a0\u00a0\u00a0\u00a0\u00a0\u00a0\u00a0 Excellent MS Office knowledge\n\u00a0\u00a0\u00a0\u00a0\u00a0\u00a0\u00a0\u00a0 Outstanding organizational and time management skills\n\u00a0\u00a0\u00a0\u00a0\u00a0\u00a0\u00a0\u00a0 Excellent verbal and written communications skills\n\u00a0\u00a0\u00a0\u00a0\u00a0\u00a0\u00a0\u00a0 Proficient in Excel (Pivot Table, VLOOKUP)\n\nInterested parties, please CLICK HERE to apply online.\n\nOr if you would like to have a further discussion about this role, please Whatsapp Hoyin Siu at 9862 0297.\n\nPlease note that only short-listed candidates will be notified. All information gathered will be treated in strict confidence and solely used for recruitment purposes.", "employment_types": ["Full Time"], "selling_points": [], "locations": ["Kwun Tong"], "categories": ["Admin & HR", "Administration / Operation Manager", "Clerical / Admin Staff", "Personal / Executive Assistant"], "post_time": "2022-01-17T03:52:45Z", "salary": {"currency": "HKD", "max": 24999, "min": 20000, "period": "monthly", "term": null}, "salary_visible": true, "title_keywords": ["executive assistant", "secretary"], "responsibilities": ["inventory", "expenses", "communication", "maintain", "reports", "phone calls"], "requirements": {"degrees": ["degree", "high school"], "majors": [], "languages": [], "language_level": [], "hard_skills": ["excel", "pivot table", "vlookup", "ms office"], "soft_skills": ["time management skills", "organizational"], "languages_combined": []}, "experience_required": {"duration": [], "field": ["administrative"]}}, {"job_id": "100003009053038", "location_code": "hk", "company": "Spidernet Recruitment Services", "job_title": "Human Resources and Administration (Office Manager /Assistant Manager Level)", "description": "Human Resources and Administration (Office Manager /Assistant Manager Level)\n\nSalary: HK$30-40k\n\nResponsibilities:\n\nHandle full spectrum of Human Resources and Administration duties, such as compensation and benefits, recruitment, expenses payments, office facilities management and office supplies procurement \u00a0\nLiaise with internal and external parties for daily HR operation & administration\nPrepare regular human resources and office administration reports for management\u2019s review\nAssist Senior Management for meeting and traveling arrangements as well as other ad hoc assignments\nProvide administrative\u00a0support including preparation of meeting minutes and presentation materials as assigned\n\nRequirements:\n\nDegree in Human Resources / Business Administration or related disciplines\nMinimum 8 years of solid experience in Human Resources and office administration\nStrong coordination and prioritization skills\nGood interpersonal and communication skills\nCompetency in both spoken and written English and Chinese, Mandarin a plus\nIndependent, self-motivated & able to work under pressure\n\nAttractive remuneration and fringe benefits will be offered to the successful candidate.\n\n\nInterested candidates should apply with detailed resume, present and expected salaries by clicking the Apply Now button.\n\nAll information received will be treated in strict confidence and used for recruitment purpose only.\n\nOnly shortlisted candidates will be notified.", "employment_types": ["Full Time", "Permanent"], "selling_points": ["Degree in HR / BA , fluent English & Mandarin", "8 yrs HR and Admin exp. Recruitment, payroll, C&B", "All round HR, Office Admin and Executive support"], "locations": ["Central & Western Area"], "categories": ["Admin & HR", "Administration / Operation Manager", "HR Director / Manager", "HR Supporting Staff"], "post_time": "2022-01-17T05:18:45Z", "salary": {"currency": null, "max": null, "min": null, "period": "monthly", "term": null}, "salary_visible": false, "title_keywords": ["assistant manager", "office manager", "human resources"], "responsibilities": ["management", "office supplies", "office administration", "hr", "expenses", "internal and external parties", "review", "payments", "recruitment", "reports", "ad hoc assignments", "liaise with", "senior management", "provide administrative support", "administration"], "requirements": {"degrees": ["degree"], "majors": ["related disciplines", "business administration"], "languages": ["english", "chinese", "mandarin"], "language_level": [], "hard_skills": ["plus"], "soft_skills": ["communication skills", "self-motivated", "independent", "coordination", "interpersonal", "work under pressure"], "languages_combined": [{"language": "english", "language_level": []}, {"language": "chinese", "language_level": []}, {"language": "mandarin", "language_level": []}]}, "experience_required": {"duration": ["minimum 8 years"], "field": ["office administration", "human resources"]}}, {"job_id": "100003009053686", "location_code": "hk", "company": "United Asia Finance Limited", "job_title": "Administrative Assistant, Administration and Facilities Management", "description": "Job Responsibilities:\n\nManage various procurement related tasks assigned by supervisor such as procurement of branch staff uniform, marketing premium, software license renewal, different kinds of services etc.\nProvide full spectrum of daily office administrative support including but not limited to arrangement of office stationery and supplies, small office equipment, cleaning and pest control etc.\nAssist in checking and reconciling of petty cash fund for Head Office and branch offices\nAssist to manage receptionist and office assistants\n\nJob Requirements:\n\nDiploma or above in any disciplines\nAt least 3 years solid\u00a0general administration experience\nAbility to deal with different levels of external business partners / contractors\nAbility to work independently and able to work under pressure\nHave knowledge of central procurement will be an advantage but not a must\nGood command of spoken English, Cantonese and Putonghua a plus\nCandidate with more experience will be considered for the post of Officer, Administration and Facilities Management\n\nWe offer attractive remuneration package which includes double pay and discretionary bonus. Interested parties please send your CV indicating your current salary, expected salary and availability to HR Department, by email via \"Apply Now\"", "employment_types": ["Full Time", "Permanent"], "selling_points": ["Manage various procurement related tasks", "Diploma or above in any disciplines", "3 years solid general administration experience"], "locations": ["Wan Chai"], "categories": ["Admin & HR", "Administration / Operation Manager", "Clerical / Admin Staff", "Others"], "post_time": "2022-01-17T07:20:55Z", "salary": {"currency": null, "max": null, "min": null, "period": "monthly", "term": null}, "salary_visible": false, "title_keywords": ["administrative assistant"], "responsibilities": ["control", "software", "administrative support", "stationery", "checking", "cleaning"], "requirements": {"degrees": ["diploma or above"], "majors": ["any disciplines"], "languages": ["cantonese", "putonghua", "english"], "language_level": ["good command"], "hard_skills": ["facilities management", "plus"], "soft_skills": ["work independently", "work under pressure"], "languages_combined": [{"language": "cantonese", "language_level": ["good command"]}, {"language": "putonghua", "language_level": ["good command"]}, {"language": "english", "language_level": ["good command"]}]}, "experience_required": {"duration": ["at least 3 years"], "field": ["management", "administration"]}}, {"job_id": "100003009052650", "location_code": "hk", "company": "Talent Preneur Management Consultancy Co. Limited", "job_title": "Personal Assistant (\u79c1\u4eba\u52a9\u7406)", "description": "\u8077\u8cac\uff1a\n\n\u70ba\u8463\u4e8b\u9577\u63d0\u4f9b\u5168\u65b9\u4f4d\u7684\u79c1\u4eba\u52a9\u7406\u652f\u63f4\uff0c\u5982\u652f\u4ed8\u6c34\u96fb\u7164\u55ae\uff0c\u8cfc\u8cb7\u7269\u8cc7\u7b49\n\u8ca0\u8cac\u8463\u4e8b\u9577\u65e5\u5e38\u9910\u98f2\u7684\u5b89\u6392\u53ca\u7dad\u6301\u5730\u65b9\u6574\u6f54\n\u5b89\u6392\u8463\u4e8b\u9577\u7684\u65e5\u7a0b\uff0c\u65e5\u5e38\u6703\u5ba2\u53ca\u6d3b\u52d5\u7684\u9810\u5831\n\u8655\u7406\u548c\u7dad\u8b77\u6a5f\u5bc6\u6587\u4ef6\n\u4e00\u822c\u79ae\u7269\u53ca\u7bc0\u65e5\u79ae\u54c1\u7684\u4e00\u5207\u5b89\u6392\n\u5354\u8abf\u5404\u9805\u516c\u53f8\u884c\u653f\u3001\u6d3b\u52d5\u7b49\u76f8\u95dc\u5de5\u4f5c\n\u6839\u64da\u9700\u8981\u9032\u884c\u6236\u5916\u5de5\u4f5c\u53ca\u57f7\u884c\u81e8\u6642\u4efb\u52d9\n\u8981\u6c42\uff1a\n\n\u5b78\u58eb\u5b78\u4f4d\u6216\u4ee5\u4e0a\u5b78\u6b77\uff0c\u6216\u5177\u5099\u79d8\u66f8\u3001\u79c1\u4eba\u52a9\u7406\u7b49\u76f8\u95dc\u7d93\u9a57\n\u61c2\u807d\u5beb\u8aaa\u5ee3\u6771\u8a71\u548c\u666e\u901a\u8a71\n\u59a5\u5584\u5730\u8655\u7406\u5404\u7a2e\u7a81\u767c\u4e8b\u4ef6\uff0c\u80fd\u5920\u7d55\u5c0d\u4fdd\u5bc6\n\u505a\u4e8b\u4ed4\u7d30\u8a8d\u771f\uff0c\u6297\u58d3\u529b\u5f37\n\u80fd\u5920\u81ea\u5f8b\u53ca\u4e3b\u52d5\u532f\u5831\u5de5\u4f5c\u9032\u5ea6\uff0c\u4e26\u53ca\u6642\u4f5c\u51fa\u56de\u61c9\n\u51fa\u8272\u7684\u4eba\u969b\u95dc\u4fc2\uff0c\u5354\u8abf\u548c\u7d44\u7e54\u80fd\u529b\n\u53ef\u5373\u6642\u4e0a\u73ed\u8005\u53ef\u512a\u5148\u8003\u616e\n\u6b61\u8fce\u6709\u5167\u5730\u80cc\u666f\u4eba\u58eb\u7533\u8acb", "employment_types": ["Full Time", "Part Time", "Permanent"], "selling_points": [], "locations": ["Shatin Area"], "categories": ["Admin & HR", "Administration / Operation Manager", "Personal / Executive Assistant", "Secretary"], "post_time": "2022-01-17T03:38:42Z", "salary": {"currency": "HKD", "max": 29999, "min": 25000, "period": "monthly", "term": null}, "salary_visible": true, "title_keywords": ["\u79c1\u4eba\u52a9\u7406", "personal assistant"], "responsibilities": [], "requirements": {"degrees": [], "majors": [], "languages": [], "language_level": [], "hard_skills": [], "soft_skills": [], "languages_combined": []}, "experience_required": {"duration": [], "field": []}}, {"job_id": "100003009050237", "location_code": "hk", "company": "Wheelock Properties (Hong Kong) Limited", "job_title": "Administration Manager", "description": "Responsibilities\n\n\nSupervise a team of\u00a0 admin colleagues including receptionists, messengers and tea ladies, etc.\nOversee and perform office space, facilities, office equipment management, maintenance & improvements and ensure smooth operation of the entire working environment\nManage office presentation, reflecting company culture, values and marketing image\nWork with dedicated project team on office renovation and relocation projects; liaise with contractors, suppliers and vendors (for security system and office equipment, etc.) to ensure all progress are in control and within timeline\nManage administrative services and initiatives, including courier services, office supplies, security access and set up workstation for new joiner etc.\nReview and maintain office administration policies and procedures\nTake initiative to assess workflow and process to improve efficiency\nAssist in communications with internal stakeholders\n\nRequirements\n\n\nDegree in Business Administration or relevant disciplines\nAt least 8 years of relevant experience in general office admin duties in sizeable companies\nExperience in managing modern/stylish office and office renovation/relocation are highly preferred\nGood problem-solving and constructive communication skills\nFast learner and a true team player with adaptivity to new corporate culture quickly\nPleasant and self-driven, committed, organized and detail-minded\nHigh proficiency in both Chinese and English (writing) languages and MS Office applications", "employment_types": ["Full Time", "Permanent"], "selling_points": [], "locations": ["Central"], "categories": ["Admin & HR", "Administration / Operation Manager"], "post_time": "2022-01-14T09:59:56Z", "salary": {"currency": null, "max": null, "min": null, "period": null, "term": null}, "salary_visible": false, "title_keywords": ["administration manager"], "responsibilities": ["management", "control", "communications with", "maintenance", "office supplies", "office administration", "policies", "renovation", "review", "procedures", "maintain", "liaise with contractors"], "requirements": {"degrees": ["degree"], "majors": ["business administration"], "languages": ["english", "chinese"], "language_level": ["proficiency"], "hard_skills": ["problem-solving", "ms office"], "soft_skills": ["detail-minded", "communication skills", "organized", "problem-solving", "driven", "pleasant", "committed", "team player", "fast learner", "constructive"], "languages_combined": [{"language": "english", "language_level": ["proficiency"]}, {"language": "chinese", "language_level": ["proficiency"]}]}, "experience_required": {"duration": ["at least 8 years"], "field": ["admin", "relevant experience"]}}, {"job_id": "100003009051610", "location_code": "hk", "company": "Charven Development Limited", "job_title": "\u9ad8\u7d1a\u884c\u653f\u53ca\u4eba\u4e8b\u52a9\u7406 Senior Administrative and HR Assistant", "description": "\u5de5\u4f5c\u5167\u5bb9\u53ca\u8077\u8cac:\n\n\u4e00\u822c\u79d8\u66f8\u8077\u52d9;\n\u5354\u8abf\u53ca\u5b89\u6392\u8463\u4e8b\u65e5\u5e38\u884c\u7a0b;\n\u7ba1\u7406\u8b70\u7a0b\u4e26\u5b89\u6392\u6703\u8b70\u53ca\u7d04\u6703,\u6703\u8b70\u8a18\u9304;\n\u5354\u52a9\u65e5\u5e38\u4eba\u529b\u8cc7\u6e90\u5de5\u4f5c:\u7c4c\u8fa6\u57f9\u8a13\u3001\u62db\u52df\u3001\u516c\u53f8\u6d3b\u52d5;\n\u5718\u968a\u696d\u7e3e\u5831\u544a\u8ffd\u8e2a\u6210\u54e1\u696d\u7e3e/\u734e\u9805;\n\u8655\u7406\u8fa6\u516c\u5ba4\u884c\u653f\u5de5\u4f5c\uff0c\u5305\u62ec\u8a02\u8cfc\u8cfc\u6587\u5177\u3001\u8fa6\u516c\u5ba4\u7528\u54c1\u3001\u540c\u4e8b\u51fa\u52e4\u53ca\u5047\u671f\u7d00\u9304\u7b49;\n\u8655\u7406\u4e0a\u7d1a\u59d4\u6d3e\u7684\u5176\u4ed6\u5de5\u4f5c\n\n\u8077\u4f4d\u8981\u6c42:\n\n\u4e00\u5e74\u7d93\u9a57\u6216\u4ee5\u4e0a\n\u5c08\u4e0a\u6559\u80b2\u6216\u5b78\u58eb\u5b78\u4f4d(\u5546\u696d/\u884c\u653f\u7ba1\u7406/\u4eba\u529b\u8cc7\u6e90/\u793e\u6703\u79d1\u5b78)\n\u826f\u597d\u7cb5\u8a9e\u3001\u826f\u597d\u666e\u901a\u8a71\u3001\u826f\u597d\u82f1\u6587\n\u61c2\u8b80\u5beb\u4e2d\u6587\u53ca\u82f1\u6587\n\u61c2Microsoft Office\u53ca\u4e2d\u82f1\u6587\u57fa\u672c\u96fb\u8166\u64cd\u4f5c\n\n\u5de5\u4f5c\u5730\u9ede: \u89c0\u5858\u5340\n\n\u798f\u5229\u5305\u62ec\uff1a\n\n\u9280\u884c\u5047\u671f\u3001\u4e94\u5929\u5de5\u4f5c\u3001\u91ab\u7642\u4fdd\u969c\u3001\u63d0\u4f9b\u54e1\u5de5\u65e9\u5348\u81b3\u300110\u5929\u6709\u85aa\u5e74\u5047\u3001\u8003\u8a66\u5047\u3001\u5a5a\u5047\u3001\u52e4\u5de5\u734e\u3002\n\n\u00a0\u6709\u610f\u61c9\u5fb5\u8005\u8acb\u628a\u8a73\u7d30\u7684\u5c65\u6b77\u767c\u9001\u7d66\u6211\u5011\uff0c\u8acb\u8a3b\u660e\u73fe\u8077\u85aa\u91d1\u548c\u671f\u671b\u85aa\u91d1\u3002", "employment_types": ["Full Time"], "selling_points": ["\u52e4\u5de5\u734e", "10\u5929\u5927\u5047", "\u4e94\u5929\u5de5\u4f5c"], "locations": ["Kwun Tong"], "categories": ["Admin & HR", "Administration / Operation Manager", "Clerical / Admin Staff", "Secretary"], "post_time": "2022-01-16T21:50:30Z", "salary": {"currency": null, "max": null, "min": null, "period": "monthly", "term": null}, "salary_visible": false, "title_keywords": ["senior administrative", "hr assistant"], "responsibilities": [], "requirements": {"degrees": [], "majors": [], "languages": [], "language_level": [], "hard_skills": [], "soft_skills": [], "languages_combined": []}, "experience_required": {"duration": [], "field": []}}, {"job_id": "100003009054025", "location_code": "hk", "company": "aalis", "job_title": "Administrative Officer - 5 day work", "description": "Job Responsibilities\n\nProvide Comprehensive administrative support\nProvide full spectrum of personal and secretarial support\nPreparing daily reports\nHandle all internal claims and invoices in the correct process, ensuring necessary supporting materials and concurrence\nPrepare regular admin related statistics and reports for management review\nHandle all administration tasks and ad-hoc projects\n\nJob Requirements\n\nHigher Diploma / Bachelor\u2019s degree holder\nCommunicate politely and sensitively, ensuring that any issues are followed up promptly\nProficient in Microsoft excel application and sensitive to numbers\nGood organisation, reporting and communication skills\nResult and detail oriented, efficient and able to multi tasks\nGood command of spoken and written English and Chinese\nImmediately available is preferred\n\n\nCompany Benefits:\n\n5-day work\nPaid annual leave; Bank holiday; Birthday off; Marriage leave\nFriendly company culture; stylish working environment; convenience location\nStaff purchase discount\nYear end discretionary bonus\nGreat promotion opportunities\n\nWe offer attractive remuneration and benefit package to the right candidate.\n\nInterested parties please send your full resume with current and expected salary, date of availability to\u00a0Human Resources Department by clicking \"Apply Now\"\n\n*Personal data collected is strictly confidential and will only be used for recruitment related purpose.", "employment_types": ["Full Time", "Permanent"], "selling_points": ["All-round administrative support", "Good organisation and reporting  skills", "Immediately available is preferred"], "locations": ["Aberdeen"], "categories": ["Admin & HR", "Administration / Operation Manager", "Clerical / Admin Staff", "HR Supporting Staff"], "post_time": "2022-01-17T08:07:27Z", "salary": {"currency": null, "max": null, "min": null, "period": "monthly", "term": null}, "salary_visible": false, "title_keywords": ["administrative officer"], "responsibilities": ["invoices", "administrative support", "reports", "secretarial support", "daily reports", "ad-hoc projects", "management review", "administration"], "requirements": {"degrees": ["diploma", "bachelor", "degree holder"], "majors": [], "languages": ["english", "chinese"], "language_level": ["good command"], "hard_skills": ["microsoft excel"], "soft_skills": ["efficient", "communication skills", "detail oriented", "organisation", "sensitive to numbers"], "languages_combined": [{"language": "english", "language_level": ["good command"]}, {"language": "chinese", "language_level": ["good command"]}]}, "experience_required": {"duration": [], "field": []}}, {"job_id": "100003009054229", "location_code": "hk", "company": "", "job_title": "Senior HR and Admin Officer", "description": "Job Description\n\nIndependently handle of C&B, recruitment and administration matters\nAssist the head of HR to plan, formulate and execute people related policies\nDeveloped training and staffing materials, KPI management align to brands requirement\nDrive company initiatives and manage projects\nFacilitate on-going communication across all levels and promote employee engagement\nResponsible for general administrative duties and office support including procurement and maintenance of office equipment / facilities, regular housekeeping, replenishment of office supplies, licenses renewal & etc.\nCo-ordinate and organize company activities and event\n\nRequirement\n\nDegree holder in Human Resources Management, Administration or related disciplines\nAt least 2 to 5 years relevant working preferably in FMCG field\nFluent in spoken and written English and Chinese\nKnowledge in Employment Ordinance and other HR related legislations\nHardworking, responsible, self-organized with good sense of judgement\nImmediate available preferred\n\nInterested parties please click apply and attach your full resume with current and expected salary and your availability.\n\nInformation provided will be treated in strict confidence and only be used for recruitment purpose. The Company may refer suitable applicants to other vacancies within the associated Group of companies. Applicants who are not invited for interview within 1 month may consider their applications unsuccessful.", "employment_types": ["Full Time", "Permanent"], "selling_points": ["C&B, staffing and training", "FMCG", "Young team, energetic"], "locations": ["Kwun Tong"], "categories": ["Admin & HR", "Administration / Operation Manager", "Compensation & Benefits", "Training & Development"], "post_time": "2022-01-17T08:51:40Z", "salary": {"currency": null, "max": null, "min": null, "period": "monthly", "term": null}, "salary_visible": false, "title_keywords": ["hr and admin officer"], "responsibilities": ["management", "housekeeping", "policies", "hr", "maintenance of office equipment", "office supplies", "office support", "replenishment", "communication", "recruitment", "manage projects", "plan", "administrative duties", "administration"], "requirements": {"degrees": ["degree holder"], "majors": ["related disciplines"], "languages": ["english", "chinese"], "language_level": ["fluent"], "hard_skills": [], "soft_skills": ["organized", "hardworking", "responsible"], "languages_combined": [{"language": "english", "language_level": ["fluent"]}, {"language": "chinese", "language_level": ["fluent"]}]}, "experience_required": {"duration": [], "field": []}}, {"job_id": "100003009054856", "location_code": "hk", "company": "Ignite Recruitment Hong Kong Limited", "job_title": "Human Resources & Administration, Senior Officer/ Assistant Manager - Corporate & Investment Bank", "description": "Our client is an expanding and well-established regional corporate & investment bank in Hong Kong. They are currently looking for a Human Resources & Admin, Senior Officer/ Assistant Manager\u00a0to join their Human Resources\u00a0Team in order to expand their business capacity in Hong Kong.\n\n\n\nResponsibilities\u00a0\n\nHuman Resources:\n\nTo provide full scope of efficient HR support and services to the company operations;\nReport to top management of the company and be responsible for full spectrum of Human Resources and Administration functions including recruitment & selection, compensation & benefits, training & development, employee relations and administration;\nReview company Human Resources policy and procedures to match with business demand and strategies;\nDrive annual compensation process including salary review, budgeting, incentive schemes to facilitate recruitment and retention program;\nCompile management reports and statistical analysis;\nLead or participate in ad hoc projects as required.\n\n\u00a0Admin:\n\nOversee various office administration functions, including facilities management, office supplies, document storage, fixed assets and inventory management\nManage office relocation, renovation projects, rental and lease agreements\nExecute office administration policies and procedures to ensure compliance with corporate requirements\nPrepare annual budget for office administration function and closely monitor operating expenditures\nAssist in appointment coordination and travel arrangement including arrangement of flights, hotel and transportation Schedule, coordinate, and organize events such as annual dinner, staff activities, meetings and conferences\nSupervise and review IT vendor service and performance\n\nRequirement\n\nDegree or above\n3 years + Human Resources & Admin working experience\nAccounting knowledge is preferable\nBanking experience would be an advantage\nCandidate with more experience would be considered for the Assistant Manager position\n\nTo apply online please click the 'Apply' button. For a confidential discussion about this role & other\u00a0 openings please contact Alex CHEUNG at +852 2121 1418 .", "employment_types": ["Full Time", "Permanent"], "selling_points": ["Expanding Regional Corporate & Investment Bank", "Excellent Work-Life Balance", "Strong Financial Performance with Attractive Bonus"], "locations": ["Central"], "categories": ["Admin & HR", "Administration / Operation Manager", "Compensation & Benefits", "HR Director / Manager"], "post_time": "2022-01-17T11:55:12Z", "salary": {"currency": "HKD", "max": 44999, "min": 25000, "period": "monthly", "term": null}, "salary_visible": true, "title_keywords": ["senior officer", "human resources", "assistant manager"], "responsibilities": ["operations", "budgeting", "renovation", "budget", "inventory management", "administration", "office administration", "monitor", "conferences", "schedule", "report", "management", "office supplies", "review", "procedures", "policies", "hr", "analysis", "ensure compliance", "coordinate", "management reports", "recruitment", "ad hoc projects", "coordination", "travel arrangement"], "requirements": {"degrees": ["degree or above"], "majors": [], "languages": [], "language_level": [], "hard_skills": [], "soft_skills": [], "languages_combined": []}, "experience_required": {"duration": ["3 years +"], "field": ["admin", "human resources", "banking experience"]}}, {"job_id": "100003009054322", "location_code": "hk", "company": "Siemens Logistics Limited", "job_title": "Project Administrator", "description": "Responsibilities:\n\nAssist Project Manager and the project team with daily project documentation\nCoordinate site purchasing and other documentation\nAssist in tracking purchase orders with approved vendors for material, machinery, equipment, tools, parts and a spectrum of other supplies or services\nHandling roster planning, leave records and administration task\nMaintain the inventory record and materials information\u00a0\nAssist in project coordination\nAssist with office administration\nOther duties as required\n\nRequirements:\n\nIndividuals who meet the following requirements or possess the equivalent combination of competence and experience are invited to apply:\n\nMinimum 2-3 years construction site experience at administrative capacity\nEffective multi-tasking skills in a fast-paced construction environment\nExcellent organizational and administrative skills with the ability to work independently and in a team environment\nDemonstrate proficiency in Microsoft Office and any other related software\nStrong attention to detail and accuracy\nStrong interpersonal and communication skills", "employment_types": ["Full Time"], "selling_points": ["Administration", "Assist in project coordination", "Assist with office administration"], "locations": ["Airport Area"], "categories": ["Admin & HR", "Administration / Operation Manager"], "post_time": "2022-01-17T09:09:27Z", "salary": {"currency": null, "max": null, "min": null, "period": "monthly", "term": null}, "salary_visible": false, "title_keywords": ["project administrator"], "responsibilities": ["administration", "project coordination", "other duties", "office administration", "project documentation", "inventory record", "coordinate", "purchase", "planning", "maintain", "documentation", "tracking"], "requirements": {"degrees": [], "majors": [], "languages": [], "language_level": [], "hard_skills": ["microsoft office"], "soft_skills": ["communication skills", "work independently", "organizational", "attention to detail", "multi-tasking skills", "interpersonal"], "languages_combined": []}, "experience_required": {"duration": ["minimum 2-3 years"], "field": ["administrative", "construction"]}}, {"job_id": "100003009052299", "location_code": "hk", "company": "Hong Kong Baptist Hospital", "job_title": "Assistant Manager (Supporting Services)", "description": "Degree holder\nMinimum 6 years of post-qualification administrative and supervisory experience, preferably in healthcare industry\nAssist Manager In-charge to manage the daily operation of hospital supporting services e.g. housekeeping service, logistics, linen and uniform management, maintain high professional standards, and responsible for general administration duties\nStrong communication, problem solving and analytical skills\nProficiency in MS Office and data analysis\nExcellent command of written and spoken Chinese and English\nWe offer attractive remuneration package and fringe benefits to the right candidates. Interested parties please apply with full resume and expected salary to Human Resources Department, Hong Kong Baptist Hospital, 18/F, Tower 2, Enterprise Square, 9 Sheung Yuet Road, Kowloon Bay, Kowloon, by email via \"Apply now\"\u00a0 or by fax to 2339 5769 on or before 31 January 2022.\nThe information provided will only be used for recruitment related purposes. All personal information on unsuccessful candidates will be destroyed within 6 months.", "employment_types": ["Full Time", "Permanent"], "selling_points": [], "locations": ["Kowloon City"], "categories": ["Admin & HR", "Administration / Operation Manager", "Medical Services", "Others", "Public / Civil", "Social Services - Community / Non-profit Organization"], "post_time": "2022-01-17T02:46:31Z", "salary": {"currency": null, "max": null, "min": null, "period": "monthly", "term": null}, "salary_visible": false, "title_keywords": ["assistant manager"], "responsibilities": ["management", "housekeeping", "daily operation", "communication", "data analysis", "maintain", "logistics", "administration"], "requirements": {"degrees": ["degree holder"], "majors": [], "languages": ["english", "chinese"], "language_level": ["excellent"], "hard_skills": ["problem solving", "analysis", "ms office", "analytical skills"], "soft_skills": ["communication", "problem solving and analytical skills", "responsible"], "languages_combined": [{"language": "english", "language_level": ["excellent"]}, {"language": "chinese", "language_level": ["excellent"]}]}, "experience_required": {"duration": ["minimum 6 years"], "field": ["healthcare industry", "administrative", "post-qualification", "supervisory experience"]}}, {"job_id": "100003009052557", "location_code": "hk", "company": "High Fashion Group", "job_title": "Executive Secretary", "description": "We are looking to hire an Executive Secretary for our business division which is a Family Investment Office that invest\u00a0mainly in property, equity and bonds. Candidates with property investment working experience is preferred.\u00a0We provide a stable and flexible career path for the right candidates.\u00a0\n\n\nResponsibilities:\u00a0\n\nProvide Secretarial support to CEO\nHandle business correspondence, minutes, reports, proposals and confidential documents as required\nPerform general clerical work, data entry and administration and HR support to the teams\nAct as personal assistant and attend business meetings\nManage and coordinate both internal and external issues including but not limited to i.e. private teacher, driver and domestic helper\nCarry out ad hoc assignments directed by management\n\nRequirements:\n\nUniversity Graduated is preferred\n3 years or above working experience\nProficiency in Microsoft Word, Excel, Power point\u00a0and Chinese typing\nProficiency in software related to graphic design will be an advantage\nFluent in Cantonese and English, fair in Mandarin\nGood\u00a0communication skill,\u00a0self-initiative, well-organized, responsible and able to work under pressure\nImmediate available is preferred\n\nWe offer an attractive package, good prospects and fringe benefits to the right candidate. Interested parties, please apply with full resume, current and expected salary to: Group Human Resources Manager of High Fashion Group. By Email: Click below \"Apply now\" button\u00a0(in MS Word format), or by mail: 11/F., High Fashion Centre, 1-11 Kwai Hei Street, Kwai Chung, New Territories\n\n\u00a0(The information received will be used for consideration of employment only and all personal data supplied will be destroyed within 6 months.)", "employment_types": ["Full Time", "Permanent"], "selling_points": ["Works in Central", "Double-pay, medical insurance and birthday leave", "5 day work week (9am-6pm)"], "locations": ["Central"], "categories": ["Accounting", "Accounting Clerk / Supervisor", "Admin & HR", "Administration / Operation Manager", "Secretary"], "post_time": "2022-01-17T03:24:49Z", "salary": {"currency": "HKD", "max": 34999, "min": 25000, "period": "monthly", "term": null}, "salary_visible": true, "title_keywords": ["executive secretary"], "responsibilities": [], "requirements": {"degrees": [], "majors": [], "languages": [], "language_level": [], "hard_skills": [], "soft_skills": [], "languages_combined": []}, "experience_required": {"duration": [], "field": []}}, {"job_id": "100003009049172", "location_code": "hk", "company": "Hong Kong Interbank Clearing Ltd", "job_title": "Assistant Manager (Administration)", "description": "Major Responsibilities\u00a0\n\nResponsible for managing general office administration, office renovation and relocation projects, reinstatement work and office improvement works\nAssist in business as usual (BAU) tasks of Administration team, such as office repairs and maintenance works and lease renewal of office premises\nPerform sourcing, analyze and exercise cost control on all purchases to optimize the pricing and product quality\nAssist in reviewing and arranging the take-out of insurance policies for the Company\u2019s perceived financial risks and office insurance including office perils and computer insurance\nHandle the procurement of office supplies, furniture and equipment and maintain an up-todate inventory record\nReview and maintain office administration policies and procedures including operating procedures, procurement guidelines and physical access control procedures\nManage and ensure general administration services including reception services and deliverables are in compliance with the corresponding statutory regulations, Company internal policies and guidelines, etc.\nLiaise with building management offices and/or relevant parties in the areas of maintenance, building facilities and general services\nOrganize Company events and functions such as annual dinner, Christmas parties, guest visits and external promotional events, etc.\nRequirements\u00a0\n\nUniversity education with at least 5 years of relevant experience in office administration and premises management; solid exposure in project co-ordination and management is preferred\nPrevious experience in handling renovation, interior fitting-out work, office relocation and facility management will be an advantage\nWell-organised, mature, self-motivated, independent, good team player and able to work under pressure\nProficiency in English business writing with strong analytical skills\nGood command of written and spoken English and Chinese\nGood knowledge of computer applications, such as MS Word, Excel, Powerpoint, PDF, etc.\nWilling to provide ad hoc support during non-office hours or adverse weather conditions if required\nCandidates with more experience may be considered for a more senior position", "employment_types": ["Full Time", "Permanent"], "selling_points": [], "locations": ["Ngau Tau Kok"], "categories": ["Admin & HR", "Administration / Operation Manager", "Clerical / Admin Staff", "Others"], "post_time": "2022-01-14T08:13:06Z", "salary": {"currency": null, "max": null, "min": null, "period": null, "term": null}, "salary_visible": false, "title_keywords": ["assistant manager"], "responsibilities": ["regulations", "renovation", "quality", "building management", "maintain", "liaise with", "administration", "reception services", "office administration", "compliance", "insurance", "office supplies", "review", "procedures", "inventory record", "maintenance", "guidelines", "policies", "cost control", "access control"], "requirements": {"degrees": [], "majors": [], "languages": ["english", "chinese"], "language_level": ["proficiency", "good command"], "hard_skills": ["ms word", "excel", "powerpoint", "analytical skills"], "soft_skills": ["good team player", "self-motivated", "independent", "mature", "analytical skills", "well-organised", "work under pressure"], "languages_combined": [{"language": "english", "language_level": ["proficiency", "good command"]}, {"language": "chinese", "language_level": ["good command"]}]}, "experience_required": {"duration": ["at least 5 years"], "field": ["office administration", "management", "relevant experience", "education"]}}, {"job_id": "100003009053733", "location_code": "hk", "company": "Koizumi Sangyo (H.K.) Corporation Limited", "job_title": "Administration and Human Resources Officer (Japanese Speaking)", "description": "Job Responsibilities\n\n- Support the CEO and Japanese staff in all aspects, Japanese working visa apply, company record renew\u00a0\n\n- Payroll calculation, staff record keeping, recruitment, MPF, insurance management, company residence for Japanese staff\u00a0\n\n- Office equipment maintenance, stationery order\n\n- Petty cash, cheque issue, payment\u00a0\n\nQualifications and other requirements:\u00a0\n\n-\u00a0Bachelor Degree or Certificate\n\n-\u00a0N2 or above, business level\u00a0of written and spoken Japanese\u00a0\n\n- At least 3 years relevant experience\n\n- Good command of written and spoken English and Chinese\u00a0(including Putonghua)\n\n- Able to work independently and willing to take responsibility\u00a0\n\n- Immediate available is preferred\u00a0\n\nFringe Benefits:\n\n- Attractive remuneration package and incentive\u00a0\u00a0\u00a0\u00a0\u00a0\u00a0\u00a0\u00a0\u00a0\u00a0\u00a0\u00a0\n\n- 5-day Work\n\n- Public Holiday\n\n- Starting from 10 days of Annual Leave (Max. 20 days)\n\n- Double pay\n\n- Discretionary Performance Bonus\n\n- Group Medical Insurance\n\n- Dental Insurance\n\n- OT allowance\n\n- Traffic allowance\n\n- Location of work: Tsim Sha Tsui\n\n\u00a0\nInterested parties, please send detailed resume with availability, current and expected\u00a0salary", "employment_types": ["Full Time"], "selling_points": [], "locations": ["Tsim Sha Tsui"], "categories": ["Admin & HR", "Administration / Operation Manager"], "post_time": "2022-01-17T07:25:16Z", "salary": {"currency": null, "max": null, "min": null, "period": "monthly", "term": null}, "salary_visible": false, "title_keywords": ["human resources officer"], "responsibilities": ["management", "mpf", "stationery", "payment", "office equipment maintenance", "recruitment", "insurance", "payroll"], "requirements": {"degrees": ["certificate", "degree", "bachelor"], "majors": [], "languages": ["japanese", "english", "chinese", "putonghua"], "language_level": ["good command"], "hard_skills": [], "soft_skills": ["work independently"], "languages_combined": [{"language": "japanese", "language_level": []}, {"language": "english", "language_level": ["good command"]}, {"language": "chinese", "language_level": ["good command"]}, {"language": "putonghua", "language_level": ["good command"]}]}, "experience_required": {"duration": ["at least 3 years"], "field": ["relevant experience"]}}, {"job_id": "100003009052048", "location_code": "hk", "company": "Swire Hotels", "job_title": "Administrative Assistant", "description": "PURPOSE OF ROLE:\n\nAs an Administrative Assistant, you will provide overall administrative assistance to Development team and Operations & Development team. This position will report to the Executive Assistant.\n\nWHAT YOU\u2019LL GET:\n\nAt Swire Hotels, we have great expectations of our team members. That's why we reward them with many in return. In addition to your competitive salary, medical/ dental and leave entitlement, we\u2019ll shower you with perks, including:\n\nDress:\u00a0Wear Smart & Casual (no formal suit) \u2013 and be as comfortable at work as you can.\nFlexibility:\u00a0Staggered working hours - pick your own work schedule to fit your own plan.\nFood:\u00a0Save thousands of dollars on food each year thanks to our team dining room.\nLocation:\u00a0 Above MTR Station, get here quickly thanks to our highly accessible location.\nWellness:\u00a0Chill yourself by joining our wellness programme and healthy pantry. Have FUN!\nLove Travel? Enjoy FREE room nights at all our hotels.\n\nWHAT YOU\u2019LL NEED:\n\nExperience: At least 2 years\u2019 relevant experience in a similar capacity, preferably in the hospitality industry or a multinational company\nEducation: Higher diploma holder or above in any discipline\nSkills: Excellent command of written and spoken English and Chinese. You\u2019ll also need strong interpersonal and communication skills in this position. Proficiency in MS office applications. Possess high integrity and respect confidentiality, and be able to work under pressure\nPersonality:\u00a0Proactive, agile, organized, presentable and detail minded\n\nWHAT YOU\u2019LL DO:\n\nAssist in arranging meetings logistics and office pantry\nManage key document and filing, corporate administration and secretarial duties\nPerform general administrative duties e.g. prepare reimbursement reports\nEngage in any ad-hoc assignments\nWant to find out more about us? Please visit\u00a0HERE.\u00a0\nInsiders have some\u00a0interview tips for you!\n\nWe offer attractive benefits (including 5-day work week) and excellent career development opportunities to our team members.\n\nWant to be one of us? Please send us your CV.\n\nApplicants who do not hear from us within six weeks of application should consider their applications unsuccessful. Information collected will be used for employment purpose only.", "employment_types": ["Full Time", "Permanent"], "selling_points": ["Provide overall administrative assistance", "Arrange meeting & office pantry", "Dynamic working environment"], "locations": ["Tai Koo"], "categories": ["Admin & HR", "Administration / Operation Manager", "Clerical / Admin Staff", "Secretary"], "post_time": "2022-01-17T02:03:50Z", "salary": {"currency": null, "max": null, "min": null, "period": null, "term": null}, "salary_visible": false, "title_keywords": ["administrative assistant"], "responsibilities": ["administration", "work under pressure", "operations", "ad-hoc assignments", "communication", "administrative assistance", "logistics", "schedule", "plan", "administrative duties", "reports", "report"], "requirements": {"degrees": ["higher diploma holder"], "majors": [], "languages": ["english", "chinese"], "language_level": ["excellent"], "hard_skills": ["no", "agile", "fun", "chill", "ms office"], "soft_skills": ["communication skills", "organized", "agile", "integrity", "presentable", "proactive", "interpersonal", "work under pressure"], "languages_combined": [{"language": "english", "language_level": ["excellent"]}, {"language": "chinese", "language_level": ["excellent"]}]}, "experience_required": {"duration": ["at least 2 years"], "field": ["hospitality industry", "relevant experience", "multinational company"]}}, {"job_id": "100003009046900", "location_code": "hk", "company": "KONG SHUM UNION PROPERTY MANAGEMENT CO., LTD.", "job_title": "Finance & Administration Manager / Assistant Finance & Administration Manager", "description": "Responsibilities\n\nResponsible for daily accounting operations including handling management fees and license fees income and issuing cheques.\nPrepare full set of monthly accounts and financial analysis independently.\nPrepare annual budget and forecast.\nEnsure internal control and compliance with company policies.\nLiaise with auditors for annual audit process.\nUpdate and maintain staff personal file\nPrepare payroll report\nPerform any other duties as assigned by the supervisor.\n\nRequirements\n\nDegree in Accounting.\nQualified Accountant.\nMinimum 5 years experiences.\nExperience in building management is an advantage.\nProficiency in MS Excel, Word and Powerpoint.\nGood command of both written and spoken English and Cantonese.\nImmediate available is preferred.\n\nImmediate available. Interested parties please send resume with expected salary by e-mail to: Apply Now\n(All personal data collected will be used for recruitment purpose only.)", "employment_types": ["Full Time"], "selling_points": [], "locations": ["Not Specified"], "categories": ["Accounting", "Accountant", "Finance / Accounting Manager", "Admin & HR", "Administration / Operation Manager"], "post_time": "2022-01-14T01:39:39Z", "salary": {"currency": null, "max": null, "min": null, "period": "monthly", "term": null}, "salary_visible": false, "title_keywords": ["finance & administration manager", "assistant"], "responsibilities": ["any other duties", "management", "annual audit", "policies", "budget", "compliance", "daily accounting operations", "financial analysis", "cheques", "maintain", "forecast", "liaise with", "report", "payroll", "internal control"], "requirements": {"degrees": ["degree"], "majors": ["accounting"], "languages": ["cantonese", "english"], "language_level": ["good command"], "hard_skills": ["ms excel", "word", "powerpoint"], "soft_skills": [], "languages_combined": [{"language": "cantonese", "language_level": ["good command"]}, {"language": "english", "language_level": ["good command"]}]}, "experience_required": {"duration": ["minimum 5 years"], "field": ["management"]}}, {"job_id": "100003009050758", "location_code": "hk", "company": "CITIC Pacific Limited", "job_title": "Senior Manager - Administration", "description": "Responsibilities:\n\nOversee a team of frontline staff such as Drivers, Receptionists, and Amahs to deliver a range of office administration services.\nPlan the office layout and manage office renovation projects to meet departments\u2019 operational needs.\nSupervise routine office services such as car pool service, document delivery, repair & maintenance of office equipment, procurement of office supplies, mailing, printing, etc.\nFormulate and review the administration policies and manuals.\nMonitor the vendors and contractors to ensure a high standard and cost effective administration services are provided to the Company\nResponsible for Ad-hoc duties and projects as required\n\nRequirements:\n\nUniversity Degree in Business Administration or related disciplines\nA minimum of 15 years' relevant experience in administrative work, 5 years of which in a supervisory capacity in a sizable organization.\nExperience in maintaining a fleet of company cars is preferred.\nProficient in PC applications in MS Office and Chinese word-processing\nGood command of spoken & written English and Chinese (Cantonese & Putonghua)\nExcellent communication and interpersonal skills and able to work with different stakeholders.\nIndependent, enthusiastic and have a good problem-solving skills\n\nPlease visit our\u00a0Career Website\u00a0\u00a0for more information.\n\nInterested parties may submit your application\u00a0by clicking the\u00a0\"Apply Now\"\u00a0button.\n\nAll information provided by applicants will be treated in strict confidence and used only for recruitment purpose. Applicants who are not contacted may consider their application unsuccessful. CITIC Pacific will retain the applications for a maximum period of one year during which applications may also be referred to other vacancies of CITIC Pacific Limited including its subsidiaries or affiliates.", "employment_types": ["Full Time", "Permanent"], "selling_points": ["5-day work, from 9am to 5pm", "Attractive remuneration package", "Comprehensive medical plan covering dependents"], "locations": ["Admiralty"], "categories": ["Admin & HR", "Administration / Operation Manager", "Clerical / Admin Staff", "Others"], "post_time": "2022-01-14T11:17:19Z", "salary": {"currency": null, "max": null, "min": null, "period": "monthly", "term": null}, "salary_visible": false, "title_keywords": ["senior manager"], "responsibilities": ["cost", "office supplies", "office administration", "maintenance of office equipment", "renovation", "review", "policies", "monitor", "repair", "plan", "ad-hoc duties", "administration"], "requirements": {"degrees": ["university degree"], "majors": ["related disciplines", "business administration"], "languages": ["cantonese", "putonghua", "english", "chinese"], "language_level": ["good command", "proficient"], "hard_skills": ["problem-solving skills", "ms office", "chinese word-processing", "pc applications"], "soft_skills": ["problem-solving skills", "communication and interpersonal skills", "independent", "enthusiastic"], "languages_combined": [{"language": "cantonese", "language_level": ["good command"]}, {"language": "putonghua", "language_level": ["good command"]}, {"language": "english", "language_level": ["good command"]}, {"language": "chinese", "language_level": ["good command", "proficient"]}]}, "experience_required": {"duration": ["5 years", "minimum of 15 years"], "field": ["sizable organization", "supervisory", "administrative", "relevant experience"]}}, {"job_id": "100003009052602", "location_code": "hk", "company": "NAHC Limited", "job_title": "Executive Assistant", "description": "Our client is a fast-growing global e-commerce business that is planning to double the team by the end of 2022. They are looking for an organised and disciplined individual to help with the C-suite's increasing administrative and communication tasks.\n\n\n\nResponsibilities\n\nProvide all-rounded secretarial assistance and administrative support to C-level executives\nCalendar management and logistical coordination of internal and external meetings\nPrepare meeting minutes, reports, presentations, and other business correspondences\nOrganize and file expense reports, daily mail, and meeting materials\nCoordinate and act as a liaison between internal and external parties\nAdministrative and communication project management\nAssisting with other ad hoc requests as required\n\nRequirements\n\nBachelor's degree holder, with formal secretarial experience would be an advantage\nExcellent prioritization and organizational skills to meet the deadlines of multiple concurrent projects under pressure\nProactively solves problems and look for ways to make systems more efficient\nOutstanding communication and interpersonal skills\nExcellent command of spoken and written English, Cantonese, and Mandarin", "employment_types": ["Full Time", "Permanent"], "selling_points": ["Fast Growing Global E-commerce Business", "Trilingual Executive Assistant", "Confident, organised and proactive team player"], "locations": ["Tsuen Wan Area"], "categories": ["Admin & HR", "Administration / Operation Manager", "Personal / Executive Assistant", "Secretary"], "post_time": "2022-01-17T03:30:46Z", "salary": {"currency": null, "max": null, "min": null, "period": "monthly", "term": null}, "salary_visible": false, "title_keywords": ["executive assistant"], "responsibilities": ["management", "administrative support", "ad hoc requests", "prepare meeting minutes", "internal and external parties", "presentations", "coordinate", "communication", "project management", "reports", "coordination"], "requirements": {"degrees": ["bachelor", "degree holder"], "majors": [], "languages": ["cantonese", "english", "mandarin"], "language_level": ["excellent"], "hard_skills": ["make"], "soft_skills": ["efficient", "organizational skills", "communication and interpersonal skills", "under pressure"], "languages_combined": [{"language": "cantonese", "language_level": ["excellent"]}, {"language": "english", "language_level": ["excellent"]}, {"language": "mandarin", "language_level": ["excellent"]}]}, "experience_required": {"duration": [], "field": ["secretarial"]}}, {"job_id": "100003009052630", "location_code": "hk", "company": "Dream Sport Academy Limited", "job_title": "Office Admin/Assistant/Marketing Assistant", "description": "The ideal candidate will be responsible for providing administrative support to ensure efficient operation of the office. You will be responsible for completing multi-level tasks in a professional and timely manner.\u00a0\n\nJob Responsibilities:\n\nOrganization and implementing business projects as well as monitoring the progress and report to Management\nOrganize and coordinate meetings and minutes, appointments, schedules, enquiries by Email & Phone calls from parents\nAssist office administrative work and handle any business support including Inventory Stock support\nPerform ad hoc assignments assigned by supervisors\n\n\n\nJob Requirement:\n\nF.5 or above education\nGood interpersonal and communication skills\nGood knowledge in MS Office e.g. Excel, Word, etc.\nExperience in Sports/fitness industry is an advantage\nIndependent, responsible, and willing to learn\nOrganized, able to handle multiple tasks and work overtime if needed\nFluent in spoken and written Mandarin and Cantonese, Good command of English is an advantage\nInterested parties please click \"APPLY NOW\" below and submit your CV and portfolio with expected salary and available date.\n\nAll information collected will be used for recruitment purpose only.", "employment_types": ["Full Time"], "selling_points": [], "locations": ["Kwai Fong"], "categories": ["Admin & HR", "Administration / Operation Manager"], "post_time": "2022-01-17T03:36:16Z", "salary": {"currency": null, "max": null, "min": null, "period": "monthly", "term": null}, "salary_visible": false, "title_keywords": ["marketing assistant", "admin", "assistant"], "responsibilities": ["management", "administrative work", "business projects", "schedules", "inventory", "monitoring", "coordinate", "ad hoc assignments", "phone calls", "report"], "requirements": {"degrees": [], "majors": [], "languages": ["cantonese", "english", "mandarin"], "language_level": ["advantage", "good command", "fluent"], "hard_skills": ["excel", "word", "ms office"], "soft_skills": ["communication skills", "organized", "work overtime", "independent", "responsible", "willing to learn", "handle multiple tasks", "interpersonal"], "languages_combined": [{"language": "cantonese", "language_level": ["advantage", "good command", "fluent"]}, {"language": "english", "language_level": ["advantage", "good command", "fluent"]}, {"language": "mandarin", "language_level": ["advantage", "good command", "fluent"]}]}, "experience_required": {"duration": [], "field": []}}, {"job_id": "100003009054581", "location_code": "hk", "company": "The Hong Kong University of Science and Technology", "job_title": "Assistant Manager (Admissions)(Job ID: 7068)", "description": "Job Title:\u00a0 \u00a0 \u00a0 \u00a0 \u00a0\u00a0Assistant Manager (Admissions)\nDepartment:\u00a0\u00a0\u00a0\u00a0School of Business and Management (MBA Programs)\nJob ID:\u00a0\u00a0\u00a0\u00a0\u00a0\u00a0\u00a0\u00a0\u00a0\u00a0\u00a0\u00a0\u00a07068\n\nJob Posting Details\n\nThe HKUST MBA Program Office is searching for an individual with strong organizational skills to fill the role of Assistant Manager (Admissions) in the Marketing & Admissions Team.\u00a0\n\nReporting to the Manager of Marketing & Admissions Team, the appointee will take part in the end-to-end candidate recruitment, admissions process management and yielding. \u00a0This role requires the exercise of independent judgement, strong administrative and excellent interpersonal skills with a focus in the following key areas:\u00a0\n\nCandidates Retention & Expectation Setting: Act as the dedicated admissions advisor and manage candidates\u2019 expectations during the pre-enrolment stage.\u00a0 Conduct personal consultations to guide the potential candidates during the admission process and achieve the team KPI in converting applicants to enrolled students.\nAdmissions Administration: Execute the University\u2019s guidelines and policies throughout the admission process.\u00a0 Manage the logistics of the entire admission process, including but not limited to handling application enquiries (phone & email); processing qualifications checking for offer issuance; scheduling interviews with potential candidates and internal interviewers; and providing regular reports on application and admission data.\nProject Management:\u00a0Conduct projects that cover different aspects of the admissions process as assigned to enhance operation efficiency and maintain partnership relations, such as system integration, AI Chabot and promotion scheme.\u00a0 \u00a0\n\nApplicants should have a bachelor\u2019s degree with at least 3 years of work experience.\u00a0 The ideal candidate should be a team player with excellent interpersonal & organizational skills.\u00a0 He/She should be proactive in problem-solving and have the capability to work under pressure and independently.\u00a0 Experience in managing CRM and admissions role is a plus.\u00a0 Prior background in global higher education is preferred but not compulsory. \u00a0Excellent communication skills and command of verbal and written English and Chinese (including Mandarin) are required.\u00a0 Occasional travel and working outside office hours including occasional weekends will be expected. (Duration: 2 years, renewable)\n\nStarting salary will be commensurate with qualifications and experience.\u00a0 Fringe benefits including annual leave, medical and dental benefits will be provided.\u00a0 A gratuity will be payable upon successful completion of contract.\n\nApplication Procedure\nIn support of a green work environment, we accept applications submitted online only.\u00a0 To apply, please complete an online application form through the HKUST Careers website (https://hkustcareers.ust.hk) and return it online to the Human Resources Office on or before Sunday, 6 February 2022.\u00a0 Applicants will receive an acknowledgement by email upon successful submission.\u00a0 We thank applicants for their interest, but advise that only shortlisted candidates will be notified of the result of the application.\n\n(Information provided by applicants will be used for recruitment and other employment-related purposes only.)\n\nHKUST is an equal opportunities employer and is committed to our core values of\ninclusiveness, diversity, and respect.", "employment_types": ["Full Time"], "selling_points": ["Candidates Retention & Expectation Setting", "Admissions Administration", "Project Management"], "locations": ["Sai Kung"], "categories": ["Admin & HR", "Administration / Operation Manager", "Education", "Others"], "post_time": "2022-01-17T10:06:16Z", "salary": {"currency": null, "max": null, "min": null, "period": "monthly", "term": null}, "salary_visible": false, "title_keywords": ["assistant manager"], "responsibilities": ["reporting", "management", "data", "guidelines", "policies", "work under pressure", "checking", "communication", "scheduling", "project management", "maintain", "recruitment", "logistics", "reports", "administration"], "requirements": {"degrees": ["degree", "bachelor"], "majors": [], "languages": ["english", "chinese", "mandarin"], "language_level": ["excellent"], "hard_skills": ["plus", "ai", "id", "problem-solving", "scheme", "project management", "integration", "focus", "processing"], "soft_skills": ["organizational skills", "communication skills", "independently", "independent", "work under pressure", "problem-solving", "project management", "team player", "interpersonal skills", "focus", "proactive", "interpersonal", "ideal"], "languages_combined": [{"language": "english", "language_level": ["excellent"]}, {"language": "chinese", "language_level": ["excellent"]}, {"language": "mandarin", "language_level": ["excellent"]}]}, "experience_required": {"duration": ["at least 3 years"], "field": []}}, {"job_id": "100003009046796", "location_code": "hk", "company": "Kingstar International Trading Ltd", "job_title": "Human Resources and Administration Manager", "description": "Responsible for full range of HR function, including recruitment, performance management, C & B and employee relations\nDesign & implement strategic HR plans & program to support the achievements of business objectives and organization growth\nSet and review HR policies, ensure all the legal compliance and requirement of employment ordinance are met\nCompile HR analytics and reports and keep the management abreast of the data trend\nSupport in formulation of talent related trainings, coordinate learning and development activities\nManage a full spectrum of administrative functions for office and warehouse operation\nCommunicate with all levels of staff and external partners for administration and HR related matters\nRequirements\nDegree Holder in Human Resources or related field\nAt least 5 years of human resources management experience in a sizable company preferred\nProficiency with HRIS and talent management systems is an advantage\nExcellent interpersonal, analytical and negotiation skills\nThorough knowledge of employment-related laws and regulations\nStrong command in verbal and written communication, English and Chinese\nWe Offer\n5 day work week\nDouble Pay\nMedical benefits\nStaff Free Goods & Staff Purchase discount\n\n\nInterested parties, please send your full resume and expected salary by clicking \"Apply Now\".\nPersonal data will be used for recruitment purpose only.", "employment_types": ["Full Time", "Permanent"], "selling_points": ["Oversee all round HR & Administration Operation", "Well-versed in Employment Ordinance", "Independent, strong problem-solving skill"], "locations": ["Tsim Sha Tsui"], "categories": ["Admin & HR", "Administration / Operation Manager", "Others", "HR Director / Manager"], "post_time": "2022-01-16T21:50:19Z", "salary": {"currency": null, "max": null, "min": null, "period": "monthly", "term": null}, "salary_visible": false, "title_keywords": ["administration manager", "human resources"], "responsibilities": ["communicate with", "regulations", "management", "data", "policies", "hr", "review", "compliance", "systems", "design", "coordinate", "communication", "recruitment", "reports", "plans", "administration"], "requirements": {"degrees": ["degree holder"], "majors": [], "languages": ["english", "chinese"], "language_level": [], "hard_skills": ["c"], "soft_skills": ["responsible", "communication", "negotiation skills", "learning", "thorough", "interpersonal"], "languages_combined": [{"language": "english", "language_level": []}, {"language": "chinese", "language_level": []}]}, "experience_required": {"duration": ["at least 5 years"], "field": ["management", "human resources"]}}, {"job_id": "100003009052959", "location_code": "hk", "company": "NexLen International Limited", "job_title": "Administrator", "description": "Job Responsibilities\n\nReceptionist\nMaintain inventory control for Sales and Purchases\nArranging courier / delivery issues\nProvide office administration support\nAd hoc tasks by managersInvioce issuing\n\nRequirements\n\n2-3 years' solid experience\nProficient in MS office especially in MS word, MS Excel\nGood communication skill, outgoing and self-motivated personality is required\nGood team player, willing to work under pressure and tight schedule\nGood command of both spoken and written English and Chinese\n\nWe offer attractive salary and fringe benefit package to the right candidate. Interested parties please send full resume with expected salary.\n\nPersonal data provided in your application will be kept in the strictest confidence. It will be used for employment-related purposes. Applications not notified within 1 month will be considered as unsuccessful. Unsuccessful application may be kept for another 3 months for new openings before properly shredded.", "employment_types": ["Full Time", "Permanent"], "selling_points": ["Salary package", "5-day working", "2-3 years' solid experience"], "locations": ["Kwun Tong"], "categories": ["Admin & HR", "Administration / Operation Manager", "Clerical / Admin Staff", "Others"], "post_time": "2022-01-17T04:42:30Z", "salary": {"currency": null, "max": null, "min": null, "period": "monthly", "term": null}, "salary_visible": false, "title_keywords": ["administrator"], "responsibilities": ["office administration support", "delivery issues", "ad hoc tasks", "inventory control", "maintain"], "requirements": {"degrees": [], "majors": [], "languages": ["english", "chinese"], "language_level": ["good command"], "hard_skills": ["ms word", "ms excel", "ms office"], "soft_skills": ["outgoing", "good team player", "self-motivated", "communication skill", "work under pressure"], "languages_combined": [{"language": "english", "language_level": ["good command"]}, {"language": "chinese", "language_level": ["good command"]}]}, "experience_required": {"duration": ["2-3 years"], "field": []}}, {"job_id": "100003009054199", "location_code": "hk", "company": "The Bank of East Asia, Limited", "job_title": "Trade Product Manager, Trade Services", "description": "Trade Product Manager, Trade Services (Job ID3374)\nResponsibilities\nTo be a team member of Trade Services Department.\nTo set up trade product team and lead subordinate(s).\nTo work with sales team and operations team of Trade Services Department.\nTo timely identify opportunity to drive and develop new trade products and to maintain and revamp existing trade products to meet business requirements.\nTo monitor and manage performance of trade products.\nTo keep close track with market trend and update and to share them with working partners.\u00a0 \u00a0\nTo conduct trade product training to working partners.\nTo cooperate working partner on trade promotion campaigns.\nTo take up ad hoc tasks as assigned.\nRequirements\nUniversity graduate in Business Administration or related discipline.\nA minimum of 10 years' working experience in banking/financial service industry, of which at least 5 years in trade product at managerial level. Trade sales or operations experience is preferred.\nSound knowledge of trade products and commodity market. \u00a0\nFamiliar with UCP, URR, URC, URDG, ISP98, ISBP, BPO, Incoterms & SWIFT etc.\nKnowledge and experience in Microsoft application implementation.\nStrong communication and project management skills.\nFluent in English, Mandarin and Cantonese.\nGood command of written English and Chinese.\n(Candidate with more experiences will be considered for the post of Senior Trade Product Manager)\nPlease apply online via the BEA Careers website at\u00a0https://careers.hkbea.com/psp/hcmprd/EMPLOYEE/HRMS/c/HRS_HRAM.HRS_APP_SCHJOB.GBL?Page=HRS_APP_JBPST&Action=UFOCUS=Applicant&SiteId=1&JobOpeningId=3374&PostingSeq=1 or by clicking the \"Apply Now\" button below. Kindly note that if you are a new user, you have to first create your User Profile before you can apply.\nPersonal data provided by job applicants will be used for recruitment purposes only and will be treated in accordance with the Bank's Personal Information Collection (Employees) Statement and Privacy Policy Statement. Applicants who are not invited for interviews within six weeks may consider their applications unsuccessful and the personal data collected will be destroyed after six months.", "employment_types": ["Full Time"], "selling_points": ["Keep close track with market trend", "University graduate in Business Administration", "A minimum of 10 years' working experience"], "locations": ["Not Specified"], "categories": ["Admin & HR", "Administration / Operation Manager", "Sales, CS & Business Devpt", "Business Development", "Others"], "post_time": "2022-01-17T08:47:15Z", "salary": {"currency": null, "max": null, "min": null, "period": "monthly", "term": null}, "salary_visible": false, "title_keywords": ["product manager"], "responsibilities": ["revamp", "operations", "monitor", "ad hoc tasks", "develop", "maintain", "sales team", "promotion campaigns", "meet business requirements"], "requirements": {"degrees": ["university graduate"], "majors": ["business administration"], "languages": ["cantonese", "english", "chinese", "mandarin"], "language_level": ["good command", "fluent"], "hard_skills": ["swift", "project management", "c"], "soft_skills": ["communication", "project management skills"], "languages_combined": [{"language": "cantonese", "language_level": ["fluent"]}, {"language": "english", "language_level": ["good command", "fluent"]}, {"language": "chinese", "language_level": ["good command"]}, {"language": "mandarin", "language_level": ["fluent"]}]}, "experience_required": {"duration": ["at least 5 years", "minimum of 10 years"], "field": ["managerial", "service industry", "financial", "banking"]}}, {"job_id": "100003009046370", "location_code": "hk", "company": "Hong Kong Institute of Construction", "job_title": "Officer - Campus Administration, HKIC", "description": "The applicant must possess\na\u00a0recognised degree;\na minimum of 3 years\u2019 post-qualification work experience in institutional administration, preferably in vocational training bodies, educational institutions, public bodies or sizable organisations;\nknowledge in construction and managerial accounting would be an advantage;\nstrong leadership, self-initiative and problem solving skills;\na high level of integrity and a strong sense of responsibility;\ngood communication and interpersonal skills;\na pro-active, resourceful and energetic character, and the ability to work independently with minimal supervision;\ngood knowledge and skills in Word, Excel, Powerpoint, English and Chinese word processing; and\na good command of both written and spoken English and Chinese.\n(Applicants who do not possess the required qualifications and / or experience may be considered for other positions within the organisation.)\nDuties include\nto oversee the daily operation of the Kowloon Bay Campus and lead the administration team to ensure smooth and effective operation;\nto initiate, plan, manage and implement new development initiatives and improvement initiatives;\nto assist the adoption of computerisation and carry out user acceptance test in system implementation;\nto assist in promoting construction training including the marketing of construction related courses to the general public and the stakeholders of the construction industry;\nto assist in obtaining qualifications recognition from local and overseas professional organisations, educational institutions and government authorities;\nto perform secretariat duties for related task forces, promotion events, seminars, conferences, and any other relevant activities;\nto prepare for the annual budget;\nto help maintain the Kowloon Bay Campus in a clean and tidy state of operation and help task the security guards and cleaners;\nto act as duty-in-charge during non-office hour operation; and\nto carry out any other duties as assigned from time to time by the Executive Director.\nApplications\nThe position is on a renewable fixed-term contract (subject to performance and operational needs) for a period of 2 years.\nPlease click the below \u201cApply Online\u201d to complete the application form and upload the updated curriculum vitae, the results of English and Chinese Language obtained in public examinations, current and expected salary together with a covering letter stating one\u2019s suitability for the job on or before\u00a027\u00a0January\u00a02022.", "employment_types": ["Full Time", "Contract"], "selling_points": ["a recognised degree", "min. 3 years\u2019 post-qualification work experience", "oversee the daily operation of the Campus"], "locations": ["Not Specified"], "categories": ["Admin & HR", "Administration / Operation Manager", "Clerical / Admin Staff", "Education", "Others"], "post_time": "2022-01-13T10:46:17Z", "salary": {"currency": null, "max": null, "min": null, "period": null, "term": null}, "salary_visible": false, "title_keywords": ["officer"], "responsibilities": ["any other duties", "budget", "daily operation", "implementation", "communication", "conferences", "maintain", "plan", "administration"], "requirements": {"degrees": ["degree"], "majors": [], "languages": ["english", "chinese"], "language_level": ["good command", "good"], "hard_skills": ["clean", "excel", "chinese word processing", "word", "powerpoint", "system implementation", "problem solving skills"], "soft_skills": ["work independently", "resourceful", "sense of responsibility", "integrity", "smooth", "communication and interpersonal skills", "self-initiative", "organisation", "pro-active", "problem solving skills", "energetic", "leadership"], "languages_combined": [{"language": "english", "language_level": ["good command", "good", "good"]}, {"language": "chinese", "language_level": ["good command", "good", "good"]}]}, "experience_required": {"duration": ["minimum of 3 years"], "field": ["post-qualification", "training", "administration"]}}, {"job_id": "100003009050549", "location_code": "hk", "company": "SOGO Hong Kong Co Ltd", "job_title": "SENIOR MANAGER, ADMINISTRATION", "description": "Responsibilities\n\nLead a team of administrative staff\u00a0to effectively perform full spectrum of administrative services\nBe responsible for cleaning management, general supply & equipment procurement & stock control, fixed assets registration and travel management\nPrepare and review contracts and tender documents in the procurement of goods and services\nBe responsible for group insurance arrangement, vendor management, leasing, office space planning, office renovation and relocation projects\nFormulate & regularly review administration policies and operational procedures, and monitor the implementation\nPrepare departmental annual budget and expense report\nLiaise with internal and external parties and manage ad-hoc assignment\n\nRequirements\n\nBachelor Degree in Business Administration or related disciplines\nMinimum 8 years of relevant experience with 5 years in management level\nInitiatives, responsible, detail-oriented, well organized and self-motivated\nExcellent communication and supervisory skills, able to work with all levels of people\nGood command of both spoken and written English and Chinese\nProficiency in Microsoft Office applications including Word, Excel, PowerPoint and Chinese Word Processing\nAttractive remuneration package, public holidays, group medical insurance, excellent career development opportunities and other competitive fringe benefits will be offered to the suitable candidate. Interested parties please click the \u2018Apply Now\u2019\u00a0button and submit your application details together with current and expected salary to the Human Resources Division.\nInformation provided will be for the purpose of selection within the Group and only shortlisted candidates will be considered. All application will be retained for a maximum period of six months.\u00a0", "employment_types": ["Full Time", "Permanent"], "selling_points": [], "locations": ["Not Specified"], "categories": ["Admin & HR", "Administration / Operation Manager"], "post_time": "2022-01-14T10:41:20Z", "salary": {"currency": null, "max": null, "min": null, "period": "monthly", "term": null}, "salary_visible": false, "title_keywords": ["senior manager"], "responsibilities": ["ad-hoc", "renovation", "budget", "internal and external parties", "liaise with", "administration", "control", "tender documents", "contracts", "monitor", "implementation", "operational procedures", "report", "management", "review", "cleaning", "policies", "lead a team", "insurance", "planning"], "requirements": {"degrees": ["degree", "bachelor"], "majors": ["related disciplines", "business administration"], "languages": ["english", "chinese"], "language_level": ["proficiency", "good command"], "hard_skills": ["excel", "chinese word processing", "microsoft office", "word", "powerpoint"], "soft_skills": ["self-motivated", "responsible", "well organized", "detail-oriented", "communication"], "languages_combined": [{"language": "english", "language_level": ["good command"]}, {"language": "chinese", "language_level": ["proficiency", "good command"]}]}, "experience_required": {"duration": ["5 years", "minimum 8 years"], "field": ["management", "relevant experience"]}}, {"job_id": "100003009054536", "location_code": "hk", "company": "The Hong Kong University of Science and Technology", "job_title": "Executive Assistant to Vice-President for Research and Development (Job ID: 7067)", "description": "Job Title:\u00a0\u00a0\u00a0\u00a0\u00a0\u00a0\u00a0\u00a0\u00a0Executive Assistant to Vice-President for Research and Development\nDepartment:\u00a0 \u00a0 Office of the Vice-President for Research and Development\nJob ID:\u00a0\u00a0\u00a0\u00a0\u00a0\u00a0\u00a0\u00a0\u00a0\u00a0\u00a0\u00a0\u00a07067\n\nJob Posting Details\n\nThe appointee will assist the Vice-President for Research and Development (VPRD) in all aspects of administration related to the VPRD Office, including strategic planning; managing and overseeing the VPRDO; planning and coordinating budgets and resources; servicing committees; preparing papers and reports; reviewing and administering research-related policies, services and activities; managing special projects; and offering advice and acting on various duties under the auspices of VPRD. The appointee will also serve as a liaison person between VPRD and members of the University to ensure effective flow of communication and smooth implementation of policy and schemes.\n\nApplicants should have a bachelor\u2019s degree with at least 10 years of relevant work experience in the higher education sector. The ideal candidate should have a strong sense of responsibility and commitment, and be highly initiative, detail-oriented and multi-task oriented.\u00a0 He/She should possess excellent and demonstrable leadership; organizational, planning and interpersonal communication; and analytical and problem-solving skills.\u00a0 Excellent command of written and spoken English and Chinese (both Cantonese and Putonghua) is required. (Duration: 2 years, renewable)\n\nStarting salary will be commensurate with qualifications and experience. \u00a0Fringe benefits including annual leave, medical and dental benefits will be provided. \u00a0A gratuity will be payable upon successful completion of contract.\n\nApplication Procedure\nIn support of a green work environment, we accept applications submitted online only. \u00a0To apply, please complete an online application form through the HKUST Careers website (https://hkustcareers.ust.hk) and return it online to the Human Resources Office on or before\u00a0Monday, 31 January 2022.\u00a0 Applicants will receive an acknowledgement by email upon successful submission.\u00a0 We thank applicants for their interest, but advise that only shortlisted candidates will be notified of the result of the application.\n\n(Information provided by applicants will be used for recruitment and other employment-related purposes only.)\n\nHKUST is an equal opportunities employer and is committed to our core values of\ninclusiveness, diversity, and respect.", "employment_types": ["Full Time"], "selling_points": ["planning and coordinating budgets and resources", "servicing committees", "preparing papers and reports"], "locations": ["Sai Kung"], "categories": ["Admin & HR", "Administration / Operation Manager", "Education", "Others"], "post_time": "2022-01-17T09:54:56Z", "salary": {"currency": null, "max": null, "min": null, "period": "monthly", "term": null}, "salary_visible": false, "title_keywords": ["vice president", "executive assistant"], "responsibilities": ["administration", "budgets", "strategic planning", "policies", "implementation", "communication", "reports", "planning"], "requirements": {"degrees": ["degree", "bachelor"], "majors": [], "languages": ["cantonese", "putonghua", "english", "chinese"], "language_level": ["excellent"], "hard_skills": ["id", "problem-solving skills"], "soft_skills": ["multi-task oriented", "sense of responsibility", "organizational", "detail-oriented", "communication", "smooth", "problem-solving skills", "interpersonal", "leadership", "initiative", "ideal"], "languages_combined": [{"language": "cantonese", "language_level": ["excellent"]}, {"language": "putonghua", "language_level": ["excellent"]}, {"language": "english", "language_level": ["excellent"]}, {"language": "chinese", "language_level": ["excellent"]}]}, "experience_required": {"duration": ["at least 10 years"], "field": ["education"]}}, {"job_id": "100003009053953", "location_code": "hk", "company": "Able Engineering Company Limited", "job_title": "Assistant Clerical Officer", "description": "Level 2 or equivalent or above in five subjects including Mathematics in the Hong Kong Diploma of Secondary Education Examination (HKDSEE), or equivalent; or\nLevel 2 / Grade E or above in five subjects including Mathematics in the Hong Kong Certificate of Education Examination (HKCEE), or equivalent;\nMet the language proficiency requirement of Level 2 or above in Chinese Language and English Language in HKDSEE or HKCEE, or equivalent; and\nChinese word processing speed of 20 words per minute and English word processing speed of 30 words per minute and knowledge in the application of common business software\n\nWe offer competitive salary package and career development opportunity to the successful candidate. Interested parties may send your full resume, present and expected salary, available date and contact number by clicking \"Apply Now\".\n\n\n\nTo visit our website for more information: www.ableeng.com.hk\n\n(As an Equal Opportunities Employer, Able is committed to eliminating discrimination in employment. The vacancy advertised is open to all applicants meeting the basic entry requirement irrespective of their disability, sex, marital status, pregnancy, age, family status, sexual orientation or race etc. Applicants not hearing from us within 6 months may consider their applications unsuccessful. Personal data collected will be used for recruitment related purposes only.)", "employment_types": ["Full Time"], "selling_points": [], "locations": ["Not Specified"], "categories": ["Admin & HR", "Administration / Operation Manager", "Clerical / Admin Staff", "HR Supporting Staff"], "post_time": "2022-01-17T07:50:21Z", "salary": {"currency": null, "max": null, "min": null, "period": "monthly", "term": null}, "salary_visible": false, "title_keywords": ["officer", "assistant"], "responsibilities": ["software"], "requirements": {"degrees": ["certificate", "diploma", "secondary education"], "majors": ["mathematics"], "languages": ["english", "chinese"], "language_level": ["proficiency"], "hard_skills": ["business software", "chinese word processing", "word processing", "words"], "soft_skills": [], "languages_combined": [{"language": "english", "language_level": ["proficiency"]}, {"language": "chinese", "language_level": ["proficiency"]}]}, "experience_required": {"duration": [], "field": []}}, {"job_id": "100003009051033", "location_code": "hk", "company": "The Wharf Group", "job_title": "Administration Supervisor", "description": "Responsibilities\u00a0\n\nAssist in renovation, relocation, security and safety management of an office of size about 70,000 g.s.f.\nSupervise\u00a0messengers, drivers, tea ladies and watchmen to deliver quality office service\nManage company cars and assign orders/works to drivers\nHandle office repair and maintenance\nAssist in\u00a0ad hoc assignments\n\nRequirements\u00a0\n\nWith\u00a0at least\u00a05 years relevant experience in\u00a0sizable\u00a0office and supervision of office junior staff and car pool drivers\nStrong sense of responsibility, hands-on and committed to deliver quality results\nOrganized, able to handle multi-tasks and prioritize works under tight schedules\nGood interpersonal and communication skills, a team player\nWilling to work beyond office hours and on holidays to supervise office renovation and relocation projects\u00a0when necessary\nProficient in spoken and written English & Chinese\u00a0(Cantonese) and Microsoft Office and AutoCAD (preferred)\nImmediately available preferred\n\n\u00a0\nInterested parties, please click \"APPLY NOW\" and attach with your application letter and full resume.\u00a0\n\nFor further information of the Wharf Group, please visit our website: www.wharfholdings.com", "employment_types": ["Full Time", "Permanent"], "selling_points": [], "locations": ["Tsim Sha Tsui"], "categories": ["Admin & HR", "Administration / Operation Manager", "Clerical / Admin Staff", "Others"], "post_time": "2022-01-15T01:20:33Z", "salary": {"currency": null, "max": null, "min": null, "period": null, "term": null}, "salary_visible": false, "title_keywords": ["supervisor"], "responsibilities": ["management", "maintenance", "renovation", "quality", "repair", "ad hoc assignments"], "requirements": {"degrees": [], "majors": [], "languages": ["cantonese", "english", "chinese"], "language_level": ["proficient"], "hard_skills": ["autocad", "microsoft office"], "soft_skills": ["organized", "communication skills", "multi-tasks", "sense of responsibility", "prioritize", "committed", "hands-on", "team player", "interpersonal"], "languages_combined": [{"language": "cantonese", "language_level": ["proficient"]}, {"language": "english", "language_level": ["proficient"]}, {"language": "chinese", "language_level": ["proficient"]}]}, "experience_required": {"duration": ["at least 5 years"], "field": ["relevant experience"]}}, {"job_id": "100003009051924", "location_code": "hk", "company": "Octopus Holdings Limited", "job_title": "Operation Services Assistant (Card Centre) Ref: OCL/OPS/2021-023-042  (Temporary)", "description": "Job Responsibilities: \u00a0\nPersonalised Octopus Application\nProcess Personalised Octopus application including data input, data verification and photo scanning for\nproduction of Personalised Octopus.\nPrepare Personalised Octopus application data preparation and work with outsourcing service providers.\nHandle internal enquiries on card orders\nCheck the quality of the written data in chip and printed data on the card face of Personalised Octopus.\nMalfunction and Sold Products Operations\nIssue replacement Octopus according to customer\u2019s request \u00a0\nHandle card refund or replacement of corporate staff Octopus\nHandle mailing consolidation and returned mails\nProvide warehouse operation support and card stock housekeeping \u00a0\nCard Refund and Lost Card Operations\nPerform investigation of Octopus refund and replacement request and perform related data entry according\nto customer\u2019s request and Octopus card refund and replacement procedures\nPrepare reports for daily reconciliation and various MIS reports\nHandle customer enquiries timely and tactfully\u00a0\n\nRequirements:\nHKCEE or DSE graduate with 5 subjects passed, including English, Chinese and Mathematics \u00a0\nUndergraduate degree holder is preferred\n1 year of clerical working experience, preferably in financial institution\nEnglish and Chinese Typing speed at 35 w.p.m.\nGood command of spoken and written English and Chinese. \u00a0\nGood numerical sense, logical and analytical skills \u00a0\nGood team player with strong sense of customer service awareness and interpersonal skills\nAble to work under pressure\nWe offer successful candidate an attractive remuneration package and excellent career prospects. Interested parties please send your resume, present and expected salary, contact details and quoting the reference number by clicking \"Apply Now\"\n\nVisit our web site: http://www.octopus.com.hk/\n\nThe personal data collected will be used for recruitment purposes only. If you are not contacted by us within six weeks, you may consider your application unsuccessful. Personal data with an unsuccessful applicant will be destroyed 12 months after rejection of the application. During this retention period, you have the right to request for correction or destruction of your personal data at any time. Any request for the correction or destruction of personal data should be addressed in writing to our Human Resources & Administration Department.\n\nOctopus is an equal opportunity employer and all employment decisions and Human Resources policies are administered; especially those relating to recruitment & selection, compensation & benefits, promotion & transfer, training & development and termination & redundancy; without discrimination on the basis of age, race, colour, religion, sex, national origin, marital status, pregnancy, physical and mental disability and family status but on genuine occupational qualification, job performance, employees\u2019 ability and internal/ external relativities.\n%MCEPASTEBIN%", "employment_types": ["Temporary", "Contract"], "selling_points": ["Perform investigation of Octopus refund", "Handle card refund or replacement", "1 year of clerical working experience"], "locations": ["Tsuen Wan Area"], "categories": ["Admin & HR", "Administration / Operation Manager", "Personal / Executive Assistant", "Others"], "post_time": "2022-01-17T01:32:40Z", "salary": {"currency": null, "max": null, "min": null, "period": "monthly", "term": null}, "salary_visible": false, "title_keywords": ["assistant"], "responsibilities": ["scanning", "handle customer enquiries", "data verification", "data", "housekeeping", "operations", "data entry", "quality", "data input", "investigation", "procedures", "reports", "prepare reports"], "requirements": {"degrees": ["dse", "degree holder"], "majors": ["mathematics"], "languages": ["english", "chinese"], "language_level": ["good command"], "hard_skills": ["typing", "analytical skills"], "soft_skills": ["good team player", "analytical skills", "customer service", "interpersonal skills", "work under pressure"], "languages_combined": [{"language": "english", "language_level": ["good command"]}, {"language": "chinese", "language_level": ["good command"]}]}, "experience_required": {"duration": ["1 year"], "field": ["clerical", "financial"]}}, {"job_id": "100003009054107", "location_code": "hk", "company": "Putien Restaurant (H.K.) Limited", "job_title": "Operation Assistant", "description": "Responsibilities:\n\nAssist the District Supervisor to develop overall strategies and initiatives for daily operations and monitor performance of the shops to maximize sales and productivity, manpower efficiency and customer service standard\nWork with District Supervisor to analyze weekly and monthly sales activity, revenue, and P&L reports, to ensure adherence to budgets, business plans and targets\nTo manage, train, motivate and mentor frontline with expectations of their respective plans\nPrepare operational analysis, reports and recommendations\nPerform clerical duties and operational support to operations team\nOther ad- hoc duties assigned by manager\n\nRequirements:\n\nDiploma or above, graduated in Hospitality Management or related disciplines will be an advantage\nMinimum 2 years relevant experience, F&B experience is preferred.\nIndependent and outgoing personality, team player with flexibility\nInitiative, willing to learn and take up challenges\nProficiency in both spoken and written English and Chinese\nGood PC skills (Microsoft PowerPoint, Word, Excel )\nStrong communication and interpersonal skills\nImmediately available or at short notice is an advantage.\nFieldwork is a necessary\n\n\n\n\u00a0We offer attractive remuneration package, commensurate with experience to the successful applicant. Interested parties please click \"send full resume with current and expected salaries to\u00a0The Human Resources Manager\n\n\u00a0\u00a0\u00a0\u201cAll application received will be kept strictly confidential and used exclusively for employment purpose only\u201d\u00a0", "employment_types": ["Full Time"], "selling_points": [], "locations": ["Tsuen Wan Area"], "categories": ["Admin & HR", "Administration / Operation Manager", "Hospitality / F & B", "Food & Beverage", "Management", "Management Trainee"], "post_time": "2022-01-17T08:25:32Z", "salary": {"currency": "HKD", "max": 19999, "min": 17000, "period": "monthly", "term": null}, "salary_visible": true, "title_keywords": ["operation assistant"], "responsibilities": ["budgets", "operational support", "monitor performance", "ensure adherence", "analysis", "operations", "p&l", "develop", "business plans", "daily operations", "customer service", "reports", "plans"], "requirements": {"degrees": ["diploma or above"], "majors": ["hospitality management", "related disciplines"], "languages": ["english", "chinese"], "language_level": ["proficiency"], "hard_skills": ["excel", "pc skills", "word", "microsoft powerpoint"], "soft_skills": ["outgoing personality", "independent", "willing to learn", "communication and interpersonal skills", "team player", "initiative"], "languages_combined": [{"language": "english", "language_level": ["proficiency"]}, {"language": "chinese", "language_level": ["proficiency"]}]}, "experience_required": {"duration": ["minimum 2 years"], "field": ["f&b", "relevant experience"]}}, {"job_id": "100003009052601", "location_code": "hk", "company": "K. Wah International Holdings Ltd", "job_title": "\u517c\u8077\u8336\u6c34\u670d\u52d9\u54e1", "description": "Role Introduction\n\n\nReports to:\u00a0Senior Solution Lead\n\nThis role is responsible for understanding business needs and driving technology direction and solution delivery within a business domain.\n\nKey Responsibilities\n\n\nThe Solution Lead (SL) is responsible for delivery of high quality IT product or applications to the business. Key responsibilities may be categorised into five areas:\n\nBusiness Engagement\n\nSupport pre-project consulting for a portfolio pipeline of initiatives\nCapture and communicate business direction, challenges and requirements\nSupport business process change\nRecommends commercially and technically viable ideas to improve the business performance\n\nTechnology Design and Implementation\n\nWork closely with the developers, analyst and architects to architect and develop the best technical design. Conceptualise and propose solution approaches\nPlanning, designing, developing, implementing, and supporting IT products and applications to meet the customer needs\nProvide an escalation point for solution analysts in order to deliver business solutions that include technology implementations and/or adaptations\nRecommends and implements simple continuous improvement of standard Cathay IT Practices\nKeep abreast of latest trends in technology, industry and corresponding business domain\nResponsible for application maintenance and striving for continuous improvements within the application lifecycle\n\nSupport\n\nManage team and 3rd parties to resolve technical issues for business\nProactively identify support needs to improve internal efficiency and business satisfaction\nAnalyze and monitor key operational metrics to help drive product and support improvements\nCollaborate with cross-functional teams on issues and defects\n\nProject Delivery\n\nFocus on small to medium scale initiatives\nInitiate, define, plan and execute tasks / initiatives\nTest all solution aspects including but not limited to security, performance, integration\nFacilitate project progress through relevant gates\nManage the day-to-day activities of the software development team and external 3rd parties as required\n\nPeople Management\n\nContribute to team resource planning\nManage external 3rd parties as required\n\nThe Solution Lead may also:\n\nBe directly involved in implement solutions in an Agile development team\nDirectly manage one or more Solution Analysts\nPerform the role of surrogate Product Owner / BU SME (generally Senior)\nCoach Solution Analysts on any aspect of their role\n\nRequirements\n\n\nDegree qualification in Information Technology related discipline, Masters preferred\n8+ years of related IT experience covering but not limited to:\nSoftware development\nSystem analysis\nBusiness analysis\nSolution definition\nSystem Testing\nClient facing experience with successful relationship management is a plus\nProven verbal and written communication skill\nProfessional, passionate, innovative, self-motivated and able to present solutions to diverse groups of stakeholders\nStrong analytical, problem-solving, and decision-making skills, leveraging both logic and creativity\nProven troubleshooting skills; ability to identify patterns and generate ideas\n\nPersonal & Application Information\n\n\nCathay Pacific is an Equal Opportunities Employer. Personal data provided by job applicants will be used strictly in accordance with our personal data policy and for recruitment purposes only. Candidates not notified within eight weeks may consider their application unsuccessful. All related information will be kept in our file for up to 24 months. A copy of our Personal Information Collection Statement will be provided upon request by contacting our Data Protection Officer.\n\nPlease note that with effect from 1 December 2021, all employees must be vaccinated in order to access Cathay City and all other Cathay Group Company premises in Hong Kong. Consideration will be given to those who are unable to get vaccinated for valid medical reasons.", "employment_types": ["Part Time"], "selling_points": [], "locations": ["North Point"], "categories": ["Admin & HR", "Administration / Operation Manager", "Others"], "post_time": "2022-01-17T03:30:28Z", "salary": {"currency": null, "max": null, "min": null, "period": "hourly", "term": null}, "salary_visible": false, "title_keywords": [], "responsibilities": ["collaborate with", "ideas", "software", "consulting", "quality", "agile development", "design", "business process", "plan", "designing", "sme", "monitor", "implementation", "developing", "develop", "project progress", "continuous improvements", "management", "cross-functional teams", "maintenance", "planning"], "requirements": {"degrees": ["degree"], "majors": ["information technology"], "languages": [], "language_level": [], "hard_skills": ["problem-solving", "analysis", "plus"], "soft_skills": ["passionate", "self-motivated", "problem-solving", "communication skill", "troubleshooting", "diverse", "innovative"], "languages_combined": []}, "experience_required": {"duration": ["8+ years"], "field": ["related", "management", "it experience"]}}, {"job_id": "100003009053028", "location_code": "hk", "company": "EC Healthcare", "job_title": "Human Resources Manager / Assistant Manager - Talent Acquisition", "description": "\u8077\u8cac :\n\n\u4e3b\u8981\u8ca0\u8cac\u8336\u6c34\u670d\u52d9\uff1b\u4e00\u822c\u6e05\u6f54\u670d\u52d9 \uff0c\u5305\u62ec\u5438\u5875\u3001\u5012\u5783\u573e\u53ca\u57fa\u672c\u6e05\u6f54\uff1b\u6574\u7406\u6703\u8b70\u5ba4\u3001\u652f\u63f4\u5404\u9805\u6703\u8b70\u53ca\u6d3b\u52d5\u4e4b\u8336\u6c34\u7b49\uff1b\u5982\u6709\u7dca\u6025\u8981\u52d9\uff0c\u9700\u5354\u52a9\u5916\u52e4\u5230\u9644\u8fd1\u9280\u884c\u5165\u7968\u6216\u8cfc\u8cb7\u88dc\u7d66\u7269\u8cc7\u7b49\n\u8cc7\u6b77 :\u6c92\u6709\u5b78\u6b77\u8981\u6c42; 1\u5e74\u7d93\u9a57; \u826f\u597d\u7cb5\u8a9e; \u61c2\u95b1\u8b80\u4e2d\u6587\n\u5f85\u9047 :\u6bcf\u5c0f\u6642$72.00, \u661f\u671f\u4e00,\u4e8c,\u56db,\u4e94: \u4e2d\u534812\u6642\u81f3\u4e0b\u53484\u6642\u53ca\u661f\u671f\u4e09: \u4e0a\u53487\u6642\u81f3\u4e0b\u53484\u6642, \u6bcf\u9031\u5de5\u4f5c5\u5929, \u6bcf\u5929\u5de5\u4f5c 4 - 9 \u5c0f\u6642\n\u7533\u8acb\u9808\u77e5 :\u6c42\u8077\u8005\u53ef\u81f4\u96fb29603323\u8207\u5609\u83ef\u570b\u969b\u96c6\u5718\u6709\u9650\u516c\u53f8\u8521\u5c0f\u59d0\u806f\u7d61\u3002", "employment_types": ["Full Time"], "selling_points": ["Determine staffing needs and produce forecasts", "Forecast future talent or staffing needs", "Budget for recruitment costs"], "locations": ["Mong Kok"], "categories": ["Admin & HR", "Administration / Operation Manager", "HR Director / Manager", "Recruitment / Executive Search"], "post_time": "2022-01-17T05:12:27Z", "salary": {"currency": null, "max": null, "min": null, "period": "monthly", "term": null}, "salary_visible": false, "title_keywords": ["assistant manager", "manager", "human resources"], "responsibilities": [], "requirements": {"degrees": [], "majors": [], "languages": [], "language_level": [], "hard_skills": [], "soft_skills": [], "languages_combined": []}, "experience_required": {"duration": [], "field": []}}, {"job_id": "100003009051236", "location_code": "hk", "company": "New Lanwa Holdings Group (HK) Limited", "job_title": "Senior Admin and Human Resources Executive  \u9ad8\u7d1a\u884c\u653f\u53ca\u4eba\u529b\u8cc7\u6e90\u4e3b\u4efb", "description": "We are looking for talent with solid talent acquisition experiences to help our company find and retain excellent talent. \u00a0This position is responsible for the full recruitment cycle, which includes developing job profiles, implementing recruitment strategies, sourcing candidates through digital platforms, coordinating the interview process, and assisting with new employee paperwork. Our ideal candidate is someone who can forecast our future talent needs and budget for the costs of talent recruitment. Applicants must have prior HR experience, and you should be familiar with applicant tracking systems.\n\nResponsibilities\n\nDetermine current staffing needs and produce forecasts\nCollaborate with hiring managers to develop job profiles\nSource potential candidates through hiring events and digital marketing campaigns, including on social media platforms\nCoordinate candidate interviews and assessments\nUpdate our applicant tracking system\nAssist with employee onboarding\nForecast future talent or staffing needs\nBudget for recruitment costs\nOrganize and/or attend career fairs, assessment centers or other events\nUse metrics to create reports and identify areas of improvement\n\nRequirements\n\nHeld a position at talent acquisition supervisory level for at least 3 yrs\nExperience in full-cycle recruiting, sourcing and employment branding\nUnderstanding of all selection methods and techniques\nProficient in the use of social media and job boards\nWillingness to understand the duties and competencies of different roles\nExcellent communicator in Cantonese, English and Mandarin in both written and spoken\nDegree holder in business administration, human resources or relevant field", "employment_types": ["Full Time"], "selling_points": [], "locations": ["Wan Chai"], "categories": ["Admin & HR", "Administration / Operation Manager", "HR Director / Manager"], "post_time": "2022-01-15T05:41:44Z", "salary": {"currency": "HKD", "max": 24999, "min": 20000, "period": "monthly", "term": null}, "salary_visible": true, "title_keywords": ["admin", "human resources executive"], "responsibilities": ["collaborate with", "digital marketing campaigns", "social media platforms", "budget", "develop", "coordinate", "recruitment", "reports", "forecast", "costs", "tracking"], "requirements": {"degrees": ["degree holder"], "majors": ["business administration"], "languages": ["cantonese", "english", "mandarin"], "language_level": ["excellent"], "hard_skills": [], "soft_skills": ["communicator"], "languages_combined": [{"language": "cantonese", "language_level": ["excellent"]}, {"language": "english", "language_level": ["excellent"]}, {"language": "mandarin", "language_level": ["excellent"]}]}, "experience_required": {"duration": [], "field": []}}, {"job_id": "100003009045736", "location_code": "hk", "company": "Television Broadcasts Limited (TVB)", "job_title": "Administration Officer", "description": "\u5de5\u4f5c\u5167\u5bb9\n\n\u8655\u7406\u5e74\u5ea6\u85aa\u916c\u8abf\u6574\u4ee5\u53ca\u82b1\u7d05\u3001\u54e1\u5de5\u91ab\u7642\u53ca\u4fdd\u96aa\u5b89\u6392\uff0c\u66f4\u65b0\u5e02\u5834\u85aa\u916c\u8cc7\u6599\n\u6df1\u8af3\u50f1\u50ad\u689d\u4f8b\u53ca\u76f8\u95dc\u6cd5\u898f\uff0c\u4e26\u5354\u52a9\u78ba\u8a8d\u54e1\u5de5\u5408\u7d04\u53ca\u689d\u6b3e\u7b26\u5408\u76f8\u95dc\u6cd5\u898f\n\u7dad\u8b77\u548c\u66f4\u65b0\u54e1\u5de5\u6578\u64da\uff0c\u5f59\u7de8\u4eba\u529b\u8cc7\u6e90\u76f8\u95dc\u5831\u544a\n\u8655\u7406\u5de5\u8cc7\u8a08\u7b97\uff0c\u5f37\u7a4d\u91d1\uff0c\u5831\u7a05\u7b49\u4e8b\u5b9c\n\u8655\u7406\u516c\u53f8\u4eba\u4e8b\u884c\u653f\uff0c\u4f8b\u5982\u5c31\u696d\u524d\u5f8c\u5982\u62db\u8058\u3001\u4e0a\u73ed\u7d00\u9304\u3001\u85aa\u916c\u798f\u5229\u548c\u54e1\u5de5\u95dc\u4fc2\n\u7ba1\u7406\u8fa6\u516c\u5ba4\u884c\u653f\u4e8b\u52d9\uff0c\u5305\u62ec\u6587\u4ef6\u53ca\u5feb\u905e\u5b89\u6392\u3001\u6587\u5177\u53ca\u8fa6\u516c\u5ba4\u8a2d\u5099\u7dad\u8b77\u7b49\n\u57f7\u884c\u4e3b\u7ba1\u5b89\u6392\u7684\u5176\u4ed6\u5de5\u4f5c\n\n\u8981\u6c42\n\n\u6301\u6709\u4eba\u529b\u8cc7\u6e90\u7ba1\u7406\u6216\u76f8\u95dc\u5927\u5b78\u5b78\u4f4d\n\u5728\u4eba\u529b\u8cc7\u6e90\u548c\u8fa6\u516c\u5ba4\u884c\u653f\u7ba1\u7406\u81f3\u5c113\u5e74\u4ee5\u4e0a\u7684\u5de5\u4f5c\u7d93\u9a57\n\u5fc5\u9700\u719f\u6089\u50f1\u50ad\u689d\u4f8b\u53ca\u76f8\u95dc\u6cd5\u898f\n\u512a\u826f\u4e2d\u82f1\u6587\u66f8\u9762\u548c\u53e3\u8a9e\u8868\u9054\u80fd\u529b\n\u5de5\u4f5c\u80fd\u529b\uff0c\u7d44\u7e54\u80fd\u529b\u53ca\u5354\u8abf\u80fd\u529b\u8981\u5f37\uff0c\u80fd\u8207\u5404\u65b9\u4e92\u52d5\n\u6709\u5354\u52a9\u5236\u5b9a\u4eba\u529b\u8cc7\u6e90\u653f\u7b56\u7d93\u9a57\u8005\u70ba\u4f73\n\n\u5176\u4ed6\u6d25\u8cbc\u6216\u798f\u5229\uff1a\u5e74\u7d42\u916c\u91d1\u3001\u914c\u60c5\u6027\u82b1\u7d05\u3001\u6709\u85aa\u5e74\u504712\u65e5\u3001\u54e1\u5de5\u8cfc\u7269\u512a\u60e0\n\n\u5de5\u4f5c\u6642\u9593\uff1a09:00 \u2013 18:00 \u6bcf\u661f\u671f\u5de5\u4f5c\u4e94\u5929\uff0c\u9031\u516d\u9593\u65b7\u6027\u8f2a\u73ed\u5de5\u4f5c\n\n\u5de5\u4f5c\u5730\u5340\uff1a\u7063\u4ed4\n\n\u6709\u610f\u8005\u8acb\u63d0\u4f9b\u4e2d\u82f1\u6587\u5c65\u6b77\uff0c\u8b1d\u8b1d\u3002\n\nSenior Admin and Human Resources Officer\u00a0\n\nJob Responsibility\n\nResponsible for payroll, MPF contribution, taxation, attendance administration and employee relations\nHandle invoice payment queries from staff and external vendors\nAssist in Recruitment process: screen resume, search resume through online recruitment channel such as Jobs DB, schedule interviews for employers and applicants\nEnsure the employee record is accurate and up-to-date and the handling of employee contract & data is in full compliance of HK Employment Ordinance and regulation, formulate, implement and review HR policies and procedures\nProvide administration support including reception, incoming and outgoing documents, courier services, stationeries, office facilities repairs, maintenance and renovation etc.\nAccountable for annual projects including annual salary review and bonus/ incentive exercise, group medical & insurance plans renewal, and market benchmark/surveys\nResponsible for HR and Administration related Ad-hoc duties and projects as required\nAd hoc projects assigned\u00a0\n\nRequirements:\n\nUniversity degree in Business Administration/HR or other related discipline;\nMinimum 3 years of solid experience in Human Resources and Admin management;\nIn-depth knowledge of HK Labour Law and regulations is a must and PRC Labour Law and regulations is an advantage;\nGood Command of English & Chinese;\nStrong logical thinking, excellent in presentation and reporting skill\nPrevious experience in formulating HR policy and improvement projects is preferred\n\nBenefits: Annual bonus, discretionary bonus, 12 days\u2019 annual leave, staff discount\n\nWorking Hours: 09:00-18:00, 5 working days a week\uff0cSaturday working sometimes.\n\nDistrict: Wanchai\n\nInterested candidates please provide your resume both in Chinese and English. Thank you.", "employment_types": ["Full Time", "Permanent"], "selling_points": [], "locations": ["Tseung Kwan O"], "categories": ["Admin & HR", "Administration / Operation Manager", "Clerical / Admin Staff", "HR Supporting Staff"], "post_time": "2022-01-13T18:55:14Z", "salary": {"currency": null, "max": null, "min": null, "period": "monthly", "term": null}, "salary_visible": false, "title_keywords": ["administration officer"], "responsibilities": ["data", "renovation", "payment", "plans", "administration", "compliance", "schedule", "attendance", "mpf", "invoice", "review", "procedures", "ad-hoc duties", "recruitment process", "payroll", "taxation", "maintenance", "policies", "hr", "recruitment", "ad hoc projects", "insurance"], "requirements": {"degrees": ["university degree"], "majors": ["business administration"], "languages": ["english", "chinese"], "language_level": ["good command"], "hard_skills": [], "soft_skills": ["presentation"], "languages_combined": [{"language": "english", "language_level": ["good command"]}, {"language": "chinese", "language_level": ["good command"]}]}, "experience_required": {"duration": ["minimum 3 years"], "field": ["hr", "management", "admin", "human resources"]}}, {"job_id": "100003009046800", "location_code": "hk", "company": "Rod and Staff Recruitment Group (Hong Kong) Limited", "job_title": "Executive Assistant / Office Manager", "description": "Responsibilities:\n\nProvide general HR and administrative support\nReport directly to HR Manager\nAssist in recruitment process, leave and benefit management\nPrepare document, contract and report\nAble to handle sensitive and confidential information\nAble to work under pressure and can be a good team player\n\n\u00a0Requirement:\n\nDiploma / Degree holder in relevant disciplines\nMinimum 2-3 years all-rounded HR experience\nProficiency in MS Office especially in Word, Excel and Chinese word processing\nGood command of both English & Chinese\nSelf-motivated, detail-oriented and hardworking\nCandidate with less experience will be considered as Assistant Administration Officer\nImmediate available would be an advantage\nLocation: Tseung Kwan O\n\nPlease apply, quoting the appropriate reference number, with details of your qualifications and experience, expected salary and a contact telephone number to The\u00a0Senior Manager, Personnel Department, Television Broadcasts Limited, TVB City, 77 Chun Choi Street, Tseung Kwan O Industrial Estate, Tseung Kwan O, Kowloon.\n\nApplications received are solely for selection purpose.\u00a0 Those not invited for an interview within 4 weeks may consider their applications unsuccessful and their applications will be filed for another 3 months for future selection.\u00a0 Afterwards, all applications would be destroyed.", "employment_types": ["Full Time"], "selling_points": ["Global opportunity", "Energetic environment", "Competitive Perks"], "locations": ["Central"], "categories": ["Admin & HR", "Administration / Operation Manager", "Personal / Executive Assistant", "Secretary"], "post_time": "2022-01-14T01:13:03Z", "salary": {"currency": null, "max": null, "min": null, "period": "monthly", "term": null}, "salary_visible": false, "title_keywords": ["executive assistant", "office manager"], "responsibilities": ["management", "administrative support", "work under pressure", "hr", "recruitment process", "report"], "requirements": {"degrees": ["diploma", "degree holder"], "majors": [], "languages": ["english", "chinese"], "language_level": ["proficiency", "good command"], "hard_skills": ["excel", "chinese word processing", "word", "ms office"], "soft_skills": ["self-motivated", "hardworking", "detail-oriented"], "languages_combined": [{"language": "english", "language_level": ["good command"]}, {"language": "chinese", "language_level": ["proficiency", "good command"]}]}, "experience_required": {"duration": ["minimum 2-3 years"], "field": ["hr", "administration"]}}, {"job_id": "100003009048949", "location_code": "hk", "company": "Randstad Hong Kong Limited", "job_title": "Admin Manager/ Office Manager (Aberdeen, NGO, 45k+)", "description": "Our client, a leading global club, is currently on the lookout for a zestful Office Manager and Executive Assistant to provide administrative support to the group in its headquarters in Hong Kong. We are looking for a confident, trustworthy, detail-oriented individual to work with talented people in a small and dynamic corporate environment. This is a great opportunity for anyone who has a real interest in football.\u00a0\n\nOffice Manager / Executive Assistant\n\n\n\nSchedule and organize meetings and conference calls for office agenda\nReception duties: welcoming clients/visitors and determining access to appropriate parties\u00a0\nResponsible for handling accounts: processing invoices, payroll, budget & forecasting etc.\u00a0\nRecord office expenditure and managing budget: Coordinate finances, assist with budget preparation.\u00a0\nOrganising the office layout and maintaining supplies of stationery, equipment and pantry supplies\u00a0\nMaintaining the condition of the office and arranging for necessary repairs;\u00a0\nClose communication with HQ office on operations, accounts and technology related issues\nProvide secretarial and executive support to the MD\nResponsible for travel arrangements, meetings and conferences for MD and staff\n\nREQUIREMENTS\u00a0\n\n\nUniversity degree\n5 to 8 years\u2019 experience as an office manager and executive assistant within corporate office\u00a0\nHigh\u00a0proficiency in English, Cantonese and Mandarin, both spoken and written\n\nAn ability to multitask and handle documentation and reports with the highest level of confidentiality\nSelf-starter and able to work in a dynamic and team-oriented environment\nGreat interest and passion in sports", "employment_types": ["Full Time", "Permanent"], "selling_points": ["Trilingual, proactive and high accuracy", "Degree holder & Flexible", "Minimum 5 years of experiences"], "locations": ["Not Specified"], "categories": ["Admin & HR", "Administration / Operation Manager"], "post_time": "2022-01-14T07:46:01Z", "salary": {"currency": "HKD", "max": 54999, "min": 35000, "period": "monthly", "term": null}, "salary_visible": true, "title_keywords": ["admin", "manager", "office manager"], "responsibilities": ["forecasting", "travel arrangements", "documentation", "invoices", "maintaining", "operations", "budget", "stationery", "executive support", "coordinate", "communication", "conferences", "reports", "schedule", "provide administrative support", "payroll"], "requirements": {"degrees": ["university degree"], "majors": [], "languages": ["cantonese", "english", "mandarin"], "language_level": ["proficiency"], "hard_skills": ["small", "documentation", "dynamic", "processing"], "soft_skills": ["confident", "responsible", "trustworthy", "passion in", "detail-oriented", "communication", "dynamic", "ability to multitask"], "languages_combined": [{"language": "cantonese", "language_level": ["proficiency"]}, {"language": "english", "language_level": ["proficiency"]}, {"language": "mandarin", "language_level": ["proficiency"]}]}, "experience_required": {"duration": ["5 to 8 years"], "field": []}}, {"job_id": "100003008374626", "location_code": "hk", "company": "Daum (Hong Kong) Limited", "job_title": "Operation Assistant", "description": "about the company.\n\nMy client is an NGO. They are looking for an Admin Manager/ Office Manager, who is independent and mature to support the board members and new business.\n\nLocation: Aberdeen\n\nabout the job.\n\nRecord office expenditure and manage the budget. organise the office layout and maintain supplies of stationery and equipment.\nHelp setting up the new business: POS, office insurance and renovation etc.\nArrange meetings for the board members\nMaintain supplies inventory\nOrganises and audits the company's systems, databases, and procedures\n\nskills & experiences required.\n\nDegree holder is a must\n5+ years of relevant experiences\nFlexible, multi-tasking and able to work under pressure\nProficient in PC Skills, MS Office and word processing\nGreat interpersonal and communication skills (English, Cantonese, and Mandarin)\n\nInterested parties please send a full resume with the portfolio. For a confidential discussion, please contact Kimka Lam.", "employment_types": ["Full Time", "Permanent", "Contract", "Internship"], "selling_points": ["Administrative, Stock, Logistic", "Keen to learn, flexible, good at organizing data", "Team player"], "locations": ["Wan Chai Area"], "categories": ["Admin & HR", "Administration / Operation Manager", "Transportation & Logistics", "Inventory / Warehousing", "Others", "Trading"], "post_time": "2022-01-14T07:33:38Z", "salary": {"currency": null, "max": null, "min": null, "period": "monthly", "term": null}, "salary_visible": false, "title_keywords": ["operation assistant"], "responsibilities": ["budget", "renovation", "stationery", "systems", "maintain supplies inventory", "procedures", "communication", "maintain", "databases", "audits", "insurance", "arrange meetings", "work under pressure"], "requirements": {"degrees": ["degree holder"], "majors": [], "languages": ["cantonese", "english", "mandarin"], "language_level": [], "hard_skills": ["pos", "word processing", "databases", "pc skills", "ms office"], "soft_skills": ["flexible", "communication skills", "independent", "mature", "multi-tasking", "interpersonal", "work under pressure"], "languages_combined": [{"language": "cantonese", "language_level": []}, {"language": "english", "language_level": []}, {"language": "mandarin", "language_level": []}]}, "experience_required": {"duration": ["5+ years"], "field": []}}, {"job_id": "100003009048333", "location_code": "hk", "company": "SEB Asia Limited", "job_title": "Administration Officer (Maternity Cover, 6-month contract)", "description": "JOB DESCRIPTION\n\nWhat you will do:\n\nAdministrative:\n- Managing and displaying products in the showroom\n- Data entering \u2013 orders, shipments, customer database, invoices\n- Preparing petty cash list\n- Filing and recording all the office utilities and fee bill\n- Responsible for all-rounded administration work in the office\nStock management:\n- Preparing bar code labels for new stocks\n- Stock taking every 4 months\n- Updating stock ad consignment records\nLogistic:\n- Managing and unpacking the new arrival goods in warehouse/ office\n- Arranging to shipment to our customers from different markets\nAd-hoc duties of assisting sales and marketing projects assigned\n\nREQUIREMENT\n- Undergraduate / fresh graduates are welcome\n- 1- 2 years working experiences\n- Proficient in using Microsoft Words, Excels (Vlookup, Iferror, etc)\n-\u00a0Good spoken and written in Cantonese/ English/ Mandarin\n- Keen to learn, detail-minded, and a good team player with good communication and interpersonal skills\n\nBENEFITS\n- Career progression opportunities\n- Free medical package\n- 13th month\n- 5 days working", "employment_types": ["Full Time", "Temporary", "Contract"], "selling_points": ["5-day work", "5 minutes walk from Olympic Station", "The Global leader in Small Domestic Appliances"], "locations": ["Yau Tsim Mong Area"], "categories": ["Admin & HR", "Administration / Operation Manager", "Clerical / Admin Staff", "Receptionist"], "post_time": "2022-01-14T06:39:11Z", "salary": {"currency": null, "max": null, "min": null, "period": "monthly", "term": null}, "salary_visible": false, "title_keywords": ["administration officer"], "responsibilities": ["stock management", "invoices", "data", "marketing projects", "database", "ad-hoc duties", "administration"], "requirements": {"degrees": [], "majors": [], "languages": ["cantonese", "english", "mandarin"], "language_level": ["good"], "hard_skills": ["vlookup", "words"], "soft_skills": ["detail-minded", "keen", "good team player", "communication and interpersonal skills"], "languages_combined": [{"language": "cantonese", "language_level": ["good"]}, {"language": "english", "language_level": ["good"]}, {"language": "mandarin", "language_level": ["good"]}]}, "experience_required": {"duration": ["1- 2 years"], "field": []}}, {"job_id": "100003009052500", "location_code": "hk", "company": "Conrad Hong Kong", "job_title": "Senior Manager, Carrier Sales", "description": "What\u2019s in it for you:\n\n\nTo assist in office maintenance and contract renewal (alarm system, telephone, IDD, copier, water leakage, air-conditioning, furniture, carpet cleaning, lighting etc.)\nTo keep inventory, order and arrange placement of office stationery and break room supply\nTo check all invoices relating to administration aspects\nTo assist in organizing staff event (annual dinner, farewell party)\nTo coordinate with staff for file storage in warehouse company and keep storage inventory list updated\nTo take charge of product distribution for staff purchase\nTo assist in group meeting (meeting room set up, visio connection, lunch ordering, etc.)\nTo assist in renovation project\nTo arrange workstation for new joining staff\nTo assist in company stationery printing\nTo back up receptionist\nTo keep the office neat and organized and monitor office safety\nTo assist in donation or charity event\nWhat we are looking for:\n\nAt least 3 years of relevant experience\nDiploma / Associate Degree graduate\nNative Cantonese, fluent English and Mandarin\nPatient, flexible, good interpersonal skills, positive attitude, willing to go extra miles\nAssertive character to deal with all levels\nProficient in MS Office Word, Excel, PowerPoint and Chinese Word Processing\n\nWe offer attractive remuneration package to the right candidate including 5-day work.\n\nInterested parties please apply with full resume with\u00a0expected salary\u00a0and current salary\u00a0to\u00a0Human Resources\u00a0Department.\u00a0For company details, please visit our\u00a0website.\n\nAll data collected is for recruitment purpose only. Candidates not invited for interview within 8 weeks from the date of this posting may consider their applications unsuccessful. Unsuccessful applications will be destroyed after 6 months.\u00a0", "employment_types": ["Full Time"], "selling_points": ["Implement sales strategy", "Prepare sales proposal and presentation", "Minimum 8 years relevant experience"], "locations": ["Not Specified"], "categories": ["Admin & HR", "Administration / Operation Manager", "Management", "General Management", "Information Technology (IT)", "IT Management"], "post_time": "2022-01-17T03:14:55Z", "salary": {"currency": null, "max": null, "min": null, "period": "monthly", "term": null}, "salary_visible": false, "title_keywords": ["senior manager", "sales"], "responsibilities": ["invoices", "maintenance", "file storage", "inventory", "renovation", "coordinate with", "stationery", "monitor", "purchase", "cleaning", "administration"], "requirements": {"degrees": ["associate degree", "diploma"], "majors": [], "languages": ["cantonese", "english", "chinese", "mandarin"], "language_level": ["native", "proficient", "fluent"], "hard_skills": ["excel", "chinese word processing", "maintenance", "word", "charity", "powerpoint", "go", "ms office"], "soft_skills": ["flexible", "organized", "assertive", "positive attitude", "interpersonal skills", "patient"], "languages_combined": [{"language": "cantonese", "language_level": ["native", "fluent"]}, {"language": "english", "language_level": ["native", "fluent"]}, {"language": "chinese", "language_level": ["proficient"]}, {"language": "mandarin", "language_level": ["native", "fluent"]}]}, "experience_required": {"duration": ["at least 3 years"], "field": ["relevant experience"]}}, {"job_id": "100003009044207", "location_code": "hk", "company": "Lorence & Company Limited", "job_title": "Senior Administration Officer", "description": "The Challenge We Pose To You\n\nSales of the full suite of products and services to new and existing carrier partners for achieving sales targets\nImplement sales strategy and customer acquisition plan on new and existing accounts\nPrepare sales proposal and presentation, aiming to close new projects by offering competitive solutions and flexible supports\nGenerate periodic sales funnel, project pipelines and sales reports\nCollaborate with internal departments aligning business objectives with customer needs\nHandle ad hoc projects as assigned\nWhat You Bring To Us\n\nUniversity graduate in Computing, Electronics Engineering or related discipline\nMinimum 8 years relevant experience in the telecommunications industry, preferably in the international market\nRelevant experience in managing global accounts or selling to carriers/Telcos\nStrong business networking in the Telecommunication industry is an asset\nStrong business acumen, analytical and strategic mind\nGood selling, communications, and interpersonal skills\nGood command of spoken and written English, Cantonese and Putonghua\nOur Offer\n\n5-day work, 14 days annual leave, a competitive remuneration package, comprehensive medical and dental plan, local and regional training and rewarding career opportunities.\n\nPlease send your complete resume (in MS word format), inclusive of your available date, current and expected salary by clicking Apply Now or by mail to:\u00a0Human Resources and Administration Department, CITIC Telecom International CPC Limited, 20/F, Lincoln House, Taikoo Place, 979 King's Road, Quarry Bay, Hong Kong.\n\nWebsite: http://www.citictel-cpc.com/\n\nAll information received will be kept strictly confidential and for employment-related purpose only.", "employment_types": ["Full Time", "Permanent"], "selling_points": ["5 - 10 years of secretarial & administrative exp.", "Higher Diploma or above", "5 Day work week"], "locations": ["Kwun Tong"], "categories": ["Admin & HR", "Administration / Operation Manager", "Secretary"], "post_time": "2022-01-13T03:24:36Z", "salary": {"currency": null, "max": null, "min": null, "period": "monthly", "term": null}, "salary_visible": false, "title_keywords": ["senior administration officer"], "responsibilities": ["collaborate with", "sales reports", "prepare sales", "website", "ad hoc projects", "plan", "administration"], "requirements": {"degrees": ["university graduate"], "majors": ["engineering"], "languages": ["cantonese", "putonghua", "english"], "language_level": ["good command"], "hard_skills": ["pipelines", "ms word", "acumen"], "soft_skills": ["flexible", "comprehensive", "interpersonal skills", "business acumen", "presentation"], "languages_combined": [{"language": "cantonese", "language_level": ["good command"]}, {"language": "putonghua", "language_level": ["good command"]}, {"language": "english", "language_level": ["good command"]}]}, "experience_required": {"duration": ["minimum 8 years"], "field": ["telecommunications", "relevant experience"]}}, {"job_id": "100003009043531", "location_code": "hk", "company": "Asia Satellite Telecommunications Co Ltd", "job_title": "Administration Officer", "description": "Responsibilities:\n\nHandle the daily operation including monitoring of office and Warehouse maintenance;\nAttend meetings, taking minutes and handling related documents.\nProvide full spectrum of corporate and office administration duties, such as data input, filing and clerical works, office equipment maintenance and repair coordination.\nHandle and monitor the attendance system for all staff\nPerform ad-hoc projects as required.\n\n\u00a0Requirements:\n\nHigher Diploma or above in business administration or related disciplines;\nGood command of spoken and written English and Chinese\n5 - 10 years of secretarial and administrative experience\nBe pro-active, presentable, responsible, discreet and trustworthy, with people skills strong enough to cope with a dynamic environment.\nImmediately Available is preferred", "employment_types": ["Full Time", "Permanent"], "selling_points": ["Office management", "Administrative & Secretarial support", "Min. 5 years' relevant experience"], "locations": ["Tai Po Area"], "categories": ["Admin & HR", "Administration / Operation Manager", "Personal / Executive Assistant", "Secretary"], "post_time": "2022-01-12T16:40:57Z", "salary": {"currency": null, "max": null, "min": null, "period": "monthly", "term": null}, "salary_visible": false, "title_keywords": ["administration officer"], "responsibilities": ["attendance", "maintenance", "related documents", "monitoring", "daily operation", "data input", "monitor", "repair", "office equipment maintenance", "coordination", "attend meetings", "office administration duties", "ad-hoc projects"], "requirements": {"degrees": ["higher diploma or above"], "majors": ["related disciplines", "business administration"], "languages": ["english", "chinese"], "language_level": ["good command"], "hard_skills": ["dynamic"], "soft_skills": ["dynamic environment", "trustworthy", "responsible", "presentable", "pro-active"], "languages_combined": [{"language": "english", "language_level": ["good command"]}, {"language": "chinese", "language_level": ["good command"]}]}, "experience_required": {"duration": ["5 - 10 years"], "field": ["secretarial", "administrative"]}}, {"job_id": "100003009047676", "location_code": "hk", "company": "Best Come Limited (Eaton Club)", "job_title": "Senior Operations Manager", "description": "\u8077\u4f4d\u63cf\u8ff0\n\n\u5de5\u4f5c\u8077\u8cac\uff1a\n\n- \u5236\u5b9a\u5408\u4f5c\u65b9\u6848\uff0c\u6587\u66f8\u8655\u7406\n- \u8655\u7406\u9805\u76ee\u9032\u5c55\u4ee5\u53ca\u76f8\u95dc\u4e8b\u9805\n- \u53c3\u8207\u5e02\u57f8\u63a8\u5ee3\u6d3b\u52d5\n- \u64f4\u95ca\u5ba2\u6236\u7db2\u7d61\n- \u8207\u5404\u500b\u90e8\u9580\u6e9d\u901a\u548c\u5408\u4f5c\n\n\u5de5\u4f5c\u8981\u6c42\uff1a\n- \u5927\u5c08\u4ee5\u4e0a\u5b78\u6b77\n- \u826f\u597d\u6e9d\u901a\u6280\u5de7\n- \u52e4\u596e\uff0c\u7d30\u5fc3\n- \u6709\u8cac\u4efb\u5fc3\u80fd\u7368\u7acb\u5de5\u4f5c\n- \u9858\u610f\u63a5\u53d7\u6311\u6230\n- \u4e00\u5e74\u5de5\u4f5c\u7d93\u9a57\u6216\u4ee5\u4e0a\n\n\u85aa\u916c\u798f\u5229\uff1a\n- $12,000-$14,000/\u6708\n- \u7e3e\u6548\u734e\u91d1\n- \u91ab\u7642\u4fdd\u96aa\n- \u516c\u53f8\u57f9\u8a13", "employment_types": ["Full Time", "Permanent"], "selling_points": ["Co-working space / business services centre", "Senior Office Administration Manager", "Senior Facility Manager"], "locations": ["Central"], "categories": ["Admin & HR", "Administration / Operation Manager", "Sales, CS & Business Devpt", "Customer Service - Manager", "Hospitality / F & B", "Hospitality / Hotel Services"], "post_time": "2022-01-14T03:42:48Z", "salary": {"currency": null, "max": null, "min": null, "period": "monthly", "term": null}, "salary_visible": false, "title_keywords": ["senior operations", "manager"], "responsibilities": [], "requirements": {"degrees": [], "majors": [], "languages": [], "language_level": [], "hard_skills": [], "soft_skills": [], "languages_combined": []}, "experience_required": {"duration": [], "field": []}}, {"job_id": "100003009053273", "location_code": "hk", "company": "Sa Sa Cosmetic Company Limited", "job_title": "HRIS - Specialist", "description": "Responsibilities:\n\nManage all our centres and set up a structural operational workflow\nFormulate strategic and operational objectives\nTrain and supervise the teams to ensure service level of the centers are in accordance with company\u2019s standards and policies\nEnsure the centers at a high standard at all times, which includes facilities and environment management\nBuild up good relationship with members and handle enquiries / complaints\nLiaise with internal and external parties to all events run effectively and efficiently\nHandle ad hoc assignments or project as required\n\nRequirements:\n\nDegree holder in Hospitality Management, Facilities Management or other related disciplines\n6 \u2013 8 years\u2019 experience in hospitality industry or flexible space industry is preferred, in which 3 years\u2019 experience in supervisory role\nExperience in managing club house or events is an advantage\nAbility to lead a team to provide the highest level of service\nStrong analytical and problem solving skills and able to multitask\nCustomer-oriented with good communications, interpersonal and presentation skills\nResponsible, mature, independent and able to work under pressure\nGood command of both spoken and written English and Chinese (including Putonghua)\nCandidates with less experience and qualifications will be considered as Operations Manager\n\nSalary and benefits will be commensurate with qualifications and experience.\u00a0 Interested parties, please send a full resume with present and expected salary, and date available to The Human Resources Department, 32/F., Great Eagle Centre, 23 Harbour Road, Wanchai, Hong Kong or e-mail to us.\u00a0\u00a0(Please quote the reference no. on the envelope and the covering letter.)\n\nTo know more about us, please visit our website at https://www.eatonclub.com.hk/\n\nWe are an equal opportunity employer and welcome applications from all qualified candidates.\n\nPersonal data collected will be treated in strict confidence and used only for recruitment-related purpose. Applicants who have not heard from us within four weeks may consider their applications unsuccessful. All personal data will be destroyed after 12 months.", "employment_types": ["Full Time"], "selling_points": ["HRIS experience is a must", "Manage data integrity in the HR system.", "Perform C&B support on Payroll"], "locations": ["Siu Sai Wan"], "categories": ["Admin & HR", "Administration / Operation Manager", "Compensation & Benefits", "Information Technology (IT)", "Support"], "post_time": "2022-01-17T06:38:34Z", "salary": {"currency": null, "max": null, "min": null, "period": null, "term": null}, "salary_visible": false, "title_keywords": ["specialist"], "responsibilities": ["management", "policies", "internal and external parties", "teams", "good relationship", "handle enquiries", "ad hoc assignments", "liaise with"], "requirements": {"degrees": ["degree holder"], "majors": ["hospitality management", "related disciplines"], "languages": ["putonghua", "english", "chinese"], "language_level": ["good command"], "hard_skills": ["facilities management", "problem solving skills"], "soft_skills": ["flexible", "independent", "responsible", "mature", "multitask", "analytical and problem solving skills", "customer-oriented", "presentation skills", "interpersonal", "work under pressure"], "languages_combined": [{"language": "putonghua", "language_level": ["good command"]}, {"language": "english", "language_level": ["good command"]}, {"language": "chinese", "language_level": ["good command"]}]}, "experience_required": {"duration": ["3 years", "8 years"], "field": ["hospitality industry", "supervisory"]}}, {"job_id": "100003009045526", "location_code": "hk", "company": "Hang Seng Bank Ltd", "job_title": "Assistant Business Support Manager", "description": "Responsibilities:\n\nResponsible to prepare advanced and predictive analysis, people metrics and HR reports on a periodic basis\nDrive HRIS initiatives and projects including liaison with vendors, team members, process management and operation review.\nMonitor HR information needs and design new or modify existing systems to meet changing requirements\nKeep abreast of local legislations\u2019 updates and ensure HR policies and practices are compliant with local legislation\nAssist a team to manage monthly payroll and benefits operation, while ensuring all payroll and tax calculations are well handled and executed effectively and efficiency\n\nRequirements:\n\nBachelor degree in HR/Business, or related disciplines, Computer Science is a definite advantage\n5 years or above solid HRIS experience preferably in sizable Company, retail, or FMCG\nStrong interpersonal skills with the ability to drive changes and communicate with different section leaders\nSelf-motivated & strong analytical skills, multi-tasking, meticulous, organized and able to meet tight deadlines\nPositive, detail-minded, well-organized and flexible\nGood command in both written and spoken English and Chinese proficiency\nimmediately available is preferred\n\n\u00a0We offer\n\n5 - day work week\nMedical Benefits\nPerformance Bonus\nStaff Purchase Discounts\nStaff Recreation Activity\nShuttle Bus Service\u00a0\n\nInterested parties please send a\u00a0full resume\u00a0with current and expected salary\u00a0by clicking APPLY NOW:\n\nHuman Resources Department\n\nSa Sa Cosmetic Co Ltd\n14/F, Block B, MP Industrial Centre\u00a0\n18 Ka Yip Street\u00a0\nChai Wan\u00a0\nHong Kong\n\nEmail:\u00a0recruitment_mgt @sasa.com\nFax: 2898 0864\n\nPlease visit our corporate website\u00a0at\u00a0http://corp.sasa.com/en/home\u00a0to know more about us.\u00a0\n\n(Sa Sa is an Equal Opportunity Employer and all qualified applicants will receive consideration for employment. Personal data collected will be kept confidential and used for recruitment purpose only)", "employment_types": ["Full Time", "Permanent"], "selling_points": [], "locations": ["Not Specified"], "categories": ["Admin & HR", "Administration / Operation Manager", "Others", "Banking / Finance", "Retail Banking"], "post_time": "2022-01-13T08:00:58Z", "salary": {"currency": null, "max": null, "min": null, "period": "monthly", "term": null}, "salary_visible": false, "title_keywords": ["manager", "assistant"], "responsibilities": ["tax", "management", "policies", "analysis", "review", "monitor", "hr reports", "hr", "design", "systems", "payroll", "legislations"], "requirements": {"degrees": ["degree", "bachelor"], "majors": ["related disciplines", "business", "computer science"], "languages": ["english", "chinese"], "language_level": ["proficiency", "good command"], "hard_skills": ["analytical skills"], "soft_skills": ["detail-minded", "meticulous", "self-motivated", "organized", "meet tight deadlines", "flexible", "well-organized", "analytical skills", "multi-tasking", "interpersonal skills", "positive"], "languages_combined": [{"language": "english", "language_level": ["proficiency", "good command"]}, {"language": "chinese", "language_level": ["proficiency", "good command"]}]}, "experience_required": {"duration": ["5 years"], "field": ["retail", "fmcg"]}}, {"job_id": "100003009051819", "location_code": "hk", "company": "RGF HR Agent Hong Kong Limited", "job_title": "Japanese Speaking Accounting, HR & Admin Manager - Japanese Company (Up to 35K/San Po Kong)", "description": "Wealth and Personal Banking \u2013 Chief Administration Office\n\nHang Seng\u2019s Wealth and Personal Banking (WPB) Chief Administration Office is a team of experienced banking professionals who strives for delivering time-to-market and efficient support and monitoring to support business growth.\n\nChief Administration Office is dedicated to implement, monitor and track business performance, prepare management information and reporting of WPB businesses for top management and coordinate project implementation in accordance to the bank\u2019s strategies.\n\nWe are currently seeking a high caliber professional to join our department as\u00a0Assistant Business Support Manager.\n\u00a0\n\nPrincipal responsibilities\n\nCarry out Hong Kong Monetary Authority (HKMA), Securities and Futures Commission (SFC), and HK Insurance Authorities (HKIA) license administration activities for business units, activities include document checking, competence assessment, license registration, deregistration, change of particulars, etc.\nAct as a gatekeeper or primary point of contact roles for license administration works\nBe a subject matter expert in license administration field\nAssisting with the execution of business initiatives and activities in support of business aims\n\nRequirements\nUniversity graduates in related discipline\nMinimum of 1-year work experience preferably in the banking industry, with good knowledge of business management and operations management\nStrong self-motivation, excellent communication, negotiation and interpersonal skills\nGreat sense of ownership and servicing mindset to ensure efficient and effective customer service processes\nStrong problem solving and negotiation skills, plus ability to work under pressure\nProficiency in both English and Chinese, fluency in Putonghua an advantage\n\n\u00a0\nIf you would like to explore other opportunities at Hang Seng Hong Kong, please visit\u00a0www.hangseng.com/careers/\u00a0for details.\n\nThe health and safety of our employees and candidates is very important to us. Due to the current situation related to the Novel Coronavirus (2019-nCoV), we\u2019re leveraging our digital capabilities to ensure we can continue to recruit top talent at the HSBC Group. \u00a0As your application progresses, you may be asked to use one of our digital tools to help you through your recruitment journey. \u00a0If so, one of our \u00a0Resourcing colleagues will explain how our video-interviewing technology will be used throughout the recruitment process and will be on hand to answer any questions you might have.\n\nAll information provided by applicants will be used only for recruitment purposes and will be used strictly in accordance with the Bank's personal data policies, a copy of which may be obtained by the applicant upon request. Unless otherwise instructed in writing by the applicant concerned, applicants may be considered for other suitable positions within the Bank and its related companies. The personal data of unsuccessful job applicants may be retained for a maximum of two years from the date when the job application is rejected and such data may be retained for a longer period if there is a subsisting reason that obliges the Bank to do so, after which the personal data will be destroyed.", "employment_types": ["Full Time", "Permanent"], "selling_points": ["Japanese Automobile Company/JLPT N2 or above", "10 yrs exp in Accounting/ACCA/HKIAAT Member", "Up to 35K/San Po Kong/ Stable job!"], "locations": ["Wong Tai Sin Area"], "categories": ["Accounting", "Finance / Accounting Manager", "Admin & HR", "Administration / Operation Manager", "HR Director / Manager"], "post_time": "2022-01-17T01:16:48Z", "salary": {"currency": null, "max": null, "min": null, "period": "monthly", "term": null}, "salary_visible": false, "title_keywords": ["admin", "hr", "accounting", "manager"], "responsibilities": ["business initiatives", "subject matter expert", "checking", "contact", "insurance", "administration"], "requirements": {"degrees": [], "majors": [], "languages": ["putonghua", "english", "chinese"], "language_level": ["fluency", "advantage", "proficiency"], "hard_skills": ["business management", "plus", "problem solving", "reason"], "soft_skills": ["efficient", "negotiation", "communication", "problem solving", "negotiation skills", "self-motivation", "interpersonal skills", "customer service", "novel", "work under pressure"], "languages_combined": [{"language": "putonghua", "language_level": ["fluency"]}, {"language": "english", "language_level": ["proficiency", "fluency", "advantage"]}, {"language": "chinese", "language_level": ["proficiency", "fluency", "advantage"]}]}, "experience_required": {"duration": ["minimum of 1-year"], "field": ["banking industry", "management", "business", "operations management"]}}, {"job_id": "100003009051139", "location_code": "hk", "company": "Think.Math Group Limited", "job_title": "Centre Manager", "description": "Our client, a Japanese automobile company is looking for an Accounting, HR & Admin Manager to join their team as follows:\n\nJob Duties:\n\u2022 Handle the full set of accounting\n\u2022 Prepare month-end consolidation\n\u2022 Manage statutory audit, J-SOX, and tax filing\n\u2022 Prepare reports according to the templates provided by the HQ in Japan\n\u2022 Oversee the HR and Admin department\n\u2022 Liaise with the HQ in Japan\n\u2022 Other ad-hoc duties as assigned\n\nRequirement:\n\u2022 Bachelor's degree or higher\n\u2022 At least 10 years of relevant experience\n\u2022 Fluent in Japanese(JLT N2 or higher), English, and Chinese\n\u2022 ACCA/ HKIAAT student member or equivalent\n\u2022 Work experience in a Japanese company is a must\n\nPackage:\n- Discretionary bonus\n- Medical insurance\n\nInterested parties please send us your resume in MS Word/PDF format in English. All information received will be kept in strict confidential and only for recruitment purpose.\n\n", "employment_types": ["Full Time"], "selling_points": ["5 days working", "Great chance of promoting to be a partner", "Provide all round training"], "locations": ["Kowloon City"], "categories": ["Admin & HR", "Administration / Operation Manager"], "post_time": "2022-01-15T03:24:09Z", "salary": {"currency": null, "max": null, "min": null, "period": "monthly", "term": null}, "salary_visible": false, "title_keywords": ["centre manager"], "responsibilities": ["hr", "tax filing", "month-end", "audit", "full set of accounting", "liaise with", "ad-hoc duties", "prepare reports"], "requirements": {"degrees": ["degree", "bachelor"], "majors": [], "languages": ["japanese", "english", "chinese"], "language_level": ["fluent"], "hard_skills": ["acca"], "soft_skills": [], "languages_combined": [{"language": "japanese", "language_level": ["fluent"]}, {"language": "english", "language_level": ["fluent"]}, {"language": "chinese", "language_level": ["fluent"]}]}, "experience_required": {"duration": ["at least 10 years"], "field": ["relevant experience"]}}, {"job_id": "100003009051834", "location_code": "hk", "company": "RGF HR Agent Hong Kong Limited", "job_title": "Japanese Speaking Accounting and Administration Officer  (Up to 20K/ Good package/ Wanchai)", "description": "Responsibilities\n\nProvide professional consultation, such as introducing course details and proposing suitable course packages, to prospective customers\nMaintain good customer relationship\nManage the centre\u2019s class schedule\nHandling walk-in inquiries, calls, and customer follow-ups\nMaintain the centre\u2019s appearance\nProvide assistance to teachers when needed\nSupervise the course details, administrative procedures, etc.\n\n\u00a0Requirements\n\nMust have passion towards young children\nWell-mannered, and possess effective communication and interpersonal skills\n1-2 years working experience preferred\nCheerful, caring, patient, responsible and initiative.\nAble to multi-task & work under pressure\nComputer literate, especially in Microsoft Office (Word & Excel)\nFluent in Cantonese and English, Mandarin is an advantage\n\nRemuneration packages\n\n5 days working\u00a0\nProvide all round training\nGreat chance of promoting to be a partner\n\nWorking hours\n\n5 days working per week (including Saturday)\n10:00am \u2013 7:30pm\u00a0(4 days between Monday-Friday) and\u00a09:00am \u2013 6:30pm (Saturday)", "employment_types": ["Full Time", "Permanent"], "selling_points": ["Japanese stationery company", "3+yrs of Acct exp is a must/ JLPT N2", "Up to 20K/ Good package/ Wanchai"], "locations": ["Wan Chai"], "categories": ["Accounting", "Accounting Clerk / Supervisor", "Admin & HR", "Administration / Operation Manager", "Sales, CS & Business Devpt", "Sales Administration"], "post_time": "2022-01-17T01:19:18Z", "salary": {"currency": null, "max": null, "min": null, "period": "monthly", "term": null}, "salary_visible": false, "title_keywords": ["administration officer", "accounting"], "responsibilities": ["maintain", "procedures", "schedule", "provide assistance"], "requirements": {"degrees": [], "majors": [], "languages": ["cantonese", "english", "mandarin"], "language_level": ["advantage", "fluent"], "hard_skills": ["excel", "word", "microsoft office"], "soft_skills": ["cheerful", "multi-task", "responsible", "communication and interpersonal skills", "patient", "initiative", "work under pressure"], "languages_combined": [{"language": "cantonese", "language_level": ["fluent"]}, {"language": "english", "language_level": ["fluent"]}, {"language": "mandarin", "language_level": ["advantage"]}]}, "experience_required": {"duration": ["1-2 years"], "field": []}}, {"job_id": "100003009048163", "location_code": "hk", "company": "CRE Properties (Hong Kong) Limited", "job_title": "\u79df\u52d9\u884c\u653f\u4e3b\u4efb/\u9ad8\u7d1a\u4e3b\u4efbLeasing Admin Officer/ Senior Leasing Admin Officer", "description": "Our client, a Japanese stationery company is looking for a Japanese Speaking Accounting and Administration Officer to join their team:\n\nJob Duties:\n\u30fbHandle basic accounting and other administrative works\n\u30fbHandle Account receivable and Accounts payable\n\u30fbDealing payment with customer and suppliers\n\u30fbSupport sales and marketing team when necessary\n\u30fbTranslation duty\n\u30fbAd-hoc duty assigned by Manager\n\nRequirement:\u00a0\n\u30fbAt least 3 years of relevant experience\n\u30fbBusiness level of Mandarin/English/Japanese (JLPT N2 or above)\n\u30fbGreat team player\n\u30fbImmediately available is advantage\n\nPackage:\n- Double pay\n-\u00a0Discretionary Bonus\n- Medical\n- Sick leave\n-\u00a0Transportation allowance\n- OT allowance\u00a0\n-\u00a0Birthday leave\n- Marriage leave\n- Work from home\n\nInterested parties please send us your resume in MS Word/PDF format in English.\nAll information received will be kept in strict confidential and only for recruitment purpose.\n\n", "employment_types": ["Full Time"], "selling_points": [], "locations": ["Wan Chai"], "categories": ["Admin & HR", "Administration / Operation Manager"], "post_time": "2022-01-14T05:43:45Z", "salary": {"currency": null, "max": null, "min": null, "period": "monthly", "term": null}, "salary_visible": false, "title_keywords": ["officer", "admin"], "responsibilities": ["payment", "accounts payable"], "requirements": {"degrees": [], "majors": [], "languages": ["japanese", "english", "mandarin"], "language_level": [], "hard_skills": [], "soft_skills": ["team player"], "languages_combined": [{"language": "japanese", "language_level": []}, {"language": "english", "language_level": []}, {"language": "mandarin", "language_level": []}]}, "experience_required": {"duration": ["least 3 years"], "field": ["relevant experience"]}}, {"job_id": "100003009046967", "location_code": "hk", "company": "Dah Chong Hong, Limited", "job_title": "Assistant Administration Officer", "description": "Responsibilities:\n\nResponsible for handling daily leasing administration works for the portfolios\nPerform administration works on leasing matters such as tenancy\u00a0agreements, license agreements and other related duties for Retail portfolios\nHandling tenant\u2019s enquiry, rental billing and collection\nConduct company search, analyze rental information and leasing reports preparation\nCoordinate closely with the leasing team to provide smooth and professional services to tenants\nPerform ad-hoc duties assigned by the department\n\nRequirements:\n\nDegree holder in Business, Accounting or related disciplines\u00a0\u00a0\nMinimum 2 years of relevant experiences in leasing administration of property industry\nFamiliar with leasing procedures and relevant legal documentation\nProactive attitude, well-organized and good team player\nProficient computer skills in MS Office and Chinese Word Processing, familiar with leasing management software or system is an advantage\nGood command in both written and spoken English, Cantonese and Mandarin", "employment_types": ["Full Time"], "selling_points": [], "locations": ["Kowloon Bay"], "categories": ["Admin & HR", "Administration / Operation Manager", "Clerical / Admin Staff", "Others"], "post_time": "2022-01-14T02:01:35Z", "salary": {"currency": null, "max": null, "min": null, "period": "monthly", "term": null}, "salary_visible": false, "title_keywords": ["assistant administration officer"], "responsibilities": ["administration", "coordinate", "reports", "ad-hoc duties", "company search"], "requirements": {"degrees": ["degree holder"], "majors": ["related disciplines", "business", "accounting"], "languages": ["cantonese", "english", "chinese", "mandarin"], "language_level": ["advantage", "good command", "proficient"], "hard_skills": ["documentation", "chinese word processing", "computer skills", "ms office"], "soft_skills": ["good team player", "proactive", "well-organized"], "languages_combined": [{"language": "cantonese", "language_level": ["good command"]}, {"language": "english", "language_level": ["good command"]}, {"language": "chinese", "language_level": ["advantage", "proficient"]}, {"language": "mandarin", "language_level": ["good command"]}]}, "experience_required": {"duration": ["minimum 2 years"], "field": ["administration"]}}, {"job_id": "100003009046990", "location_code": "hk", "company": "Andrew Lee King Fun & Associates Architects Ltd", "job_title": "Secretary(also for fresh graduate to apply)", "description": "Responsibilities\n\nResponsible for full spectrum of general office administration supports in a professional manner, including maintenance, procurement of office suppliers and other administrative or support functions required;\nMaintain staff record and HR filing system;\nTake up ad-hoc assignments as required.\n\nRequirement\n\nDiploma or above;\n1 - 2 years relevant experience;\nGood interpersonal and communication skills;\nGood command of written and spoken in both English and Cantonese;\nProficient in MS Office applications, English and Chinese Word Processing;\nImmediate availability is an absolute advantage;\nCandidate with more experience will be considered as Administration Officer.\n\nPlease send your application with resume and expected salary to The HR Manager, Dah Chong Hong Ltd, 8/F, DCH Building, 20 Kai Cheung Road, Kowloon Bay or submit your application online by clicking \"Apply Now\" or send your resume to the email address stated in our company description.\n\nInformation provided will be for the purpose of selection within the company and only shortlisted candidates will be contacted. All applications will be retained for a maximum period of 6 months.", "employment_types": ["Full Time"], "selling_points": ["Mature personality", "Manage document control processes", "Good command in English and Chinese"], "locations": ["Central"], "categories": ["Admin & HR", "Administration / Operation Manager", "Secretary", "Others"], "post_time": "2022-01-14T01:57:20Z", "salary": {"currency": null, "max": null, "min": null, "period": "monthly", "term": null}, "salary_visible": false, "title_keywords": [], "responsibilities": ["maintenance", "office administration", "hr", "ad-hoc assignments", "professional manner", "maintain"], "requirements": {"degrees": ["diploma or above"], "majors": [], "languages": ["cantonese", "english", "chinese"], "language_level": ["good command", "proficient"], "hard_skills": ["chinese word processing", "ms office"], "soft_skills": ["communication skills", "interpersonal"], "languages_combined": [{"language": "cantonese", "language_level": ["good command"]}, {"language": "english", "language_level": ["good command", "proficient"]}, {"language": "chinese", "language_level": ["proficient"]}]}, "experience_required": {"duration": ["1 - 2 years"], "field": ["relevant experience", "administration"]}}, {"job_id": "100003009047993", "location_code": "hk", "company": "The University of Hong Kong", "job_title": "Assistant Registrar/Administrative Assistant I (several posts) (Ref.: 509056)", "description": "Responsibilities:\n\nHandle architectural tender and prepare related documents\nResponsible for all correspondences with contractors, sub-contractors and clients\nManage document control processes for assigned projects\nProvide full secretarial and administration support to project team\nPrepare monthly reports with tight deadlines\nHandle project administration works\n\nRequirements:\n\n1-2 years working experience preferred and fresh graduates are welcome to apply.\nMust be attention to details, able to cope with multiple projects and tight deadlines\nMature personality, proactive, willing to work with a team and deliver results under minimum supervision\nGood in English and Chinese\nGood PC skills with proficiency in Microsoft Word, Excel, PowerPoint and Chinese Word processing\n\nInterested parties please send resume with expected salary to Head of Human Resources at recruit @ alkf.com\n\nAll information collected will be used for recruitment purpose only.\n\nANDREW LEE KING FUN & ASSOCIATE ARCHITECTS LIMITED\n\n19/F, Universal Trade Centre, 3 Arbuthnot Road, Central, Hong Kong\n\nTel: (852) 2525-0008 Fax: (852) 2868-5371 E-mail : recruit @ alkf.com\n\nWebsite: www.alkf.com", "employment_types": ["Full Time"], "selling_points": ["possess a Master\u2019s degree", "8 years\u2019 team leadership experience", "leading junior executive and clerical staff"], "locations": ["Not Specified"], "categories": ["Admin & HR", "Administration / Operation Manager", "Others", "Management", "General Management"], "post_time": "2022-01-14T04:26:15Z", "salary": {"currency": null, "max": null, "min": null, "period": "monthly", "term": null}, "salary_visible": false, "title_keywords": ["administrative assistant", "assistant"], "responsibilities": ["control", "handle project administration", "monthly reports", "related documents", "tender", "administration"], "requirements": {"degrees": [], "majors": [], "languages": ["english", "chinese"], "language_level": ["proficiency", "good"], "hard_skills": ["excel", "microsoft word", "chinese word processing", "powerpoint", "pc skills"], "soft_skills": ["mature", "proactive", "attention to details"], "languages_combined": [{"language": "english", "language_level": ["good"]}, {"language": "chinese", "language_level": ["good", "proficiency"]}]}, "experience_required": {"duration": ["1-2 years"], "field": []}}, {"job_id": "100003009051138", "location_code": "hk", "company": "Think.Math Group Limited", "job_title": "Centre Manager Trainee", "description": "Work type:\u00a0Full-time\nDepartment:\u00a0Li Ka Shing Faculty of Medicine (20000)\nCategories:\u00a0Professional & Management\n\nApplications are invited for appointment as\u00a0Assistant Registrar/Administrative Assistant I (several posts) in the LKS Faculty of Medicine\u00a0\u00a0(Ref.: 509056), to commence as soon as possible, on a two- to three-year fixed-term basis, with the possibility of renewal subject to satisfactory performance.\n\nApplicants should possess a Master\u2019s degree with at least 8 years\u2019 team leadership experience in the higher education sector or a public/quasi-public organization. They should be competent communicators with an excellent command of English and Chinese; be self-motivated with strong strategic awareness and able to work proficiently with significant independence; and possess a high level of decision-making, organizational, time-management and problem-solving skills. Demonstrated ability to plan and implement projects of high strategic value is also required. Those with lower qualifications and/or less experience may be considered as Administrative Assistant I.\n\nThe appointees will play a versatile role in leading junior executive and clerical staff to support the administration in one or more of the following areas including HR, financial budgeting, research administration, committee support, education programme management, student wellness and engagement, PR, IT, facility management, special projects, and clinical affairs. The appointments will be made under the Faculty, and the appointees may be posted to school/department/faculty office in a rotational manner. Work outside office hours and on weekends may be required occasionally. Shortlisted candidates will be invited to attend an interview and/or written test. Applicants who have responded to the previous advertisement (Ref.: 507952) need not re-apply.\n\nA highly competitive salary commensurate with qualifications and experience will be offered, in addition to annual leave and medical benefits. The appointments will attract a contract-end gratuity and University contribution to a retirement benefits scheme, totalling up to 15% of basic salary. For Assistant Registrar, housing benefits will also be provided as applicable.\n\nThe University only accepts online application for the above posts. Applicants should apply online and upload an up-to-date C.V[via APPLY NOW]. Review of applications will start as soon as possible and continue until\u00a0March 31, 2022, or until the posts are filled, whichever is earlier.\n\nAdvertised:Dec 1, 2021 (HK Time)\nApplications close:Mar 31, 2022 (HK Time)", "employment_types": ["Full Time", "Permanent"], "selling_points": ["5 days working", "Provide all round training, welcome fresh grad", "Great chance of promoting to be a partner"], "locations": ["Kowloon City"], "categories": ["Admin & HR", "Administration / Operation Manager", "Education", "Others"], "post_time": "2022-01-15T03:23:24Z", "salary": {"currency": null, "max": null, "min": null, "period": "monthly", "term": null}, "salary_visible": false, "title_keywords": ["centre manager", "trainee"], "responsibilities": ["management", "budgeting", "hr", "plan", "administration"], "requirements": {"degrees": ["degree", "master"], "majors": [], "languages": ["english", "chinese"], "language_level": ["excellent"], "hard_skills": ["problem-solving skills"], "soft_skills": ["self-motivated", "competent", "organizational", "versatile", "problem-solving skills", "leadership"], "languages_combined": [{"language": "english", "language_level": ["excellent"]}, {"language": "chinese", "language_level": ["excellent"]}]}, "experience_required": {"duration": ["at least 8 years"], "field": ["administrative", "education", "team"]}}, {"job_id": "100003009032302", "location_code": "hk", "company": "C-Mer Dennis Lam & Partners Eye Center", "job_title": "Administration Manager", "description": "Responsibilities\n\nProvide professional consultation, such as introducing course details and proposing suitable course packages, to prospective customers\nMaintain good customer relationship\nManage the centre\u2019s class schedule\nHandling walk-in inquiries, calls, and customer follow-ups\nMaintain the centre\u2019s appearance\nProvide assistance to teachers when needed\n\n\u00a0Requirements\n\nMust have passion towards young children.\nForm 6 graduate or above\nFresh graduates are welcome, but 1-2 years working experience preferred\nCheerful, caring, patient, responsible and initiative.\nAble to multi-task & work under pressure\nComputer literate, especially in Microsoft Office (Word & Excel)\nFluent in Cantonese and English, Mandarin is an advantage\n\nRemuneration packages\n\n5 days working & long lunch hour\nProvide all round training\nGreat chance of promoting to be a partner\n\nWorking hours\n\n5 days working per week (including Saturday)\n10:00am \u2013 7:30pm\u00a0(4 days between Monday-Friday) and\u00a09:00am \u2013 6:30pm (Saturday)", "employment_types": ["Full Time", "Permanent"], "selling_points": ["Lead a small team to perform office admin duties", "Manage full spectrum of Office admin duties", "Proficiency in both Chinese and English"], "locations": ["Central"], "categories": ["Admin & HR", "Administration / Operation Manager", "Clerical / Admin Staff"], "post_time": "2022-01-11T01:53:49Z", "salary": {"currency": null, "max": null, "min": null, "period": "monthly", "term": null}, "salary_visible": false, "title_keywords": ["administration manager"], "responsibilities": ["maintain", "schedule", "provide assistance"], "requirements": {"degrees": [], "majors": [], "languages": ["cantonese", "english", "mandarin"], "language_level": ["advantage", "fluent"], "hard_skills": ["excel", "word", "microsoft office"], "soft_skills": ["cheerful", "multi-task", "responsible", "patient", "initiative", "work under pressure"], "languages_combined": [{"language": "cantonese", "language_level": ["fluent"]}, {"language": "english", "language_level": ["fluent"]}, {"language": "mandarin", "language_level": ["advantage"]}]}, "experience_required": {"duration": ["1-2 years"], "field": []}}, {"job_id": "100003009050128", "location_code": "hk", "company": "HKUE Limited", "job_title": "Assistant Programme Manager (Business Programmes)", "description": "Responsibilities\n\n\nLead & supervise an office administration team for providing overall administrative and clerical support to the clinics and offices\nWork with dedicated project team on office/clinic decoration, renovation and relocation projects; liaise with contractors, suppliers and vendors (for security system and office equipment, etc.) to ensure all progress are in control and within timeline\nManage administrative services and initiatives, including courier services, office supplies, security access and set up workstation for new joiner etc.\nTake initiative to assess workflow and process to improve efficiency.\nLiaise with internal departments and top management to ensure a smooth office operation\nParticipate in ad-hoc projects as assigned\n\nRequirements\n\nDegree in Business Administration or relevant disciplines\nAround 8-10 years\u2019 experience in office administration field with at least 3 years\u2019 supervisory experience gained in sizable companies or organizations\nExperience in managing modern/stylish office and office renovation/relocation are highly preferred\nGood problem-solving and constructive communication skills\nFast learner and a true team player with adaptivity to new corporate culture quickly\nPleasant and self-driven, committed, organized and detail-minded\nGood command of written and spoken English and Chinese (including Putonghua)\nProficient in MS office\nImmediate availability is an advantage\n\nBenefits:\n\n\u00a0 \u00a0 \u00a0 \u00a0 \u00a05-day work per week\n\u00a0 \u00a0 \u00a0 \u00a0 \u00a0Medical insurance\n\u00a0 \u00a0 \u00a0 \u00a0 \u00a0Annual leave\n\u00a0 \u00a0 \u00a0 \u00a0 \u00a0Annual discretionary bonus\n\u00a0 \u00a0 \u00a0 \u00a0 \u00a0Special offer of eye treatment for staff and family", "employment_types": ["Full Time", "Permanent"], "selling_points": [], "locations": ["Mong Kok"], "categories": ["Admin & HR", "Administration / Operation Manager", "Clerical / Admin Staff", "Education", "Others"], "post_time": "2022-01-14T09:49:34Z", "salary": {"currency": null, "max": null, "min": null, "period": "monthly", "term": null}, "salary_visible": false, "title_keywords": ["manager", "assistant"], "responsibilities": ["control", "management", "office supplies", "office administration", "renovation", "administrative and clerical support", "liaise with", "ad-hoc projects", "liaise with contractors"], "requirements": {"degrees": ["degree"], "majors": ["business administration"], "languages": ["putonghua", "english", "chinese"], "language_level": ["good command"], "hard_skills": ["problem-solving", "sizable companies", "ms office"], "soft_skills": ["detail-minded", "communication skills", "organized", "problem-solving", "driven", "pleasant", "committed", "team player", "fast learner", "constructive"], "languages_combined": [{"language": "putonghua", "language_level": ["good command"]}, {"language": "english", "language_level": ["good command"]}, {"language": "chinese", "language_level": ["good command"]}]}, "experience_required": {"duration": ["at least 3 years", "8-10 years"], "field": ["office administration", "supervisory experience"]}}, {"job_id": "100003009044135", "location_code": "hk", "company": "Manulife (International) Limited", "job_title": "Administrative assistant - \u884c\u653f\u52a9\u7406\uff08Latest*\uff09", "description": "Job Responsibilities:\n\nOversee the administrative matters, course management and coordination of the Programmes, to maintain an effective day-to-day operation of the programmes, such as student records, examinations, graduation matters, course materials and lectures preparation;\nReports to the Head of School regarding programme operation matters such as managing academic related tasks and student affairs;\nPriorities key tasks, allocating duties to academic & programme staff within the Institution and in accordance with Institution policies and procedures;\nAssist in reviewing and developing/ monitoring the implementation of policies and procedures;\nPlay a key part in implementation of the QA processes & Accreditation exercise;\nUndertake committee work in various meetings, committees and boards;\nDevelop and comply various programme related reports and statistics for management review;\nPerform any other duties as assigned by the Supervisor.\n\nJob Requirements:\n\nMinimum Bachelor Degree (preferably with post graduate degree) &/or Professional qualifications in related subject areas;\nMinimum 4 years working experience in higher education programmes &/or programme administration & management in which at least 2 years in a supervisory role;\nExcellent command in both written & spoken English and Chinese;\nDemonstrated ability to scope work, generate work plans and manage to deadlines;\nA good team leader with strong communication, interpersonal and analytical skills;\nSelf-motivated, organized, detail-oriented and capable in multi-tasking;\nPresentable, personable and patient personality;\nProficientin computer software applications, such as Microsoft Word, Excel and PowerPoint;\nExperience in managing programme management team and working with students will be a definite advantage;\nImmediate availability is highly preferred.\n\nPersonal data collected will be used for recruitment purpose only, and the collected data will also be considered for other suitable positions available in our Company.\n\nOnly short-listed candidates will be notified.\n\n\n", "employment_types": ["Full Time", "Permanent"], "selling_points": ["Provide professional  administrative support", "1 year + relevant working experience", "Monthly salary 15k-20k, comission, discretionary"], "locations": ["Not Specified"], "categories": ["Admin & HR", "Administration / Operation Manager", "Sales, CS & Business Devpt", "Customer Service - Supervisor / Officer", "Marketing / Public Relations", "Marketing - General / Support"], "post_time": "2022-01-13T03:11:10Z", "salary": {"currency": "HKD", "max": 19999, "min": 14000, "period": "monthly", "term": null}, "salary_visible": true, "title_keywords": ["administrative assistant"], "responsibilities": ["any other duties", "management", "policies", "monitoring", "procedures", "developing", "implementation", "student records", "develop", "management review", "maintain", "reports", "coordination", "committee work", "day-to-day operation"], "requirements": {"degrees": ["degree", "bachelor"], "majors": [], "languages": ["english", "chinese"], "language_level": ["excellent"], "hard_skills": ["excel", "microsoft word", "professional qualifications", "powerpoint", "analytical skills"], "soft_skills": ["organized", "self-motivated", "personable", "capable", "analytical skills", "communication", "detail-oriented", "multi-tasking", "presentable", "patient", "good team leader", "interpersonal"], "languages_combined": [{"language": "english", "language_level": ["excellent"]}, {"language": "chinese", "language_level": ["excellent"]}]}, "experience_required": {"duration": ["minimum 4 years", "at least 2 years"], "field": ["management", "supervisory", "education", "team", "administration"]}}, {"job_id": "100003009051184", "location_code": "hk", "company": "LYY Limited", "job_title": "Human Resources Manager", "description": "Responsibilities:\n\nWork with departments to coordinate the project progress;\nAssist or represent the Managers, negotiate and follow up tasks with customers and partners meetings\uff08outdoor work is needed\uff09\nPrepare correspondence documents, reports, etc.;\nAssist in company meetings/ event organising\u00a0\n\n\nRequirements:\u00a0\n\nHigh diploma or above in business & communications, administration, public relations or related disciplines;\u00a0\nAt least 1 year relevant working experience\uff1b\nGood command of written and spoken English and Chinese;\nStrong interpersonal and communication skills, high teamwork spirit;\nGood knowledge of MS Office\n\n\nBenefits:\n\n5-day work week\nDiscretionary bonus\nMedical insurance\nMarriage, birthday and family care leave\n\n\n\n\u5d17\u4f4d\u8077\u8cac\uff1a\n\n\u8ca0\u8cac\u8ddf\u9032\u516c\u53f8\u8ca0\u8cac\u4eba\u76f8\u95dc\u5de5\u4f5c\u3001\u4e0b\u9054\u53ca\u8ddf\u8e64\u548c\u843d\u5be6\u60c5\u6cc1\uff1b\n\u5354\u52a9\u6216\u4ee3\u8868\u7d93\u7406\uff0c\u8207\u5ba2\u6236\u548c\u5408\u4f5c\u5925\u4f34\u5354\u5546\u548c\u8ddf\u9032\u4efb\u52d9\uff1b\n\u8ca0\u8cac\u5354\u52a9\u516c\u53f8\u8d77\u8349\u6587\u5b57\u6750\u6599\uff0c\u4ee5\u53ca\u6703\u8b70\u7d00\u8981\u3001\u7c21\u5831\u7b49\uff1b\n\u8ca0\u8cac\u516c\u53f8\u6703\u8b70\u4e8b\u52d9\u6e96\u5099\u5de5\u4f5c\uff0c\u4e26\u53c3\u8207\u516c\u53f8\u91cd\u8981\u6d3b\u52d5\u7684\u7d44\u7e54\u5b89\u6392\u5de5\u4f5c\uff1b\n\n\n\u5165\u8077\u8981\u6c42\uff1a\n\nHKCEE \u6216 DSE \u4e94\u79d1\u5408\u683c\uff0c\u9ad8\u7d1a\u6587\u6191\u6216\u4ee5\u4e0a\u5b78\u6b77\n1\u5e74\u76f8\u95dc\u5de5\u4f5c\u7d93\u9a57\uff1b\n\u826f\u597d\u7684\u82f1\u6587\u548c\u4e2d\u6587\u53e3\u8a9e\u53ca\u66f8\u5beb\u80fd\u529b;\n\u5177\u6709\u826f\u597d\u7684\u6e9d\u901a\u3001\u5354\u8abf\u80fd\u529b\uff0c\u826f\u597d\u5718\u968a\u5408\u4f5c\u7cbe\u795e\uff1b\n\u719f\u6089MS Office\n\n\n\u798f\u5229\uff1a\n\n5\u5929\u5de5\u4f5c\u9031\n\u82b1\u7d05\n\u91ab\u7642\u4fdd\u96aa\n\u5a5a\u59fb\uff0c\u751f\u65e5\u548c\u5bb6\u5ead\u8b77\u7406\u5047", "employment_types": ["Permanent"], "selling_points": [], "locations": ["Hung Hom"], "categories": ["Admin & HR", "Administration / Operation Manager"], "post_time": "2022-01-15T05:06:23Z", "salary": {"currency": null, "max": null, "min": null, "period": "monthly", "term": null}, "salary_visible": false, "title_keywords": ["manager", "human resources"], "responsibilities": ["coordinate", "reports", "project progress"], "requirements": {"degrees": ["high diploma or above"], "majors": ["related disciplines", "business", "communications"], "languages": ["english", "chinese"], "language_level": ["good command"], "hard_skills": ["ms office"], "soft_skills": ["communication skills", "teamwork spirit", "interpersonal"], "languages_combined": [{"language": "english", "language_level": ["good command"]}, {"language": "chinese", "language_level": ["good command"]}]}, "experience_required": {"duration": ["at least 1 year"], "field": ["relevant working experience"]}}, {"job_id": "100003009044053", "location_code": "hk", "company": "The Hongkong Electric Co., Ltd.", "job_title": "Manager (Administration Services) (Ref: TND-MAS-CM-JD)", "description": "Responsibilities and Duties\n\nl\u00a0\u00a0 Support the Company HR Department to supervise the subordinates to formulate working plans, including in regions of the designated region in China / Southeast Asia countries.\n\nl\u00a0\u00a0 Follow the Company strategies, to establish HR policies, positions and talent management to ensure the successful implementation of its China or overseas business\n\nl\u00a0\u00a0 Supervise all personnel job duties and responsibilities\n\nl\u00a0\u00a0 Lead the HR team to optimize the incentives mechanism, rational planning and HR budget control\u00a0\n\nl\u00a0\u00a0 Ensure both China HR management policy and employment contracts in compliance with domestic Employment Ordinance\n\nl\u00a0\u00a0 Handle the issues related to HR and take corresponding action in a timely manner\n\nRequirements\n\nl\u00a0\u00a0 High Diploma or Degree in Human Resources management\n\nl\u00a0\u00a0 5 years of experience in managerial position related PRC operations\n\nl\u00a0\u00a0 Well versed with PRC employment related rules and manpower sourcing and extensive knowledge of PRC business\n\nl\u00a0\u00a0 Strong coordination, communication and interpersonal skills\n\nl\u00a0\u00a0 Good command of written and spoken Chinese and English\n\nl\u00a0\u00a0 Willing to station in China (Guangdong province)\n\nAll Personal data collected will be used for recruitment purpose only.", "employment_types": ["Full Time", "Permanent"], "selling_points": ["Handle office administration / renovation work", "Administration policies and procedures", "Business Administration"], "locations": ["Aberdeen"], "categories": ["Admin & HR", "Administration / Operation Manager", "Clerical / Admin Staff"], "post_time": "2022-01-13T02:55:09Z", "salary": {"currency": null, "max": null, "min": null, "period": "monthly", "term": null}, "salary_visible": false, "title_keywords": ["manager"], "responsibilities": ["management", "policies", "hr", "contracts", "compliance", "implementation", "a timely manner", "plans", "budget control", "planning"], "requirements": {"degrees": ["high diploma", "degree"], "majors": [], "languages": ["english", "chinese"], "language_level": ["good command"], "hard_skills": [], "soft_skills": ["communication and interpersonal skills", "extensive", "coordination"], "languages_combined": [{"language": "english", "language_level": ["good command"]}, {"language": "chinese", "language_level": ["good command"]}]}, "experience_required": {"duration": ["5 years"], "field": ["related", "managerial"]}}, {"job_id": "100003009047937", "location_code": "hk", "company": "The Hang Seng University of Hong Kong", "job_title": "Assistant Officer / Executive Assistant \u2013 Registry (Ref: AO/EA (REG) 2022-01-14)", "description": "Responsibilities:\n\nReporting to the General Manager Office of Transmission & Distribution Division, the appointee will mainly perform the following responsibilities:\u00a0\n\nTo supervise a team to handle various office administration, renovation, catering work and provide quality secretarial / clerical services and maintain document filing system\u00a0\u00a0\nTo coordinate with department secretaries and administration officers in devising, finetuning and implementing administration policies and procedures\nTo help developing new IT systems such as SharePoint / documents archiving system and minitor employee movements\nTo prepare and consolidat annual budget and control expenditure of administration services\nTo contribute and help overseeing to health, safety and environmental initiatives of the Division\n\nRequirements:\n\nBachelor's Degree in Business Administration or related disciplines\nPossession of relevant qualification in Accounting an advantage\nA minimum of 8 years\u2019 relevant experience in sizable organisations, in which 3 years at supervisory level\nExperience in committee secretariat, general administration and budget planning\nGood command of English and Chinese languages, both spoken and written\u00a0\n\nWorking Location : Ap Lei Chau, transportation to be provided\n\nApplication:\n\nIf you are interested in this position, please send your resume\u00a0(in PDF format)\u00a0with details of qualification, experience, present and expected salaries and contact number to the Human Resources Division, The Hongkong Electric Co., Ltd. on or before\u00a027 January 2022\u00a0and quote the reference number in your application.\u00a0 Please also visit our website to know more about our company\u00a0http://www.hkelectric.com.\n\nApplicants not invited for interview within one month from the closing date may consider their applications unsuccessful.\u00a0 All unsuccessful applications will be kept for six months after the date of this advertisement.\n\nWe are an equal opportunity employer.\u00a0 Personal data provided by job applicants will be treated in strictest confidence and used only for recruitment-related purposes in accordance with the laws and ordinance of the HKSAR.", "employment_types": ["Full Time", "Permanent"], "selling_points": [], "locations": ["Not Specified"], "categories": ["Admin & HR", "Administration / Operation Manager", "Personal / Executive Assistant", "Others"], "post_time": "2022-01-14T11:24:33Z", "salary": {"currency": null, "max": null, "min": null, "period": "monthly", "term": null}, "salary_visible": false, "title_keywords": ["assistant officer", "executive assistant"], "responsibilities": ["administration", "reporting", "document filing", "control", "office administration", "policies", "renovation", "quality", "coordinate with", "procedures", "developing", "systems", "budget", "maintain", "catering"], "requirements": {"degrees": ["degree", "bachelor"], "majors": ["related disciplines", "business administration"], "languages": ["english", "chinese"], "language_level": ["good command"], "hard_skills": ["ap"], "soft_skills": ["interested in", "confidence"], "languages_combined": [{"language": "english", "language_level": ["good command"]}, {"language": "chinese", "language_level": ["good command"]}]}, "experience_required": {"duration": ["3 years", "minimum of 8 years"], "field": ["administration", "relevant experience", "supervisory level", "human resources", "planning"]}}, {"job_id": "100003009044089", "location_code": "hk", "company": "Dah Chong Hong, Limited", "job_title": "Administration Officer", "description": "(Ref: AO/EA (REG) 2022-01-14)\n\nResponsibilities:\nprovide administrative and logistic support on programme development (programme accreditation and reaccreditation), synchronisation and standardisation of programme accreditation documents, meetings and other accreditation matters;\nassist in the preparation of programme accreditation documents;\nhandle and maintain central filing on programme development and programme quality assurance matters; and\nserve as secretary to committees and working groups.\n\nApplicants should:\npossess a recognised degree, preferably with 2 years of relevant working experience;\nbe a fast learner, proactive, self-motivated, a good team player and able to work independently with strong sense of responsibility;\npossess good interpersonal and communication skills;\nhave a good command of written and spoken English and Chinese (Cantonese and Putonghua); and\nhave good PC knowledge including MS Word, Excel and Chinese Processing.\nWork experience in the tertiary education sector will be an advantage.\u00a0 Applicants with less experience will be considered as Executive Assistant.\n\n\nSalary will be commensurate with qualifications and experience.\u00a0 Interested applicant should visit this link\u00a0https://recruit.hsu.edu.hk/ and apply on or before 30 January 2022.\u00a0 The University reserves the right not to fill the position in this exercise.\nApplicants who are not invited to an interview within three months may consider their applications unsuccessful.\u00a0 All information received will be treated in strict confidence, and the data collected will be used for recruitment purposes only.\u00a0 The Personal Information Collection Statement will be provided upon request.\nThe Hang Seng University of Hong Kong, incorporated in Hong Kong with limited liability by guarantee, is an equal opportunity employer.", "employment_types": ["Full Time"], "selling_points": [], "locations": ["Kowloon Bay"], "categories": ["Admin & HR", "Administration / Operation Manager", "Clerical / Admin Staff", "Others"], "post_time": "2022-01-13T04:13:32Z", "salary": {"currency": null, "max": null, "min": null, "period": "monthly", "term": null}, "salary_visible": false, "title_keywords": ["administration officer"], "responsibilities": ["data", "quality", "logistic support", "communication", "maintain", "recruitment"], "requirements": {"degrees": ["degree"], "majors": [], "languages": ["cantonese", "putonghua", "english", "chinese"], "language_level": ["good command", "good"], "hard_skills": ["excel", "pc knowledge", "processing", "ms word"], "soft_skills": ["communication skills", "good team player", "self-motivated", "work independently", "confidence", "sense of responsibility", "proactive", "fast learner", "interpersonal"], "languages_combined": [{"language": "cantonese", "language_level": ["good command", "good"]}, {"language": "putonghua", "language_level": ["good command", "good"]}, {"language": "english", "language_level": ["good command", "good"]}, {"language": "chinese", "language_level": ["good command", "good", "good"]}]}, "experience_required": {"duration": ["2 years"], "field": ["relevant working experience", "education"]}}, {"job_id": "100003009044654", "location_code": "hk", "company": "ExcelNet Total HR Solutions", "job_title": "Administrative Assistant (MNC+ 5 days work)", "description": "Job Duties:\n\nexecute order processing upon order in placed, including customer a/c set-up\nprepare delivery and shipping arrangements\nupdate system info and status, also documentation filing\nliaise with warehouse team for daily inbound / outbound delivery\nact as customer service to handle customer enquiries\ncoordinate supply chain activities from end to end\narrange invoicing to customer\nassist stock take execution\nbook all operation cost into system\nsupport various documentation per ISO standard\nperform ad hoc duties assigned by management\n\nJob Requirements:\n\nDSE certificate or above\n8 year or above relevant working experience including 3 years in supervisory role\nExperience in System Changeover will be an advantage\nMS Dynamic NAV/any ERP system usage experience\nAverage spoken and written English and Chinese\nAttention to details, work independently, high problem-solving skill\nless experience or fresh graduates are also welcome\nImmediate available is highly preferable\n\nWe offer a 5-day working week, an attractive remuneration package and excellent career opportunities to the right candidate.\u00a0\n\nInterested parties, please send full resume\u00a0with current and expected salary\u00a0by clicking 'Apply Now'.\n\n\nAll personal data collected will be used for recruitment purposes only. Applicants who are not contacted within 6 weeks may consider your applications unsuccessful and the personal data collected will be destroyed after six months.", "employment_types": ["Full Time"], "selling_points": ["Immediate available will be an advantage", "Diploma in Business Administration, Accounting", "Knowledge SAP is an additional advantage"], "locations": ["Kwun Tong"], "categories": ["Admin & HR", "Administration / Operation Manager", "Clerical / Admin Staff"], "post_time": "2022-01-13T06:27:44Z", "salary": {"currency": null, "max": null, "min": null, "period": "monthly", "term": null}, "salary_visible": false, "title_keywords": ["administrative assistant"], "responsibilities": ["ad hoc duties", "cost", "shipping", "handle customer enquiries", "management", "stock take", "coordinate", "liaise with", "invoicing", "customer service", "order processing", "documentation"], "requirements": {"degrees": ["certificate", "dse"], "majors": [], "languages": ["english", "chinese"], "language_level": ["average"], "hard_skills": ["problem-solving", "erp system", "dynamic"], "soft_skills": ["problem-solving", "work independently", "dynamic", "attention to details"], "languages_combined": [{"language": "english", "language_level": ["average"]}, {"language": "chinese", "language_level": ["average"]}]}, "experience_required": {"duration": ["3 years", "8 year"], "field": ["supervisory", "erp system", "relevant working experience"]}}, {"job_id": "100003009050382", "location_code": "hk", "company": "OCBC Wing Hang Bank Limited", "job_title": "Manager, Property Services", "description": "Our client\u00a0is the world\u2019s leading provider of mobility solutions company is looking for a right\u00a0candidate.\u00a0 We sincerely invite you to apply for the following position:\n\nResponsibilities:\n\nTo follow up office renovation work by co-ordinating with various parties in order to ensure the work is carried out smoothly.\nTo monitor and update the data at Access Control System and to ensure the good condition of first aid box for various Siemens premises.\nTo liaise with building management office\nTo place service calls for telephone system problems and booking.\nTo handle office and fleet registration license renewal.\nTo handle other Ad-hoc requests from the line manager.\n\nRequirements:\n\nDiploma in Business Administration, Accounting, or related disciplines;\nAt least 2 years\u2019 relevant experience in large multi-national companies;\nExperience in project control will be an advantage;\nGood interpersonal and problem-solving skills;\nStrong organizing skill, quality-focused, self-initiative, flexible and result-driven;\nWell-versed in PC applications and SAP is an additional advantage;\n\nThe client offer good remuneration package and attractive benefits to the right candidate. Please send resume by clicking the below \"APPLY NOW\".\u00a0\u00a0All information will be treated in confidential and in compliance with the privacy ordinance.\u00a0\u00a0", "employment_types": ["Full Time", "Permanent"], "selling_points": ["Experience in handling retail / banking renovation", "Degree", "Minimum 8 years\u2019 relevant experience"], "locations": ["Shau Kei Wan"], "categories": ["Admin & HR", "Administration / Operation Manager", "Banking / Finance", "Others", "Property / Real Estate", "Property Management"], "post_time": "2022-01-14T10:15:41Z", "salary": {"currency": null, "max": null, "min": null, "period": "monthly", "term": null}, "salary_visible": false, "title_keywords": ["manager"], "responsibilities": ["data", "renovation", "monitor", "telephone system", "building management", "booking", "ad-hoc requests", "liaise with", "access control"], "requirements": {"degrees": ["diploma"], "majors": ["related disciplines", "accounting", "business administration"], "languages": [], "language_level": [], "hard_skills": ["problem-solving skills", "sap", "pc applications"], "soft_skills": ["flexible", "focused", "driven", "self-initiative", "problem-solving skills", "interpersonal"], "languages_combined": []}, "experience_required": {"duration": ["at least 2 years"], "field": ["relevant experience"]}}, {"job_id": "100003009051322", "location_code": "hk", "company": "Talent Consultancy Ltd", "job_title": "Senior Administrative Officer / Admin Officer (5 days, Salary $22K to $26K)", "description": "Responsibilities\n\u200bManage a team to provide a wide spectrum of renovation and facility management services. including repair & maintenance matters for office building, general offices and branches, strategic & master layout planning, overall project management,\nManage internal & external stakeholder to ensure smooth project execution,\nReview tender document and statutory submission,\nMonitor budget and progress for projects to ensure cost-effectiveness and on-time completion.\nRequirements\n\u200bUniversity degree in Engineering, Construction Management, E&M, Building Management or related discipline,\nMinimum 8 years\u2019 relevant experience in renovation project and facility management,\nFamiliar with property projects from the conceptual stage to completion stage,\nExperience in handling retail / banking renovation project,\nExperience in manage team / contractor on repair & maintenance matters for office building, general offices and branches physical security and occupational safety & health are an advantage,\nGood command of both written and spoken English and Chinese,\nGood command in MS office applications,\nGood supervisory and communication skills.\n\nAttractive remuneration package will be offered to the right candidate. Please apply with full resume stating present & expected salary and contact phone number to The Human Resources Manager, 10/F, 161 Queen\u2019s Road Central, Hong Kong. Please quote the reference. Personal data collected will be used for recruitment purpose only. For more information, please visit our website: http://www.ocbcwhhk.com.\n\u00a0", "employment_types": ["Full Time", "Permanent"], "selling_points": [], "locations": ["Not Specified"], "categories": ["Admin & HR", "Administration / Operation Manager", "Clerical / Admin Staff", "HR Director / Manager"], "post_time": "2022-01-15T08:37:06Z", "salary": {"currency": "HKD", "max": 24999, "min": 20000, "period": "monthly", "term": null}, "salary_visible": true, "title_keywords": ["officer", "senior administrative officer", "admin"], "responsibilities": ["management", "cost", "maintenance", "renovation", "review", "monitor", "budget", "project management", "repair", "tender document", "planning"], "requirements": {"degrees": ["degree"], "majors": ["building management", "construction management", "engineering"], "languages": ["english", "chinese"], "language_level": ["good command"], "hard_skills": ["maintenance", "ms office"], "soft_skills": ["communication skills"], "languages_combined": [{"language": "english", "language_level": ["good command"]}, {"language": "chinese", "language_level": ["good command"]}]}, "experience_required": {"duration": ["minimum 8 years"], "field": ["management", "maintenance", "relevant experience", "security", "banking", "retail", "team"]}}, {"job_id": "100003009050975", "location_code": "hk", "company": "The Hong Kong Polytechnic University", "job_title": "Assistant Manager (two posts)", "description": "Offer:\u00a0\n\n5 days work (Mon to Fri) per week;\nFor the Senior Admin Officer - Salary is HK$26,000, depends on Experience & Ability;\nFor the Administration Officer - Salary is HK$22,000 or above, depends on Experience & Ability;\nLong term Career even in Current Economic Downturn.\nDuties:\u00a0\u00a0\u00a0\n\nSupport the retail branches daily operations, including administrative support, management review & reports, repair and maintenance and etc.\nAssist the Management reviewing Branch Operation Procedures & Effectiveness, streamline of operation process and develop of new work flows when needs;\nWork closely with branch staff and Headquarter on branch operation system and back-office system development, including consolidation of user requirement;\nConduct internal audit of branch to review effectiveness of current operation procedures and report areas for improvement.\nRequirements:\u00a0\u00a0\n\n\nDegree holders;\nAt least 3 years solid experience in Administration function, preferably gained by retail sector or large scale company (Having Staff over 300 in Hong Kong);\nStrong analytical mind with good communication and interpersonal skills;\nGood command of both written and spoken English and Chinese;\nInitiative, independent and proficiency in MS Office.\nLess experience will be consider as Administrative Officer.\n\nAttractive remuneration package will be offered to the right candidate.\u00a0 Interested parties please use the \"APPLY NOW\" function to apply for the job.\u00a0\n\nShould you need any further assistance, please WhatsApp 92823326 (No Telephone Call will be answer) or email to dave @ talentcl.com (Can not mention the Client Name before receiving candidate's Resume).\n\n\nAll personal data collected will be used for recruitment purpose only. \u00a0Applicants not hearing from us within 3 weeks may consider their applications unsuccessful.", "employment_types": ["Full Time"], "selling_points": [], "locations": ["Not Specified"], "categories": ["Admin & HR", "Administration / Operation Manager", "Sales, CS & Business Devpt", "Business Development", "Professional Services", "Legal & Compliance"], "post_time": "2022-01-14T12:23:42Z", "salary": {"currency": null, "max": null, "min": null, "period": "monthly", "term": null}, "salary_visible": false, "title_keywords": ["assistant manager"], "responsibilities": ["user requirement", "management", "maintenance", "administrative support", "internal audit", "review", "procedures", "develop", "daily operations", "repair", "reports", "management review", "report"], "requirements": {"degrees": ["degree"], "majors": [], "languages": ["english", "chinese"], "language_level": ["good command"], "hard_skills": ["ms office"], "soft_skills": ["analytical mind", "independent", "initiative", "communication and interpersonal skills"], "languages_combined": [{"language": "english", "language_level": ["good command"]}, {"language": "chinese", "language_level": ["good command"]}]}, "experience_required": {"duration": ["at least 3 years"], "field": ["retail", "administrative", "administration"]}}, {"job_id": "100003009050522", "location_code": "hk", "company": "HH Partners", "job_title": "Company Secretary", "description": "KNOWLEDGE TRANSFER AND ENTREPRENEURSHIP OFFICE\n\nAssistant Manager (two posts) (Ref. 22011407-JCS)\n\nDuties\n\nThe appointees will work under the Intellectual Property Management and Commercialisation section and be required to:\n\n(a) assist in the execution of Intellectual Property (IP) management, commercialisation, due diligence and invention disclosures;\n\n(b) prepare written evidence-based recommendations on the potential commercialisation opportunity or impact based upon due diligence;\n\n(c) conduct patent search, prepare patent applications and provide support to office actions;\n\n(d) work closely with internal and external stakeholders such as inventors, patent attorney, funders and external consultants on issues related to IP management and commercialisation;\n\n(e) provide support to IP system, database management and other IP related matters; and\n\n(f) perform any other duties as may be assigned by the Director of the Office or his delegates.\n\nQualifications\n\nApplicants should:\n\n(a) have a recognised degree in a relevant area of Science and/or Engineering plus at least five years\u2019 relevant post-qualification working experience preferably in business, intellectual property and/or law;\n\n(b) have a good understanding of technology transfer, business development and licensing;\n\n(c) be highly motivated, result-oriented and able to work independently;\n\n(d) have a good command of both written and spoken English and Chinese (Cantonese and Putonghua); and\n\n(e) possess excellent interpersonal and communication skills.\n\nApplicants who have responded to the previous advertisement need not re-apply.\n\nRemuneration and Conditions of Service\n\nA highly competitive remuneration package will be offered. Appointment will be on a one-year gratuity-bearing contract. Applicants should state their current and expected salary in the application.\n\nApplication\n\nPlease send a completed application form by post to Human Resources Office, 13/F, Li Ka Shing Tower, The Hong Kong Polytechnic University, Hung Hom, Kowloon, Hong Kong or via email by clicking \"Apply Now\". Application forms can be downloaded from https://www.polyu.edu.hk/hro/careers/guidelines_and_forms/forms. If a separate curriculum vitae is to be provided, please still complete the application form which will help speed up the recruitment process. Consideration of applications will commence on 21 January 2022 until the positions are filled. The University\u2019s Personal Information Collection Statement for recruitment can be found at https://www.polyu.edu.hk/hro/careers/guidelines_and_forms/pics_for_recruitment.\n\nPolyU is an equal opportunity employer committed to diversity and inclusivity. All qualified applicants will receive consideration for employment without regard to gender, ethnicity, nationality, family status or physical or mental disabilities.", "employment_types": ["Full Time", "Part Time"], "selling_points": ["Work-life balance - work from home", "CSA, Microsoft office proficient", "Wanchai"], "locations": ["Wan Chai"], "categories": ["Admin & HR", "Administration / Operation Manager", "Professional Services", "Company Secretary"], "post_time": "2022-01-14T10:36:44Z", "salary": {"currency": null, "max": null, "min": null, "period": "monthly", "term": null}, "salary_visible": false, "title_keywords": ["company secretary"], "responsibilities": ["due diligence", "management", "any other duties", "provide support", "communication", "recruitment", "database", "recruitment process"], "requirements": {"degrees": ["degree"], "majors": ["science", "business", "engineering", "law"], "languages": ["cantonese", "putonghua", "english", "chinese"], "language_level": ["good command"], "hard_skills": ["ip", "plus", "c"], "soft_skills": ["communication skills", "work independently", "committed", "motivated", "interpersonal", "result-oriented"], "languages_combined": [{"language": "cantonese", "language_level": ["good command"]}, {"language": "putonghua", "language_level": ["good command"]}, {"language": "english", "language_level": ["good command"]}, {"language": "chinese", "language_level": ["good command"]}]}, "experience_required": {"duration": ["at least five years"], "field": ["business", "post-qualification", "engineering"]}}, {"job_id": "100003009042822", "location_code": "hk", "company": "City University of Hong Kong", "job_title": "Manager/Assistant Manager in the Global Engagement Office [Ref. B/525/03]", "description": "We are seeking for an experienced company secretary/administrator with at least 5 years of experience working for a professional service firm who is able to complete independently day to day company secretarial duties with limited supervision. You will be working directly with management for adhoc projects.\u00a0 \u00a0\u00a0\n\nThis position is suited to candidates with the following skillset:\n\n\nGood command of spoken and written English & Chinese (including Putonghua)\nDegree or Higher Diploma Holder with relevant experience\nICSA candidate preferred\nExperience in professional firms (in a client service role) with CSA system preferred\nGood knowledge of computer skill e.g. MS Word, Chinese Word-processing, etc.\nThe candidate should possess good attention to detail, numerical, organisational and time management skills.\u00a0\nWith our clients from all continents of the world, you will have the opportunity to work in an environment where you can build your skills in networking, cross-cultural communication, collaborative and interpersonal qualities.\n\n\nHH Partners\u00a0is proud of and cherishes its culture. Our culture has been described as welcoming, supportive and highly conscious of an ever evolving society. We aim to strike a good\u00a0work-life balance.\u00a0\n\nWe offer long-term career prospect,\u00a0 competitive remuneration package including transparent bonus system to the right candidate. Interested parties are invited\u00a0to\u00a0click the \"APPLY NOW\" button\u00a0and\u00a0send their applications,\u00a0quoting job reference number\u00a0and full resume stating\u00a0availability, present and expected salary to email below.\u00a0", "employment_types": ["Full Time", "Contract"], "selling_points": ["A Master\u2019s/Bachelor\u2019s degree", "At least 7 years\u2019 post-qualification experience", "Gratuity, leave, medical and dental schemes"], "locations": ["Not Specified"], "categories": ["Admin & HR", "Administration / Operation Manager", "Others", "HR Director / Manager"], "post_time": "2022-01-13T18:54:37Z", "salary": {"currency": null, "max": null, "min": null, "period": "monthly", "term": null}, "salary_visible": false, "title_keywords": ["assistant manager", "manager"], "responsibilities": ["communication", "management"], "requirements": {"degrees": ["degree", "higher diploma holder"], "majors": [], "languages": ["putonghua", "english", "chinese"], "language_level": ["good command"], "hard_skills": ["computer skill", "chinese word-processing", "ms word"], "soft_skills": ["supportive", "independently", "time management skills", "collaborative", "communication", "attention to detail", "interpersonal"], "languages_combined": [{"language": "putonghua", "language_level": ["good command"]}, {"language": "english", "language_level": ["good command"]}, {"language": "chinese", "language_level": ["good command"]}]}, "experience_required": {"duration": ["at least 5 years"], "field": ["secretarial", "relevant experience"]}}, {"job_id": "100003008809359", "location_code": "hk", "company": "Infineon Technologies Hong Kong Ltd", "job_title": "Contract - Administration Specialist", "description": "Duties\n\nReporting to the Deputy Director of the Office, the appointee will be responsible for:\n\nWorking with overseas/mainland partner institutions and student participants to promote and support student exchange and other global learning programmes;\nPlanning and organizing university events and visits to support internationalization;\nLeading and coaching student ambassadors in organizing activities to promote integration among local and non-local students;\nProviding non-academic advice and assistance to prospective and current non-local students;\nSupporting data management;\nVetting and sponsoring student visa applications;\nResponding to student critical incidents when needed; and\nPerforming any other duties as assigned.\n\nTravel will be required occasionally.\n\nRequirements\n\nA Master\u2019s/Bachelor\u2019s degree in Marketing/Event Management/Communication/International Relations/Psychology/Counselling with at least 7 years\u2019 post-qualification experience. \u00a0Excellent command of written and spoken English and Chinese (including Putonghua); excellent teamwork and interpersonal skills; ability to multitask on tight deadlines; ability and genuine interest to work with people from a diverse cultural background; good knowledge of computer and software applications including Word, Excel and PowerPoint are required. \u00a0Experience in overseas study/work would be an advantage. \u00a0In order to handle student emergencies and incidents that may involve people from other cultures, the candidate should be calm, positive-minded and strong in multicultural competence.\n\nCandidates with less experience may be considered for appointment as Assistant Manager.\n\nShortlisted candidates will be invited for a written test.\n\nSalary and Conditions of Service\n\nRemuneration package will be highly competitive, commensurate with qualifications and experience.\u00a0 Appointment will be made on a fixed-term contract; fringe benefits include gratuity, leave, medical and dental schemes.\n\nInformation and Application\n\nFurther information on the posts and the University is available at\u00a0http://www.cityu.edu.hk, or from the Human Resources Office, City University of Hong Kong, Tat Chee Avenue, Kowloon Tong, Hong Kong [Fax : 2788 1154 or 3442 0311].\u00a0\n\nTo apply, please submit an online application at\u00a0http://jobs.cityu.edu.hk. The closing date is\u00a028 January 2022.\u00a0 Applications will receive full consideration and only shortlisted applicants will be contacted.\u00a0 The University\u2019s privacy policy is available on the homepage.\n\nCity University of Hong Kong is an equal opportunity employer. We are committed to the principle of diversity. Personal data provided by applicants will be used for recruitment and other employment-related purposes.\n\nWorldwide recognition ranking #53 (QS survey 2022), and #4 among top 50 universities under age 50 (QS survey 2021); #1 in the World\u2019s Most International Universities (THE survey 2020); #1 in Engineering/Technology/Computer Sciences in Hong Kong (ARWU survey 2016); and #1 Business School in Asia-Pacific region (UT Dallas survey 2019).", "employment_types": ["Full Time", "Contract"], "selling_points": ["Great Place to Work", "Semiconductor Industry", "HK Science Park"], "locations": ["Others - China"], "categories": ["Admin & HR", "Administration / Operation Manager"], "post_time": "2022-01-13T03:30:53Z", "salary": {"currency": null, "max": null, "min": null, "period": "monthly", "term": null}, "salary_visible": false, "title_keywords": ["specialist"], "responsibilities": ["reporting", "management", "any other duties", "data", "planning"], "requirements": {"degrees": ["degree", "bachelor", "master"], "majors": ["psychology", "marketing", "international relations"], "languages": ["putonghua", "english", "chinese"], "language_level": ["excellent"], "hard_skills": ["excel", "word", "powerpoint"], "soft_skills": ["teamwork", "calm", "communication", "diverse", "interpersonal skills", "ability to multitask", "genuine", "positive"], "languages_combined": [{"language": "putonghua", "language_level": ["excellent"]}, {"language": "english", "language_level": ["excellent"]}, {"language": "chinese", "language_level": ["excellent"]}]}, "experience_required": {"duration": ["at least 7 years"], "field": ["management", "marketing", "post-qualification"]}}, {"job_id": "100003009048854", "location_code": "hk", "company": "IKEA", "job_title": "Store Human Resources Operations Manager (Shift duties required)", "description": "1 year contract, subject to renewal upon expiry\n\nIn your new role you will:\nI. Accounting:\nResponsible for physical count and monitoring of fixed asset\nPreparation of monthly accounts schedules\nAssist in updating actual movement for daily cashflow\nClaims processing\nII. Administration:\n\nOffice administration support\nSupport Purchasing function and relevant processes\nTravel management\nSupport in/out shipment and relevant export control and customs issues\nBack up for receptionist\nAd hoc assignment\nYou are best equipped for this task if you have:\n\n1-3 years relevant experience\nDiploma or above is preferred\nHands-on experience in Windows applications\nPositive work attitude with good interpersonal skills\nFluent in English, Mandarin an advantage", "employment_types": ["Full Time", "Permanent"], "selling_points": ["HRBP to the unit manager on all people topics", "Develop & implement strategy for retaining talents", "Familiar with labour ordinance"], "locations": ["Shatin Area"], "categories": ["Admin & HR", "Administration / Operation Manager", "Others", "HR Supporting Staff"], "post_time": "2022-01-14T07:28:02Z", "salary": {"currency": null, "max": null, "min": null, "period": "monthly", "term": null}, "salary_visible": false, "title_keywords": ["operations manager", "human resources"], "responsibilities": ["management", "control", "office administration support", "ad hoc assignment", "monitoring", "accounts schedules", "administration"], "requirements": {"degrees": ["diploma or above"], "majors": [], "languages": ["english", "mandarin"], "language_level": ["advantage", "fluent"], "hard_skills": ["processing"], "soft_skills": ["hands-on", "positive work attitude", "responsible", "interpersonal skills"], "languages_combined": [{"language": "english", "language_level": ["fluent"]}, {"language": "mandarin", "language_level": ["advantage"]}]}, "experience_required": {"duration": ["1-3 years"], "field": ["relevant experience"]}}, {"job_id": "100003009043764", "location_code": "hk", "company": "Tunbow Group Limited", "job_title": "Executive Assistant / Administrative Assistant", "description": "WHY YOU WILL LOVE US\n\nWe\u2019re a diverse group of down-to-earth, straightforward people with a passion for home furnishing. We come from all over the world, but we share an inspiring vision: \u201cto create a better everyday life for the many people\u201d. How we realize this vision is based on our shared humanistic values. These values guide our work and build our inclusive, open and honest culture. It\u2019s all based on a spirit of togetherness and enthusiasm. We work hard, but we have fun doing it. We\u2019re always looking for people who share our positive attitude and values.\n\nWHY WE WILL LOVE YOU\n\nYou have minimum 3 years\u2019 experience of working in a management role and/or the Human Resources field\nYou are a considered decision-maker with the ability to influence management colleagues\nYou have the ability to create a win-win situation when handling conflict situations\nYou have experience as a coach and/or men\nYou are self-reliant and motivated with proven ability to work as part of a team as well as independently\nYou have effective communication and relationship management experience\nYou are experience in supporting managers in resolving performance and other people management issues\nYou have the ability to identify need for and drive change within the unit\nYou are experience in organizing activities and training\nYou have good analytical skill and numerical sense\nYou have the ability to ensure integrity of HR systems, guidelines and documents\nYou can maintain a high level of confidentiality\nYou feel comfortable to work in shift and weekend\nYou are proficient in Microsoft office and Chinese Word Processing\nYou can communicate confidently and clearly in spoken and written English\n\nWHAT YOU WILL BE DOING DAY TO DAY\n\nAct as a Human Resources Business Partner to the unit manager on all people topics\nSecure that the values-based recruitment, selection and onboarding process are implemented\nDevelop and implement strategic initiatives and process for retaining diverse talent\nTogether with the store management team, execute and monitor budgeted man hour plans which secures a diverse, appropriate staff structure and meets the defined business and productivity goals in the store\nAssist Store Human Resources & Operations Manager to develop and implement people strategies and initiatives aligned with business strategy\nSupport the store management team to continuously develop leadership and business competence capabilities within their function according to business needs\nSupport the store management team in taking the lead with special focus on talents and high-performing potentials, contributing to country and regional initiatives\nBe a good example of IKEA leadership in ways that express the IKEA values within and outside IKEA, and together with the unit managers help to safeguard and promote the IKEA Culture\nImplement a co-worker relations plan that effectively manages all local interactions with co-workers and ensures that all areas in the store work with the labor relations principles and uphold policies, procedures and laws\nWork with Learning & Development team to schedule co-workers to attend internal and external learning events to meet requirements and the wider learning and development\n\nTOGETHER AS A TEAM\n\nBe a strong contributor to the store management team, provide Human Resources subject matter expertise, process Human Resources operational matters and ensure that the Human Resources strategies are translated into store actions in the most effective and efficient way in order to fulfil the purpose of the HR function in the store.\n\nSTAFF BENEFITS\n\nAnnual Fixed Bonus, 5-Day Work Week, 17 days Public Holiday, Paid Leave (Paid Annual Leave, 14 weeks Maternity Leave, 5 days Paternity Leave, 1 week Marriage Leave), Employee Medical Coverage, Non-Contributory Retirement Plan, Staff Purchase Discount, Birthday Coupon, Referral Bonus, Excellent Career Path\n\nPersonal data collected will be kept and handled confidentially by authorized personnel for recruitment purposes only. It might also be disclosed to our subsidiaries, associates and agencies authorized to process the information for appointment. The Company will retain the applications of candidates not selected for a maximum period of 24 months after the selection process is finalized. Our Personal Information Collection Statement (PICS) is available at our career site and can be provided upon request by contacting our Human Resources Department. Applicants not heard from us within six weeks may consider their applications filed for future reference.\n\nIssued by The Dairy Farm Company, Limited\n\n\n%MCEPASTEBIN%", "employment_types": ["Full Time", "Permanent"], "selling_points": ["5 days work", "attractive bonus", "experience in personal assistant"], "locations": ["Kwun Tong"], "categories": ["Admin & HR", "Administration / Operation Manager", "Personal / Executive Assistant", "HR Supporting Staff"], "post_time": "2022-01-13T01:52:48Z", "salary": {"currency": null, "max": null, "min": null, "period": "monthly", "term": null}, "salary_visible": false, "title_keywords": ["administrative assistant", "executive assistant"], "responsibilities": ["management team", "management", "guidelines", "operations", "hr", "systems", "monitor", "policies", "procedures", "develop", "communication", "maintain", "recruitment", "schedule", "plan", "plans", "operational matters"], "requirements": {"degrees": [], "majors": [], "languages": ["english", "chinese"], "language_level": ["proficient"], "hard_skills": ["analytical skill", "chinese word processing", "fun", "microsoft office", "focus"], "soft_skills": ["efficient", "analytical skill", "independently", "passion for", "integrity", "positive attitude", "diverse", "communication", "motivated", "learning", "inspiring", "honest", "focus", "leadership", "decision-maker"], "languages_combined": [{"language": "english", "language_level": []}, {"language": "chinese", "language_level": ["proficient"]}]}, "experience_required": {"duration": ["minimum 3 years"], "field": ["people management", "management", "training", "human resources"]}}, {"job_id": "100003009046300", "location_code": "hk", "company": "Television Broadcasts Limited (TVB)", "job_title": "Secretary", "description": "We are one of the dynamic and fast growing manufacturers in a leading status specialized in Electrical Appliances. To further expand our scope of business and enhance our service, we are looking for candidates of excellent caliber to join our team.\u00a0\n\nResponsibility:\n- Report to Executive Secretary, assist to handle all office administration duties, including but not limited to general inquiry, insurance, office maintenance, renovation, office supplies management\n- Support in corporate functions, such as employee activities, events, etc.\n- Provide clerical support such as prepare memos / corresponding, filing, etc.\n- Provide secretarial support to senior management when necessary\n- Perform any ad hoc project or duty as assigned\n\nRequirement:\n- Associate degree or above in business related discipline\n- Min. 2 years of working experience, administration, personal assistant or HR related is preferred\n- Good Interpersonal skills and communication skills\n- Good time management, able to work under pressure\n- Flexible and multi-tasking\n- Candidate with more experience could be considered as Officer\n\nAttractive remuneration package and career opportunities will be offered to the successful candidate (including incentive bonus on performance basis, 5 days work, medical plan after probation, sponsorship for training etc.).\n\n", "employment_types": ["Full Time", "Permanent"], "selling_points": [], "locations": ["Tseung Kwan O"], "categories": ["Admin & HR", "Administration / Operation Manager", "Secretary", "Others"], "post_time": "2022-01-14T01:17:00Z", "salary": {"currency": null, "max": null, "min": null, "period": "monthly", "term": null}, "salary_visible": false, "title_keywords": ["secretary"], "responsibilities": ["provide clerical support", "management", "ad hoc", "maintenance", "office supplies", "renovation", "secretarial support", "office administration duties", "senior management", "insurance", "report"], "requirements": {"degrees": ["degree or above"], "majors": ["business"], "languages": [], "language_level": [], "hard_skills": [], "soft_skills": ["flexible", "communication skills", "multi-tasking", "interpersonal skills", "time management", "work under pressure"], "languages_combined": []}, "experience_required": {"duration": ["2 years"], "field": ["related", "hr", "administration"]}}, {"job_id": "100003009051217", "location_code": "hk", "company": "ACT Company", "job_title": "Relationship Manager \u5ba2\u6236\u95dc\u4fc2\u7d93\u7406 - NOVA Prestige Family Office (50k-120k)", "description": "Roles and responsibilities:\n\nLead and responsible for the full spectrum of HR & Admin functions.\nManage HR functions including the processing of compensation & benefits, staff recruitment & selection, monthly payroll and staff relations programs, salary benchmarking.\nEnsure consistency of company policies and practices of human resources management with update Employment Ordinance.\nDesign and implement strategic HR plans and programs to support the achievement of business objectives and organization growth\nResponsible for all office administrative / procurement functions including office services and supplies, insurance, repair and maintenance, leasing and tenancy renewal, etc.\nReview, plan and implement administration policies and procedures.\nPlan and draft office layout plans, supervise office & warehouse renovation & relocation projects\nMonitor day-to-day admin operations and enhance office facilities.\nPlan, execute & organize company activities such as Annual Dinner, Engagement events, etc.\nOther ad-hoc works as required.\n\nRequirement:\n\nDegree holder in Human Resources Management, Business Administration or equivalent disciplines\nMinimum of 8 years\u2019 of Human Resources experience, ideally within Ecommerce or Retail & Wholesale industry\nWell-versed in Hong Kong Employment Ordinance and relevant legislation and regulations\nProficient in MS Office, including Word, Excel, PowerPoint; strong capability with HRIS software\nA good team player with strong interpersonal and communication skills\nAble to work independently and under pressure\nGood command of written and spoken English, Cantonese and Mandarin\nImmediate available is preferable", "employment_types": ["Full Time", "Part Time", "Permanent", "Temporary", "Contract", "Internship", "Freelance"], "selling_points": ["Work with The Rich", "NOVA Prestige Family Office", "50-120k"], "locations": ["Kwun Tong"], "categories": ["Admin & HR", "Administration / Operation Manager", "Professional Services", "Business Consultancy", "Management", "Top Executives (CEO, CFO, CTO, GM, MD etc.)"], "post_time": "2022-01-15T05:05:52Z", "salary": {"currency": "HKD", "max": 89999, "min": 70000, "period": "monthly", "term": null}, "salary_visible": true, "title_keywords": ["\u5ba2\u6236\u95dc\u4fc2\u7d93\u7406", "relationship manager"], "responsibilities": ["ad-hoc", "management", "maintenance", "policies", "hr", "review", "procedures", "renovation", "design", "monitor", "operations", "repair", "recruitment", "insurance", "plan", "plans", "payroll", "administration"], "requirements": {"degrees": ["degree holder"], "majors": ["business administration"], "languages": ["cantonese", "english", "mandarin"], "language_level": ["good command"], "hard_skills": ["excel", "hong kong employment ordinance", "word", "powerpoint", "ms office"], "soft_skills": ["communication skills", "good team player", "work independently", "under pressure", "interpersonal"], "languages_combined": [{"language": "cantonese", "language_level": ["good command"]}, {"language": "english", "language_level": ["good command"]}, {"language": "mandarin", "language_level": ["good command"]}]}, "experience_required": {"duration": ["minimum of 8 years"], "field": ["ecommerce", "retail", "human resources"]}}, {"job_id": "100003009050850", "location_code": "hk", "company": "Trinity Search Limited", "job_title": "Executive Assistant - Property Developer", "description": "\u300a\u4e00\u7ad9\u5f0f\u9ad8\u7aef\u5ba2\u6236\u5e73\u53f0\u516c\u53f8\u300b\n\n\u5bcc\u4eba\u8ca1\u6280/\u4fdd\u55ae\u878d\u8cc7/\u5bcc\u4eba\u53d7\u8a17/\u907a\u7522\u7a05/\u5bb6\u65cf\u4fe1\u8a17/\u79c1\u4eba\u9280\u884c\n\n\u5de5\u4f5c\u7bc4\u7587\uff1a\n\n\u516c\u53f8\u505a\u9ad8\u7aef\u5ba2\u6236\u751f\u610f\uff08\u4fdd\u55ae\u878d\u8cc7/\u9ad8\u8cc7\u7522\u589e\u503c/\u907a\u7522\u7a05/\u5bb6\u65cf\u4fe1\u8a17\uff09\n\n\u4e3b\u8981\u5354\u52a9CEO\u65e5\u5e38\u5de5\u4f5c\n\n\u5354\u52a9CEO\u63a5\u898b\u9ad8\u7aef\u5ba2\u6236\n\n\u8ca0\u8cac\u958b\u6236\u53e3/\u5206\u6790\u8cc7\u91d1\u72c0\u6cc1/\u89e3\u91cbproposal\u00a0\u00a0\n\n\u8207\u9ad8\u7aef\u5ba2\u6236\u4fdd\u6301\u806f\u7d61\u00a0\u00a0\n\n\u6587\u4ef6\u8ddf\u9032\n\n\u798f\u5229\uff1a\n\n\u6709\u4f63\u91d1\u5206\uff0c\u82b1\u7d05\n\n\u89c0\u5858\u7532\u7d1a\u5546\u5834\u5beb\u5b57\u6a13\u5de5\u4f5c\n\n\u5730\u65b9\u5bec\u8eba\uff0c\u64c1\u6709\u8212\u9069\u4f11\u606f\u7a7a\u9593\n\nWork with CEO \u6642\u9593\u81ea\u4e3b\n\n\u4e00\u5e74\u53bb\u4e00\u6b21\u4e9e\u6d32\u8207\u6b50\u6d32\uff08\u6a5f\u7968\uff0b\u9152\u5e97)\u00a0\n\n\u8981\u6c42\uff1a\n\n\u80af\u5b78\uff0c\u6709\u8010\u6027\uff01\n\n\u4e2d\u4e94\u7562\u696d\u53ca\u4e94\u79d1\u5408\u683c\n\n\u611b\u6e9d\u901a\uff0c\u4e3b\u52d5\uff0c\u6562\u65bc\u63a5\u53d7\u6311\u6230\n\n\u7d93\u9a57\u4e0d\u62d8\uff0c\u6b61\u8fce\u7562\u696d\u5927\u5b78\u751f\uff0c\u53ea\u8981\u80af\u5b78\n\n*******\u6709\u610f\u8005\u8acb\u7acb\u523b\u9ede\u64caApply Now\u4ee5\u5b89\u6392\u9762\u8a66\u00a0**********", "employment_types": ["Full Time", "Permanent"], "selling_points": ["Top Tier Property Developer", "C-Level Executive", "Minimum 10 Years Relevant Working Experience"], "locations": ["Central & Western Area"], "categories": ["Admin & HR", "Administration / Operation Manager", "Personal / Executive Assistant", "Secretary"], "post_time": "2022-01-14T11:32:28Z", "salary": {"currency": null, "max": null, "min": null, "period": "monthly", "term": null}, "salary_visible": false, "title_keywords": ["developer", "executive assistant"], "responsibilities": [], "requirements": {"degrees": [], "majors": [], "languages": [], "language_level": [], "hard_skills": [], "soft_skills": [], "languages_combined": []}, "experience_required": {"duration": [], "field": []}}, {"job_id": "100003009044471", "location_code": "hk", "company": "Iotena Technology Limited \u611b\u5929\u7acb\u79d1\u6280\u6709\u9650\u516c\u53f8", "job_title": "HR and Administration Manager", "description": "Our Client is one of the leading property developers in Asia that is listed on the HK Stock Exchange and are well known for their\u00a0iconic developments in the region. As a result of their expanding business, they are\u00a0looking\u00a0for an\u00a0Executive Assistant\u00a0to provide support to C-level executive.\n\nResponsibilities:\n\nProvide all-rounded secretarial and personal assistance\u00a0in support\u00a0of a member of senior management;\u00a0including personal and business matters.\nUndertake to monitor, organise and arrange the schedule of the senior management member;\nResponsible for completing\u00a0administrative assignments independently and professionally\u00a0under\u00a0tight deadlines\nResearching and conducting data to prepare documents for review and presentation by board of directors, committees, and executives.\nReading and analysing incoming memos, submissions, and distributing them as needed.\nHandle travel arrangements including\u00a0ticketing,\u00a0accommodation booking and expense claims\nProvide ad-hoc and general support when necessary\n\nRequirements:\n\nAt least\u00a010 years relevant experience gained from Listed Companies, Multinational conglomerates or\u00a0property developers/real estate firms\u00a0\nUniversity degree holder is preferred\nExcellent command in both English and Chinese (including Mandarin)\nAbility to handle multi-task activities with tight deadlines\nThe successful candidate must be motivated, responsible and able to work independently\u00a0with good time management", "employment_types": ["Full Time"], "selling_points": ["Degree holder in related disciplines, Aggressive", "Min 8 years experiences in HR & Admin management", "Excellent interpersonal communication. Motivated"], "locations": ["Shatin Area"], "categories": ["Admin & HR", "Administration / Operation Manager", "HR Director / Manager", "Recruitment / Executive Search"], "post_time": "2022-01-13T04:15:42Z", "salary": {"currency": null, "max": null, "min": null, "period": "monthly", "term": null}, "salary_visible": false, "title_keywords": ["administration manager", "hr"], "responsibilities": ["ad-hoc", "travel arrangements", "data", "review", "monitor", "schedule", "booking", "general support", "senior management", "prepare documents"], "requirements": {"degrees": ["university degree"], "majors": [], "languages": ["english", "chinese", "mandarin"], "language_level": ["excellent"], "hard_skills": [], "soft_skills": ["work independently", "multi-task", "responsible", "motivated", "time management"], "languages_combined": [{"language": "english", "language_level": ["excellent"]}, {"language": "chinese", "language_level": ["excellent"]}, {"language": "mandarin", "language_level": ["excellent"]}]}, "experience_required": {"duration": ["at least 10 years"], "field": ["property developers", "relevant experience"]}}, {"job_id": "100003009048002", "location_code": "hk", "company": "Fiducia Limited", "job_title": "HR Manager (MNC)", "description": "Responsibilities:\n\nAssist the Management to identify business growth initiatives & formulate strategies\nDevelop business cases and participate in decision making\nDesign execution plan, and coordinate with stakeholders for implementation to maximize productivity & efficiency\nReview workflow, streamline business operation procedures & guidelines, set up best practices and establish assessment program\nParticipate in ad-hoc projects as assigned by the Management\n\nRequirements:\n\n\nDegree holder in Business Administration or related disciplines\nDetail-minded with strong business sense and analytical mind\nLogical with good communication & interpersonal skills\nStrong drive and sense of ownership to deliver results in a fast-paced working environment\nHave genuine anxiety to do a good job in Consumer Market and to grow within a dynamic, customer-centric and futuristic Company\n\nApart from competitive remuneration package and exciting opportunity for career development within the Group, we provide attractive employee benefits such as free company shuttle, free company SIM card and preferential SIM plan offers, comprehensive medical & insurance schemes, as well as full range of other employee well-being provisions.\u00a0\n\nInterested parties, please apply with full resume, present and expected salary, by clicking \u201cAPPLY NOW\u201d. Please quote the reference number on the e-mail subject.\n\n\n\nWe are an equal opportunity employer and welcome applications from all qualified candidates. Personal data collected will be treated in the strictest confidence and handled confidentially by authorised personnel for recruitment-related purposes only within the CK Hutchison Group of companies. The personal data of unsuccessful applicants will be destroyed after the recruitment exercise pursuant to the requirements of the Personal Data (Privacy) Ordinance in Hong Kong.", "employment_types": ["Full Time", "Permanent"], "selling_points": ["Manage HR & Admin Team", "5-8 years of experience", "12+2 Behavioural Goals Bonuses"], "locations": ["Wan Chai"], "categories": ["Admin & HR", "Administration / Operation Manager", "HR Director / Manager"], "post_time": "2022-01-14T04:28:04Z", "salary": {"currency": null, "max": null, "min": null, "period": "monthly", "term": null}, "salary_visible": false, "title_keywords": ["hr manager"], "responsibilities": ["business operation", "management", "guidelines", "review", "procedures", "implementation", "design", "develop", "plan", "coordinate with stakeholders", "ad-hoc projects"], "requirements": {"degrees": ["degree holder"], "majors": ["related disciplines", "business administration"], "languages": [], "language_level": [], "hard_skills": ["dynamic"], "soft_skills": ["detail-minded", "business sense", "communication", "analytical mind", "interpersonal skills", "dynamic", "comprehensive", "genuine"], "languages_combined": []}, "experience_required": {"duration": [], "field": []}}, {"job_id": "100003009045627", "location_code": "hk", "company": "Mindcluster Limited", "job_title": "Operation Officer", "description": "About the Team: Human Resources\nOur\u00a0vision\u00a0is to create a people-oriented work environment where all Fiducians feel safe and proud to work.\u00a0When people are engaged, feel valued, and respected, they thrive to become better every day.\u00a0The HR team at Fiducia handles all aspects from talent management (planning, recruiting, developing, managing, and retaining) to operational and administrative excellence.\n\nWe act as a trusted business partner and the go-to team for all people-related matters.\n\nAbout the Role and How you will make an impact:\n\nThe ideal candidate oversees HR operations in HK; contributes to Fiducia\u2019s business by ensuring efficient and professional services for our internal clients; engages with staff, as well as drives different initiatives towards a people-focused organisation.\n\nS/he is responsible for and measured by increased HR efficiency and productivity, as well as employee engagement and satisfaction on a quarterly basis.\n\nYour Responsibilities:\n\nInteract regularly with Employees/Managers for best engagement and understanding\nOrganise cost-effective, engaging activities to upkeep employee motivation in the office/team\nEnhance HR productivity via ongoing SOP review and improvement e.g. onboarding\nUpdate HR policies, technologies, reporting; and employee handbook\nReview HR documents to ensure zero-defect and right-first-time\nEnsure employee data accuracy (including medical, payroll, HRIS)\nHandle general labour cases (e.g. work visa) with practical solutions\nPerform other duties or projects as required by HRD and management\n\nSkills & Experience:\n\nStrong communication skills to take initiative, collaborate and build trustful relationships\nExperience in leading and developing a small team of HR and Office admin staff\nProfessional in HR operations, policies, and procedures, as well as people practices\nAttention to detail with sound judgment, driving actions and results\nCreative and quick learner with an adaptive and solution-oriented mindset\nCurious, tech-savvy and up-to date with glocal HR trends\nAbility to prioritize, delegate, empower others to successfully handle seasonal workload\nStrong sense of ownership and accountability for her/his, the team\u2019s and company\u2019s success\n5-8 years\u2019 related working experience in relevant industry\nHigh proficiency in verbal and written English\nSolid knowledge of HK labor law and related regulations\nBachelor\u2019s degree or above in HRM or related discipline\u00a0\n\nWhat we offer:\n\nAnnual plus Birthday Leave\nCareer growth opportunities with established peer group\nCommercial medical insurance\nFlexible working-hour and \u201cWork-From-Home\u201d\nPeople caring culture\nRegular team-building and CSR activities\nTraining subsidies", "employment_types": ["Full Time"], "selling_points": ["Step ahead and work on future-crafting projects", "Boundless opportunities & Fast-tracked career path", "Grow with us & Embark your bespoke venture journey"], "locations": ["Kwun Tong"], "categories": ["Admin & HR", "Administration / Operation Manager"], "post_time": "2022-01-14T10:13:23Z", "salary": {"currency": null, "max": null, "min": null, "period": "monthly", "term": null}, "salary_visible": false, "title_keywords": ["operation officer"], "responsibilities": ["collaborate", "reporting", "management", "cost", "perform other duties", "regulations", "data", "operations", "hr", "review", "policies", "developing", "procedures", "communication", "payroll", "planning"], "requirements": {"degrees": ["degree or above", "bachelor"], "majors": [], "languages": ["english"], "language_level": ["proficiency"], "hard_skills": ["small", "make", "safe", "go"], "soft_skills": ["efficient", "communication skills", "focused", "responsible", "accountability", "quick learner", "prioritize", "organisation", "people-oriented", "attention to detail", "creative", "initiative", "ideal"], "languages_combined": [{"language": "english", "language_level": ["proficiency"]}]}, "experience_required": {"duration": ["5-8 years"], "field": ["related", "hr", "developing", "admin", "team"]}}, {"job_id": "100003009048581", "location_code": "hk", "company": "Global Capital International Trading Limited", "job_title": "Admin Assistant", "description": "Key Responsibilities\n\nResponsible for the procurement of office supplies, furniture & equipment and administrative services;\nMonitor suppliers\u2019 performance and quality on regular basis and perform benchmarking analysis to optimize company\u2019s internal purchasing policy;\nManage general administration services including reception and company vehicles;\nManage application and renewal of vehicle license and insurance;\nHandle ad hoc tasks and projects as assigned.\n\nRequirements\n\nUniversity degree or equivalent;\nMinimum 5 years\u2019 relevant experience including at least 2 years\u2019 experience in supervisory role in reputable organization;\nExperience in managing e-procurement system is in advantage;\u00a0\nGood command in written and spoken English and Chinese;\nProficiency in Microsoft Office applications & technically sound in office workflow system\nSelf-motivated, reliable, service mindset and possess can-do attitude;\nGood management and supervisory skills.\nWe offer long-term career prospect and competitive remuneration package to the appointed candidate. Please apply in confidence with your detailed resume stating your current and expected salary to\u00a0Group Human Resources Department\n\n\n\nby email to\u00a0recruit(at)shuntakgroup.com\n\nor mail to\u00a0Penthouse 39/F, West Tower, Shun Tak Centre, 200 Connaught Road Central, Hong Kong\n\n(Please quote reference number and applied position)\n\nThe information supplied by the applicants will be used in accordance with the Personal Data (Privacy) Policy of Shun Tak Group (a copy of which will be provided upon request). Only shortlisted candidates will be notified.\n\nwww.shuntakgroup.com", "employment_types": ["Full Time"], "selling_points": [], "locations": ["Lai Chi Kok"], "categories": ["Admin & HR", "Administration / Operation Manager"], "post_time": "2022-01-14T06:50:42Z", "salary": {"currency": null, "max": null, "min": null, "period": "monthly", "term": null}, "salary_visible": false, "title_keywords": ["admin assistant"], "responsibilities": ["office supplies", "analysis", "quality", "monitor", "ad hoc tasks", "insurance", "administration"], "requirements": {"degrees": ["university degree"], "majors": [], "languages": ["english", "chinese"], "language_level": ["good command"], "hard_skills": ["microsoft office"], "soft_skills": ["self-motivated", "reliable", "can-do attitude"], "languages_combined": [{"language": "english", "language_level": ["good command"]}, {"language": "chinese", "language_level": ["good command"]}]}, "experience_required": {"duration": ["at least 2 years", "minimum 5 years"], "field": ["supervisory", "relevant experience", "procurement"]}}, {"job_id": "100003009049006", "location_code": "hk", "company": "Transmedic China Limited", "job_title": "ADMIN ASSISTANT / OPERATION ASSISTANT (MEDICAL DEVICE)", "description": "Responsibilities:\n\nReception & general administrative duties;\nHandle daily incoming calls, mails & documents;\u00a0\nUpdating report & records etc.\nRequirements :\n\nSecondary 5\n1-2 Year(s) Experience Required\nKnowledge Microsoft Office e.g.Word & Excel & Outlook\u00a0\nFluent Cantonese ; Fair Putonghua ; Fair English\nAble to read & write Chinese ; Able to read & write English\nEmployment Terms:\nDouble Pay\nMon to Fri: 9:30AM-6:00PM and Sat: 9:30AM-1:00PM, 5 - 5.5 working days per week, 8.5 working hours per day", "employment_types": ["Full Time", "Permanent"], "selling_points": ["Diploma in any disciplines", "5 days work, Performance Bonus", "Recent Graduate will be considered"], "locations": ["Kwun Tong Area"], "categories": ["Admin & HR", "Administration / Operation Manager", "Clerical / Admin Staff", "Transportation & Logistics", "Inventory / Warehousing"], "post_time": "2022-01-14T07:54:16Z", "salary": {"currency": null, "max": null, "min": null, "period": "monthly", "term": null}, "salary_visible": false, "title_keywords": ["admin assistant", "operation assistant"], "responsibilities": ["administrative duties", "report"], "requirements": {"degrees": [], "majors": [], "languages": ["cantonese", "putonghua", "english", "chinese"], "language_level": ["fluent"], "hard_skills": ["excel", "outlook", "word", "microsoft office"], "soft_skills": [], "languages_combined": [{"language": "cantonese", "language_level": ["fluent"]}, {"language": "putonghua", "language_level": []}, {"language": "english", "language_level": []}, {"language": "chinese", "language_level": []}]}, "experience_required": {"duration": [], "field": []}}, {"job_id": "100003009050970", "location_code": "hk", "company": "Bank of Communications Hong Kong Branch", "job_title": "Section Head, Project (Operations)", "description": "JOB SCOPE\n\nProvide general administrative and operational support to Operation Team\nAssist in daily distribution, logistic arrangement and inventory management\nProvide clerical support for record keeping purpose, such as data entry, scanning and filing etc\nHandling client\u2019s enquiries, preparing quotations/tenders and follow up with customer complaints\nCoordinate with Sales Team and other parties to meet client request\nPerform any ad hoc duties as assigned\n\nJOB REQUIREMENTS\n\nDiploma or above in any disciplines\nPreferably with 2-3 years customer service or operation experience\nExperience with SAP system will be an advantage\nGood communication and interpersonal skills\n\n\u00a0Interested applicants are invited to email detailed resume with a recent photograph, stating availability, current and expected salaries to\u00a0us.\n\n\u00a0Only shortlisted candidates will be notified.", "employment_types": ["Full Time"], "selling_points": [], "locations": ["Not Specified"], "categories": ["Admin & HR", "Administration / Operation Manager", "Others"], "post_time": "2022-01-14T12:15:44Z", "salary": {"currency": null, "max": null, "min": null, "period": "monthly", "term": null}, "salary_visible": false, "title_keywords": ["operations", "section head"], "responsibilities": ["provide clerical support", "scanning", "ad hoc duties", "operational support", "data entry", "customer complaints", "coordinate with", "logistic arrangement", "inventory management", "communication", "customer service", "sales team"], "requirements": {"degrees": ["diploma or above"], "majors": ["any disciplines"], "languages": [], "language_level": [], "hard_skills": ["sap"], "soft_skills": ["customer service", "communication and interpersonal skills", "detailed"], "languages_combined": []}, "experience_required": {"duration": ["2-3 years"], "field": ["operation", "customer service"]}}, {"job_id": "100003009051354", "location_code": "hk", "company": "Raze Technology Limited", "job_title": "Human Resources Manager", "description": "The Role\nTo cope with our aggressive growth and expansion plan, we are inviting high caliber individuals to join our fast growth team.\u00a0 You will have a chance to work at a fast-paced mission driven company that brings material science to life and benefit the mass.\u00a0 We are bringing business disruption and new hygiene standard to the world with the introduction of new photocatalyst products and services. With the continuous R&D and business innovation, we are thrilled to develop the next generation technology that safeguards everyday life.\u00a0 The ideal candidate will support the full scope of Human Resources responsibilities and partner with the organization on strategic initiatives. Maintain and enhance the organization's human resources by planning, implementing, and evaluating human resources policies, programs, and practices.\n\nResponsibilities\n\nDesign and implement human resources strategies including talent acquisition, staffing retention, employment compensation, health and welfare benefits, training and development, and labour relations, etc;\nWork closely with top management by providing human resources advice, counsel, and decisions; accountable for the performance of HR function;\nSuggest appropriate innovative measures for improving performance evaluations and employee engagement;\nTranslate the business strategy into HR strategy and provide human capital and organizational change perspectives embedded into business leadership teams;\nAlign and integrate HR strategies, goals and practices to ensure high performing culture/employees/teams;\u00a0\nDrive leadership development and address organizational issues. Professional support in all change processes.\u00a0\nRequirements\n\nDegree holder or above in Human Resources Management or related disciplines;\nAt least 10 years of solid HR experience with minimum 5 years' experience in supervisory level and HRBP role;\u00a0\nSolid HR practical experience within fast-paced business environment in FMCG or consumer healthcare industry is a MUST;\nStrong capability to work with different levels of stakeholders;\nGood negotiation, motivation, strategic and leadership skills to drive success and create win-win solutions;\nPossess good planning, organizational and time management skills;\nExcellent communication and interpersonal skills; able to interact with different levels of people;\nStrong working knowledge of employment law issues, best practice processes for disciplinary, redundancies and payroll is required, as well as experience of employee relations;\nFluent in written and spoken English, Cantonese and Mandarin.\nWe offer the right candidate attractive remuneration package and outstanding prospects for career advancement and development.\u00a0 The right candidate will progress career in a forward thinking and dynamic business with exciting growth plans.\u00a0 If you are qualified and interested, please send your full resume with current & expected salary and availability by clicking \"APPLY\".\n\nAll information collected will be treated as strictly confidential and used for recruitment purposes only. (Only shortlisted candidates will be notified)", "employment_types": ["Full Time", "Permanent"], "selling_points": [], "locations": ["Southern Area"], "categories": ["Admin & HR", "Administration / Operation Manager", "HR Director / Manager", "Recruitment / Executive Search"], "post_time": "2022-01-15T10:57:20Z", "salary": {"currency": null, "max": null, "min": null, "period": "monthly", "term": null}, "salary_visible": false, "title_keywords": ["manager", "human resources"], "responsibilities": ["hr", "management", "teams", "design"], "requirements": {"degrees": ["degree holder"], "majors": ["related disciplines"], "languages": ["cantonese", "english", "mandarin"], "language_level": ["fluent"], "hard_skills": [], "soft_skills": ["negotiation", "time management skills", "organizational", "leadership skills", "communication and interpersonal skills", "business environment"], "languages_combined": [{"language": "cantonese", "language_level": ["fluent"]}, {"language": "english", "language_level": ["fluent"]}, {"language": "mandarin", "language_level": ["fluent"]}]}, "experience_required": {"duration": ["at least 10 years", "minimum 5 years"], "field": ["healthcare industry", "fmcg", "hr", "business", "supervisory level", "payroll"]}}, {"job_id": "100003009049216", "location_code": "hk", "company": "Arrow Asia Pac Ltd", "job_title": "Senior Business Process Manager", "description": "What You'll Be Doing\n\nAct as the right-hand person to senior executive to provide solid analytical support to help understand business performance and formulate strategic initiatives\nFormulating strategic planning process, rolling out business process excellence and setting ambitious & achievable goal for the business\nWork closely with senior executives in business management and supplier management, provide timely and thoughtful handling,\nInvolve in formulating budget setting, implement ad-hoc projects, meeting coordination, presentation preparation, and agenda planning\nOversee an end-to-end project management cycle and be accountable for project deliverables and timeline, able to identify potential risks and proactively recommend solutions\nKeep abreast of business situations and market trends, provide most updated market information to identify business opportunities to drive growth strategies\nOptimize organizational productivity and performance by leveraging resources\nInvolve and facilitate business meetings/conferences and business development activities, including the creation of agendas and preparation of materials\n\nWhat We Are Looking For\n\nBachelor\u2019s degree or above in any related discipline\n10 years or above experience in business planning and business process improvement projects excellent\nGood communication and presentation skills in both English and Chinese\nPossess acute business acumen, strong analytical and problem-solving skills\nStrong organizational and interpersonal skills that able to perform and prioritize multiple tasks and build relationships with stakeholders\nDemonstrate proactiveness in problem-solving and decision-making\nExcellent attention to detail\nAble to achieve high performance goals and meet deadlines in a fast-paced environment\nCandidate with less experience would be considered as Business Manager.\n\n\n\nWhat\u2019s In It For You\n\nAt Arrow, we recognize that financial rewards and great benefits are important aspects of an ideal job. That\u2019s why we offer competitive financial compensation, including various compensation plans, and a solid benefits package.\n\nDouble Pay\nPerformance Bonus\nMedical & Dental\nLife Insurance\nMPF with additional employer contributions\nPaid Time Off\nFree Shuttle to HKSTP Office\n5-Day Work Week\nGrowth Opportunities\nAnd More!", "employment_types": ["Full Time", "Permanent"], "selling_points": ["Fortune 102 US Company", "Competitive package and benefit", "Right-hand person to senior executive"], "locations": ["Shatin Area"], "categories": ["Admin & HR", "Administration / Operation Manager", "Management", "General Management"], "post_time": "2022-01-14T08:16:51Z", "salary": {"currency": null, "max": null, "min": null, "period": "monthly", "term": null}, "salary_visible": false, "title_keywords": ["manager"], "responsibilities": ["management", "market information", "strategic planning", "identify business opportunities", "project deliverables", "budget", "identify potential risks", "project management", "conferences", "business process", "communication", "coordination", "ad-hoc projects", "planning"], "requirements": {"degrees": ["degree or above", "bachelor"], "majors": [], "languages": ["english", "chinese"], "language_level": ["good"], "hard_skills": ["business management", "problem-solving", "goal", "project management", "problem-solving skills", "acumen"], "soft_skills": ["multiple tasks", "fast-paced environment", "organizational", "timely", "problem-solving", "accountable", "prioritize", "communication", "project management", "presentation skills", "interpersonal skills", "coordination", "attention to detail", "business acumen", "problem-solving skills", "meet deadlines", "presentation"], "languages_combined": [{"language": "english", "language_level": ["good"]}, {"language": "chinese", "language_level": ["good"]}]}, "experience_required": {"duration": ["10 years"], "field": ["business", "planning"]}}, {"job_id": "100003009050973", "location_code": "hk", "company": "Bank of Communications Hong Kong Branch", "job_title": "Section Head, System Management", "description": "Career Level\nMiddle\nQualification\nDegree\nYears of Experience\n8 years\nJob Type\nFull Time\nJob Functions\nAdmin & HR, Administration / Operation Manager, Others, Sales, CS & Business Devpt, Business Development", "employment_types": ["Full Time"], "selling_points": [], "locations": ["Not Specified"], "categories": ["Admin & HR", "Administration / Operation Manager", "Others", "Sales, CS & Business Devpt", "Business Development"], "post_time": "2022-01-14T12:20:34Z", "salary": {"currency": null, "max": null, "min": null, "period": "monthly", "term": null}, "salary_visible": false, "title_keywords": ["section head"], "responsibilities": ["hr", "administration"], "requirements": {"degrees": ["degree"], "majors": [], "languages": [], "language_level": [], "hard_skills": [], "soft_skills": [], "languages_combined": []}, "experience_required": {"duration": [], "field": []}}, {"job_id": "100003009044796", "location_code": "hk", "company": "Delken Group Limited", "job_title": "Assistant Vice President (Administration and Human Resources)", "description": "Our client is a Financial Institution, they are currently seeking for an\u00a0Assistant Vice President (Administration and Human Resources) \u00a0to join their team.\n\n\nResponsibilities\n\n\nTo oversee human resources and office administration functions including recruitment, compensation and benefits, performance management, procurement and employee relations;\nTo implement strategic HR initiatives and formulate respective policies and procedures related to human resources functions;\nTo prepare annual office administration budget and staff budget, headcount planning; and\nTo assist in ad hoc corporate projects and assignments from time to time\n\nResponsibilities:\n\nDegree holder in Business Administration or Human Resources Management;\nA minimum of 12 years\u2019 relevant experience of which 8 years should be gained in a managerial role;\nProactive, self-motivated and a good team player with excellent people and communication skills; and\nPolicy drafting and report writing skills are essential.\u00a0\nInterested candidates, please send your resume (MS Word document) including employment history, present and expected salary to us.\n\n\nFor more jobs, please visit our website:\u00a0www.delken.com.hk.\u00a0\n\n(All personal data submitted will be treated in strict confidential and used for recruitment purposes only.)\u00a0", "employment_types": ["Full Time", "Permanent"], "selling_points": ["12 years rel exp of which 8 years Managerial role", "Oversee HR & Office Admin functions", "Policy drafting & reporting writing skills prefer"], "locations": ["Kwun Tong"], "categories": ["Admin & HR", "Administration / Operation Manager", "HR Director / Manager", "Training & Development"], "post_time": "2022-01-13T06:18:30Z", "salary": {"currency": null, "max": null, "min": null, "period": "monthly", "term": null}, "salary_visible": false, "title_keywords": ["human resources", "assistant vice president"], "responsibilities": ["management", "ad hoc", "office administration", "hr", "policies", "procedures", "budget", "communication", "planning", "recruitment", "report", "human resources functions", "administration"], "requirements": {"degrees": ["degree holder"], "majors": ["business administration"], "languages": [], "language_level": [], "hard_skills": ["writing skills"], "soft_skills": ["communication skills", "good team player", "self-motivated", "writing skills", "proactive"], "languages_combined": []}, "experience_required": {"duration": ["8 years", "minimum of 12 years"], "field": ["managerial", "relevant experience"]}}, {"job_id": "100003009048376", "location_code": "hk", "company": "CR Construction Company Limited", "job_title": "HR Assistant", "description": "Job Responsibilities:\n\nAssist with day-to-day operations of the HR functions and duties\nMaintain/update employee records by using the company HRIS system\nAssist in\u00a0conducting new staff orientation\nAssist with leave management, on and off boarding operations, company events, meetings etc.\nProvide administrative support to HR Department\nPerform other assigned duties and ad hoc projects\n\nJob Requirement:\n\nBachelor Degree/ Higher Diploma holder\nProficiency in MS Office\nGood command in both spoken and written English and Chinese\nGood team player with a positive attitude and eager to learn and grow\nSelf-motivated with strong sense of responsibility\nHighly organized and detail-oriented\n\n\nWe offer attractive salary, medical plan and fringe benefits. Interested parties please click \"Apply Now\" or apply via our web site.\n\n(Data collected would be used for recruitment purpose only)", "employment_types": ["Full Time"], "selling_points": ["Double Pay", "Discretionary Bonus", "Medical Scheme"], "locations": ["Lai Chi Kok"], "categories": ["Admin & HR", "Administration / Operation Manager"], "post_time": "2022-01-14T06:26:45Z", "salary": {"currency": null, "max": null, "min": null, "period": "monthly", "term": null}, "salary_visible": false, "title_keywords": ["hr assistant"], "responsibilities": ["management", "operations", "hr", "day-to-day operations", "maintain", "ad hoc projects", "provide administrative support"], "requirements": {"degrees": ["degree", "bachelor", "higher diploma holder"], "majors": [], "languages": ["english", "chinese"], "language_level": ["good command"], "hard_skills": ["ms office"], "soft_skills": ["organized", "good team player", "self-motivated", "sense of responsibility", "detail-oriented", "positive attitude", "eager to learn"], "languages_combined": [{"language": "english", "language_level": ["good command"]}, {"language": "chinese", "language_level": ["good command"]}]}, "experience_required": {"duration": [], "field": []}}, {"job_id": "100003009046007", "location_code": "hk", "company": "Larus Limited", "job_title": "Operation Manager", "description": "We are looking for agile and fast-learning people to join us!\n\nResponsibilities:\n\nLead and responsible for the full spectrum of HR & Admin functions.\nDevelop, implement, and review administration policies and procedures.\nManage HR functions including probation, performance appraisal process, staff movement and termination and exit process.\nResponsible for all company administrative / procurement functions including office services and supplies, insurance, repair and maintenance, leasing and tenancy renewal, etc.\nPlan, execute & organize company activities such as Annual Dinner, etc.\nOther ad-hoc works as required.\nRequirements:\n\n\nDegree holder in related disciplines.\nMinimum 3 years\u2019 solid experiences in HR and Administration management.\nGood communications in both Chinese and English speaking & writing skills.\nAggressive and hardworking, able to work independently and take up challenge.\nImmediately Available is preferred\n\nRemarks\n\nFor application, please send your CV with your current and expected salary to us.\u00a0", "employment_types": ["Full Time", "Permanent"], "selling_points": ["Min 3 years\u2019 full spectrum HR & Admin. Experience", "Good in English and Chinese", "Immediately available preferable"], "locations": ["Tsuen Wan Area"], "categories": ["Admin & HR", "Administration / Operation Manager", "Personal / Executive Assistant", "HR Supporting Staff"], "post_time": "2022-01-13T09:26:08Z", "salary": {"currency": null, "max": null, "min": null, "period": "monthly", "term": null}, "salary_visible": false, "title_keywords": ["operation manager"], "responsibilities": ["ad-hoc", "maintenance", "policies", "hr", "review", "procedures", "develop", "repair", "plan", "insurance", "administration"], "requirements": {"degrees": ["degree holder"], "majors": ["related disciplines"], "languages": ["english", "chinese"], "language_level": ["good"], "hard_skills": ["writing skills"], "soft_skills": ["work independently", "hardworking", "writing skills"], "languages_combined": [{"language": "english", "language_level": ["good"]}, {"language": "chinese", "language_level": ["good"]}]}, "experience_required": {"duration": ["minimum 3 years"], "field": ["hr", "management", "administration"]}}, {"job_id": "100003009049023", "location_code": "hk", "company": "-", "job_title": "Manager/Senior Manager, Performance & Rewards", "description": "Job Responsibilities\nDevelop and implement salary administration and employee performance appraisal programs\nDesign and administer benefits programs such as provident fund program, medical insurance program and etc.\nParticipate in selected salary survey and conduct research regarding development in compensation and benefit programs\nInvolve in monthly payroll and benefits calculations\nPrepare various human resources analysis reports\nAssume other HR duties as needed\nJob Requirements\nUniversity Degree\nMinimum 6 years in human resources management\nGood knowledge of human resources practices, performance appraisal procedures and employment legislation\nExperience in payroll administration and salary and benefits procedures\nAbility to work independently and under pressure\nGood MS Office skills\nGood command of Chinese and English\n\n-\n\n-", "employment_types": ["Permanent"], "selling_points": [], "locations": ["Central"], "categories": ["Admin & HR", "Administration / Operation Manager", "Compensation & Benefits"], "post_time": "2022-01-14T07:56:03Z", "salary": {"currency": null, "max": null, "min": null, "period": "monthly", "term": null}, "salary_visible": false, "title_keywords": ["senior manager", "manager"], "responsibilities": ["administration", "develop"], "requirements": {"degrees": [], "majors": [], "languages": [], "language_level": [], "hard_skills": [], "soft_skills": [], "languages_combined": []}, "experience_required": {"duration": [], "field": []}}, {"job_id": "100003009038066", "location_code": "hk", "company": "The Hong Kong Jockey Club", "job_title": "Senior Administrative Officer", "description": "The Corporate Programme Management Office (\u201cCPMO\u201d) serves as the centralised Project Management Office for the Club's Strategic Programmes (SP). Principal responsibilities are to ensure that Scope, Schedule, Cost and Risk are monitored for the SP's as well as reported to various Governance bodies.\n\nThe Senior Administrative Officer (\"SAO\") will report to the Executive Manager, Technical Services & Project Risk Management (\"EMTS&PRM\") and will be responsible for working with different CPMO colleagues to provide administrative & logistic support, coordination and organisation of workshops and project related meetings, assist in the preparation of project related documents and perform office administrative tasks.\n\n\n\nThe Job\nYou will:\n\n\n\u00a0\u00a0\u00a0\u00a0\u00a0\u00a0\u00a0\u00a0 Provide administrative and logistics support including preparing correspondence, handling business claims, travel arrangement and incoming mails, as well as calendar and meeting management\n\u00a0\u00a0\u00a0\u00a0\u00a0\u00a0\u00a0\u00a0 Coordinate and support workshops and project related meetings. Prepare meeting presentation materials, agenda, minutes and action logs\n\u00a0\u00a0\u00a0\u00a0\u00a0\u00a0\u00a0\u00a0 Develop flowchart, detailed document log, maintain and control systematic filing system\n\u00a0\u00a0\u00a0\u00a0\u00a0\u00a0\u00a0\u00a0 Prepare regular reports as needed\n\u00a0\u00a0\u00a0\u00a0\u00a0\u00a0\u00a0\u00a0 Perform office administrative tasks and assist in ad hoc assignment\n\n\n\nAbout You\nYou should have:\n\n\n\u00a0\u00a0\u00a0\u00a0\u00a0\u00a0\u00a0\u00a0 University Degree qualification\n\u00a0\u00a0\u00a0\u00a0\u00a0\u00a0\u00a0\u00a0 At least 5-10 years of project management and administrative experience\n\u00a0\u00a0\u00a0\u00a0\u00a0\u00a0\u00a0\u00a0 Experience in supporting senior management / executives in sizable organization\n\u00a0\u00a0\u00a0\u00a0\u00a0\u00a0\u00a0\u00a0 Good presentation and interpersonal skills, mature and resourceful, quick in response and action with high accuracy\n\u00a0\u00a0\u00a0\u00a0\u00a0\u00a0\u00a0\u00a0 Strong organizational skills\n\u00a0\u00a0\u00a0\u00a0\u00a0\u00a0\u00a0\u00a0 Fluency in written and spoken English, Cantonese and Putonghua\n\u00a0\u00a0\u00a0\u00a0\u00a0\u00a0\u00a0\u00a0 Proficiency in MS Office (Word, Excel, PowerPoint, Visio)\n\u00a0\u00a0\u00a0\u00a0\u00a0\u00a0\u00a0\u00a0 Multi-media presentation tools and Chinese word processing, etc.\n\n\n\nTerms of employment\nThe level of appointment will be commensurate with qualifications and experience.\n\nHow to Apply\nPlease send your resume, complete with expected salary and job reference by clicking the Apply Now button\u00a0\n\n\nWe are an equal opportunity employer. Personal data provided by job applicants will be used strictly in accordance with the Club's notice to employees and prospective employees relating to the Personal Data (Privacy) Ordinance. A copy of which will be provided immediately upon request.\n\n\n\n", "employment_types": ["Full Time"], "selling_points": ["Experience in supporting senior management", "Strong organizational skills", "Provide administrative and logistics support"], "locations": ["Shatin Area"], "categories": ["Admin & HR", "Administration / Operation Manager", "Others", "Others", "Others"], "post_time": "2022-01-11T04:52:11Z", "salary": {"currency": null, "max": null, "min": null, "period": null, "term": null}, "salary_visible": false, "title_keywords": ["senior administrative officer"], "responsibilities": ["maintain", "personal data", "senior management", "control", "ad hoc assignment", "develop", "logistics", "schedule", "reports", "report", "management", "cost", "related documents", "logistic support", "administrative tasks", "coordinate", "project management", "coordination", "travel arrangement"], "requirements": {"degrees": ["university degree"], "majors": [], "languages": ["cantonese", "putonghua", "english", "chinese"], "language_level": ["fluency"], "hard_skills": ["excel", "chinese word processing", "word", "powerpoint", "project management", "workshops", "ms office"], "soft_skills": ["organizational skills", "responsible", "resourceful", "systematic", "mature", "project management", "interpersonal skills", "coordination", "organisation", "presentation", "detailed"], "languages_combined": [{"language": "cantonese", "language_level": ["fluency"]}, {"language": "putonghua", "language_level": ["fluency"]}, {"language": "english", "language_level": ["fluency"]}, {"language": "chinese", "language_level": []}]}, "experience_required": {"duration": ["at least 5-10 years"], "field": ["sizable organization", "project management", "management", "administrative"]}}, {"job_id": "100003009042970", "location_code": "hk", "company": "The Hong Kong University of Science and Technology", "job_title": "Manager (Job ID: 7048)", "description": "Job Title:\u00a0 \u00a0 \u00a0 \u00a0 \u00a0 \u00a0 Manager\nDepartment:\u00a0 \u00a0 \u00a0 \u00a0Research Office\nJob ID:\u00a0 \u00a0 \u00a0 \u00a0 \u00a0 \u00a0 \u00a0 \u00a0\u00a07048\n\nJob Posting Details\n\nThe appointee will be responsible for managing a wide range of research funding schemes and programs.\u00a0 Apart from the daily administration work involved such as proposal review; liaison with sponsors; and submission handling and monitoring, the appointee is also expected to be a meticulous, dynamic and self-motivated executive to coordinate various activities and interfaces between sponsors and internal staff.\u00a0 He/She has to provide executive support to task forces/committees and work closely with relevant offices in developing/enhancing research-related systems; supervise staff in execution of work; undertake research analytics; and take up ad-hoc projects as assigned.\u00a0 Preference will be given to those who have experience in handling research grants and the related matters.\n\nApplicants should have a bachelor\u2019s degree with at least 7 years of post-qualification experience, preferably in research administration and grant management in tertiary institution setting.\u00a0 The preferred attributes of the candidate are: (i) good coordination, organization and communication skills; (ii) a strong sense of responsibility and self-motivated; (iii) meticulous, detail-minded and multi tasks oriented; (iv) able to work independently in a dynamic working environment; (v) a good command of spoken and written English and Chinese; (vi) a good team leader with strong presentation skills.\u00a0 Shortlisted candidates will be invited for a written test. (Duration: 2 years, renewable)\n\nStarting salary will be commensurate with qualifications and experience.\u00a0 Fringe benefits including annual leave, medical and dental benefits will be provided.\u00a0 A gratuity will be payable upon successful completion of contract.\n\nApplication Procedure\nIn support of a green work environment, we accept applications submitted online only.\u00a0 To apply, please complete an online application form through the HKUST Careers website (https://hkustcareers.ust.hk) and return it online to the Human Resources Office on or before Tuesday, 25 January 2022.\u00a0 Applicants will receive an acknowledgement by email upon successful submission.\u00a0 We thank applicants for their interest, but advise that only shortlisted candidates will be notified of the result of the application.\n\n(Information provided by applicants will be used for recruitment and other employment-related purposes only.)\n\nHKUST is an equal opportunities employer and is committed to our core values of\ninclusiveness, diversity, and respect.", "employment_types": ["Full Time"], "selling_points": ["provide executive support to task forces/committee", "work closely with relevant offices", "supervise staff in execution of work"], "locations": ["Sai Kung"], "categories": ["Admin & HR", "Administration / Operation Manager", "Education", "Others"], "post_time": "2022-01-12T09:21:39Z", "salary": {"currency": null, "max": null, "min": null, "period": "monthly", "term": null}, "salary_visible": false, "title_keywords": ["manager"], "responsibilities": ["management", "monitoring", "review", "executive support", "developing", "systems", "coordinate", "communication", "coordination", "ad-hoc projects", "administration"], "requirements": {"degrees": ["degree", "bachelor"], "majors": [], "languages": ["english", "chinese"], "language_level": ["good command"], "hard_skills": ["id", "dynamic"], "soft_skills": ["detail-minded", "meticulous", "self-motivated", "communication skills", "work independently", "responsible", "sense of responsibility", "presentation skills", "dynamic", "coordination", "good team leader"], "languages_combined": [{"language": "english", "language_level": ["good command"]}, {"language": "chinese", "language_level": ["good command"]}]}, "experience_required": {"duration": ["at least 7 years"], "field": ["management", "research", "post-qualification", "related", "administration"]}}, {"job_id": "100003009048032", "location_code": "hk", "company": "The Hong Kong Exporters' Association", "job_title": "Admin Officer", "description": "Execute seminar, trade visits, etc. with the vendors/agencies/related parties.\nProvide clerical and logistic support for all project deliverables\nAnswering enquires and consolidate applicants\u2019 information and product collection procedures with vendors\nAsst. the team on marketing material preparation and administration duties.\nTravel to Mainland for event and exhibition operation\nPerform ad-hoc duties as assigned\nRequirements:\n\nUniversity degree holder or above in Communications / Administration or related fields.\nOver 5 years in administration experiences, in event management/marketing field will be an advantage\nGood coordination and communications, self-motivated and interpersonal skills\nCan work independently with can-do spirit\nGood PC Knowledge and proficiency in Microsoft Office\nWell-versed in both spoken and written English and Chinese (Cantonese and Putonghua)\nimmediately available is highly preferred\nInterested parties may send in your application together with a detailed resume stating your academic results, present & expected salaries, date of availability and the post title by email via clicking \"Apply Now\".\n(All information provided will be treated in strict confidence and used solely for recruitment purposes)", "employment_types": ["Full Time", "Contract"], "selling_points": [], "locations": ["Tsim Sha Tsui"], "categories": ["Accounting", "Finance / Accounting Manager", "Admin & HR", "Administration / Operation Manager"], "post_time": "2022-01-14T04:33:26Z", "salary": {"currency": null, "max": null, "min": null, "period": "monthly", "term": null}, "salary_visible": false, "title_keywords": ["officer", "admin"], "responsibilities": ["management", "project deliverables", "procedures", "logistic support", "coordination", "ad-hoc duties", "marketing material", "administration"], "requirements": {"degrees": ["university degree"], "majors": ["communications"], "languages": ["cantonese", "putonghua", "english", "chinese"], "language_level": [], "hard_skills": ["pc knowledge", "microsoft office"], "soft_skills": ["self-motivated", "work independently", "interpersonal skills", "coordination", "ad-hoc duties", "can-do"], "languages_combined": [{"language": "cantonese", "language_level": []}, {"language": "putonghua", "language_level": []}, {"language": "english", "language_level": []}, {"language": "chinese", "language_level": []}]}, "experience_required": {"duration": ["5 years"], "field": ["management", "marketing", "administration"]}}, {"job_id": "100003009038498", "location_code": "hk", "company": "HKR International Ltd", "job_title": "Officer \u2013 Administration", "description": "The incumbent will be responsible to monitor routine operations of Discovery Bay Office Centre (DBOC) & Staff Quarters, and provide overall administrative support.\u00a0\n\nResponsibilities:\n\nMonitor routine operations of Discovery Bay Office Centre & 2 Staff Quarters\nAdminister DBOC Building Service System, office relocation, renovation in DBOC and Group Privilege Card System annually etc.\nReview and amend rules, policies and tenancy agreement\nSupervise sub-ordinates & service contracted staff (cleaning & security service)\nCo-ordinate with offices of other inter-companies on office services provision\nPrepare budget and forecast plans, issue of internal notices, memos and outgoing letters to government bodies eg. Water Department\nReady to take up special assignment from time to time\n\n\u00a0Requirements:\n\nDegree holder in Business Administration or related disciplines\nMinimum 4 years of experiences with 2 years or above supervisory experience, preferably gained from sizeable companies;\nCandidate who has lower qualification but with more years of experience will also be considered\n\nWorking location: Discovery Bay\n\nWe offer 5-day work and competitive remuneration package including annual leave, discretionary bonus, dental and medical coverage and Top-up MPF. Appointment and salary will be commensurate with qualifications and experience.\n\nApplication Methods:\n\nOnline application \u2013 Visit our website http://www.hkri.com (Career Opportunities) to complete the online application form;\nEmail \u2013 Send your detailed resume and expected salary by clicking \"Apply Now\";\nWhatsApp \u2013 6845 7015;\nFax \u2013 2987 9665\n\nApplicants not invited for interview within two months may consider their applications unsuccessful. All information will be used solely for recruitment purpose and will be destroyed when the recruitment process is finished. Personal data provided by job applicants will be used strictly in accordance with the employer\u2019s personal data policies, a copy of which will be provided upon request.", "employment_types": ["Full Time", "Permanent"], "selling_points": ["Provide overall administrative support", "Min. 4 years of experiences", "Free transportation to Discovery Bay"], "locations": ["Lantau Island"], "categories": ["Admin & HR", "Administration / Operation Manager", "Clerical / Admin Staff"], "post_time": "2022-01-11T07:07:20Z", "salary": {"currency": null, "max": null, "min": null, "period": null, "term": null}, "salary_visible": false, "title_keywords": ["officer"], "responsibilities": ["co-ordinate with", "operations", "policies", "review", "renovation", "monitor", "budget", "letters", "forecast", "cleaning", "plans"], "requirements": {"degrees": ["degree holder"], "majors": ["related disciplines", "business administration"], "languages": [], "language_level": [], "hard_skills": [], "soft_skills": [], "languages_combined": []}, "experience_required": {"duration": ["minimum 4 years", "2 years"], "field": ["supervisory experience"]}}, {"job_id": "100003009047655", "location_code": "hk", "company": "Hong Kong Council for Accreditation of Academic and Vocational Qualifications", "job_title": "Assistant Registrar  [Ref: 2022/01/15/J]", "description": "Responsibilities\n\nThe appointee will be involved in accreditation and assessment exercises in vocational area, and conduct projects related to quality assurance of education and training programmes. Major duties may include conducting accreditation and assessment exercises; assisting in relevant research and consultancy work, liaison with institutions, government bureaux, and professional bodies; supporting the development of guidelines and procedures, and other internal and external development activities; and management of databases.\n\n\nRequirements\n\nApplicants should hold a first degree comparable to HKQF Level 5, preferably with a post-graduate qualification at HKQF Level 6 or above, with at least 5 years of post-qualification relevant work experience, preferably in education, training or quality assurance.\u00a0 We are looking for an individual who has a good understanding of the education system in Hong Kong; good analytical, project management, presentation, interpersonal and communication skills; and excellent written and spoken English and Chinese, including Putonghua.\u00a0 Being proactive, reflective, independent as well as a team player is essential. Possessing good ICT knowledge, understanding of international qualification standards and exposure to accreditation/quality assurance work in the vocational sector would be an advantage.\n\n\nConditions of Service and Application Procedures\n\nInitial appointment will normally be made on a two-year contract subject to renewal.\u00a0 We offer competitive salary commensurate with qualifications and experience, contract-end gratuity, plus fringe benefits including annual leave, medical and dental benefits.\u00a0\n\nApplicants are invited to apply by letter including a short narrative on how you can add value to HKCAAVQ together with your CV, and stating present and expected salary.\u00a0 Please send your application quoting the relevant reference number to the Assistant Executive Manager (Human Resources) either by Apply Now\u00a0or by post to HKCAAVQ, 10 Siu Sai Wan Road, Chai Wan, Hong Kong no later than 28 January 2022.\n\nPersonal data collected will be treated in the strictest confidence and only be used for recruitment purposes.\n\nFor more information on HKCAAVQ, please visit www.hkcaavq.edu.hk.", "employment_types": ["Full Time", "Contract"], "selling_points": [], "locations": ["Siu Sai Wan"], "categories": ["Admin & HR", "Administration / Operation Manager", "Education", "Tutor / Instructor", "Others"], "post_time": "2022-01-14T03:39:55Z", "salary": {"currency": null, "max": null, "min": null, "period": "monthly", "term": null}, "salary_visible": false, "title_keywords": ["assistant"], "responsibilities": ["management", "guidelines", "quality", "procedures", "databases"], "requirements": {"degrees": ["degree"], "majors": [], "languages": ["putonghua", "english", "chinese"], "language_level": ["excellent"], "hard_skills": ["no", "project management", "plus", "wan"], "soft_skills": ["communication skills", "confidence", "independent", "presentation", "project management", "team player", "proactive", "interpersonal"], "languages_combined": [{"language": "putonghua", "language_level": ["excellent"]}, {"language": "english", "language_level": ["excellent"]}, {"language": "chinese", "language_level": ["excellent"]}]}, "experience_required": {"duration": ["at least 5 years"], "field": ["post-qualification", "training", "education", "medical", "quality assurance"]}}, {"job_id": "100003009043986", "location_code": "hk", "company": "Academic Asia UK Limited", "job_title": "Secretary", "description": "Responsibilities:\n\nProvide administrative and operational supports to office operation\n\n\u00a0Requirements:\n\nDegree any discipline with 3-5 years\u2019 secretarial experience\nGraduate from the UK with boarding school and university is much desirable\nGood communication and interpersonal skills\nMature, detail-minded and responsible\nQuick learner, patient and able to work under pressure\nProficient in Microsoft Office such as Outlook, Teams, Word, Excel, PowerPoint, Online platform such as Zoom and familiar with database system operation will be most desirable\nGood spoken and written English and Chinese, including Mandarin\nImmediate available is highly preferred\u00a0\u00a0\n\nWhat we offer:\n\nAn attractive remuneration package with basic salary, bonus and comprehensive medical insurance will be offered to the successful candidate.\u00a0 Please\u00a0state\u00a0expected salary in\u00a0the c.v.\n\nWe are an Equal Opportunities employer and welcome applications from any member of the community\u00a0meeting the selection criteria for the position. Personal data provided by job applicants will be kept strictly confidential and will be used solely for recruitment purposes.", "employment_types": ["Full Time", "Permanent"], "selling_points": ["Degree in any discipline", "3 years\u2019 working experience", "5-day work, attractive remuneration package"], "locations": ["Causeway Bay"], "categories": ["Admin & HR", "Administration / Operation Manager", "Secretary", "Education", "Others"], "post_time": "2022-01-13T02:41:27Z", "salary": {"currency": null, "max": null, "min": null, "period": "monthly", "term": null}, "salary_visible": false, "title_keywords": ["secretary"], "responsibilities": [], "requirements": {"degrees": ["degree"], "majors": [], "languages": ["english", "chinese", "mandarin"], "language_level": ["good"], "hard_skills": ["excel", "microsoft office", "word", "powerpoint", "outlook"], "soft_skills": ["detail-minded", "responsible", "quick learner", "mature", "communication and interpersonal skills", "patient", "work under pressure"], "languages_combined": [{"language": "english", "language_level": ["good"]}, {"language": "chinese", "language_level": ["good"]}, {"language": "mandarin", "language_level": ["good"]}]}, "experience_required": {"duration": ["3-5 years"], "field": ["secretarial"]}}, {"job_id": "100003009040350", "location_code": "hk", "company": "Gravitas Recruitment Group (Hong Kong) Limited", "job_title": "Administration and Facilities Assistant", "description": "The Role\n\nEnsure the smooth running of the Hong Kong office and wider business by managing a variety of administrative tasks. Providing an efficient and effective office support service and acting as first point of contact for all office queries.\n\nMain Responsibilities\u00a0\n\nFacilities\n\u2022 Managing basic IT Support for the Hong Kong office, ensuring users are provided with assistance on telephone systems, computers and printers and liaising with external IT Support team as required\n\u2022 Working with the HR Team to ensure that effective and appropriate Health and Safety policies and procedures are in place which meet legal requirements, best practice and organisational objectives, in line with company requirement\n\u2022 Working with the HR and Systems team to prepare desk spaces for new starters and leavers.\n\u2022 Completing a weekly audit within the office to ensure that office facilities and equipment are maintained\n\u2022 Managing office expenditure to ensure best rates for all products and services, as well as overseeing petty cash for the office\n\u2022 Maintaining and developing relationships with building management, security and cleaning company and ensuring service level agreements are met\n\u2022 Driving existing office management processes, priorities, effectiveness and efficiencies; identifying opportunities for continuous improvement.\n\nAdministration\n\u2022 Supporting the Management Team with the planning, organisation and management of events across the business to include but not limited to networking events, charity events, recruitment fairs, incentive trips, office sales days, lunch clubs and team building events\n\u2022 Undertake one-off projects and research as the needs of the business dictates\n\u2022 Assisting with general reception duties, including meeting and greeting all visitors, diverting calls accordingly and taking accurate messages and collecting and distributing office post, where required\n\u2022 Assisting with printing and distributing documentation including the billing leagues, training material, marketing material and internal documentation, where required\n\u2022 Assisting the Finance Team.\u00a0\n\nCustomer Care and Compliance\n\u2022 Supporting the Customer Care and Compliance team in managing the contractor onboarding process.\n\u2022 Maintaining relationships with contractors & ensuring the contract extension process is managed effectively and contract paperwork is prepared and issued in a timely manner\n\u2022 Liaising directly with clients and candidate to resolve any queries in a timely manner and ensure their experience with Gravitas is a positive one\n\u2022 Supporting the Customer Care and Compliance team in running contractor payroll, including making reminder calls to candidates/clients, processing of manual timesheets and raising of invoices.\n\nAbout You\n\n\u2022 Bachelor\u2019s degree or above\n\u2022 Strong interpersonal skills with good business acumen.\n\u2022 Driven and motivated individual who can embrace challenges with a positive mindset and celebrate success.\n\u2022 Fluent English and Cantonese (Native English speaker has advantage)\n\n\n\nCompetencies\n\n\u2022\u00a0Effective Communications\n\u2022 Drive to Deliver\n\u2022 Collaborative Working\n\u2022 Role Model\n\u2022 Customer Focused Service Excellence\n\u2022 Planning, Monitoring and Analysing\n", "employment_types": ["Full Time", "Permanent"], "selling_points": ["Competitive Base Salary", "Good Company Wide Incentives/ Bonus", "Exposure Working with Singapore and UK Office"], "locations": ["Quarry Bay"], "categories": ["Admin & HR", "Administration / Operation Manager", "Clerical / Admin Staff", "Compensation & Benefits"], "post_time": "2022-01-12T02:23:21Z", "salary": {"currency": null, "max": null, "min": null, "period": "monthly", "term": null}, "salary_visible": false, "title_keywords": ["assistant"], "responsibilities": ["audit", "building management", "administration", "management team", "invoices", "maintaining", "compliance", "liaising with", "office support", "developing", "finance team", "marketing material", "management", "monitoring", "procedures", "contact", "cleaning", "documentation", "administrative tasks", "payroll", "policies", "hr", "systems", "a timely manner", "recruitment", "planning"], "requirements": {"degrees": ["degree or above", "bachelor"], "majors": [], "languages": ["cantonese", "english"], "language_level": ["native", "fluent", "advantage"], "hard_skills": ["printers", "basic", "acumen", "documentation", "processing", "charity"], "soft_skills": ["efficient", "focused", "positive mindset", "timely", "collaborative", "motivated individual", "interpersonal skills", "organisation", "smooth", "business acumen", "accurate", "driven", "positive"], "languages_combined": [{"language": "cantonese", "language_level": ["native", "fluent", "advantage"]}, {"language": "english", "language_level": ["native", "fluent", "advantage"]}]}, "experience_required": {"duration": [], "field": []}}, {"job_id": "100003009039719", "location_code": "hk", "company": "The English Schools Foundation", "job_title": "Assistant - Administration - Renaissance College", "description": "RCHK is seeking to appoint an enthusiastic candidate for the post of Assistant - Administration at RCHK.\nJob Description\nThe roles and responsibilities will include, but not necessarily be limited to:\nProvide office management and administrative support to school, teachers and heads of department\nAssist in purchasing activity, sourcing, making arrangement with suppliers and placing order, and perform yearly stock take.\nHelp with school events, exhibitions and displays hold by the departments such as Swim Gala, Design Day and IB VA DP exhibition\nAssist with field trips process and forms, i.e. field trip outing with students, money collection for teachers\nPerform general office duties and clerical works including photocopying, printing, scanning & binding\nAssist in ad hoc projects when required\nRequirements\nSound organisational and administrative skills.\nMinimum 1-2 years of relevant working experience\nThe ability to manage diverse and complex tasks independently and to show initiative.\nHigh initiative, self-starter and self-motivated team player with strong analytical and problem solving skills\nFluency in oral and written English and Chinese\nExperience of working in school would be desirable\nApplicants must be a permanent Hong Kong resident or possess a valid visa to work in Hong Kong.\nApplications will be reviewed on a rolling basis and offers may be extended prior to the job closing date.\nBy applying for this position, your application may be considered for other opportunities within ESF.\nESF is an Equal Opportunities Employer\nPersonal data provided by job applicants will be used strictly in accordance with the ESF's Personal Data Policy, a copy of which will be provided upon request.\nAligned with the recommendations of the International Task Force on Child Protection, we hold ourselves to a high standard of effective recruiting practices with specific attention to child protection.\nsupportstaff\nsupportstaffnt", "employment_types": ["Full Time", "Permanent"], "selling_points": ["Assist in ad hoc projects when required", "Sound organisational and administrative skills", "Minimum 1-2 years of relevant working experience"], "locations": ["Not Specified"], "categories": ["Admin & HR", "Administration / Operation Manager", "Clerical / Admin Staff", "Others"], "post_time": "2022-01-11T10:40:34Z", "salary": {"currency": null, "max": null, "min": null, "period": "monthly", "term": null}, "salary_visible": false, "title_keywords": ["assistant"], "responsibilities": ["scanning", "management", "administrative support", "school events", "design", "stock take", "ad hoc projects"], "requirements": {"degrees": [], "majors": [], "languages": ["english", "chinese"], "language_level": ["fluency"], "hard_skills": ["problem solving skills"], "soft_skills": ["self-motivated", "independently", "oral", "diverse", "analytical and problem solving skills", "team player", "initiative"], "languages_combined": [{"language": "english", "language_level": ["fluency"]}, {"language": "chinese", "language_level": ["fluency"]}]}, "experience_required": {"duration": ["minimum 1-2 years"], "field": ["relevant working experience"]}}]