[{"job_id": "100003009054118", "location_code": "hk", "company": "SD Electronic Materials (Hong Kong) Limited", "job_title": "\u5408\u7d04\u6587\u54e1 (3\u500b\u6708)", "description": "\u8077\u8cac\n\n\n\u4e00\u822c\u6587\u66f8\u5de5\u4f5c\n\u6587\u4ef6\u5b58\u6a94\u53ca\u8655\u7406\n\u8cc7\u6599\u8f38\u5165\n\u5354\u52a9\u90e8\u9580\u65e5\u5e38\u904b\u4f5c\n\n\u8655\u7406\u76f4\u5c6c\u4e3b\u7ba1\u6216\u90e8\u9580\u7d93\u7406\u59d4\u6d3e\u7684\u5de5\u4f5c\n\n\u5165\u8077\u8981\u6c42\n\n\u4e2d\u4e94\u6216\u4ee5\u4e0a\u7a0b\u5ea6\n1\u5e74\u4ee5\u4e0a\u76f8\u95dc\u5de5\u4f5c\u7d93\u9a57\n\n\u719f\u8b58\u96fb\u8166\u64cd\u4f5c\u53ca\u904b\u7528\u4e00\u822c\u96fb\u8166\u8edf\u4ef6\uff0c\u5305\u62ec\uff1aMicrosoft Word\u3001Microsoft Excel\u53ca\u4e2d\u82f1\u6587\u6587\u66f8\u8655\uf9e4\u7b49\n\n\u5177\u826f\u597d\u6e9d\u901a\u6280\u5de7\u3001\u5de5\u4f5c\u4e3b\u52d5\u3001\u8655\u4e8b\u7d30\u5fc3\u53ca\u8cac\u4efb\u5fc3\n\u5177\u76f8\u95dc\u5de5\u4f5c\u7d93\u9a57\u8005\u512a\u5148\u8003\u616e", "employment_types": ["Part Time"], "selling_points": ["\u4e2d\u4e94\u6216\u4ee5\u4e0a\u7a0b\u5ea6", "1\u5e74\u4ee5\u4e0a\u76f8\u95dc\u5de5\u4f5c\u7d93\u9a57", "\u5408\u7d04\u6587\u54e1 (3\u500b\u6708)"], "locations": ["Tai Po Area"], "categories": ["Admin & HR", "Clerical / Admin Staff"], "post_time": "2022-01-17T08:28:23Z", "salary": {"currency": null, "max": null, "min": null, "period": "monthly", "term": null}, "salary_visible": false, "title_keywords": [], "responsibilities": [], "requirements": {"degrees": [], "majors": [], "languages": [], "language_level": [], "hard_skills": [], "soft_skills": [], "languages_combined": []}, "experience_required": {"duration": [], "field": []}}, {"job_id": "100003009052345", "location_code": "hk", "company": "Be Priceless Limited", "job_title": "Office Administration Officer", "description": "Job Responsibilities\n\nDevelop brand and marketing strategy for the core medical brand(s) and drive the implementation to enhance brand equity and increase market penetration;\nBuild relationship with medical professionals for brand growth opportunities, including awareness building, lead generation and partnership liaison;\nEstablish partnerships with local and global patient peer groups for brand growth opportunities, including patient community engagement;\nPlan and manage B2B and B2C events, including participating or, if necessary, organizing conference, seminars, webinars;\nDevelop master sales & marketing communication assets and ensure proper adaptation and usage of the materials;\nWork closely with media (esp. news outlets) and agencies for media plan development and execution, including social media, SEM, display ad, PR (including interviews and advertorials);\nLead content development for website and social platforms;\nDevelop CRM plan and enhance the existing membership loyalty program;\nPartner with sales team to gain market insights and sharpen sales conversion tactics;\nLiaise with universities for both regular marketing activities and long-term strategic partnership.\n\nRequirements\n\nBachelor\u2019s Degree in Science or Business; Pharmacy or Medical related discipline is a plus;\n3 years of marketing experience in pharmaceutical industry; particularly in ethical channel is a plus;\nFluent in spoken and written English and Chinese;\nOpen-minded attitude and creativity to bring in new initiatives;\nStrong branding mindset and strategic thinking for long-term brand development;\nStrong desire to learn and ability to multi-task;\nGood communication and interpersonal skills;\nProficient in Microsoft Office (Excel, PowerPoint, Outlook).\n\nWorking Location: Hong Kong Science Park, Tai Po, N.T.\n\nWe offer 5-day working week and an attractive remuneration package. Interested party please submit your resume with current and expected salary by clicking \u201cAPPLY NOW\u201d. For company details, please visit\u00a0www.purapharm.com.\n\nOur company is an equal opportunity employer. All personal data collected will be used for recruitment purpose only, while the personal data of the unsuccessful applicants will be destroyed within 6 months after the recruitment process.", "employment_types": ["Full Time"], "selling_points": ["Great work place", "Learn along side professionals", "Competitive salary"], "locations": ["Central"], "categories": ["Admin & HR", "Clerical / Admin Staff", "Public / Civil", "Social Services - Community / Non-profit Organization", "Management", "Management Trainee"], "post_time": "2022-01-17T02:48:44Z", "salary": {"currency": null, "max": null, "min": null, "period": "monthly", "term": null}, "salary_visible": false, "title_keywords": ["administration officer"], "responsibilities": ["social media", "implementation", "website", "develop", "communication", "sales team", "plan", "sem", "liaise with"], "requirements": {"degrees": ["degree", "bachelor"], "majors": ["science", "business"], "languages": ["english", "chinese"], "language_level": ["fluent"], "hard_skills": ["excel", "plus", "microsoft office", "powerpoint", "outlook"], "soft_skills": ["multi-task", "strategic thinking", "open-minded", "communication and interpersonal skills", "ethical"], "languages_combined": [{"language": "english", "language_level": ["fluent"]}, {"language": "chinese", "language_level": ["fluent"]}]}, "experience_required": {"duration": ["3 years"], "field": ["pharmaceutical", "marketing"]}}, {"job_id": "100003009054550", "location_code": "hk", "company": "Tsit Wing Coffee Co Ltd", "job_title": "Administrative Assistant", "description": "Job Responsibilities\n\nDevelop and implement sales strategy to drive business growth;\nPromote medical brand(s) to potential clients in Ethical Sectors;\nBuild strong network and maintain good relationship with medical professionals and key opinion leaders within the community for lead generation;\nCollaborate with customers to create win-win relationship for both parties\u2019 business growth;\nEnsure timely and effective implementation of sales and marketing strategies to achieve sales target;\nActively share market insights and collaborate with Brand team to sharpen sales conversion tactics;\nMaintain effective communication and good working relations with teammates, Brand team and other related departments to ensure smooth operation;\nProvide support for medical conference and seminars and seek for lead generation opportunities;\nWork independently with well-planned work schedules and weekly timetables.\n\nRequirements\n\nBachelor\u2019s Degree in Pharmacy, Life Sciences, Pharmacology or related discipline;\n3-5 years of sales experience in pharmaceutical industry;\nFluent in spoken and written English and Chinese;\nGood communication, presentation, negotiation and interpersonal skills;\nDetail-orientated, self-motivated, good team player;\nEnergetic and open-minded;\nProficient in Microsoft Office (Excel, PowerPoint, Outlook);\nLess experienced candidate will be considered as Senior Medical Specialist.\n\nWorking Location: Hong Kong Science Park, Tai Po, N.T.\n\nWe offer 5-day working week and an attractive remuneration package. Interested party please submit your resume with current and expected salary by clicking \u201cAPPLY NOW\u201d. For company details, please visit\u00a0www.purapharm.com.\n\nOur company is an equal opportunity employer. All personal data collected will be used for recruitment purpose only, while the personal data of the unsuccessful applicants will be destroyed within 6 months after the recruitment process.", "employment_types": ["Full Time", "Permanent"], "selling_points": [], "locations": ["Kwai Fong"], "categories": ["Admin & HR", "Clerical / Admin Staff", "Receptionist", "Others"], "post_time": "2022-01-17T09:57:37Z", "salary": {"currency": null, "max": null, "min": null, "period": "monthly", "term": null}, "salary_visible": false, "title_keywords": ["administrative assistant"], "responsibilities": ["collaborate with", "provide support", "marketing strategies", "schedules", "sales target", "implementation", "maintain good relationship", "develop", "communication", "maintain"], "requirements": {"degrees": ["degree", "bachelor"], "majors": ["pharmacology"], "languages": ["english", "chinese"], "language_level": ["fluent"], "hard_skills": ["excel", "outlook", "powerpoint", "microsoft office"], "soft_skills": ["self-motivated", "good team player", "negotiation", "open-minded", "communication", "interpersonal skills", "energetic", "presentation"], "languages_combined": [{"language": "english", "language_level": ["fluent"]}, {"language": "chinese", "language_level": ["fluent"]}]}, "experience_required": {"duration": ["3-5 years"], "field": ["pharmaceutical"]}}, {"job_id": "100003009052087", "location_code": "hk", "company": "INSTA SPECIALILST CO.LTD", "job_title": "Administrative/Operations Assistant (Contract) \u884c\u653f\u6216\u71df\u904b\u52a9\u7406 (\u5408\u7d04\u5236)", "description": "Job Responsibilities:\n\nManage product portfolio with respect to price and cost, working with various department such as operations and sales to ensure profitability of the business unit\n\nProvide costing and pricing considerations for management team to make decisions on tenders and quotation\n\nConduct product cost review on a quarterly basis to analyse performance of different products across various market segments, including market share, price competitiveness, and value proposition against competitors\n\nSPC for all SKUs within the company on a regular or on a continuous real time basis. (at least monthly) SPC for Channel, SPC for BUs.\u00a0\n\nPerform analysis and simulations on varying pricing of different SKUs will have on the whole bottom line.\u00a0\u00a0\n\nMonitor the implementation of price change on a regular basis.\u00a0\n\nJob Qualifications:\nQualification include a\u00a0Diploma or above in Accounting/ Finance/ Mathematics/ Economics or related discipline\n\nAt least 1-2 year(s) of working experience\n\nPreferably 1-2 years working experience in products and services pricing for tenders\n\nCommercial/pricing experience in manpower intensive service industry\n\nAbility to read through tender/sales contract and building a pricing table for our sales team\n\nPossess good interpersonal, communication and presentation skill\n\nProficient in Microsoft Office applications\n\nAble to work in a fast paced environment and meticulous\n\nproficiency in Power BI is necessary\n\n*Fresh graduates are welcome", "employment_types": ["Full Time", "Contract"], "selling_points": [], "locations": ["Cheung Sha Wan"], "categories": ["Accounting", "Accounting Clerk / Supervisor", "Admin & HR", "Clerical / Admin Staff"], "post_time": "2022-01-17T02:03:58Z", "salary": {"currency": null, "max": null, "min": null, "period": "monthly", "term": null}, "salary_visible": false, "title_keywords": ["operations assistant"], "responsibilities": ["management team", "cost", "power bi", "operations", "analysis", "quotation", "review", "monitor", "implementation", "communication", "sales team", "tender", "analyse"], "requirements": {"degrees": ["diploma or above"], "majors": ["finance", "accounting", "economics", "mathematics"], "languages": [], "language_level": [], "hard_skills": ["presentation skill", "bi", "microsoft office", "analysis", "make"], "soft_skills": ["presentation skill", "meticulous", "communication", "work in a fast paced environment", "interpersonal"], "languages_combined": []}, "experience_required": {"duration": ["1-2 years"], "field": ["commercial", "service industry"]}}, {"job_id": "100003009052778", "location_code": "hk", "company": "PCC Asia Limited", "job_title": "Administrative Assistant", "description": "Job Responsibilities\n\nAssist in developing 360 digital marketing strategies, plan and drive implementation of digital marketing campaigns and digital ecosystem development to achieve business goals;\nWork with internal and external parties to build digital & data infrastructure and facilitate smooth digital transformation;\nDevelop and manage digital platforms, including website, eShop, social media, media advertising, KOL/influencer and other channels to drive multi-touch point consumer engagement;\nDevelop strategic social media plan and work with agencies to deliver quality content to audiences and enhance brand presence, acquire fans and achieve business targets;\nEnsure all digital communications are conveyed in a way that contributes to master brand image building and master campaign message delivery;\nPrepare insightful and actionable brief and collaborate closely with agencies to drive quality output to achieve defined business and marketing objectives;\nRegularly track and analyze digital performance, involving website, eShop (e.g. new customer acquisition, sales conversion), and provide cross-analysis of the results and insights for continuous improvement of digital marketing programs;\nDrive ecommerce business & CRM program, monitor and review daily operations, analyze consumer journey and keyword strategy to improve UIUX & SEO on the brand websites & eShops retention tactics for improvement;\nMonitor budgets & and campaign KPIs for ROI improvement;\nAssist in other marketing duties and handle ad hoc tasks as assigned.\n\nRequirements\n\nBachelor\u2019s Degree in Business, Marketing, Advertising, eCommerce or related disciplines;\n3 years of solid work experience in digital marketing;\nDigital-savvy and knowledgeable on the latest digital trends;\nStrong desire to learn and ability to multi-task;\nSelf-motivated, proactive and willing to take challenges;\nGood communication, presentation and interpersonal skills;\nStrong project management & organizational skills;\nLess experienced candidates may be considered as Senior Digital Marketing Executive.\n\nWorking Location: Hong Kong Science Park, Tai Po, N.T.\n\nWe offer 5-day working week and an attractive remuneration package. Interested party please submit your resume with current and expected salary by clicking \u201cAPPLY NOW\u201d. For company details, please visit\u00a0www.purapharm.com.\n\nOur company is an equal opportunity employer. All personal data collected will be used for recruitment purpose only, while the personal data of the unsuccessful applicants will be destroyed within 6 months after the recruitment process.", "employment_types": ["Full Time", "Permanent"], "selling_points": [], "locations": ["Kwun Tong"], "categories": ["Admin & HR", "Clerical / Admin Staff", "Receptionist", "Secretary"], "post_time": "2022-01-17T05:15:56Z", "salary": {"currency": null, "max": null, "min": null, "period": "monthly", "term": null}, "salary_visible": false, "title_keywords": ["administrative assistant"], "responsibilities": ["business goals", "data", "internal and external parties", "quality", "website", "plan", "collaborate", "digital marketing strategies", "advertising", "digital marketing campaigns", "infrastructure", "monitor", "implementation", "developing", "develop", "kpis", "social media", "seo", "review", "ad hoc tasks", "daily operations", "budgets", "digital marketing programs", "analysis"], "requirements": {"degrees": ["degree", "bachelor"], "majors": ["ecommerce", "related disciplines", "business", "marketing"], "languages": [], "language_level": [], "hard_skills": ["project management"], "soft_skills": ["organizational skills", "self-motivated", "multi-task", "communication", "project management", "interpersonal skills", "proactive", "presentation"], "languages_combined": []}, "experience_required": {"duration": ["3 years"], "field": ["digital marketing"]}}, {"job_id": "100003009053335", "location_code": "hk", "company": "Reach Wealth Management Consultancy", "job_title": "Administrative assistant", "description": "\u5de5\u4f5c\u804c\u8d23:\n1\u3001\u5efa\u7acb\u5b8c\u5584\u8d22\u52a1\u5236\u5ea6\u548c\u5185\u63a7\u4f53\u7cfb\u3001\u4f1a\u8ba1\u6838\u7b97\u4fe1\u606f\u5316\u4f53\u7cfb\uff1b\n2\u3001\u5bf9\u516c\u53f8\u7a0e\u6536\u8fdb\u884c\u6574\u4f53\u7b79\u5212\u4e0e\u7ba1\u7406\uff0c\u5ba1\u6838\u7a0e\u52a1\u7533\u62a5\u7684\u53ca\u65f6\u6027\u548c\u51c6\u786e\u6027\uff1b\n3\u3001\u8d1f\u8d23\u7ec4\u7ec7\u7f16\u5236\u516c\u53f8\u7684\u5e74\u5ea6\u8d22\u52a1\u8ba1\u5212\u548c\u9884\u51b3\u7b97\uff0c\u5e76\u8d1f\u8d23\u5bf9\u9884\u7b97\u7684\u6267\u884c\u8fdb\u884c\u68c0\u67e5\u548c\u5206\u6790\uff1b 4\u3001\u5ba1\u6838\u516c\u53f8\u8d44\u91d1\u8ba1\u5212\uff0c\u7ed3\u5408\u8d44\u91d1\u60c5\u51b5\u5408\u7406\u5b89\u6392\u8d44\u91d1\u9700\u6c42\uff0c\u5bf9\u95f2\u7f6e\u8d44\u91d1\u5408\u7406\u63d0\u51fa\u7406\u8d22\u5efa\u8bae\uff1b\n5\u3001\u8d1f\u8d23\u5bf9\u65e5\u5e38\u8d22\u52a1\u62a5\u8868\u7f16\u5236\u548c\u65e5\u5e38\u6536\u652f\u62a5\u9500\u5404\u9879\u5de5\u4f5c\u7684\u6574\u4f53\u6307\u5bfc\u548c\u5ba1\u6838\u3001\u76d1\u7763\uff1b\n6\u3001\u5efa\u7acb\u8d22\u52a1\u90e8\u7ba1\u7406\u4fe1\u606f\u8d44\u6599\u5e93\uff0c\u5e76\u5b8c\u5584\u8d44\u6599\u6863\u6848\u7684\u6536\u96c6\u3001\u6574\u7406\u548c\u8c03\u7528\u7b49\u7ba1\u7406\u673a\u5236\u548c\u7cfb\u7edf\u5316\u7ba1\u7406\u5de5\u4f5c\uff1b\n7\u3001\u8d1f\u8d23\u76d1\u7763\u8d22\u52a1\u5370\u9274\u53ca\u7968\u636e\u7ba1\u7406\uff0c\u786e\u4fdd\u5370\u9274\u5408\u89c4\u4f7f\u7528\u53ca\u7968\u636e\u5b89\u5168\uff1b\n8\u3001\u6839\u636e\u516c\u53f8\u8d22\u52a1\u72b6\u51b5\u5b9a\u671f\u6216\u4e0d\u5b9a\u671f\u5730\u505a\u597d\u4f01\u4e1a\u7684\u8d22\u52a1\u5206\u6790\uff0c\u7f16\u5199\u8d22\u52a1\u72b6\u51b5\u8bf4\u660e\u4e66\uff0c\u4e3a\u4f01\u4e1a\u5236\u8ba2\u7ecf\u8425\u653f\u7b56\u63d0\u4f9b\u4f9d\u636e\uff1b\n9\u3001\u96c6\u56e2\u53ca\u9886\u5bfc\u5b89\u6392\u7684\u5176\u5b83\u4e8b\u9879\u3002\n10. \u7ba1\u7406\u94f6\u884c\u8d26\u6237\u548c\u94f6\u884c\u5173\u7cfb\uff0c\u5305\u62ec\u5b9a\u671f\u4e0e\u94f6\u884c\u4e92\u52a8\u4ee5\u89e3\u51b3\u95ee\u9898\u3001\u94f6\u884c\u8d26\u6237\u7ba1\u7406\u548c\u76f8\u5173\u884c\u653f\u4e8b\u52a1\u3002\n11. \u6267\u884c\u8d37\u6b3e\u548c\u503a\u5238\u5229\u606f\u652f\u4ed8\u4ee5\u3002 \u51c6\u5907\u5b9a\u671f\u8d22\u52a1\u62a5\u544a\u548c\u62a5\u8868\u3002\n12. \u6267\u884c\u548c\u7ef4\u62a4\u4f01\u4e1a\u878d\u8d44\u9879\u76ee\uff0c\u4f8b\u5982\u53cc\u8fb9\u94f6\u884c\u8d37\u6b3e\uff0c\u4e0e\u6cd5\u5f8b\u56e2\u961f\u4e00\u8d77\u5ba1\u67e5\u8d37\u6b3e\u6587\u4ef6\n\n\u4efb\u804c\u8d44\u683c:\n1\u3001\u672c\u79d1\u53ca\u4ee5\u4e0a\u5b66\u5386\uff0c\u8d22\u52a1\u3001\u5ba1\u8ba1\u3001\u91d1\u878d\u3001\u7ba1\u7406\u7c7b\u4e13\u4e1a\uff1b\n2\u300110\u5e74\u8d22\u52a1\u5de5\u4f5c\u7ecf\u9a8c\uff0c5\u5e74\u8d22\u52a1\u7ba1\u7406\u5de5\u4f5c\u7ecf\u9a8c\uff1b\n3\u3001\u8f83\u5f3a\u7684\u5bf9\u5185\u3001\u5bf9\u5916\u6c9f\u901a\u80fd\u529b\uff0c\u5177\u6709\u8f83\u597d\u7684\u56e2\u961f\u7ec4\u7ec7\u548c\u9886\u5bfc\u80fd\u529b\uff0c\u6709\u8f83\u5f3a\u7684\u8d23\u4efb\u5fc3.", "employment_types": ["Full Time"], "selling_points": ["5 days work", "Welcome fresh graduate", "Good in Cantonese and Mandarin"], "locations": ["Causeway Bay"], "categories": ["Admin & HR", "Clerical / Admin Staff"], "post_time": "2022-01-17T06:47:46Z", "salary": {"currency": "HKD", "max": 13999, "min": 11000, "period": "monthly", "term": null}, "salary_visible": true, "title_keywords": ["administrative assistant"], "responsibilities": [], "requirements": {"degrees": [], "majors": [], "languages": [], "language_level": [], "hard_skills": [], "soft_skills": [], "languages_combined": []}, "experience_required": {"duration": [], "field": []}}, {"job_id": "100003009054415", "location_code": "hk", "company": "Getinge Group Hong Kong Limited", "job_title": "Administration Assistant", "description": "Duties/Responsibilities:\n\n\nLead annual budget process and work with business units to prepare annual budgets and forecasts.\nDevelop and maintain financial models for business units and prepare in-depth variance analysis and insight to support the performance review and business planning.\nMonitor and analysis actual KPIs and financial performance against budget/forecast and identify the cause of variances.\nAct as a business partner working closely with different stakeholders in operation teams and provide analytics support for performance improvement, cost saving and business development initiatives.\nProvide data to support decision-making process through analysis, reporting, research, and effective use of data generation from internal and external information sources.\nConduct investment appraisals and feasibility analysis on potential acquisitions and new developments to support management planning and decision making.\nManage product portfolio with respect to price and cost, working with various department such as operations and sales to ensure profitability of the business unit\nProvide costing and pricing considerations for management team to make decisions on tenders and quotation\nConduct product cost review on a quarterly basis to analyse performance of different products across various market segments, including market share, price competitiveness, and value proposition against competitors\nRequirement:\n\nBachelors degree in Finance, Accounting or related field.\n\nACCA/HKICPA or equivalent professional qualification\nMinimum of 10 years relevant finance and analytical experience.\nFluent in English and Chinese, including Mandarin.\nAdvanced Excel and financial modeling skills required.\u00a0\nStrong analytical and problem-solving skills with attention to details.\nExcellent interpersonal and communication skills.\nStrong business acumen.", "employment_types": ["Full Time", "Part Time", "Contract"], "selling_points": ["Strong international medical company background", "5-day work", "Immediately available is preferable"], "locations": ["Wong Tai Sin Area"], "categories": ["Admin & HR", "Clerical / Admin Staff", "Others", "Sales, CS & Business Devpt", "Sales Administration"], "post_time": "2022-01-17T09:26:30Z", "salary": {"currency": null, "max": null, "min": null, "period": "monthly", "term": null}, "salary_visible": false, "title_keywords": ["administration assistant"], "responsibilities": ["data", "operations", "budget", "quotation", "maintain", "management team", "financial models", "monitor", "teams", "develop", "forecast", "analyse", "kpis", "reporting", "cost", "management", "review", "variance analysis", "budgets", "analysis", "planning"], "requirements": {"degrees": ["degree"], "majors": ["finance", "accounting"], "languages": ["english", "chinese", "mandarin"], "language_level": ["fluent"], "hard_skills": ["excel", "acca", "hkicpa", "problem-solving skills", "acumen"], "soft_skills": ["communication skills", "advanced", "attention to details", "business acumen", "problem-solving skills", "interpersonal"], "languages_combined": [{"language": "english", "language_level": ["fluent"]}, {"language": "chinese", "language_level": ["fluent"]}, {"language": "mandarin", "language_level": ["fluent"]}]}, "experience_required": {"duration": ["minimum of 10 years"], "field": ["finance", "analytical"]}}, {"job_id": "100003009052118", "location_code": "hk", "company": "Purapharm Corporation Limited", "job_title": "Administrative Assistant (Full time/Part time)", "description": "Responsibilities:\n\nPerform reception duties including telephone calls, greeting and serving visitors in professional manner;\nProvide general office administrative work and clerical supports;\nSupport ad-hoc assignments.\n\nRequirements:\u00a0\n\nDiploma in Hospitality or related disciplines preferred;\n1 year's working experience in service field preferred, fresh graduate will also be considered;\nStrong sense of responsibility, proactive, energetic, pleasant and customer-oriented;\nGood PC knowledge in MS Office & Chinese Word Processing;\nProficiency in both written & spoken English and Chinese including Mandarin;\nImmediate available is preferred.\n\nWorking Location: Hong Kong Science Park, Tai Po\n\nWe offer 5-day working week and an attractive remuneration package. Interest parties please click\u00a0Apply Now. For company details, please visit\u00a0www.purapharm.com.\n\nOur Company is an equal opportunity employer. All personal data collected will be used for recruitment purpose only, while the personal data of the unsuccessful applicants will be destroyed within 6 months after the recruitment process.", "employment_types": ["Full Time", "Permanent"], "selling_points": ["Fresh graduate will be considered", "Reception and general administrative duties", "Customer-oriented"], "locations": ["Tai Po Area"], "categories": ["Admin & HR", "Clerical / Admin Staff", "Receptionist", "HR Supporting Staff"], "post_time": "2022-01-17T02:09:41Z", "salary": {"currency": null, "max": null, "min": null, "period": "monthly", "term": null}, "salary_visible": false, "title_keywords": ["administrative assistant"], "responsibilities": ["ad-hoc assignments", "professional manner", "administrative work"], "requirements": {"degrees": ["diploma", "fresh graduate"], "majors": ["related disciplines", "hospitality"], "languages": ["english", "chinese", "mandarin"], "language_level": ["proficiency", "good"], "hard_skills": ["pc knowledge", "chinese word processing", "ms office"], "soft_skills": ["proactive", "sense of responsibility", "pleasant", "customer-oriented", "energetic"], "languages_combined": [{"language": "english", "language_level": ["proficiency"]}, {"language": "chinese", "language_level": ["proficiency", "good"]}, {"language": "mandarin", "language_level": []}]}, "experience_required": {"duration": ["1 year"], "field": []}}, {"job_id": "100003009044803", "location_code": "hk", "company": "The Hong Kong Society for the Aged", "job_title": "\u6587\u54e1 Clerk (\u8077\u4f4d\u7de8\u865f\uff1aClerk - 220102)", "description": "<\u696d\u52d9\u5185\u5bb9>\n\n\u30fb\u65e5\u672c\u8a9e\u3068\u82f1\u8a9e\u3082\u3057\u304f\u306f\u5317\u4eac\u8a9e\u3068\u306e\u901a\u8a33\uff08\u30d3\u30b8\u30cd\u30b9\u30ec\u30d9\u30eb\uff09\n\n\u30fb\u65e5\u672c\u8a9e\u304b\u3089\u82f1\u8a9e\u3082\u3057\u304f\u306f\u4e2d\u56fd\u8a9e\u306e\u7ffb\u8a33\uff08\u30d3\u30b8\u30cd\u30b9\u30ec\u30d9\u30eb\uff09\n\n\u30fb\u82f1\u8a9e\u3082\u3057\u304f\u306f\u4e2d\u56fd\u8a9e\u304b\u3089\u65e5\u672c\u8a9e\u3078\u306e\u7ffb\u8a33\uff08\u30d3\u30b8\u30cd\u30b9\u30ec\u30d9\u30eb\uff09\n\n\u203b\u4e3b\u306a\u7ffb\u8a33\u304a\u3088\u3073\u901a\u8a33\u5185\u5bb9\u306f\u3001\u5065\u5eb7\u98df\u54c1\u304a\u3088\u3073\u5316\u7ca7\u54c1\u306e\u5546\u54c1\u958b\u767a\u306b\u4fc2\u308f\u308b\u5185\u5bb9\u3002\n\n\u30fb\u8cc7\u6599\u6574\u7406\u3001\u4f01\u753b\u66f8\u4f5c\u6210\u3001\u8b70\u4e8b\u9332\u4f5c\u6210\n\n\u30fb\u4f1a\u8b70\u306e\u8a2d\u5b9a\n\n\u30fb\u5065\u5eb7\u98df\u54c1\u304a\u3088\u3073\u5316\u7ca7\u54c1\u306e\u5546\u54c1\u958b\u767a\u306b\u4fc2\u308f\u308b\u60c5\u5831\u53ce\u96c6\n\n\u30fb\u5546\u54c1\u4f01\u753b/\u898b\u7a4d\u3082\u308a\u4f5c\u6210\n\n\u30fb\u5546\u54c1\u958b\u767a\u306e\u30b9\u30b1\u30b8\u30e5\u30fc\u30eb\u7ba1\u7406\n\n\u30fb\u7c21\u5358\u306a\u8cbf\u6613\u696d\u52d9\n\n\u30fb\u5728\u5b85\u52e4\u52d9\u53ef\u80fd\n\n<\u8cc7\u683c\u30fb\u8981\u4ef6>\n\n\u30fb\u65e5\u672c\u8a9e\u30d3\u30b8\u30cd\u30b9\u4f1a\u8a71\u304a\u3088\u3073\u7b46\u8a18\u304c\u53ef\u80fd\u3067\u3042\u308b\n\n\u30fb\u82f1\u8a9e\u3082\u3057\u304f\u306f\u5317\u4eac\u8a9e\u306e\u30d3\u30b8\u30cd\u30b9\u4f1a\u8a71\u304a\u3088\u3073\u7b46\u8a18\u304c\u53ef\u80fd\u3067\u3042\u308b\n\n\u30fb\u77ed\u5927\u3082\u3057\u304f\u306f\u5927\u5b66\u5352\u696d\u4ee5\u4e0a\u306e\u5b66\u4f4d\u3092\u53d6\u5f97\n\n\u30fb\u30ef\u30fc\u30c9\u3001\u30a8\u30af\u30bb\u30eb\u3001\u30d1\u30ef\u30fc\u30dd\u30a4\u30f3\u30c8\u304c\u4f7f\u7528\u3067\u304d\u308b\n\n\u00a0<\u512a\u9047\u8981\u4ef6>\n\n\u30fb\u88fd\u9020\u696d\u3084\u5546\u793e\u3067\u4e2d\u56fd\u4f01\u696d\u3068\u306e\u6298\u885d\u7d4c\u9a13\u304c\u3042\u308b\u65b9\n\n\u30fb\u4f55\u3089\u304b\u306e\u5546\u54c1\u4f01\u753b\u306e\u7d4c\u9a13\u304c\u3042\u308b\u65b9\n\n\u30fbPhotoshop\u3001Illustrator\u306e\u30b9\u30ad\u30eb\u304c\u3042\u308b\u65b9\n\n\u30fb\u5065\u5eb7\u98df\u54c1\u307e\u305f\u306f\u5316\u7ca7\u54c1\u306e\u5546\u54c1\u958b\u767a\u306b\u8208\u5473\u3092\u304a\u6301\u3061\u306e\u65b9\n\n\u30fb\u81ea\u7136\u7d20\u6750\u306b\u8208\u5473\u3092\u304a\u6301\u3061\u306e\u65b9\n\n\u30fb\u30a8\u30f3\u30b8\u30cb\u30a2\u30ea\u30f3\u30b0\u306e\u80cc\u666f\u00a0", "employment_types": ["Full Time", "Contract"], "selling_points": [], "locations": ["Quarry Bay"], "categories": ["Admin & HR", "Clerical / Admin Staff"], "post_time": "2022-01-15T19:11:26Z", "salary": {"currency": null, "max": null, "min": null, "period": "monthly", "term": null}, "salary_visible": false, "title_keywords": ["clerk", "\u6587\u54e1"], "responsibilities": [], "requirements": {"degrees": [], "majors": [], "languages": [], "language_level": [], "hard_skills": [], "soft_skills": [], "languages_combined": []}, "experience_required": {"duration": [], "field": []}}, {"job_id": "100003009053391", "location_code": "hk", "company": "Paus Architects Building Maintenance Consultants Limited", "job_title": "\u6703\u8a08/\u7c3f\u8a18\u6587\u54e1", "description": "\nRequirements :-\u00a0\nSecondary school graduated\nGood PC knowledge in MS Office and Chinese word processing\nGood communication skill\nMandarin and English\n\u00a0 Job duties :-\u00a0\nGeneral clerical duties, including filing, data input, photocopying, preparing reports etc.\nHandling telephone calls, telephone answering.\nArrange document courier.\n\u00a0 \u00a0 Interested parties please email resume with expected salary by clicking Apply Now\n(Personal data collected will only be used for recruitment purpose)\n\n", "employment_types": ["Full Time"], "selling_points": [], "locations": ["Yau Tsim Mong Area"], "categories": ["Admin & HR", "Clerical / Admin Staff", "Others"], "post_time": "2022-01-17T06:54:55Z", "salary": {"currency": null, "max": null, "min": null, "period": "monthly", "term": null}, "salary_visible": false, "title_keywords": [], "responsibilities": ["data input", "preparing reports"], "requirements": {"degrees": [], "majors": [], "languages": ["english", "chinese", "mandarin"], "language_level": ["good"], "hard_skills": ["pc knowledge", "chinese word processing", "ms office"], "soft_skills": ["communication skill"], "languages_combined": [{"language": "english", "language_level": []}, {"language": "chinese", "language_level": ["good"]}, {"language": "mandarin", "language_level": []}]}, "experience_required": {"duration": [], "field": []}}, {"job_id": "100003009032852", "location_code": "hk", "company": "Kin Ming Construction Company Ltd", "job_title": "\u6587\u54e1 Clerk", "description": "\n\u8077\u8cac :\u4e00\u822c\u6703\u8a08/\u7c3f\u8a18\u6587\u54e1\u5de5\u4f5c, \u8ca0\u8cac\u6703\u8a08\u5165\u5e33, \u8655\u7406\u5e33\u76ee\u53ca\u6587\u66f8\u5de5\u4f5c\u3002\u6587\u4ef6\u6b78\u6a94\u3002\u8fa6\u5de5\u5ba4\u96dc\u52d9\u53ca\u5916\u52e4\u3002\u8655\u7406\u8fa6\u516c\u5ba4\u96dc\u52d9\u53ca\u5916\u52e4\u4e8b\u52d9\n\n\u8cc7\u6b77 :\u4e2d\u516d\u7a0b\u5ea6; 1\u5e74\u7d93\u9a57; \u826f\u597d\u7cb5\u8a9e; \u4e00\u822c\u82f1\u8a9e; \u61c2\u8b80\u5beb\u4e2d\u6587; \u61c2\u95b1\u8b80\u82f1\u6587; \u61c2Microsoft Office; \u61c2\u82f1\u6587\u6253\u5b57; \u61c2\u4e2d\u6587\u6253\u5b57; \u5177\u6709\u57fa\u672c\u96fb\u8166\u64cd\u4f5c\u77e5\u8b58\n\n\u5f85\u9047 :\u6bcf\u6708$11,000 - $12,000, \u6709\u8d85\u6642\u5de5\u4f5c\u6d25\u8cbc, \u96d9\u7ce7, \u5e74\u504710\u5929, \u9280\u884c\u5047\u671f \u53ca\u624b\u63d0\u96fb\u8a71\u6d25\u8cbc, \u661f\u671f\u4e00\u81f3\u4e94: \u4e0a\u53489\u6642\u534a\u81f3\u4e0b\u53486\u6642, \u6bcf\u9031\u5de5\u4f5c5\u5929\n\n\u7533\u8acb\u9808\u77e5 :\u6c42\u8077\u8005\u53ef\u96fb\u90f5(Apply Now)\u5c65\u6b77\u8868\u7d66\u9b91\u6c0f\u5efa\u7bc9\u5e2b\u6a13\u5b87\u7dad\u4fee\u9867\u554f\u6709\u9650\u516c\u53f8\u3002\u5982\u8981\u7d22\u53d6\u6536\u96c6\u500b\u4eba\u8cc7\u6599\u8072\u660e, \u8acb\u8207\u5289\u5c0f\u59d0(Email)\u806f\u7d61\u3002\n\n", "employment_types": ["Full Time", "Permanent"], "selling_points": [], "locations": ["Shatin Area"], "categories": ["Admin & HR", "Clerical / Admin Staff", "Receptionist", "Others"], "post_time": "2022-01-16T21:50:08Z", "salary": {"currency": "HKD", "max": 13999, "min": 11000, "period": "monthly", "term": null}, "salary_visible": true, "title_keywords": ["clerk", "\u6587\u54e1"], "responsibilities": [], "requirements": {"degrees": [], "majors": [], "languages": [], "language_level": [], "hard_skills": [], "soft_skills": [], "languages_combined": []}, "experience_required": {"duration": [], "field": []}}, {"job_id": "100003009054680", "location_code": "hk", "company": "\u9999\u6e2f\u5bec\u983b\u4f01\u696d\u65b9\u6848\u9999\u6e2f\u6709\u9650\u516c\u53f8", "job_title": "Administration Officer", "description": "\u5730\u5340 :\u706b\u70ad\n\n\u8077\u8cac :\u4e00\u822c\u6587\u66f8\u5de5\u4f5c\uff1b\u6587\u4ef6\u5b58\u6a94\u53ca\u8655\u7406\uff0c\u8cc7\u6599\u8f38\u5165\uff1b\u5354\u52a9\u90e8\u9580\u8655\u7406\u3001\u8ddf\u9032\u63a1\u8cfc\u8a02\u55ae\u3001\u6536\u767c\u3001\u6574\u7406\u3001\u8a18\u9304\u5de5\u7a0b\u6587\u4ef6\u53ca\u7b49\u5de5\u4f5c\uff1b\u63a5\u807d\u96fb\u8a71\uff0c\u5b89\u6392\u901f\u905e\n\u8cc7\u6b77 :\u4e2d\u516d\u7a0b\u5ea6; 2\u5e74\u7d93\u9a57; \u826f\u597d\u7cb5\u8a9e; \u4e00\u822c\u666e\u901a\u8a71; \u826f\u597d\u82f1\u8a9e\u512a\u5148; \u61c2\u8b80\u5beb\u4e2d\u6587; \u61c2\u8b80\u5beb\u82f1\u6587; \u61c2Microsoft Office; \u61c2MS Word; \u61c2MS Outlook; \u61c2MS Excel; \u61c2\u4e2d\u82f1\u6587\u96fb\u8166\u64cd\u4f5c; \u51772\u5e74\u6216\u4ee5\u4e0a\u76f8\u95dc\u5de5\u4f5c\u7d93\u9a57\uff0c\u826f\u597d\u6e9d\u901a\u6280\u5de7\u53ca\u670d\u52d9\u614b\u5ea6\uff0c\u5de5\u4f5c\u7a4d\u6975\u4e3b\u52d5\u3001\u76e1\u8cac\u3001\u52e4\u596e\n\u5f85\u9047 :\u6709\u9280\u884c\u5047\u671f \u53ca\u670d\u52d9\u6eff3\u500b\u6708\u6709\u9580\u8a3a\u91ab\u7642\u54ad, \u6bcf\u9031\u5de5\u4f5c5\u5929\u534a\n\u7533\u8acb\u9808\u77e5 :\u6c42\u8077\u8005\u53ef\u96fb\u90f5\u5c65\u6b77\u8868\u7d66\u5065\u660e\u5efa\u7bc9\u6709\u9650\u516c\u53f8\u3002\u5982\u8981\u7d22\u53d6\u6536\u96c6\u500b\u4eba\u8cc7\u6599\u8072\u660e, \u8acb\u8207\u8d99\u5c0f\u59d0(Email)\u806f\u7d61\u3002", "employment_types": ["Full Time"], "selling_points": ["administrative and secretarial support", "Life-Work Priority", "Business Administration"], "locations": ["Pok Fu Lam"], "categories": ["Admin & HR", "Clerical / Admin Staff"], "post_time": "2022-01-17T10:32:49Z", "salary": {"currency": null, "max": null, "min": null, "period": "monthly", "term": null}, "salary_visible": false, "title_keywords": ["administration officer"], "responsibilities": [], "requirements": {"degrees": [], "majors": [], "languages": [], "language_level": [], "hard_skills": ["excel", "outlook", "word"], "soft_skills": [], "languages_combined": []}, "experience_required": {"duration": [], "field": []}}, {"job_id": "100003009053777", "location_code": "hk", "company": "Life Extension Company Limited", "job_title": "\u517c\u8077\u884c\u653f\u52a9\u7406", "description": "Requirements:\n\nForm 5 or above, one year relevant experience in office administration duties\nGood interpersonal skills, telephone manner and communication skills\nGood computer skills including Microsoft Word, Excel and PowerPoint, knowledge of Chinese Word Processing would be an advantage\nGood Chinese and English\nResponsibilities:\n\nPrepare general clerical duties including filing, sorting, data entry\nProvide administrative and clerical support\nAssist with ad hoc projects\nPerform other duties as assigned", "employment_types": ["Part Time"], "selling_points": [], "locations": ["Mong Kok"], "categories": ["Admin & HR", "Clerical / Admin Staff", "Others", "Others", "Others"], "post_time": "2022-01-17T07:30:50Z", "salary": {"currency": null, "max": null, "min": null, "period": "hourly", "term": null}, "salary_visible": false, "title_keywords": [], "responsibilities": ["perform other duties", "ad hoc projects", "administrative and clerical support", "data entry"], "requirements": {"degrees": ["form 5 or above"], "majors": [], "languages": ["english", "chinese"], "language_level": ["advantage", "good"], "hard_skills": ["excel", "microsoft word", "chinese word processing", "powerpoint", "computer skills"], "soft_skills": ["communication skills", "interpersonal skills", "telephone manner"], "languages_combined": [{"language": "english", "language_level": ["good"]}, {"language": "chinese", "language_level": ["advantage", "good", "good"]}]}, "experience_required": {"duration": ["one year"], "field": ["office administration", "relevant experience"]}}, {"job_id": "100003009051740", "location_code": "hk", "company": "Streamline HR", "job_title": "Administration Officer", "description": "\n\u8077\u8cac :Responsible for data entry; Filing documents; Handle other ad hoc assignments as needed\n\n\u8cc7\u6b77 :\u5c08\u4e0a\u6559\u80b2\uff1a\u526f\u5b78\u4f4d; \u826f\u597d\u7cb5\u8a9e\u512a\u5148; \u826f\u597d\u82f1\u8a9e\u512a\u5148; \u61c2\u8b80\u5beb\u4e2d\u6587; \u61c2\u8b80\u5beb\u82f1\u6587; \u61c2MS Word; \u61c2MS Outlook; \u61c2MS Excel; \u61c2\u82f1\u6587\u6253\u5b57; \u61c2\u5009\u9821/\u901f\u6210\u8f38\u5165\u6cd5; \u6ce8\u91cd\u7d30\u7bc0, \u6e96\u78ba\u5730\u8f38\u5165\u8cc7\u6599, \u826f\u597d\u6e9d\u901a\u6280\u5de7, \u80fd\u7368\u7acb\u5de5\u4f5c, \u6709\u8cac\u4efb\u611f, \u5de5\u4f5c\u4e3b\u52d5; \u6709\u5ba2\u6236\u670d\u52d9\u7d93\u9a57\u512a\u5148\n\n\u5f85\u9047 :\u6bcf\u5c0f\u6642$55.00 - $65.00, \u661f\u671f\u4e00,\u4e09,\u4e94: \u4e0a\u53489\u6642\u81f3\u4e0b\u53486\u6642\u534a, \u6bcf\u9031\u5de5\u4f5c3\u5929, \u6bcf\u5929\u5de5\u4f5c 4 - 5 \u5c0f\u6642\n\n\u7533\u8acb\u9808\u77e5 :\u6c42\u8077\u8005\u53ef\u96fb\u90f5(Apply Now)\u5c65\u6b77\u8868\u7d66\u5ef6\u5e74\u9999\u6e2f\u6709\u9650\u516c\u53f8\u3002\u5982\u8981\u7d22\u53d6\u6536\u96c6\u500b\u4eba\u8cc7\u6599\u8072\u660e, \u8acb\u8207\u9ec3\u5c0f\u59d0(Email)\u806f\u7d61\u3002\n\n", "employment_types": ["Part Time"], "selling_points": ["13 month salary", "Opportunity to work for an international company", "Located centrally in Hong Kong Island"], "locations": ["Central"], "categories": ["Admin & HR", "Clerical / Admin Staff"], "post_time": "2022-01-16T22:27:57Z", "salary": {"currency": null, "max": null, "min": null, "period": "monthly", "term": null}, "salary_visible": false, "title_keywords": ["administration officer"], "responsibilities": ["ad hoc assignments", "data entry"], "requirements": {"degrees": [], "majors": [], "languages": [], "language_level": [], "hard_skills": ["excel", "outlook", "word"], "soft_skills": ["responsible"], "languages_combined": []}, "experience_required": {"duration": [], "field": []}}, {"job_id": "100003009051638", "location_code": "hk", "company": "China Vantage International Holdings Limited", "job_title": "Programme Administrative Assistant / Clerk (Full-time)", "description": "About us\n\nThe Alexander Pacific Group is a multi-national leader in the design and construction of architectural roof structures, pre-engineered building solutions and facades for the last 15 years. With a head office based in Australia and premises in Hong Kong, Philippines, and Las Vegas, this is a successful and dynamic business actively seeking to grow their market presence. This is an award-winning business who achieve international results. An opportunity to work in a growing global business doesn\u2019t come along every day!\n\nAbout the role\n\nDue to business growth, the Alexander Pacific Group are looking for an experienced and detail orientated part-time Administration Officer to join their team based in Hong Kong Island. You will be supporting the Regional Director and the Hong Kong team with various administration duties and will initially work from home before transitioning into a new office later this year.\n\nThe key components of this role will be to:\n\nPerform a range of office administrative tasks including answering calls, responding to enquiries, greeting clients and visitors, filing, and receiving and sending correspondence\nManage the Regional Directors calendar including booking meetings, sending invitations, and responding to requests\nCollect cheques from various client and supplier offices and regularly deposit cheques at the bank\nCollect mail several times a week\nUpdate project information and data entry using various software including Salesforce\u00a0\nCoordinate travel and accommodation arrangements for senior team members\nFollow up with client and supplier invoicing and maintain a general ledger\nEnsure office is running smoothly, and manage office consumables, equipment, purchasing and maintenance as required\nPerform any other adhoc administration support including reporting, presentations and onboarding new team members\n\nAbout you\n\nTo be successful in this role you will need to:\n\nHave at least 2 years of relevant experience in an office administration role\nHave experience in a global company within the construction industry (highly advantageous) \u00a0\u00a0\u00a0\nBe proficient and fluent in both written and spoken English\nBe familiar with MS Office (Word, Excel, PowerPoint) and Salesforce\nBe a solutions orientated team player who is organised and detail-oriented\nHave excellent time management skills and an ability to manage multiple competing priorities \u00a0\nHave a positive attitude and be self-motivated\nBe able to work part time, 25 hours per week Monday - Friday\nBe able to commence after Chinese New Year\n\nWhat\u2019s In It For You?\n\nThis is a role with a huge amount of opportunity for the right candidate! You will have the chance to work alongside a highly skills team and develop your career with an established and growing company. There is a 13 month salary on offer and company medical fund benefits after probation.\n\nHow to Apply\n\nPlease send your applications by clicking the Apply button and submitting your resume with a 1 page covering letter detailing your suitability for the role. \u00a0Successful candidates will be contacted for an initial phone screen.", "employment_types": ["Full Time"], "selling_points": ["Education", "Administrative Assistant", "Administration"], "locations": ["Causeway Bay"], "categories": ["Admin & HR", "Clerical / Admin Staff", "Education", "Others"], "post_time": "2022-01-16T16:37:01Z", "salary": {"currency": null, "max": null, "min": null, "period": "monthly", "term": null}, "salary_visible": false, "title_keywords": ["administrative assistant", "clerk"], "responsibilities": ["reporting", "management", "software", "maintenance", "data entry", "general ledger", "office administration", "design", "presentations", "coordinate", "invoicing", "cheques", "maintain", "develop", "booking", "administrative tasks", "administration"], "requirements": {"degrees": [], "majors": [], "languages": ["english", "chinese"], "language_level": ["fluent", "proficient"], "hard_skills": ["excel", "salesforce", "maintenance", "word", "presentations", "powerpoint", "dynamic", "ms office"], "soft_skills": ["self-motivated", "time management skills", "detail-oriented", "positive attitude", "dynamic", "detail orientated", "organised", "team player"], "languages_combined": [{"language": "english", "language_level": ["fluent", "proficient"]}, {"language": "chinese", "language_level": []}]}, "experience_required": {"duration": ["at least 2 years"], "field": ["office administration", "construction industry", "relevant experience"]}}, {"job_id": "100003009054869", "location_code": "hk", "company": "Nu Skin Enterprises Hong Kong, LLC", "job_title": "Administrative Assistant (Part-time)", "description": "Requirement:\n-\u00a0Higher Diploma graduates or above\n-\u00a0Good command of written and spoken English and Chinese\n-\u00a0Proficient in PC applications on MS Word and Excel\n-\u00a0Good communication and inter-personal skills\n-\u00a0Pleasant disposition with excellent telephone and reception skills and manner\n-\u00a0Work in Causeway Bay\n-\u00a0Shift duty required\n-\u00a0Immediately available preferred\n-\u00a0Fresh graduates are also welcome\n\n\nResponsibility:\n- Provide supports to the Programme Administration\n- Administrative duties such as timetabling, exam invigilation, attendance etc\n- Receive, collate, distribute student coursework and prepare mark sheets\n- Maintain a good filing system and record management\n- Liaise with teachers with respect to curriculum and students progress\n- Handle phone calls including enquiries and requests from students\n- Ad hoc duties assigned by the supervisor", "employment_types": ["Part Time"], "selling_points": ["secretarial and administrative work", "Handle billings, invoices and expenses claims", "Coordinate meetings and conference calls"], "locations": ["Tin Hau"], "categories": ["Admin & HR", "Clerical / Admin Staff", "Secretary"], "post_time": "2022-01-17T12:14:08Z", "salary": {"currency": null, "max": null, "min": null, "period": "hourly", "term": null}, "salary_visible": false, "title_keywords": ["administrative assistant"], "responsibilities": ["ad hoc duties", "attendance", "management", "maintain", "administrative duties", "liaise with", "phone calls", "administration"], "requirements": {"degrees": ["diploma"], "majors": [], "languages": ["english", "chinese"], "language_level": ["good command"], "hard_skills": ["ms word", "excel", "pc applications"], "soft_skills": ["communication", "inter-personal skills", "pleasant"], "languages_combined": [{"language": "english", "language_level": ["good command"]}, {"language": "chinese", "language_level": ["good command"]}]}, "experience_required": {"duration": [], "field": []}}, {"job_id": "100003009053826", "location_code": "hk", "company": "Money Concepts (Asia) Holdings Limited", "job_title": "\u884c\u653f\u6587\u54e1**", "description": "Responsibilities:\u00a0\u00a0\n\nOffice administration work such as general filing work and data input;\nManage office supplies and the smooth running of the department;\nOrganize meetings and conference calls;\nTravel arrangement and travel expenses;\nProvide day to day administrative support.\n\nRequirement:\u00a0\u00a0\n\nGood communication, interpersonal and organization skills;\nSelf-initiative and detail-minded;\nProficient in MS Office and Chinese word processing;\nGood command of spoken and written English and Chinese including Mandarin;\nAble to provide service on 2 or 3 full days a week or half day from each day.\nImmediately available is highly preferred.\n\nWe offer friendly working environment with competitive remuneration. If you are interested in joining our company, please click\u00a0\"Apply Now\"\u00a0to submit your application.\u00a0\n\nALL PERSONAL INFORMATION WE COLLECTED IS FOR THE PURPOSE OF RECRUITMENT ONLY\n\nPlease visit www.nuskin.com to find out more about us!", "employment_types": ["Full Time"], "selling_points": [], "locations": ["Wan Chai"], "categories": ["Admin & HR", "Clerical / Admin Staff", "Others"], "post_time": "2022-01-17T07:35:26Z", "salary": {"currency": null, "max": null, "min": null, "period": "monthly", "term": null}, "salary_visible": false, "title_keywords": [], "responsibilities": ["administrative support", "office supplies", "expenses", "office administration work", "data input", "travel arrangement"], "requirements": {"degrees": [], "majors": [], "languages": ["english", "chinese", "mandarin"], "language_level": ["good command", "proficient"], "hard_skills": ["chinese word processing", "ms office"], "soft_skills": ["detail-minded", "communication", "self-initiative", "organization skills", "interpersonal"], "languages_combined": [{"language": "english", "language_level": ["good command"]}, {"language": "chinese", "language_level": ["good command", "proficient"]}, {"language": "mandarin", "language_level": ["good command"]}]}, "experience_required": {"duration": [], "field": []}}, {"job_id": "100003009054203", "location_code": "hk", "company": "Global Union Ltd", "job_title": "Admin Assistant", "description": "\n\u8077\u8cac :\u4e00\u822c\u884c\u653f\u6587\u54e1\u5de5\u4f5c, \u6587\u66f8\u8655\u7406\u53ca\u63d0\u4f9b\u65e5\u5e38\u884c\u653f\u652f\u63f4\n\n\u8cc7\u6b77 :\u5c08\u4e0a\u6559\u80b2\uff1a\u6587\u6191/\u8b49\u66f8; 4\u5e74\u7d93\u9a57; \u826f\u597d\u7cb5\u8a9e; \u826f\u597d\u666e\u901a\u8a71; \u826f\u597d\u82f1\u8a9e\u512a\u5148; \u61c2\u8b80\u5beb\u4e2d\u6587; \u61c2\u8b80\u5beb\u82f1\u6587; \u61c2MS Word; \u61c2MS Excel; \u5177\u6709\u57fa\u672c\u96fb\u8166\u64cd\u4f5c\u77e5\u8b58; Good communication & interpersonal skill; patient at work; good telephone manner.\n\n\u5f85\u9047 :\u6bcf\u6708$9,000 - $12,000, \u661f\u671f\u4e00\u81f3\u4e94: \u4e0a\u53489\u6642\u81f3\u4e0b\u53486\u6642\u53ca\u661f\u671f\u516d: \u4e0a\u53489\u6642\u81f3\u4e0b\u53481\u6642, \u6bcf\u9031\u5de5\u4f5c5\u5929\u534a, \u6bcf\u5929\u5de5\u4f5c 8 \u5c0f\u6642\n\n\u7533\u8acb\u9808\u77e5 :\u6c42\u8077\u8005\u53ef\u81f4\u96fb31052000\u8207\u7f8e\u570b\u842c\u5229\u7406\u8ca1\u63a7\u80a1\u6709\u9650\u516c\u53f8\u9127\u5148\u751f\u806f\u7d61\u3002\n\n", "employment_types": ["Full Time"], "selling_points": [], "locations": ["Kwai Fong"], "categories": ["Admin & HR", "Clerical / Admin Staff", "Receptionist", "Secretary"], "post_time": "2022-01-17T08:49:08Z", "salary": {"currency": null, "max": null, "min": null, "period": "monthly", "term": null}, "salary_visible": false, "title_keywords": ["admin assistant"], "responsibilities": ["communication"], "requirements": {"degrees": [], "majors": [], "languages": [], "language_level": [], "hard_skills": ["excel", "word"], "soft_skills": ["communication", "patient", "telephone manner", "interpersonal skill"], "languages_combined": []}, "experience_required": {"duration": [], "field": []}}, {"job_id": "100003009052170", "location_code": "hk", "company": "Faith Christian Limited", "job_title": "Administrative & Marketing Clerk\u884c\u653f\u6587\u54e1(Full-time)", "description": "\n\u8077\u8cac :\u4e00\u822c\u5009\u52d9\u6587\u54e1\u5de5\u4f5c, \u8ca0\u8cac\u65e5\u5e38\u5009\u52d9\u904b\u4f5c\u53ca\u8ca8\u5009\u7ba1\u7406, \u6536\u8ca8\u3001\u51fa\u8ca8\u53ca\u9a57\u8ca8, \u5305\u88dd\u8ca8\u7269\u3001\u76e4\u9ede\u53ca\u6574\u7406\u8ca8\u5009, \u8ddf\u9032\u8a02\u55ae, \u66f4\u65b0\u5eab\u5b58\u8a18\u9304, \u62cd\u7167\u5b58\u6a94, \u8cc7\u6599\u8f38\u5165, \u8655\u7406\u7cfb\u7d71\u8cc7\u6599\u8f38\u5165\uff0c\u51fa\u5165\u53e3\u5831\u95dc\uff0c\u4e00\u822c\u5009\u52d9\u6587\u4ef6\uff1b\u5ba2\u6236\u670d\u52d9\uff1b\u8655\u7406/ \u8ddf\u9032\u7db2\u4e0a\u8a02\u55ae\n\n\u8cc7\u6b77 :\u4e2d\u4e94\u7a0b\u5ea6; 3\u5e74\u7d93\u9a57; \u826f\u597d\u7cb5\u8a9e\u512a\u5148; \u4e00\u822c\u666e\u901a\u8a71\u512a\u5148; \u4e00\u822c\u82f1\u8a9e\u512a\u5148; \u61c2\u8b80\u5beb\u4e2d\u6587; \u7565\u61c2\u8b80\u5beb\u82f1\u6587; \u5177\u6709\u4e00\u822c\u4e92\u806f\u7db2\u77e5\u8b58; \u61c2\u4e2d\u82f1\u6587\u96fb\u8166\u64cd\u4f5c; \u5177\u6709\u57fa\u672c\u96fb\u8166\u64cd\u4f5c\u77e5\u8b58; \u6709\u76f8\u95dc\u5009\u52d9\u6587\u66f8\u5de5\u4f5c\u7d93\u9a57\u512a\u5148\uff1b\u61c2\u5009\u52d9\u7cfb\u7d71\u61ee\u5148\n\n\u5f85\u9047 :\u6bcf\u6708$13,000 - $16,000, \u6709\u96d9\u7ce7, \u6bcf\u6708\u52e4\u5de5\u734e\u91d1$1000 \u53ca\u6bcf\u65e5\u4ea4\u901a\u6d25\u8cbc$40, \u4e0a\u53489\u6642\u81f3\u4e0b\u53486\u6642, \u6bcf\u9031\u5de5\u4f5c6\u5929,\u8f2a\u4f11, \u6bcf\u5929\u5de5\u4f5c 9 \u5c0f\u6642\n\n\u7533\u8acb\u9808\u77e5 :\u6c42\u8077\u8005\u53ef\u96fb\u90f5(Apply Now)\u5c65\u6b77\u8868\u7d66\u5f97\u7269(\u9999\u6e2f)\u4f9b\u61c9\u93c8\u6709\u9650\u516c\u53f8\u3002\u5982\u8981\u7d22\u53d6\u6536\u96c6\u500b\u4eba\u8cc7\u6599\u8072\u660e, \u8acb\u8207\u56b4\u5148\u751f(Email)\u806f\u7d61\u3002\n\n", "employment_types": ["Full Time"], "selling_points": ["San Po Kong", "admin, customer service, digital marketing", "5 days work"], "locations": ["Kowloon City Area"], "categories": ["Admin & HR", "Clerical / Admin Staff", "Sales, CS & Business Devpt", "Customer Service - Supervisor / Officer", "Marketing / Public Relations", "Digital Marketing"], "post_time": "2022-01-17T02:19:52Z", "salary": {"currency": null, "max": null, "min": null, "period": "monthly", "term": null}, "salary_visible": false, "title_keywords": [], "responsibilities": [], "requirements": {"degrees": [], "majors": [], "languages": [], "language_level": [], "hard_skills": [], "soft_skills": [], "languages_combined": []}, "experience_required": {"duration": [], "field": []}}, {"job_id": "100003009053655", "location_code": "hk", "company": "AccGirl Limited", "job_title": "\u884c\u653f\u6587\u54e1", "description": "\u7db2\u4e0a\u516c\u53f8\u8aa0\u8058:\u00a0\n\nAdministrative & Marketing Clerk\u884c\u653f\u6587\u54e1(full-time)\n\n\u00a0\u8077\u8cac\uff1a\n\n\u4e00\u822c\u6587\u66f8\u5de5\u4f5c\n\u5354\u52a9\u65e5\u5e38\u904b\u4f5c\uff0c\u63d0\u4f9b\u826f\u597d\u5ba2\u6236\u670d\u52d9\n\u8010\u5fc3\u89e3\u7b54\u67e5\u8a62\n\u5354\u52a9\u5e02\u5834\u71df\u92b7 / \u7db2\u4e0a\u71df\u92b7\n\u00a0\u8077\u4f4d\u8981\u6c42:\n\n\u5927\u5c08\u7a0b\u5ea6\n\u6709\u5ba2\u670d\u7d93\u9a57\u512a\u5148\n\u5e02\u5834\u71df\u92b7\u6216\u7db2\u4e0a\u5ba3\u50b3\u7d93\u9a57\u512a\u5148\n\u719f\u6089\u4e2d\u3001\u82f1\u6587\u96fb\u8166\u64cd\u4f5c (Word, Excel\u53ca\u4e2d\u82f1\u6587\u6253\u5b57)\n\u826f\u597d\u4e2d\u82f1\u6587\u5beb\u4f5c\n2\u5e74\u4ee5\u4e0a\u5de5\u4f5c\u7d93\u9a57\u512a\u5148\n\u57fa\u7763\u5f92\u512a\u5148(\u8acb\u8a3b\u660e)\n\n\u5168\u8077\u5de5\u4f5c\u5730\u5340: \u65b0\u84b2\u5d17\n\n\u6b61\u8fce\u6709\u610f\u61c9\u5fb5\u8005\u4e0a\u8f09CV(\u8a3b\u660e\u671f\u671b\u85aa\u916c)\n\n\n\u6240\u6536\u96c6\u7684\u500b\u4eba\u8cc7\u6599\u7d55\u5c0d\u4fdd\u5bc6\u53ca\u53ea\u4f5c\u62db\u8058\u7528\u9014", "employment_types": ["Full Time"], "selling_points": [], "locations": ["North Point"], "categories": ["Admin & HR", "Clerical / Admin Staff", "Others"], "post_time": "2022-01-17T07:18:09Z", "salary": {"currency": null, "max": null, "min": null, "period": "monthly", "term": null}, "salary_visible": false, "title_keywords": [], "responsibilities": [], "requirements": {"degrees": [], "majors": [], "languages": [], "language_level": [], "hard_skills": ["word"], "soft_skills": [], "languages_combined": []}, "experience_required": {"duration": [], "field": []}}, {"job_id": "100003009052520", "location_code": "hk", "company": "\u4e2d\u570b\u653f\u4fe1\u570b\u969b\u958b\u767c\u96c6\u5718\u6709\u9650\u516c\u53f8", "job_title": "Human Resources and Administrative Assistant", "description": "\n- F.5 or above\n- 1 year clerical working experience\n- Proficient in MS office including Chinese WP\n- Good command of both written and spoken English and Chinese\n- Responsible, well-organized, stable & self-motivated\n- Take up clerical, HR and administrative work\n- Immediate available is preferred\n\n", "employment_types": ["Full Time"], "selling_points": [], "locations": ["Wan Chai"], "categories": ["Admin & HR", "Clerical / Admin Staff"], "post_time": "2022-01-17T03:18:09Z", "salary": {"currency": null, "max": null, "min": null, "period": "monthly", "term": null}, "salary_visible": false, "title_keywords": ["administrative assistant", "human resources"], "responsibilities": ["hr", "administrative work"], "requirements": {"degrees": [], "majors": [], "languages": ["english", "chinese"], "language_level": ["good command", "proficient"], "hard_skills": ["chinese wp", "ms office"], "soft_skills": ["stable", "well-organized", "self-motivated", "responsible"], "languages_combined": [{"language": "english", "language_level": ["good command"]}, {"language": "chinese", "language_level": ["good command", "proficient"]}]}, "experience_required": {"duration": ["1 year"], "field": ["clerical"]}}, {"job_id": "100003009052183", "location_code": "hk", "company": "The Hong Kong Girl Guides Association", "job_title": "Assistant Administrative Officer", "description": "Responsibilities:\n\u2022 Perform reception duties including telephone calls, greeting and serving visitors in professional manner;\n\u2022 Provide general office administrative work and clerical supports;\n\u2022 Assist in HR & Admin manager and CEO, coordinate with internal parties in different department;\n\u2022 Support ad-hoc assignments.\n\nRequirements:\n\u2022 Degree holder in Human Resources Management, Business Administration or related disciplines;\n\u2022 Good legal secretarial skills, experienced in administration and secretarial;\n\u2022 Strong sense of responsibility, well organized, meticulous & self-motivated\n\u2022 Good PC knowledge in MS Office & Chinese Word Processing;\n\u2022 Proficiency in both written & spoken English and Chinese including Mandarin;\n\u2022 Immediate available is preferred.", "employment_types": ["Full Time", "Permanent"], "selling_points": [], "locations": ["Yau Tsim Mong Area"], "categories": ["Admin & HR", "Clerical / Admin Staff", "Secretary", "Public / Civil", "Social Services - Community / Non-profit Organization"], "post_time": "2022-01-17T02:22:27Z", "salary": {"currency": null, "max": null, "min": null, "period": "monthly", "term": null}, "salary_visible": false, "title_keywords": ["administrative officer", "assistant"], "responsibilities": ["administrative work", "ad-hoc assignments", "hr", "professional manner", "coordinate with", "internal parties"], "requirements": {"degrees": ["degree holder"], "majors": ["related disciplines", "business administration"], "languages": ["english", "chinese", "mandarin"], "language_level": ["proficiency", "good"], "hard_skills": ["pc knowledge", "chinese word processing", "ms office"], "soft_skills": ["meticulous", "self-motivated", "well organized", "sense of responsibility"], "languages_combined": [{"language": "english", "language_level": ["proficiency"]}, {"language": "chinese", "language_level": ["proficiency", "good"]}, {"language": "mandarin", "language_level": []}]}, "experience_required": {"duration": [], "field": []}}, {"job_id": "100003009053687", "location_code": "hk", "company": "Kam Yuen Radio Co Ltd", "job_title": "\u71df\u696d\u90e8\u6587\u54e1**", "description": "To cope with our development, HKGGA is now looking for candidates of high caliber to join us:\n\n\nResponsibilities:\n\n\nProvide administrative and secretarial support, such as writing minutes, letters and reports for Administration Department as well as senior management.\nAnswer telephone enquiries and perform daily routine administration tasks.\nAssist senior executives to organize events and projects as required.\nIrregular working hours in weekends and public holidays is required if necessary.\n\nRequirements:\n\n\n\nBachelor of Arts or equivalent;\nAt least 2 year\u2019s administrative work experience, social service sector or NGOs is highly preferred\nProficient in spoken and written English language\nProficient in Putonghua is preferable\nWell-versed in Microsoft Office and Chinese word processing e.g. \u901f\u6210or\u5009\u9821\nAble to communicate with all levels of people\nMeticulous, patient and work under pressure\nCandidate with more experience will be considered as Administrative Officer\u00a0\n\nPlease send r\u00e9sum\u00e9 with Ref. Code and expected salary by clicking \"Apply Now\" or to Human Resources Department, 8 Gascoigne Road, Kowloon. Please mark \u201cPrivate & Confidential\u201d on the envelope.\n\nProspective employees are required to undergo Sexual Conviction Record Check.\n\u672c\u6703\u5c07\u8981\u6c42\u6e96\u50f1\u54e1\u9032\u884c\u6027\u7f6a\u884c\u5b9a\u7f6a\u7d00\u9304\u67e5\u6838\u3002\n\nPersonal data provided will be used for recruitment purpose only. All personal data of unsuccessful applicants will be destroyed on completion of the recruitment exercise.", "employment_types": ["Full Time"], "selling_points": [], "locations": ["Kwai Tsing Area"], "categories": ["Admin & HR", "Clerical / Admin Staff", "Others"], "post_time": "2022-01-17T07:21:09Z", "salary": {"currency": null, "max": null, "min": null, "period": "monthly", "term": null}, "salary_visible": false, "title_keywords": [], "responsibilities": ["letters", "reports", "secretarial support", "senior management", "administration"], "requirements": {"degrees": ["bachelor"], "majors": [], "languages": ["putonghua", "english", "chinese"], "language_level": ["proficient"], "hard_skills": ["code", "chinese word processing", "microsoft office"], "soft_skills": ["meticulous", "patient", "work under pressure"], "languages_combined": [{"language": "putonghua", "language_level": ["proficient"]}, {"language": "english", "language_level": []}, {"language": "chinese", "language_level": []}]}, "experience_required": {"duration": ["at least 2 year"], "field": ["administrative"]}}, {"job_id": "100003009053906", "location_code": "hk", "company": "Globelink International Freight Forwarding (HK) Limited", "job_title": "\u8239\u52d9\u6587\u54e1", "description": "Responsibilities:\u00a0\n\n\u00a0\u00a0\u00a0\u00a0\u00a0\u00a0\u00a0\u00a0 Perform all-round office administration and clerical duties such as equipment maintenance, replenishment of office supplies, purchasing and\u00a0etc.\u00a0\n\u00a0\u00a0\u00a0\u00a0\u00a0\u00a0\u00a0\u00a0 Assist in preparing business reports and coordinate with internal parties in different department\n\u00a0\u00a0\u00a0\u00a0\u00a0\u00a0\u00a0\u00a0 Provide clerical support to department, such as document processing, data checking, and filling\n\u00a0\u00a0\u00a0\u00a0\u00a0\u00a0\u00a0\u00a0 Participate in ad-hoc tasks\u00a0as assigned and perform other duties as assigned by Department head\n\n\u00a0Requirements:\n\n\u00a0\u00a0\u00a0\u00a0\u00a0\u00a0\u00a0\u00a0 Degree holder with minimum\u00a01 years\u00a0relevant experience\n\u00a0\u00a0\u00a0\u00a0\u00a0\u00a0\u00a0\u00a0 Detail-minded, energetic, adaptable with good organization skills;\n\u00a0\u00a0\u00a0\u00a0\u00a0\u00a0\u00a0\u00a0 Able to work independently and play as a team member;\n\u00a0\u00a0\u00a0\u00a0\u00a0\u00a0\u00a0\u00a0 Good command of\u00a0both written and spoken English and Chinese. Proficiency in Putonghua is an advantage\n\u00a0\u00a0\u00a0\u00a0\u00a0\u00a0\u00a0\u00a0 Proficiency in Microsoft Office Application\n\u00a0\u00a0\u00a0\u00a0\u00a0\u00a0\u00a0\u00a0 Immediate available is highly preferred\u00a0", "employment_types": ["Full Time"], "selling_points": [], "locations": ["Kwun Tong"], "categories": ["Admin & HR", "Clerical / Admin Staff", "Others"], "post_time": "2022-01-17T07:44:11Z", "salary": {"currency": null, "max": null, "min": null, "period": "monthly", "term": null}, "salary_visible": false, "title_keywords": [], "responsibilities": ["provide clerical support", "perform other duties", "maintenance", "data", "office supplies", "office administration", "ad-hoc tasks", "coordinate with", "replenishment", "checking", "reports", "internal parties"], "requirements": {"degrees": ["degree holder"], "majors": [], "languages": ["putonghua", "english", "chinese"], "language_level": ["advantage", "proficiency", "good command"], "hard_skills": ["microsoft office"], "soft_skills": ["detail-minded", "work independently", "adaptable", "team member", "organization skills", "energetic"], "languages_combined": [{"language": "putonghua", "language_level": ["proficiency", "advantage"]}, {"language": "english", "language_level": ["good command"]}, {"language": "chinese", "language_level": ["good command"]}]}, "experience_required": {"duration": ["minimum 1 years"], "field": ["relevant experience"]}}, {"job_id": "100003009051973", "location_code": "hk", "company": "Synergos Systems Company Limited", "job_title": "Clerk", "description": "\n\u8077\u8cac :\u4e00\u822c\u6587\u66f8\u5de5\u4f5c\uff0c\u5305\u62ec\u6587\u4ef6\u5b58\u6a94\u3001\u8cc7\u6599\u8f38\u5165\u3001\u8907\u5370\u3001\u8655\u7406\u90f5\u4ef6\u7b49\n\n\u8cc7\u6b77 :\u4e2d\u516d\u7a0b\u5ea6; \u826f\u597d\u7cb5\u8a9e\u512a\u5148; \u826f\u597d\u666e\u901a\u8a71\u512a\u5148; \u826f\u597d\u82f1\u8a9e\u512a\u5148; \u61c2\u8b80\u5beb\u4e2d\u6587; \u61c2\u8b80\u5beb\u82f1\u6587; \u53ef\u5373\u6642\u4e0a\u73ed\u53ca\u6709\u76f8\u95dc\u5de5\u4f5c\u7d93\u9a57\u512a\u5148\n\n\u5f85\u9047 :\u6bcf\u6708$10,000 - $12,000, \u6709\u6bcf\u6708\u52e4\u5de5\u734e\u91d1$450, \u9280\u884c\u5047\u671f, \u734e\u52f5\u6027\u82b1\u7d05, \u91ab\u7642\u798f\u5229 \u53ca\u5a5a\u5047, \u661f\u671f\u4e00\u81f3\u4e94: \u4e0a\u53489\u6642\u81f3\u4e0b\u53485\u6642\u534a\u53ca\u661f\u671f\u516d: \u4e0a\u53489\u6642\u81f3\u4e0b\u53481\u6642, \u6bcf\u9031\u5de5\u4f5c5\u5929\u81f35\u5929\u534a, \u6bcf\u5929\u5de5\u4f5c 7.5 - 8 \u5c0f\u6642\n\n\u7533\u8acb\u9808\u77e5 :Apply Now INTERNATIONAL FREIGHT FORWARDING (HK) LIMITED,\u7d22\u53d6\u6536\u96c6\u500b\u4eba\u8cc7\u6599\u8072\u660e, \u8acb\u8207\u67ef\u5148\u751fEmail\u806f\u7d61\n\n", "employment_types": ["Full Time"], "selling_points": [], "locations": ["Tsuen Wan Area"], "categories": ["Admin & HR", "Clerical / Admin Staff"], "post_time": "2022-01-17T01:42:07Z", "salary": {"currency": null, "max": null, "min": null, "period": "monthly", "term": null}, "salary_visible": false, "title_keywords": ["clerk"], "responsibilities": [], "requirements": {"degrees": [], "majors": [], "languages": [], "language_level": [], "hard_skills": [], "soft_skills": [], "languages_combined": []}, "experience_required": {"duration": [], "field": []}}, {"job_id": "100003009053419", "location_code": "hk", "company": "Instant Travel Service Ltd", "job_title": "\u6703\u8a08\u6587\u54e1(\u517c\u8077)", "description": "Responsibilities:\nIssuing invoice;\nAll round support;\nArrange courier;\nInventory management;\nOther ad-hoc duties as required by supervisor;\u00a0\nOutdoor work occasionally\nRequirement:\nF.5 or above ;\n2 years relevant working experience;\nGood in MS Word, Excel\nDetail mind, willing to learn, self-motivated, work independently\nImmediate available\n\nBenefits:\n\nMonthly salary $10,000 - 12,000;\n5 days work per week;\nBank holiday\nBonus", "employment_types": ["Part Time"], "selling_points": [], "locations": ["Yau Ma Tei"], "categories": ["Admin & HR", "Clerical / Admin Staff", "Others"], "post_time": "2022-01-17T06:58:00Z", "salary": {"currency": null, "max": null, "min": null, "period": "hourly", "term": null}, "salary_visible": false, "title_keywords": [], "responsibilities": ["invoice", "outdoor work", "inventory management", "ad-hoc duties"], "requirements": {"degrees": [], "majors": [], "languages": [], "language_level": [], "hard_skills": ["excel", "ms word"], "soft_skills": ["self-motivated", "willing to learn", "work independently"], "languages_combined": []}, "experience_required": {"duration": ["2 years"], "field": ["relevant working experience"]}}, {"job_id": "100003009052845", "location_code": "hk", "company": "\u9999\u6e2f\u53e3\u7f69\u88fd\u9020\u6709\u9650\u516c\u53f8", "job_title": "(\u53e3\u7f69\u516c\u53f8) General Office Clerk/Sales Assistant", "description": "\n\u8077\u8cac :\u8ca0\u8cac\u8655\u7406\u90e8\u9580\u65e5\u5e38\u6587\u66f8\u5de5\u4f5c,\u96fb\u8166\u8cc7\u6599\u8f38\u5165,\u9700\u5916\u52e4\n\n\u8cc7\u6b77 :\u4e2d\u4e94\u7a0b\u5ea6; 1\u5e74\u7d93\u9a57; \u826f\u597d\u7cb5\u8a9e; \u4e00\u822c\u666e\u901a\u8a71; \u4e00\u822c\u82f1\u8a9e; \u61c2\u8b80\u5beb\u4e2d\u6587; \u61c2\u8b80\u5beb\u82f1\u6587; \u61c2MS Word; \u61c2MS Excel; \u6301\u6709LCC\u521d\u7d1a\u8b49\u66f8; \u61c2\u82f1\u6587\u6253\u5b57; \u61c2\u4e2d\u6587\u6253\u5b57; \u6709\u7d93\u9a57/\u5c0d\u65c5\u904a\u696d\u6709\u8208\u8da3\u512a\u5148\n\n\u5f85\u9047 :\u6bcf\u5c0f\u6642$50.00 - $60.00, \u661f\u671f\u4e00\u81f3\u4e94: \u4e0b\u53482\u6642\u81f3\u4e0b\u53486\u6642, \u6bcf\u9031\u5de5\u4f5c5\u5929\n\n\u7533\u8acb\u9808\u77e5 :\u6c42\u8077\u8005\u53ef\u50b3\u771f(23858766)\u6216\u96fb\u90f5(Apply Now)\u5c65\u6b77\u8868\u7d66\u4e00\u5fc3\u65c5\u904a\u6709\u9650\u516c\u53f8\u3002\u5982\u8981\u7d22\u53d6\u6536\u96c6\u500b\u4eba\u8cc7\u6599\u8072\u660e, \u8acb\u8207\u9673\u5973\u58eb(Fax/Email)\u806f\u7d61\u3002\n\n", "employment_types": ["Full Time"], "selling_points": [], "locations": ["Southern Area"], "categories": ["Admin & HR", "Clerical / Admin Staff"], "post_time": "2022-01-17T04:16:31Z", "salary": {"currency": null, "max": null, "min": null, "period": "monthly", "term": null}, "salary_visible": false, "title_keywords": ["office clerk", "sales assistant"], "responsibilities": [], "requirements": {"degrees": [], "majors": [], "languages": [], "language_level": [], "hard_skills": ["excel", "word"], "soft_skills": [], "languages_combined": []}, "experience_required": {"duration": [], "field": []}}, {"job_id": "100003009052468", "location_code": "hk", "company": "Mingo Trims International Limited", "job_title": "General Clerk", "description": "\u8ca0\u8cac\u4e00\u822c\u8fa6\u516c\u5ba4\u652f\u63f4\u5de5\u4f5c\uff0c\u5982\u5167\u90e8\u6587\u4ef6\u50b3\u905e\u53ca\u5f71\u5370\u7b49\n\u5354\u52a9\u8fa6\u516c\u5ba4\u96dc\u52d9\u3001\u642c\u904b\u7269\u8cc7\n\u9700\u5916\u52e4\u5de5\u4f5c\uff0c\u5982\u9001\u905e\u6587\u4ef6\u53ca\u5305\u88f9\u3001\u5f80\u9280\u884c\u5165\u6578\u6216\u90f5\u5c40\u7b49\n\u4e2d\u4e94\u6216DSE\u7a0b\u5ea6\n\u4e09\u5e74\u6216\u4ee5\u4e0a\u5de5\u4f5c\u7d93\u9a57\n\u61c2\u57fa\u672c\u96fb\u8166\u64cd\u4f5c (\u5982MS Word, Excel, Outlook\u7b49)\n\u826f\u597d\u7cb5\u8a9e\uff0c\u61c2\u8b80\u5beb\u4e2d\u6587\uff0c\u7565\u61c2\u95b1\u8b80\u82f1\u6587\n\u505a\u4e8b\u6709\u689d\u7406\uff0c\u8aa0\u5be6\uff0c\u6709\u826f\u597d\u7684\u6e9d\u901a\u80fd\u529b\u53ca\u5177\u8cac\u4efb\u611f\n\u5de5\u4f5c\u5730\u9ede\uff1a\u9285\u947c\u7063\n\nPlease apply, quoting the appropriate reference number, with details of your qualifications and experience, expected salary and a contact telephone number to The Senior Manager, Personnel Department, Television Broadcasts Limited, TVB City, 77 Chun Choi Street, Tseung Kwan O Industrial Estate, Tseung Kwan O, Kowloon, Hong Kong.\n\nApplications received are solely for selection purpose. Those not invited for an interview within 4 weeks may consider their applications unsuccessful and their applications will be filed for another 3 months for future selection. Afterwards, all applications would be destroyed.", "employment_types": ["Full Time", "Permanent"], "selling_points": ["Good working environment, 5 day work", "Immediately available is highly preferred", "Kwai Chung Area"], "locations": ["Kwai Tsing Area"], "categories": ["Admin & HR", "Clerical / Admin Staff", "Others", "Student / Fresh Graduate / No Experience", "Sales, CS & Business Devpt", "Sales Administration"], "post_time": "2022-01-17T03:06:29Z", "salary": {"currency": null, "max": null, "min": null, "period": "monthly", "term": null}, "salary_visible": false, "title_keywords": ["general clerk"], "responsibilities": ["contact"], "requirements": {"degrees": [], "majors": [], "languages": [], "language_level": [], "hard_skills": ["excel", "word"], "soft_skills": [], "languages_combined": []}, "experience_required": {"duration": [], "field": []}}, {"job_id": "100003009053375", "location_code": "hk", "company": "Atlas Contract Manufacturing Limited", "job_title": "\u92b7\u552e\u8ddf\u55ae\u6587\u54e1**", "description": "Requirements:\nUniversity Degree / High Diploma with two years working experience. Fresh Graduate will also be considered.\nWorking experience in L/C application, import and export bills processing or trading operation is preferred.\nHighly independent, attentive to details, self-motivated and willing to learn.\nProficient in MS office (Word and Excel) and Chinese word processing.\nGood command of both written and spoken English and Chinese. Fluency in Putonghua is a must.\nImmediately available is preferred.\n\nJob responsibilities:\n\nHandle and process full set of bills transaction, coordinate with banks for L/C opening and T/T payment.\nAssist to follow up with supplier and purchaser, including contract review, payment and shipping document organization.\nHandle general office administrative tasks.\nProvide assistance to trading and accounting department,\u00a0handle other ad-hoc tasks as assigned.\n\nBenefits:\n\n5-days work\n13 month salary\nMedical and dental insurance\nLunch Allowance\n\nInterested parties, please submit the full resume with current and expected salary and the date of availability by clicking\u00a0\"Apply Now\" button.\u00a0All information collected will be used for recruitment only and treated in strict confidence.", "employment_types": ["Full Time"], "selling_points": [], "locations": ["Shatin Area"], "categories": ["Admin & HR", "Clerical / Admin Staff", "Others"], "post_time": "2022-01-17T06:53:14Z", "salary": {"currency": null, "max": null, "min": null, "period": "monthly", "term": null}, "salary_visible": false, "title_keywords": [], "responsibilities": ["ad-hoc tasks", "review", "coordinate with", "payment", "administrative tasks", "provide assistance", "shipping document"], "requirements": {"degrees": ["high diploma", "university degree", "fresh graduate"], "majors": [], "languages": ["putonghua", "english", "chinese"], "language_level": ["fluency", "good command", "proficient"], "hard_skills": ["excel", "chinese word processing", "word", "import and export", "c", "processing", "ms office"], "soft_skills": ["highly independent", "self-motivated", "willing to learn", "attentive to details"], "languages_combined": [{"language": "putonghua", "language_level": ["fluency"]}, {"language": "english", "language_level": ["good command"]}, {"language": "chinese", "language_level": ["good command", "proficient"]}]}, "experience_required": {"duration": ["two years"], "field": ["operation", "trading"]}}, {"job_id": "100003009053767", "location_code": "hk", "company": "Hing Sing Engineering Limited", "job_title": "\u6587\u54e1", "description": "\n\u8077\u8cac :\u8ca0\u8cac\u92b7\u552e\u3001\u8ddf\u55ae\u3001\u4e00\u822c\u6587\u66f8\u5de5\u4f5c\uff0c\u4ee5\u53ca\u7cfb\u7d71\u904b\u4f5c(\u5982\u8cc7\u6599\u8f38\u5165\u53ca\u6574\u7406\u5831\u544a)\uff1b\u8655\u7406\u8a02\u55ae\u8ddf\u9032\u3001\u8207\u5ba2\u6236\u548c\u5de5\u5ee0\u5354\u8abf\uff0c\u63a1\u8cfc\u3001\u5b89\u6392\u751f\u7522\u3001\u51fa\u8ca8\u8ddf\u9032(5\u5e74\u6216\u4ee5\u4e0a\u6709\u95dc\u7d93\u9a57)\n\n\u8cc7\u6b77 :\u4e2d\u4e94\u7a0b\u5ea6; 5\u5e74\u7d93\u9a57; \u826f\u597d\u7cb5\u8a9e; \u4e00\u822c\u666e\u901a\u8a71; \u4e00\u822c\u82f1\u8a9e; \u61c2\u95b1\u8b80\u4e2d\u6587; \u7565\u61c2\u8b80\u5beb\u82f1\u6587; \u61c2\u96fb\u5b50\u5831\u95dc; \u61c2\u8655\u7406\u51fa\u5165\u53e3\u6587\u4ef6; \u61c2\u82f1\u6587\u6253\u5b57; \u61c2\u4e2d\u6587\u6253\u5b57; \u5177\u6709\u57fa\u672c\u96fb\u8166\u64cd\u4f5c\u77e5\u8b58; \u9700\u5177\u71df\u696d\u9032\u51fa\u53e3\u53ca\u5831\u95dc\u7d93\u9a57,\u61c2\u8239\u52d9\u8655\u7406,\u6709\u5927\u9678\u5de5\u5ee0\u5c0d\u63a5\u7d93\u9a57,\u6709\u8cac\u4efb\u611f,\u52e4\u596e\u4e3b\u52d5,\u80fd\u7368\u7acb\u8655\u4e8b\n\n\u5f85\u9047 :\u6bcf\u6708$16,000 - $18,000, \u6709\u96d9\u7ce7, \u9280\u884c\u5047\u671f\u53ca\u5e74\u7d42\u734e\u91d1, \u661f\u671f\u4e00\u81f3\u4e94: \u4e0a\u53489\u6642\u81f3\u4e0b\u53486\u6642, \u6bcf\u9031\u5de5\u4f5c5\u5929, \u6bcf\u5929\u5de5\u4f5c 8 \u5c0f\u6642\n\n\u7533\u8acb\u9808\u77e5 :\u6c42\u8077\u8005\u53ef\u96fb\u90f5(Apply Now)\u5c65\u6b77\u8868\u7d66\u5929\u9df9\u8a2d\u5099\u88fd\u9020\u6709\u9650\u516c\u53f8\u3002\u5982\u8981\u7d22\u53d6\u6536\u96c6\u500b\u4eba\u8cc7\u6599\u8072\u660e, \u8acb\u8207\u6881\u5c0f\u59d0(Email)\u806f\u7d61\u3002\n\n", "employment_types": ["Full Time"], "selling_points": [], "locations": ["Kwai Tsing Area"], "categories": ["Admin & HR", "Clerical / Admin Staff", "Others"], "post_time": "2022-01-17T07:29:15Z", "salary": {"currency": null, "max": null, "min": null, "period": "monthly", "term": null}, "salary_visible": false, "title_keywords": ["\u6587\u54e1"], "responsibilities": [], "requirements": {"degrees": [], "majors": [], "languages": [], "language_level": [], "hard_skills": [], "soft_skills": [], "languages_combined": []}, "experience_required": {"duration": [], "field": []}}, {"job_id": "100003009053420", "location_code": "hk", "company": "Taipei Fubon Commercial Bank Co., Ltd", "job_title": "\u517c\u8077\u884c\u653f\u52a9\u7406 (Part-time)", "description": "\n\u8077\u8cac :\u8655\u7406\u4e00\u822c\u6587\u8077\u5de5\u4f5c\n\n\u8cc7\u6b77 :\u5c08\u4e0a\u6559\u80b2\uff1a\u6587\u6191/\u8b49\u66f8; 2\u5e74\u7d93\u9a57; \u826f\u597d\u7cb5\u8a9e; \u4e00\u822c\u666e\u901a\u8a71; \u4e00\u822c\u82f1\u8a9e; \u7565\u61c2\u8b80\u5beb\u4e2d\u6587; \u7565\u61c2\u8b80\u5beb\u82f1\u6587\n\n\u5f85\u9047 :\u6bcf\u6708$13,000 - $17,000, \u6709\u8d85\u6642\u5de5\u4f5c\u6d25\u8cbc \u53ca\u914c\u60c5\u6027\u82b1\u7d05, \u661f\u671f\u4e00\u81f3\u516d: \u4e0a\u53489\u6642\u81f3\u4e0b\u53486\u6642, \u6bcf\u9031\u5de5\u4f5c6\u5929, \u6bcf\u5929\u5de5\u4f5c 9 \u5c0f\u6642\n\n\u7533\u8acb\u9808\u77e5 :\u6c42\u8077\u8005\u53ef\u81f4\u96fb96870595\u8207\u5144\u8aa0\u5de5\u7a0b\u6709\u9650\u516c\u53f8\u674e\u5148\u751f\u806f\u7d61\u3002\n\n", "employment_types": ["Part Time", "Temporary"], "selling_points": [], "locations": ["Tsim Sha Tsui"], "categories": ["Admin & HR", "Clerical / Admin Staff", "Receptionist"], "post_time": "2022-01-17T06:57:41Z", "salary": {"currency": null, "max": null, "min": null, "period": "hourly", "term": null}, "salary_visible": false, "title_keywords": [], "responsibilities": [], "requirements": {"degrees": [], "majors": [], "languages": [], "language_level": [], "hard_skills": [], "soft_skills": [], "languages_combined": []}, "experience_required": {"duration": [], "field": []}}, {"job_id": "100003009052554", "location_code": "hk", "company": "Shun Tak Property Management Ltd", "job_title": "Assistant Officer - Administration & Quality Assurance (Ref: STPML1696)", "description": "Key Responsibilities\n\nProvide general office administration and clerical supports;\nAssist in the service and internal operation audit for HK and Macau property portfolio;\nProvide support and participate in the electronic procurement system;\nAssist in ISO Quality Management System;\nAssist ad-hoc duties as assigned.\n\nRequirements\n\nDegree in Business Administration, Journalism or related disciplines are preferred;\n1-2 years' relevant experience in commercial or public sectors;\nGood command of both spoken and written English and Chinese;\nProficiency in computer knowledge.\n\nWe offer long-term career prospect and competitive remuneration package to the appointed candidate. Please apply in confidence with your detailed resume stating your current and expected salary to Group Human Resources Department\n\nby email to\u00a0recruit(at)shuntakgroup.com\n\nor mail to Penthouse 39/F, West Tower, Shun Tak Centre, 200 Connaught Road Central, Hong Kong\n\n(Please quote reference number and applied position)\n\nThe information supplied by the applicants will be used for recruitment purpose and in accordance with the Personal Data (Privacy) Policy of Shun Tak Group (a copy of which will be provided upon request). Personal data of the unsuccessful applicants will be destroyed in twelve months from the date of application. Only shortlisted candidates will be notified.\n\nwww.shuntakgroup.com", "employment_types": ["Full Time", "Permanent"], "selling_points": ["General office administration & clerical supports", "Assist in the service & internal operation audit", "Assist in ISO Quality Management System"], "locations": ["Central & Western Area"], "categories": ["Accounting", "Audit", "Admin & HR", "Clerical / Admin Staff", "Property / Real Estate", "Property Management"], "post_time": "2022-01-17T03:24:26Z", "salary": {"currency": null, "max": null, "min": null, "period": "monthly", "term": null}, "salary_visible": false, "title_keywords": ["assistant officer"], "responsibilities": ["provide support", "management", "office administration", "quality", "audit", "ad-hoc duties"], "requirements": {"degrees": ["degree"], "majors": ["journalism", "related disciplines", "business administration"], "languages": ["english", "chinese"], "language_level": ["good command"], "hard_skills": [], "soft_skills": [], "languages_combined": [{"language": "english", "language_level": ["good command"]}, {"language": "chinese", "language_level": ["good command"]}]}, "experience_required": {"duration": ["1-2 years"], "field": ["commercial", "relevant experience"]}}, {"job_id": "100003009053484", "location_code": "hk", "company": "Jupiter Lee & Co. Certified Public Accountants (Practising)", "job_title": "\u5be9\u8a08\u6587\u54e1", "description": "\n\u5730\u5340 : \u4e0a\u74b0\n\u8077\u8cac\uff1a \u8ca0\u8cac\u5be9\u8a08\u5de5\u4f5c\n\u8cc7\u6b77\uff1a \u5c08\u4e0a\u6559\u80b2\uff1a\u6587\u6191/\u8b49\u66f8; \u826f\u597d\u7cb5\u8a9e; \u826f\u597d\u666e\u901a\u8a71; \u826f\u597d\u82f1\u8a9e; \u61c2\u8b80\u5beb\u4e2d\u6587; \u61c2\u8b80\u5beb\u82f1\u6587; \u4fee\u8b80\u6703\u8a08\u79d1; \u61c2Peachtree\u6216MYOB; \u7d30\u5fc3\u52e4\u596e; \u6709\u8cac\u4efb\u611f; \u80fd\u7368\u7acb\u8655\u7406\u4e8b\u52d9\n\u5f85\u9047\uff1a \u85aa\u91d1\u9762\u8b70, \u661f\u671f\u4e00\u81f3\u4e94: \u4e0a\u53489\u664215\u5206\u81f3\u4e0b\u53486\u6642\u53ca\u661f\u671f\u516d: \u4e0a\u53489\u6642\u81f3\u4e0b\u53481\u6642, \u6bcf\u9031\u5de5\u4f5c5\u5929\u81f35\u5929\u534a, \u6bcf\u5929\u5de5\u4f5c 7.5 \u5c0f\u6642\n\u7533\u8acb\u9808\u77e5\uff1a\u6c42\u8077\u8005\u53ef\u50b3\u771f(35852208)\u6216\u96fb\u90f5(Apply Now)\u5c65\u6b77\u8868\u7d66\u674e\u6dd1\u82b3\u6703\u8a08\u5e2b\u4e8b\u52d9\u6240\u3002\u5982\u8981\u7d22\u53d6\u6536\u96c6\u500b\u4eba\u8cc7\u6599\u8072\u660e, \u8acb\u8207\u674e\u5973\u58eb(Email)\u806f\u7d61\u3002\n\n", "employment_types": ["Full Time"], "selling_points": [], "locations": ["Central"], "categories": ["Admin & HR", "Clerical / Admin Staff", "Others"], "post_time": "2022-01-17T07:02:45Z", "salary": {"currency": null, "max": null, "min": null, "period": "monthly", "term": null}, "salary_visible": false, "title_keywords": [], "responsibilities": [], "requirements": {"degrees": [], "majors": [], "languages": [], "language_level": [], "hard_skills": [], "soft_skills": [], "languages_combined": []}, "experience_required": {"duration": [], "field": []}}, {"job_id": "100003009053679", "location_code": "hk", "company": "Success Development Information Technology Company Limited", "job_title": "\u4eba\u4e8b\u53ca\u884c\u653f\u52a9\u7406", "description": "\n\u8077\u8cac :\u8655\u7406\u5168\u9762\u7684\u4eba\u529b\u8cc7\u6e90\u8077\u80fd,\u5305\u62ec\u8655\u7406\u54e1\u5de5\u62db\u8058,\u5f37\u7a4d\u91d1,\u85aa\u916c\u798f\u5229,\u5de5\u8cc7\u7ba1\u7406;\u4fdd\u6301\u826f\u597d\u7684\u4eba\u529b\u8cc7\u6e90\u8a18\u9304\u548c\u500b\u4eba\u8cc7\u6599\u6b78\u6a94,\u4f11\u5047\u8a18\u9304,\u51fa\u52e4\u8a18\u9304\u7b49;\u7ba1\u7406\u516c\u53f8\u6703\u54e1\u6578\u64da\u5eab\u53ca\u5236\u4f5c\u71df\u696d\u5831\u544a;\u8ca0\u8cac\u8fa6\u516c\u5ba4\u884c\u653f\u5de5\u4f5c\u5305\u62ec\u8a2d\u5099\u7dad\u8b77\u548c\u8fa6\u516c\u7528\u54c1\u63a1\u8cfc,\u6587\u4ef6\u6574\u7406\u53ca\u6b78\u6a94\u7b49\n\n\u8cc7\u6b77 :\u4e2d\u4e94\u7a0b\u5ea6; 2\u5e74\u7d93\u9a57; \u4e00\u822c\u7cb5\u8a9e; \u4e00\u822c\u666e\u901a\u8a71; \u4e00\u822c\u82f1\u8a9e; \u61c2\u8b80\u5beb\u4e2d\u6587; \u7565\u61c2\u8b80\u5beb\u82f1\u6587; \u61c2Microsoft Office; \u5177\u6709\u4e00\u822c\u4e92\u806f\u7db2\u77e5\u8b58; \u61c2\u82f1\u6587\u6253\u5b57; \u61c2\u5009\u9821/\u901f\u6210\u8f38\u5165\u6cd5; \u53ef\u5373\u6642\u4e0a\u73ed\u512a\u5148(\u6839\u64da\u9700\u57f7\u884c\u81e8\u6642\u5206\u914d\u5de5\u4f5c)\n\n\u5f85\u9047 :\u6bcf\u6708$14,000 - $16,000, \u4e00\u81f3\u4e94:\u4e0a\u53489\u6642\u534a\u81f3\u4e0b\u53486\u6642,\u6bcf\u9031\u5de5\u4f5c5\u5929,\u6bcf\u5929\u5de5\u4f5c 8.5 \u5c0f\u6642(\u8ca0\u8cac\u7b56\u5283\u548c\u7d44\u7e54\u516c\u53f8\u6d3b\u52d5)\n\n\u7533\u8acb\u9808\u77e5 :\u53ef\u96fb\u90f5(Apply Now)\u5c65\u6b77\u8868\u7d66\u6210\u529f\u767c\u5c55\u8cc7\u8a0a\u79d1\u6280\u6709\u9650\u516c\u53f8\u3002\u5982\u8981\u7d22\u53d6\u6536\u96c6\u500b\u4eba\u8cc7\u6599\u8072\u660e, \u8acb\u8207\u5f35\u5c0f\u59d0(Tel:23767000)\u806f\u7d61\u3002\n\n", "employment_types": ["Full Time"], "selling_points": [], "locations": ["Kwun Tong"], "categories": ["Admin & HR", "Clerical / Admin Staff", "Manufacturing", "Others"], "post_time": "2022-01-17T07:20:36Z", "salary": {"currency": null, "max": null, "min": null, "period": "monthly", "term": null}, "salary_visible": false, "title_keywords": [], "responsibilities": [], "requirements": {"degrees": [], "majors": [], "languages": [], "language_level": [], "hard_skills": [], "soft_skills": [], "languages_combined": []}, "experience_required": {"duration": [], "field": []}}, {"job_id": "100003009052623", "location_code": "hk", "company": "Sompo Insurance (Hong Kong) Company Limited", "job_title": "Senior Administration Officer", "description": "Responsibilities\n\n\nIn charge of office maintenance and repair coordination, insurance and licensing renewal, vendor management in a professional manner\nBeing the first contact point with building management office\nMonitor external contractors / service providers for effective maintenance of various systems\nResponsible for managing inventory and document storage\nAct as\u00a0the\u00a0project lead\u00a0for\u00a0office renovation and relocation\nAssist in planning and executing company events and functions (eg: Annual dinner, Christmas party & other staff activities)\nMonitor office expenditure and budgets to enhance cost efficiency\nPerform backup reception duties when necessary\nRequirements\nHolder of Diploma in any discipline\nMinimum of 5 years\u2019 relevant work experience in office administration with supervising a small team and monitoring outsourced contractors\nExposure in office relocation / renovation is\u00a0a must\nProactive with a can-do attitude, attention to details, a strong sense of responsibility\nAble to resolve problems independently\nImmediate availability would be a great advantage\n\nWe offer 5-day week and competitive remuneration package commensurate with qualification and experience.\u00a0 Please send full resume with details of current and expected salary to HR Department by clicking \"Apply Now\".\n\nPersonal data will be used for recruitment purpose only.", "employment_types": ["Full Time", "Permanent"], "selling_points": ["Provide office administration services", "Office relocation / renovation experience prefer", "Immediate available would be advantage"], "locations": ["Quarry Bay"], "categories": ["Admin & HR", "Administration / Operation Manager", "Clerical / Admin Staff", "Receptionist"], "post_time": "2022-01-17T03:35:10Z", "salary": {"currency": null, "max": null, "min": null, "period": "monthly", "term": null}, "salary_visible": false, "title_keywords": ["senior administration officer"], "responsibilities": ["budgets", "management", "cost", "maintenance", "inventory", "systems", "professional manner", "monitor", "renovation", "building management", "repair", "executing", "contact", "coordination", "insurance", "planning"], "requirements": {"degrees": ["diploma"], "majors": [], "languages": [], "language_level": [], "hard_skills": ["small"], "soft_skills": ["independently", "sense of responsibility", "can-do attitude", "attention to details", "proactive"], "languages_combined": []}, "experience_required": {"duration": ["minimum of 5 years"], "field": ["office administration", "team"]}}, {"job_id": "100003009053661", "location_code": "hk", "company": "AccGirl Limited", "job_title": "\u5ba2\u6236\u670d\u52d9\u6587\u54e1 -\u6703\u8a08\u90e8", "description": "\n\u8077\u8cac :\u8ca0\u8cac\u5ba2\u6236\u4e4b\u6703\u8a08\u548c\u7c3f\u8a18\u670d\u52d9\u6709\u95dc\u7684\u5de5\u4f5c, \u5305\u62ec\u4e00\u822c\u65e5\u5e38\u6703\u8a08\u6838\u7b97\u5de5\u4f5c, \u89e3\u7b54\u5ba2\u6236\u67e5\u8a62(\u96fb\u8a71,\u5373\u6642\u901a\u8a0a\u7a0b\u5f0f\u7b49), \u8207\u5ba2\u6236\u6e9d\u901a, \u8655\u7406\u5ba2\u6236\u63d0\u4f9b\u4e4b\u8ca1\u52d9\u6587\u4ef6(\u5982\u9280\u884c\u6708\u7d50\u55ae\u64da,\u767c\u7968,\u6536\u64da\u7b49),\u8a18\u9304\u6703\u8a08\u5e33\u518a; \u7de8\u5236\u6703\u8a08\u8a18\u5e33\u6191\u8b49\u53ca\u96fb\u8166\u5165\u5e33\u7b49\n\n\u8cc7\u6b77 :\u5c08\u4e0a\u6559\u80b2\uff1a\u6587\u6191/\u8b49\u66f8; 1\u5e74\u7d93\u9a57; \u826f\u597d\u7cb5\u8a9e\u512a\u5148; \u826f\u597d\u666e\u901a\u8a71\u512a\u5148; \u4e00\u822c\u82f1\u8a9e; \u61c2\u8b80\u5beb\u4e2d\u6587; \u61c2\u8b80\u5beb\u82f1\u6587; \u61c2\u96fb\u8166\u6587\u66f8\u8655\u7406; \u61c2Microsoft Office; \u5177\u6709\u4e00\u822c\u6703\u8a08\u77e5\u8b58; \u61c2\u4e2d\u82f1\u6587\u96fb\u8166\u64cd\u4f5c; \u5177\u6709\u57fa\u672c\u96fb\u8166\u64cd\u4f5c\u77e5\u8b58; \u6709\u5168\u76e4\u6703\u8a08\u77e5\u8b58, \u6709\u6703\u8a08\u6216\u5ba2\u670d\u4e00\u5e74\u76f8\u95dc\u5de5\u4f5c\u7d93\u9a57\u512a\u5148\n\n\u5f85\u9047 :\u6bcf\u6708$13,000 - $16,000, \u6709\u9280\u884c\u5047\u671f, \u914c\u60c5\u6027\u82b1\u7d05, \u5728\u8077\u57f9\u8a13, \u6649\u5347\u6a5f\u6703, \u8868\u73fe\u734e\u91d1 \u53ca\u5176\u4ed6\u6d25\u8cbc/\u798f\u5229, \u661f\u671f\u4e00\u81f3\u4e94: \u4e0a\u53489\u6642\u81f3\u4e0b\u53486\u6642\u53ca\u661f\u671f\u516d: \u4e0a\u53489\u6642\u81f3\u4e0b\u53481\u6642, \u6bcf\u9031\u5de5\u4f5c5\u5929\u534a\n\n\u7533\u8acb\u9808\u77e5 :\u6c42\u8077\u8005\u53ef\u96fb\u90f5(Apply Now)\u5c65\u6b77\u8868\u7d66\u6703\u8a08\u59b9\u6709\u9650\u516c\u53f8\u3002\u5982\u8981\u7d22\u53d6\u6536\u96c6\u500b\u4eba\u8cc7\u6599\u8072\u660e, \u8acb\u8207\u8b5a\u5c0f\u59d0(Email)\u806f\u7d61\u3002\n\n", "employment_types": ["Full Time"], "selling_points": [], "locations": ["Sheung Wan"], "categories": ["Admin & HR", "Clerical / Admin Staff", "Others"], "post_time": "2022-01-17T07:18:44Z", "salary": {"currency": null, "max": null, "min": null, "period": "monthly", "term": null}, "salary_visible": false, "title_keywords": ["\u5ba2\u6236\u670d\u52d9\u6587\u54e1"], "responsibilities": [], "requirements": {"degrees": [], "majors": [], "languages": [], "language_level": [], "hard_skills": [], "soft_skills": [], "languages_combined": []}, "experience_required": {"duration": [], "field": []}}, {"job_id": "100003009053527", "location_code": "hk", "company": "VH International (Holdings) Limited", "job_title": "\u92b7\u552e\u6587\u54e1", "description": "\n\u8077\u8cac :\u8ca0\u8cac\u6587\u66f8\u548c\u884c\u653f\u652f\u6301,\u5831\u544a\u548c\u5206\u6790,\u8655\u7406\u5e38\u898f\u7684\u92b7\u552e\u548c\u884c\u653f\u8077\u8cac,\u5305\u62ec\u5f62\u5f0f\u767c\u7968\u548c\u63a1\u8cfc\u8a02\u55ae\u7684\u7c3d\u767c\u548c\u6b78\u6a94,\u8207\u5de5\u5ee0\u5c31\u751f\u7522\u548c\u4ea4\u8ca8\u8a08\u5283\u9032\u884c\u806f\u7d61,\u62dc\u8a2a\u672c\u5730\u4e3b\u8981\u5408\u4f5c\u5925\u4f34,\u7dad\u8b77\u696d\u52d9\u95dc\u4fc2,\u6839\u64da\u9700\u8981\u5354\u52a9\u57f7\u884c\u81e8\u6642\u4efb\u52d9\n\n\u8cc7\u6b77 :\u4e2d\u4e94\u7a0b\u5ea6; 2\u5e74\u7d93\u9a57; \u826f\u597d\u7cb5\u8a9e; \u826f\u597d\u666e\u901a\u8a71; \u826f\u597d\u82f1\u8a9e; \u61c2\u8b80\u5beb\u4e2d\u6587; \u61c2\u8b80\u5beb\u82f1\u6587; \u61c2\u96fb\u8166\u6587\u66f8\u8655\u7406; \u61c2Microsoft Office; \u5177\u6709\u4e00\u822c\u4e92\u806f\u7db2\u77e5\u8b58; \u61c2\u4e2d\u82f1\u6587\u96fb\u8166\u64cd\u4f5c\n\n\u5f85\u9047 :\u6bcf\u6708$15,000, \u6709\u4f63\u91d1, \u661f\u671f\u4e00\u81f3\u4e94: \u4e0a\u53489\u6642\u81f3\u4e0b\u53486\u6642, \u6bcf\u9031\u5de5\u4f5c5\u5929, \u6bcf\u5929\u5de5\u4f5c 8 \u5c0f\u6642\n\n\u7533\u8acb\u9808\u77e5 :\u6c42\u8077\u8005\u53ef\u50b3\u771f(81617602)\u6216\u96fb\u90f5(Apply Now)\u5c65\u6b77\u8868\u7d66\u8c50\u5c71\u570b\u969b(\u63a7\u80a1)\u6709\u9650\u516c\u53f8\u3002\u5982\u8981\u7d22\u53d6\u6536\u96c6\u500b\u4eba\u8cc7\u6599\u8072\u660e, \u8acb\u8207\u5085\u5c0f\u59d0(Email)\u806f\u7d61\u3002\n\n", "employment_types": ["Full Time"], "selling_points": [], "locations": ["Kwun Tong"], "categories": ["Admin & HR", "Clerical / Admin Staff", "Others"], "post_time": "2022-01-17T07:06:18Z", "salary": {"currency": null, "max": null, "min": null, "period": "monthly", "term": null}, "salary_visible": false, "title_keywords": [], "responsibilities": [], "requirements": {"degrees": [], "majors": [], "languages": [], "language_level": [], "hard_skills": [], "soft_skills": [], "languages_combined": []}, "experience_required": {"duration": [], "field": []}}, {"job_id": "100003009052710", "location_code": "hk", "company": "The Natural Tea Company (H.K.) Ltd.", "job_title": "Accounts Clerk", "description": "We are looking for an Accounts Clerk to join our company.\n\nThe ideal candidate will have at least basic accounting or bookkeeping experience. He/she will be required to maintain day to day accounts of the company, inputting of sales data and other excel spreadsheets. Someone with experience and knowledge of F&B/retail accounting is desirable. We seek someone who is organised, hard working and self-motivated to join our team.\n\nRequirements:\n\nMinimum Form 5 or above\n\nMinimum 1 years relevant experience\n\nExperience with F&B/retail accounting\u00a0\n\nKnowledge in PC applications including MS Excel, Word, Chinese Word Processing\n\nGood command of spoken and written English, Cantonese\n\nThe company offers the successful candidate an attractive salary,\u00a05 \u00bd day work week with alternate weekends off, annual leave and\u00a013 month pay.\n\nInterested parties please email a cover letter and CV with expected salary and date available\u00a0to hr @ thenaturalteacompany . com", "employment_types": ["Full Time"], "selling_points": [], "locations": ["Chai Wan"], "categories": ["Accounting", "Accountant", "Accounting Clerk / Supervisor", "Admin & HR", "Clerical / Admin Staff"], "post_time": "2022-01-17T03:46:44Z", "salary": {"currency": null, "max": null, "min": null, "period": "monthly", "term": null}, "salary_visible": false, "title_keywords": ["accounts clerk"], "responsibilities": ["maintain", "data"], "requirements": {"degrees": ["form 5 or above"], "majors": [], "languages": ["cantonese", "english", "chinese"], "language_level": ["good command"], "hard_skills": ["excel", "basic", "chinese word processing", "word", "pc applications", "ms excel"], "soft_skills": ["hard working", "organised", "self-motivated", "ideal"], "languages_combined": [{"language": "cantonese", "language_level": ["good command"]}, {"language": "english", "language_level": ["good command"]}, {"language": "chinese", "language_level": []}]}, "experience_required": {"duration": ["minimum 1 years"], "field": ["f&b", "accounting", "relevant experience", "retail"]}}, {"job_id": "100003009053953", "location_code": "hk", "company": "Able Engineering Company Limited", "job_title": "Assistant Clerical Officer", "description": "Level 2 or equivalent or above in five subjects including Mathematics in the Hong Kong Diploma of Secondary Education Examination (HKDSEE), or equivalent; or\nLevel 2 / Grade E or above in five subjects including Mathematics in the Hong Kong Certificate of Education Examination (HKCEE), or equivalent;\nMet the language proficiency requirement of Level 2 or above in Chinese Language and English Language in HKDSEE or HKCEE, or equivalent; and\nChinese word processing speed of 20 words per minute and English word processing speed of 30 words per minute and knowledge in the application of common business software\n\nWe offer competitive salary package and career development opportunity to the successful candidate. Interested parties may send your full resume, present and expected salary, available date and contact number by clicking \"Apply Now\".\n\n\n\nTo visit our website for more information: www.ableeng.com.hk\n\n(As an Equal Opportunities Employer, Able is committed to eliminating discrimination in employment. The vacancy advertised is open to all applicants meeting the basic entry requirement irrespective of their disability, sex, marital status, pregnancy, age, family status, sexual orientation or race etc. Applicants not hearing from us within 6 months may consider their applications unsuccessful. Personal data collected will be used for recruitment related purposes only.)", "employment_types": ["Full Time"], "selling_points": [], "locations": ["Not Specified"], "categories": ["Admin & HR", "Administration / Operation Manager", "Clerical / Admin Staff", "HR Supporting Staff"], "post_time": "2022-01-17T07:50:21Z", "salary": {"currency": null, "max": null, "min": null, "period": "monthly", "term": null}, "salary_visible": false, "title_keywords": ["officer", "assistant"], "responsibilities": ["software"], "requirements": {"degrees": ["certificate", "diploma", "secondary education"], "majors": ["mathematics"], "languages": ["english", "chinese"], "language_level": ["proficiency"], "hard_skills": ["business software", "chinese word processing", "word processing", "words"], "soft_skills": [], "languages_combined": [{"language": "english", "language_level": ["proficiency"]}, {"language": "chinese", "language_level": ["proficiency"]}]}, "experience_required": {"duration": [], "field": []}}, {"job_id": "100003009046541", "location_code": "hk", "company": "Pride Retail Financial Services", "job_title": "Secretary / Administrative Assistant (Full Time / Part Time)", "description": "Job Responsibilities :\n\nAssist in the administration process of sales, claims, events and recruitment related activities;\nArrange meetings, workshops, interviews, training, etc.\nProvide clerical support for the team\n\n\u00a0Job Requirements :\u00a0\n\nAssociate degree holder or above\nFresh graduate will also be considered\nA pass in mathematics in the HKCEE / HKDSE is a MUST\nAt least 1 year relevant work experience\nFamiliar with MS Office\nResponsible, positive attitude and good communication skills\n\nWe offer excellent career prospects and attractive remuneration package to the right candidate.\n\nTo apply please click the \"APPLY NOW\" button in the below.\u00a0\n\nWe are equal opportunity employers committed to workforce diversity and fair employment practices. All data collected will be used for recruitment purpose only.", "employment_types": ["Full Time", "Part Time"], "selling_points": [], "locations": ["Kwai Fong"], "categories": ["Admin & HR", "Clerical / Admin Staff"], "post_time": "2022-01-16T21:50:16Z", "salary": {"currency": null, "max": null, "min": null, "period": "monthly", "term": null}, "salary_visible": false, "title_keywords": ["administrative assistant", "secretary"], "responsibilities": ["provide clerical support", "recruitment", "arrange meetings", "administration"], "requirements": {"degrees": ["associate degree", "hkdse", "fresh graduate"], "majors": ["mathematics"], "languages": [], "language_level": [], "hard_skills": ["ms office"], "soft_skills": ["positive attitude", "communication skills", "responsible"], "languages_combined": []}, "experience_required": {"duration": ["at least 1 year"], "field": []}}, {"job_id": "100003009033125", "location_code": "hk", "company": "\u5b78\u65af\u6559\u80b2", "job_title": "\u5168\u8077\u63a5\u5f85\u54e1 / Receptionist / \u5ba2\u6236\u52a9\u7406 / Customer Service Assistant *Recent Graduate will be considered*", "description": "\u8077\u8cac \u00a0:\n\n\u61c9\u7b54\u5b78\u751f\u53ca\u5bb6\u9577\u67e5\u8a62\u53ca\u5b89\u6392\u8abf\u5802\n\u8655\u7406\u5831\u540d\u4e8b\u5b9c\n\u6574\u7406\u6587\u4ef6\u53ca\u6587\u66f8\u8655\u7406\n\u8655\u7406\u88dc\u7fd2\u4e2d\u5fc3\u65e5\u5e38\u5927\u5c0f\u4e8b\u52d9\n\n\u8077\u4f4d\u8981\u6c42 \u00a0:\n\n\u4e2d\u5b78\u7562\u696d\uff0c\u540c\u7b49\u5b78\u6b77\u6216\u4ee5\u4e0a\u7a0b\u5ea6\n\u61c2\u4e2d\u82f1\u6253\u5b57\uff0c\u719f\u8b58\u57fa\u672c\u96fb\u8166\u64cd\u4f5c\n\u7a4d\u6975\u9032\u53d6\uff0c\u7d30\u5fc3\uff0c\u5f85\u4eba\u6709\u79ae\uff0c\u6709\u8cac\u4efb\u611f\n\u5177\u76f8\u95dc\u5de5\u4f5c\u7d93\u9a57\u8005\u512a\u5148\n\n\u5de5\u4f5c\u6642\u9593 :\n\n\u4e94\u5929\u5de5\u4f5c\u65e5, \u8f2a\u4f11\n\u661f\u671f\u4e00\u81f3\u4e94\u00a0(12:00-21:00) \u53ca\u661f\u671f\u516d(09:00-19:00) 1\u5c0f\u6642\u5348\u98ef\u6642\u9593\n\u9022\u661f\u671f\u65e5\u53ca\u516c\u773e\u5047\u671f\u4f11\u606f\n\u5de5\u4f5c\u5730\u9ede: \u592a\u5b50/\u7063\u4ed4/\u6c99\u7530/\u8343\u7063/\u5143\u6717 (\u53ef\u6309\u5c45\u4f4f\u5730\u5340\u5b89\u6392)\n\n\n\u54e1\u5de5\u53ef\u4eab\u00a0:\u00a0\n\n\u52e4\u5de5\u734e\n\u5b9a\u671f\u54e1\u5de5\u6d3b\u52d5\u53ca\u805a\u9910\n\u52de\u5de5\u4fdd\u96aa\n\u91ab\u7642\u4fdd\u96aa\n\u6709\u85aa\u75c5\u5047\u3001\u5a5a\u5047\u3001\u4f8d\u7522\u5047\u3001\u751f\u65e5\u798f\u5229\n\u9022\u661f\u671f\u65e5\u53ca\u516c\u773e\u5047\u671f\u4f11\u606f\n\n\u6709\u8207\u8da3\u8005\u8acb\u628a\u5c65\u6b77\u8868\u96fb\u90f5\u7d66\u6211\u5011\uff0c\u6211\u5011\u6703\u81f4\u96fb\u76f8\u7d04\u9762\u8a66\u6642\u9593\u3002", "employment_types": ["Full Time"], "selling_points": ["\u61c9\u7b54\u5b78\u751f\u53ca\u5bb6\u9577\u67e5\u8a62", "\u8655\u7406\u88dc\u7fd2\u4e2d\u5fc3\u65e5\u5e38\u5927\u5c0f\u4e8b\u52d9", "\u4e94\u5929\u5de5\u4f5c\u65e5\u516c\u773e\u5047\u671f\u4f11\u606f"], "locations": ["Not Specified"], "categories": ["Admin & HR", "Clerical / Admin Staff", "Receptionist", "Education", "Others"], "post_time": "2022-01-16T21:50:09Z", "salary": {"currency": null, "max": null, "min": null, "period": "monthly", "term": null}, "salary_visible": false, "title_keywords": ["receptionist", "\u5ba2\u6236\u52a9\u7406", "customer service assistant"], "responsibilities": [], "requirements": {"degrees": [], "majors": [], "languages": [], "language_level": [], "hard_skills": [], "soft_skills": [], "languages_combined": []}, "experience_required": {"duration": [], "field": []}}, {"job_id": "100003009051610", "location_code": "hk", "company": "Charven Development Limited", "job_title": "\u9ad8\u7d1a\u884c\u653f\u53ca\u4eba\u4e8b\u52a9\u7406 Senior Administrative and HR Assistant", "description": "\u5de5\u4f5c\u5167\u5bb9\u53ca\u8077\u8cac:\n\n\u4e00\u822c\u79d8\u66f8\u8077\u52d9;\n\u5354\u8abf\u53ca\u5b89\u6392\u8463\u4e8b\u65e5\u5e38\u884c\u7a0b;\n\u7ba1\u7406\u8b70\u7a0b\u4e26\u5b89\u6392\u6703\u8b70\u53ca\u7d04\u6703,\u6703\u8b70\u8a18\u9304;\n\u5354\u52a9\u65e5\u5e38\u4eba\u529b\u8cc7\u6e90\u5de5\u4f5c:\u7c4c\u8fa6\u57f9\u8a13\u3001\u62db\u52df\u3001\u516c\u53f8\u6d3b\u52d5;\n\u5718\u968a\u696d\u7e3e\u5831\u544a\u8ffd\u8e2a\u6210\u54e1\u696d\u7e3e/\u734e\u9805;\n\u8655\u7406\u8fa6\u516c\u5ba4\u884c\u653f\u5de5\u4f5c\uff0c\u5305\u62ec\u8a02\u8cfc\u8cfc\u6587\u5177\u3001\u8fa6\u516c\u5ba4\u7528\u54c1\u3001\u540c\u4e8b\u51fa\u52e4\u53ca\u5047\u671f\u7d00\u9304\u7b49;\n\u8655\u7406\u4e0a\u7d1a\u59d4\u6d3e\u7684\u5176\u4ed6\u5de5\u4f5c\n\n\u8077\u4f4d\u8981\u6c42:\n\n\u4e00\u5e74\u7d93\u9a57\u6216\u4ee5\u4e0a\n\u5c08\u4e0a\u6559\u80b2\u6216\u5b78\u58eb\u5b78\u4f4d(\u5546\u696d/\u884c\u653f\u7ba1\u7406/\u4eba\u529b\u8cc7\u6e90/\u793e\u6703\u79d1\u5b78)\n\u826f\u597d\u7cb5\u8a9e\u3001\u826f\u597d\u666e\u901a\u8a71\u3001\u826f\u597d\u82f1\u6587\n\u61c2\u8b80\u5beb\u4e2d\u6587\u53ca\u82f1\u6587\n\u61c2Microsoft Office\u53ca\u4e2d\u82f1\u6587\u57fa\u672c\u96fb\u8166\u64cd\u4f5c\n\n\u5de5\u4f5c\u5730\u9ede: \u89c0\u5858\u5340\n\n\u798f\u5229\u5305\u62ec\uff1a\n\n\u9280\u884c\u5047\u671f\u3001\u4e94\u5929\u5de5\u4f5c\u3001\u91ab\u7642\u4fdd\u969c\u3001\u63d0\u4f9b\u54e1\u5de5\u65e9\u5348\u81b3\u300110\u5929\u6709\u85aa\u5e74\u5047\u3001\u8003\u8a66\u5047\u3001\u5a5a\u5047\u3001\u52e4\u5de5\u734e\u3002\n\n\u00a0\u6709\u610f\u61c9\u5fb5\u8005\u8acb\u628a\u8a73\u7d30\u7684\u5c65\u6b77\u767c\u9001\u7d66\u6211\u5011\uff0c\u8acb\u8a3b\u660e\u73fe\u8077\u85aa\u91d1\u548c\u671f\u671b\u85aa\u91d1\u3002", "employment_types": ["Full Time"], "selling_points": ["\u52e4\u5de5\u734e", "10\u5929\u5927\u5047", "\u4e94\u5929\u5de5\u4f5c"], "locations": ["Kwun Tong"], "categories": ["Admin & HR", "Administration / Operation Manager", "Clerical / Admin Staff", "Secretary"], "post_time": "2022-01-16T21:50:30Z", "salary": {"currency": null, "max": null, "min": null, "period": "monthly", "term": null}, "salary_visible": false, "title_keywords": ["senior administrative", "hr assistant"], "responsibilities": [], "requirements": {"degrees": [], "majors": [], "languages": [], "language_level": [], "hard_skills": [], "soft_skills": [], "languages_combined": []}, "experience_required": {"duration": [], "field": []}}, {"job_id": "100003009053716", "location_code": "hk", "company": "APAC Solution Corporation Limited", "job_title": "\u5e97\u52d9\u92b7\u552e\u6587\u54e1", "description": "\n\u8077\u8cac :\u4ecb\u7d39\u96fb\u5b50\u7522\u54c1\u53ca\u914d\u4ef6\uff1b\u8ca0\u8cac\u5e97\u8216\u65e5\u5e38\u6587\u66f8\u5de5\u4f5c\uff1b\u92b7\u552e\u55ae\u64da\u53ca\u8ca8\u6b3e\u8655\u7406\uff1b\u8ca8\u54c1\u51fa\u5165\u5831\u544a\u53ca\u5009\u5b58\u7ba1\u7406\uff1b\u5e97\u9762\u5546\u54c1\u6574\u7406\u53ca\u9673\u5217\uff1b\u89e3\u7b54\u9867\u5ba2\u5c0d\u7522\u54c1\u53ca\u670d\u52d9\u7684\u67e5\u8a62\n\n\u8cc7\u6b77 :\u4e2d\u4e94\u7a0b\u5ea6; \u826f\u597d\u7cb5\u8a9e\u512a\u5148; \u4e00\u822c\u666e\u901a\u8a71; \u4e00\u822c\u82f1\u8a9e; \u61c2\u8b80\u5beb\u4e2d\u6587; \u7565\u61c2\u8b80\u5beb\u82f1\u6587; \u5177\u6709\u57fa\u672c\u96fb\u8166\u64cd\u4f5c\u77e5\u8b58; \u5de5\u4f5c\u4e3b\u52d5\u7a4d\u6975\u3001\u826f\u597d\u6e9d\u901a\u6280\u5de7\u3001\u80fd\u7368\u7acb\u5de5\u4f5c\uff1b\u719f\u6089\u96fb\u5b50\u7522\u54c1\u53ca\u53ef\u7acb\u5373\u4e0a\u73ed\u512a\u5148\n\n\u5f85\u9047 :\u6bcf\u6708$11,000 - $15,000, \u6709\u52e4\u5de5\u734e\u91d1, \u5e74\u504712\u5929, \u9280\u884c\u5047\u671f, \u5728\u8077\u57f9\u8a13, \u91ab\u7642\u798f\u5229 \u53ca\u4f63\u91d1, \u4e0a\u534811\u6642\u81f3\u4e0b\u53489\u6642, \u6bcf\u9031\u5de5\u4f5c6\u5929,\u8f2a\u4f11, \u6bcf\u5929\u5de5\u4f5c 9 - 10 \u5c0f\u6642\n\n\u7533\u8acb\u9808\u77e5 :\u6c42\u8077\u8005\u53ef\u96fb\u90f5(Apply Now)\u5c65\u6b77\u8868\u7d66\u6cdb\u4e9e\u89e3\u6c7a\u65b9\u6848\u6709\u9650\u516c\u53f8\u3002\u5982\u8981\u7d22\u53d6\u6536\u96c6\u500b\u4eba\u8cc7\u6599\u8072\u660e, \u8acb\u8207\u885b\u5c0f\u59d0(Email)\u806f\u7d61\u3002\n\n", "employment_types": ["Full Time"], "selling_points": [], "locations": ["Kwun Tong"], "categories": ["Admin & HR", "Clerical / Admin Staff", "Others"], "post_time": "2022-01-17T07:24:11Z", "salary": {"currency": null, "max": null, "min": null, "period": "monthly", "term": null}, "salary_visible": false, "title_keywords": [], "responsibilities": [], "requirements": {"degrees": [], "majors": [], "languages": [], "language_level": [], "hard_skills": [], "soft_skills": [], "languages_combined": []}, "experience_required": {"duration": [], "field": []}}, {"job_id": "100003009053854", "location_code": "hk", "company": "Hey Home Property Limited", "job_title": "\u8a2d\u8a08\u6587\u54e1", "description": "\n\u8077\u8cac :\u8ca0\u8cac\u8655\u7406\u6587\u4ef6\u7d00\u9304\u53ca\u5b58\u6a94\uff0c\u6574\u7406\u5ba2\u6236\u8cc7\u6599\uff0c\u6536\u767c\u96fb\u90f5\u3001\u63a5\u807d\u96fb\u8a71\uff0c\u53ca\u5e02\u5834\u63a8\u5ee3\u8a2d\u8a08\u3001\u793e\u4ea4\u5a92\u9ad4\u5ba3\u50b3\u3001\u7db2\u7ad9\u7f8e\u8853\u8a2d\u8a08\n\n\u8cc7\u6b77 :\u5c08\u4e0a\u6559\u80b2\uff1a\u6587\u6191/\u8b49\u66f8; 1\u5e74\u7d93\u9a57; \u4e00\u822c\u7cb5\u8a9e; \u4e00\u822c\u666e\u901a\u8a71; \u826f\u597d\u82f1\u8a9e\u512a\u5148; \u61c2\u8b80\u5beb\u4e2d\u6587; \u61c2\u8b80\u5beb\u82f1\u6587; \u61c2PhotoShop; \u61c2Microsoft Office; \u61c2Illustrator; \u61c2\u4e00\u822c\u7db2\u9801\u88fd\u4f5c\n\n\u5f85\u9047 :\u6bcf\u6708$12,000 - $14,000, \u4e0a\u534810\u6642\u81f3\u4e0b\u53487\u6642, \u6bcf\u9031\u5de5\u4f5c6\u5929,\u8f2a\u4f11\n\n\u7533\u8acb\u9808\u77e5 :\u6c42\u8077\u8005\u53ef\u81f4\u96fb62562568\u8207\u559c\u5c45\u7269\u696d\u6709\u9650\u516c\u53f8\u99ae\u5c0f\u59d0\u806f\u7d61\u3002\n\n", "employment_types": ["Full Time"], "selling_points": [], "locations": ["Cheung Sha Wan"], "categories": ["Admin & HR", "Clerical / Admin Staff", "Others"], "post_time": "2022-01-17T07:37:53Z", "salary": {"currency": null, "max": null, "min": null, "period": "monthly", "term": null}, "salary_visible": false, "title_keywords": [], "responsibilities": [], "requirements": {"degrees": [], "majors": [], "languages": [], "language_level": [], "hard_skills": [], "soft_skills": [], "languages_combined": []}, "experience_required": {"duration": [], "field": []}}, {"job_id": "100003009051782", "location_code": "hk", "company": "Hing Cheong Engineering (HK) Limited", "job_title": "Administrative Assistant / Office Assistant", "description": "\uff0eHong Kong Identity Card is a MUST\n\nJob Responsibilities\n\uff0eHandle administrative and clerical duties for the construction team;\n\uff0eTo provide general administrative support Project team, with any related tasks assigned\n\uff0eProvide support including filing, answering inquiry and data refreshment in website etc.\n\uff0eHard working & Responsible\n\uff0ePerform ad-hoc projects as assigned\n\uff0eReliable, Positive and Helpful\n\uff0eHandling telephone inquiries and messages, greeting guests\n\uff0eGeneral administration & HR support, mails and courier arrangement\n\uff0eClerical works and ad hoc assignments\n\uff0eSupport company functions/staff activities\n\nJob Requirements:\n\uff0eForm 5 (HKCEE)/ Form 6 (DSE) or above\n\uff0eGood command of both English and Chinese\n\uff0eProficient in Microsoft Office applications\n\uff0eFresh graduate are also welcome\n\uff0ePC knowledge in MS Office, Chinese Word Processing etc.\n\uff0eAble to work under pressure\n\uff0eImmediate available is preferred\n\nWe offer good career prospects and attractive remuneration to the right candidate, benefits including discretionary bonus\n\nInterested parties may send C.V. indicating expected salary by clicking 'Apply Now'.\n\nPersonal data collected will be used for recruitment purpose only.", "employment_types": ["Full Time"], "selling_points": [], "locations": ["Tuen Mun Area"], "categories": ["Admin & HR", "Clerical / Admin Staff", "Others"], "post_time": "2022-01-17T01:14:17Z", "salary": {"currency": null, "max": null, "min": null, "period": "monthly", "term": null}, "salary_visible": false, "title_keywords": ["administrative assistant", "office assistant"], "responsibilities": ["data", "hr", "general administrative support", "website", "ad hoc assignments", "ad-hoc projects", "administration"], "requirements": {"degrees": ["dse"], "majors": [], "languages": ["english", "chinese"], "language_level": [], "hard_skills": ["chinese word processing", "ms office", "microsoft office"], "soft_skills": ["work under pressure"], "languages_combined": [{"language": "english", "language_level": []}, {"language": "chinese", "language_level": []}]}, "experience_required": {"duration": [], "field": []}}, {"job_id": "100003009053668", "location_code": "hk", "company": "AccGirl Limited", "job_title": "\u5ba2\u6236\u670d\u52d9\u6587\u54e1-\u516c\u53f8\u79d8\u66f8\u90e8", "description": "\n\u8077\u8cac :\u89e3\u7b54\u5ba2\u6236\u67e5\u8a62(\u96fb\u8a71,\u5373\u6642\u901a\u8a0a\u7a0b\u5f0f\u7b49), \u8ca0\u8cac\u70ba\u5ba2\u6236\u63d0\u4f9b\u670d\u52d9\u4e26\u8207\u5ba2\u6236\u6e9d\u901a\u670d\u52d9\u4e8b\u9805; \u8655\u7406\u53ca\u8ddf\u9032\u5ba2\u6236\u4e4b\u670d\u52d9; \u4e00\u822c\u65e5\u5e38\u6587\u66f8\u5de5\u4f5c(\u65e5\u5e38\u6578\u64da\u8f38\u5165\u53ca\u8655\u7406, \u5b58\u6a94\u7b49); \u5176\u4ed6\u4e0a\u7d1a\u5206\u914d\u4e4b\u5de5\u4f5c (\u6709\u6642\u9593\u7ba1\u7406\u6280\u5de7)\n\n\u8cc7\u6b77 :\u5c08\u4e0a\u6559\u80b2\uff1a\u6587\u6191/\u8b49\u66f8; \u826f\u597d\u7cb5\u8a9e\u512a\u5148; \u826f\u597d\u666e\u901a\u8a71\u512a\u5148; \u4e00\u822c\u82f1\u8a9e; \u61c2\u8b80\u5beb\u4e2d\u6587; \u61c2\u8b80\u5beb\u82f1\u6587; \u61c2\u96fb\u8166\u6587\u66f8\u8655\u7406; \u61c2Microsoft Office; \u5177\u6709\u4e00\u822c\u6703\u8a08\u77e5\u8b58; \u61c2\u4e2d\u82f1\u6587\u96fb\u8166\u64cd\u4f5c; \u5177\u6709\u57fa\u672c\u96fb\u8166\u64cd\u4f5c\u77e5\u8b58; \u826f\u597d\u6e9d\u901a\u6280\u5de7; \u6709\u5ba2\u670d/\u6703\u8a08\u76f8\u95dc\u5de5\u4f5c\u7d93\u9a57\u512a\u5148\n\n\u5f85\u9047 :\u6bcf\u6708$12,800 - $15,000, \u6709\u96d9\u7ce7, \u9280\u884c\u5047\u671f, \u8868\u73fe\u734e\u91d1, \u5728\u8077\u57f9\u8a13, \u6649\u5347\u6a5f\u6703, \u9032\u4fee\u6d25\u8cbc \u53ca\u914c\u60c5\u6027\u82b1\u7d05, \u661f\u671f\u4e00\u81f3\u4e94: \u4e0a\u53489\u6642\u81f3\u4e0b\u53486\u6642\u53ca\u661f\u671f\u516d: \u4e0a\u53489\u6642\u81f3\u4e0b\u53481\u6642, \u6bcf\u9031\u5de5\u4f5c5\u5929\u534a, \u6bcf\u5929\u5de5\u4f5c 9 \u5c0f\u6642\n\n\u7533\u8acb\u9808\u77e5 :\u6c42\u8077\u8005\u53ef\u96fb\u90f5(Apply Now)\u5c65\u6b77\u8868\u7d66\u6703\u8a08\u59b9\u6709\u9650\u516c\u53f8\u3002\u5982\u8981\u7d22\u53d6\u6536\u96c6\u500b\u4eba\u8cc7\u6599\u8072\u660e, \u8acb\u8207\u8b5a\u5c0f\u59d0(Email)\u806f\u7d61\u3002\n\n", "employment_types": ["Full Time"], "selling_points": [], "locations": ["Sheung Wan"], "categories": ["Admin & HR", "Clerical / Admin Staff", "Others"], "post_time": "2022-01-17T07:19:18Z", "salary": {"currency": null, "max": null, "min": null, "period": "monthly", "term": null}, "salary_visible": false, "title_keywords": ["\u5ba2\u6236\u670d\u52d9\u6587\u54e1"], "responsibilities": [], "requirements": {"degrees": [], "majors": [], "languages": [], "language_level": [], "hard_skills": [], "soft_skills": [], "languages_combined": []}, "experience_required": {"duration": [], "field": []}}, {"job_id": "100003009054025", "location_code": "hk", "company": "aalis", "job_title": "Administrative Officer - 5 day work", "description": "Job Responsibilities\n\nProvide Comprehensive administrative support\nProvide full spectrum of personal and secretarial support\nPreparing daily reports\nHandle all internal claims and invoices in the correct process, ensuring necessary supporting materials and concurrence\nPrepare regular admin related statistics and reports for management review\nHandle all administration tasks and ad-hoc projects\n\nJob Requirements\n\nHigher Diploma / Bachelor\u2019s degree holder\nCommunicate politely and sensitively, ensuring that any issues are followed up promptly\nProficient in Microsoft excel application and sensitive to numbers\nGood organisation, reporting and communication skills\nResult and detail oriented, efficient and able to multi tasks\nGood command of spoken and written English and Chinese\nImmediately available is preferred\n\n\nCompany Benefits:\n\n5-day work\nPaid annual leave; Bank holiday; Birthday off; Marriage leave\nFriendly company culture; stylish working environment; convenience location\nStaff purchase discount\nYear end discretionary bonus\nGreat promotion opportunities\n\nWe offer attractive remuneration and benefit package to the right candidate.\n\nInterested parties please send your full resume with current and expected salary, date of availability to\u00a0Human Resources Department by clicking \"Apply Now\"\n\n*Personal data collected is strictly confidential and will only be used for recruitment related purpose.", "employment_types": ["Full Time", "Permanent"], "selling_points": ["All-round administrative support", "Good organisation and reporting  skills", "Immediately available is preferred"], "locations": ["Aberdeen"], "categories": ["Admin & HR", "Administration / Operation Manager", "Clerical / Admin Staff", "HR Supporting Staff"], "post_time": "2022-01-17T08:07:27Z", "salary": {"currency": null, "max": null, "min": null, "period": "monthly", "term": null}, "salary_visible": false, "title_keywords": ["administrative officer"], "responsibilities": ["invoices", "administrative support", "reports", "secretarial support", "daily reports", "ad-hoc projects", "management review", "administration"], "requirements": {"degrees": ["diploma", "bachelor", "degree holder"], "majors": [], "languages": ["english", "chinese"], "language_level": ["good command"], "hard_skills": ["microsoft excel"], "soft_skills": ["efficient", "communication skills", "detail oriented", "organisation", "sensitive to numbers"], "languages_combined": [{"language": "english", "language_level": ["good command"]}, {"language": "chinese", "language_level": ["good command"]}]}, "experience_required": {"duration": [], "field": []}}, {"job_id": "100003009054378", "location_code": "hk", "company": "Strategic Public Relations Group Limited", "job_title": "Admin Assistant (6 Months Contract)", "description": "Responsibilities:\n\nProvide full spectrum administrative and clerical support to the Company\nProvide support to operation and renovation projects\nResponsible for logistics arrangement of meetings and events held at office\nResponsible for coordination of internal events and activities\nAssist in ensuring operation excellence of all office facilities\nMaintain the office supply inventory\nHandle any ad-hoc duties as required\n\n\u00a0Requirements:\n\n\nDiploma or above, with 2 years or above experience in office administration\nExperience in managing office renovation projects would be an advantage\nStrong sense of responsibility, well organized, meticulous & self-motivated\nProficiency in PC skills, including MS office and Chinese processing\nFluency in both written and spoken English, Chinese and Mandarin\nWilling to learn and able to work under pressure\nImmediate available preferred", "employment_types": ["Full Time", "Contract"], "selling_points": ["Provide administrative and clerical support", "5 Days Work/ Bank Holiday", "12 Days AL/Birthday Leave"], "locations": ["Admiralty"], "categories": ["Admin & HR", "Clerical / Admin Staff", "Others"], "post_time": "2022-01-17T09:19:00Z", "salary": {"currency": null, "max": null, "min": null, "period": "monthly", "term": null}, "salary_visible": false, "title_keywords": ["admin assistant"], "responsibilities": ["provide support", "ad-hoc duties", "logistics arrangement", "inventory", "renovation", "maintain", "coordination", "administrative and clerical support"], "requirements": {"degrees": ["diploma or above"], "majors": [], "languages": ["english", "chinese", "mandarin"], "language_level": ["fluency", "proficiency"], "hard_skills": ["processing", "pc skills", "ms office"], "soft_skills": ["meticulous", "self-motivated", "sense of responsibility", "willing to learn", "well organized", "work under pressure"], "languages_combined": [{"language": "english", "language_level": ["fluency"]}, {"language": "chinese", "language_level": ["fluency", "proficiency"]}, {"language": "mandarin", "language_level": ["fluency"]}]}, "experience_required": {"duration": ["2 years"], "field": ["office administration"]}}, {"job_id": "100003009053772", "location_code": "hk", "company": "Bee's International Group Limited", "job_title": "\u6703\u8a08\u6587\u54e1", "description": "\n\u8077\u8cac :\u8ca0\u8cac\u65e5\u5e38\u6703\u8a08\u5de5\u4f5c, \u5305\u62ec\u7531\u92b7\u552e\u81f3\u61c9\u6536\u5e33, \u63a1\u8cfc\u81f3\u61c9\u4ed8\u5e33, \u9280\u884c\u5c0d\u5e33, \u5b9a\u671f\u5831\u544a, \u8cc7\u6599\u8f38\u5165, \u6587\u4ef6\u5b58\u6a94, \u5354\u52a9\u6708\u7d50\u7b49 (With OT Meal Allowance, OT Travel Allowance, Free Books & Movies)\n\n\u8cc7\u6b77 :\u5c08\u4e0a\u6559\u80b2\uff1a\u6587\u6191/\u8b49\u66f8; \u826f\u597d\u7cb5\u8a9e; \u4e00\u822c\u82f1\u8a9e; \u7565\u61c2\u8b80\u5beb\u4e2d\u6587; \u61c2\u8b80\u5beb\u82f1\u6587; \u61c2MYOB; \u61c2MS Excel; \u5177\u6709\u4e00\u822c\u6703\u8a08\u77e5\u8b58\n\n\u5f85\u9047 :\u6bcf\u6708$12,000 - $16,000, \u6709\u5e74\u504710\u5929, \u914c\u60c5\u6027\u82b1\u7d05, \u751f\u65e5\u50472\u5929, \u9280\u884c\u5047\u671f, \u65c5\u904a\u734e\u8cde, \u5a5a\u50475\u5929, \u661f\u671f\u4e00\u81f3\u4e94: \u4e0a\u53489\u6642\u81f3\u4e0b\u53486\u6642, \u6bcf\u9031\u5de5\u4f5c5\u5929, Flexible lunch hours, occasional OT required\n\n\u7533\u8acb\u9808\u77e5 :\u6c42\u8077\u8005\u53ef\u96fb\u90f5(Apply Now)\u5c65\u6b77\u8868\u7d66THE BEES HOLDINGS LIMITED\u3002\u5982\u8981\u7d22\u53d6\u6536\u96c6\u500b\u4eba\u8cc7\u6599\u8072\u660e, \u8acb\u8207\u9ec3 \u5148\u751f(Email)\u806f\u7d61\u3002\n\n", "employment_types": ["Full Time"], "selling_points": [], "locations": ["Quarry Bay"], "categories": ["Admin & HR", "Clerical / Admin Staff", "Others"], "post_time": "2022-01-17T07:30:09Z", "salary": {"currency": null, "max": null, "min": null, "period": "monthly", "term": null}, "salary_visible": false, "title_keywords": [], "responsibilities": [], "requirements": {"degrees": [], "majors": [], "languages": [], "language_level": [], "hard_skills": ["excel"], "soft_skills": ["flexible"], "languages_combined": []}, "experience_required": {"duration": [], "field": []}}, {"job_id": "100003009052459", "location_code": "hk", "company": "Caf\u00e9 de Coral Group Limited", "job_title": "(Assistant) Account Executive (School Catering)", "description": "Responsibilities:\n\nDaily Operation\n\nManage daily operation of meal box delivery to schools, including on-site support and causal workers\u2019 performance monitoring\nHandle feedback and enquiry from clients\nSupport meal box preparation and delivery arrangement at Reheat Center\u00a0\n\nBusiness Development Support\n\n\nAssist Account Manager to organize Production Center visit and food tasting presentation\nPrepare related tender documents\nHandle general inquiry from customers including parents and school representatives, and clerical duties\nAssists in ad hoc duties or projects as required\n\nRequirements:\n\nDiploma or above in relevant disciplines\nAt least 1 year hands-on experience in F&B or Catering Industry\nOutgoing, patient, good interpersonal skills and able to work with different level of staff\nWell organized, detail-minded and problem solving\n\nGood spoken in Cantonese and good command of written English and Chinese\nProficiency in MS Office and Chinese Word Processing\nFresh graduates will also be considered\n\n**Candidate with less experience will be considered as Assistant Account Executive**\n\n\nInterested parties please send full resume with PRESENT & EXPECTED SALARY to Human Resources Department by clicking\u00a0\"APPLY NOW\"\u00a0or Whatsapp 6875 4164 for details.\uff08Please quote Reference No. or as email subject\uff09\n\n\n\nWe are an EQUAL OPPORTUNITIES EMPLOYER.\n\nAll information received will be kept in strict confidence and be used for employment-related purpose only.", "employment_types": ["Full Time", "Permanent"], "selling_points": ["Manage daily operation of meal box delivery", "hands-on experience in F&B or Catering Industry", "5 days work; 15 days AL"], "locations": ["Tsuen Wan Area"], "categories": ["Admin & HR", "Clerical / Admin Staff", "Hospitality / F & B", "Food & Beverage", "Sales, CS & Business Devpt", "Account Servicing"], "post_time": "2022-01-17T03:05:09Z", "salary": {"currency": null, "max": null, "min": null, "period": "monthly", "term": null}, "salary_visible": false, "title_keywords": ["account executive", "assistant"], "responsibilities": ["ad hoc duties", "monitoring", "daily operation", "tender documents"], "requirements": {"degrees": ["diploma or above"], "majors": [], "languages": ["cantonese", "english", "chinese"], "language_level": ["proficiency", "good command", "good"], "hard_skills": ["problem solving", "chinese word processing", "ms office"], "soft_skills": ["outgoing", "detail-minded", "well organized", "problem solving", "hands-on", "interpersonal skills", "patient"], "languages_combined": [{"language": "cantonese", "language_level": ["good command", "good"]}, {"language": "english", "language_level": ["good command", "good"]}, {"language": "chinese", "language_level": ["proficiency", "good command", "good"]}]}, "experience_required": {"duration": ["at least 1 year"], "field": ["f&b"]}}, {"job_id": "100003009053590", "location_code": "hk", "company": "Sun Eagle Development Limited", "job_title": "\u52a9\u7406\u6587\u54e1**", "description": "\n\u8077\u8cac :\u5354\u52a9\u96fb\u8166\u8cc7\u6599\u8f38\u5165,\u4e00\u822c\u6587\u66f8\u8655\u7406\uff0c\u6838\u5c0d\u7269\u6599\u53ca\u5176\u4ed6\u4e0a\u7d1a\u6307\u6d3e\u5de5\u4f5c\n\n\u8cc7\u6b77 :\u4e2d\u4e09\u7a0b\u5ea6; \u826f\u597d\u7cb5\u8a9e\u512a\u5148; \u4e00\u822c\u666e\u901a\u8a71; \u4e00\u822c\u82f1\u8a9e; \u61c2\u8b80\u5beb\u4e2d\u6587; \u7565\u61c2\u8b80\u5beb\u82f1\u6587\n\n\u5f85\u9047 :\u6bcf\u6708$11,000 - $12,500, \u6709\u8d85\u6642\u5de5\u4f5c\u6d25\u8cbc, \u8868\u73fe\u734e\u91d1, \u661f\u671f\u4e00\u81f3\u516d: \u4e0a\u53488\u6642\u81f3\u4e0b\u53485\u6642, \u6bcf\u9031\u5de5\u4f5c6\u5929, \u6bcf\u5929\u5de5\u4f5c 8 \u5c0f\u6642, \u5348\u81b3 1 \u5c0f\u6642\uff0c\u9593\u4e2d\u9700\u8981\u8d85\u6642\u5de5\u4f5c\n\n\u7533\u8acb\u9808\u77e5 :\u6c42\u8077\u8005\u53ef\u81f4\u96fb65433053\u8207\u9d6c\u6689\u767c\u5c55\u6709\u9650\u516c\u53f8\u970d\u5c0f\u59d0\u806f\u7d61\u3002\n\n", "employment_types": ["Full Time"], "selling_points": [], "locations": ["Tsuen Wan Area"], "categories": ["Admin & HR", "Clerical / Admin Staff", "Others"], "post_time": "2022-01-17T07:12:48Z", "salary": {"currency": null, "max": null, "min": null, "period": "monthly", "term": null}, "salary_visible": false, "title_keywords": ["\u52a9\u7406\u6587\u54e1"], "responsibilities": [], "requirements": {"degrees": [], "majors": [], "languages": [], "language_level": [], "hard_skills": [], "soft_skills": [], "languages_combined": []}, "experience_required": {"duration": [], "field": []}}, {"job_id": "100003009054794", "location_code": "hk", "company": "Vennic Limited", "job_title": "Operations Administrative Assistant (6-months Contract)", "description": "Responsibilities\n\nProvide general clerical and administrative support\nPerform general administrative duties such as data checking, data entry and filing\nPrepare memo, notice, minutes whenever required as requested\nCoordinate regular meetings, prepare agenda and meeting materials\nMaintain label and shops related materials when need\nCoordinate SCM system\nPerform other ad hoc tasks as assigned\n\nRequirements\n\nF.5/DSE graduated or above\nAt least 1 year experience\nIndependent, result-oriented with good time management, excellent interpersonal, communication and problem-solving skills\nProficient in MS Office and Chinese word processing is a must\nGood typing skill & communication skill in both Chinese & English\nImmediate available is preferable\n\nWe offer 5-day work week, on-the-job development program and rewarding career opportunities for ambitious individuals who are looking for challenges. If you aspire to an exciting and rewarding career, send your resume immediately with your present and expected salary.\n\n(All personal data collected will be used for recruitment purpose only.)", "employment_types": ["Temporary", "Contract"], "selling_points": ["General clerical and administrative support", "6-months Contract", "Entry Level"], "locations": ["Lai Chi Kok"], "categories": ["Admin & HR", "Clerical / Admin Staff"], "post_time": "2022-01-17T11:07:52Z", "salary": {"currency": null, "max": null, "min": null, "period": "monthly", "term": null}, "salary_visible": false, "title_keywords": ["administrative assistant", "operations"], "responsibilities": ["data entry and filing", "data", "administrative support", "memo", "ad hoc tasks", "checking", "coordinate", "maintain", "administrative duties"], "requirements": {"degrees": ["dse"], "majors": [], "languages": ["english", "chinese"], "language_level": ["good", "proficient"], "hard_skills": ["problem-solving skills", "chinese word processing", "typing", "ms office"], "soft_skills": ["independent", "interpersonal", "communication skill", "communication", "problem-solving skills", "time management", "result-oriented"], "languages_combined": [{"language": "english", "language_level": ["good"]}, {"language": "chinese", "language_level": ["good", "proficient"]}]}, "experience_required": {"duration": ["at least 1 year"], "field": []}}, {"job_id": "100003009054593", "location_code": "hk", "company": "Top Blade Limited", "job_title": "HR & Admin Assistant", "description": "Job Description\n\nResponsible for the full scope of\u00a0HR functions including recruitment, interview arrangement, employment contract, payroll, MPF and\u00a0other related matters\nUpdating databases, attendance\u00a0records such as annual leave, sick leave in HR system\nPeriodically review and appraise with company staff\nPrepare HR-related statistics and reports for management periodically\nWork closely with all departments\u00a0on administrative related issues\nOversee daily administrative activities such\u00a0as office supplies, equipment maintenance,\u00a0facilities management etc\nHandle general clerical duties such as data entry, renewal of license, insurance for the company; expenses reimbursement; service application\nAssist in contract renewal, check and manage invoices\nProvide administrative support for company's shops\nDraft and prepare company memo, internal letters and useful forms\nPerform ad hoc duties as assigned\n\nJob Requirements\n\nDiploma holder or above in Human\u00a0Resources Management,\u00a0Business Administration or related discipline\nRelevant experience in HR\u00a0and Office Administration is an advantage\nWell versed in HK Employment Ordinance\u00a0and related regulations\nProficient in MS Office including Word, Excel\nPleasant personality and good team player\nSelf-motivated, well-organized,\u00a0analytical and confident in\u00a0resolving complex issues\nBenefits:\n5 days working\nGeneral holidays (SH & PH)\n10-15 days annual leave\n14 weeks of maternity leave and 5 days paternity leave\nMarriage leave\nCompassionate leave\nSalary\n\n$14,000 - $16,000\n\nFor applicants who interested in joining our team, please WhatsApp your resume to\u00a09383 6435 (Miss Lai) or email via \u7acb\u5373\u7533\u8acb\n\n(All information provided by job applicants will be used for recruitment purpose only.)", "employment_types": ["Full Time"], "selling_points": [], "locations": ["Central"], "categories": ["Admin & HR", "Clerical / Admin Staff", "Hospitality / F & B", "Food & Beverage", "HR Supporting Staff"], "post_time": "2022-01-17T10:10:22Z", "salary": {"currency": null, "max": null, "min": null, "period": "monthly", "term": null}, "salary_visible": false, "title_keywords": ["hr & admin assistant"], "responsibilities": ["memo", "provide administrative support", "ad hoc duties", "invoices", "data entry", "expenses", "reports", "interview arrangement", "attendance", "management", "mpf", "office supplies", "review", "payroll", "administrative activities", "maintenance", "hr", "letters", "recruitment", "databases", "insurance"], "requirements": {"degrees": ["diploma holder"], "majors": ["business administration"], "languages": [], "language_level": [], "hard_skills": ["excel", "word", "ms office"], "soft_skills": ["confident", "good team player", "self-motivated", "well-organized", "pleasant"], "languages_combined": []}, "experience_required": {"duration": [], "field": ["office administration", "hr", "relevant experience"]}}, {"job_id": "100003009042190", "location_code": "hk", "company": "Estate Agents Authority", "job_title": "ADMINISTRATIVE ASSISTANT (Licensing)  (Ref No.: EAA-2022/02)", "description": "Key Responsibilities\nThe incumbent will be posted to the Licensing Section to handle the following:\n\n\nvet and pre-approve license applications\nassist in monitoring the progress of various license applications\nassist in the administrative and logistical arrangement for committee meetings\ncompile statistical reports\nliaise with mainland authorities in relation to the mutual recognition scheme\nsupervise and coach junior / new team members\nRequirements\n\n\nA recognized university degree\nAt least 2 years\u2019 relevant experience; preferably in customer service\nGood command of both written and spoken English and Chinese; fluency in Putonghua is an advantage\nProficiency in software applications (MS Word, Excel, Powerpoint, Access and Chinese word processing)\nGood interpersonal and communication skills\nStrong organizational skills and meticulous\nBe able to work independently and under pressure\nTerms of Appointment\nCompetitive remuneration package commensurate with the selected candidate\u2019s qualifications and experience will be offered. The appointee will initially be offered a 3-year contract, subject to renewal upon satisfactory performance and the service needs of the Authority.\nApplication Procedure\nApplications with full resume indicating your current and expected salaries and your public examination results should be sent to: Human Resources Section, Estate Agents Authority, 7/F, E-Trade Plaza, 24 Lee Chung Street, Chaiwan, Hong Kong or via email by clicking \"Apply Now\"\u00a0not later than\u00a031 January 2022. Please mark \u201cPrivate and Confidential\u201d on the envelope and quote the post applied for and its reference number on the envelope.\nCandidates who are not invited to attend an interview within 6 weeks from the closing date may assume their applications unsuccessful. Applications may be considered for other suitable positions within the Authority. All applications will be treated in strict confidence. Personal data provided in the applications will only be used for recruitment-related purposes. All information on non-shortlisted applicants will be destroyed after 6 months.\u00a0\n\n\nWE ARE AN EQUAL\u00a0OPPORTUNITIES EMPLOYER", "employment_types": ["Full Time", "Contract"], "selling_points": [], "locations": ["Chai Wan"], "categories": ["Admin & HR", "Clerical / Admin Staff", "Public / Civil", "Civil Services", "Sales, CS & Business Devpt", "Customer Service - Supervisor / Officer"], "post_time": "2022-01-16T21:50:00Z", "salary": {"currency": null, "max": null, "min": null, "period": "monthly", "term": null}, "salary_visible": false, "title_keywords": ["administrative assistant"], "responsibilities": ["liaise with", "license applications", "monitoring", "reports"], "requirements": {"degrees": ["university degree"], "majors": [], "languages": ["putonghua", "english", "chinese"], "language_level": ["fluency", "advantage", "proficiency", "good command"], "hard_skills": ["excel", "chinese word processing", "powerpoint", "ms word"], "soft_skills": ["communication skills", "meticulous", "organizational skills", "work independently", "under pressure", "confidence", "customer service", "interpersonal"], "languages_combined": [{"language": "putonghua", "language_level": ["fluency", "advantage"]}, {"language": "english", "language_level": ["good command"]}, {"language": "chinese", "language_level": ["proficiency", "good command"]}]}, "experience_required": {"duration": ["at least 2 years"], "field": ["relevant experience"]}}, {"job_id": "100003009053430", "location_code": "hk", "company": "\u767c\u5229\u884c\u6709\u9650\u516c\u53f8", "job_title": "\u8fa6\u516c\u5ba4\u52a9\u7406\u8ddf\u55ae\u6587\u54e1", "description": "\n\u8077\u8cac :\u8ca0\u8cac\u8655\u7406\u96fb\u8a71\u4e0b\u55ae, \u96fb\u8166\u51fa\u55ae, \u5b89\u6392\u51fa\u8ca8\u8868, \u8207\u5ba2\u4eba\u6e9d\u901a, \u8655\u7406\u4e00\u822c\u6587\u66f8\u5de5\u4f5c, \u751f\u7522\u55ae\u8ddf\u9032\u53ca\u8cc7\u6599\u6574\u7406\n\n\u8cc7\u6b77 :\u4e2d\u4e94\u7a0b\u5ea6; 1\u5e74\u7d93\u9a57; \u4e00\u822c\u7cb5\u8a9e; \u4e00\u822c\u666e\u901a\u8a71; \u4e00\u822c\u82f1\u8a9e; \u61c2\u8b80\u5beb\u4e2d\u6587; \u61c2\u8b80\u5beb\u82f1\u6587; \u61c2\u4e2d\u82f1\u6587\u96fb\u8166\u64cd\u4f5c; \u5b88\u6642, \u5de5\u4f5c\u76e1\u8cac, \u5177\u5408\u4f5c\u7cbe\u795e, \u6709\u8cac\u4efb\u5fc3, \u6709\u79ae\u8c8c\n\n\u5f85\u9047 :\u6bcf\u6708$12,500 - $13,500, \u6709\u91ab\u7642\u4fdd\u96aa, \u751f\u65e5\u5047\u53ca\u5e74\u7d42\u914c\u60c5\u6027\u82b1\u7d05, \u661f\u671f\u4e00\u81f3\u516d: \u4e0a\u53488\u6642\u81f3\u4e0b\u53485\u664215\u5206, \u6bcf\u9031\u5de5\u4f5c6\u5929\n\n\u7533\u8acb\u9808\u77e5 :\u6c42\u8077\u8005\u53ef\u81f4\u96fb26738388\u8207\u767c\u5229\u884c\u6709\u9650\u516c\u53f8\u9673\u5148\u751f\u806f\u7d61\u3002\n\n", "employment_types": ["Full Time"], "selling_points": [], "locations": ["Not Specified"], "categories": ["Admin & HR", "Clerical / Admin Staff", "Others"], "post_time": "2022-01-17T06:58:50Z", "salary": {"currency": null, "max": null, "min": null, "period": "monthly", "term": null}, "salary_visible": false, "title_keywords": [], "responsibilities": [], "requirements": {"degrees": [], "majors": [], "languages": [], "language_level": [], "hard_skills": [], "soft_skills": [], "languages_combined": []}, "experience_required": {"duration": [], "field": []}}, {"job_id": "100003009052131", "location_code": "hk", "company": "The Hong Kong Institution of Engineers", "job_title": "Programme Planning & Special Duties Officer (5-Day Work)", "description": "Duties:\n\nTo provide necessary coordination and assistance to the organisation of seminars/webinars, events, learned society activities and programmes, and ad-hoc projects\nTo assist in conducting studies/researches for specific topic(s), and collate appropriate information to facilitate the Section in executing all its tasks and activities\nTo provide secretarial support to meetings and ad-hoc committees\nTo assist in the co-ordination of matters relating to membership benefits, school and publication education programmes, etc.\nTo provide documentary support in handling enquiries and complaints\n\nRequirements:\n\nUniversity Graduate, preferably with 1-2 years work experience\nExperience in handlung complaints is an added advantage\nExcellent command of written and spoken English and Chinese\nAttention to details\nStrong PC skills in MC Word, Excel and Chinese word processing\nPossess experience and knowledge of event and online seminar execution will be an advantage\n\nPlease apply in confidence with full career details and salary expectation to the Chief Executive and Secretary, The Hong Kong Institution of Engineers, 9/F Island Beverley, No 1 Great George Street, Causeway Bay, Hong Kong, or click \u201cApply Now\u201d to submit your application. Applicants should indicate clearly on the envelope and in the letter for the post they are applying.\n\nAll information provided by applicants will be treated in strict confidence and used only for recruitment purpose.\u00a0 Only shortlisted candidates will be notified.\u00a0 All personal data of unsuccessful applicants will be destroyed after completion of the recruitment exercise.", "employment_types": ["Full Time"], "selling_points": ["Assist in conducting seminars/webinars and events", "Assist in conducting studies/researches", "Provide secretariat support to meetings/committees"], "locations": ["Causeway Bay"], "categories": ["Admin & HR", "Clerical / Admin Staff", "Secretary", "Others"], "post_time": "2022-01-17T02:11:56Z", "salary": {"currency": null, "max": null, "min": null, "period": "monthly", "term": null}, "salary_visible": false, "title_keywords": ["officer"], "responsibilities": ["ad-hoc", "executing", "secretarial support", "coordination", "ad-hoc projects"], "requirements": {"degrees": [], "majors": [], "languages": [], "language_level": [], "hard_skills": [], "soft_skills": [], "languages_combined": []}, "experience_required": {"duration": [], "field": []}}, {"job_id": "100003009053152", "location_code": "hk", "company": "Hong Kong School of Motoring", "job_title": "Assistant Operation Officer / Assistant Duty Officer", "description": "Duties:\n\nBe responsible for routine clerical duties including data input, records updating and reports preparation, etc.\nProvide support to ensure facilities of Learning Centre and Learning Vehicles / Motorcycles are in good conditions for operation \u00a0\nHandle the enquires from customers\nUndertake assigned work for operations and customer services if necessary.\n\nRequirements:\u00a0\n\nCompletion of secondary school education or above\nHolder of driving license (classes 1, 2 and / or 3)\u00a0\nAt least 1 year of customer services related working experience\nTeamwork, friendly, self-motivated and able to work under pressure\nGood presentation, communication and computer skills\nWilling to work on shift\n\nFresh graduates with sound academic background and part-time experience will be considered.\n\nWorking Location:\n\nShatin Road Safety Center\u00a0-\u00a0No. 138, Sha Tin Wai Road, Siu Lek Yuen, Shatin\nAp Lei Chau Safety Center - No. 68 Lee Nam Road, Ap Lei Chau, Hong Kong\nYuen Long Road Safety Center\u00a0- No. 38 Chung Yip Road, Nam Sang Wai, Yuen Long\n\nWe will offer attractive remuneration package, comprehensive on-the-job training and career growth opportunities to the right candidate. Interested candidates, please send application enclosing resume stating career and salary history to Human Resources Department, Hong Kong School of Motoring, 1/F Administration Building, No. 138 Sha Tin Wai Road, Siu Lek Yuen, Shatin, New Territories or by clicking \"Apply Now\" to submit the online application.\n\nWe are an equal opportunity employer and welcome applications from all qualified candidates. All information provided by applicants will be treated in strictest confidence and handled confidentially for recruitment-related purposes within the company and our associated company. We regret to inform that only shortlisted applicants will be notified. Applicants may be considered for other suitable positions within the company over a one-year period, after which their personal data will be destroyed.", "employment_types": ["Full Time", "Permanent"], "selling_points": ["Clerical duties (data input, records update, etc)", "At least 1 year of customer services experience", "Attractive performance bonus"], "locations": ["Not Specified"], "categories": ["Admin & HR", "Clerical / Admin Staff", "Sales, CS & Business Devpt", "Customer Service - Supervisor / Officer", "Others", "Student / Fresh Graduate / No Experience"], "post_time": "2022-01-17T06:08:40Z", "salary": {"currency": null, "max": null, "min": null, "period": "monthly", "term": null}, "salary_visible": false, "title_keywords": ["officer", "operation officer", "assistant"], "responsibilities": ["provide support", "operations", "data input", "customer services", "reports"], "requirements": {"degrees": [], "majors": [], "languages": [], "language_level": [], "hard_skills": ["computer skills"], "soft_skills": ["self-motivated", "teamwork", "communication", "friendly", "presentation", "work under pressure"], "languages_combined": []}, "experience_required": {"duration": ["at least 1 year"], "field": ["related", "customer services"]}}, {"job_id": "100003009054143", "location_code": "hk", "company": "Walton International Group Limited", "job_title": "Administrative Assistant (Land Services)", "description": "Responsibilities\n\n\nPerform office clerical duties such as data entry, filing and scanning\nProvide administrative and clerical support for the department\nResponsible for administrative work that concerns:\u00a0legal documents preparation;\u00a0sales order tracking;\u00a0client data management\nAssist ad hoc projects and perform other duties as assigned\nQualifications\n\nHigher Diploma or equivalent\u00a0\nHighly advanced skills of Microsoft office tools\nGood command of English and Chinese\nAbility of multitasking, prioritizing and working with deadlines\u00a0\nAdaptable, embracing and supportive to change\n\nAble to cope with fast-paced working environment and handle ad hoc duties\n\nWhy Walton\n\nAligning with a pioneer and industry leader in the land based real estate investment industry\nCompetitive salary package\nFriendly and professional working environment\nFun, energetic co-workers who share the same core values and strategies\n\nInterested candidates are invited to forward a resume by clicking apply now.\n\nPlease visit\u00a0Walton.com for company information.\n\nWe would like to thank all applicants for their interest in this position; however, only those selected for interviews will be contacted.", "employment_types": ["Full Time", "Permanent"], "selling_points": [], "locations": ["Admiralty"], "categories": ["Admin & HR", "Clerical / Admin Staff"], "post_time": "2022-01-17T08:32:49Z", "salary": {"currency": null, "max": null, "min": null, "period": "monthly", "term": null}, "salary_visible": false, "title_keywords": ["administrative assistant"], "responsibilities": ["scanning", "order tracking", "management", "perform other duties", "ad hoc duties", "administrative work", "data entry", "data", "ad hoc projects", "administrative and clerical support"], "requirements": {"degrees": ["diploma"], "majors": [], "languages": ["english", "chinese"], "language_level": ["good command"], "hard_skills": ["data management", "fun", "microsoft office"], "soft_skills": ["supportive", "advanced", "responsible", "adaptable", "friendly", "energetic", "prioritizing"], "languages_combined": [{"language": "english", "language_level": ["good command"]}, {"language": "chinese", "language_level": ["good command"]}]}, "experience_required": {"duration": [], "field": []}}, {"job_id": "100003009054601", "location_code": "hk", "company": "SAVILLS GUARDIAN", "job_title": "Assistant Administration Officer / Administration Assistant", "description": "F.5 or above\nMinimum\u00a01\u00a0year relevant working experience\nGood command of written and spoken English and Chinese\nHands-on\u00a0PC knowledge in MS Office\nWell-organized with a strong sense of responsibility, detail-minded and capable to work under pressure\nMaintain a complete and updated personnel records of newcomers, termination and movement, to ensure accuracy and compliance in HR system\nHandle monthly payroll, attendance record, work injury cases\u00a0and leave management\nProvide general clerical support and administrative duties\nCoordinating with different parties, answering telephone enquiries\u00a0and other ad hoc duties assigned by the supervisor\nApplicants with more experience will be considered as\u00a0Assistant Administration Officer\n\nWe offer competitive salary package to the right appointee. Applicants are requested submit detailed resume with present and expected salary by clicking \"APPLY NOW\".\n\nPlease Quote Emp. Ref. no. : AO/SS/012022\n\n[Personal data provided will be used strictly in accordance with our personal data policies, a copy of which will be provided immediately upon request.]", "employment_types": ["Full Time", "Permanent"], "selling_points": [], "locations": ["Hung Hom"], "categories": ["Admin & HR", "Clerical / Admin Staff", "Others", "HR Supporting Staff"], "post_time": "2022-01-17T10:12:15Z", "salary": {"currency": null, "max": null, "min": null, "period": "monthly", "term": null}, "salary_visible": false, "title_keywords": ["administration assistant", "assistant administration officer"], "responsibilities": ["ad hoc duties", "attendance", "management", "administration", "hr", "compliance", "personnel records", "clerical support", "maintain", "administrative duties", "payroll", "work under pressure"], "requirements": {"degrees": [], "majors": [], "languages": ["english", "chinese"], "language_level": ["good command"], "hard_skills": ["pc knowledge", "ms office"], "soft_skills": ["detail-minded", "capable", "sense of responsibility", "well-organized", "hands-on", "work under pressure"], "languages_combined": [{"language": "english", "language_level": ["good command"]}, {"language": "chinese", "language_level": ["good command"]}]}, "experience_required": {"duration": ["minimum 1 year"], "field": ["relevant working experience", "administration"]}}, {"job_id": "100003009052642", "location_code": "hk", "company": "Tai Luen Coffee Co Ltd", "job_title": "Temporary Clerk", "description": "Job Descriptions:\n\nProvide full spectrum of administrative and clerical support in daily operations\nAssist to prepare monthly reports, documents , correspondence and summaries\u00a0\nAssist in ad hoc assignments\n\n\u00a0The ideal candidate should be :\n\nDiploma in Business Administration or related disciplines or above\u00a0\nAble to work independently, well organized, strong sense of responsibility, detail-minded, self-motivated, good communication and interpersonal skills\nGood command in spoken and written English and Chinese\nProficiency in MS Office software application and Chinese word processing\nImmediate available is highly preferred\n\nPlease send your application with resume and expected salary to The HR Manager, Tai Luen Coffee Company Limited, 7/F, DCH Building, 20 Kai Cheung Road, Kowloon Bay or send your application online by clicking\u00a0\"Apply Now\".\n\nInformation provided will be for the purpose of selection within the company and only shortlisted candidates will be contacted. All applications will be retained for a maximum period of 6 months.\u00a0", "employment_types": ["Part Time", "Temporary"], "selling_points": [], "locations": ["Shatin Area"], "categories": ["Admin & HR", "Clerical / Admin Staff", "Transportation & Logistics", "Shipping", "Supply Chain"], "post_time": "2022-01-17T03:37:46Z", "salary": {"currency": null, "max": null, "min": null, "period": "monthly", "term": null}, "salary_visible": false, "title_keywords": ["temporary clerk"], "responsibilities": ["software", "monthly reports", "hr", "communication", "daily operations", "ad hoc assignments", "administrative and clerical support", "administration"], "requirements": {"degrees": ["diploma"], "majors": ["related disciplines", "business administration"], "languages": ["english", "chinese"], "language_level": ["proficiency", "good command"], "hard_skills": ["chinese word processing", "ms office"], "soft_skills": ["detail-minded", "work independently", "self-motivated", "sense of responsibility", "well organized", "communication and interpersonal skills", "ideal"], "languages_combined": [{"language": "english", "language_level": ["good command"]}, {"language": "chinese", "language_level": ["proficiency", "good command"]}]}, "experience_required": {"duration": [], "field": []}}, {"job_id": "100003009054181", "location_code": "hk", "company": "Hong Kong Baptist University", "job_title": "Clerk (PR0396/21-22)", "description": "SCHOOL OF CHINESE MEDICINE\n\nClinical Division\n\nClerk (PR0396/21-22)\n\nDuties:\nhandle and check the daily income of the clinics;\nprepare invoice for payment;\nhandle petty cash reimbursement;\ncalculate part-time staff salary;\nprovide support to office administration, meetings and events;\nanswer internal and external enquires; and\nperform any other duties as assigned.\nRequirements:\n\na higher diploma or an associate degree;\nat least one year of relevant work experience;\nproficiency in common computer applications including MS Office, Excel and Chinese word processing;\ngood interpersonal skills and a strong sense of responsibility; and\nability to work independently and be self-motivated.\nImmediate availability will be an advantage.\n\nShortlisted candidates will be invited to attend a computer test.\n\nSalary will be commensurate with qualifications and experience.\n\nApplication Procedure:\n\nApplicants are invited to submit their applications at the HKBU e-Recruitment System (jobs.hkbu.edu.hk). Applicants not invited for interview 8 weeks after the closing date may consider their applications unsuccessful. Details of the University\u2019s Personal Information Collection Statement can be found at http://hro.hkbu.edu.hk/pics.\n\nThe University reserves the right not to make an appointment for the post advertised, and the appointment will be made according to the terms and conditions then applicable at the time of offer.\n\nClosing date: 29 January 2022", "employment_types": ["Full Time"], "selling_points": ["a higher diploma or an associate degree", "one year of relevant work experience", "proficiency in common computer applications"], "locations": ["Kowloon City"], "categories": ["Admin & HR", "Clerical / Admin Staff", "Others", "Education", "Others"], "post_time": "2022-01-17T08:41:45Z", "salary": {"currency": null, "max": null, "min": null, "period": "monthly", "term": null}, "salary_visible": false, "title_keywords": ["clerk"], "responsibilities": ["any other duties", "provide support", "invoice", "office administration", "payment"], "requirements": {"degrees": ["associate degree", "diploma"], "majors": [], "languages": ["chinese"], "language_level": ["proficiency"], "hard_skills": ["excel", "make", "chinese word processing", "ms office"], "soft_skills": ["work independently", "interpersonal skills", "self-motivated", "sense of responsibility"], "languages_combined": [{"language": "chinese", "language_level": ["proficiency"]}]}, "experience_required": {"duration": ["at least one year"], "field": []}}, {"job_id": "100003009052484", "location_code": "hk", "company": "Offmax Limited", "job_title": "Sales Support Clerk", "description": "\u00a0\u00a0Provide general administration and clerical support.\n\u00a0 Communicate with different parties for sales related issue.\n\u00a0 Assist in ad-hoc duties as assigned\n\n\u00a0Requirements\n\n\u00a0\u00a0DSE or above\n\u00a0 Fresh graduate will also be considered.\n\u00a0 Good command of English, Cantonese and Mandarin.\n\u00a0 Proficiency in MS Office and Chinese word processing.\n\u00a0 Responsible, self-motivated, service oriented thinking with good interpersonal skills.\n\u00a0 Immediate available is highly preferred.\n\nWe offer competitive remuneration package including annual leave, medical coverage, MPF and professional training to the right candidate.\n\nInterested parties, please send resume with CURRENT & EXPECTED SALARY by APPLY\u00a0\u00a0NOW.\n\nPersonal data providing by job applicant will be used strictly in accordance with the employer\u2019s personal data policies, and will be destroyed after recruitment period.", "employment_types": ["Full Time"], "selling_points": ["5 days work", "Near MTR Station", "Annual Leave 12 days"], "locations": ["North Point"], "categories": ["Admin & HR", "Clerical / Admin Staff", "Sales, CS & Business Devpt", "Sales Administration"], "post_time": "2022-01-17T03:09:50Z", "salary": {"currency": null, "max": null, "min": null, "period": "monthly", "term": null}, "salary_visible": false, "title_keywords": ["clerk", "sales"], "responsibilities": ["communicate with", "clerical support", "ad-hoc duties", "administration"], "requirements": {"degrees": ["fresh graduate", "dse"], "majors": [], "languages": ["cantonese", "english", "chinese", "mandarin"], "language_level": ["proficiency", "good command"], "hard_skills": ["chinese word processing", "ms office"], "soft_skills": ["self-motivated", "interpersonal skills", "responsible", "ad-hoc duties"], "languages_combined": [{"language": "cantonese", "language_level": ["good command"]}, {"language": "english", "language_level": ["good command"]}, {"language": "chinese", "language_level": ["proficiency"]}, {"language": "mandarin", "language_level": ["good command"]}]}, "experience_required": {"duration": [], "field": []}}, {"job_id": "100003009053361", "location_code": "hk", "company": "Safemark Alliance Security Co Limited", "job_title": "\u4e00\u822c\u884c\u653f\u52a9\u7406", "description": "\n\u8077\u8cac :\u4e00\u822c\u884c\u653f\u53ca\u79d8\u66f8\u5de5\u4f5c, \u63a5\u807d\u96fb\u8a71\n\n\u8cc7\u6b77 :\u4e2d\u4e94\u7a0b\u5ea6; 3\u5e74\u7d93\u9a57; \u826f\u597d\u7cb5\u8a9e; \u4e00\u822c\u666e\u901a\u8a71; \u4e00\u822c\u82f1\u8a9e; \u7565\u61c2\u8b80\u5beb\u4e2d\u6587; \u61c2\u8b80\u5beb\u82f1\u6587\n\n\u5f85\u9047 :\u6bcf\u6708$13,000 - $15,000, \u6709\u9280\u884c\u5047\u671f \u53ca\u914c\u60c5\u6027\u82b1\u7d05, \u661f\u671f\u4e00\u81f3\u4e94: \u4e0a\u53489\u6642\u81f3\u4e0b\u53486\u6642, \u6bcf\u9031\u5de5\u4f5c5\u5929, \u6bcf\u5929\u5de5\u4f5c 8 \u5c0f\u6642\n\n\u7533\u8acb\u9808\u77e5 :\u6c42\u8077\u8005\u53ef\u81f4\u96fb35719130\u8207\u5b89\u76df\u4fdd\u5b89\u6709\u9650\u516c\u53f8\u9673\u5973\u58eb\u806f\u7d61\u3002\n\n", "employment_types": ["Full Time"], "selling_points": [], "locations": ["Central"], "categories": ["Admin & HR", "Clerical / Admin Staff", "Manufacturing", "Others"], "post_time": "2022-01-17T06:51:41Z", "salary": {"currency": null, "max": null, "min": null, "period": "monthly", "term": null}, "salary_visible": false, "title_keywords": [], "responsibilities": [], "requirements": {"degrees": [], "majors": [], "languages": [], "language_level": [], "hard_skills": [], "soft_skills": [], "languages_combined": []}, "experience_required": {"duration": [], "field": []}}, {"job_id": "100003009052189", "location_code": "hk", "company": "Modern Dental Laboratory Company Limited", "job_title": "Dental Lab Admin Assistant", "description": "Job Responsibilities:\n\n\nPerform full reception function in a professional manner as required.\nHandle administrative work including but not limited to data entry, data generation & analysis\u00a0\nTo serve the walk-in internal customers politely to display professional image\nCoordinate between internal departments and clients to ensure timely delivery\nHandles ad-hoc assignments and customer programs\n\nJob Requirements:\n\n\n\nDiploma or above\n2+ years of solid experience, working in a\u00a0clinic will be an advantage.\nGood command of written and spoken English and Chinese\nGood telephone manner and communication skills\nKnowledge in MS Office\nGood working attitude, polite, punctual, responsible and self-motivated.\n\nCan work under general supervision\n5.5 days work\nCandidates with more experience will be considered as Assistant Officer.\n\n\nInterested Candidates,\u00a0please send your\u00a0full resume with your\u00a0recent photo, current & expected salary\u00a0by e-mail to\u00a0hr @moderndentallab.com\n\nAll personal data collected will be used for recruitment and employment related purpose only.", "employment_types": ["Full Time", "Permanent"], "selling_points": ["Receptionist, Customer Services", "Administrative & Operations", "5.5 day work"], "locations": ["Central"], "categories": ["Admin & HR", "Clerical / Admin Staff", "Receptionist", "Sales, CS & Business Devpt", "Sales Administration"], "post_time": "2022-01-17T02:24:31Z", "salary": {"currency": null, "max": null, "min": null, "period": "monthly", "term": null}, "salary_visible": false, "title_keywords": ["admin assistant"], "responsibilities": ["administrative work", "data", "data entry", "ad-hoc assignments", "analysis", "professional manner", "coordinate"], "requirements": {"degrees": ["diploma or above"], "majors": [], "languages": ["english", "chinese"], "language_level": ["good command"], "hard_skills": ["ms office"], "soft_skills": ["communication skills", "good working attitude", "self-motivated", "polite", "responsible", "telephone manner"], "languages_combined": [{"language": "english", "language_level": ["good command"]}, {"language": "chinese", "language_level": ["good command"]}]}, "experience_required": {"duration": ["2+ years"], "field": ["clinic"]}}, {"job_id": "100003009053985", "location_code": "hk", "company": "Senton Engineering Limited", "job_title": "Clerk / Clerical Assistant / Admin staff (13k-15k)", "description": "Responsibilities:\n\nPerform general clerical duties in the Office\nHandle all clerical/filing works, word processing, typing and telephone operation.\nCommunicate with client and contractor\nOther relevant duties as assigned by senior\nHandle ad hoc duties and assignments as required\n\nRequirements:\n\nHKDSE or HKCEE\nGood command of both written and spoken English and Chinese\nGood PC knowledge in MS office applicants (MS Word and Excel) and in both Chinese and English word processing\nClerical Assistant experience is preferred", "employment_types": ["Full Time"], "selling_points": ["Entry Level", "School Certificate", "Full Time"], "locations": ["Chai Wan"], "categories": ["Admin & HR", "Clerical / Admin Staff", "Engineering", "Others"], "post_time": "2022-01-17T07:55:24Z", "salary": {"currency": null, "max": null, "min": null, "period": "monthly", "term": null}, "salary_visible": false, "title_keywords": ["clerical assistant", "admin", "clerk", "staff"], "responsibilities": ["ad hoc duties", "communicate with client"], "requirements": {"degrees": ["hkdse"], "majors": [], "languages": ["english", "chinese"], "language_level": ["good command", "good"], "hard_skills": ["excel", "chinese and english word processing", "pc knowledge", "ms office", "ms word"], "soft_skills": [], "languages_combined": [{"language": "english", "language_level": ["good command", "good", "good"]}, {"language": "chinese", "language_level": ["good command", "good", "good"]}]}, "experience_required": {"duration": [], "field": ["clerical"]}}, {"job_id": "100003009053630", "location_code": "hk", "company": "Continental Global Service Limited", "job_title": "\u5009\u52d9\u6587\u54e1", "description": "\n\u8077\u8cac:\n\u2022 \u8ca0\u8cac\u9032\u8ca8\u6e05\u9ede\u3001\u9a57\u6536\u3001\u7406\u8ca8\u3001\u5305\u88dd\u51fa\u8ca8\u3001\u76e4\u9ede\u3001\u6574\u7406\u8ca8\u5009\u7b49\u65e5\u5e38\u5009\u52d9\u5de5\u4f5c\n\u2022 \u9032\u51fa\u8ca8\u7269\u6587\u4ef6\u8655\u7406\u3001\u5c0d\u55ae\u3001\u96fb\u5b50\u5831\u95dc\u3001\u7463\u788e\u96dc\u52d9\n\u2022 \u8655\u7406\u7c21\u55ae\u6587\u66f8\u53ca\u76f8\u95dc\u5831\u8868\n\u2022 \u8655\u7406\u5009\u5b58\u8cc7\u6599\u8f38\u5165\u53ca\u66f4\u65b0\u7cfb\u7d71\uff0c\u5eab\u5b58\u7a7a\u9593\u6574\u7406\u53ca\u898f\u5283\uff0c\u6307\u6d3e\u7269\u6d41\u5de5\u4f5c\n\u2022 \u4e00\u822c\u5009\u52d9\u6587\u54e1\u5de5\u4f5c\uff0c\u5354\u52a9\u4e3b\u7ba1\u8655\u7406\u65e5\u5e38\u5009\u5132\u904b\u4f5c\n\u8981\u6c42:\n\u2022 \u4e2d\u4e94\u6216\u4ee5\u4e0a\u7a0b\u5ea6\n\u2022 \u5177\u4e09\u5e74\u5009\u52d9\u6216\u8ca8\u7269\u88dd\u904b\u5de5\u4f5c\u7d93\u9a57, \u512a\u5148\u8003\u616e\n\u2022 \u6709\u96fb\u8166\u64cd\u4f5c\u7d93\u9a57, \u5305\u62ecWord and Excel\n\u2022 \u61c2\u95b1\u8b80\u53ca\u66f8\u5beb\u4e2d\u3001\u82f1\u6587\n\u2022 \u7d30\u5fc3\u3001\u6709\u79ae\u8c8c\u3001\u8aa0\u5be6\u3001\u6709\u8cac\u4efb\u5fc3\u3001\u826f\u597d\u7684\u6e9d\u901a\u80fd\u529b\n\u2022 \u80fd\u5373\u6642\u4e0a\u4efb\u8005\u512a\u5148\u8003\u616e\n\u5de5\u4f5c\u5730\u9ede: \u89c0\u5858\n\u5de5\u4f5c\u6642\u9593:\nFT: \u661f\u671f\u4e00\u81f3\u4e94: 10:00am-7:00pm; \u661f\u671f\u516d: 10:00am-5:00pm\nPT: \u661f\u671f\u4e00\u81f3\u516d: 12:00nn-6:00pm\n\u798f\u5229:\n\u2022 \u6cd5\u5b9a\u5047\u671f\n\u2022 \u8d85\u6642\u6d25\u8cbc\n\u2022 \u5e74\u5047\n\u2022 \u5a5a\u5047\n\u2022 \u751f\u65e5\u5047\n\u2022 \u7522\u5047/\u4f8d\u7522\u5047\n\u2022 \u91ab\u7642\u798f\u5229\n\u2022 \u826f\u597d\u5de5\u4f5c\u74b0\u5883\n\n\u6709\u610f\u7533\u8acb\u4ee5\u4e0a\u8077\u4f4d\u8005\uff0c\u53ef\u81f4\u96fb3955 Apply Now\u3002\n\uff08\u6240\u6709\u6536\u96c6\u5230\u7684\u8cc7\u6599\u53ea\u7528\u65bc\u62db\u8058\u7528\u9014\uff09\n\n", "employment_types": ["Full Time"], "selling_points": [], "locations": ["Kwun Tong"], "categories": ["Admin & HR", "Clerical / Admin Staff", "Others"], "post_time": "2022-01-17T07:16:08Z", "salary": {"currency": null, "max": null, "min": null, "period": "monthly", "term": null}, "salary_visible": false, "title_keywords": ["\u5009\u52d9\u6587\u54e1"], "responsibilities": [], "requirements": {"degrees": [], "majors": [], "languages": [], "language_level": [], "hard_skills": ["excel"], "soft_skills": [], "languages_combined": []}, "experience_required": {"duration": [], "field": []}}, {"job_id": "100003009053383", "location_code": "hk", "company": "L & A Lingerie Limited", "job_title": "\u6703\u8a08\u6587\u54e1", "description": "\n\u8077\u8cac :\u8ca0\u8cac\u6703\u8a08\u53ca\u884c\u653f\u53ca\u6587\u66f8\u5de5\u4f5c, \u5165\u8cec, \u88fd\u4f5c\u55ae\u64da\u3001\u5236\u4f5c\u5831\u8868\u3001\u8cc7\u6599\u8f38\u5165\u3001\u6574\u7406\u6587\u4ef6\u5b58\u6a94\u3001\u9700\u8981\u6642\u5c11\u91cf\u5916\u52e4\u7b49\n\n\u8cc7\u6b77 :\u4e2d\u4e94\u7a0b\u5ea6; 5\u5e74\u7d93\u9a57; \u826f\u597d\u7cb5\u8a9e; \u4e00\u822c\u666e\u901a\u8a71; \u4e00\u822c\u82f1\u8a9e; \u61c2\u8b80\u5beb\u4e2d\u6587; \u61c2\u8b80\u5beb\u82f1\u6587; \u61c2MYOB; \u61c2MS Word; \u61c2MS Outlook; \u61c2MS Excel; \u61c2\u82f1\u6587\u6253\u5b57; \u61c2\u4e2d\u6587\u6253\u5b57; \u8655\u4e8b\u7d30\u5fc3, \u8a8d\u771f, \u8aa0\u5be6, \u6709\u8cac\u4efb\u611f\n\n\u5f85\u9047 :\u6bcf\u6708$12,000 - $13,000, \u6709\u96d9\u7ce7, \u9280\u884c\u5047\u671f, \u81b3\u98df\u6d25\u8cbc \u53ca\u5e74\u7d42\u734e\u91d1, \u661f\u671f\u4e00\u81f3\u4e94: \u4e0a\u53489\u6642\u534a\u81f3\u4e0b\u53486\u6642\u534a, \u6bcf\u9031\u5de5\u4f5c5\u5929, \u6bcf\u5929\u5de5\u4f5c 8 \u5c0f\u6642\n\n\u7533\u8acb\u9808\u77e5 :\u6c42\u8077\u8005\u53ef\u96fb\u90f5(Apply Now)\u5c65\u6b77\u8868\u7d66\u67cf\u9716\u5167\u8863\u6709\u9650\u516c\u53f8\u3002\u5982\u8981\u7d22\u53d6\u6536\u96c6\u500b\u4eba\u8cc7\u6599\u8072\u660e, \u8acb\u8207\u5ed6\u5c0f\u59d0(Email)\u806f\u7d61\u3002\n\n", "employment_types": ["Full Time"], "selling_points": [], "locations": ["Yau Tsim Mong Area"], "categories": ["Admin & HR", "Clerical / Admin Staff", "Others"], "post_time": "2022-01-17T06:54:17Z", "salary": {"currency": null, "max": null, "min": null, "period": "monthly", "term": null}, "salary_visible": false, "title_keywords": [], "responsibilities": [], "requirements": {"degrees": [], "majors": [], "languages": [], "language_level": [], "hard_skills": ["excel", "outlook", "word"], "soft_skills": [], "languages_combined": []}, "experience_required": {"duration": [], "field": []}}, {"job_id": "100003009051783", "location_code": "hk", "company": "The Hong Kong Jockey Club", "job_title": "\u517c\u8077\u8a2d\u65bd\u670d\u52d9\u52a9\u7406 (\u505c\u8eca\u5834\u8fa6\u4e8b\u8655) Part-time Administration Assistant (Carpark)", "description": "\u6709\u95dc\u90e8\u9580\n\u672c\u6703\u7269\u696d\u90e8\u8ca0\u8cac\u76e3\u5bdf\u99ac\u6703\u7684\u7522\u696d\u7ba1\u7406\u3001\u7269\u696d\u7ba1\u7406\u3001\u8a08\u5283\u53ca\u5efa\u7bc9\u7ba1\u7406\uff0c\u4ee5\u53ca\u5408\u7d04\u884c\u653f\u5de5\u4f5c\u3002\n\n\u5de5\u4f5c\u6027\u8cea:\n\n\u505c\u8eca\u5834\u5de1\u67e5\n\u78ba\u8a8d\u5408\u9069\u6cca\u8eca\u8a3c\u53ca\u5b89\u6392\u9069\u7576\u6cca\u8eca\u4f4d\u7f6e\n\u63a7\u5236\u4ea4\u901a\uff0c\u4ee4\u884c\u4eba\u53ca\u8eca\u8f1b\u66a2\u9806\n\u4ea4\u901a\u8a2d\u65bd/\u6a19\u8a18\u64fa\u8a2d\n\u767b\u8a18\u505c\u8eca\u5834\u6cca\u8eca\u8a18\u9304\u53ca\u89e3\u7b54\u5ba2\u4eba\u67e5\u8a62\n\n\u5de5\u4f5c\u5730\u9ede:\n\u6c99\u7530\u53ca\u8dd1\u99ac\u5730\u99ac\u5834\n\n\u6642\u85aa:\n\n$73.50\n\n\u5de5\u4f5c\u6642\u9593:\n\n\u65e5\u99ac (\u661f\u671f\u516d\u6216\u65e5)\u00a0 10:00 \u2013 18:30\n\u591c\u99ac (\u661f\u671f\u4e09)\u00a0 15:30 \u2013 23:30\n\u5fc5\u9808\u540c\u6642\u53ef\u65bc\u661f\u671f\u4e09\u53ca \u516d/\u65e5\u5de5\u4f5c\n\n\u00a0\u5165\u8077\u8981\u6c42:\u00a0\n\n\u64cd\u6d41\u5229\u5ee3\u6771\u8a71\u53ca\u7c21\u55ae\u82f1\u8a9e\u6703\u8a71\n\u4e00\u822c\u96fb\u8166\u64cd\u4f5c\u53ca\u9700\u61c2 MS Excel \u7a0b\u5f0f", "employment_types": ["Part Time"], "selling_points": ["\u5de5\u4f5c\u5730\u9ede: \u6c99\u7530\u53ca\u8dd1\u99ac\u5730\u99ac\u5834", "\u65e5\u99ac (\u661f\u671f\u516d\u6216\u65e5) 10:00 \u2013 18:30; \u591c\u99ac (\u661f\u671f\u4e09) 15:30 \u2013 23:30", "\u6642\u85aa: $73.50"], "locations": ["Not Specified"], "categories": ["Admin & HR", "Clerical / Admin Staff", "Property / Real Estate", "Property Management"], "post_time": "2022-01-17T01:06:10Z", "salary": {"currency": null, "max": null, "min": null, "period": null, "term": null}, "salary_visible": false, "title_keywords": ["administration assistant"], "responsibilities": [], "requirements": {"degrees": [], "majors": [], "languages": [], "language_level": [], "hard_skills": ["ms excel"], "soft_skills": [], "languages_combined": []}, "experience_required": {"duration": [], "field": []}}, {"job_id": "100003009051939", "location_code": "hk", "company": "Quantium Solutions (Hong Kong) Limited", "job_title": "Administration Executive/Personal Assistant", "description": "Quantium Solutions\n\nQS is an established eCommerce logistics services provider in the Asia Pacific Region. Headquartered in Singapore, we are ideally positioned to be the best gateway to Asia.\n\nOur serviced offices now serve the needs of enterprises and entrepreneurs across major 200 countries and 18 markets.\n\nAt QS, creating a workplace that provides opportunities for each of you and we believe in you and know you\u2019ll do great things. As an employer, our role is to empower you by bringing your true talents and best self to this dynamic digital world and people we serve.\n\n\n\n\nJob Description\n\nJob Responsibilities:\n\nPerform full spectrum of Administrative functions,\u00a0including\u00a0but not limited to repair & maintenance, procurement ( sourcing, price negotiation, suppliers evaluation & selection, delivery management and inventory control ) etc.\nHandle ISO documents update and filing, and provide assistance to ISO internal and external audits\nPlan and manage daily schedule of RGM including work, personal time, and trips;\nOrganize travel arrangement for the family including ticket and accommodation, itinerary planning, visa application etc\nAssist in any ad hoc project as\u00a0assigned\n\n\u00a0Job Requirements:\n\nCertificate, Diploma or\u00a0above\u00a0in Logistics, Procurement or related disciplines\nPossession of procurement experience is a must and ISO audit experience\u00a0would\u00a0be an added advantage\nGood\u00a0negotiation,\u00a0communication and interpersonal skills\nGood command of written and spoken English, Cantonese and Mandarin\nPC Literacy and working knowledge of MS Office\nImmediately available is preferred\n\nWe offer attractive remuneration package including medical insurance, life insurance, dental and other fringe benefits to the right candidate. Interested parties please send your full resume with date of availability, present and expected salaries to us\n\n\n", "employment_types": ["Full Time", "Permanent"], "selling_points": [], "locations": ["Wong Tai Sin Area"], "categories": ["Admin & HR", "Clerical / Admin Staff", "Personal / Executive Assistant", "Secretary"], "post_time": "2022-01-17T01:33:11Z", "salary": {"currency": null, "max": null, "min": null, "period": "monthly", "term": null}, "salary_visible": false, "title_keywords": ["administration executive", "personal assistant"], "responsibilities": ["management", "price negotiation", "ad hoc", "maintenance", "internal and external audits", "repair", "inventory control", "schedule", "plan", "evaluation", "travel arrangement", "provide assistance", "planning"], "requirements": {"degrees": ["certificate", "diploma or above"], "majors": ["related disciplines"], "languages": ["cantonese", "english", "mandarin"], "language_level": ["good command"], "hard_skills": ["pc", "ms office"], "soft_skills": ["communication and interpersonal skills", "negotiation"], "languages_combined": [{"language": "cantonese", "language_level": ["good command"]}, {"language": "english", "language_level": ["good command"]}, {"language": "mandarin", "language_level": ["good command"]}]}, "experience_required": {"duration": [], "field": ["audit experience", "procurement"]}}, {"job_id": "100003009052452", "location_code": "hk", "company": "Foodgears Industrial International Limited", "job_title": "Assistant Administration Officer/ Administration Officer (5-days work)", "description": "Job Duties:\u00a0\n\nHandle & review full spectrum of office administration and HR functions\nProvide secretarial and administrative support\nFamiliar with tickets and hotels reservation\nOrganize, maintain and update reports, records, and filing systems\nFollow up ad-hoc projects independently with self-initiative and strong sense of responsibility\nCoordinate with different departments among the company\n\nRequirements:\n\nUniversity Graduates\nGood command of spoken and written Chinese & English\nAble to communicate effectively with a wide range of people\nSelf-motivated with positive working attitude\nGood team player, hardworking & willing to work under pressure\nImmediate available is an advantage\nAt least 3 years of HR / Administration related experience", "employment_types": ["Full Time", "Permanent"], "selling_points": [], "locations": ["Wong Tai Sin Area"], "categories": ["Admin & HR", "Clerical / Admin Staff", "Others", "HR Supporting Staff"], "post_time": "2022-01-17T03:04:14Z", "salary": {"currency": null, "max": null, "min": null, "period": "monthly", "term": null}, "salary_visible": false, "title_keywords": ["administration officer", "assistant administration officer"], "responsibilities": ["administrative support", "office administration", "hr", "review", "systems", "coordinate with", "maintain", "reports", "ad-hoc projects"], "requirements": {"degrees": [], "majors": [], "languages": ["english", "chinese"], "language_level": ["good command"], "hard_skills": [], "soft_skills": ["self-motivated", "good team player", "positive working attitude", "hardworking", "work under pressure"], "languages_combined": [{"language": "english", "language_level": ["good command"]}, {"language": "chinese", "language_level": ["good command"]}]}, "experience_required": {"duration": ["at least 3 years"], "field": ["related", "hr", "administration"]}}, {"job_id": "100003009052012", "location_code": "hk", "company": "Phonak Hearing Centre Hong Kong Ltd", "job_title": "Personnel & Administration Assistant", "description": "KAM HEALTHCARE GROUP\n\n\u7518\u5cf0\u91ab\u7642\u4fdd\u5065\u96c6\u5718\n\nPhonak Hearing Centre HK Ltd\n\nA leading professional hearing centre in TST is seeking an applicant for the post of :\n\nPersonnel & Administration\u00a0Assistant\n\nJOB DUTIES\n\nTo be responsible for Personnel duties such as recruitment, selection and interview of new employees.\nTo be responsible for duties of payroll, leave management, attendance management, MPF/ORSO, updating staff handbook and IR56b submission.\nTo be responsible for maintaining HR Pro Personnel system by recording personal information, termination and job classifications etc.\nTo assist in preparing the work of staff appraisal and staff training and development.\nTo be responsible for duties of administration includingmedical insurance, office supplies, office machine repair and maintenance, petty cash management, whatsApp group updating etc.\nTo be responsible for additional work related to Secretary, Personnel and Administration.\nJob Requirements:\n\nDiploma/ Associate Degree or above in HR/Admin\u00a0preferred\n1-2 years working experience in HR & Admin\u00a0preferred\nGood command of spoken English & Chinese\nPC knowledge such as Microsoft Word, Excel & Chinese Word Processing\n\nWe offer attractive salary and fringe benefits including upto 20 days\u2019 annual leave, 5 day work week, year-end bonus, medical insurance, provident fund, educational assistance to the right person. Interest candidates please fax resume to 28450299 Or E-mail\u00a0", "employment_types": ["Full Time", "Permanent"], "selling_points": ["Attractive Salary Package & Benefit, 5 day work", "Diploma/Associate Degree or Above in HR & Admin", "1-2 years working experience in HR & Admin"], "locations": ["Tsim Sha Tsui"], "categories": ["Admin & HR", "Clerical / Admin Staff", "Secretary", "HR Supporting Staff"], "post_time": "2022-01-17T01:50:09Z", "salary": {"currency": null, "max": null, "min": null, "period": "monthly", "term": null}, "salary_visible": false, "title_keywords": ["administration assistant"], "responsibilities": ["attendance", "management", "mpf", "maintaining", "maintenance", "office supplies", "hr", "repair", "recruitment", "insurance", "payroll", "administration"], "requirements": {"degrees": ["diploma", "degree or above"], "majors": [], "languages": ["english", "chinese"], "language_level": ["good command"], "hard_skills": ["excel", "pc knowledge", "microsoft word", "chinese word processing"], "soft_skills": [], "languages_combined": [{"language": "english", "language_level": ["good command"]}, {"language": "chinese", "language_level": ["good command"]}]}, "experience_required": {"duration": ["1-2 years"], "field": ["hr", "admin"]}}, {"job_id": "100003009054409", "location_code": "hk", "company": "Atkins China Ltd", "job_title": "Junior Clerk", "description": "Responsibilities:\n\nProvide clerical duties to the project team: typing, filing, register\u00a0correspondence and report\u2019s preparation;\nAssist with ad-hoc duties when required;\nRequirements:\nF.5 or above;\nMin. 3 years' relevant experience, preferably has experience in construction industry;\nProficiency in MS Office (Word, Excel & PowerPoint) and Chinese Word Processing;\nGood command of written and spoken English and Chinese;\nInitiative and able to organize work efficiently and independently;\nStrong communication and interpersonal skills; and\nImmediate available is preferred.\n\nFor interested parties, please submit your application with detailed resume, current and expected salary by clicking \"Apply Now\".\n\nApplications will be treated in confidence and only be used for recruitment purposes. Those not being invited for interview within 3 months may consider their applications unsuccessful.", "employment_types": ["Full Time", "Contract"], "selling_points": ["3 years+ admin background", "HKCEE  / DSE or above", "Familiar with MS Office including Word & Excel"], "locations": ["Tsim Sha Tsui"], "categories": ["Admin & HR", "Clerical / Admin Staff", "Others", "Engineering", "Others"], "post_time": "2022-01-17T09:25:46Z", "salary": {"currency": null, "max": null, "min": null, "period": "monthly", "term": null}, "salary_visible": false, "title_keywords": ["junior clerk"], "responsibilities": ["ad-hoc duties", "report"], "requirements": {"degrees": [], "majors": [], "languages": ["english", "chinese"], "language_level": ["proficiency", "good command"], "hard_skills": ["excel", "chinese word processing", "word", "powerpoint", "ms office"], "soft_skills": ["independently", "initiative", "communication and interpersonal skills"], "languages_combined": [{"language": "english", "language_level": ["good command"]}, {"language": "chinese", "language_level": ["proficiency", "good command"]}]}, "experience_required": {"duration": ["3 years"], "field": ["construction industry", "relevant experience"]}}, {"job_id": "100003009054746", "location_code": "hk", "company": "Public Finance Limited", "job_title": "Clerks (Various Departments)", "description": "Responsibilities\nProvide administrative support\nCompile various kinds of reports\nPerform general clerical duties\nRequirements\nSecondary education\n1 year administrative / clerical working experience\nGood communication and interpersonal skills\nSelf-motivated, able to work independently\nKnowledge of MS Word / MS Excel\nBenefits\nDouble Pay\nDiscretionary Bonus\nInsurance Benefits\nStudy subsidy\nApplication Method:\nBy Whatsapp : 9309 2925By E-mail via \"Apply Now\"\nPersonal data collected will be treated in the strictest confidence in accordance with our\u00a0Personal Information Collection Statement\u00a0and\u00a0Privacy Policy\u00a0and will be handled by authorized personnel for recruitment-related purposes only. All applications will be kept for a maximum period of one year as may be considered for other suitable positions within Public Finance Ltd. and its associated companies. For details, please visit the Company\u2019s website\u00a0http://www.publicfinance.com.hk", "employment_types": ["Full Time", "Permanent"], "selling_points": [], "locations": ["Not Specified"], "categories": ["Admin & HR", "Clerical / Admin Staff", "Others", "Banking / Finance", "Financial Services"], "post_time": "2022-01-17T10:52:54Z", "salary": {"currency": null, "max": null, "min": null, "period": "monthly", "term": null}, "salary_visible": false, "title_keywords": [], "responsibilities": ["provide administrative support", "reports"], "requirements": {"degrees": ["secondary education"], "majors": [], "languages": [], "language_level": [], "hard_skills": ["ms excel", "ms word"], "soft_skills": ["self-motivated", "communication and interpersonal skills", "work independently"], "languages_combined": []}, "experience_required": {"duration": ["1 year"], "field": ["administrative", "clerical"]}}, {"job_id": "100003009054344", "location_code": "hk", "company": "Pathlab Medical Laboratories Limited", "job_title": "Laboratory Clerk", "description": "Job description and responsibilities\n\nTo enter client data into computer, clerical work, sample labeling etc.\u00a0\u00a0\nJob requirements\n\nForm 6 or above with good telephone manner.\nFast and accurate typing skills in both English & Chinese.\nNo experience in the lab field necessary but an asset.\n\nWe offer attractive remuneration package and other fringe benefits to competitive candidate.\n\nFull time with 2 evening duties a week.(5.5 working days or equivalent)\nMedical & dental plans\n14 days Annual Leave\nPublic holiday & Sundays off\nConvenient Location - Fortress Hill\n\nTo find out more about our company, please visit our website :\u00a0www.pathlabhk.com\n\n(All personal data collected are used for recruitment purpose only.)", "employment_types": ["Full Time"], "selling_points": ["Enter client data into computer & clerical work", "F. 6 or above with fast and accurate typing skills", "Competitive salary, year end double pay & bonus"], "locations": ["North Point"], "categories": ["Admin & HR", "Clerical / Admin Staff", "Medical Services", "Others"], "post_time": "2022-01-17T09:13:15Z", "salary": {"currency": null, "max": null, "min": null, "period": "monthly", "term": null}, "salary_visible": false, "title_keywords": ["clerk"], "responsibilities": ["data"], "requirements": {"degrees": [], "majors": [], "languages": ["english", "chinese"], "language_level": [], "hard_skills": ["no", "typing"], "soft_skills": ["accurate", "telephone manner"], "languages_combined": [{"language": "english", "language_level": []}, {"language": "chinese", "language_level": []}]}, "experience_required": {"duration": [], "field": []}}, {"job_id": "100003009053607", "location_code": "hk", "company": "Pal Line Industrial Company Limited", "job_title": "\u8ddf\u55ae\u6587\u54e1", "description": "\n\u8077\u8cac :\u5354\u52a9\u8ddf\u55ae\u5de5\u4f5c\n\n\u8cc7\u6b77 :\u4e2d\u516d\u7a0b\u5ea6; 1\u5e74\u7d93\u9a57; \u4e00\u822c\u7cb5\u8a9e; \u4e00\u822c\u666e\u901a\u8a71; \u4e00\u822c\u82f1\u8a9e\u512a\u5148; \u61c2\u8b80\u5beb\u4e2d\u6587; \u61c2\u8b80\u5beb\u82f1\u6587; \u61c2MS Outlook; \u61c2MS Excel; \u61c2\u4e2d\u6587\u6253\u5b57 20 \u5b57(\u6bcf\u5206\u9418); \u5de5\u4f5c\u52e4\u596e\n\n\u5f85\u9047 :\u6bcf\u6708$13,000 - $15,000, \u6709\u96d9\u7ce7, \u9280\u884c\u5047\u671f\u53ca\u5e74\u7d42\u734e\u91d1, \u661f\u671f\u4e00\u81f3\u4e94: \u4e0a\u53488\u664245\u5206\u81f3\u4e0b\u53486\u6642, \u6bcf\u9031\u5de5\u4f5c5\u5929\n\n\u7533\u8acb\u9808\u77e5 :\u6c42\u8077\u8005\u53ef\u96fb\u90f5(Apply Now)\u5c65\u6b77\u8868\u7d66\u532f\u9032\u5be6\u696d\u767c\u5c55\u6709\u9650\u516c\u53f8\u3002\u5982\u8981\u7d22\u53d6\u6536\u96c6\u500b\u4eba\u8cc7\u6599\u8072\u660e, \u8acb\u8207\u912d\u5c0f\u59d0(Email)\u806f\u7d61\u3002\n\n", "employment_types": ["Full Time"], "selling_points": [], "locations": ["Hung Hom"], "categories": ["Admin & HR", "Clerical / Admin Staff", "Others"], "post_time": "2022-01-17T07:13:48Z", "salary": {"currency": null, "max": null, "min": null, "period": "monthly", "term": null}, "salary_visible": false, "title_keywords": ["\u8ddf\u55ae\u6587\u54e1"], "responsibilities": [], "requirements": {"degrees": [], "majors": [], "languages": [], "language_level": [], "hard_skills": ["excel", "outlook"], "soft_skills": [], "languages_combined": []}, "experience_required": {"duration": [], "field": []}}, {"job_id": "100003009053058", "location_code": "hk", "company": "Jibsen Industrial Ltd", "job_title": "Accounting & Admin. Officer", "description": "Hong Kong based company with more than 20 years experience in bag manufacturing URGENTLY requires in our Kwun Tong office:\n\nAccounting & Admin. Officer\n\nResponsibilities:\n\nDaily accounting operations including general journal entries, payments, petty cash, staff reimbursement, preparing monthly reports, etc.\nGeneral office administrative work\nManaging staff attendance and leave record\nAd-hoc assignments\n\nRequirements:\n\nMin. 2 years experience; Fresh graduate will be considered;\nDiploma in accounting;\nProficient in MS Office, Chinese Word Processing;\nPrior experience with ERP is an advantage;\nGood spoken & written English, Chinese & Mandarin;\nAble to work independently, responsible, self-motivated, hardworking & eager to learn;\nImmediate available is preferred.\n\nInterested parties please send resume with salary expected to Jibsen Industrial Ltd by pressing APPLY NOW\n\n(Data collected will be used for recruitment purpose only.)", "employment_types": ["Full Time"], "selling_points": ["5-day work", "Group Medical Insurance", "Annual Leave 11 days"], "locations": ["Kwun Tong"], "categories": ["Accounting", "Accounting Clerk / Supervisor", "Admin & HR", "Clerical / Admin Staff", "Others", "Others"], "post_time": "2022-01-17T05:28:21Z", "salary": {"currency": null, "max": null, "min": null, "period": "monthly", "term": null}, "salary_visible": false, "title_keywords": ["admin", "accounting", "officer"], "responsibilities": ["attendance", "administrative work", "monthly reports", "ad-hoc assignments", "daily accounting operations", "payments", "journal entries"], "requirements": {"degrees": ["diploma", "fresh graduate"], "majors": ["accounting"], "languages": ["english", "chinese", "mandarin"], "language_level": ["good", "proficient"], "hard_skills": ["chinese word processing", "erp", "ms office"], "soft_skills": ["work independently", "self-motivated", "responsible", "eager to learn", "hardworking"], "languages_combined": [{"language": "english", "language_level": ["good"]}, {"language": "chinese", "language_level": ["good", "proficient"]}, {"language": "mandarin", "language_level": ["good"]}]}, "experience_required": {"duration": ["2 years"], "field": []}}, {"job_id": "100003009053490", "location_code": "hk", "company": "Arup", "job_title": "Assistant | Administration (Facilities Management)", "description": "Responsibilities:\nFollow up building maintenance orders and monitor the progress\nAssign tasks and prepare work schedule to the technicians\nPerform preventive and regular checking for meeting room facilities\nUpdate office map drawing and diagrams\nCoordinate with vendors and Building Management Office on repairing and maintenance work\nMaintain inventory record of consumable items\nPerform ad hoc tasks, such as minor A&A works, restacking projects\u00a0\n\nQualifications & Experience required:\n\nDiploma in Facility / Property Management or related discipline\n2 years of relevant working experience, preferably in sizable company\nProficiency in Microsoft Office applications\nResponsible, good interpersonal skills and attend to details\nProficiency in both written and spoken English and Chinese\nFresh graduates will also be considered\n\nWe offer a competitive remuneration package commensurate with qualifications and experience to the right candidate including Global Profit Share scheme, additional fringe benefits of maternity / paternity leave and long-term career development opportunities.\n\nFor interested applicants, please click \u201cApply Now\u201d to submit your online application.\n\nPersonal data collected will be used for recruitment purpose only. Applicants not contacted within 8 weeks may consider their applications unsuccessful.", "employment_types": ["Full Time", "Permanent"], "selling_points": [], "locations": ["Kowloon City"], "categories": ["Admin & HR", "Clerical / Admin Staff", "Property / Real Estate", "Property Management"], "post_time": "2022-01-17T07:03:07Z", "salary": {"currency": null, "max": null, "min": null, "period": null, "term": null}, "salary_visible": false, "title_keywords": ["assistant"], "responsibilities": ["management", "maintenance", "assign tasks", "monitor", "checking", "coordinate with", "inventory record", "ad hoc tasks", "building management", "maintain", "recruitment", "schedule", "career development", "personal data"], "requirements": {"degrees": ["diploma"], "majors": [], "languages": ["english", "chinese"], "language_level": ["proficiency"], "hard_skills": ["scheme", "maintenance", "microsoft office"], "soft_skills": ["interpersonal skills", "responsible"], "languages_combined": [{"language": "english", "language_level": ["proficiency"]}, {"language": "chinese", "language_level": ["proficiency"]}]}, "experience_required": {"duration": ["2 years"], "field": ["development", "relevant working experience"]}}, {"job_id": "100003009053845", "location_code": "hk", "company": "C S (HK) CO. Limited", "job_title": "\u64cd\u4f5c\u6587\u54e1**", "description": "\n\u8077\u8cac :\u8655\u7406\u5ba2\u6236\u8a02\u55ae\u53ca\u67e5\u8a62\uff0c\u4e00\u822c\u6587\u66f8\u5de5\u4f5c\uff0c\u57fa\u672c\u96fb\u8166\u64cd\u4f5c\uff0c\u8cc7\u6599\u8f38\u5165\n\n\u8cc7\u6b77 :\u4e2d\u4e09\u7a0b\u5ea6; \u826f\u597d\u7cb5\u8a9e; \u4e00\u822c\u666e\u901a\u8a71; \u4e00\u822c\u82f1\u8a9e; \u7565\u61c2\u8b80\u5beb\u4e2d\u6587; \u7565\u61c2\u8b80\u5beb\u82f1\u6587; \u5177\u6709\u57fa\u672c\u96fb\u8166\u64cd\u4f5c\u77e5\u8b58\n\n\u5f85\u9047 :\u6bcf\u6708$10,000 - $12,000, \u6709\u9280\u884c\u5047\u671f, \u82b1\u7d05 \u53ca\u91ab\u7642\u798f\u5229, \u661f\u671f\u4e00\u81f3\u4e94: \u4e0a\u53489\u6642\u81f3\u4e0b\u53486\u6642\u53ca\u661f\u671f\u516d: \u4e0a\u53489\u6642\u81f3\u4e0b\u53485\u6642, \u6bcf\u9031\u5de5\u4f5c6\u5929, \u6bcf\u5929\u5de5\u4f5c 8 \u5c0f\u6642\n\n\u7533\u8acb\u9808\u77e5 :\u6c42\u8077\u8005\u53ef\u96fb\u90f5(Apply Now)\u5c65\u6b77\u8868\u7d66\u9054\u610f\uff08\u9999\u6e2f\uff09\u6709\u9650\u516c\u53f8\u3002\u5982\u8981\u7d22\u53d6\u6536\u96c6\u500b\u4eba\u8cc7\u6599\u8072\u660e, \u8acb\u8207\u9ece\u5c0f\u59d0(Email)\u806f\u7d61\u3002\n\n", "employment_types": ["Full Time"], "selling_points": [], "locations": ["Kwai Tsing Area"], "categories": ["Admin & HR", "Clerical / Admin Staff", "Others"], "post_time": "2022-01-17T07:37:01Z", "salary": {"currency": null, "max": null, "min": null, "period": "monthly", "term": null}, "salary_visible": false, "title_keywords": [], "responsibilities": [], "requirements": {"degrees": [], "majors": [], "languages": [], "language_level": [], "hard_skills": [], "soft_skills": [], "languages_combined": []}, "experience_required": {"duration": [], "field": []}}, {"job_id": "100003009053392", "location_code": "hk", "company": "Good Wealth Trading Company", "job_title": "\u6703\u8a08\u6587\u54e1", "description": "\n\u8077\u8cac :\u4e00\u822c\u6703\u8a08\u4e8b\u52d9, all accounting related job tasks\n\n\u8cc7\u6b77 :\u4e2d\u4e94\u7a0b\u5ea6; 2\u5e74\u7d93\u9a57; \u826f\u597d\u7cb5\u8a9e; \u826f\u597d\u666e\u901a\u8a71; \u826f\u597d\u82f1\u8a9e; \u61c2\u8b80\u5beb\u4e2d\u6587; \u61c2\u8b80\u5beb\u82f1\u6587; \u6301\u6709LCC\u4e2d\u7d1a\u8b49\u66f8; \u61c2\u516c\u53f8\u79d8\u66f8\u76f8\u95dc\u4e8b\u5b9c\u512a\u5148\n\n\u5f85\u9047 :\u6bcf\u6708$12,000 - $15,000, \u6709\u9280\u884c\u5047\u671f, \u914c\u60c5\u6027\u82b1\u7d05 \u53ca\u9032\u4fee\u6d25\u8cbc, \u661f\u671f\u4e00\u81f3\u4e94: \u4e0a\u53489\u6642\u81f3\u4e0b\u53486\u6642, \u6bcf\u9031\u5de5\u4f5c5\u5929, \u6bcf\u5929\u5de5\u4f5c 8 \u5c0f\u6642\n\n\u7533\u8acb\u9808\u77e5 :\u6c42\u8077\u8005\u53ef\u96fb\u90f5(Apply Now)\u5c65\u6b77\u8868\u7d66\u4f73\u624d\u6709\u9650\u516c\u53f8\u3002\u5982\u8981\u7d22\u53d6\u6536\u96c6\u500b\u4eba\u8cc7\u6599\u8072\u660e, \u8acb\u8207\u6797\u5148\u751f(Email)\u806f\u7d61\u3002\n\n", "employment_types": ["Full Time"], "selling_points": [], "locations": ["Tsim Sha Tsui"], "categories": ["Admin & HR", "Clerical / Admin Staff", "Others"], "post_time": "2022-01-17T06:55:00Z", "salary": {"currency": null, "max": null, "min": null, "period": "monthly", "term": null}, "salary_visible": false, "title_keywords": [], "responsibilities": [], "requirements": {"degrees": [], "majors": [], "languages": [], "language_level": [], "hard_skills": [], "soft_skills": [], "languages_combined": []}, "experience_required": {"duration": [], "field": []}}, {"job_id": "100003009051689", "location_code": "hk", "company": "The University of Manchester Worldwide Limited", "job_title": "Operations Administrative Assistant", "description": "This is a dynamic and demanding role and will involve considerable flexibility and the ability to prioritise tasks in order to deliver administrative support for the academic community within the Centre and wider community.\u00a0 The post holder\u2019s role will be to ensure effective and professional liaison and communication with academic, administrative and external customers at all levels, to facilitate the smooth running of day-to-day activities.\n\n\nKey Responsibilities\n\n\nTo provide efficient and professional services to stakeholders\nTo provide effective support in programme, event and office administration\nTo implement the admission and registration process\nTo support teaching and learning services\nTo maintain student records and its systems\nTo support and implement event plans and concepts\n20 days annual leave, 5 days work, fringe benefits and working with global teams.", "employment_types": ["Full Time", "Contract"], "selling_points": ["H Dip or above, 3-5 yrs wk exp, Gd Eng, IT skills", "Mature, can-do, multi-task, creative, outgoing", "Int'l exposure, training, immediate, salary expect"], "locations": ["Causeway Bay"], "categories": ["Admin & HR", "Clerical / Admin Staff", "Education", "Others", "Marketing / Public Relations", "Public Relations - Event Management"], "post_time": "2022-01-16T21:50:48Z", "salary": {"currency": null, "max": null, "min": null, "period": "monthly", "term": null}, "salary_visible": false, "title_keywords": ["administrative assistant", "operations"], "responsibilities": ["administrative support", "office administration", "systems", "communication", "maintain student records", "plans"], "requirements": {"degrees": [], "majors": [], "languages": [], "language_level": [], "hard_skills": ["dynamic"], "soft_skills": ["efficient", "prioritise", "communication", "dynamic", "learning", "smooth"], "languages_combined": []}, "experience_required": {"duration": [], "field": []}}, {"job_id": "100003009052387", "location_code": "hk", "company": "Simatelex Manufactory Co., Ltd.", "job_title": "Project Clerk", "description": "\n\u8077\u8cac :\u63a5\u807d\u548c\u76f4\u64a5\u96fb\u8a71;\u8207\u5ba2\u6236\u3001\u54e1\u5de5\u548c\u5176\u4ed6\u4eba\u6e9d\u901a\u4ee5\u56de\u7b54\u554f\u984c\u3001\u8655\u7406\u6295\u8a34\u3001\u89e3\u91cb\u4fe1\u606f\u548c\u63a5\u53d7\u8a02\u55ae;\u64cd\u4f5c\u8fa6\u516c\u6a5f\u5668\uff0c\u5305\u62ec\u8907\u5370\u6a5f\u3001\u6383\u63cf\u5100\u3001\u96fb\u8a71\u548c\u8a9e\u97f3\u90f5\u4ef6\u7cfb\u7d71\u4ee5\u53ca\u8a08\u7b97\u6a5f;\u7dad\u8b77\u7528\u65bc\u6b78\u6a94\u3001\u5eab\u5b58\u3001\u90f5\u5bc4\u548c\u6578\u64da\u5eab\u7684\u66f4\u65b0\u7cfb\u7d71;\u8655\u7406\u9032\u51fa\u8fa6\u516c\u5ba4\u4fe1\u4ef6\n\n\u8cc7\u6b77 :\u4e2d\u4e03\u7a0b\u5ea6; 1\u5e74\u7d93\u9a57; \u826f\u597d\u7cb5\u8a9e; \u4e00\u822c\u666e\u901a\u8a71; \u4e00\u822c\u82f1\u8a9e; \u61c2\u8b80\u5beb\u4e2d\u6587; \u61c2\u8b80\u5beb\u82f1\u6587; \u5b8c\u6210\u5546\u79d1\u8a13\u7df4; \u5177\u6709\u57fa\u672c\u96fb\u8166\u64cd\u4f5c\u77e5\u8b58\n\n\u5f85\u9047 :\u6bcf\u6708$12,000 - $14,000, \u661f\u671f\u4e00\u81f3\u4e94: \u4e0a\u53489\u6642\u81f3\u4e0b\u53486\u6642, \u6bcf\u9031\u5de5\u4f5c5\u5929, \u6bcf\u5929\u5de5\u4f5c 8 \u5c0f\u6642\n\n\u7533\u8acb\u9808\u77e5 :\u6c42\u8077\u8005\u53ef\u96fb\u90f5(Apply Now)\u5c65\u6b77\u8868\u7d66\u7ff9\u6a02\u9867\u554f\u6709\u9650\u516c\u53f8\u3002\u5982\u8981\u7d22\u53d6\u6536\u96c6\u500b\u4eba\u8cc7\u6599\u8072\u660e, \u8acb\u8207\u6797\u5c0f\u59d0(34645222)\u806f\u7d61\u3002\n\n", "employment_types": ["Full Time", "Permanent"], "selling_points": [], "locations": ["Wan Chai"], "categories": ["Admin & HR", "Clerical / Admin Staff", "Others", "Property / Real Estate", "Others"], "post_time": "2022-01-17T02:55:24Z", "salary": {"currency": null, "max": null, "min": null, "period": null, "term": null}, "salary_visible": false, "title_keywords": ["project clerk"], "responsibilities": [], "requirements": {"degrees": [], "majors": [], "languages": [], "language_level": [], "hard_skills": [], "soft_skills": [], "languages_combined": []}, "experience_required": {"duration": [], "field": []}}, {"job_id": "100003009049434", "location_code": "hk", "company": "Job House Personnel Consultants", "job_title": "Clerk  (5-day Job)", "description": "Responsibilities : -\n\nHandling general administrative and clerical duties.\nKeeping staff attendance record.\nAnswering phone calls.\n\nRequirements : -\n\nF.5 Level or above, 1 year working experience.\nAssociate / HD / Degree fresh graduate will also be considered.\n\n\u00a0 Interested parties, please apply via Quick Apply or Non Members Apply", "employment_types": ["Full Time", "Permanent"], "selling_points": [], "locations": ["Tuen Mun Area"], "categories": ["Admin & HR", "Clerical / Admin Staff", "Marketing / Public Relations", "Marketing - General / Support", "Others", "Student / Fresh Graduate / No Experience"], "post_time": "2022-01-15T19:11:38Z", "salary": {"currency": null, "max": null, "min": null, "period": "monthly", "term": null}, "salary_visible": false, "title_keywords": ["clerk"], "responsibilities": ["attendance", "phone calls"], "requirements": {"degrees": ["degree", "fresh graduate"], "majors": [], "languages": [], "language_level": [], "hard_skills": [], "soft_skills": [], "languages_combined": []}, "experience_required": {"duration": ["1 year"], "field": []}}, {"job_id": "100003009053505", "location_code": "hk", "company": "Learning Infinity", "job_title": "\u6559\u5ba4\u63a5\u5f85\u54e1(\u986f\u5f91\u7e3d\u6821)", "description": "\n\u5730\u5340\uff1a \u5927\u570d\u00a0\u00a0\n\u8077\u8cac\uff1a \u8ca0\u8cac\u5831\u540d\u67e5\u8a62\u53ca\u6536\u8cbb, \u9810\u5099\u6559\u6750\u548c\u7269\u8cc7, \u78ba\u4fdd\u8ab2\u5802\u9806\u66a2\u9032\u884c\n\u8cc7\u6b77\uff1a \u5c08\u4e0a\u6559\u80b2\uff1a\u6587\u6191/\u8b49\u66f8; \u826f\u597d\u7cb5\u8a9e; \u4e00\u822c\u82f1\u8a9e; \u61c2\u8b80\u5beb\u4e2d\u6587; \u61c2\u8b80\u5beb\u82f1\u6587; \u61c2\u82f1\u6587\u6253\u5b57; \u5de5\u4f5c\u614b\u5ea6\u89aa\u5207\u53cb\u5584\uff0c\u5177\u826f\u597d\u6e9d\u901a\u6280\u5de7\uff0c\u6e96\u6642\u4e0a\u73ed\uff0c\u5de5\u4f5c\u614b\u5ea6\u7a4d\u6975\uff0c\u6709\u8cac\u4efb\u5fc3\uff0c\u6709\u5718\u9ad4\u5408\u4f5c\u7cbe\u795e\n\u5f85\u9047\uff1a \u6bcf\u6708$10,000 - $12,000, \u6709\u914c\u60c5\u6027\u82b1\u7d05 \u53ca\u9280\u884c\u5047\u671f, \u661f\u671f\u4e00\u81f3\u4e94: \u4e0b\u53482\u6642\u81f3\u4e0b\u53489\u6642\u53ca\u661f\u671f\u516d: \u4e0a\u534810\u6642\u81f3\u4e0b\u53483\u6642, \u6bcf\u9031\u5de5\u4f5c5\u5929\u534a\n\u7533\u8acb\u9808\u77e5\uff1a \u6c42\u8077\u8005\u53ef\u96fb\u90f5([via\u00a0 Apply Now ])\u5c65\u6b77\u8868\u7d66\u5b78\u7fd2\u7121\u9650\u3002\u5982\u8981\u7d22\u53d6\u6536\u96c6\u500b\u4eba\u8cc7\u6599\u8072\u660e, \u8acb\u8207\u66fe \u5c0f\u59d0(Email)\u806f\u7d61\u3002\n\n", "employment_types": ["Full Time"], "selling_points": [], "locations": ["Shatin Area"], "categories": ["Admin & HR", "Clerical / Admin Staff", "Receptionist", "Others"], "post_time": "2022-01-17T07:04:23Z", "salary": {"currency": null, "max": null, "min": null, "period": "monthly", "term": null}, "salary_visible": false, "title_keywords": [], "responsibilities": [], "requirements": {"degrees": [], "majors": [], "languages": [], "language_level": [], "hard_skills": [], "soft_skills": [], "languages_combined": []}, "experience_required": {"duration": [], "field": []}}, {"job_id": "100003009053776", "location_code": "hk", "company": "Yat Cheung Fish Limited", "job_title": "\u6253\u55ae\u6587\u54e1", "description": "\n\u8077\u8cac :\u8a08\u6578,\u5c0d\u6578,\u6253\u55ae,\u4e00\u822c\u5beb\u5b57\u6a13\u5de5\u4f5c\n\n\u8cc7\u6b77 :\u4e2d\u56db\u7a0b\u5ea6; 1\u5e74\u7d93\u9a57; \u826f\u597d\u7cb5\u8a9e; \u4e00\u822c\u666e\u901a\u8a71; \u4e00\u822c\u82f1\u8a9e; \u61c2\u95b1\u8b80\u4e2d\u6587; \u61c2\u95b1\u8b80\u82f1\u6587; \u5177\u6709\u57fa\u672c\u96fb\u8166\u64cd\u4f5c\u77e5\u8b58; \u6709\u5718\u968a\u5408\u4f5c\u7cbe\u795e\u53ca\u6e9d\u901a\u80fd\u529b,\u8655\u4e8b\u7d30\u5fc3\n\n\u5f85\u9047 :\u6bcf\u6708$12,000 (\u516c\u53f8\u4ee3\u4f9b\u50f1\u54e15%\u5f37\u7a4d\u91d1), \u4e0a\u53489\u664245\u5206\u81f3\u4e0b\u53485\u664245\u5206, \u6bcf\u9031\u5de5\u4f5c6\u5929,\u8f2a\u4f11\n\n\u7533\u8acb\u9808\u77e5 :\u6c42\u8077\u8005\u53ef\u96fb\u90f5(Apply Now)\u5c65\u6b77\u8868\u7d66\u65e5\u7965\u6c34\u7522\u6709\u9650\u516c\u53f8\u3002\u5982\u8981\u7d22\u53d6\u6536\u96c6\u500b\u4eba\u8cc7\u6599\u8072\u660e, \u8acb\u8207\u6eab\u5973\u58eb(Email)\u806f\u7d61\u3002\n\n", "employment_types": ["Full Time"], "selling_points": [], "locations": ["Not Specified"], "categories": ["Admin & HR", "Clerical / Admin Staff", "Others"], "post_time": "2022-01-17T07:30:37Z", "salary": {"currency": null, "max": null, "min": null, "period": "monthly", "term": null}, "salary_visible": false, "title_keywords": [], "responsibilities": [], "requirements": {"degrees": [], "majors": [], "languages": [], "language_level": [], "hard_skills": [], "soft_skills": [], "languages_combined": []}, "experience_required": {"duration": [], "field": []}}, {"job_id": "100003009053865", "location_code": "hk", "company": "Grandnorm International Wealth Management Limited", "job_title": "\u6703\u8a08\u6587\u54e1", "description": "\n\u8077\u8cac :\u8ca0\u8cac\u7de8\u88fd\u5404\u9805\u5831\u8868\u53ca\u65e5\u5e38\u6703\u8a08\u5e33\u76ee, \u8cc7\u6599\u6574\u7406\u53ca\u6b78\u6a94\u5de5\u4f5c, \u4e00\u822c\u6587\u66f8\u53ca\u884c\u653f\u5de5\u4f5c\n\n\u8cc7\u6b77 :\u4e2d\u516d\u7a0b\u5ea6; 1\u5e74\u7d93\u9a57; \u826f\u597d\u7cb5\u8a9e; \u826f\u597d\u666e\u901a\u8a71; \u826f\u597d\u82f1\u8a9e; \u61c2\u8b80\u5beb\u4e2d\u6587; \u61c2\u8b80\u5beb\u82f1\u6587; \u61c2Peachtree; \u61c2MS Word; \u61c2MS Outlook; \u61c2MS Excel; \u6301\u6709LCC\u4e2d\u7d1a\u8b49\u66f8; \u5de5\u4f5c\u7a4d\u6975\u4e3b\u52d5, \u6709\u8cac\u4efb\u611f\u53ca\u9858\u610f\u5b78\u7fd2\n\n\u5f85\u9047 :\u6bcf\u6708$14,000 - $15,000, \u6709\u96d9\u7ce7, \u9280\u884c\u5047\u671f \u53ca\u91ab\u7642\u4fdd\u96aa, \u661f\u671f\u4e00\u81f3\u4e94: \u4e0a\u53489\u6642\u81f3\u4e0b\u53486\u6642\u53ca\u661f\u671f\u516d: \u4e0a\u53489\u6642\u81f3\u4e0b\u53481\u6642, \u6bcf\u9031\u5de5\u4f5c5\u5929\u81f35\u5929\u534a\n\n\u7533\u8acb\u9808\u77e5 :\u6c42\u8077\u8005\u53ef\u96fb\u90f5(Apply Now)\u5c65\u6b77\u8868\u7d66\u6d2a\u7bc4\u570b\u969b\u8ca1\u5bcc\u7ba1\u7406\u6709\u9650\u516c\u53f8\u3002\u5982\u8981\u7d22\u53d6\u6536\u96c6\u500b\u4eba\u8cc7\u6599\u8072\u660e, \u8acb\u8207\u912d\u5148\u751f(Email)\u806f\u7d61\u3002\n\n", "employment_types": ["Full Time"], "selling_points": [], "locations": ["Tsim Sha Tsui"], "categories": ["Admin & HR", "Clerical / Admin Staff", "Others"], "post_time": "2022-01-17T07:39:19Z", "salary": {"currency": null, "max": null, "min": null, "period": "monthly", "term": null}, "salary_visible": false, "title_keywords": [], "responsibilities": [], "requirements": {"degrees": [], "majors": [], "languages": [], "language_level": [], "hard_skills": ["excel", "outlook", "word"], "soft_skills": [], "languages_combined": []}, "experience_required": {"duration": [], "field": []}}, {"job_id": "100003007253557", "location_code": "hk", "company": "For You Education Limited", "job_title": "Marketing Clerk/Junior Graphic Designer (Fresh graduated)", "description": "Job Responsibilities:\n\nManage company\u2019s social media platform and other online marketing tools.\nDeveloping concepts, graphics and layouts for\u00a0online & offline advertising materials.\nCreating innovative\u00a0concepts in line with integrated marketing campaigns.\nCollaborating with other departments in advertising materials (posters, website or leaflet) and academic materials (notes or other publications)\nResponsible for any ad-hoc duties as assigned by Senior Management\nAssist to handle daily office administration duties\n\nRequirements:\n\nDiploma in Graphic Design or related disciplines\nInterested in education field\nGood sense of marketing and graphic design skills\nHands on knowledge in computer graphics or video editing software such as Illustrator, Photoshop or iMovie / Final Cut Pro\nMulti-tasking and able to work under tight schedule\nFresh graduates are also welcome\nEnthusiasm, patient and outspoken person with excellent communication andinterpersonal skills;\nPunctual, responsible and highly self-motivated individual\nAble to work as part of a team\n\nWe are offering:\u00a0\n\nMonthly salary of $13,000 or above (negotiable) with attractive bonus scheme and annual leave\nTraining regarding online marketing\nFlexible working hours that matches your own life commitments\nWorking hours: 5 days a week including Saturday; Monday \u2013 Friday 11am-7pm, Saturday 10am-6pm\n\nInterested parties, please click \"Apply Now\" and attach your cover letter and full resume. Data collected will be used for recruitment purposes only.\nFor further information about For You Education Ltd, please visit our website:\u00a0www.foryouedu.com.hk.", "employment_types": ["Full Time", "Permanent"], "selling_points": ["5 days work", "OT compensation leave provided", "Training for online marketing will be provided"], "locations": ["Causeway Bay"], "categories": ["Admin & HR", "Clerical / Admin Staff", "Education", "Others", "Marketing / Public Relations", "Digital Marketing"], "post_time": "2022-01-17T03:10:12Z", "salary": {"currency": null, "max": null, "min": null, "period": "monthly", "term": null}, "salary_visible": false, "title_keywords": ["clerk", "junior graphic designer"], "responsibilities": ["graphics", "social media", "advertising", "leaflet", "developing", "website", "marketing campaigns", "ad-hoc duties", "office administration duties", "senior management"], "requirements": {"degrees": ["diploma"], "majors": ["related disciplines", "graphic design"], "languages": [], "language_level": [], "hard_skills": ["graphics", "final cut pro", "illustrator", "scheme", "video editing", "photoshop"], "soft_skills": ["flexible", "self-motivated", "responsible", "interested in", "outspoken", "communication", "multi-tasking", "hands on", "patient"], "languages_combined": []}, "experience_required": {"duration": [], "field": []}}, {"job_id": "100003009054192", "location_code": "hk", "company": "Hong Kong Arts Development Council", "job_title": "Office Support Assistant (Job ref: OSA-2206-JDB)", "description": "Main Duties:\n\n\u00a0 Perform all-round reception counter service, answer phone calls and general enquiries;\n\u00a0 Record and distribute incoming and outgoing mails/couriers and e-Fax etc.;\n\u00a0 Handle meeting room bookings and provide logistic support for Council / Committee meetings;\n\u00a0 Record and ensure office stationery supplies and distribution;\n\u00a0 Responsible for record grant applications registrations and distribution;\n\u00a0 Provide departmental administrative and clerical support;\n\u00a0 Other ad-hoc duties assigned by supervisors\n\nRequirements:\n\n\u00a0 F.5 graduate with 5 passes in HKDSE or above; minimum 1-year working experience;\n\u00a0 Pleasant, courteous with good telephone manner and good communication skills in both English and Chinese;\n\u00a0 Proficient in MS Office and Chinese word processing;\n\u00a0 Punctual, work independently and good at multi-tasking;\n\u00a0 Able to work on Saturday/Sunday occasionally;\n\u00a0 Fresh graduates with some working experience may also be considered.\n\nSalary offered will be commensurate with qualifications and experience. Interested parties, please send CV with details on education and work experience, stating salary history and expected salary, and indicating your earliest availability to the Human Resources Department, 10/F, 1063 King\u2019s Road, Quarry Bay, Hong Kong no later than 4 February 2022. Please quote the job reference on the envelope.\n\nApplicants not invited for interview within 16 weeks from the closing date for application may assume that their applications are unsuccessful. Personal data collected will be treated in strictest confidence and will only be used for recruitment purposes. HKADC reserves the right to consider late applications and not to make appointment for the post advertised. We do not accept applications through e-mail or fax.\n\nHKADC is an Equal Opportunities Employer", "employment_types": ["Full Time", "Permanent"], "selling_points": [], "locations": ["Quarry Bay"], "categories": ["Admin & HR", "Clerical / Admin Staff", "Receptionist", "Public / Civil", "Social Services - Community / Non-profit Organization"], "post_time": "2022-01-17T09:17:02Z", "salary": {"currency": null, "max": null, "min": null, "period": "monthly", "term": null}, "salary_visible": false, "title_keywords": ["assistant"], "responsibilities": ["logistic support", "stationery", "administrative and clerical support", "ad-hoc duties", "incoming and outgoing mails", "answer phone calls"], "requirements": {"degrees": ["hkdse"], "majors": [], "languages": ["english", "chinese"], "language_level": ["proficient", "good"], "hard_skills": ["chinese word processing", "ms office"], "soft_skills": ["communication skills", "courteous", "work independently", "pleasant", "multi-tasking", "telephone manner"], "languages_combined": [{"language": "english", "language_level": ["good"]}, {"language": "chinese", "language_level": ["proficient", "good"]}]}, "experience_required": {"duration": ["minimum 1-year"], "field": []}}, {"job_id": "100003009053548", "location_code": "hk", "company": "Hong Kong Community Network Limited", "job_title": "\u793e\u5340\u5e79\u4e8b", "description": "\n\u8077\u8cac :\u5354\u52a9\u6a5f\u69cb\u65e5\u5e38\u670d\u52d9\u53ca\u6d3b\u52d5\u3001\u6587\u66f8\u8655\u7406\n\n\u8cc7\u6b77 :\u5c08\u4e0a\u6559\u80b2\uff1a\u6587\u6191/\u8b49\u66f8; 1\u5e74\u7d93\u9a57; \u826f\u597d\u7cb5\u8a9e; \u4e00\u822c\u666e\u901a\u8a71; \u4e00\u822c\u82f1\u8a9e; \u61c2\u8b80\u5beb\u4e2d\u6587; \u61c2\u8b80\u5beb\u82f1\u6587; \u61c2\u5f97\u4f7f\u7528\u8a2d\u8a08\u8edf\u4ef6\u6216\u6709\u7db2\u9801\u7ba1\u7406\u7d93\u9a57\u512a\u5148\n\n\u5f85\u9047 :\u6bcf\u6708$10,000 - $15,000, \u661f\u671f\u4e00\u81f3\u516d: \u4e0a\u534810\u6642\u81f3\u4e0b\u53486\u6642, \u6bcf\u9031\u5de5\u4f5c5\u5929\u81f36\u5929, \u6bcf\u5929\u5de5\u4f5c 8 \u5c0f\u6642\n\n\u7533\u8acb\u9808\u77e5 :\u6c42\u8077\u8005\u53ef\u96fb\u90f5(Apply Now)\u5c65\u6b77\u8868\u7d66\u9999\u6e2f\u793e\u5340\u7db2\u7d61\u6709\u9650\u516c\u53f8\u3002\u5982\u8981\u7d22\u53d6\u6536\u96c6\u500b\u4eba\u8cc7\u6599\u8072\u660e, \u8acb\u8207\u66fe\u5148\u751f(Email)\u806f\u7d61\u3002\n\n", "employment_types": ["Full Time"], "selling_points": [], "locations": ["Kwai Hing"], "categories": ["Admin & HR", "Clerical / Admin Staff"], "post_time": "2022-01-17T07:08:32Z", "salary": {"currency": null, "max": null, "min": null, "period": "monthly", "term": null}, "salary_visible": false, "title_keywords": [], "responsibilities": [], "requirements": {"degrees": [], "majors": [], "languages": [], "language_level": [], "hard_skills": [], "soft_skills": [], "languages_combined": []}, "experience_required": {"duration": [], "field": []}}, {"job_id": "100003009052431", "location_code": "hk", "company": "CMA Exhibition Services Limited", "job_title": "Administrative Officer (Executive Officer)", "description": "Reporting to Chief Operating Officer\n\nJob duties:\n\nTo provide secretariat support to the Board of the company, including logistic arrangements for meetings, preparation of notices, circulars, agenda, reports and minutes\nTo prepare press release, speeches and letter, etc\nTo manage overall administrative duties, including asset management, office equipment maintenance, procurement, filing and general correspondence, etc\nTo handle overseas travel arrangement\nTo formulate and implement of the policies, guidelines and procedures for tender\nTo formulate and implement of the staff manual and financial manual\nTo work closely with colleagues at all levels\nTo organize division activities and gala dinner, etc\nTo perform any other appropriate duties as assigned by Chief Operating Officer\n\nJob requirements:\n\nA university degree in Journalism, Language, Business Administration preferred (fresh graduate will not be consider)\nA minimum of 1 year\u2019 relevant working experience, experience in reporter or copywriter background are highly considered\nMust be excellent command of both spoken and written English and Chinese\nHigh level of computer literacy, proficiency in using MS office including Word, Excel, PowerPoint and Chinese word processing\nMust be detail-minded, well-organised, and proactive with a strong sense of responsibility\nGood problem-solving,communication and interpersonal skills\nAbility to work independently\nAble to multi-task, work under pressure and meet tight deadlines\nWilling to work overtime\u00a0 \u00a0 \u00a0 \u00a0 \u00a0 \u00a0 \u00a0 \u00a0 \u00a0 \u00a0 \u00a0 \u00a0 \u00a0 \u00a0 \u00a0 \u00a0 \u00a0 \u00a0 \u00a0\nImmediate availability is preferred.\n\nWe offer competitive remuneration and all applications will be treated in strict confidence. If your profile matches the above requirements, please send your full resume including your last and expected salary to us\n\n\u00a0Data collected will be used for recruitment purpose only.", "employment_types": ["Full Time", "Permanent"], "selling_points": [], "locations": ["Central"], "categories": ["Admin & HR", "Clerical / Admin Staff", "HR Supporting Staff"], "post_time": "2022-01-17T03:00:42Z", "salary": {"currency": null, "max": null, "min": null, "period": "monthly", "term": null}, "salary_visible": false, "title_keywords": ["executive officer", "administrative officer"], "responsibilities": ["guidelines", "policies", "procedures", "office equipment maintenance", "administrative duties", "reports", "travel arrangement", "tender", "asset management"], "requirements": {"degrees": ["university degree", "fresh graduate"], "majors": ["journalism", "business administration"], "languages": ["english", "chinese"], "language_level": ["excellent", "proficiency"], "hard_skills": ["excel", "chinese word processing", "problem-solving", "word", "powerpoint", "ms office"], "soft_skills": ["detail-minded", "work independently", "meet tight deadlines", "multi-task", "work overtime", "sense of responsibility", "problem-solving", "computer literacy", "communication and interpersonal skills", "well-organised", "proactive", "work under pressure"], "languages_combined": [{"language": "english", "language_level": ["excellent"]}, {"language": "chinese", "language_level": ["excellent", "proficiency"]}]}, "experience_required": {"duration": ["minimum of 1 year"], "field": ["reporter", "relevant working experience"]}}, {"job_id": "100003009053742", "location_code": "hk", "company": "Top Conqueror Limited", "job_title": "\u8239\u52d9\u6587\u54e1**", "description": "\n\u8077\u8cac :\u5c0d\u5167\u5730\u4e0a\u843d\u8ca8,\u51fa\u5165\u53e3\u6587\u4ef6\uff0cTradelink, LC , \u5831\u95dc\uff0c\u5ba2\u4eba\u8ca8\u671f\u8edf\u4ef6\u64cd\u4f5c\uff0c\u4e00\u822c\u6587\u66f8\u8655\u7406\u3002\n\n\u8cc7\u6b77 :\u4e2d\u4e94\u7a0b\u5ea6; 5\u5e74\u7d93\u9a57; \u826f\u597d\u7cb5\u8a9e; \u4e00\u822c\u666e\u901a\u8a71; \u4e00\u822c\u82f1\u8a9e; \u61c2\u8b80\u5beb\u4e2d\u6587; \u61c2\u8b80\u5beb\u82f1\u6587\n\n\u5f85\u9047 :\u6bcf\u6708$13,000 - $13,500, \u6709\u4f9b\u81b3\u98df, \u661f\u671f\u4e00\u81f3\u4e94: \u4e0a\u53489\u6642\u81f3\u4e0b\u53486\u6642, \u6bcf\u9031\u5de5\u4f5c5\u5929, \u6bcf\u5929\u5de5\u4f5c 8 - 9 \u5c0f\u6642\n\n\u7533\u8acb\u9808\u77e5 :\u6c42\u8077\u8005\u53ef\u96fb\u90f5(Apply Now)\u5c65\u6b77\u8868\u7d66\u4e0a\u5ee3\u6709\u9650\u516c\u53f8\u3002\u5982\u8981\u7d22\u53d6\u6536\u96c6\u500b\u4eba\u8cc7\u6599\u8072\u660e, \u8acb\u8207\u738b\u5c0f\u59d0(Email)\u806f\u7d61\u3002\n\n", "employment_types": ["Full Time"], "selling_points": [], "locations": ["Wong Tai Sin Area"], "categories": ["Admin & HR", "Clerical / Admin Staff", "Others"], "post_time": "2022-01-17T07:26:37Z", "salary": {"currency": null, "max": null, "min": null, "period": "monthly", "term": null}, "salary_visible": false, "title_keywords": [], "responsibilities": [], "requirements": {"degrees": [], "majors": [], "languages": [], "language_level": [], "hard_skills": [], "soft_skills": [], "languages_combined": []}, "experience_required": {"duration": [], "field": []}}, {"job_id": "100003009053730", "location_code": "hk", "company": "Sunlight Eco-Tech Limited", "job_title": "\u6703\u8a08\u6587\u54e1**", "description": "\n\u8077\u8cac :\u8ca0\u8cac\u65e5\u5e38\u6703\u8a08\u4e8b\u52d9\u53ca\u5168\u76e4\u6703\u8a08\u5de5\u4f5c,\u8a08\u7ce7,\u8a08\u7b97\u5f37\u7a4d\u91d1,\u61c9\u6536,\u61c9\u4ed8,\u7c3f\u8a18,\u958b\u7968,\u5354\u52a9\u6708\u7d50\u53ca\u6574\u7406\u6587\u4ef6,\u9280\u884c\u5c0d\u8cec,\u5e74\u5ea6\u5be9\u8a08\u53ca\u5831\u7a05\u4e8b\u5b9c\n\n\u8cc7\u6b77 :\u4e2d\u4e94\u7a0b\u5ea6; 2\u5e74\u7d93\u9a57; \u4e00\u822c\u7cb5\u8a9e; \u4e00\u822c\u666e\u901a\u8a71; \u4e00\u822c\u82f1\u8a9e; \u61c2\u8b80\u5beb\u4e2d\u6587; \u7565\u61c2\u8b80\u5beb\u82f1\u6587; \u61c2\u82f1\u6587\u6253\u5b57; \u61c2\u4e2d\u82f1\u6587\u96fb\u8166\u64cd\u4f5c; \u61c2\u4e2d\u6587\u6253\u5b57; \u6301LCC\u4e2d\u7d1a\u6216\u4ee5\u4e0a\u8b49\u66f8\u6216\u540c\u7b49\u5b78\u6b77,\u51772\u5e74\u6216\u4ee5\u4e0a\u76f8\u95dc\u7d93\u9a57\n\n\u5f85\u9047 :\u6bcf\u6708$12,000\u6216\u4ee5\u4e0a, \u6709\u96d9\u7ce7 \u53ca\u9280\u884c\u5047\u671f, \u661f\u671f\u4e00\u81f3\u4e94: \u4e0a\u534810\u6642\u81f3\u4e0b\u53486\u6642, \u6bcf\u9031\u5de5\u4f5c5\u5929,\u7528\u81b3\u6642\u9593\u7531\u4e2d\u534812\u6642\u81f3\u4e0b\u53481\u6642\n\n\u7533\u8acb\u9808\u77e5 :\u6c42\u8077\u8005\u53ef\u96fb\u90f5(Apply Now)\u5c65\u6b77\u8868\u7d66\u65b0\u76c8\u74b0\u4fdd\u79d1\u6280\u6709\u9650\u516c\u53f8\u3002\u5982\u8981\u7d22\u53d6\u6536\u96c6\u500b\u4eba\u8cc7\u6599\u8072\u660e, \u8acb\u8207\u6613\u5c0f\u59d0(Email)\u806f\u7d61\u3002\n\n", "employment_types": ["Full Time"], "selling_points": [], "locations": ["Shatin Area"], "categories": ["Admin & HR", "Clerical / Admin Staff", "Others"], "post_time": "2022-01-17T07:25:20Z", "salary": {"currency": null, "max": null, "min": null, "period": "monthly", "term": null}, "salary_visible": false, "title_keywords": [], "responsibilities": [], "requirements": {"degrees": [], "majors": [], "languages": [], "language_level": [], "hard_skills": [], "soft_skills": [], "languages_combined": []}, "experience_required": {"duration": [], "field": []}}, {"job_id": "100003009053587", "location_code": "hk", "company": "Pal Line Industrial Company Limited", "job_title": "\u6587\u54e1", "description": "\n\u8077\u8cac :\u4e00\u822c\u6587\u54e1\u5de5\u4f5c, \u5354\u52a9\u8ddf\u55ae\n\n\u8cc7\u6b77 :\u4e2d\u516d\u7a0b\u5ea6; \u826f\u597d\u7cb5\u8a9e; \u4e00\u822c\u666e\u901a\u8a71; \u4e00\u822c\u82f1\u8a9e\u512a\u5148; \u61c2\u8b80\u5beb\u4e2d\u6587; \u61c2\u8b80\u5beb\u82f1\u6587; \u61c2MS Outlook; \u61c2MS Excel; \u61c2\u4e2d\u6587\u6253\u5b57 20 \u5b57(\u6bcf\u5206\u9418); \u5de5\u4f5c\u52e4\u596e, \u9858\u610f\u5b78\u7fd2\u65b0\u4e8b\u7269\n\n\u5f85\u9047 :\u6bcf\u6708$11,000 - $13,000, \u6709\u96d9\u7ce7, \u9280\u884c\u5047\u671f\u53ca\u5e74\u7d42\u734e\u91d1, \u661f\u671f\u4e00\u81f3\u4e94: \u4e0a\u53488\u664245\u5206\u81f3\u4e0b\u53486\u6642, \u6bcf\u9031\u5de5\u4f5c5\u5929\n\n\u7533\u8acb\u9808\u77e5 :\u6c42\u8077\u8005\u53ef\u96fb\u90f5(Apply Now)\u5c65\u6b77\u8868\u7d66\u532f\u9032\u5be6\u696d\u767c\u5c55\u6709\u9650\u516c\u53f8\u3002\u5982\u8981\u7d22\u53d6\u6536\u96c6\u500b\u4eba\u8cc7\u6599\u8072\u660e, \u8acb\u8207\u912d\u5c0f\u59d0(Email)\u806f\u7d61\u3002\n\n", "employment_types": ["Full Time"], "selling_points": [], "locations": ["Hung Hom"], "categories": ["Admin & HR", "Clerical / Admin Staff", "Others"], "post_time": "2022-01-17T07:12:31Z", "salary": {"currency": null, "max": null, "min": null, "period": "monthly", "term": null}, "salary_visible": false, "title_keywords": ["\u6587\u54e1"], "responsibilities": [], "requirements": {"degrees": [], "majors": [], "languages": [], "language_level": [], "hard_skills": ["excel", "outlook"], "soft_skills": [], "languages_combined": []}, "experience_required": {"duration": [], "field": []}}, {"job_id": "100003009053757", "location_code": "hk", "company": "Kalong Express Limited", "job_title": "\u7269\u6d41\u6587\u54e1", "description": "\n\u8077\u8cac :\u8ca0\u8cac\u51fa\u5165\u53e3\u6587\u4ef6\uff0c\u8655\u7406\u4e00\u822c\u6587\u66f8\u5de5\u4f5c\uff0c\u8207\u4f9b\u61c9\u5546\u5354\u8abf\u53ca\u6e9d\u901a\u8239\u52d9\u4e8b\u5b9c\u3002\n\n\u8cc7\u6b77 :\u4e2d\u4e94\u7a0b\u5ea6; 1\u5e74\u7d93\u9a57; \u826f\u597d\u7cb5\u8a9e; \u826f\u597d\u666e\u901a\u8a71\u512a\u5148; \u4e00\u822c\u82f1\u8a9e; \u61c2\u8b80\u5beb\u4e2d\u6587; \u61c2\u8b80\u5beb\u82f1\u6587; \u61c2Microsoft Office; \u61c2\u5009\u9821/\u901f\u6210\u8f38\u5165\u6cd5; \u826f\u597d\u6e9d\u901a\u53ca\u8655\u4e8b\u6280\u5de7\uff0c\u6709\u8cac\u4efb\u611f\u548c\u826f\u597d\u57f7\u884c\u6280\u5de7\uff0c\u5de5\u4f5c\u7a4d\u6975\u9032\u53d6\n\n\u5f85\u9047 :\u6bcf\u6708$11,000 - $12,000, \u6709\u9280\u884c\u5047\u671f, \u5e74\u50477-14\u5929 \u53ca\u914c\u60c5\u6027\u82b1\u7d05, \u661f\u671f\u4e00\u81f3\u4e94: \u4e0a\u53489\u6642\u81f3\u4e0b\u53486\u6642, \u6bcf\u9031\u5de5\u4f5c5\u5929, \u6bcf\u5929\u5de5\u4f5c 8 \u5c0f\u6642\n\n\u7533\u8acb\u9808\u77e5 :\u6c42\u8077\u8005\u53ef\u96fb\u90f5(Apply Now)\u5c65\u6b77\u8868\u7d66\u6ea2\u90a6\u8ca8\u904b\u6709\u9650\u516c\u53f8\u3002\u5982\u8981\u7d22\u53d6\u6536\u96c6\u500b\u4eba\u8cc7\u6599\u8072\u660e, \u8acb\u8207\u5289\u5148\u751f(Email)\u806f\u7d61\u3002\n\n", "employment_types": ["Full Time"], "selling_points": [], "locations": ["Tsuen Wan Area"], "categories": ["Admin & HR", "Clerical / Admin Staff", "Others"], "post_time": "2022-01-17T07:28:09Z", "salary": {"currency": null, "max": null, "min": null, "period": "monthly", "term": null}, "salary_visible": false, "title_keywords": [], "responsibilities": [], "requirements": {"degrees": [], "majors": [], "languages": [], "language_level": [], "hard_skills": [], "soft_skills": [], "languages_combined": []}, "experience_required": {"duration": [], "field": []}}, {"job_id": "100003009053916", "location_code": "hk", "company": "3XM Limited", "job_title": "\u6578\u78bc\u71df\u92b7\u884c\u653f\u4eba\u54e1", "description": "\n\u8077\u8cac :\u7ba1\u7406\u5728\u7dda\u71df\u92b7\u5e73\u53f0, \u5982\u7db2\u7ad9\u3001\u96fb\u5b50\u5546\u52d9\u7db2\u7ad9\u3001\u95dc\u9375\u793e\u4ea4\u5a92\u9ad4\u6e20\u9053, \u4ee5\u78ba\u4fdd\u6700\u65b0\u548c\u6642\u5c1a\u7684\u4fe1\u606f; \u70ba\u7db2\u7ad9\u548c\u71df\u92b7\u6e20\u9053\u5275\u5efa\u548c\u958b\u767c\u5f15\u4eba\u5165\u52dd\u7684\u5167\u5bb9, \u5305\u62ec\u64b0\u5beb\u548c\u7de8\u8f2f\u793e\u4ea4\u5a92\u9ad4\u63d0\u8981\u548c\u65b0\u805e\u7a3f; \u63d0\u4f9b\u5b9a\u671f\u6578\u64da\u5206\u6790\u548c\u71df\u92b7\u6d3b\u52d5\u6548\u679c\u5831\u544a; \u8a08\u5283\u3001\u7d44\u7e54\u548c\u57f7\u884c\u6bcf\u9031\u7684\u793e\u4ea4\u5a92\u9ad4\u548c\u5176\u4ed6\u71df\u92b7\u5e73\u53f0\u4fc3\u92b7\u6d3b\u52d5; \u5354\u52a9\u65e5\u5e38\u904b\u4f5c\n\n\u8cc7\u6b77 :\u5c08\u4e0a\u6559\u80b2\uff1a\u6587\u6191/\u8b49\u66f8; \u4e00\u822c\u7cb5\u8a9e; \u4e00\u822c\u666e\u901a\u8a71; \u4e00\u822c\u82f1\u8a9e\u512a\u5148; \u7565\u61c2\u8b80\u5beb\u4e2d\u6587; \u7565\u61c2\u8b80\u5beb\u82f1\u6587; \u61c2Microsoft Office; \u5177\u6709\u4e00\u822c\u4e92\u806f\u7db2\u77e5\u8b58; \u61c2\u82f1\u6587\u6253\u5b57; \u5177\u6709\u57fa\u672c\u96fb\u8166\u64cd\u4f5c\u77e5\u8b58; \u5177\u5e02\u5834\u71df\u92b7\u3001\u516c\u95dc\u3001\u50b3\u64ad\u3001\u5546\u696d\u6216\u4efb\u4f55\u5176\u4ed6\u76f8\u95dc\u9818\u57df\u6587\u6191/\u8b49\u66f8/\u5b78\u4f4d\n\n\u5f85\u9047 :\u6bcf\u6708$13,000, \u6709\u8868\u73fe\u734e\u91d1, \u661f\u671f\u4e00\u81f3\u4e94: \u4e0a\u53489\u6642\u81f3\u4e0b\u53486\u6642, \u6bcf\u9031\u5de5\u4f5c5\u5929, \u6bcf\u5929\u5de5\u4f5c 8 - 9 \u5c0f\u6642\n\n\u7533\u8acb\u9808\u77e5 :\u6c42\u8077\u8005\u53ef\u96fb\u90f5(Apply Now)\u5c65\u6b77\u8868\u7d663XM LIMITED\u3002\u5982\u8981\u7d22\u53d6\u6536\u96c6\u500b\u4eba\u8cc7\u6599\u8072\u660e, \u8acb\u8207\u9673\u5148\u751f(Email)\u806f\u7d61\u3002\n\n", "employment_types": ["Full Time"], "selling_points": [], "locations": ["Southern Area"], "categories": ["Admin & HR", "Clerical / Admin Staff", "Education", "Teacher"], "post_time": "2022-01-17T07:45:34Z", "salary": {"currency": null, "max": null, "min": null, "period": "monthly", "term": null}, "salary_visible": false, "title_keywords": [], "responsibilities": [], "requirements": {"degrees": [], "majors": [], "languages": [], "language_level": [], "hard_skills": [], "soft_skills": [], "languages_combined": []}, "experience_required": {"duration": [], "field": []}}, {"job_id": "100003009054304", "location_code": "hk", "company": "Fionza International Group Limited", "job_title": "administrative officer / manager", "description": "Job Description\n\nResponsibilities:\n\nReporting to the Company Director and Sales Director, the appointee will mainly perform the following responsibilities:\u00a0\n\nTo handle various office administration, renovation, and provide quality secretarial / clerical services and maintain document filing system\u00a0\u00a0\nTo coordinate with department secretaries and administration officers in devising, finetuning and implementing administration policies and procedures\nTo help for recruitment, payroll calculation and monitor employee movements\nTo prepare and consolidate annual budget and control expenditure of administration services\nTo contribute and help overseeing to health, safety and environmental the office.\nParticipant in ad-hoc HR & General Admin projects\n\nRequirements:\n\nBachelor's Degree in Business Administration or related disciplines\nPossession of relevant qualification in Accounting an advantage\nA minimum of 2 years\u2019 relevant experience in sizable organizations\nExperience in committee secretariat, general administration and budget planning\nGood command of English and Chinese languages, both spoken and written\u00a0\nProficiency in MS Office applications, especially Word, Excel and PowerPoint etc.\nImmediate availability or short notices is highly preferred", "employment_types": ["Full Time"], "selling_points": [], "locations": ["Not Specified"], "categories": ["Admin & HR", "Clerical / Admin Staff"], "post_time": "2022-01-17T09:05:42Z", "salary": {"currency": null, "max": null, "min": null, "period": "monthly", "term": null}, "salary_visible": false, "title_keywords": ["administrative officer", "manager"], "responsibilities": ["ad-hoc", "reporting", "document filing", "control", "office administration", "policies", "renovation", "quality", "coordinate with", "procedures", "monitor", "budget", "hr", "maintain", "recruitment", "payroll", "administration"], "requirements": {"degrees": ["degree", "bachelor"], "majors": ["related disciplines", "business administration"], "languages": ["english", "chinese"], "language_level": ["good command"], "hard_skills": ["excel", "word", "powerpoint", "ms office"], "soft_skills": [], "languages_combined": [{"language": "english", "language_level": ["good command"]}, {"language": "chinese", "language_level": ["good command"]}]}, "experience_required": {"duration": ["minimum of 2 years"], "field": ["planning", "relevant experience", "administration"]}}, {"job_id": "100003009053737", "location_code": "hk", "company": "Silver Printing Company Limited", "job_title": "\u6587\u54e1", "description": "\n\u8077\u8cac :\u8ca0\u8cac\u4e00\u822c\u5ba2\u6236\u8a02\u55ae\u8655\u7406;\u8ca0\u8cac\u570b\u5167\u5916\u5ba2\u6236\u8a02\u55ae\u8655\u7406\u548c\u4e00\u822c\u8ca8\u904b\u6587\u4ef6; Responsible for clerical duties, data entry in ERP System, documents filing etc;Follow up order & quality control\n\n\u8cc7\u6b77 :\u4e2d\u4e94\u7a0b\u5ea6; 1\u5e74\u7d93\u9a57; \u826f\u597d\u7cb5\u8a9e; \u826f\u597d\u666e\u901a\u8a71\u512a\u5148; \u826f\u597d\u82f1\u8a9e\u512a\u5148; \u61c2\u8b80\u5beb\u4e2d\u6587; \u61c2\u8b80\u5beb\u82f1\u6587; \u61c2MS Word; \u61c2MS Outlook; \u61c2MS Excel; \u6709\u88fd\u8863\u6216\u5370\u5237\u8ddf\u55ae\u5de5\u4f5c\u7d93\u9a57\u512a\u5148; Hardworking & able to work under pressure\n\n\u5f85\u9047 :\u6bcf\u6708$13,000 - $16,000, \u6709\u5e74\u7d42\u96d9\u7ce7, \u661f\u671f\u4e00\u81f3\u4e94: \u4e0a\u53489\u6642\u81f3\u4e0b\u53486\u6642\u53ca\u661f\u671f\u516d: \u4e0a\u53489\u6642\u81f3\u4e0b\u53481\u6642, \u6bcf\u9031\u5de5\u4f5c5\u5929\u534a\n\n\u7533\u8acb\u9808\u77e5 :\u6c42\u8077\u8005\u53ef\u96fb\u90f5(Apply Now)\u5c65\u6b77\u8868\u7d66\u5f0f\u6167\u5370\u5237\u6709\u9650\u516c\u53f8\u3002\u5982\u8981\u7d22\u53d6\u6536\u96c6\u500b\u4eba\u8cc7\u6599\u8072\u660e, \u8acb\u8207\u4f55\u5c0f\u59d0(Email)\u806f\u7d61\u3002\n\n", "employment_types": ["Full Time"], "selling_points": [], "locations": ["Wong Tai Sin Area"], "categories": ["Admin & HR", "Clerical / Admin Staff", "Others"], "post_time": "2022-01-17T07:26:05Z", "salary": {"currency": null, "max": null, "min": null, "period": "monthly", "term": null}, "salary_visible": false, "title_keywords": ["\u6587\u54e1"], "responsibilities": ["work under pressure", "documents filing", "quality control", "data entry"], "requirements": {"degrees": [], "majors": [], "languages": [], "language_level": [], "hard_skills": ["excel", "erp system", "outlook", "word"], "soft_skills": ["hardworking", "responsible", "work under pressure"], "languages_combined": []}, "experience_required": {"duration": [], "field": []}}, {"job_id": "100003009053568", "location_code": "hk", "company": "IH Technology Limited", "job_title": "\u5009\u52d9\u6587\u54e1", "description": "\n\u8077\u8cac :\u4e00\u822c\u5009\u52d9\u6587\u54e1\u5de5\u4f5c, \u8ca0\u8cac\u65e5\u5e38\u6587\u66f8\u53ca\u5831\u8868\u5de5\u4f5c, \u8ddf\u9032\u51fa\u8ca8\u72c0\u6cc1\n\n\u8cc7\u6b77 :\u4e2d\u4e94\u7a0b\u5ea6; 1\u5e74\u7d93\u9a57; \u826f\u597d\u7cb5\u8a9e; \u4e00\u822c\u666e\u901a\u8a71; \u4e00\u822c\u82f1\u8a9e; \u61c2\u8b80\u5beb\u4e2d\u6587; \u61c2\u8b80\u5beb\u82f1\u6587; \u61c2MS Excel; \u5177\u6709\u57fa\u672c\u96fb\u8166\u64cd\u4f5c\u77e5\u8b58; \u5de5\u4f5c\u7368\u7acb, \u8655\u4e8b\u7d30\u5fc3, \u6709\u8cac\u4efb\u5fc3, \u9858\u610f\u5b78\u7fd2\n\n\u5f85\u9047 :\u6bcf\u6708$12,000 - $14,000, \u6709\u9280\u884c\u5047\u671f\u53ca\u5e74\u7d42\u734e\u91d1, \u661f\u671f\u4e00\u81f3\u4e94: \u4e0a\u53489\u6642\u81f3\u4e0b\u53486\u6642, \u6bcf\u9031\u5de5\u4f5c5\u5929\n\n\u7533\u8acb\u9808\u77e5 :\u6c42\u8077\u8005\u53ef\u96fb\u90f5(Apply Now)\u5c65\u6b77\u8868\u7d66\u82f1\u6d69\u79d1\u6280\u6709\u9650\u516c\u53f8\u3002\u5982\u8981\u7d22\u53d6\u6536\u96c6\u500b\u4eba\u8cc7\u6599\u8072\u660e, \u8acb\u8207\u912d\u5148\u751f(Email)\u806f\u7d61\u3002\n\n", "employment_types": ["Full Time"], "selling_points": [], "locations": ["Tsuen Wan Area"], "categories": ["Admin & HR", "Clerical / Admin Staff", "Others"], "post_time": "2022-01-17T07:10:26Z", "salary": {"currency": null, "max": null, "min": null, "period": "monthly", "term": null}, "salary_visible": false, "title_keywords": ["\u5009\u52d9\u6587\u54e1"], "responsibilities": [], "requirements": {"degrees": [], "majors": [], "languages": [], "language_level": [], "hard_skills": ["excel"], "soft_skills": [], "languages_combined": []}, "experience_required": {"duration": [], "field": []}}, {"job_id": "100003009053766", "location_code": "hk", "company": "Asia Shipping International Transport (HK) Limited", "job_title": "Receptionist and Administration Clerk", "description": "Job Description\n\n\u00a0\u2022 Answer incoming calls; greet visitors\n\n\u00a0\u2022 Provide logistics support, including couriers and mailings\n\n\u00a0\u2022 Handle invoice, expenses claim and other paperwork\n\n\u00a0\u2022 Manage the schedule of meetings room, organize company events\n\n\u00a0\u2022 Liaise with building management department on maintenance of office facilities\n\n\u00a0\u2022 Assist in other office administrative tasks\n\nPrepare ad-hoc assignment from time to time assigned by Supervisor.\n\n\u00a0Requirements:\n\n\u00a0\u2022 F.5/ DSE or above with experience in hospitality industry is an advantage\n\n\u00a0\u2022 Good command of English receptionist\n\n\u00a0\u2022 Good communication and interpersonal skill with positive and helpful attitude\n\n\u00a0\u2022 Be patient, cheerful personality\n\n\u00a0\u2022 Immediate available is preferred\n\n\u00a0\u2022 Fresh graduate also welcome to apply", "employment_types": ["Full Time"], "selling_points": [], "locations": ["Cheung Sha Wan"], "categories": ["Admin & HR", "Clerical / Admin Staff", "Receptionist", "Transportation & Logistics", "Freight Forwarding"], "post_time": "2022-01-17T07:29:04Z", "salary": {"currency": null, "max": null, "min": null, "period": "monthly", "term": null}, "salary_visible": false, "title_keywords": ["receptionist", "clerk"], "responsibilities": ["ad-hoc", "maintenance", "invoice", "expenses", "provide logistics support", "building management", "schedule", "liaise with", "administrative tasks"], "requirements": {"degrees": ["fresh graduate", "dse"], "majors": ["hospitality"], "languages": ["english"], "language_level": ["good command"], "hard_skills": [], "soft_skills": ["cheerful", "interpersonal skill", "communication", "patient", "positive"], "languages_combined": [{"language": "english", "language_level": ["good command"]}]}, "experience_required": {"duration": [], "field": ["hospitality industry"]}}, {"job_id": "100003009053900", "location_code": "hk", "company": "i Logistics Company Limited", "job_title": "\u7269\u6d41\u6587\u54e1", "description": "\n\u8077\u8cac :\u4e00\u822c\u7269\u6d41\u6587\u4ef6\u8655\u7406\n\n\u8cc7\u6b77 :\u4e2d\u4e94\u7a0b\u5ea6; 2\u5e74\u7d93\u9a57; \u826f\u597d\u7cb5\u8a9e; \u4e00\u822c\u666e\u901a\u8a71; \u4e00\u822c\u82f1\u8a9e; \u61c2\u8b80\u5beb\u4e2d\u6587; \u7565\u61c2\u8b80\u5beb\u82f1\u6587; \u61c2Excel, Outlook\u512a\u5148\n\n\u5f85\u9047 :\u6bcf\u6708$12,000 - $14,000, \u6709\u96d9\u7ce7, \u661f\u671f\u4e00\u81f3\u4e94: \u4e0a\u53489\u6642\u81f3\u4e0b\u53486\u6642\u53ca\u661f\u671f\u516d: \u4e0a\u53489\u6642\u81f3\u4e0b\u53481\u6642, \u6bcf\u9031\u5de5\u4f5c5\u5929\u81f35\u5929\u534a, \u6bcf\u5929\u5de5\u4f5c 8 \u5c0f\u6642\n\n\u7533\u8acb\u9808\u77e5 :\u6c42\u8077\u8005\u53ef\u81f4\u96fb23227983\u8207I LOGISTICS COMPANY LIMITED\u6797\u5c0f\u59d0\u806f\u7d61\u3002\n\n", "employment_types": ["Full Time"], "selling_points": [], "locations": ["Yuen Long"], "categories": ["Admin & HR", "Clerical / Admin Staff", "Others"], "post_time": "2022-01-17T07:43:20Z", "salary": {"currency": null, "max": null, "min": null, "period": "monthly", "term": null}, "salary_visible": false, "title_keywords": [], "responsibilities": ["logistics"], "requirements": {"degrees": [], "majors": [], "languages": [], "language_level": [], "hard_skills": [], "soft_skills": [], "languages_combined": []}, "experience_required": {"duration": [], "field": []}}, {"job_id": "100003009053379", "location_code": "hk", "company": "Trend-tek Corporation Limited", "job_title": "\u5009\u52d9\u6587\u54e1", "description": "\n\u8077\u8cac :\u6536\u8ca8\uff0c\u51fa\u8ca8\uff0c\u586b\u901f\u905e\u55ae\uff0c\u8655\u7406\u51fa\u8ca8\u6587\u4ef6\n\n\u8cc7\u6b77 :\u4e2d\u516d\u7a0b\u5ea6; 3\u5e74\u7d93\u9a57; \u4e00\u822c\u7cb5\u8a9e; \u4e00\u822c\u666e\u901a\u8a71; \u4e00\u822c\u82f1\u8a9e; \u61c2\u8b80\u5beb\u4e2d\u6587; \u7565\u61c2\u8b80\u5beb\u82f1\u6587; \u5de5\u4f5c\u7a4d\u6975\uff0c\u6709\u8cac\u4efb\u611f\uff0c\u826f\u597d\u6e9d\u901a\u53ca\u8868\u9054\u6280\u5de7\n\n\u5f85\u9047 :\u6bcf\u6708$13,000 - $15,000, \u6709\u9280\u884c\u5047\u671f, \u751f\u65e5\u5047, \u5a5a\u5047, \u5e74\u7d42\u734e\u91d1 \u53ca\u91ab\u7642\u4fdd\u96aa, \u661f\u671f\u4e00\u81f3\u4e94: \u4e0a\u53489\u6642\u81f3\u4e0b\u53486\u6642, \u6bcf\u9031\u5de5\u4f5c5\u5929, \u6bcf\u5929\u5de5\u4f5c 8 \u5c0f\u6642\n\n\u7533\u8acb\u9808\u77e5 :\u6c42\u8077\u8005\u53ef\u96fb\u90f5(Apply Now)\u5c65\u6b77\u8868\u7d66\u6668\u6cf0(\u9999\u6e2f)\u6709\u9650\u516c\u53f8\u3002\u5982\u8981\u7d22\u53d6\u6536\u96c6\u500b\u4eba\u8cc7\u6599\u8072\u660e, \u8acb\u8207\u90ed\u5c0f\u59d0(Email)\u806f\u7d61\u3002\n\n", "employment_types": ["Full Time"], "selling_points": [], "locations": ["Kwun Tong"], "categories": ["Admin & HR", "Clerical / Admin Staff", "Others"], "post_time": "2022-01-17T06:53:37Z", "salary": {"currency": null, "max": null, "min": null, "period": "monthly", "term": null}, "salary_visible": false, "title_keywords": ["\u5009\u52d9\u6587\u54e1"], "responsibilities": [], "requirements": {"degrees": [], "majors": [], "languages": [], "language_level": [], "hard_skills": [], "soft_skills": [], "languages_combined": []}, "experience_required": {"duration": [], "field": []}}]