[{"job_id": "100003009053866", "location_code": "hk", "company": "Arcelik Hitachi Home Appliance Sales Hong Kong Limited", "job_title": "Senior Officer, Human Resources (C&B)", "description": "Responsibilities:\n\nTo be responsible for performing HR operations, including but not limited to payroll and HRIS management, tax filing, benefits administration and analysis, attendance record, etc.\nManaging HRIS enhancement and collaborating with the headquarters, planning and executing UAT, and providing essential recommendations for the HRIS transformation process\nMaintaining employee database and ensuring all personal records are up-to-date and accurate\nAssisting in the formulation and implementation of HR policies and procedures in accordance with the company\u2019s rules & regulations\nSupporting the employment cycle includes but not limited to probation and performance management, internal staff movement, and termination or exit procedure\nCompiling regular HR related statistics and reports for management\u2019s review\nPerforming other ad hoc assignments or projects when assigned\nRequirements:\n\nBachelor\u2019s degree in HRM or Business related streams\nMinimum 5-year experience as a C&B specialist in MNC or sizable corporations\nSolid payroll knowledge and proficiency in HRIS with experiences in system transformation, preferably SAP\nProficient in Microsoft Excel application and sensitive to numbers\nFamiliar with Employment Ordinance and relevant legislations and regulations\nWell-organized, result-oriented, and able to handle multi tasks simultaneously\nPleasant personality, good team player with excellent interpersonal and communication skills\nGood command of both Cantonese and English\nLess experience may also be considered as HR Officer\nImmediately available is preferred\n\nWe offer:\n\nDouble-Pay\nDiscretionary Bonus\nMedical Benefits (Free Body Check in every year)\nDental Benefits\nStaff Purchase\nOn-the-job Training\nEducation Allowance\nFull Paid Sick Leave\nAnnual Leave Up to 18 Days\nBirthday Leave\nBirthday Coupon\nMarriage Leave\nCompany Picnic\n\nSuccessful candidates will receive an offer comprising a competitive package including attractive salary, retirement & medical benefits, leave provision, staff purchase discounts, training & development opportunities, etc.\n\nInterested parties, please send full resume with present and expected salary by clicking \"APPLY NOW\"\n\n**Application without present & expected salary will not be considered**\n\nPersonal data provided by job applicants will be treated in strict confidence.\nAll information will only be used for recruitment-related purposes.\n\nVisit us at\u00a0https://www.hitachi-homeappliances.com.hk\u00a0for more information", "employment_types": ["Full Time"], "selling_points": ["HR operations", "SAP HRIS transformation", "Stable business and working environment"], "locations": ["Shatin Area"], "categories": ["Admin & HR", "Others", "Compensation & Benefits", "HR Supporting Staff"], "post_time": "2022-01-17T07:41:01Z", "salary": {"currency": null, "max": null, "min": null, "period": "monthly", "term": null}, "salary_visible": false, "title_keywords": ["senior officer", "human resources"], "responsibilities": ["regulations", "operations", "database", "administration", "uat", "maintaining", "tax filing", "implementation", "reports", "attendance", "management", "review", "procedures", "executing", "payroll", "policies", "hr", "analysis", "ad hoc assignments", "planning"], "requirements": {"degrees": ["degree", "bachelor"], "majors": ["business"], "languages": ["cantonese", "english"], "language_level": ["good command"], "hard_skills": ["sap", "microsoft excel"], "soft_skills": ["communication skills", "good team player", "well-organized", "pleasant", "sensitive to numbers", "interpersonal", "result-oriented"], "languages_combined": [{"language": "cantonese", "language_level": ["good command"]}, {"language": "english", "language_level": ["good command"]}]}, "experience_required": {"duration": ["minimum 5-year"], "field": ["hr", "payroll"]}}, {"job_id": "100003009046795", "location_code": "hk", "company": "Hong Kong Young Women\u2019s Christian Association", "job_title": "Compensation and Benefits Officer", "description": "Key Responsibilities\n\nProvide full spectrum of Payroll and Compensation & Benefits (C&B) administration\u00a0including MPF/ORSO, leave, employee compensation, medical and insurance etc\nPrepare analytics and projections on payroll and benefits costs\nPrepare payroll related data for cost allocation and tracking\nEnsure compliance with the organization Human Resources policies & procedures, and regulations\nAssist the management in the preparation and roll-out of new benefits programs\nA key player to assist in the implementation and roll-out of ERP system on all HR aspects\nAssist in ongoing research into emerging trends, issues and best practices\nPrepare various HR reports and support audit process\n\nRequirements\n\nDegree in Human Resources Management, Business Administration or related disciplines\nMinimum 5 years experience in Human Resources, of which 3 years solid C&B role\nGood command of written and spoken Chinese & English\nHands on with proficiency in MS Excel, Word, and HR system, sound proficiency in ERP on HR modules\nWell versed and keep abreast with HK Employment Ordinance and other related legislation\nResilient, strong sense of responsibility, meticulous, accurate, well-organized, independent and a fast learner\nGood presentation, communication and interpersonal skills\n\nWe offer Paid Holiday (Annual Leave, Public Holiday, Maternity Leave / Paternity Leave, Training Leave), Training Subsidy, Medical Insurance and Subsidy, MPF Employer\u2019s Voluntary Contribution, Staff Discount etc.\u00a0\n\nInterested parties please send full resume with present and expected salary by:\n\nEmail: Click 'Apply Now' button\n\nOnly short-listed candidates will be contacted for interview and all personal data collected will be used for recruitment purposes only.\n\nWe are an equal opportunities employer", "employment_types": ["Full Time", "Permanent"], "selling_points": [], "locations": ["Central"], "categories": ["Admin & HR", "Compensation & Benefits", "HR Supporting Staff", "Public / Civil", "Social Services - Community / Non-profit Organization"], "post_time": "2022-01-14T04:59:57Z", "salary": {"currency": null, "max": null, "min": null, "period": "monthly", "term": null}, "salary_visible": false, "title_keywords": ["officer"], "responsibilities": ["payroll", "mpf", "insurance", "administration"], "requirements": {"degrees": [], "majors": [], "languages": [], "language_level": [], "hard_skills": [], "soft_skills": [], "languages_combined": []}, "experience_required": {"duration": [], "field": []}}, {"job_id": "100003009053226", "location_code": "hk", "company": "Crocodile Garments Limited", "job_title": "Assistant Human Resources & Administration Officer", "description": "Responsibilities:\n\nTo provide HR and office administration support\n\u00a0To handle the recruitment and selection process, especially for retail staff\nTo assist in payroll calculation and MPF administration\u00a0for retail staff\nTo provide office administration support such as general insurance, license renewal and office maintenance\nTo handle ad-hoc duties as assigned\nRequirements:\n\nDiploma holder or above in Human Resources Management\nMinimum 1-2 years\u2019 relevant experience, especially in retail industry is preferable\nWell-versed with Hong Kong Employment Ordinance\nGood communication and presentation skills\nImmediate available is preferable\nApplicants with less experience will be considered as Human Resources & Administration Assistant\n\n\n\nInterested parties, please apply with full resume, stating date available, present and expected salary to\u00a0Human Resources & Administration Department by clicking 'Apply Now'.\n\nPersonal Data provided in the employment applications will be treated as strictly confidential and used only for recruitment purpose.\u00a0 All unsuccessful applications will be destroyed upon completion of the selection process.", "employment_types": ["Full Time", "Permanent"], "selling_points": ["Provide HR and office administration support", "Assist in recruitment and payroll calculation", "Diploma in HRM with min.1 year exp."], "locations": ["Kwun Tong"], "categories": ["Admin & HR", "Compensation & Benefits", "HR Supporting Staff", "Training & Development"], "post_time": "2022-01-17T06:29:23Z", "salary": {"currency": null, "max": null, "min": null, "period": "monthly", "term": null}, "salary_visible": false, "title_keywords": ["human resources", "administration officer", "assistant"], "responsibilities": ["office administration support", "mpf", "maintenance", "hr", "recruitment", "insurance", "ad-hoc duties", "payroll", "administration"], "requirements": {"degrees": ["diploma holder"], "majors": [], "languages": [], "language_level": [], "hard_skills": ["hong kong employment ordinance"], "soft_skills": ["communication", "presentation skills"], "languages_combined": []}, "experience_required": {"duration": ["minimum 1-2 years"], "field": ["retail industry", "relevant experience", "human resources", "administration"]}}, {"job_id": "100003009050351", "location_code": "hk", "company": "SGS Hong Kong Limited", "job_title": "Human Resources Officer (Payroll & HRIS)", "description": "Job Responsibilities:\n\nResponsible for full spectrum of Human Resources functions with main focuses on payroll calculation, leave management & C&B employee services\nPrepare various HR reports and analysis\nProvide support in HR projects such as performance management, HRIS transformation and implementation, etc\nAssist in ad-hoc duties as assigned\n\nJob Requirements:\n\nDegree holder in Human Resources Management, Business Administration or related disciplines\n3-5+ years of relevant experience with hands-on payroll & HRIS experience in sizeable company\nWell-versed in Labour Ordinance and other HR related ordinances\nOrganized, attentive to details and figures\nStrong sense of responsibility and able to work independently\nExcellent communication skills with good command of written & spoken English and Chinese\nProficiency in using Excel (Vlookup & Pivot Table)\nGood knowledge and experience in using HRIS is a must\nImmediate available is preferred\n\nWork Location:\u00a0 Ping Shan, Yuen Long (Shuttle Bus Provided)", "employment_types": ["Full Time", "Permanent"], "selling_points": ["Immediate available preferred", "Yuen Long area (Shuttle bus provided)", "Hands-on payroll & HRIS experience"], "locations": ["Yuen Long"], "categories": ["Admin & HR", "Others", "Compensation & Benefits", "HR Supporting Staff"], "post_time": "2022-01-15T03:51:02Z", "salary": {"currency": null, "max": null, "min": null, "period": "monthly", "term": null}, "salary_visible": false, "title_keywords": ["human resources officer"], "responsibilities": ["management", "provide support", "analysis", "hr", "hr reports", "implementation", "ad-hoc duties", "payroll", "human resources functions"], "requirements": {"degrees": ["degree holder"], "majors": ["related disciplines", "business administration"], "languages": ["english", "chinese"], "language_level": ["excellent", "good command"], "hard_skills": ["excel", "vlookup", "pivot table"], "soft_skills": ["organized", "work independently", "communication skills", "attentive to details", "sense of responsibility", "hands-on"], "languages_combined": [{"language": "english", "language_level": ["excellent", "good command"]}, {"language": "chinese", "language_level": ["excellent", "good command"]}]}, "experience_required": {"duration": ["5+ years"], "field": ["payroll", "relevant experience"]}}, {"job_id": "100003009046600", "location_code": "hk", "company": "Asiaray Advertising Media Limited", "job_title": "Senior Human Resources Manager", "description": "Responsibilities:\n\n\nResponsible for all-rounded human resources functions including recruitment & selection, compensation & benefits, tax issues and HRIS management etc.\nProvide one-stop services to line departments on manpower planning, talent acquisition, HR advisory and change management\nHandle C&B duties including liaising with insurance agent on various employee compensation issues and renew group insurance plans, verifying monthly payroll, HR audit, tax filing, benefits enrolment and termination\nPlan and design the variable pay schemes, such as commission, incentive and bonus schemes for different business units\nLead the annual performance management project, analyze appraisal rating and provide insightful salary review proposal for Management\u2019s consideration\nFormulate, draft, implement and constantly update the HR policies and regulations in compliance with the Group\u2019s direction and Employment Ordinance\nImplement creative, innovative and successful solutions that align with overall business strategy, and that are consistent with or complementary to the business goals\nReview the current HRIS workflow, implement system enhancement and set key business processes to ensure the system stability\nSupport HR operations of Singapore office\u00a0\n\nRequirements:\n\n\nDegree holder or above in Human Resources Management,\u00a0Business Administration\u00a0or related disciplines\nAt least 10 years of relevant HR experience; in which 5 years in supervisory level\nRegional exposure or experience in state-owned or Chinese enterprise is preferred\nFamiliar with Employment Ordinance and other statutory and compliance requirements in Hong Kong, knowledge of laws and regulations in PRC is a plus\nExcellent interpersonal, presentation, communication and negotiations skills\nAgile, meticulous, with good analytical and numerical sense\nAble to work independently, with strong sense of ownership\nExcellent writing skills in Chinese and English, good spoken in Putonghua is an advantage\nProficiency in computer applications (MS Word, Excel, PowerPoint, etc)\nImmediate availability is highly preferred\n\nWe offer a competitive remuneration package, 5-DAY work, medical insurance, dental insurance to the right candidate. Interested parties are invited to send their applications with full resume stating availability date, present and expected salary.\n\nApplicants not invited for interview within 6 weeks may consider their applications unsuccessful. Personal data provided by job applicants will be used strictly in accordance with our personal data policy and for recruitment purposes only.", "employment_types": ["Full Time", "Permanent"], "selling_points": ["Support all-rounded human resources functions", "Support HR operations of Singapore office", "Immediate availability is highly preferred"], "locations": ["Quarry Bay"], "categories": ["Admin & HR", "Compensation & Benefits", "HR Director / Manager", "Recruitment / Executive Search"], "post_time": "2022-01-14T05:53:14Z", "salary": {"currency": null, "max": null, "min": null, "period": "monthly", "term": null}, "salary_visible": false, "title_keywords": ["manager", "human resources"], "responsibilities": [], "requirements": {"degrees": [], "majors": [], "languages": [], "language_level": [], "hard_skills": [], "soft_skills": [], "languages_combined": []}, "experience_required": {"duration": [], "field": []}}, {"job_id": "100003009051660", "location_code": "hk", "company": "Tung Wah Group of Hospitals", "job_title": "Human Resources Manager (Appointments Unit I)/ Admin. Headquarters [REF: SHRM(P)1/HRM(AI)/JOBS]", "description": "Location: Sheung Wan\n\nRoles & responsibilities:\n\nLead an appointment unit to manage the corporate human resources matters pertaining to community services in Tung Wah including manpower planning, pay review, recruitment and appointment as well as staff discipline and complaints;\ndevelop and implement human resources policies to meet the corporate objectives and service needs;\nundertake regular review of personnel administration system and procedures as well as assigned ad hoc projects/tasks to cope with changing needs;\nprovide executive support to the secretarial office of the Human Resources Committee; and\nundertake ad hoc projects and other general administrative duties including management of departmental business, supervision of staff and organization of meetings.\n\nThe ideal candidate should possess:\n\nA recognized degree or equivalent, preferably human resources management;\nat least Grade D in English Language (Syllabus B) and Chinese Language in the HKCEE or equivalent;\nat least 4 years\u2019 post-qualification administration experience, preferably human resources management/public administration;\nproficiency in English and Chinese; and\ngood communication and interpersonal skills.\n\n(Please specify in the application form the HKCEE result and relevant working experience you have attained in detail.)\n\nCompensation & employment terms:\n\nThe successful candidate will initially be offered a 3-year contract with a remuneration package which will be commensurate with his/her background and experience.\u00a0 The continuation of employment and employment terms thereafter will be subject to mutual agreement.\u00a0 Apart from contributions to the MPF Scheme, other benefits include paid annual leave, medical services, a dental scheme and training sponsorships.\u00a0 The incumbent will normally work under a 5-day week schedule subject to operational needs and exigencies of the service.\n\nApplication:\n\nPlease send your resume and a completed application form [F601(n)] with indication of your current and expected salaries to the Head of Human Resources Division, Tung Wah Group of Hospitals at 4/F., Wong Fung Ling Memorial Building, 12 Po Yan Street, Hong Kong by 20 January\u00a02022.\u00a0 Application forms are obtainable in person or can be downloaded from http://www.tungwah.org.hk.\u00a0 The reference code should be marked both in the letter and on the envelope.\u00a0\u00a0Underpaid mail items will not be accepted by Tung Wah.\u00a0 For proper delivery of your mail items, please ensure your mail items bear sufficient postage with return address before posting.\u00a0 Personal data provided by applicants will be used strictly for recruitment purpose only and in accordance with the Tung\u00a0Wah\u2019s personal data policy.\u00a0 Applicants not invited to attend an interview by 30 April 2022 may assume that their applications are unsuccessful.\n\nWE ARE AN EQUAL OPPORTUNITIES EMPLOYER", "employment_types": ["Full Time"], "selling_points": [], "locations": ["Sheung Wan"], "categories": ["Admin & HR", "Compensation & Benefits", "Recruitment / Executive Search", "Public / Civil", "Social Services - Community / Non-profit Organization"], "post_time": "2022-01-16T21:50:34Z", "salary": {"currency": null, "max": null, "min": null, "period": "monthly", "term": null}, "salary_visible": false, "title_keywords": ["admin. headquarters", "manager", "human resources"], "responsibilities": ["administration", "management", "policies", "review", "procedures", "executive support", "develop", "regular review", "communication", "recruitment", "ad hoc projects", "administrative duties", "planning"], "requirements": {"degrees": ["degree"], "majors": [], "languages": ["english", "chinese"], "language_level": ["proficiency"], "hard_skills": ["wan"], "soft_skills": ["communication and interpersonal skills", "ideal"], "languages_combined": [{"language": "english", "language_level": ["proficiency"]}, {"language": "chinese", "language_level": ["proficiency"]}]}, "experience_required": {"duration": ["at least 4 years", "3-year"], "field": ["management", "post-qualification", "relevant working experience", "human resources", "administration"]}}, {"job_id": "100003009054264", "location_code": "hk", "company": "CHOW TAI FOOK JEWELLERY CO LTD", "job_title": "Associate, Human Resources", "description": "Chow Tai Fook Jewellery Company Limited is hiring\u00a0Associate, Human Resources\n\nWhat You Do:\nReport to the Business Partner of Macau & Asia Pacific Intellectual Hub (\u201cBP\u201d)\nAssist the BP to handle payroll & incentive services, insurance, work injury cases, analytical reports, salary review & budgeting, compensation benchmarking, job evaluation and audit\nWho Will Thrive:\n2 years of compensation & benefit and payroll handling experience\nDrive quality at full throttle and never settle for less\nStrong numerical sense with a keen eye for detail\nStrong sense of urgency\nExcellent written Chinese and English and sound logic for policy drafting\nAdvanced in Microsoft Excel with analytics skills\nBenefits:\n5-day work\nCompetitive salary, staff meal,\u00a0medical and dental insurance, life insurance\nVarious types of leave, e.g. Family-friendly leave, self-development leave,\u00a0Examination leave, marriage leave, birthday\u00a0leave, volunteer service leave, etc\nWe offer excellent career opportunities, attractive remuneration package & benefits to the right candidate.\u00a0Interested parties please apply by clicking \"Apply Now\" with a full resume stating the latest and expected salary.\n\n\nAll information collected will be used for recruitment purpose only.", "employment_types": ["Full Time", "Permanent"], "selling_points": ["Payroll, Compensation & Benefits (APAC)", "HRIS system development, payroll & analysis report", "Human Resources Management, Statistics"], "locations": ["Yau Ma Tei"], "categories": ["Admin & HR", "Others", "Compensation & Benefits", "HR Supporting Staff"], "post_time": "2022-01-17T08:59:39Z", "salary": {"currency": null, "max": null, "min": null, "period": "monthly", "term": null}, "salary_visible": false, "title_keywords": ["associate", "human resources"], "responsibilities": ["budgeting", "review", "quality", "audit", "reports", "insurance", "evaluation", "payroll", "report"], "requirements": {"degrees": [], "majors": [], "languages": ["english", "chinese"], "language_level": ["excellent"], "hard_skills": ["microsoft excel"], "soft_skills": ["urgency", "keen", "advanced", "eye for detail"], "languages_combined": [{"language": "english", "language_level": ["excellent"]}, {"language": "chinese", "language_level": ["excellent"]}]}, "experience_required": {"duration": ["2 years"], "field": ["payroll"]}}, {"job_id": "100003009052955", "location_code": "hk", "company": "Grosswell Ltd", "job_title": "HR & Admin Assistant", "description": "Responsibilities:\n\nAssist in all-round human resources and office administration functions\nBack up receptionist when necessary\nPerform in any other ad hoc tasks as assigned\n\nRequirements:\n\nAssociate Degree\u00a0or above in Human Resources & Administration or\u00a0relevant disciplines\u00a0\nFluent in both spoken and written English, Mandarin and Cantonese\nProficiency in Excel, MS Word, Chinese Word Processing and HRMS\n2 years' relevant experience in\u00a0Human Resources\u00a0is preferable\nFresh graduate will also be considered\nImmediate available is highly preferred\u00a0\nInterested parties, please send email to obtain an application form.", "employment_types": ["Full Time", "Part Time"], "selling_points": [], "locations": ["Yau Tsim Mong Area"], "categories": ["Admin & HR", "Clerical / Admin Staff", "Compensation & Benefits", "HR Supporting Staff"], "post_time": "2022-01-17T04:41:23Z", "salary": {"currency": null, "max": null, "min": null, "period": "monthly", "term": null}, "salary_visible": false, "title_keywords": ["hr & admin assistant"], "responsibilities": ["office administration", "ad hoc tasks"], "requirements": {"degrees": ["degree or above", "fresh graduate"], "majors": [], "languages": ["cantonese", "english", "chinese", "mandarin"], "language_level": ["proficiency", "fluent"], "hard_skills": ["excel", "chinese word processing", "ms word"], "soft_skills": [], "languages_combined": [{"language": "cantonese", "language_level": ["fluent"]}, {"language": "english", "language_level": ["fluent"]}, {"language": "chinese", "language_level": ["proficiency"]}, {"language": "mandarin", "language_level": ["fluent"]}]}, "experience_required": {"duration": ["2 years"], "field": ["relevant experience", "human resources"]}}, {"job_id": "100003009054246", "location_code": "hk", "company": "CHOW TAI FOOK JEWELLERY CO LTD", "job_title": "Officer / Senior Offier, Performance Management", "description": "What You Will Own\nReview current internal performance management workflow to improve work efficiency\nAssist in developing and implementing performance management strategies, policies and guidelines with key stakeholders\nPerform the analysis and statistic on staff performance, propose and integrate with reward programs to attract and retain talent\nPrepare the presentation materials for manager review\nConduct regular review to meet the market practice and company business strategy\nPerform other ad-hoc projects and tasks as assigned\nWho Will Thrive\nDegree in Human Resources / Business related disciplines with minimum of 2 years' experience in performance management, preferably gained from retail or luxury good industry\nStrong analytical, excel and powerpoint skills\nAbility to work independently under pressure\nSelf-motivated with good communication & interpersonal skills\nGood command of written and spoken English and Chinese as well as Putonghua\nMore experience will be considered as Senior Officer\nBenefits\n\n5-day work\nCompetitive salary, staff meal, medical and dental insurance, life insurance\nVarious types of leave, e.g. Family-friendly leave, self-development Leave, examination leave, marriage leave, birthday leave, volunteer service leave, etc\nWe offer excellent career opportunities, attractive remuneration package & benefits to the right candidate.\u00a0Interested parties please apply by clicking \"Apply Now\" with a full resume stating the latest and expected salary.\nAll information collected will be used for recruitment purposes only.", "employment_types": ["Full Time"], "selling_points": ["5-day work", "Performance management", "Perform the analysis and conduct regular review"], "locations": ["Yau Ma Tei"], "categories": ["Admin & HR", "Others", "Compensation & Benefits"], "post_time": "2022-01-17T08:56:23Z", "salary": {"currency": null, "max": null, "min": null, "period": "monthly", "term": null}, "salary_visible": false, "title_keywords": ["officer"], "responsibilities": ["management", "guidelines", "policies", "analysis", "review", "developing", "regular review", "communication", "ad-hoc projects"], "requirements": {"degrees": ["degree"], "majors": ["related disciplines", "business"], "languages": ["putonghua", "english", "chinese"], "language_level": ["good command"], "hard_skills": ["excel", "analysis", "powerpoint"], "soft_skills": ["work independently", "self-motivated", "under pressure", "communication", "interpersonal skills", "presentation"], "languages_combined": [{"language": "putonghua", "language_level": ["good command"]}, {"language": "english", "language_level": ["good command"]}, {"language": "chinese", "language_level": ["good command"]}]}, "experience_required": {"duration": ["minimum of 2 years"], "field": ["performance management", "related", "business", "retail", "human resources"]}}, {"job_id": "100003009053275", "location_code": "hk", "company": "BDO", "job_title": "Senior Associate / Associate - Payroll & HR Outsourcing", "description": "Responsibilities:\n\nPerform and manage payroll calculation for clients\nCompile monthly payroll & MPF reports and employer\u2019s tax compliance\n\nRequirements:\n\nDegree holder,\u00a0preferably major in accounting, human resources management, business studies or equivalent\n1 year of relevant experience in\u00a0payroll outsourcing\u00a0\nKnowledge and experience in Hong Kong payroll, HK Employment Ordinance, MPF and relevant taxation legislations\nAction-orientated, detail minded and organized\nApplicants with more experience will be considered as Senior Associate\n\nWe are an equal opportunity employer, and offer excellent prospects and career development for the right candidate.\u00a0 Interested parties please send your application\u00a0with full career history, current and expected salary by\u00a0clicking\u00a0Apply Now\u00a0button below.\n\nApplications will be treated in strict confidence. Personal data collected will be used for recruitment purposes only.", "employment_types": ["Full Time", "Permanent"], "selling_points": ["Provide payroll outsourcing services to clients", "1 year of experience in payroll outsourcing", "Degree in Accounting, HR or business studies"], "locations": ["Sheung Wan"], "categories": ["Accounting", "Others", "Admin & HR", "Compensation & Benefits"], "post_time": "2022-01-17T06:38:31Z", "salary": {"currency": null, "max": null, "min": null, "period": "monthly", "term": null}, "salary_visible": false, "title_keywords": ["hr", "senior associate", "associate"], "responsibilities": ["tax", "mpf", "compliance", "reports", "payroll"], "requirements": {"degrees": ["degree holder"], "majors": ["business", "accounting"], "languages": [], "language_level": [], "hard_skills": [], "soft_skills": ["organized"], "languages_combined": []}, "experience_required": {"duration": ["1 year"], "field": ["payroll", "relevant experience", "mpf"]}}, {"job_id": "100003009054321", "location_code": "hk", "company": "EVISU Group Limited", "job_title": "Human Resources & Admin Officer", "description": "Responsibilities:\n\nResponsible for all-rounded human resources functions but not limited to compensation &\u00a0 benefits, leave management, coordination of staff activities and daily operations\nParticipate in recruitment process for frontline positions, including job advertisement posting, identifying effective recruitment channels, interview arrangement and onboarding process.\nHandle monthly payroll processing and taxation arrangement\nAssist in formulating and implementing HR policies and procedures to ensure that they are aligned with local legislation requirements & business goals.\nPrepare relevant employment documents and maintain updated personnel information in system.\nPrepare HR regular and analysis reports for management\nOversee daily administration activities such as office suppliers, equipment maintenance, facilities management etc.\nPerform ad-hoc projects as assigned\u00a0\n\nRequirements:\n\nBachelor Degree in Business Administration, Human Resources Management or related disciplines\nMinimum 3 years\u2019 relevant experience in HR & Admin field, preferably retail industry\nSolid experience in processing payroll\nWell versed in HK Employment Ordinance, knowledge of the Labour Law of APAC countries is an advantage\nWilling to learn, able to work independently under tight deadlines\nDetail-minded, Proactive, well organized with strong sense of accuracy & responsibility\nExcellent communication skills\nGood command of spoken and written English and Chinese\nProficiency in PC operations including MS Word, Excel, Power Point\nImmediate availability is preferred\nLess experience will be considered as Asst. HR & Admin Officer", "employment_types": ["Full Time", "Permanent"], "selling_points": ["medical insurance, double pay, performance bonus", "Stable career development", "5 days work"], "locations": ["Kwun Tong"], "categories": ["Admin & HR", "Clerical / Admin Staff", "Compensation & Benefits", "HR Supporting Staff"], "post_time": "2022-01-17T09:09:17Z", "salary": {"currency": null, "max": null, "min": null, "period": "monthly", "term": null}, "salary_visible": false, "title_keywords": ["officer", "admin", "human resources"], "responsibilities": ["business goals", "analysis reports", "maintain", "ad-hoc projects", "administration", "interview arrangement", "management", "job advertisement", "procedures", "daily operations", "recruitment process", "payroll", "taxation", "maintenance", "policies", "hr", "recruitment", "coordination", "human resources functions"], "requirements": {"degrees": ["degree", "bachelor"], "majors": ["related disciplines", "business administration"], "languages": ["english", "chinese"], "language_level": ["good command"], "hard_skills": ["excel", "pc operations", "power point", "processing", "ms word"], "soft_skills": ["detail-minded", "communication skills", "work independently", "willing to learn", "well organized", "proactive"], "languages_combined": [{"language": "english", "language_level": ["good command"]}, {"language": "chinese", "language_level": ["good command"]}]}, "experience_required": {"duration": ["minimum 3 years"], "field": ["retail industry", "hr", "admin", "relevant experience", "payroll"]}}, {"job_id": "100003009050305", "location_code": "hk", "company": "Asia Beauty Concepts Limited", "job_title": "Human Resources Officer", "description": "Job Responsibilities\n\nAssist in handling compensation & benefits functions including payroll, tax returns, final payment, internal transfer, MPF, group insurances related issues.\nMaintain and update personnel details in HR system, time attendance system and filing system\nHandle general enquires related to HR Policies and procedures to ensure alignment with operation needs and in compliance with Employment Ordinance\nGenerate and prepare related HR reports for the management reviews\nProvide administrative and clerical support to HR Team to ensure smooth operation\nPerform ad-hoc duties assigned by HR Manager\n\nRequirements\n\nDegree in Human Resources Management or related disciplines\nAt least 1-2 years solid experience in HR (C&B Focus), preferably in\u00a0beauty, retail industry\nWell versed in Hong Kong Employment Ordinance and other HR related ordinances\nAttentive to details, sensitive in number, independent and good team-player\nGood interpersonal and communication skills\nProficient in MS Word, Excel, PowerPoint and Chinese Word Processing\nImmediate available is preferred\n\nInterested parties please send your application letter, resume, expected salary and availability to the \"Apply Now\" button.\n\n\u00a0* Data collected will be used for recruitment purpose only. It may be transferred to other companies of the Group to see if suitable vacancies arise. Applicants not contacted within 6 weeks may consider their application unsuccessful. The information will be destroyed.", "employment_types": ["Full Time", "Permanent"], "selling_points": ["Payroll, C&B, Personnel Admin", "5 days work week, Free Goods, Birthday Leave", "Retail / Beauty industry"], "locations": ["Causeway Bay"], "categories": ["Admin & HR", "Clerical / Admin Staff", "Compensation & Benefits", "HR Supporting Staff"], "post_time": "2022-01-14T10:05:25Z", "salary": {"currency": null, "max": null, "min": null, "period": "monthly", "term": null}, "salary_visible": false, "title_keywords": ["human resources officer"], "responsibilities": ["tax", "attendance", "management", "mpf", "policies", "hr", "compliance", "procedures", "hr reports", "payment", "maintain", "administrative and clerical support", "ad-hoc duties", "insurances", "payroll"], "requirements": {"degrees": ["degree"], "majors": ["related disciplines"], "languages": ["chinese"], "language_level": ["proficient"], "hard_skills": ["excel", "hong kong employment ordinance", "chinese word processing", "powerpoint", "focus", "ms word"], "soft_skills": ["communication skills", "independent", "attentive to details", "team-player", "sensitive", "focus", "interpersonal"], "languages_combined": [{"language": "chinese", "language_level": ["proficient"]}]}, "experience_required": {"duration": ["at least 1-2 years"], "field": ["retail industry", "hr", "beauty"]}}, {"job_id": "100003009049927", "location_code": "hk", "company": "Nanyang Commercial Bank", "job_title": "Assistant Human Resources Manager (Ref: II8002-RP-JDB)", "description": "Perform HR and business data analysis. Prepare HR analytical and strategic planning report. Implementation of competitive reward and benefit practices and strategies. Accountable for various HR projects including annual bonus and salary review, staff promotion, and reward programs, performance management projects and manpower budget plan. Participate in market salary and benefit survey. Prepare material and data for management reports and meetings and\u00a0support in review of HR policies and procedures to ensure the Bank is consistently complied with related regulatory requirements.\n\nRequirements:\n\nDegree holder in Human Resources Management or Business related disciplines with at least 2 years relevant experience, preferable in banking/ financial institution;\n\nStrong analytical and organization skills with strategic mindset;\nProactive team player with excellent leadership and communication skills;\nAble to handle multiple projects with tight deadlines;\nFamiliar with statutory and compliance requirements including Employment Ordinance and other relevant laws and regulations for Hong Kong and PRC;\nConversant with Chinese word processing and MS Office Suite especially in Excel and Access;\nProficient in both spoken and written English and Chinese, fluent in Putonghua is preferable.\n\nIf you are flexible enough and zeal for a harmonious and supportive working environment where enables you to grow and succeed professionally, please send a full resume indicating your public examination results (HKCEE and HKALE / HKDSE), your present and expected salary and quoting reference number attention to\u00a0Talent Acquisition Division, Nanyang Commercial Bank, 151 Des Voeux Road Central, Hong Kong or apply through email. For details, please visit https://www.ncb.com.hk/ and select the page Recruit.\n\nWe are an Equal Opportunities Employer. Data collected would be used for recruitment purposes only. Applicants who do not hear from us within 8 weeks may consider their applications unsuccessful and their data will be destroyed within 12 months of receipt.", "employment_types": ["Full Time", "Permanent"], "selling_points": ["Perform HR and business data analysis", "Accountable for various HR projects", "Degree holder in Human Resources Management"], "locations": ["Central"], "categories": ["Admin & HR", "Compensation & Benefits", "HR Director / Manager"], "post_time": "2022-01-15T03:50:42Z", "salary": {"currency": null, "max": null, "min": null, "period": "monthly", "term": null}, "salary_visible": false, "title_keywords": ["assistant human resources manager"], "responsibilities": ["regulations", "data", "regulatory requirements", "budget", "communication", "plan", "compliance", "implementation", "banking", "report", "management", "strategic planning", "review", "procedures", "data analysis", "policies", "hr", "management reports", "recruitment", "multiple projects"], "requirements": {"degrees": ["hkdse", "degree holder"], "majors": ["related disciplines", "business"], "languages": ["putonghua", "english", "chinese"], "language_level": ["fluent", "proficient"], "hard_skills": ["excel", "chinese word processing", "analysis", "management reports", "ms office"], "soft_skills": ["flexible", "communication skills", "supportive", "harmonious", "accountable", "organization skills", "team player", "proactive", "leadership"], "languages_combined": [{"language": "putonghua", "language_level": ["fluent", "proficient"]}, {"language": "english", "language_level": ["fluent", "proficient"]}, {"language": "chinese", "language_level": ["fluent", "proficient"]}]}, "experience_required": {"duration": ["at least 2 years"], "field": ["management", "related", "business", "relevant experience", "banking", "human resources", "financial"]}}, {"job_id": "100003009051657", "location_code": "hk", "company": "Tung Wah Group of Hospitals", "job_title": "Human Resources Assistant II (REF: A3/HRAII/STWS/JOBS)", "description": "Location: Sheung Wan\nRoles & responsibilities:\n\nHandle various administrative work arising from the development of staff training and welfare related information systems/e-platforms/mobile apps by researching, collecting user requirement/feedback, undertaking User Acceptance Testing and preparing relevant documents for launching of new information technology (IT) initiatives;\nprovide administrative and logistic support in organizing internal training programmes;\nperform duties related to various internal and external electronic platforms, and IT related policies;\nprocess various applications for staff welfare benefits, such as medical/dental treatment, staff welfare grants, retired staff welfare benefits and provide administrative support in staff schemes/awards by managing mass data consolidation, souvenir production and distribution;\nperform document management duties and handle telephone enquiries; and\nprovide support in organizing staff relations and welfare event as assigned.\nThe ideal candidate should possess:\n(a)\u00a05 passes in HKCEE including Chinese Language, English Language (Syl. B) and Mathematics or equivalent plus at least 2 years of relevant experience; or\n(b)\u00a0completion of F.5 plus at least 3 years of relevant experience;\nstrong computer knowledge including Chinese and English word-processing, MS Word, MS PowerPoint, MS Excel, Photoshop/PhotoImpact; and\nproficiency in written Chinese and English.\n\n(Please specify in the resume or application form the\u00a0relevant academic results/qualifications and working experience you have attained in detail.)\nCompensation & employment terms:\nThe successful candidate will initially be offered a 2-year contract with a remuneration package which will be commensurate with his/her background and experience. The continuation of employment and employment terms thereafter will be subject to mutual agreement. Apart from contributions to the MPF Scheme, other benefits include paid annual leave, medical services, a dental scheme and training sponsorships. The incumbent will normally work under a 5-day week schedule subject to operational needs and exigencies of the service.\nApplication:\nPlease send your resume or a completed application form [F601(n)] with indication of your current and expected salaries to the Head of Human Resources Division, Tung Wah Group of Hospitals at 4/F., Wong Fung Ling Memorial Building, 12 Po Yan Street, Hong Kong by 18 January 2022.\u00a0 Application forms are obtainable in person or can be downloaded from http://www.tungwah.org.hk.\u00a0\u00a0The reference code should be marked both in the letter and on the envelope.\u00a0\u00a0Underpaid mail items will not be accepted by Tung Wah.\u00a0 For proper delivery of your mail items, please ensure your mail items bear sufficient postage with return address before posting.\u00a0\u00a0Personal data provided by applicants will be used strictly for recruitment purpose only and in accordance with the Tung Wah\u2019s personal data policy. \u00a0Applicants not invited to attend an interview by 30 April 2022\u00a0may assume that their applications are unsuccessful.\nWE ARE AN EQUAL OPPORTUNITIES EMPLOYER", "employment_types": ["Full Time", "Contract"], "selling_points": [], "locations": ["Sheung Wan"], "categories": ["Admin & HR", "Clerical / Admin Staff", "Others", "Compensation & Benefits"], "post_time": "2022-01-16T21:50:32Z", "salary": {"currency": null, "max": null, "min": null, "period": "monthly", "term": null}, "salary_visible": false, "title_keywords": ["human resources assistant"], "responsibilities": ["user requirement", "management", "provide support", "administrative work", "data", "policies", "systems", "logistic support", "testing", "provide administrative support"], "requirements": {"degrees": [], "majors": [], "languages": ["english", "chinese"], "language_level": ["proficiency"], "hard_skills": ["plus", "processing", "word", "mobile", "ms excel", "photoshop", "ms powerpoint", "wan", "ms word"], "soft_skills": ["perform duties", "ideal"], "languages_combined": [{"language": "english", "language_level": ["proficiency"]}, {"language": "chinese", "language_level": ["proficiency"]}]}, "experience_required": {"duration": ["at least 2 years", "at least 3 years", "2-year"], "field": ["relevant experience"]}}, {"job_id": "100003009037664", "location_code": "hk", "company": "Wai Yuen Tong Medicine Co Ltd", "job_title": "Senior HR Officer (Recruitment)", "description": "Job Role\n\n\nManage the full spectrum of Human Resources functions including but not limited to recruitment, C&B, team member movement, employee relations according to our corporate guideline\u00a0and operations objectives.\nExecute recruitment and selection process starting from job posting to staff appointment. Work closely with department heads on the manpower and hiring plan.\nOversee and manage people strategies, including talent development, employee communications, manpower planning, performance management and other HR projects\nPlan and execute HR initiatives on employee engagement\nConduct regular review on HR practice and procedure to ensure they are compliance with local legislation\nWorking as a strategic business partner to the line management.\u00a0\n\nRequirements:\n\nUniversity graduate in Human Resources Management, Business Administration or relevant discipline\nMinimum 6 years of relevant work experience in sizeable companies; with exposure in pharmaceutical manufacturer is definitely an advantage\nWell versed in Hong Kong Labor Ordinance and related regulations\nMature, flexible and able to work under pressure\nAble to work independently and meet tight deadlines\nGood command in both spoken and written English and Chinese\nCandidate with more experience will be considered as Assistant HR Manager\nWork location: Yuen Long\n\nInterested parties please send\u00a0full resume\u00a0with present and expected salary\u00a0to Human Resources Department by clicking\u00a0\"APPLY NOW\".\n\n\u00a0(All personal data provided by applicants will be treated in strict confidence and used for employment-related purpose only.)", "employment_types": ["Full Time", "Permanent"], "selling_points": ["Recruitment focus", "Mature, independent & proactive", "Strong sense of responsibility & detail-minded"], "locations": ["Yuen Long"], "categories": ["Admin & HR", "Compensation & Benefits", "HR Supporting Staff", "Recruitment / Executive Search"], "post_time": "2022-01-15T03:49:12Z", "salary": {"currency": null, "max": null, "min": null, "period": "monthly", "term": null}, "salary_visible": false, "title_keywords": ["hr officer"], "responsibilities": ["administration", "regulations", "management", "work under pressure", "operations", "hr", "compliance", "regular review", "recruitment", "plan", "human resources functions", "planning"], "requirements": {"degrees": ["university graduate"], "majors": ["business administration"], "languages": ["english", "chinese"], "language_level": ["good command"], "hard_skills": [], "soft_skills": ["flexible", "work independently", "meet tight deadlines", "mature", "team member", "work under pressure"], "languages_combined": [{"language": "english", "language_level": ["good command"]}, {"language": "chinese", "language_level": ["good command"]}]}, "experience_required": {"duration": ["minimum 6 years"], "field": ["hr"]}}, {"job_id": "100003009049313", "location_code": "hk", "company": "China Merchants Securities International Company Limited", "job_title": "Vice President, Compensation & Benefits", "description": "Job Responsibilities\uff1a\n\nManage full spectrum of C&B functions including\u00a0monthly payroll, MPF, overtime allowances, annual tax returns, leave administration, benefits administration, employee termination, final payment reports and other C&B related matters\nProvide strategic advice and assist department head to drive and implement C&B cycles - \u00a0reviewing and enhancing the incentive/bonus scheme, performing the annual salary review, promotion, salary survey, grading structure review, headcount planning and budgeting, etc\nAssist to formulate, review and implement C&B related policies and strategies from time to time\nCompile HR reports on a regular basis for management review\nWork closely with Mainland Headquarter and involve in relevant projects\nPerform ad-hoc projects as assigned\n\nJob Requirements:\n\nDegree holder in Human Resources, Business Administration, or equivalent disciplines\n8-12 years of C&B experience gained from reputable financial institutions with sound experience on working with Mainland headquarter\nFamiliar with labour ordinances or other relevant ordinance and regulatory requirements\nDetailed minded, with good communication and analytical skills\nEnjoy teamwork, responsible and proactive, with pleasant personality\nAble to complete tasks within required time frame and respond effectively under pressure\nExcellent communication in both written and spoken Chinese (Mandarin a MUST) and English\n\nWe offer attractive remuneration and benefits including 5-day working week to the right candidates. Interested parties, please send your full resume including your\u00a0CURRENT\u00a0and\u00a0EXPECTED\u00a0salary to us by email.\u00a0\n\nPersonal data provided will be used by us for recruitment and related purposes, which is strictly in accordance with the Personal Data (Privacy) Ordinance (Cap. 486 of the Laws of Hong Kong) for Applicants for Employment. Applicants who are not contacted within 6 weeks may consider your applications unsuccessful and the personal data collected will be destroyed after 2 years or such other period as prescribed by the applicable laws.\n\n\u6709\u610f\u7533\u8acb\u8005\u8acb \u6309 APPLY NOW\u7533\u8acb\n\n", "employment_types": ["Full Time"], "selling_points": [], "locations": ["Kwun Tong"], "categories": ["Banking / Finance", "Corporate Banking", "Admin & HR", "Compensation & Benefits", "Management", "Top Executives (CEO, CFO, CTO, GM, MD etc.)"], "post_time": "2022-01-14T08:27:35Z", "salary": {"currency": null, "max": null, "min": null, "period": "monthly", "term": null}, "salary_visible": false, "title_keywords": ["vice president"], "responsibilities": ["tax", "mpf", "budgeting", "policies", "review", "hr reports", "payment", "planning", "reports", "ad-hoc projects", "payroll", "management review", "administration"], "requirements": {"degrees": ["degree holder"], "majors": ["business administration"], "languages": ["english", "chinese", "mandarin"], "language_level": ["excellent"], "hard_skills": ["analytical skills"], "soft_skills": ["under pressure", "responsible", "teamwork", "analytical skills", "communication", "pleasant", "proactive", "detailed"], "languages_combined": [{"language": "english", "language_level": ["excellent"]}, {"language": "chinese", "language_level": ["excellent"]}, {"language": "mandarin", "language_level": ["excellent"]}]}, "experience_required": {"duration": ["8-12 years"], "field": ["financial institutions"]}}, {"job_id": "100003009051025", "location_code": "hk", "company": "The Wharf Group", "job_title": "Human Resources Officer", "description": "Key Roles:\nas a member of the internal support team of the group\u2019s SAP SuccessFactors HRIS project to provide support to four HR teams and a Central Payroll team for new roll out and existing modules enhancement/maintenance\nparticipate in various tasks including but not limited to data preparation, UAT, liaison with consultants, user training and other related administrative support for HR related projects\nAnalyse HR data, headcount, payroll cost for budget and cost control and prepare reports for management's planning and control\nassist in\u00a0any\u00a0ad-hoc projects in benefits and compensation when assigned\nRequirements:\nDegree holders in Computing/Information Technology/HRM or relevant disciplines with at least 5 years' solid HR working experience of which at least 2 to 3 years in HRIS support. \u00a0Exposure in SAP SuccessFactors HRIS is preferred\nAnalytical, strong numeric sense with an advanced user of Microsoft Excel\nResponsible, organized and hardworking team player with good common sense and integrity\nable to present and communicate/present clearly and precisely\nfamiliarize with HR practices and labour ordinance\nproficient in both spoken and written English and Chinese\u00a0\nWe work 5 days per week.\n\n\nInterested parties, please click \"APPLY NOW\" and attach with your application letter and full resume.\n\nFor further information of the Wharf Group, please visit our website: www.wharfholdings.com\u00a0", "employment_types": ["Full Time", "Permanent"], "selling_points": [], "locations": ["Tsim Sha Tsui"], "categories": ["Admin & HR", "Compensation & Benefits", "HR Supporting Staff", "Information Technology (IT)", "Others"], "post_time": "2022-01-15T01:17:12Z", "salary": {"currency": null, "max": null, "min": null, "period": null, "term": null}, "salary_visible": false, "title_keywords": ["human resources officer"], "responsibilities": ["provide support", "cost", "management", "uat", "maintenance", "data", "administrative support", "control", "hr", "budget", "teams", "planning", "cost control", "prepare reports", "payroll", "analyse"], "requirements": {"degrees": [], "majors": [], "languages": [], "language_level": [], "hard_skills": ["maintenance", "sap"], "soft_skills": [], "languages_combined": []}, "experience_required": {"duration": [], "field": []}}, {"job_id": "100003009050949", "location_code": "hk", "company": "S.F. Express (Hong Kong) Limited", "job_title": "Human Resources Officer (C&B)", "description": "Responsibilities\n\nPerform C&B functions such as payroll, attendance & leave record maintenance, MPF and benefits administration\nAssist in negotiation with insurance company regarding work injury issues\nPreparing various analysis reports, handling employee attendance and leave management\nProvide support in HR Systems and payroll system, ensure HR systems run smoothly and updated for data maintenance\nProvide administrative and clerical support to the team\nPerform ad-hoc tasks as assigned\n\nJob Requirements\n\n\nDegree holder or above in Human Resources Management or related discipline\n3 to 5 years\u2019 working experience with hands-on C&B logistics arrangement experience in sizable organization\nWell versed in the HK Employment Ordinance and HR related legislation\nKnowledge of SAP is an advantage\nProficient in computer skills including PowerPoint, strong in Excel and Chinese Word Processing\nMeticulous, proactive, able to work under pressure with multi-tasking ability and crop with fast pace working environment\nGood command of spoken / written English, Mandarin and Cantonese\nImmediate available is highly preferred\nCandidates with less experience will be considered as\u00a0HR Assistant Officer\nWe offer attractive remuneration package and fringe benefits to the suitable candidates. Interested parties, please submit your application to us. If you do not want to apply as a JobsDB member, you may send your full resume with your availability, current and expected salaries to recruit01 at sf-express.com\nYou are welcome to visit our website at\u00a0https://htm.sf-express.com/hk/tc/\u00a0for more information about us.\n\nCandidates who are not invited for an interview within 1-month may consider their applications unsuccessful.\nAll personal data provided by job applicants will be used only for recruitment purposes and will be treated strictly confidential. Unsuccessful applications will be retained for a maximum period of 24-month.", "employment_types": ["Full Time", "Permanent"], "selling_points": ["Free shuttle bus coverage", "2 months or above performance bonus", "Attractive basic salary"], "locations": ["Tsing Yi"], "categories": ["Admin & HR", "Compensation & Benefits", "HR Supporting Staff"], "post_time": "2022-01-14T11:55:53Z", "salary": {"currency": null, "max": null, "min": null, "period": "monthly", "term": null}, "salary_visible": false, "title_keywords": ["human resources officer"], "responsibilities": [], "requirements": {"degrees": [], "majors": [], "languages": [], "language_level": [], "hard_skills": [], "soft_skills": [], "languages_combined": []}, "experience_required": {"duration": [], "field": []}}, {"job_id": "100003009047958", "location_code": "hk", "company": "Sime Darby Motor Services Limited", "job_title": "Officer - Human Resources (Compensation & Benefits) (Ref: JDB/SDMSL/CBHRO/20220114)", "description": "Key Responsibilities:\n\nHandle the daily tasks of Compensation & Benefits full spectrum\u00a0function, including but not limited to payroll, benefits and insurance administration, HR system and personnel data management, salary benchmarking, taxation for our Hong Kong and Macau Operations\n\nCompile\u00a0regular HR management reports such as headcount and staff cost reports, salary and commission analysis, etc.\n\nAssist in\u00a0any ad hoc Compensation & Benefits exercises as assigned\nParticipate other HR operational tasks, such as staff activities, on/off boarding arrangements, leave management, etc.\nBe one of the representatives to participate in varies company committees when assigned and organize and staff activities\n\nJob\u00a0Requirements:\n\nBachelor or above Degree holder in Human Recourses Management or related disciplines\n3 years of experience in Compensation & Benefits from sizable company\nWell versed in Hong Kong Employment Ordinance, knowledge of Macau Labor Law will be an advantage\nProficient in MS Office applications, experience in HRIS or SAP is a plus\nGood command of spoken and written Chinese and English\nAttentive to details, strong numeric sense, well organized and good team player with strong sense of responsibility\nWorking location: Tsuen Wan (7-10 minutes walk from MTR station)\n\nWe offer attractive remuneration package, 5-day work week, competitive fringe benefits and excellent career development opportunity to the right candidate. Interested parties please send your full resume quoting job reference number with present salary, expected salary and available date via e-mail to\u00a0ghr-recruitment.sdms @simedarby.com.hk\u00a0\n\n\nFor more information about us, please visit our\u00a0Website.\nFollow us on\u00a0our\u00a0LinkedIn\u00a0and stay tuned!\n\n\nAll information provided by applicants will be treated in strict confidence and used for recruitment purpose only.", "employment_types": ["Full Time", "Permanent"], "selling_points": ["3 years in Compensation & Benefits", "Degree in HRM / Related Disciplines", "Good Exposure in Automotive Sizable Company"], "locations": ["Tsuen Wan Area"], "categories": ["Admin & HR", "Compensation & Benefits", "HR Supporting Staff"], "post_time": "2022-01-14T04:26:49Z", "salary": {"currency": null, "max": null, "min": null, "period": "monthly", "term": null}, "salary_visible": false, "title_keywords": ["officer", "human resources"], "responsibilities": ["taxation", "management", "cost", "data", "operations", "hr", "analysis", "management reports", "reports", "insurance", "payroll", "administration"], "requirements": {"degrees": [], "majors": [], "languages": [], "language_level": [], "hard_skills": [], "soft_skills": [], "languages_combined": []}, "experience_required": {"duration": [], "field": []}}, {"job_id": "100003009053170", "location_code": "hk", "company": "Be Myjob Company Limited", "job_title": "Manager, Human Resources ( Financial Industry )", "description": "Responsibilities :\n\nProvide end-to-end recruitment and staff retention planning\nTo Perform all rounded HR Generalist duties\nTo liaise with department heads for identifying the hiring needs, job descriptions, selection criteria, etc.\nTo design innovative sourcing strategies and solutions to meet business growth needs and generate diverse pools of candidates\nTo develop and review recruitment policies and procedures to ensure compliance and HR effectiveness in line with corporate objective and goals\nAny other ad-hoc projects assigned (e.g.\u00a0To establish and regularly update HR manuals and related policies and procedures )\nRequirements :\u00a0\n\nDegree holder in HR Management or Other Business Related Disciplines\nMinimum 1-3 years or above human resources working experience\nEffective communication and interpersonal skills, high level of accuracy and detail oriented are required\nFluent or native speaker of Mandarin, fluent in English and Cantonese\nExcellent Chinese writing skills is a must.\nImmediately available is highly preferred", "employment_types": ["Full Time", "Permanent"], "selling_points": ["Talent Acquisition", "Brokerage Firm", "Work Life Balance"], "locations": ["Tsim Sha Tsui"], "categories": ["Admin & HR", "Others", "Compensation & Benefits", "HR Director / Manager"], "post_time": "2022-01-17T06:14:31Z", "salary": {"currency": null, "max": null, "min": null, "period": "monthly", "term": null}, "salary_visible": false, "title_keywords": ["manager", "human resources"], "responsibilities": ["policies", "hr", "review", "procedures", "design", "develop", "ensure compliance", "recruitment", "liaise with", "ad-hoc projects", "planning"], "requirements": {"degrees": ["degree holder"], "majors": ["related disciplines", "business"], "languages": ["cantonese", "english", "chinese", "mandarin"], "language_level": ["native", "excellent", "fluent"], "hard_skills": ["writing skills"], "soft_skills": ["detail oriented", "communication and interpersonal skills", "writing skills"], "languages_combined": [{"language": "cantonese", "language_level": ["native", "fluent"]}, {"language": "english", "language_level": ["native", "fluent"]}, {"language": "chinese", "language_level": ["excellent"]}, {"language": "mandarin", "language_level": ["native", "fluent"]}]}, "experience_required": {"duration": ["minimum 1-3 years"], "field": ["human resources"]}}, {"job_id": "100003009046696", "location_code": "hk", "company": "Asia Airfreight Terminal Co Ltd", "job_title": "Human Resources Officer - Fresh graduates are welcome", "description": "Duties\n\n\nProvide support to HR department for full spectrum of HR functions, including\u00a0 recruitment, performance management, staff relations, uniform management, and other personnel related issues\nAssist to prepare recruitment advertisement, screen applications, conduct interviews and make employment offer\nPrepare reports, maintain staff\u00a0 record in HR system and personal file keeping\nProvide support to ad-hoc assignment when necessary\n\nRequirements\n\n\nDegree holder or Diploma holder with minimum 1 year relevant experience; preferred in HR or qualification equivalent to the standards of Level 3 or above in HKQF in related field\nProficiency in \u00a0MS Office and Chinese word processing\nSelf-motivated and able to meet tight deadline\nA team player,\u00a0helpful and approachable\u00a0\nStrong communication and interpersonal skills\nCandidates with less working experience will be considered as a less senior position\n\nWe offer the right incumbent attractive remuneration package including 12 days annual leave, 5-day week, double pay, discretionary bonus, medical scheme, life insurance, travel allowance and education subsidy.\n\nInterested parties please send your full resume with reference no., recent and expected salary to:\u00a0Human Resources Department, Asia Airfreight Terminal Co. Ltd., 10 Chun Ping Road, Hong Kong International Airport, Lantau, Hong Kong\u00a0OR Fax to\u00a02286 0374\u00a0OR\u00a0Please click \u201cApply Now\u201d to submit your application.\n\nTo know more about AAT, please visit\u00a0http://www.aat.com.hk\n\nWe are an equal opportunity employer and welcome applications from all qualified candidates. We will not be responsible for any disclosure or the loss of personal data during transmission. All personal data collected will be used for recruitment only. Information of unsuccessful candidates will be destroyed after 3 months from the date of application.", "employment_types": ["Full Time", "Permanent"], "selling_points": ["12 days annual leave, 5-day week, double pay", "Provide support for full spectrum of HR functions", "Self-motivated, a team player, helpful"], "locations": ["Airport Area"], "categories": ["Admin & HR", "Others", "Compensation & Benefits", "HR Supporting Staff"], "post_time": "2022-01-13T18:54:25Z", "salary": {"currency": null, "max": null, "min": null, "period": "monthly", "term": null}, "salary_visible": false, "title_keywords": ["human resources officer"], "responsibilities": ["ad-hoc", "provide support", "management", "hr", "maintain", "recruitment", "prepare reports"], "requirements": {"degrees": ["diploma holder", "degree holder"], "majors": [], "languages": ["chinese"], "language_level": ["proficiency"], "hard_skills": ["chinese word processing", "scheme", "ms office"], "soft_skills": ["self-motivated", "approachable", "communication and interpersonal skills", "meet tight deadline", "team player"], "languages_combined": [{"language": "chinese", "language_level": ["proficiency"]}]}, "experience_required": {"duration": ["minimum 1 year"], "field": ["relevant experience"]}}, {"job_id": "100003009054070", "location_code": "hk", "company": "KeeReal Consulting Limited", "job_title": "HR and Administration Officer - MNC", "description": "Our client is a well-established MNC bank and recently seeking a flexible candidate for the HR and Admin Officer position to join their newly expanded branch.\u00a0\n\nResponsibilities:\u00a0\n\n\nPerform all-rounded HR support and services for company\u2019s operation\nDrive annual compensation process including salary review, budgeting, incentive schemes to facilitate recruitment and retention program;\nMaintain Staff Record including personal file, leave record and personal data updating\nDirectly report to top management level and provide full spectrum of Human Resources and Administration tasks including but not limited to recruitment & selection, C&B, and training & development\nHandle all-round administrative and clerical duties such as office supplies, office renovation, repair and maintenance\nAssist in the review, development and implementation of company policies/ procedures pertaining to human resources management\nEngage in ad hoc projects as required\nRequirement:\n\n\nDegree holder or above\nSelf-motivating, flexible and can-do attitude\u00a0\nAccounting knowledge is preferred\nAt least 3 years\u2019 experience in Human Resources sector\nProficient in English", "employment_types": ["Full Time", "Permanent"], "selling_points": ["Well-established MNC bank across Asia", "Accounting knowledge is preferred", "Min. 3 years of HR experience"], "locations": ["Central & Western Area"], "categories": ["Admin & HR", "Compensation & Benefits", "HR Supporting Staff"], "post_time": "2022-01-17T08:17:49Z", "salary": {"currency": null, "max": null, "min": null, "period": "monthly", "term": null}, "salary_visible": false, "title_keywords": ["administration officer", "hr"], "responsibilities": ["administration", "management", "maintenance", "office supplies", "company\u2019s operation", "hr", "review", "budgeting", "renovation", "implementation", "policies", "procedures", "repair", "maintain", "recruitment", "ad hoc projects", "personal data", "report"], "requirements": {"degrees": ["degree holder"], "majors": [], "languages": ["english"], "language_level": ["proficient"], "hard_skills": [], "soft_skills": ["flexible", "can-do attitude"], "languages_combined": [{"language": "english", "language_level": ["proficient"]}]}, "experience_required": {"duration": ["at least 3 years"], "field": ["human resources"]}}, {"job_id": "100003009049023", "location_code": "hk", "company": "-", "job_title": "Manager/Senior Manager, Performance & Rewards", "description": "Job Responsibilities\nDevelop and implement salary administration and employee performance appraisal programs\nDesign and administer benefits programs such as provident fund program, medical insurance program and etc.\nParticipate in selected salary survey and conduct research regarding development in compensation and benefit programs\nInvolve in monthly payroll and benefits calculations\nPrepare various human resources analysis reports\nAssume other HR duties as needed\nJob Requirements\nUniversity Degree\nMinimum 6 years in human resources management\nGood knowledge of human resources practices, performance appraisal procedures and employment legislation\nExperience in payroll administration and salary and benefits procedures\nAbility to work independently and under pressure\nGood MS Office skills\nGood command of Chinese and English\n\n-\n\n-", "employment_types": ["Permanent"], "selling_points": [], "locations": ["Central"], "categories": ["Admin & HR", "Administration / Operation Manager", "Compensation & Benefits"], "post_time": "2022-01-14T07:56:03Z", "salary": {"currency": null, "max": null, "min": null, "period": "monthly", "term": null}, "salary_visible": false, "title_keywords": ["senior manager", "manager"], "responsibilities": ["administration", "develop"], "requirements": {"degrees": [], "majors": [], "languages": [], "language_level": [], "hard_skills": [], "soft_skills": [], "languages_combined": []}, "experience_required": {"duration": [], "field": []}}, {"job_id": "100003009047681", "location_code": "hk", "company": "The Executive Centre Limited", "job_title": "Human Resources Officer", "description": "Job Duties:\n\nResponsible for full range of HR administration work including but not limited to MPF, insurance enrolment, HR correspondence and updates on orientation contents, organization charts, training materials and job descriptions for all positions\nHandle on-boarding and exit procedures and ensure all required documents are properly processed and recorded, e.g., conducting reference check, employment contracts, new hire documentations, employment certificates and all other HR-related documentation. \u00a0\nMaintains HR information system and works closely with the cities\u2019 Accountant/HR admin, to ensure HR data quality\nSupports payroll management and verifies and ensures payment accuracy\nAssist in annual budget preparation in local cities and preparing different HR-related reports\nAssist in developing user guideline for HR-related system\nWork as recruitment partner with teams in headquarter office\nBe one of the HR contact points for general employees\u2019 enquiries. Support in building positive work atmosphere\nHandle all work visa applications for all level of staff\nAssist in ad hoc projects as assigned\nCandidate with more experiences will be considered as Senior HR Officer\nJob requirements:\n\n3 - 4 years solid experiences in HR Generalist\nPreferably to have experiences on cost allocation and HRIS\nExcellent skill in Excel and other PC skills\nGood numerical skills and detailed-minded\nExcellent communication, presentation and problem-solving skills\nCommitted to work in a very fast paced environment and independently\nHighly motivated team player with positive attitude and excellent work ethics\nFluent English, Cantonese and Mandarin\nCandidates with more related experiences will be considered as Senior HR Officer\nImmediate Available is a plus", "employment_types": ["Full Time", "Permanent"], "selling_points": ["HR Administration", "C&B", "HRIS"], "locations": ["Southern Area"], "categories": ["Admin & HR", "Compensation & Benefits", "HR Supporting Staff"], "post_time": "2022-01-14T03:44:08Z", "salary": {"currency": null, "max": null, "min": null, "period": "monthly", "term": null}, "salary_visible": false, "title_keywords": ["human resources officer"], "responsibilities": ["related documentation", "data", "quality", "payment", "administration", "contracts", "teams", "developing", "reports", "management", "mpf", "procedures", "annual budget preparation", "contact", "contents", "payroll", "hr", "recruitment", "ad hoc projects", "insurance"], "requirements": {"degrees": [], "majors": [], "languages": ["cantonese", "english", "mandarin"], "language_level": ["fluent"], "hard_skills": ["excel", "plus", "numerical skills", "problem-solving skills", "pc skills"], "soft_skills": ["independently", "communication", "committed", "positive attitude", "motivated", "problem-solving skills", "team player", "presentation", "detailed"], "languages_combined": [{"language": "cantonese", "language_level": ["fluent"]}, {"language": "english", "language_level": ["fluent"]}, {"language": "mandarin", "language_level": ["fluent"]}]}, "experience_required": {"duration": ["3 - 4 years"], "field": ["related", "hr", "hr generalist"]}}, {"job_id": "100003009049195", "location_code": "hk", "company": "Premier by Dead Sea", "job_title": "Senior Human Resources Officer", "description": "Job Duties:\n\nHandling full spectrum of HR functions\nResponsible for payroll calculation, reviewing supporting document\nWork with line managers to determine hiring needs and select suitable candidates for final selection\nPrepare HR reports on regular basis for management review\nAssist in ad hoc projects\n\nJob Requirements:\n\nA Degree in Human Resources Management, Business Administration or related discipline;\nAt least 5 years of working experience in HR generalist position\u00a0\nGood interpersonal & communication skills;\nFamiliar with Employment Ordinance, MPF schemes and regulations\nMulti-tasking, meticulous, organized and able to meet tight work deadlines\nPleasant, strong sense of accountability and passionate about people\nGood command of written and spoken English and Chinese\nLess experience will be considered as Human Resources Officer", "employment_types": ["Full Time", "Permanent"], "selling_points": ["Handling full spectrum of HR functions", "Work with line managers to determine hiring needs", "Responsible for payroll calculation"], "locations": ["Kwun Tong"], "categories": ["Admin & HR", "Compensation & Benefits", "HR Supporting Staff", "Recruitment / Executive Search"], "post_time": "2022-01-14T08:15:12Z", "salary": {"currency": null, "max": null, "min": null, "period": "monthly", "term": null}, "salary_visible": false, "title_keywords": ["senior human resources officer"], "responsibilities": ["hr", "hr reports", "ad hoc projects", "payroll", "management review"], "requirements": {"degrees": ["degree"], "majors": ["business administration"], "languages": ["english", "chinese"], "language_level": ["good command"], "hard_skills": [], "soft_skills": ["organized", "communication skills", "meticulous", "accountability", "pleasant", "multi-tasking", "interpersonal", "passionate about"], "languages_combined": [{"language": "english", "language_level": ["good command"]}, {"language": "chinese", "language_level": ["good command"]}]}, "experience_required": {"duration": ["at least 5 years"], "field": ["hr generalist", "human resources"]}}, {"job_id": "100003009049392", "location_code": "hk", "company": "Amika", "job_title": "Senior Human Resources Officer", "description": "Job Duties:\n\nHandling full spectrum of HR functions\nResponsible for payroll calculation, reviewing supporting document\nWork with line managers to determine hiring needs and select suitable candidates for final selection\nPrepare HR reports on regular basis for management review\nAssist in ad hoc projects\n\nJob Requirements:\n\nA Degree in Human Resources Management, Business Administration or related discipline;\nAt least 5 years of working experience in HR generalist position\u00a0\nGood interpersonal & communication skills;\nFamiliar with Employment Ordinance, MPF schemes and regulations\nMulti-tasking, meticulous, organized and able to meet tight work deadlines\nPleasant, strong sense of accountability and passionate about people\nGood command of written and spoken English and Chinese\nLess experience will be considered as Human Resources Officer", "employment_types": ["Full Time", "Permanent"], "selling_points": ["We put people first", "Good development opportunities", "Handling full spectrum of HR functions"], "locations": ["Kwun Tong"], "categories": ["Admin & HR", "Compensation & Benefits", "HR Supporting Staff", "Recruitment / Executive Search"], "post_time": "2022-01-14T08:36:09Z", "salary": {"currency": null, "max": null, "min": null, "period": "monthly", "term": null}, "salary_visible": false, "title_keywords": ["senior human resources officer"], "responsibilities": ["hr", "hr reports", "ad hoc projects", "payroll", "management review"], "requirements": {"degrees": ["degree"], "majors": ["business administration"], "languages": ["english", "chinese"], "language_level": ["good command"], "hard_skills": [], "soft_skills": ["organized", "communication skills", "meticulous", "accountability", "pleasant", "multi-tasking", "interpersonal", "passionate about"], "languages_combined": [{"language": "english", "language_level": ["good command"]}, {"language": "chinese", "language_level": ["good command"]}]}, "experience_required": {"duration": ["at least 5 years"], "field": ["hr generalist", "human resources"]}}, {"job_id": "100003009043705", "location_code": "hk", "company": "Sino Group", "job_title": "Officer (Human Resources) (Ref: O-HR)", "description": "The successful candidate will be responsible for payroll calculation, compensation & benefits administration, and maintenance of HRIS. He/ She will also participate in HR projects as assigned.\nRequirements:\nDegree holder\nAt least 2 years of C&B experience in sizeable organization\nDetail-minded and good communication skills\nA proactive self-starter with a positive attitude\nAble to work independently and manage multiple priorities\nGood spoken and written English, Chinese and Putonghua\nStrong in MS Office including Word, Excel, PowerPoint and Chinese word processing\nWe offer attractive remuneration packages commensurate with experience and qualifications. If you aspire to an exciting and rewarding career, send your resume immediately, quoting your present and expected salaries by clicking the button\u00a0\u201cApply Now\u201d.\n\n\nIf the applicant does not receive a response by\u00a012 February 2022, the application will be considered unsuccessful.\u00a0 Please read our Personal Information Collection Statement at\u00a0https://www.sino.com/en-US/Careers/Personal-Information-Collection-Statement\u00a0before submitting your application. Information provided by applicants will be treated in strict confidence and used for recruitment purposes only.", "employment_types": ["Full Time"], "selling_points": [], "locations": ["Not Specified"], "categories": ["Admin & HR", "Others", "Compensation & Benefits", "HR Supporting Staff"], "post_time": "2022-01-13T01:33:07Z", "salary": {"currency": null, "max": null, "min": null, "period": "monthly", "term": null}, "salary_visible": false, "title_keywords": ["officer", "hr", "human resources"], "responsibilities": [], "requirements": {"degrees": [], "majors": [], "languages": [], "language_level": [], "hard_skills": [], "soft_skills": [], "languages_combined": []}, "experience_required": {"duration": [], "field": []}}, {"job_id": "100003009051290", "location_code": "hk", "company": "Hutchison Telecommunications (Hong Kong) Limited", "job_title": "Senior / Human Resources Specialist (Talent Acquisition)", "description": "Reporting to the Senior HR Manager, talent acquisition function is responsible for supporting the overall strategic talent sourcing by providing market intelligence and direct sourcing strategies to identify and attract suitable candidates across different divisions and functions.\n\n\nResponsibilities:\n\nDirect source and engage talent through social media, networks, competitive intelligence and other innovative channels\nSet up direct candidate sourcing strategies and candidate outreach to fulfil current sourcing requirements and ongoing workforce plans\nWork closely with HRBP and line managers to ensure the understanding of sourcing requirements, and keep track on feedbacks, priorities and challenges to ensure sourcing effectiveness\nProactively develop and manage talent pipelines and databases for current and future business initiatives\nProvide and research for market intelligence and industry trends\nApply HR principles, concepts and industry practices in relation to HR initiatives and projects\nPrepare analytical reports and other ad hoc projects as assigned\n\nRequirements:\n\nA tertiary qualification ideally in HR discipline\nAt least 4 years\u2019 hands-on direct candidate sourcing experience in sizable company\nCapability on passive candidates\u2019 direct outreach, engagement and cultivation\nExcellent communication skills in English and Chinese\nStrong analytical skills, detail-minded, agile with positive mindset\n\nApart from competitive remuneration package and exciting opportunity for career development within the Group, we provide attractive employee benefits such as free company shuttle, free company SIM card and preferential SIM plan offers, comprehensive medical & insurance schemes, as well as full range of other employee well-being provisions.\u00a0\n\nInterested parties, please send in your profile with your salary expectation to connie.chong@ hthk.com\u00a0\n\nWe are an equal opportunity employer and welcome applications from all qualified candidates. Personal data collected will be treated in the strictest confidence and handled confidentially by authorised personnel for recruitment-related purposes only within the CK Hutchison Group of companies. The personal data of unsuccessful applicants will be destroyed after the recruitment exercise pursuant to the requirements of the Personal Data (Privacy) Ordinance in Hong Kong.", "employment_types": ["Full Time", "Permanent", "Temporary", "Contract"], "selling_points": [], "locations": ["Kwai Tsing Area"], "categories": ["Admin & HR", "Compensation & Benefits", "Recruitment / Executive Search", "Training & Development"], "post_time": "2022-01-15T07:19:00Z", "salary": {"currency": null, "max": null, "min": null, "period": "monthly", "term": null}, "salary_visible": false, "title_keywords": ["human resources specialist"], "responsibilities": ["social media", "business initiatives", "hr", "develop", "reports", "ad hoc projects", "databases", "plans"], "requirements": {"degrees": [], "majors": [], "languages": ["english", "chinese"], "language_level": ["excellent"], "hard_skills": ["agile", "analytical skills"], "soft_skills": ["detail-minded", "communication skills", "agile", "positive mindset", "analytical skills", "hands-on", "comprehensive"], "languages_combined": [{"language": "english", "language_level": ["excellent"]}, {"language": "chinese", "language_level": ["excellent"]}]}, "experience_required": {"duration": ["at least 4 years"], "field": []}}, {"job_id": "100003009048916", "location_code": "hk", "company": "Cathay Pacific Catering Services (H.K.) Limited", "job_title": "Human Resources Officer (Business Partner)", "description": "Responsibilities\n\nAct as an HR business partner to provide the full spectrum of HR services including recruitment, staffing, performance management and C&B\nDesign and implement different recruiting and staffing programs to recruit and retain employees\nAnalyzes wage and salary reports and data to determine competitive compensation plan\nAdministers payroll and benefits programs\nAdvises management in appropriate resolution of employee relations issues\nResponds to inquiries regarding HR policies, procedures, and programs\nPrepare HR report for management review\nRequirements\n\nDegree holder in Human Resources Management or related disciplines\n1-2\u00a0years solid HR experience in a sizable multi-national company, with mass recruitment experience will be an advantage\nWell versed in Employment Ordinance and other relevant regulations\nGood interpersonal, communication skills and analytical skills\nProactive, independent, well-organized and detail-minded\nGood command of written and spoken English and Chinese;\nProficient in MS Office application and Chinese word processing\nImmediately available is highly preferred\nWe offer a competitive remuneration package and a full range of benefits. Interested parties please send your resume with your current and expected salary to Head of People,11 Catering Road East, Hong Kong International Airport, Lantau, Hong Kong or by clicking the \"Apply Now\" button\u00a0on or before 31 January 2022.\nPersonal data collected will be treated in the strictest confidence and only be used for recruitment-related purposes. Applicants who do not receive notification for an interview within six weeks may consider their application unsuccessful.", "employment_types": ["Full Time", "Permanent"], "selling_points": ["Act as a HR business partner", "Career advancement opportunities", "On job training provided"], "locations": ["Airport Area"], "categories": ["Admin & HR", "Compensation & Benefits", "HR Supporting Staff", "Recruitment / Executive Search"], "post_time": "2022-01-14T07:41:38Z", "salary": {"currency": null, "max": null, "min": null, "period": "monthly", "term": null}, "salary_visible": false, "title_keywords": ["human resources officer"], "responsibilities": ["management", "data", "hr", "design", "recruitment", "reports", "plan"], "requirements": {"degrees": [], "majors": [], "languages": [], "language_level": [], "hard_skills": [], "soft_skills": [], "languages_combined": []}, "experience_required": {"duration": [], "field": []}}, {"job_id": "100003009050918", "location_code": "hk", "company": "Bank of Communications Hong Kong Branch", "job_title": "Manager, Compensation & Benefits (HRIS)", "description": "Participate in HR system enhancement, implementation, review and streamline existing procedures through workflow analysis, convert such into user requirements and/or functional specifications\nPrepare HR reports and conduct data analysis, assist Compensation & Benefits Team in benefits administration and ad hoc HR projects\nDegree holder in Computer Studies or related discipline, with a minimum 5 years\u2019 hands-on HRIS experience preferably in banking or financial sector\nGood exposure in system evaluation, UAT and daily administration; Tactful communication, organization and project Management skills are essential\nWell versed in Employment Ordinance and HR related regulatory requirements\nProficient in excel and other software application, familiar with Database Management (e.g. SQL server)\nExperience in SQL, VB.NET, Visual Basic and MS windows system administration will be an advantage\nCandidate with more experience will be considered as Senior Manager, Compensation & Benefits", "employment_types": ["Full Time", "Permanent"], "selling_points": ["Participate in HR system enhancement", "Degree holder in Computer Studies or related", "Experience in SQL, VB.NET, Visual Basic"], "locations": ["Not Specified"], "categories": ["Admin & HR", "Administration / Operation Manager", "Others", "Compensation & Benefits"], "post_time": "2022-01-14T11:46:56Z", "salary": {"currency": null, "max": null, "min": null, "period": "monthly", "term": null}, "salary_visible": false, "title_keywords": ["manager"], "responsibilities": ["analysis", "hr", "review", "procedures", "implementation", "specifications"], "requirements": {"degrees": [], "majors": [], "languages": [], "language_level": [], "hard_skills": ["analysis"], "soft_skills": [], "languages_combined": []}, "experience_required": {"duration": [], "field": []}}, {"job_id": "100003009050431", "location_code": "hk", "company": "Broadway Photo Supply Ltd", "job_title": "Assistant Human Resources Officer / Human Resources Assistant", "description": "Responsibilities :\n\nAssist in providing support to full spectrum of human resources functions including recruitment and selection, compensation and benefits, employee relations, performance management, etc.\nPerform ad-hoc projects as assigned\n\nRequirements :\n\nDegree holder in Human Resources Management or related disciplines\nMinimum 3 years\u2019 relevant experience in sizable companies, preferably in retail industry\nWell versed in Hong Kong Employment Ordinance and other HR related regulations / ordinances\nProficiency in MS Office, Chinese Word Processing and knowledgeable in computerized HR Information System\nGood command of written and spoken English, Cantonese and Mandarin\nSelf-driven, good team-player with excellent communication and interpersonal skills\nMature, well-organized, meticulous and able to work under pressure\nImmediate available will be highly preferred\nCandidate with less experience will be considered as Human Resources Assistant\n\nThe working location is at Kwun Tong (King Yip Street). We offer 5-day work week, career advancement opportunities and attractive remuneration package to the right candidate. Interested parties, please send the full resume & expected salary to Human Resources Department via Apply Now.\n\n\n\n(All information submitted will be used for recruitment purpose only and will be destroyed after completion of the process.)", "employment_types": ["Full Time", "Permanent"], "selling_points": [], "locations": ["Kwun Tong"], "categories": ["Admin & HR", "Compensation & Benefits", "HR Supporting Staff", "Recruitment / Executive Search"], "post_time": "2022-01-14T10:24:29Z", "salary": {"currency": null, "max": null, "min": null, "period": "monthly", "term": null}, "salary_visible": false, "title_keywords": ["assistant human resources officer", "human resources assistant"], "responsibilities": ["management", "recruitment", "providing support", "ad-hoc projects", "human resources functions"], "requirements": {"degrees": ["degree holder"], "majors": ["related disciplines"], "languages": ["cantonese", "english", "chinese", "mandarin"], "language_level": ["proficiency", "good command"], "hard_skills": ["chinese word processing", "hong kong employment ordinance", "sizable companies", "information system", "ms office"], "soft_skills": ["meticulous", "team-player", "well-organized", "mature", "communication and interpersonal skills", "driven", "work under pressure"], "languages_combined": [{"language": "cantonese", "language_level": ["good command"]}, {"language": "english", "language_level": ["good command"]}, {"language": "chinese", "language_level": ["proficiency"]}, {"language": "mandarin", "language_level": ["good command"]}]}, "experience_required": {"duration": ["minimum 3 years"], "field": ["retail industry", "relevant experience", "human resources"]}}, {"job_id": "100003009047680", "location_code": "hk", "company": "Luk Fook Holdings Company Limited", "job_title": "Senior Human Resources Manager / Human Resources Manager", "description": "Job Descriptions:\n\n-\u00a0\u00a0\u00a0\u00a0\u00a0\u00a0\u00a0 Provide full spectrum of HR functions including recruitment and selection, performance management, remunerations, C&B, manpower planning, employee relations, and training & development.\n\n-\u00a0\u00a0\u00a0\u00a0\u00a0\u00a0\u00a0 Applying project management skills to lead all aspects of project lifecycle for HR initiatives to drive business outcomes\n\n-\u00a0\u00a0\u00a0\u00a0\u00a0\u00a0\u00a0 Formulate, implement and review HR and administration policies\n\n-\u00a0\u00a0\u00a0\u00a0\u00a0\u00a0\u00a0 Provide strategic and professional advice to senior management on HR related issues.\n\n-\u00a0\u00a0\u00a0\u00a0\u00a0\u00a0\u00a0 Perform ad-hoc task as assigned\n\nRequirements:\n\n-\u00a0\u00a0\u00a0\u00a0\u00a0\u00a0\u00a0 Degree holder in HR management or related disciplines\n\n-\u00a0\u00a0\u00a0\u00a0\u00a0\u00a0\u00a0 Not less than 8 years all-round HR experiences with at least 6 years at managerial level in diverse, dynamic working environment &preferably in retail industry\n\n-\u00a0\u00a0\u00a0\u00a0\u00a0\u00a0\u00a0 Excellent communication, presentation and problem solving skills\n\n-\u00a0\u00a0\u00a0\u00a0\u00a0\u00a0\u00a0 Resourceful, initiative, highly-organized and analytical with an eye for detail\n\n-\u00a0\u00a0\u00a0\u00a0\u00a0\u00a0\u00a0 A good team player, detail-oriented with high accuracy\n\n-\u00a0\u00a0\u00a0\u00a0\u00a0\u00a0\u00a0 Well versed in Employment Ordinances and related regulations\n\n-\u00a0\u00a0\u00a0\u00a0\u00a0\u00a0\u00a0 Fluent spoken and written English, Chinese and Mandarin\n\n-\u00a0\u00a0\u00a0\u00a0\u00a0\u00a0\u00a0 Less experiences will be considered as Human Resources Manager\n\n-\u00a0\u00a0\u00a0\u00a0\u00a0\u00a0\u00a0 Immediate availability is preferred", "employment_types": ["Full Time"], "selling_points": ["Provide full spectrum of HR functions", "Perform ad-hoc task as assigned", "Degree holder in HR management"], "locations": ["Shatin Area"], "categories": ["Admin & HR", "Compensation & Benefits", "HR Director / Manager", "Training & Development"], "post_time": "2022-01-14T03:44:05Z", "salary": {"currency": null, "max": null, "min": null, "period": "monthly", "term": null}, "salary_visible": false, "title_keywords": ["manager", "human resources"], "responsibilities": ["administration", "ad-hoc", "management", "policies", "hr", "review", "project management", "recruitment", "senior management", "planning"], "requirements": {"degrees": ["degree holder"], "majors": ["related disciplines"], "languages": ["english", "chinese", "mandarin"], "language_level": ["fluent"], "hard_skills": ["problem solving skills", "dynamic"], "soft_skills": ["organized", "good team player", "resourceful", "detail-oriented", "communication", "diverse", "dynamic", "eye for detail", "problem solving skills", "initiative", "presentation"], "languages_combined": [{"language": "english", "language_level": ["fluent"]}, {"language": "chinese", "language_level": ["fluent"]}, {"language": "mandarin", "language_level": ["fluent"]}]}, "experience_required": {"duration": ["at least 6 years", "8 years"], "field": ["retail industry", "managerial", "hr", "human resources"]}}, {"job_id": "100003009051029", "location_code": "hk", "company": "The Wharf Group", "job_title": "Assistant Project Manager (HRIS SAP SF)", "description": "The incumbent will be a key team member of the SAP SuccessFactors HRIS Project implementation and management team.\u00a0\u00a0\nKey Responsibilities:\nAssist the project manager to review, define and develop user requirements for four HR offices of the Group\nParticipate in the re-engineering of current HR processes across different operating entities and between HR and Central Payroll\nHandle complex information communications and collection through meetings and workshops with external vendors and internal HR coordinators\nCollection and consolidation of information and report for management review with recommendation/solutions\nAssist to manage the project timetable and flag up issues or concerns, and ensure deliverables quality in the progression of the project\nCo-ordinate the design and execution of testing cases\nKeep-up-to-date and have expertise on SAP product release and recommend appropriate actions to project manager\nProvide administration and documentation support of the project\nPerforms other duties and projects in other HR areas as assigned\n\nRequirements:\n\nBachelor\u2019s degree in Management Information Systems or related disciplines\nAt least 7- 8 years\u2019 of relevant working experience in HRIS, solid exposure in SAP SuccessFactors HRIS actual system management and project roll out and implementation is preferred\nHand on experience on SAP SF products, configurations and SAP ABAP programming\nStrong project and time management, organization and problem-solving skills\nExcellent communication, presentation and interpersonal skills and detail-minded\nEnthusiastic to assume responsibility and accountability with excellent integrity\nproficient in both spoken and written English and Chinese\n\nCandidates with less experience may be considered as Senior\u00a0HRIS Project Officer/Officer\n\n\nWe work 5 days per week.\n\nInterested parties, please click \"APPLY NOW\" and attach with your application letter and full resume.\n\n\nFor further information of the Wharf Group, please visit our website: www.wharfholdings.com\u00a0", "employment_types": ["Full Time", "Permanent"], "selling_points": [], "locations": ["Tsim Sha Tsui"], "categories": ["Admin & HR", "Compensation & Benefits", "Information Technology (IT)", "IT Project Management / Team Lead", "Others"], "post_time": "2022-01-15T01:17:13Z", "salary": {"currency": null, "max": null, "min": null, "period": null, "term": null}, "salary_visible": false, "title_keywords": ["assistant project manager"], "responsibilities": ["administration", "other duties", "hr", "review", "quality", "design", "develop", "management review", "testing", "documentation", "payroll", "re-engineering", "report"], "requirements": {"degrees": ["degree", "bachelor"], "majors": ["related disciplines"], "languages": ["english", "chinese"], "language_level": ["proficient"], "hard_skills": ["programming", "problem-solving skills", "abap", "sap"], "soft_skills": ["detail-minded", "accountability", "integrity", "communication", "interpersonal skills", "enthusiastic", "problem-solving skills", "time management", "presentation"], "languages_combined": [{"language": "english", "language_level": ["proficient"]}, {"language": "chinese", "language_level": ["proficient"]}]}, "experience_required": {"duration": ["at least 7- 8 years"], "field": ["management", "relevant working experience", "programming"]}}, {"job_id": "100003009047166", "location_code": "hk", "company": "G4S (Hong Kong - Holding) Limited", "job_title": "Human Resources Officer", "description": "\nResponsibilities:\n\nProvide monthly or ad-hoc payroll for all staff;\nMonitor the accuracy of the raw data, which are correlated to wages calculation, such as attendance records and leave records;\nPrepare a set of payroll related reports to relevant parties, e.g. Finance Department, end-user business and Human Resources Department;\nPrepare annual tax return to IRD for all staff;\nMonitor the wages hotline and respond to the wages enquiry of staff;\nAssist in staff benefit review and employee relations activities;\nProvide counter enquiry support in wages issues;\nAssist to recruit capable staff for operations and handle the new joiner issues.\nSource and recruit candidates by using databases, social media etc\nConduct interviews using various reliable recruiting and selection tools/methods to filter candidates within schedule\nConduct vetting process as per Company requirement\nProvide analytical and well documented recruiting reports\nAny ad-hoc duties assigned by Management.\n\n\u00a0Requirements:\n\nMatriculated education or above in Human Resources Management or relevant disciplines\nMinimum 3 years people management experience with proven record\nExperience in service industry would be an advantage\nRecruitment experience is a plus\nGood command in spoken & written English and Chinese\nGood knowledge of common office software, e.g., Chrome Office, MS Office, etc.\nDetails-minded, Independent, Self-initiative, Well-organized and good team player with enthusiastic and proactive behavior\nWilling to work under pressure and capable of meeting deadlines\nLabour relations experience, including a good understanding of the relevant HK Legislation\nCandidate with more experience will be considered as Assistant Human Resources Manager\n\n\n\nInterested applicants are invited to write in with a detail resume including present and expected salary to : -\n\n\u00a0The Human Resources Services Department\n\nG4S (Hong Kong - Holding) Limited\n1st Floor The Securicor Centre\n481 Castle Peak Road, Hong Kong\n\nOur Company is an equal opportunity employer and welcomes applications from all qualified candidates. The personal data provided will be used for consideration in your application for the applied post and other suitable positions in the G4S. Applications who are not invited for interview within 6 weeks may consider their applications unsuccessful. All personal data of unsuccessful candidates will be destroyed after 6 months.\u00a0", "employment_types": ["Full Time"], "selling_points": ["Matriculated education or above in Human Resources", "Minimum 3 years people management experience", "Labour relations experience"], "locations": ["Lai Chi Kok"], "categories": ["Admin & HR", "Compensation & Benefits"], "post_time": "2022-01-14T02:30:33Z", "salary": {"currency": null, "max": null, "min": null, "period": "monthly", "term": null}, "salary_visible": false, "title_keywords": ["human resources officer"], "responsibilities": ["ad-hoc", "attendance", "tax", "social media", "management", "data", "operations", "review", "monitor", "reports", "schedule", "databases", "ad-hoc duties", "payroll"], "requirements": {"degrees": [], "majors": [], "languages": ["english", "chinese"], "language_level": ["good command"], "hard_skills": ["plus", "office software", "ms office"], "soft_skills": ["good team player", "independent", "capable", "well-organized", "self-initiative", "enthusiastic", "proactive", "work under pressure"], "languages_combined": [{"language": "english", "language_level": ["good command"]}, {"language": "chinese", "language_level": ["good command"]}]}, "experience_required": {"duration": ["minimum 3 years"], "field": ["human resources", "people management", "recruitment", "service industry"]}}, {"job_id": "100003009050392", "location_code": "hk", "company": "Goodwell Property Management Ltd", "job_title": "Assistant Human Resources Manager (C&B)   (Ref. AHRM_C&B/J)", "description": "Degree\u00a0holder in\u00a0Human Resources Management or related disciplines\nMinimum 5 years' solid experience in C&B function preferably gained from sizeable organization or property management\nWell versed in Hong Kong Employment Ordinance and related legislations\nStrong computer literacy in MS office and HRIS preferably in IPL\nSelf-motivated, analytical, well-organized, strong sense of commitment and able to work under tight timeline\nGood command of both written and spoken English\u00a0& Chinese\n\nWe will offer attractive compensation package to the right candidate. Please send application enclosing resume stating career and salary history, expected salary and date of availability to\u00a0The Human Resources Manager, Goodwell Property Management Limited, 2/F New Treasure Centre, 10 Ng Fong Street, San Po Kong, Kowloon\u00a0or\u00a0by clicking\u00a0\u201cApply Now\u201d\u00a0(in Word format). Please quote the reference of the position you apply for in all correspondences.\u00a0\n\nWe are an equal opportunity employer and welcome applications from all qualified candidates.\u00a0 Personal data collected will be treated in strictest confidence and handled confidentially by authorized personnel for recruitment-related purposes within the Group. Applicants not hearing from us within six weeks from the date of\u00a0application\u00a0may consider their applications unsuccessful.\n\n(Our website :\u00a0http://www.goodwell.com.hk/)", "employment_types": ["Full Time", "Permanent"], "selling_points": ["Degree holder or above in HRM", "Minimum 5 years' relevant experience", "Well versed in Hong Kong Employment Ordinance"], "locations": ["Wong Tai Sin Area"], "categories": ["Admin & HR", "Compensation & Benefits", "HR Director / Manager"], "post_time": "2022-01-14T10:24:27Z", "salary": {"currency": null, "max": null, "min": null, "period": null, "term": null}, "salary_visible": false, "title_keywords": ["assistant human resources manager"], "responsibilities": ["management", "website", "recruitment", "personal data", "legislations"], "requirements": {"degrees": ["degree holder"], "majors": ["related disciplines"], "languages": ["english", "chinese"], "language_level": ["good command"], "hard_skills": ["ipl", "hong kong employment ordinance", "word", "ms office"], "soft_skills": ["computer literacy", "self-motivated", "confidence", "well-organized"], "languages_combined": [{"language": "english", "language_level": ["good command"]}, {"language": "chinese", "language_level": ["good command"]}]}, "experience_required": {"duration": ["minimum 5 years"], "field": ["management"]}}, {"job_id": "100003009046054", "location_code": "hk", "company": "FSE Engineering Group Limited", "job_title": "Human Resources Officer (Kowloon Bay)", "description": "Qualification & Requirements:\n\nHigher Diploma or above in Human Resources Management or related discipline.\nMinimum five years\u2019 experience gained in sizable companies, specializing in payroll and C&B administration.\nWell-versed in Hong Kong Employment Ordinance, MPF regulations and other HR-related legislations.\nProactive, meticulous, responsible, and with good communication skills.\nHands-on experience in HRIS system is essential. Proficiency in MS Excel, Word, and PowerPoint.\nProficiency Good command of both written and spoken English and Chinese.\nImmediate available. \u00a0\n\nJob Duties:\n\nParticipate in handling the full spectrum of HR functions including recruitment, compensation and benefits, training and development, employee relations, and staff activities.\nPrepare various periodical and/or ad-hoc HR analytical reports for management\u2019s review.\nCarry out the ad hoc assignments as designated.\u00a0", "employment_types": ["Full Time", "Permanent"], "selling_points": ["HD of above in HRM or related discipline.", "Min 5yrs\u2019 exp in sizable companies, HRIS system.", "Proactive, meticulous, responsible."], "locations": ["Kowloon Bay"], "categories": ["Admin & HR", "Compensation & Benefits", "HR Supporting Staff", "Recruitment / Executive Search"], "post_time": "2022-01-13T09:30:30Z", "salary": {"currency": null, "max": null, "min": null, "period": "monthly", "term": null}, "salary_visible": false, "title_keywords": ["human resources officer"], "responsibilities": ["ad-hoc", "management", "hr", "review", "recruitment", "reports", "ad hoc assignments"], "requirements": {"degrees": ["higher diploma or above"], "majors": [], "languages": ["english", "chinese"], "language_level": ["proficiency", "good command"], "hard_skills": ["hong kong employment ordinance", "sizable companies", "word", "powerpoint", "ms excel", "mpf regulations"], "soft_skills": ["communication skills", "meticulous", "responsible", "hands-on", "proactive"], "languages_combined": [{"language": "english", "language_level": ["proficiency", "good command"]}, {"language": "chinese", "language_level": ["proficiency", "good command"]}]}, "experience_required": {"duration": ["minimum five years"], "field": ["payroll", "administration"]}}, {"job_id": "100003009046409", "location_code": "hk", "company": "Harriman Property Management Limited", "job_title": "Personnel Officer", "description": "Responsibilities:\n\n\nInvolve and support the SAP HRIS changeover\nPrepare related documentation; assist in system configuration, data input, checking and conversion\nMaintain HR system to ensure all data are up-to-date and accurate\nPerform UAT with test case/data preparation\nGather regular reports, forms and HR related data\nPerform C&B and other HR duties as assigned\u00a0\u00a0\nRequirements:\nDegree in Human Resources Management / Information Technology or a related discipline\nAt least 1 year\u2019s hands-on experience in HRIS implementation and roll outs, preferably gained in property management industry or sizeable organizations\nWith payroll calculation and administration experience is highly preferred\nWell versed in Hong Kong Employment Ordinance and other employment related legislations\nProficiency in Excel skills such as Pivot Table is definitely an advantage\nExcellent communication and interpersonal kills\nNumeric sensitive, detailed minded and able to meet tight deadline\nGood command of both spoken and written English and Chinese\n\nWe offer ample opportunities for career development and attractive salary package commensurate with experience and qualifications. \u00a0Interested parties please apply with full resume via\u00a0\u201cAPPLY NOW\u201d.\u00a0\u00a0\u00a0\u00a0\u00a0\n\nFor further information on Wheelock Properties (Hong Kong) Limited, please visit our website:\u00a0www.wheelockpropertieshk.com\n\nWe are an equal opportunities employer and invite applications from all qualified candidates. Personal data collected will be treated in strict confidence and handled by authorized persons for recruitment-related purposes only within the Wheelock & Wharf Group.\u00a0 Applicants not hearing from us within two months may consider their applications unsuccessful.\n\n(All information provided by applicants will be treated in strict confidence and be used for recruitment purpose only)", "employment_types": ["Full Time", "Permanent"], "selling_points": [], "locations": ["Kwun Tong"], "categories": ["Admin & HR", "Clerical / Admin Staff", "Compensation & Benefits", "Information Technology (IT)", "Network & System"], "post_time": "2022-01-13T18:55:21Z", "salary": {"currency": null, "max": null, "min": null, "period": null, "term": null}, "salary_visible": false, "title_keywords": ["officer"], "responsibilities": ["related documentation", "uat", "data", "configuration", "hr", "checking", "data input", "hr duties", "maintain", "reports"], "requirements": {"degrees": ["degree"], "majors": ["information technology"], "languages": ["english", "chinese"], "language_level": ["good command"], "hard_skills": ["excel", "pivot table", "hong kong employment ordinance"], "soft_skills": ["communication", "hands-on", "meet tight deadline", "sensitive", "interpersonal", "detailed"], "languages_combined": [{"language": "english", "language_level": ["good command"]}, {"language": "chinese", "language_level": ["good command"]}]}, "experience_required": {"duration": ["at least 1 year"], "field": ["management", "payroll", "administration"]}}, {"job_id": "100003009037319", "location_code": "hk", "company": "METRO Sourcing International Limited", "job_title": "Human Resources Officer", "description": "Role Purpose:\n\nOur Human Resources Officer is the key person responsible for Compensation and Benefits for Hong Kong Office.\n\nWhat you\u2019ll be handling:\n\nResponsible for full spectrum of the compensation and benefits function including monthly payroll, MPF administration, leave management, medical insurance, employee compensation insurance, taxation, performance management and salary review\nIn-charge of the HR system from daily operations, regular maintenance to enhancement\nMaintain and update employee records, personnel filing and database\nInvolve in employee relation activities and programs such as Employee Engagement Survey, Annual Party, Innovation Day, etc.\nAssist in the review, development and implementation of HR policies and procedures\nTalent that we are looking for:\n\nSelf-motivated to drive for excellent service\nWell organized, attention to details with solution-oriented mindset\nStrong sense of ownership and high degree of independence\nPassionate in connecting with people\nExperience, knowledge and skills required:\n\nDegree holder in Human Resources Management, Business Administration, or related disciplines\nAt least 3 years relevant working experience required\nWell-versed in HK Employment Ordinance and other related regulations\nGood command of written and spoken English\nProficient in MS Office applications and experience in SAP HR system\nYou can enjoy:\n\nDiverse and Inclusive work environment\nFlexi Office Space with flexible working hours and home office option\n5-day work week, 13th month salary & performance bonus\nProfessional training and career advancement opportunities\nTraining Sponsorship for personal professional development\n\n\nJoin us and apply now!\nPlease send your full resume with available date, present and expected salary to us.\nResume and personal data collected will be kept strictly confidential and used for recruitment purpose only.", "employment_types": ["Full Time", "Permanent"], "selling_points": ["Exp in HR C&B function (SAP exp is in advantage)", "Resp. for full spectrum C&B function & HR system", "MNC, 5-day work, insurance, double pay, bonus"], "locations": ["Kowloon Bay"], "categories": ["Admin & HR", "Compensation & Benefits", "HR Supporting Staff"], "post_time": "2022-01-11T16:01:40Z", "salary": {"currency": null, "max": null, "min": null, "period": "monthly", "term": null}, "salary_visible": false, "title_keywords": ["human resources officer"], "responsibilities": [], "requirements": {"degrees": [], "majors": [], "languages": [], "language_level": [], "hard_skills": [], "soft_skills": [], "languages_combined": []}, "experience_required": {"duration": [], "field": []}}, {"job_id": "100003009047168", "location_code": "hk", "company": "G4S (Hong Kong - Holding) Limited", "job_title": "Senior Human Resources Officer", "description": "Main purpose of role:\n\nBe responsible for regular payroll and compensation and benefits administration, staff recruitment, monitor the operations of uniform distribution centre, \u00a0employee\u2019s Compensation case handling including but not limited to department administration for all business units.\u00a0\n\nResponsibilities:\n\nProvide monthly or ad-hoc payroll for all staff;\nMonitor the accuracy of the raw data, which are correlated to wages calculation, such as attendance records and leave records;\nPrepare a set of payroll related reports to relevant parties, e.g. Finance Department, end-user business and Human Resources Department;\nPrepare annual tax return to IRD for all staff;\nMonitor the wages hotline and respond to the wages enquiry of staff;\nAssist in staff benefit review and employee relations activities;\nProvide general administrative support of EC case to the department;\nProvide counter enquiry support in wages issues;\nMonitor the operations of uniform distribution centre\nAssist to recruit capable staff for operations and handle the new joiner issues.\nSource and recruit candidates by using databases, social media etc\nConduct interviews using various reliable recruiting and selection tools/methods to filter candidates within schedule\nConduct vetting process as per Company requirement\nProvide analytical and well documented recruiting reports\nAny ad-hoc duties assigned by Management.\n\n\u00a0Requirements:\n\nMatriculated education or above in Human Resources Management or relevant disciplines\nMinimum 3 years people management experience with proven record\nExperience in service industry would be an advantage\nRecruitment experience is a plus\nGood command in spoken & written English and Chinese\nGood knowledge of common office software, e.g., Chrome Office, MS Office, etc.\nDetails-minded, Independent, Self-initiative, Well-organized and good team player with enthusiastic and proactive behavior\nWilling to work under pressure and capable of meeting deadlines\nLabour relations experience, including a good understanding of the relevant HK Legislation\nCandidate with more experience will be considered as Assistant Human Resources Manager\n\n\n\nInterested applicants are invited to write in with a detail resume including present and expected salary to : -\n\n\u00a0The Human Resources Services Department\n\nG4S (Hong Kong - Holding) Limited\n1st Floor The Securicor Centre\n481 Castle Peak Road, Hong Kong\n\nOur Company is an equal opportunity employer and welcomes applications from all qualified candidates. The personal data provided will be used for consideration in your application for the applied post and other suitable positions in the G4S. Applications who are not invited for interview within 6 weeks may consider their applications unsuccessful. All personal data of unsuccessful candidates will be destroyed after 6 months.\u00a0", "employment_types": ["Full Time"], "selling_points": ["Matriculated education or above in Human Resources", "Minimum 3 years people management experience", "Labour relations experience"], "locations": ["Lai Chi Kok"], "categories": ["Admin & HR", "Compensation & Benefits"], "post_time": "2022-01-14T02:30:34Z", "salary": {"currency": null, "max": null, "min": null, "period": "monthly", "term": null}, "salary_visible": false, "title_keywords": ["senior human resources officer"], "responsibilities": ["ad-hoc", "attendance", "tax", "social media", "management", "data", "operations", "review", "monitor", "general administrative support", "reports", "schedule", "databases", "ad-hoc duties", "payroll"], "requirements": {"degrees": [], "majors": [], "languages": ["english", "chinese"], "language_level": ["good command"], "hard_skills": ["plus", "office software", "ms office"], "soft_skills": ["good team player", "independent", "capable", "well-organized", "self-initiative", "enthusiastic", "proactive", "work under pressure"], "languages_combined": [{"language": "english", "language_level": ["good command"]}, {"language": "chinese", "language_level": ["good command"]}]}, "experience_required": {"duration": ["minimum 3 years"], "field": ["human resources", "people management", "recruitment", "service industry"]}}, {"job_id": "100003009048925", "location_code": "hk", "company": "Miramar Travel Ltd", "job_title": "Human Resources Assistant (Job Ref. 202201-HR&A-HRA)", "description": "Responsibilities:\n\n\nTo assist in all-rounded HR functions, including recruitment, payroll & C&B, etc.\nTo handle ad hoc tasks as assigned\nRequirements:\n\nHigher Diploma or above\u00a0in HR Management or related disciplines\nAt least 2-year HR experience, preferably gained from sizeable organization.\nExcellent interpersonal, communication & presentation skills\nDetail-minded, well-organised, with strong numerical sense and high accuracy\nGood working attitude & be a good team player\nGood command of spoken & written English, Cantonese & Putonghua\nProficient in PC applications, such as Words, Excel, PowerPoint & Chinese Word Processing\nImmediate available is highly preferred\nWe offer attractive remuneration package and excellent career prospect to the right candidate.\u00a0 Salary will be commensurate with applicant\u2019s qualification and experience.\u00a0 Any interested candidates please send your full resume with CURRENT & EXPECTED SALARY and DATE OF AVAILABILITY by clicking 'Apply Now'.\n\n\n\nInformation provided will be treated in strict confidence and only be used for recruitment purpose.\n\nPlease refer to our website www.miramartravel.hk for more openings.", "employment_types": ["Full Time"], "selling_points": [], "locations": ["Causeway Bay"], "categories": ["Admin & HR", "Compensation & Benefits", "HR Supporting Staff", "Recruitment / Executive Search"], "post_time": "2022-01-14T07:43:29Z", "salary": {"currency": null, "max": null, "min": null, "period": "monthly", "term": null}, "salary_visible": false, "title_keywords": ["human resources assistant"], "responsibilities": ["hr", "payroll", "recruitment", "ad hoc tasks"], "requirements": {"degrees": ["higher diploma or above"], "majors": ["related disciplines"], "languages": ["cantonese", "putonghua", "english", "chinese"], "language_level": ["good command", "proficient"], "hard_skills": ["excel", "chinese word processing", "words", "powerpoint", "pc applications"], "soft_skills": ["detail-minded", "good working attitude", "good team player", "communication", "presentation skills", "well-organised", "interpersonal"], "languages_combined": [{"language": "cantonese", "language_level": ["good command"]}, {"language": "putonghua", "language_level": ["good command"]}, {"language": "english", "language_level": ["good command"]}, {"language": "chinese", "language_level": ["proficient"]}]}, "experience_required": {"duration": ["at least 2-year"], "field": ["hr"]}}, {"job_id": "100003009045454", "location_code": "hk", "company": "Mitsubishi HC Capital (Hong Kong) Limited", "job_title": "Senior Officer (Human Resources)", "description": "Responsibilities:\n\nProvide full spectrum of HR functions duties, such as full recruitment process, payroll and MPF administration, conduct exit interview, visa renewal, insurance renewal, maintain HRIS, etc.\nPrepare regular records and monthly report such as attendance, headcount, leave and late report, etc.\nMonitoring and supporting company activities, CSR events and coordinating training programs\nSupport the development and implementation of human resources initiatives and system\nAssist in reviewing policy, employee handbook and operation procedures in human resources and general affairs functions.\nPerform other routine duties such as maintaining filing system, procurement processing, transportation claim and other administrative function.\nProvide wide range of operational support to any human resources and general affairs functions and events\n\nRequirements:\n\nBachelor\u2019s Degree in human resources management, Communications, Language Studies or related disciplines\n5 years solid experience or above in human resources & general affairs function\nGood command of spoken and written English and Chinese including Mandarin\nProficient in MS Word, Excel, PowerPoint, Chinese Word Processing and HRIS\nGood command in documentation and filing system\nApplicants must be positive thinking, hardworking, responsible, attentive to details, initiative, with good communication and interpersonal skills\nImmediate available is preferred\n\nWe offer competitive remuneration package including 5-day work, double pay, discretionary bonus and medical & group life insurance to the right candidate. Interested parties, please send full resume with present and expected salary, as well as availability to Talent Management & General Affairs Department, Mitsubishi HC Capital \u00a0(Hong Kong) Limited.\n\nPersonal data collected will be used for recruitment purpose only.\u00a0 Applicants who do not hear from us within 8 weeks may consider their applications unsuccessful and their data will be destroyed within 12 months of receipt.\n\nWe are an Equal Opportunity Employer provides equal employment opportunities to all qualified applicants.", "employment_types": ["Full Time", "Permanent"], "selling_points": [], "locations": ["Mong Kok"], "categories": ["Admin & HR", "Compensation & Benefits", "HR Supporting Staff"], "post_time": "2022-01-13T07:53:13Z", "salary": {"currency": null, "max": null, "min": null, "period": "monthly", "term": null}, "salary_visible": false, "title_keywords": ["senior officer", "human resources"], "responsibilities": ["attendance", "operational support", "mpf", "maintaining", "hr", "monitoring", "procedures", "implementation", "maintain", "insurance", "monthly report", "recruitment process", "payroll", "report", "administration"], "requirements": {"degrees": ["degree", "bachelor"], "majors": ["related disciplines", "communications"], "languages": ["english", "chinese", "mandarin"], "language_level": ["good command", "proficient"], "hard_skills": ["excel", "chinese word processing", "powerpoint", "documentation", "ms word"], "soft_skills": ["attentive to details", "responsible", "positive thinking", "communication and interpersonal skills", "initiative", "hardworking"], "languages_combined": [{"language": "english", "language_level": ["good command"]}, {"language": "chinese", "language_level": ["good command", "proficient"]}, {"language": "mandarin", "language_level": ["good command"]}]}, "experience_required": {"duration": ["5 years"], "field": ["human resources"]}}, {"job_id": "100003009047561", "location_code": "hk", "company": "Longshore Ltd", "job_title": "Human Resources & Administration Officer", "description": "Job Responsibilities\n\nPerform end to end HK & China recruitment from drafting job advertisement, screening resumes, arranging and conducting interview to offer delivery and on boarding\nManage and review various sourcing channels\nUpdate personal details and attendance record in HR systems\nHandle administrative duties, e.g. organize company events\nPrepare regular payroll reports\nHandle ad hoc HR projects and tasks as required \u00a0\nTravel to CHN office on occasion\n\nJob Requirements\n\nForm 7 or above in Human\u00a0Resources or related disciplines\nAt least 3 years related experience\nWell versed with HK Employment Ordinance and other related legislation\nHas knowledge about PRC Labour Law is preferable but not a must\nProficient in MS Office\nMature, stable, hardworking and\u00a0good communication skills and interpersonal skills\nAble to perform in a fast-paced and dynamic environment\nCandidates with less experience will be considered as Assistant Human Resources and Administration Officer\u00a0\nImmediate available is preferred\nAlternate Saturday, Double pay, Medical, Annual leave, Bonus", "employment_types": ["Full Time", "Permanent"], "selling_points": ["Great opportunity to explore", "At least 3 years related exp, Immediate available", "Double pay, Medical, Annual leave, Bonus"], "locations": ["Hung Hom"], "categories": ["Admin & HR", "Compensation & Benefits", "HR Supporting Staff", "Recruitment / Executive Search"], "post_time": "2022-01-14T03:27:50Z", "salary": {"currency": null, "max": null, "min": null, "period": "monthly", "term": null}, "salary_visible": false, "title_keywords": ["administration officer", "human resources"], "responsibilities": ["attendance", "ad hoc", "job advertisement", "hr", "review", "systems", "screening resumes", "recruitment", "administrative duties", "reports", "payroll"], "requirements": {"degrees": [], "majors": [], "languages": [], "language_level": [], "hard_skills": ["dynamic", "ms office"], "soft_skills": ["communication skills", "dynamic environment", "mature", "interpersonal skills", "stable", "hardworking"], "languages_combined": []}, "experience_required": {"duration": ["at least 3 years"], "field": ["related", "human resources", "administration"]}}, {"job_id": "100003009047035", "location_code": "hk", "company": "KOS International Limited", "job_title": "Director of Global Total Rewards", "description": "About the Client\n\nA well renowned organization with a global presence and a strong track record of success is now seeking for a dynamic individual to join them as the Director of Global Total Rewards.\n\nAbout the Role\n\nAct as a trusted advisor and expert to the CHRO in the development of a sustainable, relevant and innovative compensation and reward strategy in line with a growing business and one that drives the performance of the organization\nFurther direct the formulation and implementation of the reward and benefits programs globally that will attract, incentivize and retain high performing employees\nOversee all global benchmarking and strategic reviews of compensation in addition to leading (in partnership with HR Regional Leads) the Global Pay Review, ensuring that remuneration and performance related pay are in line with the budget and company objective\nEstablish and ensure the implementation of all compensation & benefit schemes ensuring there is complete compliance with relevant legislation and tax regulations globally\nDevelop and direct the formulation and implementation of global benefits policies i.e pension, healthcare, life assurance\nEnsure the implementation of a relevant Global International Mobility program (including realizing full package analysis for expatriate employees and tax sensitivity analysis) which will achieve the global mobility objectives and the appropriate budget objectives of the company\nDevelop new reward tools in line with an evolving Digital Strategy and implementation of Rewards on HRIS\nAdvise Senior Leaders and HR Team on all matters relating to Compensation and Benefits\nContinuous development and improvement of current reward practices globally\n\nThe Successful Applicant\n\nBachelor's holder in Human Resources Management or relevant discipline\nA minimum 18 years of working experience in the field of HR with an expertise in Compensation & Benefits on both local and regional level\nPrior experience within a consultancy environment is a definite advantage\nHands on experience in executing and delivering total reward strategy (Compensation, Benefits, International Assignment, Recognition and Reward Systems) is a MUST\nStrong user of contemporary HR system with the experience of implementation is preferred\nNumerically sensitive with strong business acumen\nResult oriented, ability to multitask and operate in an ever-changing environment\nOrganized, good communication skills with strong stakeholder management skills\nProficient in spoken and written English and Chinese\n\nClick \"Apply Now\" to apply for this position or call Xavier Tam at +852 3180 4920 for a confidential discussion. All information collected will be kept in strict confidence and will be used for recruitment purpose only.", "employment_types": ["Full Time", "Permanent"], "selling_points": ["Report to CHRO", "Full ownership of C&B function", "Competitive remuneration package"], "locations": ["Not Specified"], "categories": ["Admin & HR", "Compensation & Benefits", "HR Director / Manager"], "post_time": "2022-01-14T02:07:02Z", "salary": {"currency": null, "max": null, "min": null, "period": "monthly", "term": null}, "salary_visible": false, "title_keywords": ["director"], "responsibilities": ["tax", "regulations", "hr", "compliance", "review", "budget", "implementation", "relevant legislation"], "requirements": {"degrees": [], "majors": [], "languages": [], "language_level": [], "hard_skills": ["dynamic"], "soft_skills": ["dynamic", "innovative"], "languages_combined": []}, "experience_required": {"duration": [], "field": []}}, {"job_id": "100003009051291", "location_code": "hk", "company": "Hutchison Telecommunications (Hong Kong) Limited", "job_title": "Human Resources Manager", "description": "Being a prominent player in the communications industry and a member of CK Hutchison Holdings, we are looking for HR practitioners who have genuine interest in helping an organization and the peoples within, to grow and succeed.\u00a0 Depending on your strengths and career orientation, here is a chance to develop in our HR Team, commensurate with your experiences and potentials.\n\nCheck out the followings. Let us know your strengths and interests to contribute in our evolution journey.\n\nDiscover Yourself\nAttributes that will earn your early success here\n\n\neager to learn and grow\nwilling to share and contribute\nkeen to raise new ideas and different perspectives\nready to take up new challenges\n\nDiscover Your Job Opportunities\nUnleash your potential and stay ahead! Here you can...\n\nperform a BP role for individual career development i.e. staffing, talent acquisition, employee caring & engagement, training & development, and/or HR analytics, etc.\nliaise with business units and provide advices on all staffing matters (e.g. manpower requirements, staffing needs, etc)\u00a0\nwork closely with team members to deliver excellent HR services while enriching HR functional skills through involvement in projects\ngain cross HR functional exposures to build up networking and holistic knowledges, say in talent sourcing, staff activities, job evaluation, total rewards exercises, etc.\nbe a resilient individual ready to take up challenges in a dynamic yet rewarding industry for next career advancement\n\nDiscover More\nApart from the unique opportunity to fast track your career here, you will enjoy competitive remuneration package, attractive employee benefits such as free company shuttle, free company SIM card and preferential SIM plan offers, comprehensive medical & insurance schemes, as well as full range of other employee well-being provisions.\u00a0\u00a0\n\nInterested parties, please send\u00a0in your profile and salary expectation to connie.chong@ hthk.com\n\nWe are an equal opportunity employer and welcome applications from all qualified candidates. Personal data collected will be treated in the strictest confidence and handled confidentially by authorised personnel for recruitment-related purposes only within the CK Hutchison Group of companies. The personal data of unsuccessful applicants will be destroyed after the recruitment exercise pursuant to the requirements of the Personal Data (Privacy) Ordinance in Hong Kong.", "employment_types": ["Full Time", "Permanent"], "selling_points": [], "locations": ["Kwai Tsing Area"], "categories": ["Admin & HR", "Compensation & Benefits", "Recruitment / Executive Search", "Training & Development"], "post_time": "2022-01-15T07:19:00Z", "salary": {"currency": null, "max": null, "min": null, "period": "monthly", "term": null}, "salary_visible": false, "title_keywords": ["manager", "human resources"], "responsibilities": ["provide advices", "ideas", "evaluation", "hr", "develop", "plan", "career development", "liaise with", "insurance"], "requirements": {"degrees": [], "majors": [], "languages": [], "language_level": [], "hard_skills": ["dynamic"], "soft_skills": ["keen", "unique", "eager to learn", "dynamic", "comprehensive", "genuine"], "languages_combined": []}, "experience_required": {"duration": [], "field": ["hr", "team"]}}, {"job_id": "100003009048839", "location_code": "hk", "company": "HKT", "job_title": "Human Resources Lead \u2013 Global Payroll", "description": "Your Role:\n\nCreate scalable payroll strategies, processes, refining current overseas payroll operations to streamline and automate processes to ensure consistency, accuracy, and best-in-class services\nEnsure accurate and timely processing of payroll, payroll funding, tax filing on a pay period and ongoing basis\nBuild, lead, develop and mentor a payroll team\nPartner closely with internal partners (HRSS, Finance, overseas country HR) to deliver pay experience to our employees\nLead payroll development and implementation process for all overseas entities, as needed\nManage the day-to-day payroll operations in all areas, coordinating with payroll providers to achieve the processing of payroll within all regulatory, labor and tax guidelines\nBuild and maintain employee confidence and trust by setting up process for promptly responding to requests, developing clear communications, and protecting the confidentiality of payroll operations\nManage the operational aspects of the payroll function including overseas vendor invoices, service level agreements, vendor contract, etc.\nManage Hong Kong final payment process\nOperate with a strategic mindset of continuous performance improvement to streamline and automate as opportunities arise\n\nTo succeed in your role:\n\nDegree holder with 6 years of hands-on experience in regional payroll\nDeep knowledge and experience with payroll vendors\nExperience to handle payroll transformation projects\nDetailed oriented, deadline driven and work well under pressure with a high degree of accuracy\nStrong communication skills, ability to comfortably interact with employees of all levels of experience and seniority, across the organization\n\n\n\u6709\u610f\u7533\u8acb\u8005\u8acb\u6309 APPLY NOW\u7533\u8acb \u00a0\u00a0\u00a0\n\n", "employment_types": ["Full Time"], "selling_points": [], "locations": ["Not Specified"], "categories": ["Admin & HR", "Compensation & Benefits", "HR Director / Manager", "Training & Development"], "post_time": "2022-01-14T07:23:57Z", "salary": {"currency": null, "max": null, "min": null, "period": "monthly", "term": null}, "salary_visible": false, "title_keywords": ["lead", "human resources"], "responsibilities": ["tax", "invoices", "guidelines", "operations", "hr", "tax filing", "implementation", "developing", "develop", "communication", "maintain", "payment process", "payroll"], "requirements": {"degrees": ["degree", "degree holder"], "majors": [], "languages": [], "language_level": [], "hard_skills": ["processing", "vendor"], "soft_skills": ["communication skills", "confidence", "detailed oriented", "under pressure", "timely", "deep", "clear", "hands-on", "accurate", "driven"], "languages_combined": []}, "experience_required": {"duration": ["6 years"], "field": ["finance", "hr", "payroll"]}}, {"job_id": "100003009048288", "location_code": "hk", "company": "Social Big Data Limited", "job_title": "Senior HR Executive", "description": "Job responsibilities\n\nHandle full spectrum of HR functions including recruitment, C&B, performance management, employee relations and training\u00a0\nDevelop and execute HR initiatives and programs to support the business needs\nResponsible for HR data analysis and reports and ensure compliance are met in all HR areas\nAdminister monthly payroll, attendance and leave management, insurance and pension scheme, and tax returns\nResponsible for market salary survey and annual salary review\u00a0\nParticipate in ad-hoc tasks and other HR related projects as required\nJob\u00a0Requirement\n\nDegree holder in\u00a0Business Administration/HR Management or related disciplines\nMinimum 5 years of HR & Admin experience\n\nExcellent leadership with practical knowledge and strong problem-solving skills\nSound knowledge in HK Employment Ordinance and related regulations and laws\nSelf-motivated and proactive with good communication and interpersonal skills\nGood command of written and spoken English and Chinese\nShort notice period or immediate available is highly preferred\nCV without expected salary will not be considered\n\n", "employment_types": ["Full Time", "Permanent"], "selling_points": ["5+ years\u2019 experience of working", "All round HR & Admin Experience", "5-day work week, Flexible Working Hour"], "locations": ["Kwun Tong"], "categories": ["Admin & HR", "Compensation & Benefits", "HR Supporting Staff", "Recruitment / Executive Search"], "post_time": "2022-01-14T06:08:52Z", "salary": {"currency": null, "max": null, "min": null, "period": "monthly", "term": null}, "salary_visible": false, "title_keywords": ["hr", "executive"], "responsibilities": ["tax", "attendance", "management", "hr", "review", "ad-hoc tasks", "develop", "data analysis", "ensure compliance", "recruitment", "reports", "insurance", "payroll"], "requirements": {"degrees": ["degree holder"], "majors": ["related disciplines", "business administration"], "languages": ["english", "chinese"], "language_level": ["good command"], "hard_skills": ["problem-solving skills"], "soft_skills": ["self-motivated", "communication and interpersonal skills", "problem-solving skills", "proactive", "leadership"], "languages_combined": [{"language": "english", "language_level": ["good command"]}, {"language": "chinese", "language_level": ["good command"]}]}, "experience_required": {"duration": ["minimum 5 years"], "field": ["hr", "admin"]}}, {"job_id": "100003009051023", "location_code": "hk", "company": "The Wharf Group", "job_title": "Assistant Human Resources Manager (Talent Acquisition)", "description": "The incumbent will\u00a0be involved in talent acquisition, e-performance management, employee engagement and CSR reports preparation consolidation.\u00a0\u00a0The ideal candidates\u00a0should be / possess :\n\nDegree holders in Human Resources Management or related disciplines preferred with grade C or above in English Language (Syl. B) of HKCEE or A Level Examination\n6 - 8 years\u2019 relevant experience gained at sizable organizations with exposure/experience in e-recruitment and e-performance management would be advantageous\u00a0\nsound knowledge on HK Employment Ordinance and other employment related ordinances\na team player with strong common sense, positive attitude and excellent integrity\nproactive,\u00a0organized, responsible, detail-minded and able to deliver timely and quality work under pressure and tight deadlines\ngood communication and presentation skills and highly proficient in written and spoken English and Chinese\nproficient in Excel and other Microsoft Office applications\n\nCandidates with less experience will be considered as Human Resources Officer / Senior Officer.\n\nWe work 5 days per week.\n\nInterested parties, please click \"APPLY NOW\" and attach with your application letter and full resume.\n\nFor further information of the Wharf Group, please visit our website: www.wharfholdings.com\u00a0", "employment_types": ["Full Time", "Permanent"], "selling_points": [], "locations": ["Tsim Sha Tsui"], "categories": ["Admin & HR", "Compensation & Benefits", "HR Supporting Staff", "Recruitment / Executive Search"], "post_time": "2022-01-15T01:13:31Z", "salary": {"currency": null, "max": null, "min": null, "period": null, "term": null}, "salary_visible": false, "title_keywords": ["assistant human resources manager"], "responsibilities": ["management", "quality", "communication", "recruitment", "reports", "work under pressure"], "requirements": {"degrees": ["degree"], "majors": ["related disciplines"], "languages": ["english", "chinese"], "language_level": ["proficient", "good"], "hard_skills": ["excel", "c", "microsoft office"], "soft_skills": ["detail-minded", "organized", "responsible", "work under pressure", "timely", "integrity", "positive attitude", "communication", "presentation skills", "team player", "proactive", "ideal"], "languages_combined": [{"language": "english", "language_level": ["proficient", "good"]}, {"language": "chinese", "language_level": ["proficient", "good"]}]}, "experience_required": {"duration": ["6 - 8 years"], "field": ["recruitment", "performance management", "relevant experience", "human resources"]}}, {"job_id": "100003009047794", "location_code": "hk", "company": "BIPO Service North Asia Limited", "job_title": "Payroll Specialist/Officer - C&B", "description": "We are looking for a talent who is keen on developing his / her career in Human Resources, to join our award-winning payroll team.\n\nIn BIPO, our team are comprised of HR professionals who have both in-house HR and service vendor experience, are passionate about Human Resources Management - C&B, Labour Law, Training & Development, Recruitment, etc. and most important we are also proud to be an\u00a0evangelist of HR Technology!\n\nThis position is required to provide accurate, timely and efficient payroll services including but not limited to payroll calculation, preparation of payroll related data, statistics, and other reports from BIPO\u2019s system to the clients.\u00a0 As a Payroll Specialist, he / she will also assist in the provision of an advisory and consultancy service to BIPO\u2019s clients (on-site payroll HR Admin. support may be required) on a range of payroll related matters.\n\nKey responsibilities:\n\nEnsure the operational aspects of payroll processing and associated activities, including salary disbursement, over-payment recovery, leave management and reporting are accurate and delivered within appropriate time frames and comply with relevant legislation\nPrepare complex payroll and human resource information for data input and assist with checking, quality control and maintenance of records to ensure accuracy, service quality and data integrity.\nAssist our customer to meet its taxation, superannuation and other legislative and statutory obligations through processing and preparation of returns, related reports, forms and other documentation as requested.\nProvide a responsive, accurate client advisory service on payroll matters, resolve difficult enquiries and assist in identifying payroll errors and implementing corrective action where required to ensure employee payments are processed accurately and database integrity is maintained.\nProvide and promote service excellence and foster effective teamwork and business relationships.\nContribute to process improvement for customers by participating in a range of payroll and service delivery reform activities.\nAct as the key account coordinator for client communication at operations level\nProvide On-site C&B / Payroll support to new or existing clients on ad-hoc basis\n\nProfessional requirements:\n\nDiploma or degree in Human Resources Management, Business Administration or any other related disciplines\nMinimum 2 years of relevant C&B experience, particularly in payroll execution.\nProficiency in spoken and written English and Chinese\nProficiency in MS Office applications, especially strong in MS Excel\nAttention to detail and high sense of accuracy\nProven ability to handle large volume headcount payroll\nExperience in use of HRIS is preferred\nFamiliar with Employment Ordinances, tax regulation and MPF Schemes Ordinance\nProven ability to meet deadlines and identify and deal with problems\nA quick learner; able to work independently and self-driven with a strong sense of commitment\nCandidate with more experience can be considered as Senior Payroll Specialist\n\nWhat\u2019s on offer\n\nAttractive salary package\n5-day work week\nAttractive remuneration package including 13-month salary, annual leave, medical and dental insurance benefit, birthday leave\nOn-the-job training", "employment_types": ["Full Time", "Permanent"], "selling_points": ["Min. 2 years of HR related experience", "Hand on payroll, C&B, HRIS exp is preferred", "Double pay, Medical, Bonus"], "locations": ["Tsuen Wan Area"], "categories": ["Admin & HR", "Clerical / Admin Staff", "Compensation & Benefits", "HR Supporting Staff"], "post_time": "2022-01-14T03:57:56Z", "salary": {"currency": null, "max": null, "min": null, "period": "monthly", "term": null}, "salary_visible": false, "title_keywords": ["specialist", "officer"], "responsibilities": ["ad-hoc", "data", "operations", "quality", "communication", "payment", "database", "service delivery", "reports", "reporting", "management", "checking", "documentation", "payroll", "taxation", "maintenance", "data input", "relevant legislation", "payments", "quality control"], "requirements": {"degrees": ["diploma", "degree"], "majors": ["related disciplines", "business administration"], "languages": ["english", "chinese"], "language_level": ["proficiency"], "hard_skills": ["ms excel", "ms office"], "soft_skills": ["work independently", "quick learner", "attention to detail", "meet deadlines", "driven"], "languages_combined": [{"language": "english", "language_level": ["proficiency"]}, {"language": "chinese", "language_level": ["proficiency"]}]}, "experience_required": {"duration": ["minimum 2 years"], "field": ["payroll"]}}, {"job_id": "100003009043836", "location_code": "hk", "company": "The Beauty Company Limited", "job_title": "Human Resources Officer (C&B)", "description": "Responsibilities:\n\nProvide all rounded clerical and administrative support;\nPrint and distribute HR statements or letters to staff;\nHandle full spectrum of C&B functions and provide comprehensive HR services in a professional manner;\nPerform C&B function e.g. monthly payroll, tax filing, MPF, insurance administration and benefits review;\nTo ensure the payroll and other payroll-related matters are proceeded with sufficient documentation and in compliance with company policies and Employment Ordinance;\nPrepare various routine and ad-hoc HR data and analytics reports for management review;\nProvide advice to superiors and answer general staff inquires regarding compensation & benefits;\nSupport the team in other HR duties as assigned.\n\nRequirements:\n\nDegree holder in Human Resources Management or other relevant disciplines\nMinimum 3 years\u2019 relevant experience in beauty industry and working experience in payroll and MPF administration\nExperience in work injury (e.g. Form 2, 2A) handling will be an advantage\nWell versed in Employment Ordinances and other relevant law and regulations\nExcellent skill in Excel and other PC skills, including Chinese word processing\nProficient in both English and Chinese\nGood numerical skills, Detail-minded and committed\nAble to work under pressure, mature and independent\nImmediate available is an advantage\n\nPlease apply in confidence with\u00a0full resume, expected salary and availability\u00a0by clicking \u201cApply Now\u201d button.\n\nYou are invited to visit our website at: https://www.thebeauty.hk\n\nThe information provided will be used for selection purpose only. All information of unsuccessful applicants will be destroyed within six months.", "employment_types": ["Full Time", "Permanent"], "selling_points": ["Immediate available is an advantage", "Minimum 3 years\u2019 relevant experience", "Focus in C&B, payroll and MPF administration"], "locations": ["Shatin Area"], "categories": ["Admin & HR", "Compensation & Benefits"], "post_time": "2022-01-13T02:07:38Z", "salary": {"currency": null, "max": null, "min": null, "period": "monthly", "term": null}, "salary_visible": false, "title_keywords": ["human resources officer"], "responsibilities": ["hr", "letters", "professional manner", "administrative support"], "requirements": {"degrees": [], "majors": [], "languages": [], "language_level": [], "hard_skills": [], "soft_skills": [], "languages_combined": []}, "experience_required": {"duration": [], "field": []}}, {"job_id": "100003009046266", "location_code": "hk", "company": "ConnectedGroup Limited", "job_title": "Compensation & Benefits Manager (retail)", "description": "My client is a renowned retail group looking for an independent and strategic C&B talent to join their growing team at their Hong Kong Headquarter.\n\nGroup role\nProject focused C&B\nNewly created position\n\nThe role\n\nReporting to the Head of C&B, you will be responsible for all strategic C&B related projects targeted to both corporate and frontline employees across the region. You will take initiative in proposing and implementing C&B strategies that align with the business vision strengthening its market competitiveness. This incumbent will manage annual practices working closely with external vendors on salary benchmarking and review, budgeting, market survey, etc. You will proactively asses and revamp current policies and benefits as needed to ensure it compliance with local labor law. Ad Hoc projects will be assigned as needed.\n\nThe candidate\n\nDegree qualification or above with a minimum of 6 years of strategic compensation & benefits experience, solid exposure dealing with complex C&B retail philosophy.\nDetail oriented and strong numerical sense\nHighly adaptable with ability to thrive in a fast-paced environment\nConfident and independent with excellent communication skills and business savvy.\nKnowledge using SAP is a must\nFluency in English is a must, Cantonese, and Mandarin.\n\nInterested parties, please apply the job online or contact Eunice Lei Ho directly via eunice.leiho@connectedgroup.com for more information. Please note that only short-listed candidates will be notified. All information gathered will be treated in strict confidence and solely used for recruitment purposes.", "employment_types": ["Full Time", "Permanent"], "selling_points": ["Group role", "Project focused C&B", "Newly created position"], "locations": ["Not Specified"], "categories": ["Admin & HR", "Compensation & Benefits"], "post_time": "2022-01-13T10:09:52Z", "salary": {"currency": null, "max": null, "min": null, "period": "monthly", "term": null}, "salary_visible": false, "title_keywords": ["manager"], "responsibilities": ["reporting", "review", "budgeting"], "requirements": {"degrees": [], "majors": [], "languages": [], "language_level": [], "hard_skills": [], "soft_skills": ["independent", "initiative", "focused", "responsible"], "languages_combined": []}, "experience_required": {"duration": [], "field": []}}, {"job_id": "100003009045865", "location_code": "hk", "company": "Bank of China (Hong Kong) Limited", "job_title": "Human Resources Manager (C&B)", "description": "Responsibilities:\nDevelop and maintain group-wide human resources strategies, HR budget, C&B schemes and\u00a0 remuneration policies, and especially participate in the management of Southeast Asia subsidiaries, including:\nReview, analyze, and co-ordinate the manpower planning of the Southeast Asia subsidiaries\nAnnual HR budgeting and allocation in accordance with the group\u2019s manpower strategy, bonus and salary review plans, and annual bonus and salary review budgeting and allocation\nStudy, formulate and execute the HR budget control mechanism\nStudy, establish and maintain rewards management policies and staff wellness programs\nConduct due diligence on Southeast Asia subsidiaries\u2019 C&B policies and management initiatives\nConduct job matching and participate various compensation and benefits surveys in both HK and Southeast Asia\nStudy, establish and maintain human resources management mechanism\nOther ad-hoc projects\nRequirements:\nDegree with major in Human Resources Management, Finance and Economics, Accounting, Business Administration or relevant discipline\nAt least 3-4 years working experience in C&B, preferably in regional bank\nFamiliar with statutory and compliance requirements including Employment Ordinance and other relevant laws and regulations for Hong Kong and Southeast Asia\nGood analytical, presentation and communication skills required\nExcellent Chinese and English writing skills required and preferably fluent in Mandarin and English speaking", "employment_types": ["Full Time"], "selling_points": ["-", "-", "-"], "locations": ["Others"], "categories": ["Admin & HR", "Compensation & Benefits"], "post_time": "2022-01-13T08:58:01Z", "salary": {"currency": null, "max": null, "min": null, "period": "monthly", "term": null}, "salary_visible": false, "title_keywords": ["manager", "human resources"], "responsibilities": ["due diligence", "management", "policies", "hr", "budget", "review", "budgeting", "develop", "maintain", "plans", "budget control", "planning"], "requirements": {"degrees": [], "majors": [], "languages": [], "language_level": [], "hard_skills": [], "soft_skills": [], "languages_combined": []}, "experience_required": {"duration": [], "field": []}}, {"job_id": "100003009033565", "location_code": "hk", "company": "MUJI (Hong Kong) Company Limited", "job_title": "Assistant Human Resources Manager, Compensation & Benefits", "description": "Responsibilities\n\nResponsible for full spectrum of compensation and benefits functions including but not limited to payroll, MPF and taxation administration\nPlan, execute and monitor various annual exercises, including annual review exercise, incentive and bonus schemes, performance management, etc.\nReview the current HRIS workflow, implement system enhancement and set key business processes to ensure the system stability\nProvide the business insights on the market trend on Compensation & Benefits and ensure the salary package is competitive in the market\nReview and implement HR policies and program to support business growth\nConduct market survey regularly for providing business insights on the market pay trend in order to ensure the salary packages competitiveness\nPrepare HR budget, forecast and various analytical reports for management review\nAssist in other ad hoc projects as assigned\n\nRequirements\n\nDegree holder in Human Resources or related disciplines\nMinimum 6 years of work experience in compensation and benefits function of retail or food & beverage industry, in which 3 years should be in managerial level\nIndependent, able to work under a fast pace environment and meet tight deadlines\nStrong analytical skill and numerical sense\nExcellent planning and organization skills\nHigh proficiency in MS Office and Chinese Word Processing\nGood command in spoken and written English and Cantonese\nCandidate with less experience will be considered as Senior Human Resources Officer\n\n\u00a0A competitive package and promising career prospect will be offered to the right candidate. Interested parties please send detailed resume with expected salary and availability by clicking \"Apply Now\" to submit your application.\n\n\n\nThe personal data collected will be treated in strict confidence and used for recruitment-related purpose only. Applicants who are not invited for interview within\u00a04 weeks may consider their applications unsuccessful.\u00a0 All personal data of unsuccessful candidates will be destroyed after 6 months.\n\nMUJI (Hong Kong) Company Limited\u00a0is an equal opportunities employer.", "employment_types": ["Full Time", "Permanent"], "selling_points": ["Full spectrum of C&B functions & HRIS enhancement", "Able to work in a fast pace business environment", "Passion for retail and food & beverage industry"], "locations": ["Tsim Sha Tsui"], "categories": ["Admin & HR", "Others", "Compensation & Benefits", "HR Director / Manager"], "post_time": "2022-01-10T01:03:58Z", "salary": {"currency": null, "max": null, "min": null, "period": "monthly", "term": null}, "salary_visible": false, "title_keywords": ["assistant human resources manager"], "responsibilities": [], "requirements": {"degrees": [], "majors": [], "languages": [], "language_level": [], "hard_skills": [], "soft_skills": [], "languages_combined": []}, "experience_required": {"duration": [], "field": []}}, {"job_id": "100003009043081", "location_code": "hk", "company": "Waihong Environmental Services Limited", "job_title": "Human Resources Officer (Ref: HC0101)", "description": "Responsibilities:\n\n\nResponsible for all rounded human resources functions including but not limited to payroll, compensation & benefits administration, leave administrations and staff relations\nProvide HR support to managers on staff related issues\nAssist in reviewing or formulating HR strategies, policies and procedures\nPrepare reports and analysis for management review\nHandle ad-hoc projects as assigned\n\nRequirements:\n\n\nDegree\u00a0holder in Human Resources Management or related disciplines\nPossess\u00a03 years\u2019 relevant experience in sizeable organizations\nWell-versed in Employment Ordinance and related legislations\nAble to work independently with strong sense of responsibility as well as good time management\nProactive, multi-tasked and able to work in fast-paced environment\nSound communications and interpersonal skills with staff of all levels\nGood command of written and spoken English & Chinese\nExperience in using IPL is an advantage\nImmediate available will be highly preferred\nWe treasure human resources as our most valuable asset. We offer 5-day work week, attractive remuneration package and career advancement opportunities to the right candidate. Interested parties please send full resume with your present and expected salary by one of the following means:\n\n\nEmail:\u00a0Click 'Apply Now'\u00a0or whhr @waihong.com.hk\nFax: \u00a0\u00a0\u00a02786 8563\nMail:\u00a0 \u00a0Unit 813, 8/F, Chevalier Commercial Centre, 8 Wang Hoi Road, Kowloon Bay, Kowloon\n\nPlease quote our reference no. on envelope / fax cover / subject line of the email.\nWaihong is an equal opportunity employer and welcomes applications from all qualified candidates. Personal data provided by job applicants will be used strictly in accordance with the employer's personal data policies, a copy of which will be provided immediately upon request.", "employment_types": ["Full Time", "Permanent"], "selling_points": [], "locations": ["Kowloon Bay"], "categories": ["Admin & HR", "Clerical / Admin Staff", "Compensation & Benefits", "HR Supporting Staff"], "post_time": "2022-01-13T08:21:17Z", "salary": {"currency": null, "max": null, "min": null, "period": "monthly", "term": null}, "salary_visible": false, "title_keywords": ["human resources officer"], "responsibilities": ["policies", "hr", "analysis", "procedures", "prepare reports", "ad-hoc projects", "payroll", "human resources functions", "management review", "administration"], "requirements": {"degrees": ["degree holder"], "majors": ["related disciplines"], "languages": ["english", "chinese"], "language_level": ["good command"], "hard_skills": ["ipl"], "soft_skills": ["work independently", "proactive", "sense of responsibility", "multi-tasked", "work in fast-paced environment", "interpersonal skills", "time management"], "languages_combined": [{"language": "english", "language_level": ["good command"]}, {"language": "chinese", "language_level": ["good command"]}]}, "experience_required": {"duration": ["3 years"], "field": ["relevant experience"]}}, {"job_id": "100003009043290", "location_code": "hk", "company": "Hong Kong Gallop Express Limited", "job_title": "Senior HR Officer (C&B focus)", "description": "Responsibilities:\nHandle full spectrum of HR functions including but not limited to recruitment and selection, personnel file and HR record, payroll, MPF, tax return, leave record, employee compensation and performance management\n\u00a0Assist in the establishment and execution of HR policies & procedures aligned with HK Law\nCreate and maintain employee data records and personnel documents\nAssist all general office administration\nRequirements:\nDiploma holder in human resources management or related disciplines\n5-6 years\u2019 experience in HR field, F&B and retail experience is highly preferred\nWell versed in Employment Ordinance and other HR related ordinances in Hong Kong; equip with HR practices in Mainland China is an advantage\nGood communication and presentation skills with proficiency in English, Chinese and Mandarin\nProficient in MS Word, Excel, Outlook, Powerpoint and Chinese Word Processing\nResponsible, self-motivated, well organized and detail-minded\nImmediate available is preferred\nBenefits\n\nCompetitive salary package\nVarious caring leave types\nGreat learning and career development platform\nExcellent working environment\n\n\nInterested parties please send your CV with current and expected package, as well as date of availability to us for selection by clicking \u201cApply Now\u201d. All information collected would be used for recruitment purpose only. Application process may take 2 to 3 weeks; candidates would not be considered, should there be no contact within 6 weeks.", "employment_types": ["Full Time", "Permanent"], "selling_points": ["C&B Focus", "Well-versed in Employment Ordinance", "Attractive package"], "locations": ["Kowloon Bay"], "categories": ["Admin & HR", "Compensation & Benefits"], "post_time": "2022-01-12T10:29:56Z", "salary": {"currency": null, "max": null, "min": null, "period": "monthly", "term": null}, "salary_visible": false, "title_keywords": ["hr officer"], "responsibilities": ["tax", "management", "mpf", "data", "policies", "hr", "office administration", "procedures", "maintain", "recruitment", "payroll"], "requirements": {"degrees": ["diploma holder"], "majors": ["related disciplines"], "languages": ["english", "chinese", "mandarin"], "language_level": ["proficient", "proficiency", "good"], "hard_skills": ["excel", "chinese word processing", "powerpoint", "outlook", "ms word"], "soft_skills": ["detail-minded", "self-motivated", "responsible", "well organized", "communication", "presentation skills"], "languages_combined": [{"language": "english", "language_level": ["proficiency", "good"]}, {"language": "chinese", "language_level": ["proficient", "proficiency", "good"]}, {"language": "mandarin", "language_level": ["proficiency", "good"]}]}, "experience_required": {"duration": ["5-6 years"], "field": ["hr", "f&b", "retail"]}}, {"job_id": "100003009046747", "location_code": "hk", "company": "Build King Holdings Ltd", "job_title": "Assistant Human Resources Officer / Human Resources Assistnat (1 year Contract) (Ref:JD/AHRO)", "description": "Key Responsibilities:\n\nContribute to and ensure payroll process services quality are delivered in high quality timely manner;\nHandle general enquiries and liaise with internal and external parties;\nPreparing data and analysis to support key initiatives and projects;\nUpdate and maintain human resources records and reports;\nProvide all-round administrative support to HR department;\nPerform ad-hoc tasks as required.\n\nRequirements:\n\nHigher Diploma or above in Human Resources Management or related discipline;\nExperience in payroll process is an advantage;\nGood communication skills, proactive, strong sense of responsibility, attention to details and able to work independently;\nProficiency in Microsoft Office (PowerPoint, Excel, Word and Chinese Word Processing) is a must;\nGood command of both written and spoken English and Chinese;\nWell-versed with Hong Kong Employment Ordinance and other related ordinances;\nImmediate available is preferable.\n\nPlease send your application with full resume and expected salary to\u00a0Human Resources Manager,\u00a0Human Resources Department, 6/F, Tower B, Manulife Financial Centre, 223 Wai Yip Street, Kwun Tong, Kowloon, Hong Kong\u00a0or\u00a0by clicking \"Apply Now\".\n\nShuttle bus of the building is available at Lam Tin and Kwun Tong MTR Station.\n\nPlease visit our website www.buildking.hk for more details.\n(Personal data collected will be used for recruitment-related purposes only.)\n\nContribute to and ensure payroll process services quality are delivered in high quality timely manner;%MCEPASTEBIN%", "employment_types": ["Full Time", "Contract"], "selling_points": ["Contribute to payroll process services", "Update and maintain human resources records", "Provide all-round administrative support"], "locations": ["Kwun Tong"], "categories": ["Admin & HR", "Others", "Compensation & Benefits", "HR Supporting Staff"], "post_time": "2022-01-14T00:41:21Z", "salary": {"currency": null, "max": null, "min": null, "period": "monthly", "term": null}, "salary_visible": false, "title_keywords": ["assistant human resources officer", "human resources"], "responsibilities": ["data", "administrative support", "analysis", "internal and external parties", "quality", "hr", "ad-hoc tasks", "maintain", "reports", "liaise with", "payroll"], "requirements": {"degrees": ["higher diploma or above"], "majors": [], "languages": ["english", "chinese"], "language_level": ["proficiency", "good command"], "hard_skills": ["excel", "chinese word processing", "hong kong employment ordinance", "microsoft office", "word", "powerpoint"], "soft_skills": ["communication skills", "work independently", "sense of responsibility", "timely", "attention to details", "proactive"], "languages_combined": [{"language": "english", "language_level": ["good command"]}, {"language": "chinese", "language_level": ["proficiency", "good command"]}]}, "experience_required": {"duration": [], "field": ["payroll"]}}, {"job_id": "100003009048901", "location_code": "hk", "company": "Asia Satellite Telecommunications Co Ltd", "job_title": "Manager, Human Resources & Administration", "description": "Job Highlights:\n\nSupport to manage full spectrum of Human Resources services covering the employment life cycle including but not limit to talent acquisition, on boarding & off-boarding, compensation and benefits, maintenance of HRIS, implementation of HR policies and other HR projects.\n\nResponsibilities:\n\nResponsible for all-rounded recruitment including from understanding the hiring needs, screening resumes, interview candidates, job offering to on-boarding arrangement, visa application and renewal\nAdminister all aspects of compensation & benefits administration including but not limited to monthly payroll, ORSO/MPF, tax returns, leave management, group medical and life insurance scheme and etc.\nResponsible for annual exercises include manpower planning, annual budget, performance management, salary and bonus review\nProvide professional advice to line managers on the employee issues and counsel employees in relation to conditions of employment\nEnsure efficient and smooth day to day HR operation is in compliance with HR policies and statutory requirements\nAssist in the\u00a0review, development and implementation of company policies / procedures pertaining to the Human Resources & Administration function as well as the review of workflow and make recommendations for continuous enhancement\nLead and supervise a small Admin. Team to provide all round office support including but not limited to procurement of office equipment and office consumables, office renovation, facilities maintenance and etc.\n\nRequirements:\u00a0\n\nBachelor degree in\u00a0Human Resources Management or related discipline\nMinimum 8 years' relevant experience in sizable establishments of which 3 years at managerial level\nWell versed in Hong Kong, China and other AP countries employment law is preferred\nGood command of written & spoken English & Chinese including Putonghua\nProficient in MS Office including Word, Excel, PowerPoint and Visio. Experience in using Vlookup and Pivot Table are essential\nSelf-starter who works well independently, able to articulate to all business levels and build strong rapport with internal stakeholders\nHighly organized, detail-minded, multi-tasking and able to meet tight deadlines\nA good team player with positive, proactive and flexible in approach, strong capability in problem-solving and drive for excellence\nImmediate available is highly preferred\nWork location in Tai Po, shuttle bus will be provided from Admiralty, Kowloon Tong and Tai Po Market Station\n\nA competitive package will be offered to the right candidate.\u00a0 Interested parties please send us your resume with current and expected salary to Human Resources Department by clicking \"APPLY NOW\".\n\nAsiaSat is an Equal Opportunities Employer. \u00a0Personal data collected will be used for recruitment purpose only.\u00a0", "employment_types": ["Full Time", "Permanent"], "selling_points": ["Manage full spectrum of Human Resources services", "Min 8 years' experience in sizable establishment", "Immediate available is highly preferred"], "locations": ["Tai Po Area"], "categories": ["Admin & HR", "Compensation & Benefits", "HR Director / Manager", "Recruitment / Executive Search"], "post_time": "2022-01-14T07:40:24Z", "salary": {"currency": null, "max": null, "min": null, "period": "monthly", "term": null}, "salary_visible": false, "title_keywords": ["manager", "human resources"], "responsibilities": ["budget", "renovation", "statutory requirements", "administration", "make recommendations", "compliance", "implementation", "office support", "management", "mpf", "review", "procedures", "screening resumes", "payroll", "tax", "maintenance", "policies", "hr", "recruitment", "insurance", "planning"], "requirements": {"degrees": ["degree", "bachelor"], "majors": [], "languages": ["putonghua", "english", "chinese"], "language_level": ["good command"], "hard_skills": ["ap", "excel", "pivot table", "problem-solving", "word", "powerpoint", "vlookup", "ms office"], "soft_skills": ["detail-minded", "organized", "meet tight deadlines", "independently", "good team player", "flexible", "problem-solving", "multi-tasking", "articulate", "proactive", "positive"], "languages_combined": [{"language": "putonghua", "language_level": ["good command"]}, {"language": "english", "language_level": ["good command"]}, {"language": "chinese", "language_level": ["good command"]}]}, "experience_required": {"duration": ["3 years", "minimum 8 years"], "field": ["managerial", "relevant experience"]}}, {"job_id": "100003009043278", "location_code": "hk", "company": "Urban Group", "job_title": "Human Resources Officer", "description": "Responsibilities:\n\nTo provide one-stop human resources solutions to Operations\nHandle all round HR functions including the processing of compensation & benefits, staff recruitment, movement and ad hoc projects\nUpdate and maintenance of HR system and prepare reports on a regular basis\n\nRequirements:\n\nDegree or above in Human Resources Management or related disciplines\nAt least 3 years\u2019 working experience in all-rounded human resources functions including payroll administration\u00a0\nAttention to detail, organized, result-oriented, analytical and methodical\nIndependent, takes the initiative & ownership for completing assignments to a high standard and able to meet tight deadlines\nExcellent verbal and written communication skills in both English & Chinese\nGood in computer skills such as Microsoft Office and Chinese word processing\n\nInterested parties please\u00a0send\u00a0application letter with detailed resume, current and expected salary to\u00a0Group Manager \u2013 Human Capital & Training\u00a0through one of the following means:\n\nMail:\u00a016/F., Chevalier Commercial Centre,8 Wang Hoi Road,\u00a0\u00a0Kowloon Bay,Kowloon,Hong Kong\n\nEmail: Click 'Apply Now'\n\n\nAll personal data collected will be used for employment-related purposes only.", "employment_types": ["Full Time", "Permanent"], "selling_points": [], "locations": ["Kowloon Bay"], "categories": ["Admin & HR", "Others", "Compensation & Benefits", "HR Supporting Staff"], "post_time": "2022-01-12T10:27:36Z", "salary": {"currency": null, "max": null, "min": null, "period": "monthly", "term": null}, "salary_visible": false, "title_keywords": ["human resources officer"], "responsibilities": ["operations"], "requirements": {"degrees": [], "majors": [], "languages": [], "language_level": [], "hard_skills": [], "soft_skills": [], "languages_combined": []}, "experience_required": {"duration": [], "field": []}}, {"job_id": "100003009042062", "location_code": "hk", "company": "CEMG Management Limited", "job_title": "Senior Human Resources Officer (C&B focus)", "description": "Responsibilities:\n\nPerform\u00a0all rounded HR Generalist duties major in compensation & benefits and daily operations\nMainly focus on handle MPF administration, taxation, payroll calculation and prepare final payment\u00a0\u00a0\nAdministrate monthly payroll for the companies\nCompile regular HR related statistics and reports for management review\nKnowledge in inestablishing and enhancing HR systems is an advantage\nParticipate\u00a0in ad hoc duties as assigned\n\nRequirements:\n\nDegree in Human Resources Management or related disciplines\nAt least 5 years solid experience in Human Resources, preferably in\u00a0beauty, healthcare, retail industry\nWell versed in Hong Kong Employment Ordinance and other HR related ordinances\nPositive thinking, attentive to details, independent and good team-player\nGood interpersonal and communication skills\nProficient in MS Word, Excel, PowerPoint and Chinese Word Processing\nGood commend in both written and spoken English & Chinese\nImmediate available is highly preferred\n\nWe offer a competitive remuneration package including excellent career prospects to the right candidate. Interested parties please click \"Quick Apply\" now.\n\nAll data collected will be used for recruitment purpose only.", "employment_types": ["Full Time", "Permanent"], "selling_points": ["5 days work", "Exp in Retail / Beauty / Healthcare industry", "Immediate Available"], "locations": ["Tin Hau"], "categories": ["Admin & HR", "Others", "Compensation & Benefits", "HR Supporting Staff"], "post_time": "2022-01-12T05:48:14Z", "salary": {"currency": null, "max": null, "min": null, "period": "monthly", "term": null}, "salary_visible": false, "title_keywords": ["senior human resources officer"], "responsibilities": [], "requirements": {"degrees": [], "majors": [], "languages": [], "language_level": [], "hard_skills": [], "soft_skills": [], "languages_combined": []}, "experience_required": {"duration": [], "field": []}}, {"job_id": "100003009042514", "location_code": "hk", "company": "Dah Chong Hong, Limited", "job_title": "Human Resources Officer", "description": "The incumbent will be responsible for providing a full spectrum of human resources services to designated Business Unit/Divisions, included but not limited to recruitment & selection, compensation & benefits and employee relations. His/ Her responsibilities are to provide professional HR advice and services to line management and business leaders to support them to drive for business growth and achieve company objectives. In addition, he/she would handle various HR reports & ad hoc projects assigned.\n\nUniversity degree in Human Resources or related discipline;\nAt least 3-4 years\u2019 hands-on experience in HR operations, recruitment & reports preparation; experience in the trading/retail industry and sizable companies would be an advantage;.\nWell versed in employment legislation and other statutory ordinances.\nSelf-motivated; Possess strong interpersonal and communication skills.\nGood numerical and analytical skills.\nProficient in Microsoft Office applications. Knowledge and experience in using PeopleSoft is an advantage\nImmediate Available is an absolute advantage\n\nPlease send your application with resume and expected salary to The HR Manager, Dah Chong Hong, Ltd, 8/F, DCH Building, 20 Kai Cheung Road, Kowloon Bay by post or email to click\u00a0\"Apply Now\".\n\n\u00a0We are equal opportunities employer. Applicants who are not invited within 2 months may consider their application unsuccessful. All applicants may be considered for other suitable positions with DCH Group / CITIC Pacific Group and will be deleted from our files after 6 months from the date of application.", "employment_types": ["Full Time"], "selling_points": [], "locations": ["Kowloon Bay"], "categories": ["Admin & HR", "Compensation & Benefits", "HR Supporting Staff", "Recruitment / Executive Search"], "post_time": "2022-01-12T07:50:29Z", "salary": {"currency": null, "max": null, "min": null, "period": "monthly", "term": null}, "salary_visible": false, "title_keywords": ["human resources officer"], "responsibilities": ["management", "operations", "hr", "hr reports", "communication", "ad hoc projects", "recruitment", "reports"], "requirements": {"degrees": ["university degree"], "majors": [], "languages": [], "language_level": [], "hard_skills": ["microsoft office", "sizable companies", "analytical skills"], "soft_skills": ["communication skills", "self-motivated", "responsible", "analytical skills", "hands-on", "interpersonal"], "languages_combined": []}, "experience_required": {"duration": ["at least 3-4 years"], "field": ["retail industry", "hr", "recruitment", "trading"]}}, {"job_id": "100003009046242", "location_code": "hk", "company": "Hong Kong Green Building Council Limited", "job_title": "Executive II \u2013 Human Resources", "description": "Established in 2009, Hong Kong Green Building Council (\u201cthe Council\u201d) is the leading body, co-founded by four major construction industry and environmental organisations, driving the market transformation towards green and sustainable buildings in Hong Kong through engagement with the industry, the government and broader community.\nHKGBC is expanding its secretariat team in line with its positioning as Hong Kong's leading member-based body dedicated to green building development, with opening for the post of Executive II \u2013 Human Resources:\nKey Roles:\nReport to Assistant Manager \u2013 Human Resources and Head of Finance and Administration, key responsibilities of the Executive II \u2013 Human Resources comprise:\nAttend to overall HR functions including recruitment, compensations and benefits, HR Information System, training and development and other HR related matters:\nAssist in recruitment activities including internship program and industrial attachment Program\nAssist in handling the full life circle of employee from on boarding to off boarding\nUpdate and maintain database of HR software system, safe-keep of personnel records\nProvide support in preparing payroll, MPF, leave management and tax returns for staff\nAssist in compiling HR related analysis reports, announcement, policies and procedures update\nAssist in various talent engagement, training and development, staff activities\nProvide support in various HR projects and initiatives and carry out the administration duties to ensure a smooth operation of HR Unit\nAny other duties as assigned by supervisors\n\u00a0Requirements:\nA degree holder, preferably in human resources management or related discipline\nOne to two years of experience in Human Resources is preferable, experiences in sizable organisation, public sector or related industry would be an advantage\nGood command of written and spoken English and Chinese (Cantonese and Mandarin)\nProficient in Microsoft Word, Excel, Powerpoint, Acrobat and general IT skills\nStrong sense of confidentiality and responsibility, well organised, \u00a0detail-oriented, able to multi-task and meet tight deadlines\nA team player with good interpersonal and communication skills\n\u00a0How to Apply\nThe Council is an equal opportunity employer and offers attractive career prospects and remuneration to our staff. Recruitment will be initially under contract terms of two years with the possibility of converting to a permanent post. Interested applicants please apply by sending\u00a0full resume with date of availability, present and expected salary, contact telephone number, as well as results of public examinations\u00a0to the\u00a0Executive Director, Hong Kong Green Building Council\u00a0via e-mail\u00a0careers @ hkgbc.org.hk, or by post to\u00a01/F, Jockey Club Environmental Building, 77 Tat Chee Avenue, Kowloon Tong, Hong Kong. Please state the position you want to apply for on the envelope.\n(N.B. Application with incomplete information as requested above may not be considered.)\nApplicants who do not receive a response within six weeks from the date of this advertisement may consider their applications filed for future reference. Personal data will be used strictly for recruitment related purposes only and retained for no more than six months.", "employment_types": ["Full Time", "Contract"], "selling_points": [], "locations": ["Kowloon City Area"], "categories": ["Admin & HR", "Compensation & Benefits", "HR Supporting Staff"], "post_time": "2022-01-13T10:04:48Z", "salary": {"currency": null, "max": null, "min": null, "period": "monthly", "term": null}, "salary_visible": false, "title_keywords": ["executive", "human resources"], "responsibilities": ["any other duties", "software", "analysis reports", "communication", "maintain", "database", "personal data", "administration", "report", "provide support", "management", "mpf", "personnel records", "procedures", "contact", "payroll", "tax", "policies", "hr", "recruitment"], "requirements": {"degrees": ["degree holder"], "majors": [], "languages": ["cantonese", "english", "chinese", "mandarin"], "language_level": ["good command"], "hard_skills": ["excel", "no", "microsoft word", "acrobat", "analysis", "information system", "powerpoint", "safe"], "soft_skills": ["communication skills", "meet tight deadlines", "multi-task", "detail-oriented", "smooth", "organisation", "organised", "team player", "interpersonal"], "languages_combined": [{"language": "cantonese", "language_level": ["good command"]}, {"language": "english", "language_level": ["good command"]}, {"language": "chinese", "language_level": ["good command"]}, {"language": "mandarin", "language_level": ["good command"]}]}, "experience_required": {"duration": ["one to two years"], "field": ["related", "human resources"]}}, {"job_id": "100003009040938", "location_code": "hk", "company": "Midland Holdings Limited", "job_title": "Assistant Human Resources Officer (C&B)", "description": "Responsibilities:\n\nResponsible\u00a0for full range of HR functions including but not limited to compensation and benefits.\nMonthly payroll calculation, MPF, staff records maintenance and leave management etc.\nPrepare and consolidate HR related reports\nHandle staff issues (e.g. disciplinary actions and staff complaints etc.)\nPerform any ad-hoc HR assignments/projects as assigned\n\nRequirements :\n\nDegree holder in any disciplines, major in HRM would be an advantage\n3 years' experience or above in sizable organization would be preferred\nWell-versed with Employment Ordinance and HR practice\nAnalytical, innovative and able to change at fast pace\nIndependent, presentable, well-organized with positive working attitude\nStrong sense of ownership,\u00a0result-oriented and ability to handle multi-tasks\nCandidates with more experience will be considered as Human Resources Officer\n\nCompetitive Salary will be offered to the right candidate. \u00a0For application, please update your resume by clicking \"APPLY NOW\" or complete the online application form which is available at\u00a0https://www.midland.com.hk/joinus/\u00a0and sent to the corresponding email address together with your full resume, present & expected salary.\n\nAll personal data collected will be used for recruitment purpose only. \u00a0Applicants not hearing from us within 2 months may consider their applications unsuccessful. \u00a0All personal data supplied will be kept for a reasonable period in accordance with the legal requirements.\n\nAs an Equal Opportunities Employer, we are committed to eliminating discrimination in employment. Our vacancy is open to all applicants meeting the basic entry requirement irrespective of their disability, sex, marital status, pregnancy, age, family status, sexual orientation and race.", "employment_types": ["Full Time", "Permanent"], "selling_points": ["Education Allowance, Medical Insurance", "Account Servicing, Payroll", "Employment Ordinance and HR practice"], "locations": ["Cheung Sha Wan"], "categories": ["Admin & HR", "Compensation & Benefits", "HR Supporting Staff"], "post_time": "2022-01-12T03:14:30Z", "salary": {"currency": null, "max": null, "min": null, "period": "monthly", "term": null}, "salary_visible": false, "title_keywords": ["assistant human resources officer"], "responsibilities": [], "requirements": {"degrees": [], "majors": [], "languages": [], "language_level": [], "hard_skills": [], "soft_skills": [], "languages_combined": []}, "experience_required": {"duration": [], "field": []}}, {"job_id": "100003009044312", "location_code": "hk", "company": "Global Management Services Limited", "job_title": "(Senior) HR & Admin Officer", "description": "Key Responsibilities\n\n\n\nReporting directly to the Country Manager(s), responsible for full spectrum of Hong Kong office\u2019s HR and office administration;\u00a0\nActing as assistant to Hong Kong office\u2019s Country Manager(s);\nResponsible for end-to-end recruitment process to support hiring managers from manpower planning, job posting, conducting interviews, selection to post-employment follow up;\nMaintain and administer an efficient and systematic procedure/system in keeping all HR records and confidential materials to ensure information security;\nPrepare management and analysis reports for annual benchmarking on compensation packages, medical insurance scheme, job grading and evaluation through market research & data analysis;\nProvide assistance to expatriates on work visa, relocation, housing, and tax arrangement;\nOrganize all business and travel arrangements including flight and hotel arrangement, visa application, travel insurance and expenses;\nSupport all office administration functions including but not limited to office moving & renovation, rental renewals, repair & maintenance and company's activities & any other ad hoc projects, etc.\n\n\n\nRequirements\n\n\nDiploma or above holder in Human Resources or related discipline;\nMinimum 4 years of work experience in the HR field ideally from a garment sourcing/fashion company with set up experience in emerging markets;\nWell-versed of Hong Kong employment ordinance and other statutory regulations related to employment;\nProficiency in MS Outlook, MS Word, Excel, and Powerpoint;\nExcellent communications, interpersonal and negotiation skills;\nPleasant, mature, and committed with a high sense of work responsibility and ethics;\nSelf-motivated, well organized, patient & attentive to details with strong numerical and analytical skills;\nStrong time management and multi-tasking skills and ability to cope with work pressure in a fast pace environment to meet strict deadlines;\nAbility to work independently with minimal supervision, positive with a can-do attitude;\nTeam players and able to create a harmonious and positive work atmosphere;\nExcellent command of written and spoken English\n\nWhat we offer\n\n\nExcellent development and career growth opportunity;\nMultinational and open-minded work environment;\nCompetitive remuneration and benefits.", "employment_types": ["Full Time", "Permanent"], "selling_points": [], "locations": ["Kowloon Bay"], "categories": ["Admin & HR", "Administration / Operation Manager", "Compensation & Benefits", "HR Supporting Staff"], "post_time": "2022-01-13T03:43:34Z", "salary": {"currency": null, "max": null, "min": null, "period": "monthly", "term": null}, "salary_visible": false, "title_keywords": ["officer", "hr", "admin"], "responsibilities": ["travel arrangements", "information security", "analysis reports", "renovation", "maintain", "evaluation", "office administration", "expenses", "conducting interviews", "provide assistance", "reporting", "management", "data analysis", "recruitment process", "tax", "maintenance", "hr", "market research", "repair", "ad hoc projects", "insurance", "planning"], "requirements": {"degrees": ["diploma or above"], "majors": [], "languages": ["english"], "language_level": ["excellent"], "hard_skills": ["excel", "hong kong employment ordinance", "powerpoint", "analytical skills", "outlook", "ms word"], "soft_skills": ["self-motivated", "work independently", "attentive to details", "can-do attitude", "harmonious", "well organized", "mature", "pleasant", "analytical skills", "committed", "negotiation skills", "multi-tasking skills", "patient", "time management", "interpersonal", "positive"], "languages_combined": [{"language": "english", "language_level": ["excellent"]}]}, "experience_required": {"duration": ["minimum 4 years"], "field": ["garment", "hr"]}}, {"job_id": "100003009039373", "location_code": "hk", "company": "Kam Lung Motors Limited", "job_title": "Human Resources Officer (HRO)", "description": "Responsibilities:\n\nResponsible for full spectrum of HR functions including but not limited to new staff on-boarding and departure processes, payroll processing, compensation & benefits, performance management, employee relations for designated functions;\nHandle internal customer enquiries in a timely and professional manner;\nMaintain staff records and manage data in HRIS on regular basis;\nFormulate and update HR policies and procedures from time to time in compliance with the relevant statutory legislation;\nProvide professional advice to all levels on HR policies and enquiries on HR areas;\nMaintain and prepare HR reports and analysis for management review;\nHandle ad hoc duties and projects as assigned;\n\nTogether with reliable, integrity and passion, our ideal staff should meet the following requirements:\n\nDegree holder in Human Resources Management or related disciplines;\nMinimum 5 years of relevant working experience;\nSound knowledge in HR practices, labor ordinance & related legal regulatory;\nPositive thinking with strong problem-solving, organizational and communication skills;\nIndependent, able to work under pressure and cope with a fast-paced environment;\nProficient in MS Applications and Chinese word processing\n\nInterested parties, please send your application with detailed resume stating expected salary and date of availability by clicking \"APPLY NOW'.\n\nAll information will be used solely for recruitment purpose and will be destroyed when the recruitment process is finished.", "employment_types": ["Full Time", "Permanent"], "selling_points": ["Assist in full spectrum of HR function", "Responsible for learning logistics management", "Maintain and prepare HR data analysis"], "locations": ["Tsuen Wan Area"], "categories": ["Admin & HR", "Compensation & Benefits", "HR Supporting Staff", "Training & Development"], "post_time": "2022-01-12T06:18:53Z", "salary": {"currency": null, "max": null, "min": null, "period": "monthly", "term": null}, "salary_visible": false, "title_keywords": ["human resources officer"], "responsibilities": ["ad hoc duties", "management", "data", "customer enquiries", "policies", "hr", "compliance", "professional manner", "procedures", "hr reports", "analysis", "communication", "maintain", "payroll", "management review", "work under pressure"], "requirements": {"degrees": ["degree holder"], "majors": ["related disciplines"], "languages": ["chinese"], "language_level": ["proficient"], "hard_skills": ["chinese word processing", "ms applications", "problem-solving", "analysis", "processing"], "soft_skills": ["communication skills", "independent", "responsible", "work under pressure", "organizational", "timely", "problem-solving", "integrity", "fast-paced environment", "positive thinking", "reliable", "ideal"], "languages_combined": [{"language": "chinese", "language_level": ["proficient"]}]}, "experience_required": {"duration": ["minimum 5 years"], "field": ["relevant working experience"]}}, {"job_id": "100003009046357", "location_code": "hk", "company": "Popsible Limited", "job_title": "Assistant HR and Admin Manager", "description": "RESPONSIBILITIES:\n\nResponsible for full functions of HR and Office Administration\nHandle payroll process, constantly review and make necessary improvements to streamline the process\nTo arrange for staff development & compliance training program and company activities\nMaster and maintain HRIS system to ensure accuracy of employee data and payroll information\nPrepare monthly employee cost analysis and improvement plan continually,\nManage tax calculation and filling for different countries and comply in local compliance\nHandle in expenses & budget control\nAdopt of refine project standards, policies, procedures and methodologies.\nParticipant in ad-hoc HR & General Admin projects\nProvide secretarial and administrative support to CEO\n\nREQUIREMENTS:\n\nDegree holder in Business Administration/ Human Resources Management or related discipline.\nMinimum 3 years working experience in relevant experience.\nExcellent organizational and time-management skills\nGood command of written and spoken Cantonese English and Mandarin.\nProficiency in MS Office applications, especially Word, Excel and PowerPoint etc.\nImmediate availability or short notices is highly preferred\n\nWe offer a competitive remuneration package including 5-day work and medical insurance to the right candidate with excellent career advancement.\u00a0Interested parties please send your application letter and detailed CV including date of availability and current and expected salary to avis[at]popsible.com, quoting the Job title in the email subject, we only offer short-listed candidates for an interview.", "employment_types": ["Full Time"], "selling_points": [], "locations": ["Tsim Sha Tsui"], "categories": ["Admin & HR", "Clerical / Admin Staff", "Personal / Executive Assistant", "Compensation & Benefits"], "post_time": "2022-01-13T10:39:50Z", "salary": {"currency": null, "max": null, "min": null, "period": "monthly", "term": null}, "salary_visible": false, "title_keywords": ["hr", "admin", "manager", "assistant"], "responsibilities": ["tax", "ad-hoc", "data", "administrative support", "office administration", "hr", "review", "compliance", "expenses", "policies", "procedures", "maintain", "plan", "cost analysis", "payroll", "budget control"], "requirements": {"degrees": ["degree holder"], "majors": ["business administration"], "languages": ["cantonese", "english", "mandarin"], "language_level": ["good command"], "hard_skills": ["excel", "word", "powerpoint", "ms office"], "soft_skills": ["organizational"], "languages_combined": [{"language": "cantonese", "language_level": ["good command"]}, {"language": "english", "language_level": ["good command"]}, {"language": "mandarin", "language_level": ["good command"]}]}, "experience_required": {"duration": ["minimum 3 years"], "field": ["relevant experience"]}}, {"job_id": "100003009044008", "location_code": "hk", "company": "KOS International Limited", "job_title": "C&B Manager - Up to 45k", "description": "About The Client\nOur client is a Hong Kong listed company with rapid growth plan in Hong Kong and Southeast Asia. Due to the business expansion, they are looking for a C&B Manager to supervise the team.\n\nAbout The Role\n\n\nDirect report to Group HR Manager and supervise a small team\nResponsible for full spectrum C&B duties including payroll calculation (both frontline and corporate function), benefits administration, salary review, bonus and incentive scheme review and budget planning\nPerform data analysis on total rewards, compile data into reports and share insight and proposal to senior management\nReview and enhance existing C&B policies and procedures\nAssist in any adhoc tasks assigned\n\nRequirements\n\nDegree holder in HR Management, Business Administration or related disciplines\nWith a minimum of 8 years of experience in C&B focus\nExcellent communication, interpersonal and presentation skills\nMotivated, dynamic and with strong can-do spirit\nGood command in English, Cantonese, and Mandarin\n\nClick \"Apply Now\" to apply for this position or call Kobe Lo at +852 3180 4948 for a confidential discussion. All information collected will be kept in strict confidence and will be used for recruitment purpose only.", "employment_types": ["Full Time", "Permanent"], "selling_points": ["Hong Kong listed company", "8+ years of full spectrum C&B experience", "Dynamic and energetic work environment"], "locations": ["Not Specified"], "categories": ["Admin & HR", "Compensation & Benefits", "HR Director / Manager"], "post_time": "2022-01-13T02:45:48Z", "salary": {"currency": null, "max": null, "min": null, "period": "monthly", "term": null}, "salary_visible": false, "title_keywords": ["manager"], "responsibilities": ["budget planning", "management", "data", "policies", "hr", "review", "procedures", "data analysis", "communication", "reports", "recruitment", "plan", "report", "senior management", "payroll", "administration"], "requirements": {"degrees": ["degree holder"], "majors": ["related disciplines", "business administration"], "languages": ["cantonese", "english", "mandarin"], "language_level": ["good command"], "hard_skills": ["small", "analysis", "scheme", "dynamic", "rapid", "focus"], "soft_skills": ["confidence", "responsible", "communication", "presentation skills", "motivated", "dynamic", "can-do", "focus", "interpersonal"], "languages_combined": [{"language": "cantonese", "language_level": ["good command"]}, {"language": "english", "language_level": ["good command"]}, {"language": "mandarin", "language_level": ["good command"]}]}, "experience_required": {"duration": ["minimum of 8 years"], "field": []}}, {"job_id": "100003009045037", "location_code": "hk", "company": "HANSEL INTERNATIONAL Executive Search Limited", "job_title": "Human Resources (Senior Officer to Assistant Manager)- Chinese Financial Institution", "description": "Our client is a full-fledged state-owned financial institution with brokerage, investment banking and asset\u00a0 management business.\u00a0\n\nResponsibilities:\u00a0\n\nResponsible of full spectrum of HR management and business operations including compensation & benefit, recruitment, training & orientation, expatriates mobility and employee relations for HK office.\nPrepare monthly payroll, MPF administration, medical & life insurance administration, tax-filing & tax related issues, leave records, etc. \u00a0of HK, Shenzhen & Shanghai office\u00a0\u00a0\nMaintain HR policies in compliance with related law and regulations.\nConduct recruitment interviews, selection, provide comments for management recommendation.\nReview and update Company handbook to meets with HQ and compliance standard from time to time\nResponsible for new hires on boarding and orientation process\nHandle visa application, relocation, accommodations in HK etc.\n\n\u00a0Requirements:\u00a0\n\nDegree holder in Human Resources Management or related disciplines\nAt least 5 years of hands-on experience in human resources with experience in financial industry will be an advantage\nExperienced in Chinese Reporting\u00a0\nWell versed in Hong Kong Employment Ordinance and other employment related\u00a0legislation\nExcellent management and leadership, planning skills, passionate, detail minded and positive attitude\nProficient in both written and spoken English and Chinese, able to speak fluent English and Mandarin\nOrganized, responsible, detailed oriented, independent and self-motivated\nStrong communication and presentation skills\nA good team player\n\nFor interested candidates, please send us your resume with your 1) current salary 2) expected salary 3) notice period.\u00a0 All personal information collected with be strictly used for recruitment purpose only.\u00a0", "employment_types": ["Full Time"], "selling_points": ["Recruitment, C&B, Performance Management", "Full fledged listed Chinese FI", "Experienced in Chinese/ HQ Reporting"], "locations": ["Sheung Wan"], "categories": ["Admin & HR", "Compensation & Benefits", "HR Director / Manager", "HR Supporting Staff"], "post_time": "2022-01-13T06:58:20Z", "salary": {"currency": null, "max": null, "min": null, "period": "monthly", "term": null}, "salary_visible": false, "title_keywords": ["senior officer", "human resources", "assistant manager"], "responsibilities": ["tax", "regulations", "management", "mpf", "operations", "hr", "policies", "compliance", "comments", "review", "maintain", "recruitment", "insurance", "payroll", "administration"], "requirements": {"degrees": ["degree holder"], "majors": ["related disciplines"], "languages": ["english", "chinese", "mandarin"], "language_level": ["fluent", "proficient"], "hard_skills": ["hong kong employment ordinance"], "soft_skills": ["passionate", "planning skills", "organized", "self-motivated", "detailed oriented", "independent", "responsible", "good team player", "positive attitude", "communication", "hands-on", "presentation skills", "leadership"], "languages_combined": [{"language": "english", "language_level": ["fluent", "proficient"]}, {"language": "chinese", "language_level": ["fluent", "proficient"]}, {"language": "mandarin", "language_level": ["fluent", "proficient"]}]}, "experience_required": {"duration": ["at least 5 years"], "field": ["financial industry", "human resources"]}}, {"job_id": "100003005793345", "location_code": "hk", "company": "Sa Sa Cosmetic Co Ltd", "job_title": "Human Resources and Administration Officer, Warehouse and Logistics (Kwai Chung)", "description": "Responsibilities\n\nProvide administrative support including operations and human resources, but not limited to recruitment, C&B, employee relations and training;\nAssist job posting, interview arrangement, leave and attendance records update;\nPerform C&B support on payroll such as attendance management, payroll calculation, final payment, exit interview;\nManage end-to-end recruitment process focusing on operative positions from job requisition to new hire on-boarding arrangements;\nConsolidate warehouse vendors and on-boarding arrangement;\nProvide general warehouse administrative support;\nPerform data entry and prepare regular reports;\nPerform ad hoc tasks as assigned.\n\nRequirements\n\nDiploma holder in any discipline;\nMinimum 2 years of HR or administration experience;\nAttentive to details and follow through;\nIndependent, self-motivated and good team player;\nGood communication skills in both written and spoken English and Chinese;\nProficient PC skills, knowledge in HR plus system is an advantage;\nCandidate with less working experience will be considered as Assistant HR Officer\nImmediate available is a great advantage.\n\nWe offer\n\n5 - day work week\nMedical Benefits\nAnnual Merit Bonus\nStaff Purchase Discounts\nStaff Recreation Activity\nShuttle Bus Service\nEducation Sponsorship\n\nInterested parties please send a full resume with current and expected salary by clicking APPLY NOW:\n\nHuman Resources Department\nSa Sa Cosmetic Co Ltd\n14/F, Block B, MP Industrial Centre\u00a0\n18 Ka Yip Street\u00a0\nChai Wan\u00a0\nHong Kong\n\nPlease visit our corporate website at\u00a0http://corp.sasa.com/en/home\u00a0to know more about us.\u00a0\n\n(Sa Sa is an Equal Opportunity Employer and all qualified applicants will receive consideration for employment. Personal data collected will be kept confidential and used for recruitment purpose only)", "employment_types": ["Full Time", "Permanent"], "selling_points": ["Handle daily C&B functions", "Payroll and allowance & commission calculation", "Conduct research and analysis"], "locations": ["Kwai Tsing Area"], "categories": ["Admin & HR", "Compensation & Benefits", "HR Supporting Staff"], "post_time": "2022-01-12T10:08:27Z", "salary": {"currency": null, "max": null, "min": null, "period": null, "term": null}, "salary_visible": false, "title_keywords": ["administration officer", "logistics", "human resources"], "responsibilities": ["attendance", "management", "administrative support", "data entry", "operations", "ad hoc tasks", "payment", "recruitment", "reports", "interview arrangement", "provide administrative support", "recruitment process", "payroll"], "requirements": {"degrees": ["diploma holder"], "majors": [], "languages": ["english", "chinese"], "language_level": ["good"], "hard_skills": ["plus", "pc skills"], "soft_skills": ["communication skills", "good team player", "self-motivated", "independent", "attentive to details"], "languages_combined": [{"language": "english", "language_level": ["good"]}, {"language": "chinese", "language_level": ["good"]}]}, "experience_required": {"duration": ["minimum 2 years"], "field": ["hr", "administration"]}}, {"job_id": "100003009043092", "location_code": "hk", "company": "B.S.C. Group Limited", "job_title": "(Senior) Human Resources Officer", "description": "Responsibilities:\n\nBe part of the Group HR Team to provide comprehensive HR services to designated business unit(s) as a business partner\nResponsible for monthly payroll administration, monitoring leave and attendance records, support\u00a0insurance affairs\u00a0and\u00a0maintain daily\u00a0HRIS\u00a0operations\nHandle regular HR internal reports for analytics presenting to the Management\nAssist in maintaining data quality of personnel databases, and preparing HR documentation for the full employment cycle\nLiaise with internal & external parties for continuous HR digital transformation process\nHandle\u00a0other ad-hoc\u00a0assignments\u00a0as assigned\n\nRequirements:\n\nDegree holder in Human Resources Management or relevant disciplines\n5+\u00a0years\u00a0solid experience from in-house HR position\nWell versed in HR-related Ordinances is essential\nKnowledge in Macau employment ordinance & experience in HRIS implementation will be a strong advantage\nMeticulous, self-motivated, open-minded and persistent in problem-solving\nAble to work with all levels of colleagues in a dynamic environment\nProficient in\u00a0MS Office applications and Chinese Word Processing\nGood command in written and spoken English and Chinese\nImmediate availability\u00a0will be a definite advantage\nCandidate with higher calibre would be considered as Senior Human Resources Officer\nWe offer attractive remuneration package and comprehensive fringe benefits including\u00a05-day work week, 14-day of annual leave, medical insurance and discretionary bonus\u00a0to the right candidate.\nInterested parties please apply with full resume and expected salary to\u00a0Human Resources Department, 19th Floor, Sino Favour Centre, 1 On Yip Street, Chaiwan, Hong Kong,\u00a0or by clicking the 'Apply Now' below.\u00a0For more information about us, please visit our website http://www.bschk.com and http://www.colourliving.com.\n\nPersonal data collected will be used for recruitment purpose only.", "employment_types": ["Full Time", "Permanent"], "selling_points": ["Responsible for monthly payroll administration", "5+ years solid experience", "5-day work week & 14-day of annual leave"], "locations": ["Chai Wan"], "categories": ["Admin & HR", "Others", "Compensation & Benefits", "HR Supporting Staff"], "post_time": "2022-01-12T09:47:52Z", "salary": {"currency": null, "max": null, "min": null, "period": "monthly", "term": null}, "salary_visible": false, "title_keywords": ["human resources officer"], "responsibilities": ["attendance", "management", "maintaining", "data", "operations", "hr", "monitoring", "quality", "external parties", "ad-hoc assignments", "liaise with", "maintain", "reports", "insurance", "databases", "documentation", "payroll", "administration"], "requirements": {"degrees": ["degree holder"], "majors": [], "languages": ["english", "chinese"], "language_level": ["good command", "proficient"], "hard_skills": ["problem-solving", "dynamic", "chinese word processing", "ms office"], "soft_skills": ["meticulous", "self-motivated", "dynamic environment", "open-minded", "problem-solving", "persistent", "comprehensive"], "languages_combined": [{"language": "english", "language_level": ["good command"]}, {"language": "chinese", "language_level": ["good command", "proficient"]}]}, "experience_required": {"duration": ["5+ years"], "field": ["hr"]}}, {"job_id": "100003009040130", "location_code": "hk", "company": "i-CABLE Communications Limited", "job_title": "Senior Human Resources Officer / Human Resources Officer - Human Resources Dept", "description": "Human Resources\u00a0Department\nTo be responsible for assisting in formulating and executing the recruitment strategy; assisting in manpower planning, recruitment & staffing; performing payroll and commission calculation; administering employees' benefits and compensation\nUniversity graduate in Human Resources Management or related discipline with minimum 3 years relevant working experience\nWell-versed in the Employment Ordinance and other HR related regulations\nFamiliar with MS Office and Chinese word processing\nGood command in spoken and written English & Chinese, Mandarin is an advantage\nDetail-minded with good interpersonal and communication skills\n\nWe offer 5-day work week, competitive remuneration packages and advancement opportunities. Interested parties, please write with full resume to Director, Human Resources, Human Resources Department, i-CABLE Communications Limited, 4/F Cable TV Tower, 9 Hoi Shing Road Tsuen Wan, N.T. or fax to 2112 7841 or via Apply Now (Please quote reference number and position applied for). For other information, please visit our website http://www.i-cable.com.\n\nYour application may be forwarded to any affiliate companies and successful applicant may be seconded to work at any office as assigned.\u00a0 The information received will be used for consideration of employment only and all personal data supplied will be destroyed within 3 months.\n\n\nWe are an equal opportunity employer.", "employment_types": ["Full Time", "Permanent"], "selling_points": [], "locations": ["Tsuen Wan Area"], "categories": ["Admin & HR", "Compensation & Benefits", "HR Supporting Staff", "Recruitment / Executive Search"], "post_time": "2022-01-12T01:33:39Z", "salary": {"currency": null, "max": null, "min": null, "period": null, "term": null}, "salary_visible": false, "title_keywords": ["senior human resources officer", "human resources officer", "human resources"], "responsibilities": ["recruitment strategy", "recruitment", "executing", "payroll", "planning"], "requirements": {"degrees": [], "majors": [], "languages": [], "language_level": [], "hard_skills": [], "soft_skills": ["responsible"], "languages_combined": []}, "experience_required": {"duration": [], "field": []}}, {"job_id": "100003009044935", "location_code": "hk", "company": "Hong Kong Food Investment Holdings Limited", "job_title": "Assistant Supervisor / Supervisor (Human Resources and Administration)", "description": "Responsibilities:\n\nProvide support to HR functions including but not limited to payroll, MPF, tax return, leave management and recruitment;\nCommunicate with all levels of staff and external parties for HR related matters;\nUpdate staff information and maintain proper filing system;\nPrepare HR reports for management review;\nResponsible for office administration duties including office maintenance, procurement, stationery, vehicle license renewal and insurance etc.;\nHandle ad-hoc projects as assigned.\n\nRequirements:\n\nHigher Diploma or above in Human Resource or Business Administrative disciplines with\u00a01-2 years of relevant experiences;\nRelevant experience in catering\u00a0will be an advantage;\nFamiliar with Employment Ordinance and other employment-related legislation;\nProficient in MS Office (MS Word, MS Excel , Chinese Word Processing & PowerPoint);\nGood command of both written and spoken English and Chinese;\nBe self-motivated, detail-minded and well-organized.\nImmediately available is preferred\n\n\n\nWe offer a competitive salary and fringe\u00a0benefits to the right\u00a0candidate.\u00a0 Interested parties please apply with full resume, current and expected salary by clicking \"Apply now\".\n\n*Personal data provided are treated in strictest confidence and for recruitment purposes only", "employment_types": ["Full Time", "Permanent"], "selling_points": [], "locations": ["Kowloon Bay"], "categories": ["Admin & HR", "Clerical / Admin Staff", "Compensation & Benefits", "HR Supporting Staff"], "post_time": "2022-01-13T06:41:02Z", "salary": {"currency": null, "max": null, "min": null, "period": "monthly", "term": null}, "salary_visible": false, "title_keywords": ["supervisor", "assistant supervisor", "human resources"], "responsibilities": ["tax", "communicate with", "provide support", "management", "mpf", "maintenance", "hr", "external parties", "hr reports", "stationery", "maintain", "recruitment", "insurance", "office administration duties", "ad-hoc projects", "payroll", "management review"], "requirements": {"degrees": ["higher diploma or above"], "majors": ["business"], "languages": ["english", "chinese"], "language_level": ["good command", "proficient"], "hard_skills": ["chinese word processing", "powerpoint", "ms excel", "ms office", "ms word"], "soft_skills": ["detail-minded", "self-motivated", "well-organized"], "languages_combined": [{"language": "english", "language_level": ["good command"]}, {"language": "chinese", "language_level": ["good command", "proficient"]}]}, "experience_required": {"duration": ["1-2 years"], "field": ["business", "relevant experience", "administrative"]}}, {"job_id": "100003009048983", "location_code": "hk", "company": "Odoo Limited", "job_title": "HR Assistant / Officer", "description": "Join a vibrant and innovative team, working within an organization that values independence, flexibility and personal growth. As an HR Assistant/Officer, you will be supporting the Senior HR Officer in general affairs, HR-related duties and other administrative tasks. This is an exciting opportunity for you to learn and to be a part of a rapidly growing company.\n\nRESPONSIBILITIES\n\n\n\nAssist with day-to-day operations of the HR functions and duties\nMaintain/update employee records accurately and effectively\nWelcoming new employees to the company by conducting orientation\nAssist with leave management, on and off boarding operations, company events, meetings etc.\nAssist with employment visa application and record management\u00a0\nAssist in preparing official documents and provide administrative support to HR Department\nKeep up-to-date with the latest HR trends and best practices\nPerform other assigned duties and ad hoc projects\nMUST HAVE\n\nBachelor\u2019s degree, or higher in related disciplines\nProficiency in productivity software / application such as MS Office & Google Workplace\nGood command in both spoken and written English and Chinese\nGood team player with a positive attitude and eager to learn and grow\nSelf-motivated with strong sense of responsibility\nHighly organized and detail-oriented\n\nNICE TO HAVE\n\nStrong software and new technology awareness\nImmediate Availability\n1-2 years relevant experience\n\nVALUES\n\nYou are able to work in a fast-paced start-up environment with a hands-on attitude\nYou are open-minded and can react to change with agility\nYou are a quick and autonomous learner\nWilling to contribute to great company culture", "employment_types": ["Full Time"], "selling_points": ["All round HR duties", "1-2 years experience", "Dynamic & international working environment"], "locations": ["Sai Ying Pun"], "categories": ["Admin & HR", "Clerical / Admin Staff", "Compensation & Benefits", "HR Supporting Staff"], "post_time": "2022-01-14T07:49:58Z", "salary": {"currency": null, "max": null, "min": null, "period": "monthly", "term": null}, "salary_visible": false, "title_keywords": ["officer", "hr assistant"], "responsibilities": ["management", "software", "operations", "hr", "day-to-day operations", "maintain", "ad hoc projects", "administrative tasks", "provide administrative support"], "requirements": {"degrees": ["degree", "bachelor"], "majors": ["related disciplines"], "languages": ["english", "chinese"], "language_level": ["good command"], "hard_skills": ["nice", "react", "ms office"], "soft_skills": ["organized", "good team player", "self-motivated", "sense of responsibility", "open-minded", "hands-on attitude", "detail-oriented", "positive attitude", "eager to learn", "autonomous", "innovative"], "languages_combined": [{"language": "english", "language_level": ["good command"]}, {"language": "chinese", "language_level": ["good command"]}]}, "experience_required": {"duration": ["1-2 years"], "field": ["relevant experience"]}}, {"job_id": "100003009046335", "location_code": "hk", "company": "KOS International Limited", "job_title": "Global C&B Director - Financial Services", "description": "About The Client\nOur client is an industry leader in the Financial Services sector. They are now hiring a Group C&B Director as part of the HR management team. 20+ years of relevant HR work experience with a focus on strategic C&B projects including the implementation of sales incentive plans and executive compensation will be essential for this role, and prior China/ Regional / Global experience highly regarded.\n\nAbout The Role\nReporting into the Group Chief HR Officer, you will:\n\n- ovesee the executive and incentive programs for the global business\n- manage the process for designing executive and incentive programmes and responsible for day to day implementation and administration of these programmes\n- collaborate with the brand and field leadership to design rewards that maximise the performance of field teams in alignment with company strategy\n- work with external vendors to execute all executive and incentive compensation activities - plan design, goal setting, reports, scorecards, drawing on business analytics partners and external vendors when necessary\n\nRequirements\nThe ideal candidate must be able to work in a self-directed manner within a cross-functional team environment and coordinate and communicate with all stakeholders. A key aspect of this role is the ability to interact with and influence senior leaders and members of the leadership team. Prior experience working for HR consultancies would be a definite advantage, and proficiency in English and Chinese required for this role.\n\nClick \"Apply Now\" to apply for this position or call Christina Lau at +852 3180 4934 for a confidential discussion. All information collected will be kept in strict confidence and will be used for recruitment purpose only.", "employment_types": ["Full Time", "Permanent"], "selling_points": ["Executive Compensation, Sales Incentive Scheme", "20+ years of relevant group level C&B experience", "Regional/Global HR experience essential"], "locations": ["Not Specified"], "categories": ["Admin & HR", "Compensation & Benefits", "HR Director / Manager"], "post_time": "2022-01-13T10:34:54Z", "salary": {"currency": null, "max": null, "min": null, "period": "monthly", "term": null}, "salary_visible": false, "title_keywords": ["director"], "responsibilities": ["collaborate with", "management team", "reporting", "communicate with", "hr", "teams", "implementation", "design", "coordinate", "reports", "recruitment", "plan", "designing", "plans", "administration"], "requirements": {"degrees": [], "majors": [], "languages": ["english", "chinese"], "language_level": ["advantage", "proficiency"], "hard_skills": ["goal", "focus"], "soft_skills": ["confidence", "responsible", "focus", "leadership", "ideal"], "languages_combined": [{"language": "english", "language_level": ["advantage", "proficiency"]}, {"language": "chinese", "language_level": ["advantage", "proficiency"]}]}, "experience_required": {"duration": ["20+ years"], "field": ["hr"]}}, {"job_id": "100003009045132", "location_code": "hk", "company": "Raise Corporation Limited", "job_title": "Senior HR & Admin Officer", "description": "Job Responsibilities\u00a0\n\nHandle the benefits administration regarding staff movement, leave applications, insurance claims, etc\nProcess monthly payroll and ad hoc payments for assigned employee groups.\nAssist in housemaids and workers recruitment, schedule relevant roster and prepare various work visa applications\nManage the work relationship of assigned employee groups and handle disputes to ensure work effectiveness and good relationship\nProvide HR and office administrative services and support\nSource, propose and organize the renewal of employees\u2019 benefits and various insurance plans\nOrganize and support staff activities and events, such as heath talk, wellness seminars\nPrepare and compile various types of management reports\nHandle various ad hoc projects as assigned\n\nJob Requirements\n\nUniversity graduate preferably in Human Resources Management or equivalent\nAt least 5 years\u2019 HR experience with strong compensation and benefits practice\nWell versed in HK Labor law and employment visa application\nExcellent command of spoken and written English and Chinese including Putonghua\nStrong communication and interpersonal skills\nWell-organized, self-motivated and meticulous\nCandidate with more experience can be considered as Assistant HR & Admin. Manager\u00a0\nInterested parties please send your CV by clicking the apply now button.", "employment_types": ["Full Time"], "selling_points": ["Payroll and benefit administration", "Recruitment of housemaids and workers", "Secretarial and Administrative support"], "locations": ["Eastern Area"], "categories": ["Admin & HR", "Administration / Operation Manager", "Compensation & Benefits", "HR Supporting Staff"], "post_time": "2022-01-13T07:15:39Z", "salary": {"currency": null, "max": null, "min": null, "period": "monthly", "term": null}, "salary_visible": false, "title_keywords": ["senior hr & admin officer"], "responsibilities": [], "requirements": {"degrees": [], "majors": [], "languages": [], "language_level": [], "hard_skills": [], "soft_skills": [], "languages_combined": []}, "experience_required": {"duration": [], "field": []}}, {"job_id": "100003009048715", "location_code": "hk", "company": "Mandarin Oriental Hotel Group Limited", "job_title": "Regional Director of Human Resources \u2013 APAC", "description": "Based at the Corporate Office in Hong Kong, the Regional Director of Human Resources - APAC will act as a Human Resources leader to the region. They will lead, organize, orchestrate and develop a cohesive Human Resources function in the region, who will execute the strategy of talent acquisition, learning and development, talent management/succession planning and compensation and benefits. They will provide expertise and support in labour relations matters. They will ensure all new openings and renovations are successfully opened on time.\n\nRequirements\n\nA minimum of 10 years in Human Resources management. Prior experience working in Asia or oversight of the region.\nDegree preferably in Human Resources or professional Human Resources accreditation\nPreferably pre-opening experience\nStrong business acumen and high degree of work ethic\nConfident, excellent communication skills and ability to build relationships\n\n\u6709\u610f\u7533\u8acb\u8005\u8acb \u6309 APPLY NOW\u7533\u8acb\n\n\nCulturally sensitive\nSelf-motivated, well organised and detail orientated\nEnjoys working in a fast paced and dynamic environment\nAble to travel when required", "employment_types": ["Full Time"], "selling_points": ["Degree preferably in Human Resources", "Confident, excellent communication skills", "Preferably pre-opening experience"], "locations": ["Not Specified"], "categories": ["Admin & HR", "Compensation & Benefits", "HR Director / Manager", "Recruitment / Executive Search"], "post_time": "2022-01-14T07:07:45Z", "salary": {"currency": null, "max": null, "min": null, "period": "monthly", "term": null}, "salary_visible": false, "title_keywords": ["director", "human resources"], "responsibilities": ["communication", "management", "planning", "develop"], "requirements": {"degrees": ["degree"], "majors": ["business"], "languages": [], "language_level": [], "hard_skills": ["dynamic", "acumen"], "soft_skills": ["confident", "communication skills", "self-motivated", "dynamic environment", "cohesive", "learning", "detail orientated", "work ethic", "sensitive", "business acumen", "organised"], "languages_combined": []}, "experience_required": {"duration": [], "field": []}}, {"job_id": "100003009046645", "location_code": "hk", "company": "Tung Wah Group of Hospitals", "job_title": "Senior Assistant Human Resources Manager (Administration)/ Admin. HQ [REF: SHRM(P)1/SAHRM(A)/JOBS]", "description": "[REF: SHRM(P)1/SAHRM(A)/JOBS]\n\nLocation: Sheung Wan\n\nRoles & responsibilities:\n\nPlan, design, develop and implement staff relations and welfare policies to align with the corporate strategies;\noversee the handling of staff welfare benefits (such as medical/dental treatment, merit awards and etc.), make recommendations for applications of staff welfare schemes/grants and ensure all applications are processed in a timely and proper manner;\nmanage staff awards such as Long Service Awards, Retirement Awards by designing the souvenir(s) and follow up the production and distribution;\nplan and formulate the office yearly plan/budget of the Section for management\u2019s approval;\nconduct review to smoothen the operation procedure of the Section and provide recommendations to optimize the staff welfare benefit schemes/grants;\nconsolidate the regular/annual exercises (i.e. annual report/plan/budget) for the Section and prepare the integrated version for management\u2019s approval;\nlead the Administration Team to maintain a smooth daily office operation for the Section; and\nplan, design and implement staff welfare/relations initiatives as assigned.\n\nThe ideal candidate should possess:\n\na recognized degree or equivalent;\nat least Grade D in English Language (Syllabus B) and Chinese Language in the HKCEE or equivalent;\nat least 4 years of administrative experience preferably in drafting administration policy/staff welfare schemes or project management;\nproficiency in English and Chinese, and preferably in Putonghua;\ncalibre as a good team player with supervisory experience and sound communication skills; and\nability to work independently with initiative and have a strong sense of responsibility.\n\n(Please specify in the application form the HKCEE result and relevant working experience you have attained in detail.)\n\nCompensation & employment terms:\n\nThe successful candidate will initially be offered a 3-year contract with a remuneration package which will be commensurate with his/her background and experience.\u00a0 The continuation of employment and employment terms thereafter will be subject to mutual agreement.\u00a0 Apart from contributions to the MPF Scheme, other benefits include paid annual leave, medical services, a dental scheme and training sponsorships.\u00a0 The incumbent will normally work under a 5-day week schedule subject to operational needs and exigencies of the service.\n\nApplication:\n\nPlease send your resume and a completed application form [F601(n)] with indication of your current and expected salaries to the Head of Human Resources Division, Tung Wah Group of Hospitals at 4/F., Wong Fung Ling Memorial Building, 12 Po Yan Street, Hong Kong by 24 January\u00a02022.\u00a0 The reference code should be marked both in the letter and on the envelope.\u00a0 Application forms are obtainable in person or can be downloaded from http://www.tungwah.org.hk.\u00a0\u00a0Underpaid mail items will not be accepted by Tung Wah.\u00a0 For proper delivery of your mail items, please ensure your mail items bear sufficient postage with return address before posting.\u00a0 Personal data provided by applicants will be used strictly for recruitment purpose only and in accordance with the Tung Wah's personal data policy.\u00a0 Applicants not invited to attend an interview by 30 April 2022 may assume that their applications are unsuccessful.\n\nWE ARE AN EQUAL OPPORTUNITIES EMPLOYER", "employment_types": ["Full Time"], "selling_points": [], "locations": ["Sheung Wan"], "categories": ["Admin & HR", "Compensation & Benefits", "HR Director / Manager", "Public / Civil", "Social Services - Community / Non-profit Organization"], "post_time": "2022-01-13T18:53:59Z", "salary": {"currency": null, "max": null, "min": null, "period": "monthly", "term": null}, "salary_visible": false, "title_keywords": ["admin", "assistant human resources manager"], "responsibilities": ["develop", "policies", "plan", "design"], "requirements": {"degrees": [], "majors": [], "languages": [], "language_level": [], "hard_skills": ["wan"], "soft_skills": [], "languages_combined": []}, "experience_required": {"duration": [], "field": []}}, {"job_id": "100003009043709", "location_code": "hk", "company": "Manpower Services (Hong Kong) Limited", "job_title": "HR Specialist", "description": "Responsibilities:\n\nEnd to end recruitment cycle\nWork closely with line manager or client for the job requirement and provide suitable candidate\nUnderstand the hiring needs and provide support in recruitment\u00a0\nHandle\u00a0C&B tasks and HR administration independently e.g. MPF enrollment, medical plan enrollment, communicate with payroll team for monthly payroll and final payment\nProvide HR consultation to line manager\u00a0or client\nDevelop candidate base through different recruitment channels\nHandle\u00a0ad hoc projects and perform other duties as assigned\n\nRequirements:\n\nDiploma holder\u00a0or above, Human Resources Management is preferred\nAt least 2 years experience in Human Resources / recruitment agency\nEnergetic, responsible, detail minded, able to work multi-tasks and independently\u00a0\nExcellent interpersonal and communication skills\nFluent in oral and written English and Chinese (Cantonese and Mandarin)\nImmediately available is highly preferable\u00a0\n\nInterested parties please submit your CV with your expected salary and availability to danise.yeung@manpowegrc.hk", "employment_types": ["Permanent"], "selling_points": ["All round HR", "Work independently", "Immediately available is highly preferable"], "locations": ["Causeway Bay"], "categories": ["Admin & HR", "Compensation & Benefits", "HR Supporting Staff", "Recruitment / Executive Search"], "post_time": "2022-01-13T01:35:57Z", "salary": {"currency": null, "max": null, "min": null, "period": "monthly", "term": null}, "salary_visible": false, "title_keywords": ["hr specialist"], "responsibilities": ["communicate with", "provide support", "enrollment", "perform other duties", "mpf", "hr", "develop", "payment", "recruitment", "ad hoc projects", "plan", "payroll", "administration"], "requirements": {"degrees": ["diploma holder"], "majors": [], "languages": ["cantonese", "english", "chinese", "mandarin"], "language_level": ["fluent"], "hard_skills": [], "soft_skills": ["communication skills", "oral", "independently", "multi-tasks", "responsible", "energetic", "interpersonal"], "languages_combined": [{"language": "cantonese", "language_level": []}, {"language": "english", "language_level": ["fluent"]}, {"language": "chinese", "language_level": ["fluent"]}, {"language": "mandarin", "language_level": []}]}, "experience_required": {"duration": ["at least 2 years"], "field": ["agency", "recruitment", "human resources"]}}, {"job_id": "100003009046478", "location_code": "hk", "company": "Cinnox Limited", "job_title": "Human Resources Officer (Talent Acquisition) - Immediate Available", "description": "Our team\nCINNOX is made of a collective of individuals driven by success while motivating and supporting one another to cultivate an environment of encouragement and trust. We are committed to continuous improvement through innovation, curiosity and creativity to help businesses compete and win by humanising customer and employee connections. We have a team that supports each other grows together. By working together, our achievements are magnified.\u00a0\nCINNOX is an equal opportunity employer, with the belief that a diverse team creates unique potential, we strive to build a diverse and inclusive community where everyone, regardless of gender, race, religion, age, or background, can belong.\nTo cope with the rapid business growth across the globe, we are looking for ambitious, passionate and self-driven talent to join our fast growing team.\nWHAT you be doing in this role:\n\nResponsible for the end-to-end recruitment process including not limited to job advertisement, CV screening & shortlisting, hiring and onboarding process automation, talent pool management and turnover analysis\nAs a Digital HR Specialist with the skills to successfully lead the digital transformation of HR by reforming HR workflows and ERP integration and implementation\nTo play the role of business partner for manpower planning and performance management\nPrepare and compile HR reports for management review\nParticipate in other HR initiatives and ad-hoc projects as assigned\nWHO are we looking for:\nDegree or above in Human Resources, Business Management or related discipline\n4 years' of relevant working experience Independent and able to work in a fast-paced work environment\nMature with good communication and interpersonal skills\nGood command of both written and spoken English & Chinese\nPositive and proactive attitude, and with strong sense of responsibility\nWorking experience in telecommunication, internet or IT industry is preferable\nCandidates with more experience will be considered as Senior Officer\nImmediately available\n***Resume without expected salary and notice of period will NOT be considered***\nCINNOX, a new way to humanise your connections, join us now!\n\nWe offer 5 days\u2019 work, medical insurance, free lunch, competitive salary package and attractive career development opportunities to the right candidate.\u00a0Interested parties please send your full resume with date of availability, present and expected salaries by clicking \"Apply Now\".\n\nFor more information about CINNOX, please visit and subscribe the below linkage:\nCINNOX Webpage\nCINNOX LinkedIn Page\nCINNOX Youtube channel\nTo protect the privacy of personal data, all applications will be treated in strict confidence. Personal data collected will be used for recruitment purposes only. Applicants not hearing from us within 6 weeks may consider their applications unsuccessful. We may also consider their application for other or future vacancies. Personal data of unsuccessful applicants will be retained for a maximum period of 6 months.", "employment_types": ["Full Time", "Permanent"], "selling_points": ["4+ years experience in HR, TA & HR Operations", "Immediate available is preferred", "5 day work, medical benefit and free luncheon"], "locations": ["Kowloon Bay"], "categories": ["Admin & HR", "Compensation & Benefits", "HR Supporting Staff", "Recruitment / Executive Search"], "post_time": "2022-01-13T11:44:23Z", "salary": {"currency": null, "max": null, "min": null, "period": "monthly", "term": null}, "salary_visible": false, "title_keywords": ["human resources officer"], "responsibilities": ["management", "cv screening", "job advertisement", "analysis", "hr", "implementation", "hr reports", "communication", "recruitment process", "ad-hoc projects", "management review", "planning"], "requirements": {"degrees": ["degree or above"], "majors": ["business"], "languages": ["english", "chinese"], "language_level": ["good command"], "hard_skills": ["business management", "analysis", "erp", "rapid", "integration"], "soft_skills": ["passionate", "independent", "responsible", "sense of responsibility", "unique", "mature", "committed", "diverse", "communication and interpersonal skills", "proactive", "driven", "positive"], "languages_combined": [{"language": "english", "language_level": ["good command"]}, {"language": "chinese", "language_level": ["good command"]}]}, "experience_required": {"duration": ["4 years"], "field": ["it", "relevant working experience"]}}, {"job_id": "100003009044893", "location_code": "hk", "company": "Cre8 (Greater China) Limited", "job_title": "HR Specialist (1 year contract)", "description": "Job\u00a0Responsibilities :\n\nManage the recruitment process including job description design, resumes screening, interview, offer negotiation and other logistics arrangement\nAssist the Supervisors to handle daily operations of Compensation & Benefits including Monthly Payroll, Leave & Benefits Administration,\u00a0HR Analysis and Reporting\nProvide support on other HR initiatives and ad hoc duties as assigned\n\n\u00a0Job Requirements :\n\nAssociate Degree or above in any disciplines\nAt least 2 years of relevant recruitment experience\nKnowledge of HR Employment Ordinance, related regulations and practices\nGood written and spoken English and Chinese\nCandidate with less experience would be considered for Human Resources Assistant\n\nWe offer an attractive remuneration package and fringe benefits to the right candidate.\n(Personal data provided will be used for recruitment purpose only)", "employment_types": ["Full Time", "Temporary", "Contract"], "selling_points": ["Manage the recruitment process", "Benefits Administration", "At least 2 years of working experience"], "locations": ["Central"], "categories": ["Admin & HR", "Compensation & Benefits", "HR Supporting Staff", "Recruitment / Executive Search"], "post_time": "2022-01-13T06:34:49Z", "salary": {"currency": null, "max": null, "min": null, "period": "monthly", "term": null}, "salary_visible": false, "title_keywords": ["hr specialist"], "responsibilities": ["ad hoc duties", "reporting", "provide support", "logistics arrangement", "hr", "analysis", "design", "daily operations", "recruitment process", "payroll", "administration"], "requirements": {"degrees": ["degree or above"], "majors": ["any disciplines"], "languages": ["english", "chinese"], "language_level": ["good"], "hard_skills": [], "soft_skills": [], "languages_combined": [{"language": "english", "language_level": ["good"]}, {"language": "chinese", "language_level": ["good"]}]}, "experience_required": {"duration": ["at least 2 years"], "field": ["recruitment", "human resources"]}}, {"job_id": "100003009042275", "location_code": "hk", "company": "AUX International Holdings Limited", "job_title": "Human Resources Manager", "description": "Responsibilities:\u00a0\n\n\nHandle full spectrum of human resources functions including recruitment & selection, compensation & benefits, employee relations, performance management, training and other Administrative functions\nImplement HR policies & procedures to meet company standards\n\nProvide professional HR advices to different business units\n\nLiaise with team heads on various HR issues\nPrepare HR reports and data for management review\nLead or assist any other ad-hoc projects as assigned\n\n\u00a0Requirements:\u00a0\n\n\nDegree or above in Human Resources or related disciplines\nWith min. 8 years' relevant experience in Human Resources functions of which at least 3 years at managerial level; with experience in F&B industry will be an advantage\nWell-versed in Employment Ordinance and related legislations\nGood command of both spoken and written English and Chinese\nExcellent communication and interpersonal skills\nProficient in MS Word and Excel; with experience in using Alpha HRMS will be an advantage\nWell-organized, meticulous and able to handle multi-tasks within deadlines and work independently\nImmediately available is preferred\n\nInterested parties please send your full resume with availability, current/last and expected salary by clicking\u00a0 \u201cAPPLY NOW\u201d\u00a0\n\n\u00a0(Personal data collected will be kept in strictest confidence and be used for recruitment purpose only.)", "employment_types": ["Full Time", "Permanent"], "selling_points": [], "locations": ["Wan Chai"], "categories": ["Admin & HR", "Compensation & Benefits", "HR Director / Manager", "Recruitment / Executive Search"], "post_time": "2022-01-12T10:00:27Z", "salary": {"currency": null, "max": null, "min": null, "period": "monthly", "term": null}, "salary_visible": false, "title_keywords": ["manager", "human resources"], "responsibilities": ["management", "data", "policies", "hr", "procedures", "hr reports", "recruitment", "liaise with", "ad-hoc projects", "human resources functions", "management review"], "requirements": {"degrees": ["degree or above"], "majors": ["related disciplines"], "languages": ["english", "chinese"], "language_level": ["good command"], "hard_skills": ["excel", "ms word"], "soft_skills": ["meticulous", "work independently", "multi-tasks", "well-organized", "communication and interpersonal skills"], "languages_combined": [{"language": "english", "language_level": ["good command"]}, {"language": "chinese", "language_level": ["good command"]}]}, "experience_required": {"duration": ["at least 3 years", "8 years"], "field": ["managerial", "f&b", "relevant experience", "human resources"]}}, {"job_id": "100003009040051", "location_code": "hk", "company": "Hong Kong Aircraft Engineering Co Ltd", "job_title": "Human Resources Specialist, Operations", "description": "Scope of Duties:\u00a0\n\nActive participation and contribution to the process re-engineering in the HR Operations team\nCollect user requirements and identify improvement areas under the direction of management in HR\nLiaise with stakeholders like different teams in HR department, line departments, and supporting departments like IT, FIN, Procurement, etc.\u00a0\nResponsible for daily, transactional HR operations tasks as assigned\nMaintain a strong communication network with all level staff and management team members\nCoordination of tasks and project activities\nResponsible for regular analysis and reports for management review\nHandle staff requests and enquiries\n\nRequirements:\u00a0\n\nA recognised Degree in Human Resources or related disciplines\nMinimum of 5 years of solid experience in Human Resources\nWell-versed in Employment Ordinance and other HR related regulations\nExperience in project coordination\nStrong analytical, reasoning and presentation skills\nProactive, independent and detail-minded with good communication and organizational skills\nGood teamwork\nGood command in both written and spoken English and Chinese\nCandidates with less experience will be considered as Human Resources Executive, Operations\n\nHow to Apply:\n\nPlease send your resume with expected salary, quoting the employer's reference no., to: Human Resources Department - Talent & Partnership Team, Hong Kong Aircraft Engineering Company Limited, 80 South Perimeter Road, Hong Kong International Airport, Lantau, Hong Kong OR submit your application via\u00a0https://careers.haeco.com/hkg/job-openings/\n\nCandidates not contacted 4-6 weeks after submission of applications and/or interviews may consider their application unsuccessful.\n\nAll information provided by candidates will be treated in strict confidence and will be used for employment purpose only.", "employment_types": ["Full Time", "Permanent"], "selling_points": ["A recognised Degree in Human Resources", "Minimum of 5 years of solid experience in HR", "Well-versed in Employment Ordinance"], "locations": ["Airport Area"], "categories": ["Admin & HR", "Others", "Compensation & Benefits", "HR Supporting Staff"], "post_time": "2022-01-12T01:04:20Z", "salary": {"currency": null, "max": null, "min": null, "period": "monthly", "term": null}, "salary_visible": false, "title_keywords": ["operations", "human resources specialist"], "responsibilities": ["management team", "management", "operations", "hr", "analysis", "teams", "management review", "communication", "maintain", "reports", "coordination", "liaise with", "re-engineering"], "requirements": {"degrees": ["degree"], "majors": ["related disciplines"], "languages": ["english", "chinese"], "language_level": ["good command"], "hard_skills": ["no", "aircraft"], "soft_skills": ["detail-minded", "organizational skills", "confidence", "independent", "teamwork", "communication", "presentation skills", "coordination", "proactive"], "languages_combined": [{"language": "english", "language_level": ["good command"]}, {"language": "chinese", "language_level": ["good command"]}]}, "experience_required": {"duration": ["minimum of 5 years"], "field": ["human resources"]}}, {"job_id": "100003009042894", "location_code": "hk", "company": "Hip Hing Construction Co Ltd", "job_title": "Assistant Human Resources Officer (HH-AHRO/JDB)", "description": "Responsibilities\nWork in Human Resources & Training Department to play a role for handling all HR activities such as recruitment & selection, talent management, compensation & benefits and any other HR initiatives as required to support continuous growth of business.\nPrepare periodic statistical reports for management review.\nSupport the formulation and implementation of HR policies, programs and initiatives.\nAssist in ad-hoc projects as assigned.\nRequirements\nDegree in Human Resources Management or equivalent\n3\u00a0years\u00a0relevant HR experience, preferably in Construction / Engineering / Property industry\nExperience in recruitment\u00a0activities would be an advantage\nWell versed in Hong Kong Employment Ordinance and other employment related ordinances\nStrong computer\u00a0literacy in MS Office, particularly PowerPoint, Excel and Word\nGood command of both written and spoken English & Cantonese\nDetail-minded, well-organized and work independently\nImmediately available is preferred\n\nCandidate with more experience will be considered as Human Resources Officer.\n\nAttractive salary and fringe benefits will be offered to the successful candidates. Please apply with full resume, available date, present and expected salary and quoting the reference code on the letter & envelope to THE HUMAN RESOURCES & TRAINING DEPARTMENT, HIP HING CONSTRUCTION CO., LTD., 11/F., Chevalier Commercial Centre, No. 8 Wang Hoi Road, Kowloon Bay, Hong Kong OR click \"Apply Now\" OR fax to 2530 4360.\nCompany Website: www.hiphing.com.hk\nAll personal data collected will be used for recruitment purposes only.\nApplicants who are not invited for an interview within 8 weeks may consider their applications unsuccessful.\n\nPlease enable the \"Pop-up\" setting of your browser, click here for steps.", "employment_types": ["Full Time", "Permanent"], "selling_points": ["Talent acquisition, Data analysis, Reporting", "Recruitment, manpower planning, construction", "Human Resources, employee engagement, Engineering"], "locations": ["Kowloon Bay"], "categories": ["Admin & HR", "Compensation & Benefits", "HR Supporting Staff", "Recruitment / Executive Search"], "post_time": "2022-01-12T09:09:22Z", "salary": {"currency": null, "max": null, "min": null, "period": null, "term": null}, "salary_visible": false, "title_keywords": ["assistant human resources officer"], "responsibilities": ["management", "policies", "hr", "implementation", "recruitment", "reports", "ad-hoc projects", "management review"], "requirements": {"degrees": ["degree"], "majors": [], "languages": ["cantonese", "english"], "language_level": ["good command"], "hard_skills": ["excel", "hong kong employment ordinance", "word", "powerpoint", "ms office"], "soft_skills": ["detail-minded", "computer literacy", "work independently", "well-organized"], "languages_combined": [{"language": "cantonese", "language_level": ["good command"]}, {"language": "english", "language_level": ["good command"]}]}, "experience_required": {"duration": ["3 years"], "field": ["engineering", "hr", "recruitment", "construction", "human resources"]}}, {"job_id": "100003009035639", "location_code": "hk", "company": "ABS (HK) Limited", "job_title": "Human Resources Specialist", "description": "This position is designed to provide comprehensive HR services across the board in different countries in ABS.\u00a0 We are inviting a high caliber candidate to grow with us on this dynamic role:\n\nKEY RESPONSIBILITIES:\n\nProvide full spectrum of HR services such as employment & benefits administration, payroll, taxation, visa management, recruitment support for countries across ABS\nAssist in preparing regular reports, documentation and HR analytics\nParticipate in HR budgeting processes, HR database development and processes streamlined\nSupport HR services enhancement under direction of HR Management\nHandle employees\u2019 enquiries in timely and professional manner, maintain communication / relationship network for staff community, participate in employee engagement initiatives\nPerform ad-hoc assignments and support HR initiatives when required\nREQUIREMENTS:\n\nDegree holder in Human Resources or related disciplines\nMinimum 4 years\u2019 all-rounded HR operations experience in multi-national company with cross countries exposure\nWell-versed in labor laws and HR practices, multi-countries exposure advantage\nSelf-motivated, meticulous, analytical with good interpersonal and communication skills\nGood command of both written and spoken English\nImmediate available highly preferred", "employment_types": ["Full Time"], "selling_points": ["Dynamic role, global HR exposure", "Full spectrum of HR services", "Experience in multi-national company"], "locations": ["Wan Chai"], "categories": ["Admin & HR", "Compensation & Benefits", "HR Supporting Staff", "Recruitment / Executive Search"], "post_time": "2022-01-11T03:31:04Z", "salary": {"currency": null, "max": null, "min": null, "period": "monthly", "term": null}, "salary_visible": false, "title_keywords": ["human resources specialist"], "responsibilities": ["taxation", "management", "budgeting", "hr", "ad-hoc assignments", "professional manner", "communication", "maintain", "recruitment", "reports", "database", "documentation", "payroll", "administration"], "requirements": {"degrees": ["degree holder"], "majors": ["related disciplines"], "languages": ["english"], "language_level": ["good command"], "hard_skills": [], "soft_skills": ["communication skills", "meticulous", "self-motivated", "interpersonal"], "languages_combined": [{"language": "english", "language_level": ["good command"]}]}, "experience_required": {"duration": ["minimum 4 years"], "field": ["hr"]}}, {"job_id": "100003009043448", "location_code": "hk", "company": "KOS International Limited", "job_title": "Senior C&B Officer - Stable Chinese Bank", "description": "About The Client\nOur client is a sizeable Chinese bank in Hong Kong. They are now hiring a Senior C&B Officer with 3+ years of relevant experience to join as part of the HR team.\n\nAbout The Role\nReport into the C&B Lead, you will:\n\nAnalyse, interpret and consolidate salary surveys, analysis, and summarsie key messages and highlight implications for senior management review\nAsissst in C&B enquiries, and support on salary review, job matching, positioning analysis, budgeting and benefits administration\nMaintain HR filings and records and ensure they are in a timely and accurate manner\nParticipate in ad hoc projects as assigned\n\nRequirements\n\nDegree holder in HR Management or related disciplines\n3+ years of C&B experience from sizeable companies, Chinese financial institutions would be an advantage\nSensitive to numbers and good analytical skills\nProficiency in Microsoft Excel, Word and Powerpoint usage\nGood command of English and Chinese (written and spoken)\nImmediate available candidates highly regarded\n\nClick \"Apply Now\" to apply for this position or call Christina Lau at +852 3180 4934 for a confidential discussion. All information collected will be kept in strict confidence and will be used for recruitment purpose only.", "employment_types": ["Full Time", "Permanent"], "selling_points": ["3+ years of C&B experience from banking sector", "Assist in C&B exercises and report consolidation", "Good command in English & Chinese"], "locations": ["Not Specified"], "categories": ["Admin & HR", "Compensation & Benefits", "HR Supporting Staff"], "post_time": "2022-01-12T12:03:40Z", "salary": {"currency": null, "max": null, "min": null, "period": "monthly", "term": null}, "salary_visible": false, "title_keywords": ["officer"], "responsibilities": ["hr", "analysis", "review", "report", "senior management", "analyse"], "requirements": {"degrees": [], "majors": [], "languages": ["chinese"], "language_level": [], "hard_skills": ["analysis"], "soft_skills": [], "languages_combined": [{"language": "chinese", "language_level": []}]}, "experience_required": {"duration": ["3+ years"], "field": ["hr", "relevant experience", "team"]}}, {"job_id": "100003009050039", "location_code": "hk", "company": "Links International", "job_title": "HR Operations - upto 35K/m - WORKDAY - FI", "description": "Our client is a well-established American Investment firm located in Central. We are seeking for a detail-minded and well-organized HR Officer to join their organization. This is a great opportunity for candidate who enjoys energetic and dynamic working environment.\n\nJob Responsibilities\n\nMainy assist with HR Operations including:\nOn-boarding, drafting employment contracts, reference checks, vendor coordination\nHR administration including documentation filing with Workday\nAssist in ad hoc project as assigned\n\nJob Requirements\n\nDegree holder in related disciplines\nHRIS Workday experience is a MUST\nFluent in English, Cantonese and Mandarin\nExcellent attention and possess great organizational skills\n3-5 years of experience in HR Administration\nImmediately available is highly preferred", "employment_types": ["Full Time", "Permanent"], "selling_points": ["Strong in HRIS - WORKDAY", "9 month Contract Mat-Coverage", "Westernized firm, 5 Day week, stable hours"], "locations": ["Not Specified"], "categories": ["Admin & HR", "Compensation & Benefits"], "post_time": "2022-01-14T09:40:12Z", "salary": {"currency": "HKD", "max": 34999, "min": 25000, "period": "monthly", "term": null}, "salary_visible": true, "title_keywords": ["operations", "hr"], "responsibilities": ["ad hoc", "operations", "hr", "contracts", "coordination", "documentation", "administration"], "requirements": {"degrees": ["degree holder"], "majors": ["related disciplines"], "languages": ["cantonese", "english", "mandarin"], "language_level": ["fluent"], "hard_skills": [], "soft_skills": ["organizational skills"], "languages_combined": [{"language": "cantonese", "language_level": ["fluent"]}, {"language": "english", "language_level": ["fluent"]}, {"language": "mandarin", "language_level": ["fluent"]}]}, "experience_required": {"duration": ["3-5 years"], "field": ["hr", "administration"]}}, {"job_id": "100003009043128", "location_code": "hk", "company": "Mason Group Holdings Limited", "job_title": "HR Officer", "description": "Responsibilities\n\nProvide all rounded HR support including Compensation & Benefit, Recruitment, Training and Employee Relations\nManage and maintain employee information and records in HRIS, ensuring that all data are accurate and up-to-date\nResponsible for monthly payroll, MPF, tax filing and HR reports\nAssist in recruitment and termination process including interview arrangement, preparation of employment contracts, on-boarding and exit formalities\nPerform general office administrative support and ad hoc assignments as required\n\nRequirements\n\nBachelor degree in any discipline with at least 5 years relevant working experiences\nWell versed in Hong Kong Labour Ordinance and HR practices\nExcellent organizational skills, accurate, detail minded and multi-tasking\nGood command of both written and spoken Chinese and English, Putonghua a plus\nProficient in MS Word, Excel, PowerPoint and Chinese word processing\nImmediate available preferred\n\n\n\nInterested parties, please submit your full resume with your availability, current & expected salary by clicking \"Apply Now\".\n\n\nPersonal data provided by job applicants will be used for recruitment purpose only.", "employment_types": ["Full Time", "Permanent"], "selling_points": [], "locations": ["Central"], "categories": ["Admin & HR", "Compensation & Benefits", "HR Supporting Staff", "Recruitment / Executive Search"], "post_time": "2022-01-12T09:52:22Z", "salary": {"currency": null, "max": null, "min": null, "period": "monthly", "term": null}, "salary_visible": false, "title_keywords": ["hr officer"], "responsibilities": ["mpf", "data", "administrative support", "contracts", "hr", "tax filing", "hr reports", "maintain", "recruitment", "ad hoc assignments", "interview arrangement", "payroll"], "requirements": {"degrees": ["degree", "bachelor"], "majors": [], "languages": ["putonghua", "english", "chinese"], "language_level": ["good command", "proficient"], "hard_skills": ["excel", "plus", "chinese word processing", "powerpoint", "ms word"], "soft_skills": ["organizational skills", "multi-tasking", "accurate"], "languages_combined": [{"language": "putonghua", "language_level": ["good command"]}, {"language": "english", "language_level": ["good command"]}, {"language": "chinese", "language_level": ["good command", "proficient"]}]}, "experience_required": {"duration": ["at least 5 years"], "field": []}}, {"job_id": "100003009042901", "location_code": "hk", "company": "Leigh & Orange Limited", "job_title": "Human Resources Officer (Ref : LO_HRO_202201)", "description": "Responsibilities:\n\nTo perform full cycle of recruitment process including but not limited to job posting, CV screening, contract preparation and on-boarding process\nTo provide HR supports in payment management, leave management, insurance, employee compensation, taxation etc.\nTo maintain and update personnel records in HRIS system\nTo consolidate HR data and prepare the various reports for management\nTo assist in reviewing company policies and benefits\nTo assist in HRIS maintenance and enhancement\n\nRequirements:\n\n\nBachelor degree holder in Human Resources Management, Business Administration or any related disciplines.\n2-3 years of relevant experience in Human Resources, experience in Architectural/Engineering industry is preferable\nHighly organization with ability to manage multiple priorities in a fast-paced environment and achieve results in a timely manner\nGood command of written and spoken English and Chinese\nGood interpersonal, communication and relationship managements skills\nWell-versed knowledge with employment ordinance and others Human Resources related statutory regulations\nStrong attention to details/deadlines and capable to work under pressure\nGood teamwork player, self-motivated and able to work independently\nImmediate available is highly preferred\nApplicant will less experience will be considered as Human Resources Assistant\nPlease send resume together with expected salary to the Human Resources Department or by clicking\u00a0\"Apply Now\".\n(We are an equal opportunity employer and welcome applications from all qualified candidates. All applications will be treated in the strictest confidence. Personal data provided will be used for recruitment purposes only. We do not assume any risks of disclosure of personal information prior to receipt of applications.\n\nUnder the Personal Data (Privacy) Ordinance, you may request access to, and/or correction of your personal data in relation to your application. If you wish to do so, please email to us)\n\n\u00a0", "employment_types": ["Full Time"], "selling_points": [], "locations": ["Quarry Bay"], "categories": ["Admin & HR", "Compensation & Benefits", "Recruitment / Executive Search"], "post_time": "2022-01-12T09:11:12Z", "salary": {"currency": null, "max": null, "min": null, "period": "monthly", "term": null}, "salary_visible": false, "title_keywords": ["human resources officer"], "responsibilities": ["taxation", "management", "cv screening", "data", "hr", "personnel records", "payment", "maintain", "reports", "recruitment process", "insurance"], "requirements": {"degrees": [], "majors": [], "languages": [], "language_level": [], "hard_skills": [], "soft_skills": [], "languages_combined": []}, "experience_required": {"duration": [], "field": []}}, {"job_id": "100003009048075", "location_code": "hk", "company": "ADECCO", "job_title": "HR Executive", "description": "Our Hong Kong team has an exciting new opportunity for an energetic individual to join us as a HR Executive. If you enjoy working in a fast-paced and high-performance environment, we would love to speak to yo today!\n\nJob Responsibilities:\n\nProvide full spectrum of human resources support and develop of HR initiatives, including but not limited to talent acquisition, compensation & benefits, learning & development and staff engagement\nResponsible for all compensation and benefits administration matters, such as processing monthly payroll calculations, final payment, leave record management and medical insurance administration for HK & Macau\nAdminister the Mandatory Provident Fund Scheme, such as enrolment and termination of members and preparing for monthly contribution\nSupport in recruitment process, including but not limited to job ads posting, screening, interviewing and preparing documents for onboarding\nTo maintain and update HRIS and participate in HRIS enhancement\nEngage in the preparation of all HR related reports and analysis\nPerform ad hoc assignments as required\n\nRequirement:\n\nBachelor's degree preferably in human resources or business administration\n2-3 years relevant experiences gained in sizeable company is preferred\nWell-versed in both HK and Macau employment ordinance and MPF regulations\nProficient in MS Office applications (Excel, Word, PowerPoint and Chinese Word Processing)\u00a0\nExcellent interpersonal and communication skills\nDetail-mined, mature and good team player\n\nFresh Graduate will also be considered for HR Assistant\n\nPlease note that only shortlisted candidates will be notified. All information gathered will be treated in strict confidential and solely used for recruitment purposes.", "employment_types": ["Full Time", "Permanent"], "selling_points": ["Develop HR initiatives", "Talent Acquisition", "Learning & Development"], "locations": ["North Point"], "categories": ["Admin & HR", "Compensation & Benefits", "Recruitment / Executive Search", "Training & Development"], "post_time": "2022-01-14T04:41:45Z", "salary": {"currency": null, "max": null, "min": null, "period": "monthly", "term": null}, "salary_visible": false, "title_keywords": ["hr", "executive"], "responsibilities": ["management", "hr", "analysis", "develop", "payment", "maintain", "reports", "ad hoc assignments", "insurance", "recruitment process", "payroll", "administration"], "requirements": {"degrees": ["degree", "bachelor", "fresh graduate"], "majors": ["business administration"], "languages": ["chinese"], "language_level": ["proficient"], "hard_skills": ["excel", "chinese word processing", "word", "powerpoint", "mpf regulations", "ms office"], "soft_skills": ["communication skills", "good team player", "interpersonal", "mature"], "languages_combined": [{"language": "chinese", "language_level": ["proficient"]}]}, "experience_required": {"duration": ["2-3 years"], "field": []}}, {"job_id": "100003009042988", "location_code": "hk", "company": "SinoMab BioScience Ltd", "job_title": "Human Resources & Administration Manager (5 days)", "description": "Responsibilities\n\nReporting to CEO, you will be responsible for:\n\nMatters related to HR & Admin in Hong Kong Headquarter\nCoordinating with HR departments in different locations in China to ensure policy consistency and compliance according to listing rules in Hong Kong\u00a0\nAssisting CEO for executing organizational development for the company, including company structure, recruitment, job changes and other organizational development matters\nManaging compensation, benefits, and payroll administration to ensure fair and consistentpractice in accordance with salary administration guidelines as stipulated by Hong Kong Headquarterand local legislation\nPrepare/Review & implement the annual HR budget\nReview and implement HR policies and procedures\nEnsuring confidentiality of data, which, if disclosed, might have significant internal effect or minor external effects\nManage daily office administrative functions\nPlan and organize staff activities and company events\nLiaise with internal and external parties\nOther ad hoc duties\n\nRequirements\n\nThe applicant should possess:\n\nUniversity Degree of relevant disciplines\nPrevious working experience in Hong Kong companies, preferably with mainland subsidiaries or business\nMinimum 10 years of human resources experience, with at least 4 years in a management capacity\nAll-round HR team leadership characterized with a positive, personable and supportive manner, a strong business partnering approach and hands on & can do attitude\nGood in HK Employment Ordinance and PRC labour ordinance is preferred\u00a0\nGood communication skills and team-work player mentality, and capabilities to work in a mature, well-organized, self-motivated, and detail oriented manner & willingness to work\u00a0under pressure and overtime\nFluency in English, Cantonese and Mandarin\nWillingness to travel occasionally including to mainland\nImmediate availability is an advantage\n\nWe offer\u00a0\n\nFive-day work week\nMedical insurance\u00a0\nDental insurance\n13 month salary", "employment_types": ["Full Time", "Permanent"], "selling_points": ["Five-day work", "HR & Admin Manager", "Medical & Dental insurance & 13 month salary"], "locations": ["Shatin Area"], "categories": ["Admin & HR", "Compensation & Benefits", "HR Director / Manager", "Recruitment / Executive Search"], "post_time": "2022-01-12T09:26:00Z", "salary": {"currency": null, "max": null, "min": null, "period": "monthly", "term": null}, "salary_visible": false, "title_keywords": ["administration manager", "human resources"], "responsibilities": ["ad hoc duties", "reporting", "data", "guidelines", "policies", "hr", "compliance", "review", "budget", "procedures", "internal and external parties", "executing", "recruitment", "plan", "liaise with", "payroll", "listing", "administration"], "requirements": {"degrees": ["university degree"], "majors": [], "languages": ["cantonese", "english", "mandarin"], "language_level": ["fluency"], "hard_skills": [], "soft_skills": ["communication skills", "supportive", "personable", "self-motivated", "under pressure", "detail oriented", "well-organized", "mature", "hands on", "willingness to work", "leadership", "positive"], "languages_combined": [{"language": "cantonese", "language_level": ["fluency"]}, {"language": "english", "language_level": ["fluency"]}, {"language": "mandarin", "language_level": ["fluency"]}]}, "experience_required": {"duration": ["at least 4 years", "minimum 10 years"], "field": ["management", "business", "human resources"]}}, {"job_id": "100003009043388", "location_code": "hk", "company": "Eco-Green Group Limited", "job_title": "Human Resources & Administration Manager/ Officer", "description": "*Candidate with more experience will be considered as\u00a0Manager.\n\n\n\u00a0Responsibilities:\u00a0\n\nPerform full spectrum of Human Resources functions;\nHandle payroll calculation, taxation, MPF administration and staff attendance record;\n\nResponsible for recruitment & selection, compensation & benefits administration, performance management and employee relations;\nResponsible for\u00a0review, development and implementation of\u00a0company policies/procedures pertaining to resources management;\nPerform ad hoc assignments and projects as assigned by management to support the\u00a0business goals.\n\nRequirements:\n\nHigher Diploma or above in Human Resources Management, Business Administration or relevant disciplines;\nMinimum 3 year of relevant working experience, preferably in Construction and Engineering industry;\nWell versed in HK employment Ordinances and related legislation;\nHighly\u00a0organized, trust-worthy and\u00a0independent;\nGood command of written and spoken\u00a0\u00a0English, Chinese & Mandarin;\nGood interpersonal, strong communication and negotiation skills;\nAble to work under pressure and result oriented;\nImmediate available is highly preferred.\n\nWe offer reasonable remuneration packages, include year-end bonus, annual leave, public holiday, 5.5 day\u00a0work /\u00a06 day\u00a0 (alternative leave),\u00a0as well as good career prospects for the right applicant. Interested parties, welcome to browse to our web site hk-egg.com, and send detail resume with expected salary & date availability by clicking \"Apply Now\"\u00a0\n\nPersonal data will be used for recruitment purpose only.", "employment_types": ["Full Time", "Permanent"], "selling_points": ["Human Resources", "Business Administration", "Construction"], "locations": ["Kowloon Bay"], "categories": ["Admin & HR", "Compensation & Benefits", "HR Director / Manager", "Recruitment / Executive Search"], "post_time": "2022-01-12T11:20:49Z", "salary": {"currency": null, "max": null, "min": null, "period": "monthly", "term": null}, "salary_visible": false, "title_keywords": ["administration manager", "officer", "human resources"], "responsibilities": ["taxation", "attendance", "mpf", "payroll", "human resources functions", "administration"], "requirements": {"degrees": [], "majors": [], "languages": [], "language_level": [], "hard_skills": [], "soft_skills": [], "languages_combined": []}, "experience_required": {"duration": [], "field": []}}, {"job_id": "100003009040113", "location_code": "hk", "company": "aimHigher Consultancy Limited", "job_title": "Human Resources Manager (C&B) / F&B Chain", "description": "Company Description\n\nOur client is a well-known restaurant chain. Due to business needs, they are currently looking for a Human Resources Manager (C&B).\u00a0\n\nResponsibilities\n\nHandle monthly payroll in an accurate and timely manner covering payroll calculation, administration of incentive schemes, tax returns, medical insurance, MPF and final payments for frontline staff\nConduct data analysis and prepare periodical reports\u00a0\nAssist in HR annual process such as salary review, performance management, Bench-marking, staff cost budgeting and allocation of employee benefits for frontline staff\nPrepare the necessary official documents for newly on board staff, internal transfers, promotions and departures; and communicate with the involved staff accordingly.\u00a0\nManage, review and improve the payroll process and policies for operational excellence.\n\nRequirements\n\nBachelor\u2019s Degree holder in Human Resources, Business Administration or any related discipline\nOver 10 years experience in C&B area is a must. F&B, FMCG and Retails experience is a plus.\nSolid experience in leading a small team and a good problem-solver\nWell-versed with Hong Kong Employment Ordinance and other relevant Ordinances\nGood analytical skills and possess excellent presentation skill\nProficiency in HRIS, MS applications (Word, Excel, Power point) and Chinese word processing\nGood command in both written and spoken English and Chinese\nInterested parties please send your updated resume in WORD format with current and expected salaries (quoting Employer Ref:)", "employment_types": ["Full Time"], "selling_points": ["Leading food & beverage company", "Rapid expansion", "Excellent exposure"], "locations": ["Not Specified"], "categories": ["Admin & HR", "Others", "Compensation & Benefits", "HR Director / Manager"], "post_time": "2022-01-12T01:28:54Z", "salary": {"currency": null, "max": null, "min": null, "period": "monthly", "term": null}, "salary_visible": false, "title_keywords": ["manager", "human resources"], "responsibilities": ["tax", "communicate with", "management", "cost", "mpf", "budgeting", "hr", "review", "policies", "data analysis", "payments", "reports", "insurance", "payroll", "administration"], "requirements": {"degrees": ["bachelor", "degree holder"], "majors": ["business administration"], "languages": ["english", "chinese"], "language_level": ["proficiency", "good command"], "hard_skills": ["small", "presentation skill", "plus", "excel", "hong kong employment ordinance", "ms applications", "chinese word processing", "word", "analytical skills", "power point"], "soft_skills": ["presentation skill", "analytical skills"], "languages_combined": [{"language": "english", "language_level": ["good command"]}, {"language": "chinese", "language_level": ["proficiency", "good command"]}]}, "experience_required": {"duration": ["10 years"], "field": ["f&b", "fmcg", "team"]}}, {"job_id": "100003009044706", "location_code": "hk", "company": "J Blooming International Limited", "job_title": "Assistant Officer, Admin and HR (5-day work)", "description": "Responsibilities:\n\nAssist HR & Admin Manager to provide clerical support on daily operation of administration and HR duties\nPerform and handle general office administrative duties including equipment procurement, maintenance, license renewal and invoice processing, etc related administration tasks\nResponsible for human resources duties, including recruiting arrangement, on/ off boarding preparation, attendance records, \u00a0payroll and MPF, etc\nHandle data input, invoice billing and filing in systematic with timelines\nHandle other ad-hoc projects as required\n\n\u00a0Requirements:\n\nAssociate degree or above\u00a0in BA or HR related disciplines\nMinimum 2\u00a0years' relevant experience in F&B or/ and retail industry\nProficiency in PC skill and MS office application\nGood command of spoken and written English\nWell-versed\u00a0in Employment Ordinance, MPF regulations and other statutory ordinances\nAble to work independently, teamwork and good communication with people\nMore experience candidate will be considered as Admin & HR Officer\n\nWe offer 5 days work week with competitive salary, discretionary performance bonus, birthday leave, staff discount, free lunch to the right candidate.\u00a0 Interested parties, please send your resume with expected salary and availability to us.\u00a0 All data collected will be used for recruitment purpose only.\u00a0", "employment_types": ["Full Time"], "selling_points": [], "locations": ["Tsuen Wan Area"], "categories": ["Admin & HR", "Clerical / Admin Staff", "Compensation & Benefits", "HR Supporting Staff"], "post_time": "2022-01-13T05:39:14Z", "salary": {"currency": null, "max": null, "min": null, "period": "monthly", "term": null}, "salary_visible": false, "title_keywords": ["assistant officer", "hr", "admin"], "responsibilities": ["provide clerical support", "attendance", "mpf", "maintenance", "invoice", "hr", "daily operation", "hr duties", "data input", "administrative duties", "ad-hoc projects", "payroll", "administration"], "requirements": {"degrees": ["degree or above"], "majors": ["related disciplines"], "languages": ["english"], "language_level": ["good command"], "hard_skills": ["mpf regulations", "pc skill", "ms office"], "soft_skills": ["communication", "work independently", "teamwork"], "languages_combined": [{"language": "english", "language_level": ["good command"]}]}, "experience_required": {"duration": ["minimum 2 years"], "field": ["retail industry", "hr", "f&b", "admin", "relevant experience"]}}, {"job_id": "100003009040209", "location_code": "hk", "company": "Robert Walters (HK)", "job_title": "C&B Operations Manager (Engineering Services)", "description": "Our client is a leading provider of engineering services, products and sourcing & contracting expertise. With more than 4,000 staff across the Asia Pacific region. Reputable market leader which has been involved in the various major projects in HK and around the region. They are looking for a C&B operation Manager to lead their high performing team.\n\nAbout the Role:\n*Responsible to look after the C&B functions for both front line and back office with around 1500 headcounts, supervising and lead a small team to handle C&B operations such as payroll processes, MPF & benefits administration, manage projects such as processes enhancement and work-flow streamlining\n*To conduct market survey, salary bench-marking and job grading exercises. Manage C&B initiatives such as annual salary review, budgeting or other related activities\n*Review and develop HR policies to ensure it compliance with local labour law\n*Perform ad-hoc projects as assigned\n\n\nAbout the People:\n*Bachelor's degree Holder in Human Resources or any related discipline\n*At least 10-12 years of related experiences gained from sizeable companies\n*Sensitive with numbers and strong in number crunching. Solid experiences in C&B operations, with excellent communication skills and comfortable to supervise a small team\n*Proficient in written and spoken Chinese (Cantonese and Mandarin) and English", "employment_types": ["Full Time", "Permanent"], "selling_points": ["Leading provider in Engineering Services", "C&B operations Role", "Stable and high performing team"], "locations": ["Not Specified"], "categories": ["Admin & HR", "Administration / Operation Manager", "Others", "Compensation & Benefits"], "post_time": "2022-01-12T01:52:36Z", "salary": {"currency": "HKD", "max": 54999, "min": 45000, "period": "monthly", "term": null}, "salary_visible": true, "title_keywords": ["operations manager"], "responsibilities": ["supervising", "mpf", "operations", "lead a small team", "review", "budgeting", "back office", "hr", "develop", "policies", "compliance", "communication", "contracting", "manage projects", "ad-hoc projects", "payroll", "administration"], "requirements": {"degrees": ["bachelor", "degree holder"], "majors": [], "languages": ["cantonese", "english", "chinese", "mandarin"], "language_level": ["proficient"], "hard_skills": ["small"], "soft_skills": ["communication skills", "responsible", "sensitive"], "languages_combined": [{"language": "cantonese", "language_level": ["proficient"]}, {"language": "english", "language_level": ["proficient"]}, {"language": "chinese", "language_level": ["proficient"]}, {"language": "mandarin", "language_level": ["proficient"]}]}, "experience_required": {"duration": ["at least 10-12 years"], "field": ["related", "team"]}}, {"job_id": "100003009039994", "location_code": "hk", "company": "Jobson Mores Limited", "job_title": "Human Capital Consulting - Compensation & Benefits Director", "description": "About the Client\n\nMy client is a leading global advisory offering risk management, insurance brokerage and Human Capital & Benefits solutions to clients around the globe.\u00a0\n\nAbout the Position\n\nPrimary objective of the team is providing strategy, design and execution support critical for paying employees appropriately and enabling organizations to attract, retain, motivate, and engage employees efficiently and cost-effectively.\n\nTheir portfolio of services includes but not limited to global total rewards philosophy development, career frameworks, compensation benchmarking and structures, incentive plans designing, Rewards program implementation etc.\n\nAs a Director, you report into the Head of Compensation & Benefits in Hong Kong, responsible for leading project teams, managing and developing talents, leading the team to execute business development and managing client relationships.\n\nAbout YOU\n\n10+ years of HR Compensation & Benefits/ Rewards experience within Financial industry, Banks, Securities or Insurance firms\nPrevious experience in HR Consulting is a strong plus\nStrong market knowledge\nSolid communication skills with the ability in discussing complex issues and offering various solutions to clients\nProven project management & presentation skills\nExperience and ability in developing high performing consulting team\nGood command of written and oral English and Mandarin", "employment_types": ["Full Time", "Permanent"], "selling_points": ["10+ yrs C&B/ Rewards exp in FI/ Banking/ Insurance", "Strong brand with established client networks", "Great opportunity/ exposure for HR professionals"], "locations": ["Central & Western Area"], "categories": ["Banking / Finance", "Project Finance", "Admin & HR", "Compensation & Benefits", "HR Director / Manager"], "post_time": "2022-01-11T18:29:13Z", "salary": {"currency": "HKD", "max": 119999, "min": 70000, "period": "monthly", "term": null}, "salary_visible": true, "title_keywords": ["director"], "responsibilities": [], "requirements": {"degrees": [], "majors": [], "languages": [], "language_level": [], "hard_skills": [], "soft_skills": [], "languages_combined": []}, "experience_required": {"duration": [], "field": []}}, {"job_id": "100003009045848", "location_code": "hk", "company": "GF Holdings (Hong Kong) Corporation Ltd", "job_title": "Analyst, Human Resources", "description": "Responsibilities\n\nInvolve in coordinating the recruitment related activities including maintaining, recruitment database, interview arrangements, progress reports, invoice payment etc.;\nAssist in new joiner\u2019s on-boarding processes and employment reference check;\nManage internal record including staff personal information, leave record, training record and training sponsorship;\nProvide data input & update and administrative support to HR Department;\nManage new and renewal employment visa process;\nPrepare HR related reports and PowerPoint;\nTake part of ad hoc HR projects or tasks.\nRequirement\n\nDegree holder in Human Resources Management, Business Administration or related disciplines;\n1 years\u2019 work experience in human resources, administration; fresh graduates will also be considered;\nExcellent command of written and spoken English and Chinese (including Cantonese and Putonghua)\nProficient in MS Office (Excel, Word, PowerPoint, Outlook) & Chinese word processing;\nGood team player with effective communication and interpersonal skills;\nHighly organized with the ability to prioritize and able to handle multi-tasks;\nDemonstrate a high level of accuracy a detailed orientation;\nImmediately available is preferred.\nWe offer attractive remuneration package and fringe benefits to the right candidate. Interested applicants please send detailed resume stating present & expected salaries and date of availability to Human Resources Department by clicking \"APPLY NOW\".\u00a0\n\nFurther information about our group companies can be found at www.gfgroup.com.hk and www.gf.com.cn.\u00a0\n\nAll applications will be treated in the strictest confidence and personal data collected will be used for recruitment purpose only.", "employment_types": ["Full Time"], "selling_points": ["Fresh graduates will also be considered", "Involve in coordinating the recruitment activities", "Provide data and administrative support to HR Dept"], "locations": ["Sheung Wan"], "categories": ["Admin & HR", "Compensation & Benefits", "HR Supporting Staff", "Recruitment / Executive Search"], "post_time": "2022-01-13T08:54:13Z", "salary": {"currency": null, "max": null, "min": null, "period": "monthly", "term": null}, "salary_visible": false, "title_keywords": ["analyst", "human resources"], "responsibilities": ["ad hoc", "maintaining", "progress reports", "invoice", "administrative support", "hr", "data input", "payment", "recruitment", "reports", "database"], "requirements": {"degrees": ["degree holder"], "majors": ["related disciplines", "business administration"], "languages": ["cantonese", "putonghua", "english", "chinese"], "language_level": ["excellent", "proficient"], "hard_skills": ["excel", "chinese word processing", "word", "powerpoint", "outlook", "ms office"], "soft_skills": ["organized", "good team player", "multi-tasks", "prioritize", "communication and interpersonal skills", "detailed"], "languages_combined": [{"language": "cantonese", "language_level": ["excellent"]}, {"language": "putonghua", "language_level": ["excellent"]}, {"language": "english", "language_level": ["excellent"]}, {"language": "chinese", "language_level": ["proficient", "excellent"]}]}, "experience_required": {"duration": ["1 years"], "field": ["human resources", "administration"]}}, {"job_id": "100003009032518", "location_code": "hk", "company": "The Great Eagle Group of Companies", "job_title": "Assistant Human Resources Manager", "description": "Responsibilities:\n\nAssist in managing the operation of compensation & benefits functions including but not limited to monthly payroll, HR audit, tax filing, benefits enrolment and termination, and leave administrations\nAssist in annual review exercise and C&B projects including but not limited to salary review, review and renew medical benefits and insurance plans\nAssist to formulate, review and implement policies and procedures\nLiaise with insurance agent on various employee compensation issues\nOrganize company events and staff activities\nMonitor and supervise the team to complete the tasks\nHandle ad hoc assignments and duties as required\n\nRequirements:\n\nDegree holder or above in Human Resources Management or related disciplines\n5 \u2013 8 years\u2019 experience in human resources in which at least 3 years in supervisory level, preferably gained in sizeable companies or diversified organizations\nExperience gained in property developer will be advantage\nWell-versed in Hong Kong Employment Ordinance and other employment-related ordinances\nWell-organized, result-oriented and able to handle multi tasks simultaneously\nSelf-motivated and able to work under pressure and tight schedule\nPleasant personality with strong communication and interpersonal skills\nProficient in MS Office applications and Chinese word processing\nExperience in using Oracle and IPL will be advantage\nGood command of both written and spoken English and Chinese\n\nSalary and benefits will be commensurate with qualifications and experience.\u00a0 Interested parties, please send a full resume with present and expected salary, and date available to The Human Resources Department, 32/F., Great Eagle Centre, 23 Harbour Road, Wanchai, Hong Kong or e-mail to us.\u00a0\u00a0(Please quote the reference no. on the envelope and the covering letter.)\n\nTo know more about us, please visit our website at http://www.greateagle.com.hk.\n\nWe are an equal opportunity employer and welcome applications from all qualified candidates.\n\nPersonal data collected will be treated in strict confidence and used only for recruitment-related purpose. Applicants who have not heard from us within four weeks may consider their applications unsuccessful. All personal data will be destroyed after 12 months.", "employment_types": ["Full Time", "Permanent"], "selling_points": ["Compensation & benefits functions", "Employee compensation issues", "Payroll, Insurance plans"], "locations": ["Wan Chai"], "categories": ["Admin & HR", "Others", "Compensation & Benefits", "HR Director / Manager"], "post_time": "2022-01-10T03:41:13Z", "salary": {"currency": null, "max": null, "min": null, "period": "monthly", "term": null}, "salary_visible": false, "title_keywords": ["assistant human resources manager"], "responsibilities": ["tax filing", "hr", "payroll", "audit"], "requirements": {"degrees": [], "majors": [], "languages": [], "language_level": [], "hard_skills": [], "soft_skills": [], "languages_combined": []}, "experience_required": {"duration": [], "field": []}}, {"job_id": "100003009044923", "location_code": "hk", "company": "Manrison Personnel Limited", "job_title": "Human Resources Officer (Medical industry, up to 35K)", "description": "Our client, the world\u2019s leading provider of genomic sequencing services and proteomic services, dedicated to hire an all rounded Human Resources Officer to support their daily operations.\n\nResponsibilities:\n\nPerform all rounded HR Generalist duties major in Compensation & Benefits and daily operations\nHandle MPF administration, taxation, payroll calculation and prepare final payment\nAdministrate monthly payroll for the companies\nAssist in coordinate employee relations activities, training arrangement, delivery of in-house training & seminar\nCompile regular HR related statistics and reports for management review\nParticipate in ad hoc duties as assigned\n\nRequirements\n\nDegree in Human Resources Management or related disciplines;\nAt least\u00a0 years solid experience in Human Resources, preferably in healthcare, medical industry;\nWell versed in Hong Kong Employment Ordinance and other HR related ordinances;\nPositive thinking, attentive to details, independent and good team-player;\nGood interpersonal and communication skills;\nProficient in MS Word, Excel, PowerPoint and Chinese Word Processing;\nGood commend in both written and spoken English & Chinese\n\n***Immediate available is highly preferred\n\nTo apply for this position, please simply click on the \u201cAPPLY NOW\u201d bottom to forward an up-to-date copy of your resume. All applications will be treated in strict confidence and used for recruitment purposes only. If this job isn't quite right for you but you are looking for a new position, please contact Ms. Fung at 6110-5379 for a confidential discussion on your career.", "employment_types": ["Full Time", "Permanent"], "selling_points": ["8-10 year work experience", "5-day work, Attractive Salary Package", "Dynamic work environment"], "locations": ["Tai Po Area"], "categories": ["Admin & HR", "Compensation & Benefits", "HR Supporting Staff", "Recruitment / Executive Search"], "post_time": "2022-01-13T06:38:37Z", "salary": {"currency": "HKD", "max": 34999, "min": 30000, "period": "monthly", "term": null}, "salary_visible": true, "title_keywords": ["human resources officer"], "responsibilities": [], "requirements": {"degrees": [], "majors": [], "languages": [], "language_level": [], "hard_skills": [], "soft_skills": [], "languages_combined": []}, "experience_required": {"duration": [], "field": []}}, {"job_id": "100003009037766", "location_code": "hk", "company": "Xcelom Limited", "job_title": "Human Resources Executive", "description": "Job Responsibilities\n\n\n\nResponsible for end-to-end recruitment activities, on/off-boarding arrangement, leave and attendance, employee relations and other HR services in daily operation.\nCoordinate CV screening, interview scheduling and reference checks on candidates.\nProvide administrative support and maintain accurate & update staff information and records via HRIS.\nAssist to review and formulate company policies and procedures if needed.\nAssist to develop training programs for operational staff to meet business needs.\nAssists to coordinate the company events.\nPerform any ad hoc projects/assignments as requested.\n\nJob Requirements\n\nDegree holder in Human Resources or related disciplines\nMinimum 2-year of solid experience in HR function\nKnowledge in HK employment ordinance\nResponsible, ability to work at fast paced environment and able to work under pressure\nWell-organized, self-motivated, multi-tasked, meticulous and detail-minded with excellent communication and interpersonal skills\nGood command of written and spoken English and Chinese (Mandarin)\nCandidate with more experience will be considered as Senior Human Resources Executive\nImmediate available will be an advantage\n\n\n\nApplication:\n\nWe offer medical insurance coverage, double pay, discretionary performance bonus, and external training opportunities in management / science to the right candidate. Please apply with your resume with details of qualification, experience, present and expected salary to us.\n\n\n\u00a0All personal data collected would be used for recruitment purpose only.", "employment_types": ["Full Time", "Permanent"], "selling_points": ["Experience in recruitment is highly preferred", "Experience in staff activities organizing", "Well versed in HK Labour Law"], "locations": ["Shatin Area"], "categories": ["Admin & HR", "Clerical / Admin Staff", "Compensation & Benefits", "HR Supporting Staff"], "post_time": "2022-01-11T03:47:02Z", "salary": {"currency": null, "max": null, "min": null, "period": "monthly", "term": null}, "salary_visible": false, "title_keywords": ["human resources executive"], "responsibilities": ["attendance", "cv screening", "policies", "hr", "review", "daily operation", "procedures", "develop", "coordinate", "scheduling", "maintain", "recruitment", "ad hoc projects", "provide administrative support"], "requirements": {"degrees": ["degree holder"], "majors": ["related disciplines"], "languages": ["english", "chinese", "mandarin"], "language_level": ["good command"], "hard_skills": [], "soft_skills": ["detail-minded", "meticulous", "self-motivated", "responsible", "well-organized", "multi-tasked", "communication and interpersonal skills", "work under pressure"], "languages_combined": [{"language": "english", "language_level": ["good command"]}, {"language": "chinese", "language_level": ["good command"]}, {"language": "mandarin", "language_level": ["good command"]}]}, "experience_required": {"duration": ["minimum 2-year"], "field": ["hr", "human resources"]}}, {"job_id": "100003009039510", "location_code": "hk", "company": "Rise Associates Asia Limited", "job_title": "Human Resources Manager (C&B)", "description": "Our client is a large scale media company.\u00a0They are now looking for a HR Manager to lead the C&B team.\u00a0\u00a0\n\nJob Descriptions:\n\nLead a small team and provide full spectrum of C&B functions to designated business units\nPerform and handle all payroll functions including but not limited to monthly payroll, final payment, MPF administration, tax filing and leave calculation; .\nEnsure compliance to local regulatory obligations and seamless provision of payroll& related HR services\nMonitor and manage all payroll activities to produce accurate and timely delivery of payroll services;\nReview existing policies and procedures, drive process improvement to ensure best-practice operation;\nAssist in preparing various analysis, annual & budgeting reports for management review;\nParticipate in system tests for system upgrade and enhancement activities;\nEnsure all HR information systems are updated and accurate;\nPerform other ad hoc duties as assigned.\nRequirements:\n\nBachelor Degree holder in Business Administration or HRM or related discipline\nAt least 8 years of work experience in C&B and hands-on payroll process including 4 years of experience at supervisory level\nWell versed in Hong Kong Employment Ordinance, relevant law and regulations. Strong numerical sense\nFast-paced, detailed mind, resilience with high level of integrity\nProficiency in MS Excel, strong knowledge and experience in using IPL system is required\nGood command of spoken and written English and Chinese, Putonghua\nCandidate with less experience will be considered as Assistant HR Manager\u00a0", "employment_types": ["Permanent"], "selling_points": ["8 yrs exp. in C&B in sizable companies", "Strong leadership skill, detail-minded", "Immediate available is preferred"], "locations": ["Not Specified"], "categories": ["Admin & HR", "Others", "Compensation & Benefits", "HR Director / Manager"], "post_time": "2022-01-11T09:56:57Z", "salary": {"currency": null, "max": null, "min": null, "period": "monthly", "term": null}, "salary_visible": false, "title_keywords": ["manager", "human resources"], "responsibilities": ["ad hoc duties", "mpf", "budgeting", "policies", "lead a small team", "tax filing", "hr", "monitor", "review", "ensure compliance", "procedures", "analysis", "payment", "systems", "reports", "payroll", "management review", "administration"], "requirements": {"degrees": ["bachelor degree holder"], "majors": ["business administration"], "languages": ["putonghua", "english", "chinese"], "language_level": ["good command"], "hard_skills": ["ms excel", "ipl", "hong kong employment ordinance"], "soft_skills": ["hands-on", "detailed mind", "integrity"], "languages_combined": [{"language": "putonghua", "language_level": ["good command"]}, {"language": "english", "language_level": ["good command"]}, {"language": "chinese", "language_level": ["good command"]}]}, "experience_required": {"duration": ["at least 8 years", "4 years"], "field": ["supervisory level", "hr", "payroll"]}}, {"job_id": "100003009044546", "location_code": "hk", "company": "Primasia Corporate Services Limited", "job_title": "Payroll Officer / Assistant Accountant for Client Accounts (Fresh Graduate Welcome)", "description": "Payroll Officer (Corporate Services Company)\n\nJob Description\u00a0\u00a0\n\nResponsible for payroll calculation and execution\nInput data into payroll software and maintenance of staff information\nPrepare monthly MPF remittance statements and payment for submission\nManage benefits administration including but not limited to leave management and medical benefits\nPrepare Hong Kong tax reporting and respond to enquiries from employees, local regulators and tax authorities\n\nAssistant Accountant for Client Accounts (Fresh Graduate Welcome)\n\n\nJob Description\nResponsible for accurate and quick data entry into system\nAssist in preparing for\u00a0full sets of accounts and bookkeeping for client\nAssist in clients\u2019 cash management and payment administration\u00a0\nAssist in other ad hoc tasks\n\n\u00a0We are looking for:\n\nDegree / Associate degree / Higher diploma\u00a0in Human Resources Management, Accounting related disciplines\u00a0\nAble to work independently\nGood English required\nImmediate availability is preferred\nCandidate with less working experience/ Fresh graduates will be considered as Assistant Accountant\n\nWe offer:\n\nGood working conditions\u00a0\nGood medical and other benefits\n5-day week\u00a0\nDiscretionary bonus\nOn the job training including Xero\u00a0and third-party courses\nA wide range of exposure\nThe opportunity to grow with a high quality, service-oriented company", "employment_types": ["Full Time", "Permanent"], "selling_points": [], "locations": ["Wan Chai"], "categories": ["Accounting", "Accountant", "Professional Services", "Business Consultancy", "Admin & HR", "Compensation & Benefits"], "post_time": "2022-01-13T04:31:22Z", "salary": {"currency": null, "max": null, "min": null, "period": "monthly", "term": null}, "salary_visible": false, "title_keywords": ["officer", "assistant accountant"], "responsibilities": ["mpf", "software", "maintenance", "data", "payment", "payroll"], "requirements": {"degrees": [], "majors": [], "languages": [], "language_level": [], "hard_skills": ["maintenance"], "soft_skills": ["responsible"], "languages_combined": []}, "experience_required": {"duration": [], "field": []}}, {"job_id": "100003009037090", "location_code": "hk", "company": "EC Healthcare", "job_title": "Human Resource Officer, C&B", "description": "Responsibilities\n\nPerform C&B functions including but not limited to payroll and commission calculation, attendance and leave record maintenance, MPF and benefits enrolment;\nAssist in HR data analysis and reporting;\nMaintain accurate employee data in HRIS;\nParticipate in ad hoc assignments and duties.\n\nRequirements\n\nDegree holder in Human Resources Management, Business Administration or related disciplines;\n2-3 years of experience, less experienced will be considered as Assistant Human Resources Officer;\nWell-versed in Employment Ordinance\nExperience in related industry or commission calculation is preferred;\nStrong analytical skills and proficient in Excel;\nSensitive to numbers, good work commitment, energetic and fast learner;\nGood command of spoken and written in English, Mandarin and Cantonese;\nImmediate available is highly preferred.", "employment_types": ["Full Time"], "selling_points": ["Growing company", "2-3 years of relevant work experience", "Familiar with Commission Schemes and Excel"], "locations": ["Mong Kok"], "categories": ["Admin & HR", "Clerical / Admin Staff", "Compensation & Benefits"], "post_time": "2022-01-11T01:40:32Z", "salary": {"currency": null, "max": null, "min": null, "period": "monthly", "term": null}, "salary_visible": false, "title_keywords": ["officer"], "responsibilities": ["attendance", "reporting", "mpf", "maintenance", "data", "hr", "data analysis", "maintain", "ad hoc assignments", "payroll"], "requirements": {"degrees": ["degree holder"], "majors": ["related disciplines", "business administration"], "languages": ["cantonese", "english", "mandarin"], "language_level": ["good command"], "hard_skills": ["excel", "analytical skills"], "soft_skills": ["sensitive to numbers", "energetic", "fast learner", "analytical skills"], "languages_combined": [{"language": "cantonese", "language_level": ["good command"]}, {"language": "english", "language_level": ["good command"]}, {"language": "mandarin", "language_level": ["good command"]}]}, "experience_required": {"duration": ["2-3 years"], "field": ["related", "human resources"]}}]