[{"job_id": "100003009046600", "location_code": "hk", "company": "Asiaray Advertising Media Limited", "job_title": "Senior Human Resources Manager", "description": "Responsibilities:\n\n\nResponsible for all-rounded human resources functions including recruitment & selection, compensation & benefits, tax issues and HRIS management etc.\nProvide one-stop services to line departments on manpower planning, talent acquisition, HR advisory and change management\nHandle C&B duties including liaising with insurance agent on various employee compensation issues and renew group insurance plans, verifying monthly payroll, HR audit, tax filing, benefits enrolment and termination\nPlan and design the variable pay schemes, such as commission, incentive and bonus schemes for different business units\nLead the annual performance management project, analyze appraisal rating and provide insightful salary review proposal for Management\u2019s consideration\nFormulate, draft, implement and constantly update the HR policies and regulations in compliance with the Group\u2019s direction and Employment Ordinance\nImplement creative, innovative and successful solutions that align with overall business strategy, and that are consistent with or complementary to the business goals\nReview the current HRIS workflow, implement system enhancement and set key business processes to ensure the system stability\nSupport HR operations of Singapore office\u00a0\n\nRequirements:\n\n\nDegree holder or above in Human Resources Management,\u00a0Business Administration\u00a0or related disciplines\nAt least 10 years of relevant HR experience; in which 5 years in supervisory level\nRegional exposure or experience in state-owned or Chinese enterprise is preferred\nFamiliar with Employment Ordinance and other statutory and compliance requirements in Hong Kong, knowledge of laws and regulations in PRC is a plus\nExcellent interpersonal, presentation, communication and negotiations skills\nAgile, meticulous, with good analytical and numerical sense\nAble to work independently, with strong sense of ownership\nExcellent writing skills in Chinese and English, good spoken in Putonghua is an advantage\nProficiency in computer applications (MS Word, Excel, PowerPoint, etc)\nImmediate availability is highly preferred\n\nWe offer a competitive remuneration package, 5-DAY work, medical insurance, dental insurance to the right candidate. Interested parties are invited to send their applications with full resume stating availability date, present and expected salary.\n\nApplicants not invited for interview within 6 weeks may consider their applications unsuccessful. Personal data provided by job applicants will be used strictly in accordance with our personal data policy and for recruitment purposes only.", "employment_types": ["Full Time", "Permanent"], "selling_points": ["Support all-rounded human resources functions", "Support HR operations of Singapore office", "Immediate availability is highly preferred"], "locations": ["Quarry Bay"], "categories": ["Admin & HR", "Compensation & Benefits", "HR Director / Manager", "Recruitment / Executive Search"], "post_time": "2022-01-14T05:53:14Z", "salary": {"currency": null, "max": null, "min": null, "period": "monthly", "term": null}, "salary_visible": false, "title_keywords": ["manager", "human resources"], "responsibilities": [], "requirements": {"degrees": [], "majors": [], "languages": [], "language_level": [], "hard_skills": [], "soft_skills": [], "languages_combined": []}, "experience_required": {"duration": [], "field": []}}, {"job_id": "100003009051906", "location_code": "hk", "company": "PwC", "job_title": "HR Transformation and Change Management Senior Manager", "description": "Responsibilities:\n\nSupervise a team of customer service to provide high quality customer service and efficient information counter services to the mall tenants and visitors\nCoordinate with Marketing team on promotional events and customer service matters\nDesign and plan the customer service strategies to align with the mall requirements\nHandle enquiries and complaints in a professional manner\nLiaise with service contractors to ensure quality services are provided\nReviewing work schedules when necessary\nAd hoc tasks assigned by the Management\n\nRequirements:\n\nDegree or above in Hospitality Management, Public Relations or any related disciplines\nMinimum 5 years\u2019 relevant experience with 2 years\u2019 in supervisory level, exposure in hospitality, customer services or aviation service industry is highly preferable\nExperience in preparing tenders and operations manual\nExperience in handling marketing promotion and events are an advantage\nIndependent with good communication skills and able to work under pressure\nAdvanced knowledge of Excel, PowerPoint, Word, Chinese Word Processing is essential\nGood command of both written and spoken English and Cantonese\nAttractive compensation package including competitive salary,\u00a0up to\u00a022 days Annual Leave and 5 days work as well as excellent career prospects will be offered. Interested parties please send full resume including your present and expected salaries by clicking \"Apply Now\".\n\n(Personal data collected would be used in accordance with our Statement on Employment-Related Data Usage, which is available at\u00a0http://www.chineseestates.com\u00a0or upon request made to the Company\u2019s Human Resources Manager. Applicants who are not invited for interview within six weeks may consider their applications unsuccessful. All personal data of unsuccessful candidates will be destroyed after six months.)", "employment_types": ["Full Time"], "selling_points": [], "locations": ["Not Specified"], "categories": ["Admin & HR", "HR Director / Manager", "Recruitment / Executive Search", "Management", "Top Executives (CEO, CFO, CTO, GM, MD etc.)"], "post_time": "2022-01-17T01:30:03Z", "salary": {"currency": null, "max": null, "min": null, "period": "monthly", "term": null}, "salary_visible": false, "title_keywords": ["senior manager", "hr"], "responsibilities": ["management", "schedules", "quality", "coordinate with", "design", "handle enquiries and complaints", "professional manner", "ad hoc tasks", "customer service", "plan", "liaise with"], "requirements": {"degrees": ["degree or above"], "majors": ["hospitality management", "related disciplines"], "languages": ["cantonese", "english", "chinese"], "language_level": ["good command"], "hard_skills": ["excel", "chinese word processing", "word", "powerpoint"], "soft_skills": ["communication skills", "independent", "advanced", "work under pressure"], "languages_combined": [{"language": "cantonese", "language_level": ["good command"]}, {"language": "english", "language_level": ["good command"]}, {"language": "chinese", "language_level": []}]}, "experience_required": {"duration": ["2 years", "minimum 5 years"], "field": ["service industry", "customer services", "marketing", "relevant experience", "supervisory level"]}}, {"job_id": "100003009051768", "location_code": "hk", "company": "Earth Products China Limited", "job_title": "Senior Human Resources & Administration Officer / Manager", "description": "We are currently expanding our office and operations in the UK and\u00a0a fantastic\u00a0opportunity has arisen\u00a0for an enthusiastic and driven individual to join us as Senior Quantity Surveyor in the UK.\n\nThe main responsibilities of this role are to prepare cost estimates, tender and contract documentation, payment & variations assessment and final accounts for property development and renovation works in Central London.\n\nThe ideal candidate should have the following qualifications and experience:.\n\n\nDegree in Quantity Surveying\nChartered member of HKIS/RICS or equivalent\nMinimum 6 years\u2019 post-qualification experience in consultant firm or developers\nStrong numerical sense, excellent data interpretation & analytical skills\nSelf-motivated and strong sense of responsibility\nEligible to work in the UK\nProficient in MS Office\nGood command in both written and spoken English & Chinese\nInterested parties please send full resume including your present and expected salaries by clicking \"Apply Now\".\n\n\n(Personal data collected would be used in accordance with our\u00a0Statement on Employment-Related Data Usage, which\u00a0is available at \u00a0http://www.chineseestates.com\u00a0\u00a0or upon request made to the Company\u2019s Human Resources Manager. \u00a0Applicants who are not invited for interview within six weeks may consider their applications unsuccessful. \u00a0All personal data of unsuccessful candidates will be destroyed after six months.)\u00a0", "employment_types": ["Full Time", "Permanent"], "selling_points": [], "locations": ["Kwai Hing"], "categories": ["Admin & HR", "HR Director / Manager", "Recruitment / Executive Search", "Training & Development"], "post_time": "2022-01-17T00:59:32Z", "salary": {"currency": null, "max": null, "min": null, "period": "monthly", "term": null}, "salary_visible": false, "title_keywords": ["administration officer", "manager", "human resources"], "responsibilities": ["cost", "data", "operations", "renovation", "payment", "contract documentation", "tender"], "requirements": {"degrees": ["degree"], "majors": ["surveying"], "languages": ["english", "chinese"], "language_level": ["good command"], "hard_skills": ["hkis", "rics", "analytical skills", "documentation", "ms office"], "soft_skills": ["self-motivated", "sense of responsibility", "analytical skills", "enthusiastic", "driven", "ideal"], "languages_combined": [{"language": "english", "language_level": ["good command"]}, {"language": "chinese", "language_level": ["good command"]}]}, "experience_required": {"duration": ["minimum 6 years"], "field": ["post-qualification"]}}, {"job_id": "100003009051354", "location_code": "hk", "company": "Raze Technology Limited", "job_title": "Human Resources Manager", "description": "Responsibilities:\n\nProvide quality property management service for a portfolio of residential properties\u00a0\nMonitor the maintenance, security and cleaning services of the properties\nHandle enquiries, complaints and emergency incidents\nPerform administrative duties and ad-hoc assignments\n\nRequirements:\n\nDiploma or above in any disciplines, preferably in Property & Facility Management or relevant disciplines\nAt least 2 years\u2019 experiences in property management\nIndependent with good communication skill and able to work under pressure\nGood customer service skill\nAdvanced knowledge of Excel, Word, PowerPoint and Chinese Word Processing is essential\nGood command of both written and spoken English and Cantonese\nAttractive compensation package including competitive salary,\u00a0up to\u00a022 days Annual Leave and 5 days work as well as excellent career prospects will be offered. Interested parties please send full resume including your present and expected salaries by clicking \"Apply Now\".\n\n(Personal data collected would be used in accordance with our Statement on Employment-Related Data Usage, which is available at\u00a0http://www.chineseestates.com\u00a0or upon request made to the Company\u2019s Human Resources Manager. Applicants who are not invited for interview within six weeks may consider their applications unsuccessful. All personal data of unsuccessful candidates will be destroyed after six months.)", "employment_types": ["Full Time", "Permanent"], "selling_points": [], "locations": ["Southern Area"], "categories": ["Admin & HR", "Administration / Operation Manager", "HR Director / Manager", "Recruitment / Executive Search"], "post_time": "2022-01-15T10:57:20Z", "salary": {"currency": null, "max": null, "min": null, "period": "monthly", "term": null}, "salary_visible": false, "title_keywords": ["manager", "human resources"], "responsibilities": ["management", "maintenance", "ad-hoc assignments", "quality", "monitor", "handle enquiries", "administrative duties", "cleaning"], "requirements": {"degrees": ["diploma or above"], "majors": ["any disciplines"], "languages": ["cantonese", "english", "chinese"], "language_level": ["good command"], "hard_skills": ["excel", "chinese word processing", "word", "powerpoint"], "soft_skills": ["independent", "advanced", "communication skill", "customer service", "work under pressure"], "languages_combined": [{"language": "cantonese", "language_level": ["good command"]}, {"language": "english", "language_level": ["good command"]}, {"language": "chinese", "language_level": []}]}, "experience_required": {"duration": ["at least 2 years"], "field": ["management"]}}, {"job_id": "100003009053089", "location_code": "hk", "company": "Marugame (HR) Limited", "job_title": "Assistant HR & Admin Manager", "description": "Oversee and manage security activities for the Group\u2019s designated properties\nEnsure the day-to-day security service meets the specification and supervise contractors to improve the security standards\nChecking on security contractor\u2019s KPI\nEnsure the day-to-day site control meets safety standards and client\u2019s expectations\nManage the contractors from end to end including service and pricing\nResponsible for team establishment and recruit new team members\nTraining of security guards and frontline staff\nReviewing work schedules when necessary\nAd hoc tasks assigned by the management\n\n\u00a0What we are looking for:\n\nTertiary education\nMinimum 5 years work experience in Security Services with management experience\nExperience in preparing tenders and operations manual\nIndependent with good communication skills and able to work under pressure\nA valid Hong Kong driving license is an advantage\nAdvanced knowledge of Excel, Word, PowerPoint and Chinese Word Processing is essential\nGood command of both written and spoken English and Cantonese\nCandidates with less experience will be considered as Guard Trainer & Site Inspector\n\nAttractive compensation package including competitive salary, up to 22 days Annual Leave, 5-day work as well as\u00a0excellent career prospects will be offered.\u00a0 Interested parties please send full resume including your present and expected salaries by clicking \u201cApply Now\u201d.\n\n(Personal data collected would be used in accordance with our\u00a0Statement on Employment-Related Data Usage, which is available at\u00a0www.chineseestates.com\u00a0or upon request made to the Company\u2019s Human Resources Manager. \u00a0Applicants who are not invited for interview within six weeks may consider their applications unsuccessful. \u00a0All personal data of unsuccessful candidates will be destroyed after six months.)", "employment_types": ["Full Time"], "selling_points": [], "locations": ["Kwun Tong"], "categories": ["Hospitality / F & B", "Food & Beverage", "Admin & HR", "HR Director / Manager"], "post_time": "2022-01-17T05:50:07Z", "salary": {"currency": null, "max": null, "min": null, "period": "monthly", "term": null}, "salary_visible": false, "title_keywords": ["hr", "admin", "manager", "assistant"], "responsibilities": ["control", "management", "supervise contractors", "schedules", "operations", "ad hoc tasks", "checking", "communication", "safety standards", "work under pressure"], "requirements": {"degrees": [], "majors": [], "languages": ["cantonese", "english", "chinese"], "language_level": ["good command"], "hard_skills": ["excel", "chinese word processing", "word", "powerpoint"], "soft_skills": ["communication skills", "independent", "advanced", "responsible", "work under pressure"], "languages_combined": [{"language": "cantonese", "language_level": ["good command"]}, {"language": "english", "language_level": ["good command"]}, {"language": "chinese", "language_level": []}]}, "experience_required": {"duration": ["minimum 5 years"], "field": ["management", "security"]}}, {"job_id": "100003009022237", "location_code": "hk", "company": "Resources Link Network Ltd", "job_title": "Human Resources Officer", "description": "Your Role & Responsibilities:\n\n\nWork as a team to perform daily receivable function in Hong Kong and China, follow up new leases/leases renewal\nLiaise with overseas office and occasional travel to China might be needed\nPrepare month-end and year-end closing and assist in other accounting related tasks and ad hoc assignment\nFollow up customers' enquiry and liaise with other departments\n\nWhat we are looking for:\n\n\nDiploma or above in Accounts or related subject\n3-5 years\u2019 solid experience in handling Accounts Receivable (AR) is a MUST\nExperience in leasing operation is an advantage\nGood communication & interpersonal skills\nDetail minded, high initiatives and able to work independently\nMulti-tasking under tight deadlines & adaptable to fast pace environment\nProficiency PC skills in MS Office preferable with knowledge of Oracle\nOccasional travel to China might be needed\nImmediate available is preferred\n\n\u00a0(Candidate with less experience will be considered as Senior Accounts Clerk)\n\nAttractive compensation package including competitive salary, up to 22 days Annual Leave, 5 days work as well as\u00a0excellent career prospects will be offered.\u00a0 Interested parties please send full resume including your present and expected salaries by clicking \"Apply Now\".\n\n(Personal data collected would be used in accordance with our Statement on Employment-Related Data Usage, which is available at http://www.chineseestates.com or upon request made to the Company\u2019s Human Resources Manager. \u00a0Applicants who are not invited for interview within six weeks may consider their applications unsuccessful. \u00a0All personal data of unsuccessful candidates will be destroyed after six months.)", "employment_types": ["Full Time"], "selling_points": ["Attractive Salary Package and Career Pathway", "Work-Life Balance, Five-day Work a Week", "World's Fortune 100 Group of Companies"], "locations": ["Wan Chai"], "categories": ["Admin & HR", "HR Director / Manager", "Information Technology (IT)", "Others"], "post_time": "2022-01-17T05:56:36Z", "salary": {"currency": null, "max": null, "min": null, "period": "monthly", "term": null}, "salary_visible": false, "title_keywords": ["human resources officer"], "responsibilities": ["month-end and year-end closing", "ar", "accounts receivable", "ad hoc assignment", "communication", "liaise with"], "requirements": {"degrees": ["diploma or above"], "majors": [], "languages": [], "language_level": [], "hard_skills": ["oracle", "pc skills", "ar", "ms office"], "soft_skills": ["work independently", "work as a team", "adaptable", "communication", "multi-tasking", "interpersonal skills"], "languages_combined": []}, "experience_required": {"duration": ["3-5 years"], "field": ["operation"]}}, {"job_id": "100003009049054", "location_code": "hk", "company": "LVMH Perfumes & Cosmetics Asia Pacific Limited", "job_title": "Human Resources Business Partner", "description": "Your Role & Responsibilities:\n\nConduct report, feasibility study and analysis on overseas property acquisition (mainly UK)\nKeep track on market dynamics, policies and regulations, industry trend and establish sources for investment development\nCo-ordinate with internal departments and external consultants for asset management on existing portfolio\nAssist in identifying potential acquisition opportunities of property information\nOther ad-hoc assignments\n\nWhat we are looking for:\n\nDegree\u00a0or above in any disciplines, preferably in Real Estate, Finance and Accounting or other relevant disciplines\nMinimum 2 years\u2019 experience in Real Estates, preferably in Property Developer or Consultancy Firm\nExperience in overseas properties (e.g. UK, US) is an added advantage\nGood communication skills\nGood command of both written and spoken English, Cantonese and Mandarin\u00a0\nAdvanced knowledge of Excel, Word, PowerPoint & Chinese Word Processing is essential\n\n(Candidates with less experience will be considered as Officer, Overseas Property)\n\nAttractive compensation package including competitive salary, up to 22 days Annual Leave, 5-day work as well as\u00a0excellent career prospects will be offered.\u00a0 Interested parties please send full resume including your present and expected salaries by clicking \u201cApply Now\u201d.\n\n(Personal data collected would be used in accordance with our\u00a0Statement on Employment-Related Data Usage, which is available at\u00a0www.chineseestates.com\u00a0or upon request made to the Company\u2019s Human Resources Manager. \u00a0Applicants who are not invited for interview within six weeks may consider their applications unsuccessful. \u00a0All personal data of unsuccessful candidates will be destroyed after six months.)", "employment_types": ["Full Time", "Permanent"], "selling_points": ["Luxury, Beauty, MNC", "HR, Business Partner", "LVMH"], "locations": ["Quarry Bay"], "categories": ["Admin & HR", "HR Director / Manager"], "post_time": "2022-01-14T07:59:49Z", "salary": {"currency": null, "max": null, "min": null, "period": "monthly", "term": null}, "salary_visible": false, "title_keywords": ["human resources"], "responsibilities": ["regulations", "co-ordinate with", "policies", "analysis", "ad-hoc assignments", "communication", "asset management", "report"], "requirements": {"degrees": ["degree or above"], "majors": ["finance", "accounting", "any disciplines"], "languages": ["cantonese", "english", "chinese", "mandarin"], "language_level": ["good command"], "hard_skills": ["excel", "chinese word processing", "analysis", "word", "powerpoint"], "soft_skills": ["communication skills", "advanced"], "languages_combined": [{"language": "cantonese", "language_level": ["good command"]}, {"language": "english", "language_level": ["good command"]}, {"language": "chinese", "language_level": []}, {"language": "mandarin", "language_level": ["good command"]}]}, "experience_required": {"duration": ["minimum 2 years"], "field": ["developer"]}}, {"job_id": "100003009052535", "location_code": "hk", "company": "Chinese Estates Holdings Limited", "job_title": "Senior Human Resources Manager / Human Resources Manager", "description": "About the Role & Responsibilities:\n\nExecute full spectrum of HR functions including but not limited to recruitment, staff movement, leave management,\u00a0compensation & benefits and employee relations\nProvide end-to-end HR support for our office & site staff and ensure smooth running of day-to-day HR operations\nHandle all aspects of payroll administration including salary calculation, final payment, cost allocation, salaries tax and MPF administration, etc.\nMaintains accurate and timely data entry to HRIS and other related systems\u00a0and prepare reports on a regular basis\nHandles ad-hoc projects\nWhat we are looking for:\n\nDegree holder in Human Resources Management, Business Administration or related disciplines\nMinimum 5 years HR generalist experience with focus on C&B/payroll\nWell versed in HK Employment / MPF Ordinance and labour related ordinance/regulations\nExperience/Knowledge in PeopleSoft is an advantage\nAble to work under pressure and with positive attitude towards changes & challenges\nGood command in both written and spoken English and Chinese\nProficient in MS Office and Chinese Word Processing\nAttractive compensation package including competitive salary, up to 22 days Annual Leave, 5 days work as well as\u00a0excellent career prospects will be offered.\u00a0Interested parties please send full resume including your present and expected salaries by clicking \"Apply Now\".\n\n\n(Personal data collected would be used in accordance with our\u00a0Statement on Employment-Related Data Usage, which\u00a0is available at \u00a0http://www.chineseestates.com \u00a0or upon request made to the Company\u2019s Human Resources Manager. \u00a0Applicants who are not invited for interview within six weeks may consider their applications unsuccessful. \u00a0All personal data of unsuccessful candidates will be destroyed after six months.)\u00a0", "employment_types": ["Full Time", "Permanent"], "selling_points": ["Full spectrum of Human Resources Management", "Familiar with Hong Kong & London Labour Ordinance", "Excellent communication skills"], "locations": ["Causeway Bay"], "categories": ["Admin & HR", "Compensation & Benefits", "HR Director / Manager", "Training & Development"], "post_time": "2022-01-17T03:20:01Z", "salary": {"currency": null, "max": null, "min": null, "period": "monthly", "term": null}, "salary_visible": false, "title_keywords": ["manager", "human resources"], "responsibilities": ["tax", "regulations", "management", "cost", "mpf", "data entry", "work under pressure", "operations", "hr", "systems", "payment", "recruitment", "prepare reports", "ad-hoc projects", "payroll", "administration"], "requirements": {"degrees": ["degree holder"], "majors": ["related disciplines", "business administration"], "languages": ["english", "chinese"], "language_level": ["good command", "proficient"], "hard_skills": ["focus", "chinese word processing", "ms office"], "soft_skills": ["timely", "positive attitude", "smooth", "focus", "accurate", "work under pressure"], "languages_combined": [{"language": "english", "language_level": ["good command"]}, {"language": "chinese", "language_level": ["good command", "proficient"]}]}, "experience_required": {"duration": ["minimum 5 years"], "field": ["payroll", "hr generalist"]}}, {"job_id": "100003009052039", "location_code": "hk", "company": "HKT Services Limited", "job_title": "Human Resources Manager", "description": "Provide full spectrum of secretarial support to senior executive\nManage calendar, arrange business meetings and daily appointments\nHandle memo, reports, news clippings and other documents\nProvide administrative and clerical support to marketing department\nHandle ad hoc projects or duties as assigned\nRequirements:\n\nDegree holder in any discipline, preferably with formal secretarial training\nAt least 3 years' relevant experience, preferably in sizeable organization\nExperience in serving senior management\nMeticulous, well-organized, reliable and able to work independently\nMature, self-motivated with excellent interpersonal and communication skills\nGood command of both written and spoken English and Chinese. Mandarin in advantage.\nProficient in MS Word, Excel, Chinese Word Processing and PowerPoint\nImmediate available is an advantage\nAttractive compensation package including competitive salary, up to 22 days Annual Leave and 5 days work as well as excellent career prospects will be offered. Interested parties please send full resume including your present and expected salaries by clicking \"Apply Now\".\n\n(Personal data collected would be used in accordance with our Statement on Employment-Related Data Usage, which is available at http://www.chineseestates.com or upon request made to the Company\u2019s Human Resources Manager. Applicants who are not invited for interview within six weeks may consider their applications unsuccessful. All personal data of unsuccessful candidates will be destroyed after six months.)", "employment_types": ["Full Time", "Permanent"], "selling_points": ["HRBP", "TA", "C&B"], "locations": ["Quarry Bay"], "categories": ["Admin & HR", "Compensation & Benefits", "HR Director / Manager", "Recruitment / Executive Search"], "post_time": "2022-01-17T01:55:04Z", "salary": {"currency": null, "max": null, "min": null, "period": null, "term": null}, "salary_visible": false, "title_keywords": ["manager", "human resources"], "responsibilities": ["memo", "communication", "ad hoc projects", "reports", "secretarial support", "administrative and clerical support", "senior management"], "requirements": {"degrees": ["degree holder"], "majors": [], "languages": ["english", "chinese", "mandarin"], "language_level": ["advantage", "good command", "proficient"], "hard_skills": ["excel", "chinese word processing", "powerpoint", "ms word"], "soft_skills": ["meticulous", "work independently", "self-motivated", "communication skills", "well-organized", "mature", "reliable", "interpersonal"], "languages_combined": [{"language": "english", "language_level": ["good command"]}, {"language": "chinese", "language_level": ["good command", "proficient"]}, {"language": "mandarin", "language_level": ["advantage"]}]}, "experience_required": {"duration": ["at least 3 years"], "field": ["management", "relevant experience"]}}, {"job_id": "100003009046796", "location_code": "hk", "company": "Kingstar International Trading Ltd", "job_title": "Human Resources and Administration Manager", "description": "Responsibilities:\nProvide full support to office administrative functions including but not limited to stationery & office supplies procurement, all relevant payment and office equipment maintenance\nAssist in general reception duties such as arranging courier services and handling incoming & outgoing mails\nAssist in planning and organizing social and recreational activities for the company\nHandle ad hoc duties as assigned\nRequirements:\n\nDiploma holder or above\nAt least 1 year\u2019 relevant experience, preferably in sizeable companies\nProficiency in both written and spoken English and Chinese (including Mandarin)\nComputer literate with MS Office (Word, Excel) and Chinese Word Processing\nGood interpersonal and communication skills\nAble to work independently and under pressure\nCandidates with more experience might be considered as\u00a0Assistant Administration Officer\n\nAttractive compensation package including competitive salary,\u00a0up to\u00a022 days Annual Leave and 5 days work as well as excellent career prospects will be offered. Interested parties please send full resume including your present and expected salaries by clicking \"Apply Now\".\n\n(Personal data collected would be used in accordance with our Statement on Employment-Related Data Usage, which is available at\u00a0http://www.chineseestates.com\u00a0or upon request made to the Company\u2019s Human Resources Manager. Applicants who are not invited for interview within six weeks may consider their applications unsuccessful. All personal data of unsuccessful candidates will be destroyed after six months.)", "employment_types": ["Full Time", "Permanent"], "selling_points": ["Oversee all round HR & Administration Operation", "Well-versed in Employment Ordinance", "Independent, strong problem-solving skill"], "locations": ["Tsim Sha Tsui"], "categories": ["Admin & HR", "Administration / Operation Manager", "Others", "HR Director / Manager"], "post_time": "2022-01-16T21:50:19Z", "salary": {"currency": null, "max": null, "min": null, "period": "monthly", "term": null}, "salary_visible": false, "title_keywords": ["administration manager", "human resources"], "responsibilities": ["ad hoc duties", "office supplies", "stationery", "payment", "office equipment maintenance", "planning"], "requirements": {"degrees": ["diploma holder"], "majors": [], "languages": ["english", "chinese", "mandarin"], "language_level": ["proficiency"], "hard_skills": ["excel", "chinese word processing", "word", "ms office"], "soft_skills": ["communication skills", "work independently", "under pressure", "interpersonal"], "languages_combined": [{"language": "english", "language_level": ["proficiency"]}, {"language": "chinese", "language_level": ["proficiency"]}, {"language": "mandarin", "language_level": []}]}, "experience_required": {"duration": ["at least 1 year"], "field": ["relevant experience", "administration"]}}, {"job_id": "100003009052050", "location_code": "hk", "company": "Hong Kong Interbank Clearing Ltd", "job_title": "Senior Manager (Human Resources)", "description": "Responsibilities:\n\nProvide full spectrum of secretarial and administrative support to Senior Management in both business activities and personal matters\nHandle business correspondence, other confidential and professional documents as instructed\nAssist to draft various English and Chinese business correspondences in a professional manner\nResponsible for arranging and monitoring the day-to-day operation for the whole family household\nManage and supervise the domestic helpers, drivers, chef, securities, etc.\nResponsible for property and facilities management and maintenance, renovation, repair, etc.\nAd hoc tasks assigned by the Management\n\nRequirements:\n\nDegree holder in any disciplines\nAt least 4 years' relevant working experience\u00a0\nGood command of both written and spoken in English and Chinese\nEthical and proper handling of confidential information is a must\nIndependent, well-organized, strong sense of responsibility and able to work under pressure\nFamiliar with MS Word, Excel and Chinese Word Processing\nImmediate availability would be an advantage\nAttractive compensation package including competitive salary, up to 22 days Annual Leave, 5-day work as well as excellent career prospects will be offered. Interested parties please send full resume including your recent photo, present and expected salaries by clicking \u201cApply Now\u201d.\n\n\n(Personal data collected would be used in accordance with our Statement on Employment-Related Data Usage, which is available at\u00a0www.chineseestates.com\u00a0or upon request made to the Company\u2019s Human Resources Manager. Applicants who are not invited for interview within six weeks may consider their applications unsuccessful. All personal data of unsuccessful candidates will be destroyed after six months.)", "employment_types": ["Full Time", "Permanent"], "selling_points": [], "locations": ["Ngau Tau Kok"], "categories": ["Admin & HR", "Others", "Banking / Finance", "Financial Services", "HR Director / Manager"], "post_time": "2022-01-17T01:57:14Z", "salary": {"currency": null, "max": null, "min": null, "period": null, "term": null}, "salary_visible": false, "title_keywords": ["senior manager", "human resources"], "responsibilities": ["management", "day-to-day operation", "administrative support", "maintenance", "monitoring", "professional manner", "renovation", "ad hoc tasks", "repair", "senior management", "business activities"], "requirements": {"degrees": ["degree holder"], "majors": ["any disciplines"], "languages": ["english", "chinese"], "language_level": ["good command"], "hard_skills": ["excel", "chinese word processing", "ms word"], "soft_skills": ["independent", "sense of responsibility", "well-organized", "ethical", "work under pressure"], "languages_combined": [{"language": "english", "language_level": ["good command"]}, {"language": "chinese", "language_level": ["good command"]}]}, "experience_required": {"duration": ["at least 4 years"], "field": ["relevant working experience"]}}, {"job_id": "100003009054133", "location_code": "hk", "company": "China Life Insurance (Overseas) Company Limited", "job_title": "Senior Human Resources Manager /Human Resources Manager", "description": "Responsibilities:\n\nReport to Technical Manager / Assistant Technical Manager, the incumbent is responsible for R&M (Repair & Maintenance) of commercial, industrial, residential and office properties in compliance with relevant statutory requirements\nPrepare & arrange tender/quotation documents & sketches, job orders, payment settlements, etc. via computer systems\nFollow up on liaison, coordination, supervision, monitoring, T&C (Testing and Commissioning) with site technicians, management colleagues, outsource contractors & consultants of various works till completion and payment settlement\nCoordinate with tenants, landlords, occupiers, Leasing team, Marketing team, management team, Public Utilities and Government Authority in related to fitting out control\nPerform project management duties on fitting-out, A&A works, improvement works & feasibility studies, etc.\nRequirements:\nDegree / Higher Diploma in Building Services Engineering, Electrical Engineering, Mechanical Engineering or related discipline\n2 years' or above relevant experience in Government Authorities, Institutions, Public Organizations, Developers, property management company, consultant or contractor firm\nExperience in working at sizable high-end commercial properties including office and shopping arcade is an advantage\u00a0\nAdvanced knowledge of Excel, PowerPoint, Word, Chinese Word Processing is essential\nKnowledgeable in AutoCAD would be an advantage\n(Candidates with less experience will be considered as Assistant Technical Officer)\n\n\u00a0Attractive compensation package including competitive salary, up to 22 days Annual Leave, 5-day work as well as excellent career prospects will be offered. Interested parties please send full resume including your present and expected salaries by clicking \u201cApply Now\u201d.\n\n(Personal data collected would be used in accordance with our Statement on Employment-Related Data Usage, which is available at\u00a0www.chineseestates.com\u00a0or upon request made to the Company\u2019s Human Resources Manager. Applicants who are not invited for interview within six weeks may consider their applications unsuccessful. All personal data of unsuccessful candidates will be destroyed after six months.)", "employment_types": ["Full Time", "Permanent"], "selling_points": ["Business Partner role", "Talent Management", "Manpower planning"], "locations": ["Hung Hom"], "categories": ["Admin & HR", "HR Director / Manager", "Recruitment / Executive Search", "Insurance", "Others"], "post_time": "2022-01-17T08:30:57Z", "salary": {"currency": null, "max": null, "min": null, "period": "monthly", "term": null}, "salary_visible": false, "title_keywords": ["manager", "human resources"], "responsibilities": ["quotation", "statutory requirements", "payment", "management team", "control", "compliance", "testing", "tender", "report", "management", "commissioning", "monitoring", "coordinate with", "sketches", "maintenance", "computer systems", "project management", "repair", "coordination"], "requirements": {"degrees": ["diploma", "degree"], "majors": ["mechanical engineering", "building services", "engineering", "electrical engineering"], "languages": ["chinese"], "language_level": [], "hard_skills": ["excel", "chinese word processing", "word", "powerpoint", "autocad"], "soft_skills": ["advanced"], "languages_combined": [{"language": "chinese", "language_level": []}]}, "experience_required": {"duration": ["2 years"], "field": ["commercial", "management", "relevant experience"]}}, {"job_id": "100003009053320", "location_code": "hk", "company": "Changjiang Securities International Financial Group Limited", "job_title": "Head of HR & Administration", "description": "About the Role & Responsibilities:\n\nProvide comprehensive property management services for the Group's designated properties\nAssist in handling complaints and inquiries from authorizers/tenants and occupiers\nResponsible for inventory control, tendering and liaise with relevant government authorities\nMonitor the site operation and performance of contractors and subordinates to ensure the compliance of statutory requirements\nOther ad-hoc assignments\n\nWhat we are looking for:\n\nTertiary education preferably in Property Management / Facility Management or relevant disciplines\n3-5 years' relevant experience in property management with experience in prestigious shopping mall is an\u00a0advantage\nGood command of English and Cantonese\nProficient in MS Office\n\nAttractive compensation package including competitive salary, up to 22\u00a0days Annual Leave, 5-day work as well as\u00a0excellent career prospects will be offered.\u00a0 Interested parties please send full resume including your present and expected salaries by clicking \u201cApply Now\u201d.\n\n(Personal data collected would be used in accordance with our\u00a0Statement on Employment-Related Data Usage, which is available at\u00a0www.chineseestates.com\u00a0or upon request made to the Company\u2019s Human Resources Manager. \u00a0Applicants who are not invited for interview within six weeks may consider their applications unsuccessful. \u00a0All personal data of unsuccessful candidates will be destroyed after six months.)", "employment_types": ["Full Time", "Permanent"], "selling_points": [], "locations": ["Sheung Wan"], "categories": ["Admin & HR", "HR Director / Manager"], "post_time": "2022-01-17T06:45:43Z", "salary": {"currency": null, "max": null, "min": null, "period": "monthly", "term": null}, "salary_visible": false, "title_keywords": ["hr"], "responsibilities": ["management", "ad-hoc assignments", "compliance", "monitor", "tendering", "statutory requirements", "inventory control", "liaise with"], "requirements": {"degrees": [], "majors": [], "languages": ["cantonese", "english"], "language_level": ["good command"], "hard_skills": ["ms office"], "soft_skills": ["comprehensive", "responsible"], "languages_combined": [{"language": "cantonese", "language_level": ["good command"]}, {"language": "english", "language_level": ["good command"]}]}, "experience_required": {"duration": ["3-5 years"], "field": ["management", "relevant experience"]}}, {"job_id": "100003009052986", "location_code": "hk", "company": "Target Search Limited", "job_title": "Senior Manager / Manager - Human Resources", "description": "This role will be leading a technical team to oversee the progress of all R&M (Repair & Maintenance), fitting-out works handled by subordinates with respect to costs, time and quality for commercial, industrial, residential and office properties.\n\nYour Role & Responsibilities:\n\nPrepare & scrutinize technical proposals, tenders, sketches, work order, payment etc. for all kinds of technical issues arising from building maintenance, feasibility study, fitting out, A&A, improvement and upgrading projects\nFollow up on liaison, coordination, supervision, monitoring, site check with team members, contractors & consultants to ensure the quality of works and performance output are up to the required standards\nCoordinate with tenants, landlords, occupiers, Leasing team, Marketing team, management team, Public Utilities and Government Authority, etc. regarding all the technical matters related to the properties assigned\nLeading a team of Technical Officers, assistance via regular performance appraisal, training, mentoring, guidance, recruiting, etc. for effective & constructive output\nWhat we are looking for:\n\nDegree / Higher Diploma in Building Surveying, Building Technology or related discipline\n10 years or above relevant experience in Government Authorities, Institutions, Public Organizations, Developers, property management company, consultant or contractor firm\nExperience in working at sizable high-end commercial properties including office and shopping arcade is an advantage\nAdvanced knowledge of Excel, PowerPoint, Word, Chinese Word Processing is essential\nKnowledgeable in AutoCAD would be an advantage\n(Candidates with less experience may be considered as Assistant Technical Manager or Senior Officer)\n\nAttractive compensation package including competitive salary, up to 22-25 days Annual Leave, 5-day work as well as excellent career prospects will be offered. Interested parties please send full resume including your present and expected salaries by clicking \u201cApply Now\u201d.\n\n\n(Personal data collected would be used in accordance with our Statement on Employment-Related Data Usage, which is available at\u00a0www.chineseestates.com\u00a0or upon request made to the Company\u2019s Human Resources Manager. Applicants who are not invited for interview within six weeks may consider their applications unsuccessful. All personal data of unsuccessful candidates will be destroyed after six months.)", "employment_types": ["Full Time", "Permanent"], "selling_points": ["Full spectrum of HR functions", "Stable working environment", "Immediately available is highly preferred"], "locations": ["Kowloon Bay"], "categories": ["Admin & HR", "Administration / Operation Manager", "Compensation & Benefits", "HR Director / Manager"], "post_time": "2022-01-17T04:56:43Z", "salary": {"currency": null, "max": null, "min": null, "period": "monthly", "term": null}, "salary_visible": false, "title_keywords": ["senior manager", "manager", "human resources"], "responsibilities": ["management team", "guidance", "management", "maintenance", "monitoring", "quality", "coordinate with", "sketches", "repair", "payment", "coordination", "costs"], "requirements": {"degrees": ["diploma", "degree"], "majors": ["building surveying"], "languages": ["chinese"], "language_level": [], "hard_skills": ["excel", "chinese word processing", "maintenance", "word", "powerpoint", "autocad"], "soft_skills": ["advanced", "constructive", "coordination"], "languages_combined": [{"language": "chinese", "language_level": []}]}, "experience_required": {"duration": ["10 years"], "field": ["commercial", "management", "relevant experience"]}}, {"job_id": "100003009054802", "location_code": "hk", "company": "Aigniter Holdings Limited", "job_title": "(Senior/Junior) Human Resources Officer", "description": "At Jarvix (Aigniter), we are on a mission to build a next-gen internet economic infrastructure that can really embed technology into everybody\u2019s day-to-day life. We firmly believe that technology shouldn\u2019t be a luxury that can only be accessed by large corporations, but a commodity that can be enjoyed by everyone. Since 2017, we have been working hard on leveraging technology to facilitate transactions of business of all sizes, and improve end consumer\u2019s quality of life. Right now, Jarvix is providing applications and services across different sectors, from e-payment, e-logistics, to e-groceries.\u00a0\n\nWe\u2019re a small, focused, and rapidly growing team with an abundance of opportunities. If you want to make a real impact and you\u2019re up for challenges, Jarvix is the ideal place for you.\n\n\n\n\nJob Description:\n\nHuman Resources Officer will be responsible for our company\u2019s Human Resources tasks such as recruitment, people management, team building and HR administration related matters. This position will also be the main driver of shaping our company culture and cultivating talents.\n\nResponsibilities:\n\nManage the recruitment pipeline, candidate interview and selection process\nManage staff onboarding and offboarding logistics\nCoordinate company team building activities\nCompile and review HR reports and HR related legal documents to ensure compliance with local regulations\nMaintain HR systems for handling payrolls, MPF, leave records and insurance\nAny other ad hoc tasks related to HR\u00a0\n\nRequirements:\n\nBachelor\u2019s Degree in Human Resources Management or related disciplines\nAt least 3 years of HR experience\nExcellent interpersonal and communication skills with good command of written/spoken Chinese and English\nExcellent attention to detail and organisational skills\nKnowledge of any kinds of HRIS (e.g. BambooHR/Workday)\nKnowledge of HR processes and general practices\nKnowledge of Hong Kong Employment Ordinance and other HR related regulations\nProficient in computer applications\nFluent in speaking Cantonese is a MUST\nStrong problem solving skills, able to face challenges with a positive and can-do attitude\nA good team player, independent, self-disciplined, responsible, self-motivated and willing to learn\n\nCompensation package:\n\nSalary ranges from HKD17,000 to HKD27,000 per month depending on experience\nMedical benefits\n\nPerks:\n\nSharp, talented and motivated co-workers\nFun and relaxed office environment\nSense of ownership\nFree snacks and drinks", "employment_types": ["Full Time", "Permanent"], "selling_points": ["HKD17,000 to HKD27,000 per month", "Medical benefits", "Fast growing tech company"], "locations": ["Wong Tai Sin Area"], "categories": ["Admin & HR", "HR Director / Manager", "HR Supporting Staff", "Recruitment / Executive Search"], "post_time": "2022-01-17T11:09:46Z", "salary": {"currency": "HKD", "max": 29999, "min": 17000, "period": "monthly", "term": null}, "salary_visible": true, "title_keywords": ["human resources officer", "junior"], "responsibilities": ["regulations", "management", "mpf", "hr", "review", "systems", "hr reports", "ad hoc tasks", "ensure compliance", "coordinate", "maintain", "logistics", "recruitment", "insurance", "administration"], "requirements": {"degrees": ["degree", "bachelor"], "majors": ["related disciplines"], "languages": ["cantonese", "english", "chinese"], "language_level": ["excellent", "good command", "fluent"], "hard_skills": ["problem solving skills", "hong kong employment ordinance"], "soft_skills": ["communication skills", "good team player", "self-motivated", "independent", "responsible", "can-do attitude", "willing to learn", "organisational skills", "attention to detail", "problem solving skills", "interpersonal", "positive"], "languages_combined": [{"language": "cantonese", "language_level": ["fluent"]}, {"language": "english", "language_level": ["excellent", "good command"]}, {"language": "chinese", "language_level": ["excellent", "good command"]}]}, "experience_required": {"duration": ["at least 3 years"], "field": ["hr"]}}, {"job_id": "100003009049927", "location_code": "hk", "company": "Nanyang Commercial Bank", "job_title": "Assistant Human Resources Manager (Ref: II8002-RP-JDB)", "description": "Perform HR and business data analysis. Prepare HR analytical and strategic planning report. Implementation of competitive reward and benefit practices and strategies. Accountable for various HR projects including annual bonus and salary review, staff promotion, and reward programs, performance management projects and manpower budget plan. Participate in market salary and benefit survey. Prepare material and data for management reports and meetings and\u00a0support in review of HR policies and procedures to ensure the Bank is consistently complied with related regulatory requirements.\n\nRequirements:\n\nDegree holder in Human Resources Management or Business related disciplines with at least 2 years relevant experience, preferable in banking/ financial institution;\n\nStrong analytical and organization skills with strategic mindset;\nProactive team player with excellent leadership and communication skills;\nAble to handle multiple projects with tight deadlines;\nFamiliar with statutory and compliance requirements including Employment Ordinance and other relevant laws and regulations for Hong Kong and PRC;\nConversant with Chinese word processing and MS Office Suite especially in Excel and Access;\nProficient in both spoken and written English and Chinese, fluent in Putonghua is preferable.\n\nIf you are flexible enough and zeal for a harmonious and supportive working environment where enables you to grow and succeed professionally, please send a full resume indicating your public examination results (HKCEE and HKALE / HKDSE), your present and expected salary and quoting reference number attention to\u00a0Talent Acquisition Division, Nanyang Commercial Bank, 151 Des Voeux Road Central, Hong Kong or apply through email. For details, please visit https://www.ncb.com.hk/ and select the page Recruit.\n\nWe are an Equal Opportunities Employer. Data collected would be used for recruitment purposes only. Applicants who do not hear from us within 8 weeks may consider their applications unsuccessful and their data will be destroyed within 12 months of receipt.", "employment_types": ["Full Time", "Permanent"], "selling_points": ["Perform HR and business data analysis", "Accountable for various HR projects", "Degree holder in Human Resources Management"], "locations": ["Central"], "categories": ["Admin & HR", "Compensation & Benefits", "HR Director / Manager"], "post_time": "2022-01-15T03:50:42Z", "salary": {"currency": null, "max": null, "min": null, "period": "monthly", "term": null}, "salary_visible": false, "title_keywords": ["assistant human resources manager"], "responsibilities": ["regulations", "data", "regulatory requirements", "budget", "communication", "plan", "compliance", "implementation", "banking", "report", "management", "strategic planning", "review", "procedures", "data analysis", "policies", "hr", "management reports", "recruitment", "multiple projects"], "requirements": {"degrees": ["hkdse", "degree holder"], "majors": ["related disciplines", "business"], "languages": ["putonghua", "english", "chinese"], "language_level": ["fluent", "proficient"], "hard_skills": ["excel", "chinese word processing", "analysis", "management reports", "ms office"], "soft_skills": ["flexible", "communication skills", "supportive", "harmonious", "accountable", "organization skills", "team player", "proactive", "leadership"], "languages_combined": [{"language": "putonghua", "language_level": ["fluent", "proficient"]}, {"language": "english", "language_level": ["fluent", "proficient"]}, {"language": "chinese", "language_level": ["fluent", "proficient"]}]}, "experience_required": {"duration": ["at least 2 years"], "field": ["management", "related", "business", "relevant experience", "banking", "human resources", "financial"]}}, {"job_id": "100003009046285", "location_code": "hk", "company": "Mott MacDonald Hong Kong Limited", "job_title": "Human Resources Advisor (Business Partner Role)", "description": "Your Next Challenge\n\n\nWork closely with business on staff issues and serve as an advisor for managers and employees in matters pertaining to people issues\nCoordinate and administer the training scheme and relevant site training\nEnsure our various HR databases, documentations, records and reports are maintained, with support from the wider HR team\nUnderstand our key business drivers, working closely with our project leads\nProvide advice and support to our teams with respect to HR policies and procedures. Contribute to our policy governance through ensuring they remain compliant with local regulations and Group HR directives\nMaintain a process improvement approach through continually looking for ways to enhance our operational efficiency\nContribute to our Hong Kong and wider regional HR initiatives and projects\nWhat You'll Need\n\nDegree holder in HRM or related discipline\nMinimum 5 years of HR experience, preferably in engineering or services industry \u00a0\nExcellent communication, and interpersonal skills, demonstrated through effective listening and establishing open dialogue with managers and staff alike\nAble to work effectively in a fast-paced environment where priorities change quickly\nBe proactive, high energy, have a strong sense of accountability\nDetailed and quality oriented, well organized\nWell-versed in employment-related laws of Hong Kong\nGood at MS Office and experience of using HRIS (preferably SAP SuccessFactors)\nWritten and spoken proficiency in English and Chinese\n\nWe offer competitive remuneration package including\u00a013th month salary, MPF plan\u00a0and\u00a0group medical insurance for dependents.\n\nInterested parties, please click 'Apply now' to submit your application with full resume including your current and expected salary, or send your full resume to recruitment.MMHK @mottmac.com .\n\nTo explore more opportunities with us, please visit www.mottmac.com/careers.\n\nAll personal data collected will be treated in strict confidence and be used for recruitment purpose only.\u00a0\n\nWe are an equal opportunity employer and value diversity at our company. We do not discriminate, and take positive steps to create an inclusive culture.", "employment_types": ["Full Time", "Permanent"], "selling_points": ["Provide end-to-end HR supports to teams", "Degree holder in HRM, 5 years of HR experience", "5 days work, 13th month salary, wellness program"], "locations": ["Ngau Tau Kok"], "categories": ["Admin & HR", "Administration / Operation Manager", "HR Director / Manager", "HR Supporting Staff"], "post_time": "2022-01-13T10:16:48Z", "salary": {"currency": null, "max": null, "min": null, "period": "monthly", "term": null}, "salary_visible": false, "title_keywords": ["advisor", "human resources"], "responsibilities": ["regulations", "policies", "hr", "teams", "procedures", "quality", "coordinate", "communication", "provide advice", "reports", "maintain", "databases"], "requirements": {"degrees": ["degree holder"], "majors": [], "languages": ["english", "chinese"], "language_level": ["proficiency"], "hard_skills": ["sap", "scheme", "databases", "documentations", "ms office"], "soft_skills": ["work effectively", "accountability", "fast-paced environment", "well organized", "communication", "interpersonal skills", "proactive", "detailed"], "languages_combined": [{"language": "english", "language_level": ["proficiency"]}, {"language": "chinese", "language_level": ["proficiency"]}]}, "experience_required": {"duration": ["minimum 5 years"], "field": ["hr", "engineering"]}}, {"job_id": "100003009044410", "location_code": "hk", "company": "Solent Manufacturing Ltd", "job_title": "Human Resources Manager (5-day Work)", "description": "Key Responsibilities:\n\n\nIdentify talent internally and externally\nEnsure comprehensive onboarding of all new talent\nEngage with other Asia offices to ensure a \u2018One Team, One Plan, One Goal\u2019 People strategy\nAct as an ambassador for the company Vision and Values and engage with teams to encourage behaviors\nDesigning and implementing various HR policies and system concerning recruitment, training, compensation and benefit, performance management, staff relational and staff discipline base on government regulations and market trend\nContinual bench-marketing of Asia teams to ensure comprehensive salary and package is utilized\nCoach Senior Team on Employee Relations\nAssist in implementing Training & Development across the Asia team\nKey Requirements:\n\nDegree in Human Resources, Business or relevant disciplines\nMinimum 3 years HR experience Human Resource and Administration in trading company environment\nWell-versed with Hong Kong & China employment related regulations, insurance and social security government requirements;\u00a0Well-versed with Vietnam employment regulations is an advantage\nHands-on with ability to work in a dynamic and fast-paced business environment\nDetail minded, willing to take responsibilities and able to take initiatives\nGood communication skill and interpersonal skill\nAble to work independently\nProficiency in written and spoken English and Chinese including Mandarin\nProficiency in MS office\nPersonal data provided by applicants will be strictly used for recruitment purpose only.", "employment_types": ["Full Time", "Permanent"], "selling_points": ["Flexible Working Hours", "Hybrid Working", "Double Pay & Discretionary Bonus"], "locations": ["Hung Hom"], "categories": ["Admin & HR", "HR Director / Manager", "HR Supporting Staff"], "post_time": "2022-01-13T03:58:18Z", "salary": {"currency": null, "max": null, "min": null, "period": "monthly", "term": null}, "salary_visible": false, "title_keywords": ["manager", "human resources"], "responsibilities": ["regulations", "management", "policies", "hr", "teams", "recruitment", "plan", "designing"], "requirements": {"degrees": ["degree"], "majors": ["business"], "languages": ["english", "chinese", "mandarin"], "language_level": ["proficiency"], "hard_skills": ["dynamic", "ms office"], "soft_skills": ["work independently", "communication skill", "interpersonal skill", "hands-on", "dynamic", "business environment"], "languages_combined": [{"language": "english", "language_level": ["proficiency"]}, {"language": "chinese", "language_level": ["proficiency"]}, {"language": "mandarin", "language_level": ["proficiency"]}]}, "experience_required": {"duration": ["minimum 3 years"], "field": ["hr", "trading", "administration"]}}, {"job_id": "100003009052022", "location_code": "hk", "company": "Multisoft Limited", "job_title": "Senior Human Resources Officer", "description": "Responsibilities:\n\n\nHandle end-to-end recruitment process and follow up all on-boarding / off-boarding procedures including conduct induction program and exit interview\nAssist in C&B functions including leave & attendance management, personal data update, payroll calculation and benefit administration\nPlan, develop, implement and review HR policies and procedures to support the Company\u2019s needs & cope with the overall business strategies\nPrepare HR and management reports e.g. salary scales, manning guide and turnover rate etc.\nIdentify and implement employee engagement opportunities and activities\nAd hoc project as assigned\n\nRequirements:\n\nBachelor\u2019s degree in human resources management or other related disciplines\nMinimum 4 years experiences in HR related discipline\nExperience in IT industry is highly preferred\nGood command of both spoken and written English and Chinese (Cantonese and Mandarin)\nAdvanced Excel, PowerPoint and database management skills\nGood stakeholder management and interpersonal skills\nStrong analytical skills and detail minded with high sensitivity to numbers\nStrong influencing relationships with different levels of management\u00a0and problem-solving skills\nIndependent, proactive with positive attitude, enjoy working in a dynamic and fast-paced environment\nCandidate with more experiences will consider as Assistant Human Resources Manager\nImmediate available is preferred\n\nJoin us, sketch the future with digitalization!\n\nInterested parties please send us your detailed resume with\u00a0current and\u00a0expected salary\u00a0by clicking the link\u00a0\"APPLY NOW\".\n\nAll information provided by applicants will be used for recruitment-related purposes and handled in strict confidence by authorized personnel. The personal data collected will be destroyed after three months.\n\nFor more information about Multisoft, please visit http://www.multisoft.com.hk/ or follow us on:\u00a0\nFacebook:\u00a0https://www.facebook.com/MultisoftLimited/\nYoutube:\u00a0https://www.youtube.com/user/MultisoftLimited\nLinkedin:\u00a0https://www.linkedin.com/company/multisoft-limited/", "employment_types": ["Full Time", "Permanent"], "selling_points": ["End-to-end recruitment process", "HRBP", "Friendly and dynamic working environment"], "locations": ["Kwun Tong"], "categories": ["Admin & HR", "HR Director / Manager", "Recruitment / Executive Search", "Training & Development"], "post_time": "2022-01-17T01:51:47Z", "salary": {"currency": null, "max": null, "min": null, "period": "monthly", "term": null}, "salary_visible": false, "title_keywords": ["senior human resources officer"], "responsibilities": ["attendance", "management", "ad hoc", "policies", "hr", "review", "procedures", "develop", "management reports", "plan", "recruitment process", "personal data", "payroll", "administration"], "requirements": {"degrees": ["degree", "bachelor"], "majors": ["related disciplines"], "languages": ["cantonese", "english", "chinese", "mandarin"], "language_level": ["good command"], "hard_skills": ["excel", "powerpoint", "analytical skills", "dynamic", "problem-solving skills"], "soft_skills": ["independent", "advanced", "fast-paced environment", "sensitivity", "enjoy working", "analytical skills", "positive attitude", "dynamic", "interpersonal skills", "problem-solving skills", "proactive"], "languages_combined": [{"language": "cantonese", "language_level": ["good command"]}, {"language": "english", "language_level": ["good command"]}, {"language": "chinese", "language_level": ["good command"]}, {"language": "mandarin", "language_level": ["good command"]}]}, "experience_required": {"duration": ["minimum 4 years"], "field": ["related", "hr", "it", "human resources"]}}, {"job_id": "100003009044385", "location_code": "hk", "company": "Strawberry Cosmetics (Services) Limited", "job_title": "Human Resources & Administration Manager", "description": "Roles and responsibilities:\n\nLead and responsible for the full spectrum of HR & Admin functions.\nManage HR functions including the processing of compensation & benefits, staff recruitment & selection, monthly payroll and staff relations programs, salary benchmarking.\nEnsure consistency of company policies and practices of human resources management with update Employment Ordinance.\nDesign and implement strategic HR plans and programs to support the achievement of business objectives and organization growth\nResponsible for all office administrative / procurement functions including office services and supplies, insurance, repair and maintenance, leasing and tenancy renewal, etc.\nReview, plan and implement administration policies and procedures.\nPlan and draft office layout plans, supervise office & warehouse renovation & relocation projects\nMonitor day-to-day admin operations and enhance office facilities.\nPlan, execute & organize company activities such as Annual Dinner, Engagement events, etc.\nOther ad-hoc works as required.\n\nRequirement:\n\nDegree holder in Human Resources Management, Business Administration or equivalent disciplines\nMinimum of 8 years\u2019 of Human Resources experience, ideally within Ecommerce or Retail & Wholesale industry\nWell-versed in Hong Kong Employment Ordinance and relevant legislation and regulations\nProficient in MS Office, including Word, Excel, PowerPoint; strong capability with HRIS software\nA good team player with strong interpersonal and communication skills\nAble to work independently and under pressure\nGood command of written and spoken English, Cantonese and Mandarin\nImmediate available is preferable", "employment_types": ["Full Time", "Permanent"], "selling_points": [], "locations": ["Shau Kei Wan"], "categories": ["Admin & HR", "Administration / Operation Manager", "HR Director / Manager"], "post_time": "2022-01-13T03:56:27Z", "salary": {"currency": null, "max": null, "min": null, "period": "monthly", "term": null}, "salary_visible": false, "title_keywords": ["administration manager", "human resources"], "responsibilities": ["ad-hoc", "management", "maintenance", "policies", "hr", "review", "procedures", "renovation", "design", "monitor", "operations", "repair", "recruitment", "insurance", "plan", "plans", "payroll", "administration"], "requirements": {"degrees": ["degree holder"], "majors": ["business administration"], "languages": ["cantonese", "english", "mandarin"], "language_level": ["good command"], "hard_skills": ["excel", "hong kong employment ordinance", "word", "powerpoint", "ms office"], "soft_skills": ["communication skills", "good team player", "work independently", "under pressure", "interpersonal"], "languages_combined": [{"language": "cantonese", "language_level": ["good command"]}, {"language": "english", "language_level": ["good command"]}, {"language": "mandarin", "language_level": ["good command"]}]}, "experience_required": {"duration": ["minimum of 8 years"], "field": ["ecommerce", "retail", "human resources"]}}, {"job_id": "100003009049887", "location_code": "hk", "company": "Gemini Executive Search & Selection", "job_title": "HR MANAGER | REGIONAL HRBP ROLE | 50-55K", "description": "Our client, a rapidly expanding start-up company with presence across the globe is currently in search of a HR Manager to join the team\n\nWe are seeking for a HR MANAGER | REGIONAL HRBP ROLE | 50-55K\n\nResponsibilities:\n\nAct as a Business Partner to the department heads and set up KPIs of the teams on performance basis\nReview regional monthly payroll and staff benefits schemes\nManage the entire performance review cycle throughout probation, quarterly and annual basis\nDevelop and analyse HR reports such as staff turnover, headcount and staff cost etc.\nConsolidate the required data from the business leaders to prepare the annual budget\nStreamline workflow of HR department to ensure work efficiency\nAssist Group HR team for global policy, program and system to be implemented locally\nConduct salary benchmarking through market survey\nHandle administrative and ad hoc tasks as assigned\n\nJob Requirements:\n\nDegree holder\nMinimum 7 years\u2019 experience gained from MNC or regional office\nKnowledge in employment ordinance or statutory regulations of Asia region\nExcellent communication and interpersonal skills\nDetail-minded with good project management skills\nAbility to perform multi-tasking under a tight timeline\nGood command of written and spoken English and Chinese (Cantonese and Mandarin)\nWell versed in MS applications, preferably strong in excel worksheet", "employment_types": ["Full Time"], "selling_points": ["Assist business leaders in setting up KPIs", "Review regional monthly payroll & staff benefits", "Regional HRBP role at a rapidly expanding company"], "locations": ["Not Specified"], "categories": ["Admin & HR", "Others", "HR Director / Manager", "Training & Development"], "post_time": "2022-01-15T03:50:38Z", "salary": {"currency": null, "max": null, "min": null, "period": "monthly", "term": null}, "salary_visible": false, "title_keywords": ["hr manager"], "responsibilities": ["kpis", "teams"], "requirements": {"degrees": [], "majors": [], "languages": [], "language_level": [], "hard_skills": [], "soft_skills": [], "languages_combined": []}, "experience_required": {"duration": [], "field": []}}, {"job_id": "100003009044471", "location_code": "hk", "company": "Iotena Technology Limited \u611b\u5929\u7acb\u79d1\u6280\u6709\u9650\u516c\u53f8", "job_title": "HR and Administration Manager", "description": "Key responsibilities\n\nl\u00a0\u00a0 Responsible for HR functions including recruitment, payroll and MPF, tax filing and employee relations etc.\n\nl\u00a0\u00a0 Implement HR process and procedure includes probation, performance appraisal process, staff movement and termination and exit process\n\nl\u00a0\u00a0 Conduct salary review, performance bonus and benefits review\n\nl\u00a0\u00a0 Implement human resources policies and procedures that align with the Company\u2019s business strategy\n\nl\u00a0\u00a0 Adopt latest technology and system to improve the HR operational efficiency\n\nl\u00a0\u00a0 Responsible for all company administration planning and implementation\n\nRequirements and Qualifications\u00a0\n\nl\u00a0\u00a0 Degree holder in related disciplines\n\nl\u00a0\u00a0 Minimum 8 years\u2019 solid experiences in HR and Administration management \u00a0\n\nl\u00a0\u00a0 Excellent interpersonal communication and presentation skill\n\nl\u00a0\u00a0 Aggressive and hardworking, able to work independently and take up challenge\n\nl\u00a0\u00a0 Self-motivated and good team player\n\nl\u00a0\u00a0 Good communications in both Chinese and English speaking & writing skills\n\nl\u00a0\u00a0 Familiar with MS Office application, including Word, Excel, Power Point & Chinese Word Processing\n\n\n", "employment_types": ["Full Time"], "selling_points": ["Degree holder in related disciplines, Aggressive", "Min 8 years experiences in HR & Admin management", "Excellent interpersonal communication. Motivated"], "locations": ["Shatin Area"], "categories": ["Admin & HR", "Administration / Operation Manager", "HR Director / Manager", "Recruitment / Executive Search"], "post_time": "2022-01-13T04:15:42Z", "salary": {"currency": null, "max": null, "min": null, "period": "monthly", "term": null}, "salary_visible": false, "title_keywords": ["administration manager", "hr"], "responsibilities": ["mpf", "hr", "tax filing", "recruitment", "payroll"], "requirements": {"degrees": [], "majors": [], "languages": [], "language_level": [], "hard_skills": [], "soft_skills": [], "languages_combined": []}, "experience_required": {"duration": [], "field": []}}, {"job_id": "100003009043519", "location_code": "hk", "company": "\u6df1\u5733\u5e02\u524d\u6d77\u80fd\u6e90\u79d1\u6280\u767c\u5c55\u6709\u9650\u516c\u53f8", "job_title": "Human Resources and Administration \u4eba\u4e8b\u884c\u653f\u5c97", "description": "\u3010\u5e94\u8058\u8005\u8bf7\u63d0\u4f9b\u4e2d\u82f1\u6587\u7b80\u5386\u3011\n\n\u5c97\u4f4d\u804c\u8d23\uff1a\n\n\u4f9d\u636e\u516c\u53f8\u89c4\u5b9a\u548c\u9999\u6e2f\u7684\u4eba\u529b\u8d44\u6e90\u76f8\u5173\u6cd5\u5f8b\u6cd5\u89c4\u548c\u8981\u6c42\uff0c\u534f\u52a9\u5efa\u7acb\u5b8c\u5584\u4eba\u529b\u8d44\u6e90\u7ba1\u7406\u4f53\u7cfb\uff0c\u5f00\u5c55\u4eba\u529b\u8d44\u6e90\u76f8\u5173\u5de5\u4f5c\uff0c\u5305\u62ec\uff1a\n\u5f00\u5c55\u5e74\u5ea6\u4eba\u529b\u8d44\u6e90\u9700\u6c42\u9884\u6d4b\u4e0e\u5206\u6790\uff0c\u7ec4\u7ec7\u5b9e\u65bd\u62db\u8058\u3001\u5f55\u7528\u7b49\u5de5\u4f5c\uff1b\n\u5f00\u5c55\u5458\u5de5\u57f9\u8bad\u3001\u85aa\u916c\u3001\u5458\u5de5\u5173\u7cfb\u3001\u8003\u52e4\u4e0e\u8bf7\u4f11\u5047\u3001\u56e0\u516c\u51fa\u56fd\uff08\u51fa\u5883\uff09\u7ba1\u7406\u7b49\u5de5\u4f5c\uff1b\n\u4e0a\u7ea7\u5b89\u6392\u7684\u5176\u4ed6\u5de5\u4f5c\u3002\n\u534f\u52a9\u5efa\u7acb\u5b8c\u5584\u884c\u653f\u540e\u52e4\u4f53\u7cfb\uff0c\u5f00\u5c55\u76f8\u5e94\u5de5\u4f5c\uff0c\u5305\u62ec\uff1a\n\u5f00\u5c55\u4f1a\u52a1\u3001\u63a5\u5f85\u3001\u5ba3\u4f20\u3001\u529e\u516c\u3001\u5370\u7ae0\u3001\u6863\u6848\u3001\u4fdd\u5bc6\u7ba1\u7406\u7b49\u5de5\u4f5c\uff1b\n\u5f00\u5c55\u975e\u751f\u4ea7\u7269\u8d44\u670d\u52a1\u91c7\u8d2d\uff0c\u4ee5\u53ca\u8d44\u4ea7\u6e05\u67e5\u4e0e\u767b\u8bb0\u3001\u7edf\u8ba1\u62a5\u544a\u7b49\u5de5\u4f5c\uff1b\n\u4e0a\u7ea7\u5b89\u6392\u7684\u5176\u4ed6\u5de5\u4f5c\u3002\nResponsiblities:\n\nCarry out HR work in accordance with the company's regulations and HK's laws and requirements; assist in establishing and improving the HR management, including:\nAnnual human resource demand forecasting and analysis, recruitment, employment, etc.\nTraining, salary, employee relationship, attendance and leave, go abroad on business, etc.Other work assigned by the superior.\nOther work assigned by the superior.\nCarry out administrative work; assist in establishing and improving the administrative management system\uff0cincluding:\nAnnual human resource demand forecasting and analysis, recruitment, employment, etc.\nTraining, salary, employee relationship, attendance and leave, go abroad on business, etc.\nOther work assigned by the superior.\n\u5c97\u4f4d\u8981\u6c42\uff1a\n\n\u4eba\u529b\u8d44\u6e90\u3001\u5de5\u5546\u7ba1\u7406\u7b49\u76f8\u5173\u4e13\u4e1a\uff1b\n\u5177\u67095\u5e74\u4ee5\u4e0a\u76f8\u5173\u5de5\u4f5c\u7ecf\u9a8c\uff1b\n\u5177\u6709\u8ba4\u53ef\u5927\u5b66\u9881\u53d1\u7684\u9ad8\u7ea7\u6587\u51ed/\u9ad8\u7b49\u8bc1\u4e66\u6216\u5177\u540c\u7b49\u5b66\u5386\uff1b\n\u6d41\u5229\u4f7f\u7528\u666e\u901a\u8bdd\u3001\u7ca4\u8bed\u548c\u82f1\u8bed\u4ea4\u6d41\uff1b\nRequirements:\u00a0\n\nHuman resources , business administration and other related majors\uff1b\nAt least 5 years related experience;\u00a0\nA higher diploma/high certificate issued by a recognized university or equivalent;\nFluently communicate in Putonghua, Cantonese and English.", "employment_types": ["Full Time", "Contract"], "selling_points": ["MPF, Bonus, Labour & Medical Insurance", "5 years related experience, Putonghua, English", "Certifiable Higher Dipolma / Higher Certificate"], "locations": ["Hung Hom"], "categories": ["Admin & HR", "Clerical / Admin Staff", "HR Director / Manager", "HR Supporting Staff"], "post_time": "2022-01-12T15:49:48Z", "salary": {"currency": "HKD", "max": 29999, "min": 25000, "period": "monthly", "term": null}, "salary_visible": true, "title_keywords": ["human resources"], "responsibilities": ["regulations", "attendance", "management", "administrative work", "analysis", "hr", "recruitment", "forecasting"], "requirements": {"degrees": ["certificate", "diploma"], "majors": [], "languages": ["cantonese", "putonghua", "english"], "language_level": [], "hard_skills": [], "soft_skills": [], "languages_combined": [{"language": "cantonese", "language_level": []}, {"language": "putonghua", "language_level": []}, {"language": "english", "language_level": []}]}, "experience_required": {"duration": ["at least 5 years"], "field": ["related"]}}, {"job_id": "100003009039836", "location_code": "hk", "company": "Soho House (Hong Kong) Limited", "job_title": "People Partner (HR Manager)", "description": "The role\u2026\n\nThe People Partner will work with and report directly into the People & Development Manager. Soho House was created to bring diverse communities of people together, and we take the same approach when building our teams. We thrive on differences and believe it is critical to our success as a global company. Soho House is proud to be an equal opportunity workplace that seeks to recruit, develop and retain the most talented people from a variety of backgrounds, perspectives, and skills. We therefore encourage applications from all genders, races, religions, ages and sexual orientations, as well as parents, people living with disabilities, and any other groups that could bring diverse perspectives to our business.\n\nSupport the implementation of our strategies on people, learning and diversity\nOwn the employee life cycle includes attracting talents, selection, onboarding, learning & development, rewards & motivation, retention and exit\nSupport the implementation of the performance evaluations and employee engagement initiatives\nMaintain positive employee relations and to provide a working environment embedding our company values\nMonitor and analyse turnover reports and use data metrics to understand trends with hiring\nEnsure that all aspects of staffing and employee relations are delivered timely and in compliance with relevant labour and commercial legislation, and House Rules\nConduct market survey to facilitate management decision on compensation and benefits\nConduct induction program and support managers in orienting the new hires in the first 90 days\nWork with different teams on planning and organising team events\nManage the HR operations including but not limited to attendance and staff benefits administration\n\nWhat we look for\u2026\n\nDegree in Human Resources management, business administration or related disciplines\nNo less than 5 years of Human Resources management experience in hospitality or retail\nWell versed in Hong Kong Employment Ordinance, Employees Compensation Ordinance and other HR related legislation\nExperience in delivering staff training would be a plus\nWell organized, motivated and detail-oriented\nStrong communication and interpersonal capabilities\nProficiency in Microsoft applications\nProficiency in both spoken and written English and Chinese\n\nWe offer\u2026\n\n5-day work week\nFlexible Working Hours\nFamily Meal\nMedical and Dental Insurance\nLife Insurance\nEnhanced MPF scheme\nLearning & Development Programme\nTeam Events \u2013 Cookhouse & House Tonic Programmes, Staff Wellness Programme and Film Screenings\nDiscretionary Bonus\n\nPeople who are eligible to work in Hong Kong or have a valid Hong Kong work permit/visa will be considered for the above position. To apply, please send us your resume with CURRENT and EXPECTED salary.\n\n(Personal data collected will be treated in strictest confidence and only for recruitment purposes.)", "employment_types": ["Full Time", "Permanent"], "selling_points": ["A private member's club", "Medical, Dental & Life Insurance", "Flexible Working Hours"], "locations": ["Sheung Wan"], "categories": ["Admin & HR", "HR Director / Manager"], "post_time": "2022-01-11T17:12:59Z", "salary": {"currency": null, "max": null, "min": null, "period": "monthly", "term": null}, "salary_visible": false, "title_keywords": ["hr manager"], "responsibilities": ["data", "compliance", "teams", "implementation", "monitor", "develop", "maintain", "reports", "analyse", "report"], "requirements": {"degrees": [], "majors": [], "languages": [], "language_level": [], "hard_skills": [], "soft_skills": ["diverse", "timely", "learning", "positive"], "languages_combined": []}, "experience_required": {"duration": [], "field": []}}, {"job_id": "100003009045927", "location_code": "hk", "company": "Funing Property Management Ltd", "job_title": "Human Resource & Administration Manager", "description": "Responsibilities:\n\nResponsible for full spectrum of recruitment activities including candidate sourcing channels, posting job advertisement, interview arrangement, orientation arrangement, etc\nWork proactively to develop close working relationships with business so as to understand the manpower requirements of various projects and respond to their staffing needs;\nFormulate and execute recruitment strategies and initiatives to attract talent to meet business needs;\nConduct recruitment activity using appropriate selection methodologies;\nAssist in preparing the regular analyzing reports, market survey, market comparison and reports to management analysis and review;\nKeep abreast of latest employment related ordinance to ensure compliance with all legal requirements; assist and recommend appropriate improvement for the work flow.\n\nRequirements:\n\nDegree in Human Resources Management or relevant disciplines;\nAt least 10 year's human resources and administration experience with focus on recruitment functions;\nPrevious experience in\u00a0 Property Management Firm is an advantage\n\u00a0\nGood command in spoken & written English and Chinese;\nProficiency in MS Office Applications & Chinese Word Processing;\nDetails-minded, Independent, Self-initiative, Well-organized and good team player with enthusiastic and proactive behavior;\nCapable of working in demanding and challenging environment;", "employment_types": ["Full Time"], "selling_points": ["Handle full spectrum of HR functions", "Plan and conduct recruitment activity", "10 years experience"], "locations": ["North Point"], "categories": ["Admin & HR", "HR Director / Manager"], "post_time": "2022-01-13T09:10:23Z", "salary": {"currency": null, "max": null, "min": null, "period": "monthly", "term": null}, "salary_visible": false, "title_keywords": ["administration manager"], "responsibilities": ["management", "job advertisement", "analysis", "review", "develop", "ensure compliance", "recruitment", "reports", "interview arrangement", "working relationships"], "requirements": {"degrees": ["degree"], "majors": [], "languages": ["english", "chinese"], "language_level": ["proficiency", "good command"], "hard_skills": ["focus", "chinese word processing", "ms office"], "soft_skills": ["good team player", "independent", "capable", "well-organized", "self-initiative", "enthusiastic", "focus", "proactive"], "languages_combined": [{"language": "english", "language_level": ["good command"]}, {"language": "chinese", "language_level": ["proficiency", "good command"]}]}, "experience_required": {"duration": ["at least 10 year"], "field": ["management", "recruitment", "human resources", "administration"]}}, {"job_id": "100003009042317", "location_code": "hk", "company": "GR8 Global Ventures Limited", "job_title": "Senior Human Resources Manager", "description": "Responsibilities:\n\nl\u00a0 Provide full spectrum of HR functions including recruitment and selection, performance management, remunerations, C&B, manpower planning, employee relations, and training & development.\n\nl\u00a0 Applying project management skills to lead all aspects of project lifecycle for HR initiatives to drive business outcomes\n\nl\u00a0 Formulate, implement and review HR and administration policies and\n\nprocedures that are consistent with corporate goals and objectives.\n\nl\u00a0 Provide strategic and professional advice to senior management on HR related issues.\n\nl\u00a0 Perform ad-hoc task as assigned\n\nRequirements:\n\nl\u00a0 Degree holder in HR management or related disciplines\n\nl\u00a0 Not less than 10 years all-round HR experiences with at least 6 years at managerial level in diverse and dynamic working environment\n\nl\u00a0 Excellent communication, presentation and problem solving skills\n\nl\u00a0 Resourceful, initiative, highly-organized and analytical with an eye for detail\n\nl\u00a0 A good team player, detail-oriented with high accuracy\n\nl\u00a0 Well versed in Employment Ordinances and related regulations\n\nl\u00a0 Fluent spoken and written English, Chinese and Mandarin\n\nl\u00a0 Immediate availability is preferred\n\n\u00a0All information provided by applicants will be treated as confidential and will be used for recruitment purpose only.", "employment_types": ["Full Time", "Permanent"], "selling_points": [], "locations": ["Sheung Wan"], "categories": ["Admin & HR", "HR Director / Manager"], "post_time": "2022-01-12T06:59:58Z", "salary": {"currency": null, "max": null, "min": null, "period": "monthly", "term": null}, "salary_visible": false, "title_keywords": ["manager", "human resources"], "responsibilities": ["administration", "ad-hoc", "management", "policies", "hr", "review", "procedures", "project management", "recruitment", "senior management", "planning"], "requirements": {"degrees": ["degree holder"], "majors": ["related disciplines"], "languages": ["english", "chinese", "mandarin"], "language_level": ["fluent"], "hard_skills": ["problem solving skills", "dynamic"], "soft_skills": ["organized", "good team player", "resourceful", "detail-oriented", "communication", "diverse", "dynamic", "eye for detail", "problem solving skills", "initiative", "presentation"], "languages_combined": [{"language": "english", "language_level": ["fluent"]}, {"language": "chinese", "language_level": ["fluent"]}, {"language": "mandarin", "language_level": ["fluent"]}]}, "experience_required": {"duration": ["at least 6 years", "10 years"], "field": ["managerial", "hr"]}}, {"job_id": "100003009048804", "location_code": "hk", "company": "Chandler Macleod Group (HK) Limited", "job_title": "Specialist, Human Resources", "description": "Duties:\n\nBe responsible for all recrutiment activities in EMEA, and support the Head of HR to provide HR services to all staff in Hong Kong and overseas offices\nUtilize various recruitment channels to source qualified candidates and maintain a candidate pipeline\nDeveloping hiring strategies and procedures in line with industry trends\nWork closely with management on all diversity initiatives involving recruitment to ensure fairness in hiring practices\nOwn the end-to-end recruitment process (From demand identification to candidate verbal acceptance)\nLiaise with various stakeholders to fully understand recruitment needs and work closely throughout the process to help create and update job descriptions on various recruitment portals\nCoordinate interviews and support throughout the interview process\n\nRequirements:\n\nMinimum 5 years of experience as HR Generalist or Recruitment focused in EMEA regions\nGood to have recruitment experience in other countries as well\nStrong understanding and hands-on experience with the full lifecycle recruitment process in EMEA regions\nStrong interpersonal, communication, organisational and stakeholder management skills\nTeam player with strong collaboration skills, credibility, and ability to gain buy-in and commitment from others\nFluent in written and spoken English\nProficient in Microsoft Office, Teams, Excel, and Outlook", "employment_types": ["Full Time", "Permanent"], "selling_points": ["Global exposure", "Talent Acquisition and business partner", "Flexible working hours"], "locations": ["Not Specified"], "categories": ["Admin & HR", "Administration / Operation Manager", "HR Director / Manager", "Recruitment / Executive Search"], "post_time": "2022-01-14T07:21:04Z", "salary": {"currency": null, "max": null, "min": null, "period": "monthly", "term": null}, "salary_visible": false, "title_keywords": ["specialist", "human resources"], "responsibilities": ["management", "hr", "procedures", "developing", "coordinate", "maintain", "recruitment", "liaise with", "recruitment process"], "requirements": {"degrees": [], "majors": [], "languages": ["english"], "language_level": ["fluent"], "hard_skills": ["excel", "outlook", "microsoft office"], "soft_skills": ["focused", "communication", "hands-on", "team player", "interpersonal"], "languages_combined": [{"language": "english", "language_level": ["fluent"]}]}, "experience_required": {"duration": ["minimum 5 years"], "field": ["recruitment", "hr generalist"]}}, {"job_id": "100003009052977", "location_code": "hk", "company": "HR Plus (Talent) Limited", "job_title": "Assistant HR Manager (C&B)", "description": "Benefit:\n\nFlexible working hours\nWork from home arrangement (A/B team)\nAttractive annual bonus\nStable leadership team\nFinancially stable company\nAbout the company:\nOur client is a leading automotive company with presence across Hong Kong and Macau. They are currently looking for a C&B Assistant Manager to join their team.\nJob Duty:\n\nSupervise a small team to handle daily operations as well as C&B projects including but not limited to annual salary review exercise, benefit plans review and renewal & payroll system upgrade\u00a0\nWork closely with operations departments to design variable pay schemes\nPerform and handle all payroll functions including but not limited to monthly payroll, final payment, MPF administration, tax filing and leave calculation;\nMonitor and manage all payroll activities to produce accurate and timely delivery of payroll services;\nFormulate, implement and constantly update the HR policies and regulations in compliance with the Group\u2019s direction and Employment Ordinance\nResponsible in preparing various analysis, annual & budgeting reports for management review;\nParticipate in system upgrade and enhancement activities;\n\nRequirements:\n\nDegree holder in Human Resources or Business Administration or related disciplines.\nAt least 8 years of work experience in C&B and hands-on payroll process including 2 years of experience at supervisory level\nStrong analytical skills, multi-tasking, organized and able to meet tight deadlines.\nProficiency in MS Excel, strong knowledge and experience in using IPL system is preferred\nExcellent command in both written and spoken English and Chinese.\n\nCompetitive remuneration package including 5-day work week will be offered to the right candidates. Interested parties please click the below \"Apply Now\" button.\n\nPersonal data provided by job applicants will be used strictly in accordance with the employer's personal data policies.\n\nAll information received will be kept in strict confidence and only for employment-related purposes.\n\n\"We are an equal opportunity employer and all qualified applicants will receive consideration for employment without regard to race, color, religion, sex, national origin, disability status, protected veteran status, or any other characteristic protected by law.\"", "employment_types": ["Full Time", "Permanent"], "selling_points": ["15 days of annual leave", "Offer: 30-40k x 12 months + Bonus", "Financially stable"], "locations": ["Not Specified"], "categories": ["Admin & HR", "Others", "Compensation & Benefits", "HR Director / Manager"], "post_time": "2022-01-17T04:58:02Z", "salary": {"currency": "HKD", "max": 44999, "min": 25000, "period": "monthly", "term": null}, "salary_visible": true, "title_keywords": ["assistant hr manager"], "responsibilities": [], "requirements": {"degrees": [], "majors": [], "languages": [], "language_level": [], "hard_skills": [], "soft_skills": [], "languages_combined": []}, "experience_required": {"duration": [], "field": []}}, {"job_id": "100003009050948", "location_code": "hk", "company": "Rise Associates Asia Limited", "job_title": "HR Manager (HRBP, property developer)", "description": "Our client is one of the most reputable developers who has an extensive real estate footprint in Hong Kong and China. They are now looking for a HR Manager to join the team.\n\u00a0\nJob descriptions:\n\nManage all-round HR activities such as talent acquisition, development and retention, performance and reward management, and employee relations in Hong Kong\nProvide constructive advice and market insights to senior management and related business units\nOversees the Group\u2019s local HR & Admin teams in various mainland cities by providing them with professional coaching and advice, ensuring compliance and alignment with corporate standard\nPrepare and monitor the implementation of the operation plan for all HR activities\n\nRequirements:\n\nUniversity graduate in Human Resources Management, Business Administration or related disciplines\nMinimum of 12 years' HRBP and/or HR account servicing experience in sizeable organizations with a minimum of 6 years in managerial level (experience in real estate industry is preferred)\nExposure in Mainland operation is preferred\nConversant with the Employment Ordinances & related Statutory regulations in Hong Kong and also prefer in Mainland\nGood command of spoken and written English and Chinese\nStrong presentation and communication skills\nProficient in Microsoft office applications\nCandidate with more experience will be considered as Senior HR Manager", "employment_types": ["Permanent"], "selling_points": ["HRBP, exp. in real estate industry preferred", "Knowledge of PRC statutory regulation preferred", "Attractive Salary Package and Fringe Benefits"], "locations": ["Not Specified"], "categories": ["Admin & HR", "HR Director / Manager", "Recruitment / Executive Search"], "post_time": "2022-01-14T11:55:06Z", "salary": {"currency": null, "max": null, "min": null, "period": "monthly", "term": null}, "salary_visible": false, "title_keywords": ["developer", "hr manager"], "responsibilities": ["management", "hr", "compliance", "teams", "monitor", "implementation", "senior management", "operation plan"], "requirements": {"degrees": ["university graduate"], "majors": ["related disciplines", "business administration"], "languages": ["english", "chinese"], "language_level": ["good command"], "hard_skills": ["microsoft office"], "soft_skills": ["communication skills", "presentation"], "languages_combined": [{"language": "english", "language_level": ["good command"]}, {"language": "chinese", "language_level": ["good command"]}]}, "experience_required": {"duration": ["minimum of 6 years", "minimum of 12 years"], "field": ["managerial", "hr", "account servicing"]}}, {"job_id": "100003009043859", "location_code": "hk", "company": "Smart Retail", "job_title": "HR & Administrative Manager", "description": "YOUR ROLE\n\n\u00a0\u00a0\u00a0\u00a0\u00a0\u00a0\u00a0 Matters related to HR & Admin in Hong Kong Headquarter\n\u00a0\u00a0\u00a0\u00a0\u00a0\u00a0\u00a0 Assisting CEO for executing organizational development for the company, including company structure, recruitment, job changes and other organizational development matters\n\u00a0\u00a0\u00a0\u00a0\u00a0\u00a0\u00a0 Managing compensation, benefits, and payroll administration\u00a0\n\u00a0\u00a0\u00a0\u00a0\u00a0\u00a0\u00a0 Review and implement HR policies and procedures\n\u00a0\u00a0\u00a0\u00a0\u00a0\u00a0\u00a0 Confidentiality of personal data\n\u00a0\u00a0\u00a0\u00a0\u00a0\u00a0\u00a0 Manage daily office administrative functions\n\u00a0\u00a0\u00a0\u00a0\u00a0\u00a0\u00a0 Plan and organize staff activities and company events\n\u00a0\u00a0\u00a0\u00a0\u00a0\u00a0\u00a0 Liaise with internal and external parties\n\u00a0\u00a0\u00a0\u00a0\u00a0\u00a0\u00a0 Procurement for parts and office supplies\n\u00a0\u00a0\u00a0\u00a0\u00a0\u00a0\u00a0 To drive down cost and aggressively reviewing internal processes and policies to reduce waste and enhance cost performance\n\n\u00a0WHO WE ARE LOOKING FOR\n\n\u00a0\u00a0\u00a0\u00a0\u00a0\u00a0\u00a0 Bachelor\u2019s degree in a relevant subject and/or equivalent work experience.\n\u00a0\u00a0\u00a0\u00a0\u00a0\u00a0\u00a0 At least 3-4 years experience with the processes, tools and guidelines for overseeing and optimizing the costs and revenues.\n\u00a0\u00a0\u00a0\u00a0\u00a0\u00a0\u00a0 Experience in start-up environment would be an advantage\n\u00a0\u00a0\u00a0\u00a0\u00a0\u00a0\u00a0 Knowledge in data networks, wireless technologies and vending machines is an advantage.\n\u00a0\u00a0\u00a0\u00a0\u00a0\u00a0\u00a0 Proven ability to juggle multiple projects at a time, while maintaining sharp attention to details.\n\u00a0\u00a0\u00a0\u00a0\u00a0\u00a0\u00a0 Solid experience with MS Office (particularly MS Excel) and Cloud base software.\n\u00a0\u00a0\u00a0\u00a0\u00a0\u00a0\u00a0 Knowledgeable in purchasing\u00a0 parts / components through Taobao is a must.\n\u00a0\u00a0\u00a0\u00a0\u00a0\u00a0\u00a0 Excellent listening, negotiation, and presentation abilities.\n\u00a0\u00a0\u00a0\u00a0\u00a0\u00a0\u00a0 Strong verbal and written communication skills in English and Chinese.\n\u00a0\u00a0\u00a0\u00a0\u00a0\u00a0\u00a0 Immediate available is preferred\n\nInterested parties please apply for the job by clicking the \u201cApply Now\u201d button with your updated resume and salary details.", "employment_types": ["Full Time", "Permanent"], "selling_points": [], "locations": ["Kowloon Bay"], "categories": ["Admin & HR", "Administration / Operation Manager", "HR Director / Manager", "Recruitment / Executive Search"], "post_time": "2022-01-13T02:11:55Z", "salary": {"currency": null, "max": null, "min": null, "period": "monthly", "term": null}, "salary_visible": false, "title_keywords": ["hr", "administrative manager"], "responsibilities": ["recruitment", "hr", "executing"], "requirements": {"degrees": [], "majors": [], "languages": [], "language_level": [], "hard_skills": [], "soft_skills": ["organizational"], "languages_combined": []}, "experience_required": {"duration": [], "field": []}}, {"job_id": "100003009042275", "location_code": "hk", "company": "AUX International Holdings Limited", "job_title": "Human Resources Manager", "description": "Responsibilities:\u00a0\n\n\nHandle full spectrum of human resources functions including recruitment & selection, compensation & benefits, employee relations, performance management, training and other Administrative functions\nImplement HR policies & procedures to meet company standards\n\nProvide professional HR advices to different business units\n\nLiaise with team heads on various HR issues\nPrepare HR reports and data for management review\nLead or assist any other ad-hoc projects as assigned\n\n\u00a0Requirements:\u00a0\n\n\nDegree or above in Human Resources or related disciplines\nWith min. 8 years' relevant experience in Human Resources functions of which at least 3 years at managerial level; with experience in F&B industry will be an advantage\nWell-versed in Employment Ordinance and related legislations\nGood command of both spoken and written English and Chinese\nExcellent communication and interpersonal skills\nProficient in MS Word and Excel; with experience in using Alpha HRMS will be an advantage\nWell-organized, meticulous and able to handle multi-tasks within deadlines and work independently\nImmediately available is preferred\n\nInterested parties please send your full resume with availability, current/last and expected salary by clicking\u00a0 \u201cAPPLY NOW\u201d\u00a0\n\n\u00a0(Personal data collected will be kept in strictest confidence and be used for recruitment purpose only.)", "employment_types": ["Full Time", "Permanent"], "selling_points": [], "locations": ["Wan Chai"], "categories": ["Admin & HR", "Compensation & Benefits", "HR Director / Manager", "Recruitment / Executive Search"], "post_time": "2022-01-12T10:00:27Z", "salary": {"currency": null, "max": null, "min": null, "period": "monthly", "term": null}, "salary_visible": false, "title_keywords": ["manager", "human resources"], "responsibilities": ["management", "data", "policies", "hr", "procedures", "hr reports", "recruitment", "liaise with", "ad-hoc projects", "human resources functions", "management review"], "requirements": {"degrees": ["degree or above"], "majors": ["related disciplines"], "languages": ["english", "chinese"], "language_level": ["good command"], "hard_skills": ["excel", "ms word"], "soft_skills": ["meticulous", "work independently", "multi-tasks", "well-organized", "communication and interpersonal skills"], "languages_combined": [{"language": "english", "language_level": ["good command"]}, {"language": "chinese", "language_level": ["good command"]}]}, "experience_required": {"duration": ["at least 3 years", "8 years"], "field": ["managerial", "f&b", "relevant experience", "human resources"]}}, {"job_id": "100003009043039", "location_code": "hk", "company": "Santa Fe Relocation", "job_title": "Human Resources Manager, Hong Kong & Taiwan", "description": "The Role\u00a0\n\nThe Human Resources Manager will be reported to the General Manager, Hong Kong & Taiwan, functionally reported to Head of Human Resources, Asia and focus on the HR functional partnership of both Hong Kong & Taiwan station by providing a prospective and effective HR support, maintaining close contact with the managers and employees, and optimizing and executing human resources policies and processes to ensure the recruitment, training, retention and motivation of quality talent.\n\nThis position requires a high calibre leader who can drive culture change, employee engagement, performance management, organizational transformation as well as processes and employee best-practice.\n\nResponsibilities:\u00a0\n\nBased in Hong Kong office.\nFocus on staffing, recruiting and manpower planning, employee engagement and performance management.\nResponsible for all HR activities in the region and ensure its HR services are in alignment with the organization goals;\nEstablish, implement and review Human Resource policy and procedures, ensuring that they are in line globally and consistently, whilst comply with local requirements.\nWork in partnership with the management to drive employee engagement, utilizing annual feedback and data from Thrive@Work survey in formulating the improvement plans;\nResponsible for other HR initiatives including the development, expansion and implementation of performance management.\nDrive and support organization development activities and initiatives, including people quantum projects and transformation programs;\nResponsible for payroll and/or payroll outsourcing matters for the region.\nEnsure annual staff cost budget of the region could be making out timely and accurately.\nManage and develop the HR team at Hong Kong office.\n\n\u00a0Requirements:\u00a0\n\nDegree holder with minimum 10 years generalist HR experience gained from MNC;\nProactive, pleasant & detail-minded;\nWell-versed in the HK Employment Ordinance and HR related legislations;\nExcellent interpersonal, problem solving and multi-tasking skills;\u00a0\u00a0\nAbility to think strategically and participate in business planning;\u00a0\u00a0\nExperience in a Regional role is definitely an advantage.", "employment_types": ["Full Time", "Permanent"], "selling_points": ["Min. 10 years of HRBP experience gained from MNC", "5 days work week, MNC working environment", "Regional exposure (Hong Kong & Taiwan)"], "locations": ["Wan Chai"], "categories": ["Admin & HR", "HR Director / Manager"], "post_time": "2022-01-12T09:36:22Z", "salary": {"currency": null, "max": null, "min": null, "period": "monthly", "term": null}, "salary_visible": false, "title_keywords": ["manager", "human resources"], "responsibilities": ["management", "cost", "data", "hr", "review", "procedures", "implementation", "budget", "develop", "plans", "payroll", "planning"], "requirements": {"degrees": ["degree holder"], "majors": [], "languages": [], "language_level": [], "hard_skills": ["problem solving"], "soft_skills": ["detail-minded", "pleasant", "problem solving", "think strategically", "multi-tasking skills", "proactive", "interpersonal"], "languages_combined": []}, "experience_required": {"duration": ["minimum 10 years"], "field": ["hr"]}}, {"job_id": "100003009042988", "location_code": "hk", "company": "SinoMab BioScience Ltd", "job_title": "Human Resources & Administration Manager (5 days)", "description": "Responsibilities\n\nReporting to CEO, you will be responsible for:\n\nMatters related to HR & Admin in Hong Kong Headquarter\nCoordinating with HR departments in different locations in China to ensure policy consistency and compliance according to listing rules in Hong Kong\u00a0\nAssisting CEO for executing organizational development for the company, including company structure, recruitment, job changes and other organizational development matters\nManaging compensation, benefits, and payroll administration to ensure fair and consistentpractice in accordance with salary administration guidelines as stipulated by Hong Kong Headquarterand local legislation\nPrepare/Review & implement the annual HR budget\nReview and implement HR policies and procedures\nEnsuring confidentiality of data, which, if disclosed, might have significant internal effect or minor external effects\nManage daily office administrative functions\nPlan and organize staff activities and company events\nLiaise with internal and external parties\nOther ad hoc duties\n\nRequirements\n\nThe applicant should possess:\n\nUniversity Degree of relevant disciplines\nPrevious working experience in Hong Kong companies, preferably with mainland subsidiaries or business\nMinimum 10 years of human resources experience, with at least 4 years in a management capacity\nAll-round HR team leadership characterized with a positive, personable and supportive manner, a strong business partnering approach and hands on & can do attitude\nGood in HK Employment Ordinance and PRC labour ordinance is preferred\u00a0\nGood communication skills and team-work player mentality, and capabilities to work in a mature, well-organized, self-motivated, and detail oriented manner & willingness to work\u00a0under pressure and overtime\nFluency in English, Cantonese and Mandarin\nWillingness to travel occasionally including to mainland\nImmediate availability is an advantage\n\nWe offer\u00a0\n\nFive-day work week\nMedical insurance\u00a0\nDental insurance\n13 month salary", "employment_types": ["Full Time", "Permanent"], "selling_points": ["Five-day work", "HR & Admin Manager", "Medical & Dental insurance & 13 month salary"], "locations": ["Shatin Area"], "categories": ["Admin & HR", "Compensation & Benefits", "HR Director / Manager", "Recruitment / Executive Search"], "post_time": "2022-01-12T09:26:00Z", "salary": {"currency": null, "max": null, "min": null, "period": "monthly", "term": null}, "salary_visible": false, "title_keywords": ["administration manager", "human resources"], "responsibilities": ["ad hoc duties", "reporting", "data", "guidelines", "policies", "hr", "compliance", "review", "budget", "procedures", "internal and external parties", "executing", "recruitment", "plan", "liaise with", "payroll", "listing", "administration"], "requirements": {"degrees": ["university degree"], "majors": [], "languages": ["cantonese", "english", "mandarin"], "language_level": ["fluency"], "hard_skills": [], "soft_skills": ["communication skills", "supportive", "personable", "self-motivated", "under pressure", "detail oriented", "well-organized", "mature", "hands on", "willingness to work", "leadership", "positive"], "languages_combined": [{"language": "cantonese", "language_level": ["fluency"]}, {"language": "english", "language_level": ["fluency"]}, {"language": "mandarin", "language_level": ["fluency"]}]}, "experience_required": {"duration": ["at least 4 years", "minimum 10 years"], "field": ["management", "business", "human resources"]}}, {"job_id": "100003009044041", "location_code": "hk", "company": "Talwin Consultants Ltd", "job_title": "Human Resources Manager (BP)", "description": "Requirements\n\nDegree holder (full time);\nWith around 10 \u2013 15 years of all-rounded Human Resources experience with focus in BP;\nA service-oriented mindset with excellent interpersonal and communication skills necessary to deal with people at all levels;\nWith motivation, drive, and passion for success;\nDynamic, resourceful with strong analytical skills and commercial acumen combined with a drive for results and problem-solving;\nWell versed with HK Employment Ordinance;\nExcellent command of both written and spoken English and Chinese\u00a0\n\nCompany:\n\nA reputable company with good career prospect\nPackage:\n\nAround HK$700K - HK$800K p.a. (neg.)", "employment_types": ["Full Time", "Permanent"], "selling_points": ["Around HK$700K - HK$800K p.a. (neg.)", "A reputable and sizable company", "All-rounded HR experience with focus in BP"], "locations": ["Not Specified"], "categories": ["Admin & HR", "Others", "HR Director / Manager", "HR Supporting Staff"], "post_time": "2022-01-13T02:53:46Z", "salary": {"currency": null, "max": null, "min": null, "period": "monthly", "term": null}, "salary_visible": false, "title_keywords": ["manager", "human resources"], "responsibilities": ["communication"], "requirements": {"degrees": ["degree holder"], "majors": [], "languages": ["english", "chinese"], "language_level": ["excellent"], "hard_skills": ["problem-solving", "analytical skills", "dynamic", "focus", "acumen"], "soft_skills": ["communication skills", "resourceful", "passion for", "service-oriented", "problem-solving", "analytical skills", "dynamic", "deal with people", "focus", "interpersonal"], "languages_combined": [{"language": "english", "language_level": ["excellent"]}, {"language": "chinese", "language_level": ["excellent"]}]}, "experience_required": {"duration": ["15 years"], "field": ["human resources"]}}, {"job_id": "100003009051602", "location_code": "hk", "company": "Success Meteor", "job_title": "Recruitment Manager", "description": "[REF: SHRM(P)1/SAHRM(A)/JOBS]\n\nLocation: Sheung Wan\n\nRoles & responsibilities:\n\nPlan, design, develop and implement staff relations and welfare policies to align with the corporate strategies;\noversee the handling of staff welfare benefits (such as medical/dental treatment, merit awards and etc.), make recommendations for applications of staff welfare schemes/grants and ensure all applications are processed in a timely and proper manner;\nmanage staff awards such as Long Service Awards, Retirement Awards by designing the souvenir(s) and follow up the production and distribution;\nplan and formulate the office yearly plan/budget of the Section for management\u2019s approval;\nconduct review to smoothen the operation procedure of the Section and provide recommendations to optimize the staff welfare benefit schemes/grants;\nconsolidate the regular/annual exercises (i.e. annual report/plan/budget) for the Section and prepare the integrated version for management\u2019s approval;\nlead the Administration Team to maintain a smooth daily office operation for the Section; and\nplan, design and implement staff welfare/relations initiatives as assigned.\n\nThe ideal candidate should possess:\n\na recognized degree or equivalent;\nat least Grade D in English Language (Syllabus B) and Chinese Language in the HKCEE or equivalent;\nat least 4 years of administrative experience preferably in drafting administration policy/staff welfare schemes or project management;\nproficiency in English and Chinese, and preferably in Putonghua;\ncalibre as a good team player with supervisory experience and sound communication skills; and\nability to work independently with initiative and have a strong sense of responsibility.\n\n(Please specify in the application form the HKCEE result and relevant working experience you have attained in detail.)\n\nCompensation & employment terms:\n\nThe successful candidate will initially be offered a 3-year contract with a remuneration package which will be commensurate with his/her background and experience.\u00a0 The continuation of employment and employment terms thereafter will be subject to mutual agreement.\u00a0 Apart from contributions to the MPF Scheme, other benefits include paid annual leave, medical services, a dental scheme and training sponsorships.\u00a0 The incumbent will normally work under a 5-day week schedule subject to operational needs and exigencies of the service.\n\nApplication:\n\nPlease send your resume and a completed application form [F601(n)] with indication of your current and expected salaries to the Head of Human Resources Division, Tung Wah Group of Hospitals at 4/F., Wong Fung Ling Memorial Building, 12 Po Yan Street, Hong Kong by 24 January\u00a02022.\u00a0 The reference code should be marked both in the letter and on the envelope.\u00a0 Application forms are obtainable in person or can be downloaded from http://www.tungwah.org.hk.\u00a0\u00a0Underpaid mail items will not be accepted by Tung Wah.\u00a0 For proper delivery of your mail items, please ensure your mail items bear sufficient postage with return address before posting.\u00a0 Personal data provided by applicants will be used strictly for recruitment purpose only and in accordance with the Tung Wah's personal data policy.\u00a0 Applicants not invited to attend an interview by 30 April 2022 may assume that their applications are unsuccessful.\n\nWE ARE AN EQUAL OPPORTUNITIES EMPLOYER", "employment_types": ["Full Time"], "selling_points": ["Excellent working environment", "Competitive basic salary and commission structure", "Candidates with relevant experience are preferable"], "locations": ["Tsim Sha Tsui"], "categories": ["Management", "General Management", "Admin & HR", "HR Director / Manager", "Insurance", "Others"], "post_time": "2022-01-16T13:59:47Z", "salary": {"currency": "HKD", "max": 54999, "min": 25000, "period": "monthly", "term": null}, "salary_visible": true, "title_keywords": ["manager"], "responsibilities": ["develop", "policies", "plan", "design"], "requirements": {"degrees": [], "majors": [], "languages": [], "language_level": [], "hard_skills": ["wan"], "soft_skills": [], "languages_combined": []}, "experience_required": {"duration": [], "field": []}}, {"job_id": "100003009038130", "location_code": "hk", "company": "Christian Action", "job_title": "Senior Manager / Head of Human Resources", "description": "Our client, a well-known securities firm in Hong Kong, is looking for a high calibre to join the group.\n\n\nResponsibilities\n\nHandle the entire recruitment process from sourcing of candidates to preparing remuneration proposal\nCommunicate with line managers for recruitment needs and requirements\nParticipate in various HR projects such as compensation & benefits, tax issues, performance appraisal and other HR initiatives as required\nDevelop, review and implement human resources strategies, policies and procedures\nParticipate ad hoc projects as assigned\u00a0\u00a0\n\nRequirements\n\nDegree holder preferably in Human resources management\nMinimum 5 years\u2019 recruitment experience in securities firm / financial industry\nIndependent, self-driven and good interpersonal skills\nGood command in spoken and written Chinese (both Cantonese & Putonghua) and English\nProficient in\u00a0PC knowledge, Word and Excel\nImmediate available is preferred\n\nTo apply, please send your detailed resume or contact Timothy Wong at 3990 3179 for a confidential discussion.\n\nOnly shortlisted candidates will be notified.\n\nApplicants who are not contacted within two weeks may consider their applications unsuccessful.\n\nAll data collected will be used for recruitment purpose only & will be used strictly confidential.\n\nConners Consulting Limited 2005 Kai Tak Commercial Building 317 Des Voeux Road Central Hong Kong.\n\nTel: (852) 3996 8090\u00a0\u00a0\u00a0\u00a0\u00a0\n\nWebsite: www.connersconsulting.com", "employment_types": ["Full Time", "Contract"], "selling_points": [], "locations": ["Wong Tai Sin Area"], "categories": ["Admin & HR", "HR Director / Manager"], "post_time": "2022-01-11T05:24:13Z", "salary": {"currency": null, "max": null, "min": null, "period": "monthly", "term": null}, "salary_visible": false, "title_keywords": ["senior manager", "human resources"], "responsibilities": ["communicate with", "recruitment process", "recruitment"], "requirements": {"degrees": [], "majors": [], "languages": [], "language_level": [], "hard_skills": [], "soft_skills": [], "languages_combined": []}, "experience_required": {"duration": [], "field": []}}, {"job_id": "100003009051793", "location_code": "hk", "company": "Compass Group Hong Kong Ltd", "job_title": "Training Manager", "description": "Responsibilities\n\nLead a small team to deliver professional HR services;\nManage full spectrum of human resources functions, such as recruitment & selection, performance management, employee relations & engagement, talent development & training, compensation & benefits, and HRIS;\nEstablish and implement human resources strategies in line with organizational objectives;\nEnsure Organization HR Policies and Procedures are compliant with local regulations, and in line with industry best practices;\nDevelop and implement various Human Resources Management Programs to support continued development and management in HR framework. Manage regular review and make necessary adjustment with follow up action accordingly;\nAct as a change agent by turning ideas into action;\nLead any special HR projects e.g. change of the HRIS;\nEnhance the HR infrastructure, policies and systems for Christian Action Representative Office in Qinghai, PRC\nSupport management by providing human resources reports, advice and counsel etc;\nPerform ad-hoc assignments and projects as assigned by the management.\n\nRequirements\n\nBachelor degree in Human Resources Management or related discipline;\nHR generalist with min. 15 years of experience with which at least 10 years in management role of multi-national/medium size organization. NGO experience is a must and exposure from PRC will be definitely advantage;\nExcellent strategic management, analytical, organizational, communication, problem-solving, executive & multitasking skills;\nInitiative, detail-minded, committed and strong sense of responsibility;\u00a0\nHands-on experience in HR operations, Employment-related Ordinances and HRIS are essential;\nBe comfortable with change and working in a dynamic & fast paced environment;\nBe able to cultivate and pursue Christian excellence in our work and align with Christian Vision, Mission and Core Values of Christian Action;\nHigh proficiency in both English and Chinese\u00a0 (including Putonghua);\n\nImmediate available is definitely an advantage\n\nInterested parties, please send your resume (MUST including present/last and expected salary)\u00a0with\u00a0applied position\u00a0through the \"APPLY NOW\" button or by post to:\u00a0\n\n\nMs Karen Sin\n\nHuman Resources Division\n\nChristian Action\n\n5/F, 55 Clear Water Bay Road\n\nChoi Wan (2) Estate\n\nKowloon\n\n(The official retirement age of Christian Action is 60 years old.)", "employment_types": ["Full Time", "Permanent"], "selling_points": ["Full spectrum of Training & Development functions", "Degree in HR or related field, 5 yrs' rel. exp.", "F&B Industry"], "locations": ["Mong Kok"], "categories": ["Admin & HR", "Others", "HR Director / Manager", "Training & Development"], "post_time": "2022-01-17T01:12:38Z", "salary": {"currency": null, "max": null, "min": null, "period": "monthly", "term": null}, "salary_visible": false, "title_keywords": ["manager"], "responsibilities": ["regulations", "management", "ideas", "policies", "hr", "lead a small team", "procedures", "infrastructure", "systems", "develop", "regular review", "ad-hoc assignments", "recruitment", "reports", "human resources functions"], "requirements": {"degrees": ["degree", "bachelor"], "majors": [], "languages": ["putonghua", "english", "chinese"], "language_level": ["proficiency"], "hard_skills": ["problem-solving", "dynamic"], "soft_skills": ["detail-minded", "sense of responsibility", "organizational", "problem-solving", "communication", "committed", "hands-on", "dynamic", "initiative"], "languages_combined": [{"language": "putonghua", "language_level": []}, {"language": "english", "language_level": ["proficiency"]}, {"language": "chinese", "language_level": ["proficiency"]}]}, "experience_required": {"duration": ["at least 10 years", "15 years"], "field": ["hr", "management", "related"]}}, {"job_id": "100003009051819", "location_code": "hk", "company": "RGF HR Agent Hong Kong Limited", "job_title": "Japanese Speaking Accounting, HR & Admin Manager - Japanese Company (Up to 35K/San Po Kong)", "description": "Degree\u00a0holder in\u00a0Human Resources Management or related disciplines\nMinimum 5 years' solid experience in C&B function preferably gained from sizeable organization or property management\nWell versed in Hong Kong Employment Ordinance and related legislations\nStrong computer literacy in MS office and HRIS preferably in IPL\nSelf-motivated, analytical, well-organized, strong sense of commitment and able to work under tight timeline\nGood command of both written and spoken English\u00a0& Chinese\n\nWe will offer attractive compensation package to the right candidate. Please send application enclosing resume stating career and salary history, expected salary and date of availability to\u00a0The Human Resources Manager, Goodwell Property Management Limited, 2/F New Treasure Centre, 10 Ng Fong Street, San Po Kong, Kowloon\u00a0or\u00a0by clicking\u00a0\u201cApply Now\u201d\u00a0(in Word format). Please quote the reference of the position you apply for in all correspondences.\u00a0\n\nWe are an equal opportunity employer and welcome applications from all qualified candidates.\u00a0 Personal data collected will be treated in strictest confidence and handled confidentially by authorized personnel for recruitment-related purposes within the Group. Applicants not hearing from us within six weeks from the date of\u00a0application\u00a0may consider their applications unsuccessful.\n\n(Our website :\u00a0http://www.goodwell.com.hk/)", "employment_types": ["Full Time", "Permanent"], "selling_points": ["Japanese Automobile Company/JLPT N2 or above", "10 yrs exp in Accounting/ACCA/HKIAAT Member", "Up to 35K/San Po Kong/ Stable job!"], "locations": ["Wong Tai Sin Area"], "categories": ["Accounting", "Finance / Accounting Manager", "Admin & HR", "Administration / Operation Manager", "HR Director / Manager"], "post_time": "2022-01-17T01:16:48Z", "salary": {"currency": null, "max": null, "min": null, "period": "monthly", "term": null}, "salary_visible": false, "title_keywords": ["admin", "hr", "accounting", "manager"], "responsibilities": ["management", "website", "recruitment", "personal data", "legislations"], "requirements": {"degrees": ["degree holder"], "majors": ["related disciplines"], "languages": ["english", "chinese"], "language_level": ["good command"], "hard_skills": ["ipl", "hong kong employment ordinance", "word", "ms office"], "soft_skills": ["computer literacy", "self-motivated", "confidence", "well-organized"], "languages_combined": [{"language": "english", "language_level": ["good command"]}, {"language": "chinese", "language_level": ["good command"]}]}, "experience_required": {"duration": ["minimum 5 years"], "field": ["management"]}}, {"job_id": "100003009041667", "location_code": "hk", "company": "Finet Holdings Limited", "job_title": "HR and Admin. Manager", "description": "Job duties\n\n\n\nDirect report to HR Director/ Head of HR\nTo provide full spectrum of HR professional skills and knowledge to the company, including General HR, recruitment, HR Policy, On/off boarding. C&B, Payroll, etc\nHandle all round office admin duties, such as office maintenance, procurement, manage receptionist/ pantry assistant, office renovation, equipment etc\nTo assist in handling C&B related matters including taxation, social insurance, expatriate package, salary increment benchmark, relocation package for Hong Kong and overseas offices.\nProvides guidance and input on business unit restructures, workforce planning, talent management and succession planning\nMaintain system and data updates, including employee record and personal details from hire to retire, including on boarding and off boarding, work visa and other related documents etc\nHandling oversea offices' payroll calculation.\nCoordinate for company events and staff activities\nLiaising between employees and management\nParticipate in ad-hoc HR projects as-needed.\n\nRequirement\n\n\n\nDegree graduate in HR Management, or related disciplines\nAt least 8 years Regional Human Resources experience primarily in the area of HR Generalist; with Adminstrative experience is an advantage\nProficiency in MS Office with good Excel and PowerPoint skill set; Excel with V-look up and Pivot Table knowledge will be a big plus\nFluency in both spoken and written English and Chinese is a MUST.\nImmediate Available is preferred\n\nInterested parties please submit your application by clicking 'apply now' below and upload your updated resume.\n\n", "employment_types": ["Full Time", "Permanent"], "selling_points": [], "locations": ["Wan Chai"], "categories": ["Admin & HR", "HR Director / Manager"], "post_time": "2022-01-12T04:11:20Z", "salary": {"currency": null, "max": null, "min": null, "period": "monthly", "term": null}, "salary_visible": false, "title_keywords": ["hr", "admin", "manager"], "responsibilities": ["ad-hoc", "taxation", "guidance", "management", "maintenance", "data", "related documents", "hr", "renovation", "coordinate", "planning", "recruitment", "maintain", "insurance", "payroll", "report"], "requirements": {"degrees": ["degree"], "majors": ["related disciplines"], "languages": ["english", "chinese"], "language_level": ["fluency"], "hard_skills": ["excel", "plus", "pivot table", "powerpoint", "ms office"], "soft_skills": [], "languages_combined": [{"language": "english", "language_level": ["fluency"]}, {"language": "chinese", "language_level": ["fluency"]}]}, "experience_required": {"duration": ["at least 8 years"], "field": ["hr generalist", "human resources"]}}, {"job_id": "100003009042170", "location_code": "hk", "company": "Bank of China (Hong Kong) Limited", "job_title": "Business Strategy Manager (Human Resources Management) \u2013 Contact Centre", "description": "Our client, a Japanese automobile company is looking for an Accounting, HR & Admin Manager to join their team as follows:\n\nJob Duties:\n\u2022 Handle the full set of accounting\n\u2022 Prepare month-end consolidation\n\u2022 Manage statutory audit, J-SOX, and tax filing\n\u2022 Prepare reports according to the templates provided by the HQ in Japan\n\u2022 Oversee the HR and Admin department\n\u2022 Liaise with the HQ in Japan\n\u2022 Other ad-hoc duties as assigned\n\nRequirement:\n\u2022 Bachelor's degree or higher\n\u2022 At least 10 years of relevant experience\n\u2022 Fluent in Japanese(JLT N2 or higher), English, and Chinese\n\u2022 ACCA/ HKIAAT student member or equivalent\n\u2022 Work experience in a Japanese company is a must\n\nPackage:\n- Discretionary bonus\n- Medical insurance\n\nInterested parties please send us your resume in MS Word/PDF format in English. All information received will be kept in strict confidential and only for recruitment purpose.\n\n", "employment_types": ["Full Time"], "selling_points": ["Review and refine the HR-related plans", "Degree holder with major in BusinessAdministration", "Degree holder w/ major in Business Administration"], "locations": ["Not Specified"], "categories": ["Banking / Finance", "Others", "Sales, CS & Business Devpt", "Business Development", "Admin & HR", "HR Director / Manager"], "post_time": "2022-01-12T06:27:28Z", "salary": {"currency": null, "max": null, "min": null, "period": "monthly", "term": null}, "salary_visible": false, "title_keywords": ["manager", "human resources"], "responsibilities": ["hr", "tax filing", "month-end", "audit", "full set of accounting", "liaise with", "ad-hoc duties", "prepare reports"], "requirements": {"degrees": ["degree", "bachelor"], "majors": [], "languages": ["japanese", "english", "chinese"], "language_level": ["fluent"], "hard_skills": ["acca"], "soft_skills": [], "languages_combined": [{"language": "japanese", "language_level": ["fluent"]}, {"language": "english", "language_level": ["fluent"]}, {"language": "chinese", "language_level": ["fluent"]}]}, "experience_required": {"duration": ["at least 10 years"], "field": ["relevant experience"]}}, {"job_id": "100003009050372", "location_code": "hk", "company": "Daniel's Group Holdings Limited", "job_title": "Human Resources Officer", "description": "Reporting to Chairlady, you will be responsible for :\n\nMatters related to HR & Admin in Hong Kong Office\nCoordinating with HR departments in different locations in China to ensure policy consistency\nManage full employee life cycle from recruitment and selection, on-boarding, engagement and development to off boarding\nFormulate recruitment and retention plan, expand varies hiring channels to attract the right talent\u00a0\nReview HR policies, ensure all the legal compliance and requirement of employment ordinance are met\nManaging compensation, benefits, and payroll administration\nManage daily office administrative functions\nReview and prepare annual appraisal report\nWork closely with management and key department heads to share HR insights and best-practices in the market\n\nRequirements :\n\nDegree holder in Human Resources or Business Administration or related disciplines\n6-8 years of working experience with at least 2 years in managerial level.\nStrong analytical skills, multi-tasking, organized and able to meet tight deadlines.\nExcellent communication & interpersonal skills.\nWell-versed in Employment Ordinance and other related legislation in Hong Kong.\nGood\u00a0command of both oral and written English and Chinese (include Mandarin).\nImmediately available is highly preferred\n\nWe offer successful candidate an attractive remuneration package and excellent career prospects. Interested parties please send your resume with recent PHOTO, present and expected salary also contact details by clicking \"Apply Now\".", "employment_types": ["Full Time"], "selling_points": [], "locations": ["Tuen Mun Area"], "categories": ["Admin & HR", "Clerical / Admin Staff", "HR Director / Manager", "HR Supporting Staff"], "post_time": "2022-01-14T10:18:22Z", "salary": {"currency": null, "max": null, "min": null, "period": "monthly", "term": null}, "salary_visible": false, "title_keywords": ["human resources officer"], "responsibilities": ["reporting", "policies", "hr", "review", "compliance", "recruitment", "plan"], "requirements": {"degrees": [], "majors": [], "languages": [], "language_level": [], "hard_skills": [], "soft_skills": ["responsible"], "languages_combined": []}, "experience_required": {"duration": [], "field": []}}, {"job_id": "100003009043615", "location_code": "hk", "company": "Wilson Communications Limited", "job_title": "Assistant Human Resources and Administration Manager", "description": "\u5d17\u4f4d\u8077\u8cac\n\nDeliver quality customer services through counter transactions\n\u6253\u9020\u5206\u884c\u4e00\u7ad9\u5f0f\u5c08\u696d\u91d1\u878d\u7406\u8ca1\u670d\u52d9\nSupport back-end branch operations\n\u8655\u7406\u5ba2\u6236\u6bcf\u65e5\u6ac3\u53f0\u4ea4\u6613(\u5305\u62ec\u73fe\u91d1\u6536\u4ed8\u3001\u5165\u7968\u3001\u8f49\u5e33\u3001\u5b9a\u671f\u3001\u532f\u6b3e\u7b49\u7684\u5de5\u4f5c)\u3001\u5ba2\u6236\u67e5\u8a62\u53ca\u5167\u90e8\u6587\u66f8\u5de5\u4f5c\nCross-sell retail banking products\n\u92b7\u552e\u53ca\u8f49\u4ecb\u5de5\u4f5c\n\u5d17\u4f4d\u8981\u6c42\n\nSecondary School graduate or above\n\u4e2d\u5b78\u6587\u6191\u6216\u4ee5\u4e0a\u7a0b\u5ea6\nStrong sales and service orientation with outgoing personality and good communication skills\n\u5177\u826f\u597d\u7684\u6e9d\u901a\u6280\u5de7\u53ca\u5ba2\u6236\u670d\u52d9\u610f\u8b58\nProficiency in English and Cantonese as well as fluency in Putonghua\n\u5177\u826f\u597d\u7684\u4e2d\u3001\u82f1\u6587\u95b1\u8b80\u3001\u66f8\u5beb\u53ca\u666e\u901a\u8a71\u8868\u9054\u80fd\u529b", "employment_types": ["Full Time", "Permanent"], "selling_points": ["Kwai Fong, 5-Day, Free Shuttle Bus", "Handle HR and Admin. duties plus leasing issues", "Experience in retail or FMCG industry is essential"], "locations": ["Kwai Fong"], "categories": ["Admin & HR", "Administration / Operation Manager", "Secretary", "HR Director / Manager"], "post_time": "2022-01-13T00:45:46Z", "salary": {"currency": null, "max": null, "min": null, "period": "monthly", "term": null}, "salary_visible": false, "title_keywords": ["human resources", "administration manager", "assistant"], "responsibilities": ["operations", "quality", "transactions", "customer services", "communication", "banking"], "requirements": {"degrees": [], "majors": [], "languages": ["cantonese", "putonghua", "english"], "language_level": ["fluency", "proficiency"], "hard_skills": [], "soft_skills": ["outgoing personality", "communication skills"], "languages_combined": [{"language": "cantonese", "language_level": ["proficiency"]}, {"language": "putonghua", "language_level": ["fluency", "proficiency"]}, {"language": "english", "language_level": ["fluency", "proficiency"]}]}, "experience_required": {"duration": [], "field": []}}, {"job_id": "100003009034816", "location_code": "hk", "company": "Moiselle (Hong Kong) Limited", "job_title": "Human Resources and Administration Manager", "description": "Responsibilities:\n\nGather and identify negative news / risk symptoms relating to particular corporate borrowers and other market information which may have risk implication to asset quality of the corporate lending portfolio\n\nMonitor corporate borrowers of elevating risk / overdue repayment and coordinate with frontline units and Risk Management Department to come with up appropriate risk mitigation strategies and proactively involve in the early recovery actions\n\nParticipate in devising and implementing thematic reviews on corporate borrowers in response to emergence of credit events / adverse changes in external economic / business environment\n\nConduct sample check on loan usage and irregularities in relation to corporate lending to ensure compliance with the Bank's relevant requirements and approved credit conditions.\n\nPrepare reports on concerned corporate borrowers and asset quality to the Senior Management, front line units and relevant departments\n\nLiaise with South-east Asian Branches to keep track with corporate borrowers exhibiting risk symptoms\n\nRequirements:\n\nDegree or above with major in Business Administration, Economics, Finance, Accounting, Law or related discipline; CFA, CPA, PRMIA-PRM, FRM or related qualification preferred\n\nAt least 3 years' working experience in corporate lending, credit risk management, credit approval / monitoring, portfolio analysis in the banking section\n\nSelf-initiated, good analytical and negotiation skills and able to perform multi-tasks within tight schedule\n\nGood command of both written and spoken English and Chinese. Proficient in Mandarin will be an added advantage\n\nProficient in computer applications (MS Word, Excel, PowerPoint, Bloomberg etc.)", "employment_types": ["Full Time"], "selling_points": ["Degree holder in Human Resources Management", "Minimum 5 years of working experience", "Retail industry"], "locations": ["Quarry Bay"], "categories": ["Admin & HR", "Compensation & Benefits", "HR Director / Manager"], "post_time": "2022-01-10T04:19:26Z", "salary": {"currency": null, "max": null, "min": null, "period": "monthly", "term": null}, "salary_visible": false, "title_keywords": ["administration manager", "human resources"], "responsibilities": ["management", "market information", "irregularities", "monitor", "quality", "coordinate with", "ensure compliance", "liaise with", "prepare reports", "senior management"], "requirements": {"degrees": ["degree or above"], "majors": ["business administration", "law", "finance", "economics", "accounting"], "languages": ["english", "chinese", "mandarin"], "language_level": ["advantage", "good command", "proficient"], "hard_skills": ["excel", "bloomberg", "cfa", "analysis", "powerpoint", "cpa", "frm", "ms word"], "soft_skills": ["negotiation skills", "multi-tasks"], "languages_combined": [{"language": "english", "language_level": ["good command"]}, {"language": "chinese", "language_level": ["good command"]}, {"language": "mandarin", "language_level": ["proficient", "advantage"]}]}, "experience_required": {"duration": ["at least 3 years"], "field": ["management", "credit risk", "banking"]}}, {"job_id": "100003009043265", "location_code": "hk", "company": "Conners Consulting Limited", "job_title": "Senior Human Resources Manager - Listed Securities Firm", "description": "Responsibilities:\nManage the daily operation of the RMB Clearing Business, which includes supervision of the team, monitoring of the systems\nIdentify, control, and report promptly to management various types of potential or existing risks, as well as other emergency matters as the case may be, and set up mitigating actions and monitor the process on adopting corrective measures\nFormulate and implement the yearly work plan\nPursue productivity-enhancement initiatives to reduce manual workload of operational activities, and improve RMB clearing efficiency and customers' satisfaction\nManage project plans for system enhancements in phases such as development of system requirements, User Acceptance Test (UAT), system implementation, and assess the effectiveness of projects\nCo-ordinate and organize the annual Disaster Drill (DD), review and prepare Business Continuity Plan (BCP)\nComplete ad-hoc tasks as assigned by superiors\nRequirements:\nDegree or above with major in Business Administration or related disciplines\nAt least 5 years experience in the Banking industry, experience in international payments operation would be a definite advantage\nStrong leadership, planning, project management, analytical, problem solving and decision making skills\nDemonstrate good organization, communication and negotiation skills\nFamiliar with the latest economic / financial market development of the Mainland of China\nGood command of both written and spoken English and Chinese, including Mandarin\nProficient in computer applications (e.g. Lotus Notes, MS Word, Excel, and\u00a0PowerPoint, etc.), and\u00a0Chinese word processing\nEvening shift duty\u00a0is\u00a0required", "employment_types": ["Full Time", "Permanent"], "selling_points": ["Securities / Equity", "HRBP", "Good prospect & Career development"], "locations": ["Not Specified"], "categories": ["Admin & HR", "HR Director / Manager"], "post_time": "2022-01-12T10:25:44Z", "salary": {"currency": null, "max": null, "min": null, "period": "monthly", "term": null}, "salary_visible": false, "title_keywords": ["manager", "human resources"], "responsibilities": ["business continuity", "control", "management", "uat", "ad-hoc tasks", "monitoring", "daily operation", "systems", "monitor", "implementation", "review", "plan", "plans", "report"], "requirements": {"degrees": ["degree or above"], "majors": ["related disciplines", "business administration"], "languages": ["english", "chinese", "mandarin"], "language_level": ["good command"], "hard_skills": ["excel", "chinese word processing", "powerpoint", "problem solving", "project management", "ms word"], "soft_skills": ["decision making skills", "problem solving", "project management", "communication", "negotiation skills", "leadership"], "languages_combined": [{"language": "english", "language_level": ["good command"]}, {"language": "chinese", "language_level": ["good command"]}, {"language": "mandarin", "language_level": ["good command"]}]}, "experience_required": {"duration": ["at least 5 years"], "field": ["banking industry", "operation"]}}, {"job_id": "100003009047674", "location_code": "hk", "company": "Forsters & Company", "job_title": "Senior Training Specialist", "description": "Responsibilities:\n\nServe a designated portfolio of accounts in the SME Banking business segment\nDevelop the portfolio by prospecting new clients and offering suitable corporate banking services to the existing customers\n\nRequirements:\n\nDegree holder or above with major in Business Administration, Finance or related disciplines\nAt least 2 years relevant experience in the SME Banking business segment\nGood knowledge of the corporate banking and treasury products and services\nFamiliar with the general banking operations and its legal and regulatory requirements\nPrevious exposure to the preparation of credit proposals\nSound interpersonal and communication skills\nGood command of both verbal and written English and Chinese\n\n(Applicants with more relevant experiences will be considered for the post of Senior Relationship Manager)", "employment_types": ["Full Time", "Permanent"], "selling_points": [], "locations": ["Not Specified"], "categories": ["Admin & HR", "HR Director / Manager", "HR Supporting Staff", "Training & Development"], "post_time": "2022-01-15T01:55:18Z", "salary": {"currency": null, "max": null, "min": null, "period": "monthly", "term": null}, "salary_visible": false, "title_keywords": ["specialist"], "responsibilities": ["sme", "develop", "banking"], "requirements": {"degrees": ["degree holder"], "majors": ["related disciplines", "finance", "business administration"], "languages": ["english", "chinese"], "language_level": ["good command"], "hard_skills": [], "soft_skills": ["communication skills", "interpersonal"], "languages_combined": [{"language": "english", "language_level": ["good command"]}, {"language": "chinese", "language_level": ["good command"]}]}, "experience_required": {"duration": ["at least 2 years"], "field": ["business", "relevant experience", "banking"]}}, {"job_id": "100003009043346", "location_code": "hk", "company": "Deloitte Touche Tohmatsu", "job_title": "Senior Recruiter / Assistant Manager (Experienced Hire) - Human Resources - Hong Kong", "description": "About the Business\nOur Human Resources professionals drive the firm\u2019s people strategy, create a unique people experience, and work with the business to drive success in the marketplace.\nJoin our Experienced Hire team to make an impact on developing and implementing a strategic resourcing plan in line with business strategies of each Function.\nWork you'll do\nWork closely with the hiring\u00a0managers / partners to develop and manage\u00a0strategic sourcing strategies\u00a0for the designated Line of Service\nSource candidates based on the respective function's needs and business strategies\nPropose suitable resourcing channels, screening applications, conduct\u00a0interviews and selection\u00a0assessments\nIdentify suitable candidates and manage the offer process effectively\nManage professional and effective relationships with internal clients, recruitment agencies and\u00a0other service providers\nPrepare recruitment related analyses\u00a0\nParticipate in talent acquisition\u00a0and branding projects\nAny other duties as assigned\n\n#LI-FL\n\nA fit for the role? Let's talk about you.\n\nWe are looking for someone with:\n\nBachelor degree holder or above in Human Resources, Psychology, business or other related disciplines\nMinimum 3 - 8 years of experience as a recruitment specialist, preferably in a service or multinational environment\nExcellent knowledge and skills in direct sourcing via social media and other channels\nFluency in English, Cantonese and Mandarin, both spoken and written are essential\nGood communication, negotiation and influencing skills with an ability to build strong client relationships\nClient focused with demonstrated resourcefulness, initiative\u00a0and flexibility\nA high level of discretion and confidentiality\nA team player with a \u201ccan do\u201d attitude\nAbility to handle pressure and manage conflicting demands", "employment_types": ["Full Time"], "selling_points": ["Talent Acquisition", "Experienced Hires", "Recruitment Specialist"], "locations": ["Tai Koo"], "categories": ["Admin & HR", "HR Director / Manager", "Recruitment / Executive Search"], "post_time": "2022-01-12T10:56:48Z", "salary": {"currency": null, "max": null, "min": null, "period": "monthly", "term": null}, "salary_visible": false, "title_keywords": ["assistant manager", "human resources"], "responsibilities": ["any other duties", "social media", "developing", "develop", "communication", "recruitment", "plan"], "requirements": {"degrees": ["bachelor degree holder"], "majors": ["related disciplines", "psychology", "business"], "languages": ["cantonese", "english", "mandarin"], "language_level": ["fluency"], "hard_skills": ["fl", "make"], "soft_skills": ["negotiation", "focused", "unique", "communication", "team player", "initiative"], "languages_combined": [{"language": "cantonese", "language_level": ["fluency"]}, {"language": "english", "language_level": ["fluency"]}, {"language": "mandarin", "language_level": ["fluency"]}]}, "experience_required": {"duration": ["minimum 3 - 8 years"], "field": ["business", "recruitment", "human resources"]}}, {"job_id": "100003009047035", "location_code": "hk", "company": "KOS International Limited", "job_title": "Director of Global Total Rewards", "description": "About the Client\n\nA well renowned organization with a global presence and a strong track record of success is now seeking for a dynamic individual to join them as the Director of Global Total Rewards.\n\nAbout the Role\n\nAct as a trusted advisor and expert to the CHRO in the development of a sustainable, relevant and innovative compensation and reward strategy in line with a growing business and one that drives the performance of the organization\nFurther direct the formulation and implementation of the reward and benefits programs globally that will attract, incentivize and retain high performing employees\nOversee all global benchmarking and strategic reviews of compensation in addition to leading (in partnership with HR Regional Leads) the Global Pay Review, ensuring that remuneration and performance related pay are in line with the budget and company objective\nEstablish and ensure the implementation of all compensation & benefit schemes ensuring there is complete compliance with relevant legislation and tax regulations globally\nDevelop and direct the formulation and implementation of global benefits policies i.e pension, healthcare, life assurance\nEnsure the implementation of a relevant Global International Mobility program (including realizing full package analysis for expatriate employees and tax sensitivity analysis) which will achieve the global mobility objectives and the appropriate budget objectives of the company\nDevelop new reward tools in line with an evolving Digital Strategy and implementation of Rewards on HRIS\nAdvise Senior Leaders and HR Team on all matters relating to Compensation and Benefits\nContinuous development and improvement of current reward practices globally\n\nThe Successful Applicant\n\nBachelor's holder in Human Resources Management or relevant discipline\nA minimum 18 years of working experience in the field of HR with an expertise in Compensation & Benefits on both local and regional level\nPrior experience within a consultancy environment is a definite advantage\nHands on experience in executing and delivering total reward strategy (Compensation, Benefits, International Assignment, Recognition and Reward Systems) is a MUST\nStrong user of contemporary HR system with the experience of implementation is preferred\nNumerically sensitive with strong business acumen\nResult oriented, ability to multitask and operate in an ever-changing environment\nOrganized, good communication skills with strong stakeholder management skills\nProficient in spoken and written English and Chinese\n\nClick \"Apply Now\" to apply for this position or call Xavier Tam at +852 3180 4920 for a confidential discussion. All information collected will be kept in strict confidence and will be used for recruitment purpose only.", "employment_types": ["Full Time", "Permanent"], "selling_points": ["Report to CHRO", "Full ownership of C&B function", "Competitive remuneration package"], "locations": ["Not Specified"], "categories": ["Admin & HR", "Compensation & Benefits", "HR Director / Manager"], "post_time": "2022-01-14T02:07:02Z", "salary": {"currency": null, "max": null, "min": null, "period": "monthly", "term": null}, "salary_visible": false, "title_keywords": ["director"], "responsibilities": ["tax", "regulations", "hr", "compliance", "review", "budget", "implementation", "relevant legislation"], "requirements": {"degrees": [], "majors": [], "languages": [], "language_level": [], "hard_skills": ["dynamic"], "soft_skills": ["dynamic", "innovative"], "languages_combined": []}, "experience_required": {"duration": [], "field": []}}, {"job_id": "100003009033380", "location_code": "hk", "company": "OliveX (HK) Limited", "job_title": "Head of HR", "description": "The Head of Human Resources is a newly created senior position that will work directly with the CEO and our management team. This role sits within the all-round HR function including recruitment, talent acquisition, talent retention, performance management, employee development, succession planning, HR policy making, HR operations and strategic planning. You will be responsible for the HR infrastructure across the OliveX Group with offices in Asia Pacific, Europe and North America.\n\nResponsibilities\n\nResponsible for building and leading the HR team to handle all round HR duties.\nOverseeing the recruitment process, on/off boarding, employee development, change management, HR reports and projects.\u00a0\nResponsible for HR strategy such as talent engagement, people planning, organizational development, operational excellence, etc.\nDeveloping corporate plans for a variety of HR matters such as compensation, benefits, health and safety etc.\nActing to support the human factor in the company by devising strategies for performance evaluation, staffing, training and development etc.\nLead and support various employee engagement activities, including but not limited to team building activities, awards amongst other staff engagement initiatives to drive company values.\nProviding advice to management on performance issue management; helping them strengthen their people leadership skills working to ensure robust and equitable outcomes.\nParticipate in ad-hoc HR projects as-needed.\n\n\u00a0Qualifications\n\nPersonal Competencies\n\nExperience working in an international environment\nCommercial mind-set; commercial acumen\nGravitas, confidence, maturity and capacity to influence (to align internal & external stakeholders)\nEnergy, ambition, self-initiative and drive\nHands on with the courage to make bold decisions, challenge status quo\nCommunication skills\nCollaborative, transparent and quality driven\nAbility to handle complexity and to navigate a results driven culture where the current business pace will increase\nForward thinking and able to advise (and not only to react / transact)\nA change agent (with a view on retention models, benefits & incentives, engagement & pride of belonging \u2026)\nIdeally from Asia or at least with 5+ in the region in a comparable role\nFluent in English; knowledge of Mandarin or Cantonese is a plus\nProfessional Competencies\n\nProven track record in HR with an ability to interact with senior leadership\nGenuine expertise in recruitment, retaining, talent management, reward & engagement\n8 to 10 years of experience in an international environment (not necessarily limited to financial services)", "employment_types": ["Full Time", "Permanent"], "selling_points": ["Fast growing FinTech Investment Company", "Career growth as CoE HR Business Partner", "Flexibility in work location, work from home"], "locations": ["Pok Fu Lam"], "categories": ["Admin & HR", "HR Director / Manager"], "post_time": "2022-01-09T12:33:08Z", "salary": {"currency": null, "max": null, "min": null, "period": "monthly", "term": null}, "salary_visible": false, "title_keywords": ["hr"], "responsibilities": ["management team", "management", "change management", "strategic planning", "operations", "hr", "infrastructure", "hr duties", "hr reports", "recruitment", "recruitment process", "planning"], "requirements": {"degrees": [], "majors": [], "languages": [], "language_level": [], "hard_skills": [], "soft_skills": ["organizational", "responsible"], "languages_combined": []}, "experience_required": {"duration": [], "field": []}}, {"job_id": "100003009043388", "location_code": "hk", "company": "Eco-Green Group Limited", "job_title": "Human Resources & Administration Manager/ Officer", "description": "*Candidate with more experience will be considered as\u00a0Manager.\n\n\n\u00a0Responsibilities:\u00a0\n\nPerform full spectrum of Human Resources functions;\nHandle payroll calculation, taxation, MPF administration and staff attendance record;\n\nResponsible for recruitment & selection, compensation & benefits administration, performance management and employee relations;\nResponsible for\u00a0review, development and implementation of\u00a0company policies/procedures pertaining to resources management;\nPerform ad hoc assignments and projects as assigned by management to support the\u00a0business goals.\n\nRequirements:\n\nHigher Diploma or above in Human Resources Management, Business Administration or relevant disciplines;\nMinimum 3 year of relevant working experience, preferably in Construction and Engineering industry;\nWell versed in HK employment Ordinances and related legislation;\nHighly\u00a0organized, trust-worthy and\u00a0independent;\nGood command of written and spoken\u00a0\u00a0English, Chinese & Mandarin;\nGood interpersonal, strong communication and negotiation skills;\nAble to work under pressure and result oriented;\nImmediate available is highly preferred.\n\nWe offer reasonable remuneration packages, include year-end bonus, annual leave, public holiday, 5.5 day\u00a0work /\u00a06 day\u00a0 (alternative leave),\u00a0as well as good career prospects for the right applicant. Interested parties, welcome to browse to our web site hk-egg.com, and send detail resume with expected salary & date availability by clicking \"Apply Now\"\u00a0\n\nPersonal data will be used for recruitment purpose only.", "employment_types": ["Full Time", "Permanent"], "selling_points": ["Human Resources", "Business Administration", "Construction"], "locations": ["Kowloon Bay"], "categories": ["Admin & HR", "Compensation & Benefits", "HR Director / Manager", "Recruitment / Executive Search"], "post_time": "2022-01-12T11:20:49Z", "salary": {"currency": null, "max": null, "min": null, "period": "monthly", "term": null}, "salary_visible": false, "title_keywords": ["administration manager", "officer", "human resources"], "responsibilities": ["taxation", "attendance", "mpf", "payroll", "human resources functions", "administration"], "requirements": {"degrees": [], "majors": [], "languages": [], "language_level": [], "hard_skills": [], "soft_skills": [], "languages_combined": []}, "experience_required": {"duration": [], "field": []}}, {"job_id": "100003009038012", "location_code": "hk", "company": "\u5bb6\u4ec1\u7259\u79d1\u4e2d\u5fc3\u6709\u9650\u516c\u53f8", "job_title": "Assistant HR & Administration Manager", "description": "Responsibilities\n\n\nResponsible for assisting in all-round HR & Administrative functions mainly in full cycle of recruitment process, compensation & benefits as well as monthly payroll processing, training & development, performance management and employee relationship;\nSupport Human Resources function, benefits administration; leave management\nMonitor and administer the office administration such as facility maintenance and repair management etc.;\nTo carry out in-depth analysis in a quality and timely manner, such as turnover rates, headcount summary, internal and external market trend, and make recommendations on talent acquisition and retention;\nSupervise administration staffs;\nAssist in ad hoc assignments\nRequirements:\u00a0\n\n\nDegree holder in Human Resources Management or equivalent;\nSolid experience in healthcare companies with 2 years in supervisory role is an advantage;\nFamiliar with HK Labour Ordinance and related employment legislation;\nSelf-motivated, energetic, able to work in fast pace environment, people-oriented with good communication and interpersonal skills to deal with all level of people;\nGood communication of spoken & written English, Mandarin will be an asset\n\nCandidates with lower qualification and experience will be considered for lower position.\u00a0 Interested parties, please send full resume, availability and expected salary to us.\n\n\n\n\n", "employment_types": ["Full Time"], "selling_points": [], "locations": ["Tsim Sha Tsui"], "categories": ["Admin & HR", "HR Director / Manager"], "post_time": "2022-01-11T04:34:22Z", "salary": {"currency": null, "max": null, "min": null, "period": "monthly", "term": null}, "salary_visible": false, "title_keywords": ["administration manager", "hr", "assistant"], "responsibilities": ["recruitment process", "hr", "payroll", "management"], "requirements": {"degrees": [], "majors": [], "languages": [], "language_level": [], "hard_skills": [], "soft_skills": [], "languages_combined": []}, "experience_required": {"duration": [], "field": []}}, {"job_id": "100003009038043", "location_code": "hk", "company": "\u8b7d\u6052\u4f01\u696d\u6709\u9650\u516c\u53f8", "job_title": "\u884c\u653f\u53ca\u4eba\u4e8b\u90e8\u7d93\u7406/\u52a9\u7406\u7d93\u7406", "description": "\u884c\u653f\u53ca\u4eba\u4e8b\u90e8\u7d93\u7406/\u52a9\u7406\u7d93\u7406\n\n\u5de5\u4f5c\u8077\u8cac\uff1a\n\n1. \u8ca0\u8cac\u884c\u653f\u524d\u53f0\u53ca\u5f8c\u52e4\u5de5\u4f5c\uff1a\u516c\u53f8\u8fa6\u516c\u7528\u54c1\u63a1\u8cfc\uff1b\u8eca\u8f1b\u6392\u7a0b\u53ca\u7ba1\u7406\uff1b\u516c\u53f8\u5404\u6d3b\u52d5\u7684\u7d44\u7e54\u3001\u7c4c\u5099\u53ca\u7ba1\u7406\u3002\n\n2. \u5354\u52a9\u65e5\u5e38\u4eba\u529b\u8cc7\u6e90\u5de5\u4f5c\uff0c\u5305\u62ec\u62db\u8058\u3001\u50f1\u50ad\u5408\u7d04\u3001\u54e1\u5de5\u85aa\u916c\u8a08\u7b97\u3001MPF\u53ca\u4fdd\u96aa\u3001\u54e1\u5de5\u798f\u5229\u53ca\u5047\u671f\u5354\u52a9\u5404\u9805\u4eba\u4e8b\u653f\u7b56\u3001\u85aa\u916c\u798f\u5229\u5236\u5ea6\u7684\u66f4\u65b0\u548c\u5b8c\u5584\u3002\n\n3. \u5354\u52a9\u5176\u4ed6\u884c\u653f\u53ca\u4eba\u4e8b\u90e8\u5de5\u4f5c, \u5305\u62ec\u5c0d\u5916\u4e8b\u52d9\u7684\u6e9d\u901a\u8207\u5354\u8abf\u3002\n\n4. \u57f7\u884c\u7ba1\u7406\u5c64\u4ea4\u8fa6\u7684\u5176\u4ed6\u5de5\u4f5c(\u5305\u62ec\u7533\u8acb\u5de5\u4f5c\u7c3d\u8b49\u7b49)\u3002\n\n\u4efb\u8077\u8981\u6c42\uff1a\n\n1. \u5c08\u4e0a\u6559\u80b2\u6216\u5b78\u58eb\u5b78\u4f4d(\u5546\u696d/\u884c\u653f\u7ba1\u7406/\u4eba\u529b\u8cc7\u6e90/\u793e\u6703\u79d1\u5b78) , \u719f\u6089\u4eba\u529b\u8cc7\u6e90\u76f8\u95dc\u6cd5\u4f8b\uff0c\u5982\u52de\u5de5\u6cd5\u4f8b\u3001\u50f1\u50ad\u689d\u4f8b\u3002\n\n2. \u5177\u67098\u5e74\u4ee5\u4e0a\u884c\u653f\u53ca\u4eba\u4e8b\u7684\u5de5\u4f5c\u7d93\u9a57, \u719f\u6089\u62db\u8058\u3001\u57f9\u8a13\u3001\u85aa\u916c\u7ba1\u7406\u7b49\u5404\u9805\u4eba\u529b\u8cc7\u6e90\u5de5\u4f5c\u8077\u80fd\u3002\n\n3. \u719f\u6089\u85aa\u916c\u798f\u5229(C&B) \u53ca HR\u8edf\u4ef6\u9032\u884c\u85aa\u916c\u652f\u4ed8\u512a\u5148\u8003\u616e\u3002\n\n4. \u6297\u58d3\u80fd\u529b\u53ca\u9069\u61c9\u529b\u5f37\uff0c\u8cac\u4efb\u5fc3\u5f37\uff0c\u5de5\u4f5c\u4e3b\u52d5\u7a4d\u6975\u3002\n\n5. \u601d\u7dad\u654f\u92b3, \u5de5\u4f5c\u6548\u7387\u9ad8, \u6709\u89e3\u6c7a\u554f\u984c\u80fd\u529b\u4e26\u64c5\u9577\u540c\u6642\u8ddf\u9032\u591a\u9805\u5de5\u4f5c\u3002\n\n6. \u5177\u5099\u826f\u597d\u7684\u6e9d\u901a\u80fd\u529b\u3001\u5354\u8abf\u80fd\u529b\u3001\u5718\u968a\u7ba1\u7406\u80fd\u529b\u3002\n\n7. \u826f\u597d\u7684\u4e2d\u82f1\u6587\u807d\u8aaa\u8b80\u5beb\u80fd\u529b\uff0c\u666e\u901a\u8a71\u6d41\u5229\u3002\n\n8. \u5fc5\u8981\u6642,\u4e0b\u73ed\u6216\u9031\u672b\u9700\u5354\u52a9\u5b89\u6392\u5de5\u4f5c\u3002\n\n\u5de5\u4f5c\u5730\u9ede: \u9999\u6e2f\u5cf6\u5357\u5340(\u8fd1\u5730\u9435\u7ad9)\n\n* \u8cc7\u683c\u548c\u7d93\u9a57\u8f03\u5c11\u7684\u7533\u8acb\u8005\u5c07\u88ab\u8003\u616e\u64d4\u4efb\u884c\u653f\u53ca\u4eba\u4e8b\u90e8\u52a9\u7406\u7d93\u7406\u7684\u8077\u4f4d\u3002", "employment_types": ["Full Time", "Permanent"], "selling_points": [], "locations": ["Southern Area"], "categories": ["Admin & HR", "Compensation & Benefits", "HR Director / Manager"], "post_time": "2022-01-11T04:43:48Z", "salary": {"currency": null, "max": null, "min": null, "period": "monthly", "term": null}, "salary_visible": false, "title_keywords": [], "responsibilities": [], "requirements": {"degrees": [], "majors": [], "languages": [], "language_level": [], "hard_skills": [], "soft_skills": [], "languages_combined": []}, "experience_required": {"duration": [], "field": []}}, {"job_id": "100003009039529", "location_code": "hk", "company": "Brown\u2019s", "job_title": "Assistant Human Resources Manager (AS-AHRM)", "description": "Responsibilities:\n\nPartnering with HR and hiring managers, develop a deep understanding of assigned positions and business groups. Identify required skills, experience, and competencies, as well as other in tangible job profile preferences.\nMaintain and recruit for an average requisition load of approximately 15 positions, from non-exempt to executive level\nDevelop and execute sourcing strategies to fill requisitions\nProactively build candidate pipelines and manage the candidate experience throughout the sourcing process for active and future requisitions.\nDevelop and implement effective, leading edge sourcing strategies. Leverage a range of sources, relevant to the job, such as universities, job boards, LinkedIn Recruiter, and other social media. Identify key diversity sourcing tools to ensure we are attracting a diverse pool of talent.\nProvide talent market insights, competitive intelligence, and talent demographics as appropriate to enable Talent Acquisition team, hiring managers, and executive leadership team to stay abreast of market conditions.\nPerform behavioral, competency and skill-based interviews to assess candidate qualifications against agreed upon position requirements and competencies.\nMeet established recruiting metrics and KPIs\n\nRequirements:\n\nBachelor\u2019s Degree required\n8+ years of talent acquisition, sourcing and recruiting experience Preferred Requirements:\nKnowledge of employment law, corporate recruitment processes, recruitment strategies are necessary.\nA combination of agency and corporate recruiting experience\nExperience recruiting at the executive level with diversity and military recruiting initiatives\nExperience with sourcing tools and technology Essential Knowledge and Skills:\nProven ability to build rapport, develop strategic working relationships and gain credibility quickly\nStrong analytical skills with passion for research, data, and creative approach to sourcing\nStrong written and verbal communication skills with demonstrated ability to present to senior leaders\nAbility to interact with and support all levels of management and staff\n\nA competitive remuneration package and career ladder will be offered to the right candidate. Interested parties please apply below with your resume for a private discussion. All information collected will be kept in strict confidentiality.\u00a0", "employment_types": ["Full Time", "Permanent"], "selling_points": ["Talent Acquisition", "8 years of relevant HR recruitment experience", "Develop and execute sourcing strategies"], "locations": ["Not Specified"], "categories": ["Admin & HR", "Others", "HR Director / Manager", "Recruitment / Executive Search"], "post_time": "2022-01-11T10:00:51Z", "salary": {"currency": null, "max": null, "min": null, "period": "monthly", "term": null}, "salary_visible": false, "title_keywords": ["assistant human resources manager"], "responsibilities": ["social media", "hr", "develop", "maintain", "kpis"], "requirements": {"degrees": ["degree", "bachelor"], "majors": [], "languages": [], "language_level": [], "hard_skills": ["ladder", "analytical skills"], "soft_skills": ["communication skills", "passion for", "creative", "analytical skills"], "languages_combined": []}, "experience_required": {"duration": ["8+ years"], "field": ["agency"]}}, {"job_id": "100003009038755", "location_code": "hk", "company": "Wellesley Associates Limited", "job_title": "HR Manager - IT Services Company / MNC / 40K+", "description": "Responsibilities\n\nOversees full spectrum of day-to-day regional HR operations, including\u00a0manpower planning, recruitment and selection, C&B, employee relations, staff retention and performance management\nImplementation and maintenance of HRIS\nLeading staff relations event and program\nSupport internal HR systems and in-house HR projects\nRegional insurance management\nReview and update the company HR policy and procedures to ensure compliance with Labour Ordinance\nProvide HR strategies and recommendations\nLead and coach the HR team with guidance\nParticipate in any other ad-hoc duties as required\n\nQualifications\n\nDegree in Human Resources Management or equivalent\nMinimum 8 years of relevant HR experience\nPositive attitude, proactive, fast paced and a good team player\nProficient in MS Office applications, knowledge in HRIS systems is a plus\nFluent in English and Chinese\n\n\u00a0If you would like to apply for this role or find out more, please apply online with your\u00a0latest CV in word format and expected salary,\u00a0quoting the job role. Kindly note that only shortlisted candidates will be notified", "employment_types": ["Full Time", "Permanent"], "selling_points": ["HR Manager - IT Services Company / MNC / 40K+", "attractive remuneration package", "Minimum 8 years experience"], "locations": ["Not Specified"], "categories": ["Admin & HR", "HR Director / Manager", "HR Supporting Staff"], "post_time": "2022-01-11T07:44:55Z", "salary": {"currency": null, "max": null, "min": null, "period": "monthly", "term": null}, "salary_visible": false, "title_keywords": ["hr manager"], "responsibilities": ["guidance", "management", "maintenance", "operations", "hr", "systems", "review", "implementation", "procedures", "ensure compliance", "recruitment", "ad-hoc duties", "insurance", "planning"], "requirements": {"degrees": ["degree"], "majors": [], "languages": ["english", "chinese"], "language_level": ["fluent"], "hard_skills": ["plus", "word", "maintenance", "ms office"], "soft_skills": ["positive attitude", "good team player", "proactive", "ad-hoc duties"], "languages_combined": [{"language": "english", "language_level": ["fluent"]}, {"language": "chinese", "language_level": ["fluent"]}]}, "experience_required": {"duration": ["minimum 8 years"], "field": ["hr"]}}, {"job_id": "100003009038213", "location_code": "hk", "company": "Top Express Infrastructure Limited", "job_title": "Assistant Human Resources Manager", "description": "The Company is seeking a high caliber candidate to provide support to the organization.\n\nJob duties:\n\nHandle end-to-end recruitment process and follow up all on-boarding/ off-boarding procedures including conduct induction program and exit interview;\nleave & attendance management, personal data maintenance in HRIS, MPF and benefit administrations;\nPlan, develop, implement and review HR policies and procedures to support the Company\u2019s needs & cope with the overall business strategies;\nHandle company insurance renewal and labour disputes;\nAd hoc project as assigned\n\nRequirements:\n\n5 passed subjects in HKCEE (including Chinese, English-Syllabus B & Mathematics) or equivalent,\u00a0 Diploma holder in Human Resources Management or related disciplines is preferrably;\nMinimum 3 years working experience in Human Resources field;\nProficient in MS Word, Excel and Chinese Word Processing;\nGood command of both spoken and written English and Chinese;\nStrong analytical skills and interpersonal skills;\nDetail-minded, well-organized and able to handle multi-tasks;\nIndependent, proactive with positive attitude, responsible;\nImmediate available is highly preferred\n\nWe offer attractive remuneration, performance bonus, medical b subsidy and other fringe benefits to the right candidate.\n\nInterest parties please send your full resume with date of availability, present and expected salary by clicking \u201cApply Now\u201d.\n\nPersonal data collected will be used for recruitment purposes only.", "employment_types": ["Permanent"], "selling_points": ["Min. 3 years related working experience", "All round HR functions", "Medical Subsidy"], "locations": ["Tsing Yi"], "categories": ["Admin & HR", "HR Director / Manager"], "post_time": "2022-01-11T06:09:29Z", "salary": {"currency": null, "max": null, "min": null, "period": "monthly", "term": null}, "salary_visible": false, "title_keywords": ["assistant human resources manager"], "responsibilities": ["attendance", "management", "ad hoc", "mpf", "maintenance", "policies", "hr", "review", "procedures", "develop", "plan", "recruitment process", "personal data", "insurance"], "requirements": {"degrees": ["diploma holder"], "majors": ["related disciplines", "mathematics"], "languages": ["english", "chinese"], "language_level": ["good command", "proficient"], "hard_skills": ["excel", "chinese word processing", "analytical skills", "ms word"], "soft_skills": ["detail-minded", "independent", "multi-tasks", "responsible", "well-organized", "analytical skills", "positive attitude", "interpersonal skills", "proactive"], "languages_combined": [{"language": "english", "language_level": ["good command"]}, {"language": "chinese", "language_level": ["good command", "proficient"]}]}, "experience_required": {"duration": ["minimum 3 years"], "field": ["human resources"]}}, {"job_id": "100003009032518", "location_code": "hk", "company": "The Great Eagle Group of Companies", "job_title": "Assistant Human Resources Manager", "description": "Responsibilities:\n\nAssist in managing the operation of compensation & benefits functions including but not limited to monthly payroll, HR audit, tax filing, benefits enrolment and termination, and leave administrations\nAssist in annual review exercise and C&B projects including but not limited to salary review, review and renew medical benefits and insurance plans\nAssist to formulate, review and implement policies and procedures\nLiaise with insurance agent on various employee compensation issues\nOrganize company events and staff activities\nMonitor and supervise the team to complete the tasks\nHandle ad hoc assignments and duties as required\n\nRequirements:\n\nDegree holder or above in Human Resources Management or related disciplines\n5 \u2013 8 years\u2019 experience in human resources in which at least 3 years in supervisory level, preferably gained in sizeable companies or diversified organizations\nExperience gained in property developer will be advantage\nWell-versed in Hong Kong Employment Ordinance and other employment-related ordinances\nWell-organized, result-oriented and able to handle multi tasks simultaneously\nSelf-motivated and able to work under pressure and tight schedule\nPleasant personality with strong communication and interpersonal skills\nProficient in MS Office applications and Chinese word processing\nExperience in using Oracle and IPL will be advantage\nGood command of both written and spoken English and Chinese\n\nSalary and benefits will be commensurate with qualifications and experience.\u00a0 Interested parties, please send a full resume with present and expected salary, and date available to The Human Resources Department, 32/F., Great Eagle Centre, 23 Harbour Road, Wanchai, Hong Kong or e-mail to us.\u00a0\u00a0(Please quote the reference no. on the envelope and the covering letter.)\n\nTo know more about us, please visit our website at http://www.greateagle.com.hk.\n\nWe are an equal opportunity employer and welcome applications from all qualified candidates.\n\nPersonal data collected will be treated in strict confidence and used only for recruitment-related purpose. Applicants who have not heard from us within four weeks may consider their applications unsuccessful. All personal data will be destroyed after 12 months.", "employment_types": ["Full Time", "Permanent"], "selling_points": ["Compensation & benefits functions", "Employee compensation issues", "Payroll, Insurance plans"], "locations": ["Wan Chai"], "categories": ["Admin & HR", "Others", "Compensation & Benefits", "HR Director / Manager"], "post_time": "2022-01-10T03:41:13Z", "salary": {"currency": null, "max": null, "min": null, "period": "monthly", "term": null}, "salary_visible": false, "title_keywords": ["assistant human resources manager"], "responsibilities": ["tax filing", "hr", "payroll", "audit"], "requirements": {"degrees": [], "majors": [], "languages": [], "language_level": [], "hard_skills": [], "soft_skills": [], "languages_combined": []}, "experience_required": {"duration": [], "field": []}}, {"job_id": "100003009033727", "location_code": "hk", "company": "Bank of Communications Co., Ltd. Hong Kong Branch", "job_title": "Manager, Compensation and Benefits", "description": "Duties:\n\nDevelop a solid understanding of the business and team environment\nConduct analysis to provide insight for management decision\nActively develop strategies for talent development and management\nHeavily lead staff engagement initiatives\nCreate and execute action plans to deliver address and facilitate initiatives\n\nRequirements:\nBachelor degree holder in Business, HR or related discipline\nMinimum 3 years but maximum of 7 years of HRBP/ Generalist experience\nProficient in Microsoft Office\nGood command of English, Cantonese, and Mandarin required\n\n\nWhat you need to do now\nIf you're interested in this role, click 'apply now' to forward an up-to-date copy of your CV, or call us now.", "employment_types": ["Full Time", "Permanent"], "selling_points": [], "locations": ["Not Specified"], "categories": ["Admin & HR", "Others", "Compensation & Benefits", "HR Director / Manager"], "post_time": "2022-01-10T01:41:37Z", "salary": {"currency": null, "max": null, "min": null, "period": "monthly", "term": null}, "salary_visible": false, "title_keywords": ["manager"], "responsibilities": ["management", "develop strategies", "analysis", "develop", "plans"], "requirements": {"degrees": ["bachelor degree holder"], "majors": ["business"], "languages": ["cantonese", "english", "mandarin"], "language_level": ["good command"], "hard_skills": ["microsoft office"], "soft_skills": ["interested in"], "languages_combined": [{"language": "cantonese", "language_level": ["good command"]}, {"language": "english", "language_level": ["good command"]}, {"language": "mandarin", "language_level": ["good command"]}]}, "experience_required": {"duration": ["of 7 years", "minimum 3 years"], "field": []}}, {"job_id": "100003009035607", "location_code": "hk", "company": "Hays", "job_title": "HR Business Partner (High Potential | FMCG)", "description": "Job Responsibilities:\n\nConduct analysis and provide insights based on internal and external data to identify opportunities to enhance program competitiveness\nCreate appropriate tools (e.g. job catalogue) to support the implementation of new programs and processes\nDevelop communications and training materials for People Business Partners, Line Managers and Employees to facilitate program execution\nEnsure quality of market benchmark by conducting job evaluations, reviewing job matching and participating in market surveys\nParticipate in any ad hoc projects as required\n\n\n\nJob Requirements:\n\nUniversity graduate with experiences in rewards projects from multinational or complex organizations (background from consulting or corporations with frontline operations will be an asset)\nKnowledge in job evaluation methodologies and job grading design\nIndependent self-starter yet a good team player with a positive and proactive attitude\nSuperior analytical ability that includes strong MS Excel skills, capable to develop result-/purpose-driven analysis independently\nEffective communication skills with all levels\nWorking location at Kowloon Bay\nFlexible work schedule (e.g. part-time) can also be considered for candidates with more experiences\n\nWe offer attractive remuneration and fringe benefits. Interested parties please send your full resume with current salary and expected salary to\u00a0Human Resources Department, Quality HealthCare Medical Services Limited, 3/F, Skyline Tower, 39 Wang Kwong Road, Kowloon Bay, Kowloon\u00a0or by clicking \"Apply Now\".\n\n(All applications will be treated in strict confidence and data collected will be used for recruitment purposes only)", "employment_types": ["Full Time", "Permanent"], "selling_points": ["Max of 7 years of work experience", "Exciting Opportunity", "Business Partnering Role"], "locations": ["Not Specified"], "categories": ["Admin & HR", "Others", "HR Director / Manager", "HR Supporting Staff"], "post_time": "2022-01-10T07:51:17Z", "salary": {"currency": "HKD", "max": 54999, "min": 45000, "period": "monthly", "term": null}, "salary_visible": true, "title_keywords": ["hr"], "responsibilities": ["provide insights", "data", "analysis", "quality", "implementation", "develop", "ad hoc projects", "catalogue"], "requirements": {"degrees": ["university graduate"], "majors": [], "languages": [], "language_level": [], "hard_skills": ["ms excel", "analysis"], "soft_skills": ["flexible", "communication skills", "good team player", "independently", "independent", "capable", "proactive", "driven", "positive", "superior"], "languages_combined": []}, "experience_required": {"duration": [], "field": ["consulting"]}}, {"job_id": "100003009043222", "location_code": "hk", "company": "Quality HealthCare Medical Services Ltd", "job_title": "Assistant Manager/ Manager, Rewards (Projects)", "description": "Responsibilities:\n\n\nBeing the Head of Human Resources, and report to the Chairman.\nFormulating HR strategies and initiatives to support the achievements of the business and operations objectives.\nOverseeing and lead the HR team, responsible for all HR services including recruitment, compensation & benefits, employee relations, training, performance management, annual salary review exercise, budgeting, agency management, BCP and HR system.\nReviewing and revamped the HR policies, procedures and systems (HR system and intranet) regularly to ensure adding values to the Company.\nManaging the performance management system, and providing strategic support on the retention and manpower planning.\nBuild the corporate culture and cohesive work force via various means of staff relations programs.\nWorking as a business partner to the line management, working together to establish different reward and bonus scheme for different business units.\nHandle ad hoc projects as assigned.\n\nRequirements:\n\n\n\nDegree holder in Human Resources Management or other related disciplines;\nMinimum 8 years'\u00a0relevant experiences with at least 3 years in managerial level;\nIndependent, proactive, self-driven and highly motivated individual;\nExcellent communication and interpersonal skills;\nCheerful and pleasant;\nGood command of spoken and written English and Chinese, with proficiency in Mandarin a plus;\nCandidate with more experience can be considered as Senior Manager.\n\nSalary and fringe benefits for the post will be highly competitive, commensurate with qualifications and experience. Interested candidates please send your resume, last and expected salary to the Human Resources and Administration by clicking \"Apply Now\".\n\nData collected will be used for recruitment purpose only.\u00a0For more details, please visit us at\u00a0www.ffg.com.hk.", "employment_types": ["Full Time", "Part Time", "Permanent"], "selling_points": ["Rewards Project", "Degree holder with relevant experience", "Effective communication skills with all levels"], "locations": ["Kowloon Bay"], "categories": ["Admin & HR", "HR Director / Manager"], "post_time": "2022-01-12T10:17:02Z", "salary": {"currency": null, "max": null, "min": null, "period": "monthly", "term": null}, "salary_visible": false, "title_keywords": ["assistant manager", "manager"], "responsibilities": ["management", "operations", "hr", "review", "budgeting", "policies", "procedures", "systems", "planning", "recruitment", "ad hoc projects", "report"], "requirements": {"degrees": ["degree holder"], "majors": ["related disciplines"], "languages": ["english", "chinese", "mandarin"], "language_level": ["proficiency", "good command"], "hard_skills": ["plus"], "soft_skills": ["cheerful", "independent", "pleasant", "motivated individual", "communication and interpersonal skills", "proactive", "driven"], "languages_combined": [{"language": "english", "language_level": ["proficiency", "good command"]}, {"language": "chinese", "language_level": ["proficiency", "good command"]}, {"language": "mandarin", "language_level": ["proficiency", "good command"]}]}, "experience_required": {"duration": ["at least 3 years", "minimum 8 years"], "field": ["managerial"]}}, {"job_id": "100003009029397", "location_code": "hk", "company": "Fulbright Securities Limited", "job_title": "Manager - Human Resources", "description": "Key Responsibilities:\nLead the C&B and HR service team to design and execute a progressive and efficient HR services framework including payroll centre, HR operation support, benefits administration, on boarding & off boarding and record management\nResponsible for providing centralized process support across disciplines including compensation, benefits, training and development, talent acquisition, employee branding, engagement, and administration\nDevelop and maintain appropriate HR policies, standards, guidelines, and procedures\nLead the designs & deliveries of cultural building initiatives, awards/staff recognition programs, staff caring programs and activities to enhance employee engagement\nHandle grievances and disciplinary cases in accordance with Company\u2019s policies and procedures\nManage annual exercise including budget and performance management cycle to ensure organizational alignment\nRegularly perform audit checks on process to anticipate risks and sensitivity, build consensus, address stakeholders\u2019 needs, and resolve conflicts in the workplace\nKey Requirements:\nUniversity degree holder or equivalent, major in human resources management is an advantage\nMinimum 10 years of experience in human resources profession preferably in multinational corporations, of which 5 years in managerial role\nFully conversant in Hong Kong employment-related ordinances and rules & regulations\nIn-depth understanding of all-round HR functions\nStrong leadership and interpersonal skills to engage and influence stakeholders\nEffective planning and project management skills\nCustomer-oriented with demonstrated drive and resilience\nTactful and diplomatic in handling employee communication\nExperience in application of Human Resources Management Systems\nGood command of Microsoft Office including Word, Excel, PowerPoint, and Outlook\nFluency in both spoken and written Chinese and English\nInterested parties please send your detailed resume stating your available date, current & expected salary to Human Resources Manager, by clicking the \u201cAPPLY NOW\u201d button below.\n\n\n\nAll information provided by applicants will be treated in strict confidence and used only for recruitment purposes. If you do not provide the information mentioned in the advertisement, we may not be able to assess your job application. You have the right to request access to, and correction of, your personal data held by us and you may lodge such request with our Data Protection Officer at pdpo@ vitasoy.com, but any such data access request will only be processed after the completion of the recruitment process.", "employment_types": ["Full Time", "Permanent"], "selling_points": [], "locations": ["Kowloon Bay"], "categories": ["Admin & HR", "Compensation & Benefits", "HR Director / Manager", "Recruitment / Executive Search"], "post_time": "2022-01-07T05:01:03Z", "salary": {"currency": null, "max": null, "min": null, "period": "monthly", "term": null}, "salary_visible": false, "title_keywords": ["manager", "human resources"], "responsibilities": ["management", "guidelines", "policies", "hr", "budget", "procedures", "audit", "design", "develop", "maintain", "payroll", "administration"], "requirements": {"degrees": ["university degree"], "majors": [], "languages": ["english", "chinese"], "language_level": ["fluency"], "hard_skills": ["excel", "microsoft office", "word", "powerpoint", "project management", "outlook"], "soft_skills": ["project management skills", "diplomatic", "communication", "customer-oriented", "interpersonal skills", "tactful", "leadership"], "languages_combined": [{"language": "english", "language_level": ["fluency"]}, {"language": "chinese", "language_level": ["fluency"]}]}, "experience_required": {"duration": ["5 years", "minimum 10 years"], "field": ["managerial", "management", "human resources"]}}, {"job_id": "100003009035570", "location_code": "hk", "company": "Vitasoy International Holdings Ltd", "job_title": "Manager, Total Awards & Services", "description": "Our client is a MNC.\n\nThey are now looking for Junior Training officer meet the growth of our business in Hong Kong.\n\nWe are now seeking for a JUNIOR TRAINING OFFICER\n\n\n\nRESPONSIBILITIES\n\nResponsible for the learning and professional development of an organisation's workforce\nEquip staff with the knowledge, practical skills and motivation to carry out the work activities effectively\nDesign, deliver and assess training programmes\nPrepare training materials\nProvide administrative support to the training department\n\nQUALIFICATIONS\n\nEducation in Human Resource, Business Admin or related disciplines\n2 years working experience or above\nFamiliar with HR Training cycle\nProficient in MS & GSuite applications\n\nAPPLY FOR THIS JOB\n\nInterested candidate, please CLICK apply button to apply online or send your resume in MS word format to Hillman Ross Recruitment Solution Professional\n\nPlease note that only shortlisted candidate will be notified. All information will be treated in strict confidence and solely used for recruitment purposes.", "employment_types": ["Full Time", "Permanent"], "selling_points": ["5 days work, Company shuttle", "Lead the C&B and HR service team", "Responsible for providing centralized support"], "locations": ["Tuen Mun Area"], "categories": ["Admin & HR", "Administration / Operation Manager", "Compensation & Benefits", "HR Director / Manager"], "post_time": "2022-01-10T07:42:21Z", "salary": {"currency": null, "max": null, "min": null, "period": "monthly", "term": null}, "salary_visible": false, "title_keywords": ["manager"], "responsibilities": ["provide administrative support", "hr", "recruitment", "design"], "requirements": {"degrees": [], "majors": [], "languages": [], "language_level": [], "hard_skills": ["ms word"], "soft_skills": ["confidence", "learning", "organisation", "responsible"], "languages_combined": []}, "experience_required": {"duration": ["2 years"], "field": []}}, {"job_id": "100003009044140", "location_code": "hk", "company": "Hillman Ross", "job_title": "Junior Training Officer (up to 25K)", "description": "\u00a0Responsibilities and Duties\u00a0\n\nManage full scope of HR responsibilities including HR system maintenance, attendance record, payroll, MPF, Compensation & Benefits, leaves, staff orientation, training and employee relations\nPrepare ongoing HR reports and workforce analysis\nManage full cycle of recruitment and selection including sourcing, scheduling, applicants screening, conducting interviews and preparing offers\nAssist in the annual exercise, including performance appraisal, company insurance, bonus, taxation, pay update, MPF ...etc.\nWork closely with the Management Team to promote and lead on employee engagement activities\nProvide coaching and development support\nManage and supervise office administration\nSupport and assist the CEO as needed\n\n\u00a0Qualifications and Experience\n\nHigher Diploma / Degree holder in Human Resources Management / Business Administration or related discipline\n3 years or more\u00a0hands-on\u00a0experience, preferably in Telecommunication or Information Technology\nWell-versed in Hong Kong employment ordinance, employees\u2019 compensation and other related legislation\nPeople-oriented mindset and approach\nStrong sense of responsibility, well organized, analytical, fast-learner, self-starter, flexible and cheerful\nGood team player with strong interpersonal and communication skills\nGood command of both written and spoken English, Cantonese and Mandarin\nProficient in Microsoft Office applications and Chinese word processing\nMainland HR Experience and knowledge will be an advantage", "employment_types": ["Full Time", "Permanent"], "selling_points": ["5 working days", "double bonus", "Medical Cover"], "locations": ["Not Specified"], "categories": ["Admin & HR", "HR Director / Manager", "HR Supporting Staff", "Training & Development"], "post_time": "2022-01-13T03:11:50Z", "salary": {"currency": null, "max": null, "min": null, "period": "monthly", "term": null}, "salary_visible": false, "title_keywords": ["officer", "junior"], "responsibilities": ["attendance", "taxation", "management team", "management", "mpf", "maintenance", "office administration", "hr", "analysis", "hr reports", "communication", "scheduling", "conducting interviews", "recruitment", "insurance", "payroll", "administration"], "requirements": {"degrees": ["diploma", "degree holder"], "majors": ["business administration"], "languages": ["cantonese", "english", "chinese", "mandarin"], "language_level": ["good command", "proficient"], "hard_skills": ["chinese word processing", "hong kong employment ordinance", "maintenance", "microsoft office", "analysis"], "soft_skills": ["flexible", "communication skills", "good team player", "cheerful", "sense of responsibility", "well organized", "hands-on", "people-oriented", "interpersonal"], "languages_combined": [{"language": "cantonese", "language_level": ["good command"]}, {"language": "english", "language_level": ["good command"]}, {"language": "chinese", "language_level": ["proficient"]}, {"language": "mandarin", "language_level": ["good command"]}]}, "experience_required": {"duration": ["3 years"], "field": ["hr", "information technology"]}}, {"job_id": "100003009036539", "location_code": "hk", "company": "John Swire & Sons (HK) Limited", "job_title": "Manager, Compensation and Benefits", "description": "Headquartered in Central, our client is a financial group with over 20 years of operations in HK.\n\nResponsibilities:\n\nLead the team of HR\nManager and supervise all HR services including recruitment, compensation & benefits, employee relations, training, performance management, annual salary review & budgeting, etc.\nFormulate HR strategies, review and revamp HR policies & procedures and HR system regularly\nAct as a Business Partner and work with line managers for HR programs such as bonus scheme, manpower planning and performance appraisal\nHandle ad-hoc projects as assigned\u00a0\n\nRequirements:\n\nBachelor Degree in Human Resources Management or other related disciplines\nMinimum 8 years' relevant experiences with at least 3 years in managerial level, preferably in financial industry\nIndependent, proactive, self-driven, with friendly and pleasant character\nExcellent communication and interpersonal skills\nGood command of spoken and written English and Chinese, proficiency in Mandarin is preferred\nCandidate with more experience can be considered as Senior Manager", "employment_types": ["Full Time"], "selling_points": ["Compensation & Benefits", "10 years' relevant experience", "Job evaluation & HRIS systems"], "locations": ["Quarry Bay"], "categories": ["Admin & HR", "Compensation & Benefits", "HR Director / Manager"], "post_time": "2022-01-10T10:58:58Z", "salary": {"currency": null, "max": null, "min": null, "period": null, "term": null}, "salary_visible": false, "title_keywords": ["manager"], "responsibilities": ["management", "revamp", "budgeting", "hr", "review", "policies", "procedures", "recruitment", "ad-hoc projects", "planning"], "requirements": {"degrees": ["degree", "bachelor"], "majors": ["related disciplines"], "languages": ["english", "chinese", "mandarin"], "language_level": ["proficiency", "good command"], "hard_skills": [], "soft_skills": ["independent", "pleasant", "communication and interpersonal skills", "friendly", "proactive", "driven"], "languages_combined": [{"language": "english", "language_level": ["proficiency", "good command"]}, {"language": "chinese", "language_level": ["proficiency", "good command"]}, {"language": "mandarin", "language_level": ["proficiency", "good command"]}]}, "experience_required": {"duration": ["at least 3 years", "minimum 8 years"], "field": ["managerial", "financial industry"]}}, {"job_id": "100003009030443", "location_code": "hk", "company": "Target Search Limited", "job_title": "Manager - Human Resources", "description": "Our client is a well-established conglomerate, with group office in Hong Kong and a strong international presence. They have offices across the globe, multiple locations in America, Asia, and Europe. They provide quality products with a strong reputation, and have excellent business performance in recent years. They are currently looking for a Regional HRBP for the Hong Kong office.\n\nClient Details\n\nOur client is a top tier, reputable, and well-established conglomerate, with group office in Hong Kong and a strong international presence. They have offices across the globe, multiple locations in America, Asia, and Europe. They provide quality products with a strong reputation, and have excellent business performance in recent years. They are currently looking for a Regional HRBP for the Hong Kong office.\n\nCompany Culture:\n\nInternational team, lean structure\nYoung and energetic\nNice and friendly working environment\nFlexible work arrangement\nEncourage internal mobility\n\nDescription\n\nManage end to end recruitment cycle, including understanding hiring needs, candidate screening, interview, offer management and etc.\nActively manage relationships with external recruitment firms to ensure turnaround time and delivery of qualified candidates\nAct as the representative of the firm and create a positive candidate experience for both the selected and non-selected candidates throughout the entire recruiting process\nCollaborate on TA related and Employer Branding projects and share best practices with the wider TA team\nSupport the Head of Talent Acquisition to develop and implement recruitment strategies\nAssist in ad hoc support\n\nProfile\n\nBachelor's degree in relevant disciplines\nAt least 8 years' experience in human resources functions from multinational company background\nCapable in executing HR projects, and implementing various programs through regular communication with group HR team\nFlexible, Detail-minded, good team player, well-organized with good interpersonal skills\nFluent English and Chinese, both written and spoken\nStrong computer skills, using MS Office\n\nJob Offer\n\nPermanent opportunity\n5 days' work\nWork from home policy in place\nGreat Discretionary Bonus\nComprehensive medical coverage for staff and dependant\nDental insurance\nAnnual Body Check Up\nExciting Project Exposure\nWork life balance\nMNC Working environment\nRegional Exposure", "employment_types": ["Full Time", "Permanent"], "selling_points": ["Oversee the HR team", "Min. 8 years' experience", "Stable working environment"], "locations": ["Kowloon Bay"], "categories": ["Admin & HR", "HR Director / Manager"], "post_time": "2022-01-07T07:56:58Z", "salary": {"currency": null, "max": null, "min": null, "period": "monthly", "term": null}, "salary_visible": false, "title_keywords": ["manager", "human resources"], "responsibilities": ["collaborate", "management", "ad hoc", "hr", "quality", "develop", "communication", "recruitment", "executing", "insurance", "human resources functions"], "requirements": {"degrees": ["degree", "bachelor"], "majors": [], "languages": ["english", "chinese"], "language_level": ["fluent"], "hard_skills": ["lean", "computer skills", "nice", "ms office"], "soft_skills": ["flexible", "detail-minded", "good team player", "capable", "well-organized", "communication", "comprehensive", "friendly", "interpersonal skills", "energetic", "mobility", "positive"], "languages_combined": [{"language": "english", "language_level": ["fluent"]}, {"language": "chinese", "language_level": ["fluent"]}]}, "experience_required": {"duration": ["at least 8 years"], "field": ["multinational company", "human resources"]}}, {"job_id": "100003009038814", "location_code": "hk", "company": "Michael Page", "job_title": "Talent Acquisition Lead", "description": "Responsibilities:\n\nHandle full spectrum of HR functions including recruitment, coaching, C&B and performance management, bonus scheme review etc\nAnalyze, identify and develop effective HR strategies, policies and operation systems to support the business needs in achieving corporate goals and visions\nProvide quality support service and foster the high motivation environment in the Company\nKeep abreast of local legislation\u2019s update and ensure HR policies and practices are compliance to local legislation's supporting to the business objectives and competitive in the market\nImplement the employee retention strategy and develop the talent workforce\nLead and participate other ad-hoc assignments to support the Company\u2019s business goals\n\nRequirements:\n\nBachelor degree in Human Resources Management or Business Administration or related disciplines\n10 years or above solid HR generalist with at least 3 years at managerial level\nExperienced in construction / retail / property development is highly preferred\nExperienced in sizable or listed Company is a must\nAble to build trust-worthy relationship with strong communication and people management skills\nPositive, detail-minded, well-organized and flexible\nStrong analytical skills, multi-tasking, meticulous, organized and able to meet tight deadlines\nStrong computer skills and proficiency in spoken and written Chinese, English and Mandarin\nImmediate available is highly preferred\nCandidate with less experience will be considered as Assistant Human Resources Manager\n\nWe offer competitive remuneration package, our benefits include:\n\nPerformance bonus\nEducation subsidy\nProfessional membership fee sponsorship\nLife & medical insurance\nMarriage Leave, Compassionate Leave, Examination Leave etc.\nPublic holidays\nStaff purchase discount\n(Information provided will be treated in strict confidence and will only be used for recruitment-related purposes.)", "employment_types": ["Full Time", "Permanent"], "selling_points": ["Top Tier Conglomerate", "Flexi Work Arrangement", "Friendly and team-based culture"], "locations": ["Quarry Bay"], "categories": ["Admin & HR", "Others", "HR Director / Manager", "Recruitment / Executive Search"], "post_time": "2022-01-11T07:52:28Z", "salary": {"currency": null, "max": null, "min": null, "period": "monthly", "term": null}, "salary_visible": false, "title_keywords": ["lead"], "responsibilities": ["management", "business goals", "policies", "hr", "review", "systems", "quality", "compliance", "develop", "ad-hoc assignments", "recruitment"], "requirements": {"degrees": ["degree", "bachelor"], "majors": ["related disciplines", "business administration"], "languages": ["english", "chinese", "mandarin"], "language_level": ["proficiency"], "hard_skills": ["computer skills", "analytical skills"], "soft_skills": ["detail-minded", "flexible", "meticulous", "organized", "meet tight deadlines", "well-organized", "analytical skills", "communication", "multi-tasking", "positive"], "languages_combined": [{"language": "english", "language_level": ["proficiency"]}, {"language": "chinese", "language_level": ["proficiency"]}, {"language": "mandarin", "language_level": ["proficiency"]}]}, "experience_required": {"duration": [], "field": ["human resources"]}}, {"job_id": "100003009035534", "location_code": "hk", "company": "Hong Kong Repertory Theatre Limited", "job_title": "\u4eba\u4e8b\u4e3b\u4efb Personnel Officer", "description": "Main Responsibilities\n\nSupport compensation and benefits functionsincluding but not limited to\u00a0payroll calculation, tax filing, MPF and benefits administration etc.;\nHandle recruitment and selection process;\nMaintain employee database and ensure all personnel records are updated and accurate;\nHelp review and formulate company HR policies and procedures, and assist in HR system upgrade and enhancement;\nProvide administrative and clerical support to the Finance and Administration Department.\u00a0 \u00a0\n\nRequirement\n\nA Bachelor Degree in Human Resources, Business\u00a0or in a related discipline;\n3 years\u2019 working experience in personnel;\nKnowledge of employment legislation;\nGood organizational and multi-tasking skills, eye for detail and sharp analytical skills, with the ability to work independently and under pressure;\nExcellent communication skills in written English and Chinese. Fluent in spoken English and Cantonese. Knowledge of Mandarin would be an advantage;\nProficiency in MS Office applications and Chinese word processing.\n\nRemuneration Package\n\nRemuneration package commensurate with candidate\u2019s qualifications and experience. Fringe benefits include annual leave, MPF and medical insurance.\n\n\n\nApplication\n\nApplication letter, together with full resume and expected salary should reach the following address :\n\nby post \u00a0\u00a0\u00a0\u00a0\u00a0\u00a0\u00a0\u00a0\u00a0\u00a0\u00a0\u00a0\u00a0\u00a0\u00a0\u00a0\u00a0\u00a0\u00a0 Finance and Administration Department\n\nHong Kong Repertory Theatre Ltd\n\n4/F Sheung Wan Municipal Services Building\n\n345 Queen's Road Central\n\nHong Kong\n\nOR\n\n\u00a0 \u00a0 \u00a0 \u00a0 \u00a0 \u00a0 \u00a0 2. Click \"Apply Now\"\n\n\n\n(Please quote \u2018Application for HKRep Post\u2019 on envelope/email subject.)\n\n\nFor more information on the Company, please visit http://www.hkrep.com. For enquiries, please call 3103 5905.\n\n\n(Information provided will be treated in strict confidence and only be used for recruitment related purpose.)", "employment_types": ["Full Time", "Permanent"], "selling_points": [], "locations": ["Sheung Wan"], "categories": ["Admin & HR", "Others", "HR Director / Manager", "HR Supporting Staff"], "post_time": "2022-01-10T07:34:39Z", "salary": {"currency": null, "max": null, "min": null, "period": "monthly", "term": null}, "salary_visible": false, "title_keywords": ["officer"], "responsibilities": [], "requirements": {"degrees": [], "majors": [], "languages": [], "language_level": [], "hard_skills": [], "soft_skills": [], "languages_combined": []}, "experience_required": {"duration": [], "field": []}}, {"job_id": "100003009025110", "location_code": "hk", "company": "", "job_title": "Human Resources & Administration Manager", "description": "We are looking for highly motivated individual who is striving for excellence and willing to take up challenges to join our team.\n\nResponsibilities:\n\nReport to Group Human Resources Director\nLead full spectrum of HR function, including talent acquisition, employee relations, payroll, benefit administration, performance management & staff welfare etc.\nReview & develop HR strategies and initiatives, with the aim to align Group business objectives and improve HR topics together with business results\nFormulate recruitment and retention plan, expand varies hiring channels to attract the right talent while build development plan for the company and staff\nMonitor monthly payroll, MPF administration and taxation, closely manage the time schedule, make sure high effectiveness on reward & incentive programs\u00a0\nMaintain HRIS and HR Projects, keep high data accuracy on HR information such as employment, leave &, attendance, and working visa application are well documented\nSet and review HR policies, ensure all the legal compliance and requirement of employment ordinance are met\nHandle general office administrative duties, such as medical & insurance,\u00a0tenancy\u00a0renewal & office renovation, repair & maintenance, office procurement etc.\u00a0\u00a0\nWork closely with management and key leaders to share HR insights and best-practices in the market\nOther Group (Corporate) Project and ad hoc duties as assigned\n\n\u00a0Requirements:\n\nUniversity Graduate in Human Resources, Psychology or Business Management\n8 years+ relevant working experience (min. 3 years in supervisory level), background in Beauty/Skincare, retail industry preferred\nPassionate about well-being, skincare, hair care, enjoy being a lifestyle advocate\nA team player with exceptional people skills, detail-oriented and able to handle challenges independently\nThrive in an entrepreneurial environment, result-oriented, keen on taking new challenges to develop sales and serving client needs\nExcellent communication skills, good command of spoken and written skills in Cantonese, Mandarin and English\nInterested candidates, please contact us at 39502919 for company details before applying.", "employment_types": ["Full Time", "Permanent"], "selling_points": ["Clean Beauty, Skincare & Lifestyle", "5 days work week, Double pay + Benefits", "Human Resources, Administration, Managerial Role"], "locations": ["Central"], "categories": ["Admin & HR", "Administration / Operation Manager", "Others", "HR Director / Manager"], "post_time": "2022-01-06T03:31:43Z", "salary": {"currency": null, "max": null, "min": null, "period": "monthly", "term": null}, "salary_visible": false, "title_keywords": ["administration manager", "human resources"], "responsibilities": ["data", "renovation", "maintain", "plan", "office procurement", "administration", "ad hoc duties", "compliance", "monitor", "develop", "schedule", "report", "attendance", "management", "mpf", "review", "administrative duties", "payroll", "taxation", "maintenance", "policies", "hr", "repair", "recruitment", "insurance"], "requirements": {"degrees": ["university graduate"], "majors": ["psychology", "business"], "languages": ["cantonese", "english", "mandarin"], "language_level": ["excellent", "good command"], "hard_skills": ["business management"], "soft_skills": ["communication skills", "independently", "keen", "detail-oriented", "team player", "result-oriented", "passionate about"], "languages_combined": [{"language": "cantonese", "language_level": ["excellent", "good command"]}, {"language": "english", "language_level": ["excellent", "good command"]}, {"language": "mandarin", "language_level": ["excellent", "good command"]}]}, "experience_required": {"duration": [], "field": ["relevant working experience"]}}, {"job_id": "100003009045816", "location_code": "hk", "company": "ConnectedGroup Limited", "job_title": "Training and Development Manager (Financial Services)", "description": "Our client is a listed financial services organization headquartered in Hong Kong. Due to current transformation they are looking for a new member to join their Human Resources team.\n\nInvestment banking\nFast-paced culture\nStrategic L&D\n\nThe role\n\nReporting to the Head of Learning and Development, this position will be a key player in supporting the implementation of programs to help develop young and future talents within the organization and its delivery. You will be accountable for analyzing and assessing training trends that matches current needs, business strategy and company compliance. You will also develop and build a strong relationship with both internal and external stakeholders. Ad-hoc projects will be assigned as needed.\n\nThe candidate\n\nDegree qualification or above with a minimum of 7 years of experience related to training and development. Exposure to multinational companies will be highly advantageous.\nStrong project management and analytical skills with a problem solving mindset and detail oriented.\nHighly adaptable and able to thrive in a fast-paced and result oriented environment.\nExcellent communication and interpersonal skills with a proactive ability to build and manage stakeholders relationship.\nCommitted and mature with high level of integrity.\nExcellent command in both written and spoken Chinese and English.\n\nInterested parties, please apply the job online or contact Eunice Lei Ho directly via eunice.leiho@connectedgroup.com for more information. Please note that only short-listed candidates will be notified. All information gathered will be treated in strict confidence and solely used for recruitment purposes.", "employment_types": ["Full Time", "Permanent"], "selling_points": ["Investment banking", "Fast-paced culture", "Strategic L&D role"], "locations": ["Not Specified"], "categories": ["Banking / Finance", "Financial Services", "Equities / Capital Markets", "Admin & HR", "HR Director / Manager"], "post_time": "2022-01-13T08:47:50Z", "salary": {"currency": null, "max": null, "min": null, "period": "monthly", "term": null}, "salary_visible": false, "title_keywords": ["manager"], "responsibilities": ["reporting", "compliance", "implementation", "develop", "communication", "project management", "banking", "ad-hoc projects"], "requirements": {"degrees": ["degree"], "majors": [], "languages": ["english", "chinese"], "language_level": ["excellent"], "hard_skills": ["problem solving", "project management", "analytical skills"], "soft_skills": ["adaptable", "detail oriented", "integrity", "accountable", "mature", "analytical skills", "problem solving", "project management", "result oriented", "learning", "communication and interpersonal skills", "committed", "proactive"], "languages_combined": [{"language": "english", "language_level": ["excellent"]}, {"language": "chinese", "language_level": ["excellent"]}]}, "experience_required": {"duration": ["minimum of 7 years"], "field": ["related", "development", "training"]}}, {"job_id": "100003009039618", "location_code": "hk", "company": "ConnectedGroup Limited", "job_title": "Senior Regional Talent Acquisition Manager", "description": "Our client is a reputable fashion retail group with strong business presence globally. In order to cope with their business expansion and transformation, they are currently looking for a senior talent acquisition manager to oversee their recruitment function across APAC region.\n\nJob duties:\n\nReport to Talent Acquisition Director, act as an internal recruiter to provide HR consultative service in talent acquisition\nResponsible for full recruitment cycle of managerial/executive level corporate positions and provide substantial advice to team lead and senior management\nManage both online and offline recruitment solutions in employer branding and engagement\nPartner with business leaders, HR business partners and global TA team to understand, develop and implement business-driven talent acquisition initiatives and projects\nSupport ad-hoc projects in recruitment technology, employer branding, learning & development and related area\n\nJob requirements:\n\nDegree holder in Business Management, HR or equivalent is preferred\nAt least 10 years of solid recruitment experience with executive search experience\nStrong interpersonal and communications skills with flexible and adaptive mindset\nProcess superb presentation, communications, project management and multi-senior stakeholders management skills\nReady to take on challenges and deal with ambiguity and tight timeline with high level of independence\nGreat team player with the ability to work independently\nHR technology savvy and proficient in MS suite\nExcellent command of English and Chinese\n\nInterested parties, please apply the job or contact Phoebe Cheung directly at phoebe.cheung@connectedgroup.com for more information. Please note that only shortlisted candidates will be notified. All information gathered will be treated in strict confidence and solely used for recruitment purposes.\n\n\nFor a more comprehensive list of our vacancies, please visit: www.connectedgroup.com", "employment_types": ["Full Time", "Permanent"], "selling_points": ["Pleasant company culture", "Competitive remuneration package", "Career growth opportunities"], "locations": ["Not Specified"], "categories": ["Admin & HR", "HR Director / Manager", "Recruitment / Executive Search"], "post_time": "2022-01-11T10:13:30Z", "salary": {"currency": "HKD", "max": 69999, "min": 55000, "period": "monthly", "term": null}, "salary_visible": true, "title_keywords": ["manager"], "responsibilities": ["ad-hoc projects", "hr", "develop", "recruitment", "senior management", "report"], "requirements": {"degrees": ["degree holder"], "majors": ["business"], "languages": ["english", "chinese"], "language_level": ["excellent"], "hard_skills": ["business management", "project management"], "soft_skills": ["flexible", "work independently", "project management", "team player", "interpersonal", "presentation"], "languages_combined": [{"language": "english", "language_level": ["excellent"]}, {"language": "chinese", "language_level": ["excellent"]}]}, "experience_required": {"duration": ["at least 10 years"], "field": ["recruitment"]}}, {"job_id": "100003009032817", "location_code": "hk", "company": "Chandler Macleod Group (HK) Limited", "job_title": "HR Manager / Senior HR Manager", "description": "Responsibilities\n\n\n\nBe a global strategic HR advisor to senior management across HK and Overseas operation\nLiaise with business leaders and execute different HR strategic planning on manpower planning, organization design, performance management, succession planning, etc.\nWork closely with HR counterparts and ensure smooth and accurate HR operations\nHandle staff enquiries and provide professional HR solution and advice\nReview and develop HR policy and procedure in HK and overseas to ensure its compliance with local regulations\nParticipate in various HR projects as required\n\nRequirements\n\n\nDegree holder of Human Resources Management or equivalent\nMinimum of 8 years relevant working experience in the HR field, preferably gained from Chinese based companies\nExperience as a HR advisor to senior management on HR strategic planning\nHands-on experience in full range of HR tasks and activities\nEffective communication skills and cultural sensitivity\nExcellent command in both verbal and written Mandarin / Chinese and English", "employment_types": ["Full Time", "Permanent"], "selling_points": ["Well-established Chinese Corporation", "Strategic BP role with Global Exposure", "13th Month Salary + Attractive Bonus"], "locations": ["Not Specified"], "categories": ["Admin & HR", "Others", "HR Director / Manager", "Recruitment / Executive Search"], "post_time": "2022-01-07T23:00:56Z", "salary": {"currency": null, "max": null, "min": null, "period": "monthly", "term": null}, "salary_visible": false, "title_keywords": ["hr manager"], "responsibilities": ["regulations", "management", "strategic planning", "operations", "hr", "review", "compliance", "design", "develop", "liaise with", "senior management", "planning"], "requirements": {"degrees": ["degree holder"], "majors": [], "languages": ["english", "chinese", "mandarin"], "language_level": ["excellent"], "hard_skills": [], "soft_skills": ["communication skills", "hands-on", "sensitivity"], "languages_combined": [{"language": "english", "language_level": ["excellent"]}, {"language": "chinese", "language_level": ["excellent"]}, {"language": "mandarin", "language_level": ["excellent"]}]}, "experience_required": {"duration": ["minimum of 8 years"], "field": ["hr", "planning", "relevant working experience", "management"]}}, {"job_id": "100003009031659", "location_code": "hk", "company": "Michael Page", "job_title": "Human Resources Manager  - Generalist", "description": "This is a all round HR generalist position where you will lead a team of 3 to support the HR operations of 200-250 staff.\n\nClient Details\n\nOur client is a renowned and well established education chain in Hong Kong.\n\nDescription\n\nWorking closely the senior management team, you will lead a small team of HR professionals and provide an all round HR service. The team is responsible for recruitment, on and off boarding, compensation & benefits admin and ensure that the HR data are well in place in order to migrate to the new HRIS in 2022. You will provide sound HR advice to the department heads on talent management and employment issues, and in times where the Covid situation is unstable, you will need to stay abreast with the government announcement and news, and determine what needs to be done to protect the staff's health and personal safety in a timely manner.\n\nProfile\n\nThe successful applicant will be degree qualified with a minimum of 15 years of all round HR generalist experience from sizable and structured companies. You will have experience managing a small team to provide all round HR services. Those with experience implementing a new HR system will have an advantage. The HR role we are hiring for this client is not complex with low turnover in their education centres. Working hours are stable and the work location is close to the MTR. We are however, looking for someone with a positive and pleasant personality as internal harmony is important to our client. You will be a good listener with a patient and personable character. A good level of English written skills is required. Candidates with less experience may be considered for an Assistant Manager position.\n\nJob Offer\n\nWork life balance\n\nCompetitive pay\n\nStable company\n\nTo apply online please click the 'Apply' button below. For a confidential discussion about this role please contact Grace Lee on +852 2848 4721", "employment_types": ["Full Time", "Permanent"], "selling_points": ["Work life balance", "Competitive Pay", "Stable working environment"], "locations": ["Not Specified"], "categories": ["Admin & HR", "HR Director / Manager"], "post_time": "2022-01-07T09:37:42Z", "salary": {"currency": null, "max": null, "min": null, "period": "monthly", "term": null}, "salary_visible": false, "title_keywords": ["manager", "human resources"], "responsibilities": ["management", "data", "operations", "hr", "lead a small team", "a timely manner", "lead a team", "recruitment", "senior management"], "requirements": {"degrees": ["degree"], "majors": [], "languages": [], "language_level": [], "hard_skills": ["small"], "soft_skills": ["timely", "structured", "responsible"], "languages_combined": []}, "experience_required": {"duration": ["minimum of 15 years"], "field": ["hr", "hr generalist", "team"]}}, {"job_id": "100003009035857", "location_code": "hk", "company": "Dorshare Limited", "job_title": "Finance Manager", "description": "Duties/Responsibilities\n\nThe Finance Manager will take ownership of all\u00a0Finance,\u00a0Accounting\u00a0and\u00a0HR\u00a0operations. He will be responsible for formulating the company\u2019s overall financial control systems to ensure that daily operations run effectively, our vendors and employees are paid promptly and making sure we are compliant with all regulatory requirements in the markets where we have subsidiaries. (US, TH, UAE, SG) \u00a0\n\nThe Role\u00a0\n\nThe Finance Manager will work closely with the board to provide strategic oversight of the business internationally. The manager\u00a0will implement internal policies and procedures that increase operational effectiveness and maximise long term performance. He or she will be an expert in analysing business performance metrics and translating it into actionable budgets that lead to business results.\u00a0\n\nResponsibilities\n\nOversee overall accounting operation\u00a0\n\nReview international staff payroll & commission\u00a0\n\nReview and draft all employment contracts\n\nReview all internal and external bill payments, A/R, A/P, GL, Cost Accounting, Inventory Accounting and Revenue Recognition\u00a0\n\nReview group cashflow projections\u00a0and secure finance\n\nManage overseas bankers, agents & auditors\u00a0\n\nResponsible for ensuring that all operations meet local & international compliance\u00a0\n\nPrepare management budget for the entire business\u00a0\n\nReview all lease contracts\u00a0\n\nReview annual insurance policies\u00a0\n\nPrepare annual review schedule for overseas bankers\u00a0\n\nManage\u00a0annual audits for all entities\u00a0\n\nDevelop and document business processes and accounting policies to maintain and strengthen internal controls\u00a0\n\nEnsure all internal and external transactions are controlled and monitored\u00a0\n\nRequirements\u00a0\n\nProven working experience as a Finance Manager\n\n10+ years of overall combined finance and HR\u00a0experience\u00a0\n\nAdvanced degree in Accounting\u00a0\n\nCPA or CMA\u00a0\n\nThorough knowledge of accounting principles and procedures\u00a0\n\nExcellent accounting software user and administration skills\u00a0\n\nExcellent communication and management skills", "employment_types": ["Full Time"], "selling_points": [], "locations": ["Kwun Tong"], "categories": ["Accounting", "Finance / Accounting Manager", "Admin & HR", "HR Director / Manager"], "post_time": "2022-01-10T08:38:45Z", "salary": {"currency": null, "max": null, "min": null, "period": "monthly", "term": null}, "salary_visible": false, "title_keywords": ["finance manager"], "responsibilities": ["operations", "regulatory requirements", "inventory", "budget", "bill payments", "transactions", "accounting policies", "maintain", "control", "contracts", "compliance", "develop", "schedule", "cost", "management", "review", "procedures", "daily operations", "audits", "payroll", "budgets", "policies", "hr", "systems", "performance metrics", "insurance"], "requirements": {"degrees": ["degree"], "majors": ["accounting"], "languages": [], "language_level": [], "hard_skills": ["accounting software", "cpa"], "soft_skills": ["communication", "thorough", "administration skills", "advanced"], "languages_combined": []}, "experience_required": {"duration": ["10+ years"], "field": ["finance", "hr", "finance manager"]}}, {"job_id": "100003009021549", "location_code": "hk", "company": "Steve Lo People Resources Ltd", "job_title": "Human Resources Leader", "description": "Human Resources Leader\n\nOur Client:\u00a0\u00a0They are one of the leading groups in beauty industry. \u00a0They own many renowned brands and have developed a strong presence in Asia.\n\nRoles and Responsibilities:\n\nReporting to the Managing Director, the incumbent will be accountable for providing HR service and strategic support to the top leader in Hong Kong and their Head Quarter in overseas.\nFormulating HR strategies and initiatives including talent management, C&B strategy, succession planning and organizational development to support the achievements of the long-term business and operations objectives.\nReview and make recommendation in change of organization structure for strengthening the internal capability to meet its current and possible future business requirements\nEnsuring in place of talent management and career progression programs for the high potential individuals, including identification of talents, succession planning, development programs, performance assessment and tracking, etc.\nProviding advice and recommendations to the top management should there be any changes on local employment laws or regulations (or related) or market practice that might have impact on the Company/ Industry.\nWorking as a strategic business partner to the line management.\u00a0\n\nThe Ideal Candidate:\n\nDegree + a minimum of 15 years related working experience, 5 years of which as the HR Leader in multi-national organization.\nFamiliar with the employment laws and related regulations in Hong Kong is essential.\nStrategic, assertive with excellent interpersonal skills are necessary attributes.\nFluent in both Cantonese and English.\nLess experienced candidate will be considered as Senior HR Manager\n\nRemuneration: \u00a0Compensation will be set at a level appropriate to the background, current position and current compensation of the successful candidate.", "employment_types": ["Full Time"], "selling_points": ["Excellent interpersonal and leadership skills", "Minimum of 15 years of HR experience", "Solid experience in retailing industry"], "locations": ["Not Specified"], "categories": ["Admin & HR", "HR Director / Manager"], "post_time": "2022-01-05T04:15:18Z", "salary": {"currency": null, "max": null, "min": null, "period": "monthly", "term": null}, "salary_visible": false, "title_keywords": ["human resources"], "responsibilities": ["regulations", "reporting", "management", "tracking", "make recommendation", "development programs", "operations", "hr", "review", "planning"], "requirements": {"degrees": ["degree"], "majors": [], "languages": ["cantonese", "english"], "language_level": ["fluent"], "hard_skills": ["make"], "soft_skills": ["assertive", "organizational", "accountable", "interpersonal skills", "ideal"], "languages_combined": [{"language": "cantonese", "language_level": ["fluent"]}, {"language": "english", "language_level": ["fluent"]}]}, "experience_required": {"duration": ["5 years", "minimum of 15 years"], "field": ["related", "hr"]}}, {"job_id": "100003009039858", "location_code": "hk", "company": "CBRE Limited", "job_title": "Head of Learning & Development - APAC", "description": "At CBRE, you are empowered to take your career path into your own hands. Our people enjoy workplace flexibility in a global organization with tremendous scale providing corporate real estate and property services. Each day you will work in an inclusive and collaborative environment with supportive teammates and be challenged to grow and be your best every day.\n\nIn line with the continued growth and expansion of our business throughout Asia Pacific, we have an exciting opportunity for an APAC Learning & Development Lead to join our team. Based in either Singapore or Hong Kong, the successful candidate will develop, lead, and implement business-relevant L&D solutions across the APAC Advisory business.\n\nKey Responsibilities:\n\nAct as a change expert, making sure that learning & development interventions are at the core of change programs and supporting leaders in delivery\nCreate and deliver initiatives that align, preserve, and develop the CBRE RISE values and desired Advisory culture\nAct as an ambassador for APAC Advisory L&D needs at a global level, actively participating in the development of global L&D programs, projects, and initiatives\nBuild and maintain regular, high quality contact with key internal stakeholders\nUnderstand what is required in each area of the business and develop L&D plans that focus on the delivery of those outcomes\nProvide input on L&D policies and processes, policy development (in line with country practices) and in achieving business plans and growth\nProvide insight and practices from outside of CBRE to stretch internal thinking/practices and advise internal stakeholders on current and future market capabilities\nDeliver L&D programs that support the attraction, development, and retention of talent\nEnsure proposed learning solutions fit within clearly defined budgetary parameters prior to delivery of learning solutions to internal clients\nMotivate and lead the L&D team, promoting a high-performance and results-based culture\nSkills & Experience:\n\n10 years\u2019 of progressive L&D experience, within an MNC\nDemonstrated creation of innovative and scalable programmes, tools and resources to support the delivery of the People agenda\nAn effective influencer and trusted advisor\nAbility to operate in a fast paced and high-volume business with strong resilience and an ability to lead and manage change\nHave managed L&D budgets with knowledge of financial terms and principles and conduct financial analysis\nSuperior written and verbal communication skills with strong oral presentation skills\nAdvanced skills in Microsoft Office suite\n\nIf working with the best in an exciting and rewarding team environment appeals to you then we want to hear from you. Please attach your CV to your application.\n\n", "employment_types": ["Full Time", "Permanent"], "selling_points": ["Regional Head of L&D", "APAC portfolio", "Leading learning & development initiatives"], "locations": ["Ngau Tau Kok"], "categories": ["Admin & HR", "HR Director / Manager"], "post_time": "2022-01-11T12:44:00Z", "salary": {"currency": null, "max": null, "min": null, "period": "monthly", "term": null}, "salary_visible": false, "title_keywords": [], "responsibilities": ["budgets", "policies", "quality", "business plans", "develop", "financial analysis", "communication", "maintain", "contact", "policy development", "plans"], "requirements": {"degrees": [], "majors": [], "languages": [], "language_level": [], "hard_skills": ["financial analysis", "microsoft office suite", "focus"], "soft_skills": ["communication skills", "supportive", "oral", "advanced", "collaborative", "presentation skills", "learning", "progressive", "focus", "innovative", "superior"], "languages_combined": []}, "experience_required": {"duration": ["10 years"], "field": []}}, {"job_id": "100003009040229", "location_code": "hk", "company": "Randstad Hong Kong Limited", "job_title": "Senior Learning & Development Manager, Digital", "description": "about the company.\n\nOur client is a well known Leading Conglomerate with growing business. They are looking for a Senior Learning & Development Manager, Digital to join their HR team, they are expanding their team.\n\nabout the team.\n\nReports to the L&D Team Head within a team of 4.\n\nabout the job.\n\nUnderstand and identify the learning needs for business units and the team\nCurate and facilitate a development strategy for course contents and journey path for specific staff groups\nDesign and implement eLearning Platform aligning with LMS system\nCreate a holistic online learning experience for employees of all levels\nMonitor vendor performance and partner closely with vendors on course and content development\nBuild learning culture for employees and ensure they are adapting to it\nKeep update to date of the market trend for learning platforms and content\nFacilitate Group HR and Business units to monitor the implication of the eLearning scheme\nMaintain relationships with internal and external stakeholders\nPerform ad hoc projects as required\n\nskills & experiences required.\n\nBachelor degree in Human Resources or related field\n8+ years of solid experience in Training & Development, eLearning and online platform development experiences are essential\nOverall solid experience with digital systems\nStrong project management experience, excellent reporting skills\nFluent in English, Cantonese and Mandarin\nAble to work as an individual contributor & great communicator\n\n\nInterested parties please apply for the job by clicking the appropriate link with your updated resume, project lists, portfolio and salary details to sum.cheung@randstad.com.hk. We regret only shortlisted candidates will be contacted.", "employment_types": ["Full Time", "Permanent"], "selling_points": ["Conglomerate", "Location: Hong Kong Island", "20 days annual leave"], "locations": ["Quarry Bay"], "categories": ["Admin & HR", "Others", "HR Director / Manager", "Training & Development"], "post_time": "2022-01-12T01:56:51Z", "salary": {"currency": "HKD", "max": 54999, "min": 45000, "period": "monthly", "term": null}, "salary_visible": true, "title_keywords": ["manager"], "responsibilities": ["maintain relationships", "reporting", "hr", "systems", "monitor", "design", "project management", "reports", "ad hoc projects", "contents"], "requirements": {"degrees": ["degree", "bachelor"], "majors": [], "languages": ["cantonese", "english", "mandarin"], "language_level": ["fluent"], "hard_skills": ["project management", "vendor", "scheme"], "soft_skills": ["project management", "communicator", "learning"], "languages_combined": [{"language": "cantonese", "language_level": ["fluent"]}, {"language": "english", "language_level": ["fluent"]}, {"language": "mandarin", "language_level": ["fluent"]}]}, "experience_required": {"duration": ["8+ years"], "field": ["development", "project management", "training", "digital"]}}, {"job_id": "100003009025878", "location_code": "hk", "company": "Gene Company Limited", "job_title": "HR Manager  (5 Days Work)", "description": "Responsibilities:\n\n\n\nProvide full spectrum of HR functions including but not limited to recruitment,compensation and benefit, succession planning and employee relations\nDesign and manage employee on-boarding, engagement and off-boarding procedures\nDrive annual compensation process including staff\u2019s appraisal, salary review, budgeting, incentive/commission schemes to facilities recruitment and retention program\nEnsure all HR and Administration processes and policies to comply with legal requirements\nSupport department head in formulating and executing HR initiatives\nParticipate in ad hoc projects and assignments\nRequirements:\u00a0\n\nDegree holder in HRM \u00a0or related discipline\nMinimum of 5 years relevant experience in Human Resources with at least 3-year in the management level\nWell-versed with Employment Ordinance\nExcellent active listening, negotiation and presentation skills\nGood command in both spoken and written English and Chinese (Cantonese and Mandarin)\nProficient in MS office (Word, Excel & PowerPoint)\n\nFringe\u00a0Benefits:\nAttractive remuneration package\nGuarantee Year-end double-pay\n5 days Work\u00a0\nPublic Holiday\nMax.15 days of Annual Leave\nSpecial Leave: Marriage Leave, Compassionate Leave\nMedical Allowance\nVoluntary MPF Contribution\nExcellent Career Prospects\n\nInterested parties please send detailed resume with current and expected salary to us (by email or\u00a0to click \"Apply Now\")\n\nFor more Company information, please visit our website at\u00a0http://www.genehk.com\n\nPersonal data collected will be used for recruitment purpose only.", "employment_types": ["Full Time", "Permanent"], "selling_points": ["Provide full spectrum of HR functions", "5 days work week", "Minimum of 5 years relevant experience"], "locations": ["Chai Wan"], "categories": ["Admin & HR", "HR Director / Manager"], "post_time": "2022-01-06T06:40:32Z", "salary": {"currency": null, "max": null, "min": null, "period": "monthly", "term": null}, "salary_visible": false, "title_keywords": ["hr manager"], "responsibilities": ["administration", "budgeting", "hr", "review", "procedures", "policies", "design", "recruitment", "executing", "ad hoc projects", "planning"], "requirements": {"degrees": ["degree holder"], "majors": [], "languages": ["cantonese", "english", "chinese", "mandarin"], "language_level": ["good command"], "hard_skills": ["excel", "word", "powerpoint", "ms office"], "soft_skills": ["presentation skills", "active", "negotiation"], "languages_combined": [{"language": "cantonese", "language_level": ["good command"]}, {"language": "english", "language_level": ["good command"]}, {"language": "chinese", "language_level": ["good command"]}, {"language": "mandarin", "language_level": ["good command"]}]}, "experience_required": {"duration": ["at least 3-year", "minimum of 5 years"], "field": ["management", "relevant experience", "human resources"]}}, {"job_id": "100003009032940", "location_code": "hk", "company": "JPC Texson Limited", "job_title": "SENIOR HUMAN RESOURCES & ADMIN OFFICER (22K-28K) - HK listed/China state-owned enterprise (TST)", "description": "\n\nTHE COMPANY :\n\n\nHK listed company\nChina state-owned enterprise\nBusiness conglomerate in international trading, natural resources and financial services\u00a0\n\nWe are looking for\u00a0 SENIOR HUMAN RESOURCES & ADMIN OFFICER\u00a0 - with details as follows :\nTHE JOB :\n\n\nJob summary : 70% human resources; 30% office administration\n\u5efa\u7acb\u8207\u7dad\u8b77\u5305\u62ec\u4f46\u4e0d\u9650\u65bc\u4eba\u4e8b\u5408\u540c\u3001\u6587\u4ef6\u3001\u6a94\u6848\u3001\u8003\u52e4\u8a18\u9304\u53ca\u5176\u4ed6\u57fa\u790e\u8cc7\u6599\uff1b\n\u8ca0\u8cac\u54e1\u5de5\u85aa\u916c\u53ca\u798f\u5229\uff0c\u5305\u62ec\u5de5\u8cc7\u3001\u88dc\u8cbc\u3001\u5f37\u7a4d\u91d1\u3001\u500b\u4eba\u5165\u606f\u7a05\uff0c\u4fdd\u96aa\u53ca\u5176\u4ed6\u798f\u5229\uff08\u5982\u9069\u7528\uff09\u7684\u8a08\u7b97\u53ca\u7d71\u8a08\uff0c\u751f\u6210\u548c\u7dad\u8b77\u8cc7\u6599\u5eab\uff0c\u7de8\u5236\u4eba\u529b\u6210\u672c\u6708\u5831\u3001\u5e74\u5831\uff0c\u4ee5\u53ca\u4e0a\u7d1a\u55ae\u4f4d\u6216\u516c\u53f8\u7ba1\u7406\u9700\u8981\u7684\u7d71\u8a08\u7d50\u679c\u8207\u5831\u544a\uff1b\n\u53c3\u8207\u4eba\u4e8b\u57f7\u884c\u8cc7\u8a0a\u7cfb\u7d71\u512a\u5316\u5de5\u4f5c\uff1b\n\u5354\u52a9\u8a55\u4f30\u5be9\u67e5\u4eba\u4e8b\u653f\u7b56\u3001\u5236\u5ea6\u6d41\u7a0b\u9069\u7528\u6027\uff0c\u63d0\u51fa\u6539\u9032\u5efa\u8b70\uff0c\u8ddf\u9032\u5f8c\u7e8c\u7684\u7dad\u8b77\u8207\u512a\u5316\u5de5\u4f5c\uff1b\n\u5354\u52a9\u9032\u884c\u4eba\u529b\u8cc7\u6e90\u5e02\u5834\u7814\u7a76\u3001\u4eba\u529b\u8cc7\u6e90\u6230\u7565\u5206\u6790\u548c\u63d0\u51fa\u89e3\u6c7a\u65b9\u6848\u5efa\u8b70\uff1b\n\u8ca0\u8cac\u516c\u53f8\u4eba\u54e1\u8077\u5d17\u7ba1\u7406\uff08\u62db\u8058\u3001\u63d0\u8058\u3001\u8abf\u5d17\u3001\u96e2\u9000\uff09\u3001\u8003\u6838\u7ba1\u7406\uff0c\u57f9\u8a13\u7b49\u5177\u9ad4\u5de5\u4f5c\uff1b\n\u5728\u90e8\u9580\u8ca0\u8cac\u4eba\u6307\u5c0e\u4e0b\uff0c\u7de8\u5236\u9999\u6e2f\u8fa6\u516c\u5ba4\u4eba\u4e8b\u884c\u653f\u5e74\u5ea6\u9810\u7b97\uff1b\nReporting to the Senior HR & Admin Manager\nWork in HR & Admin Team of 4 members\u00a0\nPerform full HR duties for Head office 30-40 staff, as well as oversee HR of various small subsidiaries\u00a0\nProvide full spectrum of human resources functions including but not limited to compensation and benefits, recruitment and selection, performance management, taxation, MPF, policy review, insurance renewal...etc\nParticipate in formulating HR related policies and procedures in compliance with legal requirements, company standard and HR practice;\nProvide support for annual salary and benefit review, salary benchmarking and benefits surveys;\nEnsure accuracy and monthly payroll calculation for both Headquarters and subsidiaries;\nManage attendance and leave data in HRIS on regular basis to facilitate report generation and payroll processing;\nMaintain updated HR records in human resources systems and personal file system;\nPrepare regular HR reports, annual budget and forecast required by the Group or Management;\nParticipate in HR system & advancement project;\nDegree holder\nOver 3-5 years human resources experience with hands-on experience in payroll and C&B function\nExperience in China state-owned enterprises is a big plus\nWell versed in Employment Ordinance, MPF and other related statutory regulations;\nProficient in Mandarin and ability to draft Chinese correspondence / memorandum\n5 days work\n\nAnnual leave : 14 days\n\nMedical benefit\nAttractive performance bonus\n\n\u00a0\n\n\u00a0\nTO APPLY for this job or similar jobs :\n\u00a0\n\n\nFor secure and confidential job application, please click the below link to get our email address.\n\u00a0\nhttp://jpc.hk/confidential_apply.htm\n\u00a0\n\u00a0\nWe provide free job hunting services to job seekers.\n\u00a0\nTo speed up our process, please do NOT send us download links.\n\u00a0\nPersonal data provided by job applicants will be used for recruitment purpose only.\n\u00a0\nYour privacy is guaranteed. We will never give out, lease, or sell your personal information.\n\u00a0\nJPC Recruiting Services was established in 1990.\n\u00a0\nhttp://www.facebook.com/pages/JPC-Texson-Ltd/500356593325952\n\u00a0\n\u00a0\n\u00a0\n\u00a0", "employment_types": ["Full Time", "Permanent"], "selling_points": ["Degree; proficient Mandarin/Chinese correspondence", "Over 3-5 yr HR; hands-on in payroll / C&B", "Exp in China state-owned enterprises a plus"], "locations": ["Yau Tsim Mong Area"], "categories": ["Admin & HR", "Compensation & Benefits", "HR Director / Manager", "HR Supporting Staff"], "post_time": "2022-01-08T03:32:01Z", "salary": {"currency": null, "max": null, "min": null, "period": "monthly", "term": null}, "salary_visible": false, "title_keywords": ["officer", "admin", "human resources"], "responsibilities": ["reporting", "management", "taxation", "mpf", "office administration", "hr", "review", "policies", "hr duties", "procedures", "compliance", "recruitment", "insurance", "human resources functions"], "requirements": {"degrees": [], "majors": [], "languages": [], "language_level": [], "hard_skills": ["small"], "soft_skills": [], "languages_combined": []}, "experience_required": {"duration": [], "field": []}}, {"job_id": "100003009024353", "location_code": "hk", "company": "EBC Technology Limited", "job_title": "HR & Administrator", "description": "About this role\n\nWe are looking for individuals and proactive HR & Administrator to join our expanding team in Hong Kong. You will be the key member to provide HR and administrative support to drive operational efficiency. This is a unique opportunity to be part of a fast-paced dynamic, team-oriented environment.\n\nRole Responsibilities\n\nResponsible to support recruitment and hiring process\nResponsible to assist with the efficient running of HK office in line with the brand standard, maintaining a new work environment\nAct as the main point of contact for HK office, liaise with Global Offices, headquarter and other stakeholders.\nAssist in the on-boarding and off-boarding processes for the Hong Kong office, payroll and benefits administration, MPF, visa applications, and other administrative processes\nWork closely with CEO, Provide support to ad hoc assignments/projects as and when required\n\nRole Requirements\n\nFresh Grad are welcome or\u00a0have experience within the HR and Admin function\nMandarin: Mandatory, Cantonese and/or English\nQuick learner in picking up new technologies or applications\nProcess and detail-oriented, able to work accurately under pressure, results-driven, experienced in project management is a plus\nAbility to work both independently and collaboratively\u00a0\n\nWhat we offer\n\nCompetitive salary\nBecome a part of a company that demonstrates a true commitment to work-life balance.\nEnergetic work environment and flat organization\nGreat career development opportunities in a growing company\nFlexible working hours, Casual work attire\u00a0\n\nAbout EBC\n\nEBC Tech is a subsidiary of EBC Financial Group, which is a London-based financial group committed to offering a trustworthy online trading service to our diversified clients across the globe. Learn More:\u00a0 www.ebcfin.co.uk\u00a0\n\n", "employment_types": ["Full Time"], "selling_points": [], "locations": ["Kowloon City Area"], "categories": ["Admin & HR", "Administration / Operation Manager", "HR Director / Manager", "HR Supporting Staff"], "post_time": "2022-01-05T17:02:58Z", "salary": {"currency": null, "max": null, "min": null, "period": "monthly", "term": null}, "salary_visible": false, "title_keywords": ["administrator", "hr"], "responsibilities": ["provide support", "mpf", "maintaining", "recruitment", "contact", "ad hoc assignments", "liaise with", "administrative processes", "payroll", "administration"], "requirements": {"degrees": [], "majors": [], "languages": ["cantonese", "english", "mandarin"], "language_level": [], "hard_skills": ["project management", "plus"], "soft_skills": ["independently", "under pressure", "quick learner", "detail-oriented", "project management", "driven"], "languages_combined": [{"language": "cantonese", "language_level": []}, {"language": "english", "language_level": []}, {"language": "mandarin", "language_level": []}]}, "experience_required": {"duration": [], "field": ["hr", "admin"]}}, {"job_id": "100003009026625", "location_code": "hk", "company": "Finet Holdings Limited", "job_title": "HR and Admin. Manager", "description": "Reporting to Chairlady, you will be responsible for :\n\nMatters related to HR & Admin in Hong Kong Office\nCoordinating with HR departments in different locations in China to ensure policy consistency\nManage full employee life cycle from recruitment and selection, on-boarding, engagement and development to off boarding\nFormulate recruitment and retention plan, expand varies hiring channels to attract the right talent\u00a0\nReview HR policies, ensure all the legal compliance and requirement of employment ordinance are met\nManaging compensation, benefits, and payroll administration\nManage daily office administrative functions\nReview and prepare annual appraisal report\nWork closely with management and key department heads to share HR insights and best-practices in the market\n\nRequirements :\n\nDegree holder in Human Resources or Business Administration or related disciplines\n6-8 years of working experience with at least 2 years in managerial level.\nStrong analytical skills, multi-tasking, organized and able to meet tight deadlines.\nExcellent communication & interpersonal skills.\nWell-versed in Employment Ordinance and other related legislation in Hong Kong.\nGood\u00a0command of both oral and written English and Chinese (include Mandarin).\nImmediately available is highly preferred\n\nWe offer successful candidate an attractive remuneration package and excellent career prospects. Interested parties please send your resume with recent PHOTO, present and expected salary also contact details by clicking \"Apply Now\".", "employment_types": ["Full Time", "Permanent"], "selling_points": [], "locations": ["Wan Chai"], "categories": ["Admin & HR", "HR Director / Manager"], "post_time": "2022-01-06T08:25:20Z", "salary": {"currency": null, "max": null, "min": null, "period": "monthly", "term": null}, "salary_visible": false, "title_keywords": ["hr", "admin", "manager"], "responsibilities": ["reporting", "policies", "hr", "review", "compliance", "recruitment", "plan"], "requirements": {"degrees": [], "majors": [], "languages": [], "language_level": [], "hard_skills": [], "soft_skills": ["responsible"], "languages_combined": []}, "experience_required": {"duration": [], "field": []}}, {"job_id": "100003009029809", "location_code": "hk", "company": "World Vision Hong Kong", "job_title": "Assistant Human Resources Manager / Senior Human Resources Officer", "description": "Job Responsibilities\n\n\nDesign and implement staff engagement activities to promote staff wellness and enhance staff communication\nPartner with line departments on recruitment matters\nCoordinate the annual staff opinion survey, conduct analysis on survey results, develop and implement the follow up actions\nCoordinate and implement talent development program\nSupport ad hoc HR projects/initiatives\n\nJob Requirements\n\n\nBachelor Degree in Human Resources or related discipline\n8 years or above of relevant experience, with experience in staff engagement and recruitment\nGood communication and interpersonal skills\nGood command in both written and spoken English and Chinese\nPleasant, outgoing and presentable\nCandidates with less experience may be considered as Senior Human Resources Officer\nOn renewable contract term for the initial two years. Candidates with satisfactory performance may convert to permanent employment afterwards based on business need\n\nPlease apply online with your full resume, listing church affiliations (if any), current and expected salary.\u00a0\n\nYou may also send your\u00a0application\u00a0to\u00a0Head of HR & Administration,\u00a0World Vision Hong Kong,\u00a02/F Mayfair Centre,\u00a04 Anchor Street, Tai Kok Tsui,\u00a0Kowloon\u00a0\n\nTo find out more about our job opportunities, please visit our website\nhttps://www.worldvision.org.hk/get-involved/vacancies\n\nWorld Vision Hong Kong is committed to safeguarding our children and adult beneficiaries from any risk of abuse, exploitation and harm. Candidates selected for interviews will be requested a self-declaration of previous records for any crimes against children or sexual offences, and may be requested to undergo Sexual Conviction Record Check by the HK Police.\n\nPersonal Data provided by job applicants will be used for recruitment purposes only and will be treated in accordance with the organization's personal data privacy policy. Applicants who are not invited for interviews within six weeks may consider their applications unsuccessful and the personal data collected will be destroyed within 12 months.", "employment_types": ["Full Time"], "selling_points": [], "locations": ["Mong Kok"], "categories": ["Admin & HR", "HR Director / Manager", "HR Supporting Staff", "Recruitment / Executive Search"], "post_time": "2022-01-07T06:13:39Z", "salary": {"currency": null, "max": null, "min": null, "period": "monthly", "term": null}, "salary_visible": false, "title_keywords": ["senior human resources officer", "assistant human resources manager"], "responsibilities": ["ad hoc", "analysis", "hr", "design", "develop", "communication", "coordinate", "recruitment"], "requirements": {"degrees": ["degree", "bachelor"], "majors": [], "languages": ["english", "chinese"], "language_level": ["good command"], "hard_skills": [], "soft_skills": ["outgoing", "presentable", "pleasant", "committed", "communication and interpersonal skills"], "languages_combined": [{"language": "english", "language_level": ["good command"]}, {"language": "chinese", "language_level": ["good command"]}]}, "experience_required": {"duration": ["8 years"], "field": ["recruitment", "relevant experience", "human resources"]}}, {"job_id": "100003009036935", "location_code": "hk", "company": "ACT Company", "job_title": "Recruiting Manager \u62db\u52df\u7d93\u7406 X Wealth Management \u8ca1\u5bcc\u7ba1\u7406", "description": "# \u8acb\u597d\u597d\u73cd\u60dc\u81ea\u5df1\u7684\u4e8b\u696d\u9ad8\u5cf0\u671f\n\n# \u8207\u5176\u5e6b\u516c\u53f8\u8001\u95c6\u8acb\u4eba\uff0c\u4e0d\u5982\u5e6b\u81ea\u5df1\u8acb\u4eba\uff1f\n# \u6709\u6c92\u6709\u60f3\u904e\u6709\u4e00\u500b\u884c\u696d\u662f\u53ef\u4ee5\u900f\u904e\"\u62db\u52df\"\u53bb\u9577\u4e45\u6301\u7e8c\u767c\u5c55\uff1f\n\nACT Company \u70ba\u5b8f\u5229\u4fdd\u96aa\u5718\u968a\uff0c\u65bc2015\u5e749\u6708\u6210\u7acb\u4ee5\u4f86\uff0c\u5feb\u901f\u6210\u70ba\u5b8f\u5229\u6700\u6709\u8ca2\u737b\uff0c\u6700\u6709\u50f9\u503c\u7684\u5718\u968a\u3002\u5982\u679c\u4f60\u71b1\u5fc3\u8ffd\u6c42\u5353\uff0c\u5c0d\u7406\u8ca1\u7b56\u5283\u884c\u696d\u5145\u6eff\u71b1\u8aa0\uff0c\u8acb\u7acb\u5373\u52a0\u5165ACT\u00a0\u7406\u8ca1\u7b56\u5283\u5718\u968a\uff0c\u5be6\u73fe\u5c08\u696d\u767c\u5c55\u8def\u5411\uff0c\u6210\u5c31\u7406\u60f3\u524d\u7a0b\u3002\n\n______________________________________________________________________________\n\nRecruiting Manager \u62db\u52df\u7d93\u7406 X Wealth Management \u8ca1\u5bcc\u7ba1\u7406\n\n\n\u5168\u884c\u7368\u6709 \u7ba1\u7406\u734e\u91d140%\u00a0\u00a0\n\n\n\u53e6\u4eab\u6709\u5e95\u85aaHKD 13,000\uff0f\u6708\u00a0\u00a0\u6216\u904e\u4f4f\u6708\u85aa\u00a080%\u00a0\u00a0*\u00a0\n\u53e6\u52a0 50%\u00a0\u4f63\u91d1\u00a0Commission\u00a0\u00a0Rate\u00a0/\u00a0\u00a0\u6bcf\u5f35\u55ae\u8a08\n\u5e73\u5747\u6708\u85aa\u53ef\u9054 HKD 30,000 - 88,000 \u6216\u66f4\u591a\n\u4e0d\u8a2d\u4efb\u4f55\u696d\u7e3e\u58d3\u529b\n\n______________________________________________________________________________\n\n\u4e00\u76f4\u4ee5\u4f86\u884c\u696d\u5546\u6a5f\u8655\u8655\uff0c\u52a0\u4e0a\u653f\u5e9c\u5927\u529b\u63a8\u52d5\uff0c\u4e09\u5927\u6700\u71b1\u9580\u5546\u6a5f1\uff09\u81ea\u9858\u6027\u91ab\u4fdd\u00a02\uff09\u6263\u7a05\u5e74\u91d1\u00a03\uff09\u5f37\u7a4d\u91d1\u534a\u81ea\u7531\u884c\u00a0\u4ee4\u6211\u5011\u7684\u5ba2\u6e90\u51fa\u73fe\u4f9b\u4e0d\u61c9\u6c42\u7684\u60c5\u6033\uff0c\u4e00\u5929\u8207\u773e\u591a\u5ba2\u6236\u6703\u9762\u4ee4\u540c\u4e8b\u611f\u5230\u5403\u529b\uff0c\u9867\u6b64\u6211\u5011\u9577\u9060\u4e5f\u9700\u8981\u6025\u589e\u524d\u7dda\u4eba\u624b\uff0c\u70ba\u4e86\u4ee4\u516c\u53f8\u8acb\u4eba\u66f4\u6709\u7cfb\u7d71\uff0c\u4ee5\u53ca\u57f9\u990a\u66f4\u591a\u4eba\u624d\uff0c\u672c\u516c\u53f8\u73fe\u6b63\u62db\u52df\u00a0\n\nRecruitment X Wealth Management\u00a0\u7279\u5225\u6b61\u8fce\u540c\u884c\u62db\u52df\u6216\u6709\u7d93\u9a57\u4eba\u58eb\n\n\u5de5\u4f5c\u7bc4\u7587\uff1a\n\n\u8ca0\u8cac\u5354\u52a9\u516c\u53f8\u62db\u52df\uff0f\u8acb\u4eba\uff0f\u9762\u8a66\n\u5354\u52a9\u968a\u54e1\u8ddf\u9032\u6bcf\u65e5\u9032\u5ea6\n\u63d0\u4f9b\u57f9\u8a13\uff0c\u52a0\u5f37\u968a\u54e1\u92b7\u552e\u80fd\u529b\uff0c\u7522\u54c1\u77e5\u8b58\n\u6703\u6709\u7d93\u7406\u57f9\u8a13\u8ab2\u7a0b\u63d0\u4f9b\n\u4ea6\u9700\u8981\u898b\u5ba2\uff0c\u70ba\u5ba2\u6236\u63d0\u4f9b\u7406\u8ca1\u7522\u54c1\u670d\u52d9\n\n\u798f\u5229\uff1a\n\n\u5e95\u85aaHKD$13,000 - 30,000\u00a0(\u8996\u4e4e\u904e\u4f4f\u7d93\u9a57\uff09\n\u53e6\u4eab\u8c50\u539a\u4f63\u91d1\uff0c\u6bcf\u6708\u734e\u91d1\u53ca\u5e74\u5c3e\u82b1\u7d05\n\u4e0d\u5b9a\u6642\u6709\u61c9\u5fb5\u8005\u63d0\u4f9b\uff0c\u9577\u9060\u5efa\u7acb\u88ab\u52d5\u6536\u5165\n\u5718\u968a\u6709Cold Market\u00a0\u63fe\u5ba2\u7cfb\u7d71\u4f5c\u652f\u63f4\n\u5c08\u5c6c\u5168\u65b9\u4f4d\u6709\u6548\u57f9\u8a13\n\u5728\u8077\u92b7\u552e\u53ca\u7522\u54c1\u57f9\u8a13\n\u516c\u5e73\u6649\u5347\u5236\u5ea6\n\u4e0d\u8a2d\u4efb\u4f55\u696d\u7e3e\u58d3\u529b\n\u89c0\u5858\u7532\u7d1a\u5546\u5834\u5beb\u5b57\u6a13\u5de5\u4f5c\n\u5730\u65b9\u5bec\u8eba\uff0c\u64c1\u6709\u8212\u9069\u4f11\u606f\u7a7a\u9593\n\u6642\u9593\u81ea\u4e3b\uff0c\u81ea\u6211\u5b89\u6392\u653e\u5047\u6642\u9593\uff0c\u4e0d\u8a2d\u5927\u5047\u65e5\u6578\n\u65c5\u884c\u734e\u8cde\uff0c\u5982\u9054\u6a19\u8005\u53ef\u4ee5\u4e00\u5e74\u53bb\u4e00\u6b21\u4e9e\u6d32\u8207\u6b50\u6d32\uff08\u6a5f\u7968\uff0b\u9152\u5e97)\u00a0\n\n\u8981\u6c42\uff1a\n\n\u4e2d\u4e94\u7562\u696d\u53ca\u4e94\u79d1\u5408\u683c\n\u6709\u826f\u597d\u7684\u4eba\u969b\u95dc\u4fc2\uff0c\u597d\u52d5\uff0c\u6709\u5275\u610f\uff0c\u611b\u8207\u4eba\u4ea4\u969b\n\u611b\u6e9d\u901a\uff0c\u4e3b\u52d5\uff0c\u6562\u65bc\u63a5\u53d7\u6311\u6230\n\u7d93\u9a57\u4e0d\u62d8\uff0c\u6b61\u8fce\u7562\u696d\u5927\u5b78\u751f\n\n*******\u6709\u610f\u8005\u8acb\u7acb\u523b\u9ede\u64caApply Now\u4ee5\u5b89\u6392\u9762\u8a66\u00a0**********", "employment_types": ["Full Time", "Permanent", "Contract"], "selling_points": ["\u6b61\u8fce\u6562\u640f\u3001\u5e74\u8f15\u3001\u6709\u6d3b\u529b", "\u5be6\u73fe\u7406\u60f3\u4e8b\u696d", "\u6642\u9593\u81ea\u4e3b\uff0c\u62db\u52df\u6210\u5c31\u4e8b\u696d\uff01"], "locations": ["Kwun Tong"], "categories": ["Admin & HR", "HR Director / Manager", "Sales, CS & Business Devpt", "Sales - Sales Management", "Banking / Finance", "Wealth Management"], "post_time": "2022-01-11T00:52:23Z", "salary": {"currency": "HKD", "max": 89999, "min": 30000, "period": "monthly", "term": null}, "salary_visible": true, "title_keywords": ["wealth management", "manager", "\u8ca1\u5bcc\u7ba1\u7406"], "responsibilities": ["management", "recruitment"], "requirements": {"degrees": [], "majors": [], "languages": [], "language_level": [], "hard_skills": [], "soft_skills": [], "languages_combined": []}, "experience_required": {"duration": [], "field": []}}, {"job_id": "100003009032565", "location_code": "hk", "company": "MEDICUS HK LTD", "job_title": "Assistant Account and HR Manager/ Account and HR Manager (5 days work)", "description": "Job Description\n\nRESPONSIBILITIES:\n\nReporting to Directors;\nHandle full set of accounts and financial reports;\nPrepare monthly management reports;\nSupport annual audit;\nLiaise with auditors, bankers, supplier and other parties related to account\nProvide full spectrum of HR functions, including but not limited to recruitment, payroll calculation, MPF, annual tax filing;\nAble to lead a small team\nPerform ad-hoc assignment as required\n\n\u00a0REQUIREMENTS:\n\n\nVTC (IVE) accounting high diploma /Degree / in Finance, HR Management or relevant disciplines\nMin 5 years of\u00a0relevant experience; working experience in trading and manufacturing industry is definitely an advantage;\u00a0more\u00a0experience will be considered as\u00a0Account and HR Manager\n\u00a0Familiar with MYOB is highly preferred;\n\u00a0Proficient in Microsoft Office; good command in English and Mandarin;\n\u00a0Able to work independently with a strong sense of responsibility;\u00a0self-motivation and able to meet tight schedules;\n\u00a0May need to travel to mainland China\n\u00a0Immediate available is preferred\n\n\n\nWe offer attractive remuneration package to the right candidate:\n\n\u00a0\u00a0\u00a0\u00a0\u00a0\u00a0\u00a0\u00a0 5-day work week and bank holiday\n\u00a0\u00a0\u00a0\u00a0\u00a0\u00a0\u00a0\u00a0 Company medical scheme\n\u00a0\u00a0\u00a0\u00a0\u00a0\u00a0\u00a0\u00a0 Incentive bonus\n\u00a0\u00a0\u00a0\u00a0\u00a0\u00a0\u00a0\u00a0 Annual leave\n\u00a0\u00a0\u00a0\u00a0\u00a0\u00a0\u00a0\u00a0 Birthday leave\n\u00a0\u00a0\u00a0\u00a0\u00a0\u00a0\u00a0\u00a0 Staff purchase discount\n\nNear Lai Chi Kok MTR Station\n\nFor interested applicants, please click 'Apply Now' and send your detailed resume with current / last and expected salary\u00a0\n", "employment_types": ["Full Time"], "selling_points": [], "locations": ["Lai Chi Kok"], "categories": ["Accounting", "Finance / Accounting Manager", "Admin & HR", "Administration / Operation Manager", "HR Director / Manager"], "post_time": "2022-01-07T11:49:44Z", "salary": {"currency": null, "max": null, "min": null, "period": "monthly", "term": null}, "salary_visible": false, "title_keywords": ["hr manager", "assistant"], "responsibilities": ["ad-hoc", "reporting", "financial reports", "mpf", "annual audit", "hr", "full set of accounts", "tax filing", "lead a small team", "management reports", "recruitment", "liaise with", "payroll"], "requirements": {"degrees": ["high diploma", "degree"], "majors": ["finance", "accounting"], "languages": ["english", "mandarin"], "language_level": ["good command"], "hard_skills": ["myob", "microsoft office"], "soft_skills": ["meet tight schedules", "work independently", "self-motivation", "sense of responsibility"], "languages_combined": [{"language": "english", "language_level": ["good command"]}, {"language": "mandarin", "language_level": ["good command"]}]}, "experience_required": {"duration": ["min 5 years"], "field": ["hr", "manufacturing industry", "relevant experience", "trading"]}}, {"job_id": "100003009026663", "location_code": "hk", "company": "ProSavvy Services Company", "job_title": "HR & Admin Manager", "description": "Our client, a HK listed organization is looking for an experienced caliber to fill in the following position:\n\nHR & ADMIN MANAGER\u00a0\n\nResponsibilities:\u00a0\n\nProvide full spectrum of human resources and office administration support;\nProvide comprehensive HR services including recruitment, compensation & benefits, performance management, PRC\u00a0social benefits, salaries tax, staff case handling;\nTo dictate HR & Admin policy and procedure;\nPrepare HR and Admin analysis report periodically;\nEnsure HR functions in compliance with Hong Kong Labour Ordinance and China local regulations;\nHandling cases relating to labor issues if necessary;\nResponsible for administrative duties such as general office administration, procurements and maintenance of office equipment and supplies and insurance etc,;\nAssist in ad-hoc projects as required.\n\nRequirements:\u00a0\n\nDegree in human resources management, business administration or related disciplines;\nAt least\u00a010-15 years or above experience in HR & Admin field of which min 5 years in managerial level;\nWell versed in Hong Kong employment Ordinance and PRC Labour Laws\nGood numerical sense, excellent data interpretation and analytical skills;\nTarget oriented, self-motivated, hardworking, proactive, able to work independent and meeting assigned timeline;\nExcellent communication & interpersonal skills.\nGood\u00a0command of both oral and written English and Chinese\n\n\u00a05 days work.\u00a0Interested candidates, please send your FULL RESUME in WORD FORMAT by clicking 'Apply Button\u201d now.\n\nAll data shall be treated as strict confidence, and solely used for recruitment purpose", "employment_types": ["Full Time", "Permanent"], "selling_points": ["Degree in HRM or related discipline", "Min 10-15 yrs in HR & Admin functions", "Well versed in HK & China Labor ordinance"], "locations": ["Not Specified"], "categories": ["Admin & HR", "Administration / Operation Manager", "HR Director / Manager", "HR Supporting Staff"], "post_time": "2022-01-06T08:28:14Z", "salary": {"currency": null, "max": null, "min": null, "period": "monthly", "term": null}, "salary_visible": false, "title_keywords": ["hr", "admin", "manager"], "responsibilities": ["tax", "regulations", "management", "office administration support", "analysis report", "office administration", "hr", "compliance", "maintenance of office equipment", "recruitment", "administrative duties", "ad-hoc projects", "insurance"], "requirements": {"degrees": ["degree"], "majors": ["related disciplines", "business administration"], "languages": ["english", "chinese"], "language_level": ["good command"], "hard_skills": ["hong kong employment ordinance", "analytical skills"], "soft_skills": ["self-motivated", "oral", "independent", "analytical skills", "communication", "interpersonal skills", "proactive", "hardworking"], "languages_combined": [{"language": "english", "language_level": ["good command"]}, {"language": "chinese", "language_level": ["good command"]}]}, "experience_required": {"duration": ["at least 10-15 years", "min 5 years"], "field": ["managerial", "hr", "admin"]}}, {"job_id": "100003009020069", "location_code": "hk", "company": "Wai Ji Christian Service", "job_title": "Human Resources & Administration Manager", "description": "(Vacancy Code: HRAM/HO/20220114/1)\n\nRequirements\n\n\n\n(a) A recognized degree in business management or related discipline, preferably in Human Resources Management;\n\n(b) Not less than 8 years of proven all-round HR working experience including payroll processing, fringe benefit / retirement scheme administration and human resources information system management, with at least 4 years in managerial/supervisory position;\n\n(c) Familiar with Employment Ordinance and other relevant legislative requirements;\n\n(d) Strong team building mindset and excellent communications and interpersonal skills;\n\n(e) Previous working experience in NGO or similar setting is an advantage;\n\n(f) Potential candidate without the required experience will be considered for a post of lower rank.\n\nResponsibilities\n\n\n\n(1) Report to the Head of Administration and lead a small team of staff to carry out all-round HR duties with focus on payroll processing, fringe benefit and retirement scheme administration, human resources information system management, staff administration, etc.\n\n(2) To ensure the Agency\u2019s daily HR operations and practices are carried out in compliance with relevant legislative requirements;\n\n(3) To assist in the design and review of HR policies, internal HR procedures and practices, and closely monitor the execution of policies;\n\n(4) To collaborate with internal departments and service units on daily HR operation and provide professional HR advice and assistance to users whenever necessary;\n\n(5) To perform other HR and administration duties assigned as required.\n\n\n\n\nClosing date: 14 January 2022\n\n\n\nInterested parties please complete the application form (HRS20) [available on our website http://www.wjcs.org.hk] and send together with a full resume to Human Resources Department, 9-15, G/F, Tung Hoi House, Tai Hang Tung Estate, Shek Kip Mei, Kowloon in a sealed envelope marked \u201cConfidential - Application for Human Resources & Administration Manager Post\u201d with the job reference code or by clicking \"APPLY NOW\".\n\nThe information supplied will be kept in strictest confidence and used for recruitment purposes only.\u00a0\n\nApplicants\u2019 personal data will be destroyed within three months' time.\n\n\u00a0WJCS is an EQUAL OPPORTUNITIES EMPLOYER", "employment_types": ["Full Time", "Contract"], "selling_points": [], "locations": ["Sham Shui Po"], "categories": ["Admin & HR", "Administration / Operation Manager", "Compensation & Benefits", "HR Director / Manager"], "post_time": "2022-01-05T01:17:33Z", "salary": {"currency": null, "max": null, "min": null, "period": "monthly", "term": null}, "salary_visible": false, "title_keywords": ["administration manager", "human resources"], "responsibilities": ["collaborate with", "management", "operations", "lead a small team", "hr", "compliance", "hr duties", "design", "review", "policies", "procedures", "monitor", "report", "payroll", "administration"], "requirements": {"degrees": ["degree"], "majors": ["business"], "languages": [], "language_level": [], "hard_skills": ["business management", "information system", "scheme", "c", "processing"], "soft_skills": ["interpersonal skills"], "languages_combined": []}, "experience_required": {"duration": ["at least 4 years", "8 years"], "field": ["managerial", "management", "supervisory", "hr", "payroll", "human resources", "administration"]}}, {"job_id": "100003009025461", "location_code": "hk", "company": "Manpower Services (Hong Kong) Limited", "job_title": "Human Resources/RPO Lead", "description": "Manpower is a world leader in the employment services industry, creating and delivering services that enable its clients to win in the changing world of work. \u00a0We are looking for an ambitious and outstanding individual with track record of success in recruitment to join our team.\n\nJob Duties:\n\nManage the end to end recruitment cycle for the client\nEnsure all deadlines are met and monitor the overall recruitment progress\nCollect requirements from the Business and HR\nWork with the Business and HR on designing and executing effective sourcing strategies and campaigns to attract and hire talents that fits with job specifications, such as job posting portal, LinkedIn, video shooting, promotion leaflets, and etc.\nParticipate in the career fair and other recruitment related activities\nConduct panel interviews with the Business and HR\nExtend offers to candidates and work with RPO recruiters to conduct reference check (employment, educational, and professional certificates)\nHold a weekly meeting with the RPO recruiters on recruitment progress update\nAttend Bi-weekly/monthly meeting with the HR Department on recruitment progress update\n\nRequirements:\u00a0\n\nDegree Holder or above in HR Management or related disciplines\n3-5 years of solid experience in HR, candidate with agency background\u00a0will be an advantage\nStrong ability to priorities workload and able to work under multi-tasking\nIndependent, detail-minded, proactive, flexible, well-organize, positive attitude\nExcellent communication and international skills\nExcellent written and verbal communication skill in all English, Cantonese and Mandarin\nImmediate available is highly preferred\n\nFor interested parties, please send your full\u00a0resume to gladys.ma@manpowergrc.hk.", "employment_types": ["Contract"], "selling_points": ["perform end to end HR excercise", "good exposure", "5 days work"], "locations": ["Causeway Bay"], "categories": ["Admin & HR", "HR Director / Manager", "Recruitment / Executive Search"], "post_time": "2022-01-06T04:35:56Z", "salary": {"currency": null, "max": null, "min": null, "period": "monthly", "term": null}, "salary_visible": false, "title_keywords": ["lead", "human resources"], "responsibilities": ["monitor", "recruitment"], "requirements": {"degrees": ["degree holder"], "majors": ["related disciplines"], "languages": ["cantonese", "english", "mandarin"], "language_level": ["excellent"], "hard_skills": ["bi"], "soft_skills": ["detail-minded", "flexible", "independent", "communication skill", "positive attitude", "communication", "multi-tasking", "proactive"], "languages_combined": [{"language": "cantonese", "language_level": ["excellent"]}, {"language": "english", "language_level": ["excellent"]}, {"language": "mandarin", "language_level": ["excellent"]}]}, "experience_required": {"duration": ["3-5 years"], "field": ["agency", "hr"]}}, {"job_id": "100003009032448", "location_code": "hk", "company": "Michael Page", "job_title": "HR Manager for Leading Educational Institute", "description": "As a HR Manager of an educational institute, this position will act as a central pillar for the organisation's operation and support organisational employees. Be part of the leadership team and act as a key member in driving company's success.\n\nClient Details\n\nOur client is a well-established and highly respected educational company with many educational institutes spread across Asia, Europe, Latin America and Middle East. Currently they are seeking an experience HR specialist to oversee their HR functions for a particular educational institute in Hong Kong.\n\nDescription\n\nKey responsibilities include but are not limited to:\n\nProvide full spectrum HR operational support to the organisation\nManage end-end recruitment process including, including drafting job posts and liaising with external vendors\nAssist with new joiners orientation program\nReview and develop HR systems, processes, and practices for operational efficiency\nAdminister payroll, MPF and tax in a timely manner\nPlan, review and manage the budget to achieve organisation's business objective\nEnsure timely updates of the Staff Handbook and in compliance with legal and regulatory requirements\nBe the lead for training projects and assist with\nManage Covid test results, vaccination leave and records\nBe the point of contact for all emloyees for HR related questions\nOther ad hoc projects as assigned\n\nProfile\n\nDegree holder in Human Resources, Business Administration Management, or relevant discipline\nMinimum 5 years of relevant work experience; ideally in an educational institutes or health care sector\nWell versed in Hong Kong Employment Ordinance and Labour Department requirements\nCustomer oriented and a professional approach to internal and external stakeholders always\nGood command of both written and spoken English\nTime management and prioritization\nStrategic mindset with a hand-on approach\nSelf-motivated with good sense of responsibility\n\nJob Offer\n\nPermanent work opportunity\nStable working environment\nConvenient working location\n5 day work week\nStable working hours\nDiscretionary Bonus\n\nTo apply online please click the 'Apply' button below. For a confidential discussion about this role please contact Sarah Wong on +852 2848 4773.", "employment_types": ["Full Time", "Permanent"], "selling_points": ["All rounded position", "Stable organization", "Good working hours"], "locations": ["Not Specified"], "categories": ["Admin & HR", "Administration / Operation Manager", "Compensation & Benefits", "HR Director / Manager"], "post_time": "2022-01-07T11:08:45Z", "salary": {"currency": null, "max": null, "min": null, "period": "monthly", "term": null}, "salary_visible": false, "title_keywords": ["hr manager"], "responsibilities": ["operational support", "regulatory requirements", "budget", "plan", "administration", "compliance", "liaising with", "develop", "management", "mpf", "review", "contact", "recruitment process", "payroll", "tax", "hr", "systems", "a timely manner", "ad hoc projects"], "requirements": {"degrees": ["degree holder"], "majors": ["business administration"], "languages": ["english"], "language_level": ["good command"], "hard_skills": ["hong kong employment ordinance"], "soft_skills": ["self-motivated", "sense of responsibility", "timely", "organisation", "stable", "time management", "leadership"], "languages_combined": [{"language": "english", "language_level": ["good command"]}]}, "experience_required": {"duration": ["minimum 5 years"], "field": ["hr"]}}, {"job_id": "100003009036957", "location_code": "hk", "company": "Hong Kong Technology Venture Company Limited", "job_title": "Senior Specialist - Learning & Development", "description": "What You Will Be Doing\n\nDevelop and implement L&D initiatives plan to achieve company objectives\nTake the initiatives and be the key person to facilitate Training Need Analysis, conduct course design and organize training or other educational manual and materials\nBe the pioneer on new flow roll out and provide the most suitable training for all end user\nSet-up and maintenance of training records and documentation\nPrepare and update all training material regularly\nEvaluate staff performance and the effectiveness, providing recommendations for improvement\nOversee the overall program runs and responsible for all end user training needs\nWork closely with L&D team to ensure timely and effective services\nSupport special of ad hoc projects\n\nWho is our Right Fit\n\nDegree Holder in any discipline\n3 to 5 years of hands-on experience in field coaching and training. Experiences in call center/customer service /retail /e-commerce/logistic industry is a plus\nMature and confident to work with different cultures and all levels of staff\nHands-on experience in program design and delivery\nFamiliar with Microsoft office applications and presentation software\nProven competencies in organization development and knowledge management would be desirable\nExcellent communication skills and writing skills in English, Cantonese and Mandarin are essential\nExcellent service manner, independent, self-motivated, detailed-minded and willing to work under pressure", "employment_types": ["Full Time", "Permanent"], "selling_points": ["Develop and implement L&D initiatives plan", "Degree Holder in any discipline", "Dynamic environment"], "locations": ["Tseung Kwan O"], "categories": ["Admin & HR", "HR Director / Manager", "Recruitment / Executive Search", "Training & Development"], "post_time": "2022-01-11T01:00:00Z", "salary": {"currency": null, "max": null, "min": null, "period": "monthly", "term": null}, "salary_visible": false, "title_keywords": ["senior specialist"], "responsibilities": ["management", "software", "maintenance", "analysis", "design", "develop", "evaluate", "communication", "customer service", "ad hoc projects", "plan", "documentation", "work under pressure"], "requirements": {"degrees": ["degree holder"], "majors": [], "languages": ["cantonese", "english", "mandarin"], "language_level": ["excellent"], "hard_skills": ["plus", "maintenance", "e-commerce", "microsoft office", "analysis", "writing skills", "documentation"], "soft_skills": ["confident", "communication skills", "self-motivated", "independent", "responsible", "work under pressure", "timely", "mature", "writing skills", "hands-on", "customer service", "presentation", "detailed"], "languages_combined": [{"language": "cantonese", "language_level": ["excellent"]}, {"language": "english", "language_level": ["excellent"]}, {"language": "mandarin", "language_level": ["excellent"]}]}, "experience_required": {"duration": ["3 to 5 years"], "field": ["call center", "training", "e-commerce", "design", "customer service", "retail"]}}, {"job_id": "100003009036188", "location_code": "hk", "company": "Randstad Hong Kong Limited", "job_title": "Global Talent Acquisition Lead (FinTech Unicorn)", "description": "about the company.\n\nMy client is a FinTech unicorn providing wide range of financial service & products for both corporate and individual clients. With the business growth, they are looking for a seasoned TA lead for their global expansion.\nabout the team.\nThis role reports to the head of TA and is going to lead a team of 2-3hc.\nabout the job.\nTake the ownership & lead the TA team for the whole recruitment activities in a timely manner and with hight quality, including budget planning, attract and source talents, define job descriptions with managers, understand business needs and market trends, manage hiring processes in the system, screen CVs, conduct phone and in-person interviews, analytics etc.\nImplement effective sourcing tools, develop & expand various recruiting channels.\nActively connect with potential talents as a pipeline for the future, and stay connected to with candidates\nGenerate comp & ben benchmarks\nWork closely with hiring managers (globally) to ensure a fast & efficient recruiting process, and advise on profiles, companies to target from etc.\nskills & experiences required.\n3+ years of regional/ global hiring experience in fintech/ trading firms\nExperience leading recruiting for technology/ Quant hirings (HFT, EMM trading positions) and to global markets\nProven experience with sourcing methods and skills\nMulti-tasking abilities and ability to work in a dynamic environment and a fast growing company\nAble to manage multiple priorities in a highly dynamic environment\nCreative, open minded and detail oriented\nFluent English (written and spoken)", "employment_types": ["Full Time", "Permanent"], "selling_points": [], "locations": ["Not Specified"], "categories": ["Admin & HR", "HR Director / Manager", "Recruitment / Executive Search"], "post_time": "2022-01-10T09:36:17Z", "salary": {"currency": null, "max": null, "min": null, "period": "monthly", "term": null}, "salary_visible": false, "title_keywords": ["lead"], "responsibilities": ["budget planning", "a timely manner", "quality", "develop", "lead a team", "recruitment", "reports"], "requirements": {"degrees": [], "majors": [], "languages": ["english"], "language_level": ["fluent"], "hard_skills": ["dynamic"], "soft_skills": ["efficient", "dynamic environment", "timely", "detail oriented", "multi-tasking", "open minded", "creative"], "languages_combined": [{"language": "english", "language_level": ["fluent"]}]}, "experience_required": {"duration": ["3+ years"], "field": ["trading"]}}, {"job_id": "100003009021464", "location_code": "hk", "company": "The Hong Kong Society for Rehabilitation", "job_title": "Deputy Manager (Human Resources) (Ref: DM(HR)_HQ_JAN22)", "description": "Perform full spectrum of HR functions with a focus on compensation and benefits.\nSupport compensation and benefits programs, including annual salary review, market benchmark, benefits review, job evaluation and staff cost budget\nSupervise a small team to monitor and manage payroll activities to ensure accurate and timely delivery of payroll services\nPrepare and compile HR\u00a0statistical and management reports\nAssist in reviewing, formulating and implementing of HR policies, procedures and workflow\nOther ad-hoc projects/duties as assigned by reporting supervisor\n\nRequirements:\n\nDegree holder in Human Resources Management or related field\nAt least 5 years in Human Resources functions in which 3 years in supervisory level\nHands on experience in Payroll and HRIS system management and administration\nExcellent command of MS Office application, especially Excel\nWell-versed in Employment Ordinance, MPF regulations, Hong Kong taxation ordinances and other related legislations\nExcellent communication and interpersonal skills and detail-minded, open-minded, customer orientated\nProficiency in both Chinese and English language with good writing skills\n\nWork Location: Lam Tin\n\nCandidate with more experience may be considered as Manager (Human Resources)\n\n(Shortlisted candidates will be invited for a written test.) Interested parties please send your full resume with reference code, present and expected salary by clicking \"Apply Now\" on or before 19 January 2022.\n\nHKSR is an equal opportunity employer\n\u00a0(Data held by HKSR relating to employment applications will be kept confidential and used only for processing applications)", "employment_types": ["Full Time", "Contract"], "selling_points": [], "locations": ["Kwun Tong Area"], "categories": ["Admin & HR", "Administration / Operation Manager", "Compensation & Benefits", "HR Director / Manager"], "post_time": "2022-01-05T04:03:33Z", "salary": {"currency": null, "max": null, "min": null, "period": "monthly", "term": null}, "salary_visible": false, "title_keywords": ["deputy manager", "human resources"], "responsibilities": [], "requirements": {"degrees": [], "majors": [], "languages": [], "language_level": [], "hard_skills": [], "soft_skills": [], "languages_combined": []}, "experience_required": {"duration": [], "field": []}}, {"job_id": "100003009024669", "location_code": "hk", "company": "RecruitPRO Consultancy Hong Kong Limited", "job_title": "(Senior) Human Resources Manager - 5 days, sizable MNC", "description": "Senior Human Resources Manager (all-round), 5 days\n\n\n(Less experienced candidates will be considered as HR Manager)\n\nSalary range : 45-60K . please must write down your last 3 jobs salary for record.\u00a0\n\u00a0\n\n\u00a0Duties:\n\n\nResponsible for all round daily operation of HR & Admin job duties.\nReport to CEO/ CFO\n\nRequirements:\n\nDegree or above in HRM or any other related disciplines\n\nAt least 10 years solid working experience in HR of listed company or MNC sizable companies, it is an advantage, but not a must.\u00a0\n\nAll round HR duties\n\nLead a small team of HR and admin dept\nGood interpersonal skills\nFluent in spoken and written of Chinese and English\n\n\nPlease send CV to:\u00a0 \u00a0 \u00a0applyexe @recruitpro662.com\n\n\nFor Job Seekers, who prefer to directly sent your CV to us, our job seekers directly apply email address is posted in our company profile above.\n\n\n\u00a0Please kindly send your CV in WORD format ONLY\u00a0with:\n\nCURRENT and EXPECTED SALARY\nAVAILABILITY\nJOB TITLE in your EMAIL SUBJECT\n\n\nThank you for your application!", "employment_types": ["Full Time", "Permanent"], "selling_points": [], "locations": ["Central & Western Area"], "categories": ["Admin & HR", "Compensation & Benefits", "HR Director / Manager", "Training & Development"], "post_time": "2022-01-06T02:07:37Z", "salary": {"currency": "HKD", "max": 69999, "min": 45000, "period": "monthly", "term": null}, "salary_visible": true, "title_keywords": ["manager", "human resources"], "responsibilities": ["hr", "daily operation", "report"], "requirements": {"degrees": ["degree or above"], "majors": ["related disciplines"], "languages": ["english", "chinese"], "language_level": ["fluent"], "hard_skills": ["small", "sizable companies", "word"], "soft_skills": ["interpersonal skills"], "languages_combined": [{"language": "english", "language_level": ["fluent"]}, {"language": "chinese", "language_level": ["fluent"]}]}, "experience_required": {"duration": ["at least 10 years"], "field": ["hr", "it"]}}, {"job_id": "100003009023705", "location_code": "hk", "company": "Cathay Pacific Catering Services (H.K.) Limited", "job_title": "People Manager", "description": "Responsibilities\n\nLead a team to provide a full range of professional HR services including but not limited to manpower planning and budgeting, staff and retention, performance management, succession planning, and staff relations\nImplement HR strategy and review related policies and procedures in alignment with the organization\u2019s direction and legislation requirements\nManage full recruitment cycle to cater for manpower needs. Engage different departments to drive flexible workforce design & planning, to project talent requirements, along with the execution of staffing plan to bring in the right talents\nManage payroll administration procedures with line departments and maintain HRMS in ensuring efficiency and accuracy\nDevelop reward system to ensure market competitiveness of the Company\u2019s C&B policies and programmes\nInculcate a performance-driven culture and work on HR projects to introduce incentive & bonus schemes and benefits programmes, salary benchmarking to retain talents\nDevelop HR dashboard and management report for enhancing employee performance and HR data analytics\nMonitor the service and quality of staff canteen and organize staff activities to enhance employee engagement and experience\nRequirements\n\nDegree holder preferably in Business Administration, Human Resources Management or Social Sciences\nAt least 10 years related working experience including 5 years in the supervisory/ managerial level\nPreferably with hands-on experience in management training, HRIS implementation and payroll administration\nWell-versed in the Employment Ordinance and other Human Resources related regulations in Hong Kong\nSolid Compensation & benefits work experience in sizeable business\nExcellent command in written and spoken English and Chinese\nStrong analytical, problem-solving and communication skills\nWell organized, meticulous, and is good at multitasking\nProficiency in MS Office applications\nWe offer a competitive remuneration package and a full range of benefits.\u00a0 Interested parties please send your resume with your current and expected salary\u00a0via post or email to our Head of People or by clicking the \"Apply Now\" button\u00a0on or before 4 February 2022.\n\nPost:11 Catering Road East, Hong Kong International Airport, Lantau, Hong Kong\u00a0\n\nPersonal data collected will be treated in the strictest confidence and only be used for recruitment-related purposes. Applicants who do not receive notification for an interview within six weeks may consider their application unsuccessful.", "employment_types": ["Full Time", "Permanent"], "selling_points": ["HR business partner", "At least 10 years related experience", "Career advancement opportunities"], "locations": ["Airport Area"], "categories": ["Admin & HR", "Compensation & Benefits", "HR Director / Manager", "HR Supporting Staff"], "post_time": "2022-01-05T09:32:25Z", "salary": {"currency": null, "max": null, "min": null, "period": "monthly", "term": null}, "salary_visible": false, "title_keywords": ["manager"], "responsibilities": ["data", "budgeting", "quality", "design", "maintain", "plan", "monitor", "develop", "management report", "management", "review", "procedures", "payroll", "policies", "hr", "administration procedures", "lead a team", "recruitment", "planning"], "requirements": {"degrees": ["degree holder"], "majors": ["business administration", "social sciences"], "languages": [], "language_level": [], "hard_skills": [], "soft_skills": ["hands-on"], "languages_combined": []}, "experience_required": {"duration": ["at least 10 years", "5 years"], "field": ["managerial", "supervisory", "management", "training", "related", "payroll", "administration"]}}, {"job_id": "100003009026218", "location_code": "hk", "company": "Robert Walters (HK)", "job_title": "Senior HR Business Partner | Conglomeration", "description": "Due to the team expansion, our top tier conglomerate client is currently looking for a senior HR business partner to provide out-standing HR consultation to designated portfolio and business stakeholders. It is a key member of a sizeable and established HR team!\n\nAbout the role\n\nReport directly to Director of HRBP and work closely with executive leaders\nPartner with COE team to provide HR business partnering service in support of business growth\nHandle the full employee life-cycle including employee relations, performance management, talent development, compensation review, and etc\nProvide insights in talent management & development to ensure succession planning for key positions\nPropose solution or advise to business leaders or management group based on internal HR data analysis\nImplement and support HR projects including transformation, employee engagement survey, learning projects, reward project, or internal communication etc.\n\n\nAbout the person\n\nDegree holder in HR Management or related disciplines\nMinimum 10 years of HR experience with multinational organisation, with strong background as business partner or all rounded generalist\nStrong interpersonal and communication skills that enhance effectiveness with all levels of people\nWilling to roll up the sleeves and work independently\nExcellent spoken and written English and Chinese\n\n** Less experienced candidate could be considered as HR Business Partner position.", "employment_types": ["Full Time", "Permanent"], "selling_points": ["Large conglomerate platform", "Prime work location with flexi work arrangement", "Attractive remuneration & benefits"], "locations": ["Not Specified"], "categories": ["Admin & HR", "HR Director / Manager"], "post_time": "2022-01-06T07:39:32Z", "salary": {"currency": null, "max": null, "min": null, "period": "monthly", "term": null}, "salary_visible": false, "title_keywords": ["hr"], "responsibilities": ["provide insights", "management", "hr", "review", "data analysis", "communication", "planning", "report"], "requirements": {"degrees": ["degree holder"], "majors": ["related disciplines"], "languages": ["english", "chinese"], "language_level": ["excellent"], "hard_skills": ["analysis"], "soft_skills": ["communication skills", "work independently", "communication", "learning", "organisation", "interpersonal"], "languages_combined": [{"language": "english", "language_level": ["excellent"]}, {"language": "chinese", "language_level": ["excellent"]}]}, "experience_required": {"duration": ["minimum 10 years"], "field": ["hr", "business partner"]}}, {"job_id": "100003009025158", "location_code": "hk", "company": "Apex Logistics International (HK) Limited", "job_title": "Assistant Human Resources Manager", "description": "Responsibilities:\n\nAct as a business partner with a focus on staffing, recruiting and manpower planning, employee engagement and performance management;\nResponsible for end-to-end talent acquisition including but not limited to search strategy set up, research, mapping, sourcing, selection and onboarding;\nEstablish and review HR policies and procedures for streamlining and maximizing the efficiency;\nCoordinate and administer training programs and activities.\n\nRequirements:\n\nDegree in Human Resource, Business Administration or related discipline would be preferred;\nMinimum 8 years of hands-on experience in all-round HR functions in which 3 years gained from freight forwarding industry;\nWell versed in Hong Kong Employment Ordinance, Employees\u2019 Compensation Ordinance and other HR related ordinances;\nGood command of spoken and written English, Cantonese and Mandarin;\nProficiency in MS Word, Excel and Chinese Word Processing;\nSelf-motivated, be able to work independently and to work as a team;\nDetail-minded with strong sense of responsibilities;", "employment_types": ["Full Time", "Permanent"], "selling_points": ["Human Resources Business Partner", "Staffing, talent acquisition & employee engagement", "Performance & talent management"], "locations": ["Kwun Tong"], "categories": ["Admin & HR", "HR Director / Manager", "Training & Development"], "post_time": "2022-01-06T03:39:07Z", "salary": {"currency": null, "max": null, "min": null, "period": "monthly", "term": null}, "salary_visible": false, "title_keywords": ["assistant human resources manager"], "responsibilities": ["management", "policies", "hr", "review", "procedures", "coordinate", "planning"], "requirements": {"degrees": ["degree"], "majors": ["business administration"], "languages": ["cantonese", "english", "chinese", "mandarin"], "language_level": ["proficiency", "good command"], "hard_skills": ["excel", "chinese word processing", "hong kong employment ordinance", "ms word"], "soft_skills": ["detail-minded", "work independently", "self-motivated", "work as a team", "hands-on", "sense of responsibilities"], "languages_combined": [{"language": "cantonese", "language_level": ["good command"]}, {"language": "english", "language_level": ["good command"]}, {"language": "chinese", "language_level": ["proficiency"]}, {"language": "mandarin", "language_level": ["good command"]}]}, "experience_required": {"duration": ["3 years", "minimum 8 years"], "field": ["hr"]}}, {"job_id": "100003009026772", "location_code": "hk", "company": "aimHigher Consultancy Limited", "job_title": "Regional Human Resources Manager", "description": "Company Description\n\nOur client is a US based technology solution company. They are looking for an experience HR professional to join their regional team as HR Manager, Asia.\n\nResponsibilities\n\nEffectively select and utilize appropriate media to recruit personnel based upon organizational needs, including regular, temporary and contract personnel. Coordinate with hiring managers to understand the requirement, conduct screening of employment applicants and interviews.\nResponsible for On-boarding New Hires in conjunction with the hiring manager and introduce new managers to various management processes through the company policies and procedures.\nManage Payroll and Employee Benefits.\nManage and oversee annual compensation & benefits projects such as performance management and annual salary review projects for the assigned offices.\nMaintain/update employee files to document personnel actions and to provide information for payroll and other uses.\nDevelop Training and Development activities in accordance with business priorities;\nResolve employee relations issues as they may occur, interface with line management as appropriate and other levels of management.\nNourish a positive employee relations environment through the application of fair, consistent and equitable Human Resources practices.\nHold regular HR / Business Reviews with senior managers and middle management locally;\nProvide advice and guidance to managers locally.\nEducate employees on HR policies, plans, programs, practices, processes and tools.\nManage and Organize employee events and activities (Wellness Program, Community\nInvolvement, Company functions and meetings for client group)\n\nRequirements\n\nDegree holder with minimum 5 years HR generalist experience in MNCs.\nHave a manufacturing environment is preferable\nBusiness orientation and well developed HR technical skills and project management skills\nFamiliar with Employment Law in APAC\nAbility to analyze, determine and recommend optimum staffing levels required\nAbility to work with a dynamic environment independently with a can-do attitude\nStrong collaborate and good interpersonal skill\nWell-organized and attention to details\nAbility to effectively communicate in the English and Chinese verbally and in writing\nInterested parties please send your updated resume in WORD format with current and expected salaries (quoting Employer Ref:)", "employment_types": ["Full Time"], "selling_points": ["US based leading technology solution company", "HR Generalist", "Regional role"], "locations": ["Not Specified"], "categories": ["Admin & HR", "Compensation & Benefits", "HR Director / Manager", "Training & Development"], "post_time": "2022-01-06T08:36:51Z", "salary": {"currency": null, "max": null, "min": null, "period": "monthly", "term": null}, "salary_visible": false, "title_keywords": ["manager", "human resources"], "responsibilities": ["policies", "management", "coordinate with", "procedures"], "requirements": {"degrees": [], "majors": [], "languages": [], "language_level": [], "hard_skills": [], "soft_skills": [], "languages_combined": []}, "experience_required": {"duration": [], "field": []}}, {"job_id": "100003009020486", "location_code": "hk", "company": "Gearing Enterprises Limited", "job_title": "People System Manager", "description": "About the role\n\nAt Gearing, we design, develop and manufacture products and precision components in medical, safety, emergency readiness, industrial and consumer fields from life-saving airbags to home appliances. We aim to build and run world-class engineering and manufacturing operations. If you are passionate about building a culture striving for excellence and inspiring people to exceed themselves, we would like to hear from you.\n\nAs People System Manager, you lead, coach and inspire people towards being the best of themselves. Your team understands and promotes the culture, organization, leadership and inclusive environment necessary for all people to take pride in their work. Your team partners with Gearing University to focus on talent development foundation and systems, and reshape organizational structure and roles according to corporate directives. In addition, your team handles a full range of people governance and administrative functions to ensure full compliance with legal and regulatory requirements and corporate policies. In-depth knowledge and experience of ISO9001:2015 methodologies and lean waste are highly appreciated.\n\nHow will you contribute\n\nTalent Development System. Talent development programs enable us to deliver better customer service and experience. Your team will partner with Gearing University and business leaders to create, implement and manage in-house continual development initiatives and practical training programs which help educate and reinforce our culture. Your team is also responsible for succession planning.\n\nPartner with Gearing University and leadership to develop integrated quality management system that identifies and recruits talent, develops leadership, verifies and validates qualifications, and plans for succession.\nFocus efforts on personal development needs, and promote a learning environment which supports on-the-job opportunities within teams and internally across the company\nDevelop learning and development plans according to current and future needs of the organization\nHandle training administrative functions such as course enrollment, training record maintenance, administration and logistics\nMonitor and evaluate the effectiveness of learning and people development programs\nAudit the effectiveness of quality management system, identify weaknesses and continually improve processes and systems\n\nPeople Governance & Administration. Your team handles a full range of people governance and administrative functions, including assistance in the review of organizational structure, roles, people policies, processes and procedures, to ensure full compliance with legal and regulatory requirements, corporate directives and corporate policies. Provides advice and counsel to managers and employees on all people related issues, including identifying key talent, succession planning, recognition, attendance/performance issues, and terminations.\n\nDevelop integrated quality management system to ensure effective governance and administration, including review of organizational structure, roles, people policies, processes and procedures\nManages compensation and benefits programs, such as annual compensation planning process, compensation surveys and analyses, benefit programs and employee services\nActively engage with business leaders on people strategy through workforce planning and organization design and structure\nAssess risks from trends or regulatory changes, and develop contingency measures\nOwn master people service database, including HR information systems, salaries survey, labour market condition and business intelligence\nConsult and advise on all aspects of employee-related issues, including manager/employee issues, policies & procedures, misconduct, investigations, terminations, review of appealed terminations, reorganizations etc.\nExecutes all people-related rules and procedures\nMonitor and review the effectiveness of people policies and procedures, and continually improve processes and systems\n\nWhat will you need\n\nHigher Diploma or above in Human Resources Management, Education or related disciplines\nMinimum 8 years of Talent Development and People Governance experience in engineering and manufacturing entities\nMinimum 4 years of working in people management in manufacturing industries in China\nWell versed with China and Hong Kong employment-related laws and labour practices in manufacturing industry\nIn-depth experience on quality management systems ISO9001; preferably IATF16949, ISO13485 and ISO9004\nAbility to lead, coach and inspire people towards being the best of themselves\nFosters trust and relationships at all levels in the organization\nStrong ability to plan in details and execute projects\nSuccinct and precise communication skills (verbal, non-verbal and written)\nWillingness and demonstrated ability to work in teams, as both a lead and a supporting team member\nGood command of Microsoft Office\nGood command of verbal and written communication skills with fluency in Cantonese and Mandarin; fluency in English is a plus\nLesser qualifications and experience will be considered as assistant manager or supervisor\nWork in Huizhou, Shenzhen, Guangdong, Hong Kong\n\nWhat do we offer\n\nWe offer remuneration packages including competitive salary, annual system bonus and comprehensive medical, dental, clinical, critical, life and travel protection.\n\nWe recognize balancing personal responsibilities and professional requirements are important to you. As part of our commitment to you, we provide flexible annual leave, general holidays, study days for certification exams and personal leave covering a range of important life events.\n\nAs a life-long learning organization, we provide ample opportunities to acquire new knowledge and practice new skills. Our Graduate School Assistance Program provides financial assistance towards pursuing an advanced degree while our Professional Development Program provides full coverage towards designated certified continuing professional development courses, such as Certified Six Sigma Program.\n\nHow to apply\n\nSubmit your cover letter, application form, CV, academic transcript(s) and relevant documents in PDF format\nDownload application form here", "employment_types": ["Full Time", "Permanent"], "selling_points": ["Joyful life-long learning and practice", "Make an impact to people and bring out their best", "Shape organization and teamwork"], "locations": ["Not Specified"], "categories": ["Admin & HR", "Administration / Operation Manager", "HR Director / Manager", "Manufacturing", "Quality Assurance, Control & Testing / ISO"], "post_time": "2022-01-04T12:55:49Z", "salary": {"currency": null, "max": null, "min": null, "period": "monthly", "term": null}, "salary_visible": false, "title_keywords": ["system manager"], "responsibilities": ["operations", "regulatory requirements", "planning process", "quality", "audit", "design", "communication", "customer service", "database", "plan", "plans", "administration", "compliance", "teams", "monitor", "develop", "logistics", "attendance", "management", "enrollment", "review", "procedures", "assess risks", "development programs", "maintenance", "policies", "hr", "systems", "evaluate", "planning"], "requirements": {"degrees": ["higher diploma or above", "master"], "majors": ["related disciplines", "business"], "languages": ["cantonese", "english", "mandarin"], "language_level": ["fluency", "good command"], "hard_skills": ["lean", "plus", "maintenance", "microsoft office", "focus", "business intelligence"], "soft_skills": ["communication skills", "responsible", "organizational", "customer service", "learning", "inspiring", "precise", "focus", "team member", "leadership", "passionate about", "world-class"], "languages_combined": [{"language": "cantonese", "language_level": ["fluency", "good command"]}, {"language": "english", "language_level": ["fluency"]}, {"language": "mandarin", "language_level": ["fluency", "good command"]}]}, "experience_required": {"duration": ["minimum 8 years"], "field": ["manufacturing", "engineering", "development", "customer service", "quality management"]}}, {"job_id": "100003009025609", "location_code": "hk", "company": "Shanghai Pudong Development Bank Co., Ltd., Hong Kong Branch", "job_title": "Assistant Human Resources Manager, Recruitment and Training (Ref.: CV_HRD_202201)", "description": "Responsibilities:\n\n\nProvide a wide range of human resources function such as recruitment, training & development, and administrative related matters. Participating in project-based tasks such as career development, company\u2019s culture event as assigned.\n\nRequirements:\n\nUniversity graduate with major in Human Resources Management or related disciplines\nMinimum 3 years of relevant work experience in HR management or training & development\nKnowledge of Employment Ordinance and related regulatory requirements\nResponsible, organizing with attention to details, able to work under pressure in fast pace work environment\nGood interpersonal and communication skills\nProficiency of English and Chinese, in both writing and verbal skills. Putonghua speaking is required\nComputer literate with good command of MS Office, especially Excel and PowerPoint\nSuitable candidates with more experience may consider for senior positions\nPlease quote the Reference No.: CV_HRD_202201 in your application.\n\nOur Bank offers attractive remuneration package to chosen candidates. Interested parties please apply with full resume stating expected salary and contact phone number via\u00a0Apply Now.\n\nAll applications will be treated in the strictest confidence and personal data collected will be used for recruitment purpose only.", "employment_types": ["Full Time", "Permanent"], "selling_points": ["Recruitment, training & development", "one-stop and all-rounded HR advisory and support", "Excellent career path in growing platform"], "locations": ["Wan Chai"], "categories": ["Admin & HR", "HR Director / Manager", "Recruitment / Executive Search", "Training & Development"], "post_time": "2022-01-06T16:08:05Z", "salary": {"currency": null, "max": null, "min": null, "period": "monthly", "term": null}, "salary_visible": false, "title_keywords": ["assistant human resources manager"], "responsibilities": ["recruitment", "career development"], "requirements": {"degrees": ["university graduate"], "majors": ["related disciplines"], "languages": ["putonghua", "english", "chinese"], "language_level": ["proficiency"], "hard_skills": ["excel", "no", "powerpoint", "ms office"], "soft_skills": ["communication skills", "responsible", "attention to details", "interpersonal", "work under pressure"], "languages_combined": [{"language": "putonghua", "language_level": []}, {"language": "english", "language_level": ["proficiency"]}, {"language": "chinese", "language_level": ["proficiency"]}]}, "experience_required": {"duration": ["minimum 3 years"], "field": ["development", "hr", "training", "management"]}}, {"job_id": "100003009018803", "location_code": "hk", "company": "HKT", "job_title": "Human Resources Manager", "description": "Your role\n\nAct as strategic HR business partner to provide a full range of quality and value-adding services to internal clients, including manpower planning, talent acquisitions, talent and organization development and employee relations so as to drive HR transformation in the assigned business units\nDevise and execute effective workforce and succession planning initiatives\nTake the lead in developing and implementing rewards management initiatives at business unit level, e.g. pay level study, salary benchmarking, deployment of career maze\nDrive the HR digital transformation within the team and prepare up-to-date HR trends and analytics\nCoach and guide team member to deliver HR services and solutions\nCollaborate with functional COEs and other HR business partners to implement corporate policies and initiatives at business unit level\nTake up any ad hoc HR projects as assigned\n\nTo succeed in this role\n\nDegree holder in Human Resources Management, Business Administration, Economics, Finance, Engineering or a related discipline\nMinimum of\u00a08 years\u2019 HR experience gained in sizeable organizations, of which at least 2 years in a supervisory role; Hands-on experience in rewards management and/or data analytics is required\nCandidates from Tech or Engineering industry is preferred\nAgile, analytical, detail-minded with good numerical sense\nCollaborative, outgoing and possessing a growth mindset\nAbility to work under pressure and multi-tasking\nGood command of spoken and written English and Chinese (Both Cantonese and Putonghua)", "employment_types": ["Full Time"], "selling_points": ["HRBP", "C&B", "C&B"], "locations": ["Quarry Bay"], "categories": ["Admin & HR", "HR Director / Manager"], "post_time": "2022-01-04T04:56:19Z", "salary": {"currency": null, "max": null, "min": null, "period": "monthly", "term": null}, "salary_visible": false, "title_keywords": ["manager", "human resources"], "responsibilities": ["collaborate with", "administration", "management", "ad hoc", "data", "work under pressure", "policies", "hr", "quality", "developing", "planning"], "requirements": {"degrees": ["degree holder"], "majors": ["finance", "economics", "business administration", "engineering"], "languages": ["cantonese", "putonghua", "english", "chinese"], "language_level": ["good command"], "hard_skills": ["data analytics", "deployment", "agile"], "soft_skills": ["detail-minded", "outgoing", "agile", "collaborative", "hands-on", "multi-tasking", "team member", "work under pressure"], "languages_combined": [{"language": "cantonese", "language_level": ["good command"]}, {"language": "putonghua", "language_level": ["good command"]}, {"language": "english", "language_level": ["good command"]}, {"language": "chinese", "language_level": ["good command"]}]}, "experience_required": {"duration": ["at least 2 years", "minimum of 8 years"], "field": ["hr", "supervisory", "management"]}}, {"job_id": "100003009028535", "location_code": "hk", "company": "Global Executive Consultants Ltd.", "job_title": "Payroll Outsourcing Manager (Human Resources / Payroll)", "description": "Responsibilities:\n\nDrive HR Strategies and Change Management\nFormulate, review and implement HR policies and procedures to sustain the growth of the company\nRevamps the resourcing process & provides timely and effective support to attract people for business growth and priorities\nProvides direction and coaching to managers at all levels and staff concerning HR policies, practices, job performance, documentation, and conflict resolution\nTransform management\u2019s direction into policies and guidelines.\u00a0 Initiate HR programs by establishing systems and process to attract, engage, manage and develop the workforce to utilize its full potential in alignment with the direction, goals and strategies of the business\nDevelop and facilitate effective sourcing strategies - mapping talent pipelines through various platforms including social media and external networks\nSupports & reviews organizational structure in term of capacity & effectiveness to support and reinforce an engaged and high performing workforce\n\nRequirement:\n\nDegree holder in Human Resources Management or related discipline\n10 years\u2019 relevant HR experience with sizable businesses in relation to a fast-paced corporate environment, preferably in F&B or retail industries\nIndependent and good team player with strong interpersonal and communication skills\nGood command of both written and spoken English and Chinese\nWith PRC experience will be an advantage", "employment_types": ["Full Time", "Permanent", "Contract"], "selling_points": ["Payroll Services", "Human Resources", "Employment Ordinance"], "locations": ["Not Specified"], "categories": ["Admin & HR", "Compensation & Benefits", "HR Director / Manager", "Recruitment / Executive Search"], "post_time": "2022-01-07T09:21:00Z", "salary": {"currency": null, "max": null, "min": null, "period": "monthly", "term": null}, "salary_visible": false, "title_keywords": ["manager", "human resources"], "responsibilities": ["social media", "management", "change management", "guidelines", "policies", "hr", "review", "procedures", "systems", "develop", "resolution", "documentation"], "requirements": {"degrees": ["degree holder"], "majors": [], "languages": ["english", "chinese"], "language_level": ["good command"], "hard_skills": [], "soft_skills": ["communication skills", "good team player", "independent", "interpersonal"], "languages_combined": [{"language": "english", "language_level": ["good command"]}, {"language": "chinese", "language_level": ["good command"]}]}, "experience_required": {"duration": ["10 years"], "field": ["hr", "f&b", "retail"]}}, {"job_id": "100003009031001", "location_code": "hk", "company": "JFE Consulting Limited", "job_title": "Assistant HR Manager, HRBP", "description": "International Education Group\nGroup Level Corporate Functions\nOversee Operation and Drive Projects\n\nThe Role\n\nReport to Head of HR, be accountable for all HR matters for corporate staff within the group in Hong Kong and China (with a small population in US and UK), with an oversight on workplace matters for the corporate office in Hong Kong\nAddress any HR operational issues carried out by local HR counterparts, and provide directions on end-to-end HR processes, from talent acquisitions, rewards management, performance management, employee development and relations, and other on/off boarding matters\nWork closely with the Head of HR on providing HR advisory to Senior Management on achieving organization/people strategies and goals\nPlan and drive continuous improvement especially on enhancing the value and best practices of HR across the organization\nRequirements\n\nBachelor degree in any discipline with at least 10 years\u2019 experience with human resources practices and disciplines with a solid understanding of HR best practices, HR business partnering, and project management\nAbility to manage ambiguity with an agile and forward-looking mindset\nGood leadership competency with good analytical and problem-solving skills\nFluent in English, Mandarin, and Cantonese\n\nInterested candidates, please email your update resume (in MS WORD format) with current and expected salary to us soonest.\n\nAlso come visit ProJOB21 www.ProJob21.com to discover other exciting career opportunities!\n\nAll information received will be kept in strict confidence and used for employment-related purposes only.", "employment_types": ["Full Time", "Permanent"], "selling_points": ["MNC technology enterprise,headcount planning", "Provide HR advice,talent acquisition,screening", "4 years experience,attractive salary package"], "locations": ["Not Specified"], "categories": ["Admin & HR", "HR Director / Manager", "HR Supporting Staff", "Recruitment / Executive Search"], "post_time": "2022-01-07T08:48:07Z", "salary": {"currency": null, "max": null, "min": null, "period": "monthly", "term": null}, "salary_visible": false, "title_keywords": ["assistant hr manager"], "responsibilities": ["management", "hr", "project management", "plan", "senior management", "report"], "requirements": {"degrees": ["degree", "bachelor"], "majors": ["project management", "business"], "languages": ["cantonese", "english", "mandarin"], "language_level": ["fluent"], "hard_skills": ["small", "project management", "problem-solving skills", "agile"], "soft_skills": ["agile", "accountable", "project management", "problem-solving skills", "leadership"], "languages_combined": [{"language": "cantonese", "language_level": ["fluent"]}, {"language": "english", "language_level": ["fluent"]}, {"language": "mandarin", "language_level": ["fluent"]}]}, "experience_required": {"duration": ["at least 10 years"], "field": ["project management", "hr", "business", "human resources"]}}, {"job_id": "100003009023717", "location_code": "hk", "company": "Manpower Services (Hong Kong) Limited", "job_title": "Senior Manager, Human Resources (50-65K)(Energy Company)", "description": "Position: \u00a0\u00a0\u00a0\u00a0\u00a0\u00a0\u00a0\u00a0\u00a0 Assistant Rewards and Systems Manager\n\nLine Manager:\u00a0 Rewards and Systems Manager\n\nMain Responsibilities\n\nAssist Rewards and Systems Manager to optimize, automate and enhance C&B processes to achieve efficiency, productivity and improve governance and control for the Group\nRevamp C&B policies and procedures in order to establish sound corporate governance practices across the Group\nKeep abreast of local labour legislation and provide advice and recommendations on the development of the local C&B practices in the region\nEnsure corporate and operational HR budgets are completed on-time and in-line with defined budget indicators\nCoordinate compensation processes across schools including annual salary reviews, discretionary bonus allocation, and HR budgeting & reporting\nConduct C&B analysis including internal and external benchmarking. Review and assist in redesigning reward programmes to improve the effectiveness, competitiveness, and attractiveness of Total Rewards programmes\nAct as the main contact point for internal or external HR queries\nEnsure global HR data is up to date and accurate\nLeverage global HR data to generate management reports and HR analytics\nOccasionally support payroll calculation, tax filing, pension administration, and implementation of HRIS for the corporate office\n\nJob Specification\n\nBachelor's degree in Human Resources management or relevant disciplines\nA minimum of 3 years of relevant experience\nPreferred experience in global or regional management organizations\nProven experience with developing HR policies and procedures\nFamiliar with analysing employee populations and developing various management reports by using Excel and other reporting tools\nStrong verbal and written communication skills in both English, Cantonese, and Mandarin; competent in\u00a0interacting with staff at all levels of the Company\nMeticulous to detail and good ability to handle and evaluate qualitative &quantitative information\nExcellent time management and highly developed organisational skills are required\nAbility to maintain and manage information of a confidential or sensitive nature\nTeam player and highly adaptable in a multi-cultural environment\n\nIf you are interested in an opportunity to work with us, please send your full resume with your current and expected salary by email to\u00a0hr @harrowinternational.org. Please state the\u00a0job title\u00a0and the reference code \u201cHIMS/ARSM/202201\u201din the subject of your email. All applications will be treated with the strictest confidence. Only short-listed candidates will be notified.", "employment_types": ["Contract"], "selling_points": ["Good Salary Package", "Excellent Salary Package with Bouns", "Good Career Path"], "locations": ["Shatin Area"], "categories": ["Admin & HR", "Administration / Operation Manager", "HR Director / Manager"], "post_time": "2022-01-05T09:35:27Z", "salary": {"currency": null, "max": null, "min": null, "period": "monthly", "term": null}, "salary_visible": false, "title_keywords": ["senior manager", "human resources"], "responsibilities": ["data", "budgeting", "budget", "communication", "maintain", "administration", "control", "tax filing", "implementation", "developing", "reporting", "management", "review", "procedures", "contact", "payroll", "budgets", "revamp", "policies", "hr", "systems", "analysis", "coordinate", "evaluate", "management reports", "provide advice"], "requirements": {"degrees": ["degree", "bachelor"], "majors": [], "languages": ["cantonese", "english", "mandarin"], "language_level": [], "hard_skills": ["excel", "analysis", "code", "management reports"], "soft_skills": ["communication skills", "meticulous", "confidence", "accurate", "competent", "adaptable", "interested in", "organisational skills", "sensitive", "team player", "time management"], "languages_combined": [{"language": "cantonese", "language_level": []}, {"language": "english", "language_level": []}, {"language": "mandarin", "language_level": []}]}, "experience_required": {"duration": ["minimum of 3 years"], "field": ["hr", "management", "relevant experience", "developing"]}}, {"job_id": "100003009029138", "location_code": "hk", "company": "Harrow International Management Services Limited", "job_title": "Assistant Rewards and Systems Manager", "description": "Our client, a well-established investment bank to invite high caliber candidates to join their company.\n\nResponsibilities\n\nHandle the entire recruitment process from sourcing of candidates to preparing remuneration proposal\nCommunicate with line managers for recruitment needs and requirements\nLiaise with external recruiters on staffing strategies\nParticipate in various HR projects such as performance appraisal, salary and benefits surveys, salary and bonus exercise, and other HR initiatives as required\nParticipate ad hoc projects as assigned \u00a0\n\nRequirements\n\nDegree holder preferably in Human resources management\nMinimum 5 years\u2019 recruitment experience in investment bank / financial industry\nIndependent, self-driven and good interpersonal skills\nGood command in spoken and written Chinese (both Cantonese & Putonghua) and English\nProficient in\u00a0PC knowledge, Word and Excel\nImmediate available is preferred\n\nTo apply, please send your detailed resume or contact Boei Yan at 3460 2012 for a confidential discussion.\nOnly shortlisted candidates will be notified.\u00a0\nApplicants who are not contacted within two weeks may consider their applications unsuccessful.\nAll data collected will be used for recruitment purpose only & will be used strictly confidential.\n\nConners Consulting Limited 2005 Kai Tak Commercial Building 317 Des Voeux Road Central Hong Kong\nTel: (852) 3996 8090\u00a0 \u00a0 \u00a0 \u00a0\u00a0\nWebsite:\u00a0http://www.connersconsulting.com/", "employment_types": ["Full Time"], "selling_points": ["Optimize, automate and enhance C&B processes", "A minimum of 3 years of relevant experience", "Bachelor's degree in Human Resources management"], "locations": ["Wan Chai"], "categories": ["Admin & HR", "Administration / Operation Manager", "Compensation & Benefits", "HR Director / Manager"], "post_time": "2022-01-07T04:48:28Z", "salary": {"currency": null, "max": null, "min": null, "period": "monthly", "term": null}, "salary_visible": false, "title_keywords": ["manager", "assistant"], "responsibilities": ["communicate with", "hr", "recruitment", "ad hoc projects", "liaise with", "recruitment process"], "requirements": {"degrees": ["degree holder"], "majors": [], "languages": ["cantonese", "putonghua", "english", "chinese"], "language_level": ["good command"], "hard_skills": ["excel", "pc knowledge", "word"], "soft_skills": ["independent", "driven", "interpersonal skills", "detailed"], "languages_combined": [{"language": "cantonese", "language_level": ["good command"]}, {"language": "putonghua", "language_level": ["good command"]}, {"language": "english", "language_level": ["good command"]}, {"language": "chinese", "language_level": ["good command"]}]}, "experience_required": {"duration": ["minimum 5 years"], "field": ["financial industry", "recruitment", "investment bank"]}}]