[{"job_id": "100003009053314", "location_code": "hk", "company": "New Life Plastics Limited", "job_title": "Human Resources Officer", "description": "Responsibilities\n\nPerform a full range of HR duties for the assigned business functions, including talent acquisition & retention, compensation & benefits, performance management, and employee relations\nEstablish partnership with business managers and offer professional help on people matters\nProvide professional answers and advices to employee enquiries on HR policies and programmes\nPrepare management reports, proposals and provide insights on data trends and recommendations on continuous improvement\nConduct employee focus groups to understand employees\u2019 views and comments, and prepare and execute improvement action plans\nProvide support on other HR initiatives and ad hoc resourcing and staff relations projects and tasks as assigned by the supervisor\n\nRequirements\n\nDegree holder in Human Resources Management or other related disciplines\nAt least 5 years' related experience\nIndependent, excellent organization skills, self-motivated and dynamic personality\nHands on and creative in recruiting different staff\nGood knowledge of Employment Ordinance of Hong Kong\nStrong communication skills with good command of spoken and written English and Chinese\n\nWork location: Ecopark, Tuen Mun\n\nWorking hours: From Monday to Friday (09:00 - 18:00)\n\nBenefits: Double pay, Public Holiday, 12 days paid annual leave, shuttle bus provided, medical insurance\n\nSalary: Depending on academic qualifications and work experience", "employment_types": ["Full Time", "Permanent"], "selling_points": ["5 years' related experience", "Degree holder", "shuttle bus provided"], "locations": ["Tuen Mun Area"], "categories": ["Admin & HR", "HR Supporting Staff"], "post_time": "2022-01-17T06:44:59Z", "salary": {"currency": null, "max": null, "min": null, "period": "monthly", "term": null}, "salary_visible": false, "title_keywords": ["human resources officer"], "responsibilities": ["provide insights", "management", "provide support", "ad hoc", "data", "policies", "hr", "comments", "hr duties", "management reports", "plans"], "requirements": {"degrees": ["degree holder"], "majors": ["related disciplines"], "languages": ["english", "chinese"], "language_level": ["good command"], "hard_skills": ["dynamic"], "soft_skills": ["communication skills", "self-motivated", "independent", "dynamic", "hands on", "organization skills", "creative"], "languages_combined": [{"language": "english", "language_level": ["good command"]}, {"language": "chinese", "language_level": ["good command"]}]}, "experience_required": {"duration": ["at least 5 years"], "field": ["related"]}}, {"job_id": "100003009054210", "location_code": "hk", "company": "Fortune Pharmacal Company Limited", "job_title": "Officer/ Assistant Officer, Human Resources", "description": "Quarry Bay School is now looking for a HR & Fiance Assistant to join the team.\nResponsibilities:\n\nThe HR & Finance Assistant assists in HR & Accounting tasks under the supervision of the HR & Finance Officer.\nUndertake accounts payable functions\nUndertake petty cash records\nAssist with procurement and related matters\nAssist with Freelance Service Provider agreement process\nAssist with Fixed Asset records and perform annual count\nOther assigned HR and Finance related tasks\nPerform other duties as directed by the HR & Finance Officer/Principal\nCompetencies required:\nGood command of written and spoken English and Chinese\nProficient with MS Excel and Word\nReliability and detail-oriented\nRequirements\nBasic accounting knowledge\nRelevant experience\nApplicants must be a permanent Hong Kong resident or possess a valid visa to work in Hong Kong.\nClosing Date:\u00a016th January 2022\nFor enquiries, please contact Doris Wong at +852 25664242 via \"Apply Now\".\nApplications will be reviewed on a rolling basis and offers may be extended prior to the job closing date.\nBy applying for this position, your application may be considered for other opportunities within ESF.\nESF is an Equal Opportunities Employer\nPersonal data provided by job applicants will be used strictly in accordance with the ESF's Personal Data Policy, a copy of which will be provided upon request.\nAligned with the recommendations of the International Task Force on Child Protection, we hold ourselves to a high standard of effective recruiting practices with specific attention to child protection.\nsupportstaff\nsupportstaffhki", "employment_types": ["Full Time", "Permanent"], "selling_points": ["Compensation and benefits focus", "5 year's C&B exp.", "Pharmaceutical Industry"], "locations": ["Yuen Long"], "categories": ["Admin & HR", "Compensation & Benefits", "HR Supporting Staff"], "post_time": "2022-01-17T08:49:22Z", "salary": {"currency": null, "max": null, "min": null, "period": "monthly", "term": null}, "salary_visible": false, "title_keywords": ["assistant officer", "officer", "human resources"], "responsibilities": ["hr", "perform other duties", "accounts payable"], "requirements": {"degrees": [], "majors": [], "languages": [], "language_level": [], "hard_skills": ["basic"], "soft_skills": [], "languages_combined": []}, "experience_required": {"duration": [], "field": ["relevant experience"]}}, {"job_id": "100003009054827", "location_code": "hk", "company": "The English Schools Foundation", "job_title": "HR and Finance Assistant - Quarry Bay School", "description": "Responsibilities:\n\nTo provide HR and office administration support\n\u00a0To handle the recruitment and selection process, especially for retail staff\nTo assist in payroll calculation and MPF administration\u00a0for retail staff\nTo provide office administration support such as general insurance, license renewal and office maintenance\nTo handle ad-hoc duties as assigned\nRequirements:\n\nDiploma holder or above in Human Resources Management\nMinimum 1-2 years\u2019 relevant experience, especially in retail industry is preferable\nWell-versed with Hong Kong Employment Ordinance\nGood communication and presentation skills\nImmediate available is preferable\nApplicants with less experience will be considered as Human Resources & Administration Assistant\n\n\n\nInterested parties, please apply with full resume, stating date available, present and expected salary to\u00a0Human Resources & Administration Department by clicking 'Apply Now'.\n\nPersonal Data provided in the employment applications will be treated as strictly confidential and used only for recruitment purpose.\u00a0 All unsuccessful applications will be destroyed upon completion of the selection process.", "employment_types": ["Full Time", "Permanent"], "selling_points": ["Undertake accounts payable functions", "Assist with procurement and related matters", "Basic accounting knowledge"], "locations": ["Not Specified"], "categories": ["Accounting", "Accounting Clerk / Supervisor", "Financial Analyst", "Admin & HR", "HR Supporting Staff"], "post_time": "2022-01-17T11:26:30Z", "salary": {"currency": null, "max": null, "min": null, "period": "monthly", "term": null}, "salary_visible": false, "title_keywords": ["hr", "finance assistant"], "responsibilities": ["office administration support", "mpf", "maintenance", "hr", "recruitment", "insurance", "ad-hoc duties", "payroll", "administration"], "requirements": {"degrees": ["diploma holder"], "majors": [], "languages": [], "language_level": [], "hard_skills": ["hong kong employment ordinance"], "soft_skills": ["communication", "presentation skills"], "languages_combined": []}, "experience_required": {"duration": ["minimum 1-2 years"], "field": ["retail industry", "relevant experience", "human resources", "administration"]}}, {"job_id": "100003009053226", "location_code": "hk", "company": "Crocodile Garments Limited", "job_title": "Assistant Human Resources & Administration Officer", "description": "Responsibilities\n\nHandle C&B functions including monthly payroll, staff movement, attendance & leave management and final payment calculation;\nHandle MPF, taxation & medical administration, and work injury cases;\nRetail section update & maintain of employee information in HR system, support the system enhancement project;\nPrepare reports on a regular basis;\n\nAssist in staff disciplinary and labor dispute cases;\n\nParticipate in ad-hoc projects and duties as required.\n\nRequirements\n\nDiploma or above in Human Resources Management or related disciplines;\n1 year of solid experience on C&B functions in a sizable organization, especially in payroll area is preferred;\nDetailed & quality-oriented and strong sense of accountability;\nGood numerical sense, good command of both spoken & written in English and Chinese;\nWell-versed in Employment Ordinance and other HR-related legislation;\nProficiency in MS Office and experiences of using HRIS;\nImmediate availability is highly preferred.\n\nWe offer\n\n5-day work week\nMedical Benefits\nPerformance Bonus\nStaff Purchase Discounts\nStaff Recreation Activity\nShuttle Bus Service\nEducation Sponsorship\n\nInterested parties please send a full resume with current and expected salary by clicking APPLY NOW:\n\nHuman Resources Department\nSa Sa Cosmetic Co Ltd\n14/F, Block B, MP Industrial Centre\n18 Ka Yip Street\nChai Wan\nHong Kong\n\nPlease visit our corporate website at http://corp.sasa.com/en/home to know more about us.\n\n(Sa Sa is an Equal Opportunity Employer and all qualified applicants will receive consideration for employment. Personal data collected will be kept confidential and used for recruitment purposes only)", "employment_types": ["Full Time", "Permanent"], "selling_points": ["Provide HR and office administration support", "Assist in recruitment and payroll calculation", "Diploma in HRM with min.1 year exp."], "locations": ["Kwun Tong"], "categories": ["Admin & HR", "Compensation & Benefits", "HR Supporting Staff", "Training & Development"], "post_time": "2022-01-17T06:29:23Z", "salary": {"currency": null, "max": null, "min": null, "period": "monthly", "term": null}, "salary_visible": false, "title_keywords": ["human resources", "administration officer", "assistant"], "responsibilities": ["taxation", "mpf", "hr", "payment", "attendance & leave management", "maintain", "prepare reports", "ad-hoc projects", "payroll", "administration"], "requirements": {"degrees": ["diploma or above"], "majors": ["related disciplines"], "languages": ["english", "chinese"], "language_level": ["good command", "good"], "hard_skills": ["ms office"], "soft_skills": ["accountability", "detailed"], "languages_combined": [{"language": "english", "language_level": ["good command", "good"]}, {"language": "chinese", "language_level": ["good command", "good"]}]}, "experience_required": {"duration": ["1 year"], "field": ["sizable organization", "payroll"]}}, {"job_id": "100003009046958", "location_code": "hk", "company": "Sa Sa Cosmetic Company Limited", "job_title": "Human Resources Assistant, (C&B / Retail section)", "description": "About Us\n\n\n\nDue to rapid expansion in our business we are now looking to recruit high calibre, self-driven candidates, to assist with various operations to help us take our services to an even broader audience.\n\nWith offices across Asia, Europe, America\u00a0and Australia we have already established a very strong network of professionals with vast experience across the financial industry.\n\nWe are currently looking for\u00a0Junior Administration Officer to help with maintaining our growing accounting duties for our international operations.\u00a0\n\n\nDuties\n\n1. Provide all-round admin support to a small team and ad-hoc duties.\n\n2. Prepare JDs for recruitment, shortlist potential candidates CV\u2019s for various positions, communicate with management and relevant departments, arrange interviews and assist on finalising offers.\n\n3. Overlook and assist with banking operations, book keeping, register daily receipts and payments.\n\n4. Responsible for company's administrative tasks, also manage, organise, sending and receiving of company documents.\n\n5. Work closely with accounting and HR teams to provide assistance on various duties, follow up and complete personnel related tasks arranged by supervisor.\n\n6. Maintain daily office order and ensure office needs are met for employee activities.\n\nRequirements\n\n1. College degree or above, at least one years recruitment experience and experience working in financial industry a plus\n\n2. Mature, responsible, proactive, strong communication skills and good teamwork ability.\n\n3. Good attention to detail, enjoys working with numbers, able to provide support to accounting and related departments.\n\n4. Proficient in Office applications including Word and Excel, strong learning ability and able to work independently, under minimal supervision.", "employment_types": ["Full Time", "Permanent"], "selling_points": ["Handle C&B functions", "Support HR system", "Immediate availability is highly preferred"], "locations": ["Siu Sai Wan"], "categories": ["Admin & HR", "Clerical / Admin Staff", "Compensation & Benefits", "HR Supporting Staff"], "post_time": "2022-01-16T21:50:17Z", "salary": {"currency": null, "max": null, "min": null, "period": null, "term": null}, "salary_visible": false, "title_keywords": ["human resources assistant"], "responsibilities": ["communicate with", "management", "receipts", "operations", "hr", "teams", "banking", "admin support", "recruitment", "payments", "maintain", "ad-hoc duties", "administrative tasks", "provide assistance"], "requirements": {"degrees": ["degree or above"], "majors": [], "languages": [], "language_level": [], "hard_skills": ["excel", "plus", "office applications", "word"], "soft_skills": ["communication skills", "work independently", "learning ability", "responsible", "teamwork", "mature", "attention to detail", "proactive"], "languages_combined": []}, "experience_required": {"duration": ["at least one years"], "field": ["financial industry", "recruitment"]}}, {"job_id": "100003009053031", "location_code": "hk", "company": "Global Technology Systems Limited", "job_title": "Junior HR & Administration Officer", "description": "Job Description:\n\nResponsible for performing all-round Human Resources duties mainly on compensation & benefits and recruitment & selection\nMaintain staff record and HR system including payroll calculation\nHandle work injury case, MPF and taxation independently\nExecute recruitment activities including career fair, recruitment day, remaining contact with NGO and others\nAssist to develop and implement HR policies and procedures\nPerform other ad hoc duties as assigned\n\nRequirement:\n\nDiploma in Human Resources Management\u00a0or related discipline\nAt least\u00a01\u00a0year experience, preferably in F&B industry\nWilling to accept challenge\nWell-versed in Hong Kong Employment Ordinance, MPF regulations and other related legislation would be an advantage\nProficient in MS Office applications and Chinese Word Processing\nGood command of spoken and written English & Chinese\nMature team player with strong communication and interpersonal skills\nFresh graduates will also be considered\nImmediate available is highly preferred\n\n\u00a0Job location: San Po Kong\n\nCompetitive remuneration package and benefits as below:\n\nFive-day work week\n\nMarriage leave\n\nStaff discount\n\nMedical & dental allowance\n\nPerformance bonus\n\nIn-service training course\n\n5 days paternity leave\n\nCompassionate Leave\n\nPromotion opportunities\n\nInterested parties may send your detailed resume with\u00a0expected salary\u00a0and\u00a0notice period\u00a0by\u00a0clicking \"Apply Now\"\n\nAll information collected will be used for recruitment purpose only.", "employment_types": ["Full Time"], "selling_points": ["A friendly international working environment", "Great Career development prospects", "Flexible working hours & health benefits"], "locations": ["Kowloon City"], "categories": ["Accounting", "Accountant", "Admin & HR", "Clerical / Admin Staff", "HR Supporting Staff"], "post_time": "2022-01-17T05:15:42Z", "salary": {"currency": "HKD", "max": 19999, "min": 14000, "period": "monthly", "term": null}, "salary_visible": true, "title_keywords": ["hr & administration officer", "junior"], "responsibilities": [], "requirements": {"degrees": [], "majors": [], "languages": [], "language_level": [], "hard_skills": [], "soft_skills": [], "languages_combined": []}, "experience_required": {"duration": [], "field": []}}, {"job_id": "100003009054093", "location_code": "hk", "company": "Taste of Asia Group Limited", "job_title": "HR & Admin Assistant", "description": "Job Description\n\n1.\u00a0Assisting with recruiting, screening, interviewing and placing workers\n\n2.\u00a0Providing clerical and administrative support to Human Resources Executives\n\n3. Compiling and updating employee records\n\n\n\nSkills and Requirements\n\n1.\u00a0Associate Degree holder or above\n\n2.\u00a0Fluent in English, Cantonese and Mandarin\n\n3.\u00a0Able to listen actively and communicate effectively\n\n4.\u00a0Willing to collaborate and work as a team\n\n5.\u00a0Systematic and organized, with an attention to detail\n\n6. Positive and willing to take initiatives", "employment_types": ["Full Time"], "selling_points": ["Five-day work week", "Medical & dental allowance", "Performance bonus"], "locations": ["Wong Tai Sin Area"], "categories": ["Admin & HR", "Others", "HR Supporting Staff", "Recruitment / Executive Search"], "post_time": "2022-01-17T08:22:19Z", "salary": {"currency": null, "max": null, "min": null, "period": "monthly", "term": null}, "salary_visible": false, "title_keywords": ["hr & admin assistant"], "responsibilities": ["administrative support"], "requirements": {"degrees": ["associate degree"], "majors": [], "languages": ["cantonese", "english", "mandarin"], "language_level": ["fluent"], "hard_skills": [], "soft_skills": ["organized", "work as a team", "systematic", "attention to detail", "positive"], "languages_combined": [{"language": "cantonese", "language_level": ["fluent"]}, {"language": "english", "language_level": ["fluent"]}, {"language": "mandarin", "language_level": ["fluent"]}]}, "experience_required": {"duration": [], "field": []}}, {"job_id": "100003009054593", "location_code": "hk", "company": "Top Blade Limited", "job_title": "HR & Admin Assistant", "description": "Job Description\n\nResponsible for the full scope of\u00a0HR functions including recruitment, interview arrangement, employment contract, payroll, MPF and\u00a0other related matters\nUpdating databases, attendance\u00a0records such as annual leave, sick leave in HR system\nPeriodically review and appraise with company staff\nPrepare HR-related statistics and reports for management periodically\nWork closely with all departments\u00a0on administrative related issues\nOversee daily administrative activities such\u00a0as office supplies, equipment maintenance,\u00a0facilities management etc\nHandle general clerical duties such as data entry, renewal of license, insurance for the company; expenses reimbursement; service application\nAssist in contract renewal, check and manage invoices\nProvide administrative support for company's shops\nDraft and prepare company memo, internal letters and useful forms\nPerform ad hoc duties as assigned\n\nJob Requirements\n\nDiploma holder or above in Human\u00a0Resources Management,\u00a0Business Administration or related discipline\nRelevant experience in HR\u00a0and Office Administration is an advantage\nWell versed in HK Employment Ordinance\u00a0and related regulations\nProficient in MS Office including Word, Excel\nPleasant personality and good team player\nSelf-motivated, well-organized,\u00a0analytical and confident in\u00a0resolving complex issues\nBenefits:\n5 days working\nGeneral holidays (SH & PH)\n10-15 days annual leave\n14 weeks of maternity leave and 5 days paternity leave\nMarriage leave\nCompassionate leave\nSalary\n\n$14,000 - $16,000\n\nFor applicants who interested in joining our team, please WhatsApp your resume to\u00a09383 6435 (Miss Lai) or email via \u7acb\u5373\u7533\u8acb\n\n(All information provided by job applicants will be used for recruitment purpose only.)", "employment_types": ["Full Time"], "selling_points": [], "locations": ["Central"], "categories": ["Admin & HR", "Clerical / Admin Staff", "Hospitality / F & B", "Food & Beverage", "HR Supporting Staff"], "post_time": "2022-01-17T10:10:22Z", "salary": {"currency": null, "max": null, "min": null, "period": "monthly", "term": null}, "salary_visible": false, "title_keywords": ["hr & admin assistant"], "responsibilities": ["memo", "provide administrative support", "ad hoc duties", "invoices", "data entry", "expenses", "reports", "interview arrangement", "attendance", "management", "mpf", "office supplies", "review", "payroll", "administrative activities", "maintenance", "hr", "letters", "recruitment", "databases", "insurance"], "requirements": {"degrees": ["diploma holder"], "majors": ["business administration"], "languages": [], "language_level": [], "hard_skills": ["excel", "word", "ms office"], "soft_skills": ["confident", "good team player", "self-motivated", "well-organized", "pleasant"], "languages_combined": []}, "experience_required": {"duration": [], "field": ["office administration", "hr", "relevant experience"]}}, {"job_id": "100003009053728", "location_code": "hk", "company": "Sunrise Diagnostic Centre Limited", "job_title": "HR Officer", "description": "Job Description\nJob Description\u00a0\n\nHandle HR functions including Recruitment and Selection, Benefits Administration, Performance Management, Training and Development, Employee Relations, and Internal Communication. Formulate, review and implement HR policy and compensation strategies with date analysis and ensure HR policies and procedures are in alignment with operational needs and compliance with local regulations.\n\nKeep track and review all Company member's performance monthly, and report to the HR team leader. Follow up Employment Visa application and extension. \u00a0\n\nJob Specification\u00a0\n\nHold a bachelor\u2019s degree or above, in Business, HR, or related discipline Be independent, proactive & self-motivated Challenge the status quo and aim for continuous improvement Have good analytical, presentation, and problem-solving skills Be a good team player and ability to work under high pressure Be fluent in written and spoken English Cantonese and Mandarin", "employment_types": ["Full Time"], "selling_points": [], "locations": ["Tai Po Area"], "categories": ["Admin & HR", "HR Supporting Staff"], "post_time": "2022-01-17T07:25:05Z", "salary": {"currency": null, "max": null, "min": null, "period": "monthly", "term": null}, "salary_visible": false, "title_keywords": ["hr officer"], "responsibilities": ["regulations", "management", "policies", "hr", "review", "analysis", "procedures", "compliance", "communication", "recruitment", "report", "administration"], "requirements": {"degrees": ["degree or above", "bachelor"], "majors": ["business"], "languages": ["cantonese", "english", "mandarin"], "language_level": ["fluent", "good"], "hard_skills": ["problem-solving skills", "analysis"], "soft_skills": ["self-motivated", "good team player", "independent", "communication", "work under high pressure", "problem-solving skills", "proactive", "presentation"], "languages_combined": [{"language": "cantonese", "language_level": ["fluent", "good"]}, {"language": "english", "language_level": ["good"]}, {"language": "mandarin", "language_level": ["fluent", "good"]}]}, "experience_required": {"duration": [], "field": []}}, {"job_id": "100003009053866", "location_code": "hk", "company": "Arcelik Hitachi Home Appliance Sales Hong Kong Limited", "job_title": "Senior Officer, Human Resources (C&B)", "description": "Responsibilities:\n\nTo be responsible for performing HR operations, including but not limited to payroll and HRIS management, tax filing, benefits administration and analysis, attendance record, etc.\nManaging HRIS enhancement and collaborating with the headquarters, planning and executing UAT, and providing essential recommendations for the HRIS transformation process\nMaintaining employee database and ensuring all personal records are up-to-date and accurate\nAssisting in the formulation and implementation of HR policies and procedures in accordance with the company\u2019s rules & regulations\nSupporting the employment cycle includes but not limited to probation and performance management, internal staff movement, and termination or exit procedure\nCompiling regular HR related statistics and reports for management\u2019s review\nPerforming other ad hoc assignments or projects when assigned\nRequirements:\n\nBachelor\u2019s degree in HRM or Business related streams\nMinimum 5-year experience as a C&B specialist in MNC or sizable corporations\nSolid payroll knowledge and proficiency in HRIS with experiences in system transformation, preferably SAP\nProficient in Microsoft Excel application and sensitive to numbers\nFamiliar with Employment Ordinance and relevant legislations and regulations\nWell-organized, result-oriented, and able to handle multi tasks simultaneously\nPleasant personality, good team player with excellent interpersonal and communication skills\nGood command of both Cantonese and English\nLess experience may also be considered as HR Officer\nImmediately available is preferred\n\nWe offer:\n\nDouble-Pay\nDiscretionary Bonus\nMedical Benefits (Free Body Check in every year)\nDental Benefits\nStaff Purchase\nOn-the-job Training\nEducation Allowance\nFull Paid Sick Leave\nAnnual Leave Up to 18 Days\nBirthday Leave\nBirthday Coupon\nMarriage Leave\nCompany Picnic\n\nSuccessful candidates will receive an offer comprising a competitive package including attractive salary, retirement & medical benefits, leave provision, staff purchase discounts, training & development opportunities, etc.\n\nInterested parties, please send full resume with present and expected salary by clicking \"APPLY NOW\"\n\n**Application without present & expected salary will not be considered**\n\nPersonal data provided by job applicants will be treated in strict confidence.\nAll information will only be used for recruitment-related purposes.\n\nVisit us at\u00a0https://www.hitachi-homeappliances.com.hk\u00a0for more information", "employment_types": ["Full Time"], "selling_points": ["HR operations", "SAP HRIS transformation", "Stable business and working environment"], "locations": ["Shatin Area"], "categories": ["Admin & HR", "Others", "Compensation & Benefits", "HR Supporting Staff"], "post_time": "2022-01-17T07:41:01Z", "salary": {"currency": null, "max": null, "min": null, "period": "monthly", "term": null}, "salary_visible": false, "title_keywords": ["senior officer", "human resources"], "responsibilities": ["regulations", "operations", "database", "administration", "uat", "maintaining", "tax filing", "implementation", "reports", "attendance", "management", "review", "procedures", "executing", "payroll", "policies", "hr", "analysis", "ad hoc assignments", "planning"], "requirements": {"degrees": ["degree", "bachelor"], "majors": ["business"], "languages": ["cantonese", "english"], "language_level": ["good command"], "hard_skills": ["sap", "microsoft excel"], "soft_skills": ["communication skills", "good team player", "well-organized", "pleasant", "sensitive to numbers", "interpersonal", "result-oriented"], "languages_combined": [{"language": "cantonese", "language_level": ["good command"]}, {"language": "english", "language_level": ["good command"]}]}, "experience_required": {"duration": ["minimum 5-year"], "field": ["hr", "payroll"]}}, {"job_id": "100003009054872", "location_code": "hk", "company": "Nu Skin Enterprises Hong Kong, LLC", "job_title": "HR Officer / Senior HR Officer (HR Generalist)", "description": "Your Responsibilities:\n\nAct as a Business Partner to work closely with internal stakeholders in providing full spectrum of HR services including but not limited to talent acquisition, staff development, staff engagement, and etc.\nExplore sourcing network to build a robust talent pipeline, manage all talent sourcing activities including but not limited to sourcing, screening, interviewing, stakeholder engagement and offering.\nParticipate in identifying training needs to foster a supportive learning culture.\nParticipate in coordinating related staff events to enhance employee morale and maintain their awareness of company core value and engagement.\nParticipate in ad-hoc HR projects and new initiatives as assigned.\n\nOur Requirements:\n\nBachelor degree holder in Human Resources Management or any related qualification.\n3-4 years of relevant experience in Human Resources. Experience in recruitment agent will be an advantage.\nWell-versed in Employment Ordinance and other HR related regulations in Hong Kong.\nFlexible, proactive and detail-minded with strong communication skill.\nStrong sense of responsibilities and able to work independently and be a good team player.\nPerformance driven with can-do attitude and able to work under pressure.\nProficiency in both written and spoken English and Chinese. Putonghua is an advantage.;\nImmediately available is highly preferred\n\nWhat We Offer?\n\n\nFlexi-work\nMonthly product allowance\nQuarterly incentive bonus & annual performance bonus\nAnnual body checkup,\nFull protection of medical benefits (including dental),\nLife & accidental insurance,\nAnnual leave and other caring leaves.\nIf you are ready for a new challenge in your career, please click\u00a0\"Apply Now\"\u00a0to submit your application with expected salary.\n\n\n\nALL PERSONAL INFORMATION WE COLLECTED IS FOR THE PURPOSE OF RECRUITMENT ONLY\n\nPlease visit www.nuskin.com to find out more about us!", "employment_types": ["Full Time", "Permanent"], "selling_points": ["Flexi-working hours & work from home arrangement", "Caring Culture", "HR Business Partner"], "locations": ["Causeway Bay"], "categories": ["Admin & HR", "HR Supporting Staff", "Recruitment / Executive Search", "Training & Development"], "post_time": "2022-01-17T12:14:09Z", "salary": {"currency": null, "max": null, "min": null, "period": "monthly", "term": null}, "salary_visible": false, "title_keywords": ["hr", "hr officer"], "responsibilities": ["ad-hoc", "hr", "maintain"], "requirements": {"degrees": ["bachelor degree holder"], "majors": [], "languages": ["putonghua", "english", "chinese"], "language_level": ["advantage", "proficiency"], "hard_skills": [], "soft_skills": ["flexible", "detail-minded", "work independently", "good team player", "can-do attitude", "work under pressure", "communication skill", "proactive", "driven", "sense of responsibilities"], "languages_combined": [{"language": "putonghua", "language_level": ["advantage"]}, {"language": "english", "language_level": ["proficiency"]}, {"language": "chinese", "language_level": ["proficiency"]}]}, "experience_required": {"duration": ["3-4 years"], "field": ["recruitment", "relevant experience", "human resources"]}}, {"job_id": "100003009054243", "location_code": "hk", "company": "Social Big Data Limited", "job_title": "HR Executive / Senior HR Executive", "description": "Job responsibilities\n\nHandle full spectrum of HR functions including recruitment, C&B, performance management, employee relations and training\u00a0\nDevelop and execute HR initiatives and programs to support the business needs\nResponsible for HR data analysis and reports and ensure compliance are met in all HR areas\nAdminister monthly payroll, attendance and leave management, insurance and pension scheme, and tax returns\nParticipate in ad-hoc tasks and other HR related projects as required\nJob\u00a0Requirement\n\nDegree holder in\u00a0Business Administration/HR Management or related disciplines\nMinimum 3 years of HR & Admin experience\nMore relevant experience in will be considered as Senior HR Executive\nExcellent leadership with practical knowledge and strong problem-solving skills\nSound knowledge in HK Employment Ordinance and related regulations and laws\nSelf-motivated and proactive with good communication and interpersonal skills\nGood command of written and spoken English and Chinese\nShort notice period or immediate available is highly preferred\nCV without expected salary will not be considered\n\n", "employment_types": ["Full Time", "Permanent"], "selling_points": ["Minimum 3 years experience of working in HR", "All round HR & Admin experience", "5-day work week"], "locations": ["Kwun Tong"], "categories": ["Admin & HR", "Compensation & Benefits", "HR Supporting Staff", "Recruitment / Executive Search"], "post_time": "2022-01-17T08:57:31Z", "salary": {"currency": null, "max": null, "min": null, "period": "monthly", "term": null}, "salary_visible": false, "title_keywords": ["hr", "executive"], "responsibilities": ["tax", "attendance", "management", "hr", "ad-hoc tasks", "develop", "data analysis", "ensure compliance", "recruitment", "reports", "insurance", "payroll"], "requirements": {"degrees": ["degree holder"], "majors": ["related disciplines", "business administration"], "languages": ["english", "chinese"], "language_level": ["good command"], "hard_skills": ["problem-solving skills"], "soft_skills": ["self-motivated", "communication and interpersonal skills", "problem-solving skills", "proactive", "leadership"], "languages_combined": [{"language": "english", "language_level": ["good command"]}, {"language": "chinese", "language_level": ["good command"]}]}, "experience_required": {"duration": ["minimum 3 years"], "field": ["hr", "admin", "relevant experience"]}}, {"job_id": "100003009054250", "location_code": "hk", "company": "CHOW TAI FOOK JEWELLERY CO LTD", "job_title": "Assistant Officer, Recruitment", "description": "What You Own\nResponsible for the whole recruitment process including job advertisement posting, sourcing, screening, arranging & conducting interview, preparing hiring proposal and making offer\nFormulate and implement recruitment strategies & initiatives to attract talents\nWork proactively to develop close working relationships with both frontline / different departments to identify the manpower needs & requirements\nExplore potential and evaluate the effectiveness of advertising, social media, job fair, recruitment day and recruitment channels, etc.\nPrepare statistics, reports and presentation materials\nPerform other ad-hoc projects and tasks as assigned\nWho Will Thrive\nDegree holder in Human Resources Management, Psychology or any other disciplines are also welcome\nMinimum 3 years' experience in HR field with emphasis on recruitment, preferably in retail business\nFamiliar with HK Employment Ordinance, related regulations & HR practice\nIndependent, detail-minded, self-motivated, able to work in a fast-paced environment and a good team player\nMature with positive mind-set as well as strong interpersonal, communication & analytical skills\nWell-versed in using MS Office including Word, Excel and PowerPoint\nGood command of written and spoken English, Cantonese & Mandarin\nCandidate with more experience will be considered as Officer\nBenefits\n5-day work\nCompetitive salary, staff meal,\u00a0medical and dental insurance, life insurance\nVarious types of leave, e.g. Family-friendly leave, self-development leave,\u00a0Examination leave, marriage leave, birthday\u00a0leave, volunteer service leave, etc\nWe offer excellent career opportunities, attractive remuneration package & benefits to the right candidate.\u00a0Interested parties please apply by clicking \"Apply Now\" with a full resume stating the latest and expected salary.\nAll information collected will be used for recruitment purposes only", "employment_types": ["Full Time"], "selling_points": ["Talent Acquisition", "Identify and response to the hiring needs", "5-day work"], "locations": ["Mong Kok"], "categories": ["Admin & HR", "HR Supporting Staff", "Recruitment / Executive Search"], "post_time": "2022-01-17T08:57:32Z", "salary": {"currency": null, "max": null, "min": null, "period": "monthly", "term": null}, "salary_visible": false, "title_keywords": ["assistant officer"], "responsibilities": ["regulations", "social media", "management", "advertising", "job advertisement", "hr", "develop", "evaluate", "communication", "recruitment", "reports", "working relationships", "recruitment process", "ad-hoc projects"], "requirements": {"degrees": ["degree holder"], "majors": ["psychology"], "languages": ["cantonese", "english", "mandarin"], "language_level": ["good command"], "hard_skills": ["excel", "word", "powerpoint", "analytical skills", "ms office"], "soft_skills": ["detail-minded", "self-motivated", "good team player", "independent", "responsible", "fast-paced environment", "mature", "analytical skills", "communication", "interpersonal", "presentation", "positive"], "languages_combined": [{"language": "cantonese", "language_level": ["good command"]}, {"language": "english", "language_level": ["good command"]}, {"language": "mandarin", "language_level": ["good command"]}]}, "experience_required": {"duration": ["minimum 3 years"], "field": ["business", "hr", "retail", "recruitment"]}}, {"job_id": "100003009051776", "location_code": "hk", "company": "ALDI Services Asia Limited", "job_title": "HR Specialist (Training & Development) (m/f)", "description": "We invite now high caliber talent to apply for\u00a0HR Specialist (m/f)\u00a0to join our growing team in Hong Kong. This position supports our\u00a0Human Resources\u00a0function in daily business matters\u00a0within a fast-paced successful team.\n\n\n\nResponsibilities\n\n\nResponsible for full spectrum of Training & Development functions including training co-ordination, e-learning and staff performance management\nConduct training survey, facilitate training needs analysis, source training providers & suitable courses, organise whole year training schedule\nEnsure smooth delivery of training from enrolment to coordination of pre- and post-training logistics with internal and external parties\nMonitor training budgets and expenses throughout budget reviews and forecasts on a regular basis\nManage Learning Management System (LMS), be the system administrator to maintain and handle system issues as well as support for online course development\nReview and improve the Company training policies, workflow and procedures\nCollect training feedback for evaluation and continuous improvement\nMaintain and update training materials, training record, prepare training statistics and reports\nAssist new joiners\u2019 on boarding processes and new employee orientation training\nProvide administrative support to staff performance management\nSupport the HR Manager to design and execute staff training and development plan\nBack up for team members as well as assist in other ad-hoc Human Resources related tasks assigned by the Manager\n\n\u00a0Your Profile\n\nDegree Holder in Human Resources or other related Business discipline required.\nMinimum 3 years of Human Resources Business Partner experience gained in sizable organization.\nResponsible, highest level of integrity and trustworthiness.\nWell-versed in Hong Kong Employment Ordinance, MPF Regulations.\nAttention to details and good organizational, coordination and planning skills.\nExcellent communications and interpersonal skills, proactive team player.\nGood command of verbal & written English and fluency in Mandarin.\nProficiency in MS Office applications.\n\n\n\nKey Benefits of working at ALDI.\n\nMarket leading remuneration package\n\nRewarding, attractive remuneration package.\nGroup Medical Insurance covering dental and maternity* benefits .\n\nWork-life balance\n\nFull time, permanent position, 5-day-work-week.\n20 days of paid Annual Leave.\n\nBeing part of a pleasant, successful, growing business\n\nALDI\u2019s business is expanding, same for the Hong Kong Office with lots of opportunities for growth and development.\nPleasant working atmosphere where proactive communication, teamwork and collaboration is highly valued.\n\nPeople Focused\n\nStructured, comprehensive orientation and on-the-job training.\nALDI empowers our people allowing staff ownership of their areas of responsibilities.\n\nTrust and Integrity\n\nWE DO WHAT WE SAY\u00a0- \u00a0for us there is no grey area, we have robust business processes, procedures and strong governance in place.\nWe treat our staff members, customers, suppliers and service providers with trust and fairness as business partners.\n\n\u00a0* Maternity benefits only apply for female employees due to local Insurance policy\n\nHow to apply\u00a0\u00a0\n\nIf you are interested in applying for the job, we look forward to receiving your full application in English, including salary expectation and possible starting date. The application should be sent through JobsDB by clicking icon \u201cApply Now\u201d or addressed to ALDI HR,\u00a018/F, Millennium City 6, 392 Kwun Tong Road, Kwun Tong, Kowloon, Hong Kong\n\nALDI is an Equal Opportunity employer.\n\nAll personal data collected will be used for recruitment purposes only and be treated in strictest confidence and highest security level in accordance with Hong Kong Data (Privacy) Ordinance as well as ALDI internal Security Policy.\n\nNo part of this job content including but not limited to company information, logo and job description may be reproduced, presented, uploaded, transmitted, modified or distributed \u00a0in any form or by any means without prior permission of ALDI Services Asia Limited / ALDI Sourcing Asia Limited (\u201cthe Company\u201d). The Company reserves the right to take legal action on any unauthorized reproduction, presentation, upload, transmission, modification or distribution. Only applications submitted directly to the Company in response to this advertisement will be considered and any application received by the Company through unauthorized third party agents or via any other channels will not be considered.", "employment_types": ["Full Time", "Permanent"], "selling_points": ["Training & Development functions", "Maintain and update training materials", "Manage Learning Management System (LMS)"], "locations": ["Kwun Tong"], "categories": ["Admin & HR", "Others", "HR Supporting Staff", "Training & Development"], "post_time": "2022-01-17T01:03:20Z", "salary": {"currency": null, "max": null, "min": null, "period": "monthly", "term": null}, "salary_visible": false, "title_keywords": ["hr specialist"], "responsibilities": ["ad-hoc", "regulations", "internal and external parties", "budget", "design", "maintain", "plan", "evaluation", "provide administrative support", "expenses", "monitor", "logistics", "schedule", "reports", "management", "mpf", "review", "procedures", "budgets", "policies", "hr", "analysis", "coordination", "planning"], "requirements": {"degrees": ["degree holder"], "majors": ["business"], "languages": ["english", "mandarin"], "language_level": ["fluency", "good command"], "hard_skills": ["ms office", "analysis", "hong kong employment ordinance", "mpf regulations"], "soft_skills": ["planning skills", "responsible", "organizational", "integrity", "learning", "interpersonal skills", "coordination", "smooth", "attention to details", "team player", "proactive"], "languages_combined": [{"language": "english", "language_level": ["fluency", "good command"]}, {"language": "mandarin", "language_level": ["good command"]}]}, "experience_required": {"duration": ["minimum 3 years"], "field": ["sizable organization", "human resources", "business partner"]}}, {"job_id": "100003009052066", "location_code": "hk", "company": "SAPR JV", "job_title": "HR and Admin Assistant", "description": "Job Description:\n\nGeneral duties of Hr and Admin Assistant, such as data input and filing,\u00a0\nHandle full spectrum of HR functions which include but not limit to recruitment, compensation & benefits, training & development, and staff relations;\nScouring\u00a0CV and perform candidate search in the market to identify the right candidates;\nReview CVs and credentials for suitability of skills, experience, and knowledge in relation to position requirements using appropriate selection techniques;\nHandling ad-hoc assignments.\nRequirements:\n\nAssociate Degree/Degree holder in Human Resources Management or related discipline;\nProficiency in Microsoft Office;\nProficiency in Mandarin, English, and Cantonese, both spoken and written\nImmediate available or short notice is preferred\nWe provide attractive remuneration package and fringe benefits for the right candidate.\u00a0 Interested parties please send detailed resume with current & expected salaries via\u00a0\u201cApply Now\u201d.", "employment_types": ["Full Time"], "selling_points": [], "locations": ["Tung Chung"], "categories": ["Admin & HR", "Clerical / Admin Staff", "HR Supporting Staff"], "post_time": "2022-01-17T02:01:09Z", "salary": {"currency": null, "max": null, "min": null, "period": "monthly", "term": null}, "salary_visible": false, "title_keywords": ["admin assistant", "hr"], "responsibilities": ["hr", "data input"], "requirements": {"degrees": [], "majors": [], "languages": [], "language_level": [], "hard_skills": [], "soft_skills": [], "languages_combined": []}, "experience_required": {"duration": [], "field": []}}, {"job_id": "100003009053982", "location_code": "hk", "company": "Loto Interactive Limited", "job_title": "\u4eba\u529b\u8cc7\u6e90\u53ca\u884c\u653f\u5c08\u54e1HR & Admin", "description": "\u8077\u8cac\u63cf\u8ff0\uff1a\n1\u3001\u5354\u52a9\u4eba\u624d\u62db\u8058\uff0c\u5982\u7be9\u9078\u7c21\u6b77\uff0c\u9080\u7d04\u9762\u8a66\u53ca\u5b89\u6392\uff0c\u914d\u5408\u96c6\u5718\u9032\u884c\u62db\u8058\u6d3b\u52d5\uff1b\n2\u3001\u5354\u52a9\u54e1\u5de5\u95dc\u7cfb\u4e8b\u5b9c\uff0c\u5982\u54e1\u5de5\u7684\u5165\u8f49\u8abf\u96e2\u624b\u7e8c\uff0c\u5de5\u4f5c\u7c3d\u8b49\u7684\u8fa6\u7406\u7b49\uff1b\n3\u3001\u8ca0\u8cac\u884c\u653f\u5f8c\u52e4\u5de5\u4f5c\u7684\u57f7\u884c\uff0c\u5982\u8077\u5834\u5efa\u8a2d\u53ca\u7dad\u6301\uff0c\u8fa6\u516c\u7528\u54c1\u7b49\u91c7\u8cfc\uff0c\u5feb\u905e\u7dad\u8b77\uff0c\u5dee\u65c5\u6c34\u96fb\u8cbb\u5831\u92b7\u7b49\uff1b\n4\u3001\u517c\u4efb\u884c\u653f\u524d\u81fa\uff0c\u8ca0\u8cac\u96fb\u8a71\u7684\u63a5\u807d\u3001\u8f49\u63a5\uff0c\u53ca\u5404\u7a2e\u4f86\u96fb\u54a8\u8a62\u5de5\u4f5c\uff1b\n5\u3001\u8ca0\u8cac\u884c\u653f\u76f8\u95dc\u8cc7\u6599\u7684\u7ba1\u7406\u53ca\u76f8\u95dc\u6703\u8b70\u7684\u5b89\u6392\uff1b\n6\u3001\u9818\u5c0e\u4ea4\u8fa6\u7684\u5176\u4ed6\u5de5\u4f5c\u3002\n\n\u4efb\u8077\u8cc7\u683c\uff1a\n1\u3001\u672c\u79d1\u6216\u4ee5\u4e0a\u5b78\u6b77\uff0c\u5c08\u696d\u4e0d\u9650\uff0c2\u5e74\u4ee5\u4e0a\u4eba\u529b\u53ca\u884c\u653f\u5de5\u4f5c\u7d93\u9a57\uff1b\n2\u3001\u6709\u670d\u52d9\u610f\u8b58\uff0c\u7a4d\u6975\u71b1\u60c5\uff0c\u982d\u8166\u9748\u6d3b\uff0c\u61c9\u8b8a\u80fd\u529b\u5f37\uff0c\u80fd\u5feb\u901f\u63a5\u53d7\u65b0\u9bae\u4e8b\u7269\uff1b\n3\u3001\u8868\u9054\u80fd\u529b\u5f37\uff0c\u6709\u89aa\u548c\u529b\uff0c\u5177\u5099\u826f\u597d\u7684\u5718\u968a\u5354\u4f5c\u7cbe\u795e\uff1b\n4\u3001\u666e\u901a\u8a71\u53ef\u6e9d\u901a\uff0c\u7cb5\u8a9e\uff0c\u82f1\u8a9e\u80fd\u529b\u512a\u79c0\u3002", "employment_types": ["Full Time", "Permanent"], "selling_points": ["2\u5e74\u4ee5\u4e0a\u4eba\u529b\u53ca\u884c\u653f\u5de5\u4f5c\u7d93\u9a57", "\u666e\u901a\u8a71\u53ef\u6c9f\u901a\uff0c\u7cb5\u8a9e\uff0c\u82f1\u8a9e\u80fd\u529b\u512a\u79c0", "\u670d\u52d9\u610f\u8b58\u5f37"], "locations": ["Pok Fu Lam"], "categories": ["Admin & HR", "HR Supporting Staff"], "post_time": "2022-01-17T07:54:36Z", "salary": {"currency": null, "max": null, "min": null, "period": "monthly", "term": null}, "salary_visible": false, "title_keywords": ["admin"], "responsibilities": [], "requirements": {"degrees": [], "majors": [], "languages": [], "language_level": [], "hard_skills": [], "soft_skills": [], "languages_combined": []}, "experience_required": {"duration": [], "field": []}}, {"job_id": "100003009052499", "location_code": "hk", "company": "Fresenius Medical Care Asia-Pacific Ltd", "job_title": "HR Officer, Regional Projects", "description": "Summary of Role:\u00a0As a member of regional HR team, the incumbent will play a role in supporting regional projects, include but not limited to C&B, talent management and learning function, managing HR reporting and analytics for Asia as well as assisting in other HR initiatives.\n\nResponsibilities in Detail:\n\n\nCompensation & Benefit\n\n\nAct as the regional user in HR system for analytics\nCompile data, conduct analysis and prepare reports/dashboards for various C&B topics\nProvide support to projects such as job evaluation, salary benchmarking and other ad-hoc tasks\n\nTalent Management\n\nCollaborate with Global, Regional and Country TMOD teams to promote and execute the regional talent management, organizational development (OD) and learning initiatives\nManage Regional TM, OD, and learning program roll-out, including communications with key stakeholders, materials design, managing the end-to-end administration, etc.\nCompile data and conduct analysis and prepare metrics/dashboards for regular HR reporting for regional management view, including but not limited to attrition and headcount, performance management, engagement survey, C&B, etc.\nAssist in regional talent review process\nOversee the regional programs including CEO award\nResponsible for regional HR intranet\nProvide support to projects such as requisition e-approval, job evaluation and ad-hoc tasks\n\nAPHQ HR support\n\nGeneral HR admin duties include but not limited to filing, record keeping, data enhancement\nSupport on regional office events and engagement activities\nQualifications, Experience and Characteristics Required:\n\nHolder of Bachelor\u2019s degree with HR or related area, \u00a0with 1-2 year HR experience\nGood command of written and spoken English and Chinese\nGood interpersonal and communication skills\nIndependent, eager to learn with curiosity and proactive to go extra miles\nExcellent analytic skills; proficiency in MS Office especially Excel\nRelevant C&B experience is a plus\n\nWe offer a stimulating and multinational work environment, competitive salary and excellent career development opportunities in our growing organization.\nPlease submit your CV with current & expected salary and availability if interested.\n(Data collected will be used for recruitment purposes only. Candidates should consider their applications unsuccessful if failed to hear a reply within six weeks.)", "employment_types": ["Full Time", "Permanent"], "selling_points": ["Human Resources", "Regional", "Project Management"], "locations": ["Wan Chai"], "categories": ["Admin & HR", "HR Supporting Staff"], "post_time": "2022-01-17T03:14:14Z", "salary": {"currency": null, "max": null, "min": null, "period": "monthly", "term": null}, "salary_visible": false, "title_keywords": ["hr officer"], "responsibilities": ["collaborate with", "reporting", "management", "provide support", "communications with", "data", "hr", "analysis", "ad-hoc tasks", "teams", "design", "review", "communication", "recruitment", "career development", "evaluation", "prepare reports", "administration"], "requirements": {"degrees": ["degree", "bachelor"], "majors": [], "languages": ["english", "chinese"], "language_level": ["good command"], "hard_skills": ["excel", "plus", "analysis", "analytic skills", "go", "ms office"], "soft_skills": ["communication skills", "independent", "responsible", "organizational", "eager to learn", "learning", "proactive", "interpersonal"], "languages_combined": [{"language": "english", "language_level": ["good command"]}, {"language": "chinese", "language_level": ["good command"]}]}, "experience_required": {"duration": ["1-2 year"], "field": ["related", "hr"]}}, {"job_id": "100003009051025", "location_code": "hk", "company": "The Wharf Group", "job_title": "Human Resources Officer", "description": "Key Roles:\nas a member of the internal support team of the group\u2019s SAP SuccessFactors HRIS project to provide support to four HR teams and a Central Payroll team for new roll out and existing modules enhancement/maintenance\nparticipate in various tasks including but not limited to data preparation, UAT, liaison with consultants, user training and other related administrative support for HR related projects\nAnalyse HR data, headcount, payroll cost for budget and cost control and prepare reports for management's planning and control\nassist in\u00a0any\u00a0ad-hoc projects in benefits and compensation when assigned\nRequirements:\nDegree holders in Computing/Information Technology/HRM or relevant disciplines with at least 5 years' solid HR working experience of which at least 2 to 3 years in HRIS support. \u00a0Exposure in SAP SuccessFactors HRIS is preferred\nAnalytical, strong numeric sense with an advanced user of Microsoft Excel\nResponsible, organized and hardworking team player with good common sense and integrity\nable to present and communicate/present clearly and precisely\nfamiliarize with HR practices and labour ordinance\nproficient in both spoken and written English and Chinese\u00a0\nWe work 5 days per week.\n\n\nInterested parties, please click \"APPLY NOW\" and attach with your application letter and full resume.\n\nFor further information of the Wharf Group, please visit our website: www.wharfholdings.com\u00a0", "employment_types": ["Full Time", "Permanent"], "selling_points": [], "locations": ["Tsim Sha Tsui"], "categories": ["Admin & HR", "Compensation & Benefits", "HR Supporting Staff", "Information Technology (IT)", "Others"], "post_time": "2022-01-15T01:17:12Z", "salary": {"currency": null, "max": null, "min": null, "period": null, "term": null}, "salary_visible": false, "title_keywords": ["human resources officer"], "responsibilities": ["provide support", "cost", "management", "uat", "maintenance", "data", "administrative support", "control", "hr", "budget", "teams", "planning", "cost control", "prepare reports", "payroll", "analyse"], "requirements": {"degrees": [], "majors": [], "languages": [], "language_level": [], "hard_skills": ["maintenance", "sap"], "soft_skills": [], "languages_combined": []}, "experience_required": {"duration": [], "field": []}}, {"job_id": "100003009054044", "location_code": "hk", "company": "Hermes Asia Pacific Limited", "job_title": "HR Intern (Training Focus)", "description": "Position Overview\n\nReporting to the Retail Training Manager, the HR Intern is responsible for a full spectrum support for training and development functions.\n\n\nResponsibilities:\nTo provide full spectrum of training administrative support including but not limited to filing, updating training data, venue booking and set up, etc\nProvide logistic support on training programs\nAssist in preparing classroom training & e-learning materials\nAssist to prepare training statistics and report in regular basis\nAssist in coordinating internal staff activities/ events\n\nRequirements:\n\nYear 2 / 3 of University student in Business Management or related disciplines\nPassion in French culture / art / luxury retail is a plus\nExcellent in communication skills with good command in English and Chinese\nProactive and eager to take up new challenges\nConscientious and detail-minded\nPleasant personality and a team player\nAbility to work in a fast-paced environment and adapt to changes quickly\nBasic computer knowledge\nAble to work on flexible schedule\n\nInterested parties, please send your resume with expected salary and date of availability to:\u00a0recruitment.hap.hk@ hermes.com\u00a0or by clicking\u00a0\"Apply Now\"\n\n(Data collected will be treated in strict confidence and used for recruitment purpose only.)", "employment_types": ["Internship"], "selling_points": ["Pleasant personality and a team player", "Conscientious and detail-minded", "Excellent in communication skills"], "locations": ["Causeway Bay"], "categories": ["Admin & HR", "HR Supporting Staff", "Training & Development"], "post_time": "2022-01-17T08:11:21Z", "salary": {"currency": null, "max": null, "min": null, "period": "monthly", "term": null}, "salary_visible": false, "title_keywords": ["hr intern"], "responsibilities": ["data", "administrative support", "logistic support", "booking", "report"], "requirements": {"degrees": [], "majors": [], "languages": ["english", "french", "chinese"], "language_level": ["excellent", "good command"], "hard_skills": ["business management", "plus", "basic"], "soft_skills": ["detail-minded", "communication skills", "flexible", "passion in", "fast-paced environment", "pleasant", "conscientious", "team player", "proactive"], "languages_combined": [{"language": "english", "language_level": ["excellent", "good command"]}, {"language": "french", "language_level": []}, {"language": "chinese", "language_level": ["excellent", "good command"]}]}, "experience_required": {"duration": [], "field": []}}, {"job_id": "100003009051795", "location_code": "hk", "company": "CIAO International Limited (Best Mart 360\u00b0)", "job_title": "Senior Recruitment Officer", "description": "Responsibilities\n\nPlan, implement and manage the overall recruitment strategy\nSet hiring goals including timeframes and deliverables\nConducting interviews and sorting through applicants to fill open positions\nAssessing applicants' knowledge, skills, and experience to best suit open positions\nExplore potential and evaluate the effectiveness of advertising, social media, job fair, recruitment day and recruitment channels, etc.\nOrganize HR events (job fairs, career days, in-house recruitment events)\nAnalyze recruitment metrics, like time-to-hire and source of hire\nAssists HR Manager to drive People Development Programme including Management Trainee and Internship Programmes\nHandle ad hoc projects as required\n\nRequirements\n\nDegree holder in HR / business related disciplines\nWith at least 5 years of relevant HR generalist experience gained in sizable organization, FMCG experience is preferred\nGood interpersonal, communication and relationship management skills\nSelf-starter and with an ability to operate independently across a complex and matrix structure\nFamiliarity with social media recruiting\nWell versed in Excel and Chinese Word Processing\nImmediately available is highly preferred\nLess experience will be considered as\u00a0Recruitment Officer\n\nWe offer competitive package including 5-day work week, medical insurance and staff discount, etc.\u00a0 Interest parties, please send full resume with current and expected salary and date of availability by clicking \"Apply Now\".\n\n(Data collected will be used for recruitment purpose only)", "employment_types": ["Full Time"], "selling_points": ["Frontline Recruitment Focus", "Drive People Development Programme", "FMCG experience is preferred"], "locations": ["Ngau Tau Kok"], "categories": ["Admin & HR", "HR Supporting Staff", "Recruitment / Executive Search"], "post_time": "2022-01-17T01:13:11Z", "salary": {"currency": null, "max": null, "min": null, "period": "monthly", "term": null}, "salary_visible": false, "title_keywords": ["recruitment officer"], "responsibilities": ["social media", "management", "advertising", "hr", "evaluate", "recruitment strategy", "conducting interviews", "recruitment", "ad hoc projects", "plan"], "requirements": {"degrees": ["degree holder"], "majors": ["related disciplines", "business"], "languages": ["chinese"], "language_level": [], "hard_skills": ["excel", "chinese word processing"], "soft_skills": ["communication", "independently", "interpersonal"], "languages_combined": [{"language": "chinese", "language_level": []}]}, "experience_required": {"duration": ["at least 5 years"], "field": ["sizable organization", "fmcg", "recruitment", "hr generalist"]}}, {"job_id": "100003009051049", "location_code": "hk", "company": "The Wharf Group", "job_title": "Human Resources Assistant", "description": "provide recruitment and on boarding support in placement advertisement, response statistics and analysis, arranging interview and tests, on boarding arrangements and training courses enrollment and preparation as well as other ad hoc assignments\nDegree holders in HRM with at least one year relevant working experience, fresh graduates with good academic and communication skills are welcome\ngood basic knowledge on HK Employment Ordinance and other employment related ordinances\nresponsible, detail-minded, accurate and a team player\ngood spoken and written English and Chinese (please state your grade/level of English Language in HKCEE / HKDSE in your c.v.)\u00a0\nproficient in Microsoft Office and Putonghua\n\nWe work 5 days per week.\n\nInterested parties, please click \"APPLY NOW\" and attach with your application letter and full resume.\n\n\nFor further information of the Wharf Group, please visit our website: www.wharfholdings.com\u00a0", "employment_types": ["Full Time", "Permanent"], "selling_points": [], "locations": ["Tsim Sha Tsui"], "categories": ["Admin & HR", "Compensation & Benefits", "HR Supporting Staff", "Recruitment / Executive Search"], "post_time": "2022-01-15T19:11:46Z", "salary": {"currency": null, "max": null, "min": null, "period": null, "term": null}, "salary_visible": false, "title_keywords": ["human resources assistant"], "responsibilities": ["enrollment", "analysis", "communication", "recruitment", "ad hoc assignments", "arranging interview"], "requirements": {"degrees": ["degree", "hkdse"], "majors": [], "languages": ["putonghua", "english", "chinese"], "language_level": ["proficient", "good"], "hard_skills": ["analysis", "c", "basic", "microsoft office"], "soft_skills": ["detail-minded", "communication skills", "responsible", "team player", "accurate"], "languages_combined": [{"language": "putonghua", "language_level": ["proficient"]}, {"language": "english", "language_level": ["good"]}, {"language": "chinese", "language_level": ["good"]}]}, "experience_required": {"duration": ["at least one year"], "field": ["relevant working experience"]}}, {"job_id": "100003009054908", "location_code": "hk", "company": "Cathay Pacific Services Limited", "job_title": "Assistant People Manager", "description": "Responsibilities:\nAssist the superior to review and design C&B and rewards schemes and programs targeted to both corporate and frontline staff for maintaining market competitiveness and equitable\nAssist\u00a0the superior to drive for performance-based compensation approach.\nLead a small team and responsible for full spectrum of C&B duties including payroll administration taxation, leave management and employee\u2019s compensations\nDrive the enhancement of HR and associated system(s), closely monitor the system performance and communicate with internal and external parties for troubleshooting and enrichment\nReview, update and implement HR Policies and Procedures from time to time to make sure that all are in compliance with the local labour law and related legislative requirements and in best practices\nResponsible for medical plan and insurance renewal\nWork with stakeholder on budgeting, benchmarking, compensation review and annual salary review\n\u00a0Direct the preparation of relevant People Reporting (dashboards, C&B analytics)\nAny ad hoc Compensation & Benefits projects as assigned by Superior\nRequirements:\nUniversity graduate in Human Resources, Business Administration and related discipline\nMinimum 6 years all-rounded personnel experience including 2 years at supervisory level\nSolid hand on experience on C&B operations\nExperience in HRIS implementation is an advantage.\nExcellent communication and interpersonal skills\nPassion to work in a fast pacing and dynamic environment\nConversant with the Employment and related Ordinances\nGood command of both English and Chinese\nChange agent, customer focused, detail minded, proactive, execute with excellence and result-orientate\n\nTo apply, you may simply click the \"Apply Online\" of this position under our web site or\u00a0email your confidential resume with date of availability, current and expected salary to recruitment @cpsl.com.hk.\u00a0Applicants not contacted within 6 weeks may consider their applications unsuccessful.\u00a0\n\u00a0\n\nCathay Pacific Services Limited is an Equal Opportunities Employer. Personal data provided by job applicants will be used strictly in accordance with our personal data policy and for recruitment purposes only. Candidates not notified within six weeks may consider their application unsuccessful. All related information will be kept in our file for up to 24 months.", "employment_types": ["Full Time", "Permanent"], "selling_points": ["Drive the enhancement of HR and associated systems", "Lead and engage a small team to manage C&B duties", "Exposure in air cargo and logistic industry"], "locations": ["Airport Area"], "categories": ["Admin & HR", "Compensation & Benefits", "HR Director / Manager", "HR Supporting Staff"], "post_time": "2022-01-17T13:33:19Z", "salary": {"currency": null, "max": null, "min": null, "period": "monthly", "term": null}, "salary_visible": false, "title_keywords": ["manager", "assistant"], "responsibilities": ["budgeting", "internal and external parties", "troubleshooting", "design", "plan", "administration", "maintaining", "compliance", "monitor", "reporting", "management", "review", "procedures", "payroll", "communicate with", "taxation", "policies", "lead a small team", "hr", "insurance"], "requirements": {"degrees": [], "majors": [], "languages": [], "language_level": [], "hard_skills": [], "soft_skills": [], "languages_combined": []}, "experience_required": {"duration": [], "field": []}}, {"job_id": "100003009050351", "location_code": "hk", "company": "SGS Hong Kong Limited", "job_title": "Human Resources Officer (Payroll & HRIS)", "description": "Job Responsibilities:\n\nResponsible for full spectrum of Human Resources functions with main focuses on payroll calculation, leave management & C&B employee services\nPrepare various HR reports and analysis\nProvide support in HR projects such as performance management, HRIS transformation and implementation, etc\nAssist in ad-hoc duties as assigned\n\nJob Requirements:\n\nDegree holder in Human Resources Management, Business Administration or related disciplines\n3-5+ years of relevant experience with hands-on payroll & HRIS experience in sizeable company\nWell-versed in Labour Ordinance and other HR related ordinances\nOrganized, attentive to details and figures\nStrong sense of responsibility and able to work independently\nExcellent communication skills with good command of written & spoken English and Chinese\nProficiency in using Excel (Vlookup & Pivot Table)\nGood knowledge and experience in using HRIS is a must\nImmediate available is preferred\n\nWork Location:\u00a0 Ping Shan, Yuen Long (Shuttle Bus Provided)", "employment_types": ["Full Time", "Permanent"], "selling_points": ["Immediate available preferred", "Yuen Long area (Shuttle bus provided)", "Hands-on payroll & HRIS experience"], "locations": ["Yuen Long"], "categories": ["Admin & HR", "Others", "Compensation & Benefits", "HR Supporting Staff"], "post_time": "2022-01-15T03:51:02Z", "salary": {"currency": null, "max": null, "min": null, "period": "monthly", "term": null}, "salary_visible": false, "title_keywords": ["human resources officer"], "responsibilities": ["management", "provide support", "analysis", "hr", "hr reports", "implementation", "ad-hoc duties", "payroll", "human resources functions"], "requirements": {"degrees": ["degree holder"], "majors": ["related disciplines", "business administration"], "languages": ["english", "chinese"], "language_level": ["excellent", "good command"], "hard_skills": ["excel", "vlookup", "pivot table"], "soft_skills": ["organized", "work independently", "communication skills", "attentive to details", "sense of responsibility", "hands-on"], "languages_combined": [{"language": "english", "language_level": ["excellent", "good command"]}, {"language": "chinese", "language_level": ["excellent", "good command"]}]}, "experience_required": {"duration": ["5+ years"], "field": ["payroll", "relevant experience"]}}, {"job_id": "100003009054909", "location_code": "hk", "company": "Cathay Pacific Services Limited", "job_title": "People Officer", "description": "Responsibilities:\nSupport full spectrum of HR functions included but not limited to recruitment,\u00a0compensation and benefit, communication, employee relations, and etc.\u00a0Main duties are:\nrecruitment logistics arrangement\nstaff event coordination & support\u00a0\nuniform and locker management\nstaff profile and personnel files handling\u00a0\nmedical scheme administration\nHR reports preparation\nHandle ad hoc project as assigned by immediate supervisor\u00a0\n\u00a0Less experience will be considered as People Assistant\u00a0\n\n\u00a0Requirements:\n\nDiploma holder in Human Resources Management or related discipline and above\n1- 2 years working experience in Human Resources field is preferable, fresh graduates are also welcome\u00a0\n\u00a0Well conversant in Employment Ordinance and other related legislation\n\u00a0Proficient in both written and spoken English and Chinese\n\u00a0Able to work independently be proactive and be a good team player\n\u00a0Good interpersonal and communication skills\n\u00a0Customer-focused, detailed minded and outgoing\n\u00a0Proficient in MS Office applications\n\n\n\nTo apply,\u00a0you may\u00a0email your confidential resume with date of availability, current and expected salary to\u00a0recruitment @cpsl.com.hk.\u00a0Applicants not contacted within 6 weeks may consider their applications unsuccessful.\n\nCathay Pacific Services Limited is an Equal Opportunities Employer. Personal data provided by job applicants will be used strictly in accordance with our personal data policy and for recruitment purposes only. Candidates not notified within six weeks may consider their application unsuccessful. All related information will be kept in our file for up to 24 months.\n\n\n\n", "employment_types": ["Full Time", "Permanent"], "selling_points": ["Provide support to full spectrum of HR functions", "Wider exposures in air cargo industry", "Fresh graduates are also welcome"], "locations": ["Airport Area"], "categories": ["Admin & HR", "Compensation & Benefits", "HR Supporting Staff", "Recruitment / Executive Search"], "post_time": "2022-01-17T13:34:02Z", "salary": {"currency": null, "max": null, "min": null, "period": "monthly", "term": null}, "salary_visible": false, "title_keywords": ["officer"], "responsibilities": ["management", "ad hoc", "logistics arrangement", "hr", "hr reports", "communication", "recruitment", "coordination", "administration"], "requirements": {"degrees": ["diploma holder"], "majors": [], "languages": ["english", "chinese"], "language_level": ["proficient"], "hard_skills": ["ms office"], "soft_skills": ["outgoing", "communication skills", "good team player", "work independently", "customer-focused", "proactive", "interpersonal", "detailed"], "languages_combined": [{"language": "english", "language_level": ["proficient"]}, {"language": "chinese", "language_level": ["proficient"]}]}, "experience_required": {"duration": ["1- 2 years"], "field": ["human resources"]}}, {"job_id": "100003009052078", "location_code": "hk", "company": "McQueen & Pitt Consultants Limited", "job_title": "Assistant Human Resources Manager / Senior Human Resources Officer", "description": "\n\nJob Responsibilities:\nProvide a full range of professional HR services and advice including but not limited to recruitment & selection, compensation & benefits, and employee relation.\nPerform end-to-end processes\u00a0related to talent acquisition.\nWork closely with line managers to provide professional advice on recruitment strategies/manpower planning.\nHandle employee issues including employment visa, exit-interview and other employment related matters.\nPrepare HR reports for management review.\nParticipate in ad hoc projects within the Company as assigned.\n\nJob Requirements:\u00a0\n\nDegree holder in Human Resources, Business Administration, or any related disciplines.\n\u00a0At least 5 years of relevant HR generalist experience.\nWell-versed in Employment Ordinance and other related legislation in Hong Kong.\n\u00a0Self-motivated and able to perform multi-tasks.\n\u00a0Good command of written and spoken English and Chinese.\n\u00a0Immediate available is preferred.\n\n**Candidates with less experience will be considered as a Senior HR Officer**\n\nInterested parties, please send us your latest resume with present salary, expected salary and availability by clicking\u00a0'Apply Now'.\u00a0\u00a0\n\nAll applications will be treated in the strictest confidence and personal data collected will be used for recruitment purposes only.\u00a0", "employment_types": ["Permanent"], "selling_points": ["5-days work", "Hands on experience (Recruitment and C&B)", "Attractive remuneration package"], "locations": ["Central"], "categories": ["Admin & HR", "HR Supporting Staff"], "post_time": "2022-01-17T02:02:40Z", "salary": {"currency": null, "max": null, "min": null, "period": "monthly", "term": null}, "salary_visible": false, "title_keywords": ["senior human resources officer", "assistant human resources manager"], "responsibilities": ["hr", "hr reports", "recruitment", "ad hoc projects", "management review", "planning"], "requirements": {"degrees": ["degree holder"], "majors": ["related disciplines", "business administration"], "languages": ["english", "chinese"], "language_level": ["good command"], "hard_skills": [], "soft_skills": ["self-motivated", "multi-tasks"], "languages_combined": [{"language": "english", "language_level": ["good command"]}, {"language": "chinese", "language_level": ["good command"]}]}, "experience_required": {"duration": ["at least 5 years"], "field": ["hr", "hr generalist"]}}, {"job_id": "100003009051479", "location_code": "hk", "company": "BDO", "job_title": "Human Resources Officer (6 month contract (subject to renewal)  / Maternity Cover)", "description": "Responsibilities:\n\nHandle a full range of C&B duties including but not limited to payroll calculation, MPF administration and tax returns filing\nMaintain HR database\nHandle staff movement and separation process\nHandle employees\u2019 compensation cases\nPrepare regular/ad-hoc HR reports and analysis for management review\nParticipate in HR-related projects and initiatives as assigned\n\nRequirements:\n\nAssociate Degree Holder or above\n2-3 years of relevant experience\nGood spoken and written English and Chinese\nProficiency in MS Office\nA good team player with effective communication and interpersonal skills\nBe passionate for providing exceptional quality service and striving for exceeding clients\u2019 expectations\n6 month contract, subject to renewal\n\nWe are an equal opportunity employer, and offer excellent prospects and career development for the right candidate.\u00a0 Interested parties please send your application\u00a0with full career history, current and expected salary by clicking\u00a0Apply Now.\n\nApplications will be treated in strict confidence. Personal data collected will be used for recruitment purposes only.\n", "employment_types": ["Temporary", "Contract"], "selling_points": ["Provide support in C&B activities", "Support in HR-related projects as assigned", "6 month contract, subject to renewal"], "locations": ["Sheung Wan"], "categories": ["Admin & HR", "Compensation & Benefits", "HR Supporting Staff"], "post_time": "2022-01-16T03:50:22Z", "salary": {"currency": null, "max": null, "min": null, "period": "monthly", "term": null}, "salary_visible": false, "title_keywords": ["human resources officer"], "responsibilities": ["tax", "ad-hoc", "mpf", "hr", "analysis", "hr reports", "maintain", "database", "payroll", "management review", "administration"], "requirements": {"degrees": ["associate degree"], "majors": [], "languages": ["english", "chinese"], "language_level": ["good"], "hard_skills": ["ms office"], "soft_skills": ["passionate", "good team player", "communication and interpersonal skills"], "languages_combined": [{"language": "english", "language_level": ["good"]}, {"language": "chinese", "language_level": ["good"]}]}, "experience_required": {"duration": ["2-3 years"], "field": ["relevant experience"]}}, {"job_id": "100003009054025", "location_code": "hk", "company": "aalis", "job_title": "Administrative Officer - 5 day work", "description": "Job Responsibilities\n\nProvide Comprehensive administrative support\nProvide full spectrum of personal and secretarial support\nPreparing daily reports\nHandle all internal claims and invoices in the correct process, ensuring necessary supporting materials and concurrence\nPrepare regular admin related statistics and reports for management review\nHandle all administration tasks and ad-hoc projects\n\nJob Requirements\n\nHigher Diploma / Bachelor\u2019s degree holder\nCommunicate politely and sensitively, ensuring that any issues are followed up promptly\nProficient in Microsoft excel application and sensitive to numbers\nGood organisation, reporting and communication skills\nResult and detail oriented, efficient and able to multi tasks\nGood command of spoken and written English and Chinese\nImmediately available is preferred\n\n\nCompany Benefits:\n\n5-day work\nPaid annual leave; Bank holiday; Birthday off; Marriage leave\nFriendly company culture; stylish working environment; convenience location\nStaff purchase discount\nYear end discretionary bonus\nGreat promotion opportunities\n\nWe offer attractive remuneration and benefit package to the right candidate.\n\nInterested parties please send your full resume with current and expected salary, date of availability to\u00a0Human Resources Department by clicking \"Apply Now\"\n\n*Personal data collected is strictly confidential and will only be used for recruitment related purpose.", "employment_types": ["Full Time", "Permanent"], "selling_points": ["All-round administrative support", "Good organisation and reporting  skills", "Immediately available is preferred"], "locations": ["Aberdeen"], "categories": ["Admin & HR", "Administration / Operation Manager", "Clerical / Admin Staff", "HR Supporting Staff"], "post_time": "2022-01-17T08:07:27Z", "salary": {"currency": null, "max": null, "min": null, "period": "monthly", "term": null}, "salary_visible": false, "title_keywords": ["administrative officer"], "responsibilities": ["invoices", "administrative support", "reports", "secretarial support", "daily reports", "ad-hoc projects", "management review", "administration"], "requirements": {"degrees": ["diploma", "bachelor", "degree holder"], "majors": [], "languages": ["english", "chinese"], "language_level": ["good command"], "hard_skills": ["microsoft excel"], "soft_skills": ["efficient", "communication skills", "detail oriented", "organisation", "sensitive to numbers"], "languages_combined": [{"language": "english", "language_level": ["good command"]}, {"language": "chinese", "language_level": ["good command"]}]}, "experience_required": {"duration": [], "field": []}}, {"job_id": "100003009052955", "location_code": "hk", "company": "Grosswell Ltd", "job_title": "HR & Admin Assistant", "description": "Responsibilities:\n\nAssist in all-round human resources and office administration functions\nBack up receptionist when necessary\nPerform in any other ad hoc tasks as assigned\n\nRequirements:\n\nAssociate Degree\u00a0or above in Human Resources & Administration or\u00a0relevant disciplines\u00a0\nFluent in both spoken and written English, Mandarin and Cantonese\nProficiency in Excel, MS Word, Chinese Word Processing and HRMS\n2 years' relevant experience in\u00a0Human Resources\u00a0is preferable\nFresh graduate will also be considered\nImmediate available is highly preferred\u00a0\nInterested parties, please send email to obtain an application form.", "employment_types": ["Full Time", "Part Time"], "selling_points": [], "locations": ["Yau Tsim Mong Area"], "categories": ["Admin & HR", "Clerical / Admin Staff", "Compensation & Benefits", "HR Supporting Staff"], "post_time": "2022-01-17T04:41:23Z", "salary": {"currency": null, "max": null, "min": null, "period": "monthly", "term": null}, "salary_visible": false, "title_keywords": ["hr & admin assistant"], "responsibilities": ["office administration", "ad hoc tasks"], "requirements": {"degrees": ["degree or above", "fresh graduate"], "majors": [], "languages": ["cantonese", "english", "chinese", "mandarin"], "language_level": ["proficiency", "fluent"], "hard_skills": ["excel", "chinese word processing", "ms word"], "soft_skills": [], "languages_combined": [{"language": "cantonese", "language_level": ["fluent"]}, {"language": "english", "language_level": ["fluent"]}, {"language": "chinese", "language_level": ["proficiency"]}, {"language": "mandarin", "language_level": ["fluent"]}]}, "experience_required": {"duration": ["2 years"], "field": ["relevant experience", "human resources"]}}, {"job_id": "100003009047561", "location_code": "hk", "company": "Longshore Ltd", "job_title": "Human Resources & Administration Officer", "description": "Job Responsibilities\n\nPerform end to end HK & China recruitment from drafting job advertisement, screening resumes, arranging and conducting interview to offer delivery and on boarding\nManage and review various sourcing channels\nUpdate personal details and attendance record in HR systems\nHandle administrative duties, e.g. organize company events\nPrepare regular payroll reports\nHandle ad hoc HR projects and tasks as required \u00a0\nTravel to CHN office on occasion\n\nJob Requirements\n\nForm 7 or above in Human\u00a0Resources or related disciplines\nAt least 3 years related experience\nWell versed with HK Employment Ordinance and other related legislation\nHas knowledge about PRC Labour Law is preferable but not a must\nProficient in MS Office\nMature, stable, hardworking and\u00a0good communication skills and interpersonal skills\nAble to perform in a fast-paced and dynamic environment\nCandidates with less experience will be considered as Assistant Human Resources and Administration Officer\u00a0\nImmediate available is preferred\nAlternate Saturday, Double pay, Medical, Annual leave, Bonus", "employment_types": ["Full Time", "Permanent"], "selling_points": ["Great opportunity to explore", "At least 3 years related exp, Immediate available", "Double pay, Medical, Annual leave, Bonus"], "locations": ["Hung Hom"], "categories": ["Admin & HR", "Compensation & Benefits", "HR Supporting Staff", "Recruitment / Executive Search"], "post_time": "2022-01-14T03:27:50Z", "salary": {"currency": null, "max": null, "min": null, "period": "monthly", "term": null}, "salary_visible": false, "title_keywords": ["administration officer", "human resources"], "responsibilities": ["attendance", "ad hoc", "job advertisement", "hr", "review", "systems", "screening resumes", "recruitment", "administrative duties", "reports", "payroll"], "requirements": {"degrees": [], "majors": [], "languages": [], "language_level": [], "hard_skills": ["dynamic", "ms office"], "soft_skills": ["communication skills", "dynamic environment", "mature", "interpersonal skills", "stable", "hardworking"], "languages_combined": []}, "experience_required": {"duration": ["at least 3 years"], "field": ["related", "human resources", "administration"]}}, {"job_id": "100003009052118", "location_code": "hk", "company": "Purapharm Corporation Limited", "job_title": "Administrative Assistant (Full time/Part time)", "description": "Responsibilities:\n\nPerform reception duties including telephone calls, greeting and serving visitors in professional manner;\nProvide general office administrative work and clerical supports;\nSupport ad-hoc assignments.\n\nRequirements:\u00a0\n\nDiploma in Hospitality or related disciplines preferred;\n1 year's working experience in service field preferred, fresh graduate will also be considered;\nStrong sense of responsibility, proactive, energetic, pleasant and customer-oriented;\nGood PC knowledge in MS Office & Chinese Word Processing;\nProficiency in both written & spoken English and Chinese including Mandarin;\nImmediate available is preferred.\n\nWorking Location: Hong Kong Science Park, Tai Po\n\nWe offer 5-day working week and an attractive remuneration package. Interest parties please click\u00a0Apply Now. For company details, please visit\u00a0www.purapharm.com.\n\nOur Company is an equal opportunity employer. All personal data collected will be used for recruitment purpose only, while the personal data of the unsuccessful applicants will be destroyed within 6 months after the recruitment process.", "employment_types": ["Full Time", "Permanent"], "selling_points": ["Fresh graduate will be considered", "Reception and general administrative duties", "Customer-oriented"], "locations": ["Tai Po Area"], "categories": ["Admin & HR", "Clerical / Admin Staff", "Receptionist", "HR Supporting Staff"], "post_time": "2022-01-17T02:09:41Z", "salary": {"currency": null, "max": null, "min": null, "period": "monthly", "term": null}, "salary_visible": false, "title_keywords": ["administrative assistant"], "responsibilities": ["ad-hoc assignments", "professional manner", "administrative work"], "requirements": {"degrees": ["diploma", "fresh graduate"], "majors": ["related disciplines", "hospitality"], "languages": ["english", "chinese", "mandarin"], "language_level": ["proficiency", "good"], "hard_skills": ["pc knowledge", "chinese word processing", "ms office"], "soft_skills": ["proactive", "sense of responsibility", "pleasant", "customer-oriented", "energetic"], "languages_combined": [{"language": "english", "language_level": ["proficiency"]}, {"language": "chinese", "language_level": ["proficiency", "good"]}, {"language": "mandarin", "language_level": []}]}, "experience_required": {"duration": ["1 year"], "field": []}}, {"job_id": "100003009051361", "location_code": "hk", "company": "Raze Technology Limited", "job_title": "Human Resources Officer (Recruitment Focus)", "description": "The Role\nTo cope with our aggressive growth and expansion plan, we are inviting high caliber individuals to join our fast growth team.\u00a0 You will have a chance to work at a fast-paced mission driven company that brings material science to life and benefit the mass.\u00a0 We are bringing business disruption and new hygiene standard to the world with the introduction of new photocatalyst products and services. With the continuous R&D and business innovation, we are thrilled to develop the next generation technology that safeguards everyday life.\u00a0\u00a0\n\nResponsibilities\n\nCommunicate and manage the recruitment requests of BUs/Hiring Managers;\nDevelop and manage recruitment process effectively from posting job advertisements, screening resumes, conducting interviews, confirming offer and recruitment project management;\nProvide end-to-end recruitment process to ensure hiring needs are fulfilled timely and effectively, support hiring managers to further develop and strengthen the talent pool;\nDevelop effective hiring channels and methodologies for recruitment pipeline;\nPrepare hiring tracking reports and liaise with hiring manager on the progress;\nPrepare HR reports and data analysis on staff turnover, retention, career development, etc;\nAssist in any other HR duties as assigned.\nRequirements\n\nDegree in Human Resources Management, Business Management or related disciplines;\nMinimum 3 years of solid recruiting experience in fast-paced business environment with proven expertise from FMCG or consumer healthcare market is a MUST;\nMature, self-motivated, ability to prioritize multiple tasks and work under pressure;\nStrong PC skills, well-versed in Microsoft applications and Chinese word processing\nImmediate available is highly preferred;\nFluent in written and spoken English, Cantonese and Mandarin.\nWe offer the right candidate attractive remuneration package and outstanding prospects for career advancement and development.\u00a0 The right candidate will progress career in a forward thinking and dynamic business with exciting growth plans.\u00a0 If you are qualified and interested, please send your full resume with current & expected salary and availability by clicking \"APPLY\".\n\nAll information collected will be treated as strictly confidential and used for recruitment purposes only. (Only shortlisted candidates will be notified)", "employment_types": ["Full Time", "Permanent"], "selling_points": [], "locations": ["Southern Area"], "categories": ["Admin & HR", "HR Supporting Staff", "Recruitment / Executive Search"], "post_time": "2022-01-15T11:09:02Z", "salary": {"currency": null, "max": null, "min": null, "period": "monthly", "term": null}, "salary_visible": false, "title_keywords": ["human resources officer"], "responsibilities": ["confirming offer", "recruitment project management", "advertisements", "hr reports", "hr duties", "develop", "data analysis", "screening resumes", "conducting interviews", "recruitment", "reports", "career development", "liaise with", "recruitment process", "tracking"], "requirements": {"degrees": ["degree"], "majors": ["related disciplines", "business"], "languages": ["cantonese", "english", "chinese", "mandarin"], "language_level": ["fluent"], "hard_skills": ["business management", "pc skills", "chinese word processing", "microsoft applications"], "soft_skills": ["self-motivated", "multiple tasks", "prioritize", "mature", "business environment", "work under pressure"], "languages_combined": [{"language": "cantonese", "language_level": ["fluent"]}, {"language": "english", "language_level": ["fluent"]}, {"language": "chinese", "language_level": []}, {"language": "mandarin", "language_level": ["fluent"]}]}, "experience_required": {"duration": ["minimum 3 years"], "field": ["healthcare", "business", "fmcg"]}}, {"job_id": "100003009052711", "location_code": "hk", "company": "Quality HealthCare Medical Services Ltd", "job_title": "Assistant Officer, Business Partner (Part-time, 5 Days)", "description": "In the heart of the role:\n\n\n\nProvide support to pre-employment logistics such as candidate document vetting, contract preparation and onboarding settlement\nAssist in handling administrative duties, such as staff probation and send out communication emails regarding staff movement\nParticipate in ad hoc duties as assigned\n\nDesired Qualification & Experience:\n\n\n\nHigh Diploma or above\nOrganized, attentive to details and multi-tasking;\nWilling to learn and strong sense of responsibilities\nWell organized, good communication and interpersonal skills, attentive to details and able to work independently\nStrong computer literacy in MS Office\nGood command of written and spoken English and Chinese\nImmediately available is preferred\n\n(All applications will be treated in strict confidence and data collected will be used for recruitment purposes only)", "employment_types": ["Part Time", "Contract"], "selling_points": ["End-to-end admin support", "High Diploma or above", "Organized, attentive to details and multi-taskin"], "locations": ["Kowloon Bay"], "categories": ["Admin & HR", "Clerical / Admin Staff", "Others", "HR Supporting Staff"], "post_time": "2022-01-17T03:46:49Z", "salary": {"currency": null, "max": null, "min": null, "period": "monthly", "term": null}, "salary_visible": false, "title_keywords": ["assistant officer"], "responsibilities": ["ad hoc duties", "provide support", "pre-employment", "data", "communication", "administrative duties", "logistics", "recruitment"], "requirements": {"degrees": ["high diploma or above"], "majors": [], "languages": ["english", "chinese"], "language_level": ["good command"], "hard_skills": ["ms office"], "soft_skills": ["organized", "work independently", "confidence", "attentive to details", "willing to learn", "well organized", "communication", "computer literacy", "multi-tasking", "communication and interpersonal skills", "sense of responsibilities"], "languages_combined": [{"language": "english", "language_level": ["good command"]}, {"language": "chinese", "language_level": ["good command"]}]}, "experience_required": {"duration": [], "field": []}}, {"job_id": "100003009053953", "location_code": "hk", "company": "Able Engineering Company Limited", "job_title": "Assistant Clerical Officer", "description": "Level 2 or equivalent or above in five subjects including Mathematics in the Hong Kong Diploma of Secondary Education Examination (HKDSEE), or equivalent; or\nLevel 2 / Grade E or above in five subjects including Mathematics in the Hong Kong Certificate of Education Examination (HKCEE), or equivalent;\nMet the language proficiency requirement of Level 2 or above in Chinese Language and English Language in HKDSEE or HKCEE, or equivalent; and\nChinese word processing speed of 20 words per minute and English word processing speed of 30 words per minute and knowledge in the application of common business software\n\nWe offer competitive salary package and career development opportunity to the successful candidate. Interested parties may send your full resume, present and expected salary, available date and contact number by clicking \"Apply Now\".\n\n\n\nTo visit our website for more information: www.ableeng.com.hk\n\n(As an Equal Opportunities Employer, Able is committed to eliminating discrimination in employment. The vacancy advertised is open to all applicants meeting the basic entry requirement irrespective of their disability, sex, marital status, pregnancy, age, family status, sexual orientation or race etc. Applicants not hearing from us within 6 months may consider their applications unsuccessful. Personal data collected will be used for recruitment related purposes only.)", "employment_types": ["Full Time"], "selling_points": [], "locations": ["Not Specified"], "categories": ["Admin & HR", "Administration / Operation Manager", "Clerical / Admin Staff", "HR Supporting Staff"], "post_time": "2022-01-17T07:50:21Z", "salary": {"currency": null, "max": null, "min": null, "period": "monthly", "term": null}, "salary_visible": false, "title_keywords": ["officer", "assistant"], "responsibilities": ["software"], "requirements": {"degrees": ["certificate", "diploma", "secondary education"], "majors": ["mathematics"], "languages": ["english", "chinese"], "language_level": ["proficiency"], "hard_skills": ["business software", "chinese word processing", "word processing", "words"], "soft_skills": [], "languages_combined": [{"language": "english", "language_level": ["proficiency"]}, {"language": "chinese", "language_level": ["proficiency"]}]}, "experience_required": {"duration": [], "field": []}}, {"job_id": "100003009052452", "location_code": "hk", "company": "Foodgears Industrial International Limited", "job_title": "Assistant Administration Officer/ Administration Officer (5-days work)", "description": "Job Duties:\u00a0\n\nHandle & review full spectrum of office administration and HR functions\nProvide secretarial and administrative support\nFamiliar with tickets and hotels reservation\nOrganize, maintain and update reports, records, and filing systems\nFollow up ad-hoc projects independently with self-initiative and strong sense of responsibility\nCoordinate with different departments among the company\n\nRequirements:\n\nUniversity Graduates\nGood command of spoken and written Chinese & English\nAble to communicate effectively with a wide range of people\nSelf-motivated with positive working attitude\nGood team player, hardworking & willing to work under pressure\nImmediate available is an advantage\nAt least 3 years of HR / Administration related experience", "employment_types": ["Full Time", "Permanent"], "selling_points": [], "locations": ["Wong Tai Sin Area"], "categories": ["Admin & HR", "Clerical / Admin Staff", "Others", "HR Supporting Staff"], "post_time": "2022-01-17T03:04:14Z", "salary": {"currency": null, "max": null, "min": null, "period": "monthly", "term": null}, "salary_visible": false, "title_keywords": ["administration officer", "assistant administration officer"], "responsibilities": ["administrative support", "office administration", "hr", "review", "systems", "coordinate with", "maintain", "reports", "ad-hoc projects"], "requirements": {"degrees": [], "majors": [], "languages": ["english", "chinese"], "language_level": ["good command"], "hard_skills": [], "soft_skills": ["self-motivated", "good team player", "positive working attitude", "hardworking", "work under pressure"], "languages_combined": [{"language": "english", "language_level": ["good command"]}, {"language": "chinese", "language_level": ["good command"]}]}, "experience_required": {"duration": ["at least 3 years"], "field": ["related", "hr", "administration"]}}, {"job_id": "100003009050305", "location_code": "hk", "company": "Asia Beauty Concepts Limited", "job_title": "Human Resources Officer", "description": "Job Responsibilities\n\nAssist in handling compensation & benefits functions including payroll, tax returns, final payment, internal transfer, MPF, group insurances related issues.\nMaintain and update personnel details in HR system, time attendance system and filing system\nHandle general enquires related to HR Policies and procedures to ensure alignment with operation needs and in compliance with Employment Ordinance\nGenerate and prepare related HR reports for the management reviews\nProvide administrative and clerical support to HR Team to ensure smooth operation\nPerform ad-hoc duties assigned by HR Manager\n\nRequirements\n\nDegree in Human Resources Management or related disciplines\nAt least 1-2 years solid experience in HR (C&B Focus), preferably in\u00a0beauty, retail industry\nWell versed in Hong Kong Employment Ordinance and other HR related ordinances\nAttentive to details, sensitive in number, independent and good team-player\nGood interpersonal and communication skills\nProficient in MS Word, Excel, PowerPoint and Chinese Word Processing\nImmediate available is preferred\n\nInterested parties please send your application letter, resume, expected salary and availability to the \"Apply Now\" button.\n\n\u00a0* Data collected will be used for recruitment purpose only. It may be transferred to other companies of the Group to see if suitable vacancies arise. Applicants not contacted within 6 weeks may consider their application unsuccessful. The information will be destroyed.", "employment_types": ["Full Time", "Permanent"], "selling_points": ["Payroll, C&B, Personnel Admin", "5 days work week, Free Goods, Birthday Leave", "Retail / Beauty industry"], "locations": ["Causeway Bay"], "categories": ["Admin & HR", "Clerical / Admin Staff", "Compensation & Benefits", "HR Supporting Staff"], "post_time": "2022-01-14T10:05:25Z", "salary": {"currency": null, "max": null, "min": null, "period": "monthly", "term": null}, "salary_visible": false, "title_keywords": ["human resources officer"], "responsibilities": ["tax", "attendance", "management", "mpf", "policies", "hr", "compliance", "procedures", "hr reports", "payment", "maintain", "administrative and clerical support", "ad-hoc duties", "insurances", "payroll"], "requirements": {"degrees": ["degree"], "majors": ["related disciplines"], "languages": ["chinese"], "language_level": ["proficient"], "hard_skills": ["excel", "hong kong employment ordinance", "chinese word processing", "powerpoint", "focus", "ms word"], "soft_skills": ["communication skills", "independent", "attentive to details", "team-player", "sensitive", "focus", "interpersonal"], "languages_combined": [{"language": "chinese", "language_level": ["proficient"]}]}, "experience_required": {"duration": ["at least 1-2 years"], "field": ["retail industry", "hr", "beauty"]}}, {"job_id": "100003009048107", "location_code": "hk", "company": "Hong Kong Sanatorium & Hospital", "job_title": "Human Resources Officer", "description": "Responsibilities\n\nHandle daily operation of the entire spectrum of Human Resources functions including recruitment and selection, benefits administration, performance management and employee relations\nAssist in reviewing operating flow, procedures and recommend effective improvement initiatives for performance enhancement\nMaintain employees\u2019 database in the Human Resources Information System\nAssist in coordinating various Human Resources projects and initiatives\nSupervise and monitor the work progress of team members\nRequirements\n\nDegree in Human Resources Management or equivalent\nMinimum 2 years\u2019 relevant experience preferably in sizable organization or healthcare industry\nExcellent command of spoken and written English and Chinese (Cantonese and Putonghua)\nFamiliar with computerised Human Resources Information System and Hong Kong Employment Ordinance\nProficiency in using Microsoft applications including Excel, PowerPoint and English & Chinese Word Processing\nCustomer-oriented with excellent interpersonal and communication skills\nProactive, responsible and able to work independently\n\nWe offer attractive remuneration package including end-of-contract gratuity, discretionary bonus, medical benefit and annual leave.\n\n\nInterested parties please send full resume with expected salary to Deputy Head of Human Resources, Human Resources Department, Hong Kong Sanatorium & Hospital, 2 Village Road, Happy Valley, Hong Kong, or email by clicking \"Apply Now\".\n\n\nAll information received will be kept in strict confidence and only used for employment-related purposes.\u00a0 Applicants who are not invited for interview within 6 weeks may consider their applications unsuccessful.\u00a0", "employment_types": ["Full Time"], "selling_points": [], "locations": ["Wan Chai Area"], "categories": ["Admin & HR", "Clerical / Admin Staff", "Others", "HR Supporting Staff"], "post_time": "2022-01-14T07:15:21Z", "salary": {"currency": null, "max": null, "min": null, "period": "monthly", "term": null}, "salary_visible": false, "title_keywords": ["human resources officer"], "responsibilities": ["management", "daily operation", "procedures", "monitor", "maintain", "recruitment", "database", "human resources functions", "administration"], "requirements": {"degrees": ["degree"], "majors": [], "languages": ["cantonese", "putonghua", "english", "chinese"], "language_level": ["excellent", "proficiency"], "hard_skills": ["excel", "hong kong employment ordinance", "chinese word processing", "microsoft applications", "information system", "powerpoint"], "soft_skills": ["communication skills", "work independently", "responsible", "customer-oriented", "proactive", "interpersonal"], "languages_combined": [{"language": "cantonese", "language_level": ["excellent"]}, {"language": "putonghua", "language_level": ["excellent"]}, {"language": "english", "language_level": ["excellent", "proficiency"]}, {"language": "chinese", "language_level": ["excellent", "proficiency"]}]}, "experience_required": {"duration": ["minimum 2 years"], "field": ["sizable organization", "healthcare industry", "relevant experience"]}}, {"job_id": "100003009048162", "location_code": "hk", "company": "Venchi HK Limited", "job_title": "Senior HR & Admin Officer", "description": "Job Responsibilities:\u00a0\n\nHandle full spectrum of Human Resources and office administration\u00a0function\nParticipate in the entire employment cycle and play a major role in staff recruitment\nResponsible for full spectrum of the compensation and benefits function including monthly payroll, MPF administration, leave management, medical insurance, employee compensation insurance, taxation, performance management and salary review\nAct as a business partner to provide advice to management and support operational needs\nMaintain Staff Record including personal file, leave record and personal data updating\nAssist in the review, development and implementation of company policies/ procedures pertaining to\u00a0human resources management\nHandle\u00a0office administration including purchase and maintenance of center supplies\u00a0and equipment, business trips arrangement, etc\n\nJob Requirements:\n\nDiploma or above in Human Resources Management or related discipline\n5-7 years hands on\u00a0experience in all-round HR & Admin functions\nExperience in retail industry is an advantage\nWell versed in Employment Ordinance, MPF regulations and other related ordinance\nGood command of written and spoken English and Chinese\nSelf-motivated, Well organized, Good analytical and detail-minded with strong sense of responsibilities\u00a0\nImmediate available is highly preferred\u00a0", "employment_types": ["Full Time"], "selling_points": ["Human Resource", "All-round HR", "Admin"], "locations": ["Wan Chai"], "categories": ["Admin & HR", "Clerical / Admin Staff", "HR Supporting Staff"], "post_time": "2022-01-14T05:33:49Z", "salary": {"currency": null, "max": null, "min": null, "period": "monthly", "term": null}, "salary_visible": false, "title_keywords": ["senior hr & admin officer"], "responsibilities": ["taxation", "management", "mpf", "maintenance", "office administration", "policies", "review", "procedures", "implementation", "purchase", "provide advice", "recruitment", "maintain", "insurance", "personal data", "payroll", "administration"], "requirements": {"degrees": ["diploma or above"], "majors": [], "languages": ["english", "chinese"], "language_level": ["good command"], "hard_skills": ["mpf regulations"], "soft_skills": ["detail-minded", "self-motivated", "well organized", "hands on", "sense of responsibilities"], "languages_combined": [{"language": "english", "language_level": ["good command"]}, {"language": "chinese", "language_level": ["good command"]}]}, "experience_required": {"duration": ["5-7 years"], "field": ["retail industry", "hr", "admin"]}}, {"job_id": "100003009047681", "location_code": "hk", "company": "The Executive Centre Limited", "job_title": "Human Resources Officer", "description": "Job Duties:\n\nResponsible for full range of HR administration work including but not limited to MPF, insurance enrolment, HR correspondence and updates on orientation contents, organization charts, training materials and job descriptions for all positions\nHandle on-boarding and exit procedures and ensure all required documents are properly processed and recorded, e.g., conducting reference check, employment contracts, new hire documentations, employment certificates and all other HR-related documentation. \u00a0\nMaintains HR information system and works closely with the cities\u2019 Accountant/HR admin, to ensure HR data quality\nSupports payroll management and verifies and ensures payment accuracy\nAssist in annual budget preparation in local cities and preparing different HR-related reports\nAssist in developing user guideline for HR-related system\nWork as recruitment partner with teams in headquarter office\nBe one of the HR contact points for general employees\u2019 enquiries. Support in building positive work atmosphere\nHandle all work visa applications for all level of staff\nAssist in ad hoc projects as assigned\nCandidate with more experiences will be considered as Senior HR Officer\nJob requirements:\n\n3 - 4 years solid experiences in HR Generalist\nPreferably to have experiences on cost allocation and HRIS\nExcellent skill in Excel and other PC skills\nGood numerical skills and detailed-minded\nExcellent communication, presentation and problem-solving skills\nCommitted to work in a very fast paced environment and independently\nHighly motivated team player with positive attitude and excellent work ethics\nFluent English, Cantonese and Mandarin\nCandidates with more related experiences will be considered as Senior HR Officer\nImmediate Available is a plus", "employment_types": ["Full Time", "Permanent"], "selling_points": ["HR Administration", "C&B", "HRIS"], "locations": ["Southern Area"], "categories": ["Admin & HR", "Compensation & Benefits", "HR Supporting Staff"], "post_time": "2022-01-14T03:44:08Z", "salary": {"currency": null, "max": null, "min": null, "period": "monthly", "term": null}, "salary_visible": false, "title_keywords": ["human resources officer"], "responsibilities": ["related documentation", "data", "quality", "payment", "administration", "contracts", "teams", "developing", "reports", "management", "mpf", "procedures", "annual budget preparation", "contact", "contents", "payroll", "hr", "recruitment", "ad hoc projects", "insurance"], "requirements": {"degrees": [], "majors": [], "languages": ["cantonese", "english", "mandarin"], "language_level": ["fluent"], "hard_skills": ["excel", "plus", "numerical skills", "problem-solving skills", "pc skills"], "soft_skills": ["independently", "communication", "committed", "positive attitude", "motivated", "problem-solving skills", "team player", "presentation", "detailed"], "languages_combined": [{"language": "cantonese", "language_level": ["fluent"]}, {"language": "english", "language_level": ["fluent"]}, {"language": "mandarin", "language_level": ["fluent"]}]}, "experience_required": {"duration": ["3 - 4 years"], "field": ["related", "hr", "hr generalist"]}}, {"job_id": "100003009051218", "location_code": "hk", "company": "Innovative Construction (SINO) Limited", "job_title": "Human Resources & Administration Assistant", "description": "Responsibilities:\n\n\nPerform HR functions including\u00a0 payroll, MPF, administration, compensation & benefits, record & recruitment, staff leave & attendance etc.\nHandle inquiries internally and externally\u00a0\nPerform administration, sourcing and general clerical duties\nPrepare regular report and analysis\nReport duties to managers and support supervisors whenever necessary\nPerform ad-hoc duties and assignment\nRequirement:\n\nHigher Diploma or above in Human Resources, Accounting, Business Administration or other related disciplines would be preferred\n1\u00a0year relevant experience would be preferred (Fresh\u00a0graduates are also welcome)\nProficient in MS office, Excel, and Chinese Word Processing\nWith strong sense of responsibility and able to meet tight deadline with high accuracy\nInitiative, self- motivated, well organized and be a good team player\nLess experience will be considered as Clerk\nImmediate available would be preferred\n\nHow to apply:\n\nIf you believe you can meet the challenge of the role, please forward your resume with current, expected salary and\u00a0availability\u00a0by\u00a0clicking ' Apply Now'.", "employment_types": ["Full Time"], "selling_points": [], "locations": ["Cheung Sha Wan"], "categories": ["Accounting", "Accounting Clerk / Supervisor", "Admin & HR", "Clerical / Admin Staff", "HR Supporting Staff"], "post_time": "2022-01-15T05:06:30Z", "salary": {"currency": null, "max": null, "min": null, "period": "monthly", "term": null}, "salary_visible": false, "title_keywords": ["administration assistant", "human resources"], "responsibilities": [], "requirements": {"degrees": [], "majors": [], "languages": [], "language_level": [], "hard_skills": [], "soft_skills": [], "languages_combined": []}, "experience_required": {"duration": [], "field": []}}, {"job_id": "100003009052751", "location_code": "hk", "company": "TOM Group International Limited", "job_title": "Assistant Manager - Group HR", "description": "Responsibilities\n\nPerform all round HR functions in Hong Kong Corporate Head Office, focusing on C&B includes payroll, P-fund, tax returns and other benefits administration.\nReview monthly payroll and C&B related payments of PRC business units to ensure local practices comply with group policy.\nPrepare\u00a0periodic HR reports\u00a0and other consolidated reports\u00a0in\u00a0timely manner.\nMaintain accurate HRIS data and employee records.\nAssist in planning and implementation of HR policies and solutions to support business needs.\nParticipate in HRIS projects and ad hoc assignments as and when required.\n\nRequirements\n\nDegree holder, major in HRM or related disciplines.\nHR generalist with minimum 6 years\u2019 relevant experience.\nWell-versed in HK employment ordinances. Sound knowledge of PRC or other regions\u2019 HR operations and practice is an advantage.\nHands on experience in Oracle or similar HRIS.\nFast learner, well-organized and attentive to details and figures.\nStrong sense of responsibility with excellent communication skills.\nProficient in in MS Office and Chinese Word Processing.\nGood command of English and Putonghua.\nImmediate available or short notice period are highly preferred.\nCandidates with less experience will be considered as Supervisor.\nInterested parties please submit your application letter with detailed resume indicating your present and expected salary to our Human Resources Department via APPLY NOW. Please quote our reference code on the application.\n\n\nFor more information, please visit our web site at\u00a0http://www.tomgroup.com\n\nWe are an equal opportunity employer and welcome applications from all qualified candidates. Personal data collected will be treated in the strictest confidence and handled confidentially by authorised personnel for recruitment-related purposes only within the TOM Group of companies. Applicants not having heard from us within four weeks of the date of application may consider their applications unsuccessful. The personal data of unsuccessful applicants will be destroyed after the recruitment exercise pursuant to the requirements of the Personal Data (Privacy) Ordinance in Hong Kong.", "employment_types": ["Full Time", "Permanent"], "selling_points": ["Assistant HR Manager", "6 years experience", "regional or PRC exposure"], "locations": ["Wan Chai"], "categories": ["Admin & HR", "HR Supporting Staff"], "post_time": "2022-01-17T03:55:50Z", "salary": {"currency": null, "max": null, "min": null, "period": "monthly", "term": null}, "salary_visible": false, "title_keywords": ["assistant manager", "hr"], "responsibilities": ["tax", "data", "policies", "hr", "review", "hr reports", "implementation", "maintain", "payments", "reports", "planning", "ad hoc assignments", "payroll", "support business needs", "administration"], "requirements": {"degrees": ["degree holder"], "majors": ["related disciplines"], "languages": ["putonghua", "english", "chinese"], "language_level": ["good command", "proficient"], "hard_skills": ["chinese word processing", "ms office", "oracle"], "soft_skills": ["communication skills", "attentive to details", "sense of responsibility", "well-organized", "hands on", "fast learner"], "languages_combined": [{"language": "putonghua", "language_level": ["good command"]}, {"language": "english", "language_level": ["good command"]}, {"language": "chinese", "language_level": ["proficient"]}]}, "experience_required": {"duration": ["minimum 6 years"], "field": ["relevant experience", "hr generalist"]}}, {"job_id": "100003009053407", "location_code": "hk", "company": "Wide Ocean Printing Company Limited", "job_title": "\u5370\u5237\u90e8\u4e3b\u7ba1", "description": "\nWide Ocean Printing Co., Limited \u662f\u4e00\u9593\u4f4d\u65bc\u9999\u6e2f\u89c0\u5858\u5340\u7684\u5370\u5237\u6709\u9650\u516c\u53f8,\u9644\u8a2d\u6df1\u5733\u576a\u5c71\u5340\u5ee0\u623f\u3002\n\u672c\u516c\u53f8\u696d\u52d9\u4e3b\u8981\u70ba\u7d19\u54c1\u67ef\u5f0f\u5370\u5237,\u63d0\u4f9b\u5370\u5f8c\u52a0\u5de5\u6548\u679c\u9867\u554f\u670d\u52d9\u4ee5\u914d\u5408\u5ba2\u6236\u7684\u7522\u54c1\u8a2d\u8a08\u3002\n\u7d93\u5b58\u5728\u8d85\u904e28\u5e74\uff0c\u70ba\u914d\u5408\u6211\u5011\u7684\u64f4\u5f35\uff0c\u6211\u5011\u6b63\u5728\u5c0b\u627e\u4e00\u500b\u5408\u9069\u7684\uff0c\u6709\u80fd\u529b\u548c\u5fe0\u8aa0\u7684\u5019\u9078\u4eba\u5982\u4e0b\u4f4d\u7f6e\uff1a\n\u8077\u8cac\u53ca\u5de5\u4f5c\u8981\u6c42 :\n\u2022 \u8ca0\u8cac\u7ba1\u7406\u6574\u500b\u5370\u5237\u90e8\u3001\u6309PMC\u6392\u671f\u751f\u7522\u3001\u5b89\u6392\u7522\u524d\u5099\u6599\u8abf\u8272\u7b49\u5de5\u4f5c\n\u2022 \u5177\u826f\u597d\u7684\u7d44\u7e54\u53ca\u57f7\u884c\u529b\u3001\u4eba\u54e1\u8abf\u914d\u3001\u6280\u8853\u6307\u5c0e\n\u2022 \u5c0d\u90e8\u9580\u4eba\u54e1\u9032\u884c\u57f9\u8a13, \u5305\u62ec\u56b4\u8085\u57f7\u884c\u516c\u53f8\u5236\u5ea6-5S, \u5b89\u5168\u751f\u7522, \u6a5f\u5668\u7dad\u4fee\u4fdd\u990a\u53ca\u76f8\u95dc\u7ba1\u7406\u4e8b\u52d9\n\u2022 \u5fc5\u9808\u80fd\u7368\u7acb\u64cd\u4f5cKBA\u6216\u5c0f\u68eeHUV\u6a5f\u7a2e \u53ca \u7dad\u4fee\u6a5f\u5668\n\u6bcf\u661f\u671f6\u5929\u99d0\u6df1\u5733\u576a\u5c71\u570b\u5167\u5ee0\u5de5\u4f5c [\u73fe\u5c45\u65bc\u570b\u5167\u53ca\u7acb\u5373\u4e0a\u73ed\u70ba\u6d3d]\n\n", "employment_types": ["Contract"], "selling_points": [], "locations": ["Not Specified"], "categories": ["Admin & HR", "HR Supporting Staff"], "post_time": "2022-01-17T06:56:27Z", "salary": {"currency": null, "max": null, "min": null, "period": "monthly", "term": null}, "salary_visible": false, "title_keywords": [], "responsibilities": [], "requirements": {"degrees": [], "majors": [], "languages": [], "language_level": [], "hard_skills": [], "soft_skills": [], "languages_combined": []}, "experience_required": {"duration": [], "field": []}}, {"job_id": "100003009054695", "location_code": "hk", "company": "Omni Group Asia Limited", "job_title": "Human Resources & Administrative Senior Officer (\u4eba\u529b\u8cc7\u6e90\u548c\u884c\u653f\u5b98)", "description": "Our client is a world leading blockchain and digital asset service provider/ FinTech company serving over a million users in 100+ countries across the globe. They provide a wide range of products and services from cryptocurrency exchange, decentralized wallet, mining pools to DeFi, NFT, other Dapps projects. This is an exciting opportunity to join the team as a HR Senior Officer.\n\n\u5d17\u4f4d\u8077\u8cac\uff1a\n\n\u00a0\u5354\u52a9\u5168\u65b9\u4f4d\u7684\u4eba\u529b\u8cc7\u6e90\u5de5\u4f5c\uff0c\u5982\u85aa\u916c\u53ca\u798f\u5229\u3001\u62db\u8058\u3001\u85aa\u8cc7\u53ca\u5f37\u7a4d\u91d1\u8a08\u7b97\u3001\u54e1\u5de5\u51fa\u52e4\u3001\u4f11\u5047\u8a18\u9304\u3001\u54e1\u5de5\u5eb7\u6a02\u6d3b\u52d5\uff1b\nAssist in the full spectrum of Human Resources Duties such as Compensation and Benefits, recruitment, payroll, and MPF calculation, employee attendance, leave record, staff recreation activities.\n\u4eba\u54e1\u8cc7\u8a0a\u9304\u5165\u548c\u4eba\u4e8b\u8a18\u9304\u5099\u6848\uff0c\u5f9e\u5165\u8077\u3001\u8a66\u7528\u671f\u5be9\u67e5\u3001\u8ddf\u9032\u548c\u96e2\u8077\u6d41\u7a0b\u958b\u59cb\u7ba1\u7406\u54e1\u5de5\u751f\u547d\u9031\u671f\uff1bPerform Personnel information entry and personnel record filing, manage the employee life cycle by starting from the entry, probationary review, follow-up and resignation process.\n\u00a0\u6839\u64da\u300a\u52de\u5de5\u689d\u4f8b\u300b\u3001\u300a\u5f37\u7a4d\u91d1\u689d\u4f8b\u300b\u53ca\u300a\u7a05\u52d9\u689d\u4f8b\u300b\uff0c\u4e0d\u6642\u66f4\u65b0\u4fee\u6539\u96c7\u54e1\u624b\u518a\uff0c\u52a0\u5165\u65b0\u7684\u4eba\u529b\u8cc7\u6e90\u653f\u7b56\u53ca\u6d41\u7a0b\uff1bUpdate and review employee handbook with newly Human Resources policies and procedures from time to time in compliance with Labour Ordinance, MPF Ordinance, and Inland Revenue Ordinance.\n\u63d0\u4f9b\u8fa6\u516c\u5ba4\u7ba1\u7406\u652f\u6301\nProvide office administration support.\n\u5354\u52a9\u5b8c\u6210\u7e3d\u90e8\u5b89\u6392\u7684\u5176\u4ed6\u81e8\u6642\u4efb\u52d9\nAssist in other ad-hoc assignments.\n\n\u4efb\u8077\u8981\u6c42\uff1a\n\n\u4eba\u529b\u8cc7\u6e90\u7ba1\u7406\u6216\u76f8\u95dc\u5b78\u79d1\u7684\u672c\u79d1\u4ee5\u4e0a\u6587\u6191\u6301\u6709\u8005\uff1b\nDiploma holder or above in Human Resources management or related discipline\n\u00a0 \u81f3\u5c115\u5e74\u624e\u5be6\u7684\u4eba\u529b\u8cc7\u6e90\u5be6\u8e10\u7d93\u9a57\nAt least 5 years solid experience in Human Resources related experience.\n\u4e92\u806f\u7db2\u3001\u91d1\u878d\u7684\u4eba\u529b\u8cc7\u6e90\u591a\u65b9\u9762\u4eba\u624d\u512a\u5148\u8003\u616e\uff1b\nHaving Human Resources related experience in Internet industry or Financial industry is preferred\n\u7cbe\u901a\u300a\u96c7\u50ad\u689d\u4f8b\u300b\u3001\u300a\u96c7\u54e1\u88dc\u511f\u689d\u4f8b\u300b\u3001\u5f37\u7a4d\u91d1\u8a08\u756b\u53ca\u5176\u4ed6\u8207\u96c7\u50ad\u6709\u95dc\u7684\u6cd5\u4f8b\uff1bGood knowledge in HK Employment Ordinance, Employee Compensation Ordinance, MPF and other Human Resources related statutory regulations\n\u826f\u597d\u7684\u4e2d\u82f1\u6587\u66f8\u9762\u548c\u53e3\u8a9e\uff08\u5305\u62ec\u666e\u901a\u8a71\uff09\u80fd\u529b\uff1b\nGood command of written and spoken English and Mandarin.\u00a0\u00a0\n\u7cbe\u901aMS Office\uff0cFoxmail\uff0c\u6709\u826f\u597d\u7684\u8fa6\u516c\u8edf\u9ad4\u4f7f\u7528\u57fa\u790e\uff1b\nGood knowledge in MS office and Foxmail.\n\u81ea\u6211\u6fc0\u52f5\uff0c\u6ce8\u91cd\u7d30\u7bc0\uff0c\u6709\u689d\u7406\uff0c\u8cac\u4efb\u5fc3\u5f37\uff0c\u591a\u4efb\u52d9\u8655\u7406\u80fd\u529b\u5f37\uff1b\nSelf-motivated, details-oriented, well organized, responsible and capable to cope with multi-tasks well.\nA copy of your Chinese AND English CV is required for this application.*", "employment_types": ["Full Time", "Permanent"], "selling_points": ["Fast-growing FinTech Blockchain Company", "Full spectrum HR opportunity", "Prestigious office in the heart of Central"], "locations": ["Central"], "categories": ["Admin & HR", "Administration / Operation Manager", "HR Director / Manager", "HR Supporting Staff"], "post_time": "2022-01-17T10:36:29Z", "salary": {"currency": null, "max": null, "min": null, "period": "monthly", "term": null}, "salary_visible": false, "title_keywords": ["senior officer", "human resources"], "responsibilities": ["regulations", "attendance", "management", "office administration support", "mpf", "policies", "hr", "review", "procedures", "compliance", "ad-hoc assignments", "recruitment", "payroll"], "requirements": {"degrees": ["diploma holder"], "majors": [], "languages": ["english", "chinese", "mandarin"], "language_level": ["good command"], "hard_skills": ["blockchain", "ms office", "exchange", "cryptocurrency"], "soft_skills": ["self-motivated", "capable", "multi-tasks", "responsible", "well organized"], "languages_combined": [{"language": "english", "language_level": ["good command"]}, {"language": "chinese", "language_level": []}, {"language": "mandarin", "language_level": ["good command"]}]}, "experience_required": {"duration": ["at least 5 years"], "field": ["related", "financial industry", "human resources"]}}, {"job_id": "100003009052188", "location_code": "hk", "company": "SCOR Reinsurance Co (Asia) Ltd", "job_title": "Human Resources Information System - Talent Acquisition Internship", "description": "Job Summary\n\nWe are looking for an intern to start immediately and finish in May 2022, with minimum commitment of three working days per week. You will visit the office if work activity is required, or you will be by default working from home.\n\nYou will work with the globally teams to deliver a new recruitment system in this internship.\n\nThe role will work closely with the project team through the submission and UAT (User Acceptance Testing) phases of the Human Resources Information System \u2013 Talent Acquisition stream project. Reporting to the project owner directly, you will support the UAT coordination and run part of the UAT.\n\nIn this internship, you will learn Talent Acquisition process, HRIS system \u2013 Oracle and have the experience to work with an international team across Asia, Europe, UK and US.\n\nTo be qualified, you will need to be available for three days or more per working week. The internship period is from January 2022 to May 2022.\n\nResponsibilities\n\nLearning of Talent Acquisition operational process\n\nLearn and understand the end-to-end recruitment process in Scor\nGet familiar with the workflow to be effective in UAT period\n\nUser Acceptance Testing\n\nAssist Project Owner to organize the testing period\nPerform UAT tasks as part of the testing team\nRecord testing results and follow up on tickets with the process owner and consultants\n\nProject Coordination\n\nAttend project meetings and workshops with the global project team to better understand the project\nCommunicate with neccesary parties to facilitate project flow\n\nRequired experience & competencies\n\nExperience:\nPrior Human Resources or User Acceptance Testing internship experience is beneficial\n\nPersonal Competences:\nResponsible, logical, meticulous\nStrong interpersonal and communication skills\nGood knowledge of MS Office applications\n\nRequired Education\n\nUndergraduate in Human Resources Management or Information System degree\n\nJob Type: Internship\n\n\u6709\u610f\u7533\u8acb\u8005\u8acb \u6309 APPLY NOW\u7533\u8acb", "employment_types": ["Internship"], "selling_points": [], "locations": ["Not Specified"], "categories": ["Admin & HR", "Clerical / Admin Staff", "HR Supporting Staff", "Recruitment / Executive Search"], "post_time": "2022-01-17T02:24:13Z", "salary": {"currency": null, "max": null, "min": null, "period": "monthly", "term": null}, "salary_visible": false, "title_keywords": ["human resources", "internship"], "responsibilities": ["communicate with", "reporting", "management", "uat", "project coordination", "teams", "testing", "communication", "team across", "recruitment", "coordination", "recruitment process"], "requirements": {"degrees": ["degree"], "majors": [], "languages": [], "language_level": [], "hard_skills": ["workshops", "ms office", "information system", "oracle"], "soft_skills": ["meticulous", "communication skills", "responsible", "learning", "coordination", "interpersonal"], "languages_combined": []}, "experience_required": {"duration": [], "field": ["testing", "human resources", "team"]}}, {"job_id": "100003009053038", "location_code": "hk", "company": "Spidernet Recruitment Services", "job_title": "Human Resources and Administration (Office Manager /Assistant Manager Level)", "description": "Human Resources and Administration (Office Manager /Assistant Manager Level)\n\nSalary: HK$30-40k\n\nResponsibilities:\n\nHandle full spectrum of Human Resources and Administration duties, such as compensation and benefits, recruitment, expenses payments, office facilities management and office supplies procurement \u00a0\nLiaise with internal and external parties for daily HR operation & administration\nPrepare regular human resources and office administration reports for management\u2019s review\nAssist Senior Management for meeting and traveling arrangements as well as other ad hoc assignments\nProvide administrative\u00a0support including preparation of meeting minutes and presentation materials as assigned\n\nRequirements:\n\nDegree in Human Resources / Business Administration or related disciplines\nMinimum 8 years of solid experience in Human Resources and office administration\nStrong coordination and prioritization skills\nGood interpersonal and communication skills\nCompetency in both spoken and written English and Chinese, Mandarin a plus\nIndependent, self-motivated & able to work under pressure\n\nAttractive remuneration and fringe benefits will be offered to the successful candidate.\n\n\nInterested candidates should apply with detailed resume, present and expected salaries by clicking the Apply Now button.\n\nAll information received will be treated in strict confidence and used for recruitment purpose only.\n\nOnly shortlisted candidates will be notified.", "employment_types": ["Full Time", "Permanent"], "selling_points": ["Degree in HR / BA , fluent English & Mandarin", "8 yrs HR and Admin exp. Recruitment, payroll, C&B", "All round HR, Office Admin and Executive support"], "locations": ["Central & Western Area"], "categories": ["Admin & HR", "Administration / Operation Manager", "HR Director / Manager", "HR Supporting Staff"], "post_time": "2022-01-17T05:18:45Z", "salary": {"currency": null, "max": null, "min": null, "period": "monthly", "term": null}, "salary_visible": false, "title_keywords": ["assistant manager", "office manager", "human resources"], "responsibilities": ["management", "office supplies", "office administration", "hr", "expenses", "internal and external parties", "review", "payments", "recruitment", "reports", "ad hoc assignments", "liaise with", "senior management", "provide administrative support", "administration"], "requirements": {"degrees": ["degree"], "majors": ["related disciplines", "business administration"], "languages": ["english", "chinese", "mandarin"], "language_level": [], "hard_skills": ["plus"], "soft_skills": ["communication skills", "self-motivated", "independent", "coordination", "interpersonal", "work under pressure"], "languages_combined": [{"language": "english", "language_level": []}, {"language": "chinese", "language_level": []}, {"language": "mandarin", "language_level": []}]}, "experience_required": {"duration": ["minimum 8 years"], "field": ["office administration", "human resources"]}}, {"job_id": "100003009054039", "location_code": "hk", "company": "EQC Advisory Limited", "job_title": "Part-Time / Full-Time Business Assistant (HK$55 - 75 per hour)", "description": "We are looking for 3-4 highly proactive members to assist with our business expansion plans.\u00a0The opportunity will allow the successful candidate to assist in HR, administrative and marketing activities of a start-up in the compliance advisory industry. \u00a0\n\nFor more information about us, please visit our website at\u00a0https://eqcadvisory.com/\n\nJOB\u00a0RESPONSIBILITIES\n\nYou may be assigned to one or more of the following responsibilities:\n\nProvide administrative support in the delivery of assignments as and when required\nHandle launch of a customer loyalty programme\nMaintain and update client records & grant access to online training courses to clients\nSupport marketing and administrative activities, such as newsletters, online and offline promotions, maintaining office supplies, managing expenses, etc.\nMaintain brand image by managing social media apps, website updates, and liaise with multi-media designers / producers (videos, graphics, etc.)\nMulti-media related students will be a plus\n\nJOB REQUIREMENTS:\n\nForm 5 / DSE or above with 1 year of relevant work experience, or university students in any discipline will be considered.\u00a0\nWell organised and detail oriented with office working experience.\nProficient in written English\nProficiency in PC software, e.g. MS Word and Excel\nExperience in online marketing is an advantage\nImmediately available is preferred\n\nWHAT WE OFFER:\n\n$55 - 75 per hour based on qualifications / relevant working experience\nSemi-annual appraisals and upward salary adjustments & discretionary performance-based bonus\n2 to 5 working days per week from Monday to Friday (4 hours+ per shift)", "employment_types": ["Part Time", "Temporary"], "selling_points": ["DSE with Experience / Current students are welcome", "Assist with Marketing and Administration", "Gain exposure to audit and compliance"], "locations": ["Causeway Bay"], "categories": ["Admin & HR", "HR Supporting Staff", "Marketing / Public Relations", "Marketing - Marketing Communication", "Media & Advertising", "Photography / Video"], "post_time": "2022-01-17T08:10:49Z", "salary": {"currency": "HKD", "max": 74, "min": 60, "period": "hourly", "term": null}, "salary_visible": true, "title_keywords": ["assistant"], "responsibilities": ["graphics", "social media", "maintaining", "office supplies", "expenses", "website", "liaise with", "maintain", "provide administrative support", "administrative activities"], "requirements": {"degrees": ["form 5", "dse"], "majors": [], "languages": ["english"], "language_level": ["proficient"], "hard_skills": ["pc", "excel", "ms word"], "soft_skills": ["detail oriented", "organised"], "languages_combined": [{"language": "english", "language_level": ["proficient"]}]}, "experience_required": {"duration": ["1 year"], "field": ["marketing"]}}, {"job_id": "100003009047468", "location_code": "hk", "company": "Harbour City Estates Ltd", "job_title": "SENIOR HUMAN RESOURCES OFFICER", "description": "The successful candidate will be responsible for the provision of quality Human Resources services including recruitment & selection, compensation & benefits, planning and organizing employee wellbeing programmes and statistical reporting as well as participating in other Human Resources initiatives/projects as assigned.\n\nApplicants should be University graduate in Human Resources Management or related disciplines, with at least 7 years\u2019 relevant experience in sizable companies.\u00a0 The ideal candidate should be attentive, precise, independent with strong planning, organizing and communication skills in both written and spoken English and Chinese.\u00a0 Conversance with HK Labour Ordinance and good PC literacy in Windows applications are prerequisites. \u00a0\n\nWe offer competitive salary package that will be commensurate with experience and qualifications.\u00a0 Interested parties are invited to send full resume stating contact telephone number, date available, present and expected salary to our recruitment email address.\n\n(Personal data provided will be used strictly in accordance with the Company\u2019s personal data policy which is available upon request.)", "employment_types": ["Full Time", "Permanent"], "selling_points": ["Responsible for the provision of HR Services", "Participating in other Human Resources initiatives", "At least 7 years\u2019 relevant experience"], "locations": ["Tsim Sha Tsui"], "categories": ["Admin & HR", "Compensation & Benefits", "HR Supporting Staff", "Recruitment / Executive Search"], "post_time": "2022-01-15T03:49:45Z", "salary": {"currency": null, "max": null, "min": null, "period": null, "term": null}, "salary_visible": false, "title_keywords": ["senior human resources officer"], "responsibilities": ["reporting", "management", "quality", "communication", "recruitment", "planning"], "requirements": {"degrees": ["university graduate"], "majors": ["related disciplines"], "languages": ["english", "chinese"], "language_level": [], "hard_skills": ["pc", "sizable companies"], "soft_skills": ["attentive", "communication skills", "independent", "responsible", "precise", "ideal"], "languages_combined": [{"language": "english", "language_level": []}, {"language": "chinese", "language_level": []}]}, "experience_required": {"duration": ["at least 7 years"], "field": ["related", "management", "relevant experience", "human resources"]}}, {"job_id": "100003009054070", "location_code": "hk", "company": "KeeReal Consulting Limited", "job_title": "HR and Administration Officer - MNC", "description": "Our client is a well-established MNC bank and recently seeking a flexible candidate for the HR and Admin Officer position to join their newly expanded branch.\u00a0\n\nResponsibilities:\u00a0\n\n\nPerform all-rounded HR support and services for company\u2019s operation\nDrive annual compensation process including salary review, budgeting, incentive schemes to facilitate recruitment and retention program;\nMaintain Staff Record including personal file, leave record and personal data updating\nDirectly report to top management level and provide full spectrum of Human Resources and Administration tasks including but not limited to recruitment & selection, C&B, and training & development\nHandle all-round administrative and clerical duties such as office supplies, office renovation, repair and maintenance\nAssist in the review, development and implementation of company policies/ procedures pertaining to human resources management\nEngage in ad hoc projects as required\nRequirement:\n\n\nDegree holder or above\nSelf-motivating, flexible and can-do attitude\u00a0\nAccounting knowledge is preferred\nAt least 3 years\u2019 experience in Human Resources sector\nProficient in English", "employment_types": ["Full Time", "Permanent"], "selling_points": ["Well-established MNC bank across Asia", "Accounting knowledge is preferred", "Min. 3 years of HR experience"], "locations": ["Central & Western Area"], "categories": ["Admin & HR", "Compensation & Benefits", "HR Supporting Staff"], "post_time": "2022-01-17T08:17:49Z", "salary": {"currency": null, "max": null, "min": null, "period": "monthly", "term": null}, "salary_visible": false, "title_keywords": ["administration officer", "hr"], "responsibilities": ["administration", "management", "maintenance", "office supplies", "company\u2019s operation", "hr", "review", "budgeting", "renovation", "implementation", "policies", "procedures", "repair", "maintain", "recruitment", "ad hoc projects", "personal data", "report"], "requirements": {"degrees": ["degree holder"], "majors": [], "languages": ["english"], "language_level": ["proficient"], "hard_skills": [], "soft_skills": ["flexible", "can-do attitude"], "languages_combined": [{"language": "english", "language_level": ["proficient"]}]}, "experience_required": {"duration": ["at least 3 years"], "field": ["human resources"]}}, {"job_id": "100003009054601", "location_code": "hk", "company": "SAVILLS GUARDIAN", "job_title": "Assistant Administration Officer / Administration Assistant", "description": "F.5 or above\nMinimum\u00a01\u00a0year relevant working experience\nGood command of written and spoken English and Chinese\nHands-on\u00a0PC knowledge in MS Office\nWell-organized with a strong sense of responsibility, detail-minded and capable to work under pressure\nMaintain a complete and updated personnel records of newcomers, termination and movement, to ensure accuracy and compliance in HR system\nHandle monthly payroll, attendance record, work injury cases\u00a0and leave management\nProvide general clerical support and administrative duties\nCoordinating with different parties, answering telephone enquiries\u00a0and other ad hoc duties assigned by the supervisor\nApplicants with more experience will be considered as\u00a0Assistant Administration Officer\n\nWe offer competitive salary package to the right appointee. Applicants are requested submit detailed resume with present and expected salary by clicking \"APPLY NOW\".\n\nPlease Quote Emp. Ref. no. : AO/SS/012022\n\n[Personal data provided will be used strictly in accordance with our personal data policies, a copy of which will be provided immediately upon request.]", "employment_types": ["Full Time", "Permanent"], "selling_points": [], "locations": ["Hung Hom"], "categories": ["Admin & HR", "Clerical / Admin Staff", "Others", "HR Supporting Staff"], "post_time": "2022-01-17T10:12:15Z", "salary": {"currency": null, "max": null, "min": null, "period": "monthly", "term": null}, "salary_visible": false, "title_keywords": ["administration assistant", "assistant administration officer"], "responsibilities": ["ad hoc duties", "attendance", "management", "administration", "hr", "compliance", "personnel records", "clerical support", "maintain", "administrative duties", "payroll", "work under pressure"], "requirements": {"degrees": [], "majors": [], "languages": ["english", "chinese"], "language_level": ["good command"], "hard_skills": ["pc knowledge", "ms office"], "soft_skills": ["detail-minded", "capable", "sense of responsibility", "well-organized", "hands-on", "work under pressure"], "languages_combined": [{"language": "english", "language_level": ["good command"]}, {"language": "chinese", "language_level": ["good command"]}]}, "experience_required": {"duration": ["minimum 1 year"], "field": ["relevant working experience", "administration"]}}, {"job_id": "100003009037664", "location_code": "hk", "company": "Wai Yuen Tong Medicine Co Ltd", "job_title": "Senior HR Officer (Recruitment)", "description": "Job Role\n\n\nManage the full spectrum of Human Resources functions including but not limited to recruitment, C&B, team member movement, employee relations according to our corporate guideline\u00a0and operations objectives.\nExecute recruitment and selection process starting from job posting to staff appointment. Work closely with department heads on the manpower and hiring plan.\nOversee and manage people strategies, including talent development, employee communications, manpower planning, performance management and other HR projects\nPlan and execute HR initiatives on employee engagement\nConduct regular review on HR practice and procedure to ensure they are compliance with local legislation\nWorking as a strategic business partner to the line management.\u00a0\n\nRequirements:\n\nUniversity graduate in Human Resources Management, Business Administration or relevant discipline\nMinimum 6 years of relevant work experience in sizeable companies; with exposure in pharmaceutical manufacturer is definitely an advantage\nWell versed in Hong Kong Labor Ordinance and related regulations\nMature, flexible and able to work under pressure\nAble to work independently and meet tight deadlines\nGood command in both spoken and written English and Chinese\nCandidate with more experience will be considered as Assistant HR Manager\nWork location: Yuen Long\n\nInterested parties please send\u00a0full resume\u00a0with present and expected salary\u00a0to Human Resources Department by clicking\u00a0\"APPLY NOW\".\n\n\u00a0(All personal data provided by applicants will be treated in strict confidence and used for employment-related purpose only.)", "employment_types": ["Full Time", "Permanent"], "selling_points": ["Recruitment focus", "Mature, independent & proactive", "Strong sense of responsibility & detail-minded"], "locations": ["Yuen Long"], "categories": ["Admin & HR", "Compensation & Benefits", "HR Supporting Staff", "Recruitment / Executive Search"], "post_time": "2022-01-15T03:49:12Z", "salary": {"currency": null, "max": null, "min": null, "period": "monthly", "term": null}, "salary_visible": false, "title_keywords": ["hr officer"], "responsibilities": ["administration", "regulations", "management", "work under pressure", "operations", "hr", "compliance", "regular review", "recruitment", "plan", "human resources functions", "planning"], "requirements": {"degrees": ["university graduate"], "majors": ["business administration"], "languages": ["english", "chinese"], "language_level": ["good command"], "hard_skills": [], "soft_skills": ["flexible", "work independently", "meet tight deadlines", "mature", "team member", "work under pressure"], "languages_combined": [{"language": "english", "language_level": ["good command"]}, {"language": "chinese", "language_level": ["good command"]}]}, "experience_required": {"duration": ["minimum 6 years"], "field": ["hr"]}}, {"job_id": "100003009052274", "location_code": "hk", "company": "Lubuds F&B Group", "job_title": "Talent Acquisition Specialist", "description": "Responsibilities:\nDesign and implement overall recruiting strategy.\nDevelop and update job descriptions and job specifications.\nPreparing and post jobs to appropriate recruitment channels.\nSource and attract candidates by using databases and social media.\nScreen candidates resumes and job applications.\nConduct interviews, assess applicants\u2019 relevant knowledge, skills, soft skills, experience and aptitudes.\nMonitor and apply HR recruiting best practices.\nDevelop and maintain a candidate data base to facilitate the recruitment process\u00a0\u00a0\nAct as a point of contact and build influential candidate relationships during the selection process.\nPromote company\u2019s reputation as \u201cbest place to work\u201d.\nRequirements:\nDegree in Human Resources Management or relevant disciplines\n3 years of relevant experience in recruitment, preferably in F&B industry\nWith HR experience in F&B industry is an advantage\nWell-versed in Hong Kong Employment Ordinance, MPF regulations and other related\u00a0legislation\nGood command of spoken and written in English and Chinese\nProficiency in\u00a0Excel and Chinese\u00a0word processing\nImmediate Available\n\n\n\nWe offer attractive remuneration package and excellent career opportunities to the right candidate. Interested parties, please click on below button \u201cApply Now\u201d.\n\nInformation collected will be treated in strict confidence and used for recruitment purposes only. Only suitable candidates will be notified.", "employment_types": ["Full Time", "Permanent"], "selling_points": [], "locations": ["Aberdeen"], "categories": ["Admin & HR", "Others", "HR Supporting Staff", "Recruitment / Executive Search"], "post_time": "2022-01-17T02:37:34Z", "salary": {"currency": null, "max": null, "min": null, "period": "monthly", "term": null}, "salary_visible": false, "title_keywords": ["specialist"], "responsibilities": ["social media", "data", "hr", "monitor", "design", "develop", "specifications", "recruitment", "maintain", "databases", "contact", "recruitment process"], "requirements": {"degrees": ["degree"], "majors": [], "languages": ["english", "chinese"], "language_level": ["proficiency", "good command"], "hard_skills": ["excel", "chinese word processing", "hong kong employment ordinance", "mpf regulations"], "soft_skills": [], "languages_combined": [{"language": "english", "language_level": ["good command"]}, {"language": "chinese", "language_level": ["proficiency", "good command"]}]}, "experience_required": {"duration": ["3 years"], "field": ["recruitment", "f&b", "relevant experience", "hr"]}}, {"job_id": "100003009049940", "location_code": "hk", "company": "Paul Y. Engineering Group", "job_title": "Human Resources Assistant", "description": "Overview of the Role\n\nReport to the HR Manager and the Team Leads. The major duties and responsibilities of this role will take place in the delivery of HR services in the below aspects:\n\nRecruitment and selection;\nEmployee insurance administration; and\nGeneral Human Resources administration.\n\nJob Responsibilities\n\nSupport the recruitment team on daily operations of HR functions;\nMaintain an effective record system;\nAssist in managing staff benefits;\nProvide full spectrum of administrative tasks including filing, documentation, data entry, and reports preparation; and\nHandle ad hoc projects and perform other duties as assigned.\n\nJob Requirements\n\nDegree in Human Resources Management, Business Administration, or related disciplines;\n1 year of relevant working experience preferred (fresh graduates will also be considered);\nStrong computer literacy, well versed in MS Office applications and Chinese Word Processing;\nGood command of written and spoken English and Chinese; and\nResponsible, proactive, and detail-minded with good communication and organizational skills.\n\n***What we offer?\n\nCompetitive remuneration package\nAdditional leave (Family Care Leave, Exam Leave, Qualification Leave, etc.)\nDiscretionary bonus\nStudy Subsidies\nComprehensive training and professional career development\n\nInterested parties please apply by clicking \"APPLY NOW\" with detailed CV stating expected salary and date of availability.\n\nCompany Website: \u00a0http://www.pyengineering.com/\n\nAll personal data provided will be used strictly in accordance with our \u201cPersonal Information Collection Statement Pertaining to Recruitment\u201d, a copy of which is available upon written request to us by E-mail.", "employment_types": ["Full Time", "Permanent"], "selling_points": ["Degree holder in HRM/ BBA", "Fresh graduates will also be considered", "Stable and professional team, friendly culture"], "locations": ["Kwun Tong"], "categories": ["Admin & HR", "Clerical / Admin Staff", "HR Supporting Staff"], "post_time": "2022-01-15T03:50:44Z", "salary": {"currency": null, "max": null, "min": null, "period": "monthly", "term": null}, "salary_visible": false, "title_keywords": ["human resources assistant"], "responsibilities": ["hr", "daily operations", "maintain", "recruitment"], "requirements": {"degrees": [], "majors": [], "languages": [], "language_level": [], "hard_skills": [], "soft_skills": [], "languages_combined": []}, "experience_required": {"duration": [], "field": []}}, {"job_id": "100003009047958", "location_code": "hk", "company": "Sime Darby Motor Services Limited", "job_title": "Officer - Human Resources (Compensation & Benefits) (Ref: JDB/SDMSL/CBHRO/20220114)", "description": "Key Responsibilities:\n\nHandle the daily tasks of Compensation & Benefits full spectrum\u00a0function, including but not limited to payroll, benefits and insurance administration, HR system and personnel data management, salary benchmarking, taxation for our Hong Kong and Macau Operations\n\nCompile\u00a0regular HR management reports such as headcount and staff cost reports, salary and commission analysis, etc.\n\nAssist in\u00a0any ad hoc Compensation & Benefits exercises as assigned\nParticipate other HR operational tasks, such as staff activities, on/off boarding arrangements, leave management, etc.\nBe one of the representatives to participate in varies company committees when assigned and organize and staff activities\n\nJob\u00a0Requirements:\n\nBachelor or above Degree holder in Human Recourses Management or related disciplines\n3 years of experience in Compensation & Benefits from sizable company\nWell versed in Hong Kong Employment Ordinance, knowledge of Macau Labor Law will be an advantage\nProficient in MS Office applications, experience in HRIS or SAP is a plus\nGood command of spoken and written Chinese and English\nAttentive to details, strong numeric sense, well organized and good team player with strong sense of responsibility\nWorking location: Tsuen Wan (7-10 minutes walk from MTR station)\n\nWe offer attractive remuneration package, 5-day work week, competitive fringe benefits and excellent career development opportunity to the right candidate. Interested parties please send your full resume quoting job reference number with present salary, expected salary and available date via e-mail to\u00a0ghr-recruitment.sdms @simedarby.com.hk\u00a0\n\n\nFor more information about us, please visit our\u00a0Website.\nFollow us on\u00a0our\u00a0LinkedIn\u00a0and stay tuned!\n\n\nAll information provided by applicants will be treated in strict confidence and used for recruitment purpose only.", "employment_types": ["Full Time", "Permanent"], "selling_points": ["3 years in Compensation & Benefits", "Degree in HRM / Related Disciplines", "Good Exposure in Automotive Sizable Company"], "locations": ["Tsuen Wan Area"], "categories": ["Admin & HR", "Compensation & Benefits", "HR Supporting Staff"], "post_time": "2022-01-14T04:26:49Z", "salary": {"currency": null, "max": null, "min": null, "period": "monthly", "term": null}, "salary_visible": false, "title_keywords": ["officer", "human resources"], "responsibilities": ["taxation", "management", "cost", "data", "operations", "hr", "analysis", "management reports", "reports", "insurance", "payroll", "administration"], "requirements": {"degrees": [], "majors": [], "languages": [], "language_level": [], "hard_skills": [], "soft_skills": [], "languages_combined": []}, "experience_required": {"duration": [], "field": []}}, {"job_id": "100003009048144", "location_code": "hk", "company": "Isshin Group Holdings Company Limited", "job_title": "Human Resources Officer", "description": "Responsibilities\n\nResponsible for HR functions including but not limited to talent acquisitions, contract management, reporting, C&B, etc\nProvide one-stop recruitment services from screening, shortlisting, interviewing, and on / off boarding\nExplore different recruitment channels and evaluate the effectiveness such as advertising, social media, recruitment day\nFormulate and implement recruitment strategies & initiatives to attract talents\nAssist in HR policies and procedures formulation and execution\nAssist in other ad hoc projects as assigned\n\nRequirements\n\nProfessional qualifications in HR and/or any related disciplines\n2+ years\u2019 experience preferably in F&B industry\nFamiliar with HK Employment Ordinance and related regulations\nGood communication and\u00a0interpersonal skills\nMulti-tasking, pro-active\u00a0and with can-do-attitude\nProficient\u00a0in MS Word, PowerPoint, and Excel\nImmediate available is highly preferred\u00a0\n\nAll data collected will only be used for recruitment purposes.", "employment_types": ["Full Time"], "selling_points": ["Fast Growing F&B Group", "Career Development Opportunity", "Immediate Available Preferred"], "locations": ["Sheung Wan"], "categories": ["Hospitality / F & B", "Food & Beverage", "Admin & HR", "HR Supporting Staff", "Recruitment / Executive Search"], "post_time": "2022-01-14T05:19:23Z", "salary": {"currency": null, "max": null, "min": null, "period": "monthly", "term": null}, "salary_visible": false, "title_keywords": ["human resources officer"], "responsibilities": ["reporting", "social media", "advertising", "policies", "hr", "procedures", "contract management", "evaluate", "recruitment", "ad hoc projects"], "requirements": {"degrees": [], "majors": [], "languages": [], "language_level": [], "hard_skills": ["ms word", "excel", "powerpoint", "professional qualifications"], "soft_skills": ["multi-tasking", "communication and interpersonal skills", "can-do", "pro-active"], "languages_combined": []}, "experience_required": {"duration": ["2+ years"], "field": ["f&b"]}}, {"job_id": "100003009048983", "location_code": "hk", "company": "Odoo Limited", "job_title": "HR Assistant / Officer", "description": "Join a vibrant and innovative team, working within an organization that values independence, flexibility and personal growth. As an HR Assistant/Officer, you will be supporting the Senior HR Officer in general affairs, HR-related duties and other administrative tasks. This is an exciting opportunity for you to learn and to be a part of a rapidly growing company.\n\nRESPONSIBILITIES\n\n\n\nAssist with day-to-day operations of the HR functions and duties\nMaintain/update employee records accurately and effectively\nWelcoming new employees to the company by conducting orientation\nAssist with leave management, on and off boarding operations, company events, meetings etc.\nAssist with employment visa application and record management\u00a0\nAssist in preparing official documents and provide administrative support to HR Department\nKeep up-to-date with the latest HR trends and best practices\nPerform other assigned duties and ad hoc projects\nMUST HAVE\n\nBachelor\u2019s degree, or higher in related disciplines\nProficiency in productivity software / application such as MS Office & Google Workplace\nGood command in both spoken and written English and Chinese\nGood team player with a positive attitude and eager to learn and grow\nSelf-motivated with strong sense of responsibility\nHighly organized and detail-oriented\n\nNICE TO HAVE\n\nStrong software and new technology awareness\nImmediate Availability\n1-2 years relevant experience\n\nVALUES\n\nYou are able to work in a fast-paced start-up environment with a hands-on attitude\nYou are open-minded and can react to change with agility\nYou are a quick and autonomous learner\nWilling to contribute to great company culture", "employment_types": ["Full Time"], "selling_points": ["All round HR duties", "1-2 years experience", "Dynamic & international working environment"], "locations": ["Sai Ying Pun"], "categories": ["Admin & HR", "Clerical / Admin Staff", "Compensation & Benefits", "HR Supporting Staff"], "post_time": "2022-01-14T07:49:58Z", "salary": {"currency": null, "max": null, "min": null, "period": "monthly", "term": null}, "salary_visible": false, "title_keywords": ["officer", "hr assistant"], "responsibilities": ["management", "software", "operations", "hr", "day-to-day operations", "maintain", "ad hoc projects", "administrative tasks", "provide administrative support"], "requirements": {"degrees": ["degree", "bachelor"], "majors": ["related disciplines"], "languages": ["english", "chinese"], "language_level": ["good command"], "hard_skills": ["nice", "react", "ms office"], "soft_skills": ["organized", "good team player", "self-motivated", "sense of responsibility", "open-minded", "hands-on attitude", "detail-oriented", "positive attitude", "eager to learn", "autonomous", "innovative"], "languages_combined": [{"language": "english", "language_level": ["good command"]}, {"language": "chinese", "language_level": ["good command"]}]}, "experience_required": {"duration": ["1-2 years"], "field": ["relevant experience"]}}, {"job_id": "100003009054681", "location_code": "hk", "company": "Haitong International Securities Group Limited", "job_title": "Human Resources Manager (Training & Development), Human Resources (Ref.: JDB/HR/HRM_T&D)", "description": "The Job :\u00a0\n\nAssist in the design and implementation of effective corporate training and development programs, including Management Trainee Program and Talent Programs to groom talents and future leaders.\nConduct training needs analysis to identify trainings for employees and design training curriculum.\nPropose training solutions that meet business needs, source external vendors, and evaluate training effectiveness based on the feedback from internal users.\nCoordinate and collaborate with internal and external stakeholders to develop and deliver training for employees, manage external vendors well and maintain good relationship.\nPrepare periodic training reports and analyze training data to review the trend and future training needs.\nOrganize training classes or coordinate online training, handle course enrolment, registration, email notification, and logistics arrangement of training venue.\nAssist in developing and reviewing operation procedure manuals and other necessary control documents. Review training processes to enhance efficiency.\nWork together with Compliance Department on managing CPT/D training to meet compliance requirements for all license holders.\nMaintain proper and accurate training record for all staff and license holders; handle LMS administration.\nAddress staff enquires related to training.\nPerform any other ad hoc duties as required.\n\nRequirements:\u00a0\nWe support local hire with solid relevant working experience in HK.\n\n\nUniversity degree in Human Resources Management or related disciplines;\nA minimum of 7 years\u2019 relevant experience training and development roles in financial industry;\nGood command of written and spoken Chinese and English;\nDetailed minded with strong analytical, problem solving and project management skills;\nFlexible and able to work in a fast-pace, result-oriented environment;\nExcellent communication and interpersonal skills\n\nApplication Method:\n\nWe are committed to build a team of competence individuals who have acquired relevant local solid working experience and with diversified exposure to work together with us. Applicants who do not hear from us within 6 weeks may consider their applications unsuccessful.\n\nWe provide attractive remuneration package and fringe benefits for the right candidate.\u00a0Interested parties please send detailed resume with current and expected salaries to\u00a0Human Resources Department\u00a0i) by mail: 22/F, Li Po Chun Chambers, 189 Des Voeux Road Central, HK;\u00a0ii) by fax:2537 5431; or\u00a0iii) by using\u00a0\u201cApply Now\u201d.\n\nPlease quote the reference in the application.If application is submitted in hard copy format, it should be placed in a sealed envelope marked \u201cConfidential\u201d.\u00a0 All applications will be treated in strict confidence and personal data provided by job applications will be used for recruitment purposes only.\u00a0 A copy of our Personal Information Collection Statement will be available upon request.", "employment_types": ["Full Time", "Permanent"], "selling_points": [], "locations": ["Southern Area"], "categories": ["Admin & HR", "Others", "HR Supporting Staff", "Training & Development"], "post_time": "2022-01-17T10:32:56Z", "salary": {"currency": null, "max": null, "min": null, "period": null, "term": null}, "salary_visible": false, "title_keywords": ["hr", "manager", "human resources"], "responsibilities": ["collaborate with", "data", "design", "maintain", "administration", "ad hoc duties", "control", "compliance", "implementation", "developing", "develop", "maintain good relationship", "reports", "management", "logistics arrangement", "review", "development programs", "analysis", "evaluate", "coordinate"], "requirements": {"degrees": ["university degree"], "majors": ["related disciplines"], "languages": ["english", "chinese"], "language_level": ["good command"], "hard_skills": ["problem solving", "project management"], "soft_skills": ["flexible", "project management skills", "problem solving", "committed", "communication and interpersonal skills", "result-oriented", "detailed"], "languages_combined": [{"language": "english", "language_level": ["good command"]}, {"language": "chinese", "language_level": ["good command"]}]}, "experience_required": {"duration": ["minimum of 7 years"], "field": ["training", "development", "financial industry", "relevant working experience", "relevant experience", "team"]}}, {"job_id": "100003009046899", "location_code": "hk", "company": "CITIC Telecom International CPC Limited", "job_title": "Human Resources Assistant (1 year contract) - with gratuity provided", "description": "The Challenge We Pose to You:\n\nProvide administrative support in full spectrum of Human Resources processes, including talent acquisition, training and other HR operations\nSupport in HR routine and ad-hoc reports & projects\nMaintain an updated HR records including data entry and record filing etc.\u00a0\nAssist in planning, designing, developing and implementing staff engagement and CSR activities\nAssist in ad-hoc assignments\n\n\u00a0What You Bring to Us:\n\nDegree in Human Resources Management or related discipline\n1 year HR experience (fresh graduates are also welcome)\nGood team player with good interpersonal & communication skills\nStrong sense of confidentiality, responsibility and commitment\nFluent spoken & written in both English and Chinese\nProficient in MS offices and Chinese word processing\nImmediate available is highly preferred\nCandidate with more experience will be considered as Assistant Officer\n\nOur Offer:\u00a0\n\n5-day work, 12 annual leave,\u00a0a competitive remuneration package with gratuity, medical plan, local and regional training and rewarding career opportunities.\n\nPlease send your\u00a0complete resume (in MS word format), inclusive of\u00a0your available date, current and expected salary\u00a0by clicking\u00a0'Apply Now'\u00a0or\u00a0by\u00a0mail to:\u00a0Human Resources and Administration Department,\u00a0CITIC Telecom International CPC\u00a0Limited,\u00a020/F, Lincoln House, Taikoo Place, 979 King's Road, Quarry Bay, Hong Kong.\u00a0\n\nWebsite:\u00a0 www.citictel-cpc.com\n\nAll information received will be kept in strict confidence and for employment-related purpose only.", "employment_types": ["Full Time", "Contract"], "selling_points": ["1 year contract with gratuity provided", "HR assistant, fresh graduate also welcome", "Support in HR operations"], "locations": ["Quarry Bay"], "categories": ["Admin & HR", "Clerical / Admin Staff", "HR Supporting Staff"], "post_time": "2022-01-14T01:39:23Z", "salary": {"currency": null, "max": null, "min": null, "period": "monthly", "term": null}, "salary_visible": false, "title_keywords": ["human resources assistant"], "responsibilities": ["ad-hoc", "administration", "management", "data entry", "operations", "hr", "ad-hoc assignments", "developing", "website", "communication", "maintain", "reports", "plan", "designing", "provide administrative support", "planning"], "requirements": {"degrees": ["degree"], "majors": [], "languages": ["english", "chinese"], "language_level": ["proficient", "fluent"], "hard_skills": ["chinese word processing", "ms word"], "soft_skills": ["communication skills", "good team player", "confidence", "interpersonal"], "languages_combined": [{"language": "english", "language_level": ["fluent"]}, {"language": "chinese", "language_level": ["proficient", "fluent"]}]}, "experience_required": {"duration": ["1 year"], "field": ["hr"]}}, {"job_id": "100003009050949", "location_code": "hk", "company": "S.F. Express (Hong Kong) Limited", "job_title": "Human Resources Officer (C&B)", "description": "Responsibilities\n\nPerform C&B functions such as payroll, attendance & leave record maintenance, MPF and benefits administration\nAssist in negotiation with insurance company regarding work injury issues\nPreparing various analysis reports, handling employee attendance and leave management\nProvide support in HR Systems and payroll system, ensure HR systems run smoothly and updated for data maintenance\nProvide administrative and clerical support to the team\nPerform ad-hoc tasks as assigned\n\nJob Requirements\n\n\nDegree holder or above in Human Resources Management or related discipline\n3 to 5 years\u2019 working experience with hands-on C&B logistics arrangement experience in sizable organization\nWell versed in the HK Employment Ordinance and HR related legislation\nKnowledge of SAP is an advantage\nProficient in computer skills including PowerPoint, strong in Excel and Chinese Word Processing\nMeticulous, proactive, able to work under pressure with multi-tasking ability and crop with fast pace working environment\nGood command of spoken / written English, Mandarin and Cantonese\nImmediate available is highly preferred\nCandidates with less experience will be considered as\u00a0HR Assistant Officer\nWe offer attractive remuneration package and fringe benefits to the suitable candidates. Interested parties, please submit your application to us. If you do not want to apply as a JobsDB member, you may send your full resume with your availability, current and expected salaries to recruit01 at sf-express.com\nYou are welcome to visit our website at\u00a0https://htm.sf-express.com/hk/tc/\u00a0for more information about us.\n\nCandidates who are not invited for an interview within 1-month may consider their applications unsuccessful.\nAll personal data provided by job applicants will be used only for recruitment purposes and will be treated strictly confidential. Unsuccessful applications will be retained for a maximum period of 24-month.", "employment_types": ["Full Time", "Permanent"], "selling_points": ["Free shuttle bus coverage", "2 months or above performance bonus", "Attractive basic salary"], "locations": ["Tsing Yi"], "categories": ["Admin & HR", "Compensation & Benefits", "HR Supporting Staff"], "post_time": "2022-01-14T11:55:53Z", "salary": {"currency": null, "max": null, "min": null, "period": "monthly", "term": null}, "salary_visible": false, "title_keywords": ["human resources officer"], "responsibilities": [], "requirements": {"degrees": [], "majors": [], "languages": [], "language_level": [], "hard_skills": [], "soft_skills": [], "languages_combined": []}, "experience_required": {"duration": [], "field": []}}, {"job_id": "100003009042530", "location_code": "hk", "company": "WPG Electronics (HK) Limited", "job_title": "Human Resources Assistant", "description": "\u00a0Responsibilities\u00a0\n\nAssist in handling full spectrum of HR functions including recruitment, compensation and benefits, training and development and employee relations.\nProvide administrative support to HR department.\nResponsible for ad-hoc projects as assigned.\n\nRequirements\u00a0\n\nDegree Holder in Human Resources Management or related discipline.\nAt least 1 years relevant experience in sizeable organizations.\nGood command of spoken and written English, Chinese and Mandarin.\nProficient in Windows 10 and MS Office 365 applications as well as Chinese Word Processing.\nImmediate available is preferred.\n\nBenefits & package\n\nDouble pay and\u00a0Performance bonus\nDental insurance\nLife insurance\nMedical insurance\n5-day work etc.\n\nWPG Electronics (HK) Limited is an equal opportunity employer and welcomes applications from all qualified candidates. Information provided will be treated in strict confidence and only be used for recruitment related purposes. Applicants who are not contacted within 6 weeks may consider their application unsuccessful. Unsuccessful applications may be kept for another 3 months for being considered for other suitable positions available in our Company. The unsuccessful applications will be destroyed after the said period of retention.", "employment_types": ["Full Time", "Permanent"], "selling_points": ["At least 1 years experience in HR", "Proficient in Windows 10 and  MS Office 365", "Work in a vibrant, flexible and caring culture"], "locations": ["Tsuen Wan Area"], "categories": ["Admin & HR", "Clerical / Admin Staff", "HR Supporting Staff", "Information Technology (IT)", "Support"], "post_time": "2022-01-15T03:49:14Z", "salary": {"currency": null, "max": null, "min": null, "period": "monthly", "term": null}, "salary_visible": false, "title_keywords": ["human resources assistant"], "responsibilities": [], "requirements": {"degrees": [], "majors": [], "languages": [], "language_level": [], "hard_skills": [], "soft_skills": [], "languages_combined": []}, "experience_required": {"duration": [], "field": []}}, {"job_id": "100003009052012", "location_code": "hk", "company": "Phonak Hearing Centre Hong Kong Ltd", "job_title": "Personnel & Administration Assistant", "description": "KAM HEALTHCARE GROUP\n\n\u7518\u5cf0\u91ab\u7642\u4fdd\u5065\u96c6\u5718\n\nPhonak Hearing Centre HK Ltd\n\nA leading professional hearing centre in TST is seeking an applicant for the post of :\n\nPersonnel & Administration\u00a0Assistant\n\nJOB DUTIES\n\nTo be responsible for Personnel duties such as recruitment, selection and interview of new employees.\nTo be responsible for duties of payroll, leave management, attendance management, MPF/ORSO, updating staff handbook and IR56b submission.\nTo be responsible for maintaining HR Pro Personnel system by recording personal information, termination and job classifications etc.\nTo assist in preparing the work of staff appraisal and staff training and development.\nTo be responsible for duties of administration includingmedical insurance, office supplies, office machine repair and maintenance, petty cash management, whatsApp group updating etc.\nTo be responsible for additional work related to Secretary, Personnel and Administration.\nJob Requirements:\n\nDiploma/ Associate Degree or above in HR/Admin\u00a0preferred\n1-2 years working experience in HR & Admin\u00a0preferred\nGood command of spoken English & Chinese\nPC knowledge such as Microsoft Word, Excel & Chinese Word Processing\n\nWe offer attractive salary and fringe benefits including upto 20 days\u2019 annual leave, 5 day work week, year-end bonus, medical insurance, provident fund, educational assistance to the right person. Interest candidates please fax resume to 28450299 Or E-mail\u00a0", "employment_types": ["Full Time", "Permanent"], "selling_points": ["Attractive Salary Package & Benefit, 5 day work", "Diploma/Associate Degree or Above in HR & Admin", "1-2 years working experience in HR & Admin"], "locations": ["Tsim Sha Tsui"], "categories": ["Admin & HR", "Clerical / Admin Staff", "Secretary", "HR Supporting Staff"], "post_time": "2022-01-17T01:50:09Z", "salary": {"currency": null, "max": null, "min": null, "period": "monthly", "term": null}, "salary_visible": false, "title_keywords": ["administration assistant"], "responsibilities": ["attendance", "management", "mpf", "maintaining", "maintenance", "office supplies", "hr", "repair", "recruitment", "insurance", "payroll", "administration"], "requirements": {"degrees": ["diploma", "degree or above"], "majors": [], "languages": ["english", "chinese"], "language_level": ["good command"], "hard_skills": ["excel", "pc knowledge", "microsoft word", "chinese word processing"], "soft_skills": [], "languages_combined": [{"language": "english", "language_level": ["good command"]}, {"language": "chinese", "language_level": ["good command"]}]}, "experience_required": {"duration": ["1-2 years"], "field": ["hr", "admin"]}}, {"job_id": "100003009049316", "location_code": "hk", "company": "Bright Future Pharmaceutical Laboratories Ltd", "job_title": "HR Officer", "description": "Responsibilities\n\nProvide HR functions including but not limited to recruitment, compensation & benefits, administration support and employee relations.\nResponsible for payroll calculation, tax reporting, MPF and leave administration, maintain HR database in accurate manner (such as personal information, leave and attendance records), and filing etc.\nAssist in recruitment activities such as CV screening, phone interviews, job fairs and recruitment talks.\nPrepare regular HR reports for management review.\nPerform ad hoc projects as assigned.\n\nRequirements\n\nDegree in Human Resources Management/Business Administration or equivalent. Attention to details with good numerical & analytical skills.\nStrong PC skills and proficient in MS Office applications (Word, Excel, PowerPoint and Chinese Word Processing).\nWell versed in HK Employment Ordinance and related legislation.\nGood team player with enthusiastic and cheerful personality.\nWell-organized, self-initiated, willing to learn.\nGood command of written and spoken English and Chinese.\nFresh Graduate will also considered\n\n\nAttractive salary and fringe benefits will be offered to the successful candidates. Please apply with full resume, available date, present and expected salary and quoting the reference code on the letter & envelope to THE HUMAN RESOURCES & TRAINING DEPARTMENT, HIP HING CONSTRUCTION CO., LTD., 11/F., Chevalier Commercial Centre, No. 8 Wang Hoi Road, Kowloon Bay, Hong Kong OR click \"Apply Now\" OR fax to 2530 4360.\n\nCompany Website: www.hiphing.com.hk\n\nAll personal data collected will be used for recruitment purposes only.\nApplicants who are not invited for an interview within 8 weeks may consider their applications unsuccessful.\nPlease enable the \"Pop-up\" setting of your browser, click here for steps.", "employment_types": ["Full Time", "Permanent"], "selling_points": ["Free shuttle bus in Yuen Long/Fanling and luncheon", "Higher Diploma holder, major in HR", "Able to work in a fast-paced environment"], "locations": ["Yuen Long"], "categories": ["Admin & HR", "HR Supporting Staff", "Recruitment / Executive Search"], "post_time": "2022-01-14T08:27:55Z", "salary": {"currency": null, "max": null, "min": null, "period": "monthly", "term": null}, "salary_visible": false, "title_keywords": ["hr officer"], "responsibilities": [], "requirements": {"degrees": [], "majors": [], "languages": [], "language_level": [], "hard_skills": [], "soft_skills": [], "languages_combined": []}, "experience_required": {"duration": [], "field": []}}, {"job_id": "100003009046696", "location_code": "hk", "company": "Asia Airfreight Terminal Co Ltd", "job_title": "Human Resources Officer - Fresh graduates are welcome", "description": "Duties\n\n\nProvide support to HR department for full spectrum of HR functions, including\u00a0 recruitment, performance management, staff relations, uniform management, and other personnel related issues\nAssist to prepare recruitment advertisement, screen applications, conduct interviews and make employment offer\nPrepare reports, maintain staff\u00a0 record in HR system and personal file keeping\nProvide support to ad-hoc assignment when necessary\n\nRequirements\n\n\nDegree holder or Diploma holder with minimum 1 year relevant experience; preferred in HR or qualification equivalent to the standards of Level 3 or above in HKQF in related field\nProficiency in \u00a0MS Office and Chinese word processing\nSelf-motivated and able to meet tight deadline\nA team player,\u00a0helpful and approachable\u00a0\nStrong communication and interpersonal skills\nCandidates with less working experience will be considered as a less senior position\n\nWe offer the right incumbent attractive remuneration package including 12 days annual leave, 5-day week, double pay, discretionary bonus, medical scheme, life insurance, travel allowance and education subsidy.\n\nInterested parties please send your full resume with reference no., recent and expected salary to:\u00a0Human Resources Department, Asia Airfreight Terminal Co. Ltd., 10 Chun Ping Road, Hong Kong International Airport, Lantau, Hong Kong\u00a0OR Fax to\u00a02286 0374\u00a0OR\u00a0Please click \u201cApply Now\u201d to submit your application.\n\nTo know more about AAT, please visit\u00a0http://www.aat.com.hk\n\nWe are an equal opportunity employer and welcome applications from all qualified candidates. We will not be responsible for any disclosure or the loss of personal data during transmission. All personal data collected will be used for recruitment only. Information of unsuccessful candidates will be destroyed after 3 months from the date of application.", "employment_types": ["Full Time", "Permanent"], "selling_points": ["12 days annual leave, 5-day week, double pay", "Provide support for full spectrum of HR functions", "Self-motivated, a team player, helpful"], "locations": ["Airport Area"], "categories": ["Admin & HR", "Others", "Compensation & Benefits", "HR Supporting Staff"], "post_time": "2022-01-13T18:54:25Z", "salary": {"currency": null, "max": null, "min": null, "period": "monthly", "term": null}, "salary_visible": false, "title_keywords": ["human resources officer"], "responsibilities": ["ad-hoc", "provide support", "management", "hr", "maintain", "recruitment", "prepare reports"], "requirements": {"degrees": ["diploma holder", "degree holder"], "majors": [], "languages": ["chinese"], "language_level": ["proficiency"], "hard_skills": ["chinese word processing", "scheme", "ms office"], "soft_skills": ["self-motivated", "approachable", "communication and interpersonal skills", "meet tight deadline", "team player"], "languages_combined": [{"language": "chinese", "language_level": ["proficiency"]}]}, "experience_required": {"duration": ["minimum 1 year"], "field": ["relevant experience"]}}, {"job_id": "100003009054569", "location_code": "hk", "company": "RecruitFirst Limited", "job_title": "HR Business Partner / HR Executive", "description": "RecruitFirst is part of HRnetGroup - A Singapore listed company with offices in 13 Asian cities.\n\nAs the Group HRBP, you will:\n\n\nHandle end-to-end local or regional recruitment by matching talents to our recruitment brands\nPerform full spectrum of internal recruitment process includes sourcing of candidates, interview assessments and on-boarding process\nDrive internship programs and campus recruitment to achieve the hiring goals of the Group\nConduct orientation and training on a regular basis and to support annual performance evaluation\nEnhance employer branding through participation in marketing activities such as CSR events, career fairs etc\nAssist in HR administration and support in various HR projects and functions\n\nRequirements:\n\nBachelor\u2019s degree with minimum 3 years of experience, previous experience in recruitment agency or human resources is preferred\nIndependent, proactive, good communication and possess strong problem-solving skills\nPassionate, organized with a positive attitude and is able to work under pressure\nGood communication skills and fluent in English & Chinese\nCandidate with less experience maybe considered as HR Executive", "employment_types": ["Full Time", "Permanent"], "selling_points": [], "locations": ["Wan Chai"], "categories": ["Sales, CS & Business Devpt", "Customer Service - Supervisor / Officer", "Admin & HR", "HR Supporting Staff", "Recruitment / Executive Search"], "post_time": "2022-01-17T10:06:54Z", "salary": {"currency": null, "max": null, "min": null, "period": "monthly", "term": null}, "salary_visible": false, "title_keywords": ["hr", "executive"], "responsibilities": ["work under pressure", "hr", "communication", "recruitment", "evaluation", "recruitment process", "administration"], "requirements": {"degrees": ["degree", "bachelor"], "majors": [], "languages": ["english", "chinese"], "language_level": ["fluent", "good"], "hard_skills": ["problem-solving skills"], "soft_skills": ["passionate", "organized", "communication skills", "independent", "communication", "positive attitude", "problem-solving skills", "proactive", "work under pressure"], "languages_combined": [{"language": "english", "language_level": ["fluent", "good"]}, {"language": "chinese", "language_level": ["fluent", "good"]}]}, "experience_required": {"duration": ["minimum 3 years"], "field": ["agency", "hr", "recruitment", "human resources"]}}, {"job_id": "100003009050431", "location_code": "hk", "company": "Broadway Photo Supply Ltd", "job_title": "Assistant Human Resources Officer / Human Resources Assistant", "description": "Responsibilities :\n\nAssist in providing support to full spectrum of human resources functions including recruitment and selection, compensation and benefits, employee relations, performance management, etc.\nPerform ad-hoc projects as assigned\n\nRequirements :\n\nDegree holder in Human Resources Management or related disciplines\nMinimum 3 years\u2019 relevant experience in sizable companies, preferably in retail industry\nWell versed in Hong Kong Employment Ordinance and other HR related regulations / ordinances\nProficiency in MS Office, Chinese Word Processing and knowledgeable in computerized HR Information System\nGood command of written and spoken English, Cantonese and Mandarin\nSelf-driven, good team-player with excellent communication and interpersonal skills\nMature, well-organized, meticulous and able to work under pressure\nImmediate available will be highly preferred\nCandidate with less experience will be considered as Human Resources Assistant\n\nThe working location is at Kwun Tong (King Yip Street). We offer 5-day work week, career advancement opportunities and attractive remuneration package to the right candidate. Interested parties, please send the full resume & expected salary to Human Resources Department via Apply Now.\n\n\n\n(All information submitted will be used for recruitment purpose only and will be destroyed after completion of the process.)", "employment_types": ["Full Time", "Permanent"], "selling_points": [], "locations": ["Kwun Tong"], "categories": ["Admin & HR", "Compensation & Benefits", "HR Supporting Staff", "Recruitment / Executive Search"], "post_time": "2022-01-14T10:24:29Z", "salary": {"currency": null, "max": null, "min": null, "period": "monthly", "term": null}, "salary_visible": false, "title_keywords": ["assistant human resources officer", "human resources assistant"], "responsibilities": ["management", "recruitment", "providing support", "ad-hoc projects", "human resources functions"], "requirements": {"degrees": ["degree holder"], "majors": ["related disciplines"], "languages": ["cantonese", "english", "chinese", "mandarin"], "language_level": ["proficiency", "good command"], "hard_skills": ["chinese word processing", "hong kong employment ordinance", "sizable companies", "information system", "ms office"], "soft_skills": ["meticulous", "team-player", "well-organized", "mature", "communication and interpersonal skills", "driven", "work under pressure"], "languages_combined": [{"language": "cantonese", "language_level": ["good command"]}, {"language": "english", "language_level": ["good command"]}, {"language": "chinese", "language_level": ["proficiency"]}, {"language": "mandarin", "language_level": ["good command"]}]}, "experience_required": {"duration": ["minimum 3 years"], "field": ["retail industry", "relevant experience", "human resources"]}}, {"job_id": "100003009050060", "location_code": "hk", "company": "Network Guard Limited", "job_title": "HR Operations Specialist", "description": "Responsibilities\n\nManage HR system and handle filing work to ensure completeness of HR records and maintenance of most up-to-date staff data\nUpdate changes and adjustments to the Company\u2019s payroll system\nResponsible for recruitment including job posting, prepare interview, prepare employment contract, on-board arrangement and staff orientation\nCoordinate and execute various employee engagement, employee relations programs and activities\nPerform full spectrum of office administrative operations and functions, including but not limited to office, equipment procurement and maintenance\n\n\u00a0Requirement:\n\nHigher Diploma holder or above in Human Resources Management or related disciplines\nMinimum 3 years relevant working experience\nAble to work under tight schedules and react to change\nWell versed with HK Labour Law\nImmediate available is highly preferred\n\nAll applications will be treated in strict confidence and used for recruitment purpose only.", "employment_types": ["Full Time", "Permanent"], "selling_points": ["Flexible working hours", "Multicultural teams", "Challenging, collaborative, and fun environment"], "locations": ["Wan Chai"], "categories": ["Admin & HR", "Clerical / Admin Staff", "Others", "HR Supporting Staff"], "post_time": "2022-01-14T09:45:33Z", "salary": {"currency": null, "max": null, "min": null, "period": "monthly", "term": null}, "salary_visible": false, "title_keywords": ["specialist", "operations", "hr"], "responsibilities": ["maintenance", "data", "operations", "hr", "coordinate", "recruitment", "payroll"], "requirements": {"degrees": ["higher diploma holder"], "majors": ["related disciplines"], "languages": [], "language_level": [], "hard_skills": ["react"], "soft_skills": ["confidence"], "languages_combined": []}, "experience_required": {"duration": ["minimum 3 years"], "field": ["relevant working experience"]}}, {"job_id": "100003009027494", "location_code": "hk", "company": "Swire Waste Management Limited", "job_title": "Human Resources & Administration Officer", "description": "Location: HK\n\nAbout This Role\n\nWe are looking for a meticulous and proactive HR Operations Specialist to join our expanding Human Resources team in Hong Kong. You will report to and work directly with the Senior HR & Office Manager as a key member of the team provides administrative support of all-round HR functions to drive operational efficiency.\u00a0\n\nYou are confident, detail-oriented, friendly with helpful nature, able to effectively communicate with people at all levels. You will be one of the key contributors to providing excellent HR services to the fast-growing company.\u00a0\n\n\nRole Responsibilities\n\n\nEnsure the accuracy and data freshness of the HRIS system\nAssist in the on-boarding and off-boarding processes, payroll and benefits administration, MPF, visa applications, and other administrative processes\nPrepare monthly & quarterly HR analytics and reporting\nResolve inquiries from employees related to employment visas, MPF, benefits, policies and more.\nArrange employee engagement activities\nOrganise training workshops to internal staffs\nRole Requirements\n\n\nAt least 2 years of working experience within the HR function\nAbility to work both independently and collaboratively\nFluent communication skills in English and Chinese\nExcellent computer skills (e.g. Microsoft Office, G-suite)\nQuick learner in picking up new technologies or applications\nOptional\n\n\nExperience working within the technology industry\nHand-on experience in using HRIS systems\nWhat we offer\n\n\nChallenging work in a fun and collaborative environment\nAttractive compensation and time-off benefits\nSpacious open-concept and centrally located offices\nFinancially successful and profitable company\nFull-time employment with flexible working hours\nFully stocked pantry with healthy foods and fresh fruit\nTeam lunches and company events every quarter\nMulticultural teams represented by 30+ nationalities\nNote: Please upload your resume as a PDF and do not include any salary or compensation information in it.", "employment_types": ["Full Time"], "selling_points": ["Diploma holder in Human Resources Management", "Minimum 2 year\u2019s related working experience", "Strong numerical sense and accounting concepts"], "locations": ["North Point"], "categories": ["Admin & HR", "Clerical / Admin Staff", "Others", "HR Supporting Staff"], "post_time": "2022-01-13T18:54:42Z", "salary": {"currency": null, "max": null, "min": null, "period": "monthly", "term": null}, "salary_visible": false, "title_keywords": ["administration officer", "human resources"], "responsibilities": ["data"], "requirements": {"degrees": [], "majors": [], "languages": [], "language_level": [], "hard_skills": [], "soft_skills": [], "languages_combined": []}, "experience_required": {"duration": [], "field": []}}, {"job_id": "100003009051121", "location_code": "hk", "company": "Fortress", "job_title": "People Services (HR) Specialist", "description": "Job Description\n\nThe incumbent will assist the Assistant Manager, Human Resources & Administration Officer to perform HR and Administration functions\nPerform full spectrum of HR functions and activities including payroll administration, recruitment, compensation and benefits, performance management, training and development, and employee relations\nParticipate in various HR projects such as salary and benefit surveys, salary and bonus exercise, performance appraisal, insurance renewal and other HR initiatives as required\nMaintain and update the HR system, employee personnel files and records\nHandle all-round administrative and clerical duties such as office supplies replenishment and management, office renovation, repair and maintenance; IT support service coordination\nHandle renewal of license for the company vehicle;\nPrepare monthly report with progress updates in an accurate and timely manner;\nCoordinate and assist in organizing staff activities and events and ad hoc projects as assigned\n\nRequirement\n\nDiploma holder in Human Resources Management, Business Administration or related disciplines\nMinimum 2 year\u2019s related working experience\nStrong numerical sense and accounting concepts\nSelf-motivated to drive for excellent service\nWell organized, proactive and able to work under pressure\nProficient in Microsoft Office applications Excel, Words and Powerpoint\nGood command of spoken and written Chinese and English\n\nNorth Point area. We offer 5-day work, medical insurance and competitive remuneration package to the right candidate.", "employment_types": ["Full Time"], "selling_points": [], "locations": ["Shatin Area"], "categories": ["Admin & HR", "HR Supporting Staff"], "post_time": "2022-01-15T03:00:00Z", "salary": {"currency": null, "max": null, "min": null, "period": null, "term": null}, "salary_visible": false, "title_keywords": ["specialist", "hr"], "responsibilities": ["management", "maintenance", "office supplies", "hr", "renovation", "replenishment", "coordinate", "repair", "maintain", "recruitment", "ad hoc projects", "insurance", "coordination", "monthly report", "payroll", "administration"], "requirements": {"degrees": ["diploma holder"], "majors": ["related disciplines", "business administration"], "languages": ["english", "chinese"], "language_level": ["good command"], "hard_skills": ["powerpoint", "excel", "words", "microsoft office"], "soft_skills": ["self-motivated", "proactive", "well organized", "work under pressure"], "languages_combined": [{"language": "english", "language_level": ["good command"]}, {"language": "chinese", "language_level": ["good command"]}]}, "experience_required": {"duration": ["minimum 2 year"], "field": ["related"]}}, {"job_id": "100003009053497", "location_code": "hk", "company": "Automated Systems (HK) Ltd", "job_title": "Recruiter", "description": "The successful candidate will be responsible for:\n\nParticipate in recruitment related activities including job ad design (O+O), talent sourcing, interview arrangements, onboarding and offboarding process\nProvide professional advice & support to line managers on staffing & manpower planning issue\nProvide support in various employee relations initiatives and events such as staff development, communication sessions, team building activities, employer branding initiatives\nDevelop creative concept in staff recruitment and employer branding involving the use of digital platform\nMaintain people record & database and compile regular report & analysis for management review\n\n\u00a0Requirements:\n\nBachelor's Degree in Human Resources or related disciplines\nAt least\u00a03 years' of experience in People Management\nPrevious experience in Retail or FMCG Industry will be an advantage\nWell organized and ability to manage multiple tasks within a tight deadline\nA proactive team player with good communication in both written and spoken English and Mandarin\nProficient in using MS Office including Word, Excel and Power Point\nCandidate with more experience will be considered as Senior People Services Specialist\n\nA rewarding remuneration package will be offered to the successful candidate. Interested parties please forward detailed resume stating expected salary by email to us.\n\nWe are an equal opportunity employer and welcome applications from all qualified candidates. The information provided will be treated in strict confidence and be used only for consideration of your application for relevant / similar posts within the A.S. Watson Group. All personal data of unsuccessful applicants will be destroyed within 12 months from the date of application.", "employment_types": ["Full Time"], "selling_points": ["Degree in in Business Administration", "1 years\u2019 experience in recruitment", "Attractive Commission Scheme"], "locations": ["Shatin Area"], "categories": ["Admin & HR", "Others", "HR Supporting Staff", "Recruitment / Executive Search"], "post_time": "2022-01-17T07:03:26Z", "salary": {"currency": null, "max": null, "min": null, "period": "monthly", "term": null}, "salary_visible": false, "title_keywords": [], "responsibilities": ["provide support", "management", "analysis", "design", "develop", "communication", "digital platform", "maintain", "recruitment", "database", "report", "management review", "planning"], "requirements": {"degrees": ["degree", "bachelor"], "majors": ["related disciplines"], "languages": ["english", "mandarin"], "language_level": ["good"], "hard_skills": ["excel", "analysis", "fmcg industry", "word", "power point", "ms office"], "soft_skills": ["proactive", "responsible", "multiple tasks", "well organized", "communication", "team player", "creative"], "languages_combined": [{"language": "english", "language_level": ["good"]}, {"language": "mandarin", "language_level": ["good"]}]}, "experience_required": {"duration": ["at least 3 years"], "field": ["people management", "retail", "fmcg"]}}, {"job_id": "100003009052927", "location_code": "hk", "company": "Swing Consulting Limited", "job_title": "Recruitment Assistant", "description": "We are looking for a young and ambitious talent to join our in-house recruitment team. You will work closely with the HR team and Hiring Managers in delivering excellent services.\n\n\nJob Responsibilities:\n\n\nDevelop and implement creative recruitment strategies including job advertisements, conducting proactive search.\nWork with hiring managers to develop strategies for talent search.\nPerform end-to-end recruitment process from sourcing to offer negotiation.\nSource candidates from different channels.\nExplore new and effective sourcing channels.\nEnhance and maintain relationship with candidates and internal client.\nEstablish and maintain a database of candidates.\nDeal with the related procedure of talent engagement.\n\nJob Requirements:\n\n\nDegree in in Business Administration, Human Resources or any related field.\nMinimum 1 years\u2019 experience in recruitment agencies or in IT companies.\nIT related recruiting experience will be preferred.\nProficient in English and Chinese is a MUST.\nStrong communication skills to collaborate with team members.\nSelf-driven and result-oriented personality.\nProactive, strong sense of responsibility, detail-oriented.\nAble to be multi-tasking in a tight schedule.\nImmediately available or short notice period is preferred\n\n\nWe offer 5-day week, public holidays, medical benefits, excellent career opportunities, considerable remuneration to the right candidates.\n\u201cIf you have the desire for an exciting and rewarding career, please send us your resume, stating your notice period, present and expected salary to Human Resources Department by clicking \"Apply Now\".\nTo learn us more, please visit our website:\u00a0www.asl.com.hk\nWe are an equal opportunity employer. All applications will be treated in strict confidence. We regret that only shortlisted candidates will be notified. All personal data will be destroyed within six months after the selection process.", "employment_types": ["Full Time", "Permanent"], "selling_points": ["Handle recruitment and selection process", "Candidates sourcing, CVs screening, Interviewing", "5-day work 9:30am to 6pm, good career development"], "locations": ["Kwun Tong"], "categories": ["Admin & HR", "HR Supporting Staff", "Recruitment / Executive Search", "Sales, CS & Business Devpt", "Sales Administration"], "post_time": "2022-01-17T04:34:17Z", "salary": {"currency": "HKD", "max": 19999, "min": 14000, "period": "monthly", "term": null}, "salary_visible": true, "title_keywords": ["assistant"], "responsibilities": ["develop strategies", "advertisements", "develop", "maintain", "recruitment", "database", "recruitment process"], "requirements": {"degrees": ["degree"], "majors": ["business administration"], "languages": ["english", "chinese"], "language_level": ["proficient"], "hard_skills": [], "soft_skills": ["communication skills", "sense of responsibility", "driven", "detail-oriented", "multi-tasking", "proactive", "result-oriented"], "languages_combined": [{"language": "english", "language_level": ["proficient"]}, {"language": "chinese", "language_level": ["proficient"]}]}, "experience_required": {"duration": ["minimum 1 years"], "field": ["related", "it", "recruitment"]}}, {"job_id": "100003009049195", "location_code": "hk", "company": "Premier by Dead Sea", "job_title": "Senior Human Resources Officer", "description": "Responsibilities:\n\nHandle recruitment and selection process, including job posting, candidates sourcing, CVs screening, interviewing, etc.\nReview CVs and credentials for suitability of skills, experience and knowledge in relation to position requirements using appropriate selection techniques\nBrief candidates on suitable positions and prepare them for interview with clients\nPrepare regular advertisement postings on different channels\nHandle other ad-hoc projects and assignments\n\n\u00a0Requirements:\n\nDiploma or above.\nSelf-disciplined, hardworking and able to work independently.\nStrong organization skills, independent, professional.\nGood command of both written and spoken English and Chinese.\nImmediate available will be an advantage.\nFresh Graduate is welcome.\nWorking Hour: 9:30am - 6:00pm (Mon to Fri)\n\nTo apply, you may click the\u00a0Apply Now\u00a0button below\u00a0or\u00a0send your full resume to\u00a0fax: 3426 2763\n\nFor other vacancies, please visit our website www.swing-hk.com\n\nJoin us on facebook \u2013 www.facebook.com/swinghk\n\nAll information provided will be treated in strict confidence and used for recruitment purposes only.", "employment_types": ["Full Time", "Permanent"], "selling_points": ["Handling full spectrum of HR functions", "Work with line managers to determine hiring needs", "Responsible for payroll calculation"], "locations": ["Kwun Tong"], "categories": ["Admin & HR", "Compensation & Benefits", "HR Supporting Staff", "Recruitment / Executive Search"], "post_time": "2022-01-14T08:15:12Z", "salary": {"currency": null, "max": null, "min": null, "period": "monthly", "term": null}, "salary_visible": false, "title_keywords": ["senior human resources officer"], "responsibilities": ["ad-hoc projects", "review", "recruitment"], "requirements": {"degrees": ["fresh graduate", "diploma or above"], "majors": [], "languages": ["english", "chinese"], "language_level": ["good command"], "hard_skills": ["facebook"], "soft_skills": ["work independently", "confidence", "independent", "organization skills", "hardworking"], "languages_combined": [{"language": "english", "language_level": ["good command"]}, {"language": "chinese", "language_level": ["good command"]}]}, "experience_required": {"duration": [], "field": []}}, {"job_id": "100003009048925", "location_code": "hk", "company": "Miramar Travel Ltd", "job_title": "Human Resources Assistant (Job Ref. 202201-HR&A-HRA)", "description": "Responsibilities\n\nProvide administrative support on different aspects of Human Resources including talent acquisition, employee relations, HRIS data maintenance, leave management, general administrative support, etc.\nHandle visitors\u2019 enquiries and incoming calls\nAssist in Human Resources related ad hoc projects and other duties as assigned by supervisors\n\nRequirements\n\nBachelor degree\u00a0in Human Resources Management or related disciplines\nFresh graduates will be considered.\nCandidate with more experience will be considered as Assistant Human Resources Officer\nGood communication and interpersonal skills with good telephone manner\nWell organized, multi-tasking and able to work independently\nPositive thinking and possesses teamwork spirit\nGood command of both written and spoken English and Chinese\nProficient in MS Office including Word, Excel & PowerPoint\n\nWe offer an attractive remuneration package and excellent career prospects to the right candidate.\n\nPlease apply with full details of academic qualifications, work experience, date of available, present and expected salary and email to\u00a0[via APPLY NOW]\n\nPlease refer to our website\u00a0www.compass-hk.com\u00a0for more information about our company.\n\nWe are an equal opportunity employer and welcome applications from all qualified candidates.", "employment_types": ["Full Time"], "selling_points": [], "locations": ["Causeway Bay"], "categories": ["Admin & HR", "Compensation & Benefits", "HR Supporting Staff", "Recruitment / Executive Search"], "post_time": "2022-01-14T07:43:29Z", "salary": {"currency": null, "max": null, "min": null, "period": "monthly", "term": null}, "salary_visible": false, "title_keywords": ["human resources assistant"], "responsibilities": ["management", "maintenance", "data", "other duties", "general administrative support", "ad hoc projects", "provide administrative support"], "requirements": {"degrees": ["degree", "bachelor"], "majors": ["related disciplines"], "languages": ["english", "chinese"], "language_level": ["good command"], "hard_skills": ["excel", "word", "powerpoint", "ms office"], "soft_skills": ["work independently", "well organized", "positive thinking", "multi-tasking", "communication and interpersonal skills", "teamwork spirit", "telephone manner"], "languages_combined": [{"language": "english", "language_level": ["good command"]}, {"language": "chinese", "language_level": ["good command"]}]}, "experience_required": {"duration": [], "field": ["human resources"]}}, {"job_id": "100003009048158", "location_code": "hk", "company": "Global Enterprises (HK) Limited", "job_title": "Senior HR & Admin Officer", "description": "Job Duties:\n\nHandling full spectrum of HR functions\nResponsible for payroll calculation, reviewing supporting document\nWork with line managers to determine hiring needs and select suitable candidates for final selection\nPrepare HR reports on regular basis for management review\nAssist in ad hoc projects\n\nJob Requirements:\n\nA Degree in Human Resources Management, Business Administration or related discipline;\nAt least 5 years of working experience in HR generalist position\u00a0\nGood interpersonal & communication skills;\nFamiliar with Employment Ordinance, MPF schemes and regulations\nMulti-tasking, meticulous, organized and able to meet tight work deadlines\nPleasant, strong sense of accountability and passionate about people\nGood command of written and spoken English and Chinese\nLess experience will be considered as Human Resources Officer", "employment_types": ["Full Time", "Permanent"], "selling_points": ["Discretionary Bonus", "5-day work", "Familiar with Hong Kong Employment Ordinance"], "locations": ["Tsim Sha Tsui"], "categories": ["Admin & HR", "HR Supporting Staff"], "post_time": "2022-01-14T05:30:05Z", "salary": {"currency": null, "max": null, "min": null, "period": "monthly", "term": null}, "salary_visible": false, "title_keywords": ["senior hr & admin officer"], "responsibilities": ["hr", "hr reports", "ad hoc projects", "payroll", "management review"], "requirements": {"degrees": ["degree"], "majors": ["business administration"], "languages": ["english", "chinese"], "language_level": ["good command"], "hard_skills": [], "soft_skills": ["organized", "communication skills", "meticulous", "accountability", "pleasant", "multi-tasking", "interpersonal", "passionate about"], "languages_combined": [{"language": "english", "language_level": ["good command"]}, {"language": "chinese", "language_level": ["good command"]}]}, "experience_required": {"duration": ["at least 5 years"], "field": ["hr generalist", "human resources"]}}, {"job_id": "100003009047245", "location_code": "hk", "company": "Hong Kong Aero Engine Services Ltd", "job_title": "Human Resources Assistant (Ref. no.: HRA251121-B)", "description": "Responsibilities:\n\n\nTo assist in all-rounded HR functions, including recruitment, payroll & C&B, etc.\nTo handle ad hoc tasks as assigned\nRequirements:\n\nHigher Diploma or above\u00a0in HR Management or related disciplines\nAt least 2-year HR experience, preferably gained from sizeable organization.\nExcellent interpersonal, communication & presentation skills\nDetail-minded, well-organised, with strong numerical sense and high accuracy\nGood working attitude & be a good team player\nGood command of spoken & written English, Cantonese & Putonghua\nProficient in PC applications, such as Words, Excel, PowerPoint & Chinese Word Processing\nImmediate available is highly preferred\nWe offer attractive remuneration package and excellent career prospect to the right candidate.\u00a0 Salary will be commensurate with applicant\u2019s qualification and experience.\u00a0 Any interested candidates please send your full resume with CURRENT & EXPECTED SALARY and DATE OF AVAILABILITY by clicking 'Apply Now'.\n\n\n\nInformation provided will be treated in strict confidence and only be used for recruitment purpose.\n\nPlease refer to our website www.miramartravel.hk for more openings.", "employment_types": ["Full Time", "Permanent"], "selling_points": ["Provide a wide range of human resources services", "Handle HRIS data maintenance", "Fresh graduates are welcome"], "locations": ["Tseung Kwan O"], "categories": ["Admin & HR", "Clerical / Admin Staff", "HR Supporting Staff", "Recruitment / Executive Search"], "post_time": "2022-01-14T02:39:27Z", "salary": {"currency": null, "max": null, "min": null, "period": "monthly", "term": null}, "salary_visible": false, "title_keywords": ["human resources assistant"], "responsibilities": ["hr", "payroll", "recruitment", "ad hoc tasks"], "requirements": {"degrees": ["higher diploma or above"], "majors": ["related disciplines"], "languages": ["cantonese", "putonghua", "english", "chinese"], "language_level": ["good command", "proficient"], "hard_skills": ["excel", "chinese word processing", "words", "powerpoint", "pc applications"], "soft_skills": ["detail-minded", "good working attitude", "good team player", "communication", "presentation skills", "well-organised", "interpersonal"], "languages_combined": [{"language": "cantonese", "language_level": ["good command"]}, {"language": "putonghua", "language_level": ["good command"]}, {"language": "english", "language_level": ["good command"]}, {"language": "chinese", "language_level": ["proficient"]}]}, "experience_required": {"duration": ["at least 2-year"], "field": ["hr"]}}, {"job_id": "100003009046793", "location_code": "hk", "company": "Cinnox Limited", "job_title": "Assistant HR Officer / HR Assistant (Immedately available)", "description": "\u5de5\u4f5c\u7bc4\u570d\u8207\u8077\u8cac\n\u5efa\u7acb\u8207\u7dad\u8b77\u5305\u62ec\u4f46\u4e0d\u9650\u65bc\u4eba\u4e8b\u5408\u540c\u3001\u6587\u4ef6\u3001\u6a94\u6848\u3001\u8003\u52e4\u8a18\u9304\u53ca\u5176\u4ed6\u57fa\u790e\u8cc7\u6599\uff1b\n\u8ca0\u8cac\u9999\u6e2f\u54e1\u5de5\u85aa\u916c\u53ca\u798f\u5229\uff0c\u5305\u62ec\u5de5\u8cc7\u3001\u88dc\u8cbc\u3001\u5f37\u7a4d\u91d1\u3001\u500b\u4eba\u5165\u606f\u7a05\uff0c\u4fdd\u96aa\u53ca\u5176\u4ed6\u798f\u5229\uff08\u5982\u9069\u7528\uff09\u7684\u8a08\u7b97\u53ca\u7d71\u8a08\uff0c\u751f\u6210\u548c\u7dad\u8b77\u8cc7\u6599\u5eab\uff0c\u7de8\u5236\u4eba\u529b\u6210\u672c\u6708\u5831\u3001\u5e74\u5831\uff0c\u4ee5\u53ca\u4e0a\u7d1a\u55ae\u4f4d\u6216\u516c\u53f8\u7ba1\u7406\u9700\u8981\u7684\u7d71\u8a08\u7d50\u679c\u8207\u5831\u544a\uff1b\n\u53c3\u8207\u4eba\u4e8b\u57f7\u884c\u8cc7\u8a0a\u7cfb\u7d71\u512a\u5316\u5de5\u4f5c\uff1b\n\u5354\u52a9\u8a55\u4f30\u5be9\u67e5\u4eba\u4e8b\u653f\u7b56\u3001\u5236\u5ea6\u6d41\u7a0b\u9069\u7528\u6027\uff0c\u63d0\u51fa\u6539\u9032\u5efa\u8b70\uff0c\u8ddf\u9032\u5f8c\u7e8c\u7684\u7dad\u8b77\u8207\u512a\u5316\u5de5\u4f5c\uff1b\n\u5354\u52a9\u9032\u884c\u4eba\u529b\u8cc7\u6e90\u5e02\u5834\u7814\u7a76\u3001\u4eba\u529b\u8cc7\u6e90\u6230\u7565\u5206\u6790\u548c\u63d0\u51fa\u89e3\u6c7a\u65b9\u6848\u5efa\u8b70\uff1b\n\u8ca0\u8cac\u516c\u53f8\u4eba\u54e1\u8077\u5d17\u7ba1\u7406\uff08\u62db\u8058\u3001\u63d0\u8058\u3001\u8abf\u5d17\u3001\u96e2\u9000\uff09\u3001\u8003\u6838\u7ba1\u7406\uff0c\u57f9\u8a13\u7b49\u5177\u9ad4\u5de5\u4f5c\uff1b\n\u5728\u90e8\u9580\u8ca0\u8cac\u4eba\u6307\u5c0e\u4e0b\uff0c\u7de8\u5236\u9999\u6e2f\u8fa6\u516c\u5ba4\u4eba\u4e8b\u884c\u653f\u5e74\u5ea6\u9810\u7b97\uff1b\n\u505a\u597d\u90e8\u9580\u4ea4\u8fa6\u7684\u5176\u4ed6\u5de5\u4f5c\u3002\n\nJob Descriptions:\n\n\nReporting to the Head of HR and Administration in providing full spectrum of human resources functions including but not limited to compensation and benefits, recruitment and selection, performance management, taxation, MPF, policy review, insurance renewal, system implementation and ad-hoc projects.\n\n\nParticipate in formulating HR related policies and procedures in compliance with legal requirements, company standard and HR practice;\nProvide support for annual salary and benefit review, salary benchmarking and benefits surveys;\nEnsure accuracy and monthly payroll calculation for both Headquarter and subsidiaries;\nManage attendance and leave data in HRIS on regular basis to facilitate report generation and payroll processing;\nMaintain updated HR records in human resources systems and personal file system;\nPrepare regular HR reports, annual budget and forecast required by the Group or Management;\nParticipate in HR system & advancement project;\nSupport HR ad-hoc duty assigned by Supervisor.\n\nRequirements:\n\n\nBachelor Degree holder in Human Resources Management or related discipline;\nMinimum 3-5 years of relevant working experience with\u00a0hands-on experience in payroll and C&B function; with experience in Chinese Enterprises is an advantage;\nWell versed in Employment Ordinance, MPF and other related statutory regulations;\nIndependent, well-organized with positive working attitude and ability to handle multi-tasks;\nStrong command of written and spoken English & Chinese including Mandarin is a MUST;\nImmediately available is preferred;\nCandidate with less experience will be considered as HR Officer.", "employment_types": ["Full Time", "Permanent"], "selling_points": ["1+ year HR experience with IT/Telecom knowledge", "Familiar with HR Operation, strong in HK labor law", "5 day work, medical Benefit and free luncheon"], "locations": ["Kowloon Bay"], "categories": ["Admin & HR", "HR Supporting Staff", "Recruitment / Executive Search", "Training & Development"], "post_time": "2022-01-14T01:09:54Z", "salary": {"currency": null, "max": null, "min": null, "period": "monthly", "term": null}, "salary_visible": false, "title_keywords": ["hr officer", "hr assistant", "assistant"], "responsibilities": ["reporting", "management", "taxation", "mpf", "policies", "hr", "review", "procedures", "implementation", "compliance", "recruitment", "ad-hoc projects", "insurance", "human resources functions", "administration"], "requirements": {"degrees": [], "majors": [], "languages": [], "language_level": [], "hard_skills": [], "soft_skills": [], "languages_combined": []}, "experience_required": {"duration": [], "field": []}}, {"job_id": "100003009054420", "location_code": "hk", "company": "RecruitFirst Limited", "job_title": "Part-time Payroll & Admin Executive", "description": "Responsibilities:\n\nProvide a wide range of human resources services, such as recruitment & selection, compensation & benefits, employee relations, leave administration, staff benefits provision and training administration\nProvide support to company activities and event administration\nHandle HRIS data maintenance and ad hoc HR projects\n\nRequirements:\n\n\nDegree in Human Resources Management or other related discipline\nProficient in MS Office, especially in MS Excel would be an advantage\nExcellent interpersonal and communication skills\nGood analytical & organizing skills\nProficiency in spoken & written English\nA team player with self-initiative, pleasant, responsible and detail-minded\n1-3 years relevant experience\nFresh graduates are welcome\n\nInterested parties please send a full resume with expected salary and quote our reference number to Human Resources Department, Hong Kong Aero Engine Services Ltd., 70 Chun Choi Street, Tseung Kwan O Industrial Estate, N.T. or alternatively, email us by clicking \"Apply Now\".\n\n\nPlease feel free to visit our company website at www.haesl.com.\n\nData collected will be used for recruitment purpose only\n\n\u201cApplicants not invited for interview within three weeks from the date of submitting CV may consider their application unsuccessful.\u201d", "employment_types": ["Part Time", "Temporary", "Freelance"], "selling_points": [], "locations": ["Wan Chai"], "categories": ["Admin & HR", "Clerical / Admin Staff", "Compensation & Benefits", "HR Supporting Staff"], "post_time": "2022-01-17T09:27:37Z", "salary": {"currency": null, "max": null, "min": null, "period": "monthly", "term": null}, "salary_visible": false, "title_keywords": ["admin", "executive"], "responsibilities": ["provide support", "ad hoc", "maintenance", "data", "hr", "recruitment", "administration"], "requirements": {"degrees": ["degree"], "majors": [], "languages": ["english"], "language_level": ["proficiency"], "hard_skills": ["ms excel", "ms office"], "soft_skills": ["detail-minded", "communication skills", "responsible", "pleasant", "self-initiative", "team player", "interpersonal"], "languages_combined": [{"language": "english", "language_level": ["proficiency"]}]}, "experience_required": {"duration": ["1-3 years"], "field": ["relevant experience"]}}, {"job_id": "100003009047792", "location_code": "hk", "company": "Shun Hing Electric Service Centre Limited", "job_title": "Assistant Human Resources Officer", "description": "WHAT you be doing in this role:\n\nAssist in full spectrum of HR functions including talent acquisition, training & development, compensation & benefits and employee relations etc.;\nHandle end-to-end recruitment process and support colleagues' life cycle administration including on-boarding and off-boarding logistics arrangement\nMaintain HR database/record management, medical insurance administration, filing system\nHandle and follow up internal colleagues' inquiries\nPrepare HR reports for management review\nImplement employee engagement activities and opportunities\nAdminister online learning management system\nParticipate in other HR initiatives and ad-hoc projects as assigned\nWHO are we looking for:\nHigh Diploma or above in Human Resources Management or other related disciplines\n1 year of HR related working experience, experience in Information Technology / Telecommunication industry is highly preferred\nGood knowledge of labor laws and regulations is preferred\nMature with good communication and interpersonal skills\nGood command of both written and spoken English & Chinese\nIndependent, proactive with positive attitude, enjoy working in a dynamic and fast-paced environment\nImmediate available is preferred\n***Candidates with more experience will be considered as Assistant HR Officer***\n\nWe offer 5 days\u2019 work, medical insurance, free lunch, competitive salary package and attractive career development opportunities to the right candidate.\u00a0Interested parties please send your full resume with date of availability, present and expected salaries by clicking \"Apply Now\".\n\n\nTo protect the privacy of personal data, all applications will be treated in strict confidence. Personal data collected will be used for recruitment purposes only. Applicants not hearing from us within 6 weeks may consider their applications unsuccessful. We may also consider their application for other or future vacancies. Personal data of unsuccessful applicants will be retained for a maximum period of 6 months.", "employment_types": ["Full Time", "Permanent"], "selling_points": [], "locations": ["Kwai Fong"], "categories": ["Admin & HR", "HR Supporting Staff", "Recruitment / Executive Search"], "post_time": "2022-01-14T03:54:37Z", "salary": {"currency": null, "max": null, "min": null, "period": "monthly", "term": null}, "salary_visible": false, "title_keywords": ["assistant human resources officer"], "responsibilities": [], "requirements": {"degrees": [], "majors": [], "languages": [], "language_level": [], "hard_skills": [], "soft_skills": [], "languages_combined": []}, "experience_required": {"duration": [], "field": []}}, {"job_id": "100003009049544", "location_code": "hk", "company": "TDK Electronics Hong Kong Limited", "job_title": "HR Officer (Temporary for 6 months)", "description": "The Role:\n\n\u00a0\u00a0\u00a0\u00a0\u00a0\u00a0\u00a0\u00a0 Provide full scope of payroll processing for Temp / Contract employees\n\u00a0\u00a0\u00a0\u00a0\u00a0\u00a0\u00a0\u00a0 Preparation of billing and on-time dispatch of invoices to clients\n\u00a0\u00a0\u00a0\u00a0\u00a0\u00a0\u00a0\u00a0 Work closely with consultants, temp/ contract employees and clients on payroll\u00a0 and billing queries and instructions\n\u00a0\u00a0\u00a0\u00a0\u00a0\u00a0\u00a0\u00a0 Assist in preparing payroll reports for business leaders\n\u00a0 \u00a0 \u00a0 \u00a0 \u00a0Assist in any ad hoc admin duties assigned by supervisor\n\nRequirements:\n\n\u00a0\u00a0\u00a0\u00a0\u00a0\u00a0\u00a0\u00a0 At least 2 years of experience processing payroll calculation in MNC\n\u00a0\u00a0\u00a0\u00a0\u00a0\u00a0\u00a0\u00a0 Full understanding of the Hong Kong Employment Law, labour ordinance, MPF and tax\u00a0 guidelines\n\u00a0\u00a0\u00a0\u00a0\u00a0\u00a0\u00a0\u00a0 Candidate must possess a Bachelor Degree in any discipline\n\u00a0\u00a0\u00a0\u00a0\u00a0\u00a0\u00a0\u00a0 Good command of spoken and written English and Chinese\n\nInterested candidates can send their latest resume by clicking APPLY NOW\u00a0\n\n** For more job opportunities, please visit our website: www.recruitfirst.com.hk **\n\n** Shortlisted candidates will be notified to the contacts provided **", "employment_types": ["Full Time", "Temporary", "Contract"], "selling_points": [], "locations": ["Shatin Area"], "categories": ["Admin & HR", "Others", "HR Supporting Staff", "Training & Development"], "post_time": "2022-01-14T08:51:15Z", "salary": {"currency": null, "max": null, "min": null, "period": "monthly", "term": null}, "salary_visible": false, "title_keywords": ["hr officer"], "responsibilities": ["tax", "ad hoc", "mpf", "invoices", "guidelines", "reports", "payroll"], "requirements": {"degrees": ["degree", "bachelor"], "majors": [], "languages": ["english", "chinese"], "language_level": ["good command"], "hard_skills": ["processing"], "soft_skills": [], "languages_combined": [{"language": "english", "language_level": ["good command"]}, {"language": "chinese", "language_level": ["good command"]}]}, "experience_required": {"duration": ["at least 2 years"], "field": ["payroll"]}}, {"job_id": "100003009050395", "location_code": "hk", "company": "Gold Partners (Asia) Asset Management Company Limited", "job_title": "Receptionist / HR & Admin Assistant", "description": "Responsibilities:\n\nHandle full spectrum of recruitment activities\u00a0such as job posting, conduct interview and on-board arrangement\nCoordinate, monitor and evaluate internal/external training programmes and maintain accurate training records\nAssist in preparing reports, agenda and minutes\nParticipate in organizing company functions and recreation activities\nProvide support in daily HR operations and administrative work\n\n\u00a0Requirements:\n\nDegree in Human Resources Management\nFamiliar with employment related ordinance and HR Practice\nProficient in MS Word and Excel\nGood communication and interpersonal skills\nSelf-motivated and attentive to details\nWorking experience preferred but fresh graduates are also welcome\nIELTS Score 6.5 or above preferable\n\nInterested parties please send full resume stating the\u00a0expected salary & date of availability.\n\nData collected will be used for recruitment purpose only. It may be transferred to other companies of the Group to see if suitable vacancies arise. Applicants not contacted within 6 weeks may consider their applications unsuccessful. The information will be destroyed.", "employment_types": ["Full Time", "Permanent"], "selling_points": [], "locations": ["Kowloon Bay"], "categories": ["Admin & HR", "Clerical / Admin Staff", "Receptionist", "HR Supporting Staff"], "post_time": "2022-01-14T10:17:19Z", "salary": {"currency": null, "max": null, "min": null, "period": "monthly", "term": null}, "salary_visible": false, "title_keywords": ["receptionist", "hr & admin assistant"], "responsibilities": ["provide support", "administrative work", "operations", "hr", "monitor", "coordinate", "evaluate", "maintain", "recruitment", "preparing reports"], "requirements": {"degrees": ["degree"], "majors": [], "languages": [], "language_level": [], "hard_skills": ["excel", "ms word"], "soft_skills": ["self-motivated", "communication and interpersonal skills", "attentive to details"], "languages_combined": []}, "experience_required": {"duration": [], "field": []}}, {"job_id": "100003009047368", "location_code": "hk", "company": "Hong Kong Ming Wah Shipping Company Limited", "job_title": "Officer / Deputy Officer, Human Resources Department \u4eba\u529b\u8cc7\u6e90\u90e8\u4e3b\u7ba1 / \u526f\u4e3b\u7ba1", "description": "Job Duties:\n\nSupport the HR team in performing the HR functions for GC regions\nPrepare regular HR reports and presentation meeting materials\nAssist to translate HR system guideline from English to Chinese\nSupport the meetings /on-line training logistics\nSupport the HR system enhancement / data management\nAd hoc tasks as assigned by supervisor\nQualification:\n\nA degree in Business Administration with major in Human Resources Management is preferred\nGood command of spoken and written in English and Mandarin\nProficiency in PC applications including MS Word, Excel, PowerPoint, etc.\u00a0\nWilling to learn, detail-minded, good communication and interpersonal skill, able to work under a tight schedule\n3 years or above relevant working experience.\nFlexible working hour is applicable\n\nOur office is located in Hong Kong Science Park, Shatin. All data collected will be used for recruitment purpose only.", "employment_types": ["Full Time", "Permanent"], "selling_points": ["Performance Bonus, Double Pay", "Holiday Benefits, Meal Allowance", "Excellent Prospects for Promotion"], "locations": ["Sheung Wan"], "categories": ["Admin & HR", "Clerical / Admin Staff", "Personal / Executive Assistant", "HR Supporting Staff"], "post_time": "2022-01-14T02:55:32Z", "salary": {"currency": null, "max": null, "min": null, "period": "monthly", "term": null}, "salary_visible": false, "title_keywords": ["officer", "human resources"], "responsibilities": ["management", "data", "hr", "ad hoc tasks", "hr reports", "communication", "logistics", "schedule", "recruitment", "administration"], "requirements": {"degrees": ["degree"], "majors": ["business administration"], "languages": ["english", "chinese", "mandarin"], "language_level": ["good command"], "hard_skills": ["excel", "data management", "powerpoint", "pc applications", "ms word"], "soft_skills": ["detail-minded", "flexible", "willing to learn", "interpersonal skill", "communication", "presentation"], "languages_combined": [{"language": "english", "language_level": ["good command"]}, {"language": "chinese", "language_level": []}, {"language": "mandarin", "language_level": ["good command"]}]}, "experience_required": {"duration": ["3 years"], "field": ["relevant working experience"]}}, {"job_id": "100003009044131", "location_code": "hk", "company": "Woopie Social Enterprises Limited", "job_title": "Human Resources Assistant/Officer", "description": "Responsibilities\n\nResponsible for reception counter duties, handle incoming phone calls, courier, greet visitors etc.\nCarry out clerical and HR / administrative duties in support of department's operations\nCoordinate meeting and travel arrangement\nCoordinate on the office equipment / Tel lines and facilities maintenance\nPrepare HR & clerical regular reports\nHandle other ad hoc projects as required\n\nRequirements\n\nF.6 or above, with minimum 1-2 years working experience in HR & Admin field preferable\u00a0\u00a0\nPleasant personality with good telephone manner, initiative, mature and with good communication skills\nProficiency with MS Word, Excel and Chinese Word Processing\nGood command of spoken and written English, Chinese and Mandarin\u00a0\nImmediate available is preferable\nFresh graduate will be considered\n\nWe Offer:\n\n12 Days Annual Leave\nMedical & Dental Scheme\nOn-the-job Training\nYear-end Bonus\nExcellent Career Advancement Opportunities\nCollaborative working environment\nStaff Caring Benefit, e.g. Festival Gift, Home-made Chinese Herbal Drinks/Soup\u00a0\n\nWe offer competitive remuneration package with excellent career path.\n\nInterested applicants please fax your resume with present &\u00a0expected salary\u00a0to HR & Admin Department at 8161-6498 or click \u201cApply Now\u201d underneath.\n\nFor company information, please visit our website:\u00a0www.goldpartners.com.hk\n\nAll information provided by applicants will be kept confidential and used for recruitment purposes only. The company will retain the information collected for a maximum period of 1 year and may refer suitable\u00a0applicants to other vacancies within the Group.", "employment_types": ["Full Time", "Permanent"], "selling_points": ["Perform all-rounded HR duties", "Develop HR projects for employer branding", "Fresh graduates are welcome to apply"], "locations": ["Lai Chi Kok"], "categories": ["Admin & HR", "Clerical / Admin Staff", "HR Supporting Staff", "Recruitment / Executive Search"], "post_time": "2022-01-13T03:10:37Z", "salary": {"currency": null, "max": null, "min": null, "period": "monthly", "term": null}, "salary_visible": false, "title_keywords": ["officer", "human resources assistant"], "responsibilities": ["maintenance", "operations", "hr", "incoming phone calls", "coordinate", "administrative duties", "reports", "travel arrangement", "ad hoc projects"], "requirements": {"degrees": ["fresh graduate"], "majors": [], "languages": ["english", "chinese", "mandarin"], "language_level": ["proficiency", "good command"], "hard_skills": ["excel", "chinese word processing", "ms word"], "soft_skills": ["communication skills", "mature", "pleasant", "telephone manner", "initiative"], "languages_combined": [{"language": "english", "language_level": ["good command"]}, {"language": "chinese", "language_level": ["proficiency", "good command"]}, {"language": "mandarin", "language_level": ["good command"]}]}, "experience_required": {"duration": ["minimum 1-2 years"], "field": ["hr", "admin"]}}, {"job_id": "100003009046795", "location_code": "hk", "company": "Hong Kong Young Women\u2019s Christian Association", "job_title": "Compensation and Benefits Officer", "description": "Responsibilities:\n\nHandle\u00a0and coordinate\u00a0routine HR functions, including\u00a0recruitment advertisement\u00a0posting, interview arrangement, onboarding arrangement and so\u00a0on;\nParticipate in job fair, recruitment day and other recruitment\u00a0activities;\nAssist in\u00a0developing HR projects\u00a0including\u00a0on-the-job training,\u00a0team-building activities\u00a0and\u00a0other\u00a0staff\u00a0relations\u00a0activities;\nAssist senior executives for the development of\u00a0an effective recruitment\u00a0channel\u00a0for employer branding and talent\u00a0sourcing;\nCommunicate and coordinate with internal and external stakeholders, including\u00a0secondary and\u00a0tertiary education\u00a0institutions;\nPerform any ad hoc projects as assigned\n\nRequirements:\n\nDiploma or above in\u00a0Human Resources Management, Business Administrations or related\u00a0disciplines;\nMinimum\u00a02 to 3 years\u00a0relevant working experience in the field of human resources,\u00a0candidate with less experience will be considered as\u00a0Human Resources Assistant;\nWell versed in Hong Kong\u00a0Employment\u00a0Ordinance and related\u00a0legislation;\nExcellent\u00a0interpersonal and\u00a0communication\u00a0skills;\nResponsible,\u00a0fast-paced,\u00a0self-motivated, well-organized and detail-minded;\nGood command of written and spoken English and\u00a0Chinese;\nProficiency in Microsoft Office applications (Word, Excel & PowerPoint) and Chinese word\u00a0processing;\nImmediately available is highly\u00a0preferred;\nFresh graduates are welcome to apply", "employment_types": ["Full Time", "Permanent"], "selling_points": [], "locations": ["Central"], "categories": ["Admin & HR", "Compensation & Benefits", "HR Supporting Staff", "Public / Civil", "Social Services - Community / Non-profit Organization"], "post_time": "2022-01-14T04:59:57Z", "salary": {"currency": null, "max": null, "min": null, "period": "monthly", "term": null}, "salary_visible": false, "title_keywords": ["officer"], "responsibilities": ["hr", "coordinate with", "developing", "coordinate", "recruitment", "ad hoc projects", "interview arrangement"], "requirements": {"degrees": ["diploma or above"], "majors": ["related disciplines", "business"], "languages": ["english", "chinese"], "language_level": ["proficiency", "good command"], "hard_skills": ["excel", "hong kong employment ordinance", "chinese word processing", "microsoft office", "word", "powerpoint"], "soft_skills": ["detail-minded", "communication skills", "self-motivated", "responsible", "well-organized", "interpersonal"], "languages_combined": [{"language": "english", "language_level": ["good command"]}, {"language": "chinese", "language_level": ["proficiency", "good command"]}]}, "experience_required": {"duration": ["minimum 2 to 3 years"], "field": ["relevant working experience", "human resources"]}}, {"job_id": "100003009047388", "location_code": "hk", "company": "Tung Chun Management Services Company Limited", "job_title": "HR & Admin Officer / Assistant HR & Admin Officer", "description": "Responsibilities\n\nAct as an HR business partner to provide the full spectrum of HR services including recruitment, staffing, performance management and C&B\nDesign and implement different recruiting and staffing programs to recruit and retain employees\nAnalyzes wage and salary reports and data to determine competitive compensation plan\nAdministers payroll and benefits programs\nAdvises management in appropriate resolution of employee relations issues\nResponds to inquiries regarding HR policies, procedures, and programs\nPrepare HR report for management review\nRequirements\n\nDegree holder in Human Resources Management or related disciplines\n1-2\u00a0years solid HR experience in a sizable multi-national company, with mass recruitment experience will be an advantage\nWell versed in Employment Ordinance and other relevant regulations\nGood interpersonal, communication skills and analytical skills\nProactive, independent, well-organized and detail-minded\nGood command of written and spoken English and Chinese;\nProficient in MS Office application and Chinese word processing\nImmediately available is highly preferred\nWe offer a competitive remuneration package and a full range of benefits. Interested parties please send your resume with your current and expected salary to Head of People,11 Catering Road East, Hong Kong International Airport, Lantau, Hong Kong or by clicking the \"Apply Now\" button\u00a0on or before 31 January 2022.\nPersonal data collected will be treated in the strictest confidence and only be used for recruitment-related purposes. Applicants who do not receive notification for an interview within six weeks may consider their application unsuccessful.", "employment_types": ["Full Time"], "selling_points": [], "locations": ["Mong Kok"], "categories": ["Admin & HR", "Compensation & Benefits", "HR Supporting Staff", "Recruitment / Executive Search"], "post_time": "2022-01-14T02:58:04Z", "salary": {"currency": null, "max": null, "min": null, "period": "monthly", "term": null}, "salary_visible": false, "title_keywords": ["officer", "hr", "admin", "assistant"], "responsibilities": ["management", "data", "hr", "design", "recruitment", "reports", "plan"], "requirements": {"degrees": [], "majors": [], "languages": [], "language_level": [], "hard_skills": [], "soft_skills": [], "languages_combined": []}, "experience_required": {"duration": [], "field": []}}, {"job_id": "100003009047102", "location_code": "hk", "company": "Noatum Logistics Hong Kong Limited", "job_title": "HR Clerk (Welcome fresh graduates) (6-Month Contract)", "description": "Facilitate day-to-day HR operations matters for Hong Kong office\nAssisted in recruitment including CV screening and arrange interviews\nSupport and execute new hire onboarding process and conduct induction\nMaintain proper employee records and P-file in HR Information System.\nAssist in organizing company welfare events\nHandle staff medical benefits, insurance matters and leave administration\nHandle the headcount tracking report and submission\nCarry out any ad-hoc projects/duties as required\n\n\u00a0Job Requirement:\n\n\nF.5 or above\nProficient in MS Word, Excel, PowerPoint and Chinese Word Processing\nWith relevant working experience is preferred\nStrong understanding of HK labor laws, employment ordinance, etc.\nSelf-Discipline", "employment_types": ["Full Time", "Part Time", "Permanent", "Temporary", "Contract", "Internship"], "selling_points": ["5-day work, Welcome fresh graduates", "Temporary to Permanent, With Contract End Bonus", "Self-Discipline and fast learning"], "locations": ["Wong Tai Sin Area"], "categories": ["Admin & HR", "Clerical / Admin Staff", "HR Supporting Staff", "Recruitment / Executive Search"], "post_time": "2022-01-14T02:20:09Z", "salary": {"currency": null, "max": null, "min": null, "period": "monthly", "term": null}, "salary_visible": false, "title_keywords": ["hr clerk"], "responsibilities": ["cv screening", "operations", "hr", "maintain", "recruitment"], "requirements": {"degrees": [], "majors": [], "languages": [], "language_level": [], "hard_skills": ["information system"], "soft_skills": [], "languages_combined": []}, "experience_required": {"duration": [], "field": []}}, {"job_id": "100003009049095", "location_code": "hk", "company": "South Asia Knitting Factory Limited", "job_title": "Human Resources Officer (5 day work)", "description": "Job Responsibilities:\u00a0\n\nHandle full spectrum of HR functions including all staffing matters such as recruitment and selection, employment contract renewal, staff relations, payroll\nEnsure HR policies, guidelines, and procedures being compliant with HK Employment Ordinance and other local regulations\nFollow up staff matters, C&B renewal, and internal memos\nPerform ad hoc projects or tasks as assigned\n\n\u00a0Job Requirements:\n\nDegree holder in Human Resources Management, Administration or related disciplines\nAt least 3 to 5 years relevant working experience\nWell-versed with the Employment Ordinance, MPF Schemes Ordinance and other Hong Kong regulatory compliance\nGood written and spoken English and Chinese\nGood interpersonal and communication skills\nProficient in MS Word, Excel, PowerPoint and Chinese Word Processing\n\nWe provide the high caliber\u00a0with\u00a0attractive salary, good career prospect and benefits package\u00a0including\u00a05 day work week,\u00a0discretionary bonus,\u00a0education allowance and\u00a0medical scheme.\n\u00a0\nInterested parties please send your full resume with your availability, current and expected salary details by clicking \"APPLY NOW\"\n\n\u00a0(All applications will be treated in strict confidence and data collected will be used for recruitment purposes only)", "employment_types": ["Full Time", "Permanent"], "selling_points": ["(5 day work)", "Kwun Tong", "discretionary bonus"], "locations": ["Kwun Tong"], "categories": ["Admin & HR", "HR Supporting Staff"], "post_time": "2022-01-14T08:06:47Z", "salary": {"currency": null, "max": null, "min": null, "period": "monthly", "term": null}, "salary_visible": false, "title_keywords": ["human resources officer"], "responsibilities": ["regulations", "guidelines", "policies", "hr", "procedures", "recruitment", "ad hoc projects", "payroll"], "requirements": {"degrees": ["degree holder"], "majors": ["related disciplines"], "languages": ["english", "chinese"], "language_level": ["proficient", "good"], "hard_skills": ["excel", "chinese word processing", "powerpoint", "ms word"], "soft_skills": ["communication skills", "interpersonal"], "languages_combined": [{"language": "english", "language_level": ["good"]}, {"language": "chinese", "language_level": ["proficient", "good"]}]}, "experience_required": {"duration": ["at least 3 to 5 years"], "field": ["relevant working experience"]}}, {"job_id": "100003009049392", "location_code": "hk", "company": "Amika", "job_title": "Senior Human Resources Officer", "description": "Job Duties:\n\nHandling full spectrum of HR functions\nResponsible for payroll calculation, reviewing supporting document\nWork with line managers to determine hiring needs and select suitable candidates for final selection\nPrepare HR reports on regular basis for management review\nAssist in ad hoc projects\n\nJob Requirements:\n\nA Degree in Human Resources Management, Business Administration or related discipline;\nAt least 5 years of working experience in HR generalist position\u00a0\nGood interpersonal & communication skills;\nFamiliar with Employment Ordinance, MPF schemes and regulations\nMulti-tasking, meticulous, organized and able to meet tight work deadlines\nPleasant, strong sense of accountability and passionate about people\nGood command of written and spoken English and Chinese\nLess experience will be considered as Human Resources Officer", "employment_types": ["Full Time", "Permanent"], "selling_points": ["We put people first", "Good development opportunities", "Handling full spectrum of HR functions"], "locations": ["Kwun Tong"], "categories": ["Admin & HR", "Compensation & Benefits", "HR Supporting Staff", "Recruitment / Executive Search"], "post_time": "2022-01-14T08:36:09Z", "salary": {"currency": null, "max": null, "min": null, "period": "monthly", "term": null}, "salary_visible": false, "title_keywords": ["senior human resources officer"], "responsibilities": ["hr", "hr reports", "ad hoc projects", "payroll", "management review"], "requirements": {"degrees": ["degree"], "majors": ["business administration"], "languages": ["english", "chinese"], "language_level": ["good command"], "hard_skills": [], "soft_skills": ["organized", "communication skills", "meticulous", "accountability", "pleasant", "multi-tasking", "interpersonal", "passionate about"], "languages_combined": [{"language": "english", "language_level": ["good command"]}, {"language": "chinese", "language_level": ["good command"]}]}, "experience_required": {"duration": ["at least 5 years"], "field": ["hr generalist", "human resources"]}}, {"job_id": "100003009053846", "location_code": "hk", "company": "Konew Financial Express Limited \u5eb7\u696d\u4fe1\u8cb8\u5feb\u905e", "job_title": "Assistant Manager, Learning and Development", "description": "Main Duties & Responsibilities:\u00a0\n\nIdentify and analyze training needs and formulate training strategies to meet people development and business needs\nDesign and deliver training programs including classroom training and e-learning courses\nAdminister and support the whole training process in relation to course enrollment, attendance, evaluation records as well as relevant coordination duties\nReview course evaluation for further enhancement or improvement\nPrepare regular reports on training activities\nSource and liaise with external training institutes, consultants or vendors\nRequirements:\n\nBachelor Degree in\u202fHuman Resources, Business Management\u202for related disciplines\nMinimum 6 years\u2019 solid experience in developing new training programs and delivering soft skills programs\nExperienced in delivering video sales related training would be added advantage\nTrainer background is highly preferred\nGood presentation, communications, and interpersonal skills\nStrong\u202fself-motivation, able to work independently under pressure and tight deadline\u202f\nExcellent command of spoken and written\u00a0English and\u00a0Chinese\nProficiency in MS Office\n\nWe offer:\n\nDiscretionary bonus\nMedical insurance\nDental insurance\nHardship allowance\nCompetitive annual leave days\nBirthday leave\nAnniversary leave\nStudy leave\nMarriage leave\nCompassionate leave\n\nHow to apply:\n\nInterested parties, please send your resume stating your expected salary to Human Capital Department\u00a0by clicking \"APPLY NOW\".\n\n(We are an equal opportunity employer.\u00a0 Personal data collected will be used for recruitment purpose only.\u00a0 The unsuccessful applications will be destroyed after 6 months.)\u00a0", "employment_types": ["Full Time", "Permanent"], "selling_points": ["Design and deliver training programs", "Administer and support the whole training process", "5 days work, birthday leave, anniversary leave"], "locations": ["Central"], "categories": ["Education", "Tutor / Instructor", "Admin & HR", "HR Supporting Staff", "Training & Development"], "post_time": "2022-01-17T07:37:01Z", "salary": {"currency": null, "max": null, "min": null, "period": "monthly", "term": null}, "salary_visible": false, "title_keywords": ["assistant manager,"], "responsibilities": ["attendance", "enrollment", "training activities", "review", "design", "reports", "coordination", "evaluation", "liaise with"], "requirements": {"degrees": ["degree", "bachelor"], "majors": ["related disciplines", "business"], "languages": ["english", "chinese"], "language_level": ["excellent"], "hard_skills": ["business management", "ms office"], "soft_skills": ["work independently", "under pressure", "self-motivation", "interpersonal skills", "presentation"], "languages_combined": [{"language": "english", "language_level": ["excellent"]}, {"language": "chinese", "language_level": ["excellent"]}]}, "experience_required": {"duration": ["minimum 6 years"], "field": ["training", "developing"]}}, {"job_id": "100003009047377", "location_code": "hk", "company": "AP Rentals Limited", "job_title": "Administration & Human Resources Assistant", "description": "Job Description\n\nTo assist in full spectrum of Human Resources functions, i.e. Recruitment, Payroll Calculation, Leave & Attendance Record Maintenance, Policies Review, etc.\nTo maintain and update HRIS record\u00a0\nTo provide\u00a0all round office administration support, i.e. Facilities Maintenance, Stationery Order, etc.\nTo prepare internal correspondence and different kinds of reports\nTo maintain the filing system for the department\nTo\u00a0perform ad hoc assignments as required\n\nJob Requirements\n\nDegree\u00a0holder in Human Resources Management or any related disciplines\n1\u00a0year of relevant\u00a0experience is preferred but not a must\nFamiliar with Labour Ordinance and other related legislations of HK\nGood command of spoken & written English and Chinese including Putonghua\nIndependent, responsible and self-motivated\nProficient in MS Office, e.g. PowerPoint, Excel, Word\u00a0and Chinese\u00a0Word Processing\nWork Location: Yuen Long\n\n\u00a0\u00a0\u00a0\u00a0\u00a0\u00a0\u00a0* Fresh graduate will also be considered\n\nInterested parties, please apply by \"APPLY NOW\" with full resume, stating date available, present and expected salary.\n\n(Applicant without stating the expected salary will not be considered)\n\nAll data collected will be used for recruitment purpose only and will be treated as strictly confidential.\u00a0 All unsuccessful applications will be destroyed upon completion of the selection process.\n\nOur website: www.aprentalshk.com", "employment_types": ["Full Time", "Permanent"], "selling_points": [], "locations": ["Yuen Long"], "categories": ["Admin & HR", "Clerical / Admin Staff", "HR Supporting Staff", "Recruitment / Executive Search"], "post_time": "2022-01-14T02:56:36Z", "salary": {"currency": null, "max": null, "min": null, "period": "monthly", "term": null}, "salary_visible": false, "title_keywords": ["human resources assistant"], "responsibilities": ["attendance", "office administration support", "maintenance", "policies", "review", "stationery", "maintain", "recruitment", "reports", "ad hoc assignments", "payroll", "human resources functions"], "requirements": {"degrees": ["degree holder"], "majors": ["related disciplines"], "languages": ["putonghua", "english", "chinese"], "language_level": ["good command"], "hard_skills": ["excel", "chinese word processing", "word", "powerpoint", "ms office"], "soft_skills": ["self-motivated", "independent", "responsible"], "languages_combined": [{"language": "putonghua", "language_level": ["good command"]}, {"language": "english", "language_level": ["good command"]}, {"language": "chinese", "language_level": ["good command"]}]}, "experience_required": {"duration": ["1 year"], "field": ["relevant experience"]}}, {"job_id": "100003009048922", "location_code": "hk", "company": "Simone Intellectual Property Services Asia Limited", "job_title": "Human Resources & Administration Officer", "description": "Reporting to the Human Resources Director, the HR & Admin Officer will be responsible for the following duties:\n\u00a0\n\nKey Responsibilities\n\n\nResponsible for full range of HR administration work including but not limited to MPF, insurance enrolment, orientation contents;\nHandle onboarding and exit procedures to ensure all required documents are properly processed;\nCreate and maintain employee data records and personnel documents, maintain HR software system;\nMaintain and update annual leave record;\nSupports payroll management and statutory requirements from the Inland Revenue Department;\nBe one of the HR contact points for general employees\u2019 inquiries;\nHandle work visa applications for expatriate staff;\nAssist all general office administration and ad hoc projects as required\n\n\u00a0Requirements\u00a0\n\nA university graduate with at least 3 years solid experience as a HR Generalist;\nGood command of written and spoken English & Chinese, Mandarin is a plus;\nMeticulous and attention to detail;\nExcellent communication and problem-solving skills;\nWell organized, self-motivated, able to work independently and multi-tasking;\nCan-do attitude and a team player\n\nInterested parties, please submit with your detailed resume stating your current and expected salary.\n\n\u00a0All information provided will be treated with strict confidence and will be used for recruitment purposes only.", "employment_types": ["Full Time"], "selling_points": [], "locations": ["Wan Chai"], "categories": ["Admin & HR", "HR Supporting Staff"], "post_time": "2022-01-14T08:02:45Z", "salary": {"currency": null, "max": null, "min": null, "period": "monthly", "term": null}, "salary_visible": false, "title_keywords": ["administration officer", "human resources"], "responsibilities": ["management", "mpf", "software", "data", "office administration", "hr", "procedures", "statutory requirements", "maintain", "ad hoc projects", "contact", "payroll", "contents", "insurance", "administration"], "requirements": {"degrees": ["university graduate"], "majors": [], "languages": ["english", "chinese", "mandarin"], "language_level": ["good command"], "hard_skills": ["problem-solving skills", "plus"], "soft_skills": ["meticulous", "self-motivated", "work independently", "can-do attitude", "well organized", "communication", "multi-tasking", "attention to detail", "problem-solving skills", "team player"], "languages_combined": [{"language": "english", "language_level": ["good command"]}, {"language": "chinese", "language_level": ["good command"]}, {"language": "mandarin", "language_level": ["good command"]}]}, "experience_required": {"duration": ["at least 3 years"], "field": ["hr generalist"]}}, {"job_id": "100003009048601", "location_code": "hk", "company": "Anglo-Eastern Ship Management Limited", "job_title": "Assistant HR Officer", "description": "Responsibilities:\n\nReporting to Senior Human Resources Manager\nResponsible for full spectrum of HR cycle for employees including but not limited to Recruitment & Selection, Employee Relation and related process\nArrange work permit / work visa application for overseas employees\nPersonnel database and personal files maintenance for shore and personnel\nAdminister Retirement plans (MPF, ORSO) for shore personnel of the Hong Kong office.\nDiscipline documentation for shore employees of the Company\nAssist in ad hoc project\nRequirements:\n\nDegree holder in Human Resources Management or related discipline\nMinimum 2-3 year or above relevant experience in Human Resources is preferred\nWell versed with HK Employment Ordinance and other HR legislations\nExcellent command of written and spoken English and Chinese\nBe able to communicate and work efficiently with different levels of staff\nStrong administration, interpersonal and communication skills; Self-motivated and a team-player\nBe able to work independently under pressure\nProficiency in MS Office in particular Excel, Words and PowerPoint\nImmediate availabe is highly preferred.\u00a0", "employment_types": ["Full Time", "Permanent"], "selling_points": ["Good career prospects", "Global exposure", "Work Life Balance"], "locations": ["Kowloon Bay"], "categories": ["Admin & HR", "HR Supporting Staff"], "post_time": "2022-01-14T06:53:27Z", "salary": {"currency": null, "max": null, "min": null, "period": "monthly", "term": null}, "salary_visible": false, "title_keywords": ["hr officer", "assistant"], "responsibilities": ["reporting", "ad hoc", "mpf", "maintenance", "hr", "recruitment", "database", "documentation", "plans"], "requirements": {"degrees": ["degree holder"], "majors": [], "languages": ["english", "chinese"], "language_level": ["excellent"], "hard_skills": ["powerpoint", "excel", "words", "ms office"], "soft_skills": ["communication skills", "self-motivated", "work independently", "under pressure", "team-player", "interpersonal"], "languages_combined": [{"language": "english", "language_level": ["excellent"]}, {"language": "chinese", "language_level": ["excellent"]}]}, "experience_required": {"duration": ["minimum 2-3 year"], "field": ["relevant experience", "human resources"]}}, {"job_id": "100003009043081", "location_code": "hk", "company": "Waihong Environmental Services Limited", "job_title": "Human Resources Officer (Ref: HC0101)", "description": "Responsibilities:\n\n\nResponsible for all rounded human resources functions including but not limited to payroll, compensation & benefits administration, leave administrations and staff relations\nProvide HR support to managers on staff related issues\nAssist in reviewing or formulating HR strategies, policies and procedures\nPrepare reports and analysis for management review\nHandle ad-hoc projects as assigned\n\nRequirements:\n\n\nDegree\u00a0holder in Human Resources Management or related disciplines\nPossess\u00a03 years\u2019 relevant experience in sizeable organizations\nWell-versed in Employment Ordinance and related legislations\nAble to work independently with strong sense of responsibility as well as good time management\nProactive, multi-tasked and able to work in fast-paced environment\nSound communications and interpersonal skills with staff of all levels\nGood command of written and spoken English & Chinese\nExperience in using IPL is an advantage\nImmediate available will be highly preferred\nWe treasure human resources as our most valuable asset. We offer 5-day work week, attractive remuneration package and career advancement opportunities to the right candidate. Interested parties please send full resume with your present and expected salary by one of the following means:\n\n\nEmail:\u00a0Click 'Apply Now'\u00a0or whhr @waihong.com.hk\nFax: \u00a0\u00a0\u00a02786 8563\nMail:\u00a0 \u00a0Unit 813, 8/F, Chevalier Commercial Centre, 8 Wang Hoi Road, Kowloon Bay, Kowloon\n\nPlease quote our reference no. on envelope / fax cover / subject line of the email.\nWaihong is an equal opportunity employer and welcomes applications from all qualified candidates. Personal data provided by job applicants will be used strictly in accordance with the employer's personal data policies, a copy of which will be provided immediately upon request.", "employment_types": ["Full Time", "Permanent"], "selling_points": [], "locations": ["Kowloon Bay"], "categories": ["Admin & HR", "Clerical / Admin Staff", "Compensation & Benefits", "HR Supporting Staff"], "post_time": "2022-01-13T08:21:17Z", "salary": {"currency": null, "max": null, "min": null, "period": "monthly", "term": null}, "salary_visible": false, "title_keywords": ["human resources officer"], "responsibilities": ["policies", "hr", "analysis", "procedures", "prepare reports", "ad-hoc projects", "payroll", "human resources functions", "management review", "administration"], "requirements": {"degrees": ["degree holder"], "majors": ["related disciplines"], "languages": ["english", "chinese"], "language_level": ["good command"], "hard_skills": ["ipl"], "soft_skills": ["work independently", "proactive", "sense of responsibility", "multi-tasked", "work in fast-paced environment", "interpersonal skills", "time management"], "languages_combined": [{"language": "english", "language_level": ["good command"]}, {"language": "chinese", "language_level": ["good command"]}]}, "experience_required": {"duration": ["3 years"], "field": ["relevant experience"]}}, {"job_id": "100003009050859", "location_code": "hk", "company": "Williams Lea (Hong Kong) Ltd", "job_title": "HR Officer", "description": "Job Responsibilities:\n\nIdentifying, proactively sourcing, cultivating, assessing, and managing high quality candidates through the full candidate lifecycle\nBuilding talent pipelines to fill current and future roles and drive improvements in time to hire\nWork with the candidates and our interviewers to schedule interviews\nUtilizing the applicant tracking system to actively track, manage and report candidate pipelines\nSupport the conversion process for the offerees\nWork with other HR functions to prepare the related documents and process\nSupport the recruiting, training, and staffing activities\nOther ad-hoc requests as needed\n\nJob Requirement:\n\nBachelor\u2019s degree with at least 2 years of relevant experience\nProficiency in MS Office, particularly Excel, PowerPoint, Word, and Outlook\nExcellent oral and written communication skills in English, Cantonese, and Mandarin Chinese\nAble to perform well in a fast-paced, deadline driven and service-oriented environment\nStrong interpersonal skills and ability to work independently and effectively in a virtual team environment, partnering across functions, geographies, cultures, and staff levels\nTeam player, highly motivated, energetic, resourceful, and friendly\n\nWe offer attractive remuneration package to the successful candidate.\u00a0 In addition, you will have an opportunity to work in a reputable company with excellent career exposure.\u00a0 Interested parties, please click \"APPLY NOW\" to submit your application.\n\nAll information provided will be treated confidentially and used solely for recruitment purpose.\u00a0", "employment_types": ["Full Time", "Temporary", "Contract"], "selling_points": ["Work Location: Quarry Bay", "Monday to Friday 0900 - 1800", "AL 15 Days, Medical & Dental Coverage"], "locations": ["Quarry Bay"], "categories": ["Admin & HR", "HR Supporting Staff", "Recruitment / Executive Search"], "post_time": "2022-01-14T11:36:27Z", "salary": {"currency": null, "max": null, "min": null, "period": "monthly", "term": null}, "salary_visible": false, "title_keywords": ["hr officer"], "responsibilities": ["tracking", "related documents", "hr", "quality", "schedule", "ad-hoc requests", "report"], "requirements": {"degrees": ["degree", "bachelor"], "majors": [], "languages": ["cantonese", "english", "mandarin chinese"], "language_level": ["excellent"], "hard_skills": ["excel", "word", "powerpoint", "outlook", "ms office"], "soft_skills": ["communication skills", "oral", "work independently", "resourceful", "service-oriented", "motivated", "interpersonal skills", "friendly", "team player", "energetic", "driven"], "languages_combined": [{"language": "cantonese", "language_level": ["excellent"]}, {"language": "english", "language_level": ["excellent"]}, {"language": "mandarin chinese", "language_level": ["excellent"]}]}, "experience_required": {"duration": ["at least 2 years"], "field": ["relevant experience"]}}, {"job_id": "100003009044373", "location_code": "hk", "company": "CLP Power Hong Kong Limited", "job_title": "Human Resources Assistant [Ref. CLPP-HR-S]", "description": "The candidate is required to provide full range of project and administrative support to the Director \u2013 Human Resources (CLPPHK).\u00a0 It is a development position and ideal for candidates who are passionate in starting a professional career in HR management and want to gain all rounded exposure in a dynamic environment\n\nAssist the Director- HR(CLPPHK) with administrative duties and completes a broad variety of tasks such as managing calendar, event management, leave management, archiving etc.\nCoordinate internal and external meetings, manage agenda and prepare for minutes\nManage and support professional development programs, employee engagement and communication initiatives for the HR team\nSupport the Director in preparing for presentations, organization charts, reports, dashboards and postings\nCoordinate HR budget\nManage HR processes and administrative duties, not limited to maintaining HR records in the HR Information System, budget preparation, materials prepared for talent succession, etc.\nKeep track of projects and priority deliverable completion status.\u00a0 Take up ad hoc assignments and projects as and when required\n\nRequirements\n\nBachelor degree or above in psychology, business or other relevant disciplines\nAt least 2 years of work experience\nGood command of English and Chinese language skills\nExperience in managing physical and virtual events\nHigh level of proficiency in using powerpoint, excel, virtual interactions tools and social media\nPrior experience in HR management or diverse work environment from sizeable organizations preferred\nWell organized, strong interpersonal skills, team player, self-starter and able to work under pressure\nPlease apply by\u00a0clicking the button \"Apply Now\"\u00a0\u00a0giving a detailed C.V., including career history, major achievements and personal attributes on or before 21\u00a0January 2022.\n\n\nApplicants not invited for interview within 6 weeks from the closing date may assume their applications unsuccessful.\n\nInformation provided will be for recruitment purpose within the CLP Group and only short-listed candidates will be contacted. We comply with all applicable laws and regulations of HKSAR in handling applications. For details of the Personal Information Collection Statement, please visit our website: https://clp.to/engPICS\n\nFor further information on our company, please visit our website:\n\nhttps://www.clpgroup.com/", "employment_types": ["Full Time", "Permanent"], "selling_points": [], "locations": ["Hung Hom"], "categories": ["Admin & HR", "Others", "HR Supporting Staff"], "post_time": "2022-01-13T18:54:33Z", "salary": {"currency": null, "max": null, "min": null, "period": "monthly", "term": null}, "salary_visible": false, "title_keywords": ["hr", "human resources assistant"], "responsibilities": ["regulations", "social media", "management", "development programs", "maintaining", "administrative support", "hr", "budget", "website", "presentations", "coordinate", "communication", "administrative duties", "reports", "ad hoc assignments", "recruitment", "work under pressure"], "requirements": {"degrees": ["degree or above", "bachelor"], "majors": ["psychology", "business"], "languages": ["english", "chinese"], "language_level": ["good command"], "hard_skills": ["excel", "information system", "powerpoint", "presentations", "dynamic", "c"], "soft_skills": ["passionate", "dynamic environment", "work under pressure", "well organized", "detailed", "communication", "diverse", "interpersonal skills", "team player", "ideal"], "languages_combined": [{"language": "english", "language_level": ["good command"]}, {"language": "chinese", "language_level": ["good command"]}]}, "experience_required": {"duration": ["at least 2 years"], "field": ["hr", "management"]}}, {"job_id": "100003009041478", "location_code": "hk", "company": "Precision Spec Medical Group Limited", "job_title": "Administration and Human Resources Officer", "description": "Responsibilities:\n\n\nAssist in all round office administration including but not limited to procurement of office equipment's and office supplies, filing, office equipment's maintenance, stationeries and pantry\u2019s supplies etc.;\nWork closely with internal departments and business units to provide HR support for frontline staff;\nProvide support on full spectrum of Human Resources services including but not limited to recruitment and selection, compensation and benefits administration, MPF administration, performance management, employee relations and taxation issues, etc;\u00a0\nResponsible for monthly payroll calculation including commission, incentives & bonus scheme calculations;\nResponsible for the duty roster, staff record and leave record;\nPrepare statistical report and presentation materials for management review;\u00a0\nBusiness and personal support to Director;\nParticipate in ad-hoc duties or project as assigned;\n\nMature and can work independently;\n\n\u00a0Requirements:\n\nHigh Diploma holder in Business Administration, Human Resources or related discipline;\nAt least 3 years Admin and Human Resources experiences in Medical industry will be an advantage;\nMedical beauty or Clinic experience is highly preferable;;\nResponsible, well organized and willing to learn;\u00a0\nA good team player with strong interpersonal and problem solving skills;\nGood knowledge in HK Employment Ordinance and related regulations;\nGood command of Cantonese, Mandarin and English;\n\nWe offer on these roles\n\nIf the above job requirements ideally match your profile, we would like to invite you to email your full resume with your current & expected remuneration and earliest commencement date by clicking\u00a0\"Apply Now\".", "employment_types": ["Full Time"], "selling_points": ["5 days work", "Full Time", "Medical Service"], "locations": ["Tsim Sha Tsui"], "categories": ["Admin & HR", "HR Supporting Staff"], "post_time": "2022-01-12T23:26:12Z", "salary": {"currency": null, "max": null, "min": null, "period": "monthly", "term": null}, "salary_visible": false, "title_keywords": ["human resources officer"], "responsibilities": ["taxation", "provide support", "management", "mpf", "maintenance", "office supplies", "office administration", "hr", "recruitment", "ad-hoc duties", "report", "payroll", "management review", "administration"], "requirements": {"degrees": ["high diploma"], "majors": ["business administration"], "languages": ["cantonese", "english", "mandarin"], "language_level": ["good command"], "hard_skills": ["problem solving skills"], "soft_skills": ["good team player", "responsible", "willing to learn", "well organized", "problem solving skills", "interpersonal"], "languages_combined": [{"language": "cantonese", "language_level": ["good command"]}, {"language": "english", "language_level": ["good command"]}, {"language": "mandarin", "language_level": ["good command"]}]}, "experience_required": {"duration": ["at least 3 years"], "field": ["clinic", "admin", "beauty", "human resources", "medical"]}}, {"job_id": "100003009046418", "location_code": "hk", "company": "Rich Goldman Holdings Limited", "job_title": "Human Resources & Administration Officer", "description": "Job Highlights\n\n5 days work| Bonus| Medical Insurance| Free snack\nCareer Advancement |Young & Energetic |Stable Work\n3 years or above experience in HR & Admin field\n\nJob Description\n\nResponsibilities\n\nHandle full spectrum of Human Resources function, including payroll calculation, tax returns, leave management, performance appraisal, recruitment, employee relations and staff activities.\nDevelop and utilize different channels / platforms for employer branding and talent sourcing\nProvide support in administration duties including all stationery, office equipment maintenance, procurement, filing and general correspondence etc.\nAssist in managing work\u00a0permit application and visa renewal\nAssist in preparing regular and ad hoc reports.\nHandle ad-hoc project as required.\n\nRequirements\n\nDegree Holder or Higher Diploma Holder or higher in any discipline;\n3 years or above relevant experience in HR & Administration field;\nSelf-driven with supportive and positive mentality and attitude;\nWell versed in Hong Kong Employment Ordinances and related Ordinances\nIndependent, well-organized, attentive to details and accountability;\nExcellent command of written and spoken English & Chinese including Mandarin is a MUST;\nProficiency in MS Office (Word, Excel and Chinese Word Processing)", "employment_types": ["Full Time", "Part Time"], "selling_points": ["3 years or above experience in HR & Admin field", "Career Advancement |Young & Energetic |Stable Work", "5 days work| Bonus| Medical Insurance| Free snack"], "locations": ["Sheung Wan"], "categories": ["Admin & HR", "Clerical / Admin Staff", "HR Supporting Staff", "Recruitment / Executive Search"], "post_time": "2022-01-13T11:04:25Z", "salary": {"currency": null, "max": null, "min": null, "period": "monthly", "term": null}, "salary_visible": false, "title_keywords": ["administration officer", "human resources"], "responsibilities": ["tax", "ad-hoc", "management", "provide support", "ad hoc", "stationery", "develop", "office equipment maintenance", "recruitment", "reports", "payroll", "administration"], "requirements": {"degrees": ["higher diploma holder", "degree holder"], "majors": [], "languages": ["english", "chinese", "mandarin"], "language_level": ["excellent", "proficiency"], "hard_skills": ["excel", "chinese word processing", "word", "ms office"], "soft_skills": ["supportive", "positive mentality", "independent", "attentive to details", "accountability", "well-organized", "driven"], "languages_combined": [{"language": "english", "language_level": ["excellent"]}, {"language": "chinese", "language_level": ["excellent", "proficiency"]}, {"language": "mandarin", "language_level": ["excellent"]}]}, "experience_required": {"duration": ["3 years"], "field": ["hr", "relevant experience", "administration"]}}, {"job_id": "100003000392441", "location_code": "hk", "company": "Tsui Wah Restaurant", "job_title": "Human Resources Assistant (Part Time)", "description": "Job Responsibilities:\n\nHandle general clerical duties such as data entry, expenses reimbursement; service application\nMaintain proper employee records and P-file in HRIS.\nAssist in ad-hoc assignments and projects as assigned.\nRequirement:\n\nBachelor Students are welcome\nSolid knowledge of using MS Excel, Words, and other MS application\nStrong detail-orientation and sense of responsibility\nImmediate available or short notice is preferred\n\n\n\nWe offer an attractive remuneration package to the right candidates. Interested parties please apply in full resume including current salary, expected salary, and earliest availability by clicking\u00a0APPLY NOW.\u00a0\n\nApplications without\u00a0expected salaries will not be considered.\nPersonal data collected will be used for recruitment purposes only.", "employment_types": ["Part Time", "Internship"], "selling_points": ["Team Player, detail oriented & Flexible", "General support to human resources department", "Joyful and friendly working envirnment"], "locations": ["Kwai Hing"], "categories": ["Admin & HR", "Clerical / Admin Staff", "Hospitality / F & B", "Food & Beverage", "HR Supporting Staff"], "post_time": "2022-01-14T07:12:49Z", "salary": {"currency": null, "max": null, "min": null, "period": "hourly", "term": null}, "salary_visible": false, "title_keywords": ["human resources assistant"], "responsibilities": ["maintain", "ad-hoc assignments", "expenses", "data entry"], "requirements": {"degrees": ["bachelor"], "majors": [], "languages": [], "language_level": [], "hard_skills": ["ms excel", "words", "ms application"], "soft_skills": ["sense of responsibility"], "languages_combined": []}, "experience_required": {"duration": [], "field": []}}, {"job_id": "100003009044893", "location_code": "hk", "company": "Cre8 (Greater China) Limited", "job_title": "HR Specialist (1 year contract)", "description": "Job\u00a0Responsibilities :\n\nManage the recruitment process including job description design, resumes screening, interview, offer negotiation and other logistics arrangement\nAssist the Supervisors to handle daily operations of Compensation & Benefits including Monthly Payroll, Leave & Benefits Administration,\u00a0HR Analysis and Reporting\nProvide support on other HR initiatives and ad hoc duties as assigned\n\n\u00a0Job Requirements :\n\nAssociate Degree or above in any disciplines\nAt least 2 years of relevant recruitment experience\nKnowledge of HR Employment Ordinance, related regulations and practices\nGood written and spoken English and Chinese\nCandidate with less experience would be considered for Human Resources Assistant\n\nWe offer an attractive remuneration package and fringe benefits to the right candidate.\n(Personal data provided will be used for recruitment purpose only)", "employment_types": ["Full Time", "Temporary", "Contract"], "selling_points": ["Manage the recruitment process", "Benefits Administration", "At least 2 years of working experience"], "locations": ["Central"], "categories": ["Admin & HR", "Compensation & Benefits", "HR Supporting Staff", "Recruitment / Executive Search"], "post_time": "2022-01-13T06:34:49Z", "salary": {"currency": null, "max": null, "min": null, "period": "monthly", "term": null}, "salary_visible": false, "title_keywords": ["hr specialist"], "responsibilities": ["ad hoc duties", "reporting", "provide support", "logistics arrangement", "hr", "analysis", "design", "daily operations", "recruitment process", "payroll", "administration"], "requirements": {"degrees": ["degree or above"], "majors": ["any disciplines"], "languages": ["english", "chinese"], "language_level": ["good"], "hard_skills": [], "soft_skills": [], "languages_combined": [{"language": "english", "language_level": ["good"]}, {"language": "chinese", "language_level": ["good"]}]}, "experience_required": {"duration": ["at least 2 years"], "field": ["recruitment", "human resources"]}}, {"job_id": "100003009050123", "location_code": "hk", "company": "Luen Thai International Group Ltd", "job_title": "Human Resources and Administration Officer", "description": "Responsibilities:\n\nProvide support in all-round Administration (70%) and Human Resources (30%) functions;\nRenew license and insurances in compliance with updated regulatory requirements;\nLead a small team to carry out daily office administration duties including maintenance and repair of office facilities and equipment, arrangement of company vehicles, procurement of office supplies, courier and delivery service, general expenses and company activities coordination, etc.;\nMaintain good HR records and filing of personal data, leave records, attendance, etc.;\nPrepare regular HR & Admin report, correspondence and announcement;\nAssist in formulating and implementing administrative policies and procedures;\nPerform any ad hoc duties as assigned by supervisors.\n\n\nRequirements:\n\nAt least Diploma in Human Resources Management or related disciplines;\nMin. 5 years of relevant working experience;\nWell versed in Hong Kong Employment Ordinance and relevant regulations;\nA good team player with excellent communication and interpersonal skills;\nStrong sense of responsibility, trustworthy, self-motivated\u00a0and able to work under pressure;\nGood command of both written and spoken English, Cantonese and Mandarin;\nCandidate with more experience may be considered as Senior Officer.\n\nWe offer an attractive remuneration package to qualified candidates who wish to advance their careers in a people-centered business. Interested parties please send your detailed resume with current & expected salary and availability.\n\nFor more information, please visit www.luenthai.com.\n\nAll applications will be treated in strict confidence and only be used for recruitment related purpose.", "employment_types": ["Full Time", "Permanent"], "selling_points": ["Min. 5 years of relevant working experience", "Diploma in HR Management or related disciplines", "Strong sense of responsibility & trustworthy"], "locations": ["Kwun Tong"], "categories": ["Admin & HR", "Clerical / Admin Staff", "Others", "HR Supporting Staff"], "post_time": "2022-01-14T09:48:49Z", "salary": {"currency": null, "max": null, "min": null, "period": "monthly", "term": null}, "salary_visible": false, "title_keywords": ["administration officer", "human resources"], "responsibilities": ["regulatory requirements", "maintain", "personal data", "administration", "ad hoc duties", "compliance", "expenses", "report", "attendance", "provide support", "office supplies", "procedures", "insurances", "maintenance", "policies", "lead a small team", "hr", "repair", "coordination", "office administration duties"], "requirements": {"degrees": ["diploma"], "majors": ["related disciplines"], "languages": ["cantonese", "english", "mandarin"], "language_level": ["good command"], "hard_skills": ["hong kong employment ordinance"], "soft_skills": ["good team player", "self-motivated", "trustworthy", "sense of responsibility", "communication and interpersonal skills", "work under pressure"], "languages_combined": [{"language": "cantonese", "language_level": ["good command"]}, {"language": "english", "language_level": ["good command"]}, {"language": "mandarin", "language_level": ["good command"]}]}, "experience_required": {"duration": ["5 years"], "field": ["relevant working experience"]}}, {"job_id": "100003009048091", "location_code": "hk", "company": "Taste Gourmet Group Limited", "job_title": "Human Resources Junior Assistant / Clerk", "description": "\nResponsibilities:\n\n- Assist in general HR operations.\n\n- Data input and matching.\n\n- General administrative works. Filling, scanning and typing etc.\n\n- Assist and participate in ad hoc duties as assigned.\n\nRequirements:\n\n- A team player with detail-minded.\n\n- Good interpersonal and communication skill.\n\n- Able to work under tight deadlines.\n\n- Proficient in MS Office Word, Excel, PowerPoint and Chinese Word Processing.\n\n- Experience in F&B industry is a strong advantage.\n\n- Fresh graduates with positive attitude are welcome.\n\nWe offer attractive salary package and fringe benefits including double pay and medical benefit, etc to the right candidate. Interested parties, please send full resume with availability, current and expected salary to us by clicking \u201cApply Now\u201d\n\n*All information provided by applicants will be treated in strict confidence and used only for recruitment purposes", "employment_types": ["Full Time", "Permanent"], "selling_points": [], "locations": ["Kwai Fong"], "categories": ["Admin & HR", "HR Supporting Staff"], "post_time": "2022-01-14T04:47:56Z", "salary": {"currency": null, "max": null, "min": null, "period": "monthly", "term": null}, "salary_visible": false, "title_keywords": ["clerk", "assistant", "human resources", "junior"], "responsibilities": ["scanning", "ad hoc duties", "operations", "hr", "data input"], "requirements": {"degrees": [], "majors": [], "languages": ["chinese"], "language_level": ["proficient"], "hard_skills": ["excel", "chinese word processing", "word", "powerpoint", "ms office"], "soft_skills": ["detail-minded", "communication skill", "positive attitude", "team player", "interpersonal"], "languages_combined": [{"language": "chinese", "language_level": ["proficient"]}]}, "experience_required": {"duration": [], "field": ["f&b"]}}, {"job_id": "100003009045801", "location_code": "hk", "company": "CLPS Technology (Hong Kong) Co., Limited", "job_title": "Human Resources and Administrative Assistant", "description": "Job Description\n\nl\u00a0 \u00a0A supporting role to carrying out administrative tasks related to all aspects of the company\u2019s HRA operations\n\nl\u00a0\u00a0 Assist to implement company policies, procedures, ensure all tasks executed comply with these policies\n\nl\u00a0\u00a0 Provide support in annual performance and salary review exercise\n\nl\u00a0\u00a0 Handle administrative duties (e.g. ordering office consumables, claims, leave application, visa applications, flight ticket arrangement)\n\nl\u00a0\u00a0 Provide IT support, working with internal and external parties to resolve technical issues\n\nl\u00a0\u00a0 Perform other ad-hoc tasks as required\n\nRequirements\n\nl\u00a0\u00a0 Degree holder in Human Resources Management, Business Administration or related disciplines\n\nl\u00a0\u00a0 One year's relevant experience is highly preferred\n\nl\u00a0\u00a0 Able to work independently in a fast-paced environment\n\nl\u00a0\u00a0 Effective communication, interpersonal and organizational skills\n\nl\u00a0\u00a0 Proficiency in Microsoft Office (Excel, Word, PowerPoint and Chinese Word Processing)\n\nl\u00a0\u00a0 Good command of written and spoken English, Chinese and Mandarin\n\nl\u00a0\u00a0 Immediately or short notices is preferred\n\nInterested candidate, please send your resume with the expected salary through\u00a0\u201cApply Now\u201d\n\n(Personal data collected will be used for recruitment purposes only)", "employment_types": ["Full Time", "Permanent"], "selling_points": ["flexbile working enviroment", "HRA, Asssistant, Human Resource", "5 days work, medical insurance, performance bonus"], "locations": ["Kwun Tong"], "categories": ["Admin & HR", "Clerical / Admin Staff", "Personal / Executive Assistant", "HR Supporting Staff"], "post_time": "2022-01-13T08:45:34Z", "salary": {"currency": null, "max": null, "min": null, "period": "monthly", "term": null}, "salary_visible": false, "title_keywords": ["administrative assistant", "human resources"], "responsibilities": ["provide support", "operations", "policies", "review", "procedures", "internal and external parties", "ad-hoc tasks", "administrative duties", "administrative tasks"], "requirements": {"degrees": ["degree holder"], "majors": ["related disciplines", "business administration"], "languages": ["english", "chinese", "mandarin"], "language_level": ["proficiency", "good command"], "hard_skills": ["excel", "chinese word processing", "microsoft office", "word", "powerpoint"], "soft_skills": ["organizational skills", "work independently", "fast-paced environment", "communication", "interpersonal"], "languages_combined": [{"language": "english", "language_level": ["good command"]}, {"language": "chinese", "language_level": ["proficiency", "good command"]}, {"language": "mandarin", "language_level": ["good command"]}]}, "experience_required": {"duration": ["one year"], "field": ["relevant experience"]}}, {"job_id": "100003009051664", "location_code": "hk", "company": "Tung Wah Group of Hospitals", "job_title": "\u81e8\u6642\u6587\u66f8\u652f\u63f4\u52a9\u7406 (\u8077\u4f4d\u7de8\u865f\uff1aA3/TCSA/HQ/JOBS)", "description": "(\u8077\u4f4d\u7de8\u865f\uff1aA3/TCSA/HQ/JOBS)\n\u5de5\u4f5c\u5730\u9ede\uff1a\u4e0a\u74b0\n\u8077\u8cac\uff1a\n\u8ca0\u8cac\u6578\u64da\u8f38\u5165\u3001\u6574\u7406\u6587\u4ef6\u53ca\u4e00\u822c\u6587\u66f8\u5de5\u4f5c\u3002\n\u7406\u60f3\u7684\u7533\u8acb\u8005\u61c9\u5177\u5099\uff1a\n\u4e2d\u56db\u6216\u4ee5\u4e0a\u7a0b\u5ea6\uff0c\u719f\u6089\u96fb\u8166\u64cd\u4f5c\u53ca\u4e2d\u82f1\u6587\u6587\u66f8\u8655\u7406\u6280\u5de7\u3002\n\u85aa\u916c\u53ca\u8058\u7528\u689d\u4ef6\uff1a\n\u7372\u9078\u7684\u7533\u8acb\u4eba\u5c07\u4ee5\u81e8\u6642\u5408\u7d04\u689d\u6b3e\u53d7\u8058\uff0c\u6bcf\u6708\u85aa\u91d1\u73fe\u6642\u70ba$11,500\u3002\u4efb\u8077\u8005\u5c07\u6309\u4e94\u5929\u5de5\u4f5c\u5468\u5b89\u6392\u4e0a\u73ed\uff0c\u60df\u4ecd\u9808\u8996\u4e4e\u90e8\u9580\u904b\u4f5c\u53ca\u670d\u52d9\u9700\u8981\u800c\u5b9a\u3002\n\u7533\u8acb\u7a0b\u5e8f\uff1a\n\u8acb\u5c07\u500b\u4eba\u5c65\u6b77\u6216\u586b\u59a5\u7533\u8acb\u8868\u683c<F601>(\u53ef\u89aa\u81e8\u7d22\u53d6\u6216\u5f9e\u672c\u9662\u7684\u7db2\u9801https://www.tungwah.org.hk\u4e0b\u8f09)\uff0c\u5bc4\u9999\u6e2f\u4e0a\u74b0\u666e\u4ec1\u8857\u5341\u4e8c\u865f\u6771\u83ef\u4e09\u9662\u9ec3\u9cf3\u7fce\u7d00\u5ff5\u5927\u6a13\u56db\u6a13\u4eba\u529b\u8cc7\u6e90\u79d1\u4e3b\u7ba1\u6536\uff0c\u4fe1\u5167\u53ca\u4fe1\u5c01\u9762\u8acb\u8a3b\u660e\u7533\u8acb\u7684\u8077\u4f4d\u53ca\u8077\u4f4d\u7de8\u865f\u3002\u6771\u83ef\u4e09\u9662\u4e0d\u6703\u63a5\u6536\u90f5\u8cc7\u4e0d\u8db3\u7684\u4fe1\u4ef6\u3002\u70ba\u78ba\u4fdd\u90f5\u905e\u7121\u8aa4\uff0c\u8acb\u5728\u6295\u5bc4\u90f5\u4ef6\u6642\u652f\u4ed8\u8db3\u984d\u90f5\u8cc7\u53ca\u8a3b\u660e\u56de\u90f5\u5730\u5740\u3002\u6771\u83ef\u4e09\u9662\u5728\u4f7f\u7528\u6c42\u8077\u8005\u63d0\u4f9b\u7684\u500b\u4eba\u8cc7\u6599\u6642\uff0c\u53ea\u6703\u5c07\u8cc7\u6599\u4f5c\u6709\u95dc\u62db\u8058\u7528\u9014\uff0c\u4e26\u6703\u56b4\u683c\u9075\u5b88\u9662\u65b9\u500b\u4eba\u8cc7\u6599\u653f\u7b56\u7684\u898f\u5b9a\u3002\n\n\u6211\u5011\u662f\u5e73\u7b49\u6a5f\u6703\u50f1\u4e3b", "employment_types": ["Temporary", "Contract"], "selling_points": [], "locations": ["Sheung Wan"], "categories": ["Admin & HR", "Clerical / Admin Staff", "Others", "HR Supporting Staff"], "post_time": "2022-01-16T21:50:36Z", "salary": {"currency": null, "max": null, "min": null, "period": "monthly", "term": null}, "salary_visible": false, "title_keywords": [], "responsibilities": [], "requirements": {"degrees": [], "majors": [], "languages": [], "language_level": [], "hard_skills": [], "soft_skills": [], "languages_combined": []}, "experience_required": {"duration": [], "field": []}}, {"job_id": "100003009049728", "location_code": "hk", "company": "Arup", "job_title": "Senior People Officer (HR Operations)", "description": "Responsibilities:\n\n\nSupport human resources operations including but not limited to recruitment, staff transfer, visa applications, HRIS and fringe benefits administration etc\nCoordinate and prepare documentation to support on- and off-boarding, salary review, promotion \u00a0and staff movement etc\nMaintain and manage staff data in systems ; data validation and data governance from multiple sources to ensure accuracy and consistency\nSupport new people system migration and implementation\nParticipate in ad-hoc projects as required\n\nQualifications & Experience required:\n\n\nDegree in Human Resources / Business Management or related discipline\n6 years of relevant experiences with prior experience in fast-paced environment or sizable company would be an advantage\nTeam player, self-initiated, responsible and detail-minded\nProficiency of Microsoft Office applications, including Word, Excel and Access\nGood command in both written and spoken English and Chinese\n\n\n\nCandidates with less experience will be considered for People Officer or Assistant People Officer.\n\nWe offer a competitive remuneration package commensurate with qualifications and experience to the right candidate including Global Profit Share scheme, additional fringe benefits of maternity / paternity leave and long-term career development opportunities.\n\nFor interested applicants, please click \"Apply Now\" to submit your online application.\n\nPersonal data collected will be used for recruitment purpose only. Applicants not contacted within 8 weeks may consider their applications unsuccessful.", "employment_types": ["Full Time", "Permanent"], "selling_points": [], "locations": ["Kowloon City"], "categories": ["Admin & HR", "Others", "HR Supporting Staff"], "post_time": "2022-01-14T09:10:07Z", "salary": {"currency": null, "max": null, "min": null, "period": null, "term": null}, "salary_visible": false, "title_keywords": ["officer", "hr", "operations"], "responsibilities": ["management", "data", "operations", "review", "systems", "implementation", "coordinate", "personal data", "maintain", "recruitment", "career development", "documentation", "ad-hoc projects", "migration", "administration"], "requirements": {"degrees": ["degree"], "majors": ["business"], "languages": ["english", "chinese"], "language_level": ["good command"], "hard_skills": ["business management", "excel", "microsoft office", "word", "scheme", "documentation"], "soft_skills": ["fast-paced environment", "team player", "detail-minded", "responsible"], "languages_combined": [{"language": "english", "language_level": ["good command"]}, {"language": "chinese", "language_level": ["good command"]}]}, "experience_required": {"duration": ["6 years"], "field": ["development"]}}]