[{"job_id": "100003009052131", "location_code": "hk", "company": "The Hong Kong Institution of Engineers", "job_title": "Programme Planning & Special Duties Officer (5-Day Work)", "description": "Duties:\n\nTo provide necessary coordination and assistance to the organisation of seminars/webinars, events, learned society activities and programmes, and ad-hoc projects\nTo assist in conducting studies/researches for specific topic(s), and collate appropriate information to facilitate the Section in executing all its tasks and activities\nTo provide secretarial support to meetings and ad-hoc committees\nTo assist in the co-ordination of matters relating to membership benefits, school and publication education programmes, etc.\nTo provide documentary support in handling enquiries and complaints\n\nRequirements:\n\nUniversity Graduate, preferably with 1-2 years work experience\nExperience in handlung complaints is an added advantage\nExcellent command of written and spoken English and Chinese\nAttention to details\nStrong PC skills in MC Word, Excel and Chinese word processing\nPossess experience and knowledge of event and online seminar execution will be an advantage\n\nPlease apply in confidence with full career details and salary expectation to the Chief Executive and Secretary, The Hong Kong Institution of Engineers, 9/F Island Beverley, No 1 Great George Street, Causeway Bay, Hong Kong, or click \u201cApply Now\u201d to submit your application. Applicants should indicate clearly on the envelope and in the letter for the post they are applying.\n\nAll information provided by applicants will be treated in strict confidence and used only for recruitment purpose.\u00a0 Only shortlisted candidates will be notified.\u00a0 All personal data of unsuccessful applicants will be destroyed after completion of the recruitment exercise.", "employment_types": ["Full Time"], "selling_points": ["Assist in conducting seminars/webinars and events", "Assist in conducting studies/researches", "Provide secretariat support to meetings/committees"], "locations": ["Causeway Bay"], "categories": ["Admin & HR", "Clerical / Admin Staff", "Secretary", "Others"], "post_time": "2022-01-17T02:11:56Z", "salary": {"currency": null, "max": null, "min": null, "period": "monthly", "term": null}, "salary_visible": false, "title_keywords": ["officer"], "responsibilities": ["ad-hoc", "executing", "secretarial support", "coordination", "ad-hoc projects"], "requirements": {"degrees": [], "majors": [], "languages": [], "language_level": [], "hard_skills": [], "soft_skills": [], "languages_combined": []}, "experience_required": {"duration": [], "field": []}}, {"job_id": "100003009054550", "location_code": "hk", "company": "Tsit Wing Coffee Co Ltd", "job_title": "Administrative Assistant", "description": "Responsibilities\n\nResponsible for general office administration, such as reception, office supplies, office renovation, repair & maintenance of facilities, handle payment and update reports\nCoordinate the administration work with different kinds of vendors\u00a0\nControl submissions and maintain a good filing system\nAssist the team in all aspects of administrative functions\nHandle ad-hoc projects as required\n\nRequirements\n\nDiploma with 2 years' relevant experience\nFresh graduate will also be considered\nAble to handle multi-task jobs effectively\nExcellent communication skills, must be able to interact with all different kinds of people\nGood team player, initiative, independent, and able to work under pressure\nGood communication and interpersonal skills\nGood command of English and Chinese\nStrong in PC skill such as MS Words, Excel, PowerPoint and Chinese word processing\nImmediate available is preferable\n\n\n\nWorking location:\u00a0Kwai Chung\n\n\n\nStaff Benefit\n\nDiscretionary Bonus\nMedical & Life Insurance\nAnnual Leave\nPayable Sick Leave\nEncourage continuing education and on-job training\nOpen office working environment\nOffer promotion opportunities and long-term career path\u00a0\n\nWe offer a competitive remuneration package to the right candidate.\u00a0Interested parties\u00a0please click\u00a0\"Apply Now\"\u00a0to submit your application\u00a0or by email to\u00a0hr1 @twcoffee.com\n\n\u00a0(All personal data provided by applicants will be treated in strict confidence and used for employment-related purpose only.)", "employment_types": ["Full Time", "Permanent"], "selling_points": [], "locations": ["Kwai Fong"], "categories": ["Admin & HR", "Clerical / Admin Staff", "Receptionist", "Others"], "post_time": "2022-01-17T09:57:37Z", "salary": {"currency": null, "max": null, "min": null, "period": "monthly", "term": null}, "salary_visible": false, "title_keywords": ["administrative assistant"], "responsibilities": ["control", "maintenance", "office supplies", "office administration", "renovation", "coordinate", "repair", "payment", "reports", "maintain", "ad-hoc projects", "administration"], "requirements": {"degrees": ["diploma", "fresh graduate"], "majors": [], "languages": ["english", "chinese"], "language_level": ["good command"], "hard_skills": ["excel", "chinese word processing", "ms words", "powerpoint", "pc skill"], "soft_skills": ["communication skills", "good team player", "multi-task", "independent", "communication and interpersonal skills", "initiative", "work under pressure"], "languages_combined": [{"language": "english", "language_level": ["good command"]}, {"language": "chinese", "language_level": ["good command"]}]}, "experience_required": {"duration": ["2 years"], "field": ["relevant experience"]}}, {"job_id": "100003009053742", "location_code": "hk", "company": "Top Conqueror Limited", "job_title": "\u8239\u52d9\u6587\u54e1**", "description": "\n\u8077\u8cac :\u5c0d\u5167\u5730\u4e0a\u843d\u8ca8,\u51fa\u5165\u53e3\u6587\u4ef6\uff0cTradelink, LC , \u5831\u95dc\uff0c\u5ba2\u4eba\u8ca8\u671f\u8edf\u4ef6\u64cd\u4f5c\uff0c\u4e00\u822c\u6587\u66f8\u8655\u7406\u3002\n\n\u8cc7\u6b77 :\u4e2d\u4e94\u7a0b\u5ea6; 5\u5e74\u7d93\u9a57; \u826f\u597d\u7cb5\u8a9e; \u4e00\u822c\u666e\u901a\u8a71; \u4e00\u822c\u82f1\u8a9e; \u61c2\u8b80\u5beb\u4e2d\u6587; \u61c2\u8b80\u5beb\u82f1\u6587\n\n\u5f85\u9047 :\u6bcf\u6708$13,000 - $13,500, \u6709\u4f9b\u81b3\u98df, \u661f\u671f\u4e00\u81f3\u4e94: \u4e0a\u53489\u6642\u81f3\u4e0b\u53486\u6642, \u6bcf\u9031\u5de5\u4f5c5\u5929, \u6bcf\u5929\u5de5\u4f5c 8 - 9 \u5c0f\u6642\n\n\u7533\u8acb\u9808\u77e5 :\u6c42\u8077\u8005\u53ef\u96fb\u90f5(Apply Now)\u5c65\u6b77\u8868\u7d66\u4e0a\u5ee3\u6709\u9650\u516c\u53f8\u3002\u5982\u8981\u7d22\u53d6\u6536\u96c6\u500b\u4eba\u8cc7\u6599\u8072\u660e, \u8acb\u8207\u738b\u5c0f\u59d0(Email)\u806f\u7d61\u3002\n\n", "employment_types": ["Full Time"], "selling_points": [], "locations": ["Wong Tai Sin Area"], "categories": ["Admin & HR", "Clerical / Admin Staff", "Others"], "post_time": "2022-01-17T07:26:37Z", "salary": {"currency": null, "max": null, "min": null, "period": "monthly", "term": null}, "salary_visible": false, "title_keywords": [], "responsibilities": [], "requirements": {"degrees": [], "majors": [], "languages": [], "language_level": [], "hard_skills": [], "soft_skills": [], "languages_combined": []}, "experience_required": {"duration": [], "field": []}}, {"job_id": "100003009053379", "location_code": "hk", "company": "Trend-tek Corporation Limited", "job_title": "\u5009\u52d9\u6587\u54e1", "description": "\n\u8077\u8cac :\u6536\u8ca8\uff0c\u51fa\u8ca8\uff0c\u586b\u901f\u905e\u55ae\uff0c\u8655\u7406\u51fa\u8ca8\u6587\u4ef6\n\n\u8cc7\u6b77 :\u4e2d\u516d\u7a0b\u5ea6; 3\u5e74\u7d93\u9a57; \u4e00\u822c\u7cb5\u8a9e; \u4e00\u822c\u666e\u901a\u8a71; \u4e00\u822c\u82f1\u8a9e; \u61c2\u8b80\u5beb\u4e2d\u6587; \u7565\u61c2\u8b80\u5beb\u82f1\u6587; \u5de5\u4f5c\u7a4d\u6975\uff0c\u6709\u8cac\u4efb\u611f\uff0c\u826f\u597d\u6e9d\u901a\u53ca\u8868\u9054\u6280\u5de7\n\n\u5f85\u9047 :\u6bcf\u6708$13,000 - $15,000, \u6709\u9280\u884c\u5047\u671f, \u751f\u65e5\u5047, \u5a5a\u5047, \u5e74\u7d42\u734e\u91d1 \u53ca\u91ab\u7642\u4fdd\u96aa, \u661f\u671f\u4e00\u81f3\u4e94: \u4e0a\u53489\u6642\u81f3\u4e0b\u53486\u6642, \u6bcf\u9031\u5de5\u4f5c5\u5929, \u6bcf\u5929\u5de5\u4f5c 8 \u5c0f\u6642\n\n\u7533\u8acb\u9808\u77e5 :\u6c42\u8077\u8005\u53ef\u96fb\u90f5(Apply Now)\u5c65\u6b77\u8868\u7d66\u6668\u6cf0(\u9999\u6e2f)\u6709\u9650\u516c\u53f8\u3002\u5982\u8981\u7d22\u53d6\u6536\u96c6\u500b\u4eba\u8cc7\u6599\u8072\u660e, \u8acb\u8207\u90ed\u5c0f\u59d0(Email)\u806f\u7d61\u3002\n\n", "employment_types": ["Full Time"], "selling_points": [], "locations": ["Kwun Tong"], "categories": ["Admin & HR", "Clerical / Admin Staff", "Others"], "post_time": "2022-01-17T06:53:37Z", "salary": {"currency": null, "max": null, "min": null, "period": "monthly", "term": null}, "salary_visible": false, "title_keywords": ["\u5009\u52d9\u6587\u54e1"], "responsibilities": [], "requirements": {"degrees": [], "majors": [], "languages": [], "language_level": [], "hard_skills": [], "soft_skills": [], "languages_combined": []}, "experience_required": {"duration": [], "field": []}}, {"job_id": "100003009053845", "location_code": "hk", "company": "C S (HK) CO. Limited", "job_title": "\u64cd\u4f5c\u6587\u54e1**", "description": "\n\u8077\u8cac :\u8655\u7406\u5ba2\u6236\u8a02\u55ae\u53ca\u67e5\u8a62\uff0c\u4e00\u822c\u6587\u66f8\u5de5\u4f5c\uff0c\u57fa\u672c\u96fb\u8166\u64cd\u4f5c\uff0c\u8cc7\u6599\u8f38\u5165\n\n\u8cc7\u6b77 :\u4e2d\u4e09\u7a0b\u5ea6; \u826f\u597d\u7cb5\u8a9e; \u4e00\u822c\u666e\u901a\u8a71; \u4e00\u822c\u82f1\u8a9e; \u7565\u61c2\u8b80\u5beb\u4e2d\u6587; \u7565\u61c2\u8b80\u5beb\u82f1\u6587; \u5177\u6709\u57fa\u672c\u96fb\u8166\u64cd\u4f5c\u77e5\u8b58\n\n\u5f85\u9047 :\u6bcf\u6708$10,000 - $12,000, \u6709\u9280\u884c\u5047\u671f, \u82b1\u7d05 \u53ca\u91ab\u7642\u798f\u5229, \u661f\u671f\u4e00\u81f3\u4e94: \u4e0a\u53489\u6642\u81f3\u4e0b\u53486\u6642\u53ca\u661f\u671f\u516d: \u4e0a\u53489\u6642\u81f3\u4e0b\u53485\u6642, \u6bcf\u9031\u5de5\u4f5c6\u5929, \u6bcf\u5929\u5de5\u4f5c 8 \u5c0f\u6642\n\n\u7533\u8acb\u9808\u77e5 :\u6c42\u8077\u8005\u53ef\u96fb\u90f5(Apply Now)\u5c65\u6b77\u8868\u7d66\u9054\u610f\uff08\u9999\u6e2f\uff09\u6709\u9650\u516c\u53f8\u3002\u5982\u8981\u7d22\u53d6\u6536\u96c6\u500b\u4eba\u8cc7\u6599\u8072\u660e, \u8acb\u8207\u9ece\u5c0f\u59d0(Email)\u806f\u7d61\u3002\n\n", "employment_types": ["Full Time"], "selling_points": [], "locations": ["Kwai Tsing Area"], "categories": ["Admin & HR", "Clerical / Admin Staff", "Others"], "post_time": "2022-01-17T07:37:01Z", "salary": {"currency": null, "max": null, "min": null, "period": "monthly", "term": null}, "salary_visible": false, "title_keywords": [], "responsibilities": [], "requirements": {"degrees": [], "majors": [], "languages": [], "language_level": [], "hard_skills": [], "soft_skills": [], "languages_combined": []}, "experience_required": {"duration": [], "field": []}}, {"job_id": "100003009053730", "location_code": "hk", "company": "Sunlight Eco-Tech Limited", "job_title": "\u6703\u8a08\u6587\u54e1**", "description": "\n\u8077\u8cac :\u8ca0\u8cac\u65e5\u5e38\u6703\u8a08\u4e8b\u52d9\u53ca\u5168\u76e4\u6703\u8a08\u5de5\u4f5c,\u8a08\u7ce7,\u8a08\u7b97\u5f37\u7a4d\u91d1,\u61c9\u6536,\u61c9\u4ed8,\u7c3f\u8a18,\u958b\u7968,\u5354\u52a9\u6708\u7d50\u53ca\u6574\u7406\u6587\u4ef6,\u9280\u884c\u5c0d\u8cec,\u5e74\u5ea6\u5be9\u8a08\u53ca\u5831\u7a05\u4e8b\u5b9c\n\n\u8cc7\u6b77 :\u4e2d\u4e94\u7a0b\u5ea6; 2\u5e74\u7d93\u9a57; \u4e00\u822c\u7cb5\u8a9e; \u4e00\u822c\u666e\u901a\u8a71; \u4e00\u822c\u82f1\u8a9e; \u61c2\u8b80\u5beb\u4e2d\u6587; \u7565\u61c2\u8b80\u5beb\u82f1\u6587; \u61c2\u82f1\u6587\u6253\u5b57; \u61c2\u4e2d\u82f1\u6587\u96fb\u8166\u64cd\u4f5c; \u61c2\u4e2d\u6587\u6253\u5b57; \u6301LCC\u4e2d\u7d1a\u6216\u4ee5\u4e0a\u8b49\u66f8\u6216\u540c\u7b49\u5b78\u6b77,\u51772\u5e74\u6216\u4ee5\u4e0a\u76f8\u95dc\u7d93\u9a57\n\n\u5f85\u9047 :\u6bcf\u6708$12,000\u6216\u4ee5\u4e0a, \u6709\u96d9\u7ce7 \u53ca\u9280\u884c\u5047\u671f, \u661f\u671f\u4e00\u81f3\u4e94: \u4e0a\u534810\u6642\u81f3\u4e0b\u53486\u6642, \u6bcf\u9031\u5de5\u4f5c5\u5929,\u7528\u81b3\u6642\u9593\u7531\u4e2d\u534812\u6642\u81f3\u4e0b\u53481\u6642\n\n\u7533\u8acb\u9808\u77e5 :\u6c42\u8077\u8005\u53ef\u96fb\u90f5(Apply Now)\u5c65\u6b77\u8868\u7d66\u65b0\u76c8\u74b0\u4fdd\u79d1\u6280\u6709\u9650\u516c\u53f8\u3002\u5982\u8981\u7d22\u53d6\u6536\u96c6\u500b\u4eba\u8cc7\u6599\u8072\u660e, \u8acb\u8207\u6613\u5c0f\u59d0(Email)\u806f\u7d61\u3002\n\n", "employment_types": ["Full Time"], "selling_points": [], "locations": ["Shatin Area"], "categories": ["Admin & HR", "Clerical / Admin Staff", "Others"], "post_time": "2022-01-17T07:25:20Z", "salary": {"currency": null, "max": null, "min": null, "period": "monthly", "term": null}, "salary_visible": false, "title_keywords": [], "responsibilities": [], "requirements": {"degrees": [], "majors": [], "languages": [], "language_level": [], "hard_skills": [], "soft_skills": [], "languages_combined": []}, "experience_required": {"duration": [], "field": []}}, {"job_id": "100003009051664", "location_code": "hk", "company": "Tung Wah Group of Hospitals", "job_title": "\u81e8\u6642\u6587\u66f8\u652f\u63f4\u52a9\u7406 (\u8077\u4f4d\u7de8\u865f\uff1aA3/TCSA/HQ/JOBS)", "description": "(\u8077\u4f4d\u7de8\u865f\uff1aA3/TCSA/HQ/JOBS)\n\u5de5\u4f5c\u5730\u9ede\uff1a\u4e0a\u74b0\n\u8077\u8cac\uff1a\n\u8ca0\u8cac\u6578\u64da\u8f38\u5165\u3001\u6574\u7406\u6587\u4ef6\u53ca\u4e00\u822c\u6587\u66f8\u5de5\u4f5c\u3002\n\u7406\u60f3\u7684\u7533\u8acb\u8005\u61c9\u5177\u5099\uff1a\n\u4e2d\u56db\u6216\u4ee5\u4e0a\u7a0b\u5ea6\uff0c\u719f\u6089\u96fb\u8166\u64cd\u4f5c\u53ca\u4e2d\u82f1\u6587\u6587\u66f8\u8655\u7406\u6280\u5de7\u3002\n\u85aa\u916c\u53ca\u8058\u7528\u689d\u4ef6\uff1a\n\u7372\u9078\u7684\u7533\u8acb\u4eba\u5c07\u4ee5\u81e8\u6642\u5408\u7d04\u689d\u6b3e\u53d7\u8058\uff0c\u6bcf\u6708\u85aa\u91d1\u73fe\u6642\u70ba$11,500\u3002\u4efb\u8077\u8005\u5c07\u6309\u4e94\u5929\u5de5\u4f5c\u5468\u5b89\u6392\u4e0a\u73ed\uff0c\u60df\u4ecd\u9808\u8996\u4e4e\u90e8\u9580\u904b\u4f5c\u53ca\u670d\u52d9\u9700\u8981\u800c\u5b9a\u3002\n\u7533\u8acb\u7a0b\u5e8f\uff1a\n\u8acb\u5c07\u500b\u4eba\u5c65\u6b77\u6216\u586b\u59a5\u7533\u8acb\u8868\u683c<F601>(\u53ef\u89aa\u81e8\u7d22\u53d6\u6216\u5f9e\u672c\u9662\u7684\u7db2\u9801https://www.tungwah.org.hk\u4e0b\u8f09)\uff0c\u5bc4\u9999\u6e2f\u4e0a\u74b0\u666e\u4ec1\u8857\u5341\u4e8c\u865f\u6771\u83ef\u4e09\u9662\u9ec3\u9cf3\u7fce\u7d00\u5ff5\u5927\u6a13\u56db\u6a13\u4eba\u529b\u8cc7\u6e90\u79d1\u4e3b\u7ba1\u6536\uff0c\u4fe1\u5167\u53ca\u4fe1\u5c01\u9762\u8acb\u8a3b\u660e\u7533\u8acb\u7684\u8077\u4f4d\u53ca\u8077\u4f4d\u7de8\u865f\u3002\u6771\u83ef\u4e09\u9662\u4e0d\u6703\u63a5\u6536\u90f5\u8cc7\u4e0d\u8db3\u7684\u4fe1\u4ef6\u3002\u70ba\u78ba\u4fdd\u90f5\u905e\u7121\u8aa4\uff0c\u8acb\u5728\u6295\u5bc4\u90f5\u4ef6\u6642\u652f\u4ed8\u8db3\u984d\u90f5\u8cc7\u53ca\u8a3b\u660e\u56de\u90f5\u5730\u5740\u3002\u6771\u83ef\u4e09\u9662\u5728\u4f7f\u7528\u6c42\u8077\u8005\u63d0\u4f9b\u7684\u500b\u4eba\u8cc7\u6599\u6642\uff0c\u53ea\u6703\u5c07\u8cc7\u6599\u4f5c\u6709\u95dc\u62db\u8058\u7528\u9014\uff0c\u4e26\u6703\u56b4\u683c\u9075\u5b88\u9662\u65b9\u500b\u4eba\u8cc7\u6599\u653f\u7b56\u7684\u898f\u5b9a\u3002\n\n\u6211\u5011\u662f\u5e73\u7b49\u6a5f\u6703\u50f1\u4e3b", "employment_types": ["Temporary", "Contract"], "selling_points": [], "locations": ["Sheung Wan"], "categories": ["Admin & HR", "Clerical / Admin Staff", "Others", "HR Supporting Staff"], "post_time": "2022-01-16T21:50:36Z", "salary": {"currency": null, "max": null, "min": null, "period": "monthly", "term": null}, "salary_visible": false, "title_keywords": [], "responsibilities": [], "requirements": {"degrees": [], "majors": [], "languages": [], "language_level": [], "hard_skills": [], "soft_skills": [], "languages_combined": []}, "experience_required": {"duration": [], "field": []}}, {"job_id": "100003009053854", "location_code": "hk", "company": "Hey Home Property Limited", "job_title": "\u8a2d\u8a08\u6587\u54e1", "description": "\n\u8077\u8cac :\u8ca0\u8cac\u8655\u7406\u6587\u4ef6\u7d00\u9304\u53ca\u5b58\u6a94\uff0c\u6574\u7406\u5ba2\u6236\u8cc7\u6599\uff0c\u6536\u767c\u96fb\u90f5\u3001\u63a5\u807d\u96fb\u8a71\uff0c\u53ca\u5e02\u5834\u63a8\u5ee3\u8a2d\u8a08\u3001\u793e\u4ea4\u5a92\u9ad4\u5ba3\u50b3\u3001\u7db2\u7ad9\u7f8e\u8853\u8a2d\u8a08\n\n\u8cc7\u6b77 :\u5c08\u4e0a\u6559\u80b2\uff1a\u6587\u6191/\u8b49\u66f8; 1\u5e74\u7d93\u9a57; \u4e00\u822c\u7cb5\u8a9e; \u4e00\u822c\u666e\u901a\u8a71; \u826f\u597d\u82f1\u8a9e\u512a\u5148; \u61c2\u8b80\u5beb\u4e2d\u6587; \u61c2\u8b80\u5beb\u82f1\u6587; \u61c2PhotoShop; \u61c2Microsoft Office; \u61c2Illustrator; \u61c2\u4e00\u822c\u7db2\u9801\u88fd\u4f5c\n\n\u5f85\u9047 :\u6bcf\u6708$12,000 - $14,000, \u4e0a\u534810\u6642\u81f3\u4e0b\u53487\u6642, \u6bcf\u9031\u5de5\u4f5c6\u5929,\u8f2a\u4f11\n\n\u7533\u8acb\u9808\u77e5 :\u6c42\u8077\u8005\u53ef\u81f4\u96fb62562568\u8207\u559c\u5c45\u7269\u696d\u6709\u9650\u516c\u53f8\u99ae\u5c0f\u59d0\u806f\u7d61\u3002\n\n", "employment_types": ["Full Time"], "selling_points": [], "locations": ["Cheung Sha Wan"], "categories": ["Admin & HR", "Clerical / Admin Staff", "Others"], "post_time": "2022-01-17T07:37:53Z", "salary": {"currency": null, "max": null, "min": null, "period": "monthly", "term": null}, "salary_visible": false, "title_keywords": [], "responsibilities": [], "requirements": {"degrees": [], "majors": [], "languages": [], "language_level": [], "hard_skills": [], "soft_skills": [], "languages_combined": []}, "experience_required": {"duration": [], "field": []}}, {"job_id": "100003009053385", "location_code": "hk", "company": "BEL International Logistics Limited", "job_title": "\u7a7a\u904b\u51fa\u53e3\u90e8\u6587\u54e1", "description": "\n\u8077\u8cac :\u4e00\u822c\u6587\u66f8\u5de5\u4f5c\uff0c\u8655\u7406\u7a7a\u904b\u51fa\u53e3\u6587\u4ef6; \u914d\u5408\u8ca8\u5009\u5b89\u6392\u904b\u8f38\n\n\u8cc7\u6b77 :\u4e2d\u4e09\u7a0b\u5ea6; \u826f\u597d\u7cb5\u8a9e; \u4e00\u822c\u666e\u901a\u8a71; \u4e00\u822c\u82f1\u8a9e; \u61c2\u8b80\u5beb\u4e2d\u6587; \u7565\u61c2\u8b80\u5beb\u82f1\u6587; \u5177\u6709\u57fa\u672c\u96fb\u8166\u64cd\u4f5c\u77e5\u8b58; \u5177\u7a7a\u904b\u8ca8\u904b\u4ee3\u7406\u5de5\u4f5c\u7d93\u9a57\u512a\u5148, \u9858\u610f\u52a0\u73ed, \u6709\u8cac\u4efb\u5fc3\n\n\u5f85\u9047 :\u6bcf\u6708$11,000 - $18,000, \u6709\u52e4\u5de5\u734e\u91d1, \u5e74\u504712\u5929, \u914c\u60c5\u6027\u82b1\u7d05 \u53ca\u91ab\u7642\u798f\u5229, \u661f\u671f\u4e00\u81f3\u516d: \u4e0a\u53489\u6642\u81f3\u4e0b\u53485\u6642\u534a\u6216\u4e0b\u53484\u6642\u81f3\u51cc\u66680\u6642\u534a, \u6bcf\u9031\u5de5\u4f5c6\u5929,\u8f2a\u73ed\n\n\u7533\u8acb\u9808\u77e5 :\u6c42\u8077\u8005\u53ef\u50b3\u771f(26114994)\u6216\u96fb\u90f5(Apply Now)\u5c65\u6b77\u8868\u7d66\u5275\u696d\u570b\u969b\u7269\u6d41\u6709\u9650\u516c\u53f8\u3002\u5982\u8981\u7d22\u53d6\u6536\u96c6\u500b\u4eba\u8cc7\u6599\u8072\u660e, \u8acb\u8207\u8d99\u5c0f\u59d0(Fax)\u806f\u7d61\u3002\n\n", "employment_types": ["Full Time"], "selling_points": [], "locations": ["Kwai Tsing Area"], "categories": ["Admin & HR", "Clerical / Admin Staff", "Others"], "post_time": "2022-01-17T06:54:25Z", "salary": {"currency": null, "max": null, "min": null, "period": "monthly", "term": null}, "salary_visible": false, "title_keywords": [], "responsibilities": [], "requirements": {"degrees": [], "majors": [], "languages": [], "language_level": [], "hard_skills": [], "soft_skills": [], "languages_combined": []}, "experience_required": {"duration": [], "field": []}}, {"job_id": "100003009053505", "location_code": "hk", "company": "Learning Infinity", "job_title": "\u6559\u5ba4\u63a5\u5f85\u54e1(\u986f\u5f91\u7e3d\u6821)", "description": "\n\u5730\u5340\uff1a \u5927\u570d\u00a0\u00a0\n\u8077\u8cac\uff1a \u8ca0\u8cac\u5831\u540d\u67e5\u8a62\u53ca\u6536\u8cbb, \u9810\u5099\u6559\u6750\u548c\u7269\u8cc7, \u78ba\u4fdd\u8ab2\u5802\u9806\u66a2\u9032\u884c\n\u8cc7\u6b77\uff1a \u5c08\u4e0a\u6559\u80b2\uff1a\u6587\u6191/\u8b49\u66f8; \u826f\u597d\u7cb5\u8a9e; \u4e00\u822c\u82f1\u8a9e; \u61c2\u8b80\u5beb\u4e2d\u6587; \u61c2\u8b80\u5beb\u82f1\u6587; \u61c2\u82f1\u6587\u6253\u5b57; \u5de5\u4f5c\u614b\u5ea6\u89aa\u5207\u53cb\u5584\uff0c\u5177\u826f\u597d\u6e9d\u901a\u6280\u5de7\uff0c\u6e96\u6642\u4e0a\u73ed\uff0c\u5de5\u4f5c\u614b\u5ea6\u7a4d\u6975\uff0c\u6709\u8cac\u4efb\u5fc3\uff0c\u6709\u5718\u9ad4\u5408\u4f5c\u7cbe\u795e\n\u5f85\u9047\uff1a \u6bcf\u6708$10,000 - $12,000, \u6709\u914c\u60c5\u6027\u82b1\u7d05 \u53ca\u9280\u884c\u5047\u671f, \u661f\u671f\u4e00\u81f3\u4e94: \u4e0b\u53482\u6642\u81f3\u4e0b\u53489\u6642\u53ca\u661f\u671f\u516d: \u4e0a\u534810\u6642\u81f3\u4e0b\u53483\u6642, \u6bcf\u9031\u5de5\u4f5c5\u5929\u534a\n\u7533\u8acb\u9808\u77e5\uff1a \u6c42\u8077\u8005\u53ef\u96fb\u90f5([via\u00a0 Apply Now ])\u5c65\u6b77\u8868\u7d66\u5b78\u7fd2\u7121\u9650\u3002\u5982\u8981\u7d22\u53d6\u6536\u96c6\u500b\u4eba\u8cc7\u6599\u8072\u660e, \u8acb\u8207\u66fe \u5c0f\u59d0(Email)\u806f\u7d61\u3002\n\n", "employment_types": ["Full Time"], "selling_points": [], "locations": ["Shatin Area"], "categories": ["Admin & HR", "Clerical / Admin Staff", "Receptionist", "Others"], "post_time": "2022-01-17T07:04:23Z", "salary": {"currency": null, "max": null, "min": null, "period": "monthly", "term": null}, "salary_visible": false, "title_keywords": [], "responsibilities": [], "requirements": {"degrees": [], "majors": [], "languages": [], "language_level": [], "hard_skills": [], "soft_skills": [], "languages_combined": []}, "experience_required": {"duration": [], "field": []}}, {"job_id": "100003009053640", "location_code": "hk", "company": "Health Factor Foods Company Limited", "job_title": "\u8fa6\u516c\u5ba4\u6587\u54e1", "description": "\n\u5730\u5340 : \u89c0\u5858\n\u8077\u8cac : \u8ca0\u8cac\u958b\u7acb\u92b7\u552e\u5408\u540c\u3001\u767c\u7968\u53ca\u76f8\u95dc\u6587\u4ef6\uff0c\u5167\u90e8\u90e8\u9580\u6e9d\u901a\u5b89\u6392\u9001\u8ca8\uff0c\u53ca\u4e00\u822c\u8f38\u5165\u7cfb\u7d71\u6578\u64da\n\u8cc7\u6b77 : \u4e2d\u4e94\u7a0b\u5ea6; \u826f\u597d\u7cb5\u8a9e\u512a\u5148; \u4e00\u822c\u666e\u901a\u8a71; \u4e00\u822c\u82f1\u8a9e; \u61c2\u8b80\u5beb\u4e2d\u6587; \u61c2\u8b80\u5beb\u82f1\u6587; \u61c2MS Word; \u5177\u6709\u57fa\u672c\u96fb\u8166\u64cd\u4f5c\u77e5\u8b58; Diligent, initiative and hardworking\n\u5f85\u9047 : \u6bcf\u6708$10,000 - $12,000, \u6709\u9280\u884c\u5047\u671f, \u54e1\u5de5\u8cfc\u7269\u512a\u60e0 \u53ca\u91ab\u7642\u4fdd\u96aa, \u661f\u671f\u4e00\u81f3\u4e94: \u4e0a\u53489\u6642\u81f3\u4e0b\u53486\u6642\u53ca\u661f\u671f\u516d: \u4e0a\u53489\u6642\u81f3\u4e0b\u53481\u6642, \u6bcf\u9031\u5de5\u4f5c5\u5929\u81f35\u5929\u534a\n\u7533\u8acb\u9808\u77e5 : \u6c42\u8077\u8005\u53ef\u96fb\u90f5(Apply Now)\u5c65\u6b77\u8868\u7d66\u5065\u5eb7\u5143\u7d20\u98df\u54c1\u6709\u9650\u516c\u53f8\u3002\u5982\u8981\u7d22\u53d6\u6536\u96c6\u500b\u4eba\u8cc7\u6599\u8072\u660e, \u8acb\u8207\u6881\u5c0f\u59d0(Email)\u806f\u7d61\u3002\n\n", "employment_types": ["Full Time"], "selling_points": [], "locations": ["Kwun Tong"], "categories": ["Admin & HR", "Clerical / Admin Staff", "Others"], "post_time": "2022-01-17T07:16:43Z", "salary": {"currency": null, "max": null, "min": null, "period": "monthly", "term": null}, "salary_visible": false, "title_keywords": [], "responsibilities": [], "requirements": {"degrees": [], "majors": [], "languages": [], "language_level": [], "hard_skills": ["word"], "soft_skills": ["diligent", "initiative", "hardworking"], "languages_combined": []}, "experience_required": {"duration": [], "field": []}}, {"job_id": "100003009053929", "location_code": "hk", "company": "Crown Harvest Group Limited", "job_title": "\u81e8\u6642\u6703\u8a08\u6587\u54e1", "description": "\n\u8077\u8cac :\u4e00\u822c\u6703\u8a08\u6587\u54e1\u5de5\u4f5c, \u8cc7\u6599\u8f38\u5165, \u6587\u4ef6\u8655\u7406\n\n\u8cc7\u6b77 :\u4e2d\u4e94\u7a0b\u5ea6; 1\u5e74\u7d93\u9a57; \u4e00\u822c\u7cb5\u8a9e; \u4e00\u822c\u666e\u901a\u8a71; \u4e00\u822c\u82f1\u8a9e; \u61c2\u8b80\u5beb\u4e2d\u6587; \u61c2\u95b1\u8b80\u82f1\u6587\n\n\u5f85\u9047 :\u6bcf\u5c0f\u6642$60.00, \u661f\u671f\u4e00\u81f3\u4e94: \u4e0a\u53489\u6642\u81f3\u4e0b\u53486\u6642, \u6bcf\u9031\u5de5\u4f5c5\u5929, \u5de5\u4f5c\u671f1\u500b\u6708, \u6bcf\u5929\u5de5\u4f5c 9 \u5c0f\u6642\n\n\u7533\u8acb\u9808\u77e5 :\u6c42\u8077\u8005\u53ef\u96fb\u90f5(Apply Now)\u5c65\u6b77\u8868\u7d66\u51a0\u6797\u96c6\u5718\u6709\u9650\u516c\u53f8\u3002\u5982\u8981\u7d22\u53d6\u6536\u96c6\u500b\u4eba\u8cc7\u6599\u8072\u660e, \u8acb\u8207\u674e\u5148\u751f(Email)\u806f\u7d61\u3002\n\n", "employment_types": ["Part Time"], "selling_points": [], "locations": ["Kwai Tsing Area"], "categories": ["Admin & HR", "Clerical / Admin Staff", "Others"], "post_time": "2022-01-17T07:47:47Z", "salary": {"currency": null, "max": null, "min": null, "period": "hourly", "term": null}, "salary_visible": false, "title_keywords": [], "responsibilities": [], "requirements": {"degrees": [], "majors": [], "languages": [], "language_level": [], "hard_skills": [], "soft_skills": [], "languages_combined": []}, "experience_required": {"duration": [], "field": []}}, {"job_id": "100003009052511", "location_code": "hk", "company": "Sodexo (Hong Kong) Limited", "job_title": "Office Assistant \u8fa6\u516c\u5ba4\u52a9\u7406", "description": "Job Duties \u8077\u8cac:\u00a0\n\nMail room services, Support collect and distribute incoming and internal letters to pigeon holes\nCoordinate with courier services for incoming/outcoming mail\nGo to post offices deliver documents and bank cheque deposits\u00a0\nAssist in conference room settings for meetings or trainings\nOther ad hoc general office administrative work may be assigned\n\u8655\u7406\u4ee5\u53ca\u5206\u767c\u4fe1\u4ef6/\u6587\u4ef6\n\u806f\u7d61\u901f\u905e\u6536\u767c\u4fe1\u4ef6\n\u9700\u5916\u52e4\u5de5\u4f5c\u5982\u5230\u90f5\u653f\u5c40\u6216\u9280\u884c\n\u70ba\u6703\u8b70\u53ca\u57f9\u8a13\u4f48\u7f6e\u6703\u8b70\u5ba4\n\u652f\u63f4\u4e00\u822c\u8fa6\u516c\u5ba4\u884c\u653f\u5de5\u4f5c\n\nRequirement\u00a0\u4efb\u8077\u8981\u6c42:\u00a0\n\nWith 2 years working experience in office management\nFamiliar with office equipment and supplies\nFair in written and spoken\u00a0English and\u00a0Chinese\n2\u5e74\u6216\u4ee5\u4e0a\u76f8\u95dc\u8fa6\u516c\u5ba4\u5de5\u4f5c\u7d93\u9a57\n\u719f\u6089\u8fa6\u516c\u5ba4\u8a2d\u65bd\u53ca\u7528\u54c1\n\u4e00\u822c\u4e2d\u82f1\u6587\u5c0d\u8a71\u53ca\u66f8\u5beb\u80fd\u529b\n\nWorking Location \u5de5\u4f5c\u5730\u9ede:\u00a0\n\nHong Kong Island (Monday to Friday, 9:00a.m.\u00a0to 18:00p.m.)\n\u6e2f\u5cf6\u5340 (\u661f\u671f\u4e00\u81f3\u4e94\uff0c\u4e0a\u53489\u9ede\u81f3\u4e0b\u53486\u9ede)\n\nBenefits\u00a0\u54e1\u5de5\u798f\u5229:\n\n5-day work week\nPublic Holiday\nMedical Benefits\nBirthday Leave\nA fun and lively working environment where you will be valued and developed\n5\u5929\u5de5\u4f5c\u9031\n\u516c\u773e\u5047\u671f\n\u91ab\u7642\u798f\u5229\n\u751f\u65e5\u5047\u671f\n\u5145\u6eff\u6d3b\u529b\u7684\u5de5\u4f5c\u74b0\u5883\uff0c\u826f\u597d\u767c\u5c55\u4ee5\u53ca\u6649\u5347\u6a5f\u6703\n\nApplication \u7533\u8acb\u8fa6\u6cd5:\n\nWe offer competitive remuneration to the right candidates. Please apply with\u00a0detailed resume\u00a0and\u00a0salary expectation\u00a0to Human Resources Department, Sodexo (Hong Kong) Limited by clicking\u00a0Apply Now.\u00a0\u00a0\n\u7533\u8acb\u4eba\u53ef\u6309\u300cApply Now\u300d\u5c07\u5c65\u6b77\u8868\u53ca\u8981\u6c42\u5f85\u9047\u50b3\u9001\u81f3\u4eba\u529b\u8cc7\u6e90\u90e8\u3002", "employment_types": ["Full Time", "Permanent"], "selling_points": ["Corporate Office", "2 years working experience in office management", "Fair in written and spoken English and Chinese"], "locations": ["Central & Western Area"], "categories": ["Admin & HR", "Clerical / Admin Staff", "Others"], "post_time": "2022-01-17T03:17:17Z", "salary": {"currency": null, "max": null, "min": null, "period": "monthly", "term": null}, "salary_visible": false, "title_keywords": ["office assistant", "\u8fa6\u516c\u5ba4\u52a9\u7406"], "responsibilities": ["ad hoc", "letters", "administrative work", "coordinate with"], "requirements": {"degrees": [], "majors": [], "languages": ["english", "chinese"], "language_level": [], "hard_skills": [], "soft_skills": [], "languages_combined": [{"language": "english", "language_level": []}, {"language": "chinese", "language_level": []}]}, "experience_required": {"duration": ["2 years"], "field": ["management"]}}, {"job_id": "100003009053867", "location_code": "hk", "company": "Dickinson Garment Factory Limited", "job_title": "\u8fa6\u516c\u5ba4\u52a9\u7406**", "description": "\n\u8077\u8cac :\u5916\u52e4\u5de5\u4f5c\uff0c\u5982\u5230\u9280\u884c\u3001\u90f5\u5c40\u8207\u5916\u51fa\u6536\u767c\u6587\u4ef6\uff0c\u4e00\u822c\u8fa6\u516c\u5ba4\u52a9\u7406\u5de5\u4f5c\uff0c\u8ca0\u8cac\u4e00\u822c\u8fa6\u516c\u5ba4\u8336\u6c34\u5de5\u4f5c\uff0c\u6309\u516c\u53f8\u6307\u793a\u5b89\u6392\u5de5\u4f5c\u3002\n\n\u8cc7\u6b77 :\u5c0f\u4e09\u7a0b\u5ea6; 1\u5e74\u7d93\u9a57; \u826f\u597d\u7cb5\u8a9e\u512a\u5148; \u4e00\u822c\u82f1\u8a9e; \u61c2\u8b80\u5beb\u4e2d\u6587; \u61c2\u95b1\u8b80\u82f1\u6587\n\n\u5f85\u9047 :\u6bcf\u6708$10,000 - $12,000, \u6709\u91ab\u7642\u4fdd\u96aa, \u661f\u671f\u4e00\u81f3\u4e94: \u4e0a\u53489\u6642\u81f3\u4e0b\u53486\u6642, \u6bcf\u9031\u5de5\u4f5c5\u5929, \u5f48\u6027\u7528\u81b3\u6642\u9593\n\n\u7533\u8acb\u9808\u77e5 :\u6c42\u8077\u8005\u53ef\u96fb\u90f5(Apply Now)\u5c65\u6b77\u8868\u7d66\u5fb7\u749f\u6cf0\u5be6\u696d\u6709\u9650\u516c\u53f8\u3002\u5982\u8981\u7d22\u53d6\u6536\u96c6\u500b\u4eba\u8cc7\u6599\u8072\u660e, \u8acb\u8207\u5289\u5c0f\u59d0(Email)\u806f\u7d61\u3002\n\n", "employment_types": ["Full Time"], "selling_points": [], "locations": ["Kwun Tong"], "categories": ["Admin & HR", "Clerical / Admin Staff", "Others", "Others", "Trading"], "post_time": "2022-01-17T07:39:39Z", "salary": {"currency": null, "max": null, "min": null, "period": "monthly", "term": null}, "salary_visible": false, "title_keywords": ["\u8fa6\u516c\u5ba4\u52a9\u7406"], "responsibilities": [], "requirements": {"degrees": [], "majors": [], "languages": [], "language_level": [], "hard_skills": [], "soft_skills": [], "languages_combined": []}, "experience_required": {"duration": [], "field": []}}, {"job_id": "100003009053737", "location_code": "hk", "company": "Silver Printing Company Limited", "job_title": "\u6587\u54e1", "description": "\n\u8077\u8cac :\u8ca0\u8cac\u4e00\u822c\u5ba2\u6236\u8a02\u55ae\u8655\u7406;\u8ca0\u8cac\u570b\u5167\u5916\u5ba2\u6236\u8a02\u55ae\u8655\u7406\u548c\u4e00\u822c\u8ca8\u904b\u6587\u4ef6; Responsible for clerical duties, data entry in ERP System, documents filing etc;Follow up order & quality control\n\n\u8cc7\u6b77 :\u4e2d\u4e94\u7a0b\u5ea6; 1\u5e74\u7d93\u9a57; \u826f\u597d\u7cb5\u8a9e; \u826f\u597d\u666e\u901a\u8a71\u512a\u5148; \u826f\u597d\u82f1\u8a9e\u512a\u5148; \u61c2\u8b80\u5beb\u4e2d\u6587; \u61c2\u8b80\u5beb\u82f1\u6587; \u61c2MS Word; \u61c2MS Outlook; \u61c2MS Excel; \u6709\u88fd\u8863\u6216\u5370\u5237\u8ddf\u55ae\u5de5\u4f5c\u7d93\u9a57\u512a\u5148; Hardworking & able to work under pressure\n\n\u5f85\u9047 :\u6bcf\u6708$13,000 - $16,000, \u6709\u5e74\u7d42\u96d9\u7ce7, \u661f\u671f\u4e00\u81f3\u4e94: \u4e0a\u53489\u6642\u81f3\u4e0b\u53486\u6642\u53ca\u661f\u671f\u516d: \u4e0a\u53489\u6642\u81f3\u4e0b\u53481\u6642, \u6bcf\u9031\u5de5\u4f5c5\u5929\u534a\n\n\u7533\u8acb\u9808\u77e5 :\u6c42\u8077\u8005\u53ef\u96fb\u90f5(Apply Now)\u5c65\u6b77\u8868\u7d66\u5f0f\u6167\u5370\u5237\u6709\u9650\u516c\u53f8\u3002\u5982\u8981\u7d22\u53d6\u6536\u96c6\u500b\u4eba\u8cc7\u6599\u8072\u660e, \u8acb\u8207\u4f55\u5c0f\u59d0(Email)\u806f\u7d61\u3002\n\n", "employment_types": ["Full Time"], "selling_points": [], "locations": ["Wong Tai Sin Area"], "categories": ["Admin & HR", "Clerical / Admin Staff", "Others"], "post_time": "2022-01-17T07:26:05Z", "salary": {"currency": null, "max": null, "min": null, "period": "monthly", "term": null}, "salary_visible": false, "title_keywords": ["\u6587\u54e1"], "responsibilities": ["work under pressure", "documents filing", "quality control", "data entry"], "requirements": {"degrees": [], "majors": [], "languages": [], "language_level": [], "hard_skills": ["excel", "erp system", "outlook", "word"], "soft_skills": ["hardworking", "responsible", "work under pressure"], "languages_combined": []}, "experience_required": {"duration": [], "field": []}}, {"job_id": "100003009053522", "location_code": "hk", "company": "Tin's Label Factory Ltd", "job_title": "\u96dc\u5de5(\u67ef\u5f0f\u5ee0)", "description": "\n\u8077\u8cac :\u8ca0\u8cac\u5de5\u5834\u4e00\u5207\u96dc\u52d9 (\u4e0a\u73ed\u65e5\u671f: 14/2/2022\u958b\u59cb)\n\n\u8cc7\u6b77 :\u6c92\u6709\u5b78\u6b77\u8981\u6c42; \u7565\u61c2\u8b80\u5beb\u4e2d\u6587; \u7565\u61c2\u8b80\u5beb\u82f1\u6587\n\n\u5f85\u9047 :\u6bcf\u6708$10,000, \u6709\u8d85\u6642\u5de5\u4f5c\u6d25\u8cbc, \u661f\u671f\u4e00\u81f3\u516d: \u4e0a\u53489\u6642\u81f3\u4e0b\u53486\u6642, \u6bcf\u9031\u5de5\u4f5c6\u5929\n\n\u7533\u8acb\u9808\u77e5 :\u6c42\u8077\u8005\u53ef\u81f4\u96fb27423690\u8207\u7530\u6c0f\u5370\u561c\u81a0\u8cbc\u5546\u6a19\u5ee0\u6709\u9650\u516c\u53f8\u5f35\u5c0f\u59d0\u806f\u7d61\u3002\n\n", "employment_types": ["Full Time"], "selling_points": [], "locations": ["Kwai Tsing Area"], "categories": ["Admin & HR", "Others", "Hospitality / F & B", "Others", "Building & Construction", "Others"], "post_time": "2022-01-17T07:05:41Z", "salary": {"currency": null, "max": null, "min": null, "period": "monthly", "term": null}, "salary_visible": false, "title_keywords": [], "responsibilities": [], "requirements": {"degrees": [], "majors": [], "languages": [], "language_level": [], "hard_skills": [], "soft_skills": [], "languages_combined": []}, "experience_required": {"duration": [], "field": []}}, {"job_id": "100003009053763", "location_code": "hk", "company": "Soil Services Testing Company Limited", "job_title": "\u6280\u8853\u6587\u54e1", "description": "\n\u8077\u8cac :\u64cd\u4f5c\u8a66\u9a57\u6aa2\u6e2c\u6a23\u54c1\uff0c\u8a18\u9304\u6578\u64da\uff0c\u6574\u7406\u5831\u544a\n\n\u8cc7\u6b77 :\u4e2d\u4e94\u7a0b\u5ea6; \u826f\u597d\u7cb5\u8a9e; \u4e00\u822c\u666e\u901a\u8a71; \u4e00\u822c\u82f1\u8a9e; \u61c2\u8b80\u5beb\u4e2d\u6587; \u61c2\u8b80\u5beb\u82f1\u6587\n\n\u5f85\u9047 :\u6bcf\u6708$13,000 - $14,000, \u6709\u8d85\u6642\u5de5\u4f5c\u6d25\u8cbc, \u96d9\u7ce7, \u9280\u884c\u5047\u671f \u53ca\u5728\u8077\u57f9\u8a13, \u661f\u671f\u4e00\u81f3\u4e94: \u4e0a\u53489\u6642\u81f3\u4e0b\u53486\u6642\u53ca\u661f\u671f\u516d: \u4e0a\u53489\u6642\u81f3\u4e0b\u53481\u6642, \u6bcf\u9031\u5de5\u4f5c5\u5929\u534a, \u6bcf\u5929\u5de5\u4f5c 7 - 8 \u5c0f\u6642\n\n\u7533\u8acb\u9808\u77e5 :\u6c42\u8077\u8005\u53ef\u50b3\u771f(24630609)\u6216\u96fb\u90f5(Apply Now)\u5c65\u6b77\u8868\u7d66\u571f\u8cea\u8a66\u9a57\u6709\u9650\u516c\u53f8\u3002\u5982\u8981\u7d22\u53d6\u6536\u96c6\u500b\u4eba\u8cc7\u6599\u8072\u660e, \u8acb\u8207\u8a31\u5148\u751f(Email)\u806f\u7d61\u3002\n\n", "employment_types": ["Full Time"], "selling_points": [], "locations": ["Tuen Mun Area"], "categories": ["Admin & HR", "Clerical / Admin Staff", "Others"], "post_time": "2022-01-17T07:28:42Z", "salary": {"currency": null, "max": null, "min": null, "period": "monthly", "term": null}, "salary_visible": false, "title_keywords": [], "responsibilities": [], "requirements": {"degrees": [], "majors": [], "languages": [], "language_level": [], "hard_skills": [], "soft_skills": [], "languages_combined": []}, "experience_required": {"duration": [], "field": []}}, {"job_id": "100003009053590", "location_code": "hk", "company": "Sun Eagle Development Limited", "job_title": "\u52a9\u7406\u6587\u54e1**", "description": "\n\u8077\u8cac :\u5354\u52a9\u96fb\u8166\u8cc7\u6599\u8f38\u5165,\u4e00\u822c\u6587\u66f8\u8655\u7406\uff0c\u6838\u5c0d\u7269\u6599\u53ca\u5176\u4ed6\u4e0a\u7d1a\u6307\u6d3e\u5de5\u4f5c\n\n\u8cc7\u6b77 :\u4e2d\u4e09\u7a0b\u5ea6; \u826f\u597d\u7cb5\u8a9e\u512a\u5148; \u4e00\u822c\u666e\u901a\u8a71; \u4e00\u822c\u82f1\u8a9e; \u61c2\u8b80\u5beb\u4e2d\u6587; \u7565\u61c2\u8b80\u5beb\u82f1\u6587\n\n\u5f85\u9047 :\u6bcf\u6708$11,000 - $12,500, \u6709\u8d85\u6642\u5de5\u4f5c\u6d25\u8cbc, \u8868\u73fe\u734e\u91d1, \u661f\u671f\u4e00\u81f3\u516d: \u4e0a\u53488\u6642\u81f3\u4e0b\u53485\u6642, \u6bcf\u9031\u5de5\u4f5c6\u5929, \u6bcf\u5929\u5de5\u4f5c 8 \u5c0f\u6642, \u5348\u81b3 1 \u5c0f\u6642\uff0c\u9593\u4e2d\u9700\u8981\u8d85\u6642\u5de5\u4f5c\n\n\u7533\u8acb\u9808\u77e5 :\u6c42\u8077\u8005\u53ef\u81f4\u96fb65433053\u8207\u9d6c\u6689\u767c\u5c55\u6709\u9650\u516c\u53f8\u970d\u5c0f\u59d0\u806f\u7d61\u3002\n\n", "employment_types": ["Full Time"], "selling_points": [], "locations": ["Tsuen Wan Area"], "categories": ["Admin & HR", "Clerical / Admin Staff", "Others"], "post_time": "2022-01-17T07:12:48Z", "salary": {"currency": null, "max": null, "min": null, "period": "monthly", "term": null}, "salary_visible": false, "title_keywords": ["\u52a9\u7406\u6587\u54e1"], "responsibilities": [], "requirements": {"degrees": [], "majors": [], "languages": [], "language_level": [], "hard_skills": [], "soft_skills": [], "languages_combined": []}, "experience_required": {"duration": [], "field": []}}, {"job_id": "100003009053716", "location_code": "hk", "company": "APAC Solution Corporation Limited", "job_title": "\u5e97\u52d9\u92b7\u552e\u6587\u54e1", "description": "\n\u8077\u8cac :\u4ecb\u7d39\u96fb\u5b50\u7522\u54c1\u53ca\u914d\u4ef6\uff1b\u8ca0\u8cac\u5e97\u8216\u65e5\u5e38\u6587\u66f8\u5de5\u4f5c\uff1b\u92b7\u552e\u55ae\u64da\u53ca\u8ca8\u6b3e\u8655\u7406\uff1b\u8ca8\u54c1\u51fa\u5165\u5831\u544a\u53ca\u5009\u5b58\u7ba1\u7406\uff1b\u5e97\u9762\u5546\u54c1\u6574\u7406\u53ca\u9673\u5217\uff1b\u89e3\u7b54\u9867\u5ba2\u5c0d\u7522\u54c1\u53ca\u670d\u52d9\u7684\u67e5\u8a62\n\n\u8cc7\u6b77 :\u4e2d\u4e94\u7a0b\u5ea6; \u826f\u597d\u7cb5\u8a9e\u512a\u5148; \u4e00\u822c\u666e\u901a\u8a71; \u4e00\u822c\u82f1\u8a9e; \u61c2\u8b80\u5beb\u4e2d\u6587; \u7565\u61c2\u8b80\u5beb\u82f1\u6587; \u5177\u6709\u57fa\u672c\u96fb\u8166\u64cd\u4f5c\u77e5\u8b58; \u5de5\u4f5c\u4e3b\u52d5\u7a4d\u6975\u3001\u826f\u597d\u6e9d\u901a\u6280\u5de7\u3001\u80fd\u7368\u7acb\u5de5\u4f5c\uff1b\u719f\u6089\u96fb\u5b50\u7522\u54c1\u53ca\u53ef\u7acb\u5373\u4e0a\u73ed\u512a\u5148\n\n\u5f85\u9047 :\u6bcf\u6708$11,000 - $15,000, \u6709\u52e4\u5de5\u734e\u91d1, \u5e74\u504712\u5929, \u9280\u884c\u5047\u671f, \u5728\u8077\u57f9\u8a13, \u91ab\u7642\u798f\u5229 \u53ca\u4f63\u91d1, \u4e0a\u534811\u6642\u81f3\u4e0b\u53489\u6642, \u6bcf\u9031\u5de5\u4f5c6\u5929,\u8f2a\u4f11, \u6bcf\u5929\u5de5\u4f5c 9 - 10 \u5c0f\u6642\n\n\u7533\u8acb\u9808\u77e5 :\u6c42\u8077\u8005\u53ef\u96fb\u90f5(Apply Now)\u5c65\u6b77\u8868\u7d66\u6cdb\u4e9e\u89e3\u6c7a\u65b9\u6848\u6709\u9650\u516c\u53f8\u3002\u5982\u8981\u7d22\u53d6\u6536\u96c6\u500b\u4eba\u8cc7\u6599\u8072\u660e, \u8acb\u8207\u885b\u5c0f\u59d0(Email)\u806f\u7d61\u3002\n\n", "employment_types": ["Full Time"], "selling_points": [], "locations": ["Kwun Tong"], "categories": ["Admin & HR", "Clerical / Admin Staff", "Others"], "post_time": "2022-01-17T07:24:11Z", "salary": {"currency": null, "max": null, "min": null, "period": "monthly", "term": null}, "salary_visible": false, "title_keywords": [], "responsibilities": [], "requirements": {"degrees": [], "majors": [], "languages": [], "language_level": [], "hard_skills": [], "soft_skills": [], "languages_combined": []}, "experience_required": {"duration": [], "field": []}}, {"job_id": "100003009053757", "location_code": "hk", "company": "Kalong Express Limited", "job_title": "\u7269\u6d41\u6587\u54e1", "description": "\n\u8077\u8cac :\u8ca0\u8cac\u51fa\u5165\u53e3\u6587\u4ef6\uff0c\u8655\u7406\u4e00\u822c\u6587\u66f8\u5de5\u4f5c\uff0c\u8207\u4f9b\u61c9\u5546\u5354\u8abf\u53ca\u6e9d\u901a\u8239\u52d9\u4e8b\u5b9c\u3002\n\n\u8cc7\u6b77 :\u4e2d\u4e94\u7a0b\u5ea6; 1\u5e74\u7d93\u9a57; \u826f\u597d\u7cb5\u8a9e; \u826f\u597d\u666e\u901a\u8a71\u512a\u5148; \u4e00\u822c\u82f1\u8a9e; \u61c2\u8b80\u5beb\u4e2d\u6587; \u61c2\u8b80\u5beb\u82f1\u6587; \u61c2Microsoft Office; \u61c2\u5009\u9821/\u901f\u6210\u8f38\u5165\u6cd5; \u826f\u597d\u6e9d\u901a\u53ca\u8655\u4e8b\u6280\u5de7\uff0c\u6709\u8cac\u4efb\u611f\u548c\u826f\u597d\u57f7\u884c\u6280\u5de7\uff0c\u5de5\u4f5c\u7a4d\u6975\u9032\u53d6\n\n\u5f85\u9047 :\u6bcf\u6708$11,000 - $12,000, \u6709\u9280\u884c\u5047\u671f, \u5e74\u50477-14\u5929 \u53ca\u914c\u60c5\u6027\u82b1\u7d05, \u661f\u671f\u4e00\u81f3\u4e94: \u4e0a\u53489\u6642\u81f3\u4e0b\u53486\u6642, \u6bcf\u9031\u5de5\u4f5c5\u5929, \u6bcf\u5929\u5de5\u4f5c 8 \u5c0f\u6642\n\n\u7533\u8acb\u9808\u77e5 :\u6c42\u8077\u8005\u53ef\u96fb\u90f5(Apply Now)\u5c65\u6b77\u8868\u7d66\u6ea2\u90a6\u8ca8\u904b\u6709\u9650\u516c\u53f8\u3002\u5982\u8981\u7d22\u53d6\u6536\u96c6\u500b\u4eba\u8cc7\u6599\u8072\u660e, \u8acb\u8207\u5289\u5148\u751f(Email)\u806f\u7d61\u3002\n\n", "employment_types": ["Full Time"], "selling_points": [], "locations": ["Tsuen Wan Area"], "categories": ["Admin & HR", "Clerical / Admin Staff", "Others"], "post_time": "2022-01-17T07:28:09Z", "salary": {"currency": null, "max": null, "min": null, "period": "monthly", "term": null}, "salary_visible": false, "title_keywords": [], "responsibilities": [], "requirements": {"degrees": [], "majors": [], "languages": [], "language_level": [], "hard_skills": [], "soft_skills": [], "languages_combined": []}, "experience_required": {"duration": [], "field": []}}, {"job_id": "100003009053826", "location_code": "hk", "company": "Money Concepts (Asia) Holdings Limited", "job_title": "\u884c\u653f\u6587\u54e1**", "description": "\n\u8077\u8cac :\u4e00\u822c\u884c\u653f\u6587\u54e1\u5de5\u4f5c, \u6587\u66f8\u8655\u7406\u53ca\u63d0\u4f9b\u65e5\u5e38\u884c\u653f\u652f\u63f4\n\n\u8cc7\u6b77 :\u5c08\u4e0a\u6559\u80b2\uff1a\u6587\u6191/\u8b49\u66f8; 4\u5e74\u7d93\u9a57; \u826f\u597d\u7cb5\u8a9e; \u826f\u597d\u666e\u901a\u8a71; \u826f\u597d\u82f1\u8a9e\u512a\u5148; \u61c2\u8b80\u5beb\u4e2d\u6587; \u61c2\u8b80\u5beb\u82f1\u6587; \u61c2MS Word; \u61c2MS Excel; \u5177\u6709\u57fa\u672c\u96fb\u8166\u64cd\u4f5c\u77e5\u8b58; Good communication & interpersonal skill; patient at work; good telephone manner.\n\n\u5f85\u9047 :\u6bcf\u6708$9,000 - $12,000, \u661f\u671f\u4e00\u81f3\u4e94: \u4e0a\u53489\u6642\u81f3\u4e0b\u53486\u6642\u53ca\u661f\u671f\u516d: \u4e0a\u53489\u6642\u81f3\u4e0b\u53481\u6642, \u6bcf\u9031\u5de5\u4f5c5\u5929\u534a, \u6bcf\u5929\u5de5\u4f5c 8 \u5c0f\u6642\n\n\u7533\u8acb\u9808\u77e5 :\u6c42\u8077\u8005\u53ef\u81f4\u96fb31052000\u8207\u7f8e\u570b\u842c\u5229\u7406\u8ca1\u63a7\u80a1\u6709\u9650\u516c\u53f8\u9127\u5148\u751f\u806f\u7d61\u3002\n\n", "employment_types": ["Full Time"], "selling_points": [], "locations": ["Wan Chai"], "categories": ["Admin & HR", "Clerical / Admin Staff", "Others"], "post_time": "2022-01-17T07:35:26Z", "salary": {"currency": null, "max": null, "min": null, "period": "monthly", "term": null}, "salary_visible": false, "title_keywords": [], "responsibilities": ["communication"], "requirements": {"degrees": [], "majors": [], "languages": [], "language_level": [], "hard_skills": ["excel", "word"], "soft_skills": ["communication", "patient", "telephone manner", "interpersonal skill"], "languages_combined": []}, "experience_required": {"duration": [], "field": []}}, {"job_id": "100003009053419", "location_code": "hk", "company": "Instant Travel Service Ltd", "job_title": "\u6703\u8a08\u6587\u54e1(\u517c\u8077)", "description": "\n\u8077\u8cac :\u8ca0\u8cac\u8655\u7406\u90e8\u9580\u65e5\u5e38\u6587\u66f8\u5de5\u4f5c,\u96fb\u8166\u8cc7\u6599\u8f38\u5165,\u9700\u5916\u52e4\n\n\u8cc7\u6b77 :\u4e2d\u4e94\u7a0b\u5ea6; 1\u5e74\u7d93\u9a57; \u826f\u597d\u7cb5\u8a9e; \u4e00\u822c\u666e\u901a\u8a71; \u4e00\u822c\u82f1\u8a9e; \u61c2\u8b80\u5beb\u4e2d\u6587; \u61c2\u8b80\u5beb\u82f1\u6587; \u61c2MS Word; \u61c2MS Excel; \u6301\u6709LCC\u521d\u7d1a\u8b49\u66f8; \u61c2\u82f1\u6587\u6253\u5b57; \u61c2\u4e2d\u6587\u6253\u5b57; \u6709\u7d93\u9a57/\u5c0d\u65c5\u904a\u696d\u6709\u8208\u8da3\u512a\u5148\n\n\u5f85\u9047 :\u6bcf\u5c0f\u6642$50.00 - $60.00, \u661f\u671f\u4e00\u81f3\u4e94: \u4e0b\u53482\u6642\u81f3\u4e0b\u53486\u6642, \u6bcf\u9031\u5de5\u4f5c5\u5929\n\n\u7533\u8acb\u9808\u77e5 :\u6c42\u8077\u8005\u53ef\u50b3\u771f(23858766)\u6216\u96fb\u90f5(Apply Now)\u5c65\u6b77\u8868\u7d66\u4e00\u5fc3\u65c5\u904a\u6709\u9650\u516c\u53f8\u3002\u5982\u8981\u7d22\u53d6\u6536\u96c6\u500b\u4eba\u8cc7\u6599\u8072\u660e, \u8acb\u8207\u9673\u5973\u58eb(Fax/Email)\u806f\u7d61\u3002\n\n", "employment_types": ["Part Time"], "selling_points": [], "locations": ["Yau Ma Tei"], "categories": ["Admin & HR", "Clerical / Admin Staff", "Others"], "post_time": "2022-01-17T06:58:00Z", "salary": {"currency": null, "max": null, "min": null, "period": "hourly", "term": null}, "salary_visible": false, "title_keywords": [], "responsibilities": [], "requirements": {"degrees": [], "majors": [], "languages": [], "language_level": [], "hard_skills": ["excel", "word"], "soft_skills": [], "languages_combined": []}, "experience_required": {"duration": [], "field": []}}, {"job_id": "100003009053122", "location_code": "hk", "company": "GenNex Financial Media Limited", "job_title": "\u8fa6\u516c\u5ba4\u52a9\u7406\u517c\u8336\u6c34\u54e1", "description": "\u8077\u8cac :\u8ca0\u8cac\u4e00\u822c\u8fa6\u516c\u5ba4\u8336\u6c34\u670d\u52d9\u3001\u6b3e\u5f85\u5ba2\u4eba\u3001\u8fa6\u516c\u5ba4\u96dc\u52d9; \u4fdd\u6301\u8336\u6c34\u9593\u3001\u6703\u8b70\u5ba4\u53ca\u8fa6\u516c\u5ba4\u6574\u6f54 ; \u5b89\u6392\u516c\u53f8\u5167\u5ba2\u4eba\u4e4b\u5348\u81b3\u3001\u665a\u81b3\u6216\u8336\u9ede ; \u6709\u9700\u8981\u5916\u52e4\u5de5\u4f5c\uff0c\u50b3\u9001\u6587\u4ef6\n\u8cc7\u6b77 :\u4e2d\u4e09\u7a0b\u5ea6; \u826f\u597d\u7cb5\u8a9e; \u4e00\u822c\u666e\u901a\u8a71; \u61c2\u8b80\u5beb\u4e2d\u6587; \u7565\u61c2\u8b80\u5beb\u82f1\u6587; \u5b88\u6642\u3001\u52e4\u596e\u3001\u5bcc\u8cac\u4efb\u611f\u53ca\u8aa0\u5be6\u6709\u79ae\uff0c\u5373\u6642\u4e0a\u73ed\u512a\u5148\n\u5f85\u9047 :\u6bcf\u6708$10,000, \u6709\u5e74\u504711\u5929, \u91ab\u7642\u798f\u5229 \u53ca\u8d85\u6642\u5de5\u4f5c\u6d25\u8cbc, \u661f\u671f\u4e00\u81f3\u4e94: \u4e0a\u53488\u6642\u534a\u81f3\u4e0b\u53485\u6642\u534a, \u6bcf\u9031\u5de5\u4f5c5\u5929, \u6bcf\u5929\u5de5\u4f5c 9 \u5c0f\u6642\n\u7533\u8acb\u9808\u77e5 :\u6c42\u8077\u8005\u53ef\u6309 APPLY NOW\u7533\u8acb", "employment_types": ["Full Time"], "selling_points": [], "locations": ["Central"], "categories": ["Admin & HR", "Clerical / Admin Staff", "Others", "Others", "Others"], "post_time": "2022-01-17T05:57:51Z", "salary": {"currency": null, "max": null, "min": null, "period": "monthly", "term": null}, "salary_visible": false, "title_keywords": [], "responsibilities": [], "requirements": {"degrees": [], "majors": [], "languages": [], "language_level": [], "hard_skills": [], "soft_skills": [], "languages_combined": []}, "experience_required": {"duration": [], "field": []}}, {"job_id": "100003009053913", "location_code": "hk", "company": "Swacoo (H.K.) Limited", "job_title": "\u51fa\u5165\u53e3\u6587\u54e1", "description": "\n\u8077\u8cac :\u8fa6\u7406\u51fa\u8ca8\u6587\u4ef6(INV ,PL,AIRWAYBILL,\u5165\u5009\u7eb8), \u51fa\u8ca8\u7ba1\u7406 , \u78ba\u8a8d\u4ea4\u8ca8\u671f, \u76e4\u9ede, \u4e00\u822c\u6587\u66f8\u5de5\u4f5c, \u8cbf\u6613\u901a\u5831\u95dc, \u53ca\u8ca8\u7269\u5206\u985e, \u6253\u5305, \u9700\u9ad4\u529b\u52de\u52d5\u5de5\u4f5c\n\n\u8cc7\u6b77 :\u4e2d\u516d\u7a0b\u5ea6; 2\u5e74\u7d93\u9a57; \u826f\u597d\u7cb5\u8a9e; \u826f\u597d\u666e\u901a\u8a71; \u826f\u597d\u82f1\u8a9e; \u61c2\u8b80\u5beb\u4e2d\u6587; \u61c2\u8b80\u5beb\u82f1\u6587\n\n\u5f85\u9047 :\u6bcf\u6708$14,000 - $15,000, \u6709\u8d85\u6642\u5de5\u4f5c\u88dc\u5047, \u96d9\u7ce7, \u91ab\u7642\u798f\u5229 \u53ca\u4ea4\u901a\u6d25\u8cbc, \u661f\u671f\u4e00\u81f3\u4e94: \u4e0a\u53489\u6642\u81f3\u4e0b\u53486\u6642\u53ca\u661f\u671f\u516d: \u4e0a\u53489\u6642\u81f3\u4e0b\u53481\u6642, \u6bcf\u9031\u5de5\u4f5c5\u5929\u81f35\u5929\u534a, \u6bcf\u5929\u5de5\u4f5c 8 \u5c0f\u6642\n\n\u7533\u8acb\u9808\u77e5 :\u6c42\u8077\u8005\u53ef\u96fb\u90f5(Apply Now)\u5c65\u6b77\u8868\u7d66\u8acf\u8a2a\u660c\u6709\u9650\u516c\u53f8\u3002\u5982\u8981\u7d22\u53d6\u6536\u96c6\u500b\u4eba\u8cc7\u6599\u8072\u660e, \u8acb\u8207\u5433\u5148\u751f(Email)\u806f\u7d61\u3002\n\n", "employment_types": ["Full Time"], "selling_points": [], "locations": ["Kwai Tsing Area"], "categories": ["Admin & HR", "Clerical / Admin Staff", "Others"], "post_time": "2022-01-17T07:45:21Z", "salary": {"currency": null, "max": null, "min": null, "period": "monthly", "term": null}, "salary_visible": false, "title_keywords": [], "responsibilities": [], "requirements": {"degrees": [], "majors": [], "languages": [], "language_level": [], "hard_skills": ["pl"], "soft_skills": [], "languages_combined": []}, "experience_required": {"duration": [], "field": []}}, {"job_id": "100003009053476", "location_code": "hk", "company": "First Green Knitters Factory Limited", "job_title": "\u6587\u54e1", "description": "\n\u8077\u8cac :\u4e00\u822c\u6587\u54e1\u5de5\u4f5c\n\n\u8cc7\u6b77 :\u4e2d\u4e94\u7a0b\u5ea6; \u4e00\u822c\u7cb5\u8a9e; \u4e00\u822c\u666e\u901a\u8a71; \u4e00\u822c\u82f1\u8a9e; \u7565\u61c2\u8b80\u5beb\u4e2d\u6587; \u7565\u61c2\u8b80\u5beb\u82f1\u6587\n\n\u5f85\u9047 :\u6bcf\u6708$10,000 - $13,000, \u6709\u96d9\u7ce7 \u53ca\u9280\u884c\u5047\u671f, \u661f\u671f\u4e00\u81f3\u4e94: \u4e0a\u53489\u6642\u81f3\u4e0b\u53486\u6642, \u6bcf\u9031\u5de5\u4f5c5\u5929\n\n\u7533\u8acb\u9808\u77e5 :\u6c42\u8077\u8005\u53ef\u81f4\u96fb24226849\u8207\u5bcc\u5229\u5065\u91dd\u7e54\u5ee0\u6709\u9650\u516c\u53f8\u5f35\u5c0f\u59d0\u806f\u7d61\u3002\n\n", "employment_types": ["Full Time"], "selling_points": [], "locations": ["Kwai Tsing Area"], "categories": ["Admin & HR", "Clerical / Admin Staff", "Others"], "post_time": "2022-01-17T07:02:21Z", "salary": {"currency": null, "max": null, "min": null, "period": "monthly", "term": null}, "salary_visible": false, "title_keywords": ["\u6587\u54e1"], "responsibilities": [], "requirements": {"degrees": [], "majors": [], "languages": [], "language_level": [], "hard_skills": [], "soft_skills": [], "languages_combined": []}, "experience_required": {"duration": [], "field": []}}, {"job_id": "100003009053549", "location_code": "hk", "company": "Leung & So", "job_title": "\u6587\u54e1", "description": "\n\u8077\u8cac :\u4e00\u822c\u6587\u54e1\u5de5\u4f5c, \u4e00\u822c\u6587\u66f8\u5de5\u4f5c\uff0c\u5305\u62ec\u6587\u4ef6\u5b58\u6a94\u3001\u8cc7\u6599\u8f38\u5165\u3001\u8907\u5370\u3001\u7de8\u5236\u5831\u544a\u7b49, \u8655\u7406\u7279\u6d3e\u5de5\u4f5c\n\n\u8cc7\u6b77 :\u4e2d\u516d\u7a0b\u5ea6; 1\u5e74\u7d93\u9a57; \u826f\u597d\u7cb5\u8a9e; \u4e00\u822c\u666e\u901a\u8a71; \u4e00\u822c\u82f1\u8a9e; \u61c2\u8b80\u5beb\u4e2d\u6587; \u61c2\u8b80\u5beb\u82f1\u6587; \u61c2MS Excel; \u6301\u6709LCC\u521d\u7d1a\u8b49\u66f8; \u61c2\u82f1\u6587\u6253\u5b57; \u61c2\u5009\u9821/\u901f\u6210\u8f38\u5165\u6cd5; \u5177\u6709\u57fa\u672c\u96fb\u8166\u64cd\u4f5c\u77e5\u8b58\n\n\u5f85\u9047 :\u6bcf\u6708$10,000 - $12,000, \u6709\u5e74\u504710\u5929 \u53ca\u9280\u884c\u5047\u671f, \u661f\u671f\u4e00\u81f3\u4e94: \u4e0a\u53488\u6642\u534a\u81f3\u4e0b\u53485\u6642\u534a, \u6bcf\u9031\u5de5\u4f5c5\u5929, \u6bcf\u5929\u5de5\u4f5c 8 \u5c0f\u6642\n\n\u7533\u8acb\u9808\u77e5 :\u6c42\u8077\u8005\u53ef\u96fb\u90f5(Apply Now)\u5c65\u6b77\u8868\u7d66\u6881\u8607\u6703\u8a08\u5e2b\u4e8b\u52d9\u6240\u3002\u5982\u8981\u7d22\u53d6\u6536\u96c6\u500b\u4eba\u8cc7\u6599\u8072\u660e, \u8acb\u8207\u66fe\u5c0f\u59d0(Email)\u806f\u7d61\u3002\n\n", "employment_types": ["Full Time"], "selling_points": [], "locations": ["Causeway Bay"], "categories": ["Admin & HR", "Clerical / Admin Staff", "Others"], "post_time": "2022-01-17T07:08:51Z", "salary": {"currency": null, "max": null, "min": null, "period": "monthly", "term": null}, "salary_visible": false, "title_keywords": ["\u6587\u54e1"], "responsibilities": [], "requirements": {"degrees": [], "majors": [], "languages": [], "language_level": [], "hard_skills": ["excel"], "soft_skills": [], "languages_combined": []}, "experience_required": {"duration": [], "field": []}}, {"job_id": "100003009053900", "location_code": "hk", "company": "i Logistics Company Limited", "job_title": "\u7269\u6d41\u6587\u54e1", "description": "\n\u8077\u8cac :\u4e00\u822c\u7269\u6d41\u6587\u4ef6\u8655\u7406\n\n\u8cc7\u6b77 :\u4e2d\u4e94\u7a0b\u5ea6; 2\u5e74\u7d93\u9a57; \u826f\u597d\u7cb5\u8a9e; \u4e00\u822c\u666e\u901a\u8a71; \u4e00\u822c\u82f1\u8a9e; \u61c2\u8b80\u5beb\u4e2d\u6587; \u7565\u61c2\u8b80\u5beb\u82f1\u6587; \u61c2Excel, Outlook\u512a\u5148\n\n\u5f85\u9047 :\u6bcf\u6708$12,000 - $14,000, \u6709\u96d9\u7ce7, \u661f\u671f\u4e00\u81f3\u4e94: \u4e0a\u53489\u6642\u81f3\u4e0b\u53486\u6642\u53ca\u661f\u671f\u516d: \u4e0a\u53489\u6642\u81f3\u4e0b\u53481\u6642, \u6bcf\u9031\u5de5\u4f5c5\u5929\u81f35\u5929\u534a, \u6bcf\u5929\u5de5\u4f5c 8 \u5c0f\u6642\n\n\u7533\u8acb\u9808\u77e5 :\u6c42\u8077\u8005\u53ef\u81f4\u96fb23227983\u8207I LOGISTICS COMPANY LIMITED\u6797\u5c0f\u59d0\u806f\u7d61\u3002\n\n", "employment_types": ["Full Time"], "selling_points": [], "locations": ["Yuen Long"], "categories": ["Admin & HR", "Clerical / Admin Staff", "Others"], "post_time": "2022-01-17T07:43:20Z", "salary": {"currency": null, "max": null, "min": null, "period": "monthly", "term": null}, "salary_visible": false, "title_keywords": [], "responsibilities": ["logistics"], "requirements": {"degrees": [], "majors": [], "languages": [], "language_level": [], "hard_skills": [], "soft_skills": [], "languages_combined": []}, "experience_required": {"duration": [], "field": []}}, {"job_id": "100003009053382", "location_code": "hk", "company": "Sharpwell Technology Ltd", "job_title": "\u8ddf\u55ae\u6587\u54e1**", "description": "\n\u8077\u8cac :\u8ca0\u8cac\u8ddf\u9032\u5ba2\u4eba\u8a02\u55ae\u53ca\u67e5\u8a62\n\n\u8cc7\u6b77 :\u4e2d\u4e94\u7a0b\u5ea6; 2\u5e746\u500b\u6708\u7d93\u9a57; \u826f\u597d\u7cb5\u8a9e; \u826f\u597d\u666e\u901a\u8a71; \u826f\u597d\u82f1\u8a9e; \u61c2\u8b80\u5beb\u4e2d\u6587; \u61c2\u8b80\u5beb\u82f1\u6587\n\n\u5f85\u9047 :\u6bcf\u6708$15,000, \u661f\u671f\u4e00\u81f3\u4e94: \u4e0a\u53489\u6642\u81f3\u4e0b\u53486\u6642\u53ca\u661f\u671f\u516d: \u4e0a\u53489\u6642\u81f3\u4e0b\u53481\u6642, \u6bcf\u9031\u5de5\u4f5c5\u5929\u534a\n\n\u7533\u8acb\u9808\u77e5 :\u6c42\u8077\u8005\u53ef\u96fb\u90f5(Apply Now)\u5c65\u6b77\u8868\u7d66\u6a19\u6e96\u79d1\u6280\u6709\u9650\u516c\u53f8\u3002\u5982\u8981\u7d22\u53d6\u6536\u96c6\u500b\u4eba\u8cc7\u6599\u8072\u660e, \u8acb\u8207\u5f35\u5c0f\u59d0(Email)\u806f\u7d61\u3002\n\n", "employment_types": ["Full Time"], "selling_points": [], "locations": ["Tsuen Wan Area"], "categories": ["Admin & HR", "Clerical / Admin Staff", "Others"], "post_time": "2022-01-17T06:53:49Z", "salary": {"currency": null, "max": null, "min": null, "period": "monthly", "term": null}, "salary_visible": false, "title_keywords": ["\u8ddf\u55ae\u6587\u54e1"], "responsibilities": [], "requirements": {"degrees": [], "majors": [], "languages": [], "language_level": [], "hard_skills": [], "soft_skills": [], "languages_combined": []}, "experience_required": {"duration": [], "field": []}}, {"job_id": "100003009053391", "location_code": "hk", "company": "Paus Architects Building Maintenance Consultants Limited", "job_title": "\u6703\u8a08/\u7c3f\u8a18\u6587\u54e1", "description": "\n\u8077\u8cac :\u4e00\u822c\u6703\u8a08/\u7c3f\u8a18\u6587\u54e1\u5de5\u4f5c, \u8ca0\u8cac\u6703\u8a08\u5165\u5e33, \u8655\u7406\u5e33\u76ee\u53ca\u6587\u66f8\u5de5\u4f5c\u3002\u6587\u4ef6\u6b78\u6a94\u3002\u8fa6\u5de5\u5ba4\u96dc\u52d9\u53ca\u5916\u52e4\u3002\u8655\u7406\u8fa6\u516c\u5ba4\u96dc\u52d9\u53ca\u5916\u52e4\u4e8b\u52d9\n\n\u8cc7\u6b77 :\u4e2d\u516d\u7a0b\u5ea6; 1\u5e74\u7d93\u9a57; \u826f\u597d\u7cb5\u8a9e; \u4e00\u822c\u82f1\u8a9e; \u61c2\u8b80\u5beb\u4e2d\u6587; \u61c2\u95b1\u8b80\u82f1\u6587; \u61c2Microsoft Office; \u61c2\u82f1\u6587\u6253\u5b57; \u61c2\u4e2d\u6587\u6253\u5b57; \u5177\u6709\u57fa\u672c\u96fb\u8166\u64cd\u4f5c\u77e5\u8b58\n\n\u5f85\u9047 :\u6bcf\u6708$11,000 - $12,000, \u6709\u8d85\u6642\u5de5\u4f5c\u6d25\u8cbc, \u96d9\u7ce7, \u5e74\u504710\u5929, \u9280\u884c\u5047\u671f \u53ca\u624b\u63d0\u96fb\u8a71\u6d25\u8cbc, \u661f\u671f\u4e00\u81f3\u4e94: \u4e0a\u53489\u6642\u534a\u81f3\u4e0b\u53486\u6642, \u6bcf\u9031\u5de5\u4f5c5\u5929\n\n\u7533\u8acb\u9808\u77e5 :\u6c42\u8077\u8005\u53ef\u96fb\u90f5(Apply Now)\u5c65\u6b77\u8868\u7d66\u9b91\u6c0f\u5efa\u7bc9\u5e2b\u6a13\u5b87\u7dad\u4fee\u9867\u554f\u6709\u9650\u516c\u53f8\u3002\u5982\u8981\u7d22\u53d6\u6536\u96c6\u500b\u4eba\u8cc7\u6599\u8072\u660e, \u8acb\u8207\u5289\u5c0f\u59d0(Email)\u806f\u7d61\u3002\n\n", "employment_types": ["Full Time"], "selling_points": [], "locations": ["Yau Tsim Mong Area"], "categories": ["Admin & HR", "Clerical / Admin Staff", "Others"], "post_time": "2022-01-17T06:54:55Z", "salary": {"currency": null, "max": null, "min": null, "period": "monthly", "term": null}, "salary_visible": false, "title_keywords": [], "responsibilities": [], "requirements": {"degrees": [], "majors": [], "languages": [], "language_level": [], "hard_skills": [], "soft_skills": [], "languages_combined": []}, "experience_required": {"duration": [], "field": []}}, {"job_id": "100003009053568", "location_code": "hk", "company": "IH Technology Limited", "job_title": "\u5009\u52d9\u6587\u54e1", "description": "\n\u8077\u8cac :\u4e00\u822c\u5009\u52d9\u6587\u54e1\u5de5\u4f5c, \u8ca0\u8cac\u65e5\u5e38\u6587\u66f8\u53ca\u5831\u8868\u5de5\u4f5c, \u8ddf\u9032\u51fa\u8ca8\u72c0\u6cc1\n\n\u8cc7\u6b77 :\u4e2d\u4e94\u7a0b\u5ea6; 1\u5e74\u7d93\u9a57; \u826f\u597d\u7cb5\u8a9e; \u4e00\u822c\u666e\u901a\u8a71; \u4e00\u822c\u82f1\u8a9e; \u61c2\u8b80\u5beb\u4e2d\u6587; \u61c2\u8b80\u5beb\u82f1\u6587; \u61c2MS Excel; \u5177\u6709\u57fa\u672c\u96fb\u8166\u64cd\u4f5c\u77e5\u8b58; \u5de5\u4f5c\u7368\u7acb, \u8655\u4e8b\u7d30\u5fc3, \u6709\u8cac\u4efb\u5fc3, \u9858\u610f\u5b78\u7fd2\n\n\u5f85\u9047 :\u6bcf\u6708$12,000 - $14,000, \u6709\u9280\u884c\u5047\u671f\u53ca\u5e74\u7d42\u734e\u91d1, \u661f\u671f\u4e00\u81f3\u4e94: \u4e0a\u53489\u6642\u81f3\u4e0b\u53486\u6642, \u6bcf\u9031\u5de5\u4f5c5\u5929\n\n\u7533\u8acb\u9808\u77e5 :\u6c42\u8077\u8005\u53ef\u96fb\u90f5(Apply Now)\u5c65\u6b77\u8868\u7d66\u82f1\u6d69\u79d1\u6280\u6709\u9650\u516c\u53f8\u3002\u5982\u8981\u7d22\u53d6\u6536\u96c6\u500b\u4eba\u8cc7\u6599\u8072\u660e, \u8acb\u8207\u912d\u5148\u751f(Email)\u806f\u7d61\u3002\n\n", "employment_types": ["Full Time"], "selling_points": [], "locations": ["Tsuen Wan Area"], "categories": ["Admin & HR", "Clerical / Admin Staff", "Others"], "post_time": "2022-01-17T07:10:26Z", "salary": {"currency": null, "max": null, "min": null, "period": "monthly", "term": null}, "salary_visible": false, "title_keywords": ["\u5009\u52d9\u6587\u54e1"], "responsibilities": [], "requirements": {"degrees": [], "majors": [], "languages": [], "language_level": [], "hard_skills": ["excel"], "soft_skills": [], "languages_combined": []}, "experience_required": {"duration": [], "field": []}}, {"job_id": "100003009053772", "location_code": "hk", "company": "Bee's International Group Limited", "job_title": "\u6703\u8a08\u6587\u54e1", "description": "\n\u8077\u8cac :\u8ca0\u8cac\u65e5\u5e38\u6703\u8a08\u5de5\u4f5c, \u5305\u62ec\u7531\u92b7\u552e\u81f3\u61c9\u6536\u5e33, \u63a1\u8cfc\u81f3\u61c9\u4ed8\u5e33, \u9280\u884c\u5c0d\u5e33, \u5b9a\u671f\u5831\u544a, \u8cc7\u6599\u8f38\u5165, \u6587\u4ef6\u5b58\u6a94, \u5354\u52a9\u6708\u7d50\u7b49 (With OT Meal Allowance, OT Travel Allowance, Free Books & Movies)\n\n\u8cc7\u6b77 :\u5c08\u4e0a\u6559\u80b2\uff1a\u6587\u6191/\u8b49\u66f8; \u826f\u597d\u7cb5\u8a9e; \u4e00\u822c\u82f1\u8a9e; \u7565\u61c2\u8b80\u5beb\u4e2d\u6587; \u61c2\u8b80\u5beb\u82f1\u6587; \u61c2MYOB; \u61c2MS Excel; \u5177\u6709\u4e00\u822c\u6703\u8a08\u77e5\u8b58\n\n\u5f85\u9047 :\u6bcf\u6708$12,000 - $16,000, \u6709\u5e74\u504710\u5929, \u914c\u60c5\u6027\u82b1\u7d05, \u751f\u65e5\u50472\u5929, \u9280\u884c\u5047\u671f, \u65c5\u904a\u734e\u8cde, \u5a5a\u50475\u5929, \u661f\u671f\u4e00\u81f3\u4e94: \u4e0a\u53489\u6642\u81f3\u4e0b\u53486\u6642, \u6bcf\u9031\u5de5\u4f5c5\u5929, Flexible lunch hours, occasional OT required\n\n\u7533\u8acb\u9808\u77e5 :\u6c42\u8077\u8005\u53ef\u96fb\u90f5(Apply Now)\u5c65\u6b77\u8868\u7d66THE BEES HOLDINGS LIMITED\u3002\u5982\u8981\u7d22\u53d6\u6536\u96c6\u500b\u4eba\u8cc7\u6599\u8072\u660e, \u8acb\u8207\u9ec3 \u5148\u751f(Email)\u806f\u7d61\u3002\n\n", "employment_types": ["Full Time"], "selling_points": [], "locations": ["Quarry Bay"], "categories": ["Admin & HR", "Clerical / Admin Staff", "Others"], "post_time": "2022-01-17T07:30:09Z", "salary": {"currency": null, "max": null, "min": null, "period": "monthly", "term": null}, "salary_visible": false, "title_keywords": [], "responsibilities": [], "requirements": {"degrees": [], "majors": [], "languages": [], "language_level": [], "hard_skills": ["excel"], "soft_skills": ["flexible"], "languages_combined": []}, "experience_required": {"duration": [], "field": []}}, {"job_id": "100003009052878", "location_code": "hk", "company": "Spidernet Recruitment Services", "job_title": "Office/Pantry Assistant \u8fa6\u516c\u5ba4 / \u8336\u6c34\u9593\u52a9\u7406", "description": "\u8fa6\u516c\u5ba4/\u8336\u6c34\u9593\u52a9\u7406\n\n\n\u4e3b\u8981\u8077\u8cac:\n\n\u8ca0\u8cac\u8fa6\u516c\u5ba4\u8336\u6c34\u670d\u52d9\u5de5\u4f5c, \u516c\u53f8\u7528\u81b3\u6642\u5b89\u6392\u9910\u5177\u9001\u9910\n\u64d4\u4efb\u5916\u52e4\u5de5\u4f5c,\u00a0\u5982\u5230\u9280\u884c\u3001\u90f5\u5c40\u8207\u5916\u51fa\u6536\u767c\u6587\u4ef6\n\u4fdd\u6301\u6703\u8b70\u5ba4\u53ca\u8336\u6c34\u9593\u6574\u6f54, \u8ca0\u8cac\u8336\u6c34\u9593\u7269\u8cc7\u53ca\u8fa6\u516c\u5ba4\u6587\u5177\u88dc\u7d66\n\u652f\u63f4\u884c\u653f\u4e8b\u52d9, \u5305\u62ec\u5f71\u5370\u3001\u50b3\u771f\u53ca\u5354\u52a9\u5176\u4ed6\u8fa6\u516c\u5ba4\u96dc\u52d9\n\n\u8981\u6c42:\n\n\u4e2d\u4e09\u6216\u4ee5\u4e0a\u7a0b\u5ea6\n2-3\u5e74\u76f8\u95dc\u5de5\u4f5c\u7d93\u9a57\n\u826f\u597d\u7cb5\u8a9e\u3001\u00a0\u7c21\u55ae\u666e\u901a\u8a71\u53ca\u7c21\u55ae\u82f1\u8a9e\u6e9d\u901a\n\u6709\u8cac\u4efb\u611f\u3001\u71b1\u8aa0\u6709\u79ae\u53ca\u5177\u826f\u597d\u6e9d\u901a\u6280\u5de7\n\n\u6709\u610f\u8005\u8acb\u9644\u5c65\u6b77\uff0c\u6309Apply Now\u00a0\u9375\u4ee5\u96fb\u90f5\u7533\u8acb\u00a0 \u00a0\u6216\u50b3\u771f\u52302155 1068\u00a0", "employment_types": ["Full Time", "Permanent"], "selling_points": ["2-3yrs Office Assistant / Tea Serving experience", "Outdoor work, Large company experience", "OA, Pantry Assistant, Wanchi"], "locations": ["Wan Chai"], "categories": ["Admin & HR", "Clerical / Admin Staff", "Others", "Others", "Others"], "post_time": "2022-01-17T04:23:41Z", "salary": {"currency": null, "max": null, "min": null, "period": "monthly", "term": null}, "salary_visible": false, "title_keywords": ["assistant"], "responsibilities": [], "requirements": {"degrees": [], "majors": [], "languages": [], "language_level": [], "hard_skills": [], "soft_skills": [], "languages_combined": []}, "experience_required": {"duration": [], "field": []}}, {"job_id": "100003009053767", "location_code": "hk", "company": "Hing Sing Engineering Limited", "job_title": "\u6587\u54e1", "description": "\n\u8077\u8cac :\u8655\u7406\u4e00\u822c\u6587\u8077\u5de5\u4f5c\n\n\u8cc7\u6b77 :\u5c08\u4e0a\u6559\u80b2\uff1a\u6587\u6191/\u8b49\u66f8; 2\u5e74\u7d93\u9a57; \u826f\u597d\u7cb5\u8a9e; \u4e00\u822c\u666e\u901a\u8a71; \u4e00\u822c\u82f1\u8a9e; \u7565\u61c2\u8b80\u5beb\u4e2d\u6587; \u7565\u61c2\u8b80\u5beb\u82f1\u6587\n\n\u5f85\u9047 :\u6bcf\u6708$13,000 - $17,000, \u6709\u8d85\u6642\u5de5\u4f5c\u6d25\u8cbc \u53ca\u914c\u60c5\u6027\u82b1\u7d05, \u661f\u671f\u4e00\u81f3\u516d: \u4e0a\u53489\u6642\u81f3\u4e0b\u53486\u6642, \u6bcf\u9031\u5de5\u4f5c6\u5929, \u6bcf\u5929\u5de5\u4f5c 9 \u5c0f\u6642\n\n\u7533\u8acb\u9808\u77e5 :\u6c42\u8077\u8005\u53ef\u81f4\u96fb96870595\u8207\u5144\u8aa0\u5de5\u7a0b\u6709\u9650\u516c\u53f8\u674e\u5148\u751f\u806f\u7d61\u3002\n\n", "employment_types": ["Full Time"], "selling_points": [], "locations": ["Kwai Tsing Area"], "categories": ["Admin & HR", "Clerical / Admin Staff", "Others"], "post_time": "2022-01-17T07:29:15Z", "salary": {"currency": null, "max": null, "min": null, "period": "monthly", "term": null}, "salary_visible": false, "title_keywords": ["\u6587\u54e1"], "responsibilities": [], "requirements": {"degrees": [], "majors": [], "languages": [], "language_level": [], "hard_skills": [], "soft_skills": [], "languages_combined": []}, "experience_required": {"duration": [], "field": []}}, {"job_id": "100003009053637", "location_code": "hk", "company": "Bare Limited", "job_title": "Trainee \u7f8e\u5bb9\u5b78\u5f99 / \u521d\u7d1a\u7f8e\u5bb9\u5e2b", "description": "\n\u5168\u884c\u6700\u9ad8\u4f63\u91d1\n\u5718\u968a\u734e\u91d1\u3001\u4ecb\u7d39\u4eba\u734e\u91d1\n\u534a\u5e74\u5305\u85aa $17k\n\u6bcf\u6708\u5e73\u5747 7-8 \u5929\u6709\u85aa\u4f8b\u5047\n\u9022\u661f\u671f\u65e5\u4f11\u606f\uff0c\u53ef\u8207\u661f\u671f\u65e5\u3001\u4e00\u53ca\u4e8c\u9023\u653e\u4e09\u5929\n\u6c23\u6c1b\u878d\u6d3d\u7121\u9b25\u722d\n\u6bcf\u6708\u76e1\u4eab\u514d\u8cbb\u7642\u7a0b\n\u54e1\u5de5\u7642\u7a0b\u512a\u60e0\n\u00a0 \u8077\u8cac\uff1a\n\u2022 \u5354\u52a9\u904b\u4f5c\u7f8e\u5bb9\u9662\u65e5\u5e38\u5de5\u4f5c\n\u2022 \u5411\u5ba2\u4eba\u63d0\u4f9b\u512a\u8cea\u5c08\u696d\u7f8e\u5bb9\u670d\u52d9\n\u2022 \u70ba\u5ba2\u6236\u9032\u884c\u7f8e\u5bb9\u53ca\u6fc0\u5149\u7642\u7a0b\n\u2022 \u8ddf\u9032\u5ba2\u4eba\u7642\u7a0b\u53ca\u552e\u5f8c\u670d\u52d9\n\u2022 \u8207\u5ba2\u4eba\u5efa\u7acb\u826f\u597d\u95dc\u4fc2\n\n\u8981\u6c42\uff1a\n\u2022 \u6d41\u5229\u5ee3\u6771\u8a71\n\u2022 \u6c92\u6709\u76f8\u95dc\u7f8e\u5bb9\u7d93\u9a57\u4ea6\u53ef\n\u2022 \u6301\u8a8d\u53ef\u5c08\u696d\u7f8e\u5bb9\u6587\u6191\u6216\u8b49\u66f8\u8005\u512a\u5148\n\u2022 \u7a4d\u6975\u4e3b\u52d5\n\u2022 \u601d\u60f3\u6b63\u9762\u3001\u5bcc\u8cac\u4efb\u611f\u3001\u670d\u52d9\u614b\u5ea6\u53cb\u5584\u3001\u6027\u683c\u958b\u6717\n\u2022 \u5c0d\u7f8e\u5bb9\u884c\u696d\u6709\u71b1\u8aa0\n\n\u524d\u7dda\u54e1\u5de5\u798f\u5229\ufe30\n\u2022 \u6bcf\u5929\u5de5\u4f5c9\u5c0f\u6642\n\u2022 \u661f\u671f\u516d\u53ca\u516c\u773e\u5047\u671f\u5747\u53ef\u65e9\u6536\n\u2022 \u7bc0\u65e5\u65e9\u653e\n\u2022 \u63d0\u4f9b\u5a5a\u5047\u3001\u751f\u65e5\u5047\u3001\u6069\u6064\u5047\n\u2022 \u52a0\u73ed\u88dc\u9418\n\u2022 \u5c08\u696d\u514d\u8cbb\u5728\u8077\u57f9\u8a13\n\u2022 \u7279\u5feb\u6649\u5347\u6a5f\u6703\n\u2022 \u8cfc\u7269\u512a\u60e0\u53ca\u514d\u8cbb\u7642\u7a0b\n\u2022 \u5bb6\u5c6c\u597d\u53cb\u6298\u6263\u512a\u60e0\n\u00a0 \u5de5\u4f5c\u5730\u9ede\ufe30\u65fa\u89d2 / \u9285\u947c\u7063 / \u89c0\u5858\n\n", "employment_types": ["Full Time"], "selling_points": [], "locations": ["Kwun Tong"], "categories": ["Admin & HR", "Others", "Sales, CS & Business Devpt", "Business Development", "Others"], "post_time": "2022-01-17T07:16:33Z", "salary": {"currency": null, "max": null, "min": null, "period": "monthly", "term": null}, "salary_visible": false, "title_keywords": ["trainee"], "responsibilities": [], "requirements": {"degrees": [], "majors": [], "languages": [], "language_level": [], "hard_skills": [], "soft_skills": [], "languages_combined": []}, "experience_required": {"duration": [], "field": []}}, {"job_id": "100003009053587", "location_code": "hk", "company": "Pal Line Industrial Company Limited", "job_title": "\u6587\u54e1", "description": "\n\u8077\u8cac :\u4e00\u822c\u6587\u54e1\u5de5\u4f5c, \u5354\u52a9\u8ddf\u55ae\n\n\u8cc7\u6b77 :\u4e2d\u516d\u7a0b\u5ea6; \u826f\u597d\u7cb5\u8a9e; \u4e00\u822c\u666e\u901a\u8a71; \u4e00\u822c\u82f1\u8a9e\u512a\u5148; \u61c2\u8b80\u5beb\u4e2d\u6587; \u61c2\u8b80\u5beb\u82f1\u6587; \u61c2MS Outlook; \u61c2MS Excel; \u61c2\u4e2d\u6587\u6253\u5b57 20 \u5b57(\u6bcf\u5206\u9418); \u5de5\u4f5c\u52e4\u596e, \u9858\u610f\u5b78\u7fd2\u65b0\u4e8b\u7269\n\n\u5f85\u9047 :\u6bcf\u6708$11,000 - $13,000, \u6709\u96d9\u7ce7, \u9280\u884c\u5047\u671f\u53ca\u5e74\u7d42\u734e\u91d1, \u661f\u671f\u4e00\u81f3\u4e94: \u4e0a\u53488\u664245\u5206\u81f3\u4e0b\u53486\u6642, \u6bcf\u9031\u5de5\u4f5c5\u5929\n\n\u7533\u8acb\u9808\u77e5 :\u6c42\u8077\u8005\u53ef\u96fb\u90f5(Apply Now)\u5c65\u6b77\u8868\u7d66\u532f\u9032\u5be6\u696d\u767c\u5c55\u6709\u9650\u516c\u53f8\u3002\u5982\u8981\u7d22\u53d6\u6536\u96c6\u500b\u4eba\u8cc7\u6599\u8072\u660e, \u8acb\u8207\u912d\u5c0f\u59d0(Email)\u806f\u7d61\u3002\n\n", "employment_types": ["Full Time"], "selling_points": [], "locations": ["Hung Hom"], "categories": ["Admin & HR", "Clerical / Admin Staff", "Others"], "post_time": "2022-01-17T07:12:31Z", "salary": {"currency": null, "max": null, "min": null, "period": "monthly", "term": null}, "salary_visible": false, "title_keywords": ["\u6587\u54e1"], "responsibilities": [], "requirements": {"degrees": [], "majors": [], "languages": [], "language_level": [], "hard_skills": ["excel", "outlook"], "soft_skills": [], "languages_combined": []}, "experience_required": {"duration": [], "field": []}}, {"job_id": "100003009053671", "location_code": "hk", "company": "Prism Consultancy Company Limited", "job_title": "\u884c\u653f\u6587\u54e1", "description": "\n\u8077\u8cac :\u63a5\u807d\u548c\u76f4\u64a5\u96fb\u8a71;\u8207\u5ba2\u6236\u3001\u54e1\u5de5\u548c\u5176\u4ed6\u4eba\u6e9d\u901a\u4ee5\u56de\u7b54\u554f\u984c\u3001\u8655\u7406\u6295\u8a34\u3001\u89e3\u91cb\u4fe1\u606f\u548c\u63a5\u53d7\u8a02\u55ae;\u64cd\u4f5c\u8fa6\u516c\u6a5f\u5668\uff0c\u5305\u62ec\u8907\u5370\u6a5f\u3001\u6383\u63cf\u5100\u3001\u96fb\u8a71\u548c\u8a9e\u97f3\u90f5\u4ef6\u7cfb\u7d71\u4ee5\u53ca\u8a08\u7b97\u6a5f;\u7dad\u8b77\u7528\u65bc\u6b78\u6a94\u3001\u5eab\u5b58\u3001\u90f5\u5bc4\u548c\u6578\u64da\u5eab\u7684\u66f4\u65b0\u7cfb\u7d71;\u8655\u7406\u9032\u51fa\u8fa6\u516c\u5ba4\u4fe1\u4ef6\n\n\u8cc7\u6b77 :\u4e2d\u4e03\u7a0b\u5ea6; 1\u5e74\u7d93\u9a57; \u826f\u597d\u7cb5\u8a9e; \u4e00\u822c\u666e\u901a\u8a71; \u4e00\u822c\u82f1\u8a9e; \u61c2\u8b80\u5beb\u4e2d\u6587; \u61c2\u8b80\u5beb\u82f1\u6587; \u5b8c\u6210\u5546\u79d1\u8a13\u7df4; \u5177\u6709\u57fa\u672c\u96fb\u8166\u64cd\u4f5c\u77e5\u8b58\n\n\u5f85\u9047 :\u6bcf\u6708$12,000 - $14,000, \u661f\u671f\u4e00\u81f3\u4e94: \u4e0a\u53489\u6642\u81f3\u4e0b\u53486\u6642, \u6bcf\u9031\u5de5\u4f5c5\u5929, \u6bcf\u5929\u5de5\u4f5c 8 \u5c0f\u6642\n\n\u7533\u8acb\u9808\u77e5 :\u6c42\u8077\u8005\u53ef\u96fb\u90f5(Apply Now)\u5c65\u6b77\u8868\u7d66\u7ff9\u6a02\u9867\u554f\u6709\u9650\u516c\u53f8\u3002\u5982\u8981\u7d22\u53d6\u6536\u96c6\u500b\u4eba\u8cc7\u6599\u8072\u660e, \u8acb\u8207\u6797\u5c0f\u59d0(34645222)\u806f\u7d61\u3002\n\n", "employment_types": ["Full Time"], "selling_points": [], "locations": ["Wan Chai"], "categories": ["Admin & HR", "Clerical / Admin Staff", "Others"], "post_time": "2022-01-17T07:19:24Z", "salary": {"currency": null, "max": null, "min": null, "period": "monthly", "term": null}, "salary_visible": false, "title_keywords": [], "responsibilities": [], "requirements": {"degrees": [], "majors": [], "languages": [], "language_level": [], "hard_skills": [], "soft_skills": [], "languages_combined": []}, "experience_required": {"duration": [], "field": []}}, {"job_id": "100003009053473", "location_code": "hk", "company": "Metro Property Management Limited", "job_title": "\u9ad8\u7d1a\u7269\u696d\u52a9\u7406 / Senior Property Assistant", "description": "Responsibilities\n\nTo Handle the public complaints, queries, requests, claims, attending neighborhood meetings & any other public concerned issues in connection with the project works;\nCommunicate and liaise with the local community and District Council members.\n\nRequirements\n\nDegree holder in Communications / Public Relations or equivalent;\nAt least 4 years of hands-on experience in public affairs, community relations, complaint handling, corporate communications and crisis management;\u00a0\nExperience in releasing press materials and handling general public enquiries;\nProficiency in English and Chinese (both Cantonese and Putonghua);\nExcellent interpersonal and communications skills;\nWell versed in MS office applications (e.g. Word, Excel, PowerPoint and Chinese word processing); and\nWilling to work at construction site office.\n\nWe offer competitive package and attractive employee benefits including 5-day work\u00a0/ 5.5-day work (2 ex-gratia Sat-off per month),\u00a0ex-gratia rest day, birthday holiday, All-in-One Flexible Benefit Plan,\u00a0training sponsorship and discretionary bonus.\n\nApplication with full resume, current and expected salary, and available date should be sent through email to\u00a0The Human Resources Manager,\u00a0quoting the appropriate reference number via email to\u00a0hr @chunwo.com\u00a0write to\u00a05C, Hong Kong Spinners Industrial Building, 601-603 Tai Nan West Street, Cheung Sha Wan, Kowloon, Hong Kong. \u00a0\n\nFor more information, please visit our website at www.chunwo.com.\nPersonal data provided by job applicants would be used for recruitment purposes only.", "employment_types": ["Full Time"], "selling_points": [], "locations": ["Causeway Bay"], "categories": ["Admin & HR", "Others", "Medical Services", "Others"], "post_time": "2022-01-17T07:01:52Z", "salary": {"currency": null, "max": null, "min": null, "period": "monthly", "term": null}, "salary_visible": false, "title_keywords": ["property assistant"], "responsibilities": ["liaise with"], "requirements": {"degrees": ["degree holder"], "majors": ["communications"], "languages": ["cantonese", "putonghua", "english", "chinese"], "language_level": ["proficiency"], "hard_skills": ["excel", "chinese word processing", "word", "powerpoint", "ms office"], "soft_skills": ["hands-on", "interpersonal"], "languages_combined": [{"language": "cantonese", "language_level": []}, {"language": "putonghua", "language_level": []}, {"language": "english", "language_level": ["proficiency"]}, {"language": "chinese", "language_level": ["proficiency"]}]}, "experience_required": {"duration": ["at least 4 years"], "field": ["management"]}}, {"job_id": "100003009053747", "location_code": "hk", "company": "Top Conqueror Limited", "job_title": "\u8ddf\u55ae\u6587\u54e1", "description": "\n\u8077\u8cac :\u4e00\u822c\u63a1\u8cfc\u54e1/\u8ddf\u55ae\u54e1\u5de5\u4f5c, \u9593\u4e2d\u9700\u5f80\u570b\u5167\u5de5\u4f5c\n\n\u8cc7\u6b77 :\u4e2d\u4e94\u7a0b\u5ea6; 5\u5e74\u7d93\u9a57; \u826f\u597d\u7cb5\u8a9e; \u4e00\u822c\u666e\u901a\u8a71; \u4e00\u822c\u82f1\u8a9e; \u61c2\u8b80\u5beb\u4e2d\u6587; \u61c2\u8b80\u5beb\u82f1\u6587; \u5177\u6709\u57fa\u672c\u96fb\u8166\u64cd\u4f5c\u77e5\u8b58; \u5c0d\u68b3\u7e54\u6210\u8863\u719f\u8b58, \u51775\u5e74\u6210\u8863\u8ddf\u55ae\u7d93\u9a57\n\n\u5f85\u9047 :\u6bcf\u6708$13,000 - $13,500, \u6709\u4f9b\u81b3\u98df, \u661f\u671f\u4e00\u81f3\u4e94: \u4e0a\u53489\u6642\u81f3\u4e0b\u53486\u6642, \u6bcf\u9031\u5de5\u4f5c5\u5929, \u6bcf\u5929\u5de5\u4f5c 8 - 9 \u5c0f\u6642, \u9593\u4e2d\u9700\u8d85\u6642\u5de5\u4f5c\n\n\u7533\u8acb\u9808\u77e5 :\u6c42\u8077\u8005\u53ef\u96fb\u90f5(Apply Now)\u5c65\u6b77\u8868\u7d66\u4e0a\u5ee3\u6709\u9650\u516c\u53f8\u3002\u5982\u8981\u7d22\u53d6\u6536\u96c6\u500b\u4eba\u8cc7\u6599\u8072\u660e, \u8acb\u8207\u738b\u5c0f\u59d0(Email)\u806f\u7d61\u3002\n\n", "employment_types": ["Full Time"], "selling_points": [], "locations": ["Wong Tai Sin Area"], "categories": ["Admin & HR", "Clerical / Admin Staff", "Others"], "post_time": "2022-01-17T07:27:09Z", "salary": {"currency": null, "max": null, "min": null, "period": "monthly", "term": null}, "salary_visible": false, "title_keywords": ["\u8ddf\u55ae\u6587\u54e1"], "responsibilities": [], "requirements": {"degrees": [], "majors": [], "languages": [], "language_level": [], "hard_skills": [], "soft_skills": [], "languages_combined": []}, "experience_required": {"duration": [], "field": []}}, {"job_id": "100003009052301", "location_code": "hk", "company": "Hong Kong World Star Technology Limited", "job_title": "General Clerk \uff08Full time / Part time)", "description": "Requirements:\n\nForm 5 or above, one year relevant experience in office administration duties\nGood interpersonal skills, telephone manner and communication skills\nGood computer skills including Microsoft Word, Excel and PowerPoint, knowledge of Chinese Word Processing would be an advantage\nGood Chinese and English\nResponsibilities:\n\nPrepare general clerical duties including filing, sorting, data entry\nProvide administrative and clerical support\nAssist with ad hoc projects\nPerform other duties as assigned", "employment_types": ["Full Time", "Part Time"], "selling_points": ["5 Days Work Week", "Form 5 or above", "1yr relevant exp in office administration duties"], "locations": ["Wan Chai"], "categories": ["Admin & HR", "Clerical / Admin Staff", "Receptionist", "Others"], "post_time": "2022-01-17T04:15:45Z", "salary": {"currency": null, "max": null, "min": null, "period": "monthly", "term": null}, "salary_visible": false, "title_keywords": ["general clerk"], "responsibilities": ["perform other duties", "ad hoc projects", "administrative and clerical support", "data entry"], "requirements": {"degrees": ["form 5 or above"], "majors": [], "languages": ["english", "chinese"], "language_level": ["advantage", "good"], "hard_skills": ["excel", "microsoft word", "chinese word processing", "powerpoint", "computer skills"], "soft_skills": ["communication skills", "interpersonal skills", "telephone manner"], "languages_combined": [{"language": "english", "language_level": ["good"]}, {"language": "chinese", "language_level": ["advantage", "good", "good"]}]}, "experience_required": {"duration": ["one year"], "field": ["office administration", "relevant experience"]}}, {"job_id": "100003009053658", "location_code": "hk", "company": "United Asia Finance Limited", "job_title": "Officer, Administration and Facilities Management", "description": "Job Responsibilities:\n\nResponsible for managing Repair and Maintenance (R&M) works such as E&M facilities, water supply & drainage, signage & lightboxes, fire services equipment of headquarter and all branch offices.\nHandle renovation projects, ad hoc tasks as assigned and FM related procurement works.\nResponsible for renovation projects including liaison with contractor on design and build proposal, coordination on selection of renovation materials, tender opening, and preparation of quotation analysis\nManage various procurement related tasks assigned by supervisor such as procurement of branch staff uniform, marketing premium, software license renewal, different kinds of services etc.\n\nJob Requirements:\n\nHigher Diploma/ Associate Degree holder in Facilities Management / Property Management / Business Administration or equivalent\n2-3 year experience in office admin / facilities management services.\nAbility to deal with different levels of external business partners / contractors\nAbility to work independently and able to work under pressure\nHave knowledge of central procurement will be an advantage\nGood command of spoken English, Cantonese and Putonghua a plus\n\nWe offer attractive remuneration package which includes double pay and discretionary bonus. Interested parties please send your CV indicating your current salary, expected salary and availability to HR Department, by email via \"Apply Now\"\n\n(Personal data collected will be treated in the strictest confidence and will be handled by authorized personnel for recruitment-related purposes only. Applicants who do not hear from us within 3 months may consider their application unsuccessful and their data will be destroyed within 24 months of receipt.)\n", "employment_types": ["Full Time", "Permanent"], "selling_points": ["Responsible for renovation projects", "Higher Diploma/ Associate Degree holder", "2-3 year experience in office admin / facilities"], "locations": ["Not Specified"], "categories": ["Admin & HR", "Clerical / Admin Staff", "Others", "Property / Real Estate", "Property Management"], "post_time": "2022-01-17T07:18:21Z", "salary": {"currency": null, "max": null, "min": null, "period": "monthly", "term": null}, "salary_visible": false, "title_keywords": ["officer"], "responsibilities": ["software", "maintenance", "analysis", "renovation", "ad hoc tasks", "quotation", "design", "repair", "coordination", "tender"], "requirements": {"degrees": ["associate degree", "diploma"], "majors": ["business administration"], "languages": ["cantonese", "putonghua", "english"], "language_level": ["good command"], "hard_skills": ["facilities management", "plus"], "soft_skills": ["work independently", "work under pressure"], "languages_combined": [{"language": "cantonese", "language_level": ["good command"]}, {"language": "putonghua", "language_level": ["good command"]}, {"language": "english", "language_level": ["good command"]}]}, "experience_required": {"duration": ["2-3 year"], "field": ["management", "admin"]}}, {"job_id": "100003009053777", "location_code": "hk", "company": "Life Extension Company Limited", "job_title": "\u517c\u8077\u884c\u653f\u52a9\u7406", "description": "\n\u8077\u8cac :Responsible for data entry; Filing documents; Handle other ad hoc assignments as needed\n\n\u8cc7\u6b77 :\u5c08\u4e0a\u6559\u80b2\uff1a\u526f\u5b78\u4f4d; \u826f\u597d\u7cb5\u8a9e\u512a\u5148; \u826f\u597d\u82f1\u8a9e\u512a\u5148; \u61c2\u8b80\u5beb\u4e2d\u6587; \u61c2\u8b80\u5beb\u82f1\u6587; \u61c2MS Word; \u61c2MS Outlook; \u61c2MS Excel; \u61c2\u82f1\u6587\u6253\u5b57; \u61c2\u5009\u9821/\u901f\u6210\u8f38\u5165\u6cd5; \u6ce8\u91cd\u7d30\u7bc0, \u6e96\u78ba\u5730\u8f38\u5165\u8cc7\u6599, \u826f\u597d\u6e9d\u901a\u6280\u5de7, \u80fd\u7368\u7acb\u5de5\u4f5c, \u6709\u8cac\u4efb\u611f, \u5de5\u4f5c\u4e3b\u52d5; \u6709\u5ba2\u6236\u670d\u52d9\u7d93\u9a57\u512a\u5148\n\n\u5f85\u9047 :\u6bcf\u5c0f\u6642$55.00 - $65.00, \u661f\u671f\u4e00,\u4e09,\u4e94: \u4e0a\u53489\u6642\u81f3\u4e0b\u53486\u6642\u534a, \u6bcf\u9031\u5de5\u4f5c3\u5929, \u6bcf\u5929\u5de5\u4f5c 4 - 5 \u5c0f\u6642\n\n\u7533\u8acb\u9808\u77e5 :\u6c42\u8077\u8005\u53ef\u96fb\u90f5(Apply Now)\u5c65\u6b77\u8868\u7d66\u5ef6\u5e74\u9999\u6e2f\u6709\u9650\u516c\u53f8\u3002\u5982\u8981\u7d22\u53d6\u6536\u96c6\u500b\u4eba\u8cc7\u6599\u8072\u660e, \u8acb\u8207\u9ec3\u5c0f\u59d0(Email)\u806f\u7d61\u3002\n\n", "employment_types": ["Part Time"], "selling_points": [], "locations": ["Mong Kok"], "categories": ["Admin & HR", "Clerical / Admin Staff", "Others", "Others", "Others"], "post_time": "2022-01-17T07:30:50Z", "salary": {"currency": null, "max": null, "min": null, "period": "hourly", "term": null}, "salary_visible": false, "title_keywords": [], "responsibilities": ["ad hoc assignments", "data entry"], "requirements": {"degrees": [], "majors": [], "languages": [], "language_level": [], "hard_skills": ["excel", "outlook", "word"], "soft_skills": ["responsible"], "languages_combined": []}, "experience_required": {"duration": [], "field": []}}, {"job_id": "100003009053631", "location_code": "hk", "company": "Prudence Engineering Limited", "job_title": "\u6703\u8a08\u6587\u54e1", "description": "\n\u8077\u8cac :\u8655\u7406\u61c9\u4ed8\u53ca\u61c9\u6536\u8cec\uff1b\u4e00\u822c\u6587\u66f8\u5de5\u4f5c\uff1b\u8655\u7406\u4e00\u822c\u6703\u8a08\u96dc\u9805\n\n\u8cc7\u6b77 :\u5c08\u4e0a\u6559\u80b2\uff1a\u6587\u6191/\u8b49\u66f8; 2\u5e74\u7d93\u9a57; \u826f\u597d\u7cb5\u8a9e\u512a\u5148; \u4e00\u822c\u82f1\u8a9e\u512a\u5148; \u61c2\u8b80\u5beb\u4e2d\u6587; \u61c2\u8b80\u5beb\u82f1\u6587; \u61c2\u96fb\u8166\u6587\u66f8\u8655\u7406; \u6301\u6709LCC\u521d\u7d1a\u8b49\u66f8; \u5177\u6709\u57fa\u672c\u96fb\u8166\u64cd\u4f5c\u77e5\u8b58; \u7565\u61c2\u6703\u8a08\u8cec\u76ee, \u9858\u610f\u670d\u5f9e\u4e0a\u53f8\u6307\u5c0e\u3001\u6709\u8010\u6027\u3001\u6709\u8cac\u4efb\u611f\uff0c\u7565\u61c2\u6703\u8a08\u7cfb\u7d71(MYOB), \u51772\u5e74\u6216\u4ee5\u4e0a\u76f8\u95dc\u5de5\u4f5c\u7d93\u9a57\n\n\u5f85\u9047 :\u6bcf\u6708$15,000 - $18,000, \u6709\u9280\u884c\u5047\u671f, \u751f\u65e5\u50471\u5929 \u53ca\u8a66\u7528\u671f\u5f8c\u6bcf\u5e74\u751f\u65e5\u5229\u662f$1000, \u661f\u671f\u4e00\u81f3\u4e94: \u4e0a\u53489\u6642\u81f3\u4e0b\u53486\u6642, \u6bcf\u9031\u5de5\u4f5c5\u5929, \u6bcf\u5929\u5de5\u4f5c 9 \u5c0f\u6642\n\n\u7533\u8acb\u9808\u77e5 :\u6c42\u8077\u8005\u53ef\u96fb\u90f5(Apply Now)\u5c65\u6b77\u8868\u7d66\u8c9d\u767b\u5de5\u7a0b\u6709\u9650\u516c\u53f8\u3002\u5982\u8981\u7d22\u53d6\u6536\u96c6\u500b\u4eba\u8cc7\u6599\u8072\u660e, \u8acb\u8207\u5f35\u5148\u751f(Email)\u806f\u7d61\u3002\n\n", "employment_types": ["Full Time"], "selling_points": [], "locations": ["Tsuen Wan Area"], "categories": ["Admin & HR", "Clerical / Admin Staff", "Others"], "post_time": "2022-01-17T07:16:07Z", "salary": {"currency": null, "max": null, "min": null, "period": "monthly", "term": null}, "salary_visible": false, "title_keywords": [], "responsibilities": [], "requirements": {"degrees": [], "majors": [], "languages": [], "language_level": [], "hard_skills": [], "soft_skills": [], "languages_combined": []}, "experience_required": {"duration": [], "field": []}}, {"job_id": "100003009053760", "location_code": "hk", "company": "Thousand Leaves Corporation Limited", "job_title": "\u6587\u54e1", "description": "\n\u8077\u8cac :\u4e00\u822c\u6587\u54e1\u5de5\u4f5c, \u4e00\u822c\u6587\u8077\u5de5\u4f5c\uff0c\u5e6b\u52a9\u4e0a\u53f8\u8655\u7406\u71df\u904b\u696d\u52d9;\u64cd\u4f5c\u96fb\u8166\u7cfb\u7d71\u8655\u7406\u53ca\u8ddf\u9032\u8a02\u55ae,\u5305\u88dd\u53ca\u51fa\u4ef6;\u6574\u7406\u5b58\u5009;\u7c21\u55ae\u96fb\u8166\u64cd\u4f5c(Excel, Word)\n\n\u8cc7\u6b77 :\u4e2d\u4e94\u7a0b\u5ea6; 2\u5e74\u7d93\u9a57; \u826f\u597d\u7cb5\u8a9e; \u4e00\u822c\u666e\u901a\u8a71; \u4e00\u822c\u82f1\u8a9e; \u61c2\u8b80\u5beb\u4e2d\u6587; \u7565\u61c2\u8b80\u5beb\u82f1\u6587; \u61c2\u4e2d\u82f1\u6587\u96fb\u8166\u64cd\u4f5c; \u5177\u8cac\u4efb\u611f, \u8aa0\u5be6\u6709\u79ae\u53ca\u5b88\u6642, \u6709\u64cd\u4f5c\u7db2\u4e0a\u8cfc\u7269\u5e73\u53f0\u5de5\u4f5c\u7d93\u9a57\u512a\u5148\n\n\u5f85\u9047 :\u6bcf\u6708$10,000 - $11,000, \u6709\u6bcf\u6708\u52e4\u5de5\u734e\u91d1$1000, \u661f\u671f\u4e00\u81f3\u516d: \u4e0a\u53489\u6642\u81f3\u4e0b\u53486\u6642, \u6bcf\u9031\u5de5\u4f5c5\u5929, \u6bcf\u5929\u5de5\u4f5c 8 \u5c0f\u6642\n\n\u7533\u8acb\u9808\u77e5 :\u6c42\u8077\u8005\u53ef\u96fb\u90f5(Apply Now)\u5c65\u6b77\u8868\u7d66\u5343\u8449\u8349\u96c6\u5718\u6709\u9650\u516c\u53f8\u3002\u5982\u8981\u7d22\u53d6\u6536\u96c6\u500b\u4eba\u8cc7\u6599\u8072\u660e, \u8acb\u8207\u6881\u5c0f\u59d0(Email)\u806f\u7d61\u3002\n\n", "employment_types": ["Full Time"], "selling_points": [], "locations": ["Shatin Area"], "categories": ["Admin & HR", "Clerical / Admin Staff", "Others"], "post_time": "2022-01-17T07:28:21Z", "salary": {"currency": null, "max": null, "min": null, "period": "monthly", "term": null}, "salary_visible": false, "title_keywords": ["\u6587\u54e1"], "responsibilities": [], "requirements": {"degrees": [], "majors": [], "languages": [], "language_level": [], "hard_skills": ["word"], "soft_skills": [], "languages_combined": []}, "experience_required": {"duration": [], "field": []}}, {"job_id": "100003009053607", "location_code": "hk", "company": "Pal Line Industrial Company Limited", "job_title": "\u8ddf\u55ae\u6587\u54e1", "description": "\n\u8077\u8cac :\u5354\u52a9\u8ddf\u55ae\u5de5\u4f5c\n\n\u8cc7\u6b77 :\u4e2d\u516d\u7a0b\u5ea6; 1\u5e74\u7d93\u9a57; \u4e00\u822c\u7cb5\u8a9e; \u4e00\u822c\u666e\u901a\u8a71; \u4e00\u822c\u82f1\u8a9e\u512a\u5148; \u61c2\u8b80\u5beb\u4e2d\u6587; \u61c2\u8b80\u5beb\u82f1\u6587; \u61c2MS Outlook; \u61c2MS Excel; \u61c2\u4e2d\u6587\u6253\u5b57 20 \u5b57(\u6bcf\u5206\u9418); \u5de5\u4f5c\u52e4\u596e\n\n\u5f85\u9047 :\u6bcf\u6708$13,000 - $15,000, \u6709\u96d9\u7ce7, \u9280\u884c\u5047\u671f\u53ca\u5e74\u7d42\u734e\u91d1, \u661f\u671f\u4e00\u81f3\u4e94: \u4e0a\u53488\u664245\u5206\u81f3\u4e0b\u53486\u6642, \u6bcf\u9031\u5de5\u4f5c5\u5929\n\n\u7533\u8acb\u9808\u77e5 :\u6c42\u8077\u8005\u53ef\u96fb\u90f5(Apply Now)\u5c65\u6b77\u8868\u7d66\u532f\u9032\u5be6\u696d\u767c\u5c55\u6709\u9650\u516c\u53f8\u3002\u5982\u8981\u7d22\u53d6\u6536\u96c6\u500b\u4eba\u8cc7\u6599\u8072\u660e, \u8acb\u8207\u912d\u5c0f\u59d0(Email)\u806f\u7d61\u3002\n\n", "employment_types": ["Full Time"], "selling_points": [], "locations": ["Hung Hom"], "categories": ["Admin & HR", "Clerical / Admin Staff", "Others"], "post_time": "2022-01-17T07:13:48Z", "salary": {"currency": null, "max": null, "min": null, "period": "monthly", "term": null}, "salary_visible": false, "title_keywords": ["\u8ddf\u55ae\u6587\u54e1"], "responsibilities": [], "requirements": {"degrees": [], "majors": [], "languages": [], "language_level": [], "hard_skills": ["excel", "outlook"], "soft_skills": [], "languages_combined": []}, "experience_required": {"duration": [], "field": []}}, {"job_id": "100003009052456", "location_code": "hk", "company": "PC Partner Ltd", "job_title": "Receptionist", "description": "To cope with recent business development, we are looking for a full-time Receptionist to join our Administration Team. The ideal candidate will have a cheerful, pleasant & helpful personality, while willing to learn and with \"Can-do\" attitude.\n\nMajor Responsibilities:\n\nGreeting and announcing clients and visitors\nReceiving\u00a0and directing incoming calls to appropriate personnel and voicemail as well as providing administrative support to the HR & Admin Department\nCoordinating meetings, appointments and travel arrangement\nPreparing staff attendance record; handle inventory control, maintenance of office supplies and equipment; coordinate overall environmental cleanliness of the office\nAssisting in company activities and other ad-hoc projects as assigned\n\nRequirements:\n\nMinimum 1 year of solid relevant working experience\nExcellent telephone manner and customer service skill is essential\nPleasant, detail-minded, self-motivated, independent, adaptive, willing to learn and take on responsibilities with positive working attitude\nProficient in MS Office; proficiency in Chinese word processing is an advantage not a must\nFluency in spoken and written English and Chinese, including Mandarin\nImmediate availability is highly preferable\n\nWe offer 5-day work, bank holidays and medical insurance. We also offer attractive package commensurate with qualification & experience. Interested parties please send your full resume with CURRENT/LAST & EXPECTED SALARY.\n\n(Information collected will be used for recruitment purpose only)", "employment_types": ["Full Time", "Permanent"], "selling_points": [], "locations": ["Shatin Area"], "categories": ["Admin & HR", "Clerical / Admin Staff", "Receptionist", "Others"], "post_time": "2022-01-17T03:04:39Z", "salary": {"currency": null, "max": null, "min": null, "period": "monthly", "term": null}, "salary_visible": false, "title_keywords": ["receptionist"], "responsibilities": ["attendance", "coordinating meetings", "maintenance", "administrative support", "office supplies", "hr", "coordinate", "inventory control", "travel arrangement", "ad-hoc projects"], "requirements": {"degrees": [], "majors": [], "languages": ["english", "chinese", "mandarin"], "language_level": ["fluency", "advantage", "proficiency"], "hard_skills": ["chinese word processing", "ms office"], "soft_skills": ["detail-minded", "self-motivated", "independent", "willing to learn", "pleasant", "positive working attitude", "customer service", "telephone manner"], "languages_combined": [{"language": "english", "language_level": ["fluency"]}, {"language": "chinese", "language_level": ["fluency", "advantage", "proficiency"]}, {"language": "mandarin", "language_level": ["fluency"]}]}, "experience_required": {"duration": ["minimum 1 year"], "field": ["relevant working experience"]}}, {"job_id": "100003009054501", "location_code": "hk", "company": "GF Holdings (Hong Kong) Corporation Ltd", "job_title": "Analyst, Office Administration", "description": "Responsibilities\n\nAssist in full spectrum of Office Administration Services including procurement, repair and maintenance, security, housekeeping, carpool, mailing and other routine administration functions.\nWork together with a team consisting receptionist, office assistants and drivers to deliver various administration support services in a professional manner\nHands on experience in managing office space planning and renovation project\nParticipate in organizing company events such as annual meeting, annual dinner, etc\nProvide secretarial support to Company management\nAd-hoc assignment as and when required\nRequirements\n\nDegree in any discipline\nAt least 2 years relevant working experience in office administration\nA good team player with strong communication skills\nWilling to work at weekend and holidays in needed\nProficiency in MS Office and Chinese Character Processing\nGood Commend of both spoken and written English. Fluency in Putonghua\nWe offer attractive remuneration package and fringe benefits to the right candidate. Interested applicants please send detailed resume stating present & expected salaries and date of availability to Human Resources Department by clicking \"APPLY NOW\".\n\nFurther information about our group companies can be found at www.gfgroup.com.hk and www.gf.com.cn.\n\nAll applications will be treated in the strictest confidence and personal data collected will be used for recruitment purpose only.", "employment_types": ["Full Time"], "selling_points": ["2 years experience in office administration", "Willing to work at weekend and holidays in needed", "Fluency in Putonghua"], "locations": ["Sheung Wan"], "categories": ["Admin & HR", "Clerical / Admin Staff", "Receptionist", "Others"], "post_time": "2022-01-17T09:48:42Z", "salary": {"currency": null, "max": null, "min": null, "period": "monthly", "term": null}, "salary_visible": false, "title_keywords": ["analyst"], "responsibilities": ["ad-hoc", "management", "maintenance", "housekeeping", "office administration", "support services", "professional manner", "renovation", "repair", "planning", "secretarial support", "administration"], "requirements": {"degrees": ["degree"], "majors": [], "languages": ["putonghua", "english", "chinese"], "language_level": ["fluency", "proficiency", "good"], "hard_skills": ["processing", "ms office"], "soft_skills": ["communication skills", "good team player"], "languages_combined": [{"language": "putonghua", "language_level": ["fluency"]}, {"language": "english", "language_level": ["good"]}, {"language": "chinese", "language_level": ["proficiency"]}]}, "experience_required": {"duration": ["at least 2 years"], "field": ["office administration", "relevant working experience"]}}, {"job_id": "100003009053383", "location_code": "hk", "company": "L & A Lingerie Limited", "job_title": "\u6703\u8a08\u6587\u54e1", "description": "\n\u8077\u8cac :\u8ca0\u8cac\u6703\u8a08\u53ca\u884c\u653f\u53ca\u6587\u66f8\u5de5\u4f5c, \u5165\u8cec, \u88fd\u4f5c\u55ae\u64da\u3001\u5236\u4f5c\u5831\u8868\u3001\u8cc7\u6599\u8f38\u5165\u3001\u6574\u7406\u6587\u4ef6\u5b58\u6a94\u3001\u9700\u8981\u6642\u5c11\u91cf\u5916\u52e4\u7b49\n\n\u8cc7\u6b77 :\u4e2d\u4e94\u7a0b\u5ea6; 5\u5e74\u7d93\u9a57; \u826f\u597d\u7cb5\u8a9e; \u4e00\u822c\u666e\u901a\u8a71; \u4e00\u822c\u82f1\u8a9e; \u61c2\u8b80\u5beb\u4e2d\u6587; \u61c2\u8b80\u5beb\u82f1\u6587; \u61c2MYOB; \u61c2MS Word; \u61c2MS Outlook; \u61c2MS Excel; \u61c2\u82f1\u6587\u6253\u5b57; \u61c2\u4e2d\u6587\u6253\u5b57; \u8655\u4e8b\u7d30\u5fc3, \u8a8d\u771f, \u8aa0\u5be6, \u6709\u8cac\u4efb\u611f\n\n\u5f85\u9047 :\u6bcf\u6708$12,000 - $13,000, \u6709\u96d9\u7ce7, \u9280\u884c\u5047\u671f, \u81b3\u98df\u6d25\u8cbc \u53ca\u5e74\u7d42\u734e\u91d1, \u661f\u671f\u4e00\u81f3\u4e94: \u4e0a\u53489\u6642\u534a\u81f3\u4e0b\u53486\u6642\u534a, \u6bcf\u9031\u5de5\u4f5c5\u5929, \u6bcf\u5929\u5de5\u4f5c 8 \u5c0f\u6642\n\n\u7533\u8acb\u9808\u77e5 :\u6c42\u8077\u8005\u53ef\u96fb\u90f5(Apply Now)\u5c65\u6b77\u8868\u7d66\u67cf\u9716\u5167\u8863\u6709\u9650\u516c\u53f8\u3002\u5982\u8981\u7d22\u53d6\u6536\u96c6\u500b\u4eba\u8cc7\u6599\u8072\u660e, \u8acb\u8207\u5ed6\u5c0f\u59d0(Email)\u806f\u7d61\u3002\n\n", "employment_types": ["Full Time"], "selling_points": [], "locations": ["Yau Tsim Mong Area"], "categories": ["Admin & HR", "Clerical / Admin Staff", "Others"], "post_time": "2022-01-17T06:54:17Z", "salary": {"currency": null, "max": null, "min": null, "period": "monthly", "term": null}, "salary_visible": false, "title_keywords": [], "responsibilities": [], "requirements": {"degrees": [], "majors": [], "languages": [], "language_level": [], "hard_skills": ["excel", "outlook", "word"], "soft_skills": [], "languages_combined": []}, "experience_required": {"duration": [], "field": []}}, {"job_id": "100003009052068", "location_code": "hk", "company": "\u4e2d\u570b\u570b\u969b\u91d1\u878d\u63a7\u80a1\u6709\u9650\u516c\u53f8", "job_title": "Office Assistant \u8fa6\u516c\u5ba4\u52a9\u7406", "description": "Job Highlights\n\n\u5de5\u4f5c\u74b0\u5883\u7a69\u5b9a\n\u8a66\u7528\u671f\u6eff\u5f8c\u6709\u5b8c\u6574\u91ab\u7642\u798f\u5229\n7-10\u5e74\u4ee5\u4e0a\u5de5\u4f5c\u7d93\u9a57\u53ca\u559c\u6b61\u7a69\u5b9a\u5de5\u4f5c\n\n\u00a0Job Description\n\n1.\u00a0 \u00a0\u5354\u52a9\u8463\u4e8b\u9577\u51fa\u884c\u53ca\u4f4f\u6240\u79c1\u4eba\u4e8b\u52d9\n2.\u00a0 \u00a0\u5354\u52a9\u6574\u7406\u8463\u4e8b\u9577\u500b\u4eba\u4fe1\u7528\u5361\u8cec\u55ae\n3.\u00a0 \u00a0\u8463\u4e8b\u9577\u53ca\u516c\u53f8\u54e1\u5de5\u9152\u5e97\u548c\u6a5f\u7968\u9810\u8a02\n4.\u00a0 \u00a0\u516c\u53f8\u7bc0\u65e5\u79ae\u7269\u3001\u79ae\u54c1\u8cfc\u8d08\u5de5\u4f5c\u5b89\u6392\n5.\u00a0 \u00a0\u8fa6\u516c\u5ba4\u65e5\u5e38\u8cc7\u6e90\u88dc\u5145\u3001\u5206\u914d\u53ca\u7ba1\u7406\uff0c\u5305\u62ec\u8a18\u9304\u90e8\u9580\u4f7f\u7528\u7269\u8cc7\u7e3d\u91cf\u53ca\u7de8\u5beb\u9810\u7b97\n6.\u00a0 \u00a0\u516c\u53f8\u79ae\u54c1\u5eab\u5b58\u767b\u8a18\n7.\u00a0 \u00a0\u5354\u52a9\u516c\u95dc\u90e8\u9580\u7d93\u7406\u5b89\u6392\u516c\u53f8\u5167\u90e8\u5bb4\u6703\n8.\u00a0 \u00a0\u5206\u985e\u53ca\u6d3e\u767c\u4f86\u4fe1\u548c\u5b89\u6392\u5bc4\u905e\u90f5\u4ef6\n9.\u00a0 \u00a0\u7167\u9867\u8463\u4e8b\u9577\u5348\u9910\u5b89\u6392\n10.\u00a0\u7d71\u7c4c\u53ca\u56de\u8986\u54e1\u5de5\u53ca\u8a2a\u5ba2\u67e5\u8a62\n\n", "employment_types": ["Full Time"], "selling_points": [], "locations": ["Kwun Tong"], "categories": ["Admin & HR", "Others"], "post_time": "2022-01-17T02:02:25Z", "salary": {"currency": "HKD", "max": 13999, "min": 11000, "period": "monthly", "term": null}, "salary_visible": true, "title_keywords": ["office assistant", "\u8fa6\u516c\u5ba4\u52a9\u7406"], "responsibilities": [], "requirements": {"degrees": [], "majors": [], "languages": [], "language_level": [], "hard_skills": [], "soft_skills": [], "languages_combined": []}, "experience_required": {"duration": [], "field": []}}, {"job_id": "100003009053906", "location_code": "hk", "company": "Globelink International Freight Forwarding (HK) Limited", "job_title": "\u8239\u52d9\u6587\u54e1", "description": "\n\u8077\u8cac :\u4e00\u822c\u6587\u66f8\u5de5\u4f5c\uff0c\u5305\u62ec\u6587\u4ef6\u5b58\u6a94\u3001\u8cc7\u6599\u8f38\u5165\u3001\u8907\u5370\u3001\u8655\u7406\u90f5\u4ef6\u7b49\n\n\u8cc7\u6b77 :\u4e2d\u516d\u7a0b\u5ea6; \u826f\u597d\u7cb5\u8a9e\u512a\u5148; \u826f\u597d\u666e\u901a\u8a71\u512a\u5148; \u826f\u597d\u82f1\u8a9e\u512a\u5148; \u61c2\u8b80\u5beb\u4e2d\u6587; \u61c2\u8b80\u5beb\u82f1\u6587; \u53ef\u5373\u6642\u4e0a\u73ed\u53ca\u6709\u76f8\u95dc\u5de5\u4f5c\u7d93\u9a57\u512a\u5148\n\n\u5f85\u9047 :\u6bcf\u6708$10,000 - $12,000, \u6709\u6bcf\u6708\u52e4\u5de5\u734e\u91d1$450, \u9280\u884c\u5047\u671f, \u734e\u52f5\u6027\u82b1\u7d05, \u91ab\u7642\u798f\u5229 \u53ca\u5a5a\u5047, \u661f\u671f\u4e00\u81f3\u4e94: \u4e0a\u53489\u6642\u81f3\u4e0b\u53485\u6642\u534a\u53ca\u661f\u671f\u516d: \u4e0a\u53489\u6642\u81f3\u4e0b\u53481\u6642, \u6bcf\u9031\u5de5\u4f5c5\u5929\u81f35\u5929\u534a, \u6bcf\u5929\u5de5\u4f5c 7.5 - 8 \u5c0f\u6642\n\n\u7533\u8acb\u9808\u77e5 :Apply Now INTERNATIONAL FREIGHT FORWARDING (HK) LIMITED,\u7d22\u53d6\u6536\u96c6\u500b\u4eba\u8cc7\u6599\u8072\u660e, \u8acb\u8207\u67ef\u5148\u751fEmail\u806f\u7d61\n\n", "employment_types": ["Full Time"], "selling_points": [], "locations": ["Kwun Tong"], "categories": ["Admin & HR", "Clerical / Admin Staff", "Others"], "post_time": "2022-01-17T07:44:11Z", "salary": {"currency": null, "max": null, "min": null, "period": "monthly", "term": null}, "salary_visible": false, "title_keywords": [], "responsibilities": [], "requirements": {"degrees": [], "majors": [], "languages": [], "language_level": [], "hard_skills": [], "soft_skills": [], "languages_combined": []}, "experience_required": {"duration": [], "field": []}}, {"job_id": "100003009051885", "location_code": "hk", "company": "LAWSGROUP", "job_title": "Administrative Assistant", "description": "Job Description:\n\nProvide secretarial services and administrative support for Directors and Senior Secretaries by maintaining filing systems, coordinating schedule for meetings and travel arrangement, handling reports and correspondences, drafting minutes etc\nDraft general correspondence, including letters, memos, faxes and reports etc.\nAssist in organizing travel itineraries, including booking flights, hotels, restaurants etc.\nHandle ad hoc projects as required\n\nJob Requirements:\n\nDegree / High Diploma holder, preferably in Business Administration\nMinimum 1 year relevant experience\nGood command of both spoken and written English, Chinese and Mandarin\nExcellent interpersonal skills, independent, meticulous, well-organized, proactive and eager to learn\nPositive working attitude and able to work under pressure\nProficient in MS office including MS Word, Excel, Powerpoint & Chinese Word Processing\nCandidate with more experience will be considered as Administrative Executive\nWe\u00a0offer\u00a0attractive remuneration package to the right candidate. Interested parties please click the \"APPLY NOW\" button below and send your application together with a detailed resume including current & expected salary and availability to Human Resources Department.\nCompany website:\u00a0https://www.lawsgroup.com\n(Data collected will be treated in strict confidence and used for recruitment purpose only)", "employment_types": ["Full Time", "Permanent"], "selling_points": ["Higher Diploma or above in Business Administration", "At least 1 year relevant experience", "Provide secretarial services and admin support"], "locations": ["Lai Chi Kok"], "categories": ["Admin & HR", "Clerical / Admin Staff", "Secretary", "Others"], "post_time": "2022-01-17T01:26:49Z", "salary": {"currency": null, "max": null, "min": null, "period": "monthly", "term": null}, "salary_visible": false, "title_keywords": ["administrative assistant"], "responsibilities": ["maintaining", "administrative support", "systems", "letters", "reports", "schedule", "travel arrangement", "booking", "ad hoc projects"], "requirements": {"degrees": ["high diploma", "degree"], "majors": ["business administration"], "languages": ["english", "chinese", "mandarin"], "language_level": ["good command", "proficient"], "hard_skills": ["excel", "chinese word processing", "powerpoint", "ms office", "ms word"], "soft_skills": ["meticulous", "independent", "well-organized", "eager to learn", "positive working attitude", "interpersonal skills", "proactive", "work under pressure"], "languages_combined": [{"language": "english", "language_level": ["good command"]}, {"language": "chinese", "language_level": ["good command", "proficient"]}, {"language": "mandarin", "language_level": ["good command"]}]}, "experience_required": {"duration": ["minimum 1 year"], "field": ["administrative", "relevant experience"]}}, {"job_id": "100003009053865", "location_code": "hk", "company": "Grandnorm International Wealth Management Limited", "job_title": "\u6703\u8a08\u6587\u54e1", "description": "\n\u8077\u8cac :\u8ca0\u8cac\u7de8\u88fd\u5404\u9805\u5831\u8868\u53ca\u65e5\u5e38\u6703\u8a08\u5e33\u76ee, \u8cc7\u6599\u6574\u7406\u53ca\u6b78\u6a94\u5de5\u4f5c, \u4e00\u822c\u6587\u66f8\u53ca\u884c\u653f\u5de5\u4f5c\n\n\u8cc7\u6b77 :\u4e2d\u516d\u7a0b\u5ea6; 1\u5e74\u7d93\u9a57; \u826f\u597d\u7cb5\u8a9e; \u826f\u597d\u666e\u901a\u8a71; \u826f\u597d\u82f1\u8a9e; \u61c2\u8b80\u5beb\u4e2d\u6587; \u61c2\u8b80\u5beb\u82f1\u6587; \u61c2Peachtree; \u61c2MS Word; \u61c2MS Outlook; \u61c2MS Excel; \u6301\u6709LCC\u4e2d\u7d1a\u8b49\u66f8; \u5de5\u4f5c\u7a4d\u6975\u4e3b\u52d5, \u6709\u8cac\u4efb\u611f\u53ca\u9858\u610f\u5b78\u7fd2\n\n\u5f85\u9047 :\u6bcf\u6708$14,000 - $15,000, \u6709\u96d9\u7ce7, \u9280\u884c\u5047\u671f \u53ca\u91ab\u7642\u4fdd\u96aa, \u661f\u671f\u4e00\u81f3\u4e94: \u4e0a\u53489\u6642\u81f3\u4e0b\u53486\u6642\u53ca\u661f\u671f\u516d: \u4e0a\u53489\u6642\u81f3\u4e0b\u53481\u6642, \u6bcf\u9031\u5de5\u4f5c5\u5929\u81f35\u5929\u534a\n\n\u7533\u8acb\u9808\u77e5 :\u6c42\u8077\u8005\u53ef\u96fb\u90f5(Apply Now)\u5c65\u6b77\u8868\u7d66\u6d2a\u7bc4\u570b\u969b\u8ca1\u5bcc\u7ba1\u7406\u6709\u9650\u516c\u53f8\u3002\u5982\u8981\u7d22\u53d6\u6536\u96c6\u500b\u4eba\u8cc7\u6599\u8072\u660e, \u8acb\u8207\u912d\u5148\u751f(Email)\u806f\u7d61\u3002\n\n", "employment_types": ["Full Time"], "selling_points": [], "locations": ["Tsim Sha Tsui"], "categories": ["Admin & HR", "Clerical / Admin Staff", "Others"], "post_time": "2022-01-17T07:39:19Z", "salary": {"currency": null, "max": null, "min": null, "period": "monthly", "term": null}, "salary_visible": false, "title_keywords": [], "responsibilities": [], "requirements": {"degrees": [], "majors": [], "languages": [], "language_level": [], "hard_skills": ["excel", "outlook", "word"], "soft_skills": [], "languages_combined": []}, "experience_required": {"duration": [], "field": []}}, {"job_id": "100003009054146", "location_code": "hk", "company": "Hong Kong Baptist University", "job_title": "General Clerk (PR0473/21-22)", "description": "GRADUATE SCHOOL\n\nGeneral Clerk (PR0473/21-22)\n\nThe HKBU Graduate School (GS) supports the development of the University\u2019s strategic directions and provides central administration for the University\u2019s postgraduate education.\u00a0 We are now looking for a dedicated team player to join the Office Management and Development Team to perform duties relating to programme administration and other central duties.\n\nRoles and Responsibilities:\nmanage student data and compile statistical reports;\nhandle email/telephone/walk-in enquiries;\nProvide general administrative support to the Office;\nprovide counter services; and\ncarry out ad hoc tasks as assigned.\nApplicant should have:\n\ncompleted secondary education or specialised vocational training;\nat least two years of relevant work experience;\na good command of written and spoken English and Chinese (including Putonghua); and\ngood computer application skills, good communication and interpersonal skills.\nInitial appointment will be made on a fixed-term contract of two years. Re-appointment thereafter will be subject to mutual agreement and availability of funding.\u00a0\n\nSalary will be commensurate with qualifications and experience.\n\nApplication Procedure:\n\nApplicants are invited to submit their applications at the HKBU e-Recruitment System (jobs.hkbu.edu.hk). Those not invited for interview 8 weeks after the closing date may consider their applications unsuccessful. Details of the University\u2019s Personal Information Collection Statement can be found at http://hro.hkbu.edu.hk/pics.\n\nThe University reserves the right not to make an appointment for the post advertised, and the appointment will be made according to the terms and conditions then applicable at the time of offer.\n\nClosing date: 30 January 2022", "employment_types": ["Full Time"], "selling_points": ["manage student data", "handle email/telephone/walk-in enquiries", "Provide general administrative support"], "locations": ["Kowloon City"], "categories": ["Admin & HR", "Clerical / Admin Staff", "Receptionist", "Others"], "post_time": "2022-01-17T08:33:20Z", "salary": {"currency": null, "max": null, "min": null, "period": "monthly", "term": null}, "salary_visible": false, "title_keywords": ["general clerk"], "responsibilities": ["management", "data", "general administrative support", "ad hoc tasks", "communication", "reports", "recruitment", "administration"], "requirements": {"degrees": ["secondary education"], "majors": [], "languages": ["putonghua", "english", "chinese"], "language_level": ["good command"], "hard_skills": ["make"], "soft_skills": ["perform duties", "team player", "communication and interpersonal skills"], "languages_combined": [{"language": "putonghua", "language_level": ["good command"]}, {"language": "english", "language_level": ["good command"]}, {"language": "chinese", "language_level": ["good command"]}]}, "experience_required": {"duration": ["at least two years"], "field": []}}, {"job_id": "100003009053430", "location_code": "hk", "company": "\u767c\u5229\u884c\u6709\u9650\u516c\u53f8", "job_title": "\u8fa6\u516c\u5ba4\u52a9\u7406\u8ddf\u55ae\u6587\u54e1", "description": "\n\u8077\u8cac :\u8ca0\u8cac\u8655\u7406\u96fb\u8a71\u4e0b\u55ae, \u96fb\u8166\u51fa\u55ae, \u5b89\u6392\u51fa\u8ca8\u8868, \u8207\u5ba2\u4eba\u6e9d\u901a, \u8655\u7406\u4e00\u822c\u6587\u66f8\u5de5\u4f5c, \u751f\u7522\u55ae\u8ddf\u9032\u53ca\u8cc7\u6599\u6574\u7406\n\n\u8cc7\u6b77 :\u4e2d\u4e94\u7a0b\u5ea6; 1\u5e74\u7d93\u9a57; \u4e00\u822c\u7cb5\u8a9e; \u4e00\u822c\u666e\u901a\u8a71; \u4e00\u822c\u82f1\u8a9e; \u61c2\u8b80\u5beb\u4e2d\u6587; \u61c2\u8b80\u5beb\u82f1\u6587; \u61c2\u4e2d\u82f1\u6587\u96fb\u8166\u64cd\u4f5c; \u5b88\u6642, \u5de5\u4f5c\u76e1\u8cac, \u5177\u5408\u4f5c\u7cbe\u795e, \u6709\u8cac\u4efb\u5fc3, \u6709\u79ae\u8c8c\n\n\u5f85\u9047 :\u6bcf\u6708$12,500 - $13,500, \u6709\u91ab\u7642\u4fdd\u96aa, \u751f\u65e5\u5047\u53ca\u5e74\u7d42\u914c\u60c5\u6027\u82b1\u7d05, \u661f\u671f\u4e00\u81f3\u516d: \u4e0a\u53488\u6642\u81f3\u4e0b\u53485\u664215\u5206, \u6bcf\u9031\u5de5\u4f5c6\u5929\n\n\u7533\u8acb\u9808\u77e5 :\u6c42\u8077\u8005\u53ef\u81f4\u96fb26738388\u8207\u767c\u5229\u884c\u6709\u9650\u516c\u53f8\u9673\u5148\u751f\u806f\u7d61\u3002\n\n", "employment_types": ["Full Time"], "selling_points": [], "locations": ["Not Specified"], "categories": ["Admin & HR", "Clerical / Admin Staff", "Others"], "post_time": "2022-01-17T06:58:50Z", "salary": {"currency": null, "max": null, "min": null, "period": "monthly", "term": null}, "salary_visible": false, "title_keywords": [], "responsibilities": [], "requirements": {"degrees": [], "majors": [], "languages": [], "language_level": [], "hard_skills": [], "soft_skills": [], "languages_combined": []}, "experience_required": {"duration": [], "field": []}}, {"job_id": "100003009053923", "location_code": "hk", "company": "Towa Tours Ltd", "job_title": "\u9ad8\u7d1a\u6703\u8a08\u6587\u54e1 (\u517c\u8077)", "description": "\n\u8077\u8cac :Handle full set of accounts, including but not limited to the preparation of vouchers, bank reconciliation and various accounting reports;Handle telegraphic Transfer, bank guarantee, etc\n\n\u8cc7\u6b77 :\u4e2d\u4e94\u7a0b\u5ea6; 2\u5e74\u7d93\u9a57; \u826f\u597d\u7cb5\u8a9e; \u4e00\u822c\u82f1\u8a9e; \u61c2\u8b80\u5beb\u4e2d\u6587; \u61c2\u8b80\u5beb\u82f1\u6587; \u61c2Xero; \u61c2Peachtree; \u6301\u6709LCC\u9ad8\u7d1a\u8b49\u66f8\n\n\u5f85\u9047 :\u6bcf\u5c0f\u6642$100.00 - $120.00, \u6709\u8d85\u6642\u5de5\u4f5c\u6d25\u8cbc, \u661f\u671f\u4e00\u81f3\u516d: \u4e0a\u53489\u6642\u81f3\u4e0b\u53486\u6642, \u6bcf\u9031\u5de5\u4f5c3\u5929\u81f34\u5929, \u6bcf\u5929\u5de5\u4f5c 4 \u5c0f\u6642, \u5348\u81b3\u6642\u9593: 1300 - 1400, \u6709\u9700\u8981\u6642\u661f\u671f\u516d\u9700\u5168\u65e5\u4e0a\u73ed\n\n\u7533\u8acb\u9808\u77e5 :\u6c42\u8077\u8005\u53ef\u96fb\u90f5(Apply Now)\u5c65\u6b77\u8868\u7d66\u6771\u548c\u65c5\u904a\u6709\u9650\u516c\u53f8\u3002\u5982\u8981\u7d22\u53d6\u6536\u96c6\u500b\u4eba\u8cc7\u6599\u8072\u660e, \u8acb\u8207\u674e\u5973\u58eb(Email)\u806f\u7d61\u3002\n\n", "employment_types": ["Part Time"], "selling_points": [], "locations": ["Tsim Sha Tsui"], "categories": ["Admin & HR", "Clerical / Admin Staff", "Others"], "post_time": "2022-01-17T07:47:14Z", "salary": {"currency": null, "max": null, "min": null, "period": "hourly", "term": null}, "salary_visible": false, "title_keywords": [], "responsibilities": ["full set of accounts", "reports", "bank reconciliation"], "requirements": {"degrees": [], "majors": [], "languages": [], "language_level": [], "hard_skills": [], "soft_skills": [], "languages_combined": []}, "experience_required": {"duration": [], "field": []}}, {"job_id": "100003009053687", "location_code": "hk", "company": "Kam Yuen Radio Co Ltd", "job_title": "\u71df\u696d\u90e8\u6587\u54e1**", "description": "\n\u8077\u8cac :\u4e00\u822c\u6587\u66f8\u8655\u7406, \u806f\u7d61\u5ba2\u6237, \u8ddf\u9032\u8a02\u55ae, \u8cc7\u6599\u8f38\u5165\n\n\u8cc7\u6b77 :\u4e2d\u4e94\u7a0b\u5ea6; 2\u5e74\u7d93\u9a57; \u826f\u597d\u7cb5\u8a9e\u512a\u5148; \u4e00\u822c\u82f1\u8a9e; \u61c2\u8b80\u5beb\u4e2d\u6587; \u61c2\u95b1\u8b80\u82f1\u6587; \u61c2MS Outlook; \u61c2MS Excel; \u5177\u6709\u4e00\u822c\u4e92\u806f\u7db2\u77e5\u8b58; \u61c2\u5009\u9821/\u901f\u6210\u8f38\u5165\u6cd5; \u5177\u6709\u57fa\u672c\u96fb\u8166\u64cd\u4f5c\u77e5\u8b58; \u5de5\u4f5c\u8b39\u614e, \u76e1\u8cac, \u5b88\u6642, \u52e4\u596e, \u79ae\u8c8c\u5c0d\u5f85\u5ba2\u6237\n\n\u5f85\u9047 :\u6bcf\u6708$12,000, \u6709\u96d9\u7ce7, \u9280\u884c\u5047\u671f, \u751f\u65e5\u50471\u5929, \u734e\u52f5\u6027\u82b1\u7d05 \u53ca\u4f9b\u81b3\u98df, \u661f\u671f\u4e00\u81f3\u4e94: \u4e0a\u53489\u6642\u81f3\u4e0b\u53486\u6642,\u661f\u671f\u516d: \u4e0a\u53489\u6642\u81f3\u4e0b\u53481\u6642\u6216\u4e0a\u53489\u6642\u81f3\u4e0b\u53483\u6642, \u6bcf\u9031\u5de5\u4f5c6\u5929, \u6bcf\u5929\u5de5\u4f5c 8 \u5c0f\u6642, \u9022\u661f\u671f\u516d\u9700\u8f2a\u653e\u5de5\u6642\u6bb5\n\n\u7533\u8acb\u9808\u77e5 :\u6c42\u8077\u8005\u53ef\u96fb\u90f5(Apply Now)\u5c65\u6b77\u8868\u7d66\u91d1\u6e90\u7121\u7dda\u96fb\u884c\u6709\u9650\u516c\u53f8\u3002\u5982\u8981\u7d22\u53d6\u6536\u96c6\u500b\u4eba\u8cc7\u6599\u8072\u660e, \u8acb\u8207\u9673\u5c0f\u59d0(Email)\u806f\u7d61\u3002\n\n", "employment_types": ["Full Time"], "selling_points": [], "locations": ["Kwai Tsing Area"], "categories": ["Admin & HR", "Clerical / Admin Staff", "Others"], "post_time": "2022-01-17T07:21:09Z", "salary": {"currency": null, "max": null, "min": null, "period": "monthly", "term": null}, "salary_visible": false, "title_keywords": [], "responsibilities": [], "requirements": {"degrees": [], "majors": [], "languages": [], "language_level": [], "hard_skills": ["excel", "outlook"], "soft_skills": [], "languages_combined": []}, "experience_required": {"duration": [], "field": []}}, {"job_id": "100003009053527", "location_code": "hk", "company": "VH International (Holdings) Limited", "job_title": "\u92b7\u552e\u6587\u54e1", "description": "\n\u8077\u8cac :\u8ca0\u8cac\u6587\u66f8\u548c\u884c\u653f\u652f\u6301,\u5831\u544a\u548c\u5206\u6790,\u8655\u7406\u5e38\u898f\u7684\u92b7\u552e\u548c\u884c\u653f\u8077\u8cac,\u5305\u62ec\u5f62\u5f0f\u767c\u7968\u548c\u63a1\u8cfc\u8a02\u55ae\u7684\u7c3d\u767c\u548c\u6b78\u6a94,\u8207\u5de5\u5ee0\u5c31\u751f\u7522\u548c\u4ea4\u8ca8\u8a08\u5283\u9032\u884c\u806f\u7d61,\u62dc\u8a2a\u672c\u5730\u4e3b\u8981\u5408\u4f5c\u5925\u4f34,\u7dad\u8b77\u696d\u52d9\u95dc\u4fc2,\u6839\u64da\u9700\u8981\u5354\u52a9\u57f7\u884c\u81e8\u6642\u4efb\u52d9\n\n\u8cc7\u6b77 :\u4e2d\u4e94\u7a0b\u5ea6; 2\u5e74\u7d93\u9a57; \u826f\u597d\u7cb5\u8a9e; \u826f\u597d\u666e\u901a\u8a71; \u826f\u597d\u82f1\u8a9e; \u61c2\u8b80\u5beb\u4e2d\u6587; \u61c2\u8b80\u5beb\u82f1\u6587; \u61c2\u96fb\u8166\u6587\u66f8\u8655\u7406; \u61c2Microsoft Office; \u5177\u6709\u4e00\u822c\u4e92\u806f\u7db2\u77e5\u8b58; \u61c2\u4e2d\u82f1\u6587\u96fb\u8166\u64cd\u4f5c\n\n\u5f85\u9047 :\u6bcf\u6708$15,000, \u6709\u4f63\u91d1, \u661f\u671f\u4e00\u81f3\u4e94: \u4e0a\u53489\u6642\u81f3\u4e0b\u53486\u6642, \u6bcf\u9031\u5de5\u4f5c5\u5929, \u6bcf\u5929\u5de5\u4f5c 8 \u5c0f\u6642\n\n\u7533\u8acb\u9808\u77e5 :\u6c42\u8077\u8005\u53ef\u50b3\u771f(81617602)\u6216\u96fb\u90f5(Apply Now)\u5c65\u6b77\u8868\u7d66\u8c50\u5c71\u570b\u969b(\u63a7\u80a1)\u6709\u9650\u516c\u53f8\u3002\u5982\u8981\u7d22\u53d6\u6536\u96c6\u500b\u4eba\u8cc7\u6599\u8072\u660e, \u8acb\u8207\u5085\u5c0f\u59d0(Email)\u806f\u7d61\u3002\n\n", "employment_types": ["Full Time"], "selling_points": [], "locations": ["Kwun Tong"], "categories": ["Admin & HR", "Clerical / Admin Staff", "Others"], "post_time": "2022-01-17T07:06:18Z", "salary": {"currency": null, "max": null, "min": null, "period": "monthly", "term": null}, "salary_visible": false, "title_keywords": [], "responsibilities": [], "requirements": {"degrees": [], "majors": [], "languages": [], "language_level": [], "hard_skills": [], "soft_skills": [], "languages_combined": []}, "experience_required": {"duration": [], "field": []}}, {"job_id": "100003009053319", "location_code": "hk", "company": "Herbs Generation International Limited", "job_title": "Clerk (5 Days Work)", "description": "Responsibilities:\n\nProvide administration and clerical support to CRM department\nDraw a data, call list and mailing list\nPrepare regular sales report and statistical analysis in daily and monthly basis\nPrepare sales invoice and related documents\nCoordinate between internal departments and customers\nResponsible for member survey and DM mailing\nArrange courier and delivery schedule\nPerform ad hoc project as assigned\nWorking Location: Tsim Sha Tsui\n\nRequirements\n\nDSE or above with 1 year relevant experience is preferred\nProficiency in using MS-Excel (Vlookup and Pivot table)\nStrong sense of responsibilities, detailed-minded, well-organized, self-motivated & hardworking\nGood communication skills and able to work independently\nProficient in MS Word, Excel, PowerPoint and Chinese Word Processing\nGood command of both written and spoken English and Chinese\nImmediate available is preferred\n\nStaff Benefits\n\nMaximum 16 days Annual Leave ,Public Holiday,\u00a0Birthday Leave,\u00a0Marriage Leave,\u00a0Performance Bonus,\u00a0Free Gift,\u00a0Medical and dental insurance\n\nWe offer 5 days work, attractive remuneration and career development opportunities. Interested parties please send full resume with expected salary to HRA Department by e-mail via \"Apply Now\"\n\n\nLearn more about us at www.herbs.hk/ www.zino.hk/ www.zinomall.com\n\n*Personal data collected will be used for recruitment purpose only.", "employment_types": ["Full Time", "Permanent"], "selling_points": [], "locations": ["Tsim Sha Tsui"], "categories": ["Admin & HR", "Clerical / Admin Staff", "Others", "Sales, CS & Business Devpt", "Customer Service - Supervisor / Officer"], "post_time": "2022-01-17T06:47:52Z", "salary": {"currency": null, "max": null, "min": null, "period": "monthly", "term": null}, "salary_visible": false, "title_keywords": ["clerk"], "responsibilities": ["sales report", "ad hoc", "data", "invoice", "related documents", "analysis", "prepare sales", "clerical support", "coordinate", "delivery schedule", "administration"], "requirements": {"degrees": ["dse"], "majors": [], "languages": ["english", "chinese"], "language_level": ["good command", "proficient"], "hard_skills": ["excel", "chinese word processing", "pivot table", "powerpoint", "ms-excel", "vlookup", "ms word"], "soft_skills": ["communication skills", "self-motivated", "work independently", "well-organized", "sense of responsibilities", "hardworking", "detailed"], "languages_combined": [{"language": "english", "language_level": ["good command"]}, {"language": "chinese", "language_level": ["good command", "proficient"]}]}, "experience_required": {"duration": ["1 year"], "field": ["relevant experience"]}}, {"job_id": "100003009032852", "location_code": "hk", "company": "Kin Ming Construction Company Ltd", "job_title": "\u6587\u54e1 Clerk", "description": "\u5730\u5340 :\u706b\u70ad\n\n\u8077\u8cac :\u4e00\u822c\u6587\u66f8\u5de5\u4f5c\uff1b\u6587\u4ef6\u5b58\u6a94\u53ca\u8655\u7406\uff0c\u8cc7\u6599\u8f38\u5165\uff1b\u5354\u52a9\u90e8\u9580\u8655\u7406\u3001\u8ddf\u9032\u63a1\u8cfc\u8a02\u55ae\u3001\u6536\u767c\u3001\u6574\u7406\u3001\u8a18\u9304\u5de5\u7a0b\u6587\u4ef6\u53ca\u7b49\u5de5\u4f5c\uff1b\u63a5\u807d\u96fb\u8a71\uff0c\u5b89\u6392\u901f\u905e\n\u8cc7\u6b77 :\u4e2d\u516d\u7a0b\u5ea6; 2\u5e74\u7d93\u9a57; \u826f\u597d\u7cb5\u8a9e; \u4e00\u822c\u666e\u901a\u8a71; \u826f\u597d\u82f1\u8a9e\u512a\u5148; \u61c2\u8b80\u5beb\u4e2d\u6587; \u61c2\u8b80\u5beb\u82f1\u6587; \u61c2Microsoft Office; \u61c2MS Word; \u61c2MS Outlook; \u61c2MS Excel; \u61c2\u4e2d\u82f1\u6587\u96fb\u8166\u64cd\u4f5c; \u51772\u5e74\u6216\u4ee5\u4e0a\u76f8\u95dc\u5de5\u4f5c\u7d93\u9a57\uff0c\u826f\u597d\u6e9d\u901a\u6280\u5de7\u53ca\u670d\u52d9\u614b\u5ea6\uff0c\u5de5\u4f5c\u7a4d\u6975\u4e3b\u52d5\u3001\u76e1\u8cac\u3001\u52e4\u596e\n\u5f85\u9047 :\u6709\u9280\u884c\u5047\u671f \u53ca\u670d\u52d9\u6eff3\u500b\u6708\u6709\u9580\u8a3a\u91ab\u7642\u54ad, \u6bcf\u9031\u5de5\u4f5c5\u5929\u534a\n\u7533\u8acb\u9808\u77e5 :\u6c42\u8077\u8005\u53ef\u96fb\u90f5\u5c65\u6b77\u8868\u7d66\u5065\u660e\u5efa\u7bc9\u6709\u9650\u516c\u53f8\u3002\u5982\u8981\u7d22\u53d6\u6536\u96c6\u500b\u4eba\u8cc7\u6599\u8072\u660e, \u8acb\u8207\u8d99\u5c0f\u59d0(Email)\u806f\u7d61\u3002", "employment_types": ["Full Time", "Permanent"], "selling_points": [], "locations": ["Shatin Area"], "categories": ["Admin & HR", "Clerical / Admin Staff", "Receptionist", "Others"], "post_time": "2022-01-16T21:50:08Z", "salary": {"currency": "HKD", "max": 13999, "min": 11000, "period": "monthly", "term": null}, "salary_visible": true, "title_keywords": ["clerk", "\u6587\u54e1"], "responsibilities": [], "requirements": {"degrees": [], "majors": [], "languages": [], "language_level": [], "hard_skills": ["excel", "outlook", "word"], "soft_skills": [], "languages_combined": []}, "experience_required": {"duration": [], "field": []}}, {"job_id": "100003009053655", "location_code": "hk", "company": "AccGirl Limited", "job_title": "\u884c\u653f\u6587\u54e1", "description": "\n\u8077\u8cac :\u4e00\u822c\u884c\u653f\u53ca\u6587\u66f8\u5de5\u4f5c\uff0c\u5305\u62ec\u6587\u4ef6\u5b58\u6a94\u3001\u8cc7\u6599\u8f38\u5165\u7b49, \u8ca0\u8cac\u5354\u52a9\u884c\u653f\u90e8\u7684\u65e5\u5e38\u904b\u4f5c; \u8655\u7406\u90f5\u4ef6\u53ca\u50b3\u771f; \u96fb\u8166\u6587\u4ef6\u8655\u7406; \u8ca0\u8cac\u5354\u52a9\u8ca1\u52d9\u6536\u652f,\u5305\u62ec:\u958b\u5404\u9805\u652f\u7968; \u51fa\u5831\u50f9\u55ae\u3001\u767c\u7968\u7b49\u55ae\u64da; \u5354\u52a9\u63a1\u8cfc,\u5305\u62ec:\u5b89\u6392\u6587\u5177/\u8fa6\u516c\u8a2d\u5099/\u7dad\u4fee\u4e8b\u9805; \u5176\u4ed6\u4e0a\u7d1a\u5206\u914d\u4e4b\u5de5\u4f5c(\u6709 \u914c\u60c5\u6027\u82b1\u7d05 \u53ca\u5176\u4ed6\u6d25\u8cbc/\u798f\u5229)\n\n\u8cc7\u6b77 :\u4e2d\u516d\u7a0b\u5ea6; 1\u5e74\u7d93\u9a57; \u826f\u597d\u7cb5\u8a9e\u512a\u5148; \u826f\u597d\u666e\u901a\u8a71\u512a\u5148; \u4e00\u822c\u82f1\u8a9e; \u61c2\u8b80\u5beb\u4e2d\u6587; \u61c2\u8b80\u5beb\u82f1\u6587; \u61c2\u96fb\u8166\u6587\u66f8\u8655\u7406; \u61c2Microsoft Office; \u61c2\u4e2d\u82f1\u6587\u96fb\u8166\u64cd\u4f5c; \u5177\u6709\u57fa\u672c\u96fb\u8166\u64cd\u4f5c\u77e5\u8b58; \u826f\u597d\u6e9d\u901a\u53ca\u6642\u9593\u7ba1\u7406\u6280\u5de7; \u5177\u4e00\u5e74\u76f8\u95dc\u7684\u5de5\u4f5c\u7d93\u9a57\u512a\u5148\n\n\u5f85\u9047 :\u6bcf\u6708$13,000 - $15,000, \u6709\u8d85\u6642\u5de5\u4f5c\u88dc\u5047, \u96d9\u7ce7, \u9280\u884c\u5047\u671f, \u8868\u73fe\u734e\u91d1, \u6649\u5347\u6a5f\u6703, \u9032\u4fee\u6d25\u8cbc, \u661f\u671f\u4e00\u81f3\u4e94: \u4e0a\u53489\u6642\u81f3\u4e0b\u53486\u6642\u53ca\u661f\u671f\u516d: \u4e0a\u53489\u6642\u81f3\u4e0b\u53481\u6642, \u6bcf\u9031\u5de5\u4f5c5\u5929\u534a\n\n\u7533\u8acb\u9808\u77e5 :\u6c42\u8077\u8005\u53ef\u96fb\u90f5(Apply Now)\u5c65\u6b77\u8868\u7d66\u6703\u8a08\u59b9\u6709\u9650\u516c\u53f8\u3002\u5982\u8981\u7d22\u53d6\u6536\u96c6\u500b\u4eba\u8cc7\u6599\u8072\u660e, \u8acb\u8207\u8b5a\u5c0f\u59d0(Email)\u806f\u7d61\u3002\n\n", "employment_types": ["Full Time"], "selling_points": [], "locations": ["North Point"], "categories": ["Admin & HR", "Clerical / Admin Staff", "Others"], "post_time": "2022-01-17T07:18:09Z", "salary": {"currency": null, "max": null, "min": null, "period": "monthly", "term": null}, "salary_visible": false, "title_keywords": [], "responsibilities": [], "requirements": {"degrees": [], "majors": [], "languages": [], "language_level": [], "hard_skills": [], "soft_skills": [], "languages_combined": []}, "experience_required": {"duration": [], "field": []}}, {"job_id": "100003009047782", "location_code": "hk", "company": "Tung Wah Group of Hospitals", "job_title": "\u5eb6\u52d9\u54e1(\u6e05\u6f54)(\u8077\u4f4d\u7de8\u865f\uff1aA3/GA(C)/BCAD/JOBS)", "description": "\u5de5\u4f5c\u5730\u9ede\uff1a\u4e0a\u74b0\n\u8077\u8cac\uff1a\n\u8ca0\u8cac\u884c\u653f\u5927\u6a13\u7684\u6e05\u6f54\u53ca\u8336\u6c34\u5de5\u4f5c\u3001\u6587\u4ef6\u7684\u50b3\u9001\u3001\u7c21\u55ae\u7684\u6587\u66f8\u53ca\u4e00\u822c\u5eb6\u52d9\u5de5\u4f5c\u3002\n\u7406\u60f3\u7684\u7533\u8acb\u8005\u61c9\u5177\u5099\uff1a\n\u5b8c\u6210\u5c0f\u5b78\u7a0b\u5ea6\uff0c\u80fd\u95b2\u8b80\u7c21\u55ae\u4e2d\u82f1\u6587\uff0c\u64cd\u6d41\u5229\u7cb5\u8a9e\u3002\u5177\u76f8\u95dc\u5de5\u4f5c\u7d93\u9a57\u8005\u5c07\u7372\u512a\u5148\u8003\u616e\u3002\n\u85aa\u916c\u53ca\u8058\u7528\u689d\u4ef6\uff1a\n\u7372\u9078\u7684\u7533\u8acb\u4eba\u5c07\u4ee5\u5408\u7d04\u689d\u6b3e\u53d7\u8058\u3002\u6709\u95dc\u85aa\u91d1\u6703\u6309\u5e74\u5c31\u54e1\u5de5\u7684\u8868\u73fe\u53ca\u6771\u83ef\u898f\u5b9a\u800c\u5411\u4e0a/\u4e0b\u8abf\u6574\u6216\u51cd\u7d50\u3002\u54e1\u5de5\u798f\u5229\u5305\u62ec\u6709\u85aa\u5047\u671f\u3001\u9032\u4fee\u6d25\u8cbc\u3001\u91ab\u7642\u53ca\u7259\u9f52\u4fdd\u5065\u3002\u4efb\u8077\u8005\u5c07\u6309\u4e94\u5929\u5de5\u4f5c\u5468\u5b89\u6392\u4e0a\u73ed\uff0c\u60df\u4ecd\u9808\u8996\u4e4e\u90e8\u9580\u904b\u4f5c\u53ca\u670d\u52d9\u9700\u8981\u800c\u5b9a\u3002\n\u7533\u8acb\u7a0b\u5e8f\uff1a\n\u8acb\u5c07\u500b\u4eba\u5c65\u6b77\u6216\u586b\u59a5\u7533\u8acb\u8868\u683c<\u8868\u865f\uff1aF601(n)>(\u53ef\u89aa\u81e8\u7d22\u53d6\u6216\u5f9e\u672c\u9662\u7684\u7db2\u9801http://www.tungwah.org.hk\u4e0b\u8f09)\u4e26\u5217\u660e\u73fe\u6642\u53ca\u8981\u6c42\u85aa\u916c\u5f85\u9047\uff0c\u65bc\u4e8c\uff10\u4e8c\u4e8c\u5e74\u4e8c\u6708\u5341\u56db\u65e5\u524d\u5bc4\u9999\u6e2f\u4e0a\u74b0\u666e\u4ec1\u8857\u5341\u4e8c\u865f\u6771\u83ef\u4e09\u9662\u9ec3\u9cf3\u7fce\u7d00\u5ff5\u5927\u6a13\u56db\u6a13\u4eba\u529b\u8cc7\u6e90\u79d1\u4e3b\u7ba1\u6536\uff0c\u4fe1\u5167\u53ca\u4fe1\u5c01\u9762\u8acb\u8a3b\u660e\u7533\u8acb\u7684\u8077\u4f4d\u53ca\u8077\u4f4d\u7de8\u865f\u3002\u6771\u83ef\u4e09\u9662\u4e0d\u6703\u63a5\u6536\u90f5\u8cc7\u4e0d\u8db3\u7684\u4fe1\u4ef6\u3002\u70ba\u78ba\u4fdd\u90f5\u905e\u7121\u8aa4\uff0c\u8acb\u5728\u6295\u5bc4\u90f5\u4ef6\u6642\u652f\u4ed8\u8db3\u984d\u90f5\u8cc7\u53ca\u8a3b\u660e\u56de\u90f5\u5730\u5740\u3002\u6771\u83ef\u4e09\u9662\u5728\u4f7f\u7528\u6c42\u8077\u8005\u63d0\u4f9b\u7684\u500b\u4eba\u8cc7\u6599\u6642\uff0c\u53ea\u6703\u5c07\u8cc7\u6599\u4f5c\u6709\u95dc\u62db\u8058\u7528\u9014\uff0c\u4e26\u6703\u56b4\u683c\u9075\u5b88\u9662\u65b9\u500b\u4eba\u8cc7\u6599\u653f\u7b56\u7684\u898f\u5b9a\u3002\u51e1\u65bc\u4e8c\uff10\u4e8c\u4e8c\u5e74\u4e94\u6708\u4e09\u5341\u4e00\u65e5\u524d\u672a\u7372\u7d04\u898b\u8005\uff0c\u53ef\u4f5c\u843d\u9078\u8ad6\u3002\n\u6211\u5011\u662f\u5e73\u7b49\u6a5f\u6703\u50f1\u4e3b", "employment_types": ["Full Time", "Contract"], "selling_points": [], "locations": ["Sheung Wan"], "categories": ["Admin & HR", "Others", "Public / Civil", "Social Services - Community / Non-profit Organization", "Others"], "post_time": "2022-01-17T08:55:07Z", "salary": {"currency": null, "max": null, "min": null, "period": "monthly", "term": null}, "salary_visible": false, "title_keywords": [], "responsibilities": [], "requirements": {"degrees": [], "majors": [], "languages": [], "language_level": [], "hard_skills": [], "soft_skills": [], "languages_combined": []}, "experience_required": {"duration": [], "field": []}}, {"job_id": "100003009053646", "location_code": "hk", "company": "Kotan (Hong Kong) Company Limited", "job_title": "General Office Clerk", "description": "\nResponsibilities: General duties of General Office Clerk\nRequirements :Secondary 6; Fluent Cantonese preferred; Fair Putonghua ; Fair English ; Able to read & write Chinese ; Able to read & write English ; Word-processing; General Internet Knowledge; Eng/Chi PC operation; Chinese Typing; Changjie / Simplified Changjie input method; Basic Computer Operation Knowledge; \u61c2\u5831\u95dc, \u61c2\u64cd\u4f5c\u7db2\u4e0a\u5e73\u53f0\u76f8\u95dc\u5de5\u4f5c, \u6709\u8cac\u4efb\u5fc3, \u5177\u826f\u597d\u96fb\u8166\u904b\u7528\u64cd\u4f5c\u6280\u5de7, \u80fd\u7368\u7acb\u8655\u7406\u6587\u4ef6\u5de5\u4f5c\nEmployment Terms:$50.00 - $70.00 per hour, with Purchase Discount, Mon to Fri: 9:00AM-2:00PM and Sat: 9:00AM-1:00PM, 5.5 working days per week, 5 working hours per day\nApplication Information:Job seekers may contact MISS KWONG of KOTAN (HONG KONG) COMPANY LIMITED at 24151212.\n\n", "employment_types": ["Full Time"], "selling_points": [], "locations": ["Tsuen Wan Area"], "categories": ["Admin & HR", "Clerical / Admin Staff", "Others"], "post_time": "2022-01-17T07:17:16Z", "salary": {"currency": null, "max": null, "min": null, "period": "monthly", "term": null}, "salary_visible": false, "title_keywords": ["office clerk"], "responsibilities": [], "requirements": {"degrees": [], "majors": [], "languages": ["cantonese", "putonghua", "english", "chinese"], "language_level": ["fluent"], "hard_skills": ["basic", "word", "typing", "pc", "processing", "computer operation knowledge"], "soft_skills": [], "languages_combined": [{"language": "cantonese", "language_level": ["fluent"]}, {"language": "putonghua", "language_level": []}, {"language": "english", "language_level": []}, {"language": "chinese", "language_level": []}]}, "experience_required": {"duration": [], "field": []}}, {"job_id": "100003009053866", "location_code": "hk", "company": "Arcelik Hitachi Home Appliance Sales Hong Kong Limited", "job_title": "Senior Officer, Human Resources (C&B)", "description": "Responsibilities:\n\nTo be responsible for performing HR operations, including but not limited to payroll and HRIS management, tax filing, benefits administration and analysis, attendance record, etc.\nManaging HRIS enhancement and collaborating with the headquarters, planning and executing UAT, and providing essential recommendations for the HRIS transformation process\nMaintaining employee database and ensuring all personal records are up-to-date and accurate\nAssisting in the formulation and implementation of HR policies and procedures in accordance with the company\u2019s rules & regulations\nSupporting the employment cycle includes but not limited to probation and performance management, internal staff movement, and termination or exit procedure\nCompiling regular HR related statistics and reports for management\u2019s review\nPerforming other ad hoc assignments or projects when assigned\nRequirements:\n\nBachelor\u2019s degree in HRM or Business related streams\nMinimum 5-year experience as a C&B specialist in MNC or sizable corporations\nSolid payroll knowledge and proficiency in HRIS with experiences in system transformation, preferably SAP\nProficient in Microsoft Excel application and sensitive to numbers\nFamiliar with Employment Ordinance and relevant legislations and regulations\nWell-organized, result-oriented, and able to handle multi tasks simultaneously\nPleasant personality, good team player with excellent interpersonal and communication skills\nGood command of both Cantonese and English\nLess experience may also be considered as HR Officer\nImmediately available is preferred\n\nWe offer:\n\nDouble-Pay\nDiscretionary Bonus\nMedical Benefits (Free Body Check in every year)\nDental Benefits\nStaff Purchase\nOn-the-job Training\nEducation Allowance\nFull Paid Sick Leave\nAnnual Leave Up to 18 Days\nBirthday Leave\nBirthday Coupon\nMarriage Leave\nCompany Picnic\n\nSuccessful candidates will receive an offer comprising a competitive package including attractive salary, retirement & medical benefits, leave provision, staff purchase discounts, training & development opportunities, etc.\n\nInterested parties, please send full resume with present and expected salary by clicking \"APPLY NOW\"\n\n**Application without present & expected salary will not be considered**\n\nPersonal data provided by job applicants will be treated in strict confidence.\nAll information will only be used for recruitment-related purposes.\n\nVisit us at\u00a0https://www.hitachi-homeappliances.com.hk\u00a0for more information", "employment_types": ["Full Time"], "selling_points": ["HR operations", "SAP HRIS transformation", "Stable business and working environment"], "locations": ["Shatin Area"], "categories": ["Admin & HR", "Others", "Compensation & Benefits", "HR Supporting Staff"], "post_time": "2022-01-17T07:41:01Z", "salary": {"currency": null, "max": null, "min": null, "period": "monthly", "term": null}, "salary_visible": false, "title_keywords": ["senior officer", "human resources"], "responsibilities": ["regulations", "operations", "database", "administration", "uat", "maintaining", "tax filing", "implementation", "reports", "attendance", "management", "review", "procedures", "executing", "payroll", "policies", "hr", "analysis", "ad hoc assignments", "planning"], "requirements": {"degrees": ["degree", "bachelor"], "majors": ["business"], "languages": ["cantonese", "english"], "language_level": ["good command"], "hard_skills": ["sap", "microsoft excel"], "soft_skills": ["communication skills", "good team player", "well-organized", "pleasant", "sensitive to numbers", "interpersonal", "result-oriented"], "languages_combined": [{"language": "cantonese", "language_level": ["good command"]}, {"language": "english", "language_level": ["good command"]}]}, "experience_required": {"duration": ["minimum 5-year"], "field": ["hr", "payroll"]}}, {"job_id": "100003009054601", "location_code": "hk", "company": "SAVILLS GUARDIAN", "job_title": "Assistant Administration Officer / Administration Assistant", "description": "F.5 or above\nMinimum\u00a01\u00a0year relevant working experience\nGood command of written and spoken English and Chinese\nHands-on\u00a0PC knowledge in MS Office\nWell-organized with a strong sense of responsibility, detail-minded and capable to work under pressure\nMaintain a complete and updated personnel records of newcomers, termination and movement, to ensure accuracy and compliance in HR system\nHandle monthly payroll, attendance record, work injury cases\u00a0and leave management\nProvide general clerical support and administrative duties\nCoordinating with different parties, answering telephone enquiries\u00a0and other ad hoc duties assigned by the supervisor\nApplicants with more experience will be considered as\u00a0Assistant Administration Officer\n\nWe offer competitive salary package to the right appointee. Applicants are requested submit detailed resume with present and expected salary by clicking \"APPLY NOW\".\n\nPlease Quote Emp. Ref. no. : AO/SS/012022\n\n[Personal data provided will be used strictly in accordance with our personal data policies, a copy of which will be provided immediately upon request.]", "employment_types": ["Full Time", "Permanent"], "selling_points": [], "locations": ["Hung Hom"], "categories": ["Admin & HR", "Clerical / Admin Staff", "Others", "HR Supporting Staff"], "post_time": "2022-01-17T10:12:15Z", "salary": {"currency": null, "max": null, "min": null, "period": "monthly", "term": null}, "salary_visible": false, "title_keywords": ["administration assistant", "assistant administration officer"], "responsibilities": ["ad hoc duties", "attendance", "management", "administration", "hr", "compliance", "personnel records", "clerical support", "maintain", "administrative duties", "payroll", "work under pressure"], "requirements": {"degrees": [], "majors": [], "languages": ["english", "chinese"], "language_level": ["good command"], "hard_skills": ["pc knowledge", "ms office"], "soft_skills": ["detail-minded", "capable", "sense of responsibility", "well-organized", "hands-on", "work under pressure"], "languages_combined": [{"language": "english", "language_level": ["good command"]}, {"language": "chinese", "language_level": ["good command"]}]}, "experience_required": {"duration": ["minimum 1 year"], "field": ["relevant working experience", "administration"]}}, {"job_id": "100003009052421", "location_code": "hk", "company": "Television Broadcasts Limited (TVB)", "job_title": "Office Assistant", "description": "\u8ca0\u8cac\u4e00\u822c\u8fa6\u516c\u5ba4\u652f\u63f4\u5de5\u4f5c\uff0c\u5982\u5167\u90e8\u6587\u4ef6\u50b3\u905e\u53ca\u5f71\u5370\u7b49\n\u5354\u52a9\u8fa6\u516c\u5ba4\u96dc\u52d9\u3001\u642c\u904b\u7269\u8cc7\n\u9700\u5916\u52e4\u5de5\u4f5c\uff0c\u5982\u9001\u905e\u6587\u4ef6\u53ca\u5305\u88f9\u3001\u5f80\u9280\u884c\u5165\u6578\u6216\u90f5\u5c40\u7b49\n\u4e2d\u4e94\u6216DSE\u7a0b\u5ea6\n\u4e09\u5e74\u6216\u4ee5\u4e0a\u5de5\u4f5c\u7d93\u9a57\n\u61c2\u57fa\u672c\u96fb\u8166\u64cd\u4f5c (\u5982MS Word, Excel, Outlook\u7b49)\n\u826f\u597d\u7cb5\u8a9e\uff0c\u61c2\u8b80\u5beb\u4e2d\u6587\uff0c\u7565\u61c2\u95b1\u8b80\u82f1\u6587\n\u505a\u4e8b\u6709\u689d\u7406\uff0c\u8aa0\u5be6\uff0c\u6709\u826f\u597d\u7684\u6e9d\u901a\u80fd\u529b\u53ca\u5177\u8cac\u4efb\u611f\n\u5de5\u4f5c\u5730\u9ede\uff1a\u9285\u947c\u7063\n\nPlease apply, quoting the appropriate reference number, with details of your qualifications and experience, expected salary and a contact telephone number to The Senior Manager, Personnel Department, Television Broadcasts Limited, TVB City, 77 Chun Choi Street, Tseung Kwan O Industrial Estate, Tseung Kwan O, Kowloon, Hong Kong.\n\nApplications received are solely for selection purpose. Those not invited for an interview within 4 weeks may consider their applications unsuccessful and their applications will be filed for another 3 months for future selection. Afterwards, all applications would be destroyed.", "employment_types": ["Full Time", "Permanent"], "selling_points": [], "locations": ["Causeway Bay"], "categories": ["Admin & HR", "Clerical / Admin Staff", "Others"], "post_time": "2022-01-17T03:12:25Z", "salary": {"currency": null, "max": null, "min": null, "period": "monthly", "term": null}, "salary_visible": false, "title_keywords": ["office assistant"], "responsibilities": ["contact"], "requirements": {"degrees": [], "majors": [], "languages": [], "language_level": [], "hard_skills": ["excel", "word"], "soft_skills": [], "languages_combined": []}, "experience_required": {"duration": [], "field": []}}, {"job_id": "100003009054378", "location_code": "hk", "company": "Strategic Public Relations Group Limited", "job_title": "Admin Assistant (6 Months Contract)", "description": "Responsibilities:\n\nProvide full spectrum administrative and clerical support to the Company\nProvide support to operation and renovation projects\nResponsible for logistics arrangement of meetings and events held at office\nResponsible for coordination of internal events and activities\nAssist in ensuring operation excellence of all office facilities\nMaintain the office supply inventory\nHandle any ad-hoc duties as required\n\n\u00a0Requirements:\n\n\nDiploma or above, with 2 years or above experience in office administration\nExperience in managing office renovation projects would be an advantage\nStrong sense of responsibility, well organized, meticulous & self-motivated\nProficiency in PC skills, including MS office and Chinese processing\nFluency in both written and spoken English, Chinese and Mandarin\nWilling to learn and able to work under pressure\nImmediate available preferred", "employment_types": ["Full Time", "Contract"], "selling_points": ["Provide administrative and clerical support", "5 Days Work/ Bank Holiday", "12 Days AL/Birthday Leave"], "locations": ["Admiralty"], "categories": ["Admin & HR", "Clerical / Admin Staff", "Others"], "post_time": "2022-01-17T09:19:00Z", "salary": {"currency": null, "max": null, "min": null, "period": "monthly", "term": null}, "salary_visible": false, "title_keywords": ["admin assistant"], "responsibilities": ["provide support", "ad-hoc duties", "logistics arrangement", "inventory", "renovation", "maintain", "coordination", "administrative and clerical support"], "requirements": {"degrees": ["diploma or above"], "majors": [], "languages": ["english", "chinese", "mandarin"], "language_level": ["fluency", "proficiency"], "hard_skills": ["processing", "pc skills", "ms office"], "soft_skills": ["meticulous", "self-motivated", "sense of responsibility", "willing to learn", "well organized", "work under pressure"], "languages_combined": [{"language": "english", "language_level": ["fluency"]}, {"language": "chinese", "language_level": ["fluency", "proficiency"]}, {"language": "mandarin", "language_level": ["fluency"]}]}, "experience_required": {"duration": ["2 years"], "field": ["office administration"]}}, {"job_id": "100003009053559", "location_code": "hk", "company": "Cheung Hing Lifting Components (Hong Kong) Limited", "job_title": "Sourcing and Administration Officer", "description": "Responsibilities:\n\nTo source and evaluate suppliers\u2019 abilities, quality and production capacities.\nPreparation of costings and other analytical reports for cost calculation, comparison, control, and other purposes.\nPlace orders and arrange shipment and logistic handling.\nBuild relationships with suppliers while monitoring and driving their performance.\nPrepare Monthly Purchase & Inventory Report and price analysis.\nCommunicate with Sales Department to source and develop new products.\nTake care of office administration.\nPrepare marketing materials and product information.\nAssist in data input into the Accounting database.\nCarry out cost control measure.\nTo support ad-hoc duties as assigned upon request.\n\nRequirements:\n\nForm 7, DSE or above.\nSolid working experience in similar nature is preferred.\nQuick thinking and eager to take up responsibility.\nExcellent negotiation and communication skills.\nClear minded and able to resolve problems independently.\nCan work under pressure with tight deadline schedule.\nCan work independently with can-do spirit\nFluent spoken and written in English, Chinese and Mandarin.\nWorking on one Saturday morning for every month is required.\n\nSalary and Prospect:\n\nYear end bonus will be offered which makes up to totally 14 months salary per year.\n\nAfter completion of 1 year employment with the performance achieved more than 85% of the works assigned, we will offer at least 10% increase of the second year salary.\n\nOnly short listed candidates will be contacted.\u00a0 All personal information will be treated with strict confidence for recruitment purpose only, and will be disposed after six months.", "employment_types": ["Full Time", "Permanent"], "selling_points": ["To source and evaluate suppliers\u2019 abilities", "Form 7, DSE or above", "year end bonus"], "locations": ["Tsim Sha Tsui"], "categories": ["Admin & HR", "Clerical / Admin Staff", "Others", "Merchandising & Purchasing", "Procurement / Purchasing / Sourcing"], "post_time": "2022-01-17T07:09:33Z", "salary": {"currency": null, "max": null, "min": null, "period": "monthly", "term": null}, "salary_visible": false, "title_keywords": ["sourcing and administration officer"], "responsibilities": ["communicate with", "cost", "control", "ad-hoc duties", "office administration", "inventory", "monitoring", "quality", "analysis", "data input", "develop", "evaluate", "purchase", "reports", "database", "cost control", "prepare marketing materials", "report"], "requirements": {"degrees": ["dse"], "majors": [], "languages": ["english", "chinese", "mandarin"], "language_level": ["fluent"], "hard_skills": [], "soft_skills": ["communication skills", "work independently", "independently", "confidence", "negotiation", "clear", "can-do", "work under pressure"], "languages_combined": [{"language": "english", "language_level": ["fluent"]}, {"language": "chinese", "language_level": ["fluent"]}, {"language": "mandarin", "language_level": ["fluent"]}]}, "experience_required": {"duration": [], "field": []}}, {"job_id": "100003009053797", "location_code": "hk", "company": "De Wu (HK) Supply Chain Company Limited", "job_title": "\u5009\u52d9\u6587\u54e1", "description": "\n\u8077\u8cac :\u4e00\u822c\u5009\u52d9\u6587\u54e1\u5de5\u4f5c, \u8ca0\u8cac\u65e5\u5e38\u5009\u52d9\u904b\u4f5c\u53ca\u8ca8\u5009\u7ba1\u7406, \u6536\u8ca8\u3001\u51fa\u8ca8\u53ca\u9a57\u8ca8, \u5305\u88dd\u8ca8\u7269\u3001\u76e4\u9ede\u53ca\u6574\u7406\u8ca8\u5009, \u8ddf\u9032\u8a02\u55ae, \u66f4\u65b0\u5eab\u5b58\u8a18\u9304, \u62cd\u7167\u5b58\u6a94, \u8cc7\u6599\u8f38\u5165, \u8655\u7406\u7cfb\u7d71\u8cc7\u6599\u8f38\u5165\uff0c\u51fa\u5165\u53e3\u5831\u95dc\uff0c\u4e00\u822c\u5009\u52d9\u6587\u4ef6\uff1b\u5ba2\u6236\u670d\u52d9\uff1b\u8655\u7406/ \u8ddf\u9032\u7db2\u4e0a\u8a02\u55ae\n\n\u8cc7\u6b77 :\u4e2d\u4e94\u7a0b\u5ea6; 3\u5e74\u7d93\u9a57; \u826f\u597d\u7cb5\u8a9e\u512a\u5148; \u4e00\u822c\u666e\u901a\u8a71\u512a\u5148; \u4e00\u822c\u82f1\u8a9e\u512a\u5148; \u61c2\u8b80\u5beb\u4e2d\u6587; \u7565\u61c2\u8b80\u5beb\u82f1\u6587; \u5177\u6709\u4e00\u822c\u4e92\u806f\u7db2\u77e5\u8b58; \u61c2\u4e2d\u82f1\u6587\u96fb\u8166\u64cd\u4f5c; \u5177\u6709\u57fa\u672c\u96fb\u8166\u64cd\u4f5c\u77e5\u8b58; \u6709\u76f8\u95dc\u5009\u52d9\u6587\u66f8\u5de5\u4f5c\u7d93\u9a57\u512a\u5148\uff1b\u61c2\u5009\u52d9\u7cfb\u7d71\u61ee\u5148\n\n\u5f85\u9047 :\u6bcf\u6708$13,000 - $16,000, \u6709\u96d9\u7ce7, \u6bcf\u6708\u52e4\u5de5\u734e\u91d1$1000 \u53ca\u6bcf\u65e5\u4ea4\u901a\u6d25\u8cbc$40, \u4e0a\u53489\u6642\u81f3\u4e0b\u53486\u6642, \u6bcf\u9031\u5de5\u4f5c6\u5929,\u8f2a\u4f11, \u6bcf\u5929\u5de5\u4f5c 9 \u5c0f\u6642\n\n\u7533\u8acb\u9808\u77e5 :\u6c42\u8077\u8005\u53ef\u96fb\u90f5(Apply Now)\u5c65\u6b77\u8868\u7d66\u5f97\u7269(\u9999\u6e2f)\u4f9b\u61c9\u93c8\u6709\u9650\u516c\u53f8\u3002\u5982\u8981\u7d22\u53d6\u6536\u96c6\u500b\u4eba\u8cc7\u6599\u8072\u660e, \u8acb\u8207\u56b4\u5148\u751f(Email)\u806f\u7d61\u3002\n\n", "employment_types": ["Full Time"], "selling_points": [], "locations": ["Tin Shui Wai"], "categories": ["Admin & HR", "Clerical / Admin Staff", "Others"], "post_time": "2022-01-17T07:31:45Z", "salary": {"currency": null, "max": null, "min": null, "period": "monthly", "term": null}, "salary_visible": false, "title_keywords": ["\u5009\u52d9\u6587\u54e1"], "responsibilities": [], "requirements": {"degrees": [], "majors": [], "languages": [], "language_level": [], "hard_skills": [], "soft_skills": [], "languages_combined": []}, "experience_required": {"duration": [], "field": []}}, {"job_id": "100003009051782", "location_code": "hk", "company": "Hing Cheong Engineering (HK) Limited", "job_title": "Administrative Assistant / Office Assistant", "description": "\uff0eHong Kong Identity Card is a MUST\n\nJob Responsibilities\n\uff0eHandle administrative and clerical duties for the construction team;\n\uff0eTo provide general administrative support Project team, with any related tasks assigned\n\uff0eProvide support including filing, answering inquiry and data refreshment in website etc.\n\uff0eHard working & Responsible\n\uff0ePerform ad-hoc projects as assigned\n\uff0eReliable, Positive and Helpful\n\uff0eHandling telephone inquiries and messages, greeting guests\n\uff0eGeneral administration & HR support, mails and courier arrangement\n\uff0eClerical works and ad hoc assignments\n\uff0eSupport company functions/staff activities\n\nJob Requirements:\n\uff0eForm 5 (HKCEE)/ Form 6 (DSE) or above\n\uff0eGood command of both English and Chinese\n\uff0eProficient in Microsoft Office applications\n\uff0eFresh graduate are also welcome\n\uff0ePC knowledge in MS Office, Chinese Word Processing etc.\n\uff0eAble to work under pressure\n\uff0eImmediate available is preferred\n\nWe offer good career prospects and attractive remuneration to the right candidate, benefits including discretionary bonus\n\nInterested parties may send C.V. indicating expected salary by clicking 'Apply Now'.\n\nPersonal data collected will be used for recruitment purpose only.", "employment_types": ["Full Time"], "selling_points": [], "locations": ["Tuen Mun Area"], "categories": ["Admin & HR", "Clerical / Admin Staff", "Others"], "post_time": "2022-01-17T01:14:17Z", "salary": {"currency": null, "max": null, "min": null, "period": "monthly", "term": null}, "salary_visible": false, "title_keywords": ["administrative assistant", "office assistant"], "responsibilities": ["data", "hr", "general administrative support", "website", "ad hoc assignments", "ad-hoc projects", "administration"], "requirements": {"degrees": ["dse"], "majors": [], "languages": ["english", "chinese"], "language_level": [], "hard_skills": ["chinese word processing", "ms office", "microsoft office"], "soft_skills": ["work under pressure"], "languages_combined": [{"language": "english", "language_level": []}, {"language": "chinese", "language_level": []}]}, "experience_required": {"duration": [], "field": []}}, {"job_id": "100003009053753", "location_code": "hk", "company": "Hong Kong College of Engineering", "job_title": "\u517c\u8077\u884c\u653f\u6587\u54e1", "description": "\n\u8077\u8cac :\u63a5\u807d\u96fb\u8a71, \u4e00\u822c\u6821\u52d9\u53ca\u6587\u66f8\u5de5\u4f5c, \u5354\u52a9\u8b1b\u5e2b\u4f5c\u597d\u8ab2\u524d\u5404\u9805\u8a2d\u65bd\u6e96\u5099\u5de5\u4f5c, \u653e\u5de5\u7684\u6e96\u5099\u5de5\u4f5c, \u5354\u52a9\u5b78\u9662\u5176\u4ed6\u540c\u4e8b\u7684\u5de5\u4f5c\n\n\u8cc7\u6b77 :\u4e2d\u4e94\u7a0b\u5ea6; 2\u5e74\u7d93\u9a57; \u826f\u597d\u7cb5\u8a9e; \u4e00\u822c\u666e\u901a\u8a71; \u826f\u597d\u82f1\u8a9e\u512a\u5148; \u61c2\u8b80\u5beb\u4e2d\u6587; \u61c2\u8b80\u5beb\u82f1\u6587\n\n\u5f85\u9047 :\u6bcf\u5c0f\u6642$60.00, \u661f\u671f\u4e8c\u81f3\u516d: \u4e0b\u53486\u6642\u81f3\u4e0b\u534810\u6642\u53ca\u661f\u671f\u516d: \u4e0b\u53481\u6642\u81f3\u4e0b\u534810\u6642, \u6bcf\u9031\u5de5\u4f5c5\u5929,\u8f2a\u73ed, \u6bcf\u5929\u5de5\u4f5c 3 - 4 \u5c0f\u6642\n\n\u7533\u8acb\u9808\u77e5 :\u6c42\u8077\u8005\u53ef\u96fb\u90f5(Apply Now)\u5c65\u6b77\u8868\u7d66\u9999\u6e2f\u8a2d\u65bd\u5de5\u7a0b\u5b78\u9662\u3002\u5982\u8981\u7d22\u53d6\u6536\u96c6\u500b\u4eba\u8cc7\u6599\u8072\u660e, \u8acb\u8207\u6d82\u5973\u58eb(Tel:31658167 Ext.23)\u806f\u7d61\u3002\n\n", "employment_types": ["Part Time"], "selling_points": [], "locations": ["Mong Kok"], "categories": ["Admin & HR", "Clerical / Admin Staff", "Others"], "post_time": "2022-01-17T07:27:46Z", "salary": {"currency": null, "max": null, "min": null, "period": "hourly", "term": null}, "salary_visible": false, "title_keywords": [], "responsibilities": [], "requirements": {"degrees": [], "majors": [], "languages": [], "language_level": [], "hard_skills": [], "soft_skills": [], "languages_combined": []}, "experience_required": {"duration": [], "field": []}}, {"job_id": "100003009053516", "location_code": "hk", "company": "Eminence Plus", "job_title": "\u97f3\u6a02\u5b78\u6821\u63a5\u5f85\u54e1 Full time receptionist", "description": "\n\u00a0 \u8077\u8cac:\n\u2022 \u8655\u7406\u9867\u5ba2\u670d\u52d9\u5de5\u4f5c,\u5305\u62ec\u89e3\u7b54\u8ab2\u7a0b\u67e5\u8a62\u3001\u63a8\u5ee3\u8ab2\u7a0b\u53ca\u8655\u7406\u5831\u540d\u624b\u7e8c\n\u2022 \u8655\u7406\u6587\u66f8\u53ca\u884c\u653f\u5de5\u4f5c,\u5305\u62ec\u5b78\u8cbb\u53ca\u73fe\u91d1\u7ba1\u7406\u3001\u7de8\u6392\u4e0a\u8ab2\u6642\u9593\u8868\u7b49\n\u5165\u8077\u8981\u6c42:\n\u2022 \u6b61\u8fce\u4efb\u4f55\u4eba\u58eb\u7533\u8acb\n\u2022 \u826f\u597d\u6e9d\u901a\u6280\u5de7\u3001\u505a\u4e8b\u6574\u9f4a\u6709\u5e8f\u53ca\u80fd\u7368\u7acb\u8655\u7406\u5de5\u4f5c\n\u2022 \u6027\u683c\u958b\u6717\u3001\u6709\u611b\u5fc3\u548c\u8010\u6027\u3001\u559c\u6b61\u5c0f\u670b\u53cb,\u5177\u5718\u968a\u7cbe\u795e\n\u2022 \u826f\u597d\u5ee3\u6771\u8a71\n\u2022 \u719f\u6089\u4e2d\u6587\u8f38\u5165\u6cd5\n\u2022 \u6709\u7ba1\u7406\u7d93\u9a57\u6216\u6709\u92b7\u552e\u7d93\u9a57\u512a\u5148\n\u2022 \u80fd\u5373\u6642\u4e0a\u73ed\u8005\u512a\u5148\u8003\u616e\n\u5f85\u9047:\n\u2022 \u5728\u8077\u5de5\u4f5c\u57f9\u8a13\n\u2022 \u4e00\u661f\u671f5-6\u5929\u5de5\u4f5c\n\u2022 \u8868\u73fe\u512a\u7570\u8005,\u53ef\u7372\u767c\u52e4\u5de5\u734e\u53ca\u8868\u73fe\u734e\u91d1,\u4e26\u6709\u6a5f\u6703\u6649\u5347\n\u2022 \u6709\u54e1\u5de5\u6298\u6263\u53ca\u512a\u60e0\n\u2022 \u8212\u9069\u7684\u5de5\u4f5c\u74b0\u5883,\u5730\u9ede\u4fbf\u5229,\u6e2f\u9435\u53ef\u9054\n**\u6709\u610f\u8005\u8acb\u96fb\u90f5\u6309Apply Now\u63d0\u4ea4\u500b\u4eba\u5c65\u6b77\u53ca\u8981\u6c42\u5f85\u9047,\u4e26\u8acb\u8a3b\u660e\u7533\u8acb\u8077\u4f4d\u3002\u5982\u6709\u554f\u984c\u53efWHATSAPP 60677186\u67e5\u8a62\n*\u6ce8\u610f,\u53ea\u6709\u5165\u570d\u7533\u8acb\u4eba\u5c07\u88ab\u901a\u77e5\u3002\u6240\u6709\u6536\u96c6\u5230\u7684\u4fe1\u606f\u90fd\u5c07\u56b4\u683c\u4fdd\u5bc6,\u50c5\u7528\u65bc\u62db\u8058\u76ee\u7684\u3002\n\u00a0 Job Duties\n\u2022 To handle booking and requests with proper telephone manners\n\u2022 To greet customers\n\u2022 To arrange customer bookings and registrations upon visits\n\u2022 To perform day-to-day routine office administrative tasks\n\u2022 To perform other ad-hoc tasks as assigned\nRequirements\n\u2022 Good command of English and Cantonese\n\u2022 Strong communication, interpersonal, self-motivated and detail-oriented\nProficiency in MS Office (MS Word, Excel)\n\u2022 Excellent telephone manner with pleasant and professional attitudes\n\u2022 Experience in office administration function is an advantage\nBenefits\n\u2022 Professional on-the-job training\n\u2022 Good career prospects\n\u2022 Staff purchase and service discount\nInterested parties, please send email by clicking Apply Now, remark the applied position ,send your resume with start-date availability, your current and expected salary.\nPersonal data collected will be used for recruitment purposes only and kept confidential.\n\n", "employment_types": ["Full Time"], "selling_points": [], "locations": ["Not Specified"], "categories": ["Admin & HR", "Clerical / Admin Staff", "Receptionist", "Others"], "post_time": "2022-01-17T07:05:06Z", "salary": {"currency": null, "max": null, "min": null, "period": "monthly", "term": null}, "salary_visible": false, "title_keywords": ["receptionist"], "responsibilities": ["administrative tasks", "customer bookings", "ad-hoc tasks", "booking"], "requirements": {"degrees": [], "majors": [], "languages": ["cantonese", "english"], "language_level": ["good command"], "hard_skills": ["ms word", "excel", "ms office"], "soft_skills": ["self-motivated", "detail-oriented", "communication", "pleasant", "telephone manner", "interpersonal"], "languages_combined": [{"language": "cantonese", "language_level": ["good command"]}, {"language": "english", "language_level": ["good command"]}]}, "experience_required": {"duration": [], "field": ["office administration"]}}, {"job_id": "100003009052385", "location_code": "hk", "company": "Wecon Limited", "job_title": "Senior Administrative Assistant (12 months contract)", "description": "Job Descriptions:\nTo provide general clerical and administration support in construction site;\nTo handle and maintenance the attendance record of site staffs/Labourers;\nOther general administration duties\nRequirements:\nForm 5 or above;\nAbove 3 years site admin experience;\nProficiency in PC applications including MS Office and Chinese Word Processing;\nWilling to work at site office\nWe offer very attractive remuneration package and career advancement opportunities for the right candidates.\u00a0 Interested parties please send a covering letter and detailed resume including current and expected salary to the Head of HR & Admin, 18/F., Tung Hip Commercial Building, 244-252, Des Voeux Road Central, Hong Kong or by email via \"Apply Now\"\nPersonal data collected will be treated in strictest confidence and handled confidentially by authorized personnel for recruitment-related purposes only.\u00a0", "employment_types": ["Full Time", "Permanent"], "selling_points": [], "locations": ["Wong Tai Sin Area"], "categories": ["Admin & HR", "Clerical / Admin Staff", "Others", "Building & Construction", "Others"], "post_time": "2022-01-17T02:57:10Z", "salary": {"currency": null, "max": null, "min": null, "period": "monthly", "term": null}, "salary_visible": false, "title_keywords": ["senior administrative", "assistant"], "responsibilities": ["attendance", "maintenance", "administration"], "requirements": {"degrees": ["form 5 or above"], "majors": [], "languages": ["chinese"], "language_level": ["proficiency"], "hard_skills": ["chinese word processing", "ms office", "pc applications"], "soft_skills": [], "languages_combined": [{"language": "chinese", "language_level": ["proficiency"]}]}, "experience_required": {"duration": ["3 years"], "field": ["admin"]}}, {"job_id": "100003009052794", "location_code": "hk", "company": "Ferrari Logistics (Asia) Ltd", "job_title": "Accounts Clerk", "description": "Job Descriptions:\n\nAccounts receivables, invoicing and general accounting duties.\nWork closely with other department for daily operations.\nFiling and data entries.\nPrepare ad-hoc assignment from time to time assigned by Manager.\nRequirements:\nForm 5 or above.\nAt least 1 year of experience in accounting.\nProficiency in computer application, especially in MS Word and Excel.\nHigh threshold for paperwork and detail-minded.\nProficiency in both written and spoken English and Chinese\u00a0(Cantonese and Putonghua).\nImmediate availability is highly preferred.\nInterested parties please submit your FULL RESUME with AVAILABILITY, CURRENT and EXPECTED SALARY by clicking\u00a0APPLY NOW.\nAll information of candidates will be treated as strictly confidential and used for recruitment purposes only.\u00a0\u00a0", "employment_types": ["Full Time", "Permanent"], "selling_points": ["Accounts receivables", "Dynamic culture", "Excellent fringe benefits"], "locations": ["Kwai Hing"], "categories": ["Accounting", "Accounting Clerk / Supervisor", "Admin & HR", "Others"], "post_time": "2022-01-17T04:05:25Z", "salary": {"currency": null, "max": null, "min": null, "period": "monthly", "term": null}, "salary_visible": false, "title_keywords": ["accounts clerk"], "responsibilities": ["ad-hoc", "data", "invoicing", "daily operations", "general accounting duties"], "requirements": {"degrees": ["form 5 or above"], "majors": [], "languages": ["cantonese", "putonghua", "english", "chinese"], "language_level": ["proficiency"], "hard_skills": ["excel", "ms word"], "soft_skills": ["detail-minded"], "languages_combined": [{"language": "cantonese", "language_level": []}, {"language": "putonghua", "language_level": []}, {"language": "english", "language_level": ["proficiency"]}, {"language": "chinese", "language_level": ["proficiency"]}]}, "experience_required": {"duration": ["at least 1 year"], "field": ["accounting"]}}, {"job_id": "100003009053686", "location_code": "hk", "company": "United Asia Finance Limited", "job_title": "Administrative Assistant, Administration and Facilities Management", "description": "Job Responsibilities:\n\nManage various procurement related tasks assigned by supervisor such as procurement of branch staff uniform, marketing premium, software license renewal, different kinds of services etc.\nProvide full spectrum of daily office administrative support including but not limited to arrangement of office stationery and supplies, small office equipment, cleaning and pest control etc.\nAssist in checking and reconciling of petty cash fund for Head Office and branch offices\nAssist to manage receptionist and office assistants\n\nJob Requirements:\n\nDiploma or above in any disciplines\nAt least 3 years solid\u00a0general administration experience\nAbility to deal with different levels of external business partners / contractors\nAbility to work independently and able to work under pressure\nHave knowledge of central procurement will be an advantage but not a must\nGood command of spoken English, Cantonese and Putonghua a plus\nCandidate with more experience will be considered for the post of Officer, Administration and Facilities Management\n\nWe offer attractive remuneration package which includes double pay and discretionary bonus. Interested parties please send your CV indicating your current salary, expected salary and availability to HR Department, by email via \"Apply Now\"", "employment_types": ["Full Time", "Permanent"], "selling_points": ["Manage various procurement related tasks", "Diploma or above in any disciplines", "3 years solid general administration experience"], "locations": ["Wan Chai"], "categories": ["Admin & HR", "Administration / Operation Manager", "Clerical / Admin Staff", "Others"], "post_time": "2022-01-17T07:20:55Z", "salary": {"currency": null, "max": null, "min": null, "period": "monthly", "term": null}, "salary_visible": false, "title_keywords": ["administrative assistant"], "responsibilities": ["control", "software", "administrative support", "stationery", "checking", "cleaning"], "requirements": {"degrees": ["diploma or above"], "majors": ["any disciplines"], "languages": ["cantonese", "putonghua", "english"], "language_level": ["good command"], "hard_skills": ["facilities management", "plus"], "soft_skills": ["work independently", "work under pressure"], "languages_combined": [{"language": "cantonese", "language_level": ["good command"]}, {"language": "putonghua", "language_level": ["good command"]}, {"language": "english", "language_level": ["good command"]}]}, "experience_required": {"duration": ["at least 3 years"], "field": ["management", "administration"]}}, {"job_id": "100003009052110", "location_code": "hk", "company": "Chevalier Group - Corporate Office", "job_title": "Human Resources Officer", "description": "Our\u00a0Human Resources\u00a0Department is now inviting high calibre persons to apply for this position :\n\nResponsibilities\n\nWorking in the Corporate Human Resources Department of Chevalier Group, the incumbent will be responsible for the following duties:\n\nHandle full spectrum of Human Resources\u00a0functions including but not limited to recruitment & selection, compensation & benefits, payroll administration, performance management etc. for designated subsidiaries of the Group\nAssist in planning and organizing\u00a0various HR\u00a0activities for the Group including\u00a0employee welfare programs, interest classes,\u00a0job fairs etc.\nParticipate in\u00a0ad hoc HR assignments\nRequirements\n\nDegree holder in Human Resources Management, Business Administration,\u00a0Language Studies or other related disciplines\n4 years'\u00a0relevant working\u00a0experience in sizable company, some exposure in the engineering sector will be an advantage\nExperience in\u00a0processing payroll and recruitment\u00a0\nWell-versed in\u00a0Hong Kong Employment Ordinance\nDetail-minded, proactive,\u00a0outgoing personality and strong sense of responsibility\nExcellent\u00a0interpersonal and communications skills\nExcellent\u00a0command of both spoken and written English and\u00a0Chinese\nProficient in PC operations including MS Word, Excel, PowerPoint and Chinese word processing\n\nCandidate with more experience may be considered for the position of Senior Human Resources Officer.\n\nAttractive remuneration package will be offered to the right candidate. Interested parties, please send us your resume with current and expected salary by clicking \"Apply Now\" or mail to:\n\nThe Human Resources Manager, Chevalier Group, 22F, Chevalier\u00a0Commercial Centre,\u00a08\u00a0Wang Hoi\u00a0Road, Kowloon Bay, Hong Kong.\n\nWe are an equal opportunity employer and welcome applications from all qualified candidates. Personal data collected would be used for recruitment purpose only.", "employment_types": ["Full Time", "Permanent"], "selling_points": ["Perform full spectrum of HR duties", "Recruitment & Payroll knowledge", "4 yrs HR experience"], "locations": ["Kowloon Bay"], "categories": ["Admin & HR", "Others", "Compensation & Benefits", "HR Supporting Staff"], "post_time": "2022-01-17T02:07:06Z", "salary": {"currency": null, "max": null, "min": null, "period": null, "term": null}, "salary_visible": false, "title_keywords": ["human resources officer"], "responsibilities": ["management", "ad hoc", "hr", "planning", "recruitment", "payroll", "human resources functions", "administration"], "requirements": {"degrees": ["degree holder"], "majors": ["related disciplines", "business administration"], "languages": ["english", "chinese"], "language_level": ["excellent", "proficient"], "hard_skills": ["excel", "hong kong employment ordinance", "chinese word processing", "pc operations", "powerpoint", "processing", "ms word"], "soft_skills": ["detail-minded", "outgoing personality", "sense of responsibility", "proactive", "interpersonal"], "languages_combined": [{"language": "english", "language_level": ["excellent"]}, {"language": "chinese", "language_level": ["excellent", "proficient"]}]}, "experience_required": {"duration": ["4 years"], "field": ["engineering", "relevant working experience", "recruitment", "payroll", "human resources"]}}, {"job_id": "100003009052446", "location_code": "hk", "company": "AVT Design Architects Limited", "job_title": "Receptionist and Administration Clerk", "description": "Responsibilities\u00a0\u00a0\n\n\nHandle telephone calls, reception enquiries and guest greeting in a professional manner\nProvide clerical & administrative support including meeting room reservation, courier & mailing arrangement, flight & hotel bookings, management of warehouses, procurement, stationery and supplies,\u00a0etc\nCo-ordinate with internal & external parties including cleaning, maintenance for offices\nPerform other ad-hoc tasks as assigned\n\nRequirements\n\n\nForm 5 / DSE graduated or above\nPositive attitude, good interpersonal skills, telephone manner and communication skills\nCheerful, stable, well organized, detail-minded, self-motivated and able to work independently\nProficiency in MS Word, Excel, PowerPoint, English & Chinese Word Processing\nFluent in English, Chinese and Putonghua will be an advantage\nImmediate available preferred\n\n\u00a0\nBenefit\n\n\nMedical allowance\nFive-Day Work week\nBirthday Leave\u00a0\n\nPlease send us your application with current salary, expected salary and availability by clicking \"APPLY NOW\".\n\nAll personal information submitted to us is kept private and confidential and will be used for the recruitment purpose only.\u00a0", "employment_types": ["Full Time", "Permanent"], "selling_points": ["Detail-minded", "5 Days Work", "Initiative, Proactive"], "locations": ["Lai Chi Kok"], "categories": ["Admin & HR", "Others", "Manufacturing", "General / Production Workers", "Others"], "post_time": "2022-01-17T03:03:41Z", "salary": {"currency": null, "max": null, "min": null, "period": "monthly", "term": null}, "salary_visible": false, "title_keywords": ["receptionist", "clerk"], "responsibilities": ["management", "maintenance", "administrative support", "co-ordinate with", "ad-hoc tasks", "external parties", "professional manner", "stationery", "cleaning"], "requirements": {"degrees": ["form 5", "dse"], "majors": [], "languages": ["putonghua", "english", "chinese"], "language_level": ["advantage", "proficiency", "fluent"], "hard_skills": ["excel", "chinese word processing", "powerpoint", "ms word"], "soft_skills": ["detail-minded", "communication skills", "self-motivated", "cheerful", "work independently", "well organized", "positive attitude", "interpersonal skills", "stable", "telephone manner"], "languages_combined": [{"language": "putonghua", "language_level": ["advantage", "fluent"]}, {"language": "english", "language_level": ["advantage", "proficiency", "fluent"]}, {"language": "chinese", "language_level": ["advantage", "proficiency", "fluent"]}]}, "experience_required": {"duration": [], "field": []}}, {"job_id": "100003009053431", "location_code": "hk", "company": "Yang Dental Clinic", "job_title": "\u517c\u8077 / \u534a\u8077\u7259\u91ab\u52a9\u8b77 (\u591c\u8a3a) (PT / HTDSA) (Part-Time / Half-Time Dental Surgeon Assistant)", "description": "\n\u00a0 \u2022 \u4e2d\u5b78\u7a0b\u5ea6\uff1b\u64cd\u6d41\u5229\u7cb5\u8a9e\uff1b\u57fa\u672c\u82f1\u8a9e\u53ca\u666e\u901a\u8a71\uff1b\u57fa\u672c\u96fb\u8166\u64cd\u4f5c\u77e5\u8b58\n\u2022 \u6301\u6709\u7259\u79d1\u52a9\u8b77\u8b49\u66f8\u8005\u512a\u5148\n\u2022 \u9808\u6709\u76f8\u95dc\u5de5\u4f5c\u7d93\u9a57\n\u2022 \u5177\u5718\u968a\u5de5\u4f5c\u80fd\u529b\uff0c\u6709\u8cac\u4efb\u611f\n\u5de5\u4f5c\u6642\u9593\uff1a\u517c\u8077 (\u661f\u671f\u4e00\u81f3\u4e94\u665a\u4e0a 6 \u6642\u81f3 9 \u6642\uff1b\u661f\u671f\u516d\u4e0a\u5348 9 \u6642\u81f3\u4e0b\u5348 5 \u6642)\n\u2022 \u85aa\u91d1\u9762\u8b70\n\u2022 \u5de5\u4f5c\u5730\u9ede\uff1a\u4e5d\u9f8d\u5340\nEnquiries\n\u6709\u610f\u8005\u8acb\u9644\u5c65\u6b77\uff0c\u4fe1\u5c01\u9762\u8acb\u8a3b\u660e\u7533\u8acb\u8077\u4f4d\u53ca\u6642\u6bb5\uff0c\u96fb\u90f5\u6309Apply Now\u7533\u8acb\uff1b\u6216\u90f5\u5bc4\u81f3\u4e5d\u9f8d\u7aa9\u6253\u8001\u9053 54 \u865f 2 \u6a13 - \u4eba\u529b\u8cc7\u6e90 / \u884c\u653f\u90e8\u6536\u3002\u5408\u5247\u7d04\u898b\u3002\n\n\u7533\u8acb\u4eba\u6240\u63d0\u4f9b\u7684\u8cc7\u6599\u5c07\u4e88\u4fdd\u5bc6\u53ca\u53ea\u4f5c\u6709\u95dc\u8077\u4f4d\u7528\u9014\u3002\n\n", "employment_types": ["Part Time"], "selling_points": [], "locations": ["Not Specified"], "categories": ["Admin & HR", "Others", "Medical Services", "Others"], "post_time": "2022-01-17T06:58:52Z", "salary": {"currency": null, "max": null, "min": null, "period": "hourly", "term": null}, "salary_visible": false, "title_keywords": ["assistant"], "responsibilities": [], "requirements": {"degrees": [], "majors": [], "languages": [], "language_level": [], "hard_skills": [], "soft_skills": [], "languages_combined": []}, "experience_required": {"duration": [], "field": []}}, {"job_id": "100003009053901", "location_code": "hk", "company": "Globelink International Freight Forwarding (HK) Limited", "job_title": "\u7d93\u9a57\u7269\u6d41\u5165\u53e3\u8239\u52d9\u6587\u54e1", "description": "\n\u8077\u8cac :\u8ca0\u8cac\u7368\u7acb\u8655\u7406\u65e5\u5e38\u8239\u52d9\u51fa\u5165\u53e3\u5de5\u4f5c, \u806f\u7d61\u904b\u8f38\u53ca\u8239\u516c\u53f8\n\n\u8cc7\u6b77 :\u4e2d\u516d\u7a0b\u5ea6; 2\u5e74\u7d93\u9a57; \u826f\u597d\u7cb5\u8a9e; \u826f\u597d\u666e\u901a\u8a71\u512a\u5148; \u826f\u597d\u82f1\u8a9e\u512a\u5148; \u61c2\u8b80\u5beb\u4e2d\u6587; \u61c2\u8b80\u5beb\u82f1\u6587; \u53ef\u5373\u6642\u4e0a\u73ed\u512a\u5148\n\n\u5f85\u9047 :\u6bcf\u6708$12,000 - $14,000, \u6709\u6bcf\u6708\u52e4\u5de5\u734e\u91d1$450, \u9280\u884c\u5047\u671f, \u82b1\u7d05 \u53ca\u91ab\u7642\u798f\u5229, \u661f\u671f\u4e00\u81f3\u4e94: \u4e0a\u53489\u6642\u81f3\u4e0b\u53485\u6642\u534a\u53ca\u661f\u671f\u516d: \u4e0a\u53489\u6642\u81f3\u4e0b\u53481\u6642, \u6bcf\u9031\u5de5\u4f5c5\u5929\u81f35\u5929\u534a, \u6bcf\u5929\u5de5\u4f5c 7.5 - 8 \u5c0f\u6642, \u8a66\u7528\u671f\u5f8c\u661f\u671f\u516d\u8fd41\u500b\u9577\u90313\u500b\u77ed\u9031\n\n\u7533\u8acb\u9808\u77e5 :Apply Now INTERNATIONAL FREIGHT FORWARDING (HK) LIMITED,\u7d22\u53d6\u6536\u96c6\u500b\u4eba\u8cc7\u6599\u8072\u660e, \u8acb\u8207\u67ef\u5148\u751fEmail\u806f\u7d61\n\n", "employment_types": ["Full Time"], "selling_points": [], "locations": ["Kwun Tong"], "categories": ["Admin & HR", "Clerical / Admin Staff", "Others"], "post_time": "2022-01-17T07:43:46Z", "salary": {"currency": null, "max": null, "min": null, "period": "monthly", "term": null}, "salary_visible": false, "title_keywords": [], "responsibilities": [], "requirements": {"degrees": [], "majors": [], "languages": [], "language_level": [], "hard_skills": [], "soft_skills": [], "languages_combined": []}, "experience_required": {"duration": [], "field": []}}, {"job_id": "100003009053734", "location_code": "hk", "company": "Alpha Quant Financial Technology Limited", "job_title": "Accounting Clerk", "description": "\nJob Description\n-Reconciliation of bank statement and invoice\n-Perform daily accounting operations\n-Other ad hoc duties\nRequirements\n-Degree in Accounting/ other discipline\n-Proficiency in computer operations (PC, MS Office, Excel, Chinese word typing)\n-Experience and knowledge in accounting work\nSalary: Competitive, Negotiable\nJob Types: Full-time, Contract, Permanent\nJob Types: Full-time, Permanent, Contract\nSalary: $10,000.00 - $20,000.00 per month\nSchedule:\n\u2022 Monday to Friday\n\n", "employment_types": ["Full Time"], "selling_points": [], "locations": ["Tsim Sha Tsui"], "categories": ["Accounting", "Accounting Clerk / Supervisor", "Others", "Admin & HR", "Others"], "post_time": "2022-01-17T07:25:38Z", "salary": {"currency": null, "max": null, "min": null, "period": "monthly", "term": null}, "salary_visible": false, "title_keywords": ["accounting clerk"], "responsibilities": ["invoice", "daily accounting operations", "ad hoc duties"], "requirements": {"degrees": [], "majors": [], "languages": ["chinese"], "language_level": [], "hard_skills": ["excel", "typing", "word", "pc", "ms office"], "soft_skills": [], "languages_combined": [{"language": "chinese", "language_level": []}]}, "experience_required": {"duration": [], "field": []}}, {"job_id": "100003009053375", "location_code": "hk", "company": "Atlas Contract Manufacturing Limited", "job_title": "\u92b7\u552e\u8ddf\u55ae\u6587\u54e1**", "description": "\n\u8077\u8cac :\u8ca0\u8cac\u92b7\u552e\u3001\u8ddf\u55ae\u3001\u4e00\u822c\u6587\u66f8\u5de5\u4f5c\uff0c\u4ee5\u53ca\u7cfb\u7d71\u904b\u4f5c(\u5982\u8cc7\u6599\u8f38\u5165\u53ca\u6574\u7406\u5831\u544a)\uff1b\u8655\u7406\u8a02\u55ae\u8ddf\u9032\u3001\u8207\u5ba2\u6236\u548c\u5de5\u5ee0\u5354\u8abf\uff0c\u63a1\u8cfc\u3001\u5b89\u6392\u751f\u7522\u3001\u51fa\u8ca8\u8ddf\u9032(5\u5e74\u6216\u4ee5\u4e0a\u6709\u95dc\u7d93\u9a57)\n\n\u8cc7\u6b77 :\u4e2d\u4e94\u7a0b\u5ea6; 5\u5e74\u7d93\u9a57; \u826f\u597d\u7cb5\u8a9e; \u4e00\u822c\u666e\u901a\u8a71; \u4e00\u822c\u82f1\u8a9e; \u61c2\u95b1\u8b80\u4e2d\u6587; \u7565\u61c2\u8b80\u5beb\u82f1\u6587; \u61c2\u96fb\u5b50\u5831\u95dc; \u61c2\u8655\u7406\u51fa\u5165\u53e3\u6587\u4ef6; \u61c2\u82f1\u6587\u6253\u5b57; \u61c2\u4e2d\u6587\u6253\u5b57; \u5177\u6709\u57fa\u672c\u96fb\u8166\u64cd\u4f5c\u77e5\u8b58; \u9700\u5177\u71df\u696d\u9032\u51fa\u53e3\u53ca\u5831\u95dc\u7d93\u9a57,\u61c2\u8239\u52d9\u8655\u7406,\u6709\u5927\u9678\u5de5\u5ee0\u5c0d\u63a5\u7d93\u9a57,\u6709\u8cac\u4efb\u611f,\u52e4\u596e\u4e3b\u52d5,\u80fd\u7368\u7acb\u8655\u4e8b\n\n\u5f85\u9047 :\u6bcf\u6708$16,000 - $18,000, \u6709\u96d9\u7ce7, \u9280\u884c\u5047\u671f\u53ca\u5e74\u7d42\u734e\u91d1, \u661f\u671f\u4e00\u81f3\u4e94: \u4e0a\u53489\u6642\u81f3\u4e0b\u53486\u6642, \u6bcf\u9031\u5de5\u4f5c5\u5929, \u6bcf\u5929\u5de5\u4f5c 8 \u5c0f\u6642\n\n\u7533\u8acb\u9808\u77e5 :\u6c42\u8077\u8005\u53ef\u96fb\u90f5(Apply Now)\u5c65\u6b77\u8868\u7d66\u5929\u9df9\u8a2d\u5099\u88fd\u9020\u6709\u9650\u516c\u53f8\u3002\u5982\u8981\u7d22\u53d6\u6536\u96c6\u500b\u4eba\u8cc7\u6599\u8072\u660e, \u8acb\u8207\u6881\u5c0f\u59d0(Email)\u806f\u7d61\u3002\n\n", "employment_types": ["Full Time"], "selling_points": [], "locations": ["Shatin Area"], "categories": ["Admin & HR", "Clerical / Admin Staff", "Others"], "post_time": "2022-01-17T06:53:14Z", "salary": {"currency": null, "max": null, "min": null, "period": "monthly", "term": null}, "salary_visible": false, "title_keywords": [], "responsibilities": [], "requirements": {"degrees": [], "majors": [], "languages": [], "language_level": [], "hard_skills": [], "soft_skills": [], "languages_combined": []}, "experience_required": {"duration": [], "field": []}}, {"job_id": "100003009053986", "location_code": "hk", "company": "Kee Wah Group Limited", "job_title": "Human Resources Assistant", "description": "Responsibilities\n\nPerform Human Resources functions including but not limited to recruitment, manpower planning, compensation & benefits administration, employee relation and other related HR services\nParticipate in the full cycle of front line\u00a0recruitment process such as exploring new recruitment channels, preparing recruitment advertisement, screening, interviewing, selecting, on-boarding arrangements and induction for new joiners\nAssist in company events and activities\nPrepare and consolidate HR reports timely & accurately\nMaintain systematic personnel records and document filings\nHandle ad hoc assignments as assigned\nRequirements\n\nHigher diploma or above in Human Resources Management, Business Administration or related disciplines\n1-2 years relevant experience\nSelf-motivated, mature and can work independently\nGood command in both written and spoken English and Chinese\nFamiliar with MS Office applications, especially in Excel\u00a0(e.g. VLOOKUP\u00a0and Pivot table etc.) and Chinese Word Processing\nCandidate with more experience will be considered as\u00a0Assistant Human Resources Officer\u00a0\nPlease apply with detailed resume, stating current and expected salary, availability and quoting the Employer Reference Number.\n(Personal data\u00a0relating to employment applications will be used for recruitment only)", "employment_types": ["Full Time", "Permanent"], "selling_points": ["Excellent career development opportunity", "Leading brand and sizable company", "Competitive pay and benefits"], "locations": ["Not Specified"], "categories": ["Admin & HR", "Others", "HR Supporting Staff", "Recruitment / Executive Search"], "post_time": "2022-01-17T07:55:44Z", "salary": {"currency": null, "max": null, "min": null, "period": "monthly", "term": null}, "salary_visible": false, "title_keywords": ["human resources assistant"], "responsibilities": ["hr", "personnel records", "hr reports", "planning", "recruitment", "maintain", "ad hoc assignments", "recruitment process", "human resources functions", "administration"], "requirements": {"degrees": ["higher diploma or above"], "majors": ["related disciplines", "business administration"], "languages": ["english", "chinese"], "language_level": ["good command"], "hard_skills": ["excel", "chinese word processing", "pivot table", "vlookup", "ms office"], "soft_skills": ["self-motivated", "work independently", "mature", "detailed"], "languages_combined": [{"language": "english", "language_level": ["good command"]}, {"language": "chinese", "language_level": ["good command"]}]}, "experience_required": {"duration": ["1-2 years"], "field": ["relevant experience", "human resources"]}}, {"job_id": "100003009053630", "location_code": "hk", "company": "Continental Global Service Limited", "job_title": "\u5009\u52d9\u6587\u54e1", "description": "\n\u8077\u8cac:\n\u2022 \u8ca0\u8cac\u9032\u8ca8\u6e05\u9ede\u3001\u9a57\u6536\u3001\u7406\u8ca8\u3001\u5305\u88dd\u51fa\u8ca8\u3001\u76e4\u9ede\u3001\u6574\u7406\u8ca8\u5009\u7b49\u65e5\u5e38\u5009\u52d9\u5de5\u4f5c\n\u2022 \u9032\u51fa\u8ca8\u7269\u6587\u4ef6\u8655\u7406\u3001\u5c0d\u55ae\u3001\u96fb\u5b50\u5831\u95dc\u3001\u7463\u788e\u96dc\u52d9\n\u2022 \u8655\u7406\u7c21\u55ae\u6587\u66f8\u53ca\u76f8\u95dc\u5831\u8868\n\u2022 \u8655\u7406\u5009\u5b58\u8cc7\u6599\u8f38\u5165\u53ca\u66f4\u65b0\u7cfb\u7d71\uff0c\u5eab\u5b58\u7a7a\u9593\u6574\u7406\u53ca\u898f\u5283\uff0c\u6307\u6d3e\u7269\u6d41\u5de5\u4f5c\n\u2022 \u4e00\u822c\u5009\u52d9\u6587\u54e1\u5de5\u4f5c\uff0c\u5354\u52a9\u4e3b\u7ba1\u8655\u7406\u65e5\u5e38\u5009\u5132\u904b\u4f5c\n\u8981\u6c42:\n\u2022 \u4e2d\u4e94\u6216\u4ee5\u4e0a\u7a0b\u5ea6\n\u2022 \u5177\u4e09\u5e74\u5009\u52d9\u6216\u8ca8\u7269\u88dd\u904b\u5de5\u4f5c\u7d93\u9a57, \u512a\u5148\u8003\u616e\n\u2022 \u6709\u96fb\u8166\u64cd\u4f5c\u7d93\u9a57, \u5305\u62ecWord and Excel\n\u2022 \u61c2\u95b1\u8b80\u53ca\u66f8\u5beb\u4e2d\u3001\u82f1\u6587\n\u2022 \u7d30\u5fc3\u3001\u6709\u79ae\u8c8c\u3001\u8aa0\u5be6\u3001\u6709\u8cac\u4efb\u5fc3\u3001\u826f\u597d\u7684\u6e9d\u901a\u80fd\u529b\n\u2022 \u80fd\u5373\u6642\u4e0a\u4efb\u8005\u512a\u5148\u8003\u616e\n\u5de5\u4f5c\u5730\u9ede: \u89c0\u5858\n\u5de5\u4f5c\u6642\u9593:\nFT: \u661f\u671f\u4e00\u81f3\u4e94: 10:00am-7:00pm; \u661f\u671f\u516d: 10:00am-5:00pm\nPT: \u661f\u671f\u4e00\u81f3\u516d: 12:00nn-6:00pm\n\u798f\u5229:\n\u2022 \u6cd5\u5b9a\u5047\u671f\n\u2022 \u8d85\u6642\u6d25\u8cbc\n\u2022 \u5e74\u5047\n\u2022 \u5a5a\u5047\n\u2022 \u751f\u65e5\u5047\n\u2022 \u7522\u5047/\u4f8d\u7522\u5047\n\u2022 \u91ab\u7642\u798f\u5229\n\u2022 \u826f\u597d\u5de5\u4f5c\u74b0\u5883\n\n\u6709\u610f\u7533\u8acb\u4ee5\u4e0a\u8077\u4f4d\u8005\uff0c\u53ef\u81f4\u96fb3955 Apply Now\u3002\n\uff08\u6240\u6709\u6536\u96c6\u5230\u7684\u8cc7\u6599\u53ea\u7528\u65bc\u62db\u8058\u7528\u9014\uff09\n\n", "employment_types": ["Full Time"], "selling_points": [], "locations": ["Kwun Tong"], "categories": ["Admin & HR", "Clerical / Admin Staff", "Others"], "post_time": "2022-01-17T07:16:08Z", "salary": {"currency": null, "max": null, "min": null, "period": "monthly", "term": null}, "salary_visible": false, "title_keywords": ["\u5009\u52d9\u6587\u54e1"], "responsibilities": [], "requirements": {"degrees": [], "majors": [], "languages": [], "language_level": [], "hard_skills": ["excel"], "soft_skills": [], "languages_combined": []}, "experience_required": {"duration": [], "field": []}}, {"job_id": "100003009054878", "location_code": "hk", "company": "Cathay Pacific Services Limited", "job_title": "Administrative Officer", "description": "Responsibilities\nProvide general administrative supports to the company\nHandle stationery order, company car booking, car park management, small equipment & warranty handling and etc.\nHandle Duty Travel arrangement for concern parties including ticket, accommodation and etc.\nPerform delivery and outdoor tasks including dispatch of mail / documents and etc.\nInvolve in office supplies and services purchasing.\nAssist in corporate activities coordination, such as festival office decoration, lion dance and etc.\nAdministrative support to Executive Office if necessary.\nCo-ordinate and handle ad hoc duties as assigned.\nRequirement\nUniversity graduate in related discipline or equivalent.\n1-2 years working experience in Administration functions.\nKnowledge and experience in SAP system are highly preferred\nPossessing of valid Hong Kong Driving License (class 1 and 2) is preferable.\nGood communication and interpersonal skill.\nAble to work independently, be proactive and be a good team player.\nGood numerical sense, detail-minded, and multi-tasking capability.\nHands-on experience of MS Word and Excel.\nProficiency in English and Chinese.\nImmediately available is highly preferred\n\nTo apply,\u00a0you may email your confidential resume with date of availability, current and expected salary to\u00a0recruitment @cpsl.com.hk.\u00a0Applicants not contacted within 6 weeks may consider their applications unsuccessful.\n\nCathay Pacific Services Limited is an Equal Opportunities Employer. Personal data provided by job applicants will be used strictly in accordance with our personal data policy and for recruitment purposes only. Candidates not notified within six weeks may consider their application unsuccessful. All related information will be kept in our file for up to 24 months.", "employment_types": ["Full Time", "Permanent"], "selling_points": ["Provide general administrative supports", "Perform delivery and outdoor tasks", "Involve in office supplies and services purchasing"], "locations": ["Airport Area"], "categories": ["Admin & HR", "Clerical / Admin Staff", "Others", "Transportation & Logistics", "Aviation Services"], "post_time": "2022-01-17T12:19:49Z", "salary": {"currency": null, "max": null, "min": null, "period": "monthly", "term": null}, "salary_visible": false, "title_keywords": ["administrative officer"], "responsibilities": ["ad hoc duties", "management", "administrative support", "office supplies", "stationery", "booking", "travel arrangement", "coordination"], "requirements": {"degrees": ["university graduate"], "majors": [], "languages": ["english", "chinese"], "language_level": ["proficiency"], "hard_skills": ["excel", "sap", "ms word"], "soft_skills": ["detail-minded", "good team player", "work independently", "interpersonal skill", "communication", "multi-tasking", "hands-on", "proactive"], "languages_combined": [{"language": "english", "language_level": ["proficiency"]}, {"language": "chinese", "language_level": ["proficiency"]}]}, "experience_required": {"duration": ["1-2 years"], "field": ["administration"]}}, {"job_id": "100003009053411", "location_code": "hk", "company": "United CPA & Co.", "job_title": "General Office Clerk", "description": "\nRequirements :-\u00a0\nSecondary school graduated\nGood PC knowledge in MS Office and Chinese word processing\nGood communication skill\nMandarin and English\n\u00a0 Job duties :-\u00a0\nGeneral clerical duties, including filing, data input, photocopying, preparing reports etc.\nHandling telephone calls, telephone answering.\nArrange document courier.\n\u00a0 \u00a0 Interested parties please email resume with expected salary by clicking Apply Now\n(Personal data collected will only be used for recruitment purpose)\n\n", "employment_types": ["Full Time"], "selling_points": [], "locations": ["Not Specified"], "categories": ["Admin & HR", "Clerical / Admin Staff", "Others"], "post_time": "2022-01-17T06:56:46Z", "salary": {"currency": null, "max": null, "min": null, "period": "monthly", "term": null}, "salary_visible": false, "title_keywords": ["office clerk"], "responsibilities": ["data input", "preparing reports"], "requirements": {"degrees": [], "majors": [], "languages": ["english", "chinese", "mandarin"], "language_level": ["good"], "hard_skills": ["pc knowledge", "chinese word processing", "ms office"], "soft_skills": ["communication skill"], "languages_combined": [{"language": "english", "language_level": []}, {"language": "chinese", "language_level": ["good"]}, {"language": "mandarin", "language_level": []}]}, "experience_required": {"duration": [], "field": []}}, {"job_id": "100003009054409", "location_code": "hk", "company": "Atkins China Ltd", "job_title": "Junior Clerk", "description": "Responsibilities:\n\nProvide clerical duties to the project team: typing, filing, register\u00a0correspondence and report\u2019s preparation;\nAssist with ad-hoc duties when required;\nRequirements:\nF.5 or above;\nMin. 3 years' relevant experience, preferably has experience in construction industry;\nProficiency in MS Office (Word, Excel & PowerPoint) and Chinese Word Processing;\nGood command of written and spoken English and Chinese;\nInitiative and able to organize work efficiently and independently;\nStrong communication and interpersonal skills; and\nImmediate available is preferred.\n\nFor interested parties, please submit your application with detailed resume, current and expected salary by clicking \"Apply Now\".\n\nApplications will be treated in confidence and only be used for recruitment purposes. Those not being invited for interview within 3 months may consider their applications unsuccessful.", "employment_types": ["Full Time", "Contract"], "selling_points": ["3 years+ admin background", "HKCEE  / DSE or above", "Familiar with MS Office including Word & Excel"], "locations": ["Tsim Sha Tsui"], "categories": ["Admin & HR", "Clerical / Admin Staff", "Others", "Engineering", "Others"], "post_time": "2022-01-17T09:25:46Z", "salary": {"currency": null, "max": null, "min": null, "period": "monthly", "term": null}, "salary_visible": false, "title_keywords": ["junior clerk"], "responsibilities": ["ad-hoc duties", "report"], "requirements": {"degrees": [], "majors": [], "languages": ["english", "chinese"], "language_level": ["proficiency", "good command"], "hard_skills": ["excel", "chinese word processing", "word", "powerpoint", "ms office"], "soft_skills": ["independently", "initiative", "communication and interpersonal skills"], "languages_combined": [{"language": "english", "language_level": ["good command"]}, {"language": "chinese", "language_level": ["proficiency", "good command"]}]}, "experience_required": {"duration": ["3 years"], "field": ["construction industry", "relevant experience"]}}, {"job_id": "100003009054488", "location_code": "hk", "company": "JH Partners (Asia) Company Limited", "job_title": "HR & Admin Officer - Crypto Exchange", "description": "Our client is a leading crypto exchange who is looking for a HR & Admin officer.\n\nResponsibilities\n\nAssist\u00a0in\u00a0the\u00a0full\u00a0spectrum\u00a0of\u00a0Human\u00a0Resources\u00a0Duties\u00a0such\u00a0as\u00a0Compensation\u00a0and Benefits,\u00a0recruitment,\u00a0payroll,\u00a0and\u00a0MPF\u00a0calculation,\u00a0employee\u00a0attendance,\u00a0leave\u00a0record,\u00a0staff\u00a0recreation\u00a0activities.\nPerform\u00a0Personnel\u00a0information\u00a0entry\u00a0and\u00a0personnel\u00a0record\u00a0filing,\u00a0manage\u00a0the\u00a0employee\u00a0life\u00a0cycle\u00a0by\u00a0starting\u00a0from\u00a0the\u00a0entry,\u00a0probationary\u00a0review,\u00a0follow-up\u00a0and\u00a0resignation\u00a0process.\nUpdate\u00a0and\u00a0review\u00a0employee\u00a0handbook\u00a0with\u00a0newly\u00a0Human\u00a0Resources\u00a0policies\u00a0and\u00a0procedures\u00a0from\u00a0time\u00a0to\u00a0time\u00a0in\u00a0compliance\u00a0with\u00a0Labour\u00a0Ordinance,\u00a0MPF\u00a0Ordinance,\u00a0and\u00a0Inland\u00a0Revenue\u00a0Ordinance.\nProvide\u00a0office\u00a0administration\u00a0support.\nAssist\u00a0in\u00a0other\u00a0ad-hoc\u00a0assignments.\n\nRequirements\n\nDiploma\u00a0holder\u00a0or\u00a0above\u00a0in\u00a0Human\u00a0Resources\u00a0management\u00a0or\u00a0related\u00a0discipline.\nAt\u00a0least\u00a05\u00a0years\u00a0solid\u00a0experience\u00a0in\u00a0Human\u00a0Resources\u00a0related\u00a0experience.\nHaving\u00a0Human\u00a0Resources\u00a0related\u00a0experience\u00a0in\u00a0Internet\u00a0industry\u00a0or\u00a0Financial\u00a0industry\u00a0is\u00a0preferred\nGood\u00a0knowledge\u00a0in\u00a0HK\u00a0Employment\u00a0Ordinance,\u00a0Employee\u00a0Compensation\u00a0Ordinance,\u00a0MPF\u00a0and\u00a0other\u00a0Human\u00a0Resources\u00a0related\u00a0statutory\u00a0regulations\nGood\u00a0command\u00a0of\u00a0written\u00a0and\u00a0spoken\u00a0English\u00a0and\u00a0Mandarin.\u00a0\u00a0\u00a0\nGood\u00a0PC\u00a0knowledge\u00a0in\u00a0MS\u00a0office\u00a0and\u00a0Foxmail.\nself-motivated,\u00a0details-oriented,\u00a0well-organized,\u00a0responsible\u00a0and\u00a0capable\u00a0to\u00a0cope\u00a0with\u00a0multi-tasks\u00a0well.", "employment_types": ["Full Time"], "selling_points": ["Human Resources", "Admin", "Crypto"], "locations": ["Not Specified"], "categories": ["Admin & HR", "Others"], "post_time": "2022-01-17T09:45:24Z", "salary": {"currency": null, "max": null, "min": null, "period": "monthly", "term": null}, "salary_visible": false, "title_keywords": ["officer", "hr", "admin"], "responsibilities": ["attendance", "office administration support", "mpf", "policies", "ad-hoc assignments", "review", "procedures", "compliance", "recruitment", "payroll"], "requirements": {"degrees": ["diploma holder"], "majors": [], "languages": ["english", "mandarin"], "language_level": ["good command"], "hard_skills": ["pc knowledge", "ms office"], "soft_skills": ["self-motivated", "capable", "multi-tasks", "responsible", "well-organized"], "languages_combined": [{"language": "english", "language_level": ["good command"]}, {"language": "mandarin", "language_level": ["good command"]}]}, "experience_required": {"duration": ["at least 5 years"], "field": ["related", "financial industry", "human resources"]}}, {"job_id": "100003009001286", "location_code": "hk", "company": "Lik On Security Limited", "job_title": "Senior Project Engineer", "description": "\u00a0Job Responsibilities:\n\n\n\nOrganize/follow ELV/Security system and the installation work\nResponsible for design submission, planning, supervision and monitoring\nEnsure working procedure, inspection and quality standard\nLiaise with suppliers for technical purchasing\nLiaise with customers for job specification\n\nJob Requirements:\u00a0\n\n\nAssociate Degree or above in Electronic/Computer/Communication engineering\n3 years or above working experience in project co-ordination\u00a0is preferred\nWell versed in MS office and Auto CAD applications\nGood command of English, Mandarin and Cantonese\nGood project handling, presentation, communication and interpersonal skills\nStrong logical thinking, well organization, energetic and sense of responsibility\n\nGood remuneration and attractive benefits will be offered to the right person. Interested parties please send full resume with expected salary via \"APPLY NOW\"\u00a0or by fax:\u00a02552-1888\u00a0or by post to\u00a0The Human Resources and Administration Department \u2013 Recruitment & Selection Section, Lik On Security Limited,\u00a08/F, Cheung Lung Industrial Building, 10 Cheung Yee Street, Cheung Sha Wan Kowloon\u00a0or\u00a0call\u00a02485-2485\u00a0for interview.\n\nWe are an Equal Opportunity Employer. Personal data collected will be used for recruitment purpose only.", "employment_types": ["Full Time", "Permanent"], "selling_points": ["Associate Degree or above in Electronic / Computer", "3 yrs or above working exp in proj co-ordination", "Organize/follow ELV/Security system"], "locations": ["Cheung Sha Wan"], "categories": ["Admin & HR", "Clerical / Admin Staff", "Receptionist", "Others"], "post_time": "2022-01-16T21:50:07Z", "salary": {"currency": null, "max": null, "min": null, "period": "monthly", "term": null}, "salary_visible": false, "title_keywords": ["senior project engineer"], "responsibilities": ["installation", "monitoring", "quality", "design", "inspection", "liaise with", "liaise with suppliers", "planning"], "requirements": {"degrees": ["degree or above"], "majors": ["engineering"], "languages": ["cantonese", "english", "mandarin"], "language_level": ["good command"], "hard_skills": ["auto cad", "ms office"], "soft_skills": ["sense of responsibility", "communication", "communication and interpersonal skills", "energetic", "presentation"], "languages_combined": [{"language": "cantonese", "language_level": ["good command"]}, {"language": "english", "language_level": ["good command"]}, {"language": "mandarin", "language_level": ["good command"]}]}, "experience_required": {"duration": ["3 years"], "field": []}}, {"job_id": "100003009052959", "location_code": "hk", "company": "NexLen International Limited", "job_title": "Administrator", "description": "Job Responsibilities\n\nReceptionist\nMaintain inventory control for Sales and Purchases\nArranging courier / delivery issues\nProvide office administration support\nAd hoc tasks by managersInvioce issuing\n\nRequirements\n\n2-3 years' solid experience\nProficient in MS office especially in MS word, MS Excel\nGood communication skill, outgoing and self-motivated personality is required\nGood team player, willing to work under pressure and tight schedule\nGood command of both spoken and written English and Chinese\n\nWe offer attractive salary and fringe benefit package to the right candidate. Interested parties please send full resume with expected salary.\n\nPersonal data provided in your application will be kept in the strictest confidence. It will be used for employment-related purposes. Applications not notified within 1 month will be considered as unsuccessful. Unsuccessful application may be kept for another 3 months for new openings before properly shredded.", "employment_types": ["Full Time", "Permanent"], "selling_points": ["Salary package", "5-day working", "2-3 years' solid experience"], "locations": ["Kwun Tong"], "categories": ["Admin & HR", "Administration / Operation Manager", "Clerical / Admin Staff", "Others"], "post_time": "2022-01-17T04:42:30Z", "salary": {"currency": null, "max": null, "min": null, "period": "monthly", "term": null}, "salary_visible": false, "title_keywords": ["administrator"], "responsibilities": ["office administration support", "delivery issues", "ad hoc tasks", "inventory control", "maintain"], "requirements": {"degrees": [], "majors": [], "languages": ["english", "chinese"], "language_level": ["good command"], "hard_skills": ["ms word", "ms excel", "ms office"], "soft_skills": ["outgoing", "good team player", "self-motivated", "communication skill", "work under pressure"], "languages_combined": [{"language": "english", "language_level": ["good command"]}, {"language": "chinese", "language_level": ["good command"]}]}, "experience_required": {"duration": ["2-3 years"], "field": []}}, {"job_id": "100003009054093", "location_code": "hk", "company": "Taste of Asia Group Limited", "job_title": "HR & Admin Assistant", "description": "Job Description:\n\nResponsible for performing all-round Human Resources duties mainly on compensation & benefits and recruitment & selection\nMaintain staff record and HR system including payroll calculation\nHandle work injury case, MPF and taxation independently\nExecute recruitment activities including career fair, recruitment day, remaining contact with NGO and others\nAssist to develop and implement HR policies and procedures\nPerform other ad hoc duties as assigned\n\nRequirement:\n\nDiploma in Human Resources Management\u00a0or related discipline\nAt least\u00a01\u00a0year experience, preferably in F&B industry\nWilling to accept challenge\nWell-versed in Hong Kong Employment Ordinance, MPF regulations and other related legislation would be an advantage\nProficient in MS Office applications and Chinese Word Processing\nGood command of spoken and written English & Chinese\nMature team player with strong communication and interpersonal skills\nFresh graduates will also be considered\nImmediate available is highly preferred\n\n\u00a0Job location: San Po Kong\n\nCompetitive remuneration package and benefits as below:\n\nFive-day work week\n\nMarriage leave\n\nStaff discount\n\nMedical & dental allowance\n\nPerformance bonus\n\nIn-service training course\n\n5 days paternity leave\n\nCompassionate Leave\n\nPromotion opportunities\n\nInterested parties may send your detailed resume with\u00a0expected salary\u00a0and\u00a0notice period\u00a0by\u00a0clicking \"Apply Now\"\n\nAll information collected will be used for recruitment purpose only.", "employment_types": ["Full Time"], "selling_points": ["Five-day work week", "Medical & dental allowance", "Performance bonus"], "locations": ["Wong Tai Sin Area"], "categories": ["Admin & HR", "Others", "HR Supporting Staff", "Recruitment / Executive Search"], "post_time": "2022-01-17T08:22:19Z", "salary": {"currency": null, "max": null, "min": null, "period": "monthly", "term": null}, "salary_visible": false, "title_keywords": ["hr & admin assistant"], "responsibilities": [], "requirements": {"degrees": [], "majors": [], "languages": [], "language_level": [], "hard_skills": [], "soft_skills": [], "languages_combined": []}, "experience_required": {"duration": [], "field": []}}, {"job_id": "100003009052280", "location_code": "hk", "company": "Cheung Hing Lifting Components (Hong Kong) Limited", "job_title": "Secretary", "description": "Responsibilities:\n\nPrepare quotations, tender documents and contracts\nResponsible for coordination with oversea manufacturers\nPrepare marketing materials and supporting documents\nResponsible for general office administration works\nCarry out duties and works assigned by directors\n\nRequirements:\n\nForm 7, DSE or above.\nAt least 2 years working experience at similar nature of works.\nPositive \u201ccan-do\u201d attitude.\nEager to learn and take up responsibility.\nCan work under pressure and tight deadline schedule.\nHonest and loyal to company.\nCan communicate with spoken English and Mandarin.\nImmediate availability is preferable.\nWorking on one Saturday morning for every month is required.\n\nSalary and Prospect:\n\n\nAfter successfully completion of probation period, we may offer mid year and year end bonus which makes up to totally 14 months salary per year if performance is above average.\n\nWe may also offer gratuity for working in the company after every three years if performance is above average.\n\nCandidate with good performance can be promoted to Assistant to Director.\n\nPlease send your curriculum vitae with expected salary by clicking 'Apply Now'.\n\nOnly short listed candidates will be contacted.\u00a0 All personal information will be treated with strict confidence for recruitment purpose only, and will be disposed after six months.", "employment_types": ["Full Time", "Permanent"], "selling_points": ["Responsible for preparing quotations and contracts", "Responsible for general office administration work", "."], "locations": ["Tsim Sha Tsui"], "categories": ["Admin & HR", "Clerical / Admin Staff", "Secretary", "Others"], "post_time": "2022-01-17T02:38:48Z", "salary": {"currency": null, "max": null, "min": null, "period": "monthly", "term": null}, "salary_visible": false, "title_keywords": ["secretary"], "responsibilities": ["tender documents", "contracts", "office administration", "coordination with", "prepare marketing materials"], "requirements": {"degrees": ["dse"], "majors": [], "languages": ["english", "mandarin"], "language_level": [], "hard_skills": [], "soft_skills": ["confidence", "eager to learn", "can-do", "honest", "loyal", "positive", "work under pressure"], "languages_combined": [{"language": "english", "language_level": []}, {"language": "mandarin", "language_level": []}]}, "experience_required": {"duration": ["at least 2 years"], "field": []}}, {"job_id": "100003009053535", "location_code": "hk", "company": "St. Francis' Canossian College", "job_title": "Library Assistant", "description": "\n\u5609\u8afe\u6492\u8056\u65b9\u6fdf\u5404\u66f8\u9662 St. Francis\u2019 Canossian College\nLibrary Assistant\nRequirements:\nDegree Holder or above. Good IT skills. Good communication skills in both English and Chinese.\nInterested parties are invited to send their applications, enclosing full resumes stating qualifications, career history, aspirations and contact numbers latest by 31 January 2022 to:\nThe Principal\nSt. Francis\u2019 Canossian College\n9 \u2013 13 Kennedy Road, Wanchai, Hong Kong\nOr via email to: Apply Now\nInformation/ Personal data collected will be used for employment purposes only.\nPlease specify the applied position on the envelope or in the email.\n\u5b78\u6821 / \u6a5f\u69cb\u57fa\u672c\u8cc7\u6599\n\u2022 \u62db\u8058\u5b78\u6821/\u6a5f\u69cb\u540d\u7a31 \u5609\u8afe\u6492\u8056\u65b9\u6fdf\u5404\u66f8\u9662\n\u2022 \u7533\u8acb\u806f\u7d61\u4eba \u5229\u5c0f\u59d0 Ms. Li\n\u2022 \u96fb\u8a71 25872700\n\u2022 \u50b3\u771f 25291758\n\u2022 \u96fb\u90f5 Apply Now\n\u2022 \u5730\u5740 9-13 Kennedy Road, Wan Chai, Hong Kong.\n\u2022 \u6a5f\u69cb\u985e\u5225 \u4e2d\u5b78\n\n", "employment_types": ["Full Time"], "selling_points": [], "locations": ["Wan Chai"], "categories": ["Admin & HR", "Others", "Medical Services", "Others"], "post_time": "2022-01-17T07:07:07Z", "salary": {"currency": null, "max": null, "min": null, "period": "monthly", "term": null}, "salary_visible": false, "title_keywords": ["assistant"], "responsibilities": ["communication"], "requirements": {"degrees": ["degree holder"], "majors": [], "languages": ["english", "chinese"], "language_level": ["good"], "hard_skills": [], "soft_skills": ["communication skills"], "languages_combined": [{"language": "english", "language_level": ["good"]}, {"language": "chinese", "language_level": ["good"]}]}, "experience_required": {"duration": [], "field": []}}, {"job_id": "100003009053627", "location_code": "hk", "company": "Bare Limited", "job_title": "Receptionist \u63a5\u5f85\u54e1", "description": "\n\u8077\u8cac\uff1a\n\u2022 \u63a5\u5f85\u9867\u5ba2\u3001\u63a5\u807d\u96fb\u8a71\u53ca\u5b89\u6392\u5ba2\u4eba\u7684\u7642\u7a0b\u9810\u7d04\u6642\u9593\n\u2022 \u8ca0\u8cac\u8655\u7406\u73fe\u91d1\u53ca\u4fe1\u7528\u5361\u4ea4\u6613\u5de5\u4f5c\u3001\u96fb\u8166\u6253\u55ae\u53ca\u57cb\u6578\n\u2022 \u5354\u52a9\u4e3b\u7ba1\u53ca\u9867\u554f\u8655\u7406\u65e5\u5e38\u5ba2\u6236\u670d\u52d9\u53ca\u5e97\u92ea\u71df\u904b\u5de5\u4f5c\n\u00a0 \u8981\u6c42\uff1a\n\u2022 \u6d41\u5229\u5ee3\u6771\u8a71\n\u2022 \u7121\u9700\u76f8\u95dc\u7d93\u9a57\u4ea6\u53ef\n\u2022 \u7a4d\u6975\u4e3b\u52d5\n\u2022 \u601d\u60f3\u6b63\u9762\u3001\u5bcc\u8cac\u4efb\u611f\u3001\u670d\u52d9\u614b\u5ea6\u53cb\u5584\u3001\u6027\u683c\u958b\u6717\n\u61c2\u96fb\u8166\u64cd\u4f5c (MS EXCEL, WORD\u7b49)\n\u00a0 \u524d\u7dda\u54e1\u5de5\u798f\u5229\uff1a\n\u2022 \u6bcf\u5929\u5de5\u4f5c9\u5c0f\u6642\n\u2022 \u661f\u671f\u516d\u53ca\u516c\u773e\u5047\u671f\u5747\u53ef\u65e9\u6536\n\u2022 \u7bc0\u65e5\u65e9\u653e\n\u2022 \u63d0\u4f9b\u5a5a\u5047\u3001\u751f\u65e5\u5047\u3001\u6069\u6064\u5047\n\u2022 \u52a0\u73ed\u88dc\u9418\n\u2022 \u5c08\u696d\u514d\u8cbb\u5728\u8077\u57f9\u8a13\n\u2022 \u7279\u5feb\u6649\u5347\u6a5f\u6703\n\u2022 \u8cfc\u7269\u512a\u60e0\u53ca\u514d\u8cbb\u7642\u7a0b\n\u2022 \u5bb6\u5c6c\u597d\u53cb\u6298\u6263\u512a\u60e0\n\u00a0 \u5de5\u4f5c\u5730\u9ede\uff1a\u65fa\u89d2 / \u89c0\u5858\n\u5de5\u4f5c\u6642\u9593\uff1a\u9031\u4e00\u81f3\u9031\u4e94 12:00 - 21:00\n\u00a0 \u00a0 \u00a0 \u00a0 \u00a0 \u00a0 \u00a0 \u00a0 \u00a0 \u00a0 \u9031\u516d\u53ca\u516c\u773e\u5047\u671f 10:30 - 18:30\n\n", "employment_types": ["Full Time"], "selling_points": [], "locations": ["Kwun Tong"], "categories": ["Admin & HR", "Clerical / Admin Staff", "Receptionist", "Others"], "post_time": "2022-01-17T07:15:56Z", "salary": {"currency": null, "max": null, "min": null, "period": "monthly", "term": null}, "salary_visible": false, "title_keywords": ["receptionist"], "responsibilities": [], "requirements": {"degrees": [], "majors": [], "languages": [], "language_level": [], "hard_skills": ["ms excel"], "soft_skills": [], "languages_combined": []}, "experience_required": {"duration": [], "field": []}}, {"job_id": "100003009053492", "location_code": "hk", "company": "Maxim's Caterers Ltd", "job_title": "Human Resources Officer (Generalist/Business Partner)", "description": "Responsibilities\n\nProvide consultative and operational support to line managers on all HR matters including compensation & benefits, employee issues/enquiries, reporting etc.\nHandle staff issues including, but not limited to disputes, disciplinary actions, and work injury\nSupport HR projects and initiatives\nPrepare various HR reports for management review\nPerform all HR administration works including but limited to staff movement, leave management, performance management, final payment administration and other benefit administration\nPerform any other ad hoc duties as assigned\n\nRequirements\n\nBachelor's Degree in Human Resources Management or related disciplines\nA minimum of 3 years' HR experience\nGood communication, problem-solving and analytical skills\nDetail-minded, mature, independent and must be respectful with excellent interpersonal skills\nSelf-motivated,\u00a0well-organized and able to work independently\nWell-versed in Hong Kong Employment Ordinance and other regulatory practices\nGood command of both spoken and written English and Chinese\nProficient in MS Office (Word, Excel & PowerPoint) and Chinese Word Processing\nCandidates with more experiences may be considered as Senior HR officer\n\nInterested parties please apply with full resume, state expected salaries by clicking \"Apply Now\".\n\nAll applications and data collected will be treated in strict confidential and used exclusively for recruitment purposes.\u00a0 Only short listed candidates will be invited for interview.\u00a0The company will retain the applications for a maximum period of 6 months and may refer suitable candidates to other vacancies within the Group.\u00a0", "employment_types": ["Full Time", "Permanent"], "selling_points": ["Largest F&B group with more than 70 brands", "Support HR operations and enquiries", "Development opportunities"], "locations": ["Not Specified"], "categories": ["Admin & HR", "Others", "HR Supporting Staff"], "post_time": "2022-01-17T07:03:02Z", "salary": {"currency": null, "max": null, "min": null, "period": "monthly", "term": null}, "salary_visible": false, "title_keywords": ["human resources officer"], "responsibilities": ["ad hoc duties", "reporting", "management", "operational support", "hr", "hr reports", "payment", "management review", "administration"], "requirements": {"degrees": ["degree", "bachelor"], "majors": ["related disciplines"], "languages": ["english", "chinese"], "language_level": ["good command", "proficient"], "hard_skills": ["excel", "hong kong employment ordinance", "chinese word processing", "problem-solving", "word", "powerpoint", "analytical skills", "ms office"], "soft_skills": ["detail-minded", "self-motivated", "work independently", "independent", "problem-solving", "well-organized", "mature", "analytical skills", "communication", "interpersonal skills", "respectful"], "languages_combined": [{"language": "english", "language_level": ["good command"]}, {"language": "chinese", "language_level": ["good command", "proficient"]}]}, "experience_required": {"duration": ["minimum of 3 years"], "field": ["hr"]}}, {"job_id": "100003009052174", "location_code": "hk", "company": "The Hong Kong Girl Guides Association", "job_title": "Assistant Project Officer", "description": "Responsibilities:\n\nTo assist the Senior Officer and Executive to develop Golden Guide services for senior / elder women\nTo coordinate, collaborate and liaise with other colleagues, committees, members and volunteers to plan, organize, implement, and evaluate programmes and activities\nTo promote services and activities and increase service outreach via various social media\nTo liaise and collaborate with other colleagues, volunteers, funding organisations and external parties to ensure smooth service operation\nTo perform general administration and office duties and handle enquiries and requests from members and the public\nTo assist Senior Officer and Executive to prepare reports, service and programme statistics, and analyse data as required\nTo work on weekends/public holidays / night as required\n\nRequirements:\n\n5 passes in HKCEE, including English (Syl. B) and Chinese Language OR 5 subjects obtained Level 2 or above in HKDSEE, including English and Chinese\nUniversity graduate\nAt least 2-3 years\u2019 relevant working experience in social welfare sector\nExperience in planning and organizing activities and events in NGOs\nAble to work independently and interested in communicating with elderly people, deal with multiple tasks and work under pressure\nWell-organised and attentive to details\nWell-versed in Microsoft application, power-point, Chinese word processing of \u5009\u9821 or \u901f\u6210\nKnowledge in Photoshop and/or AI is preferable\nGood manner, sociable and cheerful character with strong communication and interpersonal skill\nGuiding experience will be considered an advantage\n\nPlease send r\u00e9sum\u00e9 with your expected salary (a must) by clicking \"Apply Now\" or to Human Resources Department, 8 Gascoigne Road, Kowloon.\u00a0 Please mark \u201cPrivate & Confidential\u201d on the envelope.\n\nProspective employees are required to undergo Sexual Conviction Record Check.\n\u672c\u6703\u5c07\u8981\u6c42\u6e96\u50f1\u54e1\u9032\u884c\u6027\u7f6a\u884c\u5b9a\u7f6a\u7d00\u9304\u67e5\u6838\u3002\n\nPersonal data provided will be used for recruitment purpose only. All personal data of unsuccessful applicants will be destroyed on completion of the recruitment exercise.", "employment_types": ["Full Time", "Permanent"], "selling_points": [], "locations": ["Yau Tsim Mong Area"], "categories": ["Admin & HR", "Clerical / Admin Staff", "Others", "Public / Civil", "Social Services - Community / Non-profit Organization"], "post_time": "2022-01-17T02:21:04Z", "salary": {"currency": null, "max": null, "min": null, "period": "monthly", "term": null}, "salary_visible": false, "title_keywords": ["assistant project officer"], "responsibilities": ["collaborate", "social media", "liaise", "collaborate with", "prepare reports", "data", "external parties", "develop", "coordinate", "evaluate", "handle enquiries", "plan", "analyse", "liaise with", "administration"], "requirements": {"degrees": ["university graduate"], "majors": [], "languages": ["english", "chinese"], "language_level": [], "hard_skills": ["ai", "chinese word processing", "photoshop"], "soft_skills": ["work independently", "cheerful", "attentive to details", "multiple tasks", "interested in", "sociable", "interpersonal skill", "communication", "well-organised", "work under pressure"], "languages_combined": [{"language": "english", "language_level": []}, {"language": "chinese", "language_level": []}]}, "experience_required": {"duration": ["at least 2-3 years"], "field": ["relevant working experience", "planning"]}}, {"job_id": "100003009053748", "location_code": "hk", "company": "Fullteam Information Technology Limited", "job_title": "Digital Marketing Assistant - Part time", "description": "\nResponsibilities:\n\u2022 implement online marketing activities and explore new digital marketing channels\n\u2022 assisting in SEO and SEM\n\u2022 assist in company EDM\n\u2022 administrate and update the company websites\nRequirements:\n\u2022 post secondary education or training in digital marketing, graphic design is an advantage\n\u2022 good at graphic design is an advantage\n\u2022 have eperience in email marketing & data analytic\n\u2022 Good English and Chinese writing skill\n\u2022 knowledge in photoshops, AI, video editing software, EDM tools\nOffer:\n$60.00 - $80.00 per hours\nMondat to Friday\n10:00 - 13:00 or 14:00 - 17:00\nPls contact : +852-39572480\nEmail:Apply Now\nFULLTEAM INFORMATION TECHNOLOGY LIMITED\n\n", "employment_types": ["Full Time"], "selling_points": [], "locations": ["Kwun Tong"], "categories": ["Admin & HR", "Others", "Marketing / Public Relations", "Marketing - General / Support", "Others"], "post_time": "2022-01-17T07:27:27Z", "salary": {"currency": null, "max": null, "min": null, "period": "monthly", "term": null}, "salary_visible": false, "title_keywords": ["digital marketing", "assistant"], "responsibilities": ["company websites", "seo", "edm", "digital marketing", "sem"], "requirements": {"degrees": ["secondary education"], "majors": ["graphic design", "digital marketing"], "languages": ["english", "chinese"], "language_level": ["good"], "hard_skills": ["ai", "video editing", "writing skill"], "soft_skills": ["writing skill"], "languages_combined": [{"language": "english", "language_level": ["good"]}, {"language": "chinese", "language_level": ["good"]}]}, "experience_required": {"duration": [], "field": []}}, {"job_id": "100003009054175", "location_code": "hk", "company": "", "job_title": "\u516c\u53f8\u53f8\u6a5f", "description": "\u5de5\u4f5c\u5167\u5bb9:\n\n\n\u8ca0\u8cac\u63a5\u9001\u516c\u53f8\u7ba1\u7406\u5c64\u53ca\u5bb6\u5ead\u6210\u54e1\n\u8eca\u8f1b\u6e05\u6f54\u3001\u4fdd\u990a\u3001\u9a57\u8eca\u53ca\u7e8c\u724c\u4e8b\u5b9c\n\n\u5165\u8077\u8981\u6c42:\n\n\n\u4e2d\u4e94\u6216\u4ee5\u4e0a\u7a0b\u5ea6\uff0c\u80fd\u807d\u8b1b\u666e\u901a\u8a71\u53ca\u7565\u61c2\u7c21\u55ae\u82f1\u8a9e\u66f4\u4f73\n\u6301\u6709\u9999\u6e2f1\u30012\u724c\n\u5177\u67095\u5e74\u6216\u4ee5\u4e0a\u5de5\u4f5c\u99d5\u99db\u516c\u53f8\u79c1\u5bb6\u8eca\u53ca\u4e03\u4eba\u8eca\u7d93\u9a57\n\u5fc5\u9808\u63d0\u4f9b\u826f\u597d\u99d5\u99db\u7d00\u9304\u3001\u6709\u8cac\u4efb\u611f\u3001\u826f\u597d\u5de5\u4f5c\u614b\u5ea6\n\u80fd\u63a5\u53d7\u8d85\u6642\u53ca\u5f48\u6027\u5de5\u4f5c\u6642\u9593\n\u53ef\u5373\u6642\u4e0a\u73ed\u8005\u512a\u5148\n\n\u5de5\u4f5c\u6642\u9593:\n\u4e0a\u53487\u6642\u81f3\u4e0b\u53487\u6642 /\u00a0\u4e0a\u53487\u6642\u534a\u81f3\u4e0b\u53487\u6642\u534a (12\u5c0f\u6642)\n\u516d\u5929\u5de5\u4f5c\n\n\n\u7533\u8acb\u4eba\u6240\u63d0\u4f9b\u7684\u8cc7\u6599\u7d55\u5c0d\u4fdd\u5bc6\uff0c\u4e26\u53ea\u4f5c\u8207\u62db\u8058\u6709\u95dc\u7684\u7528\u9014\u3002\n\nInterested candidates, please contact us at 31966253 for company details before applying.\n", "employment_types": ["Permanent", "Temporary"], "selling_points": ["\u5177\u67098\u5e74\u6216\u4ee5\u4e0a\u5de5\u4f5c\u99d5\u99db\u516c\u53f8\u79c1\u5bb6\u8eca\u53ca\u4e03\u4eba\u8eca\u7d93\u9a57", "\u826f\u597d\u99d5\u99db\u7d00\u9304", "\u80fd\u63a5\u53d7\u8d85\u6642\u53ca\u5f48\u6027\u5de5\u4f5c\u6642\u9593"], "locations": ["Central & Western Area"], "categories": ["Admin & HR", "Others", "Transportation & Logistics", "Private Transportation"], "post_time": "2022-01-17T08:40:24Z", "salary": {"currency": null, "max": null, "min": null, "period": "monthly", "term": null}, "salary_visible": false, "title_keywords": [], "responsibilities": [], "requirements": {"degrees": [], "majors": [], "languages": [], "language_level": [], "hard_skills": [], "soft_skills": [], "languages_combined": []}, "experience_required": {"duration": [], "field": []}}, {"job_id": "100003009053685", "location_code": "hk", "company": "Belle Cosmetic Limited", "job_title": "\u63a5\u5f85\u54e1", "description": "\n\u6708\u5165$15,000-$20,000\n\n", "employment_types": ["Full Time"], "selling_points": [], "locations": ["Not Specified"], "categories": ["Admin & HR", "Clerical / Admin Staff", "Receptionist", "Others"], "post_time": "2022-01-17T07:21:09Z", "salary": {"currency": null, "max": null, "min": null, "period": "monthly", "term": null}, "salary_visible": false, "title_keywords": [], "responsibilities": [], "requirements": {"degrees": [], "majors": [], "languages": [], "language_level": [], "hard_skills": [], "soft_skills": [], "languages_combined": []}, "experience_required": {"duration": [], "field": []}}, {"job_id": "100003009052713", "location_code": "hk", "company": "HKU School of Professional & Continuing Education", "job_title": "Temporary Clerical Assistants I/II", "description": "Monthly/Hour Salary:\u00a0 \u00a0 \u00a0 \u00a0 \u00a0\n\nHK$12,140 / HK$72 (Temporary Clerical Assistant I)\nHK$10,940 / HK$65 (Temporary Clerical Assistant II)\n\nDuties:\nThe appointees will provide clerical support, including English and Chinese word processing, filing, data input and answering general enquiries.\nThe contract period will be from 1 month to 1 year, depending on operational needs.\nPart-time posts are also available.\nRequirements:\n(i) Level 2 or equivalent or above in five subjects including Chinese Language and English Language in the Hong Kong Diploma of Secondary Education Examination (HKDSEE) or equivalent; or (ii) Level 2 / Grade E or above in five subjects including Chinese Language and English Language in the Hong Kong Certificate of Education Examination (HKCEE), or equivalent.\nGood command of written and spoken English, Chinese and Putonghua as well as proficiency in computer skills including Microsoft Office and Chinese word processing.\nImmediate availability will be an advantage.\nApplications: Please send application quoting the reference number to the Human Resources Team, HKU SPACE, 7/F., T. T. Tsui Building, The University of Hong Kong, Pokfulam Road, Hong Kong. You may apply online or download an application form at http://hkuspace.hku.hk/jobs or request one by fax (852) 2540 3271.\n\n\nThe information provided in an application will only be used for the purpose of consideration for appointment by HKU SPACE. Applicants not contacted within eight weeks from the closing date may assume that their applications are unsuccessful. Unsuccessful applications will be kept for a maximum period of 24 months.", "employment_types": ["Full Time", "Part Time", "Temporary", "Contract"], "selling_points": ["Provide clerical support", "Full-time & part-time posts are available", "Contract period will be from 1 month to 1 year"], "locations": ["Not Specified"], "categories": ["Admin & HR", "Clerical / Admin Staff", "Others", "Others", "Student / Fresh Graduate / No Experience"], "post_time": "2022-01-17T03:47:08Z", "salary": {"currency": null, "max": null, "min": null, "period": "hourly", "term": null}, "salary_visible": false, "title_keywords": [], "responsibilities": ["provide clerical support", "data input"], "requirements": {"degrees": ["certificate", "diploma", "secondary education"], "majors": [], "languages": ["putonghua", "english", "chinese"], "language_level": ["proficiency", "good command"], "hard_skills": ["chinese word processing", "computer skills", "microsoft office"], "soft_skills": [], "languages_combined": [{"language": "putonghua", "language_level": ["good command"]}, {"language": "english", "language_level": ["proficiency", "good command"]}, {"language": "chinese", "language_level": ["proficiency", "good command"]}]}, "experience_required": {"duration": [], "field": []}}, {"job_id": "100003009052711", "location_code": "hk", "company": "Quality HealthCare Medical Services Ltd", "job_title": "Assistant Officer, Business Partner (Part-time, 5 Days)", "description": "In the heart of the role:\n\n\n\nProvide support to pre-employment logistics such as candidate document vetting, contract preparation and onboarding settlement\nAssist in handling administrative duties, such as staff probation and send out communication emails regarding staff movement\nParticipate in ad hoc duties as assigned\n\nDesired Qualification & Experience:\n\n\n\nHigh Diploma or above\nOrganized, attentive to details and multi-tasking;\nWilling to learn and strong sense of responsibilities\nWell organized, good communication and interpersonal skills, attentive to details and able to work independently\nStrong computer literacy in MS Office\nGood command of written and spoken English and Chinese\nImmediately available is preferred\n\n(All applications will be treated in strict confidence and data collected will be used for recruitment purposes only)", "employment_types": ["Part Time", "Contract"], "selling_points": ["End-to-end admin support", "High Diploma or above", "Organized, attentive to details and multi-taskin"], "locations": ["Kowloon Bay"], "categories": ["Admin & HR", "Clerical / Admin Staff", "Others", "HR Supporting Staff"], "post_time": "2022-01-17T03:46:49Z", "salary": {"currency": null, "max": null, "min": null, "period": "monthly", "term": null}, "salary_visible": false, "title_keywords": ["assistant officer"], "responsibilities": ["ad hoc duties", "provide support", "pre-employment", "data", "communication", "administrative duties", "logistics", "recruitment"], "requirements": {"degrees": ["high diploma or above"], "majors": [], "languages": ["english", "chinese"], "language_level": ["good command"], "hard_skills": ["ms office"], "soft_skills": ["organized", "work independently", "confidence", "attentive to details", "willing to learn", "well organized", "communication", "computer literacy", "multi-tasking", "communication and interpersonal skills", "sense of responsibilities"], "languages_combined": [{"language": "english", "language_level": ["good command"]}, {"language": "chinese", "language_level": ["good command"]}]}, "experience_required": {"duration": [], "field": []}}, {"job_id": "100003009051977", "location_code": "hk", "company": "Pangaea (H.K.) Limited", "job_title": "\u79c1\u5bb6\u8eca\u53f8\u6a5f", "description": "\u5de5\u4f5c\u7bc4\u570d\uff1a\u63a5\u8f09\u8001\u95c6\u3001\u5bb6\u5c6c\u53ca\u5ba2\u4eba\u3001\u8eca\u8f1b\u65e5\u5e38\u6e05\u6f54\u3001\u8ddf\u9032\u7dad\u4fee\u4fdd\u990a\u3001\u8fa6\u7406\u9a57\u8eca\n\n\u8981\u6c42\uff1a\n\n5 \u5e74\u6216\u4ee5\u4e0a\u4efb\u8077\u79c1\u4eba\u6216\u5bb6\u5ead\u8eca\u53f8\u6a5f\u7d93\u9a57\n\u4e2d\u4e94\u7a0b\u5ea6\uff0c\u64cd\u6d41\u5229\u5ee3\u6771\u8a71\uff0c\u61c2\u7c21\u55ae\u82f1\u8a9e\u53ca\u666e\u901a\u8a71\n\u6301\u6709\u6548\u9999\u6e2f\u99d5\u99db\u57f7\u7167\u53ca\u5167\u5730\u99d5\u99db\u57f7\u7167\n\u5b89\u5168\u99d5\u99db\u7d00\u9304\u53ca\u7121\u72af\u7f6a\u8a18\u9304\n\u719f\u6089\u9999\u6e2f\u9053\u8def\uff0c\u5177\u570b\u5167\u99d5\u99db\u7d93\u9a57\u512a\u5148\n\u5177\u8cac\u4efb\u611f\u3001\u5b88\u6642\u3001\u8aa0\u5be6\u6709\u79ae\u53ca\u8863\u8457\u6574\u6f54\n\u7121\u4e0d\u826f\u55dc\u597d\uff0c\u4e0d\u5438\u7159\n\u80fd\u5373\u6642\u4e0a\u73ed\u8005\u53ca\u5c45\u6e2f\u5cf6\u5357\u5340\u512a\u5148\u8003\u616e\n\u672c\u516c\u53f8\u63d0\u4f9b\u512a\u539a\u5f85\u9047\u53ca\u798f\u5229\uff0c\u5305\u62ec\u91ab\u7642\u4fdd\u96aa\u3001\u52a0\u73ed\u8cbb\u3001\u4ea4\u901a\u53ca\u9910\u8cbb\u6d25\u8cbc\u3001\u5e74\u5047\u7b49\u3002\u6709\u610f\u8005\uff0c\u81f4\u96fb2202 2332\u00a0\u95dc\u5c0f\u59d0\u3002", "employment_types": ["Full Time", "Permanent"], "selling_points": [], "locations": ["Wan Chai"], "categories": ["Admin & HR", "Others", "Others", "Others"], "post_time": "2022-01-17T01:48:36Z", "salary": {"currency": null, "max": null, "min": null, "period": "monthly", "term": null}, "salary_visible": false, "title_keywords": [], "responsibilities": [], "requirements": {"degrees": [], "majors": [], "languages": [], "language_level": [], "hard_skills": [], "soft_skills": [], "languages_combined": []}, "experience_required": {"duration": [], "field": []}}, {"job_id": "100003009053609", "location_code": "hk", "company": "Keen Max Trading Company Limited", "job_title": "Retail Operation Officer", "description": "\nResponsibilities:\n\u2022 Assisting the Retail team to deliver the effective store operations service;\n\u2022 Provide daily operations support to all shops, including stock inventory control, customer service enquiry, manpower planning, periodic stock take and any other ad hoc project;\n\u2022 Preparing and analyzing retail reports;\n\u2022 Conducting and Supervising frontline staffs if needed;\n\u2022 Coordinating corporate sales and administration activities;\n\u2022 Providing other supports on frontline operations.\n\u2022 Handle customer relations and complaints\nRequirements:\n\u2022 Minimum 2 years\u2019 solid experience in retail operations or relevant industry;\n\u2022 Solid experience in fashion retail operations support is preferred\n\u2022 Responsible, independent, detailed oriented and able to work under pressure\n\u2022 Energetic, Self-motived and team player\n\u2022 Good command of both written and spoken English and Chinese\n\u2022 Proficiency in using MS Office & Chinese word processing\n\u2022 Immediate available is preferred\n\u5de5\u4f5c\u985e\u578b: \u5168\u8077, \u9577\u5de5\n\u6642\u9593:\n\u2022 \u65e5\u73ed\n\u798f\u5229:\n\u2022 \u54e1\u5de5\u8cfc\u7269\u512a\u60e0\n\u2022 \u7522\u5047\n\u2022 \u91ab\u7642\u4fdd\u96aa\n\u88dc\u5145\u85aa\u916c:\n\u2022 \u5e74\u7d42\u734e\u91d1\n\u9060\u7a0b\u5de5\u4f5c:\n\u2022 \u5426\n\n", "employment_types": ["Full Time"], "selling_points": [], "locations": ["Kwai Tsing Area"], "categories": ["Admin & HR", "Clerical / Admin Staff", "Others"], "post_time": "2022-01-17T07:14:25Z", "salary": {"currency": null, "max": null, "min": null, "period": "monthly", "term": null}, "salary_visible": false, "title_keywords": ["officer", "retail operation"], "responsibilities": ["administration", "supervising", "ad hoc", "operations", "stock take", "daily operations", "inventory control", "customer service", "reports", "planning"], "requirements": {"degrees": [], "majors": [], "languages": ["english", "chinese"], "language_level": ["proficiency", "good command"], "hard_skills": ["chinese word processing", "ms office"], "soft_skills": ["detailed oriented", "independent", "responsible", "team player", "energetic", "work under pressure"], "languages_combined": [{"language": "english", "language_level": ["good command"]}, {"language": "chinese", "language_level": ["proficiency", "good command"]}]}, "experience_required": {"duration": ["minimum 2 years"], "field": ["retail operations"]}}]