[{"job_id": "100003008017686", "location_code": "hk", "company": "Exceed Consulting Limited", "job_title": "Executive Assistant to Management (Confidential Role)", "description": "Our client, is a reputable conglomerate with a diverse businesses around APAC. They are looking for an Executive Assistant to report to a senior management in Hong Kong to look after the business and personal matters.\u00a0\n\nJob Description\u00a0\n\n\nProvide full spectrum of secretarial support\nMaintain an accurate and detailed calendar, manage and log incoming scheduling requests\nManage international & local travel scheduling and arrangement\nLiaise with other senior management's executive assistant to coordinate the meetings/conference calls and customers visit\nOrganize internal and external meetings and draft replies and calls, including logistics and preparation\n\nRequirement\n\n8-10 years of experience in serving C-level or top management\nCandidate with experience working in legal services or giant corporations will be highly preferred\nExcellent spoken and written English and Mandarin\nGreat organizational Skills\nInterpersonal and communication skills Active listening skills\nProductivity and initiative\nKeeping calm under pressure\nAccuracy and attention to detail\nTrustworthiness, discretion, confidentiality and responsibility\nAlternative Saturday Morning, Flexible to work on Public Holidays (Compensation Leave)", "employment_types": ["Full Time", "Permanent"], "selling_points": ["Reputable Conglomerate (45K - 50K per month)", "Attractive Year End Bonus", "Excellent Fringe Benefits"], "locations": ["Eastern Area"], "categories": ["Admin & HR", "Personal / Executive Assistant", "Secretary"], "post_time": "2022-01-17T06:59:14Z", "salary": {"currency": null, "max": null, "min": null, "period": "monthly", "term": null}, "salary_visible": false, "title_keywords": ["executive assistant"], "responsibilities": ["coordinate", "scheduling", "maintain", "logistics", "secretarial support", "liaise with", "senior management"], "requirements": {"degrees": [], "majors": [], "languages": ["english", "mandarin"], "language_level": ["excellent"], "hard_skills": ["c"], "soft_skills": ["flexible", "communication skills", "organizational skills", "under pressure", "interpersonal", "calm", "attention to detail", "active", "initiative"], "languages_combined": [{"language": "english", "language_level": ["excellent"]}, {"language": "mandarin", "language_level": ["excellent"]}]}, "experience_required": {"duration": ["8-10 years"], "field": ["management", "legal"]}}, {"job_id": "100003009052740", "location_code": "hk", "company": "ADECCO", "job_title": "Executive Assistant (+Secretary) (+Administration)", "description": "Job Description\n\n\n\nProvide general Secretarial, Administrative, HR support to high management\nManage and coordinate all business-related affairs for Director\nAdministration of confidential documents and record management\nAssist in coordination of activities and guidelines set out by the Founder\nClosely collaborate with management team in planning, developing and managing in implementation of new and various projects;\nPerform other ad-hoc duties as required\n\nRequirements\n\nProvide general Secretarial, Administrative, HR support to high management\nManage and coordinate all business-related affairs for Director\nAdministration of confidential documents and record management\nAssist in coordination of activities and guidelines set out by the Founder\nClosely collaborate with management team in planning, developing and managing in implementation of new and various projects;\nPerform other ad-hoc duties as required", "employment_types": ["Full Time"], "selling_points": [], "locations": ["Kwun Tong"], "categories": ["Admin & HR", "Administration / Operation Manager", "Clerical / Admin Staff", "Personal / Executive Assistant"], "post_time": "2022-01-17T03:52:45Z", "salary": {"currency": "HKD", "max": 24999, "min": 20000, "period": "monthly", "term": null}, "salary_visible": true, "title_keywords": ["executive assistant", "secretary"], "responsibilities": ["collaborate with", "management team", "management", "guidelines", "hr", "developing", "implementation", "coordinate", "planning", "coordination", "ad-hoc duties", "administration"], "requirements": {"degrees": [], "majors": [], "languages": [], "language_level": [], "hard_skills": [], "soft_skills": ["coordination", "ad-hoc duties"], "languages_combined": []}, "experience_required": {"duration": [], "field": []}}, {"job_id": "100003009052602", "location_code": "hk", "company": "NAHC Limited", "job_title": "Executive Assistant", "description": "Our client, a multinational oil and gas company,\u00a0is now looking for Executive Assistant (+Secretary) (+Administration)\n\nJob Responsibilities\n\n\u00a0\u00a0\u00a0\u00a0\u00a0\u00a0\u00a0\u00a0 Manage information flow in a timely and accurate manner\n\u00a0\u00a0\u00a0\u00a0\u00a0\u00a0\u00a0\u00a0 Manage executives\u2019 calendars and set up meetings\n\u00a0\u00a0\u00a0\u00a0\u00a0\u00a0\u00a0\u00a0 Make travel and accommodation arrangements\n\u00a0\u00a0\u00a0\u00a0\u00a0\u00a0\u00a0\u00a0 Rack daily expenses and prepare weekly, monthly or quarterly reports\n\u00a0\u00a0\u00a0\u00a0\u00a0\u00a0\u00a0\u00a0 Keepup with office supply inventory\n\u00a0\u00a0\u00a0\u00a0\u00a0\u00a0\u00a0\u00a0 Format information for internal and external communication\n\u00a0\u00a0\u00a0\u00a0\u00a0\u00a0\u00a0\u00a0 Take minutes during meetings\n\u00a0\u00a0\u00a0\u00a0\u00a0\u00a0\u00a0\u00a0 Screen and direct phone calls and distribute correspondence\n\u00a0\u00a0\u00a0\u00a0\u00a0\u00a0\u00a0\u00a0 Organize and maintain the office filing system\n\nJob Requirements\n\n\u00a0\u00a0\u00a0\u00a0\u00a0\u00a0\u00a0\u00a0 High School degree\n\u00a0\u00a0\u00a0\u00a0\u00a0\u00a0\u00a0\u00a0 Work experience as an Executive Assistant, Administrative Assistant or similar role\n\u00a0\u00a0\u00a0\u00a0\u00a0\u00a0\u00a0\u00a0 Excellent MS Office knowledge\n\u00a0\u00a0\u00a0\u00a0\u00a0\u00a0\u00a0\u00a0 Outstanding organizational and time management skills\n\u00a0\u00a0\u00a0\u00a0\u00a0\u00a0\u00a0\u00a0 Excellent verbal and written communications skills\n\u00a0\u00a0\u00a0\u00a0\u00a0\u00a0\u00a0\u00a0 Proficient in Excel (Pivot Table, VLOOKUP)\n\nInterested parties, please CLICK HERE to apply online.\n\nOr if you would like to have a further discussion about this role, please Whatsapp Hoyin Siu at 9862 0297.\n\nPlease note that only short-listed candidates will be notified. All information gathered will be treated in strict confidence and solely used for recruitment purposes.", "employment_types": ["Full Time", "Permanent"], "selling_points": ["Fast Growing Global E-commerce Business", "Trilingual Executive Assistant", "Confident, organised and proactive team player"], "locations": ["Tsuen Wan Area"], "categories": ["Admin & HR", "Administration / Operation Manager", "Personal / Executive Assistant", "Secretary"], "post_time": "2022-01-17T03:30:46Z", "salary": {"currency": null, "max": null, "min": null, "period": "monthly", "term": null}, "salary_visible": false, "title_keywords": ["executive assistant"], "responsibilities": ["inventory", "expenses", "communication", "maintain", "reports", "phone calls"], "requirements": {"degrees": ["degree", "high school"], "majors": [], "languages": [], "language_level": [], "hard_skills": ["excel", "pivot table", "vlookup", "ms office"], "soft_skills": ["time management skills", "organizational"], "languages_combined": []}, "experience_required": {"duration": [], "field": ["administrative"]}}, {"job_id": "100003009052034", "location_code": "hk", "company": "ProJob21.com Limited", "job_title": "Executive Assistant for Principal Partner, Global Private Equity & Asset Management", "description": "Our client is a fast-growing global e-commerce business that is planning to double the team by the end of 2022. They are looking for an organised and disciplined individual to help with the C-suite's increasing administrative and communication tasks.\n\n\n\nResponsibilities\n\nProvide all-rounded secretarial assistance and administrative support to C-level executives\nCalendar management and logistical coordination of internal and external meetings\nPrepare meeting minutes, reports, presentations, and other business correspondences\nOrganize and file expense reports, daily mail, and meeting materials\nCoordinate and act as a liaison between internal and external parties\nAdministrative and communication project management\nAssisting with other ad hoc requests as required\n\nRequirements\n\nBachelor's degree holder, with formal secretarial experience would be an advantage\nExcellent prioritization and organizational skills to meet the deadlines of multiple concurrent projects under pressure\nProactively solves problems and look for ways to make systems more efficient\nOutstanding communication and interpersonal skills\nExcellent command of spoken and written English, Cantonese, and Mandarin", "employment_types": ["Full Time"], "selling_points": [], "locations": ["Not Specified"], "categories": ["Admin & HR", "Personal / Executive Assistant", "Secretary", "Banking / Finance", "Asset Management"], "post_time": "2022-01-17T02:50:51Z", "salary": {"currency": null, "max": null, "min": null, "period": "monthly", "term": null}, "salary_visible": false, "title_keywords": ["executive assistant", "asset management"], "responsibilities": ["management", "administrative support", "ad hoc requests", "prepare meeting minutes", "internal and external parties", "presentations", "coordinate", "communication", "project management", "reports", "coordination"], "requirements": {"degrees": ["bachelor", "degree holder"], "majors": [], "languages": ["cantonese", "english", "mandarin"], "language_level": ["excellent"], "hard_skills": ["make"], "soft_skills": ["efficient", "organizational skills", "communication and interpersonal skills", "under pressure"], "languages_combined": [{"language": "cantonese", "language_level": ["excellent"]}, {"language": "english", "language_level": ["excellent"]}, {"language": "mandarin", "language_level": ["excellent"]}]}, "experience_required": {"duration": [], "field": ["secretarial"]}}, {"job_id": "100003009054613", "location_code": "hk", "company": "Wealth Capital Limited", "job_title": "Personal Assistant", "description": "World class and global industry leaders of alternative and asset managers are in search for Executive Assistant for Principal Partner for Asia Pacific region.\n\n\nGlobal Industry Leader in Alternative & Asset Mgmt\n1 to 1 PA/Biz support to Asia Principal Partner\nHybrid work mode & Multi-cultural Environment\n\nAccountabilities:\n\nReport to Regional Principal Partner\nResponsible for full spectrum of business support including calendar management and complex schedule arrangement that called for extensive liaison with global institutional investors/senior management across the region/headquarters\nPrepare presentation material; fund raising logistic and on-going investment management meetings\nFacilitate the planning & arrangement of personal & family schedules\n\nRequirements:\n\nDegree holder with 8-10years+ relevant experience supporting regional senior executives in charge of front office ideally from investment, deal and strategic business development\nRelevant industry experience ideally from asset management, private equity or alternative investment is highly desirable\nProactive team player with proven competency to working in a dynamic multicultural environment\nProfessional, Efficient and multi-tasked with seasoned communication skill in English, Mandarin and Cantonese\nHighly proficient in Excel/PowerPoint\n\n\n\nInterested candidates, please email your update resume (in MS WORD format) with current and expected salary to us soonest.\n\nAlso come visit ProJOB21 www.ProJob21.com to discover other exciting career opportunities!\n\nAll information received will be kept in strict confidence and used for employment-related purposes only.", "employment_types": ["Full Time"], "selling_points": ["5-day work week", "Nice working environment", "Free lunch"], "locations": ["Southern Area"], "categories": ["Admin & HR", "Personal / Executive Assistant"], "post_time": "2022-01-17T10:14:37Z", "salary": {"currency": null, "max": null, "min": null, "period": "monthly", "term": null}, "salary_visible": false, "title_keywords": ["personal assistant"], "responsibilities": ["management", "schedules", "communication", "asset management", "schedule", "report", "senior management", "planning"], "requirements": {"degrees": ["degree holder"], "majors": ["business"], "languages": ["cantonese", "english", "mandarin"], "language_level": [], "hard_skills": ["excel", "dynamic", "private equity", "powerpoint"], "soft_skills": ["efficient", "responsible", "communication skill", "dynamic", "multi-tasked", "team player", "proactive", "extensive", "presentation"], "languages_combined": [{"language": "cantonese", "language_level": []}, {"language": "english", "language_level": []}, {"language": "mandarin", "language_level": []}]}, "experience_required": {"duration": [], "field": ["business development", "relevant experience", "investment", "asset management"]}}, {"job_id": "100003009051939", "location_code": "hk", "company": "Quantium Solutions (Hong Kong) Limited", "job_title": "Administration Executive/Personal Assistant", "description": "Job Responsibilities:\n\nProvide full spectrum of secretarial, personal support to Managing Director\nOrganize and prepare correspondence and documents\nCompile filling and archive management\nMaintain a systematic filing system and inventory record for Company's physical assets e.g.artwork\nProvide household support for Managing Director family\nSupport other ad-hoc projects and duties\nJob Requirement/Qualification:\n\nBachelor's degree Holder in any discipline\nMinimum 2 years relevant experience in office administration, personal assistant\u00a0\nSelf-motivated with excellent interpersonal skills, well-organized, and very patient\nGood in time management\nAble to work independently and handle multiple tasks concurrently\nHigh professional standard of integrity and confidentiality\nProficiency in Microsoft Excel, Word, PowerPoint and Chinese Word Processing\nProficiency in English and Chinese (Cantonese, Mandarin)\nResidence on Hong Kong island is preferred\nImmediate availability is a plus\nBenefits:\n\nFive-day work week, Double pay, Performance bonus, Medical insurance, Free lunch\nPlease apply with full resume by clicking \"Apply Now\"\u00a0", "employment_types": ["Full Time", "Permanent"], "selling_points": [], "locations": ["Wong Tai Sin Area"], "categories": ["Admin & HR", "Clerical / Admin Staff", "Personal / Executive Assistant", "Secretary"], "post_time": "2022-01-17T01:33:11Z", "salary": {"currency": null, "max": null, "min": null, "period": "monthly", "term": null}, "salary_visible": false, "title_keywords": ["administration executive", "personal assistant"], "responsibilities": ["ad-hoc projects", "management", "maintain", "inventory record"], "requirements": {"degrees": ["bachelor", "degree holder"], "majors": [], "languages": ["cantonese", "english", "chinese", "mandarin"], "language_level": ["proficiency"], "hard_skills": ["plus", "chinese word processing", "word", "powerpoint", "microsoft excel"], "soft_skills": ["self-motivated", "work independently", "well-organized", "integrity", "handle multiple tasks", "interpersonal skills", "patient", "time management"], "languages_combined": [{"language": "cantonese", "language_level": []}, {"language": "english", "language_level": ["proficiency"]}, {"language": "chinese", "language_level": ["proficiency"]}, {"language": "mandarin", "language_level": []}]}, "experience_required": {"duration": ["minimum 2 years"], "field": ["office administration", "relevant experience"]}}, {"job_id": "100003009053167", "location_code": "hk", "company": "", "job_title": "Personal Assistant", "description": "Quantium Solutions\n\nQS is an established eCommerce logistics services provider in the Asia Pacific Region. Headquartered in Singapore, we are ideally positioned to be the best gateway to Asia.\n\nOur serviced offices now serve the needs of enterprises and entrepreneurs across major 200 countries and 18 markets.\n\nAt QS, creating a workplace that provides opportunities for each of you and we believe in you and know you\u2019ll do great things. As an employer, our role is to empower you by bringing your true talents and best self to this dynamic digital world and people we serve.\n\n\n\n\nJob Description\n\nJob Responsibilities:\n\nPerform full spectrum of Administrative functions,\u00a0including\u00a0but not limited to repair & maintenance, procurement ( sourcing, price negotiation, suppliers evaluation & selection, delivery management and inventory control ) etc.\nHandle ISO documents update and filing, and provide assistance to ISO internal and external audits\nPlan and manage daily schedule of RGM including work, personal time, and trips;\nOrganize travel arrangement for the family including ticket and accommodation, itinerary planning, visa application etc\nAssist in any ad hoc project as\u00a0assigned\n\n\u00a0Job Requirements:\n\nCertificate, Diploma or\u00a0above\u00a0in Logistics, Procurement or related disciplines\nPossession of procurement experience is a must and ISO audit experience\u00a0would\u00a0be an added advantage\nGood\u00a0negotiation,\u00a0communication and interpersonal skills\nGood command of written and spoken English, Cantonese and Mandarin\nPC Literacy and working knowledge of MS Office\nImmediately available is preferred\n\nWe offer attractive remuneration package including medical insurance, life insurance, dental and other fringe benefits to the right candidate. Interested parties please send your full resume with date of availability, present and expected salaries to us\n\n\n", "employment_types": ["Full Time", "Permanent"], "selling_points": [], "locations": ["Kwun Tong Area"], "categories": ["Admin & HR", "Personal / Executive Assistant", "Secretary"], "post_time": "2022-01-17T06:13:17Z", "salary": {"currency": null, "max": null, "min": null, "period": "monthly", "term": null}, "salary_visible": false, "title_keywords": ["personal assistant"], "responsibilities": ["management", "price negotiation", "ad hoc", "maintenance", "internal and external audits", "repair", "inventory control", "schedule", "plan", "evaluation", "travel arrangement", "provide assistance", "planning"], "requirements": {"degrees": ["certificate", "diploma or above"], "majors": ["related disciplines"], "languages": ["cantonese", "english", "mandarin"], "language_level": ["good command"], "hard_skills": ["pc", "ms office"], "soft_skills": ["communication and interpersonal skills", "negotiation"], "languages_combined": [{"language": "cantonese", "language_level": ["good command"]}, {"language": "english", "language_level": ["good command"]}, {"language": "mandarin", "language_level": ["good command"]}]}, "experience_required": {"duration": [], "field": ["audit experience", "procurement"]}}, {"job_id": "100003009052055", "location_code": "hk", "company": "Chemtax Industrial Company Limited", "job_title": "Personal Assistant", "description": "Job responsibilities:-\n\n- Provide full range of secretarial and administrative support to Chairman;\n- Manage calendars, meeting schedules, personal & family affairs including director's quarter maintenance, maids and drivers management, administrative support to the relatives of Chairman;\n- Maintain filling system and confidential information in a professional manner;\n- Closely liaise and coordinate with internal and external parties to ensure smooth business operations.\n\nJobs requirements:-\n\n- Degree holder with 3 years solid experience;\n- Excellent command in spoken and written English, Cantonese and Mandarin;\n- Proficient PC knowledge in MS Word and Excel;\n- Multi-tasking, well-organized, detail-minded with strong communication and interpersonal skills;\n- Immediately available is highly preferred.", "employment_types": ["Full Time"], "selling_points": ["10 years or above relevant working experience", "Excellent command of written English and Chinese", "Willing to travel to China"], "locations": ["Kwai Hing"], "categories": ["Admin & HR", "Personal / Executive Assistant"], "post_time": "2022-01-17T01:59:03Z", "salary": {"currency": null, "max": null, "min": null, "period": "monthly", "term": null}, "salary_visible": false, "title_keywords": ["personal assistant"], "responsibilities": ["liaise", "management", "maintenance", "administrative support", "schedules", "operations", "internal and external parties", "professional manner", "coordinate with", "maintain"], "requirements": {"degrees": ["degree holder"], "majors": [], "languages": ["cantonese", "english", "mandarin"], "language_level": ["excellent"], "hard_skills": ["excel", "pc knowledge", "ms word"], "soft_skills": ["detail-minded", "multi-tasking", "communication and interpersonal skills", "well-organized"], "languages_combined": [{"language": "cantonese", "language_level": ["excellent"]}, {"language": "english", "language_level": ["excellent"]}, {"language": "mandarin", "language_level": ["excellent"]}]}, "experience_required": {"duration": ["3 years"], "field": []}}, {"job_id": "100003009051655", "location_code": "hk", "company": "Icon Wealth Management Company", "job_title": "Personal Assistant to Director", "description": "Requirements:\n\n10 years or above relevant working experience\nExcellent command of written English and Chinese; fluent in spoken English, Cantonese, and Putonghua\nProficient in MS applications, Google-powered business tools, and database management\nWilling to travel to China\nAble to work independently\n\nResponsibilities:\n\nProvide full spectrum of secretarial support for both business and personal matters\nManage daily schedule, business appointments, and travel itineraries\nLiaise with associations and business contacts individually\nOrganize company events and activities e.g. exhibitions, seminars, dinners, etc", "employment_types": ["Full Time", "Permanent"], "selling_points": ["Good in English, Mandarin and Cantonese", "Willing to learn, good at multitasking", "All-rounded pre-job and on-job trainings"], "locations": ["North Point"], "categories": ["Admin & HR", "Personal / Executive Assistant", "Education", "Tutor / Instructor", "Marketing / Public Relations", "Marketing - Marketing Communication"], "post_time": "2022-01-16T21:50:31Z", "salary": {"currency": "HKD", "max": 19999, "min": 14000, "period": "monthly", "term": null}, "salary_visible": true, "title_keywords": ["director", "personal assistant"], "responsibilities": ["liaise with", "secretarial support", "schedule"], "requirements": {"degrees": [], "majors": [], "languages": ["cantonese", "putonghua", "english", "chinese"], "language_level": ["excellent", "fluent"], "hard_skills": ["ms applications"], "soft_skills": ["work independently"], "languages_combined": [{"language": "cantonese", "language_level": ["fluent"]}, {"language": "putonghua", "language_level": ["fluent"]}, {"language": "english", "language_level": ["excellent", "fluent"]}, {"language": "chinese", "language_level": ["excellent"]}]}, "experience_required": {"duration": ["10 years"], "field": ["relevant working experience"]}}, {"job_id": "100003009054941", "location_code": "hk", "company": "Sun Hung Kai Properties Ltd", "job_title": "PERSONAL ASSISTANT", "description": "Requirements:\n\n\nHigher Diploma or above with secretarial training preferred\nMinimum 10 years\u2019 working experience in secretarial/administrative field\nProven English and Chinese proficiency\nGood interpersonal and communication skills\nFamiliar with PC software e.g. MS Word, Excel, PowerPoint & Chinese Word Processing\nOrganized, efficient & detail-minded\nPatient, Pleasant & a good team player\n\nResponsibilities:\n\n\nProvide secretarial support and handle personal family matters of the manager\nPerform administrative support to a team of senior executives\nCoordinate & schedule internal & external meetings\nHandle business correspondences and provide daily administrative support\n\nGood remuneration and attractive fringe benefits will be offered to the successful applicant. Interested parties please apply with full resume, present and expected salary, available date by clicking \"Apply Now\".\n\nFor further information, please visit our company website: http://www.shkp.com/.\n\nWe are an equal opportunity employer and welcome applications from all qualified candidates. All personal data collected will be used for recruitment purpose only.\u00a0 Applicants not hearing from us within 3 months may consider their applications unsuccessful.\u00a0 All personal data collected will be destroyed within 24 months.", "employment_types": ["Full Time", "Permanent"], "selling_points": ["Higher Diploma or above with secretarial training", "10 years\u2019 working exp in secretarial/admin field", "Familiar with PC software"], "locations": ["Wan Chai"], "categories": ["Admin & HR", "Clerical / Admin Staff", "Personal / Executive Assistant", "Secretary"], "post_time": "2022-01-17T14:32:28Z", "salary": {"currency": null, "max": null, "min": null, "period": null, "term": null}, "salary_visible": false, "title_keywords": ["personal assistant"], "responsibilities": ["coordinate", "schedule", "secretarial support", "administrative support"], "requirements": {"degrees": ["higher diploma or above"], "majors": [], "languages": ["english", "chinese"], "language_level": ["proficiency"], "hard_skills": ["excel", "chinese word processing", "powerpoint", "pc", "ms word"], "soft_skills": ["detail-minded", "organized", "communication skills", "efficient", "good team player", "pleasant", "patient", "interpersonal"], "languages_combined": [{"language": "english", "language_level": ["proficiency"]}, {"language": "chinese", "language_level": ["proficiency"]}]}, "experience_required": {"duration": ["minimum 10 years"], "field": ["secretarial", "administrative"]}}, {"job_id": "100003009052673", "location_code": "hk", "company": "Oxford Asset Management Limited", "job_title": "Executive Assistant / Management Associate", "description": "We\u00a0are a\u00a0well-established\u00a0property\u00a0leasing,\u00a0management and investment company located in Wanchai-Admiralty area, now inviting an experienced candidate for the position of\u00a0Executive Assistant (Trainee) / Management Associate.\n\nResponsibilities:\n\nAssist Senior Management by providing administrative and co-ordination support in the various areas of business duties;\nDraft English and Chinese correspondences, emails, memos, letters, presentation materials and reports;\nCoordinate meetings, prepare agenda and minutes;\nAssist in coordination of daily tasks and liaise with internal and external parties;\nSupport office administrative work when necessary.\n\nRequirements:\u00a0\n\nDegree holder in any disciplines with at least 2 years\u2019 working experience in assisting executive management;\nA good team player with strong communication and interpersonal skills;\nOwned driving license is an advantage;\nSelf-motivated and loyal, with strong sense of commitment;\nSkills in PC office softwares (English/Chinese);\nProficient in English, Cantonese and Mandarin;\nOverseas travelling may be required;\nCandidates with less experience will be considered as Executive Assistant Trainee.\n\nWe offer an attractive remuneration package and excellent career prospects to the right candidate.\u00a0 Please send full resume, current and expected salary, contact number and the availability to us for interview.\n\nPersonal data collected will be used for recruitment purpose only.", "employment_types": ["Full Time", "Permanent"], "selling_points": [], "locations": ["Wan Chai"], "categories": ["Admin & HR", "Personal / Executive Assistant", "Others"], "post_time": "2022-01-17T03:41:10Z", "salary": {"currency": null, "max": null, "min": null, "period": "monthly", "term": null}, "salary_visible": false, "title_keywords": ["executive assistant", "management associate"], "responsibilities": ["administrative work", "internal and external parties", "letters", "coordinate", "reports", "coordination", "liaise with", "senior management"], "requirements": {"degrees": ["degree holder"], "majors": ["any disciplines"], "languages": ["cantonese", "english", "chinese", "mandarin"], "language_level": ["proficient"], "hard_skills": ["pc"], "soft_skills": ["good team player", "communication and interpersonal skills", "self-motivated", "loyal"], "languages_combined": [{"language": "cantonese", "language_level": ["proficient"]}, {"language": "english", "language_level": ["proficient"]}, {"language": "chinese", "language_level": []}, {"language": "mandarin", "language_level": ["proficient"]}]}, "experience_required": {"duration": ["at least 2 years"], "field": ["management"]}}, {"job_id": "100003009052206", "location_code": "hk", "company": "Gemini Personnel Limited", "job_title": "Personal Assistant (22 day annual leave) PRC-J078023", "description": "My client, one of the leading property developers and focus on property investment nd development in Hong\u00a0 Kong. They are looking for a Personal Assistant.\n\n\n\nResponsibilities:\n\nProvide full spectrum of secretarial and administrative support to Senior Management\u00a0\nHandle business correspondence, other confidential and professional documents as instructed\nAssist to draft various English and Chinese business correspondences in a professional manner\nResponsible for arranging and monitoring the day-to-day operation for the whole family household\nManage and supervise the domestic helpers, drivers, chef, securities, etc.\nResponsible for property and facilities management and maintenance, renovation, repair, etc.\nAd hoc tasks assigned by the Management\n\nRequirements:\n\nDegree holder in any disciplines\nAt least 2 years secretary / personal assistant experience in Property, Finance or Investment industry\nGood command of both written and spoken in English and Chinese\nPC knowledge of\u00a0 MS Word, Excel and Chinese Word Processing\nImmediate availability would be an advantage\nBenefits:\n\nAnnual Leave 22 days\nBonus\nLife Insurance\nMedical Insurance\neducation Allowance\nFive day work per week\n\nInterested parties, please send your resume with expected salary submit by APPLY NOW or contact with Miss Priscilla Cheng at 35529110 WhatsApp +852 98651325 for discussion.", "employment_types": ["Full Time", "Permanent"], "selling_points": ["Provide full secretarial to Senior Management", "Handling confidential information & document", "Fluent English and Mandarin"], "locations": ["Causeway Bay"], "categories": ["Admin & HR", "Personal / Executive Assistant", "Secretary"], "post_time": "2022-01-17T02:28:02Z", "salary": {"currency": null, "max": null, "min": null, "period": "monthly", "term": null}, "salary_visible": false, "title_keywords": ["personal assistant"], "responsibilities": ["management", "maintenance", "administrative support", "monitoring", "professional manner", "renovation", "ad hoc tasks", "repair", "senior management", "day-to-day operation"], "requirements": {"degrees": ["degree holder"], "majors": ["any disciplines"], "languages": ["english", "chinese"], "language_level": ["good command"], "hard_skills": ["excel", "pc knowledge", "chinese word processing", "ms word"], "soft_skills": [], "languages_combined": [{"language": "english", "language_level": ["good command"]}, {"language": "chinese", "language_level": ["good command"]}]}, "experience_required": {"duration": ["at least 2 years"], "field": ["finance", "investment"]}}, {"job_id": "100003009054583", "location_code": "hk", "company": "Value Partners Ltd", "job_title": "Junior Executive Assistant (Fresh Graduates Welcome)", "description": "Job Description:\n\nAssist Senior Personal Assistant to provide full spectrum of personal and business support to senior executive\nLiaise with internal and external parties for business activities, project management, etc.\nManage calendar, coordinate meetings, events, organize daily schedules and travel arrangement\nHandle business correspondence, confidential documents and other administrative duties\nWilling to handle multi-tasks and ad hoc assignment is required\nBe prepared for fieldwork, overtime and flexible working hours may be required\nOther ad-hoc personal matters as required\n\nJob Requirement:\n\nBachelor Degree or above\nFresh graduates are welcome\nExcellent command of spoken and written English and Mandarin\nWell versed in MS Office (Word, Excel and PowerPoint), Chinese word processing and familiar\u00a0with IOS device setting\nStrong sense of responsibility with handling of confidential information is a must\nGood time management, strong interpersonal and communication skills is required\nAbility to work and be highly organized under pressure, able to prioritize and handle multiple\u00a0tasks\nIndependent, meticulous, detail-oriented and be self-initiated\nWilling to travel occasionally\nInterested candidates please send your full resume with current and expected salary in MS Word Format. Personal data will be used for recruitment purpose only.\n\nOnly shortlisted candidates will be notified.", "employment_types": ["Full Time"], "selling_points": ["Personal Assistant to Leadership Committee Member", "Fresh Graduates Welcome", "Fluent in English"], "locations": ["Central"], "categories": ["Admin & HR", "Personal / Executive Assistant", "Secretary"], "post_time": "2022-01-17T10:06:54Z", "salary": {"currency": null, "max": null, "min": null, "period": "monthly", "term": null}, "salary_visible": false, "title_keywords": ["junior executive", "assistant"], "responsibilities": ["ad-hoc", "schedules", "ad hoc assignment", "internal and external parties", "coordinate", "project management", "administrative duties", "travel arrangement", "liaise with", "business activities"], "requirements": {"degrees": ["degree or above", "bachelor"], "majors": [], "languages": ["english", "chinese", "mandarin"], "language_level": ["excellent"], "hard_skills": ["excel", "chinese word processing", "word", "powerpoint", "ms office"], "soft_skills": ["organized", "communication skills", "meticulous", "under pressure", "independent", "able to prioritize", "sense of responsibility", "detail-oriented", "handle multiple tasks", "time management", "interpersonal"], "languages_combined": [{"language": "english", "language_level": ["excellent"]}, {"language": "chinese", "language_level": []}, {"language": "mandarin", "language_level": ["excellent"]}]}, "experience_required": {"duration": [], "field": []}}, {"job_id": "100003009053284", "location_code": "hk", "company": "OSMA Consulting Limited", "job_title": "Executive Assistant \uff08\u8463\u4e8b\u52a9\u7406\uff09", "description": "Our client is a reputable investment group with business lines across multiple industries in Asia. The high level seniors of this group are currently looking for qualified individual to assist on group's daily business and operation.\n\u6211\u4eec\u7684\u5ba2\u6237\u662f\u4e00\u5bb6\u58f0\u8a89\u5353\u8457\u7684\u6295\u8d44\u96c6\u56e2\uff0c\u4e1a\u52a1\u904d\u53ca\u4e9a\u6d32\u591a\u4e2a\u884c\u4e1a\u3002 \u8be5\u96c6\u56e2\u7684\u9ad8\u5c42\u76ee\u524d\u6b63\u5728\u5bfb\u627e\u5408\u683c\u7684\u4e2a\u4eba\u6765\u534f\u52a9\u96c6\u56e2\u7684\u65e5\u5e38\u4e1a\u52a1\u548c\u8fd0\u8425\u3002\n\nResponsibilities:\n-Coordination with internal departments (BD, IR, HR, etc) regarding daily operation;\u00a0\n-Liaising with various external parties (Clients' representatives or Guests) on business affairs;\n-Occasionally attend business meeting with senior management and take minutes ;\u00a0\n-Director's office administration work and back up other admin colleagues when needed;\n-Perform any other ad-hoc requests from management.\n\nQualifications:\n-Bachelor Degree or above;\n-Past experience in finance industry is a plus;\n-Mature and presentable;\n-Good command in English and Chinese.\n\n\n\u804c\u8d23\uff1a\n-\u4e0e\u5185\u90e8\u90e8\u95e8\uff08BD\u3001IR\u3001HR\u7b49\uff09\u5c31\u65e5\u5e38\u8fd0\u4f5c\u8fdb\u884c\u534f\u8c03\uff1b\n-\u5c31\u5546\u52a1\u4e8b\u5b9c\u4e0e\u5404\u79cd\u5916\u90e8\u5404\u65b9\uff08\u5ba2\u6237\u4ee3\u8868\u6216\u5ba2\u4eba\uff09\u8054\u7edc\uff1b\n-\u5076\u5c14\u53c2\u52a0\u4e0e\u9ad8\u7ea7\u7ba1\u7406\u4eba\u5458\u7684\u5546\u52a1\u4f1a\u8bae\u5e76\u505a\u4f1a\u8bae\u8bb0\u5f55\uff1b\n-\u4e3b\u7ba1\u529e\u516c\u5ba4\u884c\u653f\u5de5\u4f5c\uff0c\u5e76\u5728\u9700\u8981\u65f6\u652f\u6301\u5176\u4ed6\u884c\u653f\u540c\u4e8b\uff1b\n- \u6267\u884c\u6765\u81ea\u7ba1\u7406\u5c42\u7684\u4efb\u4f55\u5176\u4ed6\u4e34\u65f6\u8bf7\u6c42\u3002\n\n\u8d44\u683c\uff1a\n-\u672c\u79d1\u53ca\u4ee5\u4e0a\u5b66\u5386\uff1b\n-\u6709\u91d1\u878d\u884c\u4e1a\u7ecf\u9a8c\u8005\u4f18\u5148\uff1b\n-\u6210\u719f\u4e14\u6709\u8d23\u4efb\u5fc3\uff1b\n-\u826f\u597d\u7684\u4e2d\u82f1\u6587\u8868\u8fbe\u3002\n\n", "employment_types": ["Full Time"], "selling_points": ["Reputable investment group", "Excellent career exposure", "Attractive package"], "locations": ["Central"], "categories": ["Admin & HR", "Administration / Operation Manager", "Personal / Executive Assistant", "Secretary"], "post_time": "2022-01-17T06:47:02Z", "salary": {"currency": null, "max": null, "min": null, "period": "monthly", "term": null}, "salary_visible": false, "title_keywords": ["executive assistant"], "responsibilities": ["management", "hr", "external parties", "daily operation", "office administration work", "ad-hoc requests", "senior management"], "requirements": {"degrees": ["degree or above"], "majors": [], "languages": ["english", "chinese"], "language_level": [], "hard_skills": ["plus"], "soft_skills": ["presentable"], "languages_combined": [{"language": "english", "language_level": []}, {"language": "chinese", "language_level": []}]}, "experience_required": {"duration": [], "field": ["finance industry"]}}, {"job_id": "100003009051647", "location_code": "hk", "company": "Dining Art Group", "job_title": "Executive Assistant / Personal Assistant", "description": "Job Description\n\n\n\nProvide general Secretarial, Administrative, HR support to high management\nManage and coordinate all business-related affairs for Director\nAdministration of confidential documents and record management\nAssist in coordination of activities and guidelines set out by the Founder\nClosely collaborate with management team in planning, developing and managing in implementation of new and various projects;\nPerform other ad-hoc duties as required\n\nRequirements\n\nProvide general Secretarial, Administrative, HR support to high management\nManage and coordinate all business-related affairs for Director\nAdministration of confidential documents and record management\nAssist in coordination of activities and guidelines set out by the Founder\nClosely collaborate with management team in planning, developing and managing in implementation of new and various projects;\nPerform other ad-hoc duties as required", "employment_types": ["Full Time", "Permanent"], "selling_points": [], "locations": ["Tsim Sha Tsui"], "categories": ["Admin & HR", "Personal / Executive Assistant"], "post_time": "2022-01-16T19:15:31Z", "salary": {"currency": null, "max": null, "min": null, "period": "monthly", "term": null}, "salary_visible": false, "title_keywords": ["executive assistant", "personal assistant"], "responsibilities": ["collaborate with", "management team", "management", "guidelines", "hr", "developing", "implementation", "coordinate", "planning", "coordination", "ad-hoc duties", "administration"], "requirements": {"degrees": [], "majors": [], "languages": [], "language_level": [], "hard_skills": [], "soft_skills": ["coordination", "ad-hoc duties"], "languages_combined": []}, "experience_required": {"duration": [], "field": []}}, {"job_id": "100003009053834", "location_code": "hk", "company": "Konew Financial Express Limited \u5eb7\u696d\u4fe1\u8cb8\u5feb\u905e", "job_title": "Personal Assistant to Senior Executive", "description": "Main Duties & Responsibilities:\n\n\nProvide full spectrum of personal and business support to senior executive\nLiaise with internal and external parties for business activities, project management, etc.\nManage calendar, coordinate meetings, events, organize daily schedules and travel arrangement\nHandle business correspondence, confidential documents and other administrative duties\nWilling to handle multi-tasks and ad hoc assignment is required\n\nRequirements:\n\nBachelor Degree or above\nAt least 3 years relevant working experience\nExcellent communication and interpersonal skills\nWell organized, attentive to details, able to handle multi-tasks with strong sense of responsibility\nGood\u00a0command of spoken and written\u00a0English and\u00a0Chinese\nProficiency in MS Office\n\nWe offer:\n\nDiscretionary bonus\nMedical insurance\nDental insurance\nCompetitive annual leave days\nBirthday leave\nAnniversary leave\nStudy leave\nMarriage leave\nCompassionate leave\n\nHow to apply:\n\nInterested parties, please send your resume stating your expected salary\u00a0to\u00a0Human Capital Department\u00a0by clicking\u00a0\"APPLY NOW\".\n\n(We are an equal opportunity employer.\u00a0 Personal data collected will be used for recruitment purpose only.\u00a0 The unsuccessful applications will be destroyed after 6 months.)", "employment_types": ["Full Time", "Permanent"], "selling_points": ["Support personal and business activities", "Interact with people at all levels", "Proactive, flexible and detail-minded"], "locations": ["Central"], "categories": ["Admin & HR", "Clerical / Admin Staff", "Personal / Executive Assistant", "Secretary"], "post_time": "2022-01-17T07:36:07Z", "salary": {"currency": null, "max": null, "min": null, "period": "monthly", "term": null}, "salary_visible": false, "title_keywords": ["senior executive", "personal assistant"], "responsibilities": ["schedules", "ad hoc assignment", "internal and external parties", "coordinate", "project management", "administrative duties", "travel arrangement", "liaise with", "business activities"], "requirements": {"degrees": ["degree or above", "bachelor"], "majors": [], "languages": ["english", "chinese"], "language_level": ["good command"], "hard_skills": ["ms office"], "soft_skills": ["multi-tasks", "attentive to details", "sense of responsibility", "well organized", "communication and interpersonal skills"], "languages_combined": [{"language": "english", "language_level": ["good command"]}, {"language": "chinese", "language_level": ["good command"]}]}, "experience_required": {"duration": ["at least 3 years"], "field": ["relevant working experience"]}}, {"job_id": "100003009053001", "location_code": "hk", "company": "Bright Sun Global Enterprise Limited", "job_title": "Personal Assistant to Director", "description": "Responsibilities:\n\nAssist in Company\u2019s projects to liaise with various internal and external parties.\nCoordinate with various parties to handle daily office operations, commercial, caring & other activities.\nAssist in HR matters such as hiring, onboarding, engagement & development to offboarding.\nManage schedules, coordinate meetings, appointments and events.\nHandle a broad variety of assigned errands, tasks and projects whenever requested.\n\nRequirements:\n\nDegree holder or above.\nAt least 3 years working experience. Admin & HR experience will be an advantage.\nProficient in MS office, Chinese word processing, video conference tools like Zoom and MS Teams.\nHighly-organized, open-minded, flexible, and capable of working under pressure with multi-task assignments.\nGood command in English, Mandarin and Cantonese, both written and spoken.\nBased in Hong Kong. Travel to PRC is needed.", "employment_types": ["Full Time"], "selling_points": [], "locations": ["Kowloon Bay"], "categories": ["Admin & HR", "Personal / Executive Assistant", "Others", "Trading"], "post_time": "2022-01-17T06:47:26Z", "salary": {"currency": null, "max": null, "min": null, "period": "monthly", "term": null}, "salary_visible": false, "title_keywords": ["director", "personal assistant"], "responsibilities": ["schedules", "operations", "hr", "internal and external parties", "coordinate with", "coordinate", "liaise with"], "requirements": {"degrees": ["degree holder"], "majors": [], "languages": ["cantonese", "english", "chinese", "mandarin"], "language_level": ["good command", "proficient"], "hard_skills": ["chinese word processing", "ms office"], "soft_skills": ["flexible", "organized", "under pressure", "capable", "multi-task", "open-minded"], "languages_combined": [{"language": "cantonese", "language_level": ["good command"]}, {"language": "english", "language_level": ["good command"]}, {"language": "chinese", "language_level": ["proficient"]}, {"language": "mandarin", "language_level": ["good command"]}]}, "experience_required": {"duration": ["at least 3 years"], "field": ["hr", "admin"]}}, {"job_id": "100003009049605", "location_code": "hk", "company": "Lidl Asia Pte. Limited (Hong Kong Branch)", "job_title": "Executive Assistant", "description": "HR & Admin Officer/ HR & Admin Assistant\nLocation : Hung Hom,\u00a0\u00a0Salary : 16-28K\n\nResponsibilities:\n\nProvide full support of human resources function including but not limited to recruitment, orientation and employee activities etc\nProvide clerical and administrative support to the other department & Administration Dept.\nManage and review various sourcing channels\nUpdate personal details and attendance record in HR systems\nHandle monthly payroll administration, final payments, leave management and\u00a0 MPF administration\nTravel to China office occasionally ( Once a month )\nPrepare HR reports and assist in ad hoc duties as assigned\n\nRequirements:\n\nA diploma or above with a minimum of 2-3 year relevant working experience\nAt least 2-6 years related experience\nWell versed with HK Employment Ordinance and other related legislation\nProficient in MS Office\nAble to perform in a fast-paced and dynamic environment\nCandidates with less experience will be considered as\u00a0 Human Resources and Administration Assistant\u00a0\nTravel to CHN office occasionally\nImmediate available is preferred\nExecutive Assistant/ Secretarial\nLocation : Hung Hom,\u00a0\u00a0Salary : 18-26K\nResponsibilities\n\nProvide efficient, accurate and responsive secretarial and administrative support to Director\nMaintain daily routines, coordinate and set up appointments\nPrepare minutes, reports and the presentation materials\nManage travel arrangement including flight schedule, visa, hotel and expenses claim\nAssist in other ad hoc assignments and projects if necessary\nRequirements\n\nDegree holder in Business Administration or related disciplines or formal secretarial training is preferred\nAt least 1-3 years of secretarial experience in toys industry is an advantage\nFluent in written & spoken English & Mandarin\nProficiency in Microsoft Office (e.g. Excel, Word)\nDetail-minded, Smart, FAST pace , High stress resistance , Multi-task with a strong sense of responsibility\nGood interpersonal and communication skills\nImmediate available is preferred\n\n** Personal data will be treated with strict confidential and used for recruitment purpose only.", "employment_types": ["Full Time"], "selling_points": ["Proven experience as an executive assistant", "Excellent interpersonal skills at all levels", "Attention to detail. 5 days work. Office at ICC."], "locations": ["Others"], "categories": ["Admin & HR", "Personal / Executive Assistant"], "post_time": "2022-01-14T08:57:03Z", "salary": {"currency": null, "max": null, "min": null, "period": "monthly", "term": null}, "salary_visible": false, "title_keywords": ["executive assistant"], "responsibilities": ["ad hoc duties", "attendance", "management", "mpf", "administrative support", "hr", "review", "systems", "hr reports", "recruitment", "payments", "payroll", "administration"], "requirements": {"degrees": ["diploma or above", "degree holder"], "majors": ["related disciplines", "business administration"], "languages": ["english", "mandarin"], "language_level": ["fluent"], "hard_skills": ["excel", "microsoft office", "word", "dynamic", "ms office"], "soft_skills": ["efficient", "detail-minded", "dynamic environment", "communication skills", "multi-task", "sense of responsibility", "interpersonal", "accurate", "responsive", "presentation"], "languages_combined": [{"language": "english", "language_level": ["fluent"]}, {"language": "mandarin", "language_level": ["fluent"]}]}, "experience_required": {"duration": ["minimum of 2-3 year", "at least 1-3 years", "at least 2-6 years"], "field": ["toys", "secretarial", "related", "relevant working experience", "human resources", "administration"]}}, {"job_id": "100003009051859", "location_code": "hk", "company": "Construction Industry Council", "job_title": "Assistant Officer / Assistant - Registration Services", "description": "Summary\n\nThe main objective of this position is to provide clerical support and handle important tasks to assist executive-level employees and ensure all specified deadlines are met.\n\nWhat will you do?\n\n\u2022\u00a0\u00a0 \u00a0Acting as the point of contact between the executives and internal or external colleagues\n\u2022\u00a0\u00a0 \u00a0Researching and conducting data to prepare documents for review and presentation by boards of directors, committees, and executives\n\u2022\u00a0\u00a0 \u00a0Organising meetings and booking meeting rooms\n\u2022\u00a0\u00a0 \u00a0Reading and analyzing incoming memos, submissions, and distributing them as needed, ensuring all deadlines for correspondence are met. \u00a0\n\u2022\u00a0\u00a0 \u00a0Making travel arrangements and detailed travel itineraries\n\u2022\u00a0\u00a0 \u00a0Taking dictation and minutes and writing them up subsequently\n\u2022\u00a0\u00a0 \u00a0Producing reports and presentations using various software, including word processing, spreadsheets, databases, and presentation software.\u00a0\n\u2022\u00a0\u00a0 \u00a0Maintaining the current filing and database system, and looking for ways to improve current systems\n\u2022\u00a0\u00a0 \u00a0Answering phones and routing calls to the correct person or taking messages\n\nWhat will you need?\n\n\u2022\u00a0\u00a0 \u00a0Proven experience as an executive assistant or other relevant administrative support experience.\n\u2022\u00a0\u00a0 \u00a0In-depth understanding of entire MS Office suite.\n\u2022\u00a0\u00a0 \u00a0High school diploma.\n\u2022\u00a0\u00a0 \u00a0Ability to organize a daily workload by priorities.\n\u2022\u00a0\u00a0 \u00a0Must be able to meet deadlines in a fast-paced quickly changing environment.\n\u2022\u00a0\u00a0 \u00a0A proactive approach to problem-solving with strong decision-making skills.\n\u2022\u00a0\u00a0 \u00a0Professional level verbal and written communications skillsOther required Knowledge, Skills, and Abilities:\n\u2022\u00a0\u00a0 \u00a0Excellent interpersonal skills at all levels, including people-management.\n\u2022\u00a0\u00a0 \u00a0Ability to multitask and prioritise tasks\n\u2022\u00a0\u00a0 \u00a0Excellent time management skills\n\u2022\u00a0\u00a0 \u00a0Well-developed organisational skills\n\u2022\u00a0\u00a0 \u00a0Attention to detail\n\u2022\u00a0\u00a0 \u00a0English Language both written and verbal a must.\u00a0\n\u2022\u00a0\u00a0 \u00a0Cantonese verbal a must, German and Mandarin beneficial\n\u2022\u00a0\u00a0 \u00a0Professional discretion\n\u00a0\n\nWhat do we offer?\n\nWe are dedicated to fostering a family-friendly culture and work environment and we are an equal opportunities employer and welcome applications from all candidates with the required skills and experience.\n\n\u00a0\nMarket Leading Remuneration Package:\n\nDouble pay and discretionary bonus\n\nChoice of MPF provider\n\nLife Insurance\n\nMedical Insurance\n\nSupportive Environment:\n\nRental re-imbursement scheme\n\nFlexible work arrangements\n\nIn-house training courses\n\nTraining sponsorship scheme\n\nHealth Check\n\nVision Check\n\nSupporting your child\u2019s education with advice from a leading education consultant\n\nWork-Life Balance:\n\n5 day week\n\nCompetitive Annual Leave\n\nCharity, Community and Sporting Events\n\nWe are dedicated to fostering a family-friendly culture and work environment and we are an equal opportunities employer and welcome applications from all candidates with the required skills and experience.\n\n\u00a0\nMarket Leading Remuneration Package:\n\nDouble pay and discretionary bonus\n\nChoice of MPF provider\n\nLife Insurance\n\nMedical Insurance\n\nSupportive Environment:\n\nRental re-imbursement scheme\n\nFlexible work arrangements\n\nIn-house training courses\n\nTraining sponsorship scheme\n\nHealth Check\n\nVision Check\n\nSupporting your child\u2019s education with advice from a leading education consultant\n\nWork-Life Balance:\n\n5 day week\n\nCompetitive Annual Leave\n\nCharity, Community and Sporting Events", "employment_types": ["Full Time", "Contract"], "selling_points": ["a recognised degree", "a minimum of 1 year's post-qualification work exp.", "to vet the registration scheme applications"], "locations": ["Not Specified"], "categories": ["Admin & HR", "Clerical / Admin Staff", "Personal / Executive Assistant", "Public / Civil", "Others"], "post_time": "2022-01-17T01:23:55Z", "salary": {"currency": null, "max": null, "min": null, "period": null, "term": null}, "salary_visible": false, "title_keywords": ["assistant officer", "assistant"], "responsibilities": ["provide clerical support", "travel arrangements", "management", "software", "maintaining", "data", "administrative support", "review", "systems", "presentations", "reports", "contact", "booking", "databases", "database", "prepare documents"], "requirements": {"degrees": ["high school diploma"], "majors": [], "languages": ["german", "cantonese", "english", "mandarin"], "language_level": [], "hard_skills": ["problem-solving", "word processing", "presentations", "databases", "ms office"], "soft_skills": ["time management skills", "ability to multitask", "problem-solving", "prioritise", "organisational skills", "interpersonal skills", "attention to detail", "meet deadlines", "proactive", "presentation", "detailed"], "languages_combined": [{"language": "german", "language_level": []}, {"language": "cantonese", "language_level": []}, {"language": "english", "language_level": []}, {"language": "mandarin", "language_level": []}]}, "experience_required": {"duration": [], "field": ["administrative"]}}, {"job_id": "100003009047935", "location_code": "hk", "company": "Links International", "job_title": "Executive Assistant  (Private Equity)", "description": "The applicant must possess\na recognised degree;\na minimum of 1 year's post-qualification experience;\nproactive and customer-oriented;\ngood sense of responsibility and be a pleasant team player;\nproficiency in Cangjie and / or Sucheng input method; and\ngood command of both written and spoken English and Chinese (including Putonghua).\n(Applicants who do not possess the required qualifications and / or experience may be considered for Assistant \u2013 Registration Services.)\n\nDuties include\nto vet the registration scheme applications in accordance to the Policies and Procedures as well as service pledge;\nto provide registration services and application services to other CIC service offerings in CIC Service Centres located at Kowloon Bay and Nam Cheong or other CIC premises;\nto perform data entry and data analysis work;\nto handle enquiries and complaints according to service pledge;\nto maintain the IT System and update the scheme website and publicity materials;\nto support events and other administrative duties of the Registration Services; and\nto carry out any other duties as assigned from time to time by the Executive Director.\n\nApplications\nThe position is on a renewable fixed-term contract (subject to performance and operational needs) for a period of 2 years.\nPlease click the below \u201cApply Online\u201d to complete the application form and upload the updated curriculum vitae, the results of English and Chinese Language obtained in public examinations, current and expected salary together with a covering letter stating one\u2019s suitability for the job on or before 31 January 2022.\nFor further details on CIC please refer to website:\u00a0http://www.cic.hk.", "employment_types": ["Full Time", "Permanent"], "selling_points": ["Short notice is preferred", "Handling Business and Personal Support", "Excellent communication in English and Chinese"], "locations": ["Central"], "categories": ["Admin & HR", "Personal / Executive Assistant", "Secretary"], "post_time": "2022-01-14T04:18:58Z", "salary": {"currency": null, "max": null, "min": null, "period": "monthly", "term": null}, "salary_visible": false, "title_keywords": ["executive assistant"], "responsibilities": ["any other duties", "data entry", "policies", "procedures", "handle enquiries and complaints", "website", "data analysis", "maintain", "administrative duties"], "requirements": {"degrees": ["degree"], "majors": [], "languages": ["putonghua", "english", "chinese"], "language_level": ["good command"], "hard_skills": ["analysis", "scheme"], "soft_skills": ["sense of responsibility", "pleasant", "customer-oriented", "team player", "proactive"], "languages_combined": [{"language": "putonghua", "language_level": ["good command"]}, {"language": "english", "language_level": ["good command"]}, {"language": "chinese", "language_level": ["good command"]}]}, "experience_required": {"duration": ["minimum of 1 year"], "field": ["post-qualification"]}}, {"job_id": "100003009054495", "location_code": "hk", "company": "\u5b8f\u5de5\u6709\u9650\u516c\u53f8", "job_title": "Administrative Assistant/ Officer", "description": "Key responsibilities:\n\n\nPlan and manage complex travel arrangements and itineraries\nEffectively liaize with clients, management and other contacts\nAssist in the creation and preparation of presentations, both for internal and external use\nWork collaboratively with other team assistants in a team environment\nHandle incoming phone calls, take messages, arrange conference calls\nHandle and arrange the reimbursement of monthly business, travel and entertainment expenses.\nOutlook maintenance. Maintain updated master calendar and records in database accurately and in a timely manner.\nOrganize client and internal meetings, events and personnel committees.\nMaintain databases, contacts/distribution lists\nHandle Senior Executive's personal matters\nAd-hoc project work dependent on team's needs\n\nRequirements:\n\n\n\nA few years for experience in a similar role, preferrably within the asset management industry.\nProven organizational skills\nAbility to handle multiple deadlines with excellent time management and instinct for prioritization\nAble to switch between detailed work and the bigger picture\nAble to work on own initiative and to have a solutions-orientated approach\nPositive attitude with a willingness to provide the highest levels of internal and external client service. Trustworthy and confidential.\nAble to work seamlessly with other team assistants and used to working in a team environment\nHighly effective communicator with excellent verbal and written English and Chinese skills\nHave the ability to work accurately and effectively under pressure.\nProactive with ability to think ahead\nSelf-motivated, flexibility to work outside normal office hours.\nStrong skills in MS Office, including Excel/PowerPoint.", "employment_types": ["Full Time", "Permanent", "Contract"], "selling_points": ["5-day-work", "Considerable salary with development bonus", "Career path to Office Manager"], "locations": ["Tsim Sha Tsui"], "categories": ["Admin & HR", "Personal / Executive Assistant", "Recruitment / Executive Search", "Sales, CS & Business Devpt", "Sales Administration"], "post_time": "2022-01-17T09:47:28Z", "salary": {"currency": "HKD", "max": 19999, "min": 14000, "period": "monthly", "term": null}, "salary_visible": true, "title_keywords": ["administrative assistant", "officer"], "responsibilities": ["ad-hoc", "travel arrangements", "management", "maintenance", "expenses", "a timely manner", "incoming phone calls", "presentations", "maintain", "plan", "database", "databases"], "requirements": {"degrees": [], "majors": [], "languages": ["english", "chinese"], "language_level": ["excellent"], "hard_skills": ["excel", "switch", "powerpoint", "ms office"], "soft_skills": ["organizational skills", "self-motivated", "proactive", "under pressure", "trustworthy", "positive attitude", "communicator", "time management", "initiative", "detailed"], "languages_combined": [{"language": "english", "language_level": ["excellent"]}, {"language": "chinese", "language_level": ["excellent"]}]}, "experience_required": {"duration": [], "field": ["asset management"]}}, {"job_id": "100003009050045", "location_code": "hk", "company": "Links International", "job_title": "Executive Assistant - upto 45K - Finanicial Firm", "description": "Office Location: Tsim Sha Tsui\n\nJob Description\n\nThe position is directed to Branch/ Division managers,\n\n1)\u00a0\u00a0\u00a0\u00a0\u00a0 Provide all-round secretarial and administrative support in a timely, accurate and complete manner, including but not limited to:\n\n-\u00a0\u00a0\u00a0\u00a0\u00a0\u00a0\u00a0\u00a0\u00a0 Assist in preparing presentation materials\n\n-\u00a0\u00a0\u00a0\u00a0\u00a0\u00a0\u00a0\u00a0\u00a0 Assist in planning team engagement activities as requested\n\n-\u00a0\u00a0\u00a0\u00a0\u00a0\u00a0\u00a0\u00a0\u00a0 Maintain good relationship with internal and external parties\n\n2)\u00a0\u00a0\u00a0\u00a0\u00a0 Pre-job and onboard arrangement to associates, including but not limited to:\n\n-\u00a0\u00a0\u00a0\u00a0\u00a0\u00a0\u00a0\u00a0\u00a0 Initiate and monitor recruitment schemes\n\n-\u00a0\u00a0\u00a0\u00a0\u00a0\u00a0\u00a0\u00a0\u00a0 Arrange meetings and appointments with candidates and managers\n\n-\u00a0\u00a0\u00a0\u00a0\u00a0\u00a0\u00a0\u00a0\u00a0 Assist in planning team engagement activities as requested\n\nJob Requirement\n\n-\u00a0\u00a0\u00a0\u00a0\u00a0\u00a0\u00a0\u00a0\u00a0 Degree in any discipline\n\n-\u00a0\u00a0\u00a0\u00a0\u00a0\u00a0\u00a0\u00a0\u00a0 2 years' experience or above\n\n-\u00a0\u00a0\u00a0\u00a0\u00a0\u00a0\u00a0\u00a0\u00a0 Proficient use of Microsoft Office/ Excel/ PowerPoint and other illustration tools\n\n-\u00a0\u00a0\u00a0\u00a0\u00a0\u00a0\u00a0\u00a0\u00a0 Very strong sense of responsibility\n\n-\u00a0\u00a0\u00a0\u00a0\u00a0\u00a0\u00a0\u00a0\u00a0 Efficient, detail and performance oriented\n\n-\u00a0\u00a0\u00a0\u00a0\u00a0\u00a0\u00a0\u00a0\u00a0 Independent and self-motivated\n\n-\u00a0\u00a0\u00a0\u00a0\u00a0\u00a0\u00a0\u00a0\u00a0 Good command of spoken and written Chinese (both Cantonese and Mandarin), and English", "employment_types": ["Full Time", "Permanent"], "selling_points": ["Fluent Mandarin, English, Cantonese", "6 yrs exp - Financial Firm", "Assisting Senior Management"], "locations": ["Not Specified"], "categories": ["Admin & HR", "Personal / Executive Assistant"], "post_time": "2022-01-14T09:41:02Z", "salary": {"currency": "HKD", "max": 44999, "min": 35000, "period": "monthly", "term": null}, "salary_visible": true, "title_keywords": ["executive assistant"], "responsibilities": ["administrative support", "internal and external parties", "monitor", "maintain good relationship", "recruitment", "arrange meetings", "planning"], "requirements": {"degrees": ["degree"], "majors": [], "languages": ["cantonese", "english", "chinese", "mandarin"], "language_level": ["good command"], "hard_skills": ["excel", "illustration", "powerpoint", "microsoft office"], "soft_skills": ["efficient", "self-motivated", "independent", "sense of responsibility"], "languages_combined": [{"language": "cantonese", "language_level": ["good command"]}, {"language": "english", "language_level": ["good command"]}, {"language": "chinese", "language_level": ["good command"]}, {"language": "mandarin", "language_level": ["good command"]}]}, "experience_required": {"duration": ["2 years"], "field": []}}, {"job_id": "100003009051375", "location_code": "hk", "company": "", "job_title": "Senior Secretary", "description": "Our client is a professional finanicial firm located in Central. They are currently looking for an Executive Assistant experienced with assisting senior C-level management. This is a great opportunity tp work in a fast paced friendly Westernized enviornment.\n\nJob Responsibilities\n\nProvide secretarial and administrative support to senior management\nSchdule appointments and manage interactions with high level management from international firm\nDetail oriented in a fast paced enviornment\nConduct research as needed required and data filling of confidential information\nProvide any ad-hoc assignments when needed\n\n\n\nJob Requirements\n\nDegree holder with excellent command of English and Cantonese, Fluent Mandarin is a must\nAt least 5 years of experience serving senior executive preferably within a financial firm\nStrong communicator with outgoing poersonality\nHold strong interpersonal communication skills, positive, and detail oriented\nAdaptable and personable", "employment_types": ["Full Time"], "selling_points": [], "locations": ["Kwun Tong Area"], "categories": ["Admin & HR", "Personal / Executive Assistant", "Secretary", "Others"], "post_time": "2022-01-15T12:34:43Z", "salary": {"currency": null, "max": null, "min": null, "period": "monthly", "term": null}, "salary_visible": false, "title_keywords": ["senior secretary"], "responsibilities": ["management", "data", "administrative support", "ad-hoc assignments", "senior management", "conduct research"], "requirements": {"degrees": ["degree holder"], "majors": [], "languages": ["cantonese", "english", "mandarin"], "language_level": ["excellent", "fluent"], "hard_skills": [], "soft_skills": ["outgoing", "communication skills", "personable", "adaptable", "detail oriented", "communicator", "interpersonal", "positive"], "languages_combined": [{"language": "cantonese", "language_level": ["excellent", "fluent"]}, {"language": "english", "language_level": ["excellent", "fluent"]}, {"language": "mandarin", "language_level": ["excellent", "fluent"]}]}, "experience_required": {"duration": ["at least 5 years"], "field": ["financial"]}}, {"job_id": "100003009054467", "location_code": "hk", "company": "Epro Telecom Services Limited", "job_title": "Museum Research Assistant (Contract/Government)", "description": "* Diploma with formal secretarial training with at least 5 years relevant working experience.\n\n* Responsible to provide professional secretarial and administravtive duties to Directors and Senior Executives.\n\n* Handle correspondence, telephone calls & emails.\n\n* Supervise office administration works, finance related filing & reminder management.\n\n* Collect and prepare information for use in discussions / meetings.\n\n* Handle details of confidential and critical nature.\n\n* Mature , well-organized, self-discipline and good interpersonal skills.\n\n* Good Communication skills in written & spoken English, Cantonese and Mandarin.\n\n* Proficiency in computer skills including Microsoft Word and Excel, Chinese Word Processing.\n\n* Periodic travel to PRC is required.\n\nWe offer attractive remuneration package to the successful candidate.\u00a0\n\n(Personal data provided by job application will be used for\u00a0recruitment purpose only.)\n\nInterested candidates, please contact us at 69176190 for company details before applying.\n", "employment_types": ["Full Time", "Contract"], "selling_points": [], "locations": ["Tsim Sha Tsui"], "categories": ["Admin & HR", "Personal / Executive Assistant", "Sciences, Lab, R&D", "Energy / Natural Resources / Oil & Gas", "Environmental Science / Waste Management"], "post_time": "2022-01-17T09:40:22Z", "salary": {"currency": null, "max": null, "min": null, "period": "monthly", "term": null}, "salary_visible": false, "title_keywords": ["research assistant"], "responsibilities": ["communication", "office administration", "management"], "requirements": {"degrees": ["diploma"], "majors": [], "languages": ["cantonese", "english", "chinese", "mandarin"], "language_level": ["proficiency", "good"], "hard_skills": ["excel", "chinese word processing", "microsoft word", "computer skills"], "soft_skills": ["communication skills", "responsible", "well-organized", "mature", "interpersonal skills"], "languages_combined": [{"language": "cantonese", "language_level": ["good"]}, {"language": "english", "language_level": ["good"]}, {"language": "chinese", "language_level": ["proficiency"]}, {"language": "mandarin", "language_level": ["good"]}]}, "experience_required": {"duration": ["at least 5 years"], "field": ["secretarial", "relevant working experience", "training"]}}, {"job_id": "100003009049869", "location_code": "hk", "company": "Ozaru Limited", "job_title": "Personal Assistant", "description": "Our client, a leading global club, is currently on the lookout for a zestful Office Manager and Executive Assistant to provide administrative support to the group in its headquarters in Hong Kong. We are looking for a confident, trustworthy, detail-oriented individual to work with talented people in a small and dynamic corporate environment. This is a great opportunity for anyone who has a real interest in football.\u00a0\n\nOffice Manager / Executive Assistant\n\n\n\nSchedule and organize meetings and conference calls for office agenda\nReception duties: welcoming clients/visitors and determining access to appropriate parties\u00a0\nResponsible for handling accounts: processing invoices, payroll, budget & forecasting etc.\u00a0\nRecord office expenditure and managing budget: Coordinate finances, assist with budget preparation.\u00a0\nOrganising the office layout and maintaining supplies of stationery, equipment and pantry supplies\u00a0\nMaintaining the condition of the office and arranging for necessary repairs;\u00a0\nClose communication with HQ office on operations, accounts and technology related issues\nProvide secretarial and executive support to the MD\nResponsible for travel arrangements, meetings and conferences for MD and staff\n\nREQUIREMENTS\u00a0\n\n\nUniversity degree\n5 to 8 years\u2019 experience as an office manager and executive assistant within corporate office\u00a0\nHigh\u00a0proficiency in English, Cantonese and Mandarin, both spoken and written\n\nAn ability to multitask and handle documentation and reports with the highest level of confidentiality\nSelf-starter and able to work in a dynamic and team-oriented environment\nGreat interest and passion in sports", "employment_types": ["Full Time", "Permanent"], "selling_points": ["Proper handling of confidential information", "2years+ relvant experience", "Able to work independently and be detail-oriented"], "locations": ["Tsim Sha Tsui"], "categories": ["Admin & HR", "Personal / Executive Assistant"], "post_time": "2022-01-14T09:21:44Z", "salary": {"currency": null, "max": null, "min": null, "period": "monthly", "term": null}, "salary_visible": false, "title_keywords": ["personal assistant"], "responsibilities": ["forecasting", "travel arrangements", "documentation", "invoices", "maintaining", "operations", "budget", "stationery", "executive support", "coordinate", "communication", "conferences", "reports", "schedule", "provide administrative support", "payroll"], "requirements": {"degrees": ["university degree"], "majors": [], "languages": ["cantonese", "english", "mandarin"], "language_level": ["proficiency"], "hard_skills": ["small", "documentation", "dynamic", "processing"], "soft_skills": ["confident", "responsible", "trustworthy", "passion in", "detail-oriented", "communication", "dynamic", "ability to multitask"], "languages_combined": [{"language": "cantonese", "language_level": ["proficiency"]}, {"language": "english", "language_level": ["proficiency"]}, {"language": "mandarin", "language_level": ["proficiency"]}]}, "experience_required": {"duration": ["5 to 8 years"], "field": []}}, {"job_id": "100003009047436", "location_code": "hk", "company": "Richfield Realty Limited", "job_title": "Personal Assistant to Director", "description": "We are a young marketing agency determined to bring together our expertise and creativity to our counterparts. We believe that every individual's potential can create a huge impact. Being part of Ozaru is more than just a job - it\u2019s an adventure. Interact with various departments across the globe that form the unique Ozaru team. We take chances on technology we believe can have a positive impact on the world by empowering people and have the unique mix of talents which has brought and will continue to bring that idea into life.\n\nAbout The Role\n\nWe are on the lookout for a full-time personal assistant who is collaborative, reliable and result-oriented to join our rapid growing business. This role will be supporting our executive directors and ensuring the smooth running of business.\n\nWhat You\u2019ll Do\n\nProvide all-rounded secretarial and administrative support to the executive directors in both business activities and personal matters\u00a0\nManage directors\u2019 electronic diaries, assess priority of appointments and reallocation as necessary\nArrange travel, visas and accommodation, take notes or dictation at meetings or to provide general assistance during presentations\u00a0\nProvide support to the general office administrative tasks, assist and follow up on policy setting, execution and controlling of projects and programs\nResponsible for daily accounting operations including invoicing, staff expense claims, vendor payments, bank reconciliation statement, monthly management accounting and payment related documentation filing\nMaintain office systems, including data management and filing, personal letters, documents, bank statement etc.\nHandle facsimile, emails, phone calls, general and confidential documents\nOrder office supplies and replacements, as well as managing mail and courier services\nBasic book keeping and managing household bills, purchases, credit card/ account reconciliations\nHandle busines correspondence, other confidential and professional documents as instructed\nAny other duties as may reasonably be required by the directors\n\nWhat You\u2019ll Need\n\nDegree holder with at least 2 years relevant experience\u00a0\nEthical and proper handling of confidential information is a must\nAble to work independently and be detail-oriented\nStrong interpersonal and communication skills\nMust be well organised and can work under pressure and tight deadlines\nStrong sense of urgency and problem-solving skills\nAbility to act with integrity, professionalism, and confidentiality\nComfortable in multitasking and can provide efficient results\nProficient computer skills including Word, Excel, PowerPoint, and Outlook\n\nEmployees First, Company Second --- What We Offer\n\nA competitive remuneration package that includes 5-day work, birthday leave, seasonal incentive bonus, medical and dental insurance\nUnlimited coffee, drinks, snacks and more\nA vibrant and dynamic office environment\nFlexible working hours and a flat hierarchical structure\n\nOzaru is committed to a policy of equal employment opportunities and does not discriminate in the terms, conditions, or privileges of employment on account of race, age, color, sex, national origin, physical or mental disability, or religion.", "employment_types": ["Full Time"], "selling_points": [], "locations": ["Tsim Sha Tsui"], "categories": ["Admin & HR", "Personal / Executive Assistant", "Secretary"], "post_time": "2022-01-14T06:04:06Z", "salary": {"currency": null, "max": null, "min": null, "period": "monthly", "term": null}, "salary_visible": false, "title_keywords": ["director", "personal assistant"], "responsibilities": ["any other duties", "related documentation", "data", "bank reconciliation", "communication", "payment", "maintain", "phone calls", "work under pressure", "daily accounting operations", "presentations", "business activities", "provide support", "management", "administrative support", "office supplies", "reconciliations", "administrative tasks", "systems", "letters", "diaries", "invoicing", "payments"], "requirements": {"degrees": ["degree holder"], "majors": [], "languages": [], "language_level": [], "hard_skills": ["excel", "data management", "basic", "vendor", "presentations", "word", "powerpoint", "computer skills", "outlook", "rapid", "documentation", "problem-solving skills"], "soft_skills": ["collaborative", "detail-oriented", "work under pressure", "efficient", "determined", "integrity", "ethical", "smooth", "reliable", "interpersonal", "communication skills", "work independently", "unique", "problem-solving skills", "result-oriented", "positive", "responsible", "urgency", "organised"], "languages_combined": []}, "experience_required": {"duration": ["at least 2 years"], "field": ["relevant experience"]}}, {"job_id": "100003009048699", "location_code": "hk", "company": "Henderson Land Development Company Limited", "job_title": "SENIOR SECRETARY", "description": "Responsibilities:\n\n\u00a0Provide secretarial and all round support to Director & Management;\n\u00a0Assist in all personal matters, business development activities and handle all internal correspondences;\n\u00a0Work cohesively with other departments to ensure smooth operation;\n\u00a0Prepare presentation materials, proposals and reports;\n\u00a0Attend meetings\u00a0and functions with senior Manager;\n\u00a0Perform ad hoc and confidential duties and responsibilities as assigned.\n\nRequirements:\n\n\u00a0University graduate\u00a0with formal secretarial training.\n\u00a01-2\u00a0years\u00a0of relevant secretarial experience with stable employment history at sizable companies.\n\u00a0Able to handle business\u00a0correspondence professionally.\n\u00a0Good command of English and Cantonese included Mandarin.\n\u00a0Young, Cheerful, Energetic and Good Communication Skill\n\u00a0Occasional\u00a0travel may be required.\n\u00a0Presentable, independent, organized and self-motivated.\n\u00a0Willing to work under pressure and overtime.\n\u00a0Immediately available is highly preferred.\n\nWe offer 5-day work with one\u00a0Saturday (half working day) per month, Banking Holiday, Free Meal, Double Pay, Year-end Bonus and attractive remuneration to right candidate.\n\nInterested parties please send your detailed resume with current and expected salary,\u00a0contact number and email\u00a0address to by clicking \"Apply Now\".\n\n(Personal data collected will be used for recruitment purpose only).", "employment_types": ["Full Time", "Permanent"], "selling_points": ["Medical Allowance", "Education Allowance", "Free Lunch"], "locations": ["Central"], "categories": ["Admin & HR", "Personal / Executive Assistant", "Secretary", "Property / Real Estate", "Others"], "post_time": "2022-01-14T07:04:08Z", "salary": {"currency": null, "max": null, "min": null, "period": "monthly", "term": null}, "salary_visible": false, "title_keywords": ["senior secretary"], "responsibilities": ["attend meetings", "management", "reports", "ad hoc"], "requirements": {"degrees": ["university graduate"], "majors": [], "languages": ["cantonese", "english", "mandarin"], "language_level": ["good command"], "hard_skills": ["sizable companies"], "soft_skills": ["organized", "self-motivated", "cheerful", "independent", "communication skill", "presentable", "stable", "energetic", "work under pressure"], "languages_combined": [{"language": "cantonese", "language_level": ["good command"]}, {"language": "english", "language_level": ["good command"]}, {"language": "mandarin", "language_level": ["good command"]}]}, "experience_required": {"duration": ["1-2 years"], "field": ["secretarial"]}}, {"job_id": "100003009052148", "location_code": "hk", "company": "KPMG", "job_title": "Administrative / Operation Officer (Fresh Graduate / Full-time / Part-time are welcomed)", "description": "Ref. No.: JDB/SS\n\nUniversity graduate from overseas university\nExcellent in both written and spoken English and Chinese including Putonghua\nGood command of PC knowledge\nMinimum 10 years' relevant experience in supporting the top management with formal secretarial training\nAble to handle business correspondence, arrange tight schedule professionally\nAble to work independently and under pressure, with initiative and flexible with good working attitude\nHigh professional standard of integrity and confidentiality\n\nAttractive salary and fringe benefits will be offered to the successful candidates. Please apply with full resume by mail to\u00a0Human Resources Department, Henderson Land Development Co. Ltd., 71/F, Two International Finance Centre, 8 Finance Street, Central, Hong Kong\u00a0or by fax at\u00a02905 1855\u00a0or visit our homepage at\u00a0http://www.hld.com\u00a0or\u00a0by clicking \"Apply Now\".\n\n(Please quote the ref. no. on letter)\u00a0\n\nPersonal data provided by job applicants will be used for recruitment purpose only.\u00a0", "employment_types": ["Full Time", "Part Time"], "selling_points": ["Diploma degree or above in any discipline", "Experience of handling application processes", "Experience of working in customer service"], "locations": ["Aberdeen"], "categories": ["Admin & HR", "Clerical / Admin Staff", "Personal / Executive Assistant", "Others"], "post_time": "2022-01-17T02:16:22Z", "salary": {"currency": null, "max": null, "min": null, "period": "monthly", "term": null}, "salary_visible": false, "title_keywords": ["operation officer"], "responsibilities": ["management", "schedule"], "requirements": {"degrees": ["university graduate"], "majors": [], "languages": ["putonghua", "english", "chinese"], "language_level": ["excellent"], "hard_skills": ["no", "pc knowledge"], "soft_skills": ["flexible", "good working attitude", "work independently", "under pressure", "integrity", "initiative"], "languages_combined": [{"language": "putonghua", "language_level": []}, {"language": "english", "language_level": ["excellent"]}, {"language": "chinese", "language_level": ["excellent"]}]}, "experience_required": {"duration": ["minimum 10 years"], "field": ["management", "relevant experience", "training", "secretarial"]}}, {"job_id": "100003009047927", "location_code": "hk", "company": "On Time Express Ltd", "job_title": "Executive Assistant", "description": "Overview\n\nKPMG Managed Services (MSS) delivers large scale processing and remediation services through innovative and technology-enabled solutions.\u00a0 Through remediation services, we provide cost effective business solutions to clients, and provide organisations with customised project plans and regulated business processes to achieve operational efficiencies across different sectors and industries.\n\nFor those who enjoy administration activities, this role will be interesting for you.\n\nResponsibilities\n\nThis is an operations based role where you\u00a0will be part of a big team with individual caseload responsibilities. You will:-\n\nEngage\u00a0directly with customers to obtain specific information\nHandle customer enquiries and feedback professionally to make customer experience positive\nProcess and review customer applications from start to finish and take prompt actions along the journey to ensure timely and compliant completion\nLearn technical skills and become fluent and familiar with established Operation Guidelines and Standard Operating Procedures \u00a0\nConduct and support quality assurance, quality control, vetting and internal compliance checks on individual cases\nProvide feedback/results to relevant stakeholders in a timely manner\nBe required to deliver high standards in productivity and quality outputs.\nPart-time is also welcomed\n\nRequirements\n\nExperience of handling application processes / administrative work is helpful\u00a0\nCandidates with no relevant experience and fresh graduate would also be considered. Training will be provided\nGood communication skills and good command of written and spoken Chinese (Cantonese) and English. Proficiency in Mandarin is an advantage\nDiploma degree or above in any discipline (candidates with HKALE / HKDSE / HKCEE or equivalent secondary education background and prior administrative experience would also be considered)\nProficiency in Microsoft Office (PowerPoint, Word, Excel) or similar applications\nGood analytical and problem-solving capabilities with an enquiring mind\nA good team player, efficient and can remain composed under pressure\nStable work environment\n\nHow to apply\n\nTo apply please send your CV and salary expectation to us.\n\nWe offer successful candidates an attractive remuneration package and the opportunity to work in a dynamic and exciting environment.\u00a0\n\nFor candidates who are looking for positions in KPMG Audit, Tax and Advisory functions, please refer to\u00a0https://joinus.kpmg.com.cn/en/listing/\u00a0 for job openings.\n\nPersonal data collected will be used for recruitment purposes only.\u00a0\n\n\u00a9 2021 KPMG, a Hong Kong partnership and a member firm of the KPMG global organisation of independent member firms affiliated with KPMG International Limited, a private English company limited by guarantee. All rights reserved.", "employment_types": ["Full Time", "Permanent"], "selling_points": ["Organizing meeting appointment, answer phone call", "Collecting and drafting document, report & minutes", "Travel, Visa & travel Itinerary"], "locations": ["Kowloon Bay"], "categories": ["Admin & HR", "Personal / Executive Assistant", "Secretary", "Transportation & Logistics", "Freight Forwarding"], "post_time": "2022-01-14T04:17:19Z", "salary": {"currency": null, "max": null, "min": null, "period": "monthly", "term": null}, "salary_visible": false, "title_keywords": ["executive assistant"], "responsibilities": ["handle customer enquiries", "guidelines", "operations", "review", "procedures", "quality", "compliance", "a timely manner", "quality control"], "requirements": {"degrees": ["fresh graduate", "secondary education", "degree or above", "diploma", "hkdse"], "majors": [], "languages": ["cantonese", "english", "chinese", "mandarin"], "language_level": ["advantage", "proficiency", "good command", "good"], "hard_skills": ["excel", "no", "microsoft office", "problem-solving", "word", "powerpoint"], "soft_skills": ["efficient", "communication skills", "good team player", "under pressure", "problem-solving", "stable"], "languages_combined": [{"language": "cantonese", "language_level": ["good command", "good"]}, {"language": "english", "language_level": ["good command", "good"]}, {"language": "chinese", "language_level": ["good command", "good"]}, {"language": "mandarin", "language_level": ["proficiency", "advantage"]}]}, "experience_required": {"duration": [], "field": ["administrative", "relevant experience", "education"]}}, {"job_id": "100003009047910", "location_code": "hk", "company": "Links International", "job_title": "Personal Assistant (Personal/ Family support) - up to50K", "description": "Responsibilities:\n\nScreening phone calls, enquiries and requests, and handling them when appropriate\nOrganizing and maintaining diaries and making appointments\nOrganizing meeting appointments\nCollecting and Drafting documents, briefing papers, reports, presentations, agenda & minutes\nLiaising with internal staffs, external clients and business partners\nAssist in responding to Station Manager's email\nMeeting and greeting visitors\nArranging travel, visas and accommodation and organizing travel and preparing travel itineraries\nReport to Station Manager\n\n\u00a0Requirements:\n\nHigh Diploma or above and min 2 years related experience preferable\nGood in spoken Mandarin and excellent in written English\nFamiliar with Outlook, Microsoft Excel, Words and Powerpoint\nWorking experience in freight forwarder industry is preferred\nGood interpersonal & communication skills\nAbility to work on your own initiative\nAbility to multi task and result-oriented\nHonesty and reliability\n\nWe offer an exciting work environment and excellent career development opportunities. If you have the desire for an exciting and rewarding career, please send us your resume\u00a0stating current & expected salary and date of availability by clicking \"Apply Now\" below.\n\nOnly short-listed candidates will be contacted.\n\nOn Time\u00a0is an equal opportunity employer and welcomes applications from all qualified candidates. Information provided will be treated in strict confidence and will only be used for recruitment-related purposes. Personal data provided by job applicants will be used strictly in accordance.\u00a0", "employment_types": ["Full Time", "Permanent"], "selling_points": ["Support personal, family and kids schedule", "Work at client's home", "5 days office work (Mon - Sat Altn)"], "locations": ["Not Specified"], "categories": ["Admin & HR", "Personal / Executive Assistant", "Secretary"], "post_time": "2022-01-14T04:13:03Z", "salary": {"currency": "HKD", "max": 54999, "min": 30000, "period": "monthly", "term": null}, "salary_visible": true, "title_keywords": ["personal", "personal assistant"], "responsibilities": ["maintaining", "liaising with", "presentations", "diaries", "reports", "report", "phone calls", "greeting visitors"], "requirements": {"degrees": ["high diploma or above"], "majors": [], "languages": ["english", "mandarin"], "language_level": ["excellent", "good"], "hard_skills": ["powerpoint", "outlook", "words", "microsoft excel"], "soft_skills": ["result-oriented", "communication skills", "initiative", "interpersonal"], "languages_combined": [{"language": "english", "language_level": []}, {"language": "mandarin", "language_level": ["good", "excellent"]}]}, "experience_required": {"duration": ["min 2 years"], "field": ["related"]}}, {"job_id": "100003009047825", "location_code": "hk", "company": "C-Mer Dennis Lam & Partners Eye Center", "job_title": "Executive Assistant", "description": "\nResponsibilities:\n\n\n\nProvide full spectrum of Personal and family support the boss\nAssist for family support, working closely with the butler, drivers, helpers and private tutor\nResponsible for inventory management, stock arrangement, household admin work etc\nAssist for kid's arrangement, such as school activities, after school tutor, enrolment etc\nArranging family event and public events, invite guest, prepare materials and follow up the logistic etc\nBack up for family matters when the butler is on leave, such as payroll, assign helper's duties, furniture repairs, household expense etc\nHandle ad-hoc tasks are assigned\n\nSkills and requirements:\n\n\n\nMin 5 years' experience in hospitality, family PA or other relevant work experience\nPrevious working experience in Personal Assistant or Secretary is an advantage\nStrong organizational, communication and interpersonal skills\nExcellent command in both written and spoken English & Chinese\nGood computer literacy (Microsoft Word, Excel, PowerPoint, Chinese Word Processing and Outlook)\nImmediate available is preferred\n\n\nInterested parties please submit your application by clicking 'apply now' below and upload your updated resume.\n\n", "employment_types": ["Full Time"], "selling_points": ["Support administrative duties of Marketing team", "5-day work, Monday to Friday", "Candidates with aviation/hotel exp will be a plus"], "locations": ["Central"], "categories": ["Admin & HR", "Clerical / Admin Staff", "Personal / Executive Assistant", "Secretary"], "post_time": "2022-01-14T03:58:00Z", "salary": {"currency": null, "max": null, "min": null, "period": "monthly", "term": null}, "salary_visible": false, "title_keywords": ["executive assistant"], "responsibilities": ["inventory management", "ad-hoc tasks", "payroll"], "requirements": {"degrees": [], "majors": [], "languages": ["english", "chinese"], "language_level": ["excellent", "good"], "hard_skills": ["excel", "microsoft word", "chinese word processing", "powerpoint", "outlook"], "soft_skills": ["organizational", "communication and interpersonal skills", "computer literacy"], "languages_combined": [{"language": "english", "language_level": ["excellent"]}, {"language": "chinese", "language_level": ["excellent", "good"]}]}, "experience_required": {"duration": ["min 5 years"], "field": []}}, {"job_id": "100003009049833", "location_code": "hk", "company": "Tin Ching Industrial Company Limited", "job_title": "Personal Assistant", "description": "Responsibilities:\n\nHandle internal & external delivery/filing of marketing materials\nCoordinate and manage the office administrative affairs & office equipment\nSupport for organizing department events, meetings and take meeting notes\nProvide full range administration support, including filing, documentation, data entry and reports preparation\nProvide a wide range of administrative & clerical duties to support Marketing Director\nWork on marketing related admin jobs\nOther ad hoc duties assigned by the management\n\nRequirements:\n\nDiploma holder or above\nAt least 1 year experience in administrative work. Fresh graduates will also be considered\nCandidates with aviation/hotel industry experience will be a plus\nSelf-motivated, proactive, well-organized, detail-minded, and independent with strong interpersonal skills\nAble to work independently and multi-task effectively in a fast-paced environment\nComputer literacy in Microsoft Word, Excel, PowerPoint and Chinese Word Processing\nImmediate available is preferred\n*Please include a recent photo and your expected salary in the CV for the application*", "employment_types": ["Full Time"], "selling_points": ["Secretarial and administrative support", "Calendar management, prepare documents", "To coordinate with internal and external parties"], "locations": ["Admiralty"], "categories": ["Admin & HR", "Personal / Executive Assistant", "Secretary"], "post_time": "2022-01-14T09:18:20Z", "salary": {"currency": null, "max": null, "min": null, "period": "monthly", "term": null}, "salary_visible": false, "title_keywords": ["personal assistant"], "responsibilities": ["ad hoc duties", "management", "documentation", "data entry", "coordinate", "reports", "marketing materials", "administration"], "requirements": {"degrees": ["diploma holder"], "majors": [], "languages": ["chinese"], "language_level": [], "hard_skills": ["excel", "plus", "microsoft word", "chinese word processing", "powerpoint"], "soft_skills": ["detail-minded", "self-motivated", "work independently", "independent", "multi-task", "fast-paced environment", "well-organized", "computer literacy", "interpersonal skills", "proactive"], "languages_combined": [{"language": "chinese", "language_level": []}]}, "experience_required": {"duration": ["at least 1 year"], "field": ["administrative", "hotel industry"]}}, {"job_id": "100003009047063", "location_code": "hk", "company": "i-CABLE Communications Limited", "job_title": "Executive Assistant", "description": "Responsibilities:\n\n\nProvide\u00a0 secretarial and administrative support to Senior Management in both business activities and personal matters\nResponsible for scheduling meeting, travel arrangement, calendar management, as well as prepare documents\u00a0\nTo coordinate with internal and external parties on personal matters and business operations\nAd hoc tasks assigned by the Management\n\nRequirements:\n\nDegree holder\u00a0with 2 years or more relevant working experience\nHigh proficiency in MS Office\nExcellent research and analytical skills\nWell organized, attentive to details, able to handle multi-tasks with strong sense of responsibility\nImmediately available is preferred\nFresh graduate will be considered", "employment_types": ["Full Time", "Permanent"], "selling_points": [], "locations": ["Tsuen Wan Area"], "categories": ["Admin & HR", "Clerical / Admin Staff", "Personal / Executive Assistant", "Secretary"], "post_time": "2022-01-14T02:13:08Z", "salary": {"currency": null, "max": null, "min": null, "period": null, "term": null}, "salary_visible": false, "title_keywords": ["executive assistant"], "responsibilities": ["management", "administrative support", "operations", "internal and external parties", "coordinate with", "ad hoc tasks", "scheduling", "travel arrangement", "senior management", "prepare documents", "business activities"], "requirements": {"degrees": ["fresh graduate", "degree holder"], "majors": [], "languages": [], "language_level": [], "hard_skills": ["analytical skills", "ms office"], "soft_skills": ["multi-tasks", "sense of responsibility", "attentive to details", "well organized", "analytical skills"], "languages_combined": []}, "experience_required": {"duration": ["2 years"], "field": ["relevant working experience"]}}, {"job_id": "100003009051248", "location_code": "hk", "company": "King's Cross Recruitment", "job_title": "Admin/Personal Assistant", "description": "\u00a0 \u00a0 \u00a0 \u00a0 \u00a0 \u00a0 \u00a0 \u00a0 \u00a0 \u00a0 \u00a0 \u00a0 \u00a0 \u00a0 \u00a0 \u00a0 \u00a0 \u00a0 \u00a0 \u00a0 \u00a0 \u00a0 \u00a0 \u00a0 \u00a0Strategy and Transformation Department\n\nKey responsibilities\nTo manage administrative matters and office support, such as arranging meetings, managing office resources, and any other ad hoc tasks as instructed\nTo manage information flow in a timely and accurate manner\nTo coordinate and liaise with external parties on various tasks, acting as the point of contract and ensuring smooth communication and handling\nTo plan and organize team activities, workshops, and other events in a timely manner, making sure team\u2019s priorities are met\n\nCompetencies\u00a0\nFlexible team player; able to work with people from different background, adaptable and good personality\nHigh integrity\nExcellent written and verbal communication skills\nStrong time-management skills and ability to organize and coordinate multiple projects at the same time\nProficiency in Microsoft Office and other office productivity tools\nFast learning skills with aptitude to learn new software or systems\nWork experience in administrative role preferred\nWe offer 5-day work week, competitive remuneration packages and advancement opportunities. Interested parties, please write with full resume to Director, Human Resources, Human Resources Department, i-CABLE Communications Limited, 4/F Cable TV Tower, 9 Hoi Shing Road Tsuen Wan, N.T. or fax to 2112 7841 or via Apply Now (Please quote reference number and position applied for). For other information, please visit our website http://www.i-cable.com.\n\nYour application may be forwarded to any affiliate companies and successful applicant may be seconded to work at any office as assigned.\u00a0 The information received will be used for consideration of employment only and all personal data supplied will be destroyed within 3 months.\n\nWe are an equal opportunity employer.", "employment_types": ["Full Time", "Permanent"], "selling_points": ["5 day work, 14 days annual leave", "Base 11k+bonus", "Double pay"], "locations": ["Tsim Sha Tsui"], "categories": ["Admin & HR", "Clerical / Admin Staff", "Personal / Executive Assistant", "HR Supporting Staff"], "post_time": "2022-01-15T06:11:26Z", "salary": {"currency": "HKD", "max": 13999, "min": 11000, "period": "monthly", "term": null}, "salary_visible": true, "title_keywords": ["admin", "personal assistant"], "responsibilities": ["management", "software", "external parties", "ad hoc tasks", "office support", "a timely manner", "systems", "coordinate", "communication", "plan", "liaise with", "multiple projects"], "requirements": {"degrees": [], "majors": [], "languages": [], "language_level": [], "hard_skills": ["workshops", "microsoft office"], "soft_skills": ["flexible", "communication skills", "adaptable", "timely", "integrity", "communication", "learning", "smooth", "team player", "accurate"], "languages_combined": []}, "experience_required": {"duration": [], "field": ["administrative"]}}, {"job_id": "100003009048023", "location_code": "hk", "company": "The Hong Kong Polytechnic University", "job_title": "Executive Assistant", "description": "Job Description\u00a0\n\n\n\n\u00a0Handle Recruitment\u00a0\n\u00a0Ensure smooth day to day business operation\u00a0\u00a0\n\u00a0Other ad-hoc duties as assign\u00a0\n\u00a0Sort and review incoming mails/ emails/ correspondences\u00a0\n\nJob\u00a0Requirements\n\n\u00a0DSE holder or above\n\u00a0\u00a0Strong coordination, communication, excellent representational and interpersonal skills, able to work independently and a good team player\n\u00a0 Attention to details\n\u00a0 Fluent in Cantonese, English and Mandarin a plus\nImmediately available is highly preferred\u00a0\u00a0\nKnowledge of Microsoft Office\nWe Offer\n\n\n\u00a0Base Salary of 11k + Bonus\n\u00a05 Days work\nDouble Pay\nMedical insurance and MPF\n14 Days annual leave\u00a0", "employment_types": ["Full Time"], "selling_points": [], "locations": ["Not Specified"], "categories": ["Admin & HR", "Clerical / Admin Staff", "Personal / Executive Assistant", "Secretary"], "post_time": "2022-01-14T04:34:07Z", "salary": {"currency": null, "max": null, "min": null, "period": "monthly", "term": null}, "salary_visible": false, "title_keywords": ["executive assistant"], "responsibilities": ["day to day business operation", "review", "recruitment", "ad-hoc duties"], "requirements": {"degrees": ["dse"], "majors": [], "languages": ["cantonese", "english", "mandarin"], "language_level": ["fluent"], "hard_skills": ["plus", "microsoft office"], "soft_skills": ["good team player", "work independently", "communication", "interpersonal skills", "coordination", "attention to details"], "languages_combined": [{"language": "cantonese", "language_level": ["fluent"]}, {"language": "english", "language_level": ["fluent"]}, {"language": "mandarin", "language_level": ["fluent"]}]}, "experience_required": {"duration": [], "field": []}}, {"job_id": "100003009051924", "location_code": "hk", "company": "Octopus Holdings Limited", "job_title": "Operation Services Assistant (Card Centre) Ref: OCL/OPS/2021-023-042  (Temporary)", "description": "DEPARTMENT OF ELECTRICAL ENGINEERING\n\nExecutive\u00a0Assistant (Ref. 22011404-E)\n\nDuties\n\nThe appointee will be required to:\n\n(a) provide administrative support to both academic and research programmes;\n\n(b) support a wide range of activities of the Unit, including administration of student-related matters (e.g. admission, registration, examination, timetabling and student record), and various student-related events and projects;\n\n(c) provide secretarial support to meetings and committees;\n\n(d) compile statistical reports and maintain database;\n\n(e) support general office administration; and\n\n(f) perform any other duties as assigned by the Head of the Unit or his delegates.\nThe appointee may be required to work outside office hours.\n\nQualifications\n\nApplicants should have:\n\n(a) a recognized degree or an equivalent qualification;\n\n(b) at least two years of relevant post-qualification experience;\n\n(c) a good command of both English and Chinese, with fluency in Putonghua being an advantage;\n\n(d) proficiency in computer software applications including MS office (e.g. MS Excel, Word, PowerPoint) and Chinese word processing;\n\n(e) good communication, interpersonal and time management skills; and\n\n(f) self-motivation and the ability to work independently and proactively.\n\nPreference will be given to those with experience in tertiary institutions/similar organizations.\n\nShortlisted candidates may be invited to sit for a written test and a computer test.\n\nRemuneration and Conditions of Service\n\nA highly competitive remuneration package will be offered. Initial appointment will be on a fixed-term one-year gratuity-bearing contract. Re-engagement thereafter is subject to mutual agreement. Applicants should state their current and expected salary in the application.\n\nApplication\n\nPlease send a completed application form by post to Human Resources Office, 13/F, Li Ka Shing Tower, The Hong Kong Polytechnic University, Hung Hom, Kowloon, Hong Kong or via email by clicking \"Apply Now\".\u00a0 Application forms can be downloaded from https://www.polyu.edu.hk/hro/careers/guidelines_and_forms/forms.\u00a0 If a separate curriculum vitae is to be provided, please still complete the application form which will help speed up the recruitment process.\u00a0 Consideration of applications will commence on 26 January 2022 until the position is filled.\u00a0 The University\u2019s Personal Information Collection Statement for recruitment can be found at https://www.polyu.edu.hk/hro/careers/guidelines_and_forms/pics_for_recruitment.\n\nPolyU is an equal opportunity employer committed to diversity and inclusivity.\u00a0 All qualified applicants will receive consideration for employment without regard to gender, ethnicity, nationality, family status or physical or mental disabilities.", "employment_types": ["Temporary", "Contract"], "selling_points": ["Perform investigation of Octopus refund", "Handle card refund or replacement", "1 year of clerical working experience"], "locations": ["Tsuen Wan Area"], "categories": ["Admin & HR", "Administration / Operation Manager", "Personal / Executive Assistant", "Others"], "post_time": "2022-01-17T01:32:40Z", "salary": {"currency": null, "max": null, "min": null, "period": "monthly", "term": null}, "salary_visible": false, "title_keywords": ["assistant"], "responsibilities": ["any other duties", "management", "software", "office administration", "communication", "maintain", "reports", "secretarial support", "database", "recruitment", "provide administrative support", "recruitment process", "administration"], "requirements": {"degrees": ["degree"], "majors": [], "languages": ["putonghua", "english", "chinese"], "language_level": ["fluency", "advantage", "good command"], "hard_skills": ["chinese word processing", "word", "powerpoint", "ms excel", "c", "ms office"], "soft_skills": ["work independently", "time management skills", "communication", "committed", "self-motivation", "interpersonal"], "languages_combined": [{"language": "putonghua", "language_level": ["fluency", "advantage", "good command"]}, {"language": "english", "language_level": ["advantage", "good command"]}, {"language": "chinese", "language_level": ["advantage", "good command"]}]}, "experience_required": {"duration": ["at least two years"], "field": ["post-qualification"]}}, {"job_id": "100003009049181", "location_code": "hk", "company": "Kaisa Capital Investment Holdings Limited", "job_title": "Personal Assistant \u79c1\u4eba\u52a9\u7406", "description": "Job Responsibilities: \u00a0\nPersonalised Octopus Application\nProcess Personalised Octopus application including data input, data verification and photo scanning for\nproduction of Personalised Octopus.\nPrepare Personalised Octopus application data preparation and work with outsourcing service providers.\nHandle internal enquiries on card orders\nCheck the quality of the written data in chip and printed data on the card face of Personalised Octopus.\nMalfunction and Sold Products Operations\nIssue replacement Octopus according to customer\u2019s request \u00a0\nHandle card refund or replacement of corporate staff Octopus\nHandle mailing consolidation and returned mails\nProvide warehouse operation support and card stock housekeeping \u00a0\nCard Refund and Lost Card Operations\nPerform investigation of Octopus refund and replacement request and perform related data entry according\nto customer\u2019s request and Octopus card refund and replacement procedures\nPrepare reports for daily reconciliation and various MIS reports\nHandle customer enquiries timely and tactfully\u00a0\n\nRequirements:\nHKCEE or DSE graduate with 5 subjects passed, including English, Chinese and Mathematics \u00a0\nUndergraduate degree holder is preferred\n1 year of clerical working experience, preferably in financial institution\nEnglish and Chinese Typing speed at 35 w.p.m.\nGood command of spoken and written English and Chinese. \u00a0\nGood numerical sense, logical and analytical skills \u00a0\nGood team player with strong sense of customer service awareness and interpersonal skills\nAble to work under pressure\nWe offer successful candidate an attractive remuneration package and excellent career prospects. Interested parties please send your resume, present and expected salary, contact details and quoting the reference number by clicking \"Apply Now\"\n\nVisit our web site: http://www.octopus.com.hk/\n\nThe personal data collected will be used for recruitment purposes only. If you are not contacted by us within six weeks, you may consider your application unsuccessful. Personal data with an unsuccessful applicant will be destroyed 12 months after rejection of the application. During this retention period, you have the right to request for correction or destruction of your personal data at any time. Any request for the correction or destruction of personal data should be addressed in writing to our Human Resources & Administration Department.\n\nOctopus is an equal opportunity employer and all employment decisions and Human Resources policies are administered; especially those relating to recruitment & selection, compensation & benefits, promotion & transfer, training & development and termination & redundancy; without discrimination on the basis of age, race, colour, religion, sex, national origin, marital status, pregnancy, physical and mental disability and family status but on genuine occupational qualification, job performance, employees\u2019 ability and internal/ external relativities.\n%MCEPASTEBIN%", "employment_types": ["Full Time"], "selling_points": ["Degree", "Good command in Putonghua", "At least 2 years experience"], "locations": ["Others"], "categories": ["Admin & HR", "Personal / Executive Assistant"], "post_time": "2022-01-14T08:13:58Z", "salary": {"currency": null, "max": null, "min": null, "period": "monthly", "term": null}, "salary_visible": false, "title_keywords": ["\u79c1\u4eba\u52a9\u7406", "personal assistant"], "responsibilities": ["scanning", "handle customer enquiries", "data verification", "data", "housekeeping", "operations", "data entry", "quality", "data input", "investigation", "procedures", "reports", "prepare reports"], "requirements": {"degrees": ["dse", "degree holder"], "majors": ["mathematics"], "languages": ["english", "chinese"], "language_level": ["good command"], "hard_skills": ["typing", "analytical skills"], "soft_skills": ["good team player", "analytical skills", "customer service", "interpersonal skills", "work under pressure"], "languages_combined": [{"language": "english", "language_level": ["good command"]}, {"language": "chinese", "language_level": ["good command"]}]}, "experience_required": {"duration": ["1 year"], "field": ["clerical", "financial"]}}, {"job_id": "100003009049378", "location_code": "hk", "company": "Sincere Brand Management Limited", "job_title": "Executive Assistant", "description": "Responsibilities:\n\nManage calendar, coordinate meetings, events, organize daily schedules and travel arrangement\nProvide support to the employer and family on a daily basis.\nWilling to handle multi-tasks and ad hoc assignment is required\nRequirement:\u00a0\n\nDegree Holder\n2years of solid experience serving top executives\nGood command in Putonghua; excellent written and spoken English\nWell-organized, details-oriented and able to work independently;\nDriving License\u00a0\nInterested party please apply the position by clicking \"Apply\" to send us your resume with your expected / current salary.", "employment_types": ["Full Time"], "selling_points": ["Listed Company", "Provide secretarial and administrative support", "Report to Managing Director"], "locations": ["Central"], "categories": ["Admin & HR", "Personal / Executive Assistant", "Secretary", "Others"], "post_time": "2022-01-14T08:31:49Z", "salary": {"currency": null, "max": null, "min": null, "period": "monthly", "term": null}, "salary_visible": false, "title_keywords": ["executive assistant"], "responsibilities": ["provide support", "schedules", "ad hoc assignment", "coordinate", "travel arrangement"], "requirements": {"degrees": ["degree holder"], "majors": [], "languages": ["putonghua", "english"], "language_level": ["excellent", "good command"], "hard_skills": [], "soft_skills": ["work independently", "well-organized"], "languages_combined": [{"language": "putonghua", "language_level": ["good command"]}, {"language": "english", "language_level": ["excellent"]}]}, "experience_required": {"duration": [], "field": []}}, {"job_id": "100003009046414", "location_code": "hk", "company": "BlessVision Foundation Limited", "job_title": "Personal Assistant to Senior Management", "description": "Key Responsibilities:\u00a0\n\nProviding a full spectrum of secretarial and administrative supports to Managing Director / Top Management\nPreparing reports, memos, PowerPoint slides and correspondences\nTranslating documents, PowerPoint slides, emails, marketing materials between Simplified Chinese and English\nHelping prepare for meetings and accurately recording meetings minutes\nServing as a contact point between company driver and internal parties for the travelling schedule\nCo-ordinating car repairing and maintenance, handling renewal of licenses and other related works as required\u00a0\nMaking travel arrangements including flights, accommodations, visa applications and local transportations\nCoordinating and organizing corporate events / activities\nPerforming ad hoc duties as assigned\nRequirements:\n\n\nDiploma or above with at least 3 years\u2019 relevant working experience in serving top management\nDetail-minded in organizing schedules and completing tasks efficiently\nSelf-starter, mature, reliable and cheerful\nFlexible, multi-tasking, able to work\u00a0independently and under pressure,\u00a0and meet tight deadlines\nProactive, reliable, detail-oriented and well-organized\nQuick response with excellent interpersonal and communication skills\nProficiency in PowerPoint, Word, Excel and Chinese Word Processing\nExcellent command in spoken and written English and Chinese (Cantonese and Putonghua)\nInterest parties please click the \"Apply Now\" button below and submit your full and updated resume with current and expected salary and date of availability.\u00a0\n\n\n\nPlease visit our website at http://www.sincerewatch.com.hk to know more about us.\n\nAll personal data provided will be used for recruitment purpose and treated in strict confidence.", "employment_types": ["Full Time"], "selling_points": ["Excellent written and verbal communication skills", "Mature, organized, cheerful and positive attitude", "With caring heart by Jesus\u2019 love"], "locations": ["Ngau Tau Kok"], "categories": ["Admin & HR", "Personal / Executive Assistant", "Secretary"], "post_time": "2022-01-14T06:27:36Z", "salary": {"currency": null, "max": null, "min": null, "period": "monthly", "term": null}, "salary_visible": false, "title_keywords": ["personal assistant"], "responsibilities": ["ad hoc duties", "management", "travel arrangements", "maintenance", "contact", "preparing reports", "schedule", "marketing materials", "internal parties"], "requirements": {"degrees": ["diploma or above"], "majors": [], "languages": ["cantonese", "putonghua", "english", "chinese"], "language_level": ["proficiency", "excellent"], "hard_skills": ["excel", "chinese word processing", "word", "powerpoint"], "soft_skills": ["detail-minded", "flexible", "work independently", "cheerful", "under pressure", "meet tight deadlines", "proactive", "communication skills", "confidence", "well-organized", "mature", "detail-oriented", "multi-tasking", "reliable", "interpersonal"], "languages_combined": [{"language": "cantonese", "language_level": ["excellent"]}, {"language": "putonghua", "language_level": ["excellent"]}, {"language": "english", "language_level": ["excellent"]}, {"language": "chinese", "language_level": ["proficiency", "excellent"]}]}, "experience_required": {"duration": ["at least 3 years"], "field": ["management", "relevant working experience"]}}, {"job_id": "100003009050010", "location_code": "hk", "company": "Qookia Limited", "job_title": "Personal Assistant", "description": "BlessVision Foundation is a registered charitable organization in HK. We based on Christian values to provide charitable works, life education and humanitarian care. Through media productions, to spread Jesus\u2019 love and support to those are vulnerable from different nationalities. To promote human wellness in body, mind, society and spirit levels. To cope with our continued growth, we are looking for a right candidate to join us.\n\nResponsibilities:\n\nTo provide all-rounded of secretarial support to the Senior Management regarding both organization and personal matters\nExcellent written and verbal communication skills\nStrong interpersonal skills - closely liaise with external parties (Christian media and Christian caring organizations etc.) to ensure smooth ministries\u2019 development /operations\nAssist the Senior Management to handle general correspondences, phone, emails, presentations etc. as required\nManage the Senior Management\u2019s appointments/calendar by planning and scheduling meetings.\nSpecial Projects assistance/coordination/lead\n\nRequirements:\n\nMinimum 2 years of relevant secretary experience\nDisplay strong communication skills to different parties and ad-hoc matters\nExcellent command of written English and Chinese; fluent in spoken English, Cantonese and Putonghua preferred.\nProficient in MS applications and Google-powered business tools (email, calendar, docs)\nWith caring heart by Jesus\u2019 love\nMature, organized, confidential, cheerful and positive attitude\nDedicated and willing to work to irregular time schedules\nStrong commitment to the mission, vision and values of BlessVision Foundation\n\nInterest parties please email your full resume with present & expected salary and state the date of availability.", "employment_types": ["Full Time", "Permanent"], "selling_points": ["Birthday Leave + pocket money", "Joyful working environment with free snacks/drinks", "Flexible working hours"], "locations": ["Kwai Fong"], "categories": ["Admin & HR", "Clerical / Admin Staff", "Personal / Executive Assistant", "Secretary"], "post_time": "2022-01-14T09:37:50Z", "salary": {"currency": null, "max": null, "min": null, "period": "monthly", "term": null}, "salary_visible": false, "title_keywords": ["personal assistant"], "responsibilities": ["operations", "external parties", "presentations", "communication", "scheduling", "secretarial support", "coordination", "liaise with", "senior management", "planning"], "requirements": {"degrees": [], "majors": [], "languages": ["cantonese", "putonghua", "english", "chinese"], "language_level": ["excellent", "fluent"], "hard_skills": ["ms applications"], "soft_skills": ["organized", "communication skills", "cheerful", "mature", "positive attitude"], "languages_combined": [{"language": "cantonese", "language_level": ["fluent"]}, {"language": "putonghua", "language_level": ["fluent"]}, {"language": "english", "language_level": ["excellent", "fluent"]}, {"language": "chinese", "language_level": ["excellent"]}]}, "experience_required": {"duration": ["minimum 2 years"], "field": []}}, {"job_id": "100003009050032", "location_code": "hk", "company": "Grand Cru Cellar International Limited", "job_title": "Secretary / Personal Assistant", "description": "Job Responsibilities\n\nProvide full range of secretarial and administrative support to Management.\nAssistant in handling office administration duties, organizing files, records, and other materials.\nLiaise and coordinate with all internal and external parties\nManage calendars including meeting schedules, personal & family affairs, and travel arrangements\nMaintain filing system and confidential information.\nClosely liaise and coordinate with internal and external parties to ensure smooth business operations.\nPerform ad hoc task as required and other duties as assigned\n\nRequirement:\u00a0\n\nBachelor\u2019s degree or equivalent experience with Business Management or legal background.\n3-5 years\u2019 experience of providing support for upper-level management in a related organization\nStrong organizational skills that reflect ability to perform and prioritize multiple tasks seamlessly with excellent attention to detail.\nExcellent written (English, Traditional and simplified Chinese)\nEnjoy to work with team of diversities. People oriented mindset.\nWork in fast-paced environment and flexibility.\nDriving license is an advantage\n\nBenefits:\n\n5-day work and bank holiday\nPaid birthday leave\nBirthday pocket money\nPerformance bonus\nMedical insurance\nFriendly working environment\n\nInterested parties please apply with the following details:\n\nResume/ CV\nExpected Salary\nEarliest Availability\n\nPlease ensure ALL of the information above are true and up-to-date. All information collected will be used for recruitment purposes only.", "employment_types": ["Permanent"], "selling_points": ["Secretary Personal Assistant", "Provide all-round administrative", "Degree holder or equivalent"], "locations": ["Not Specified"], "categories": ["Admin & HR", "Clerical / Admin Staff", "Personal / Executive Assistant", "Secretary"], "post_time": "2022-01-14T09:39:48Z", "salary": {"currency": null, "max": null, "min": null, "period": "monthly", "term": null}, "salary_visible": false, "title_keywords": ["secretary", "personal assistant"], "responsibilities": ["liaise", "management", "travel arrangements", "ad hoc", "other duties", "administrative support", "schedules", "operations", "internal and external parties", "coordinate with", "maintain", "office administration duties"], "requirements": {"degrees": ["degree", "bachelor"], "majors": ["business"], "languages": ["english", "chinese"], "language_level": ["excellent"], "hard_skills": ["business management"], "soft_skills": ["organizational skills", "prioritize multiple tasks seamlessly", "work in fast-paced environment", "attention to detail"], "languages_combined": [{"language": "english", "language_level": ["excellent"]}, {"language": "chinese", "language_level": ["excellent"]}]}, "experience_required": {"duration": ["3-5 years"], "field": ["related", "management", "business", "legal"]}}, {"job_id": "100003009050617", "location_code": "hk", "company": "Giant Mind (China) Limited", "job_title": "Executive Secretary", "description": "Duties:\n\nProvide all-round administrative and secretarial support to Director/Senior Management\nHandle calendar management and travel logistics arrangement\nWork and communicate closely with driver\nMaintain an efficient administrative and filing system\nAssist to organizing company events and office procurement\nUndertake ad hoc duties as assigned\n\n\u00a0Requirements:\n\nDegree holder or equivalent, with formal secretarial training would be an advantage\n3 years or above of \u00a0relevant working experience\nFamiliar with MS applications (MS Word, Excel, PowerPoint)\nGood command of both spoken & written English, Mandarin & Cantonese\nExcellent team player with strong motivation, proactive, able to work in fast paced, tight deadlines and results-driven environment\nImmediate available would be an advantage\nFresh graduate will also be considered\u00a0as Junior Secretary", "employment_types": ["Full Time"], "selling_points": ["5.5 working days", "bachelor's degree or above", "Relevant experience preferred"], "locations": ["Central"], "categories": ["Admin & HR", "Personal / Executive Assistant", "Secretary"], "post_time": "2022-01-14T10:57:55Z", "salary": {"currency": null, "max": null, "min": null, "period": "monthly", "term": null}, "salary_visible": false, "title_keywords": ["executive secretary"], "responsibilities": ["ad hoc duties", "management", "logistics arrangement", "maintain", "secretarial support", "office procurement", "senior management"], "requirements": {"degrees": ["fresh graduate", "degree holder"], "majors": [], "languages": ["cantonese", "english", "mandarin"], "language_level": ["good command"], "hard_skills": ["excel", "ms applications", "powerpoint", "ms word"], "soft_skills": ["team player", "proactive", "driven"], "languages_combined": [{"language": "cantonese", "language_level": ["good command"]}, {"language": "english", "language_level": ["good command"]}, {"language": "mandarin", "language_level": ["good command"]}]}, "experience_required": {"duration": ["3 years"], "field": ["relevant working experience"]}}, {"job_id": "100003009047937", "location_code": "hk", "company": "The Hang Seng University of Hong Kong", "job_title": "Assistant Officer / Executive Assistant \u2013 Registry (Ref: AO/EA (REG) 2022-01-14)", "description": "ROLES & RESPONSIBILITIES:\n\nResponsible for recruitment process including interview and selection, handle employees on-boarding to off-boarding, verification of candidate's qualification and visa application procedures;\nResponsible for issuing employment contract and other personnel letters;\nPerform payroll functions including monthly payroll, MPF, and filing of tax return;\nLiaise with the Government departments to ensure compliance with Employment Ordinance, Inland Revenue Ordinances, etc;\nLiaise with different services providers such as broker, insurers and MPF trustee for HR operations;\nSupport the development and implementation HR policies, procedures and HR system;\nTo maintain accurate employee record in HR system and filing system;\nResponsible for daily HR operations and general staff enquiries; and\nHandle ad-hoc projects as assigned.\n\nREQUIREMENTS:\n\nHigher diploma or above in Human Resources Management or related disciplines;\nBe well-versed in Employment Ordinance and human resource business functions;\nAt least 1 year of human resources experience;\nHave self-motivation, strong analytical and coordination skills;\nAble to handle sensitive information with confidentiality;\nAble to work under pressure and finish tasks with tight deadline; and\nPossess excellent command written and spoken English and Chinese languages (including Putonghua).\n\nAppointment will initially be made on contract basis for up to two years, renewable subject to performance.", "employment_types": ["Full Time", "Permanent"], "selling_points": [], "locations": ["Not Specified"], "categories": ["Admin & HR", "Administration / Operation Manager", "Personal / Executive Assistant", "Others"], "post_time": "2022-01-14T11:24:33Z", "salary": {"currency": null, "max": null, "min": null, "period": "monthly", "term": null}, "salary_visible": false, "title_keywords": ["assistant officer", "executive assistant"], "responsibilities": ["tax", "mpf", "operations", "hr", "policies", "letters", "procedures", "implementation", "ensure compliance", "maintain", "liaise with", "recruitment process", "ad-hoc projects", "payroll"], "requirements": {"degrees": ["higher diploma or above"], "majors": ["related disciplines"], "languages": ["putonghua", "english", "chinese"], "language_level": ["excellent"], "hard_skills": [], "soft_skills": ["work under pressure", "self-motivation", "coordination skills", "sensitive"], "languages_combined": [{"language": "putonghua", "language_level": ["excellent"]}, {"language": "english", "language_level": ["excellent"]}, {"language": "chinese", "language_level": ["excellent"]}]}, "experience_required": {"duration": ["at least 1 year"], "field": ["human resources"]}}, {"job_id": "100003009048031", "location_code": "hk", "company": "The Hang Seng University of Hong Kong", "job_title": "Assistant Officer / Executive Assistant \u2013 Department of English  (Ref: AO / EA (ENG) 2022-01-14)", "description": "(Ref: AO/EA (REG) 2022-01-14)\n\nResponsibilities:\nprovide administrative and logistic support on programme development (programme accreditation and reaccreditation), synchronisation and standardisation of programme accreditation documents, meetings and other accreditation matters;\nassist in the preparation of programme accreditation documents;\nhandle and maintain central filing on programme development and programme quality assurance matters; and\nserve as secretary to committees and working groups.\n\nApplicants should:\npossess a recognised degree, preferably with 2 years of relevant working experience;\nbe a fast learner, proactive, self-motivated, a good team player and able to work independently with strong sense of responsibility;\npossess good interpersonal and communication skills;\nhave a good command of written and spoken English and Chinese (Cantonese and Putonghua); and\nhave good PC knowledge including MS Word, Excel and Chinese Processing.\nWork experience in the tertiary education sector will be an advantage.\u00a0 Applicants with less experience will be considered as Executive Assistant.\n\n\nSalary will be commensurate with qualifications and experience.\u00a0 Interested applicant should visit this link\u00a0https://recruit.hsu.edu.hk/ and apply on or before 30 January 2022.\u00a0 The University reserves the right not to fill the position in this exercise.\nApplicants who are not invited to an interview within three months may consider their applications unsuccessful.\u00a0 All information received will be treated in strict confidence, and the data collected will be used for recruitment purposes only.\u00a0 The Personal Information Collection Statement will be provided upon request.\nThe Hang Seng University of Hong Kong, incorporated in Hong Kong with limited liability by guarantee, is an equal opportunity employer.", "employment_types": ["Full Time", "Permanent"], "selling_points": [], "locations": ["Not Specified"], "categories": ["Admin & HR", "Clerical / Admin Staff", "Personal / Executive Assistant", "Others"], "post_time": "2022-01-14T11:21:09Z", "salary": {"currency": null, "max": null, "min": null, "period": "monthly", "term": null}, "salary_visible": false, "title_keywords": ["assistant officer", "executive assistant"], "responsibilities": ["data", "quality", "logistic support", "communication", "maintain", "recruitment"], "requirements": {"degrees": ["degree"], "majors": [], "languages": ["cantonese", "putonghua", "english", "chinese"], "language_level": ["good command", "good"], "hard_skills": ["excel", "pc knowledge", "processing", "ms word"], "soft_skills": ["communication skills", "good team player", "self-motivated", "work independently", "confidence", "sense of responsibility", "proactive", "fast learner", "interpersonal"], "languages_combined": [{"language": "cantonese", "language_level": ["good command", "good"]}, {"language": "putonghua", "language_level": ["good command", "good"]}, {"language": "english", "language_level": ["good command", "good"]}, {"language": "chinese", "language_level": ["good command", "good", "good"]}]}, "experience_required": {"duration": ["2 years"], "field": ["relevant working experience", "education"]}}, {"job_id": "100003009041908", "location_code": "hk", "company": "\u83ef\u79d1\u8cc7\u672c\u6709\u9650\u516c\u53f8", "job_title": "Executive Secretary (Board of Director Office)", "description": "\u00a0Responsibilities:\n\nProvide all-rounded secretarial and administrative support to Senior Management in a professional manner;\nArrange & coordinate calendar management & meetings for senior management;\nAssist Management in liaising with internal and external parties for the group's business activities & project management etc.;\nPrepare various types of document including presentation materials, management report, minutes and meeting agenda etc.;\nMaintain records, filing and handle details of highly confidential matters properly;\nHandle incoming and outgoing correspondence and some translations if necessary; and\nPerform ad-hoc duties and business travel as assigned by company\n\nRequirements:\n\nDegree holder in law or business related disciplines;\nAt least 3 years' relevant working experience gained from sizable conglomerate groups or financial groups or serving listing executives;\nCandidate with experience working in financial industry or listing firms is a plus;\nStrong familiarity and knowledge in communicating and working with Executive Management and Senior Executives\nExcellent organizing and planning skills, able to perform multi-tasks to meet tight schedule and attentive to details\u00a0\nMature, responsible, trustworthy, flexible;\nExcellent command in spoken and written English and Chinese (including Putonghua); and\u00a0\nProficient in MS office including Word, Excel, PowerPoint and Chinese Word Processing\n\nPlease submit your application to us with your\u00a0 availability\u00a0 and\u00a0 expected salary.\n\n", "employment_types": ["Full Time", "Permanent"], "selling_points": [], "locations": ["Central"], "categories": ["Admin & HR", "Clerical / Admin Staff", "Personal / Executive Assistant", "Secretary"], "post_time": "2022-01-12T04:38:42Z", "salary": {"currency": null, "max": null, "min": null, "period": "monthly", "term": null}, "salary_visible": false, "title_keywords": ["executive secretary", "director"], "responsibilities": ["management", "administrative support", "internal and external parties", "professional manner", "liaising with", "coordinate", "project management", "maintain", "ad-hoc duties", "senior management", "management report", "business activities"], "requirements": {"degrees": ["degree holder"], "majors": ["related disciplines", "business", "law"], "languages": ["putonghua", "english", "chinese"], "language_level": ["excellent", "proficient"], "hard_skills": ["excel", "plus", "chinese word processing", "word", "powerpoint", "ms office"], "soft_skills": ["flexible", "planning skills", "attentive to details", "multi-tasks", "responsible", "trustworthy", "mature"], "languages_combined": [{"language": "putonghua", "language_level": ["excellent"]}, {"language": "english", "language_level": ["excellent"]}, {"language": "chinese", "language_level": ["excellent", "proficient"]}]}, "experience_required": {"duration": ["at least 3 years"], "field": ["financial industry", "relevant working experience", "financial"]}}, {"job_id": "100003009042596", "location_code": "hk", "company": "Manfield Limited", "job_title": "URGENT - Executive Secretary", "description": "Responsibilities:\n\nReporting to a Director\nProvide full range of good quality secretarial and administrative support;\nManage all business and personal issues for the Director in professional manner, including but not limited to meeting and travel schedules, social events and functions co-ordination etc.;\nPrepare business correspondences, presentation materials, compile reports and meeting minutes in a variety of formats independently and professionally;\nLiaise with internal and external parties to ensure smooth business operations;\nManage payments, claims and reimbursements;\nHandle sensitive and confidential data and documents in professional manner;\nAssist in ad-hoc duties as assigned.\n\n\nRequirements:\u00a0 \u00a0 \u00a0 \u00a0 \u00a0 \u00a0\n\nUniversity Graduate or equivalent;\nMinimum 8 years\u2019 relevant experience with proven track record in serving senior executives or directors, preferably in sizeable companies;\nAbility of maintaining sensitive and confidential information with strictest confidence;\nProficient in MS Office applications with Chinese word processing;\nStrong inter-personal and communication skills;\nExcellent command of spoken and written English, Cantonese and Mandarin;\nMature, self-motivated, meticulous and able to handle multiple tasks with discretion.", "employment_types": ["Full Time", "Permanent"], "selling_points": [], "locations": ["Tsuen Wan Area"], "categories": ["Admin & HR", "Personal / Executive Assistant", "Secretary", "Others"], "post_time": "2022-01-12T10:02:23Z", "salary": {"currency": null, "max": null, "min": null, "period": "monthly", "term": null}, "salary_visible": false, "title_keywords": ["executive secretary"], "responsibilities": ["reporting", "administrative support", "schedules", "compile reports", "operations", "internal and external parties", "quality", "professional manner", "data", "payments", "ad-hoc duties", "liaise with"], "requirements": {"degrees": ["university graduate"], "majors": [], "languages": ["cantonese", "english", "chinese", "mandarin"], "language_level": ["excellent", "proficient"], "hard_skills": ["chinese word processing", "ms office"], "soft_skills": ["communication skills", "self-motivated", "confidence", "meticulous", "inter-personal", "mature", "handle multiple tasks", "sensitive"], "languages_combined": [{"language": "cantonese", "language_level": ["excellent"]}, {"language": "english", "language_level": ["excellent"]}, {"language": "chinese", "language_level": ["proficient"]}, {"language": "mandarin", "language_level": ["excellent"]}]}, "experience_required": {"duration": ["minimum 8 years"], "field": ["relevant experience"]}}, {"job_id": "100003009039357", "location_code": "hk", "company": "Easy Property Co Ltd", "job_title": "Executive Secretary to Director", "description": "Duties & Responsibilities:\n\nProviding secretarial support to the Managing Director\nOrganising the Managing Director\u2019s diary and making appointments\nArranging meetings and taking notes at meetings\nOrganising and maintaining office systems\nPerforming daily HR and administrative works\nAssisting in handling property management & related promotion works\nPerforming other tasks as assigned\n\nRequirements:\n\nForm 7 or above, with formal secretarial training or qualification in business administration is an advantage\nMinimum 5 years of executive or secretarial experience\nGood command of both written and spoken English and Chinese (including Putonghua)\nActive listening, and with excellent communication and interpersonal skills\nExcellent administrative and organisational skills\nStrong problem-solving and multitasking skills\nThe ability to prioritise tasks and remain calm under pressure\nKnowledge of general office procedures and organising an office\u2019s filing system\nProficient in relevant computer and software programs such as MS word, Excel, PowerPoint & Chinese word processing\n\n\n\nInterested parties please send your CV together with your expected salary and date of availability to the Human Resources and Administration Department by simply clicking the \"Apply Now\" button below\n\n\u00a0(Personal data collected would be used for recruitment purpose only.)\n\n\n", "employment_types": ["Full Time", "Permanent"], "selling_points": [], "locations": ["Tsim Sha Tsui"], "categories": ["Admin & HR", "Personal / Executive Assistant", "Secretary"], "post_time": "2022-01-11T16:01:50Z", "salary": {"currency": null, "max": null, "min": null, "period": "monthly", "term": null}, "salary_visible": false, "title_keywords": ["executive secretary", "director"], "responsibilities": ["management", "maintaining", "hr", "systems", "providing secretarial support", "other tasks"], "requirements": {"degrees": [], "majors": [], "languages": ["putonghua", "english", "chinese"], "language_level": ["good command", "proficient"], "hard_skills": ["excel", "chinese word processing", "problem-solving", "powerpoint", "ms word"], "soft_skills": ["under pressure", "problem-solving", "prioritise", "calm", "organisational skills", "communication and interpersonal skills", "active"], "languages_combined": [{"language": "putonghua", "language_level": ["good command"]}, {"language": "english", "language_level": ["good command"]}, {"language": "chinese", "language_level": ["good command", "proficient"]}]}, "experience_required": {"duration": ["minimum 5 years"], "field": ["secretarial"]}}, {"job_id": "100003009048035", "location_code": "hk", "company": "Fangyuan Financial (Hong Kong) Limited", "job_title": "Receptionist", "description": "Location:\u00a0 \u00a0\u00a0\u00a0\u00a0\u00a0\u00a0\u00a0 Central, Hong Kong\n\nPosition: \u00a0\u00a0\u00a0\u00a0\u00a0\u00a0\u00a0\u00a0\u00a0 Permanent\n\nResponsibilities:\n\n\nPerform receptionist duties in professional manner;\nMaintain workspaces at a high standard at all times;\nProvide full spectrum of office administrative and clerical support;\nHandle ad-hoc tasks as assigned.\n\n\u00a0Requirements:\n\n\nExperiences in\u00a0financial or professional services preferred;\nDetail-minded with a can-do attitude;\nExcellent command in written and spoken English and Mandarin.\n\n\u00a0Additional Information and Application Method:\n\nWe offer competitive remuneration package: 5-days work week, minimum 15 days annual paid leave, medical benefit, complimentary office lunch, on the job training and a stable harmonious working environment.\u00a0\n\nInterested parties please send your resume in English and Chinese with\u00a0expected salary\u00a0toby clicking \"APPLY NOW\".\n\n\nAll information received will be kept in strict confidence and only for employment-related purpose.\n\nPersonal Information Collection Statement pertaining to Recruitment:\n\nAll information received will be kept in strict confidence and only for employment-related purpose. The personal data collected will be used to assess your suitability to assume the job duties of the position for which you have applied and to determine preliminary remuneration, benefits package to be discussed with you subject to selection for the position. It is our policy to retain the personal data of unsuccessful applicants for future recruitment purposes for a period of two years.\n\nUnder the Personal Data (Privacy) Ordinance, you have a right to request access to, and to request correction of, your personal data in relation to your application. If you wish to exercise these rights, please complete the \u201cData Access Request Form\u201d specified by the Privacy Commissioner for Personal Data and forward it to HR personnel.\n", "employment_types": ["Full Time"], "selling_points": ["Receptionist", "Central", "Competitive benefit"], "locations": ["Central"], "categories": ["Admin & HR", "Clerical / Admin Staff", "Personal / Executive Assistant", "Receptionist"], "post_time": "2022-01-14T04:34:54Z", "salary": {"currency": null, "max": null, "min": null, "period": "monthly", "term": null}, "salary_visible": false, "title_keywords": ["receptionist"], "responsibilities": ["ad-hoc tasks", "maintain", "professional manner", "administrative and clerical support"], "requirements": {"degrees": [], "majors": [], "languages": ["english", "mandarin"], "language_level": ["excellent"], "hard_skills": [], "soft_skills": ["detail-minded", "stable", "harmonious", "can-do attitude"], "languages_combined": [{"language": "english", "language_level": ["excellent"]}, {"language": "mandarin", "language_level": ["excellent"]}]}, "experience_required": {"duration": [], "field": ["financial"]}}, {"job_id": "100003009043531", "location_code": "hk", "company": "Asia Satellite Telecommunications Co Ltd", "job_title": "Administration Officer", "description": "Responsibilities:\n\nProvide a full spectrum of administrative and secretarial support to the Department / Team\nPrepare minutes and reports, presentation and meeting materials including translation\nDiary management; schedule and coordinate meetings, conference calls and video- conference.\nHandle travel arrangement, flight and accommodation booking and expense reimbursement\nAssist in the office administration duties including manage receptionist duties, stationery and printing, office equipment maintenance, office supplies, fixed assets management, incoming and outgoing couriers/mails and etc.\nHandle procurement related activities including sourcing, issue PO, follow up order delivery as well as billing and invoice settlement.\nHandle Import license application and Export / Import declaration\nResponsible for inventory control, such as stationery, consumables and equipment, etc.\n\nRequirements:\u00a0\n\nDegree holder in\u00a0Business Administration or related discipline\nMinimum 5 years' relevant experience \u00a0in administrative / secretarial field\nPossess a customer-service orientated approach to problem resolution and sustainable in high demanding working environment;\nHighly organized, detail-minded, multi-tasking and able to meet tight deadlines\nIndependent, a good team player with positive, proactive and flexible attitude\nGood command of written & spoken English & Chinese including Putonghua\nProficient in MS Office including Word, Excel, PowerPoint and Chinese Word Processing\nImmediate available is highly preferred\n\nA competitive package will be offered to the right candidate.\u00a0\u00a0Interested parties please email their resume with expected salary to Human Resources Department by clicking \"Apply Now\".\n\nAsiaSat is an Equal Opportunities Employer. \u00a0Personal data collected will be used for recruitment purpose only.\u00a0", "employment_types": ["Full Time", "Permanent"], "selling_points": ["Office management", "Administrative & Secretarial support", "Min. 5 years' relevant experience"], "locations": ["Tai Po Area"], "categories": ["Admin & HR", "Administration / Operation Manager", "Personal / Executive Assistant", "Secretary"], "post_time": "2022-01-12T16:40:57Z", "salary": {"currency": null, "max": null, "min": null, "period": "monthly", "term": null}, "salary_visible": false, "title_keywords": ["administration officer"], "responsibilities": ["management", "office supplies", "invoice", "stationery", "coordinate", "fixed assets management", "office equipment maintenance", "reports", "secretarial support", "schedule", "travel arrangement", "booking", "office administration duties", "license application", "inventory control"], "requirements": {"degrees": ["degree holder"], "majors": ["business administration"], "languages": ["putonghua", "english", "chinese"], "language_level": ["good command", "proficient"], "hard_skills": ["excel", "chinese word processing", "word", "powerpoint", "ms office"], "soft_skills": ["detail-minded", "organized", "meet tight deadlines", "good team player", "independent", "flexible", "multi-tasking", "proactive", "positive"], "languages_combined": [{"language": "putonghua", "language_level": ["good command"]}, {"language": "english", "language_level": ["good command"]}, {"language": "chinese", "language_level": ["good command", "proficient"]}]}, "experience_required": {"duration": ["minimum 5 years"], "field": ["secretarial", "administrative", "relevant experience"]}}, {"job_id": "100003009042626", "location_code": "hk", "company": "Ngai Hing Hong Plastic Materials (Hong Kong) Ltd", "job_title": "Assistant to Group Company Secretary  ( REF#NHH(HK)2201 )", "description": "Responsibilities:\n\nAssist our group company secretary on company secretarial matters\nAssist in preparation of company secretarial documentation\nManage and assist in all corporate projects assigned with professional manner & judgement\nLiaise with internal and external parties on business and banking matters proactively & independently\nPrepare presentation materials, management reports, meeting agenda and minutes\nAssist in preparation of annual report, announcements, circulars, SFO filings, organising board meetings and general meetings\nHandle daily correspondence, enquiries and phone calls\nAdministrative support and backup whenever necessary\n\n\u00a0Requirements:\n\nHigher Diploma or above with at least 3 years of working experience\nKnowledge of company secretarial duties is an advantage\nStrong interpersonal skills with strong business sense\nWilling to work overtime and able to work under pressure\nProficient in computer skills, e.g. Word, Excel, PowerPoint, etc.\nGood command of written and spoken English & Chinese (both Cantonese and Mandarin)\nImmediately available is highly preferred", "employment_types": ["Full Time"], "selling_points": ["\u6709\u85aa\u4f11\u606f\u65e5", "\u9580\u8a3a\u53ca\u4f4f\u9662\u4fdd\u969c", "\u8fd1\u6e2f\u9435\u7ad9 (\u706b\u70ad)"], "locations": ["Shatin Area"], "categories": ["Admin & HR", "Clerical / Admin Staff", "Personal / Executive Assistant", "Secretary"], "post_time": "2022-01-12T10:19:20Z", "salary": {"currency": null, "max": null, "min": null, "period": "monthly", "term": null}, "salary_visible": false, "title_keywords": ["company secretary", "assistant"], "responsibilities": ["administrative support", "internal and external parties", "professional manner", "liaise with", "management reports", "banking", "documentation", "phone calls", "report"], "requirements": {"degrees": ["higher diploma or above"], "majors": [], "languages": ["cantonese", "english", "chinese", "mandarin"], "language_level": ["good command"], "hard_skills": ["excel", "computer skills", "word", "powerpoint"], "soft_skills": ["work under pressure", "work overtime", "interpersonal skills", "business sense"], "languages_combined": [{"language": "cantonese", "language_level": ["good command"]}, {"language": "english", "language_level": ["good command"]}, {"language": "chinese", "language_level": ["good command"]}, {"language": "mandarin", "language_level": ["good command"]}]}, "experience_required": {"duration": ["at least 3 years"], "field": []}}, {"job_id": "100003009051141", "location_code": "hk", "company": "", "job_title": "**URGENT Bank / Finance Experience** - Managerial Position (Special Promotion Packages)", "description": "Manulife (International) Ltd\n\n\n\nRe: **URGENT Bank / Finance Experience** - Managerial Position (Special Promotion Packages)\n\nTo cope with our expansion, we are urgently looking for a high calibre candidate who can work independently and\u00a0confidently.\n\nCandidate with\u00a0bank/finance experience\u00a0would be an advantage.\u00a0 We will offer\u00a0\u00a0SPECIAL PROMOTION PACKAGES.\n\nIf you are\u00a0caring about your future career development, and would like to\u00a0catch up your existing status and income level, this is a good opportunity for you to start with.\u00a0\n\n\nOur Benefits and packages:\n\nMonthly income up to $25000 to $60000 including bonus\nAdditional management overrides after promotion\nInitial training and On-Job training provided\nSPECIAL PROMOTION TRAINING PROGRAM to Team Manager in just 6 months\nExcellent Career Path to Management Ladder\nFirst Year income around $300,000 to $700,000\nLife and Medical Insurance\nBank holidays and Pension scheme\nLow mortgage interest rate\nFlexible working hours\nWork-Life Balance\n\nRequirements:\n\nDegree holder preferred\n3 years working experience or above\nNo need on finance experience, but supervisory or management experience is an advantage\nHKID card holder is a MUST\nFluent Cantonese and English\nImmediate past income not less than $150,000\nMature, responsible, and strong desire for success\nNo bankruptcy\n\nJob Functions:\n\nProvide professional financial planning to individual clients for wealth management, medical and life insurance,\nretirement scheme, investment, etc\nProvide benefits to corporate clients such as MPF, Group Medical, Business Insurance, etc\nTeam building for your career management development\nProvide training and coaching to team-members\n\nInterested candidates please send C.V. via \"APPLY NOW\"\u00a0\n\nOr send to Recruiting Manager: polly_lm_chan @ manulife.com.hk\n\nOr call 69045196 Polly Chan to arrange interview.\n\n\nPersonal data collected will be used for recruitment purposes only.\n\nRemarks: The recruitment offer is subject to the terms & conditions as stipulated in the agreement to be signed.", "employment_types": ["Full Time", "Permanent"], "selling_points": [], "locations": ["Others"], "categories": ["Accounting", "Chief Accountant", "Admin & HR", "Personal / Executive Assistant", "Banking / Finance", "Private Banking"], "post_time": "2022-01-15T03:25:43Z", "salary": {"currency": "HKD", "max": 69999, "min": 25000, "period": "monthly", "term": null}, "salary_visible": true, "title_keywords": [], "responsibilities": ["career development"], "requirements": {"degrees": [], "majors": [], "languages": [], "language_level": [], "hard_skills": [], "soft_skills": ["work independently"], "languages_combined": []}, "experience_required": {"duration": [], "field": ["finance", "managerial"]}}, {"job_id": "100003009049069", "location_code": "hk", "company": "ConnectedGroup Limited", "job_title": "Strategic & Project Assistant (MNC)", "description": "Strategic & Project Assistant (MNC)\n\nOur client is an international business which has over 70 year's history with global presence. They are looking for a Strategic & Project Assistant to join their global team.\n\nPosition Responsibilities\n\nServes as a trusted partner, maintaining confidentiality and professionalism in all situations.\nPartners and collaborates with peers and direct reports to manage cross-functional initiatives from conception to completion\nEffective calendar management, advanced planning and preparation of leadership team meetings internally and externally, including but not limited to townhall meetings, off- sites, vendor webinars, one-on-one meetings, etc.\nEvent management - organization of quarterly meetings, volunteering events, off-sites, webinars, summits etc.\nCreation and editions of document (Word, PPT, Excel, Power BI, Tableau) to support the direct report across the full spectrum of their work\nWork with cross-functional teams in the definition of project scope and objectives and resourcing, as aligned to company's strategies.\nManage synchronization across all dependencies.\nProvide oversight to project progress, issues/risks and decisions required.\nManage execution of initiatives ensuring that all projects are delivered on-time, within scope and within budget.\nManages all executive correspondence; directing or responding to customer and vendor communication.\nExpense management duties.\nOversee department budget.\nOther administrative duties as requested.\n\nPosition Requirements\n\nMBA and Master Degree holder is strongly preferred\nConsulting background candidates are highly preferred as well\nSolid administrative or project management experience; with experience supporting C-level executives\nLearning agility and a curiosity for understanding the business\nHigh attention to detail, organization and process.\nStrong teamwork skills and a strong ability to offer suggestions and improvements to process and work effectively.\nStrong relationship management skills.\nHigh level of confidentiality, discernment and judgment.\nAbility to be flexible in response to changing priorities and needs.\nProven ability to manage projects, work under pressure and consistently make deadlines.\nDemonstrated ability and willingness to continuously acquire new competencies and accept new challenges.\nStrong communication, oral and written. Ability to communicate clearly and effectively with senior leaders and external business partners.\nFluent in English and Chinese communication.\n\nInterested individuals can apply now and send CV to Vivian Wong, or call +852 3972 5831 for more information. Only relevant candidates will be contacted\n\nFor a more comprehensive list of our vacancies, please visit: www.connectedgroup.com", "employment_types": ["Full Time", "Permanent"], "selling_points": ["One of the market leading players in the industry", "International working environment", "Attractive package with promising career prospect"], "locations": ["Not Specified"], "categories": ["Accounting", "Others", "Admin & HR", "Personal / Executive Assistant", "Professional Services", "Business Consultancy"], "post_time": "2022-01-14T08:03:03Z", "salary": {"currency": null, "max": null, "min": null, "period": "monthly", "term": null}, "salary_visible": false, "title_keywords": ["project assistant"], "responsibilities": ["management", "power bi", "maintaining", "budget", "project progress", "from conception to completion", "communication", "reports", "administrative duties", "report", "cross-functional teams", "planning"], "requirements": {"degrees": ["master degree"], "majors": [], "languages": ["english", "chinese"], "language_level": ["fluent"], "hard_skills": ["project management", "make", "c"], "soft_skills": ["work effectively", "flexible", "oral", "teamwork", "communication", "project management", "learning", "comprehensive", "attention to detail", "work under pressure"], "languages_combined": [{"language": "english", "language_level": ["fluent"]}, {"language": "chinese", "language_level": ["fluent"]}]}, "experience_required": {"duration": [], "field": ["project management", "administrative"]}}, {"job_id": "100003009046852", "location_code": "hk", "company": "China Merchants Energy Shipping (Hong Kong) Company Limited", "job_title": "\u884c\u653f\u7ba1\u7406\u90e8\u6587\u79d8\u884c\u653f\u5c97/Administrative Officer", "description": "\uff08\u4e00\uff09\u5de5\u4f5c\u804c\u8d23\n\n\u8d1f\u8d23\u516c\u53f8\u516c\u6587\u3001\u8d44\u6599\u7684\u9884\u5904\u7406\uff1b\n\u8d1f\u8d23\u63a5\u6536\u3001\u4e0b\u8fbe\u53ca\u8ddf\u8e2a\u5904\u7406\u9886\u5bfc\u6307\u793a\u53ca\u843d\u5b9e\u60c5\u51b5\uff1b\n\u8d1f\u8d23\u8d77\u8349\u516c\u53f8\u7efc\u5408\u6027\u6587\u5b57\u6750\u6599\uff0c\u5305\u62ec\u4f1a\u8bae\u7eaa\u8981\u3001\u62a5\u544a\u3001\u7b80\u62a5\u7b49\uff1b\n\u8d1f\u8d23\u516c\u53f8\u4f1a\u8bae\u4f1a\u52a1\u51c6\u5907\u5de5\u4f5c\uff0c\u53c2\u4e0e\u516c\u53f8\u91cd\u8981\u6d3b\u52a8\u7684\u7ec4\u7ec7\u5b89\u6392\u5de5\u4f5c\uff1b\n\u5b8c\u6210\u9886\u5bfc\u4ea4\u529e\u7684\u5176\u4ed6\u5de5\u4f5c\u3002\n\n\uff08\u4e8c\uff09\u4efb\u804c\u8981\u6c42\n\n\u7814\u7a76\u751f\u53ca\u4ee5\u4e0a\u5b66\u5386\uff0c\u67093\u5e74\u4ee5\u4e0a\u5de5\u4f5c\u7ecf\u9a8c\uff1b\n\u6709\u8f83\u5f3a\u7684\u6587\u5b57\u529f\u5e95\uff0c\u64c5\u957f\u516c\u6587\u5199\u4f5c\u548c\u6587\u5b57\u8868\u8fbe\uff1b\n\u6709\u8f83\u5f3a\u7684\u6c9f\u901a\u534f\u8c03\u80fd\u529b\uff0c\u5177\u6709\u4e00\u5b9a\u7684\u4f1a\u52a1\u7ec4\u7ec7\u7ecf\u9a8c\uff1b\n\u6709\u8f83\u5f3a\u7684\u5de5\u4f5c\u8d23\u4efb\u5fc3\uff0c\u826f\u597d\u7684\u804c\u4e1a\u7d20\u517b\u548c\u804c\u4e1a\u64cd\u5b88\uff1b\n\u82f1\u8bed\u542c\u8bf4\u8bfb\u5199\u6d41\u5229\uff0c\u6709\u6d77\u5916\u5b66\u4e60\u3001\u751f\u6d3b\u7ecf\u5386\u8005\u4f18\u5148\u8003\u8651\uff1b\n\u9999\u6e2f\u5c45\u6c11\u4f18\u5148\u8003\u8651\u3002\n\n\uff08\u4e00\uff09Job Responsibilities\uff1a\n\nPreliminarily handle files, documents and other information for the supervisor.\nTake and distribute messages for the supervisor, coordinate the flow of information dealing.\nDraft and produce reports, memorandums, etc.\nSchedule and coordinate meetings and conferences, assist in organizing the company\u2019s important activities.\nOther duties as assigned.\n\n\uff08\u4e8c\uff09Job Requirements\uff1a\n\nMaster degree or above, minimum 3 years working experience.\nGood command of report writing and presentation skills.\nWith excellent communication skills and good at coordinating meetings and conferences.\nPossess a strong sense of responsibility, well professionalism and work ethics.\nExcellent English language skills, overseas working or studying experience is preferable.\nHong Kong residents are preferred.", "employment_types": ["Full Time", "Permanent"], "selling_points": ["Draft and produce reports, memorandums", "Good command of report writing", "Master degree"], "locations": ["Sheung Wan"], "categories": ["Admin & HR", "Clerical / Admin Staff", "Personal / Executive Assistant", "Secretary"], "post_time": "2022-01-14T01:29:09Z", "salary": {"currency": null, "max": null, "min": null, "period": "monthly", "term": null}, "salary_visible": false, "title_keywords": ["administrative officer"], "responsibilities": ["other duties", "coordinate", "conferences", "reports", "schedule"], "requirements": {"degrees": ["degree or above", "master"], "majors": [], "languages": ["english"], "language_level": ["excellent"], "hard_skills": [], "soft_skills": ["communication skills", "presentation skills", "sense of responsibility"], "languages_combined": [{"language": "english", "language_level": ["excellent"]}]}, "experience_required": {"duration": ["minimum 3 years"], "field": []}}, {"job_id": "100003009043371", "location_code": "hk", "company": "\u9769\u5320\u7ba1\u5bb6\u6709\u9650\u516c\u53f8", "job_title": "Accounts Supervisor and Personal Assistance to CEO", "description": "We are looking for an Accounts Supervisor and Personal Assistance to CEO to join our team and support the day-to-day activities of our Accounts department and provide personal assistance to Chief Executive Officer.\n\nJob Description:\n\nHandle full set of Account in Hong Kong\nManaging and Organizing all Accounts and Finance activities\nFollow up finance project\nPrepare, review, and cost analyze Consolidated financial statements for different globe subsidiary companies\nConsolidate and monitor cashflow status for the Group\nPrepare Quarterly and Yearly budget and comparison reports for the Group\nCooperate with different subsidiary companies to set up routine operation systems to provide overseeing office management function\nOrganizing and managing travel arrangements and itineraries for CEO and staff\nDrafting email as requested by CEO\nProvide secretarial job for CEO\nConducting or preparing any research that CEO may require\n\n\u00a0Qualification:\n\nDegree holder / Diploma or equivalent\nAt least 5 years of relevant experience in progressive accounting Field\nExcellent writing and editing skills in English. Fluent Mandarin speaking is bonus\nBe Mature, Ability to work independently in a fast-paced environment and handle multiple projects concurrently\nExcellent organizational skills\nAdvanced Microsoft Excel skills. Experience with Quick book System is preferred\nImmediate available is preferred", "employment_types": ["Full Time"], "selling_points": [], "locations": ["Kwai Hing"], "categories": ["Accounting", "Accounting Clerk / Supervisor", "Finance / Accounting Manager", "Admin & HR", "Personal / Executive Assistant"], "post_time": "2022-01-12T11:08:22Z", "salary": {"currency": null, "max": null, "min": null, "period": "monthly", "term": null}, "salary_visible": false, "title_keywords": ["accounts supervisor", "personal", "assistance", "ceo"], "responsibilities": ["cost", "management", "travel arrangements", "review", "monitor", "budget", "financial statements", "systems", "reports", "multiple projects", "editing", "cooperate with"], "requirements": {"degrees": ["diploma", "degree holder"], "majors": [], "languages": ["english", "mandarin"], "language_level": ["excellent", "fluent"], "hard_skills": ["microsoft excel skills", "quick book"], "soft_skills": ["organizational skills", "work independently", "advanced", "fast-paced environment", "mature", "progressive"], "languages_combined": [{"language": "english", "language_level": ["excellent"]}, {"language": "mandarin", "language_level": ["fluent"]}]}, "experience_required": {"duration": ["at least 5 years"], "field": ["accounting", "relevant experience"]}}, {"job_id": "100003009042763", "location_code": "hk", "company": "City University of Hong Kong", "job_title": "Executive Officer I/II in the Centre for Judicial Education and Research [Ref. B/512/03]", "description": "Duties\nProvide administrative assistance to the Centre Director and maintain daily operation of the Centre;\nProvide assistance in the logistics arrangements of Centre\u2019s activities, including ceremonies/conferences/lecturers/seminars/visits;\nConduct market analysis;\nManage social media platforms and update website;\nDesign online/printing promotional materials;\nPrepare reports/speeches/web stories/write up for media publicity; and\nPerform any other duties as assigned.\nRequirements\n\nA Bachelor\u2019s degree with relevant working experience. Excellent command of written and spoken English and Chinese (including Putonghua); good organizational, communication and interpersonal skills; strong sense of responsibility with initiatives and ability to work independently are required. Prior experience in tertiary education institutions would be an advantage.\n\nCandidates with more than 5 years\u2019 relevant experience may be considered for appointment as Executive Officer I.\n\nShortlisted candidates will be invited for a written test.\n\nSalary and Conditions of Service\n\nRemuneration package will be highly competitive, commensurate with qualifications and experience.\u00a0 Appointment will be made on a fixed-term contract; fringe benefits include gratuity, leave, medical and dental schemes.\n\nInformation and Application\n\nFurther information on the posts and the University is available at\u00a0http://www.cityu.edu.hk, or from the Human Resources Office, City University of Hong Kong, Tat Chee Avenue, Kowloon Tong, Hong Kong [Fax : 2788 1154 or 3442 0311].\u00a0\n\nTo apply, please submit an online application at\u00a0http://jobs.cityu.edu.hk.\u00a0The closing date is 28 January 2022.\u00a0\u00a0Applications will receive full consideration and only shortlisted applicants will be contacted.\u00a0 The University\u2019s privacy policy is available on the homepage.\n\nCity University of Hong Kong is an equal opportunity employer. We are committed to the principle of diversity. Personal data provided by applicants will be used for recruitment and other employment-related purposes.\n\nWorldwide recognition ranking #53 (QS survey 2022), and #4 among top 50 universities under age 50 (QS survey 2021); #1 in the World\u2019s Most International Universities (THE survey 2020); #1 in Engineering/Technology/Computer Sciences in Hong Kong (ARWU survey 2016); and #1 Business School in Asia-Pacific region (UT Dallas survey 2019).", "employment_types": ["Full Time", "Contract"], "selling_points": ["Bachelor\u2019s degree", "Relevant working experience", "Gratuity, leave, medical and dental schemes"], "locations": ["Wong Tai Sin Area"], "categories": ["Admin & HR", "Clerical / Admin Staff", "Personal / Executive Assistant", "Education", "Others"], "post_time": "2022-01-13T18:54:36Z", "salary": {"currency": null, "max": null, "min": null, "period": "monthly", "term": null}, "salary_visible": false, "title_keywords": ["executive officer"], "responsibilities": ["any other duties", "logistics arrangements", "daily operation", "social media platforms", "website", "design", "conferences", "maintain", "administrative assistance", "market analysis", "promotional materials", "prepare reports", "provide assistance"], "requirements": {"degrees": ["degree", "bachelor"], "majors": [], "languages": ["putonghua", "english", "chinese"], "language_level": ["excellent"], "hard_skills": [], "soft_skills": ["organizational", "work independently", "communication and interpersonal skills", "sense of responsibility"], "languages_combined": [{"language": "putonghua", "language_level": ["excellent"]}, {"language": "english", "language_level": ["excellent"]}, {"language": "chinese", "language_level": ["excellent"]}]}, "experience_required": {"duration": ["5 years"], "field": ["relevant experience", "relevant working experience", "education"]}}, {"job_id": "100003009039673", "location_code": "hk", "company": "Yulan Group Limited", "job_title": "Executive Assistant", "description": "Job Responsibilities:\n\nProvide full spectrum of secretarial support to the Senior Executive on both business and personal issues\nProvide routine office administrative support\nCoordinate appointments and necessary arrangements for business, social and personal activities\nAssist to manage\u00a0social media accounts\nAssist in managing household matters such as utility bills, domestic helps\u2019 and drivers\u2019 schedules, maintenance and etc\nManage calendar, coordinate meetings, events, organize daily schedules, courier and logistics arrangement\nLiaise with the internal and external parties on different projects\nAccomplish ad-hoc duties assigned by the Management\n\nJob Requirements:\n\nHolder of degree in Business Administration or related discipline\nMin 1 year of relevant working experience supporting top management\nProficient in MS Office applications\nBe discreet when dealing with private and confidential information\n\nWe offer career opportunities and excellent remuneration package to the right candidate. Please email your full resume with current and expected salary to Human Resources Department or on Whatsapp 5976 5391.\n\nYulan Group Limited is an equal opportunity employer. Applicants not invited for interview within six weeks may consider their applications unsuccessful. All information will be used solely for recruitment purpose and will be destroyed when the recruitment process is finished.", "employment_types": ["Full Time", "Permanent"], "selling_points": ["Provide full spectrum of secretarial support", "Provide routine office administrative support", "Liaise with the internal and external parties"], "locations": ["Southern Area"], "categories": ["Admin & HR", "Clerical / Admin Staff", "Personal / Executive Assistant", "Hospitality / F & B", "Others"], "post_time": "2022-01-11T10:26:27Z", "salary": {"currency": null, "max": null, "min": null, "period": "monthly", "term": null}, "salary_visible": false, "title_keywords": ["executive assistant"], "responsibilities": ["social media", "management", "maintenance", "administrative support", "schedules", "logistics arrangement", "internal and external parties", "coordinate", "secretarial support", "ad-hoc duties", "liaise with"], "requirements": {"degrees": ["degree"], "majors": ["business administration"], "languages": [], "language_level": [], "hard_skills": ["ms office"], "soft_skills": [], "languages_combined": []}, "experience_required": {"duration": ["min 1 year"], "field": ["management", "relevant working experience"]}}, {"job_id": "100003009042670", "location_code": "hk", "company": "Win Capital Investments Limited", "job_title": "Accounts and Executive Assistant", "description": "Responsibilities\n\nPrepare vouchers & cheque payments, filing and any general accounting duties\nProvide full spectrum of executive support to Management on both business and personal issues\nAny other ad hoc tasks assigned by Management\n\nResponsibilities\n\nDegree holder or above in accounting or other related business discipline\nMinimum of 2 years' relevant working experience in similar duties\nExperience in Accounting system (MYOB) is on advantage\nProficiency in Microsoft Word, Excel and Chinese Typing\nGood command of spoken and written English and Chinese, fluent in Putonghua\nSelf-motivated, responsible, stable, hard working, and willing to learn\nImmediate availabile is highly preferred\n\nWe offer an attractive remuneration package and excellent career development opportunities. Interested parties please send your resume (in Microsoft word or PDF format) full details of education, work experience, present and expected salaries, contact telephone number and earliest date available by clicking \u201cApply Now\u201d.\n\nAll information collected will be kept in strict confidence and will be used for recruitment purpose only.", "employment_types": ["Full Time"], "selling_points": [], "locations": ["Sheung Wan"], "categories": ["Accounting", "Accounting Clerk / Supervisor", "Admin & HR", "Personal / Executive Assistant"], "post_time": "2022-01-12T08:20:05Z", "salary": {"currency": null, "max": null, "min": null, "period": "monthly", "term": null}, "salary_visible": false, "title_keywords": ["executive assistant"], "responsibilities": ["management", "ad hoc tasks", "executive support", "general accounting duties", "payments"], "requirements": {"degrees": ["degree holder"], "majors": ["business", "accounting"], "languages": ["putonghua", "english", "chinese"], "language_level": ["proficiency", "good command", "fluent"], "hard_skills": ["excel", "microsoft word", "typing", "accounting system", "myob"], "soft_skills": ["self-motivated", "responsible", "hard working", "willing to learn", "stable"], "languages_combined": [{"language": "putonghua", "language_level": ["fluent", "good command"]}, {"language": "english", "language_level": ["fluent", "good command"]}, {"language": "chinese", "language_level": ["fluent", "proficiency", "good command"]}]}, "experience_required": {"duration": ["minimum of 2 years"], "field": ["accounting", "relevant working experience"]}}, {"job_id": "100003009042701", "location_code": "hk", "company": "Hong Kong Baptist University", "job_title": "Executive Officer / Executive Assistant (PR0466/21-22)", "description": "SCHOOL OF COMMUNICATIION AND FILM\n\nAcademy of Film\n\nExecutive Officer / Executive Assistant (PR0466/21-22)\n\nThe appointee is expected to provide secretarial and administrative support to undergraduate programme offered by the Academy of Film.\n\nDuties:\nassisting in the day-to-day operation, including programme promotion and development, student recruitment and admissions, student record update, course and examination scheduling, and organisation of events and activities such as workshops, seminars and study tours;\nproviding secretarial support to the Programme Director, course instructors and Programme Management Committee;\ncompiling reports and proposals for programme development and quality assurance;\nhandling student-related matters;\nmaintaining and updating website; and\nperforming any other duties as assigned.\nRequirements:\n\na bachelor\u2019s degree preferably with three to four years of relevant work experience;\nan excellent command of English and Chinese (both Cantonese and Putonghua);\nproficiency in MS Office, Chinese and English word processing, multimedia, and software for website maintenance;\ngood interpersonal skills and be a good team player; and\nself-motivated and able to work independently.\nInitial appointment will be offered on a fixed-term contract of one to two years commencing as soon as possible. Re-appointment thereafter will be subject to mutual agreement. Candidates with less experience will be considered as Executive Assistant.\n\nRank and salary will be commensurate with qualifications and experience.\n\nApplication Procedure:\n\nApplicants are invited to submit their applications at the HKBU e-Recruitment System (jobs.hkbu.edu.hk). Those not invited for interview 8 weeks after the closing date may consider their applications unsuccessful. Details of the University\u2019s Personal Information Collection Statement can be found at\u00a0\u00a0http://hro.hkbu.edu.hk/pics.\n\nThe University reserves the right not to make an appointment for the post advertised, and the appointment will be made according to the terms and conditions then applicable at the time of offer.\n\nClosing date: 26 January 2022", "employment_types": ["Full Time"], "selling_points": ["assisting in the day-to-day operation", "providing secretarial support", "handling student-related matters"], "locations": ["Kowloon City"], "categories": ["Admin & HR", "Clerical / Admin Staff", "Personal / Executive Assistant", "Education", "Others"], "post_time": "2022-01-12T08:27:06Z", "salary": {"currency": null, "max": null, "min": null, "period": "monthly", "term": null}, "salary_visible": false, "title_keywords": ["executive officer", "executive assistant"], "responsibilities": ["any other duties", "management", "maintaining", "quality", "website", "providing secretarial support", "scheduling", "recruitment", "reports", "day-to-day operation"], "requirements": {"degrees": ["degree", "bachelor"], "majors": [], "languages": ["cantonese", "putonghua", "english", "chinese"], "language_level": ["excellent", "proficiency"], "hard_skills": ["maintenance", "chinese and english word processing", "make", "multimedia", "ms office"], "soft_skills": ["good team player", "interpersonal skills", "work independently", "self-motivated"], "languages_combined": [{"language": "cantonese", "language_level": ["excellent"]}, {"language": "putonghua", "language_level": ["excellent"]}, {"language": "english", "language_level": ["excellent", "proficiency"]}, {"language": "chinese", "language_level": ["excellent", "proficiency"]}]}, "experience_required": {"duration": ["three to four years"], "field": []}}, {"job_id": "100003009038399", "location_code": "hk", "company": "CMB International Capital Corporation Limited", "job_title": "Executive Assistant - Structured Finance Department (1-Year Contract)", "description": "Job Description\n\nProvide all-rounded secretarial support and administrative duties to the department,\u00a0including but not limited to\u00a0managing schedules, meeting arrangements and\u00a0business travel applications and reimbursement processes etc.;\nAssist in internal reports drafting, processing and internal reporting materials preparation;\nAct as the point of contact among internal teams and other departments for administrative support;\nCoordinate with the team in team building activities preparation, organization and execution;\nHandle any ad-hoc duties as assigned.\n\nRequirements\n\nBachelor degree in finance, business administration or related disciplines;\nAt least 2 years\u2019 relevant experience in sizable financial institutions;\nKnowledge in a wide range of investment banking products;\nDetail-minded, self-motivated and is a good team player;\nProficient in written and spoken English and Chinese (including Mandarin).\n\nWe offer competitive remuneration package and comprehensive fringe benefit to the right candidate. Interested parties please forward your full resume with availability, expected salary by pressing \"Apply now\".\n\nPersonal data collected will be used for recruitment related purposes only. Applicants not invited\u00a0for\u00a0an\u00a0interview within 2 months from the date of this posting may consider their applications unsuccessful. Personal data will be destroyed after 3 months.\n\nFor further information about our Company, please visit our website:\u00a0https://www.cmbi.com.hk/en-US/", "employment_types": ["Full Time", "Contract"], "selling_points": ["Provide all-rounded secretarial and admin support", "At least 2 years\u2019 relevant experience", "Bachelor degree in finance"], "locations": ["Central"], "categories": ["Admin & HR", "Personal / Executive Assistant", "Secretary", "Banking / Finance", "Others"], "post_time": "2022-01-11T06:51:15Z", "salary": {"currency": null, "max": null, "min": null, "period": "monthly", "term": null}, "salary_visible": false, "title_keywords": ["executive assistant"], "responsibilities": ["reporting", "ad-hoc duties", "administrative support", "schedules", "teams", "coordinate with", "administrative duties", "secretarial support", "reports", "contact"], "requirements": {"degrees": ["degree", "bachelor"], "majors": ["related disciplines", "finance", "business administration"], "languages": ["english", "chinese", "mandarin"], "language_level": ["proficient"], "hard_skills": [], "soft_skills": ["detail-minded", "good team player", "self-motivated"], "languages_combined": [{"language": "english", "language_level": ["proficient"]}, {"language": "chinese", "language_level": ["proficient"]}, {"language": "mandarin", "language_level": ["proficient"]}]}, "experience_required": {"duration": ["at least 2 years"], "field": ["financial institutions", "relevant experience"]}}, {"job_id": "100003009049647", "location_code": "hk", "company": "Strategic Financial Relations (China) Ltd.", "job_title": "Coordinator", "description": "\u00a0General\n\nUpdate the database of business contacts\nType English and Chinese proposals\nPrepare PowerPoint presentation slides\nComplete expense claim forms\nCoordinate with client servicing teams and other departments\nHandle general office work\n\nEvent / Client Support\n\nPrepare news monitoring reports and monthly / project reports\nModify PowerPoint presentation slides and press releases\nPrepare and send invitations and make RSVP calls\nDisseminate press release and other client information to media and investors and follow up\nLogistics arrangement (hotel/function room or restaurant booking, ticketing, car rental, etc)\nVenue set-up and on-site support of events\n\nRequirements:\n\nHolder of University Degree, Associate Degree or Diploma with formal secretarial training\nPreferably with 2 to 4 years of working experience, but fresh graduates may also be considered\nGood computer skills, proficient in MS office including Word Processing, PowerPoint and Excel\nGood language skills, proficient in English & Mandarin\nWell-organized,\u00a0detail-minded, responsible\u00a0& independent\nImmediate availability is preferred\nInterested parties please complete the standard application form by clicking the\u00a0Apply now\u00a0button. You can also attach your tailored CV and Cover letter with your current and expected salary which we will use to review applications.\n\n\n\u00a0It is Our Company policy to comply with the requirements of the Personal Data (Privacy) Ordinance (Cap. 486) of the Laws of the Hong Kong Special Administrative Region. Any personal data which is collected shall be handled in accordance with this Personal Information Collection Statement (\u201cPICS\u201d).\n\nThe personal data collected from you will be used for purposes relating to your application for employment with the Company. You must ensure that all personal data provided to the Company are accurate, complete and up-to-date. For correction of or access to personal data after submission of the job application or enquiries on recruitment matters, please contact the HR or subject officer as specified in the recruitment advertisement.\n\nWebsite:\u00a0\u00a0www.sprg.com.hk\u00a0/\u00a0www.sprg.asia\n\nFacebook:\u00a0\u00a0https://www.facebook.com/SPRGAsia /\u00a0https://www.facebook.com/CSR.SPRG", "employment_types": ["Full Time", "Permanent"], "selling_points": ["with formal secretarial training", "5 Days Work / Bank Holiday", "12 Days AL/B-day Leave/Medical&Life Insurance"], "locations": ["Admiralty"], "categories": ["Admin & HR", "Clerical / Admin Staff", "Personal / Executive Assistant", "Secretary"], "post_time": "2022-01-14T09:01:01Z", "salary": {"currency": null, "max": null, "min": null, "period": "monthly", "term": null}, "salary_visible": false, "title_keywords": ["coordinator"], "responsibilities": ["logistics arrangement", "monitoring", "teams", "coordinate with", "client information", "project reports", "reports", "booking", "database"], "requirements": {"degrees": ["associate degree", "university degree", "diploma"], "majors": [], "languages": ["english", "chinese", "mandarin"], "language_level": ["proficient", "good"], "hard_skills": ["excel", "word processing", "powerpoint", "make", "computer skills", "ms office"], "soft_skills": ["detail-minded", "independent", "responsible", "well-organized", "presentation"], "languages_combined": [{"language": "english", "language_level": ["proficient", "good"]}, {"language": "chinese", "language_level": []}, {"language": "mandarin", "language_level": ["proficient", "good"]}]}, "experience_required": {"duration": ["2 to 4 years"], "field": []}}, {"job_id": "100003009039163", "location_code": "hk", "company": "City University of Hong Kong", "job_title": "Executive Officer in the Student Development Services [Ref. B/506/03]", "description": "Duties\nReporting to the Associate Director (Student Life and Resources), the appointee will be responsible for:\n\n\nPlanning and organizing student development programmes, activities and special projects to support and enhance student learning;\nProviding advice, support and training to Students\u2019 Union, student societies and student groups;\nServing as the Secretary for Student Orientation Working Group, coordinating the welcoming ceremony, orientation activities for new students, and the Student Orientation website;\nCoordinating the IT projects and providing support for SLR websites and social media;\nLiaising with different stakeholders for student development activities/programmes; and\nPerforming any other duties as assigned.\nThe appointee will be also required to work flexible hours on a need basis.\nRequirements\nA Bachelor\u2019s degree or an equivalent qualification, preferably with a postgraduate qualification;\nRelevant working experience in related fields, preferably in higher education or youth work;\nWorking knowledge of computer applications;\nOutgoing personality and ability to communicate with young people;\nGood problem solving skills, being resourceful and self-motivated; and\nGood command of written and spoken English and Chinese (including Putonghua).\n\nShortlisted candidates will be invited for a written test.\n\n(Those who have responded to the previous advertisement need not re-apply.)\n\n\nSalary and Conditions of Service\n\nRemuneration package will be highly competitive, commensurate with qualifications and experience.\u00a0 Appointment will be made on a fixed-term contract; fringe benefits include gratuity, leave, medical and dental schemes.\nInformation and Application\nFurther information on the post and the University is available at\u00a0http://www.cityu.edu.hk, or from the Human Resources Office, City University of Hong Kong, Tat Chee Avenue, Kowloon Tong, Hong Kong [Fax : 2788 1154 or 3442 0311].\u00a0\n\nTo apply, please submit an online application at\u00a0http://jobs.cityu.edu.hk. The closing date is\u00a028 January 2022.\u00a0 Applications will receive full consideration and only shortlisted applicants will be contacted.\u00a0 The University\u2019s privacy policy is available on the homepage.\n\nCity University of Hong Kong is an equal opportunity employer. We are committed to the principle of diversity. Personal data provided by applicants will be used for recruitment and other employment-related purposes.\n\nWorldwide recognition ranking #53 (QS survey 2022), and #4 among top 50 universities under age 50 (QS survey 2021); #1 in the World\u2019s Most International Universities (THE survey 2020); #1 in Engineering/Technology/Computer Sciences in Hong Kong (ARWU survey 2016); and #1 Business School in Asia-Pacific region (UT Dallas survey 2019).", "employment_types": ["Full Time", "Contract"], "selling_points": ["A Bachelor\u2019s degree", "Relevant working experience", "Gratuity, leave, medical and dental schemes."], "locations": ["Wong Tai Sin Area"], "categories": ["Admin & HR", "Clerical / Admin Staff", "Personal / Executive Assistant", "Education", "Others"], "post_time": "2022-01-13T18:54:36Z", "salary": {"currency": null, "max": null, "min": null, "period": "monthly", "term": null}, "salary_visible": false, "title_keywords": ["executive officer"], "responsibilities": ["reporting", "social media", "any other duties", "website", "liaising with", "providing support", "planning"], "requirements": {"degrees": ["degree", "bachelor"], "majors": [], "languages": ["putonghua", "english", "chinese"], "language_level": ["good command"], "hard_skills": ["problem solving skills"], "soft_skills": ["outgoing personality", "problem solving skills", "self-motivated", "resourceful"], "languages_combined": [{"language": "putonghua", "language_level": ["good command"]}, {"language": "english", "language_level": ["good command"]}, {"language": "chinese", "language_level": ["good command"]}]}, "experience_required": {"duration": [], "field": ["related", "relevant working experience", "education"]}}, {"job_id": "100003009051332", "location_code": "hk", "company": "Assurance Education Limited", "job_title": "Administrative Assistant/Secretary, Full Time", "description": "Job Description: Administrative Assistant/Secretary\n\nOrganization\n\nAssurance aims to help students make blossom and make the most out of high school. Assurance is headquartered in Hong Kong and maintains offices in Shenzhen and Shanghai. Our managing director and founder undertook undergraduate education in law at the University of Cambridge. He has taught English for more than ten years. All of our consultants are from top universities such as Wharton, Harvard, UPenn and UChicago. For more information, please visit www.assuranceedu.com.\n\nPosition\n\nAdministrative Assistant/Secretary, Full Time\n\nLocation\n\nCauseway Bay\n\nHours\n\n5 days work week\nTuesday to Saturday\n9.30am to 6.30pm\n\nResponsibilities\n\nProvide administrative support\nHandle correspondence\nManage school application forms\nAssist in seminars and events\n\nRequirements\n\nFluency in Cantonese, English and Mandarin\nProficient in Word, Excel, and word processing in English & Chinese\n1 year of experience as administrative assistant/secretary\nDegree holder in any discipline\n\nCompensation\n\nWe offer a starting salary of $15000-$17,000/month. Please state your expected salary.\n\nApplication\n\nInterested parties please submit your resume and cover letter to Ms. Tiffany Cheung at admin @ AssuranceEDU.com\u00a0with \u201c[Name] Assurance Recruitment]\u201d in the email title. Please state your expected salary.", "employment_types": ["Full Time"], "selling_points": ["Proficiency in English, Cantonese & Mandarin", "Degree holder, 1 year of experience", "Salary $15-17K, 5 days working"], "locations": ["Causeway Bay"], "categories": ["Admin & HR", "Personal / Executive Assistant", "Receptionist", "Secretary"], "post_time": "2022-01-15T09:22:29Z", "salary": {"currency": "HKD", "max": 16999, "min": 14000, "period": "monthly", "term": null}, "salary_visible": true, "title_keywords": ["administrative assistant", "secretary"], "responsibilities": ["provide administrative support"], "requirements": {"degrees": ["degree holder"], "majors": [], "languages": ["cantonese", "english", "chinese", "mandarin"], "language_level": ["fluency", "proficient"], "hard_skills": ["excel", "word processing", "word"], "soft_skills": [], "languages_combined": [{"language": "cantonese", "language_level": ["fluency"]}, {"language": "english", "language_level": ["fluency", "proficient"]}, {"language": "chinese", "language_level": ["fluency", "proficient"]}, {"language": "mandarin", "language_level": ["fluency"]}]}, "experience_required": {"duration": ["1 year"], "field": ["administrative"]}}, {"job_id": "100003009047465", "location_code": "hk", "company": "The Hong Kong Polytechnic University", "job_title": "Project Assistant / Project Administrative Assistant", "description": "JOCKEY CLUB DESIGN INSTITUTE FOR SOCIAL INNOVATION\nProject Assistant / Project Administrative Assistant (Ref. 22011312)\n[Appointment period: twelve months initially, with possibility of further appointment]\nJockey Club Design Institute for Social Innovation is a unit aims at providing an innovative and human-centred platform to envision a better life in the society, connecting people with passion and nurturing doers of all ages to innovate with collective wisdom to enable impactful action.\nDuties\nThe appointee will assist the project leader in the research project \u2013 \u201cPolyU Jockey Club Operation SoInno\u201d.\u00a0 He/She will be required to:\n(a)\u00a0\u00a0 \u00a0handle administrative and expense claims of the Unit;\n(b)\u00a0\u00a0 \u00a0assist in the preparation of reports and maintain database;\n(c)\u00a0\u00a0 \u00a0support a wide range of project activities;\n(d)\u00a0\u00a0 \u00a0assist in the regular updating of the Unit\u2019s website and other online promotion platforms; and\n(e)\u00a0\u00a0 \u00a0perform any other duties as assigned by the Director of Jockey Club Design Institute for Social Innovation or his delegates.\nThe appointee may be required to work occasionally outside normal office hours, including Saturdays and Sundays.\nQualifications\nApplicants for the Project Assistant post should have an honours degree or an equivalent qualification, preferably in Business Administration, Social Sciences or relevant disciplines with at least one year of relevant post-qualification experience. \u00a0\nApplicants for the Project Administrative Assistant post should have five passes in HKCEE including English Language (at least Grade C if Syllabus A; Level 2 if results are obtained from 2007 onwards), Chinese Language (Level 2 if results are obtained from 2007 onwards) and Mathematics; or a combination of results in five HKDSE subjects of Level 2 in New Senior Secondary subjects / \u201cAttained\u201d in Applied Learning subjects / Grade E in Other Language subjects, and the five subjects must include English Language, Chinese Language and Mathematics.\u00a0 He/She should have at least two years of relevant post-qualification experience.\nApplicants should also:\n(a)\u00a0\u00a0 \u00a0have good planning, administrative and organizational skills with high self-motivation;\n(b)\u00a0\u00a0 \u00a0be able to work independently and under pressure;\n(c)\u00a0\u00a0 \u00a0have a good command of both written and spoken English and Chinese;\n(d)\u00a0\u00a0 \u00a0have good interpersonal and communication skills as well as team spirit;\n(e)\u00a0\u00a0 \u00a0have good computer literacy, including the use of Internet, social media platforms, online meeting tools and MS Office applications, i.e. Chinese word processing, Excel, PowerPoint and Outlook; and\n(f)\u00a0\u00a0 \u00a0be competent in using the Adobe Illustrator or website Content Management System being an advantage.\nApplicants are invited to contact Ms Alice Law at tel no. 3400 3435 or email via \"Apply Now\" for further information.\nApplicants should submit a covering letter together with completed application form and curriculum vitae.\nRemuneration\nA highly competitive remuneration package will be offered.\u00a0 Applicants should state their current and expected salary in the application.\nApplication\nPlease send a completed application form by post to Human Resources Office, 13/F, Li Ka Shing Tower, The Hong Kong Polytechnic University, Hung Hom, Kowloon, Hong Kong or via email by clicking \"Apply Now\".\u00a0 Application forms can be downloaded from https://www.polyu.edu.hk/hro/careers/guidelines_and_forms/forms.\u00a0 If a separate curriculum vitae is to be provided, please still complete the application form which will help speed up the recruitment process.\u00a0 Consideration of applications will commence on 20 January 2022 until the position is filled.\u00a0 Applications should be addressed directly to Ms Alice Law (please state Jockey Club Design Institute for Social Innovation on the envelope).\u00a0 The University\u2019s Personal Information Collection Statement for recruitment can be found at https://www.polyu.edu.hk/hro/careers/guidelines_and_forms/pics_for_recruitment.\nPolyU is an equal opportunity employer committed to diversity and inclusivity.\u00a0 All qualified applicants will receive consideration for employment without regard to gender, ethnicity, nationality, family status or physical or mental disabilities.", "employment_types": ["Full Time"], "selling_points": [], "locations": ["Not Specified"], "categories": ["Admin & HR", "Clerical / Admin Staff", "Personal / Executive Assistant", "Education", "Others"], "post_time": "2022-01-14T03:11:19Z", "salary": {"currency": null, "max": null, "min": null, "period": null, "term": null}, "salary_visible": false, "title_keywords": ["administrative assistant", "project assistant"], "responsibilities": ["administration", "any other duties", "management", "social media platforms", "website", "design", "communication", "maintain", "reports", "planning", "database", "contact", "recruitment", "recruitment process", "online promotion"], "requirements": {"degrees": ["degree", "hkdse"], "majors": ["mathematics", "business administration", "social sciences"], "languages": ["english", "chinese"], "language_level": ["good command"], "hard_skills": ["excel", "alice", "no", "chinese word processing", "powerpoint", "adobe illustrator", "c", "outlook", "ms office"], "soft_skills": ["organizational skills", "work independently", "communication skills", "under pressure", "team spirit", "competent", "computer literacy", "committed", "self-motivation", "learning", "innovative", "interpersonal"], "languages_combined": [{"language": "english", "language_level": ["good command"]}, {"language": "chinese", "language_level": ["good command"]}]}, "experience_required": {"duration": ["at least one year", "at least two years"], "field": ["post-qualification", "business administration"]}}, {"job_id": "100003009050523", "location_code": "hk", "company": "initial Fashion Co Limited", "job_title": "Part-time Office Administrative Assistant (2-3 days/ week)", "description": "Responsibilities:\n\nProvide general clerical support including filing, arranging payment and preparing regular expenses report.\nPerform receptionist duties such as greeting guests, handling telephone calls, courier and mail arrangement.\nProvide administrative and clerical support for HR and Administration Department.\nArrange office cleaning, pest control and fire system services on regular basis.\nAssist ad hoc projects and perform other duties as assigned from time to time.\nRequirements:\n\nSchool certificate with relevant working experience in office administration duties.\nDetail-oriented, responsible and reliable.\nGood interpersonal skills, telephone manner and communication skills.\nPet lover is a must.\nProficiency in computer skills including Microsoft Office.\n\nWe are looking for candidates with vision, energy and a strong fashion sense who want to be part of a dynamic team and create value. We offer career development as well as regional and local advancement opportunities.\n\nWe are a Hong Kong-based fashion label established in 2000, currently with operations in Hong Kong, Macau and the Chinese Mainland. We create a culture rather than just a piece of clothing.\u00a0 Our philosophy and personality is unique and our outlook is global, we bring \u201cThe Unusual Experience\u201d to our customers.\n\nInterested parties please send your\u00a0resume with expected salary\u00a0to Human Resources Department via Apply Now.\n\nPlease visit our company website\u00a0http://www.initialfashion.com\u00a0for more company information.\n\nAll information received will be treated in strict confidence and for recruitment purpose only.\n", "employment_types": ["Part Time"], "selling_points": ["Previous experience in office administration.", "Detail-oriented, responsible and reliable.", "Immediate available is highly preferred"], "locations": ["Kwun Tong"], "categories": ["Admin & HR", "Clerical / Admin Staff", "Personal / Executive Assistant", "Receptionist"], "post_time": "2022-01-14T10:36:44Z", "salary": {"currency": null, "max": null, "min": null, "period": "hourly", "term": null}, "salary_visible": false, "title_keywords": ["administrative assistant"], "responsibilities": ["administration", "control", "perform other duties", "hr", "expenses", "clerical support", "payment", "ad hoc projects", "administrative and clerical support", "cleaning", "report"], "requirements": {"degrees": ["certificate"], "majors": [], "languages": [], "language_level": [], "hard_skills": ["dynamic", "computer skills", "microsoft office"], "soft_skills": ["communication skills", "responsible", "detail-oriented", "dynamic", "interpersonal skills", "reliable", "telephone manner"], "languages_combined": []}, "experience_required": {"duration": [], "field": ["office administration", "relevant working experience"]}}, {"job_id": "100003009039466", "location_code": "hk", "company": "Zheng He Capital Management Limited", "job_title": "Personal Assistant to Chairman (Personal Matters)", "description": "Job Duties:\n\nDeliver efficient and high level secretarial and personal assistance to the Chairman of the company, including but not exclusive to: calendar management, medical claims, business trips and meeting arrangements\nCoordinating and dealing with other Personal Matters of Chairman's family members\nMaintain effective and efficient communication with Chairman's drivers and maids\nTo supervise and control general office administration, and ensures the provision of an efficient working environment\nPreparation and consolidation of reports and in various format within standards\nSeeks ways to continuously improve service, productivity and quality of work\nProvide support on ad hoc projects as required\n\nRequirements:\n\nBachelor\u2019s degree with 5+ years of secretarial and administrative experience supporting C-Suite executives in sizable companies\nFamiliar with MS Outlook, Excel, PowerPoint and Chinese Word Processing\nAbility to manage multiple tasks whilst working in a fast-paced environment\nExcellent communication, organizational and prioritization skills with high attention to details\nFluent in English, Cantonese, and Mandarin\nStable working history\nBe able to work independently and under pressure\nCheerful, strong sense of responsibility, excellent team player and detailed-oriented\n*Immediately available is highly preferred*", "employment_types": ["Full Time"], "selling_points": [], "locations": ["Central"], "categories": ["Admin & HR", "Personal / Executive Assistant"], "post_time": "2022-01-11T09:51:58Z", "salary": {"currency": null, "max": null, "min": null, "period": "monthly", "term": null}, "salary_visible": false, "title_keywords": ["personal", "personal assistant"], "responsibilities": ["management", "control", "provide support", "office administration", "quality", "communication", "maintain", "reports", "ad hoc projects"], "requirements": {"degrees": ["degree", "bachelor"], "majors": [], "languages": ["cantonese", "english", "chinese", "mandarin"], "language_level": ["fluent"], "hard_skills": ["excel", "chinese word processing", "sizable companies", "powerpoint", "c", "outlook"], "soft_skills": ["work independently", "cheerful", "under pressure", "multiple tasks", "fast-paced environment", "organizational", "sense of responsibility", "communication", "team player", "attention to details", "stable", "detailed"], "languages_combined": [{"language": "cantonese", "language_level": ["fluent"]}, {"language": "english", "language_level": ["fluent"]}, {"language": "chinese", "language_level": []}, {"language": "mandarin", "language_level": ["fluent"]}]}, "experience_required": {"duration": ["5+ years"], "field": ["secretarial", "administrative"]}}, {"job_id": "100003009039885", "location_code": "hk", "company": "KOS International Limited", "job_title": "Executive Secretary - Up to 38k", "description": "About Out Client\n\nOur client is a well-known family business, reputable in engaging private investments in Hong Kong. They are currently hiring an Executive Secretary to support the Director and his family.\n\nAbout the Role\n\nHandle the Investment Director & his family's personal matters and provide secretarial support\nManage daily calendar and personal appointments for the Director & his family\nResponsible for managing family travelling plans, organising private and social events\nHandle flight tickets, hotel accommodation and visa arrangements\nAssist in any ad hoc assignments if required\n\nThe Successful Candidate\n\nWith a minimum of 3 years experience as Executive Assistant/ Personal Assistant, ideally in a multicultural work environment\nPresentable, dependable and dynamic, able to work independently and be detail-oriented\nStrong multi-tasking and stakeholders management skills\nImmediately available is highly preferred\nGood command of English and Cantonese is required\n\nClick \"Apply Now\" to apply for this position or call Kobe Lo at +852 3180 4948 for a confidential discussion. All information collected will be kept in strict confidence and will be used for recruitment purpose only.", "employment_types": ["Full Time", "Permanent"], "selling_points": ["Investment & Real Estate company", "3-5 years of EA/ PA experience", "Experienced in support expatriate(s)"], "locations": ["Central"], "categories": ["Admin & HR", "Personal / Executive Assistant", "Secretary"], "post_time": "2022-01-11T13:52:28Z", "salary": {"currency": null, "max": null, "min": null, "period": "monthly", "term": null}, "salary_visible": false, "title_keywords": ["executive secretary"], "responsibilities": ["management", "hotel accommodation", "recruitment", "secretarial support", "ad hoc assignments", "personal appointments", "plans"], "requirements": {"degrees": [], "majors": [], "languages": ["cantonese", "english"], "language_level": ["good command"], "hard_skills": ["dynamic"], "soft_skills": ["work independently", "confidence", "responsible", "detail-oriented", "presentable", "multi-tasking", "dynamic"], "languages_combined": [{"language": "cantonese", "language_level": ["good command"]}, {"language": "english", "language_level": ["good command"]}]}, "experience_required": {"duration": ["minimum of 3 years"], "field": []}}, {"job_id": "100003009044240", "location_code": "hk", "company": "The Hong Kong And China Gas Co Ltd", "job_title": "Administrative Assistant (Secretarial Support)", "description": "The Role:\n\nProvide full administrative support, including but not limited to management of calendar, scheduling of meetings, travel arrangements etc.\nAssist in documentation management to fulfil the internal and external standards\nPrepare correspondences and payment related documents for management approval\nSupport ad-hoc administrative work upon request\nThe Person:\n\nTertiary education with at least 5 years\u2019 relevant working experiences, preferably gained in financial institutions\nExcellent interpersonal and communication skills\nResponsible, self-motivated and able to work independently\nProficient in MS Applications (Excel, PowerPoint and Words) and Chinese words processing; knowledge of SAP is preferred\nGood command of written and spoken English & Chinese; able to read simplified Chinese and proficiency in Putonghua is a must\n\nApplication with full details stating current and expected salary to: APPLY NOW\u00a0\n\nPlease quote the reference number (ID/AA/JDB01/22) your application.\u00a0\n\n\n(All personal data provided will be treated in strict confidence and used for recruitment purposes only.)", "employment_types": ["Permanent"], "selling_points": ["Provide secretarial support to General Manager", "Provide administrative support in Investment Dept", "5yrs' working exp. preferably gained in FI"], "locations": ["North Point"], "categories": ["Admin & HR", "Clerical / Admin Staff", "Personal / Executive Assistant"], "post_time": "2022-01-13T03:30:21Z", "salary": {"currency": null, "max": null, "min": null, "period": "monthly", "term": null}, "salary_visible": false, "title_keywords": ["administrative assistant"], "responsibilities": ["ad-hoc", "travel arrangements", "management", "administrative work", "administrative support", "related documents", "communication", "payment", "recruitment", "documentation", "personal data", "scheduling of meetings"], "requirements": {"degrees": [], "majors": [], "languages": ["putonghua", "english", "chinese"], "language_level": ["proficiency", "good command", "proficient"], "hard_skills": ["excel", "ms applications", "words", "sap", "id", "powerpoint", "documentation", "processing"], "soft_skills": ["communication skills", "self-motivated", "work independently", "confidence", "responsible", "interpersonal"], "languages_combined": [{"language": "putonghua", "language_level": []}, {"language": "english", "language_level": ["good command"]}, {"language": "chinese", "language_level": ["proficiency", "good command", "proficient"]}]}, "experience_required": {"duration": ["at least 5 years"], "field": ["financial institutions", "education"]}}, {"job_id": "100003009043829", "location_code": "hk", "company": "Attivo Consulting Limited", "job_title": "Admin Assistant (22-28K)", "description": "Our client is a full owned subsidiary under a HK listed company which focusing in properties and construction business. To cope with their rapid growth, they are looking for an Admin Assistant to work in their Headquarter Office. \u00a0\n\nResponsibilities:\n\nTo work in admin team to provide professional full spectrum of admin and secretarial support for the Group Chairman\nIncluding scheduling travel itinerary, ensure Chairman meeting arrangement in smooth; Assist preparing various sales reports, meeting materials preparation, PowerPoint presentation, marketing materials and office administration affairs\nReport to Senior Secretary; Support ad-hoc project\n\nRequirements:\n\nBachelor degree in any discipline\n3 years or above experience in personal assistant, admin assistant, secretary, sales administration or related discipline\nProficiency in PC skills and Microsoft Applications; Chinese word processing skills is essential\nA good team player with good organizational skills set; helpful person with coachable character\nIndependent person with ability to perform efficiently in a fast-paced environment\nExcellent command of spoken English, Cantonese and Mandarin\n\nInterested parties please\u00a0click on \"Apply Now\" to attach your full resume (with expected salary & date available) or email to resume(at)attivoasia.com", "employment_types": ["Permanent"], "selling_points": ["HK listed Co. subsidiary, 22-28K x 13 + bonus", "Report to Senior Secretary, Good Eng & Mandarin", "Decent, Good manner, Presentable, Polite person"], "locations": ["Wan Chai"], "categories": ["Admin & HR", "Clerical / Admin Staff", "Personal / Executive Assistant", "Secretary"], "post_time": "2022-01-13T02:06:34Z", "salary": {"currency": null, "max": null, "min": null, "period": "monthly", "term": null}, "salary_visible": false, "title_keywords": ["admin assistant"], "responsibilities": ["ad-hoc", "sales reports", "office administration", "scheduling", "secretarial support", "marketing materials", "report"], "requirements": {"degrees": ["degree", "bachelor"], "majors": [], "languages": ["cantonese", "english", "chinese", "mandarin"], "language_level": ["excellent"], "hard_skills": ["pc skills", "chinese word processing", "microsoft applications"], "soft_skills": ["fast-paced environment", "organizational skills", "good team player", "independent"], "languages_combined": [{"language": "cantonese", "language_level": ["excellent"]}, {"language": "english", "language_level": ["excellent"]}, {"language": "chinese", "language_level": []}, {"language": "mandarin", "language_level": ["excellent"]}]}, "experience_required": {"duration": ["3 years"], "field": ["related", "sales administration", "admin"]}}, {"job_id": "100003009039699", "location_code": "hk", "company": "Hong Kong Examinations and Assessment Authority", "job_title": "Senior Personal Assistant (Ref: SGO/01/808)", "description": "Duties: The appointee will provide administrative and secretarial support to the Secretary General and Directors as assigned. Major duties including drafting and editing documents, office administration, scheduling meetings, assisting in the preparation, compilation and distribution of Council/Committee papers and documents, maintaining filing system and publications, coordinating with internal and external parties in connection with committee work and the Authority matters, and supporting in other organisational initiatives/corporate events and projects as assigned.\nRequirements:\n(a)\u00a0\u00a0 \u00a0A Bachelor\u2019s Degree in Business Administration or related disciplines;\n(b)\u00a0\u00a0 \u00a0At least 5 years\u2019 relevant experience in executive secretarial and/or administrative support;\n(c)\u00a0\u00a0 \u00a0Good command of spoken and written English and Chinese, knowledge of Putonghua is an advantage;\n(d)\u00a0\u00a0 \u00a0Proficient in computer applications including MS Word, Excel, Access and Chinese word processing;\n(e)\u00a0\u00a0 \u00a0Able to work independently with excellent interpersonal and communication skills;\n(f)\u00a0\u00a0 \u00a0Strong time management and organising skills;\n(g)\u00a0\u00a0 \u00a0Vigilance and attentive to details; and\n(h)\u00a0\u00a0 \u00a0Multi-tasking and able to work under pressure.\nCandidates with less experience will be considered for the position of Personal Assistant.\nEmployment Terms:\u00a0 The remuneration package will be commensurate with qualifications and experience.\u00a0 Appointment will be on a fixed-term contract with contract-end-gratuity, MPF benefits, medical and dental care.\u00a0 Future employment may be offered on renewable contracts subject to performance and staffing needs.\nDate for Application Review: 25 January 2022\nApplications would be considered until the post is filled.\nApplication forms can be obtained from the HKEAA office on 13/F., Southorn Centre, 130 Hennessy Road, Wan Chai, Hong Kong or downloaded from the HKEAA website (www.hkeaa.edu.hk/tc/Career/general.html).\u00a0 Completed application forms should be returned to the Manager \u2013 Human Resources at the above address. Due to the secrecy nature of HKEAA's job duties, applicants invited for interview may be required to make a declaration of any conflict of interests. Applicants not notified within 10 weeks from the application review date should consider their applications unsuccessful.\nThe HKEAA is an equal opportunities employer and welcomes applications from all qualified candidates. Information provided relating to employment will be kept confidential and used only for processing applications. For details, please refer to the Policy Statement on Equal Opportunities and the Personal Information Collection Statement on the HKEAA website (www.hkeaa.edu.hk).", "employment_types": ["Full Time", "Contract"], "selling_points": [], "locations": ["Not Specified"], "categories": ["Admin & HR", "Personal / Executive Assistant", "Others"], "post_time": "2022-01-11T10:34:40Z", "salary": {"currency": null, "max": null, "min": null, "period": null, "term": null}, "salary_visible": false, "title_keywords": ["personal assistant"], "responsibilities": ["management", "maintaining", "administrative support", "work under pressure", "office administration", "internal and external parties", "communication", "scheduling", "secretarial support", "committee work", "computer applications", "editing", "administration"], "requirements": {"degrees": ["degree", "bachelor"], "majors": ["related disciplines", "business administration"], "languages": ["putonghua", "english", "chinese"], "language_level": ["advantage", "good command", "proficient"], "hard_skills": ["excel", "c", "chinese word processing", "ms word"], "soft_skills": ["communication skills", "work independently", "attentive to details", "multi-tasking", "time management", "interpersonal", "work under pressure"], "languages_combined": [{"language": "putonghua", "language_level": ["good command"]}, {"language": "english", "language_level": ["advantage", "good command"]}, {"language": "chinese", "language_level": ["advantage", "good command", "proficient"]}]}, "experience_required": {"duration": ["at least 5 years"], "field": ["secretarial", "administrative", "relevant experience"]}}, {"job_id": "100003009048294", "location_code": "hk", "company": "Top Personnel Consultant", "job_title": "Legal Secretary ($18-23K)", "description": "Our client is a sizable\u00a0legal firm\u00a0in Admiralty with 5 days\u2019 work urgently looking for a\u00a0Legal Secretary\u00a0to join their company with details as follows:\u00a0\u00a0\n\nJob Duties:\u00a0\n\nProvide general secretarial support to Litigation Solicitor\nLiaise with internal & external parties\nLegal billing & manage legal filing systems\nEnglish & Chinese WP\u00a0 \u00a0\u00a0\n\n\u00a0Requirements:\u00a0\n\nDegree holder with 3 years' up stable secretarial experience in any business nature OR\u00a0Diploma up with legal firm experience\u00a0\nGood at both English & Chinese typing\n\nSalary negotiable ($18-23K) depends on qualifications & experience.\n\nInterested parties, please email detailed resume by Clicking \"Apply Now\"\u00a0or call 2866\u00a01088 (Ms. Yuen) for further inquiries.\n\nFor more information about our\u00a0agency, please visit www.toppersonnel.com.hk\n\nThe information provided by applicants will be used for employment related purpose only.", "employment_types": ["Full Time", "Permanent"], "selling_points": ["Degree + 3 yrs up Sec. Exp. OR", "Diploma up with legal firm exp., 5 Days", "HK$18-23K + Medical + DB + Dental, Admiralty"], "locations": ["Admiralty"], "categories": ["Admin & HR", "Personal / Executive Assistant", "Secretary", "Professional Services", "Legal & Compliance"], "post_time": "2022-01-14T06:09:21Z", "salary": {"currency": null, "max": null, "min": null, "period": "monthly", "term": null}, "salary_visible": false, "title_keywords": ["legal secretary"], "responsibilities": ["liaise with", "external parties", "secretarial support", "systems"], "requirements": {"degrees": ["diploma", "degree holder"], "majors": ["business"], "languages": ["english", "chinese"], "language_level": ["good"], "hard_skills": ["typing"], "soft_skills": ["stable"], "languages_combined": [{"language": "english", "language_level": ["good"]}, {"language": "chinese", "language_level": ["good"]}]}, "experience_required": {"duration": ["3 years"], "field": ["secretarial", "business", "legal"]}}, {"job_id": "100003009046886", "location_code": "hk", "company": "Hong Kong Aircraft Engineering Co Ltd", "job_title": "Administrative Officer", "description": "Scope of Duties:\u00a0\n\nVisible as POC for general inquiries to Group Corporate Development, Digital, Group BI&SD and Group HR teams.\nSupports in formal communications & distributes to internal / external stakeholders.\nCoordinate meetings & scheduling with internal / external stakeholders, maintain shared calendars of Group\nCorporate Development and other teams as defined.\nProcesses documents for signatory & routing.\u00a0\nMaintains files & data bases as assigned / monitors statutory requirements.\nAssists in the onboarding of new employees into the Group Corporate Development, Group Digital, Group BI&SD and Group HR.\nProvides reports / documents on scheduled basis / or per request.\nUndertakes ad-hoc projects as assigned / assists in preparing presentation materials.\nArranges travel bookings & itinerary on business travels.\nPrepares expense reports, coordinates submission on expenses.\nProvides support to members of Group Corporate Development and other teams defined on travel arrangement.\nScreens expense reports submitted by employees prior to approval.\nMaintains compliance with HAECO processes and policies.\n\nRequirements:\u00a0\n\nDegree / Diploma holder with minimum 5 years of relevant experience in sizeable organization.\nWell-organized and independent; self-motivated; attentive to details; and service-oriented attitude.\nStrong communication and interpersonal skills.\nExcellent command of English, written and spoken; Cantonese and / or Mandarin an advantage.\nProficient in MS Office (Microsoft Word, Excel, and PowerPoint).\nSelf-motivated to achieve results; attentive to details.\nAbility to work with others in cross cultural / cross functional environments. Motivates self \u2013 and others thru positive attitude and excellent interpersonal skills.\nDemonstrates ability to manage corporate office functions supporting Sr. leadership and functional teams.\u00a0 Shows attention to details and has ability to multi-task and pro-actively support others in assigned duties or ad-hoc tasks.\nKnowledgeable in use of MS Office Software, CRM, ERP, and software tools\n\nHow to Apply:\n\nPlease send your resume with expected salary, quoting the employer's reference no., to: Human Resources Department - Talent & Partnership Team, Hong Kong Aircraft Engineering Company Limited, 80 South Perimeter Road, Hong Kong International Airport, Lantau, Hong Kong OR submit your application via\u00a0https://careers.haeco.com/hkg/job-openings/\n\nCandidates not contacted 4-6 weeks after submission of applications and/or interviews may consider their application unsuccessful.\n\nAll information provided by candidates will be treated in strict confidence and will be used for employment purpose only.", "employment_types": ["Full Time", "Permanent"], "selling_points": ["Minimum 5 years of relevant experience", "Excellent command of English", "Proficient in MS Office"], "locations": ["Airport Area"], "categories": ["Admin & HR", "Clerical / Admin Staff", "Personal / Executive Assistant", "Others"], "post_time": "2022-01-14T01:41:20Z", "salary": {"currency": null, "max": null, "min": null, "period": "monthly", "term": null}, "salary_visible": false, "title_keywords": ["administrative officer"], "responsibilities": ["data", "policies", "hr", "expenses", "teams", "compliance", "coordinate", "scheduling", "statutory requirements", "maintain", "reports", "travel arrangement", "ad-hoc projects"], "requirements": {"degrees": ["diploma holder", "degree"], "majors": [], "languages": ["cantonese", "english", "mandarin"], "language_level": ["advantage", "excellent"], "hard_skills": ["excel", "no", "microsoft word", "aircraft", "powerpoint", "erp", "sr", "ms office"], "soft_skills": ["self-motivated", "confidence", "independent", "multi-task", "attentive to details", "service-oriented", "well-organized", "positive attitude", "communication and interpersonal skills", "interpersonal skills", "attention to details", "leadership"], "languages_combined": [{"language": "cantonese", "language_level": ["advantage"]}, {"language": "english", "language_level": ["excellent"]}, {"language": "mandarin", "language_level": ["advantage"]}]}, "experience_required": {"duration": ["minimum 5 years"], "field": ["relevant experience"]}}, {"job_id": "100003009037423", "location_code": "hk", "company": "Hai Kang Life Corporation Ltd", "job_title": "Personal Assistant", "description": "JOB DESCRIPTION\n\nProvide full range of secretarial & administrative support to Chairman/ Senior Management regarding both business and personal matter\nMaintain the Chairman/ Senior Management\u2019s complex daily schedule including but not limited to local & overseas business-related activities, appointments, meetings, conference & travel and keep a good system of calendar arrangement\nAssist in meeting agenda & minutes, handle general correspondence, emails, memos, letters and reports as required\nSupervise the team & assist in daily operation of the Company\nLead & manage ad-hoc projects such as evens, social functions, exhibitions etc.\nLiaise and co-ordinate with various internal and external parties\n\nQUALIFICATION REQUIREMENTS\n\nBachelor\u00a0Degree holder with 5 years of relevant experience\nAt least 2 years in supervisor level\nExperience in membership-based/ service focused organisation\nWilling to support out usual working hours\nMature, self-motivated, initiative, well-organised & detail-minded with excellent interpersonal & communication skills\nFluent in written & spoken English & Chinese\nProficient in MS Office especially Word, Excel, PowerPoint, Google-powered business tools (email, calendar, docs); knowledge in Photoshop & AI", "employment_types": ["Full Time", "Permanent"], "selling_points": [], "locations": ["Shatin Area"], "categories": ["Admin & HR", "Personal / Executive Assistant", "Secretary"], "post_time": "2022-01-11T02:46:50Z", "salary": {"currency": null, "max": null, "min": null, "period": "monthly", "term": null}, "salary_visible": false, "title_keywords": ["personal assistant"], "responsibilities": ["liaise", "ad-hoc projects", "administrative support", "co-ordinate with", "internal and external parties", "letters", "daily operation", "maintain", "reports", "schedule", "senior management"], "requirements": {"degrees": ["bachelor degree holder"], "majors": [], "languages": ["english", "chinese"], "language_level": ["fluent"], "hard_skills": ["excel", "ai", "word", "powerpoint", "ms office", "photoshop"], "soft_skills": ["detail-minded", "communication skills", "self-motivated", "focused", "mature", "organisation", "well-organised", "interpersonal", "initiative"], "languages_combined": [{"language": "english", "language_level": ["fluent"]}, {"language": "chinese", "language_level": ["fluent"]}]}, "experience_required": {"duration": ["5 years"], "field": ["relevant experience"]}}, {"job_id": "100003009045801", "location_code": "hk", "company": "CLPS Technology (Hong Kong) Co., Limited", "job_title": "Human Resources and Administrative Assistant", "description": "Job Description\n\nl\u00a0 \u00a0A supporting role to carrying out administrative tasks related to all aspects of the company\u2019s HRA operations\n\nl\u00a0\u00a0 Assist to implement company policies, procedures, ensure all tasks executed comply with these policies\n\nl\u00a0\u00a0 Provide support in annual performance and salary review exercise\n\nl\u00a0\u00a0 Handle administrative duties (e.g. ordering office consumables, claims, leave application, visa applications, flight ticket arrangement)\n\nl\u00a0\u00a0 Provide IT support, working with internal and external parties to resolve technical issues\n\nl\u00a0\u00a0 Perform other ad-hoc tasks as required\n\nRequirements\n\nl\u00a0\u00a0 Degree holder in Human Resources Management, Business Administration or related disciplines\n\nl\u00a0\u00a0 One year's relevant experience is highly preferred\n\nl\u00a0\u00a0 Able to work independently in a fast-paced environment\n\nl\u00a0\u00a0 Effective communication, interpersonal and organizational skills\n\nl\u00a0\u00a0 Proficiency in Microsoft Office (Excel, Word, PowerPoint and Chinese Word Processing)\n\nl\u00a0\u00a0 Good command of written and spoken English, Chinese and Mandarin\n\nl\u00a0\u00a0 Immediately or short notices is preferred\n\nInterested candidate, please send your resume with the expected salary through\u00a0\u201cApply Now\u201d\n\n(Personal data collected will be used for recruitment purposes only)", "employment_types": ["Full Time", "Permanent"], "selling_points": ["flexbile working enviroment", "HRA, Asssistant, Human Resource", "5 days work, medical insurance, performance bonus"], "locations": ["Kwun Tong"], "categories": ["Admin & HR", "Clerical / Admin Staff", "Personal / Executive Assistant", "HR Supporting Staff"], "post_time": "2022-01-13T08:45:34Z", "salary": {"currency": null, "max": null, "min": null, "period": "monthly", "term": null}, "salary_visible": false, "title_keywords": ["administrative assistant", "human resources"], "responsibilities": ["provide support", "operations", "policies", "review", "procedures", "internal and external parties", "ad-hoc tasks", "administrative duties", "administrative tasks"], "requirements": {"degrees": ["degree holder"], "majors": ["related disciplines", "business administration"], "languages": ["english", "chinese", "mandarin"], "language_level": ["proficiency", "good command"], "hard_skills": ["excel", "chinese word processing", "microsoft office", "word", "powerpoint"], "soft_skills": ["organizational skills", "work independently", "fast-paced environment", "communication", "interpersonal"], "languages_combined": [{"language": "english", "language_level": ["good command"]}, {"language": "chinese", "language_level": ["proficiency", "good command"]}, {"language": "mandarin", "language_level": ["good command"]}]}, "experience_required": {"duration": ["one year"], "field": ["relevant experience"]}}, {"job_id": "100003009036775", "location_code": "hk", "company": "Austen Capital Partners Holding Limited", "job_title": "Executive Assistant", "description": "Responsibilities\n\nProvide personal assistance to CEO as required\nAssist with record keeping, payment and accounting services\nManage\u00a0correspondence and\u00a0schedule appointments\n\nRequirements\n\nHard-working\nPrior experience is an advantage but not a necessity\nManagement accounting knowledge and experience required\nExcellent in Microsoft Office (MS Word, Excel, PowerPoint)\nWell-organized, self-motivated and able to work independently\nExcellent command of verbal and written English and Chinese (Mandarin a plus)\n\nJob Offer\n\nAttractive package", "employment_types": ["Full Time", "Part Time", "Permanent"], "selling_points": ["Oversee office administration", "Provide secretarial support", "Co-ordinate internal and external meetings"], "locations": ["Tsim Sha Tsui"], "categories": ["Admin & HR", "Personal / Executive Assistant", "Media & Advertising", "Account Servicing", "Professional Services", "Company Secretary"], "post_time": "2022-01-10T14:03:10Z", "salary": {"currency": null, "max": null, "min": null, "period": "monthly", "term": null}, "salary_visible": false, "title_keywords": ["executive assistant"], "responsibilities": ["payment", "schedule"], "requirements": {"degrees": [], "majors": [], "languages": ["english", "chinese", "mandarin"], "language_level": ["excellent"], "hard_skills": ["excel", "plus", "microsoft office", "powerpoint", "ms word"], "soft_skills": ["self-motivated", "hard-working", "well-organized", "work independently"], "languages_combined": [{"language": "english", "language_level": ["excellent"]}, {"language": "chinese", "language_level": ["excellent"]}, {"language": "mandarin", "language_level": ["excellent"]}]}, "experience_required": {"duration": [], "field": ["management accounting"]}}, {"job_id": "100003009051333", "location_code": "hk", "company": "Assurance Education Limited", "job_title": "Education Consultant, Full Time", "description": "Job Description: Education Consultant\n\nOrganization\n\nAssurance aims to help students make blossom and make the most out of high school. Assurance is headquartered in Hong Kong and maintains offices in Shenzhen and Shanghai. All of our consultants are from top universities such as Wharton, Harvard, UPenn and UChicago. For more information, please visit www.assuranceedu.com.\n\nPosition\n\nEducation Consultant, Full Time\n\nLocation\n\nCauseway Bay\n\nHours\n\n5 days work week\nTuesday to Saturday\n9.30am to 6.30pm\n\nResponsibilities\n\nProvide administrative support\nHandle correspondence\nManage school application forms\nAssist in seminars and events\n\nRequirements\n\nFluency in Cantonese, English and Mandarin\nProficient in Word, Excel, and word processing in English & Chinese\n1 year of experience as administrative assistant/secretary\nDegree holder in any discipline\n\nCompensation\n\nWe offer a starting salary of $15000-$17,000/month. Please state your expected salary.\n\nApplication\n\nInterested parties please submit your resume and cover letter to Ms. Tiffany Cheung at admin @ AssuranceEDU.com\u00a0with \u201c[Name] Assurance Recruitment]\u201d in the email title. Please state your expected salary.", "employment_types": ["Full Time"], "selling_points": ["Proficiency in English, Cantonese & Mandarin", "Degree holder, 1 year of experience", "Salary $15-17K, 5 days working"], "locations": ["Causeway Bay"], "categories": ["Admin & HR", "Personal / Executive Assistant", "Secretary", "Education", "Others"], "post_time": "2022-01-15T09:22:56Z", "salary": {"currency": "HKD", "max": 16999, "min": 14000, "period": "monthly", "term": null}, "salary_visible": true, "title_keywords": ["education consultant"], "responsibilities": ["provide administrative support"], "requirements": {"degrees": ["degree holder"], "majors": [], "languages": ["cantonese", "english", "chinese", "mandarin"], "language_level": ["fluency", "proficient"], "hard_skills": ["excel", "word processing", "word"], "soft_skills": [], "languages_combined": [{"language": "cantonese", "language_level": ["fluency"]}, {"language": "english", "language_level": ["fluency", "proficient"]}, {"language": "chinese", "language_level": ["fluency", "proficient"]}, {"language": "mandarin", "language_level": ["fluency"]}]}, "experience_required": {"duration": ["1 year"], "field": ["administrative"]}}, {"job_id": "100003009046055", "location_code": "hk", "company": "Talent Connect Limited", "job_title": "Full Time Project Assistant", "description": "Job Description\n\nResponsibilities:\n\u00b7 To prepare project submission document report and proposal\n\u00b7 To communicate and coordinate with internal and external stakeholders\n\u00b7 To work collaboratively with project team\n\u00b7 To assist with ad hoc activities if needed.\n\n\u00a0Requirements:\n\u2022 Degree holder in any disciplines (Fresh graduates will also be considered)\n\u2022 Minimum of 1-year work experience preferably gained in project management, sales and marketing\n\u2022 Good written and spoken English and Chinese, knowledge in Putonghua is an advantage\n\u2022 Self-motivated, well-organized, Ability to work independently and as part of a team, with limited supervision\n\u2022 Willing to learn and be multi-tasking in various projects\n\u2022 Proficiency in Microsoft Office applications (Word, Excel & PowerPoint) and Chinese word processing\n\nBenefits and Others\n\u2022 Salary 12-15K\n\u2022 5 days work , 10am-7pm\n\u2022 Annual leave\n\u2022 Job Training and Education Allowance\n\u2022 Performance Bonus\n\u2022 Medical insurance", "employment_types": ["Full Time"], "selling_points": ["5 days work", "Annual leave", "Job Training and Education Allowance"], "locations": ["Mong Kok"], "categories": ["Admin & HR", "Personal / Executive Assistant"], "post_time": "2022-01-13T09:30:41Z", "salary": {"currency": null, "max": null, "min": null, "period": "monthly", "term": null}, "salary_visible": false, "title_keywords": ["project assistant"], "responsibilities": ["ad hoc", "coordinate with", "report"], "requirements": {"degrees": ["degree holder"], "majors": ["any disciplines"], "languages": ["putonghua", "english", "chinese"], "language_level": ["advantage", "proficiency", "good"], "hard_skills": ["excel", "chinese word processing", "microsoft office", "word", "powerpoint", "project management"], "soft_skills": ["self-motivated", "work independently", "willing to learn", "well-organized", "project management", "multi-tasking"], "languages_combined": [{"language": "putonghua", "language_level": ["advantage", "good"]}, {"language": "english", "language_level": ["advantage", "good"]}, {"language": "chinese", "language_level": ["advantage", "proficiency", "good"]}]}, "experience_required": {"duration": ["minimum of 1-year"], "field": ["project management", "marketing"]}}, {"job_id": "100003009035460", "location_code": "hk", "company": "Hillman Ross", "job_title": "Executive Assistant (MNC, Contract)", "description": "Our client is a Multinational Corporation, an opportunity has arisen for an Executive Assistant (MNC, contract) to join their team.\n\n\nWe are now seeking for Executive Assistant (MNC, contract)\n\n\nRESPONSIBILITIES\n\nMaintaining a busy calendar; planning and organizing meetings\nPrepare presentation documents and reports for management meetings\nEvent management includes regular meetings, in-house activities, and off-site events, etc.\nOverseas travel management and accommodation arrangement\nHandle executive correspondence\nExpenses management duties\nOther administrative support as requested.\nResponsible for monthly reporting and support for ad hoc projects as needed\n\nQUALIFICATIONS\n\nDegree holder in Business Administration or related disciplines\n8 years or above of secretarial & administrative support experience in multinational corporations (at least 5 years serving C-level executives preferred)\nDegree or Diploma holder\nExcellent command of oral and written English.\nStrong computer skills (e.g. Microsoft Office: Outlook, Word, Excel, PPT, etc)\nHigh level of confidentiality and professionalism\nHigh attention to detail, good time management skills, and ability to be flexible in response to changing priorities\nAbility to communicate clearly and effectively with senior leaders and external business partners.\nImmediately available\n\n\nAPPLY FOR THIS JOB\nInterested candidate please CLICK apply button to apply online or send your resume in MS word format to Hillman Ross Recruitment Solution Professional\n\n\n\n\nPlease note that only shortlisted candidate will be notified. All information will be treated in strict confidence and solely used for recruitment purposes.", "employment_types": ["Full Time", "Permanent"], "selling_points": ["5 days per week", "Competitive salary package", "Good communication and interpersonal skills"], "locations": ["Not Specified"], "categories": ["Admin & HR", "Personal / Executive Assistant"], "post_time": "2022-01-10T07:15:14Z", "salary": {"currency": null, "max": null, "min": null, "period": "monthly", "term": null}, "salary_visible": false, "title_keywords": ["executive assistant"], "responsibilities": ["administration", "reporting", "management", "maintaining", "administrative support", "expenses", "reports", "ad hoc projects", "recruitment", "planning"], "requirements": {"degrees": ["diploma holder", "degree", "degree holder"], "majors": ["related disciplines", "business administration"], "languages": ["english"], "language_level": ["excellent"], "hard_skills": ["excel", "microsoft office", "word", "c", "computer skills", "outlook", "ms word"], "soft_skills": ["flexible", "oral", "confidence", "responsible", "time management skills", "attention to detail", "presentation"], "languages_combined": [{"language": "english", "language_level": ["excellent"]}]}, "experience_required": {"duration": ["at least 5 years", "8 years"], "field": ["secretarial", "administrative"]}}, {"job_id": "100003009042206", "location_code": "hk", "company": "CTS Limited", "job_title": "Administrator Assistant/ Secretary", "description": "Requirements:\n\nDegree holder / Diploma with\u00a0secretarial/administrative training preferred\nMinimum\u00a02\u00a0years working experience in the capacity of Executive Assistant\nStrong analytical and communication skills\nMature, reliable, well organized and systematic\nResponsible, self-initiated, meticulous and well-organized\nAble to\u00a0handle multi tasks and work independently\n\nResponsibilities:\n\n\u00a0Deliver full secretarial and administration support to Business Director\nOverall administrative and secretarial supports (including typing, filing, taking minutes, scheduling meetings, screening phone calls, handling correspondence)\nHandle calendar management, travel booking and business meetings arrangement\nLiaising with internal staffs, external clients and business partners\n\u00a0Co-ordinate projects and function\nOrganize and prepare presentation materials, proposals, reports, taking minutes and other correspondences including drafting emails and letters", "employment_types": ["Full Time"], "selling_points": ["Secretarial", "Administrative", "HR"], "locations": ["Kwun Tong"], "categories": ["Admin & HR", "Administration / Operation Manager", "Personal / Executive Assistant", "Secretary"], "post_time": "2022-01-12T06:36:02Z", "salary": {"currency": null, "max": null, "min": null, "period": "monthly", "term": null}, "salary_visible": false, "title_keywords": ["administrator", "secretary", "assistant"], "responsibilities": ["management", "letters", "liaising with", "scheduling", "reports", "booking", "phone calls", "administration"], "requirements": {"degrees": ["diploma", "degree holder"], "majors": [], "languages": [], "language_level": [], "hard_skills": [], "soft_skills": ["communication skills", "meticulous", "work independently", "responsible", "well organized", "well-organized", "systematic", "mature", "reliable"], "languages_combined": []}, "experience_required": {"duration": ["minimum 2 years"], "field": []}}, {"job_id": "100003009042039", "location_code": "hk", "company": "E-buy Global Limited", "job_title": "Executive Assistant", "description": "Responsibilities:\n\nAct as the point of contact among executives, employees, clients and other external partners\nManage information flow in a timely and accurate manner\nManage executives\u2019 calendars and set up meetings\nRack daily expenses and prepare weekly, monthly or quarterly reports\nFormat information for internal and external communication \u2013 memos, emails, presentations, reports\nOrganize and maintain the office filing system\nTake minutes during meetings\nPerform any other administrative and office duties as assigned by the Director\n\nRequirements:\n\n\u00a0University\u00a0graduate with\u00a0less working experience\u00a0will also be considered\n\u00a0Experience as an Executive Assistant, Personal Assistant or similar role is preferable\n\u00a0Native English verbal and written communications skills\n\u00a0Excellent Chinese verbal and written communications skills\n\u00a0Excellent word processing and MS office skills\n\u00a0Familiar with office gadgets and applications\n\u00a0Outstanding organizational and time management skills\n\u00a0Aggressive and willing to work at Start-up company\n\u00a0Discretion and confidentiality", "employment_types": ["Full Time"], "selling_points": ["University graduate", "Experience as an Executive Assistant, PA", "5-day work week"], "locations": ["Kwai Hing"], "categories": ["Admin & HR", "Personal / Executive Assistant", "Secretary", "Others"], "post_time": "2022-01-12T05:36:23Z", "salary": {"currency": null, "max": null, "min": null, "period": "monthly", "term": null}, "salary_visible": false, "title_keywords": ["executive assistant"], "responsibilities": ["expenses", "presentations", "communication", "maintain", "reports", "contact"], "requirements": {"degrees": ["university graduate"], "majors": [], "languages": ["english", "chinese"], "language_level": ["native", "excellent"], "hard_skills": ["word processing", "ms office"], "soft_skills": ["time management skills", "organizational"], "languages_combined": [{"language": "english", "language_level": ["native"]}, {"language": "chinese", "language_level": ["excellent"]}]}, "experience_required": {"duration": [], "field": []}}, {"job_id": "100003009046922", "location_code": "hk", "company": "DKNT CPA Limited", "job_title": "Junior Secretary", "description": "Requirements:\n\nPost-secondary graduate\nGood command of spoken English a must\nStrong\u00a0organizational\u00a0and self management skills\nProactive and client focused\nEager to learn, thrive under pressure\n1 - 2 years' experience / candidates with no experience will also be considered", "employment_types": ["Full Time"], "selling_points": ["5-day week", "study leaves, examination support", "good promotion prospect"], "locations": ["Wan Chai"], "categories": ["Admin & HR", "Clerical / Admin Staff", "Personal / Executive Assistant", "Secretary"], "post_time": "2022-01-14T01:43:58Z", "salary": {"currency": null, "max": null, "min": null, "period": "monthly", "term": null}, "salary_visible": false, "title_keywords": ["junior secretary"], "responsibilities": ["management"], "requirements": {"degrees": [], "majors": [], "languages": ["english"], "language_level": ["good command"], "hard_skills": ["no"], "soft_skills": ["under pressure", "focused", "organizational", "eager to learn", "proactive"], "languages_combined": [{"language": "english", "language_level": ["good command"]}]}, "experience_required": {"duration": ["1 - 2 years"], "field": []}}, {"job_id": "100003009039785", "location_code": "hk", "company": "Hudson Global Resources (Hong Kong) Limited", "job_title": "EA to Regional CEO (Famous International Financial Service; 35-50k)", "description": "A one-off and genuinely exciting opportunity for an outstanding, supremely efficient Executive Assistant to work for a very successful and highly respected individual and well-known international financial service. This Regional CEO is a dream to work for \u2013 considerate, straight forward, calm \u2013 but super busy and in huge demand so the CEO time is precious and the EA needs to manage this intelligently and effectively.\n\nWe are looking for an EA who has about 8 years\u2019 experience working as an EA/PA (ideally business rather than solely private) for a key individual in the financial/bank industry. The company is really going places and it\u2019s incredibly fast moving so his EA needs to be an expert plate spinner, relish a pacey environment and have the experience and emotional intelligence to confidently and accurately prioritise without/with minimal referral.\n\nYou will need to be impressive \u2026\u2026\u2026.. at the top of your game, and enjoy working in a creative, collaborative and constantly changing environment.\u00a0 It\u2019s important you are intelligent, sharp and pick things up quickly and are able to cope with pressure and stress calmly.\u00a0 A warm and charming personality with a sense of humour is essential.\u00a0 Discretion is a given.\u00a0 European languages useful.\n\nIt\u2019s an amazing job working for a wonderful boss, in a wonderful company with wonderful colleagues \u2026\u2026\u2026\u2026in a very exciting world.\n\nIf this sounds like you then apply now / send your resume directly to Olivia.chung @ hudson.com!\u00a0\n\nTo apply please click on the \u201cApply\u201d button or enter 732345 in the Keyword section of jobsearch.hk.hudson.com or contact Olivia for a confidential discussion. Alternatively, email your resume to olivia.chung @ hudson.com quoting ref no. 732345. Your interest will be treated in strict confidence.\n\nPrivacy Statement\n\nData collected will be used for recruitment purposes only. Personal data provided will be used strictly in accordance with the relevant data protection law and Hudson's personal information and privacy policy.", "employment_types": ["Full Time", "Permanent"], "selling_points": ["5-day work", "International working experience", "Great job exposure"], "locations": ["Not Specified"], "categories": ["Admin & HR", "Clerical / Admin Staff", "Personal / Executive Assistant", "Secretary"], "post_time": "2022-01-11T11:19:59Z", "salary": {"currency": null, "max": null, "min": null, "period": "monthly", "term": null}, "salary_visible": false, "title_keywords": ["ceo"], "responsibilities": ["personal data", "recruitment", "contact", "data"], "requirements": {"degrees": [], "majors": [], "languages": [], "language_level": [], "hard_skills": ["no"], "soft_skills": ["efficient", "confidence", "enjoy working", "collaborative", "prioritise", "calm", "creative"], "languages_combined": []}, "experience_required": {"duration": ["8 years"], "field": ["business", "it", "financial"]}}, {"job_id": "100003009044548", "location_code": "hk", "company": "Owlsome Limited", "job_title": "Procurement Officer / Assistant", "description": "Job Duties:\n\nThe scope of your job responsibilities will include but is not limited to the following:\n\nComprehend petty cash management and efficiency analysis to ensure proper cashflow statements;\nMaintain and monitor procurement and supply management in relation to current suppliers, credit term maintenance, and marginal cost evaluations;\nAssist in sourcing items as they relate to all functions of the restaurants including but not limited to food, drink, structural, and miscellaneous goods;\nAssistant accounting and human resource divisions with Owlsome group as needed at the instruction and guidance of the general manager;\nFulfil roster and shift duties across multiple restaurants as needed as the instruction and guidance of the general manager;\nAssist in coordination of activities and guidelines set out by the general manager in relation to marketing, community, or group related activities as it relates to any or all of our restaurant locations;\nWork hand in hand with shop managers in the daily operations of the business to help provide timely information, proper maintenance, and effective leadership as outlined and instructed by the General Manager of Owlsome restaurants;\nIn addition to the duties which this job normally entails, you may from time to time be required to undertake additional or other duties as necessary to meet the needs of the Company\u2019s business;\nActively participate and support\u00a0outside office company-held events occasionally;\nAny company events activities as required.\nInterested candidates please send full resume with expected salary by clicking \u201cApply Now\u201d.\n\n\nOur company is an equal opportunity employer. It provides equal opportunity to all employees and applicants for employment in accordance with all applicable laws and regulations.\n\nPersonal data collected will be treated in the strictest confidence and only be used for recruitment related purpose.", "employment_types": ["Full Time", "Permanent"], "selling_points": [], "locations": ["Admiralty"], "categories": ["Admin & HR", "Personal / Executive Assistant", "Hospitality / F & B", "Food & Beverage", "Merchandising & Purchasing", "Procurement / Purchasing / Sourcing"], "post_time": "2022-01-13T04:32:19Z", "salary": {"currency": null, "max": null, "min": null, "period": "monthly", "term": null}, "salary_visible": false, "title_keywords": ["procurement officer", "assistant"], "responsibilities": ["guidance", "management", "cost", "maintenance", "other duties", "guidelines", "analysis", "monitor", "daily operations", "maintain", "coordination"], "requirements": {"degrees": [], "majors": [], "languages": [], "language_level": [], "hard_skills": ["analysis", "maintenance"], "soft_skills": ["timely", "leadership", "coordination"], "languages_combined": []}, "experience_required": {"duration": [], "field": []}}, {"job_id": "100003009036275", "location_code": "hk", "company": "Animoca Brands Limited", "job_title": "Executive Assistant", "description": "Roles & Responsibilities:\n\nProvide a broad range of administrative support which may include but are not limited to calendar management, arranging meetings while coordinating with other assistants, coordinating with internal and external parties while working across multiple time zones effectively and expediently\nHandle expense reimbursement and local transportation for client meetings; arrange/coordinate meals when needed\nHandle travel arrangements. Manage hotels, flights, ground transportations, visas, etc. while minimizing costs\nFollow up on outstanding meeting items and handling confidential matters judiciously\u00a0\nCoordinate and handle sensitive/ confidential information/ meetings for senior management teams\nHandle personal matters including family trip bookings, coordinate with airlines/memberships for upgrades &/or ticket redemptions, handle insurance or medical claims\nAssist in ad-hoc tasks and projects as assigned.\nRequirements:\n\nOverseas (regional or global) or MNC exposure plus comfortable working in multicultural and diverse environment is a MUST\nBachelor degree holder with a minimum 5 years of relevant experience in supporting senior management\nExcellent telephone manners and etiquettes\u00a0\nProficiency in Microsoft Office suite and Google Drive\nHigh levels of adaptability, flexibility and ability to multitask, prioritize work under tight deadlines; able to respond quickly to changes during non-work hours (e.g., managing calendars)\nOutstanding organizational, time and diary management skills\nExcellent problem solving and decision making skills; collaborative and team-oriented\nExcellent and fluent in English, Chinese (verbal and written communications skills)\nDemonstrated record of being to handle sensitive and confidential information; highest standards of integrity\nThe Perks:\n\n5-day work week\n15 days annual leave\nMedical, Life & Personal Accident insurance\nTransportation allowance\nCasual work attire\nFree coffee, tea and fruit daily\nMulti-cultural work environment (15 nationalities and counting!)\nFlat company structure: your ideas get heard by the right people very quickly\nDiverse range of game and app genres: learn and try different projects from time to time\nRegular (and fun) company activities\nOther leaves (Marriage Leave, Compassionate Leave, Exam Leave)\nTo apply for this position please send your resume with position applied, academic transcript (for recent graduates), current and expected salary to our email.\n\n\nInformation provided will be treated in strict confidence and will only be used for recruitment-related purposes. Only short-listed candidates will be contacted. Information of unsuccessful applicants will be destroyed after six months.", "employment_types": ["Full Time"], "selling_points": ["Provide administrative support", "Multi-cultural work environment", "Free coffee, tea and fruit daily"], "locations": ["Pok Fu Lam"], "categories": ["Admin & HR", "Personal / Executive Assistant"], "post_time": "2022-01-10T09:53:21Z", "salary": {"currency": null, "max": null, "min": null, "period": "monthly", "term": null}, "salary_visible": false, "title_keywords": ["executive assistant"], "responsibilities": ["management", "travel arrangements", "administrative support", "upgrades", "ad-hoc tasks", "internal and external parties", "teams", "coordinate with", "coordinate", "senior management", "insurance", "costs"], "requirements": {"degrees": ["bachelor degree holder"], "majors": [], "languages": ["english", "chinese"], "language_level": ["excellent", "fluent"], "hard_skills": ["plus", "tea", "transcript", "fun", "problem solving", "microsoft office suite"], "soft_skills": ["decision making skills", "confidence", "organizational", "integrity", "collaborative", "prioritize", "problem solving", "diverse", "adaptability", "sensitive", "ability to multitask"], "languages_combined": [{"language": "english", "language_level": ["excellent", "fluent"]}, {"language": "chinese", "language_level": ["excellent", "fluent"]}]}, "experience_required": {"duration": ["minimum 5 years"], "field": ["management", "relevant experience"]}}, {"job_id": "100003009050885", "location_code": "hk", "company": "Page Personnel", "job_title": "Human Resources Associate - Electricity Company", "description": "You will join a well-structured HR team, directly report to Head of the HR department. This role has excellent exposure of all rounded HR functions and has the opportunity to rotate in different teams. In addition to daily HR operation, you will also provide administrative and secretarial support to Head of HR.\n\nClient Details\n\nOur client is a Hong Kong based electricity company with long history and more than 4,000 employees. As the industry leader, they provide excellent staff benefits and attrative package. They are looking for a helpful HR candidate to support HR department and Head of HR. Fast-track career progression will be provided to the suitable candidate.\n\nDescription\n\nAssist the Head of HR on daily HR operation\nArrange logistics of internal and external meetings, prepare agenda and meeting minutes\nConduct data analysis, prepare regular HR reports, dashboards, and presentations\nOrganize HR projects such as development programs and employee engagement activities\nRotate in different HR functions and get familiar with the operation of the whole HR department\n\nProfile\n\nMinimum 2 years working experience, preferably from sizable organization\nBachelor's degree in related field\nGood command of both English and Chinese\nProficient in MS Office, including Word, Excel and PowerPoint\n\nJob Offer\n\nAttractive package\nMedical and dental coverage\nGood career progression\nAdditional allowance\n\nTo apply online please click the 'Apply' button below. For a confidential discussion about this role please contact Scarlett Niu on +852 3602 2453", "employment_types": ["Full Time", "Permanent"], "selling_points": ["Fast track career progression", "Directly report to Head of HR", "Attractive compensation and benefits"], "locations": ["Not Specified"], "categories": ["Admin & HR", "Clerical / Admin Staff", "Personal / Executive Assistant", "HR Supporting Staff"], "post_time": "2022-01-14T11:39:03Z", "salary": {"currency": null, "max": null, "min": null, "period": "monthly", "term": null}, "salary_visible": false, "title_keywords": ["associate", "human resources"], "responsibilities": ["hr", "teams", "secretarial support", "report"], "requirements": {"degrees": [], "majors": [], "languages": [], "language_level": [], "hard_skills": [], "soft_skills": ["structured"], "languages_combined": []}, "experience_required": {"duration": [], "field": []}}, {"job_id": "100003009038835", "location_code": "hk", "company": "Drake International and Vertical Talent HK", "job_title": "Executive Assistant / Team Secretary, HR Consultancy, Up to 38K", "description": "Our Client\n\nOur client is a international well established professional consultancy firm. They are currently looking for an Executive Assistant to support 2 senior management.\n\n\nThe Role\n\nThe role reports to senior partners, work closely with the office manager to provide secretarial support.\n\nSupport senior management\nResponsible to provide coordination in HR consultancy activities\nCoordinate and manage events when necessary\nPreparing business correspondences according to instructions and, where necessary, composing it independently with clarity, accuracy, and efficiency\nProvide all rounded support such as travel booking, meeting coordination, expenses and claims report\nManage partners' diaries and arrange business travels and meetings accordingly\nOther administrative duties\n\n\nTo Qualify\n\nThe successful candidate is required to have the following qualities:\n\nBachelor Degree holder\nMinimum 3 years of experience in team or management support\nPrevious support experience\nExcellent interpersonal and communication skills\nExcellent command of spoken and written English and Chinese is a must\nTeam Assistant or Recruitment Coordinator who are seeking to gain more dynamic experience are welcome to apply\nImmediate availability are highly preferred\n\n\nWhat does it mean for you\n\nThis is an exciting opportunity for a proven support professional who wishes to provide top quality of senior management support and to gain more dynamic exposure in coordination duties. An experience which will help you to gain wide exposure to cross functions and a chance to connect with industry leaders and professionals adding value to your professional career.\n\n\nTo Apply\n\nIf you feel your experience and professionalism can make an impact with this firm, please click the Apply now button.\n\nDue to a high volume of applicants, only shortlisted candidates will be contacted.\n\nPersonal data provided by job applicants will be used strictly in accordance with the employer's personal data policies and for recruitment services purposes only.", "employment_types": ["Full Time", "Permanent"], "selling_points": ["HR consultancy support", "Support 2 consultants", "International/ APAC Exposure"], "locations": ["Central"], "categories": ["Admin & HR", "Personal / Executive Assistant", "HR Supporting Staff", "Recruitment / Executive Search"], "post_time": "2022-01-11T07:55:06Z", "salary": {"currency": null, "max": null, "min": null, "period": "monthly", "term": null}, "salary_visible": false, "title_keywords": ["team secretary", "hr", "executive assistant"], "responsibilities": ["management", "policies", "hr", "expenses", "quality", "diaries", "coordinate", "communication", "personal data", "reports", "secretarial support", "coordination", "booking", "administrative duties", "recruitment", "senior management", "report"], "requirements": {"degrees": ["bachelor degree holder"], "majors": [], "languages": ["english", "chinese"], "language_level": ["excellent"], "hard_skills": ["make", "dynamic"], "soft_skills": ["communication skills", "independently", "responsible", "dynamic", "coordination", "interpersonal"], "languages_combined": [{"language": "english", "language_level": ["excellent"]}, {"language": "chinese", "language_level": ["excellent"]}]}, "experience_required": {"duration": ["minimum 3 years"], "field": ["management", "recruitment", "team"]}}, {"job_id": "100003009030880", "location_code": "hk", "company": "Ebro Executive Search Limited", "job_title": "Personal Assistant (M) to Chairman", "description": "The Job\n\nClient: An established Group with diversified business\nPosition: Personal Assistant\nResponsibilities:\nReporting to the Chairman and provide full spectrum of administrative support on both business and personal issues;\nResponsible for organizing meetings and appointments;\nHandle travel arrangement for business or leisure trips, including flights, hotel & accommodation, itinerary planning and visa application\nPrepare presentations materials;\nLiaising with internal and external parties;\n$30-60K. 5-day, medical, bonus, incentives\n\nRequirements\n\nDegree holder from reputable universities. Overseas graduates highly preferred\nRelevant PA experience in serving C-level gained with sizable companies or MNCs.\nWell organized, detail-minded, self-initiative and hard working\nExcellent command of languages; Cantonese, English, Putonghua\nFluent speaker of Japanese will be an advantage but not a must\nWilling to travel\nBoth Male and female applicants are welcome.\nCandidates meeting the above requirements but without PA experience are also welcome", "employment_types": ["Full Time", "Permanent"], "selling_points": ["An established Group with diversified business", "Deg holder w/ Native lv English, Smart, organized", "$30-60K. 5-day, medical, bonus, allowance"], "locations": ["Not Specified"], "categories": ["Admin & HR", "Personal / Executive Assistant", "Beauty Care / Health", "Athletics / Fitness / Sports & Recreation"], "post_time": "2022-01-09T16:25:47Z", "salary": {"currency": "HKD", "max": 69999, "min": 35000, "period": "monthly", "term": null}, "salary_visible": true, "title_keywords": ["personal assistant"], "responsibilities": ["reporting", "administrative support", "internal and external parties", "liaising with", "presentations", "travel arrangement", "planning"], "requirements": {"degrees": ["degree holder"], "majors": [], "languages": ["cantonese", "putonghua", "english", "japanese"], "language_level": ["advantage", "fluent"], "hard_skills": ["sizable companies", "c"], "soft_skills": ["detail-minded", "hard working", "well organized", "self-initiative"], "languages_combined": [{"language": "cantonese", "language_level": []}, {"language": "putonghua", "language_level": []}, {"language": "english", "language_level": []}, {"language": "japanese", "language_level": ["advantage", "fluent"]}]}, "experience_required": {"duration": [], "field": []}}, {"job_id": "100003009035905", "location_code": "hk", "company": "Ambition", "job_title": "Executive Assistant to C-Level (37k x 13), Tuen Mun", "description": "Job Descriptions\n\nProvide secretrial support to CHRO including scheduling meeting, coordinating high level projects, updating HRIS system, travel arrangement etc.\nSupport CHRO on paperwork screening prior to signature\nSupport onboarding of regional senior level hires including visa application, orientation scheduling etc.\nInterview scheduleing for senior hires\nWork closely with Group HR team on any administrative support\n\nQualification and Experience\n\nMinimum 10 years experience in relevant position in a sizeable company\nHR experience is ideal\nStrong English and Mandarin\nOutgoing and with strong interpersonal and communication skills\nOrganized, independent, customer-oriented and able to work under pressure\n\nOffer\n\n35-37k/month x 13\nDiscretionary bonus\nReputable and stable HK company\nTuen Mun office (5 mins from MTR)\n\nContact Jenny Yuen on (852) 3103 4362 or APPLY NOW by clicking the button below\n\nwww.ambition.com.hk\n\nData provided is for recruitment purposes only\n\nIf this job isn't quite right for you, but you know someone who would be great at this role, why not take advantage of our referral scheme? We offer HKD1000 in Apple gift cards for every referred candidate who we place in a role. Terms & Conditions Apply. https://www.ambition.com.hk/refer-a-friend", "employment_types": ["Full Time", "Permanent"], "selling_points": ["Support CHRO (expat)", "Stable and sizable company", "Good English"], "locations": ["Tuen Mun Area"], "categories": ["Admin & HR", "Administration / Operation Manager", "Personal / Executive Assistant", "Others"], "post_time": "2022-01-10T08:44:17Z", "salary": {"currency": null, "max": null, "min": null, "period": "monthly", "term": null}, "salary_visible": false, "title_keywords": ["executive assistant"], "responsibilities": ["administrative support", "data", "hr", "communication", "scheduling", "recruitment", "contact", "travel arrangement", "work under pressure"], "requirements": {"degrees": [], "majors": [], "languages": ["english", "mandarin"], "language_level": [], "hard_skills": ["scheme"], "soft_skills": ["outgoing", "communication skills", "organized", "independent", "work under pressure", "customer-oriented", "stable", "interpersonal", "ideal"], "languages_combined": [{"language": "english", "language_level": []}, {"language": "mandarin", "language_level": []}]}, "experience_required": {"duration": ["minimum 10 years"], "field": ["hr"]}}, {"job_id": "100003009048068", "location_code": "hk", "company": "A&A Limited", "job_title": "Account & Administrative Executive", "description": "Responsibilities:\n\nPerform daily accounting operations, such as account payable/receivable, cash management and expenses\nResponsible for general HR functions such as payroll calculation, MPF,\u00a0employee compensation,\u00a0attendance, recruitment, etc.\nResponsible for general office administration, such as office supplies, office renovation, repair & maintenance of facilities, handle payment and update reports\nResponsible for daily data input and ad hoc assignments\nImmediately available is preferred\n\nRequirements:\n\nHigher Diploma or above in related discipline\nSelf-driven with supportive and positive mentality and attitude\nIndependent, well-organized, attentive to details and accountability\nWillingness to learn and adapt to the fast-growing digital industry\nProficiency in Excel, Words and Chinese Word Processing\nExcellent communication skill in both Cantonese and English\n\n\u00a0Benefits we offer:\n\n5 days\u2019 work\nFlexible working hours\nMedical Insurance\nPerformance Bonus\nOvertime meal and transportation allowance\nFun, young and joyful work environment with many social activities", "employment_types": ["Full Time"], "selling_points": ["Daily Account & Administrative operations", "Organized, accurate, detailed, multi-tasking", "5 days' work"], "locations": ["Kwun Tong"], "categories": ["Accounting", "Accounting Clerk / Supervisor", "Admin & HR", "Personal / Executive Assistant", "HR Supporting Staff"], "post_time": "2022-01-14T04:39:30Z", "salary": {"currency": null, "max": null, "min": null, "period": "monthly", "term": null}, "salary_visible": false, "title_keywords": ["administrative executive"], "responsibilities": ["attendance", "management", "mpf", "maintenance", "office supplies", "office administration", "hr", "expenses", "renovation", "daily accounting operations", "data input", "repair", "payment", "recruitment", "reports", "ad hoc assignments", "payroll"], "requirements": {"degrees": ["higher diploma or above"], "majors": [], "languages": ["cantonese", "english", "chinese"], "language_level": ["proficiency", "excellent"], "hard_skills": ["excel", "chinese word processing", "words"], "soft_skills": ["supportive", "positive mentality", "independent", "attentive to details", "accountability", "communication skill", "well-organized", "driven"], "languages_combined": [{"language": "cantonese", "language_level": ["excellent"]}, {"language": "english", "language_level": ["excellent"]}, {"language": "chinese", "language_level": ["proficiency"]}]}, "experience_required": {"duration": [], "field": []}}, {"job_id": "100003009044157", "location_code": "hk", "company": "David James Recruitment Limited", "job_title": "Accounting Team Secretary \u2013 Financial Services Institute (HK$30 \u2013 35K)", "description": "Our client is a sizable and well-established global financial services company with a stable and friendly accounting team of Asia Pacific in Hong Kong. To replace the existing team mate who is having internal promotion, they are currently hiring a responsible and experienced talent for the team secretary / executive assistant role.\n\nResponsibilities:\n\nReporting to CFO, you will be supporting a team of 5-6 including the Financial Controller and Accountants\nAnswering phone calls and taking messages\nArranging meetings and business trips for the team\nConsolidating accounting reports by using MS Excel\nPreparing expenses claims reports\nCommunicating with other departments including global offices\nPreparing Power Point presentation and meeting agenda for CFO\u2019s meetings and conferences\nClerical support such as filing and scanning documents\nOrganize CSR events and activities for the team\nAd hoc team administrative support\n\nRequirements:\n\nDegree holder (preferably major in accounting) with not less than 3 years team administrative support work experience\nExperience with bank/fund house/investment firm/global business consulting firm/ MNC is highly preferred\nGood understanding of MS Excel usage including pivot table is a MUST\nGood command of both written and spoken English required\nGood team player with can-do attitude and coordination skill", "employment_types": ["Full Time", "Permanent"], "selling_points": ["1yr renewable contract with high chance to be perm", "Friendly, stable and multi-cultural environment", "All-rounded team administrative work"], "locations": ["Central"], "categories": ["Admin & HR", "Personal / Executive Assistant", "Secretary", "Banking / Finance", "Others"], "post_time": "2022-01-13T03:14:55Z", "salary": {"currency": null, "max": null, "min": null, "period": "monthly", "term": null}, "salary_visible": false, "title_keywords": ["team secretary", "accounting"], "responsibilities": ["scanning", "reporting", "ad hoc", "administrative support", "expenses", "clerical support", "conferences", "communicating with", "reports", "phone calls"], "requirements": {"degrees": ["degree holder"], "majors": ["accounting"], "languages": ["english"], "language_level": ["good command"], "hard_skills": ["pivot table", "ms excel"], "soft_skills": ["good team player", "coordination skill", "can-do attitude"], "languages_combined": [{"language": "english", "language_level": ["good command"]}]}, "experience_required": {"duration": ["3 years"], "field": ["consulting", "administrative", "business", "investment", "accounting", "team"]}}, {"job_id": "100003009045156", "location_code": "hk", "company": "P3 Impex Limited", "job_title": "Office Administrative Assistant", "description": "Job Description:\u00a0\n\nResponsibilities:\n\nProvide full range of Administrative duties with respect to smooth functioning of office.\nPrepare Import / Export declarations\nOrder Stationery ,Furniture & fixtures.\nHandle Filing and documentation\nManage lease contracts .\nLiase with banks on a daily basis\nAssist in other ad-hoc assignments\n\nTo be successful in this role, you will need to have :\n\nHigher Diploma / Degree holder in any discipline\nAt least 2-3 years of relevant working experience.\u00a0\nProficient in Cantonese, Mandarin and English\nProficient in MS office, Excel.\nStrong sense of integrity, responsible and able to meet tight deadlines with high accuracy\nInitiative, self- motivated, well organized and be a good team player\nImmediately available is highly preferred\nImmediate available or short notice is preferred", "employment_types": ["Full Time", "Contract"], "selling_points": [], "locations": ["Hung Hom"], "categories": ["Admin & HR", "Administration / Operation Manager", "Clerical / Admin Staff", "Personal / Executive Assistant"], "post_time": "2022-01-13T07:20:03Z", "salary": {"currency": null, "max": null, "min": null, "period": "monthly", "term": null}, "salary_visible": false, "title_keywords": ["administrative assistant"], "responsibilities": ["contracts", "ad-hoc assignments", "stationery", "administrative duties", "documentation"], "requirements": {"degrees": ["diploma", "degree holder"], "majors": [], "languages": ["cantonese", "english", "mandarin"], "language_level": ["proficient"], "hard_skills": ["documentation", "excel", "ms office"], "soft_skills": ["meet tight deadlines", "good team player", "responsible", "integrity", "well organized", "motivated", "smooth", "initiative"], "languages_combined": [{"language": "cantonese", "language_level": ["proficient"]}, {"language": "english", "language_level": ["proficient"]}, {"language": "mandarin", "language_level": ["proficient"]}]}, "experience_required": {"duration": ["at least 2-3 years"], "field": ["relevant working experience"]}}, {"job_id": "100003009043443", "location_code": "hk", "company": "KOS International Limited", "job_title": "Senior Admin Officer - Secretarial Support", "description": "About Our Client\n\nOur client is a leading organisation in Hong Kong and currently looking for a Senior Admin Officer to provide secretarial support to group senior executives and a small team.\n\nAbout The Role\n\nProvide business support the group executives on a daily basis\nData consolidation and prepare marketing analysis reports, research and contribute necessary recommendations\nMaintain calendar and meeting schedules of the executives in a timely and professional manner with internal and external parties\nResponisble for meeting arrangement, drafting meeting agenda, preparing meeting materials, minutes, reports, PowerPoint presentation and take respective follow-up actions\nCoordinate with internal and external parties to ensure all assigned tasks are on-track\nAssist with ad hoc activities if needed\n\nThe Successful Applicant\n\nDegree holder with a minimum of 3 years experience as Executive Assistant\nExcellent command in English and Chinese\nProficient in using Microsoft Outlook, Word, Excel, PowerPoint\nFast paced and dynamic, able to work independently and be detail-oriented\nGood stakeholder management skills\nExcellent communication, interpersonal skills, able to work in a fast-paced environment.\n\nClick \"Apply Now\" to apply for this position or call Christy Cheng at +852 3180 4946 for a confidential discussion. All information collected will be kept in strict confidence and will be used for recruitment purpose only.", "employment_types": ["Full Time", "Permanent"], "selling_points": ["Expats boss, excellent command of English", "Secretarial support to a small team", "Competitive Salary and Benefits"], "locations": ["Not Specified"], "categories": ["Admin & HR", "Clerical / Admin Staff", "Personal / Executive Assistant", "Secretary"], "post_time": "2022-01-12T11:55:38Z", "salary": {"currency": null, "max": null, "min": null, "period": "monthly", "term": null}, "salary_visible": false, "title_keywords": ["officer", "admin"], "responsibilities": ["management", "ad hoc", "data", "analysis reports", "schedules", "internal and external parties", "professional manner", "coordinate with", "communication", "maintain", "reports", "secretarial support", "recruitment"], "requirements": {"degrees": ["degree holder"], "majors": [], "languages": ["english", "chinese"], "language_level": ["excellent"], "hard_skills": ["small", "excel", "analysis", "word", "powerpoint", "dynamic", "outlook"], "soft_skills": ["work independently", "confidence", "fast-paced environment", "timely", "detail-oriented", "communication", "dynamic", "interpersonal skills", "organisation", "presentation"], "languages_combined": [{"language": "english", "language_level": ["excellent"]}, {"language": "chinese", "language_level": ["excellent"]}]}, "experience_required": {"duration": ["minimum of 3 years"], "field": []}}, {"job_id": "100003009043943", "location_code": "hk", "company": "The Hongkong Electric Co., Ltd", "job_title": "Assistant Officer (Administration) (Ref: TND-CM-AO-JD)", "description": "Responsibilities:\n\n\n\nReporting to the Chief Construction & Maintenance Engineer (Central), the appointee will mainly perform the following responsibilities:\n\nTo provide general administrative support including handling correspondences, excavation permit and leave administration, etc.\nTo perform document filing and coordinate report submission\nTo update records in various systems\nTo maintain fixed asset records and handle procurement of assets\n\nRequirements:\n\nHigher Diploma / Certificate in Business Administration or related disciplines\nA minimum of 2 years\u2019 relevant work experience\nExperience in handling application of excavation permits an advantage\nBasic knowledge in ISO 9001, ISO 1400, ISO 55001 and ISO 18001 an advantage\nProficient in Microsoft applications such as Word, Excel, PowerPoint, Sharepoint etc. and Chinese typing\nGood command of English and Chinese languages, both spoken and written\n\nWorking Location: Ap Lei Chau, transportation to be provided\n\nCandidate with more experience with lower qualification will be considered\n\nThis is a 1-year contract position. The renewal of contract is subject to the Company's business needs and performance of the individual.\n\nApplication:\n\nIf you are interested in this position, please send your resume (in PDF format)\u00a0with details of qualification, experience, present and expected salaries and contact number to the Human Resources Division, The Hongkong Electric Co., Ltd. on or before 27 January 2022\u00a0and quote the reference number in your application.\u00a0 Please also visit our website to know more about our company http://www.hkelectric.com.\n\nApplicants not invited for interview within one month from the closing date may consider their applications unsuccessful.\u00a0 All unsuccessful applications will be kept for six months after the date of this advertisement.\n\nWe are an equal opportunity employer.\u00a0 Personal data provided by job applicants will be treated in strictest confidence and used only for recruitment-related purposes in accordance with the laws and ordinance of the HKSAR.", "employment_types": ["Full Time", "Contract"], "selling_points": ["Provide general administrative support", "Higher Diploma/Certificate in Business Admin", "Minimum of 2 years\u2019 relevant work experience"], "locations": ["Aberdeen"], "categories": ["Admin & HR", "Clerical / Admin Staff", "Personal / Executive Assistant", "Others"], "post_time": "2022-01-13T02:32:51Z", "salary": {"currency": null, "max": null, "min": null, "period": "monthly", "term": null}, "salary_visible": false, "title_keywords": ["assistant officer"], "responsibilities": ["reporting", "document filing", "maintenance", "general administrative support", "systems", "coordinate", "maintain", "report", "administration"], "requirements": {"degrees": ["certificate", "diploma"], "majors": ["related disciplines", "business administration"], "languages": ["english", "chinese"], "language_level": ["good command"], "hard_skills": ["ap", "excel", "basic", "microsoft applications", "word", "powerpoint", "typing"], "soft_skills": ["interested in", "confidence"], "languages_combined": [{"language": "english", "language_level": ["good command"]}, {"language": "chinese", "language_level": ["good command"]}]}, "experience_required": {"duration": ["minimum of 2 years"], "field": ["human resources"]}}, {"job_id": "100003009035374", "location_code": "hk", "company": "PressLogic Limited", "job_title": "Executive Assistant to CEO", "description": "Responsibilities:\n\nPerform general company secretarial duties;\nProvide administrative support to CEO as personal assistant;\nManage business correspondence, minutes, meeting agenda, mails, emails, telephone calls, document filling and other administrative duties;\nHandle full set of company statutory records including but not limited to preparing minutes, statutory returns and filings;\nLiaise with internal and external parties on business issues independently;\nProactively take part in marketing roles which includes but not limited to marketing activities;\nDraft English and Chinese correspondences, emails, memo, presentations and reports;\nRequire to perform outdoor activities and communicate with different parties for project reviews and tracking reports;\nManage sensitive and confidential information with discretion and diplomacy\nOrganize and coordinate various projects, events and/or activities; and\u00a0\nAssist in various operations and/or ad-hoc project as assigned\n\nRequirements:\n\n\nUniversity degree with formal secretarial training is preferred\n3-5 years\u2019 solid experience in serving C-level or top management\nCandidate with experience working in Technology, Professional Services or Marketing a plus\nMature, responsible, trustworthy\nDetailed oriented, organized, calm, productive and adaptive\nSelf-motivated and loyal, with strong sense of commitment\nAble to work in a fast-paced and flexible environment\nAbility to manage sensitive and confidential information with discretion and diplomacy is a must\nExcellent interpersonal and communication skills as well as active listening skill\nProficiency in MS Office and Chinese Word Processing\nExcellent spoken and written English, Cantonese and Mandarin\n\nWe Offer:\n\n5 Days work\nFlexible Working Hour\nBirthday Leave & Anniversary Leave\nMedical Coverage\nFun, young and joyful office environment\u00a0\n\nInterested candidates, please email full resume with 1.) EXPECTED SALARY 2.) AVAILABILITY 3.) WORK REFERENCE\u00a0 to the HR department by clicking 'Apply Now'.\n\nFor company information, please refer to the website http://www.presslogic.com/.\n\nAll information received will be kept in strict confidence and only for employment-related purposes.", "employment_types": ["Full Time", "Permanent"], "selling_points": ["Full Spectrum of Secretarial Service to CEO", "Proactively take part in marketing role", "Assist in various operations and ad-hoc project"], "locations": ["Lai Chi Kok"], "categories": ["Admin & HR", "Personal / Executive Assistant", "Secretary", "Professional Services", "Company Secretary"], "post_time": "2022-01-10T06:57:51Z", "salary": {"currency": null, "max": null, "min": null, "period": "monthly", "term": null}, "salary_visible": false, "title_keywords": ["executive assistant to ceo"], "responsibilities": ["communicate with", "ad-hoc", "memo", "operations", "internal and external parties", "presentations", "coordinate", "liaise with", "administrative duties", "reports", "provide administrative support", "tracking"], "requirements": {"degrees": ["university degree"], "majors": [], "languages": ["cantonese", "english", "chinese", "mandarin"], "language_level": ["proficiency", "excellent"], "hard_skills": ["plus", "c", "chinese word processing", "ms office"], "soft_skills": ["productive", "organized", "self-motivated", "flexible", "detailed oriented", "communication skills", "trustworthy", "responsible", "mature", "calm", "loyal", "active", "interpersonal", "sensitive"], "languages_combined": [{"language": "cantonese", "language_level": ["excellent"]}, {"language": "english", "language_level": ["excellent"]}, {"language": "chinese", "language_level": ["proficiency"]}, {"language": "mandarin", "language_level": ["excellent"]}]}, "experience_required": {"duration": ["3-5 years"], "field": ["management", "marketing"]}}, {"job_id": "100003009047368", "location_code": "hk", "company": "Hong Kong Ming Wah Shipping Company Limited", "job_title": "Officer / Deputy Officer, Human Resources Department \u4eba\u529b\u8cc7\u6e90\u90e8\u4e3b\u7ba1 / \u526f\u4e3b\u7ba1", "description": "Responsibilities:\n\nManage full spectrum of human resources functions including recruitment and selection, training and development, employee relations, compensation and benefits administration, payroll, performance appraisal, etc.;\nWork closely with various departments on manpower planning and budget management;\nImplement HR strategies to meet company targets and requirements;\nTo be responsible for preparation of statistical and management reports; and\nHandle other ad hoc projects.\n\nRequirements:\n\nDegree in Human Resources Management or related discipline\nMinimum 5 years of working experience preferable in sizable organizations or listed companies\nPossess good knowledge of the Mainland Labour Ordinance and HK Employment Ordinance\nGood command of both spoken and written English and Chinese, strong proficiency in Putonghua is a MUST\nGood analytical mind and ability to multi-task independently under high pressure\nProficient in Microsoft Office applications (Word, Excel, PowerPoint, Power BI)\n\nApplicants with less working experience will also be considered as Deputy Officer, Human Resources Department.\n\nWe offer 5 days work, 13 months salaries, bank holiday and competitive remuneration package to the right candidates. Interested parties please provide your English and Chinese version CV by clicking apply now\n\n**Personal data collected would be used for recruitment related purpose only**", "employment_types": ["Full Time", "Permanent"], "selling_points": ["Performance Bonus, Double Pay", "Holiday Benefits, Meal Allowance", "Excellent Prospects for Promotion"], "locations": ["Sheung Wan"], "categories": ["Admin & HR", "Clerical / Admin Staff", "Personal / Executive Assistant", "HR Supporting Staff"], "post_time": "2022-01-14T02:55:32Z", "salary": {"currency": null, "max": null, "min": null, "period": "monthly", "term": null}, "salary_visible": false, "title_keywords": ["officer", "human resources"], "responsibilities": ["administration", "management", "hr", "budget", "management reports", "recruitment", "ad hoc projects", "payroll", "human resources functions", "planning"], "requirements": {"degrees": ["degree"], "majors": [], "languages": ["putonghua", "english", "chinese"], "language_level": ["proficiency", "good command"], "hard_skills": ["excel", "bi", "microsoft office", "word", "powerpoint"], "soft_skills": ["analytical mind", "multi-task", "independently"], "languages_combined": [{"language": "putonghua", "language_level": ["proficiency", "good command"]}, {"language": "english", "language_level": ["good command"]}, {"language": "chinese", "language_level": ["good command"]}]}, "experience_required": {"duration": ["minimum 5 years"], "field": ["human resources"]}}, {"job_id": "100003009040218", "location_code": "hk", "company": "Chinese Estates Holdings Limited", "job_title": "Secretary", "description": "Provide full spectrum of secretarial support to senior executive\nManage calendar, arrange business meetings and daily appointments\nHandle memo, reports, news clippings and other documents\nProvide administrative and clerical support to marketing department\nHandle ad hoc projects or duties as assigned\nRequirements:\n\nDegree holder in any discipline, preferably with formal secretarial training\nAt least 3 years' relevant experience, preferably in sizeable organization\nExperience in serving senior management\nMeticulous, well-organized, reliable and able to work independently\nMature, self-motivated with excellent interpersonal and communication skills\nGood command of both written and spoken English and Chinese. Mandarin in advantage.\nProficient in MS Word, Excel, Chinese Word Processing and PowerPoint\nImmediate available is an advantage\nAttractive compensation package including competitive salary, up to 22 days Annual Leave and 5 days work as well as excellent career prospects will be offered. Interested parties please send full resume including your present and expected salaries by clicking \"Apply Now\".\n\n(Personal data collected would be used in accordance with our Statement on Employment-Related Data Usage, which is available at http://www.chineseestates.com or upon request made to the Company\u2019s Human Resources Manager. Applicants who are not invited for interview within six weeks may consider their applications unsuccessful. All personal data of unsuccessful candidates will be destroyed after six months.)", "employment_types": ["Full Time", "Permanent"], "selling_points": ["3 yrs exp, preferably in sizeable organization", "Experience in serving senior management", "Meticulous,well-organized,mature & self-motivated"], "locations": ["Causeway Bay"], "categories": ["Admin & HR", "Clerical / Admin Staff", "Personal / Executive Assistant", "Secretary"], "post_time": "2022-01-12T01:55:15Z", "salary": {"currency": null, "max": null, "min": null, "period": "monthly", "term": null}, "salary_visible": false, "title_keywords": ["secretary"], "responsibilities": ["memo", "communication", "ad hoc projects", "reports", "secretarial support", "administrative and clerical support", "senior management"], "requirements": {"degrees": ["degree holder"], "majors": [], "languages": ["english", "chinese", "mandarin"], "language_level": ["advantage", "good command", "proficient"], "hard_skills": ["excel", "chinese word processing", "powerpoint", "ms word"], "soft_skills": ["meticulous", "work independently", "self-motivated", "communication skills", "well-organized", "mature", "reliable", "interpersonal"], "languages_combined": [{"language": "english", "language_level": ["good command"]}, {"language": "chinese", "language_level": ["good command", "proficient"]}, {"language": "mandarin", "language_level": ["advantage"]}]}, "experience_required": {"duration": ["at least 3 years"], "field": ["management", "relevant experience"]}}, {"job_id": "100003009050978", "location_code": "hk", "company": "Vocational Training Council", "job_title": "Term Executive Assistant II", "description": "School for Higher and Professional Education (SHAPE)\nRef. no : O/SHAPE_CW_ST/Term_EA2/12/21\nThe School for Higher and Professional Education (SHAPE) is a self-financed arm of the Vocational Training Council (VTC).\u00a0 It offers top-up bachelor degree programmes to VTC\u2019s Higher Diploma graduates and other sub-degree holders in collaboration with overseas universities.\u00a0 Applications are now invited for Term Executive Assistant II post at SHAPE.\nMajor Duties:\n(a) \u00a0\u00a0 \u00a0To provide support in one or more of the following areas:\n\u00a0 \u00a0\u00a0 \u00a0(i) \u00a0\u00a0 \u00a0general / course administration;\n\u00a0 \u00a0\u00a0 \u00a0(ii) \u00a0\u00a0 \u00a0student affairs and student admissions;\n\u00a0 \u00a0\u00a0 \u00a0(iii) \u00a0\u00a0 \u00a0supplies and stores administration;\n\u00a0 \u00a0\u00a0 \u00a0(iv) \u00a0\u00a0 \u00a0human resources administration;\n\u00a0 \u00a0\u00a0 \u00a0(v) \u00a0\u00a0 \u00a0course promotion or event organisation; and\n\u00a0 \u00a0\u00a0 \u00a0(vi) \u00a0\u00a0 \u00a0data input and filing duties;\n(b) \u00a0\u00a0 \u00a0To assist in website maintenance; and\n(c) \u00a0\u00a0 \u00a0To draft simple correspondence and handle enquiries.\nRequirements:\n(a) \u00a0\u00a0 \u00a0(i) \u00a0\u00a0 \u00a05 subjects in the Hong Kong Certificate of Education Examination (HKCEE) at Grade E / Level 2 or above, including English Language (Syllabus B)*, Chinese Language and Mathematics, or equivalent; OR\n\u00a0 \u00a0\u00a0 \u00a0(ii) \u00a0\u00a0 \u00a0A combination of results in 5 subjects in the Hong Kong Diploma of Secondary Education (HKDSE) Examination at Level 2 or above in New Senior Secondary subjects / \u201cAttained\u201d or above in Applied Learning subjects / Grade E or above in Other Language subjects; and the 5 subjects should include English Language*, Chinese Language and Mathematics; OR\n\u00a0 \u00a0\u00a0 \u00a0(iii) \u00a0\u00a0 \u00a0A recognised Certificate / Diploma / Foundation Diploma / Foundation Certificate, or Project Yi Jin;\n* \u00a0\u00a0 \u00a0Completion of Hong Kong Vocational English Programme (HKVEP) at Level 2 / Passing 5 specific VTC\u2019s Vocational English Module Certificates is considered an alternative qualification.\n(b) \u00a0\u00a0 \u00a0Proficiency in computer software application, including MS Word, MS Excel, MS PowerPoint, MS Teams and Chinese word processing;\n(c) \u00a0\u00a0 \u00a0Good communication, interpersonal and organisation skills;\n(d) \u00a0\u00a0 \u00a0Detail-minded, able to work independently and be a good team player;\n(e) \u00a0\u00a0 \u00a0Good command of both spoken and written English and Chinese, fluency in Putonghua is definitely an advantage;\n(f) \u00a0\u00a0 \u00a0Candidates who possess knowledge / skills in Adobe software, e.g. Illustrator and Photoshop would have an advantage; and\n(g) \u00a0\u00a0 \u00a0Preference will be given to applicants with relevant work experience.\nNotes:\n(1) \u00a0\u00a0 \u00a0The appointee(s) may be initially posted to one of the SHAPE Offices located at Chai Wan or Sha Tin.\n(2) \u00a0\u00a0 \u00a0Shortlisted applicants will be required to attend a Computer Skills Test (CST) including document formatting, English and Chinese typing, and use of spreadsheet.\n(3) \u00a0\u00a0 \u00a0The appointee(s) may be required to perform duties outside normal office hours and/or work on shift duty.\nApplication Procedures:\nA completed application form [VTC-1 (Rev. Rev. 1/2018)], together with a full curriculum vitae, should be sent to the School for Higher and Professional Education (Central Office), Room S604, Lee Wai Lee Building, 30 Shing Tai Road, Chai Wan, Hong Kong.\u00a0 Please specify on the envelope the reference of the post being applied for.\nClosing date for application: 7 February 2022\nApplicants not invited for interview within 10 weeks from the closing date may consider their applications unsuccessful.\nThe Council reserves the right not to fill the post(s).\nPersonal data collected will be used for recruitment purposes only. Information on unsuccessful candidates will normally be destroyed 12 months after the completion of the recruitment exercise.", "employment_types": ["Full Time"], "selling_points": ["To assist in website maintenance", "To draft simple correspondence", "To provide support in one or more"], "locations": ["Not Specified"], "categories": ["Admin & HR", "Clerical / Admin Staff", "Personal / Executive Assistant", "Others"], "post_time": "2022-01-14T12:27:08Z", "salary": {"currency": null, "max": null, "min": null, "period": "monthly", "term": null}, "salary_visible": false, "title_keywords": ["executive assistant"], "responsibilities": ["provide support", "website maintenance", "data input", "handle enquiries", "administration"], "requirements": {"degrees": ["certificate", "diploma", "hkdse", "secondary education"], "majors": ["mathematics"], "languages": ["putonghua", "english", "chinese"], "language_level": ["fluency", "advantage", "proficiency", "good command"], "hard_skills": ["chinese word processing", "illustrator", "typing", "ms excel", "c", "adobe software", "photoshop", "computer skills", "ms powerpoint", "wan", "spreadsheet", "ms word"], "soft_skills": ["detail-minded", "work independently", "good team player", "perform duties", "communication", "learning", "organisation", "interpersonal"], "languages_combined": [{"language": "putonghua", "language_level": ["fluency", "advantage", "good command"]}, {"language": "english", "language_level": ["advantage", "good command"]}, {"language": "chinese", "language_level": ["advantage", "proficiency", "good command"]}]}, "experience_required": {"duration": [], "field": []}}, {"job_id": "100003009035108", "location_code": "hk", "company": "ASM Global", "job_title": "Executive Assistant", "description": "Department\u00a0: Executive Office\n\nReports to\u00a0: Executive Director\n\nRole Introduction\nProvide administrative support to the Executive Director and Directors, collectively the \u2018Senior Management Team\u2019.\n\n\nKey Responsibilities\n\n\nProvide full spectrum of secretarial and administrative support to Senior Management Team\nImplement effective, professional communication and liaison skills as the first point of contact \u00a0\nManage diaries including scheduling appointments and meetings\nCoordinate meetings including room bookings, specific equipment requirements, refreshments, organising of documents e.g. agendas, reports, minutes etc. and taking of minutes if required\nCoordinate and book travel arrangements\nPrepare correspondence, briefing packs, reports, itineraries and presentations\nSupport the Senior Management Team when preparing reviews and updates to business plan and budget\nHelp plan company event and employee team building activities or social projects\nSet up and implement document control systems\nHandle general administrative duties, such as expenses claim, documentation, etc.\nCoordinate with international office, internal staff and external parties to ensure effective communication\nAssist in any ad-hoc projects as assigned by the Senior Management Team\n\nRequirements\n\nUniversity degree holder with minimum 3 years\u2019 relevant experience in a fast-paced and dynamic environment,\nMinimum 3 years recent experience in a similar role\nFormal secretarial training preferred\nMature, well-organized, strong interpersonal, communication and problem-solving capability\nAble to handle and prioritize multiple tasks independently as well as work under pressure\nStrong knowledge of Microsoft Word, PowerPoint & Excel and Chinese Word Processing\nGood command of spoken and written Chinese and English, including Putonghua\nMeticulous and gives attention to details\nInterested parties please send full resume with current salary, expected salary and availability by clicking 'Apply Now'.\n\n\nPersonal & Application Information\n\nWe are an equal opportunity employer. Data collected will be treated in strict confidence and used for recruitment purpose only. Applicants who are not invited for interviews within 4 weeks may consider their applications unsuccessful.", "employment_types": ["Full Time", "Permanent"], "selling_points": ["Degree holder with good communication skills", "Administrative support & coordination", "Good writing and presentation skills"], "locations": ["Kowloon City"], "categories": ["Admin & HR", "Administration / Operation Manager", "Clerical / Admin Staff", "Personal / Executive Assistant"], "post_time": "2022-01-10T06:01:34Z", "salary": {"currency": null, "max": null, "min": null, "period": "monthly", "term": null}, "salary_visible": false, "title_keywords": ["executive assistant"], "responsibilities": ["travel arrangements", "budget", "external parties", "communication", "plan", "senior management", "ad-hoc projects", "control", "expenses", "presentations", "reports", "business plan", "administrative support", "coordinate with", "scheduling", "administrative duties", "contact", "documentation", "systems", "diaries", "coordinate"], "requirements": {"degrees": ["university degree"], "majors": [], "languages": ["putonghua", "english", "chinese"], "language_level": ["good command"], "hard_skills": ["excel", "microsoft word", "chinese word processing", "problem-solving", "powerpoint", "dynamic"], "soft_skills": ["meticulous", "dynamic environment", "independently", "multiple tasks", "problem-solving", "well-organized", "mature", "prioritize", "communication", "attention to details", "interpersonal", "work under pressure"], "languages_combined": [{"language": "putonghua", "language_level": ["good command"]}, {"language": "english", "language_level": ["good command"]}, {"language": "chinese", "language_level": ["good command"]}]}, "experience_required": {"duration": ["minimum 3 years"], "field": ["relevant experience"]}}, {"job_id": "100003009034505", "location_code": "hk", "company": "", "job_title": "Personal Assistant /Junior Secretary", "description": "Job Description\nSupport senior executive and his family of five, including 3 children aged 5-10\n\nResponsibilities\n\nSupport senior executive\u2019s personal matters including calendar management, family trip, travel arrangement etc\u2026\nOversee children's schedules including school-related and extra-curricular activities, liaise with teachers and coaches,\nSupervise domestic helpers and driver to co-ordinate schedules.\nHandle house maintenance and renovations.\nManage general household administration, including bills, correspondence, license and insurance renewals.\nGeneral secretarial support in office for senior executive.\n\n\nJob requirements\n\nDetail-minded and patient with tedious work\nPleasant, enjoy working with children.\nHigh level of integrity.\nEnergetic and positive attitude; organized and able to multi-task. Languages: spoken and written Chinese (Cantonese or Mandarin) and English.\nWork location : based in office in Central, outdoor work occasionally.\n\n\nRemunerations:\n\u00a0For interested parties, please contact us at 31966253 for company details before applying.\n\nPersonal data collected is for recruitment purpose only.\n", "employment_types": ["Full Time", "Permanent"], "selling_points": [], "locations": ["Central"], "categories": ["Admin & HR", "Personal / Executive Assistant"], "post_time": "2022-01-10T03:32:21Z", "salary": {"currency": null, "max": null, "min": null, "period": "monthly", "term": null}, "salary_visible": false, "title_keywords": ["personal assistant", "junior secretary"], "responsibilities": ["management", "maintenance", "schedules", "secretarial support", "travel arrangement", "liaise with", "insurance", "administration"], "requirements": {"degrees": [], "majors": [], "languages": ["cantonese", "english", "chinese", "mandarin"], "language_level": [], "hard_skills": [], "soft_skills": ["detail-minded", "organized", "multi-task", "enjoy working", "integrity", "pleasant", "positive attitude", "patient", "energetic"], "languages_combined": [{"language": "cantonese", "language_level": []}, {"language": "english", "language_level": []}, {"language": "chinese", "language_level": []}, {"language": "mandarin", "language_level": []}]}, "experience_required": {"duration": [], "field": []}}, {"job_id": "100003009039496", "location_code": "hk", "company": "", "job_title": "Event Assistant", "description": "Responsibilities:\n\nPlanning and organizing of a diverse range of events (e.g. Birthday Party, Artist\u2019s Events, VIP dinners etc.)\nAssist for family support\nHandle personal matters and ad hoc assignment\nResponsible for property and facilities management and maintenance, renovation, worker recruitment if necessary\n\nRequirement:\n\nDegree Holder, Oversea graduates are welcomed\nMinimum 3 years of working experience\nOutgoing, detail-oriented, independent and pleasant personality\nExcellent command of both written and spoken English and Chinese (Cantonese & Mandarin)\nExcellent interpersonal and communication skills\nA good team player with proactive working attitude and positive thinking\n\nAttractive remuneration package will be offered to the suitable candidates. All personal data collected will be used for recruitment purpose only. Should you have any queries,please contact Ms Au at 2895 9936 for further information.", "employment_types": ["Full Time", "Permanent"], "selling_points": [], "locations": ["Wan Chai"], "categories": ["Admin & HR", "Personal / Executive Assistant", "Secretary", "Marketing / Public Relations", "Public Relations - Event Management"], "post_time": "2022-01-11T09:55:53Z", "salary": {"currency": null, "max": null, "min": null, "period": "monthly", "term": null}, "salary_visible": false, "title_keywords": ["event assistant"], "responsibilities": ["management", "maintenance", "ad hoc assignment", "renovation", "recruitment", "planning"], "requirements": {"degrees": ["degree holder"], "majors": [], "languages": ["cantonese", "english", "chinese", "mandarin"], "language_level": ["excellent"], "hard_skills": [], "soft_skills": ["outgoing", "communication skills", "good team player", "independent", "positive thinking", "pleasant", "detail-oriented", "proactive", "interpersonal"], "languages_combined": [{"language": "cantonese", "language_level": ["excellent"]}, {"language": "english", "language_level": ["excellent"]}, {"language": "chinese", "language_level": ["excellent"]}, {"language": "mandarin", "language_level": ["excellent"]}]}, "experience_required": {"duration": ["minimum 3 years"], "field": []}}, {"job_id": "100003009044727", "location_code": "hk", "company": "Asia Elite Consultancy", "job_title": "\u4fdd\u55ae\u8ddf\u9032\u54e1", "description": "We are helping our clients to recruit different position in different industry.\nBelow are the job details\n-------------------------------------------------------------\n\u4fdd\u55ae\u8ddf\u9032\u54e1(\u5168\u8077/\u517c\u8077)\n\n\u53c3\u8207\u914d\u5408\u5718\u968a\u767c\u5c55\u53ca\u6d3b\u52d5\n\u4e00\u822c\u79d8\u66f8\u5de5\u4f5c, \u63d0\u4f9b\u884c\u653f\u652f\u63f4, \u652f\u63f4\u7ba1\u7406\u4eba\u54e1\u7684\u65e5\u5e38\u5de5\u4f5c, \u540c\u6642\u5354\u52a9\u8655\u7406\u548c\u89e3\u7b54\u5ba2\u6236\u67e5\u8a62\n\u6574\u7406\u65e5\u5e38\u6587\u4ef6\u53ca\u5831\u544a\n\u8ddf\u9032\u5ba2\u4eba\u4fdd\u55ae\n\n\u8981\u6c42:\n\n\u6b61\u8fce\u4efb\u4f55\u5728\u8077\u5728\u5b78\u4eba\u58eb\uff0c\u5927\u5c08/\u5927\u5b78/\u61c9\u5c48DSE\u7562\u696d\u751f\n\u61c2\u7528\u96fb\u8166\u6587\u66f8\u8655\u7406, Mirosoft Office, MS PowerPoint, MS Excel\n\u5f48\u6027\u5de5\u4f5c(\u5168\u8077/\u517c\u8077)\n\n\u6709\u8208\u8da3\u8005\u8acb\u7db2\u4e0a\u7533\u8acb/WhatsApp\u81f391692458\uff08\u674e\u751f\uff09\n\n\nInterested parties please click \"Apply Now\" online or contact Mr. Lee at 91692458(WhatsApp) for application enquiry.\n\nWe are an equal opportunity employer who welcomes application from all qualified candidates. The information provided will be treated in strict confidence and used only for recruitment purposes.\u00a0", "employment_types": ["Full Time", "Part Time", "Permanent", "Temporary", "Contract", "Internship", "Freelance"], "selling_points": ["Part Time/ Full Time", "Welcome fresh grad", "Internship"], "locations": ["Not Specified"], "categories": ["Admin & HR", "Personal / Executive Assistant", "Sales, CS & Business Devpt", "Customer Service - Supervisor / Officer", "Others", "Student / Fresh Graduate / No Experience"], "post_time": "2022-01-13T05:50:44Z", "salary": {"currency": null, "max": null, "min": null, "period": "monthly", "term": null}, "salary_visible": false, "title_keywords": ["\u4fdd\u55ae\u8ddf\u9032\u54e1"], "responsibilities": [], "requirements": {"degrees": [], "majors": [], "languages": [], "language_level": [], "hard_skills": ["ms powerpoint", "ms excel"], "soft_skills": [], "languages_combined": []}, "experience_required": {"duration": [], "field": []}}]