[{"job_id": "100003009054190", "location_code": "hk", "company": "China Overseas Holdings Limited", "job_title": "Receptionist", "description": "Responsibilities:\n\n\nPerform reception duties including guests greeting, phone calls and taking messages\nHandle courier services, incoming and out-going mailing and fax distribution and take records\nMaintain smooth operation of the reception counter and meeting room arrangement\nProvide administrative and clerical support to departments e.g. office supplies administration and procurement, expense reimbursement, compiling simple statistics, data entry, filing\nPerform ad hoc duties assigned by supervisor\n\n\u00a0Requirements:\n\n\nDiploma holder or above with at least 3 years' relevant experiences\nGood command in both written and spoken English, Chinese and Mandarin\nGood PC knowledge in MS Words, Excel & Chinese Word Processing\nPolite and pleasant personalities\nResponsible and well organized\nDecent telephone manner and communication skills\nImmediate availability is preferred", "employment_types": ["Full Time", "Permanent"], "selling_points": ["Office location - Admiralty", "5-day work", "Attractive salary package"], "locations": ["Admiralty"], "categories": ["Admin & HR", "Receptionist"], "post_time": "2022-01-17T08:44:40Z", "salary": {"currency": null, "max": null, "min": null, "period": "monthly", "term": null}, "salary_visible": false, "title_keywords": ["receptionist"], "responsibilities": ["ad hoc duties", "data entry", "office supplies", "maintain", "administrative and clerical support", "phone calls", "administration"], "requirements": {"degrees": ["diploma holder"], "majors": [], "languages": ["english", "chinese", "mandarin"], "language_level": ["good command", "good"], "hard_skills": ["excel", "pc knowledge", "chinese word processing", "ms words"], "soft_skills": ["communication skills", "polite", "responsible", "well organized", "pleasant", "telephone manner"], "languages_combined": [{"language": "english", "language_level": ["good command", "good"]}, {"language": "chinese", "language_level": ["good command", "good", "good"]}, {"language": "mandarin", "language_level": ["good command", "good"]}]}, "experience_required": {"duration": ["at least 3 years"], "field": []}}, {"job_id": "100003009052118", "location_code": "hk", "company": "Purapharm Corporation Limited", "job_title": "Administrative Assistant (Full time/Part time)", "description": "Responsibilities:\n\nPerform reception duties including telephone calls, greeting and serving visitors in professional manner;\nProvide general office administrative work and clerical supports;\nSupport ad-hoc assignments.\n\nRequirements:\u00a0\n\nDiploma in Hospitality or related disciplines preferred;\n1 year's working experience in service field preferred, fresh graduate will also be considered;\nStrong sense of responsibility, proactive, energetic, pleasant and customer-oriented;\nGood PC knowledge in MS Office & Chinese Word Processing;\nProficiency in both written & spoken English and Chinese including Mandarin;\nImmediate available is preferred.\n\nWorking Location: Hong Kong Science Park, Tai Po\n\nWe offer 5-day working week and an attractive remuneration package. Interest parties please click\u00a0Apply Now. For company details, please visit\u00a0www.purapharm.com.\n\nOur Company is an equal opportunity employer. All personal data collected will be used for recruitment purpose only, while the personal data of the unsuccessful applicants will be destroyed within 6 months after the recruitment process.", "employment_types": ["Full Time", "Permanent"], "selling_points": ["Fresh graduate will be considered", "Reception and general administrative duties", "Customer-oriented"], "locations": ["Tai Po Area"], "categories": ["Admin & HR", "Clerical / Admin Staff", "Receptionist", "HR Supporting Staff"], "post_time": "2022-01-17T02:09:41Z", "salary": {"currency": null, "max": null, "min": null, "period": "monthly", "term": null}, "salary_visible": false, "title_keywords": ["administrative assistant"], "responsibilities": ["ad-hoc assignments", "professional manner", "administrative work"], "requirements": {"degrees": ["diploma", "fresh graduate"], "majors": ["related disciplines", "hospitality"], "languages": ["english", "chinese", "mandarin"], "language_level": ["proficiency", "good"], "hard_skills": ["pc knowledge", "chinese word processing", "ms office"], "soft_skills": ["proactive", "sense of responsibility", "pleasant", "customer-oriented", "energetic"], "languages_combined": [{"language": "english", "language_level": ["proficiency"]}, {"language": "chinese", "language_level": ["proficiency", "good"]}, {"language": "mandarin", "language_level": []}]}, "experience_required": {"duration": ["1 year"], "field": []}}, {"job_id": "100003009052746", "location_code": "hk", "company": "Hien Lee Engineering Co Ltd", "job_title": "Receptionist", "description": "Responsibilities\n\nHandle general front desk duties includes greeting clients and guests, daily registration, answering incoming calls and enquiries\nImmediate available or short notice period is preferred\n\nQualification :\u00a0\u00a0\u00a0\u00a0\u00a0\u00a0\u00a0\u00a0\u00a0\u00a0\u00a0\u00a0\u00a0\u00a0\u00a0\n\nDiploma or above with 1 year or above working experience, prefer in customer service industry\nProficiency in MS Office\nGood command in English and Chinese (Cantonese & Mandarin)\n\nInterested parties please send your full resume with photo included\u00a0expected salary\u00a0by\u00a0clicking 'Apply Now' below.", "employment_types": ["Full Time"], "selling_points": [], "locations": ["Sai Wan"], "categories": ["Admin & HR", "Receptionist"], "post_time": "2022-01-17T03:54:22Z", "salary": {"currency": "HKD", "max": 13999, "min": 11000, "period": "monthly", "term": null}, "salary_visible": true, "title_keywords": ["receptionist"], "responsibilities": ["customer service"], "requirements": {"degrees": ["diploma or above"], "majors": [], "languages": ["cantonese", "english", "chinese", "mandarin"], "language_level": ["good command"], "hard_skills": ["ms office"], "soft_skills": ["customer service"], "languages_combined": [{"language": "cantonese", "language_level": ["good command"]}, {"language": "english", "language_level": ["good command"]}, {"language": "chinese", "language_level": ["good command"]}, {"language": "mandarin", "language_level": ["good command"]}]}, "experience_required": {"duration": ["1 year"], "field": ["customer service"]}}, {"job_id": "100003009052456", "location_code": "hk", "company": "PC Partner Ltd", "job_title": "Receptionist", "description": "To cope with recent business development, we are looking for a full-time Receptionist to join our Administration Team. The ideal candidate will have a cheerful, pleasant & helpful personality, while willing to learn and with \"Can-do\" attitude.\n\nMajor Responsibilities:\n\nGreeting and announcing clients and visitors\nReceiving\u00a0and directing incoming calls to appropriate personnel and voicemail as well as providing administrative support to the HR & Admin Department\nCoordinating meetings, appointments and travel arrangement\nPreparing staff attendance record; handle inventory control, maintenance of office supplies and equipment; coordinate overall environmental cleanliness of the office\nAssisting in company activities and other ad-hoc projects as assigned\n\nRequirements:\n\nMinimum 1 year of solid relevant working experience\nExcellent telephone manner and customer service skill is essential\nPleasant, detail-minded, self-motivated, independent, adaptive, willing to learn and take on responsibilities with positive working attitude\nProficient in MS Office; proficiency in Chinese word processing is an advantage not a must\nFluency in spoken and written English and Chinese, including Mandarin\nImmediate availability is highly preferable\n\nWe offer 5-day work, bank holidays and medical insurance. We also offer attractive package commensurate with qualification & experience. Interested parties please send your full resume with CURRENT/LAST & EXPECTED SALARY.\n\n(Information collected will be used for recruitment purpose only)", "employment_types": ["Full Time", "Permanent"], "selling_points": [], "locations": ["Shatin Area"], "categories": ["Admin & HR", "Clerical / Admin Staff", "Receptionist", "Others"], "post_time": "2022-01-17T03:04:39Z", "salary": {"currency": null, "max": null, "min": null, "period": "monthly", "term": null}, "salary_visible": false, "title_keywords": ["receptionist"], "responsibilities": ["attendance", "coordinating meetings", "maintenance", "administrative support", "office supplies", "hr", "coordinate", "inventory control", "travel arrangement", "ad-hoc projects"], "requirements": {"degrees": [], "majors": [], "languages": ["english", "chinese", "mandarin"], "language_level": ["fluency", "advantage", "proficiency"], "hard_skills": ["chinese word processing", "ms office"], "soft_skills": ["detail-minded", "self-motivated", "independent", "willing to learn", "pleasant", "positive working attitude", "customer service", "telephone manner"], "languages_combined": [{"language": "english", "language_level": ["fluency"]}, {"language": "chinese", "language_level": ["fluency", "advantage", "proficiency"]}, {"language": "mandarin", "language_level": ["fluency"]}]}, "experience_required": {"duration": ["minimum 1 year"], "field": ["relevant working experience"]}}, {"job_id": "100003009053766", "location_code": "hk", "company": "Asia Shipping International Transport (HK) Limited", "job_title": "Receptionist and Administration Clerk", "description": "Job Description\n\n\u00a0\u2022 Answer incoming calls; greet visitors\n\n\u00a0\u2022 Provide logistics support, including couriers and mailings\n\n\u00a0\u2022 Handle invoice, expenses claim and other paperwork\n\n\u00a0\u2022 Manage the schedule of meetings room, organize company events\n\n\u00a0\u2022 Liaise with building management department on maintenance of office facilities\n\n\u00a0\u2022 Assist in other office administrative tasks\n\nPrepare ad-hoc assignment from time to time assigned by Supervisor.\n\n\u00a0Requirements:\n\n\u00a0\u2022 F.5/ DSE or above with experience in hospitality industry is an advantage\n\n\u00a0\u2022 Good command of English receptionist\n\n\u00a0\u2022 Good communication and interpersonal skill with positive and helpful attitude\n\n\u00a0\u2022 Be patient, cheerful personality\n\n\u00a0\u2022 Immediate available is preferred\n\n\u00a0\u2022 Fresh graduate also welcome to apply", "employment_types": ["Full Time"], "selling_points": [], "locations": ["Cheung Sha Wan"], "categories": ["Admin & HR", "Clerical / Admin Staff", "Receptionist", "Transportation & Logistics", "Freight Forwarding"], "post_time": "2022-01-17T07:29:04Z", "salary": {"currency": null, "max": null, "min": null, "period": "monthly", "term": null}, "salary_visible": false, "title_keywords": ["receptionist", "clerk"], "responsibilities": ["ad-hoc", "maintenance", "invoice", "expenses", "provide logistics support", "building management", "schedule", "liaise with", "administrative tasks"], "requirements": {"degrees": ["fresh graduate", "dse"], "majors": ["hospitality"], "languages": ["english"], "language_level": ["good command"], "hard_skills": [], "soft_skills": ["cheerful", "interpersonal skill", "communication", "patient", "positive"], "languages_combined": [{"language": "english", "language_level": ["good command"]}]}, "experience_required": {"duration": [], "field": ["hospitality industry"]}}, {"job_id": "100003009053516", "location_code": "hk", "company": "Eminence Plus", "job_title": "\u97f3\u6a02\u5b78\u6821\u63a5\u5f85\u54e1 Full time receptionist", "description": "\n\u00a0 \u8077\u8cac:\n\u2022 \u8655\u7406\u9867\u5ba2\u670d\u52d9\u5de5\u4f5c,\u5305\u62ec\u89e3\u7b54\u8ab2\u7a0b\u67e5\u8a62\u3001\u63a8\u5ee3\u8ab2\u7a0b\u53ca\u8655\u7406\u5831\u540d\u624b\u7e8c\n\u2022 \u8655\u7406\u6587\u66f8\u53ca\u884c\u653f\u5de5\u4f5c,\u5305\u62ec\u5b78\u8cbb\u53ca\u73fe\u91d1\u7ba1\u7406\u3001\u7de8\u6392\u4e0a\u8ab2\u6642\u9593\u8868\u7b49\n\u5165\u8077\u8981\u6c42:\n\u2022 \u6b61\u8fce\u4efb\u4f55\u4eba\u58eb\u7533\u8acb\n\u2022 \u826f\u597d\u6e9d\u901a\u6280\u5de7\u3001\u505a\u4e8b\u6574\u9f4a\u6709\u5e8f\u53ca\u80fd\u7368\u7acb\u8655\u7406\u5de5\u4f5c\n\u2022 \u6027\u683c\u958b\u6717\u3001\u6709\u611b\u5fc3\u548c\u8010\u6027\u3001\u559c\u6b61\u5c0f\u670b\u53cb,\u5177\u5718\u968a\u7cbe\u795e\n\u2022 \u826f\u597d\u5ee3\u6771\u8a71\n\u2022 \u719f\u6089\u4e2d\u6587\u8f38\u5165\u6cd5\n\u2022 \u6709\u7ba1\u7406\u7d93\u9a57\u6216\u6709\u92b7\u552e\u7d93\u9a57\u512a\u5148\n\u2022 \u80fd\u5373\u6642\u4e0a\u73ed\u8005\u512a\u5148\u8003\u616e\n\u5f85\u9047:\n\u2022 \u5728\u8077\u5de5\u4f5c\u57f9\u8a13\n\u2022 \u4e00\u661f\u671f5-6\u5929\u5de5\u4f5c\n\u2022 \u8868\u73fe\u512a\u7570\u8005,\u53ef\u7372\u767c\u52e4\u5de5\u734e\u53ca\u8868\u73fe\u734e\u91d1,\u4e26\u6709\u6a5f\u6703\u6649\u5347\n\u2022 \u6709\u54e1\u5de5\u6298\u6263\u53ca\u512a\u60e0\n\u2022 \u8212\u9069\u7684\u5de5\u4f5c\u74b0\u5883,\u5730\u9ede\u4fbf\u5229,\u6e2f\u9435\u53ef\u9054\n**\u6709\u610f\u8005\u8acb\u96fb\u90f5\u6309Apply Now\u63d0\u4ea4\u500b\u4eba\u5c65\u6b77\u53ca\u8981\u6c42\u5f85\u9047,\u4e26\u8acb\u8a3b\u660e\u7533\u8acb\u8077\u4f4d\u3002\u5982\u6709\u554f\u984c\u53efWHATSAPP 60677186\u67e5\u8a62\n*\u6ce8\u610f,\u53ea\u6709\u5165\u570d\u7533\u8acb\u4eba\u5c07\u88ab\u901a\u77e5\u3002\u6240\u6709\u6536\u96c6\u5230\u7684\u4fe1\u606f\u90fd\u5c07\u56b4\u683c\u4fdd\u5bc6,\u50c5\u7528\u65bc\u62db\u8058\u76ee\u7684\u3002\n\u00a0 Job Duties\n\u2022 To handle booking and requests with proper telephone manners\n\u2022 To greet customers\n\u2022 To arrange customer bookings and registrations upon visits\n\u2022 To perform day-to-day routine office administrative tasks\n\u2022 To perform other ad-hoc tasks as assigned\nRequirements\n\u2022 Good command of English and Cantonese\n\u2022 Strong communication, interpersonal, self-motivated and detail-oriented\nProficiency in MS Office (MS Word, Excel)\n\u2022 Excellent telephone manner with pleasant and professional attitudes\n\u2022 Experience in office administration function is an advantage\nBenefits\n\u2022 Professional on-the-job training\n\u2022 Good career prospects\n\u2022 Staff purchase and service discount\nInterested parties, please send email by clicking Apply Now, remark the applied position ,send your resume with start-date availability, your current and expected salary.\nPersonal data collected will be used for recruitment purposes only and kept confidential.\n\n", "employment_types": ["Full Time"], "selling_points": [], "locations": ["Not Specified"], "categories": ["Admin & HR", "Clerical / Admin Staff", "Receptionist", "Others"], "post_time": "2022-01-17T07:05:06Z", "salary": {"currency": null, "max": null, "min": null, "period": "monthly", "term": null}, "salary_visible": false, "title_keywords": ["receptionist"], "responsibilities": ["administrative tasks", "customer bookings", "ad-hoc tasks", "booking"], "requirements": {"degrees": [], "majors": [], "languages": ["cantonese", "english"], "language_level": ["good command"], "hard_skills": ["ms word", "excel", "ms office"], "soft_skills": ["self-motivated", "detail-oriented", "communication", "pleasant", "telephone manner", "interpersonal"], "languages_combined": [{"language": "cantonese", "language_level": ["good command"]}, {"language": "english", "language_level": ["good command"]}]}, "experience_required": {"duration": [], "field": ["office administration"]}}, {"job_id": "100003009054605", "location_code": "hk", "company": "Auberge Hospitality Limited", "job_title": "And we are hiring \u2013 Restaurant Receptionist, Discovery Bay Recreation Club", "description": "Responsibilities:\nResponsible for restaurant receptionist duties including check reservations, escort guests to assigned tables, handle telephone enquiries and manage guest\u2019s bookings\nBuild up a good relationship with guests and providing prompt response to guests\nProperly and accurately process guest's payments\nRequirements:\nDiploma or above, graduated in Hospitality Management will be an advantage\n1 - 2 years relevant work experience, preferably with clubs, hotels or restaurants work experience\nPleasant, service-oriented and outgoing personality\nProficiency in both spoken and written English and Chinese\nWe offer an attractive remuneration package and excellent career opportunities to the right candidate. Interested applicants please send your CV by email via \"Apply Now\" or by WhatsApp at 63173527.\nPersonal data provided by job applicants will be used strictly for recruitment purposes only.", "employment_types": ["Full Time", "Permanent"], "selling_points": ["Properly and accurately process guest's payments", "Diploma or above", "1 - 2 years relevant work experience"], "locations": ["Lantau Island"], "categories": ["Admin & HR", "Receptionist", "Hospitality / F & B", "Hospitality / Hotel Services", "Others"], "post_time": "2022-01-17T10:13:33Z", "salary": {"currency": null, "max": null, "min": null, "period": "monthly", "term": null}, "salary_visible": false, "title_keywords": ["restaurant receptionist"], "responsibilities": ["good relationship", "payments"], "requirements": {"degrees": ["diploma or above"], "majors": ["hospitality management"], "languages": ["english", "chinese"], "language_level": ["proficiency"], "hard_skills": [], "soft_skills": ["outgoing personality", "service-oriented", "pleasant"], "languages_combined": [{"language": "english", "language_level": ["proficiency"]}, {"language": "chinese", "language_level": ["proficiency"]}]}, "experience_required": {"duration": ["1 - 2 years"], "field": ["hotels"]}}, {"job_id": "100003009053980", "location_code": "hk", "company": "Compass Offices", "job_title": "Receptionist / Client Service Executive (Fresh Graduate Welcome!)", "description": "Adventure, discovery, work hard play hard, a unique work-life balance, no weekend shifts and no night shifts; this is but a part of what you can experience as a valued employee of Compass Offices.\n\nBring your passion for working in a team and helping people!\n\nCompass Offices currently offers over 5,000 workstations in Hong Kong and many more in Australia, China, Japan, Malaysia, Philippines, Singapore and Vietnam, visit our company website to find out more.\n\n\n\nhttps://www.compassoffices.com\n\n\nFresh Graduates are welcome.\n\nWorking Hours: Monday to Friday \u2013 Office hours\n\n\nYour activities:\n\nWelcome all clients and guests and be a great first impression\nMaintain optimal client relations, manage clients\u2019 check-in and check-out, ad hoc requests and reservations\nProviding services and support in accordance with clients\u2019 preferences\nEnsure that all customer contact is handled politely and efficiently and accurately meets the needs\nInspect the front and back areas and make sure all is always impeccable\nPerform any other reasonable duties as required by the Management from time to time.\n\nWhat you bring:\n\nPrior experience in customer service and hospitality is a plus\nProficiency in written and spoken English\u00a0\nAn outgoing personality, strong communication skills and great team player\nA proactive, dynamic and enthusiastic attitude\nWillingness to learn and develop\n\nPlease submit your resume with current and expected salary. All applications will be treated strictly confidential for recruitment purpose only.\n\n\n", "employment_types": ["Full Time", "Permanent"], "selling_points": ["Top leading Serviced Office provider in HK", "5-Day work, NO night & NO weekend shift!", "Fresh graduate welcomed with Career Opportunity"], "locations": ["Central & Western Area"], "categories": ["Admin & HR", "Receptionist", "Sales, CS & Business Devpt", "Customer Service - Supervisor / Officer", "Hospitality / F & B", "Hospitality / Hotel Services"], "post_time": "2022-01-17T07:54:17Z", "salary": {"currency": null, "max": null, "min": null, "period": "monthly", "term": null}, "salary_visible": false, "title_keywords": ["receptionist", "service executive"], "responsibilities": ["management", "ad hoc requests", "develop", "communication", "maintain", "customer service", "contact", "recruitment", "company website"], "requirements": {"degrees": [], "majors": [], "languages": ["english"], "language_level": ["proficiency"], "hard_skills": ["no", "plus", "make", "dynamic", "compass"], "soft_skills": ["outgoing personality", "communication skills", "passion for", "unique", "customer service", "dynamic", "enthusiastic", "team player", "proactive"], "languages_combined": [{"language": "english", "language_level": ["proficiency"]}]}, "experience_required": {"duration": [], "field": ["customer service"]}}, {"job_id": "100003009053714", "location_code": "hk", "company": "Famous Car Trade Company Limited", "job_title": "Receptionist \u63a5\u5f85\u54e1 (\u4e5d\u9f8d\u7063)", "description": "\n\u5de5\u4f5c\u8077\u8cac: \u8ca0\u8cac\u7dad\u4fee\u4e2d\u5fc3\u7684\u4e00\u822c\u524d\u53f0\u63a5\u5f85\u5ba2\u4eba\u7684\u5de5\u4f5c\n\u5de5\u4f5c\u6642\u9593: \u516d\u5929\u5de5\u4f5c\n\u5de5\u4f5c\u6642\u9593 0830-1800\n\u7d05\u65e5\u53ca\u661f\u671f\u65e5\u6bcb\u9700\u4e0a\u73ed\n\u5de5\u4f5c\u8981\u6c42: \u6709\u8cac\u4efb\u5fc3, \u5b88\u6642\u8005\u512a\u5148\n\u826f\u597d\u5ee3\u6771\u8a71 \u826f\u597d\u7684\u6e9d\u901a\u80fd\u529b\n\u6642\u85aa:$70 (\u4e0d\u5305\u62ec\u98ef\u9418)\n\u5408\u7d04\u671f: 12 \u500b\u6708\n\u517c\u8077\u6642\u6578: \u6bcf\u661f\u671f 57\n\u5de5\u4f5c\u985e\u578b: \u517c\u8077, \u5408\u7d04\n\u85aa\u916c: $65.00\u81f3$70.00(\u6bcf\u5c0f\u6642)\n\u6642\u9593:\n\u2022 \u65e5\u73ed\nCOVID-19 \u75ab\u60c5\u8003\u91cf:\n\u6240\u6709\u5ba2\u6236\u90fd\u5fc5\u9808\u6234\u53e3\u7f69\n\u9060\u7a0b\u5de5\u4f5c:\n\u2022 \u5426\n\n", "employment_types": ["Full Time"], "selling_points": [], "locations": ["Kwun Tong Area"], "categories": ["Admin & HR", "Clerical / Admin Staff", "Receptionist", "Others"], "post_time": "2022-01-17T07:24:01Z", "salary": {"currency": null, "max": null, "min": null, "period": "monthly", "term": null}, "salary_visible": false, "title_keywords": ["receptionist"], "responsibilities": [], "requirements": {"degrees": [], "majors": [], "languages": [], "language_level": [], "hard_skills": [], "soft_skills": [], "languages_combined": []}, "experience_required": {"duration": [], "field": []}}, {"job_id": "100003009053078", "location_code": "hk", "company": "Spidernet Recruitment Services", "job_title": "Receptionist and Administration Assistant", "description": "Receptionist and Administration Assistant\n\nSalary: HK$18-22k\n\nResponsibilities:\n\nHandle incoming calls and greeting visitors in a professional and polite manner\nAssist in the office administration function including office and facilities maintenance, ordering stationery & pantry supplies, maintain the cleanliness and tidiness of the office area, booking and monitoring the use of conference rooms and company cars and drivers\nHandle courier services, coordinate the dispatch and distribution of local & overseas parcels/documents\n\u00adProcessing of the expenses claims through systems\n\nRequirements:\n\nFluency in spoken Mandarin (a must), Cantonese and English is essential\nAt least 3-5 years Receptionist and Office Administration experience in sizable, preferable have experience in China-based company\nGood interpersonal and communications skills\nProficient with MS Word, Excel & Chinese Word Processing\n\u00adCustomer Focus and Service Oriented\nHard working with strong sense of responsibility\n\u00adDetail-orientated and resourceful\nOrganized, self-motivated and a good team player\n\nAttractive remuneration and fringe benefits will be offered to the successful candidate.\n\nInterested candidates should apply with detailed resume, present and expected salaries by clicking the Apply Now button.\n\nAll information received will be treated in strict confidence and used for recruitment purpose only.\n\nOnly shortlisted candidates will be notified.", "employment_types": ["Full Time", "Permanent"], "selling_points": ["Fluent spoken of Mandarin is a must", "3-5 yrs Receptionist and Administration exp.", "Immediately available is preferable"], "locations": ["Central & Western Area"], "categories": ["Admin & HR", "Clerical / Admin Staff", "Receptionist", "Secretary"], "post_time": "2022-01-17T05:40:00Z", "salary": {"currency": null, "max": null, "min": null, "period": "monthly", "term": null}, "salary_visible": false, "title_keywords": ["receptionist", "administration assistant"], "responsibilities": ["maintenance", "office administration", "monitoring", "expenses", "stationery", "systems", "coordinate", "maintain", "booking", "greeting visitors"], "requirements": {"degrees": [], "majors": [], "languages": ["cantonese", "english", "chinese", "mandarin"], "language_level": ["fluency", "proficient"], "hard_skills": ["excel", "focus", "chinese word processing", "ms word"], "soft_skills": ["organized", "self-motivated", "good team player", "resourceful", "sense of responsibility", "hard working", "focus", "interpersonal"], "languages_combined": [{"language": "cantonese", "language_level": []}, {"language": "english", "language_level": []}, {"language": "chinese", "language_level": ["proficient"]}, {"language": "mandarin", "language_level": ["fluency"]}]}, "experience_required": {"duration": ["at least 3-5 years"], "field": ["office administration"]}}, {"job_id": "100003009051414", "location_code": "hk", "company": "Medifast (Hong Kong) Limited", "job_title": "Receptionist / Clinic Assistant", "description": "Responsibilities\n\nResponsible for general office administration, such as reception, office supplies, office renovation, repair & maintenance of facilities, handle payment and update reports\nCoordinate the administration work with different kinds of vendors\u00a0\nControl submissions and maintain a good filing system\nAssist the team in all aspects of administrative functions\nHandle ad-hoc projects as required\n\nRequirements\n\nDiploma with 2 years' relevant experience\nFresh graduate will also be considered\nAble to handle multi-task jobs effectively\nExcellent communication skills, must be able to interact with all different kinds of people\nGood team player, initiative, independent, and able to work under pressure\nGood communication and interpersonal skills\nGood command of English and Chinese\nStrong in PC skill such as MS Words, Excel, PowerPoint and Chinese word processing\nImmediate available is preferable\n\n\n\nWorking location:\u00a0Kwai Chung\n\n\n\nStaff Benefit\n\nDiscretionary Bonus\nMedical & Life Insurance\nAnnual Leave\nPayable Sick Leave\nEncourage continuing education and on-job training\nOpen office working environment\nOffer promotion opportunities and long-term career path\u00a0\n\nWe offer a competitive remuneration package to the right candidate.\u00a0Interested parties\u00a0please click\u00a0\"Apply Now\"\u00a0to submit your application\u00a0or by email to\u00a0hr1 @twcoffee.com\n\n\u00a0(All personal data provided by applicants will be treated in strict confidence and used for employment-related purpose only.)", "employment_types": ["Full Time", "Permanent"], "selling_points": [], "locations": ["Mong Kok"], "categories": ["Admin & HR", "Clerical / Admin Staff", "Receptionist", "Medical Services", "Others"], "post_time": "2022-01-15T15:14:06Z", "salary": {"currency": null, "max": null, "min": null, "period": "monthly", "term": null}, "salary_visible": false, "title_keywords": ["receptionist", "clinic assistant"], "responsibilities": ["control", "maintenance", "office supplies", "office administration", "renovation", "coordinate", "repair", "payment", "reports", "maintain", "ad-hoc projects", "administration"], "requirements": {"degrees": ["diploma", "fresh graduate"], "majors": [], "languages": ["english", "chinese"], "language_level": ["good command"], "hard_skills": ["excel", "chinese word processing", "ms words", "powerpoint", "pc skill"], "soft_skills": ["communication skills", "good team player", "multi-task", "independent", "communication and interpersonal skills", "initiative", "work under pressure"], "languages_combined": [{"language": "english", "language_level": ["good command"]}, {"language": "chinese", "language_level": ["good command"]}]}, "experience_required": {"duration": ["2 years"], "field": ["relevant experience"]}}, {"job_id": "100003009054550", "location_code": "hk", "company": "Tsit Wing Coffee Co Ltd", "job_title": "Administrative Assistant", "description": "\n\u8077\u8cac\uff1a\n\u2022 \u63a5\u5f85\u9867\u5ba2\u3001\u63a5\u807d\u96fb\u8a71\u53ca\u5b89\u6392\u5ba2\u4eba\u7684\u7642\u7a0b\u9810\u7d04\u6642\u9593\n\u2022 \u8ca0\u8cac\u8655\u7406\u73fe\u91d1\u53ca\u4fe1\u7528\u5361\u4ea4\u6613\u5de5\u4f5c\u3001\u96fb\u8166\u6253\u55ae\u53ca\u57cb\u6578\n\u2022 \u5354\u52a9\u4e3b\u7ba1\u53ca\u9867\u554f\u8655\u7406\u65e5\u5e38\u5ba2\u6236\u670d\u52d9\u53ca\u5e97\u92ea\u71df\u904b\u5de5\u4f5c\n\u00a0 \u8981\u6c42\uff1a\n\u2022 \u6d41\u5229\u5ee3\u6771\u8a71\n\u2022 \u7121\u9700\u76f8\u95dc\u7d93\u9a57\u4ea6\u53ef\n\u2022 \u7a4d\u6975\u4e3b\u52d5\n\u2022 \u601d\u60f3\u6b63\u9762\u3001\u5bcc\u8cac\u4efb\u611f\u3001\u670d\u52d9\u614b\u5ea6\u53cb\u5584\u3001\u6027\u683c\u958b\u6717\n\u61c2\u96fb\u8166\u64cd\u4f5c (MS EXCEL, WORD\u7b49)\n\u00a0 \u524d\u7dda\u54e1\u5de5\u798f\u5229\uff1a\n\u2022 \u6bcf\u5929\u5de5\u4f5c9\u5c0f\u6642\n\u2022 \u661f\u671f\u516d\u53ca\u516c\u773e\u5047\u671f\u5747\u53ef\u65e9\u6536\n\u2022 \u7bc0\u65e5\u65e9\u653e\n\u2022 \u63d0\u4f9b\u5a5a\u5047\u3001\u751f\u65e5\u5047\u3001\u6069\u6064\u5047\n\u2022 \u52a0\u73ed\u88dc\u9418\n\u2022 \u5c08\u696d\u514d\u8cbb\u5728\u8077\u57f9\u8a13\n\u2022 \u7279\u5feb\u6649\u5347\u6a5f\u6703\n\u2022 \u8cfc\u7269\u512a\u60e0\u53ca\u514d\u8cbb\u7642\u7a0b\n\u2022 \u5bb6\u5c6c\u597d\u53cb\u6298\u6263\u512a\u60e0\n\u00a0 \u5de5\u4f5c\u5730\u9ede\uff1a\u65fa\u89d2 / \u89c0\u5858\n\u5de5\u4f5c\u6642\u9593\uff1a\u9031\u4e00\u81f3\u9031\u4e94 12:00 - 21:00\n\u00a0 \u00a0 \u00a0 \u00a0 \u00a0 \u00a0 \u00a0 \u00a0 \u00a0 \u00a0 \u9031\u516d\u53ca\u516c\u773e\u5047\u671f 10:30 - 18:30\n\n", "employment_types": ["Full Time", "Permanent"], "selling_points": [], "locations": ["Kwai Fong"], "categories": ["Admin & HR", "Clerical / Admin Staff", "Receptionist", "Others"], "post_time": "2022-01-17T09:57:37Z", "salary": {"currency": null, "max": null, "min": null, "period": "monthly", "term": null}, "salary_visible": false, "title_keywords": ["administrative assistant"], "responsibilities": [], "requirements": {"degrees": [], "majors": [], "languages": [], "language_level": [], "hard_skills": ["ms excel"], "soft_skills": [], "languages_combined": []}, "experience_required": {"duration": [], "field": []}}, {"job_id": "100003009053627", "location_code": "hk", "company": "Bare Limited", "job_title": "Receptionist \u63a5\u5f85\u54e1", "description": "Responsible for handling telephone calls and provide counter service\nSecondary school graduate\nGood telephone manners and customer service skills\nKnowledge of Chinese word processing is an advantage\nWorking hours : 14:30 - 23:00\nRotated rest day is required\u00a0\n\n\nApplication Method\n\nWe offer free shuttle bus, free parking and fringe benefits including medical scheme, discretionary bonus and public holidays to the right candidate. Interested parties, please send full resume with expected salary to ORIENTAL HUMAN RESOURCES LIMITED\u00a0by\u00a0clicking \"Apply now\" ;\u00a0or\u00a0fax to 3600 1900\u00a0( Please quote reference on the application letter )\n\n\nPersonal Information Collection Statement\n\nPersonal data collected will be treated in accordance with our Personal Data Policy and handled in strict confidence by authorized personnel for recruitment related purpose only.\n\non.cc", "employment_types": ["Full Time"], "selling_points": [], "locations": ["Kwun Tong"], "categories": ["Admin & HR", "Clerical / Admin Staff", "Receptionist", "Others"], "post_time": "2022-01-17T07:15:56Z", "salary": {"currency": null, "max": null, "min": null, "period": "monthly", "term": null}, "salary_visible": false, "title_keywords": ["receptionist"], "responsibilities": ["customer service"], "requirements": {"degrees": [], "majors": [], "languages": ["chinese"], "language_level": ["advantage"], "hard_skills": ["chinese word processing"], "soft_skills": ["customer service skills", "responsible"], "languages_combined": [{"language": "chinese", "language_level": ["advantage"]}]}, "experience_required": {"duration": [], "field": []}}, {"job_id": "100003009050244", "location_code": "hk", "company": "SAVILLS GUARDIAN", "job_title": "RECEPTIONIST", "description": "Responsibilities\n\n\nResponsible for greeting guests, handling incoming calls, managing conference room booking, courier arrangement, mail services and guests registration\nInterface with external customers and internal customers of all levels\nEnsure the cleanliness and tidiness of the reception area\nProvide clerical and administrative support to Administration Department\nHandle ad hoc projects as required\n\nRequirements\n\n\nForm 5 / HKDSE or above\nMinimum 2 years\u2019 relevant experience in sizable organizations, candidates with customer services experience in other industries will also be considered\nMature and good interpersonal skill\nGood command of written and spoken English and Chinese (including Putonghua)\nProficient in PC knowledge such as Word, Excel, PowerPoint and Chinese word processing\nImmediate available is preferable\n\nWe offer competitive salary package to the right appointees. Applicants are requested to submit detailed resume with expected salary by clicking \"Apply Now\".\n\nPlease quote Emp. Ref No.: ADMIN/01202\n\n(Personal data provided will be used strictly in accordance with our personal data policies, a copy of which will be provided immediately upon request.)", "employment_types": ["Full Time", "Permanent"], "selling_points": ["Responsible for greeting guests", "Interface with external customers", "Minimum 2 years\u2019 relevant experience"], "locations": ["Tai Koo"], "categories": ["Admin & HR", "Clerical / Admin Staff", "Receptionist", "Others"], "post_time": "2022-01-14T10:00:26Z", "salary": {"currency": null, "max": null, "min": null, "period": "monthly", "term": null}, "salary_visible": false, "title_keywords": ["receptionist"], "responsibilities": ["administration", "ad hoc projects", "booking", "administrative support"], "requirements": {"degrees": ["form 5", "hkdse"], "majors": [], "languages": ["putonghua", "english", "chinese"], "language_level": ["good command", "proficient"], "hard_skills": ["excel", "chinese word processing", "word", "powerpoint", "pc knowledge"], "soft_skills": ["mature", "interpersonal skill"], "languages_combined": [{"language": "putonghua", "language_level": ["good command"]}, {"language": "english", "language_level": ["good command"]}, {"language": "chinese", "language_level": ["good command", "proficient"]}]}, "experience_required": {"duration": ["minimum 2 years"], "field": ["relevant experience", "customer services"]}}, {"job_id": "100003009052222", "location_code": "hk", "company": "ORIENTAL HUMAN RESOURCES LIMITED", "job_title": "Receptionist", "description": "\n\u5de5\u4f5c\u8077\u8cac:\n\u2022 \u8ca0\u8cac\u9673\u5217\u5ba4\u7684\u4e00\u822c\u524d\u53f0\u884c\u653f\u5de5\u4f5c,\u4f8b\u5982\u63a5\u807d\u96fb\u8a71\u3001\u63a5\u5f85\u5ba2\u4eba\n\u5de5\u4f5c\u6642\u9593:\n\u2022 \u661f\u671f\u4e00\u81f3\u4e94 0900-1730\n\u2022 \u7d05\u65e5,\u661f\u671f\u516d\u53ca\u661f\u671f\u65e5\u6bcb\u9700\u4e0a\u73ed\n\u5de5\u4f5c\u8981\u6c42:\n\u2022 \u826f\u597d\u5ee3\u6771\u8a71\u53ca\u666e\u901a\u8a71\n\u2022 \u826f\u597d\u7684\u6e9d\u901a\u80fd\u529b\n\u2022 \u719f\u6089Excel & Word\n\u5b88\u6642,\u6709\u8cac\u4efb\u5fc3\u8005\u512a\u5148\n\u6642\u85aa : $70 (\u4e0d\u5305\u62ec\u98ef\u9418)\n\u5408\u7d04\u671f: 12 \u500b\u6708\n\u517c\u8077\u6642\u6578: \u6bcf\u661f\u671f 42.5\n\u5de5\u4f5c\u985e\u578b: \u517c\u8077, \u5408\u7d04\n\u85aa\u916c: $65.00\u81f3$70.00(\u6bcf\u5c0f\u6642)\n\u6642\u9593:\n\u2022 \u65e5\u73ed\n\u9060\u7a0b\u5de5\u4f5c:\n\u2022 \u5426\n\n", "employment_types": ["Full Time"], "selling_points": [], "locations": ["Tai Po Area"], "categories": ["Admin & HR", "Clerical / Admin Staff", "Receptionist", "Hospitality / F & B", "Hospitality / Hotel Services"], "post_time": "2022-01-17T02:30:38Z", "salary": {"currency": null, "max": null, "min": null, "period": "monthly", "term": null}, "salary_visible": false, "title_keywords": ["receptionist"], "responsibilities": [], "requirements": {"degrees": [], "majors": [], "languages": [], "language_level": [], "hard_skills": ["word"], "soft_skills": [], "languages_combined": []}, "experience_required": {"duration": [], "field": []}}, {"job_id": "100003009053708", "location_code": "hk", "company": "Famous Car Trade Company Limited", "job_title": "Receptionist \u63a5\u5f85\u54e1 ( \u8343\u7063 )", "description": "Responsibilities:\nProvide general office administrative support including invoice checking, office supplies procurement, repair and maintenance, etc\nHandle clerical duties including data entry, report preparation and filing work\nBackup for general reception duties such as handling courier services, incoming & outgoing mails when necessary\nOther ad-hoc tasks designated by the supervisor\nRequirements:\n\nPost-secondary or above\n1 - 2 years experience in office administration is preferred\nIndependent, responsible and self-motivated\nA good team player with good interpersonal and communication skills\nGood command of both written and spoken Cantonese, Mandarin and English\nProficient in MS Office (Word, Excel) and Chinese input is a must\nWe offer an attractive remuneration package including 5-days work, medical scheme and bank holidays to the right candidate. If you aspired to an exciting and rewarding career, please send a full resume with the expected salary and available starting date by clicking \u201cAPPLY NOW\u201d to the Human\u00a0Resources Department.\n\nTo know more about us, please visit our website at www.chargeurs-pcc.com\n(Personal data collected will be kept confidential and used for recruitment purposes only.)", "employment_types": ["Full Time"], "selling_points": [], "locations": ["Tsuen Wan Area"], "categories": ["Admin & HR", "Clerical / Admin Staff", "Receptionist", "Others"], "post_time": "2022-01-17T07:23:27Z", "salary": {"currency": null, "max": null, "min": null, "period": "monthly", "term": null}, "salary_visible": false, "title_keywords": ["receptionist"], "responsibilities": ["maintenance", "administrative support", "invoice", "office supplies", "data entry", "ad-hoc tasks", "checking", "repair", "report"], "requirements": {"degrees": [], "majors": [], "languages": ["cantonese", "english", "chinese", "mandarin"], "language_level": ["good command", "proficient"], "hard_skills": ["chinese input", "excel", "word", "ms office"], "soft_skills": ["communication skills", "good team player", "self-motivated", "independent", "responsible", "interpersonal"], "languages_combined": [{"language": "cantonese", "language_level": ["good command"]}, {"language": "english", "language_level": ["good command"]}, {"language": "chinese", "language_level": ["proficient"]}, {"language": "mandarin", "language_level": ["good command"]}]}, "experience_required": {"duration": ["1 - 2 years"], "field": ["office administration"]}}, {"job_id": "100003009052778", "location_code": "hk", "company": "PCC Asia Limited", "job_title": "Administrative Assistant", "description": "\u8077\u8cac \u00a0:\n\n\u61c9\u7b54\u5b78\u751f\u53ca\u5bb6\u9577\u67e5\u8a62\u53ca\u5b89\u6392\u8abf\u5802\n\u8655\u7406\u5831\u540d\u4e8b\u5b9c\n\u6574\u7406\u6587\u4ef6\u53ca\u6587\u66f8\u8655\u7406\n\u8655\u7406\u88dc\u7fd2\u4e2d\u5fc3\u65e5\u5e38\u5927\u5c0f\u4e8b\u52d9\n\n\u8077\u4f4d\u8981\u6c42 \u00a0:\n\n\u4e2d\u5b78\u7562\u696d\uff0c\u540c\u7b49\u5b78\u6b77\u6216\u4ee5\u4e0a\u7a0b\u5ea6\n\u61c2\u4e2d\u82f1\u6253\u5b57\uff0c\u719f\u8b58\u57fa\u672c\u96fb\u8166\u64cd\u4f5c\n\u7a4d\u6975\u9032\u53d6\uff0c\u7d30\u5fc3\uff0c\u5f85\u4eba\u6709\u79ae\uff0c\u6709\u8cac\u4efb\u611f\n\u5177\u76f8\u95dc\u5de5\u4f5c\u7d93\u9a57\u8005\u512a\u5148\n\n\u5de5\u4f5c\u6642\u9593 :\n\n\u4e94\u5929\u5de5\u4f5c\u65e5, \u8f2a\u4f11\n\u661f\u671f\u4e00\u81f3\u4e94\u00a0(12:00-21:00) \u53ca\u661f\u671f\u516d(09:00-19:00) 1\u5c0f\u6642\u5348\u98ef\u6642\u9593\n\u9022\u661f\u671f\u65e5\u53ca\u516c\u773e\u5047\u671f\u4f11\u606f\n\u5de5\u4f5c\u5730\u9ede: \u592a\u5b50/\u7063\u4ed4/\u6c99\u7530/\u8343\u7063/\u5143\u6717 (\u53ef\u6309\u5c45\u4f4f\u5730\u5340\u5b89\u6392)\n\n\n\u54e1\u5de5\u53ef\u4eab\u00a0:\u00a0\n\n\u52e4\u5de5\u734e\n\u5b9a\u671f\u54e1\u5de5\u6d3b\u52d5\u53ca\u805a\u9910\n\u52de\u5de5\u4fdd\u96aa\n\u91ab\u7642\u4fdd\u96aa\n\u6709\u85aa\u75c5\u5047\u3001\u5a5a\u5047\u3001\u4f8d\u7522\u5047\u3001\u751f\u65e5\u798f\u5229\n\u9022\u661f\u671f\u65e5\u53ca\u516c\u773e\u5047\u671f\u4f11\u606f\n\n\u6709\u8207\u8da3\u8005\u8acb\u628a\u5c65\u6b77\u8868\u96fb\u90f5\u7d66\u6211\u5011\uff0c\u6211\u5011\u6703\u81f4\u96fb\u76f8\u7d04\u9762\u8a66\u6642\u9593\u3002", "employment_types": ["Full Time", "Permanent"], "selling_points": [], "locations": ["Kwun Tong"], "categories": ["Admin & HR", "Clerical / Admin Staff", "Receptionist", "Secretary"], "post_time": "2022-01-17T05:15:56Z", "salary": {"currency": null, "max": null, "min": null, "period": "monthly", "term": null}, "salary_visible": false, "title_keywords": ["administrative assistant"], "responsibilities": [], "requirements": {"degrees": [], "majors": [], "languages": [], "language_level": [], "hard_skills": [], "soft_skills": [], "languages_combined": []}, "experience_required": {"duration": [], "field": []}}, {"job_id": "100003009033125", "location_code": "hk", "company": "\u5b78\u65af\u6559\u80b2", "job_title": "\u5168\u8077\u63a5\u5f85\u54e1 / Receptionist / \u5ba2\u6236\u52a9\u7406 / Customer Service Assistant *Recent Graduate will be considered*", "description": "The appointee is expected to carry out general administrative duties for Division of Continuing and Professional Education. Major duties include: (a) assisting in the day-to-day operation of the programmes, including but not limited to class scheduling, examination arrangement, student record updating, and organisation of student activities; (b) liaising with internal and external parties (including staff, students and external bodies) and handling enquiries and complaints; (c) compiling information and figures and maintaining database / file records; and (d) providing supports to ad-hoc duties as assigned by the supervisor(s).\nMinimum Requirements:\n\u00a0(i) Holder of Higher Diploma or Associate Degree with preferably 2 years of related experience; OR (ii) with at least 5 passes in HKCEE including English Language (at least Grade C if Syllabus A/Level 2 from 2007) and Chinese Language (at least Level 2 from 2007), or at least 5 subjects attaining Level 2 in HKDSE including English Language and Chinese Language with more work experience;\nHolder of Bachelor\u2019s degree with at least 1 year of work experience will also be considered;\nEffective interpersonal and multi-tasking skills;\nAble to work under tight schedule;\nGood command of written and spoken English and Chinese; and\nProficient in MS Office applications (English and Chinese) and Excel.\nSalary will be commensurate with qualifications and experience.\nApplication Procedure:\nApplicants are invited to submit their applications at the HKBU e-Recruitment System (jobs.hkbu.edu.hk). Shortlisted candidates will be invited to sit for written test. Applicants not invited for interview 8 weeks after the closing date may consider their applications unsuccessful. Details of the University's Personal Information Collection Statement can be found at http://hro.hkbu.edu.hk/pics.\nThe School reserves the right not to make an appointment for the post advertised, and the appointment will be made according to the terms and conditions then applicable at the time of offer.\nClosing date: 31 January 2022", "employment_types": ["Full Time"], "selling_points": ["\u61c9\u7b54\u5b78\u751f\u53ca\u5bb6\u9577\u67e5\u8a62", "\u8655\u7406\u88dc\u7fd2\u4e2d\u5fc3\u65e5\u5e38\u5927\u5c0f\u4e8b\u52d9", "\u4e94\u5929\u5de5\u4f5c\u65e5\u516c\u773e\u5047\u671f\u4f11\u606f"], "locations": ["Not Specified"], "categories": ["Admin & HR", "Clerical / Admin Staff", "Receptionist", "Education", "Others"], "post_time": "2022-01-16T21:50:09Z", "salary": {"currency": null, "max": null, "min": null, "period": "monthly", "term": null}, "salary_visible": false, "title_keywords": ["receptionist", "\u5ba2\u6236\u52a9\u7406", "customer service assistant"], "responsibilities": ["maintaining", "internal and external parties", "liaising with", "scheduling", "administrative duties", "schedule", "database", "ad-hoc duties", "recruitment", "day-to-day operation"], "requirements": {"degrees": ["associate degree", "bachelor", "diploma", "degree", "hkdse"], "majors": [], "languages": ["english", "chinese"], "language_level": ["good command", "proficient"], "hard_skills": ["excel", "make", "c", "ms office"], "soft_skills": ["multi-tasking skills", "interpersonal", "organisation", "ad-hoc duties"], "languages_combined": [{"language": "english", "language_level": ["good command", "proficient"]}, {"language": "chinese", "language_level": ["good command", "proficient"]}]}, "experience_required": {"duration": ["2 years", "at least 1 year"], "field": ["related", "chinese language"]}}, {"job_id": "100003009052538", "location_code": "hk", "company": "School of Continuing Education, HKBU", "job_title": "Programme Assistant (Ref. No.: PRSCE0037/21-22)", "description": "Job Responsibilities:\n\n\nPerform full reception function in a professional manner as required.\nHandle administrative work including but not limited to data entry, data generation & analysis\u00a0\nTo serve the walk-in internal customers politely to display professional image\nCoordinate between internal departments and clients to ensure timely delivery\nHandles ad-hoc assignments and customer programs\n\nJob Requirements:\n\n\n\nDiploma or above\n2+ years of solid experience, working in a\u00a0clinic will be an advantage.\nGood command of written and spoken English and Chinese\nGood telephone manner and communication skills\nKnowledge in MS Office\nGood working attitude, polite, punctual, responsible and self-motivated.\n\nCan work under general supervision\n5.5 days work\nCandidates with more experience will be considered as Assistant Officer.\n\n\nInterested Candidates,\u00a0please send your\u00a0full resume with your\u00a0recent photo, current & expected salary\u00a0by e-mail to\u00a0hr @moderndentallab.com\n\nAll personal data collected will be used for recruitment and employment related purpose only.", "employment_types": ["Full Time"], "selling_points": [], "locations": ["Tsim Sha Tsui"], "categories": ["Admin & HR", "Clerical / Admin Staff", "Receptionist", "Education", "Others"], "post_time": "2022-01-17T03:20:13Z", "salary": {"currency": null, "max": null, "min": null, "period": "monthly", "term": null}, "salary_visible": false, "title_keywords": ["assistant"], "responsibilities": ["administrative work", "data", "data entry", "ad-hoc assignments", "analysis", "professional manner", "coordinate"], "requirements": {"degrees": ["diploma or above"], "majors": [], "languages": ["english", "chinese"], "language_level": ["good command"], "hard_skills": ["ms office"], "soft_skills": ["communication skills", "good working attitude", "self-motivated", "polite", "responsible", "telephone manner"], "languages_combined": [{"language": "english", "language_level": ["good command"]}, {"language": "chinese", "language_level": ["good command"]}]}, "experience_required": {"duration": ["2+ years"], "field": ["clinic"]}}, {"job_id": "100003009052189", "location_code": "hk", "company": "Modern Dental Laboratory Company Limited", "job_title": "Dental Lab Admin Assistant", "description": "Provide general office administrative supports for Receptionist\none year promotion program for Management Trainee\nProject assigned by management for Internship\n\nRequirements :\n\nMature and pleasant personalities\nFluency in spoken Cantonese and written Chinese (English and Mandarin is a plus)\nBasic knowledge in Microsoft Office such as Word, Excel & Chinese Word Processing\nDetermined person with passion and self-motivated\nGood interpersonal and presentation skills\nIANG background will be an advantage", "employment_types": ["Full Time", "Permanent"], "selling_points": ["Receptionist, Customer Services", "Administrative & Operations", "5.5 day work"], "locations": ["Central"], "categories": ["Admin & HR", "Clerical / Admin Staff", "Receptionist", "Sales, CS & Business Devpt", "Sales Administration"], "post_time": "2022-01-17T02:24:31Z", "salary": {"currency": null, "max": null, "min": null, "period": "monthly", "term": null}, "salary_visible": false, "title_keywords": ["admin assistant"], "responsibilities": ["management"], "requirements": {"degrees": [], "majors": [], "languages": ["cantonese", "english", "chinese", "mandarin"], "language_level": ["fluency", "basic"], "hard_skills": ["excel", "plus", "basic", "chinese word processing", "microsoft office", "word"], "soft_skills": ["self-motivated", "determined", "mature", "pleasant", "presentation skills", "interpersonal"], "languages_combined": [{"language": "cantonese", "language_level": ["fluency"]}, {"language": "english", "language_level": []}, {"language": "chinese", "language_level": ["basic"]}, {"language": "mandarin", "language_level": []}]}, "experience_required": {"duration": [], "field": []}}, {"job_id": "100003009051504", "location_code": "hk", "company": "SDD Limited", "job_title": "Receptionist & Admin/Management Trainee/Internship", "description": "\n\u5730\u5340\uff1a \u5927\u570d\u00a0\u00a0\n\u8077\u8cac\uff1a \u8ca0\u8cac\u5831\u540d\u67e5\u8a62\u53ca\u6536\u8cbb, \u9810\u5099\u6559\u6750\u548c\u7269\u8cc7, \u78ba\u4fdd\u8ab2\u5802\u9806\u66a2\u9032\u884c\n\u8cc7\u6b77\uff1a \u5c08\u4e0a\u6559\u80b2\uff1a\u6587\u6191/\u8b49\u66f8; \u826f\u597d\u7cb5\u8a9e; \u4e00\u822c\u82f1\u8a9e; \u61c2\u8b80\u5beb\u4e2d\u6587; \u61c2\u8b80\u5beb\u82f1\u6587; \u61c2\u82f1\u6587\u6253\u5b57; \u5de5\u4f5c\u614b\u5ea6\u89aa\u5207\u53cb\u5584\uff0c\u5177\u826f\u597d\u6e9d\u901a\u6280\u5de7\uff0c\u6e96\u6642\u4e0a\u73ed\uff0c\u5de5\u4f5c\u614b\u5ea6\u7a4d\u6975\uff0c\u6709\u8cac\u4efb\u5fc3\uff0c\u6709\u5718\u9ad4\u5408\u4f5c\u7cbe\u795e\n\u5f85\u9047\uff1a \u6bcf\u6708$10,000 - $12,000, \u6709\u914c\u60c5\u6027\u82b1\u7d05 \u53ca\u9280\u884c\u5047\u671f, \u661f\u671f\u4e00\u81f3\u4e94: \u4e0b\u53482\u6642\u81f3\u4e0b\u53489\u6642\u53ca\u661f\u671f\u516d: \u4e0a\u534810\u6642\u81f3\u4e0b\u53483\u6642, \u6bcf\u9031\u5de5\u4f5c5\u5929\u534a\n\u7533\u8acb\u9808\u77e5\uff1a \u6c42\u8077\u8005\u53ef\u96fb\u90f5([via\u00a0 Apply Now ])\u5c65\u6b77\u8868\u7d66\u5b78\u7fd2\u7121\u9650\u3002\u5982\u8981\u7d22\u53d6\u6536\u96c6\u500b\u4eba\u8cc7\u6599\u8072\u660e, \u8acb\u8207\u66fe \u5c0f\u59d0(Email)\u806f\u7d61\u3002\n\n", "employment_types": ["Full Time"], "selling_points": ["5 days work", "Professional training and personal development", "Good team culture and working environment"], "locations": ["Quarry Bay"], "categories": ["Accounting", "Finance / Accounting Manager", "Admin & HR", "Receptionist", "Management", "Management Trainee"], "post_time": "2022-01-16T05:57:25Z", "salary": {"currency": null, "max": null, "min": null, "period": "monthly", "term": null}, "salary_visible": false, "title_keywords": ["receptionist", "management trainee", "admin", "internship"], "responsibilities": [], "requirements": {"degrees": [], "majors": [], "languages": [], "language_level": [], "hard_skills": [], "soft_skills": [], "languages_combined": []}, "experience_required": {"duration": [], "field": []}}, {"job_id": "100003009053505", "location_code": "hk", "company": "Learning Infinity", "job_title": "\u6559\u5ba4\u63a5\u5f85\u54e1(\u986f\u5f91\u7e3d\u6821)", "description": "Job Duties:\n\nAnswering telephone call and handle appointment bookings\nPerform general receptionist duties and serve customers\nGeneral clinical administrative duties\nLiaise with different departments to follow up customer\u2019s request\n\nRequirements\n\nForm 5 or above\n1 to 2 years working experience preferably in servicing industry\nCheerful personality with good interpersonal and communication skills\n\nWe offer group medical insurance, annual\u00a0medical check up plan,\u00a0staff purchase discount & bank holiday to right candidate. Please send resume with expected salary to HR Dept., (Data collected will be used for recruitment purposes only.)", "employment_types": ["Full Time"], "selling_points": [], "locations": ["Shatin Area"], "categories": ["Admin & HR", "Clerical / Admin Staff", "Receptionist", "Others"], "post_time": "2022-01-17T07:04:23Z", "salary": {"currency": null, "max": null, "min": null, "period": "monthly", "term": null}, "salary_visible": false, "title_keywords": [], "responsibilities": ["liaise with", "administrative duties", "telephone call"], "requirements": {"degrees": ["form 5 or above"], "majors": [], "languages": [], "language_level": [], "hard_skills": [], "soft_skills": ["communication skills", "cheerful", "interpersonal"], "languages_combined": []}, "experience_required": {"duration": ["1 to 2 years"], "field": ["servicing industry"]}}, {"job_id": "100003009054192", "location_code": "hk", "company": "Hong Kong Arts Development Council", "job_title": "Office Support Assistant (Job ref: OSA-2206-JDB)", "description": "Main Duties:\n\n\u00a0 Perform all-round reception counter service, answer phone calls and general enquiries;\n\u00a0 Record and distribute incoming and outgoing mails/couriers and e-Fax etc.;\n\u00a0 Handle meeting room bookings and provide logistic support for Council / Committee meetings;\n\u00a0 Record and ensure office stationery supplies and distribution;\n\u00a0 Responsible for record grant applications registrations and distribution;\n\u00a0 Provide departmental administrative and clerical support;\n\u00a0 Other ad-hoc duties assigned by supervisors\n\nRequirements:\n\n\u00a0 F.5 graduate with 5 passes in HKDSE or above; minimum 1-year working experience;\n\u00a0 Pleasant, courteous with good telephone manner and good communication skills in both English and Chinese;\n\u00a0 Proficient in MS Office and Chinese word processing;\n\u00a0 Punctual, work independently and good at multi-tasking;\n\u00a0 Able to work on Saturday/Sunday occasionally;\n\u00a0 Fresh graduates with some working experience may also be considered.\n\nSalary offered will be commensurate with qualifications and experience. Interested parties, please send CV with details on education and work experience, stating salary history and expected salary, and indicating your earliest availability to the Human Resources Department, 10/F, 1063 King\u2019s Road, Quarry Bay, Hong Kong no later than 4 February 2022. Please quote the job reference on the envelope.\n\nApplicants not invited for interview within 16 weeks from the closing date for application may assume that their applications are unsuccessful. Personal data collected will be treated in strictest confidence and will only be used for recruitment purposes. HKADC reserves the right to consider late applications and not to make appointment for the post advertised. We do not accept applications through e-mail or fax.\n\nHKADC is an Equal Opportunities Employer", "employment_types": ["Full Time", "Permanent"], "selling_points": [], "locations": ["Quarry Bay"], "categories": ["Admin & HR", "Clerical / Admin Staff", "Receptionist", "Public / Civil", "Social Services - Community / Non-profit Organization"], "post_time": "2022-01-17T09:17:02Z", "salary": {"currency": null, "max": null, "min": null, "period": "monthly", "term": null}, "salary_visible": false, "title_keywords": ["assistant"], "responsibilities": ["logistic support", "stationery", "administrative and clerical support", "ad-hoc duties", "incoming and outgoing mails", "answer phone calls"], "requirements": {"degrees": ["hkdse"], "majors": [], "languages": ["english", "chinese"], "language_level": ["proficient", "good"], "hard_skills": ["chinese word processing", "ms office"], "soft_skills": ["communication skills", "courteous", "work independently", "pleasant", "multi-tasking", "telephone manner"], "languages_combined": [{"language": "english", "language_level": ["good"]}, {"language": "chinese", "language_level": ["proficient", "good"]}]}, "experience_required": {"duration": ["minimum 1-year"], "field": []}}, {"job_id": "100003009054636", "location_code": "hk", "company": "Auberge Hospitality Limited", "job_title": "And we are hiring \u2013 Assistant \u2013 Member Services, Discovery Bay Recreation Club", "description": "Responsibilities:\nMonitor the front desk office to ensure efficient and effective operation of our clubhouse\nAssist in membership strategy planning and organizing various functions and activities to the club members\nHandle other ad-hoc function assigned by supervisor\nRequirements:\nDiploma or above, graduated in Hospitality Management will be an advantage\n1 - 2 years relevant work experience, preferably with club or hospitality experience\nStrong leadership and communication skills\nInitiative, willing to learn and take up challenges\nProficiency in both spoken and written English and Chinese\nMore experience will be considered as Senior Assistant \u2013 Member Services\nWe offer an attractive remuneration package and excellent career opportunities to the right candidate. Interested applicants please send your CV by email via \"Apply Now\" or by WhatsApp at 63173527.\nPersonal data provided by job applicants will be used strictly for recruitment purposes only.", "employment_types": ["Full Time", "Permanent"], "selling_points": ["Monitor the front desk office to ensure efficient", "Diploma or above, graduated", "1 - 2 years relevant work experience"], "locations": ["Lantau Island"], "categories": ["Admin & HR", "Receptionist", "Hospitality / F & B", "Hospitality / Hotel Services", "Others"], "post_time": "2022-01-17T10:21:12Z", "salary": {"currency": null, "max": null, "min": null, "period": "monthly", "term": null}, "salary_visible": false, "title_keywords": ["assistant"], "responsibilities": ["ad-hoc", "monitor", "planning"], "requirements": {"degrees": ["diploma or above"], "majors": ["hospitality management"], "languages": ["english", "chinese"], "language_level": ["proficiency"], "hard_skills": [], "soft_skills": ["communication skills", "willing to learn", "leadership", "initiative"], "languages_combined": [{"language": "english", "language_level": ["proficiency"]}, {"language": "chinese", "language_level": ["proficiency"]}]}, "experience_required": {"duration": ["1 - 2 years"], "field": []}}, {"job_id": "100003009054203", "location_code": "hk", "company": "Global Union Ltd", "job_title": "Admin Assistant", "description": "Responsibilities:\n\nUpdating reports and filing documents\nFollow up the project progress\nAnalysis market data\nProvide general admin support\nAny other personal duties as may reasonably be required by the Director\nPerform ad-hoc assignments\n\n\u00a0Requirements:\u00a0\n\nDiploma holder or equivalent or above\nGood command of written and spoken English and Cantonese\nKnowledge in Word and Excel\nIndependent, well-organized, self-motivated with strong sense of responsibility\nFresh graduates or less working experience will be more preferred\nImmediate available is highly preferred\n\n\u00a0We offer attractive salaries and benefits for the right candidates.\n(Personal data collected will be used for recruitment purpose)\n", "employment_types": ["Full Time"], "selling_points": [], "locations": ["Kwai Fong"], "categories": ["Admin & HR", "Clerical / Admin Staff", "Receptionist", "Secretary"], "post_time": "2022-01-17T08:49:08Z", "salary": {"currency": null, "max": null, "min": null, "period": "monthly", "term": null}, "salary_visible": false, "title_keywords": ["admin assistant"], "responsibilities": ["ad-hoc assignments", "analysis", "project progress", "admin support", "reports", "market data"], "requirements": {"degrees": ["diploma holder"], "majors": [], "languages": ["cantonese", "english"], "language_level": ["good command"], "hard_skills": ["excel", "word"], "soft_skills": ["self-motivated", "independent", "well-organized", "sense of responsibility"], "languages_combined": [{"language": "cantonese", "language_level": ["good command"]}, {"language": "english", "language_level": ["good command"]}]}, "experience_required": {"duration": [], "field": []}}, {"job_id": "100003009051132", "location_code": "hk", "company": "JAN Financial Press Limited", "job_title": "Receptionist - Financial Printing (Central, 5 days work)", "description": "Responsibilities:\n\nPerform general reception duties such as greet visitors and guests at the front desk\nHandle phone calls and manage incoming and outgoing couriers and mails\nHandle conference room reservations and scheduling\nReplenish office supplies including stationery, grocery and beverages\nEnsure the tidiness of the reception area, pantry and conference rooms\nProvide general clerical and administrative support\nAd hoc duties as assigned by supervisor\n\nRequirements:\n\nDSE /\u00a0 Diploma or above\nOne year relevant working experience; fresh graduated are also welcome\nFamiliarize with Microsoft Office including Word, excel and Chinese word processing\nGood command of spoken English, Cantonese and Mandarin\u00a0\u00a0\nWilling to learn, self-motivated, good interpersonal skill with pleasant personality\nOvertime working may required with OT pay\nImmediate available is preferred\n\nBenefits:\n\n5 Days Work\nOT Pay\nBank Holiday\nMedical Insurance\u00a0\nDiscretionary Bonus\nWork Location: Central (one minute to MTR station)\n\nWe offer excellent career development opportunities, attractive remuneration and benefits to the right candidate. Interested parties please click \"quick apply\"\u00a0for interview.\n\n*Personal data collected will be used for recruitment purpose only*", "employment_types": ["Full Time", "Permanent"], "selling_points": ["General reception duties, Admin support", "DSE/Diploma, nice working environment", "Fresh graduated is welcomed"], "locations": ["Central"], "categories": ["Admin & HR", "Receptionist", "Banking / Finance", "Financial Services"], "post_time": "2022-01-15T03:07:13Z", "salary": {"currency": null, "max": null, "min": null, "period": "monthly", "term": null}, "salary_visible": false, "title_keywords": ["receptionist"], "responsibilities": ["ad hoc duties", "administrative support", "office supplies", "stationery", "scheduling", "phone calls"], "requirements": {"degrees": ["diploma or above", "dse"], "majors": [], "languages": ["cantonese", "english", "chinese", "mandarin"], "language_level": ["good command"], "hard_skills": ["excel", "chinese word processing", "word", "microsoft office"], "soft_skills": ["pleasant", "self-motivated", "willing to learn", "interpersonal skill"], "languages_combined": [{"language": "cantonese", "language_level": ["good command"]}, {"language": "english", "language_level": ["good command"]}, {"language": "chinese", "language_level": []}, {"language": "mandarin", "language_level": ["good command"]}]}, "experience_required": {"duration": ["one year"], "field": ["relevant working experience"]}}, {"job_id": "100003009054501", "location_code": "hk", "company": "GF Holdings (Hong Kong) Corporation Ltd", "job_title": "Analyst, Office Administration", "description": "Responsibilities\n\nAssist in full spectrum of Office Administration Services including procurement, repair and maintenance, security, housekeeping, carpool, mailing and other routine administration functions.\nWork together with a team consisting receptionist, office assistants and drivers to deliver various administration support services in a professional manner\nHands on experience in managing office space planning and renovation project\nParticipate in organizing company events such as annual meeting, annual dinner, etc\nProvide secretarial support to Company management\nAd-hoc assignment as and when required\nRequirements\n\nDegree in any discipline\nAt least 2 years relevant working experience in office administration\nA good team player with strong communication skills\nWilling to work at weekend and holidays in needed\nProficiency in MS Office and Chinese Character Processing\nGood Commend of both spoken and written English. Fluency in Putonghua\nWe offer attractive remuneration package and fringe benefits to the right candidate. Interested applicants please send detailed resume stating present & expected salaries and date of availability to Human Resources Department by clicking \"APPLY NOW\".\n\nFurther information about our group companies can be found at www.gfgroup.com.hk and www.gf.com.cn.\n\nAll applications will be treated in the strictest confidence and personal data collected will be used for recruitment purpose only.", "employment_types": ["Full Time"], "selling_points": ["2 years experience in office administration", "Willing to work at weekend and holidays in needed", "Fluency in Putonghua"], "locations": ["Sheung Wan"], "categories": ["Admin & HR", "Clerical / Admin Staff", "Receptionist", "Others"], "post_time": "2022-01-17T09:48:42Z", "salary": {"currency": null, "max": null, "min": null, "period": "monthly", "term": null}, "salary_visible": false, "title_keywords": ["analyst"], "responsibilities": ["ad-hoc", "management", "maintenance", "housekeeping", "office administration", "support services", "professional manner", "renovation", "repair", "planning", "secretarial support", "administration"], "requirements": {"degrees": ["degree"], "majors": [], "languages": ["putonghua", "english", "chinese"], "language_level": ["fluency", "proficiency", "good"], "hard_skills": ["processing", "ms office"], "soft_skills": ["communication skills", "good team player"], "languages_combined": [{"language": "putonghua", "language_level": ["fluency"]}, {"language": "english", "language_level": ["good"]}, {"language": "chinese", "language_level": ["proficiency"]}]}, "experience_required": {"duration": ["at least 2 years"], "field": ["office administration", "relevant working experience"]}}, {"job_id": "100003009052889", "location_code": "hk", "company": "\u6674\u5e0c\u6d3b\u52d5\u4e2d\u5fc3", "job_title": "\u5168\u8077\u88dc\u7fd2\u793e\u63a5\u5f85\u54e1", "description": "\u6674\u5e0c\u6d3b\u52d5\u4e2d\u5fc3\u73fe\u8058\u8acb\u5168\u8077\u63a5\u5f85\u54e1\n\n\u8077\u8cac :\n\u8655\u7406\u5b78\u751f\u53ca\u5bb6\u9577\u67e5\u8a62\u53ca\u5b89\u6392\u8abf\u5802\n\u5354\u52a9\u5c0e\u5e2b\u6e96\u5099\u6559\u6750\u53ca\u5354\u52a9\u5c0e\u5e2b\u6559\u5b78\n\u7ba1\u7406\u8ab2\u5802\u79e9\u5e8f\n\u8655\u7406\u5bb6\u9577\u5831\u540d\u4e8b\u5b9c\n\u6574\u7406\u6587\u4ef6\u53ca\u4e00\u822c\u6587\u66f8\u8655\u7406\n\u8655\u7406\u6d3b\u52d5\u4e2d\u5fc3\u65e5\u5e38\u5927\u5c0f\u4e8b\u52d9\n\n\u8077\u4f4d\u8981\u6c42 :\n\u4e2d\u516d\u7562\u696d\u6216\u4ee5\u4e0a\u7a0b\u5ea6\n\u61c2\u4e2d\u82f1\u6253\u5b57,\u719f\u8b58\u57fa\u672c\u96fb\u8166\u64cd\u4f5c(Excel, Word)\n\u5b88\u6642\u3001\u76e1\u8cac\u3001\u6709\u611b\u5fc3\u3001\u559c\u6b61\u8207\u5c0f\u670b\u53cb\u76f8\u8655\u3001\u6709\u8010\u6027\u3001\u7d30\u5fc3\u3001\u826f\u597d\u6e9d\u901a\u6280\u5de7\u3001\n\u6709\u76f8\u95dc\u5de5\u4f5c\u7d93\u9a57\u8005\u512a\u5148\n\n\u5de5\u4f5c\u6642\u9593 :\n\u516d\u5929\u5de5\u4f5c\u65e5\n\u661f\u671f\u4e00\u81f3\u4e94 (12:00-20:00) \u53ca\u661f\u671f\u516d(12:00-19:00)\n\u9022\u661f\u671f\u65e5\u53ca\u516c\u773e\u5047\u671f\u4f11\u606f\n\n\u5de5\u4f5c\u5730\u9ede:\n\u725b\u982d\u89d2\n\n\u85aa\u916c\uff1a\n$11,000 - $13,000 (\u6bcf\u6708)\u00a0\n\n\u6709\u8207\u8da3\u8005\u8acb\u628a\u5c65\u6b77\u8868\u7528WhatsApp\u767c\u523095377675\u6216\u6309\u4ee5\u4e0bApply Now\u7533\u8acb, \u6211\u5011\u6703\u81f4\u96fb\u76f8\u7d04\u9762\u8a66\u6642\u9593\u3002", "employment_types": ["Full Time"], "selling_points": ["\u8655\u7406\u5b78\u751f\u3001\u5bb6\u9577\u67e5\u8a62\u53ca\u6d3b\u52d5\u4e2d\u5fc3\u65e5\u5e38\u5927\u5c0f\u4e8b\u52d9", "\u826f\u597d\u4e2d\u3001\u82f1\u6587\u66f8\u5beb\uff1b\u53ef\u5373\u6642\u4e0a\u73ed\u6216\u6709\u76f8\u95dc\u7d93\u9a57\u512a\u5148", "\u661f\u671f\u65e5\u53ca\u516c\u773e\u5047\u671f\u4f11\u606f"], "locations": ["Ngau Tau Kok"], "categories": ["Admin & HR", "Receptionist"], "post_time": "2022-01-17T04:26:59Z", "salary": {"currency": "HKD", "max": 13999, "min": 11000, "period": "monthly", "term": null}, "salary_visible": true, "title_keywords": [], "responsibilities": [], "requirements": {"degrees": [], "majors": [], "languages": [], "language_level": [], "hard_skills": ["word"], "soft_skills": [], "languages_combined": []}, "experience_required": {"duration": [], "field": []}}, {"job_id": "100003009032852", "location_code": "hk", "company": "Kin Ming Construction Company Ltd", "job_title": "\u6587\u54e1 Clerk", "description": "\u5730\u5340 :\u706b\u70ad\n\n\u8077\u8cac :\u4e00\u822c\u6587\u66f8\u5de5\u4f5c\uff1b\u6587\u4ef6\u5b58\u6a94\u53ca\u8655\u7406\uff0c\u8cc7\u6599\u8f38\u5165\uff1b\u5354\u52a9\u90e8\u9580\u8655\u7406\u3001\u8ddf\u9032\u63a1\u8cfc\u8a02\u55ae\u3001\u6536\u767c\u3001\u6574\u7406\u3001\u8a18\u9304\u5de5\u7a0b\u6587\u4ef6\u53ca\u7b49\u5de5\u4f5c\uff1b\u63a5\u807d\u96fb\u8a71\uff0c\u5b89\u6392\u901f\u905e\n\u8cc7\u6b77 :\u4e2d\u516d\u7a0b\u5ea6; 2\u5e74\u7d93\u9a57; \u826f\u597d\u7cb5\u8a9e; \u4e00\u822c\u666e\u901a\u8a71; \u826f\u597d\u82f1\u8a9e\u512a\u5148; \u61c2\u8b80\u5beb\u4e2d\u6587; \u61c2\u8b80\u5beb\u82f1\u6587; \u61c2Microsoft Office; \u61c2MS Word; \u61c2MS Outlook; \u61c2MS Excel; \u61c2\u4e2d\u82f1\u6587\u96fb\u8166\u64cd\u4f5c; \u51772\u5e74\u6216\u4ee5\u4e0a\u76f8\u95dc\u5de5\u4f5c\u7d93\u9a57\uff0c\u826f\u597d\u6e9d\u901a\u6280\u5de7\u53ca\u670d\u52d9\u614b\u5ea6\uff0c\u5de5\u4f5c\u7a4d\u6975\u4e3b\u52d5\u3001\u76e1\u8cac\u3001\u52e4\u596e\n\u5f85\u9047 :\u6709\u9280\u884c\u5047\u671f \u53ca\u670d\u52d9\u6eff3\u500b\u6708\u6709\u9580\u8a3a\u91ab\u7642\u54ad, \u6bcf\u9031\u5de5\u4f5c5\u5929\u534a\n\u7533\u8acb\u9808\u77e5 :\u6c42\u8077\u8005\u53ef\u96fb\u90f5\u5c65\u6b77\u8868\u7d66\u5065\u660e\u5efa\u7bc9\u6709\u9650\u516c\u53f8\u3002\u5982\u8981\u7d22\u53d6\u6536\u96c6\u500b\u4eba\u8cc7\u6599\u8072\u660e, \u8acb\u8207\u8d99\u5c0f\u59d0(Email)\u806f\u7d61\u3002", "employment_types": ["Full Time", "Permanent"], "selling_points": [], "locations": ["Shatin Area"], "categories": ["Admin & HR", "Clerical / Admin Staff", "Receptionist", "Others"], "post_time": "2022-01-16T21:50:08Z", "salary": {"currency": "HKD", "max": 13999, "min": 11000, "period": "monthly", "term": null}, "salary_visible": true, "title_keywords": ["clerk", "\u6587\u54e1"], "responsibilities": [], "requirements": {"degrees": [], "majors": [], "languages": [], "language_level": [], "hard_skills": ["excel", "outlook", "word"], "soft_skills": [], "languages_combined": []}, "experience_required": {"duration": [], "field": []}}, {"job_id": "100003009053903", "location_code": "hk", "company": "Bacera Co. Pty Limited", "job_title": "Administrative Assistant (5-days work week)", "description": "Requirements:\n\nF.5 Standard or above\nMinimum 2 years working experience in office reception & administration\nPleasant personality and good telephone manner\nGood command of spoken English & Mandarin\nProficient in MS Office and Chinese Word Processing\nExcellent analytical and problem solving skills\nAble to work effectively both independently and in a team environment\nAble to work directly with business managers, with little or no direct development management supervision\nStrong verbal and written communication skills with the ability to interact and communicate with various levels of personnel\nPleasant and willing to learn\nWilling to perform overtime work\nImmediate available is preferred\nFresh graduate will be considered\n\n\n\nBenefits\n\nMedical welfare and bonus will be available after probation period is completed.\n\nInterested parties please send full resume giving details of expected salaries and availability by clicking \"Apply Now\"\n\nPersonal data collected will be used for recruitment purpose only.", "employment_types": ["Full Time", "Permanent"], "selling_points": ["F.5 Standard or above", "5-days work, Medical welfare and bonus", "Proficient in MS Office & Chinese Word Processing"], "locations": ["Sheung Wan"], "categories": ["Admin & HR", "Clerical / Admin Staff", "Receptionist", "Others", "Student / Fresh Graduate / No Experience"], "post_time": "2022-01-17T07:43:50Z", "salary": {"currency": null, "max": null, "min": null, "period": "monthly", "term": null}, "salary_visible": false, "title_keywords": ["administrative assistant"], "responsibilities": ["communication", "management", "communicate with", "administration"], "requirements": {"degrees": ["fresh graduate"], "majors": [], "languages": ["english", "chinese", "mandarin"], "language_level": ["good command", "proficient"], "hard_skills": ["no", "problem solving skills", "chinese word processing", "ms office"], "soft_skills": ["work effectively", "communication skills", "independently", "willing to learn", "pleasant", "analytical and problem solving skills", "willing to perform overtime work", "telephone manner"], "languages_combined": [{"language": "english", "language_level": ["good command"]}, {"language": "chinese", "language_level": ["proficient"]}, {"language": "mandarin", "language_level": ["good command"]}]}, "experience_required": {"duration": ["minimum 2 years"], "field": ["administration"]}}, {"job_id": "100003009052301", "location_code": "hk", "company": "Hong Kong World Star Technology Limited", "job_title": "General Clerk \uff08Full time / Part time)", "description": "Requirements:\n\nForm 5 or above, one year relevant experience in office administration duties\nGood interpersonal skills, telephone manner and communication skills\nGood computer skills including Microsoft Word, Excel and PowerPoint, knowledge of Chinese Word Processing would be an advantage\nGood Chinese and English\nResponsibilities:\n\nPrepare general clerical duties including filing, sorting, data entry\nProvide administrative and clerical support\nAssist with ad hoc projects\nPerform other duties as assigned", "employment_types": ["Full Time", "Part Time"], "selling_points": ["5 Days Work Week", "Form 5 or above", "1yr relevant exp in office administration duties"], "locations": ["Wan Chai"], "categories": ["Admin & HR", "Clerical / Admin Staff", "Receptionist", "Others"], "post_time": "2022-01-17T04:15:45Z", "salary": {"currency": null, "max": null, "min": null, "period": "monthly", "term": null}, "salary_visible": false, "title_keywords": ["general clerk"], "responsibilities": ["perform other duties", "ad hoc projects", "administrative and clerical support", "data entry"], "requirements": {"degrees": ["form 5 or above"], "majors": [], "languages": ["english", "chinese"], "language_level": ["advantage", "good"], "hard_skills": ["excel", "microsoft word", "chinese word processing", "powerpoint", "computer skills"], "soft_skills": ["communication skills", "interpersonal skills", "telephone manner"], "languages_combined": [{"language": "english", "language_level": ["good"]}, {"language": "chinese", "language_level": ["advantage", "good", "good"]}]}, "experience_required": {"duration": ["one year"], "field": ["office administration", "relevant experience"]}}, {"job_id": "100003009054013", "location_code": "hk", "company": "The Hong Kong Polytechnic University", "job_title": "\u8a3a\u6240\u52a9\u7406 (\u4e2d\u91ab\u90e8)", "description": "\u9999\u6e2f\u7406\u5de5\u5927\u5b78\n\n\u5927\u5b78\u91ab\u7642\u4fdd\u5065\u8655\n\n\u8a3a\u6240\u52a9\u7406 (\u4e2d\u91ab\u90e8) (\u7de8\u865f\uff1a22011704-IE)\n\n\u8077\u8cac\u5305\u62ec\ufe30\n\n(\u4e00)\u00a0\u00a0\u00a0\u00a0\u00a0\u00a0 \u8ca0\u8cac\u8a3a\u6240\u63a5\u5f85\u5de5\u4f5c\uff0c\u5305\u62ec\u9810\u7d04\u3001\u767b\u8a18\u3001\u6536\u8cbb\u3001\u8655\u7406\u91ab\u7642\u8a18\u9304\u53ca\u76f8\u95dc\u670d\u52d9\uff1b\n\n\n(\u4e8c)\u00a0\u00a0\u00a0\u00a0\u00a0\u00a0 \u89e3\u7b54\u4e00\u822c\u96fb\u8a71\u67e5\u8a62\u6216\u50b3\u9054\u8aee\u8a62\u4e88\u6709\u95dc\u54e1\u5de5\u4f5c\u51fa\u8ddf\u9032\uff1b\n\n\n(\u4e09)\u00a0\u00a0\u00a0\u00a0\u00a0\u00a0 \u914d\u767c\u8655\u65b9\u4e2d\u85e5\u7d66\u75c5\u4eba\uff1b\n\n\n(\u56db)\u00a0\u00a0\u00a0\u00a0\u00a0\u00a0 \u5354\u52a9\u76e4\u9ede\u3001\u5eab\u5b58\u53ca\u8a02\u8cfc\u4e2d\u85e5\u3001\u91dd\u7078\u3001\u9aa8\u50b7\u91ab\u7642\u7528\u54c1\uff1b\n\n\n(\u4e94)\u00a0\u00a0\u00a0\u00a0\u00a0\u00a0 \u5354\u52a9\u4e2d\u91ab\u5e2b\u8655\u7406\u6709\u95dc\u91dd\u7078\u53ca\u9aa8\u50b7\u8a3a\u7642\u5de5\u4f5c\uff1b\u53ca\n\n\n(\u516d)\u00a0\u00a0\u00a0\u00a0\u00a0\u00a0 \u5354\u52a9\u63a8\u5ee3\u4e2d\u91ab\u5065\u5eb7\u6559\u80b2\u5ba3\u50b3\u6d3b\u52d5\u3002\n\n\u53d7\u8058\u8005\u6216\u9700\u8f2a\u73ed\u5de5\u4f5c\u3002\u00a0\n\n\u61c9\u5fb5\u8005\u9808\u5177\ufe30\n\n(\u4e00)\u00a0\u00a0\u00a0\u00a0\u00a0\u00a0 \u4e2d\u4e94\u7562\u696d\u6216\u4ee5\u4e0a\uff1b\n\n\n(\u4e8c)\u00a0\u00a0\u00a0\u00a0\u00a0\u00a0 \u4e00\u5e74\u4ee5\u4e0a\u5728\u9999\u6e2f\u914d\u767c\u4e2d\u85e5\u6750\u7684\u5de5\u4f5c\u7d93\u9a57\uff1b\n\n\n(\u4e09)\u00a0\u00a0\u00a0\u00a0\u00a0\u00a0 \u826f\u597d\u4eba\u969b\u95dc\u4fc2\u53ca\u6e9d\u901a\u6280\u5de7(\u80fd\u64cd\u5ee3\u6771\u8a71\u3001\u666e\u901a\u8a71\u53ca\u7c21\u55ae\u82f1\u8a9e)\uff1b\u53ca\n\n\n(\u56db)\u00a0\u00a0\u00a0\u00a0\u00a0\u00a0 \u57fa\u672c\u96fb\u8166\u64cd\u4f5c\u77e5\u8b58\u3002\n\n\u6301\u6709\u7531\u9999\u6e2f\u4efb\u4f55\u4e00\u6240\u5927\u5b78\u6216\u8077\u696d\u8a13\u7df4\u5c40\u9812\u767c\u7684\u4e2d\u85e5\u8b49\u66f8\u53ca\u5c0d\u4e2d\u91ab\u7d93\u7d61\u7a74\u4f4d\u7565\u6709\u8a8d\u8b58\u8005\uff0c\u5c07\u7372\u512a\u5148\u8003\u616e\u3002\n\n\u85aa\u91d1\u53ca\u670d\u52d9\u689d\u4ef6\n\n\n\u672c\u8077\u4f4d\u5c07\u4ee5\u5408\u7d04\u5f62\u5f0f\u8058\u8acb\u3002\u53d7\u8058\u8005\u53ef\u65bc\u5408\u7d04\u5713\u6eff\u5c65\u884c\u5f8c\uff0c\u4eab\u6709\u7d04\u6eff\u916c\u91d1\uff1b\u7e8c\u7d04\u8207\u5426\u7531\u96d9\u65b9\u5354\u5b9a\u3002\u5927\u5b78\u4e26\u70ba\u50f1\u54e1\u63d0\u4f9b\u512a\u539a\u798f\u5229\u3002\u7533\u8acb\u8005\u9808\u5217\u660e\u73fe\u8077\u85aa\u91d1\u53ca\u8981\u6c42\u4e4b\u5f85\u9047\u3002\n\n\u7533\u8acb\u65b9\u6cd5\n\n\n\u8acb\u5c07\u586b\u59a5\u4e4b\u7533\u8acb\u8868\u683c\u5bc4\u56de\u9999\u6e2f\u4e5d\u9f8d\u7d05\u78e1\u9999\u6e2f\u7406\u5de5\u5927\u5b78\u674e\u5609\u8aa0\u6a13\u5341\u4e09\u6a13\u4eba\u529b\u8cc7\u6e90\u8655\u6216\u96fb\u90f5\u00a0\u00a0\u00a0 \u81f3Apply Now\u3002\u7533\u8acb\u8868\u683c\u53ef\u5f9ehttps://www.polyu.edu.hk/hro/careers/guidelines_and_forms/forms \u4e0b\u8f09\u3002\u7504\u9078\u7a0b\u5e8f\u5c07\u65bc\u4e8c\u96f6\u4e8c\u4e8c\u5e74\u4e00\u6708\u4e8c\u5341\u516b\u65e5\u958b\u59cb\uff0c\u76f4\u81f3\u8993\u5f97\u9069\u7576\u4eba\u9078\u70ba\u6b62\u3002\u6709\u95dc\u672c\u5927\u5b78\u6536\u96c6\u500b\u4eba\u8cc7\u6599\u4ee5\u4f5c\u62db\u8058\u7528\u9014\u7684\u8072\u660e\uff0c\u53ef\u700f\u89bd\u4ee5\u4e0b\u7db2\u5740https://www.polyu.edu.hk/hro/careers/guidelines_and_forms/pics_for_recruitment\u3002\n\n\u7406\u5927\u70ba\u5e73\u7b49\u6a5f\u6703\u50f1\u4e3b\uff0c\u81f4\u529b\u63a8\u52d5\u591a\u5143\u5171\u878d\u6587\u5316\u3002\u6240\u6709\u5408\u8cc7\u683c\u7533\u8acb\u4eba\u58eb\uff0c\u4e0d\u8ad6\u5176\u6027\u5225\u3001\u65cf\u88d4\u3001\u570b\u7c4d\u3001\u5bb6\u5ead\u5d17\u4f4d\u53ca\u8eab\u9ad4\u53ca\u7cbe\u795e\u6b98\u75be\uff0c\u5747\u6703\u7372\u8058\u4efb\u8003\u616e\u3002", "employment_types": ["Full Time"], "selling_points": [], "locations": ["Not Specified"], "categories": ["Admin & HR", "Receptionist", "Others", "Medical Services", "Others"], "post_time": "2022-01-17T08:12:43Z", "salary": {"currency": null, "max": null, "min": null, "period": "monthly", "term": null}, "salary_visible": false, "title_keywords": ["\u8a3a\u6240\u52a9\u7406"], "responsibilities": [], "requirements": {"degrees": [], "majors": [], "languages": [], "language_level": [], "hard_skills": [], "soft_skills": [], "languages_combined": []}, "experience_required": {"duration": [], "field": []}}, {"job_id": "100003009047811", "location_code": "hk", "company": "Kerry Properties Limited", "job_title": "Receptionist (MegaBox)", "description": "What You'll Do (Job Summary and Key Roles & Responsibilities)\n\nKey Responsibilities\n\nPerform general receptionist duties\nAnswer telephone calls and manage meeting rooms scheduling\u00a0\nGreet guests and visitors in a professional manner\nCoordinate incoming and outgoing mails, documents and courier services\nProvide office administrative support\nPerform other ah-hoc tasks as assigned\n\nWho You'll Work With\n\n\nYou will work with internal & external parties to provide excellent services.\n\n\nWho You Are (Competencies, Experience, Professional Qualifications etc)\u00a0\n\n\nCompetencies\n\nKPL\u2019s Ambassador \u2013 Makes a positive first impression. \u00a0Presents a confident and professional brand that reflects the quality and values expected of a KPL ambassador\nShows Empathy and Respect \u2013 Develops meaningful relationships with clients and and colleagues by understanding how they feel and showing empathy care and respect in all interactions with them\nCustomer oriented \u2013 Understands and delivers on different customer segments and key stakeholder expectations.\nDSE or above\n1 - 2 years\u2019 relevant working experience\nGood command in spoken English, Cantonese and Putonghua\u00a0\nKnowledge of PC applications including MS Office and Chinese Word Processing\nGood telephone manner and interpersonal skills\nPolite, pleasant, good customer service attitude\nImmediately available preferred", "employment_types": ["Full Time"], "selling_points": ["Top-tier Property Developer", "Promising Career Path", "Competitive Compensation Package"], "locations": ["Kowloon Bay"], "categories": ["Admin & HR", "Receptionist"], "post_time": "2022-01-14T03:57:06Z", "salary": {"currency": null, "max": null, "min": null, "period": "monthly", "term": null}, "salary_visible": false, "title_keywords": ["receptionist"], "responsibilities": ["administrative support", "external parties", "professional manner", "quality", "coordinate", "scheduling", "customer service", "incoming and outgoing mails"], "requirements": {"degrees": ["dse"], "majors": [], "languages": ["cantonese", "putonghua", "english", "chinese"], "language_level": ["good command"], "hard_skills": ["chinese word processing", "pc applications", "ms office", "professional qualifications"], "soft_skills": ["outgoing", "confident", "polite", "telephone manner", "pleasant", "customer service", "interpersonal skills", "empathy", "positive"], "languages_combined": [{"language": "cantonese", "language_level": ["good command"]}, {"language": "putonghua", "language_level": ["good command"]}, {"language": "english", "language_level": ["good command"]}, {"language": "chinese", "language_level": []}]}, "experience_required": {"duration": ["1 - 2 years"], "field": ["relevant working experience"]}}, {"job_id": "100003009053420", "location_code": "hk", "company": "Taipei Fubon Commercial Bank Co., Ltd", "job_title": "\u517c\u8077\u884c\u653f\u52a9\u7406 (Part-time)", "description": "\u8077\u8cac\uff1a\u8ca0\u8cac\u63a5\u5f85\u8655\u3001\u7e3d\u6a5f\u3001\u5354\u52a9\u8655\u7406\u4e00\u822c\u6587\u66f8\u5de5\u4f5c\u5982:\u8cc7\u6599\u8f38\u5165\u3001\u6838\u5c0d\u6587\u4ef6\u3001\u4fdd\u5b58\u6a94\u6848\u53ca\u8a18\u9304;\n\n\u8cc7\u6b77\uff1a\u5c08\u4e0a\u6559\u80b2\u7a0b\u5ea6\u6216\u4ee5\u4e0a; \u826f\u597d\u7cb5\u8a9e; \u826f\u597d\u666e\u901a\u8a71; \u61c2\u8b80\u5beb\u4e2d\u6587; \u61c2\u8b80\u5beb\u82f1\u6587\n\n\u5de5\u4f5c\u671f\u9593\uff1a 01/2022 \u81f3 12/2022\u00a0\n\n\u5de5\u4f5c\u6642\u9593\uff1a\u661f\u671f\u4e00\u81f3\u4e94\uff0c\u4e0a\u53489\u6642\u81f3\u4e0b\u53486\u6642\uff0c\u6bcf\u90313-5\u65e5\uff0c\u6bcf\u65e5 8 \u5c0f\u6642\uff08\u5f48\u6027\u5de5\u6642\uff09", "employment_types": ["Part Time", "Temporary"], "selling_points": [], "locations": ["Tsim Sha Tsui"], "categories": ["Admin & HR", "Clerical / Admin Staff", "Receptionist"], "post_time": "2022-01-17T06:57:41Z", "salary": {"currency": null, "max": null, "min": null, "period": "hourly", "term": null}, "salary_visible": false, "title_keywords": [], "responsibilities": [], "requirements": {"degrees": [], "majors": [], "languages": [], "language_level": [], "hard_skills": [], "soft_skills": [], "languages_combined": []}, "experience_required": {"duration": [], "field": []}}, {"job_id": "100003009052816", "location_code": "hk", "company": "Hong Kong Golf & Tennis Academy Management Co. Ltd", "job_title": "Guest Relations Officer (All Day Dining Restaurant)", "description": "Responsibilities:\nPerform and manage reception duties\n\nManage reservations, greet guests cordially, plan table placements and escort customers to their tables\n\nSet up, organize and coordinate private events and parties if required\n\nProvide excellent customer service to customers\n\nSupport daily operation of the restaurant\n\nRequirements:\nDiploma or above\n\nMinimum 3 years of relevant experience within F&B / hospitality industries\n\nFull-service experience is highly preferred\n\nGood team player and great communication skills\n\nFluent in both Cantonese and English (with at least Fair Mandarin)\n\nAble to work for flexible hours (evenings / weekends / holidays)\n\nWe offer an attractive remuneration package and excellent career prospects to the right candidate. Please send full resume including the current & expected salary and the contact information by clicking \"APPLY NOW\".\n\n(Personal data collected will be used for recruitment purpose only)", "employment_types": ["Full Time"], "selling_points": ["Perform and manage reception duties", "Provide excellent customer service to customers", "Minimum 3 years of relevant experience"], "locations": ["Not Specified"], "categories": ["Admin & HR", "Clerical / Admin Staff", "Receptionist", "Hospitality / F & B", "Hospitality / Hotel Services"], "post_time": "2022-01-17T04:09:39Z", "salary": {"currency": null, "max": null, "min": null, "period": "monthly", "term": null}, "salary_visible": false, "title_keywords": ["guest relations officer"], "responsibilities": ["coordinate", "customer service", "daily operation", "plan"], "requirements": {"degrees": ["diploma or above"], "majors": [], "languages": ["cantonese", "english", "mandarin"], "language_level": ["fluent"], "hard_skills": [], "soft_skills": ["flexible", "communication skills", "good team player"], "languages_combined": [{"language": "cantonese", "language_level": ["fluent"]}, {"language": "english", "language_level": ["fluent"]}, {"language": "mandarin", "language_level": []}]}, "experience_required": {"duration": ["minimum 3 years"], "field": ["hospitality industries", "f&b", "relevant experience"]}}, {"job_id": "100003009047633", "location_code": "hk", "company": "Defond Electrical Industries Limited", "job_title": "Receptionist", "description": "Duties:\n\nPerform receptionist duties including greeting guests and telephone inquiries;\nHandle incoming and outgoing mails, courier documents and postage arrangement;\nCoordinate conference rooms bookings;\nProvide general administration and clerical support;\nPerform and assist in ad hoc projects as assigned.\n\nRequirements:\n\nHigher diploma or above in any disciplines;\nMinimum 3 years of relevant experience in sizable company;\nProficient in MS Office and Chinese Word Processing;\nGood command of written and spoken English and Chinese;\nPleasant personality with excellent telephone manner;\nGood communication and interpersonal skills;\nStrong sense of responsibility, self-motivated, and detail-oriented.\n\n\n\nInterested parties please apply in full resume including current and expected salary by clicking\u00a0\"Apply now\"\n\nFor more information, please visit our website:\u00a0http://www.defondetech.com\n\nPersonal data collected will be used for recruitment purpose only.", "employment_types": ["Full Time"], "selling_points": ["5-days work per week", "13-month salary", "Near MTR station"], "locations": ["Chai Wan"], "categories": ["Admin & HR", "Receptionist"], "post_time": "2022-01-14T03:37:31Z", "salary": {"currency": null, "max": null, "min": null, "period": "monthly", "term": null}, "salary_visible": false, "title_keywords": ["receptionist"], "responsibilities": ["clerical support", "coordinate", "ad hoc projects", "incoming and outgoing mails", "administration"], "requirements": {"degrees": ["higher diploma or above"], "majors": ["any disciplines"], "languages": ["english", "chinese"], "language_level": ["good command", "proficient"], "hard_skills": ["chinese word processing", "ms office"], "soft_skills": ["self-motivated", "sense of responsibility", "pleasant", "detail-oriented", "communication and interpersonal skills", "telephone manner"], "languages_combined": [{"language": "english", "language_level": ["good command"]}, {"language": "chinese", "language_level": ["good command", "proficient"]}]}, "experience_required": {"duration": ["minimum 3 years"], "field": ["relevant experience"]}}, {"job_id": "100003009052623", "location_code": "hk", "company": "Sompo Insurance (Hong Kong) Company Limited", "job_title": "Senior Administration Officer", "description": "Responsibilities\n\n\nIn charge of office maintenance and repair coordination, insurance and licensing renewal, vendor management in a professional manner\nBeing the first contact point with building management office\nMonitor external contractors / service providers for effective maintenance of various systems\nResponsible for managing inventory and document storage\nAct as\u00a0the\u00a0project lead\u00a0for\u00a0office renovation and relocation\nAssist in planning and executing company events and functions (eg: Annual dinner, Christmas party & other staff activities)\nMonitor office expenditure and budgets to enhance cost efficiency\nPerform backup reception duties when necessary\nRequirements\nHolder of Diploma in any discipline\nMinimum of 5 years\u2019 relevant work experience in office administration with supervising a small team and monitoring outsourced contractors\nExposure in office relocation / renovation is\u00a0a must\nProactive with a can-do attitude, attention to details, a strong sense of responsibility\nAble to resolve problems independently\nImmediate availability would be a great advantage\n\nWe offer 5-day week and competitive remuneration package commensurate with qualification and experience.\u00a0 Please send full resume with details of current and expected salary to HR Department by clicking \"Apply Now\".\n\nPersonal data will be used for recruitment purpose only.", "employment_types": ["Full Time", "Permanent"], "selling_points": ["Provide office administration services", "Office relocation / renovation experience prefer", "Immediate available would be advantage"], "locations": ["Quarry Bay"], "categories": ["Admin & HR", "Administration / Operation Manager", "Clerical / Admin Staff", "Receptionist"], "post_time": "2022-01-17T03:35:10Z", "salary": {"currency": null, "max": null, "min": null, "period": "monthly", "term": null}, "salary_visible": false, "title_keywords": ["senior administration officer"], "responsibilities": ["budgets", "management", "cost", "maintenance", "inventory", "systems", "professional manner", "monitor", "renovation", "building management", "repair", "executing", "contact", "coordination", "insurance", "planning"], "requirements": {"degrees": ["diploma"], "majors": [], "languages": [], "language_level": [], "hard_skills": ["small"], "soft_skills": ["independently", "sense of responsibility", "can-do attitude", "attention to details", "proactive"], "languages_combined": []}, "experience_required": {"duration": ["minimum of 5 years"], "field": ["office administration", "team"]}}, {"job_id": "100003009046836", "location_code": "hk", "company": "", "job_title": "Receptionist", "description": "Job Requirements:\n\nForm 5 or above;\nGood command of spoken English, Chinese and Putonghua;\nFamiliar with computer knowledge and MS Office;\n\nJob Description:\n\nPerform reception duties and office admin;\nHandle incoming call, room booking and great client;\nOutdoor work and other ad hoc duties\u00a0may be required;\n\nAttractive salary with medical benefits and provident fund provided. For interested candidates, please contact\u00a0Grandall Zimmern Law Firm. \u2013 Attn. : HR Department at 14/F., The Hong Kong Club Building, 3A Chater Road, Central, Hong Kong\u00a0\u00a0\n", "employment_types": ["Full Time"], "selling_points": [], "locations": ["Central"], "categories": ["Admin & HR", "Clerical / Admin Staff", "Receptionist"], "post_time": "2022-01-14T01:25:53Z", "salary": {"currency": null, "max": null, "min": null, "period": "monthly", "term": null}, "salary_visible": false, "title_keywords": ["receptionist"], "responsibilities": ["ad hoc duties", "outdoor work", "booking"], "requirements": {"degrees": ["form 5 or above"], "majors": [], "languages": ["putonghua", "english", "chinese"], "language_level": ["good command"], "hard_skills": ["ms office"], "soft_skills": [], "languages_combined": [{"language": "putonghua", "language_level": ["good command"]}, {"language": "english", "language_level": ["good command"]}, {"language": "chinese", "language_level": ["good command"]}]}, "experience_required": {"duration": [], "field": []}}, {"job_id": "100003009048035", "location_code": "hk", "company": "Fangyuan Financial (Hong Kong) Limited", "job_title": "Receptionist", "description": "Location:\u00a0 \u00a0\u00a0\u00a0\u00a0\u00a0\u00a0\u00a0 Central, Hong Kong\n\nPosition: \u00a0\u00a0\u00a0\u00a0\u00a0\u00a0\u00a0\u00a0\u00a0 Permanent\n\nResponsibilities:\n\n\nPerform receptionist duties in professional manner;\nMaintain workspaces at a high standard at all times;\nProvide full spectrum of office administrative and clerical support;\nHandle ad-hoc tasks as assigned.\n\n\u00a0Requirements:\n\n\nExperiences in\u00a0financial or professional services preferred;\nDetail-minded with a can-do attitude;\nExcellent command in written and spoken English and Mandarin.\n\n\u00a0Additional Information and Application Method:\n\nWe offer competitive remuneration package: 5-days work week, minimum 15 days annual paid leave, medical benefit, complimentary office lunch, on the job training and a stable harmonious working environment.\u00a0\n\nInterested parties please send your resume in English and Chinese with\u00a0expected salary\u00a0toby clicking \"APPLY NOW\".\n\n\nAll information received will be kept in strict confidence and only for employment-related purpose.\n\nPersonal Information Collection Statement pertaining to Recruitment:\n\nAll information received will be kept in strict confidence and only for employment-related purpose. The personal data collected will be used to assess your suitability to assume the job duties of the position for which you have applied and to determine preliminary remuneration, benefits package to be discussed with you subject to selection for the position. It is our policy to retain the personal data of unsuccessful applicants for future recruitment purposes for a period of two years.\n\nUnder the Personal Data (Privacy) Ordinance, you have a right to request access to, and to request correction of, your personal data in relation to your application. If you wish to exercise these rights, please complete the \u201cData Access Request Form\u201d specified by the Privacy Commissioner for Personal Data and forward it to HR personnel.\n", "employment_types": ["Full Time"], "selling_points": ["Receptionist", "Central", "Competitive benefit"], "locations": ["Central"], "categories": ["Admin & HR", "Clerical / Admin Staff", "Personal / Executive Assistant", "Receptionist"], "post_time": "2022-01-14T04:34:54Z", "salary": {"currency": null, "max": null, "min": null, "period": "monthly", "term": null}, "salary_visible": false, "title_keywords": ["receptionist"], "responsibilities": ["ad-hoc tasks", "maintain", "professional manner", "administrative and clerical support"], "requirements": {"degrees": [], "majors": [], "languages": ["english", "mandarin"], "language_level": ["excellent"], "hard_skills": [], "soft_skills": ["detail-minded", "stable", "harmonious", "can-do attitude"], "languages_combined": [{"language": "english", "language_level": ["excellent"]}, {"language": "mandarin", "language_level": ["excellent"]}]}, "experience_required": {"duration": [], "field": ["financial"]}}, {"job_id": "100003009048680", "location_code": "hk", "company": "Henderson Land Development Company Limited", "job_title": "RECEPTIONIST", "description": "Ref. No.: JDB/HLD02/REC\u00a0\n\nHKDSE or above\nMinimum 2 years\u2019 relevant experience in sizable organizations, candidates with customer services experience in other industries will also be considered\nFluency in spoken English and Chinese including Putonghua\nResponsible for greeting guests, handling incoming calls, managing conference room booking and guests registration\nKnowledge of PC applications including Chinese word-processing\nPresentable with pleasant personality and good telephone manner\n\nAttractive salary and fringe benefits will be offered to the successful candidates. Please apply with full resume by mail to\u00a0Human Resources Department, Henderson Land Development Co. Ltd., 71/F, Two International Finance Centre, 8 Finance Street, Central, Hong Kong\u00a0or by fax at\u00a02905 1855\u00a0or visit our homepage at\u00a0http://www.hld.com\u00a0or\u00a0by clicking \"Apply Now\".\n\n(Please quote the ref. no. on letter)\n\nPersonal data provided by job applicants will be used for recruitment purpose only.", "employment_types": ["Full Time", "Permanent"], "selling_points": ["Medical Allowance", "Education Allowance", "Free Lunch"], "locations": ["Central"], "categories": ["Admin & HR", "Receptionist", "Others", "Property / Real Estate", "Others"], "post_time": "2022-01-14T07:02:01Z", "salary": {"currency": null, "max": null, "min": null, "period": "monthly", "term": null}, "salary_visible": false, "title_keywords": ["receptionist"], "responsibilities": ["booking", "customer services"], "requirements": {"degrees": ["hkdse"], "majors": [], "languages": ["putonghua", "english", "chinese"], "language_level": ["fluency"], "hard_skills": ["no", "chinese word-processing", "pc applications"], "soft_skills": ["pleasant", "telephone manner", "responsible", "presentable"], "languages_combined": [{"language": "putonghua", "language_level": ["fluency"]}, {"language": "english", "language_level": ["fluency"]}, {"language": "chinese", "language_level": ["fluency"]}]}, "experience_required": {"duration": ["minimum 2 years"], "field": ["relevant experience", "customer services"]}}, {"job_id": "100003009051090", "location_code": "hk", "company": "Central Medical Practice Limited", "job_title": "Clinic Receptionist", "description": "Passed DSE or above\nTwo to three years working experience preferred\nWith clinic experience and good customer service skill is an advantage\nFluent in English and Cantonese, Mandarin is an advantage\nAnswering telephone calls\nArranging the appointment for patients\nDoing registration for patients\nRegistration for patient\u2019s medical cards\nAssisting to notify patients of changes or cancellations of appointment when necessary\nPromoting and maintaining effective relationships and communication within the team\nWorking at Central\nAvailability : Immediately\nPlease state expected salary", "employment_types": ["Full Time", "Permanent"], "selling_points": [], "locations": ["Central"], "categories": ["Admin & HR", "Clerical / Admin Staff", "Receptionist", "Medical Services", "Others"], "post_time": "2022-01-15T02:07:40Z", "salary": {"currency": null, "max": null, "min": null, "period": "monthly", "term": null}, "salary_visible": false, "title_keywords": ["receptionist"], "responsibilities": ["communication", "customer service", "maintaining"], "requirements": {"degrees": ["dse"], "majors": [], "languages": ["cantonese", "english", "mandarin"], "language_level": ["advantage", "fluent"], "hard_skills": [], "soft_skills": ["communication", "patient", "customer service"], "languages_combined": [{"language": "cantonese", "language_level": ["fluent"]}, {"language": "english", "language_level": ["fluent"]}, {"language": "mandarin", "language_level": ["advantage", "fluent"]}]}, "experience_required": {"duration": ["two to three years"], "field": ["clinic", "customer service"]}}, {"job_id": "100003009054146", "location_code": "hk", "company": "Hong Kong Baptist University", "job_title": "General Clerk (PR0473/21-22)", "description": "GRADUATE SCHOOL\n\nGeneral Clerk (PR0473/21-22)\n\nThe HKBU Graduate School (GS) supports the development of the University\u2019s strategic directions and provides central administration for the University\u2019s postgraduate education.\u00a0 We are now looking for a dedicated team player to join the Office Management and Development Team to perform duties relating to programme administration and other central duties.\n\nRoles and Responsibilities:\nmanage student data and compile statistical reports;\nhandle email/telephone/walk-in enquiries;\nProvide general administrative support to the Office;\nprovide counter services; and\ncarry out ad hoc tasks as assigned.\nApplicant should have:\n\ncompleted secondary education or specialised vocational training;\nat least two years of relevant work experience;\na good command of written and spoken English and Chinese (including Putonghua); and\ngood computer application skills, good communication and interpersonal skills.\nInitial appointment will be made on a fixed-term contract of two years. Re-appointment thereafter will be subject to mutual agreement and availability of funding.\u00a0\n\nSalary will be commensurate with qualifications and experience.\n\nApplication Procedure:\n\nApplicants are invited to submit their applications at the HKBU e-Recruitment System (jobs.hkbu.edu.hk). Those not invited for interview 8 weeks after the closing date may consider their applications unsuccessful. Details of the University\u2019s Personal Information Collection Statement can be found at http://hro.hkbu.edu.hk/pics.\n\nThe University reserves the right not to make an appointment for the post advertised, and the appointment will be made according to the terms and conditions then applicable at the time of offer.\n\nClosing date: 30 January 2022", "employment_types": ["Full Time"], "selling_points": ["manage student data", "handle email/telephone/walk-in enquiries", "Provide general administrative support"], "locations": ["Kowloon City"], "categories": ["Admin & HR", "Clerical / Admin Staff", "Receptionist", "Others"], "post_time": "2022-01-17T08:33:20Z", "salary": {"currency": null, "max": null, "min": null, "period": "monthly", "term": null}, "salary_visible": false, "title_keywords": ["general clerk"], "responsibilities": ["management", "data", "general administrative support", "ad hoc tasks", "communication", "reports", "recruitment", "administration"], "requirements": {"degrees": ["secondary education"], "majors": [], "languages": ["putonghua", "english", "chinese"], "language_level": ["good command"], "hard_skills": ["make"], "soft_skills": ["perform duties", "team player", "communication and interpersonal skills"], "languages_combined": [{"language": "putonghua", "language_level": ["good command"]}, {"language": "english", "language_level": ["good command"]}, {"language": "chinese", "language_level": ["good command"]}]}, "experience_required": {"duration": ["at least two years"], "field": []}}, {"job_id": "100003009048476", "location_code": "hk", "company": "Ulba International Limited", "job_title": "Receptionist", "description": "Responsibilities:\n\n-\u00a0\u00a0\u00a0\u00a0\u00a0\u00a0\u00a0\u00a0 Provide clerical and administrative support to the team,\n\n-\u00a0\u00a0\u00a0\u00a0\u00a0\u00a0\u00a0\u00a0\u00a0Assist in other ad hoc tasks as requested.\n\nRequirements:\n\n-\u00a0\u00a0\u00a0\u00a0\u00a0\u00a0\u00a0\u00a0 Form 5 or above,\n\n-\u00a0\u00a0\u00a0\u00a0\u00a0\u00a0\u00a0\u00a0 Familiar with computer knowledge and MS Office,\n\n-\u00a0\u00a0\u00a0\u00a0\u00a0\u00a0\u00a0\u00a0 Good command of written / spoken English and Chinese,\n\n-\u00a0\u00a0\u00a0\u00a0\u00a0\u00a0\u00a0\u00a0 With working experience is preferred,\n\n-\u00a0\u00a0\u00a0\u00a0 Immediate available is preferred.\n\nInterested parties please apply with full resume, present and expected salary, available date by via \"APPLY NOW\".", "employment_types": ["Full Time", "Permanent"], "selling_points": [], "locations": ["Tsim Sha Tsui"], "categories": ["Admin & HR", "Receptionist"], "post_time": "2022-01-14T06:38:15Z", "salary": {"currency": null, "max": null, "min": null, "period": "monthly", "term": null}, "salary_visible": false, "title_keywords": ["receptionist"], "responsibilities": ["ad hoc tasks", "administrative support"], "requirements": {"degrees": ["form 5 or above"], "majors": [], "languages": ["english", "chinese"], "language_level": ["good command"], "hard_skills": ["ms office"], "soft_skills": [], "languages_combined": [{"language": "english", "language_level": ["good command"]}, {"language": "chinese", "language_level": ["good command"]}]}, "experience_required": {"duration": [], "field": []}}, {"job_id": "100003009048590", "location_code": "hk", "company": "CL3 Architects Ltd", "job_title": "Junior Secretary / Receptionist", "description": "Responsibilities:\n\nProvide efficient, accurate and responsive secretarial and administrative support to the team\nPerform reception duties including guests greeting, phone calls and taking messages\nProvide administrative and clerical support to departments e.g. office supplies administration and procurement, expense reimbursement, compiling simple statistics, data entry, filing\nParticipate in ad-hoc tasks as assigned\n\nRequirements:\n\nDiploma holder or above in related disciplines or professionally trained in Secretarial Studies\n2-3 year's relevant experiences\nExcellent telephone manner\nTeam player with ability to work independently and with strong sense of responsibility\nMature, well organized, attention to details and willing to work under pressure\nGood command of both spoken and written English and Chinese\nProficiency in MS Office (Word, Excel, PowerPoint & Project)\nCandidates with more experience will be considered Senior Secretary\nImmediate available is preferred\nFor interested applicants, please send your full resume with availability, present, and expected salary by clicking the \u201cAPPLY NOW\u201d button below.\n\nAll information received will be treated in strict confidence and used for the purpose of employment-related only.\n", "employment_types": ["Full Time", "Permanent"], "selling_points": [], "locations": ["Wan Chai"], "categories": ["Admin & HR", "Clerical / Admin Staff", "Receptionist", "HR Supporting Staff"], "post_time": "2022-01-14T06:51:50Z", "salary": {"currency": null, "max": null, "min": null, "period": "monthly", "term": null}, "salary_visible": false, "title_keywords": ["receptionist", "junior secretary"], "responsibilities": ["administrative support", "office supplies", "data entry", "ad-hoc tasks", "administrative and clerical support", "phone calls", "administration"], "requirements": {"degrees": ["diploma holder"], "majors": ["related disciplines"], "languages": ["english", "chinese"], "language_level": ["good command"], "hard_skills": ["excel", "word", "powerpoint", "ms office"], "soft_skills": ["work independently", "confidence", "sense of responsibility", "well organized", "mature", "attention to details", "team player", "telephone manner", "work under pressure"], "languages_combined": [{"language": "english", "language_level": ["good command"]}, {"language": "chinese", "language_level": ["good command"]}]}, "experience_required": {"duration": ["2-3 year"], "field": []}}, {"job_id": "100003009053685", "location_code": "hk", "company": "Belle Cosmetic Limited", "job_title": "\u63a5\u5f85\u54e1", "description": "\n\u6708\u5165$15,000-$20,000\n\n", "employment_types": ["Full Time"], "selling_points": [], "locations": ["Not Specified"], "categories": ["Admin & HR", "Clerical / Admin Staff", "Receptionist", "Others"], "post_time": "2022-01-17T07:21:09Z", "salary": {"currency": null, "max": null, "min": null, "period": "monthly", "term": null}, "salary_visible": false, "title_keywords": [], "responsibilities": [], "requirements": {"degrees": [], "majors": [], "languages": [], "language_level": [], "hard_skills": [], "soft_skills": [], "languages_combined": []}, "experience_required": {"duration": [], "field": []}}, {"job_id": "100003009047812", "location_code": "hk", "company": "Best Come Limited (Eaton Club)", "job_title": "Client Experience Executive / Receptionist", "description": "Responsibilities:\n\nResponsible for providing all-round administrative and operations support to club members\nProvide excellent service in our private members lounge and event venue including but not limited to greeting, phone handling, concierge service, secretarial services, etc.\nMaintain workspaces at a high standard at all times, which includes facilities and environment management\nBuild up good relationship with members and manage membership database\nCollaborate with internal parties to support events logistics and ensure all events run effectively and efficiently\nHandle ad hoc assignments or project as required\n\nRequirements:\n\nDiploma or above in Hospitality Management or other related disciplines\nExperience in frontline customer services, preferably gained in hospitality industry or business center\nCheerful, initiative, service-oriented and able to communicate with people of different culture background\nPassionate, friendly, pleasant with professional manner\nStrong communication and interpersonal skills\nGood command of both spoken and written English and Chinese (including Putonghua)\nFresh graduates will also be considered\n\nSalary and benefits will be commensurate with qualifications and experience.\u00a0 Interested parties, please send a full resume with present and expected salary, and date available to The Human Resources Department, 32/F., Great Eagle Centre, 23 Harbour Road, Wanchai, Hong Kong or e-mail to \u5c74.\u00a0\u00a0(Please quote the reference no. on the envelope and the covering letter.)\n\nTo know more about us, please visit our website at https://www.eatonclub.com.hk/\n\nWe are an equal opportunity employer and welcome applications from all qualified candidates.\n\nPersonal data collected will be treated in strict confidence and used only for recruitment-related purpose. Applicants who have not heard from us within four weeks may consider their applications unsuccessful. All personal data will be destroyed after 12 months.", "employment_types": ["Full Time", "Permanent"], "selling_points": ["Front Desk Officer / Receptionist", "Business Centre, Co-working space", "Fresh graduates will also be considered"], "locations": ["Central"], "categories": ["Admin & HR", "Receptionist", "Sales, CS & Business Devpt", "Customer Service - Supervisor / Officer", "Hospitality / F & B", "Hospitality / Hotel Services"], "post_time": "2022-01-14T03:57:10Z", "salary": {"currency": null, "max": null, "min": null, "period": "monthly", "term": null}, "salary_visible": false, "title_keywords": ["receptionist", "executive"], "responsibilities": ["collaborate with", "management", "operations", "good relationship", "maintain", "logistics", "ad hoc assignments", "database", "internal parties"], "requirements": {"degrees": ["diploma or above"], "majors": ["hospitality management", "related disciplines"], "languages": ["putonghua", "english", "chinese"], "language_level": ["good command"], "hard_skills": [], "soft_skills": ["passionate", "cheerful", "service-oriented", "pleasant", "communication and interpersonal skills", "friendly", "initiative"], "languages_combined": [{"language": "putonghua", "language_level": ["good command"]}, {"language": "english", "language_level": ["good command"]}, {"language": "chinese", "language_level": ["good command"]}]}, "experience_required": {"duration": [], "field": ["hospitality industry", "business", "customer services"]}}, {"job_id": "100003009045075", "location_code": "hk", "company": "Dyxnet Limited", "job_title": "HR & Admin Assistant (Receptionist)", "description": "Job Responsibilities\n\nProvide clerical support for Human Resources & Admin Department\nPerform receptionist duties\nHandling staff business travel arrangement, medical insurance\nAssist in providing HR services including\u00a0benefits, employee relationships etc;\nMaintain the staff leave and attendance records\nAssist in HR & Admin related duties\nAssist in ad-hoc tasks and projects\n\nJob Requirements\n\n1-2 years'\u00a0HR & Administration experience\nProficient in MS Word, Excel and\u00a0PowerPoint\nGood working attitude and willing to learn\nAble to perform multi-tasks and work under pressure\nImmediately available will be advantage\n\n\n\nAttractive remuneration and compensation package, including year end bonus, medical scheme, life insurance\u00a0and MPF, as well as career development opportunities will be offered.\n\nInterested parties please send your resume with expected salary and availability to Human Resources Department, Dyxnet Group, 37/F, Tower 1, Metoplaza, 223 Hing Fong Road, Kwai Fong.\n\nWelcome to visit our website: http://www.dyxnet.com for further information of our company.\n\nData collected will be used for recruitment purpose only.", "employment_types": ["Full Time", "Permanent"], "selling_points": ["Assist in HR & Admin related duties", "Perform receptionist duties", "5 days work"], "locations": ["Kwai Fong"], "categories": ["Admin & HR", "Clerical / Admin Staff", "Receptionist", "HR Supporting Staff"], "post_time": "2022-01-13T07:05:22Z", "salary": {"currency": null, "max": null, "min": null, "period": "monthly", "term": null}, "salary_visible": false, "title_keywords": ["receptionist", "hr & admin assistant"], "responsibilities": ["provide clerical support", "insurance", "travel arrangement"], "requirements": {"degrees": [], "majors": [], "languages": [], "language_level": [], "hard_skills": [], "soft_skills": [], "languages_combined": []}, "experience_required": {"duration": [], "field": []}}, {"job_id": "100003009051164", "location_code": "hk", "company": "School of Continuing Education, HKBU", "job_title": "Administrative Assistant (Ref. No.: PRSCE0036/21-22)", "description": "The appointee will be assigned to the Learning Centre Administration Section of the School to provide administrative and clerical support in the day-to-day operation. Duties include but not limited to: a) assisting in daily class operation and teaching equipment / centre facilities preparation; b) maintaining records, preparing reports, and performing administrative duties such as filing and photocopying; c) data inputting and compiling; d) providing frontline support for classes and counter services including enquiry handling; and e) coordinating and liaising with internal and external parties such as instructors, students and contractors. The appointee is also required to perform shift duty on weekday evenings.\nMinimum Requirements:\nHKCEE 5 passes including English Language (at least grade C if Syllabus A / Level 2 from 2007), or at least 5 subjects attaining Level 2 in HKDSE including English Language and Chinese Language, or Yi Jin graduates;\nAt least 2 years of relevant experience;\nGood communication and customer services skills;\nCompetency in computer software applications;\nKnowledge in basic operation and setup of audio-visual equipment is an advantage; and\nHolders of Associate Degree / Higher Diploma with less experience may also be considered.\nSalary will be commensurate with qualifications and experience.\nApplication Procedure:\nApplicants are invited to submit their applications at the HKBU e-Recruitment System (jobs.hkbu.edu.hk). Applicants not invited for interview 8 weeks after the closing date may consider their applications unsuccessful. Details of the University's Personal Information Collection Statement can be found at http://hro.hkbu.edu.hk/pics.\nThe School reserves the right not to make an appointment for the post advertised, and the appointment will be made according to the terms and conditions then applicable at the time of offer.\nClosing date: 24 January 2022", "employment_types": ["Full Time"], "selling_points": [], "locations": ["Tsim Sha Tsui"], "categories": ["Admin & HR", "Clerical / Admin Staff", "Receptionist", "Education", "Others"], "post_time": "2022-01-15T03:48:54Z", "salary": {"currency": null, "max": null, "min": null, "period": "monthly", "term": null}, "salary_visible": false, "title_keywords": ["administrative assistant"], "responsibilities": ["software", "maintaining", "data", "internal and external parties", "liaising with", "customer services", "communication", "administrative duties", "visual", "preparing reports", "administrative and clerical support", "recruitment", "audio", "setup", "day-to-day operation", "administration"], "requirements": {"degrees": ["associate degree", "diploma", "hkdse"], "majors": [], "languages": ["english", "chinese"], "language_level": [], "hard_skills": ["make", "c", "basic"], "soft_skills": ["communication", "learning", "customer services skills"], "languages_combined": [{"language": "english", "language_level": []}, {"language": "chinese", "language_level": []}]}, "experience_required": {"duration": ["at least 2 years"], "field": ["relevant experience"]}}, {"job_id": "100003009048124", "location_code": "hk", "company": "New Focus Textiles Limited", "job_title": "Administrative Assistant", "description": "Responsibilities:\n\nPerform receptionist functions including but not limited to greeting and serving tea to guests, handling phone calls,mailing courier;\n\nHandle day to day office administration duties including procurement of office stationery and equipment maintenanceand ensure all records are up to date;\n\nEnsure smooth operation of the reception counter to co-ordinate all in/out mails/parcels with couriers or internal office assistants, handle simple outdoor works when required;\n\nOther ad hoc duties as assigned.\n\nRequirements:\n\nF.5/DSE or above;\n\nRelevant experience in Receptionist and administration preferred;\nStrong communication skills;\n\nMature, independent, detail minded with strong sense of responsibility;\n\nGood command of both written and spoken Cantonese, Mandarin and English;\n\nProficient in MS Office (Word, Excel) and Chinese input is must.", "employment_types": ["Full Time"], "selling_points": [], "locations": ["Lai Chi Kok"], "categories": ["Admin & HR", "Clerical / Admin Staff", "Receptionist", "Others"], "post_time": "2022-01-14T06:22:30Z", "salary": {"currency": null, "max": null, "min": null, "period": "monthly", "term": null}, "salary_visible": false, "title_keywords": ["administrative assistant"], "responsibilities": ["ad hoc duties", "office administration duties", "phone calls", "stationery"], "requirements": {"degrees": ["dse"], "majors": [], "languages": ["cantonese", "english", "chinese", "mandarin"], "language_level": ["good command", "proficient"], "hard_skills": ["chinese input", "excel", "word", "ms office"], "soft_skills": ["communication skills", "independent", "mature", "sense of responsibility"], "languages_combined": [{"language": "cantonese", "language_level": ["good command"]}, {"language": "english", "language_level": ["good command"]}, {"language": "chinese", "language_level": ["proficient"]}, {"language": "mandarin", "language_level": ["good command"]}]}, "experience_required": {"duration": [], "field": ["relevant experience", "administration"]}}, {"job_id": "100003009045026", "location_code": "hk", "company": "P3 Impex Limited", "job_title": "Front Desk Receptionist", "description": "Our client in Luxury industry is looking for Front desk Receptionist\u00a0\nResponsibilities\n\n\u00a0Perform reception duties including guests greeting, answering phone calls and taking message\n\u00a0Handle courier services, incoming and out-going mailing and fax distribution and take record\u00a0\n\u00a0Maintain smooth operation of the reception counter and meeting room arrangement\n\u00a0Provide administrative and clerical support\n\u00a0Perform ad hoc duties assigned by the upper management.\n\n\u00a0Requirements:\n\n\u00a0\u00a0\u00a0\u00a0\u00a0\u00a0\u00a0\u00a0 Fluent in Cantonese and conversational English; Mandarin is a plus\n\u00a0\u00a0\u00a0\u00a0\u00a0\u00a0\u00a0\u00a0 Good PC knowledge in MS Words, Excel & Chinese Word Processing\n\u00a0 \u00a0 \u00a0 \u00a0 \u00a0Responsible\u00a0 & attention to detail.\n\u00a0\u00a0\u00a0\u00a0\u00a0\u00a0\u00a0\u00a0 Immediate availability is preferred\n\u00a0 \u00a0 \u00a0 \u00a0 \u00a0One year contract ,5.5 days of work", "employment_types": ["Full Time"], "selling_points": [], "locations": ["Hung Hom"], "categories": ["Admin & HR", "Clerical / Admin Staff", "Receptionist"], "post_time": "2022-01-13T06:56:15Z", "salary": {"currency": null, "max": null, "min": null, "period": "monthly", "term": null}, "salary_visible": false, "title_keywords": ["receptionist"], "responsibilities": ["ad hoc duties", "management", "maintain", "administrative and clerical support", "phone calls"], "requirements": {"degrees": [], "majors": [], "languages": ["cantonese", "english", "chinese", "mandarin"], "language_level": ["good", "conversational", "fluent"], "hard_skills": ["excel", "plus", "chinese word processing", "ms words", "pc knowledge"], "soft_skills": ["attention to detail", "responsible"], "languages_combined": [{"language": "cantonese", "language_level": ["fluent", "conversational"]}, {"language": "english", "language_level": []}, {"language": "chinese", "language_level": ["good"]}, {"language": "mandarin", "language_level": []}]}, "experience_required": {"duration": [], "field": []}}, {"job_id": "100003009048596", "location_code": "hk", "company": "Association of Hong Kong Flag-Guards Limited", "job_title": "\u6587\u54e1", "description": "\u8981\u6c42\ufe30\n\u2022 \u8a8d\u540c\u672c\u6703\u5b97\u65e8\n\u2022 \u4e2d\u5b78\u6703\u8003\u4e94\u79d1\u5408\u683c\uff0c\u5305\u62ec\u4e2d\u3001\u82f1\u6587(\u4e59)\u6216\u7b49\u540c\n\u2022 \u826f\u597d\u4e2d\u3001\u82f1\u6587\u5beb\u4f5c\u80fd\u529b\n\u2022 \u719f\u7fd2\u4e00\u822c\u96fb\u8166\u6587\u66f8\u8edf\u4ef6\u5982MS word\u3001Excel\u3001Powerpoint\u53ca\u9700\u8981\u4e2d\u82f1\u6587\u8f38\u5165\u6cd5\u6253\u5b57\u5feb\u901f(\u4e2d\u6587 30\uff0c\u82f1\u6587 40\u6216\u4ee5\u4e0a)\n\u2022 \u8655\u4e8b\u9808\u7d30\u5fc3\u53ca\u8b39\u614e\uff0c\u80fd\u4e3b\u52d5\u53ca\u7368\u7acb\u5730\u5b8c\u6210\u5de5\u4f5c\n\u2022 \u5584\u65bc\u8207\u4eba\u6e9d\u901a\u53ca\u5efa\u7acb\u826f\u597d\u95dc\u4fc2\uff0c\u91cd\u8996\u5718\u968a\u7cbe\u795e\n\n\u8077\u8cac\ufe30\n\u2022 \u8ca0\u8cac\u6d3b\u52d5\u884c\u653f\u5de5\u4f5c\uff0c\u5305\u62ec\u5831\u540d\u7a0b\u5e8f\u3001\u806f\u7d61\u5b78\u6821/\u6a5f\u69cb\u7b49\n\u2022 \u8ca0\u8cac\u6703\u5167\u884c\u653f\u5de5\u4f5c\uff0c\u5305\u62ec\u63a1\u8cfc\u53ca\u4e00\u822c\u8fa6\u516c\u5ba4\u96dc\u52d9\n\u2022 \u5354\u52a9\u6587\u66f8\u5de5\u4f5c\uff0c\u5305\u62ec\u6703\u8b70\u7d00\u9304\u3001\u64b0\u5beb\u66f8\u4fe1\u53ca\u901a\u544a\u3001\u5354\u52a9\u6574\u7406\u8a08\u5283\u66f8\u53ca\u5831\u544a\u7b49\n\u2022 \u9700\u8981\u5354\u52a9\u5eab\u5b58\u548c\u57f7\u5236\u670d\u5de5\u4f5c\n\u2022 \u6bcf\u9031\u5de5\u4f5c5\u5929\u534a\uff0c\u661f\u671f\u4e00\u81f3\u516d\u5de5\u4f5c", "employment_types": ["Full Time", "Contract"], "selling_points": ["\u5584\u65bc\u8207\u4eba\u6e9d\u901a\u53ca\u5efa\u7acb\u826f\u597d\u95dc\u4fc2\uff0c\u91cd\u8996\u5718\u968a\u7cbe\u795e", "\u719f\u7fd2\u4e00\u822c\u96fb\u8166\u6587\u66f8\u8edf\u4ef6\u5982MS word\u3001Excel\u3001Powerpoint\u53ca\u4e2d\u82f1\u6587\u8f38\u5165\u6cd5", "\u4e2d\u5b78\u6703\u8003\u4e94\u79d1\u5408\u683c\uff0c\u5305\u62ec\u4e2d\u3001\u82f1\u6587(\u4e59)\u6216\u7b49\u540c"], "locations": ["Not Specified"], "categories": ["Admin & HR", "Receptionist"], "post_time": "2022-01-15T03:50:02Z", "salary": {"currency": null, "max": null, "min": null, "period": "monthly", "term": null}, "salary_visible": false, "title_keywords": ["\u6587\u54e1"], "responsibilities": [], "requirements": {"degrees": [], "majors": [], "languages": [], "language_level": [], "hard_skills": [], "soft_skills": [], "languages_combined": []}, "experience_required": {"duration": [], "field": []}}, {"job_id": "100003009047040", "location_code": "hk", "company": "Drake International and Vertical Talent HK", "job_title": "Receptionist & Admin, Financial Services (1 year contract)", "description": "Our Client\n\nOur client, a well established venture capital firm located in Central is looking to seek a polished and professional receptionist to join their team.\n\nThe Role\n\nThe receptionist will have the opportunity to give a world class first impression to top tier clients and to ensure the smooth running of the front desk. Duties include:\u00a0\n\nAnswer telephone, screen and direct calls\nTake and relay messages\nProvide information to callers\nGreet persons entering organisation\nDeal with queries from the public and customers\nProvide general administrative and clerical support\nMaintain appointment diary either manually or electronically\nOrganise conference and meeting room bookings\nCatering coordination\n\nTo Qualify\n\nPrevious experience as receptionist/ admin in financial or professional services preferred\nExcellent interpersonal and communication skills\nExcellent English (spoken and written) and Chinese is essential\nKnowledge of computers and relevant software application\nImpeccable professional personal presentation\nInitiative and reliability\n\nWhat does this mean for you?\n\nThis role is ideal for a receptionist with a positive and friendly manner to join a great firm and develop their skills in office administration. They will enjoy an excellent salary and benefits and the opportunity to work with a friendly welcoming team.\n\nTo Apply\n\nIf you feel your experience and professionalism can make an impact with this firm, please click the Apply now button, or email\u00a0jkhoo @ drake.com.hk for more information.\n\nDue to a high volume of applicants, only shortlisted candidates will be contacted.\n\nPersonal data provided by job applicants will be used strictly in accordance with the employer's personal data policies and for recruitment services purposes only.", "employment_types": ["Full Time", "Permanent"], "selling_points": ["Excellent salary", "Great work location and office", "Good work-life balance and company culture"], "locations": ["Central"], "categories": ["Admin & HR", "Clerical / Admin Staff", "Receptionist"], "post_time": "2022-01-14T02:08:45Z", "salary": {"currency": null, "max": null, "min": null, "period": "monthly", "term": null}, "salary_visible": false, "title_keywords": ["receptionist", "admin"], "responsibilities": ["software", "office administration", "develop", "communication", "maintain", "coordination", "administrative and clerical support", "catering"], "requirements": {"degrees": [], "majors": [], "languages": ["english", "chinese"], "language_level": ["excellent"], "hard_skills": ["bookings", "venture capital"], "soft_skills": ["communication skills", "presentation", "smooth", "friendly", "coordination", "organisation", "initiative", "interpersonal", "positive", "ideal"], "languages_combined": [{"language": "english", "language_level": ["excellent"]}, {"language": "chinese", "language_level": ["excellent"]}]}, "experience_required": {"duration": [], "field": ["admin", "financial"]}}, {"job_id": "100003009051110", "location_code": "hk", "company": "The Tien Chu (Hong Kong) Company Limited", "job_title": "Administrative Officer/ Assistant", "description": "Responsibilities:\n\nTo perform full spectrum of office administration functions, include but not limited to procurement of office equipment & maintenance, stationary, pantry and utility items.\nPerform general clerical duties to include but not limited to incoming calls, mails handling, greeting visitors, maintaining meeting rooms schedule,\u00a0filing and other administrative supports;\nAssist to setup and coordinate meetings and conferences;\nSourcing, purchasing and recording all company materials and inventory control, e.g. stationery, sundries items;\nCoordinate conference room bookings;\nAssist to coordinate Company events, such as Christmas Party, Annual Dinner etc;\nOrganize all office helper\u2019s working schedule and monitor their working performance, to ensure the office environment in tidy up, clean and comfortable conditions;\nHandling other administrative duties as required;\nOther duties as assigned by supervisor.\n\nRequirements:\n\n\n\nHigher Diploma in Business related disciplines\nWith 1-3 years or above experience in Administration field\nAttention to detail and problem-solving skills;\nGood command of written and spoken in English and Chinese;\u00a0Fluency in Putonghua is an advantage\nStrong organizational skills with the ability to multi-task;\nProficiency in MS Office, and Chinese word processing ;\nAbility to work independently and willingness to take up responsibility ;\n\nWe offer competitive package to right candidate, including but unlimited double pay, performance bonus, free lunch, shuttle bus, education allowance, housing allowance, Medical and other benefits.\n\nWorking hours : Monday to Friday 9:00am to 5:00pm & Saturday 9:00am to 12:00noon\n\nInterested parties please send\u00a0full resume in Chinese and English\u00a0in strict confidence with expected salary & earliest availability to us for interview.\n\nFor more details, please visit\u00a0www.tienchu.com\n\n(Personal data collected is solely for recruitment related purpose\u00a0and will be treated in strict confidence.)", "employment_types": ["Full Time", "Permanent"], "selling_points": ["Administrative works", "Double pay, performance bonus, free lunch", "Shuttle(Tsing Yi,Mei Foo,Prince Edward,To Kwa Wan)"], "locations": ["Tsing Yi"], "categories": ["Admin & HR", "Clerical / Admin Staff", "Personal / Executive Assistant", "Receptionist"], "post_time": "2022-01-15T02:45:12Z", "salary": {"currency": null, "max": null, "min": null, "period": "monthly", "term": null}, "salary_visible": false, "title_keywords": ["administrative officer", "assistant"], "responsibilities": ["maintaining", "maintenance", "other duties", "office administration", "monitor", "stationery", "coordinate", "conferences", "inventory control", "administrative duties", "schedule", "setup", "greeting visitors"], "requirements": {"degrees": ["diploma"], "majors": ["related disciplines", "business"], "languages": ["putonghua", "english", "chinese"], "language_level": ["fluency", "advantage", "proficiency", "good command"], "hard_skills": ["problem-solving skills", "chinese word processing", "ms office"], "soft_skills": ["organizational skills", "work independently", "multi-task", "attention to detail", "problem-solving skills"], "languages_combined": [{"language": "putonghua", "language_level": ["fluency", "advantage"]}, {"language": "english", "language_level": ["good command"]}, {"language": "chinese", "language_level": ["proficiency", "good command"]}]}, "experience_required": {"duration": ["1-3 years"], "field": ["administration"]}}, {"job_id": "100003009048183", "location_code": "hk", "company": "Nitto Denko (H K) Co Ltd", "job_title": "Administration Assistant", "description": "Job Responsibilities\n\nHandle a wide range of administration functions including office supplies administration, company facilities and equipment maintenance, office decoration and etc.\nAssist in receptionist duties, such as ticket and hotel reservation, courier and mailing services management, etc.\nAssist in organizing staff activities and events\nHandle ad hoc assignments as\u00a0required\u00a0\n\n\u00a0\u00a0\u00a0Job Requirements\u00a0\n\nDSE (or A-Level) or above\n1-2 years\u2019 experience in office administration is preferred. Fresh graduates will also be considered\nGood command of English & Chinese language skills\nKnowledge in Microsoft Word, Excel, PowerPoint and Chinese word processing and good email writing skill in English\nCourteous, proactive, good communication and willing to learn\nImmediate available is preferred\nAttractive salary package and fringe benefits including 5-day work, double pay, performance bonus, life and medical insurance, education sponsorship,\u00a0etc.\u00a0would be offered to the right candidate.\n\nInterested parties please click \u201cApply Now\u201d.\u00a0\n\nInformation provided will be treated in strict confidence and will only be used for recruitment-related purposes. Personal data provided by job applicants will be used strictly in accordance with the employer's personal data policies, a copy of which will be provided immediately upon request.\n", "employment_types": ["Full Time", "Permanent"], "selling_points": ["5-day work week", "Near Kwai Fong MTR", "Fresh graduates will also be considered"], "locations": ["Kwai Fong"], "categories": ["Admin & HR", "Clerical / Admin Staff", "Receptionist", "Others"], "post_time": "2022-01-14T05:52:58Z", "salary": {"currency": null, "max": null, "min": null, "period": "monthly", "term": null}, "salary_visible": false, "title_keywords": ["administration assistant"], "responsibilities": ["management", "maintenance", "office supplies", "ad hoc assignments", "administration"], "requirements": {"degrees": ["dse"], "majors": [], "languages": ["english", "chinese"], "language_level": ["good command", "good"], "hard_skills": ["excel", "microsoft word", "chinese word processing", "powerpoint", "writing skill"], "soft_skills": ["courteous", "willing to learn", "writing skill", "communication", "proactive"], "languages_combined": [{"language": "english", "language_level": ["good command", "good", "good"]}, {"language": "chinese", "language_level": ["good command", "good", "good"]}]}, "experience_required": {"duration": ["1-2 years"], "field": ["office administration"]}}, {"job_id": "100003009045060", "location_code": "hk", "company": "Harbour City Estates Ltd", "job_title": "ADMINISTRATION ASSISTANT (5-DAY WORK)", "description": "Responsibilities:\n\nProvide full spectrum of general administration support\u00a0including\u00a0document filing, invoice vetting, membership renewal, etc.\nMaintain and update the records in the Central Filing System in timely manner\nPerform\u00a0safety inspection and ensure compliance with the regulatory requirements\nAssist in data consolidation and prepare periodic reports\u00a0\nPerform reception duties when necessary\nHandle ad-hoc assignments and various administrative projects as assigned\n\nRequirements:\n\nTertiary Education or above in Business Administration or related disciplines\nMinimum 3 years\u2019 relevant experience, preferably gained in sizable companies\nDetail-oriented, sensitive to numbers and receptive to new ideas\nGood organizational, interpersonal and analytical skills\nGood command in both written and spoken English and Chinese\nProficiency in Microsoft Office and PC skills\n\nWe offer competitive remuneration package that commensurate with experience and qualifications. Interested parties are invited to send full resume stating contact telephone number, date available, present and expected salary to our recruitment email address.\u00a0\n\n(Personal data provided will be used strictly in accordance with the Company's personal data policy which is available upon request.)", "employment_types": ["Full Time", "Permanent"], "selling_points": ["Tertiary Education or above", "Minimum 3 years\u2019 relevant experience", "Detail-oriented and sensitive to numbers"], "locations": ["Tsim Sha Tsui"], "categories": ["Admin & HR", "Clerical / Admin Staff", "Receptionist", "Others"], "post_time": "2022-01-15T03:49:28Z", "salary": {"currency": null, "max": null, "min": null, "period": null, "term": null}, "salary_visible": false, "title_keywords": ["administration assistant"], "responsibilities": ["document filing", "data", "invoice", "regulatory requirements", "ad-hoc assignments", "inspection", "ensure compliance", "maintain", "reports", "administration"], "requirements": {"degrees": [], "majors": [], "languages": ["english", "chinese"], "language_level": ["good command"], "hard_skills": ["microsoft office", "sizable companies", "pc skills", "analytical skills"], "soft_skills": ["organizational", "receptive", "detail-oriented", "analytical skills", "sensitive to numbers", "interpersonal"], "languages_combined": [{"language": "english", "language_level": ["good command"]}, {"language": "chinese", "language_level": ["good command"]}]}, "experience_required": {"duration": ["minimum 3 years"], "field": ["relevant experience"]}}, {"job_id": "100003009051031", "location_code": "hk", "company": "The Wharf Group", "job_title": "Administration Assistant/Clerk", "description": "\u00a0Responsibilities\u00a0\u00a0\n\nProvide clerical support in checking office expenses and payments; handling business travel applications and claims; updating data base and reports; and handling of office administration routines\nRelieve receptionists in greeting visitors, answering phone calls, taking messages and handling meeting room bookings\n\n\u00a0Requirements\u00a0\u00a0\n\nA pass in English and Chinese Languages and Mathematics in HKCEE/HKDSE\nAt least\u00a02\u00a0years\u2019\u00a0relevant working experience in sizable companies\u00a0\nHigher education level and more experienced candidates will be considered as Administration Assistant\nFluent in spoken English, Cantonese and Putonghua\nPleasant and polite, self-motivated, organized and detail-oriented\nGood interpersonal and communication skills with common sense and good telephone manner\nProficient\u00a0in Microsoft Office (Word /\u00a0Excel) and Chinese Word Processing\nImmediate available preferred\n\nWe work 5 days per week.\n\nInterested parties, please click \"APPLY NOW\" and attach with your application letter and full resume.\u00a0\n\n\nFor further information of the Wharf Group, please visit our website:\u00a0www.wharfholdings.com", "employment_types": ["Full Time", "Permanent"], "selling_points": [], "locations": ["Tsim Sha Tsui"], "categories": ["Admin & HR", "Clerical / Admin Staff", "Receptionist", "Others"], "post_time": "2022-01-15T01:17:14Z", "salary": {"currency": null, "max": null, "min": null, "period": null, "term": null}, "salary_visible": false, "title_keywords": ["administration assistant", "clerk"], "responsibilities": ["provide clerical support", "data", "office administration", "expenses", "checking", "payments", "reports", "phone calls", "greeting visitors"], "requirements": {"degrees": ["hkdse"], "majors": ["mathematics"], "languages": ["cantonese", "putonghua", "english", "chinese"], "language_level": ["proficient", "fluent"], "hard_skills": ["excel", "chinese word processing", "microsoft office", "sizable companies", "word"], "soft_skills": ["organized", "self-motivated", "communication skills", "polite", "detail-oriented", "pleasant", "telephone manner", "interpersonal"], "languages_combined": [{"language": "cantonese", "language_level": ["fluent"]}, {"language": "putonghua", "language_level": ["fluent"]}, {"language": "english", "language_level": ["fluent"]}, {"language": "chinese", "language_level": ["proficient"]}]}, "experience_required": {"duration": ["at least 2 years"], "field": ["relevant working experience"]}}, {"job_id": "100003009037819", "location_code": "hk", "company": "Dream International Ltd", "job_title": "Receptionist  & Admin Assistant", "description": "Responsibilities:\nPerform reception duties including guests greeting, phone calls\u00a0\nHandle courier services, incoming and out-going mailing and take records\nMaintain smooth operation of the reception counter and meeting room arrangement\nProvide administrative and clerical support to departments e.g. office supplies administration and procurement, expense reimbursement, compiling simple statistics, data entry, filing\nPerform ad hoc duties assigned by supervisor\n\n\u00a0Requirements:\n\nDSE / A-Level or above with at least 3 years' relevant experiences\nGood command in both written and spoken English, Chinese and Mandarin\nGood PC knowledge in MS Words, Excel & Chinese Word Processing\nPolite and pleasant personalities\nResponsible and well organized\nDecent telephone manner and communication skills\nImmediate availability is preferred\n\nWe offer attractive remuneration package to the right candidate;\nHong Kong Listed Compnay\n\n14 months salary a year\nMedical insurance\nMPF\n5 days work\n\nInterested parties, please apply with full resume with expected salary to HR Dept., via APPLY NOW\n\nFor details of our group, please visit our website:\u00a0www.dream-i.com.hk", "employment_types": ["Full Time", "Permanent"], "selling_points": [], "locations": ["Tsim Sha Tsui"], "categories": ["Admin & HR", "Receptionist"], "post_time": "2022-01-13T03:01:28Z", "salary": {"currency": null, "max": null, "min": null, "period": "monthly", "term": null}, "salary_visible": false, "title_keywords": ["receptionist", "admin assistant"], "responsibilities": ["ad hoc duties", "data entry", "office supplies", "maintain", "administrative and clerical support", "phone calls", "administration"], "requirements": {"degrees": ["dse"], "majors": [], "languages": ["english", "chinese", "mandarin"], "language_level": ["good command", "good"], "hard_skills": ["excel", "pc knowledge", "chinese word processing", "ms words"], "soft_skills": ["communication skills", "polite", "responsible", "well organized", "pleasant", "telephone manner"], "languages_combined": [{"language": "english", "language_level": ["good command", "good"]}, {"language": "chinese", "language_level": ["good command", "good", "good"]}, {"language": "mandarin", "language_level": ["good command", "good"]}]}, "experience_required": {"duration": ["at least 3 years"], "field": []}}, {"job_id": "100003009050395", "location_code": "hk", "company": "Gold Partners (Asia) Asset Management Company Limited", "job_title": "Receptionist / HR & Admin Assistant", "description": "Responsibilities\n\nResponsible for reception counter duties, handle incoming phone calls, courier, greet visitors etc.\nCarry out clerical and HR / administrative duties in support of department's operations\nCoordinate meeting and travel arrangement\nCoordinate on the office equipment / Tel lines and facilities maintenance\nPrepare HR & clerical regular reports\nHandle other ad hoc projects as required\n\nRequirements\n\nF.6 or above, with minimum 1-2 years working experience in HR & Admin field preferable\u00a0\u00a0\nPleasant personality with good telephone manner, initiative, mature and with good communication skills\nProficiency with MS Word, Excel and Chinese Word Processing\nGood command of spoken and written English, Chinese and Mandarin\u00a0\nImmediate available is preferable\nFresh graduate will be considered\n\nWe Offer:\n\n12 Days Annual Leave\nMedical & Dental Scheme\nOn-the-job Training\nYear-end Bonus\nExcellent Career Advancement Opportunities\nCollaborative working environment\nStaff Caring Benefit, e.g. Festival Gift, Home-made Chinese Herbal Drinks/Soup\u00a0\n\nWe offer competitive remuneration package with excellent career path.\n\nInterested applicants please fax your resume with present &\u00a0expected salary\u00a0to HR & Admin Department at 8161-6498 or click \u201cApply Now\u201d underneath.\n\nFor company information, please visit our website:\u00a0www.goldpartners.com.hk\n\nAll information provided by applicants will be kept confidential and used for recruitment purposes only. The company will retain the information collected for a maximum period of 1 year and may refer suitable\u00a0applicants to other vacancies within the Group.", "employment_types": ["Full Time", "Permanent"], "selling_points": [], "locations": ["Kowloon Bay"], "categories": ["Admin & HR", "Clerical / Admin Staff", "Receptionist", "HR Supporting Staff"], "post_time": "2022-01-14T10:17:19Z", "salary": {"currency": null, "max": null, "min": null, "period": "monthly", "term": null}, "salary_visible": false, "title_keywords": ["receptionist", "hr & admin assistant"], "responsibilities": ["maintenance", "operations", "hr", "incoming phone calls", "coordinate", "administrative duties", "reports", "travel arrangement", "ad hoc projects"], "requirements": {"degrees": ["fresh graduate"], "majors": [], "languages": ["english", "chinese", "mandarin"], "language_level": ["proficiency", "good command"], "hard_skills": ["excel", "chinese word processing", "ms word"], "soft_skills": ["communication skills", "mature", "pleasant", "telephone manner", "initiative"], "languages_combined": [{"language": "english", "language_level": ["good command"]}, {"language": "chinese", "language_level": ["proficiency", "good command"]}, {"language": "mandarin", "language_level": ["good command"]}]}, "experience_required": {"duration": ["minimum 1-2 years"], "field": ["hr", "admin"]}}, {"job_id": "100003009045106", "location_code": "hk", "company": "Union Hospital", "job_title": "Guest Relations Representative\u5ba2\u52d9\u95dc\u4fc2\u4ee3\u8868 (Admission Department) (Ref: JDB/130122/ADO_GRR)", "description": "Duties:\nHandle admission booking and registration\nAnswer enquiries from customers and doctors\nRequirements:\nMinimum DSE graduate or with equivalent qualification, fresh graduates with positive attitude are welcome\nFluent spoken Cantonese, English and Putonghua \u00a0\nFive working days\nShift duty required\nNight shift allowance available\nInterested candidates please download the Job Application Form on\u00a0www.union.org (quote the \"Ref No.\") and send to: HR Department, Union Hospital, 18 Fu Kin Street, Tai Wai, Shatin, N.T. or by fax at 2697 5028 or by e-mail via \"Apply Now\"\n\nDue to the implementation of the Sexual Conviction Record Check (SCRC) Scheme, the Hospital may request the prospective employees of relevant positions to undergo SCRC.\n(Applicants not hearing from us within 2 months may consider their applications unsuccessful. Applicants who have applied for the same position within half year need not re-apply.)\n*Data collected will be used for recruitment purpose only", "employment_types": ["Full Time", "Permanent"], "selling_points": ["Five working days", "Handle admission booking and registration", "Minimum DSE graduate"], "locations": ["Shatin Area"], "categories": ["Admin & HR", "Receptionist", "Sales, CS & Business Devpt", "Customer Service - Supervisor / Officer", "Others"], "post_time": "2022-01-13T07:46:05Z", "salary": {"currency": null, "max": null, "min": null, "period": "monthly", "term": null}, "salary_visible": false, "title_keywords": [], "responsibilities": ["booking"], "requirements": {"degrees": ["dse"], "majors": [], "languages": ["cantonese", "putonghua", "english"], "language_level": ["fluent"], "hard_skills": [], "soft_skills": ["positive attitude"], "languages_combined": [{"language": "cantonese", "language_level": ["fluent"]}, {"language": "putonghua", "language_level": []}, {"language": "english", "language_level": []}]}, "experience_required": {"duration": [], "field": []}}, {"job_id": "100003009045271", "location_code": "hk", "company": "Salon de Lotus", "job_title": "Salon Receptionist", "description": "\nAbout Us\nSalon de Lotus, located in one of the busiest areas in Central has been rapidly established for 3 years.\nWe have developed a loyal and very friendly client base who love the relaxed and positive culture we have worked hard to create. We pride ourselves on our industry expertise, premium services, happy team vibes and active and results driven products.\nJob Description\nSalon de Lotus is a premium salon located in Central. We are looking for suitable candidates with enthusiasm, positive service attitude to fill the position to help expanding our business.\nJob Highlights\n\u2022 General duties of Receptionist\n\u2022 Receiving incoming calls and handling telephone enquiries\n\u2022 Scheduling appointments,\n\u2022 Greeting and receiving customers, handling customers,\n\u2022 General clerical duties\n\u2022 Assisting in daily operation at front desk\n\u2022 Assisting in seating arrangement\nSkills and Qualifications\n\u2022 Coordinating staff shifts and cleaning schedules\n\u2022 Excellent communication skills\n\u2022 Supervising the appointment booking and cancellation schedules\n\u2022 Ensuring that the salon is kept clean and organized\n\u2022 Friendly & well presented\n\u2022 Above average understanding of treatments and procedures\n\u2022 Positive and motivated attitude\n\u2022 Ability to build rapport with clients and other team members\n\u2022 Exceptional social skills\n\u2022 Willingness to learn and up skill\n\u2022 Proficiency in administrative computer software, such as MS Word, Excel, and Outlook\n\u2022 Above all, genuinely passionate about this amazing industry!\nWhy Join Us?\nThis is an amazing opportunity to join a highly respected business that will invest in your growth with ongoing training and development opportunities.\n\u2022 Be treated like family; not just another employee\n\u2022 Hands-on training to ensure you feel supported\n\u2022 Well equipped salon\n\u517c\u8077\u6642\u6578: \u6bcf\u661f\u671f 45\n\u5de5\u4f5c\u985e\u578b: \u5168\u8077, \u517c\u8077, \u9577\u5de5, \u5408\u7d04\n\u85aa\u916c: $11,000.00\u81f3$15,000.00(\u6bcf\u6708)\n\u6642\u9593:\n\u2022 \u65e5\u73ed\n\u2022 \u65e9\u73ed\n\u798f\u5229:\n\u2022 \u5728\u8077\u5c08\u696d\u57f9\u8a13\n\u2022 \u54e1\u5de5\u8cfc\u7269\u512a\u60e0\n\u2022 \u6649\u5347\u6a5f\u6703\n\u88dc\u5145\u85aa\u916c:\n\u2022 \u8d85\u6642\u52a0\u73ed\u8cbb\n\u2022 \u52e4\u5de5\u734e\u91d1\n\u6559\u80b2\u7a0b\u5ea6:\n\u4e2d\u4e94 (\u5fc5\u8981\u689d\u4ef6)\n\u5de5\u4f5c\u7d93\u9a57:\nReceptionist: 2 \u5e74 (\u5fc5\u8981\u689d\u4ef6)\n\u8a9e\u8a00:\nEnglish (\u5fc5\u8981\u689d\u4ef6)\nCantonese (\u5fc5\u8981\u689d\u4ef6)\n\u53ef\u2022 \u5426\u8f2a\u66f4:\n\u65e5\u66f4 (\u5fc5\u8981\u689d\u4ef6)\n\u591c\u66f4 (\u5fc5\u8981\u689d\u4ef6)\n\u9060\u7a0b\u5de5\u4f5c:\n\u2022 \u5426\n\n", "employment_types": ["Full Time"], "selling_points": [], "locations": ["Central"], "categories": ["Admin & HR", "Clerical / Admin Staff", "Receptionist", "Others"], "post_time": "2022-01-13T07:31:47Z", "salary": {"currency": null, "max": null, "min": null, "period": "monthly", "term": null}, "salary_visible": false, "title_keywords": ["receptionist"], "responsibilities": ["supervising", "software", "schedules", "daily operation", "procedures", "communication", "scheduling", "client base", "booking", "cleaning"], "requirements": {"degrees": [], "majors": [], "languages": ["cantonese", "english"], "language_level": [], "hard_skills": ["clean", "excel", "outlook", "ms word"], "soft_skills": ["communication skills", "organized", "passionate about", "hands-on", "motivated", "friendly", "loyal", "active", "driven", "positive"], "languages_combined": [{"language": "cantonese", "language_level": []}, {"language": "english", "language_level": []}]}, "experience_required": {"duration": [], "field": []}}, {"job_id": "100003009043574", "location_code": "hk", "company": "Elite Partners CPA Limited", "job_title": "Receptionist", "description": "Job Description and Responsibilities:\n\nPerform receptionist duties in professional manner, including greeting guests and handling income phone calls, dealing with courier, etc.\nPrepare vouchers & statement, filing, petty cash, issue cheque, issue invoice\nAssist in data entry, documentation tasks and other clerical supports\nHandle ad-hoc duties as assigned\n\nRequirements:\n\nExcellent telephone manner, cheerful, initiative, service-oriented and able to communicate with people of different culture background\nExperience in frontline customer services, preferably gained in CPA firm\nFluent speaking and writing in\u00a0English, Cantonese and Mandarin\nProficiency in MS Office application such as Word, Excel & Chinese Word processing\nAble to work independently with multi-task assignment, attention to details\nImmediate available is preferred\n\nWe offers a competitive salary and a comprehensive range of staff benefits.\n\nMedical Insurance\nBirthday Leave\nPerformance Bonus\n\nA competitive remuneration package & excellent career prospects will be offered to the right candidate. Interest parties please send your full resume (both in English and Chinese) including your salary history and expected salary to Human Resources Department by email.\n\nPersonal data collected will be used for recruitment purpose only.", "employment_types": ["Full Time", "Permanent"], "selling_points": ["Handle reception and office administration duties", "Immediate available is preferred", "5-day work"], "locations": ["Tsim Sha Tsui"], "categories": ["Admin & HR", "Receptionist"], "post_time": "2022-01-12T23:19:03Z", "salary": {"currency": null, "max": null, "min": null, "period": "monthly", "term": null}, "salary_visible": false, "title_keywords": ["receptionist"], "responsibilities": ["data entry", "invoice", "professional manner", "ad-hoc duties", "documentation", "phone calls"], "requirements": {"degrees": [], "majors": [], "languages": ["cantonese", "english", "chinese", "mandarin"], "language_level": ["proficiency", "fluent"], "hard_skills": ["excel", "chinese word processing", "word", "cpa", "ms office"], "soft_skills": ["work independently", "cheerful", "multi-task", "service-oriented", "attention to details", "telephone manner", "initiative"], "languages_combined": [{"language": "cantonese", "language_level": ["fluent"]}, {"language": "english", "language_level": ["fluent"]}, {"language": "chinese", "language_level": ["proficiency"]}, {"language": "mandarin", "language_level": ["fluent"]}]}, "experience_required": {"duration": [], "field": ["cpa firm", "customer services"]}}, {"job_id": "100003009043990", "location_code": "hk", "company": "Konica Minolta Business Solutions (HK) Limited", "job_title": "Receptionist (Quarry Bay)", "description": "Responsibilities\n\nHandle general front desk duties includes greeting clients and guests, daily registration, answering incoming calls and enquiries\nPerform ad hoc duties as assigned\nImmediate available or short notice period is preferred\nSuccessful candidate will be offered a 1-year contract\n\nQualification :\u00a0\u00a0\u00a0\u00a0\u00a0\u00a0\u00a0\u00a0\u00a0\u00a0\u00a0\u00a0\u00a0\u00a0\u00a0\n\nDiploma or above with 1 year or above working experience, prefer in customer service industry\nProficiency in MS Office\nExcellent communication in English is a must,\u00a0Good command in Chinese (Cantonese & Mandarin)\n\nBenefits:\n\n5-day work week\nAttendance Bonus\nMedical Benefits\nOver-time Pay\nBank Holiday\nPerformance Bonus\nCompany Recreational Activities\n\nInterested parties please send your full resume\u00a0included\u00a0expected salary\u00a0by\u00a0clicking 'Apply Now' below.", "employment_types": ["Full Time", "Contract"], "selling_points": ["5-day work, Bank Holiday", "Front Desk", "Receptionist, Admin support"], "locations": ["Not Specified"], "categories": ["Admin & HR", "Clerical / Admin Staff", "Receptionist", "Hospitality / F & B", "Hospitality / Hotel Services"], "post_time": "2022-01-13T02:42:05Z", "salary": {"currency": null, "max": null, "min": null, "period": "monthly", "term": null}, "salary_visible": false, "title_keywords": ["receptionist"], "responsibilities": ["ad hoc duties", "customer service", "communication"], "requirements": {"degrees": ["diploma or above"], "majors": [], "languages": ["cantonese", "english", "chinese", "mandarin"], "language_level": ["excellent", "good command"], "hard_skills": ["ms office"], "soft_skills": ["communication", "customer service"], "languages_combined": [{"language": "cantonese", "language_level": ["excellent", "good command"]}, {"language": "english", "language_level": ["excellent", "good command"]}, {"language": "chinese", "language_level": ["excellent", "good command"]}, {"language": "mandarin", "language_level": ["excellent", "good command"]}]}, "experience_required": {"duration": ["1 year"], "field": ["customer service"]}}, {"job_id": "100003009048847", "location_code": "hk", "company": "EF Education Limited", "job_title": "Office Management Assistant", "description": "We are looking for an Office Management Assistant.\u00a0\n\n\nResponsibilities:\n\nPerform general receptionist duties including handling phone calls, greeting and serving walk in guests\n\nHandle and distribute incoming/outgoing mail, arranging courier service\n\nLiaise with our logistic company for stocking in & out the company items.\n\nProvide full spectrum of general office administrative duties such as managing office supplies and equipment maintenance, business card preparation.\n\nHandle visa applications, hotel reservations, company projects such as staff activities and events.\n\nPerform ad-hoc duties as assigned\n\nRequirements:\n\nHKDSE or above.\n\nWorking experience in office reception, administration or customer service field will be an advantage\n\nGood communication and interpersonal skill, good telephone manner, pleasant personality and detail-minded\n\nProficiency in MS Office\n\nGood command of both written and spoken English and Cantonese, Mandarin is a plus.\n\nAbility to work on multiple tasks\n\nFresh Graduates are also welcome", "employment_types": ["Full Time", "Permanent"], "selling_points": ["English-speaking environment, Cantonese a must", "Relevant administrative experience, HKDSE above", "Sizeable MNC in Hong Kong, international network"], "locations": ["Causeway Bay"], "categories": ["Admin & HR", "Clerical / Admin Staff", "Receptionist"], "post_time": "2022-01-14T07:26:43Z", "salary": {"currency": null, "max": null, "min": null, "period": "monthly", "term": null}, "salary_visible": false, "title_keywords": ["assistant"], "responsibilities": ["maintenance", "office supplies", "administrative duties", "ad-hoc duties", "liaise with", "phone calls", "outgoing mail"], "requirements": {"degrees": ["hkdse"], "majors": [], "languages": ["cantonese", "english", "mandarin"], "language_level": ["good command"], "hard_skills": ["plus", "ms office"], "soft_skills": ["detail-minded", "multiple tasks", "pleasant", "communication", "interpersonal skill", "customer service", "telephone manner"], "languages_combined": [{"language": "cantonese", "language_level": ["good command"]}, {"language": "english", "language_level": ["good command"]}, {"language": "mandarin", "language_level": ["good command"]}]}, "experience_required": {"duration": [], "field": ["customer service", "administration"]}}, {"job_id": "100003009044019", "location_code": "hk", "company": "East Asia Sentinel Limited", "job_title": "Receptionist", "description": "Requirement:\n\n-\u00a0\u00a0\u00a0\u00a0\u00a0\u00a0\u00a0\u00a0\u00a0 Handle receptionist duties of greeting guest, answering phone calls, mailing\u00a0\n\n\u00a0 \u00a0\u00a0\u00a0\u00a0\u00a0\u00a0\u00a0\u00a0 order and courier service;\n\n\n-\u00a0\u00a0\u00a0\u00a0\u00a0\u00a0\u00a0\u00a0\u00a0 Minimum 1 year relevant experience;\n\n\n-\u00a0\u00a0\u00a0\u00a0\u00a0\u00a0\u00a0\u00a0\u00a0 Qualification of DSE / HKCEE or above;\n\n\n-\u00a0\u00a0\u00a0\u00a0\u00a0\u00a0\u00a0\u00a0\u00a0 Good customer service skill with solid experience;\n\n\n-\u00a0\u00a0\u00a0\u00a0\u00a0\u00a0\u00a0\u00a0\u00a0 Good spoken English / Cantonese / Mandarin;\n\n\n-\u00a0\u00a0\u00a0\u00a0\u00a0\u00a0\u00a0\u00a0\u00a0 Immediate availability is highly preferred.\n\nPlease send your resume with full details of experience & qualifications, current and expected salary to Human Resources Manager, East Asia Sentinel Limited at 22/F., Tai Yau Building, 181 Johnston Road, Wanchai, Hong Kong or by email at", "employment_types": ["Full Time"], "selling_points": [], "locations": ["Wan Chai"], "categories": ["Admin & HR", "Receptionist"], "post_time": "2022-01-13T02:48:19Z", "salary": {"currency": null, "max": null, "min": null, "period": "monthly", "term": null}, "salary_visible": false, "title_keywords": ["receptionist"], "responsibilities": ["customer service", "phone calls"], "requirements": {"degrees": ["dse"], "majors": [], "languages": ["cantonese", "english", "mandarin"], "language_level": ["good"], "hard_skills": [], "soft_skills": ["customer service"], "languages_combined": [{"language": "cantonese", "language_level": ["good"]}, {"language": "english", "language_level": ["good"]}, {"language": "mandarin", "language_level": ["good"]}]}, "experience_required": {"duration": ["minimum 1 year"], "field": ["customer service", "relevant experience", "human resources"]}}, {"job_id": "100003009045957", "location_code": "hk", "company": "Flex Recruitment", "job_title": "Receptionist", "description": "Our client is a kid star training academy, providing training courses aimed at enhancing children's confidence, training their acting talent, and identifying potential children to become professional child stars\n\nResponsibilities\n\nManage centre operations\nProvide\u00a0administrative and clerical\u00a0support to the centre and teachers\nManage class schedules and collect tuition fees\nProvide reception counter services and handle enquiries, incoming calls, and guest greeting in a professional manner\nMaintain centre and classrooms\u2019 hygiene and outlook\nIntroduce school programs to clients\nProvide teaching support to the tutor in the class\nComplete assigned responsibilities during follow-up shooting (e.g., taking photos)\n\nRequirement\n\n\n5 year or above working experience preferred\nExperience in being a receptionist is a plus\nEnjoys in interact and communication with children\nWilling to involve in sale tasks\nPleasant, courteous & hardworking\nGood communication, presentation, and customer service skills\nGood command of spoken English & Chinese\nPC knowledge such as Microsoft Word & Chinese Word Processing\n\nWorking hours\n\nDay off at each Monday\nTuesday to Friday: 11:00-19:00\nSaturday to Sunday: 13:00-21:00\nWorking location: Ma On Shan/Tseung Kwan O/Tai Koo/Tsuen Wan/North Point/Kowloon Bay\n\nBenefit\n\nAttendance Bonus\nTransportation Allowance\nDiscretionary Bonus\n10 days Annual Leave\nStatutory Holidays\nBirthday Leave\nWedding Leave\nStaff Discount\nReferral Bonus", "employment_types": ["Full Time"], "selling_points": ["Pleasant, courteous & hardworking", "Experience in being a receptionist is preferred", "Willing to communicate and interact with children"], "locations": ["Wong Tai Sin Area"], "categories": ["Admin & HR", "Clerical / Admin Staff", "Receptionist", "Sales, CS & Business Devpt", "Customer Service - Supervisor / Officer"], "post_time": "2022-01-13T09:14:05Z", "salary": {"currency": null, "max": null, "min": null, "period": "monthly", "term": null}, "salary_visible": false, "title_keywords": ["receptionist"], "responsibilities": ["schedules", "operations", "professional manner", "handle enquiries", "hygiene", "maintain", "administrative and clerical support"], "requirements": {"degrees": [], "majors": [], "languages": ["english", "chinese"], "language_level": ["good command"], "hard_skills": ["plus", "microsoft word", "chinese word processing", "pc knowledge", "wan"], "soft_skills": ["customer service skills", "courteous", "pleasant", "communication", "presentation", "hardworking"], "languages_combined": [{"language": "english", "language_level": ["good command"]}, {"language": "chinese", "language_level": ["good command"]}]}, "experience_required": {"duration": ["5 year"], "field": []}}, {"job_id": "100003009047957", "location_code": "hk", "company": "The Chinese General Chamber of Commerce", "job_title": "Office Assistant (Administration)", "description": "Office Assistant\n\nDuties:\n\n-\u00a0\u00a0\u00a0\u00a0\u00a0\u00a0 provide tea services for guests and visitors\n\n-\u00a0\u00a0\u00a0\u00a0\u00a0\u00a0 maintain cleanliness and tidiness of pantry and facility area\n\n-\u00a0\u00a0\u00a0\u00a0\u00a0\u00a0 replenish supplies in pantry\n\n-\u00a0\u00a0\u00a0\u00a0\u00a0\u00a0 assist in general office administration works including mail arrangement and\n\ndeliveries\n\nQualifications:\n\n-\u00a0\u00a0\u00a0\u00a0\u00a0\u00a0 From 5 or above\n\n-\u00a0\u00a0\u00a0\u00a0\u00a0\u00a0 Simple spoken English, good command of spoken Cantonese\n\n-\u00a0\u00a0\u00a0\u00a0\u00a0\u00a0 3-4 years of relevant work experience\n\n-\u00a0\u00a0\u00a0\u00a0\u00a0\u00a0 5.5 working days", "employment_types": ["Full Time", "Permanent"], "selling_points": [], "locations": ["Central"], "categories": ["Admin & HR", "Clerical / Admin Staff", "Receptionist", "Public / Civil", "Civil Services"], "post_time": "2022-01-14T04:23:08Z", "salary": {"currency": null, "max": null, "min": null, "period": "monthly", "term": null}, "salary_visible": false, "title_keywords": ["office assistant"], "responsibilities": ["office administration", "maintain"], "requirements": {"degrees": [], "majors": [], "languages": ["cantonese", "english"], "language_level": ["good command"], "hard_skills": ["simple", "tea"], "soft_skills": [], "languages_combined": [{"language": "cantonese", "language_level": ["good command"]}, {"language": "english", "language_level": ["good command"]}]}, "experience_required": {"duration": ["3-4 years"], "field": []}}, {"job_id": "100003009050523", "location_code": "hk", "company": "initial Fashion Co Limited", "job_title": "Part-time Office Administrative Assistant (2-3 days/ week)", "description": "Responsibilities:\n\nProvide general clerical support including filing, arranging payment and preparing regular expenses report.\nPerform receptionist duties such as greeting guests, handling telephone calls, courier and mail arrangement.\nProvide administrative and clerical support for HR and Administration Department.\nArrange office cleaning, pest control and fire system services on regular basis.\nAssist ad hoc projects and perform other duties as assigned from time to time.\nRequirements:\n\nSchool certificate with relevant working experience in office administration duties.\nDetail-oriented, responsible and reliable.\nGood interpersonal skills, telephone manner and communication skills.\nPet lover is a must.\nProficiency in computer skills including Microsoft Office.\n\nWe are looking for candidates with vision, energy and a strong fashion sense who want to be part of a dynamic team and create value. We offer career development as well as regional and local advancement opportunities.\n\nWe are a Hong Kong-based fashion label established in 2000, currently with operations in Hong Kong, Macau and the Chinese Mainland. We create a culture rather than just a piece of clothing.\u00a0 Our philosophy and personality is unique and our outlook is global, we bring \u201cThe Unusual Experience\u201d to our customers.\n\nInterested parties please send your\u00a0resume with expected salary\u00a0to Human Resources Department via Apply Now.\n\nPlease visit our company website\u00a0http://www.initialfashion.com\u00a0for more company information.\n\nAll information received will be treated in strict confidence and for recruitment purpose only.\n", "employment_types": ["Part Time"], "selling_points": ["Previous experience in office administration.", "Detail-oriented, responsible and reliable.", "Immediate available is highly preferred"], "locations": ["Kwun Tong"], "categories": ["Admin & HR", "Clerical / Admin Staff", "Personal / Executive Assistant", "Receptionist"], "post_time": "2022-01-14T10:36:44Z", "salary": {"currency": null, "max": null, "min": null, "period": "hourly", "term": null}, "salary_visible": false, "title_keywords": ["administrative assistant"], "responsibilities": ["administration", "control", "perform other duties", "hr", "expenses", "clerical support", "payment", "ad hoc projects", "administrative and clerical support", "cleaning", "report"], "requirements": {"degrees": ["certificate"], "majors": [], "languages": [], "language_level": [], "hard_skills": ["dynamic", "computer skills", "microsoft office"], "soft_skills": ["communication skills", "responsible", "detail-oriented", "dynamic", "interpersonal skills", "reliable", "telephone manner"], "languages_combined": []}, "experience_required": {"duration": [], "field": ["office administration", "relevant working experience"]}}, {"job_id": "100003009050587", "location_code": "hk", "company": "Exact Medical Group Limited", "job_title": "Clinic Assistant / Health Care Assistant (Full-Time & Part-Time)", "description": "Job Duties:\n\nAssisting to prepare medical & transactions reports according to instructions\nAssisting health care assistants, nurses and radiographers to carry out daily medical routine\nOther clerical duties including filing, scanning & retrieving medical records in an organized manner\n\nRequirements:\n\nHKDSE / HKALE or above\nProficiency in PC knowledge including Microsoft Excel, Word and Chinese Word Processing\nHaving experiences in blood taking or assisting in ultrasound imaging is an advantage\nFluent in Cantonese, Good command of English and Mandarin is an advantage\nResponsible, Good working attitude and Able to work independently\u00a0\nImmediately available is highly preferred\u00a0\n\nRest day on Sundays and public holidays. Night-shift is NOT required.\n\n\u00a0Data collected will be treated in strict confidence and used for recruitment purpose only.", "employment_types": ["Full Time", "Part Time"], "selling_points": ["Clinic", "Health Care", "Ultrasound"], "locations": ["Tsim Sha Tsui"], "categories": ["Admin & HR", "Clerical / Admin Staff", "Receptionist", "Medical Services", "Others"], "post_time": "2022-01-14T10:50:29Z", "salary": {"currency": null, "max": null, "min": null, "period": "hourly", "term": null}, "salary_visible": false, "title_keywords": ["clinic assistant", "health care assistant"], "responsibilities": ["scanning", "reports", "transactions"], "requirements": {"degrees": ["hkdse"], "majors": [], "languages": ["cantonese", "english", "chinese", "mandarin"], "language_level": ["advantage", "proficiency", "good command", "fluent"], "hard_skills": ["pc knowledge", "chinese word processing", "word", "microsoft excel"], "soft_skills": ["good working attitude", "work independently", "confidence", "responsible"], "languages_combined": [{"language": "cantonese", "language_level": ["fluent", "advantage", "good command"]}, {"language": "english", "language_level": ["advantage", "good command"]}, {"language": "chinese", "language_level": ["proficiency"]}, {"language": "mandarin", "language_level": ["advantage", "good command"]}]}, "experience_required": {"duration": [], "field": []}}, {"job_id": "100003009039644", "location_code": "hk", "company": "Cedric & Co.", "job_title": "Receptionist", "description": "ResponsibilitiesPerform reception duties including guests greeting, phone calls and taking messages\n\n\u00a0\u00a0\u00a0\u00a0\u00a0\u00a0\u00a0\u00a0 Handle courier services, incoming and out-going mailing and fax distribution and take records\n\u00a0\u00a0\u00a0\u00a0\u00a0\u00a0\u00a0\u00a0 Maintain smooth operation of the reception counter and meeting room arrangement\n\u00a0\u00a0\u00a0\u00a0\u00a0\u00a0\u00a0\u00a0 Provide administrative and clerical support\n\u00a0\u00a0\u00a0\u00a0\u00a0\u00a0\u00a0\u00a0 Perform ad hoc duties assigned by supervisor\n\n\u00a0Requirements:\n\n\u00a0\u00a0\u00a0\u00a0\u00a0\u00a0\u00a0\u00a0 Fluent in Cantonese and conversational English; Mandarin is a plus\n\u00a0\u00a0\u00a0\u00a0\u00a0\u00a0\u00a0\u00a0 Good PC knowledge in MS Words, Excel & Chinese Word Processing\n\u00a0\u00a0\u00a0\u00a0\u00a0\u00a0\u00a0\u00a0 Immediate availability is preferred", "employment_types": ["Full Time"], "selling_points": [], "locations": ["Central"], "categories": ["Admin & HR", "Clerical / Admin Staff", "Receptionist"], "post_time": "2022-01-11T16:01:53Z", "salary": {"currency": null, "max": null, "min": null, "period": "monthly", "term": null}, "salary_visible": false, "title_keywords": ["receptionist"], "responsibilities": ["ad hoc duties", "maintain", "phone calls", "administrative and clerical support"], "requirements": {"degrees": [], "majors": [], "languages": ["cantonese", "english", "chinese", "mandarin"], "language_level": ["good", "conversational", "fluent"], "hard_skills": ["excel", "plus", "chinese word processing", "ms words", "pc knowledge"], "soft_skills": ["smooth"], "languages_combined": [{"language": "cantonese", "language_level": ["fluent", "conversational"]}, {"language": "english", "language_level": []}, {"language": "chinese", "language_level": ["good"]}, {"language": "mandarin", "language_level": []}]}, "experience_required": {"duration": [], "field": []}}, {"job_id": "100003009040998", "location_code": "hk", "company": "MacDonald and Company", "job_title": "Receptionist (Flight Attendants Welcome) - 5 Day (Urgent)", "description": "To perform general reception duties at the reception area, including greeting and serving visitors\nHandling phone calls, in/out mails/fax and courier arrangement\nTo responsible for meeting room reservation and manage tidiness of the reception and meeting rooms\nAssist in any ad-hoc tasks as assigned\n1-2 years' experience preferred\nGood command of English & Chinese\nCommitted, detail-minded, hardworking, co-operative and responsible\nProficiency MSO usage and Chinese Word Processing\nFlight Attendants from airlines are very welcome\n\nOffer:\n\nHigh basic salary with bonus\nMedical plan and insurance\nLocation in Central\n5 Days work and Working hour: 9am-6pm\n\nInterested parties, please send your CV to\u00a0mlai @macdonaldandcompany.com", "employment_types": ["Full Time", "Permanent"], "selling_points": ["Receptionist", "Office in Central", "5 days work"], "locations": ["Central"], "categories": ["Admin & HR", "Clerical / Admin Staff", "Receptionist", "Marketing / Public Relations", "Digital Marketing"], "post_time": "2022-01-12T03:18:55Z", "salary": {"currency": null, "max": null, "min": null, "period": "monthly", "term": null}, "salary_visible": false, "title_keywords": ["receptionist"], "responsibilities": ["ad-hoc tasks", "insurance", "phone calls", "plan"], "requirements": {"degrees": [], "majors": [], "languages": ["english", "chinese"], "language_level": ["proficiency", "good command"], "hard_skills": ["chinese word processing", "airlines", "basic"], "soft_skills": ["detail-minded", "committed", "hardworking", "responsible"], "languages_combined": [{"language": "english", "language_level": ["good command"]}, {"language": "chinese", "language_level": ["proficiency", "good command"]}]}, "experience_required": {"duration": ["1-2 years"], "field": []}}, {"job_id": "100003009050303", "location_code": "hk", "company": "IDP Education Limited", "job_title": "Administrative Assistant (Student Services)", "description": "Key responsibilities:\n\nSubmit applications to overseas institutions, obtain offers and facilitate enrolments\nProvide visa information and assistance to international students\nGeneral administrative duties and to support in education exhibitions, seminars and day-to-day operations on all aspects of marketing and promoting overseas education.\nPromoting IDP products and services to students\n\nRequirements:\n\n\nDegree holder with at least two years customer service work experience preferred\nProactive, well-organized and customer-oriented\nAbility to multi-task effectively in a fast-paced environment\nGood team player with excellent interpersonal and communication skills\nExperience in working with CRM system will be desirable\nProficiency in written and spoken English and Chinese\n\nWorking Location:\u00a0Wan Chai / Mong kok\n\nA competitive salary commensurate with qualifications and experience will be offered.\n\nApplication: A detailed C.V. stating current and expected salary with covering letter.\n\nClosing date for application:\u00a0\u00a0Monday 31 January 2022\n\nWebsite:\u00a0www.idp.com/hongkong\n\nPersonal data collected will be used for recruitment purpose only.\n\nWe are an Equal Opportunities employer and welcome applications from any member of the community who meets the selection criteria for the position.", "employment_types": ["Full Time", "Permanent"], "selling_points": [], "locations": ["Not Specified"], "categories": ["Admin & HR", "Receptionist", "Others", "Sales, CS & Business Devpt", "Others"], "post_time": "2022-01-14T10:05:18Z", "salary": {"currency": null, "max": null, "min": null, "period": "monthly", "term": null}, "salary_visible": false, "title_keywords": ["administrative assistant"], "responsibilities": ["day-to-day operations", "administrative duties"], "requirements": {"degrees": ["degree holder"], "majors": [], "languages": ["english", "chinese"], "language_level": ["proficiency"], "hard_skills": ["c", "wan"], "soft_skills": ["communication skills", "good team player", "multi-task", "fast-paced environment", "well-organized", "customer-oriented", "customer service", "proactive", "interpersonal", "detailed"], "languages_combined": [{"language": "english", "language_level": ["proficiency"]}, {"language": "chinese", "language_level": ["proficiency"]}]}, "experience_required": {"duration": ["at least two years"], "field": ["customer service"]}}, {"job_id": "100003009034962", "location_code": "hk", "company": "OneStart Group Limited", "job_title": "Centre Receptionist (Full-time & Part-time)", "description": "Duties & Responsibilities\n\nTo perform reception duties including telephone calls, greeting and serving visitors in a professional manner\nHandling incoming and outgoing mails\nTo provide general office administrative and clerical support\u00a0\nContact our client for renewal and/or addition of our services by phone call.\nOther ad-hoc assignments by supervisor\n\n\u00a0Requirements\n\nDSE\u00a0or above\n1-year relevant experience\nGood communication and interpersonal skills\nGood telephone manner, polite, initiative, and willing to learn\nGood command in both written and spoken English, Cantonese & Mandarin\nImmediate available is highly preferred\nCandidates with less experience or fresh graduates will also be considered\n\n\u00a0Working Location:\n\n\u00a0Lai Chi Kok, Mongkok, Kwun Tong, Central, Causeway Bay\n\n\u00a0The hourly wage for the part-time position:\n\n\u00a0$50 per hour\n\nWe offer 5-day work per week and fringe benefits to the right\u00a0candidate\u00a0for a Full-Time position.\u00a0Interested parties please send your\u00a0full resume with date of availability, current and expected salary\u00a0by JobsDB\u00a0to us.\n\nAll information provided by applicants will be used for recruitment-related purposes only and will be treated in the strictest confidence by authorized personnel.\n\n\u00a0For\u00a0further information on our company, please visit our website: https://www.onestartoffices.com/", "employment_types": ["Full Time", "Permanent"], "selling_points": [], "locations": ["Others"], "categories": ["Admin & HR", "Receptionist", "Sales, CS & Business Devpt", "Others", "Others", "Student / Fresh Graduate / No Experience"], "post_time": "2022-01-12T10:16:00Z", "salary": {"currency": null, "max": null, "min": null, "period": "monthly", "term": null}, "salary_visible": false, "title_keywords": ["receptionist"], "responsibilities": ["ad-hoc assignments", "professional manner", "contact", "administrative and clerical support", "incoming and outgoing mails"], "requirements": {"degrees": ["dse"], "majors": [], "languages": ["cantonese", "english", "mandarin"], "language_level": ["good command"], "hard_skills": [], "soft_skills": ["polite", "willing to learn", "communication and interpersonal skills", "telephone manner", "initiative"], "languages_combined": [{"language": "cantonese", "language_level": ["good command"]}, {"language": "english", "language_level": ["good command"]}, {"language": "mandarin", "language_level": ["good command"]}]}, "experience_required": {"duration": ["1-year"], "field": ["relevant experience"]}}, {"job_id": "100003009050863", "location_code": "hk", "company": "Williams Lea (Hong Kong) Ltd", "job_title": "Mailroom Associate", "description": "Mailroom Associate\n\nJob Responsibilities:\n\nMail sorting, collection,\u00a0and distribution\nBooking, receiving, and distribution of courier items\nCollating incoming / outgoing mail and\u00a0courier data\nHandle incoming calls and enquiries in mailroom\nGeneral office administration and other ad hoc duties as assigned by supervisor(s) from time to time\u00a0\nJob Requirements:\n\u00a0\n\nForm 5 / Hong Kong Diploma of Secondary Education Examination or above\nWith at least 1\u00a0year\u00a0of\u00a0relevant work experience; preferably in large corporation or sizable business\nAble to communicate in English\nGood communications skills, attention to detail and reliability\n\nWe offer attractive remuneration package and fringe benefits such as 5 days work, 15 days of annual leave, group medical, dental and life insurance coverage to the successful candidate.\u00a0 In addition, you will have an opportunity to work in a reputable company with excellent career exposure.\u00a0 Interested parties,\u00a0please click \"APPLY NOW\" to submit your application.\n\nAll information provided will be treated confidentially\u00a0and used solely for recruitment purpose.\u00a0\u00a0\n\n\n\n", "employment_types": ["Full Time", "Permanent"], "selling_points": ["Work Location: Central, Hong Kong", "Work Hours: 0900 - 1800, Mon to Fri", "15 Days of AL, Medical, Dental and Life Insurance"], "locations": ["Central"], "categories": ["Admin & HR", "Clerical / Admin Staff", "Receptionist"], "post_time": "2022-01-14T11:35:37Z", "salary": {"currency": null, "max": null, "min": null, "period": "monthly", "term": null}, "salary_visible": false, "title_keywords": ["associate"], "responsibilities": ["ad hoc duties", "data", "office administration", "booking", "outgoing mail"], "requirements": {"degrees": ["form 5", "diploma", "secondary education"], "majors": [], "languages": ["english"], "language_level": [], "hard_skills": [], "soft_skills": ["attention to detail"], "languages_combined": [{"language": "english", "language_level": []}]}, "experience_required": {"duration": ["at least 1 year"], "field": []}}, {"job_id": "100003009047846", "location_code": "hk", "company": "The Chinese General Chamber of Commerce", "job_title": "Clerk (Administration)", "description": "Clerk (Administration)\n\nDuties:\n\n-\u00a0\u00a0\u00a0\u00a0\u00a0\u00a0 Handle daily correspondence\n\n-\u00a0\u00a0\u00a0\u00a0\u00a0\u00a0 Provide administrative support to the department\n\n-\u00a0\u00a0\u00a0\u00a0\u00a0\u00a0 Act as substitute receptionist when needed\n\nQualifications:\n\n-\u00a0\u00a0\u00a0\u00a0\u00a0\u00a0 Form 5 or above, with PC knowledge, familiar with Excel& Photoshop preferable\n\n-\u00a0\u00a0\u00a0\u00a0\u00a0\u00a0 Experience in meeting venue set-up with basic technical knowledge of on-line meeting an advantage\n\n-\u00a0\u00a0\u00a0\u00a0\u00a0\u00a0 Fluent in Cantonese, English & Putonghua\n\n-\u00a0\u00a0\u00a0\u00a0\u00a0\u00a0 Good telephone manner with patience & politeness\n\n-\u00a0\u00a0\u00a0\u00a0\u00a0\u00a0 Preferable with at least 1 year relevant experience", "employment_types": ["Full Time", "Permanent"], "selling_points": [], "locations": ["Central"], "categories": ["Admin & HR", "Clerical / Admin Staff", "Receptionist", "Public / Civil", "Civil Services"], "post_time": "2022-01-14T04:02:18Z", "salary": {"currency": null, "max": null, "min": null, "period": "monthly", "term": null}, "salary_visible": false, "title_keywords": ["clerk"], "responsibilities": ["provide administrative support", "administration"], "requirements": {"degrees": ["form 5 or above"], "majors": [], "languages": ["cantonese", "putonghua", "english"], "language_level": ["fluent"], "hard_skills": ["excel", "pc knowledge", "basic", "photoshop"], "soft_skills": ["telephone manner", "patience"], "languages_combined": [{"language": "cantonese", "language_level": ["fluent"]}, {"language": "putonghua", "language_level": ["fluent"]}, {"language": "english", "language_level": ["fluent"]}]}, "experience_required": {"duration": ["at least 1 year"], "field": ["relevant experience"]}}, {"job_id": "100003009038054", "location_code": "hk", "company": "SAVILLS GUARDIAN", "job_title": "RECEPTIONIST", "description": "Responsibilities\n\n\nResponsible for greeting guests, handling incoming calls, managing conference room booking, courier arrangement, mail services and guests registration\nInterface with external customers and internal customers of all levels\nEnsure the cleanliness and tidiness of the reception area\nProvide clerical and administrative support to Administration Department\nHandle ad hoc projects as required\n\nRequirements\n\n\nForm 5 / HKDSE or above\nMinimum 2 years\u2019 relevant experience in sizable organizations, candidates with customer services experience in other industries will also be considered\nMature and good interpersonal skill\nGood command of written and spoken English and Chinese (including Putonghua)\nProficient in PC knowledge such as Word, Excel, PowerPoint and Chinese word processing\nImmediate available is preferable\n\nWe offer competitive salary package to the right appointees. Applicants are requested to submit detailed resume with expected salary by clicking \"Apply Now\".\n\nPlease quote Emp. Ref No.: ADMIN/012022\n\n(Personal data provided will be used strictly in accordance with our personal data policies, a copy of which will be provided immediately upon request.)", "employment_types": ["Full Time", "Permanent"], "selling_points": ["Responsible for greeting guests", "Interface with external customers", "Minimum 2 years\u2019 relevant experience"], "locations": ["Tai Koo"], "categories": ["Admin & HR", "Clerical / Admin Staff", "Receptionist", "Others"], "post_time": "2022-01-11T04:47:04Z", "salary": {"currency": null, "max": null, "min": null, "period": "monthly", "term": null}, "salary_visible": false, "title_keywords": ["receptionist"], "responsibilities": ["administration", "ad hoc projects", "booking", "administrative support"], "requirements": {"degrees": ["form 5", "hkdse"], "majors": [], "languages": ["putonghua", "english", "chinese"], "language_level": ["good command", "proficient"], "hard_skills": ["excel", "chinese word processing", "word", "powerpoint", "pc knowledge"], "soft_skills": ["mature", "interpersonal skill"], "languages_combined": [{"language": "putonghua", "language_level": ["good command"]}, {"language": "english", "language_level": ["good command"]}, {"language": "chinese", "language_level": ["good command", "proficient"]}]}, "experience_required": {"duration": ["minimum 2 years"], "field": ["relevant experience", "customer services"]}}, {"job_id": "100003009048352", "location_code": "hk", "company": "Action Medical Sundries Limited", "job_title": "Operation Assistant", "description": "Responsibilities:\n\nCoordinate and communicate with external parties and internal staff\nProvide clerical and administrative supports to our Sales and E-commerce Team\nFollow up sale orders and enquires in a professional manner\nAssist in general reception duties, such as such as handling phone calls, greeting visitors, and managing incoming and outgoing courier & mail\nPerform ad-hoc duties as assigned.\n\nRequirements:\n\nDiploma in Business Administration or related disciplines with 1-2 solid working experiences\nGood command of both written and spoken in English and Chinese, fair in Mandarin\nGood command in PC skills, Excel, Word, PowerPoint\nExcellent team player with strong organization skills\nFresh graduates will also be welcome\n\nWe offer attractive compensation package to suitable candidates. Interested parties, please click \"Apply Now\" to\u00a0submit your application.\n\n\n(Personal data collected will be used for recruitment purposes only.)", "employment_types": ["Full Time"], "selling_points": [], "locations": ["Kwai Hing"], "categories": ["Admin & HR", "Clerical / Admin Staff", "Receptionist", "Sales, CS & Business Devpt", "Sales Administration"], "post_time": "2022-01-14T06:24:21Z", "salary": {"currency": null, "max": null, "min": null, "period": "monthly", "term": null}, "salary_visible": false, "title_keywords": ["operation assistant"], "responsibilities": ["communicate with", "external parties", "professional manner", "coordinate", "ad-hoc duties", "phone calls", "greeting visitors"], "requirements": {"degrees": ["diploma"], "majors": ["related disciplines", "business administration"], "languages": ["english", "chinese", "mandarin"], "language_level": ["good command"], "hard_skills": ["excel", "pc skills", "word", "powerpoint"], "soft_skills": ["organization skills", "team player"], "languages_combined": [{"language": "english", "language_level": ["good command"]}, {"language": "chinese", "language_level": ["good command"]}, {"language": "mandarin", "language_level": ["good command"]}]}, "experience_required": {"duration": [], "field": ["related", "business administration"]}}, {"job_id": "100003009042102", "location_code": "hk", "company": "PAN-ASIA ASSETS CONSULTANT LTD.", "job_title": "RECEPTIONIST", "description": "Requirements:\n\n- Higher Diploma or above with 1-2 years relevant working experience.\n\n- Independent and able to work under pressure.\n\n- Mature, well-organized, self-discipline and good interpersonal skills.\n\n- Good Communication skills in written & spoken English, Cantonese and Mandarin.\n\n- Proficiency in computer skills including Microsoft Word, Excel and PowerPoint.\n\n- Fresh Graduate would be considered\n\nJob Responsibilities:\n\n- Responsible to provide professional administrative duties to Managers.\n\n- Handle correspondence telephone calls & emails.\n\n- Coordinate and assist in company events and activities.\n\n- Provide office administration duties and filing system management.\n\n- Provide assistance on PowerPoint presentation materials preparation.\n\n- Collect and prepare information for use in discussions / meetings of internal staff and outside individuals.\n\n- Handles details of a highly confidential and critical nature.\n\nWe offer an attractive salary and benefits for the right candidate. \u00a0Interested parties, please send CV with expected salary\u00a0for application.\u00a0\u00a0Personal data collected will be used solely for recruitment & employment purposes.", "employment_types": ["Full Time"], "selling_points": [], "locations": ["Tsim Sha Tsui"], "categories": ["Admin & HR", "Clerical / Admin Staff", "Receptionist"], "post_time": "2022-01-12T06:08:52Z", "salary": {"currency": null, "max": null, "min": null, "period": "monthly", "term": null}, "salary_visible": false, "title_keywords": ["receptionist"], "responsibilities": ["management", "coordinate", "administrative duties", "office administration duties", "provide assistance"], "requirements": {"degrees": ["higher diploma or above", "fresh graduate"], "majors": [], "languages": ["cantonese", "english", "mandarin"], "language_level": ["good"], "hard_skills": ["excel", "microsoft word", "computer skills", "powerpoint"], "soft_skills": ["communication skills", "independent", "well-organized", "mature", "interpersonal skills", "work under pressure"], "languages_combined": [{"language": "cantonese", "language_level": ["good"]}, {"language": "english", "language_level": ["good"]}, {"language": "mandarin", "language_level": ["good"]}]}, "experience_required": {"duration": ["1-2 years"], "field": ["relevant working experience"]}}, {"job_id": "100003009042848", "location_code": "hk", "company": "Page Personnel", "job_title": "Receptionist - MNC Investment Firm", "description": "Excellent opportunity to join an international investment firm, which is now seeking an experienced Receptionist to provide high quality customer services support.\n\nClient Details\n\nOur client is a well-established international investment firm with over 20 years history in Hong Kong. They provide professional business services for their clients. They are now looking for a Receptionist to join their team.\n\nDescription\n\nCommunicate with clients with calls and emails\nManage and arrange meetings and conference venue for client meeting\nEnsure and maintain conference set up for meetings\nCoordinate visitors' accommodation and workstation matters\nArrange catering and beverage service for clients meeting\nManage rooms cleanliness and maintenance activities\nAssist in any ad-hoc activities assigned by manager\n\nProfile\n\nAbove 2 year's receptionist or client servicing experience from legal, financial or professional services firms\nGood command in spoken and written English and Cantonese\nAdvanced Mandarin is a plus\nAdvanced customer services skills\nExcellent communication and interpersonal skills\nGood team player, good time management and detail minded\n\nJob Offer\n\nStable workdays and work hours\nPremium working location in core Central area\nFriendly and dynamic working environment\nCompetitive remuneration and benefits\n\nTo apply online please click the 'Apply' button below. For a confidential discussion about this role please contact Chloe Chan on +852 3602 2454.", "employment_types": ["Full Time", "Permanent"], "selling_points": ["Dynamic and Westernized culture", "Market leading firm", "Premium work location"], "locations": ["Central & Western Area"], "categories": ["Admin & HR", "Receptionist"], "post_time": "2022-01-12T08:59:38Z", "salary": {"currency": null, "max": null, "min": null, "period": "monthly", "term": null}, "salary_visible": false, "title_keywords": ["receptionist"], "responsibilities": ["communicate with", "ad-hoc", "management", "maintenance", "quality", "customer services", "coordinate", "communication", "maintain", "arrange meetings", "catering"], "requirements": {"degrees": [], "majors": [], "languages": ["cantonese", "english", "mandarin"], "language_level": ["good command"], "hard_skills": ["plus", "dynamic", "maintenance"], "soft_skills": ["good team player", "customer services skills", "advanced", "communication and interpersonal skills", "friendly", "dynamic", "stable", "time management"], "languages_combined": [{"language": "cantonese", "language_level": ["good command"]}, {"language": "english", "language_level": ["good command"]}, {"language": "mandarin", "language_level": []}]}, "experience_required": {"duration": ["2 year"], "field": ["legal", "financial"]}}, {"job_id": "100003009041171", "location_code": "hk", "company": "Aurex Group Limited", "job_title": "Receptionist (Fresh Grad Welcome) - Up to 18k", "description": "5 day work; no OT\nShuttle bus; ORSO scheme\nLocation: Cyberport\nResponsibilities:\n\nPerform reception duties including guests greeting, phone calls and taking messages\nHandle courier services, incoming and out-going mailing and fax distribution and take records\nMaintain smooth operation of the reception counter and meeting room arrangement\nPerform ad hoc duties assigned by supervisor\nRequirements:\n\nGood command in both written and spoken English, Chinese and Mandarin\nGood PC knowledge in MS Words, Excel & Chinese Word Processing\nPolite and pleasant personalities\nResponsible and well organized\n\nIf you believe this opportunity is right for you, please send your CV in English to Sharon Lam by using the \"Apply Now\" button below.\n\nTo view similar opportunities or express interest in related positions, please visit our website www.aurexgroup.com and follow us on LinkedIn https://lnkd.in/fgAWEBa", "employment_types": ["Full Time"], "selling_points": ["5 day work; no OT", "Shuttle Bus; ORSO Scheme", "Location: Cyberport"], "locations": ["Pok Fu Lam"], "categories": ["Admin & HR", "Clerical / Admin Staff", "Receptionist"], "post_time": "2022-01-12T03:32:45Z", "salary": {"currency": null, "max": null, "min": null, "period": "monthly", "term": null}, "salary_visible": false, "title_keywords": ["receptionist"], "responsibilities": ["ad hoc duties", "maintain", "phone calls"], "requirements": {"degrees": [], "majors": [], "languages": ["english", "chinese", "mandarin"], "language_level": ["good command", "good"], "hard_skills": ["excel", "pc knowledge", "chinese word processing", "ms words"], "soft_skills": ["well organized", "polite", "responsible", "pleasant"], "languages_combined": [{"language": "english", "language_level": ["good command", "good"]}, {"language": "chinese", "language_level": ["good command", "good", "good"]}, {"language": "mandarin", "language_level": ["good command", "good"]}]}, "experience_required": {"duration": [], "field": []}}, {"job_id": "100003009043629", "location_code": "hk", "company": "ABC Pathways School", "job_title": "Student Affair Officer / Student Service Officer", "description": "Responsibilities:\n\nHandling general enquiries about appropriate course options and courses offered.\nEnrolling students and taking payments according to the School\u2019s procedures.\nMaintaining filing, indexing or record systems.\nProviding after-sales services and enquiry follow up.\nAssisting to monitor students\u2019 progress and offer support to parents.\nUndertaking other routine administrative duties.\nResponsible to the Centre Manager or the supervisor for providing assistance in school routines.\n\nRequirements:\n\nForm 6 or above, with a 1-2 year working experience in a customer service or related field.\nGood command in spoken and written English as well as Chinese.\nFamiliar in using Microsoft Office (Excel, Word, and PowerPoint).\nStrong sense of responsibility and attention to details.\nGood communication skills with a positive attitude.\nRostered to work 5-day a week including Saturday; prepared to work some Sundays.\nFlexibility in adjusting hours is required when there is an operational need to do so. \u00a0\n\nEmployment Benefits\n\nOff on all Public Holidays\nPerformance Bonus\nMonthly and Annual Good Attendance Bonus\nStaff Price on Tuition Fee\nMedical benefits\n\nRemarks:\n\nMore qualified candidates may be considered for the position of\u00a0Student\u00a0Affair\u00a0Officer / Student Service Officer \u00a0(full time).\nAll successful candidates will be expected to begin as\u00a0Education Trainee.\n\nInterested parties please send full resume, expected salary and date of availability to the Human Resources Director, at Room 2503-05, 25/F., 148 Electric Road, North Point, Hong Kong\n\n\u00a0\u00a0\u00a0\u00a0\u00a0\u00a0\u00a0\u00a0\u00a0\u00a0\u00a0\u00a0\u00a0\u00a0\u00a0\u00a0\u00a0\u00a0\u00a0\u00a0\u00a0\u00a0\u00a0\u00a0\u00a0\u00a0\u00a0 (all data collected will be for recruitment purpose only)", "employment_types": ["Full Time"], "selling_points": ["Form 6 or above", "Relevant customer service experience", "Flexible working hours"], "locations": ["Not Specified"], "categories": ["Admin & HR", "Receptionist", "Sales, CS & Business Devpt", "Customer Service - Supervisor / Officer", "Education", "Others"], "post_time": "2022-01-13T01:07:54Z", "salary": {"currency": null, "max": null, "min": null, "period": "monthly", "term": null}, "salary_visible": false, "title_keywords": ["officer", "student service officer"], "responsibilities": ["maintaining", "systems", "monitor", "procedures", "providing assistance", "payments", "administrative duties"], "requirements": {"degrees": [], "majors": [], "languages": ["english", "chinese"], "language_level": ["good command"], "hard_skills": ["excel", "word", "powerpoint", "microsoft office"], "soft_skills": ["communication skills", "sense of responsibility", "positive attitude", "customer service", "attention to details"], "languages_combined": [{"language": "english", "language_level": ["good command"]}, {"language": "chinese", "language_level": ["good command"]}]}, "experience_required": {"duration": ["1-2 year"], "field": ["related", "customer service"]}}, {"job_id": "100003009045335", "location_code": "hk", "company": "T6 Group Limited", "job_title": "\u524d\u53f0\u63a5\u5f85\u54e1/ Receptionist & CS", "description": "\n\u901a\u8b58\u96c6\u5718\u6709\u9650\u516c\u53f8\u4f4d\u65bc\u6771\u4e5d\u9f8d\u7532\u7d1a\u5546\u696d\u5927\u5ec8\uff0c\u662f\u4e00\u500b\u91dd\u5c0d\u5e7c\u5152\u754c\u5225\u7684\u591a\u5143\u5316\u96c6\u5718\uff0c\u96c6\u5718\u53ca\u5176\u9644\u5c6c\u516c\u53f8\u4e4b\u696d\u52d9\u5305\u62ec\uff1a\u6559\u80b2\uff0c\u8a2d\u8a08\uff0c\u651d\u5f71\uff0c\u5370\u5237\uff0c\u96fb\u8166\u5de5\u7a0b\u53ca\u66f8\u5e97\u7b49\u3002\n\n\u53e6\u4eab \u6bcf\u90315\u5929\u5de5\u4f5c,\u9280\u884c\u5047\u671f,10\u5929\u5e74\u5047,\u52e4\u5de5\u734e\u91d1\u53ca\u8868\u73fe\u734e\u91d1,\u984d\u5916\u4f11\u606f\u65e5,\u5e74\u5c3e\u82b1\u7d05,\u96c6\u5718\u54e1\u5de5\u798f\u5229,\u6bcf\u5e74\u516c\u53f8\u65c5\u884c\u3002\n\n\u8077\u4f4d\u8981\u6c42\n\u2022 \u4e2d\u516d\u6216\u540c\u7b49\u5b78\u6b77\u4ee5\u4e0a\n\u2022 \u4e00\u5e74\u6216\u4ee5\u4e0a\u5de5\u4f5c\u7d93\u9a57\uff0c\u66fe\u65bc\u5ba2\u6236\u670d\u52d9/\u96fb\u8a71\u92b7\u552e\u5de5\u4f5c\u7d93\u9a57\u8005\u512a\u5148\n\u2022 \u7a4d\u6975\u4e3b\u52d5\u3001\u5177\u5099\u826f\u597d\u670d\u52d9\u614b\u5ea6\u3001\u826f\u597d\u6e9d\u901a\u80fd\u529b\u548c\u5206\u6790\u89e3\u6c7a\u554f\u984c\u80fd\u529b\n\u2022 \u57fa\u672c\u96fb\u8166\u64cd\u4f5c\uff0c\u901f\u6210\u6216\u5009\u9821\u4e2d\u6587\u8f38\u5165\u6cd5\n\u2022 \u5fc5\u9808\u61c2\u7cb5\u8a9e\u53ca\u57fa\u672c\u82f1\u8a9e\u53ca\u666e\u901a\u8a71\n\n\u00a0 \u5de5\u4f5c\u7bc4\u570d\n\u2022 \u524d\u53f0\u5de5\u4f5c\u53ca\u63a5\u5f85\u5ba2\u4eba\n\u2022 \u8ddf\u9032\u8a02\u55ae\u9032\u5ea6\uff0c\u4e00\u822c\u6587\u66f8\u5de5\u4f5c\uff0c\u8cc7\u6599\u8f38\u5165\uff0c\u8655\u7406\u96fb\u8a71\u67e5\u8a62\n\u2022 \u4e3b\u52d5\u7a4d\u6975\u63d0\u4f9b\u512a\u8cea\u5ba2\u6236\u670d\u52d9\n\u2022 \u5354\u52a9\u96c6\u5718\u65e5\u5e38\u904b\u4f5c\n\n\u00a0 \u5de5\u4f5c\u6642\u9593\n\u2022 \u4e0a\u534810\u9ede\u81f3\u4e0b\u53487\u9ede\uff0c\u8f2a\u4f11\n\u2022 \u6b61\u8fce\u7562\u696d\u751f\u7533\u8acb\n\n\u00a0 \u7533\u8acb\u7a0b\u5e8f\n\u6709\u610f\u8005\u8acb\u9023\u540c\u5c65\u6b77\u6309Apply Now\u7533\u8acb \uff0c\u4e26\u5217\u660e\u53ef\u5230\u8077\u65e5\u671f\u53ca\u8981\u6c42\u5f85\u9047\u3002\n(\u7533\u8acb\u8cc7\u6599\u53ea\u4f5c\u62db\u8058\u7528\u9014\uff0c\u4e26\u7d55\u5c0d\u4fdd\u5bc6\u3002)\n\u00a0\n", "employment_types": ["Full Time"], "selling_points": [], "locations": ["Not Specified"], "categories": ["Admin & HR", "Clerical / Admin Staff", "Receptionist", "Others"], "post_time": "2022-01-13T07:38:43Z", "salary": {"currency": null, "max": null, "min": null, "period": "monthly", "term": null}, "salary_visible": false, "title_keywords": ["receptionist"], "responsibilities": [], "requirements": {"degrees": [], "majors": [], "languages": [], "language_level": [], "hard_skills": [], "soft_skills": [], "languages_combined": []}, "experience_required": {"duration": [], "field": []}}, {"job_id": "100003009050578", "location_code": "hk", "company": "Exact Medical Group Limited", "job_title": "Accounting & Admin. Assistant", "description": "Job Description\n\n1) Assisting Accounting duties:\n\nHandling daily general accounting duties, data entry and filing\nHandling the month end closing and bank reconciliation\nCoordinating accounting functions for the inter-company transactions and reconciliation\n2) Assisting General Administrative and Receptionist duties:\u00a0\n\nBeing responsible for courier and mails arrangement\nBeing responsible for office & pantry supplies procurement and inventory control\nBeing responsible for office equipment repair and maintenance\n\n3) Performing ad-hoc duties assigned by Manager\n\n\nRequirements\n\nDiploma or above\n1-2 years of related experience is preferable (fresh graduates are also welcomed)\nGood command in both spoken and written English and Chinese\nGood typing skill and knowledge of PC (including WORD, EXCEL)\nIndependent with strong sense of responsibility and attention to details", "employment_types": ["Full Time", "Permanent"], "selling_points": ["Accounting", "Admin", "Clerk"], "locations": ["Tsim Sha Tsui"], "categories": ["Accounting", "Others", "Admin & HR", "Clerical / Admin Staff", "Receptionist"], "post_time": "2022-01-14T10:48:54Z", "salary": {"currency": null, "max": null, "min": null, "period": "monthly", "term": null}, "salary_visible": false, "title_keywords": ["accounting & admin. assistant"], "responsibilities": ["month end closing", "data entry and filing", "maintenance", "bank reconciliation", "transactions", "repair", "inventory control", "general accounting duties", "ad-hoc duties", "accounting duties"], "requirements": {"degrees": ["diploma or above"], "majors": [], "languages": ["english", "chinese"], "language_level": ["good command"], "hard_skills": ["pc", "excel", "typing", "word"], "soft_skills": ["independent", "attention to details", "sense of responsibility"], "languages_combined": [{"language": "english", "language_level": ["good command"]}, {"language": "chinese", "language_level": ["good command"]}]}, "experience_required": {"duration": ["1-2 years"], "field": ["related"]}}, {"job_id": "100003009037396", "location_code": "hk", "company": "Anahata Yoga Limited", "job_title": "Customer Service (Full-time)", "description": "Responsibilities\n\nGreeting guests, answering incoming calls\nEnsure reception area is tidy and presentable\nProvide basic and accurate information in-person and via phone/email\nSchedule bookings\nSales\n\n\nRequirements:\n\nGood Command of English, Cantonese speaking is preferred\n\nGood communication, interpersonal skill with positive and helpful attitude\nResponsible and hard working\nTeam player and able to work independently\nDriven and sales oriented (may be considered for the sales position)\nSales experience are bonus\n\nWe offer:\n\nAttractive salary\n6 days work (Full-Time)\nFree membership\u00a0\nWork in Central\n\nFor sales position, in addition to the above,\u00a0\n\nSales Commission\u00a0\nBonus\n\nInterest parties, please forward a detailed resume, stating your availability, current and expected salary to\n\nTel: 2905-1822 Fax: 2905-1885\n\n\u00a0(All personal data collected will be used for recruitment purpose only.)", "employment_types": ["Full Time"], "selling_points": [], "locations": ["Central"], "categories": ["Admin & HR", "Receptionist", "Sales, CS & Business Devpt", "Customer Service - Supervisor / Officer", "Sales Administration"], "post_time": "2022-01-11T02:43:33Z", "salary": {"currency": null, "max": null, "min": null, "period": "monthly", "term": null}, "salary_visible": false, "title_keywords": ["customer service"], "responsibilities": ["schedule"], "requirements": {"degrees": [], "majors": [], "languages": ["cantonese", "english"], "language_level": ["good command"], "hard_skills": [], "soft_skills": ["work independently", "responsible", "hard working", "interpersonal skill", "communication", "team player", "driven", "positive"], "languages_combined": [{"language": "cantonese", "language_level": ["good command"]}, {"language": "english", "language_level": ["good command"]}]}, "experience_required": {"duration": [], "field": []}}, {"job_id": "100003009049891", "location_code": "hk", "company": "Learning Habitat Families (Hampton Loft) Limited", "job_title": "Administrative Assistant", "description": "Responsibilities\n\nHandle incoming inquires and application on a daily basis;\nAssist and guide parents through the application process;\nHandle office administrative duties;\nPerform other ad-hoc duties as assigned\n\nRequirement\n\nDegree holder;\u00a0\n1-2 years office administration experience;\nExperiences working at learning centre preferred;\nExcellent command of written / spoken English and Chinese;\nAttention to details;\nLove Kids with cheerful and passionate personality;\nBe able to work independently and as part of a team;\nProficient in MS Word, Excel, PowerPoint & Chinese Word Processing;\nWork location: Tsueng Kwan O;\nWorking hour: 8:30 am to 5:15 pm, Tuesday toSaturday\n\nWe offer competitive salaries and benefits commensurate with experiences and qualifications.\n\nInterested party please apply with your full resume with your preferred teaching timeslots and expected salary.\n\nTo know more about us, please visit our website:\u00a0https://littlehabs.com/\n\nAll information received will be kept in strict confidential and only for employment-related purposes within our Bluetop Group of Companies. You may consider your application unsuccessful if you do not hear from us within 12 weeks.", "employment_types": ["Full Time", "Permanent"], "selling_points": ["Excellent command of English & Chinese", "1-2 experiences", "Love Kids with cheerful personality"], "locations": ["Tseung Kwan O"], "categories": ["Admin & HR", "Clerical / Admin Staff", "Receptionist", "Others"], "post_time": "2022-01-14T09:24:22Z", "salary": {"currency": null, "max": null, "min": null, "period": "monthly", "term": null}, "salary_visible": false, "title_keywords": ["administrative assistant"], "responsibilities": ["administrative duties", "ad-hoc duties"], "requirements": {"degrees": ["degree holder"], "majors": [], "languages": ["english", "chinese"], "language_level": ["excellent", "proficient"], "hard_skills": ["excel", "chinese word processing", "powerpoint", "ms word"], "soft_skills": ["work independently", "cheerful", "learning", "passionate personality", "attention to details"], "languages_combined": [{"language": "english", "language_level": ["excellent"]}, {"language": "chinese", "language_level": ["excellent", "proficient"]}]}, "experience_required": {"duration": ["1-2 years"], "field": ["office administration"]}}, {"job_id": "100003009043791", "location_code": "hk", "company": "Hypebeast Hong Kong Limited", "job_title": "Administrative Assistant", "description": "Hypebeast Ltd. started from a sneaker website founded by Kevin Ma in 2005 to a publicly listed media company in 2016. With a total reach of over 44.6M users across all platforms, The media group boasts a global readership across Asia Pacific, North America, Europe and more, with the flagship platform available in five languages. The group has expanded its publishing brands to a wider scope in recent years, encompassing Hypebeast and its multiple content distribution platforms, HBX, our e-commerce and retail platform, and Hypemaker, our global agency.\n\nHypebeast Ltd. has been featured in Forbes\u2019 \u201cAsia\u2019s 200 Best Under A Billion\u201d in 2020.\n\nResponsibilities:\n\nGreet guests and visitors.\nScreen and answer phone calls in a professional and timely manner.\nCoordinate mailings, courier and deliveries.\nMonitor attendance of staff and prepare attendance reports on a monthly basis.\nWorking with various departments to ensure that guests are promptly served.\nResponsible for office supplies and maintenance.\nParticipate in any ad hoc tasks and assigned projects.\nRequirements:\n\n1+ year of experience in an assistant role.\nProficient in MS Office Skills.\nExcellent proficiency in both spoken and written English.\nProfound attention to detail, good time management skills and is able to multitask a number of projects at any given time.\nProactive with excellent interpersonal and communication skills.\nAble to work independently and effectively.\nAbility to lift objects up to 25lb.\nFresh graduates with passion are welcome.\nIf you think you\u2019ve got what it takes, please provide your cover letter, CV and expected salary.\n\nThis role is located and based in Hong Kong. Candidate must be eligible to work in Hong Kong.\n\nPersonal data collected is for recruitment purpose only.", "employment_types": ["Full Time"], "selling_points": ["Multi-cultural with energetic working environment", "Young, creative and international team members", "Fresh graduates are welcome"], "locations": ["Tsuen Wan Area"], "categories": ["Admin & HR", "Clerical / Admin Staff", "Receptionist", "Transportation & Logistics", "Inventory / Warehousing"], "post_time": "2022-01-13T01:57:39Z", "salary": {"currency": null, "max": null, "min": null, "period": "monthly", "term": null}, "salary_visible": false, "title_keywords": ["administrative assistant"], "responsibilities": ["attendance", "maintenance", "office supplies", "monitor", "ad hoc tasks", "coordinate", "reports", "answer phone calls"], "requirements": {"degrees": [], "majors": [], "languages": ["english"], "language_level": ["excellent", "proficiency"], "hard_skills": ["ms office"], "soft_skills": ["communication skills", "work independently", "time management skills", "multitask", "attention to detail", "proactive", "interpersonal"], "languages_combined": [{"language": "english", "language_level": ["excellent", "proficiency"]}]}, "experience_required": {"duration": ["1+ year"], "field": []}}, {"job_id": "100003009046716", "location_code": "hk", "company": "QSC Audio", "job_title": "Sales/Office Administrator (temporary)", "description": "Job description:\n\nIn the role of a Sales/Office administrator you are responsible for support and manage the QSC, Asia office and sales administration work. This is a 6-months temporary position.\n\n\n\nResponsibilitiesAssignment will cover the following areas:\n\nSales Admin:\n\nSales force pipeline\nSales force Contact points update\nMDF (Marketing development fund) Communications with partners\nAny additional projects as assigned\nOffice Admin:\n\nManage Travel Arrangement\nCourier arrangement\nTrack stocks of office supplies and place orders when necessary\nWelcoming visitors\nOverseeing the maintenance of office facilities and equipment\nAssist colleagues whenever necessary\n\n\n\nRequired profile:\n\nQualifications\nProven experience as an office assistant or relevant role\nGood communication and interpersonal abilities\nUniversity degree holder in BA or related discupline with professional administrative and secretarial training preferred\nProactive, mature, ordanized and details-oriented\nExcellent comments in spoken and written English and Cantonese\nImmediate availability a PLUS\nMust be able to work Monday to Friday, 9am to 4:30 pm. (1-1.5 hours for lunch)\n\n\n\nWhat we offer:\n\nN/A - To be discussed at a later date", "employment_types": ["Temporary"], "selling_points": [], "locations": ["Tsuen Wan Area"], "categories": ["Admin & HR", "Clerical / Admin Staff", "Receptionist", "Others"], "post_time": "2022-01-13T23:43:59Z", "salary": {"currency": null, "max": null, "min": null, "period": null, "term": null}, "salary_visible": false, "title_keywords": ["administrator", "sales"], "responsibilities": ["sales administration", "communications with", "maintenance", "office supplies", "comments", "communication", "contact", "travel arrangement"], "requirements": {"degrees": ["university degree"], "majors": [], "languages": ["cantonese", "english"], "language_level": ["excellent"], "hard_skills": ["plus", "maintenance"], "soft_skills": ["responsible", "mature", "communication", "proactive", "interpersonal"], "languages_combined": [{"language": "cantonese", "language_level": ["excellent"]}, {"language": "english", "language_level": ["excellent"]}]}, "experience_required": {"duration": [], "field": []}}, {"job_id": "100003009051332", "location_code": "hk", "company": "Assurance Education Limited", "job_title": "Administrative Assistant/Secretary, Full Time", "description": "Job Description: Administrative Assistant/Secretary\n\nOrganization\n\nAssurance aims to help students make blossom and make the most out of high school. Assurance is headquartered in Hong Kong and maintains offices in Shenzhen and Shanghai. Our managing director and founder undertook undergraduate education in law at the University of Cambridge. He has taught English for more than ten years. All of our consultants are from top universities such as Wharton, Harvard, UPenn and UChicago. For more information, please visit www.assuranceedu.com.\n\nPosition\n\nAdministrative Assistant/Secretary, Full Time\n\nLocation\n\nCauseway Bay\n\nHours\n\n5 days work week\nTuesday to Saturday\n9.30am to 6.30pm\n\nResponsibilities\n\nProvide administrative support\nHandle correspondence\nManage school application forms\nAssist in seminars and events\n\nRequirements\n\nFluency in Cantonese, English and Mandarin\nProficient in Word, Excel, and word processing in English & Chinese\n1 year of experience as administrative assistant/secretary\nDegree holder in any discipline\n\nCompensation\n\nWe offer a starting salary of $15000-$17,000/month. Please state your expected salary.\n\nApplication\n\nInterested parties please submit your resume and cover letter to Ms. Tiffany Cheung at admin @ AssuranceEDU.com\u00a0with \u201c[Name] Assurance Recruitment]\u201d in the email title. Please state your expected salary.", "employment_types": ["Full Time"], "selling_points": ["Proficiency in English, Cantonese & Mandarin", "Degree holder, 1 year of experience", "Salary $15-17K, 5 days working"], "locations": ["Causeway Bay"], "categories": ["Admin & HR", "Personal / Executive Assistant", "Receptionist", "Secretary"], "post_time": "2022-01-15T09:22:29Z", "salary": {"currency": "HKD", "max": 16999, "min": 14000, "period": "monthly", "term": null}, "salary_visible": true, "title_keywords": ["administrative assistant", "secretary"], "responsibilities": ["provide administrative support"], "requirements": {"degrees": ["degree holder"], "majors": [], "languages": ["cantonese", "english", "chinese", "mandarin"], "language_level": ["fluency", "proficient"], "hard_skills": ["excel", "word processing", "word"], "soft_skills": [], "languages_combined": [{"language": "cantonese", "language_level": ["fluency"]}, {"language": "english", "language_level": ["fluency", "proficient"]}, {"language": "chinese", "language_level": ["fluency", "proficient"]}, {"language": "mandarin", "language_level": ["fluency"]}]}, "experience_required": {"duration": ["1 year"], "field": ["administrative"]}}, {"job_id": "100003009051065", "location_code": "hk", "company": "AL Design & Associates Limited", "job_title": "Account & Admin. Clerk", "description": "Job Highlights\n\nAccounting routine job tasks\nAsst. in office administration\nImmediately Available\n\nJob Description\n\nResponsibilities:\n\nHandle account payables and receivables\nPrepare payment vouchers and receipts\nProvide general clerical and administrative supports including data entry & filing\nReceive, direct and relay telephone calls and messages\nAssist in company activities and other ad-hoc projects as assigned.\n\nRequirements:\n\nF.6 or above , prefer 1-2 years relevant working experience\nKnowledge in MS Office, especially in Excel and Word\nFresh Graduates will also be considered\nGood command of both written and spoken English and Chinese\nSelf-motivated, independent, hardworking and responsible\nWilling to learn and work under pressure\nImmediate availability is preferred\n\nWe offer competitive remuneration package (12 days Annual Leave, Discretionary Bonus, Group Medical Insurance) with long-term career prospects to the right candidate.\u00a0Our new office is located in the heart of Kwun Tong, offering a spacious and relaxed teamwork environment.\u00a0\u00a0Interested parties please mark in the email subject which post you apply\u00a0for and send full resume, availability, current salary and expected salary to HR Dept. by email recruitment @ aldesign.com.hk", "employment_types": ["Full Time", "Permanent"], "selling_points": ["Account clerk, Admin. clerk", "1-2 years experience,", "Fluent in English & Cantonese"], "locations": ["Kwun Tong"], "categories": ["Accounting", "Accounting Clerk / Supervisor", "Admin & HR", "Clerical / Admin Staff", "Receptionist"], "post_time": "2022-01-15T01:40:28Z", "salary": {"currency": null, "max": null, "min": null, "period": "monthly", "term": null}, "salary_visible": false, "title_keywords": ["admin", "clerk"], "responsibilities": ["payment", "ad-hoc projects", "receipts", "data entry"], "requirements": {"degrees": [], "majors": [], "languages": ["english", "chinese"], "language_level": ["good command"], "hard_skills": ["excel", "word", "ms office"], "soft_skills": ["self-motivated", "independent", "responsible", "teamwork", "willing to learn", "hardworking", "work under pressure"], "languages_combined": [{"language": "english", "language_level": ["good command"]}, {"language": "chinese", "language_level": ["good command"]}]}, "experience_required": {"duration": ["1-2 years"], "field": ["relevant working experience"]}}, {"job_id": "100003009049911", "location_code": "hk", "company": "Michael Kors (HK) Limited", "job_title": "Administration Officer (6 months Contract)", "description": "ESSENTIAL JOB RESPONSIBILITIES:\n\n\n\nProvide all-rounded support for office relocation project including but not limited to coordinate moving logistics, handle related enquiries etc.\nHandle flight and hotel bookings for staff and visitors\nManage stationery procurement, office cleaning & pest control and license renewal\nManage incoming and outgoing courier / mail / fax arrangement\nPerform administration support to office and stores, and other ad hoc duties as assigned\n\nREQUIREMENTS:\u00a0\u00a0\n\n\nDiploma or above, major in administration management will be preferable\nAt least 2 years or above relevant working experience\nExcellent telephone manner with good interpersonal skills\nProficiency in Microsoft Office and Chinese typewriting\nPresentable, meticulous, well organized, good communication skills with strong sense of responsibility\nGood command of written and spoken English, Mandarin and Cantonese\nImmediate available is highly desirable\n\nWe offer remuneration package\u00a0commensurate with qualification and experience to the successful candidate.\u00a0 If you would like to apply for this position or find out more, please press 'Apply Now'.\n\n(Data collected will be treated as strict confidential and will be used for recruitment purpose only.)", "employment_types": ["Contract"], "selling_points": ["Immediate available is highly desirable", "Responsible for office relocation project", "Assist any ad-hoc tasks"], "locations": ["Tsim Sha Tsui"], "categories": ["Admin & HR", "Clerical / Admin Staff", "Receptionist", "Others"], "post_time": "2022-01-14T09:26:44Z", "salary": {"currency": null, "max": null, "min": null, "period": "monthly", "term": null}, "salary_visible": false, "title_keywords": ["administration officer"], "responsibilities": ["ad hoc duties", "control", "stationery", "coordinate", "logistics", "cleaning", "administration"], "requirements": {"degrees": ["diploma or above"], "majors": [], "languages": ["cantonese", "english", "chinese", "mandarin"], "language_level": ["proficiency", "good command"], "hard_skills": ["typewriting", "microsoft office"], "soft_skills": ["meticulous", "communication skills", "sense of responsibility", "well organized", "presentable", "interpersonal skills", "telephone manner"], "languages_combined": [{"language": "cantonese", "language_level": ["good command"]}, {"language": "english", "language_level": ["good command"]}, {"language": "chinese", "language_level": ["proficiency"]}, {"language": "mandarin", "language_level": ["good command"]}]}, "experience_required": {"duration": ["at least 2 years"], "field": ["relevant working experience"]}}, {"job_id": "100003009045972", "location_code": "hk", "company": "Tricor Staffing Solutions Limited", "job_title": "Admin Assistant (Government Center) Ref No: CT59PC", "description": "Job Descriptions\n\nOur client is working in the cultural sector. They are now looking for new candidates that could support their further operations.\n\nResponsibilities\n\nAssist in general administrative duties, including faxing, photocopying, mailing, updating system, answering enquires\nHandle booking and operational issues, such as updating booking system, answering phone inquiry, preparing documents and compiling statistics\nPrepare monthly calendars for publication and liaise with other departments and parties\nAssist in documents preparation for program and event arrangement\n\nRequirements\n\nPermanent resident of the HKSAR\nForm 5 or above\nLevel 2 or above in English Language and Chinese Language\nAt least 4 years of working experience, preferably in secretary and admin field or under government and civil setting\nGood command in both written and spoken English and Chinese\nProficient in MS Office applications\nCan work independently and with good communication skills\n\nApplicants should click \u201cAPPLY NOW\u201d to apply for the job.\u00a0 Please quote the ref. \u2018Admin Assistant (Government Center) Ref No: CT59PC\u2019 on your application.\u00a0\u00a0 For inquiries, please contact on +852 55477049 (WhatsApp only)", "employment_types": ["Full Time", "Contract"], "selling_points": ["Working hours: 9:00am \u2013 6:00pm (5 days of work)", "Admin duties", "Form 5 or above"], "locations": ["Kwun Tong"], "categories": ["Admin & HR", "Clerical / Admin Staff", "Receptionist", "Marketing / Public Relations", "Public Relations - General / Support"], "post_time": "2022-01-13T09:17:15Z", "salary": {"currency": null, "max": null, "min": null, "period": null, "term": null}, "salary_visible": false, "title_keywords": ["admin assistant"], "responsibilities": ["operations", "administrative duties", "booking", "liaise with", "publication"], "requirements": {"degrees": ["form 5 or above"], "majors": [], "languages": ["english", "chinese"], "language_level": ["good command"], "hard_skills": ["whatsapp", "no", "ms office"], "soft_skills": ["communication skills", "work independently"], "languages_combined": [{"language": "english", "language_level": ["good command"]}, {"language": "chinese", "language_level": ["good command"]}]}, "experience_required": {"duration": ["at least 4 years"], "field": ["admin"]}}, {"job_id": "100003009040660", "location_code": "hk", "company": "Pretty Beauty International Limited", "job_title": "\u7f8e\u5bb9\u9662\u63a5\u5f85\u54e1 Receptionist", "description": "\n\u5de5\u4f5c\u8077\u8cac:\n\u8ca0\u8cac\u5206\u5e97\u63a5\u5f85\u5de5\u4f5c\u53ca\u63a5\u807d\u9810\u7d04\u96fb\u8a71\u89e3\u7b54\u5ba2\u6236\u4e00\u822c\u67e5\u8a62\u4e00\u822c\u6587\u66f8\u5de5\u4f5c\n\u5165\u8077\u8981\u6c42:\n\u4e00\u5e74\u4ee5\u4e0a\u76f8\u95dc\u5de5\u4f5c\u7d93\u9a57\u61c2\n\u2022 Microsoft Office\n\u2022 \u4e2d\u82f1\u6587\u6253\u5b57\u8207\u5ba2\u4eba\u5efa\u7acb\u4e26\u4fdd\u6301\u826f\u597d\u95dc\u4fc2\u6709\u71b1\u8aa0\u3001\u6709\u4e0a\u9032\u5fc3\u3001\u89aa\u5207\u6709\u79ae\n\u2022 \u6709\u8cac\u4efb\u611f\n\u2022 \u826f\u597d\u670d\u52d9\u614b\u5ea6\u548c\u6e9d\u901a\u6280\u5de7\u559c\u611b\u5718\u968a\u5de5\u4f5c\u5de5\u4f5c\u71b1\u8aa0\n\u2022 \u7a4d\u6975\u4e3b\u52d5\n\u2022 \u8457\u91cd\u5718\u9ad4\u7cbe\u795e\n\u54e1\u5de5\u798f\u5229:\n\u2022 \u5c08\u696d\u5728\u8077\u57f9\u8a13\n\u2022 \u826f\u597d\u6649\u5347\u6a5f\u6703\n\u2022 \u6709\u85aa\u5047\u671f\n\u2022 \u512a\u539a\u85aa\u916c\n\u2022 \u6bcf\u6708\u53ef\u90546\u5929\u6709\u85aa\u4f8b\u5047\n\u2022 \u6709\u85aa\u5e74\u5047\u53ef\u905414\u5929\n\u62db\u8058\u71b1\u7dda: 3425 4351/WhatsApp 6673 3251/ \u96fb\u90f5\u5230 hr @prettybeautygroup.com\n(*\u6c42\u8077\u8005\u905e\u4ea4\u500b\u4eba\u8cc7\u6599\u53ea\u4f5c\u62db\u8058\u7528\u9014*,\u6240\u6709\u8cc7\u6599\u7d55\u5c0d\u4fdd\u5bc6\u3002)\n16\u9593\u5206\u5e97\u904d\u4f48\u9999\u6e2f, \u4e5d\u9f8d, \u65b0\u754c:\u534a\u5c71\u3001\u9285\u947c\u7063\u3001\u5c16\u6c99\u5480\u3001\u592a\u5b50\u3001\u65fa\u89d2\u3001\u89c0\u5858\u3001\u8343\u7063\u3001\u5143\u6717\u3001\u5c6f\u9580\u3001\u6c99\u7530\u3001\u4e0a\u6c34\n\u6240\u6709\u6536\u96c6\u7684\u7533\u8acb\u8cc7\u6599\u548c\u6578\u64da\u5c07\u56b4\u683c\u4fdd\u5bc6,\u50c5\u7528\u65bc\u62db\u8058\u76ee\u7684\u3002\u53ea\u6709\u5165\u570d\u7684\u5019\u9078\u4eba\u5c07\u88ab\u9080\u8acb\u53c3\u52a0\u9762\u8a66\u3002\u516c\u53f8\u5c07\u4fdd\u7559\u7533\u8acb\u8cc7\u6599\u7684\u6700\u9577\u671f\u9650\u70ba6*\u500b\u6708,\u671f\u5f8c\u5168\u90e8\u522a\u9664\u3002*\n\u5de5\u4f5c\u985e\u578b: \u5168\u8077, \u9577\u5de5\n\u85aa\u916c: $12,000.00\u81f3$14,000.00(\u6bcf\u6708)\n\u6642\u9593:\n\u2022 \u65e5\u73ed\n\u798f\u5229:\n\u2022 \u5728\u8077\u5c08\u696d\u57f9\u8a13\n\u9060\u7a0b\u5de5\u4f5c:\n\u2022 \u5426\n\n", "employment_types": ["Full Time"], "selling_points": [], "locations": ["Not Specified"], "categories": ["Admin & HR", "Clerical / Admin Staff", "Receptionist", "Others"], "post_time": "2022-01-12T02:55:35Z", "salary": {"currency": null, "max": null, "min": null, "period": "monthly", "term": null}, "salary_visible": false, "title_keywords": ["receptionist", "\u7f8e\u5bb9\u9662\u63a5\u5f85\u54e1"], "responsibilities": ["hr"], "requirements": {"degrees": [], "majors": [], "languages": [], "language_level": [], "hard_skills": ["whatsapp", "microsoft office"], "soft_skills": [], "languages_combined": []}, "experience_required": {"duration": [], "field": []}}, {"job_id": "100003009048333", "location_code": "hk", "company": "SEB Asia Limited", "job_title": "Administration Officer (Maternity Cover, 6-month contract)", "description": "What\u2019s in it for you:\n\n\nTo assist in office maintenance and contract renewal (alarm system, telephone, IDD, copier, water leakage, air-conditioning, furniture, carpet cleaning, lighting etc.)\nTo keep inventory, order and arrange placement of office stationery and break room supply\nTo check all invoices relating to administration aspects\nTo assist in organizing staff event (annual dinner, farewell party)\nTo coordinate with staff for file storage in warehouse company and keep storage inventory list updated\nTo take charge of product distribution for staff purchase\nTo assist in group meeting (meeting room set up, visio connection, lunch ordering, etc.)\nTo assist in renovation project\nTo arrange workstation for new joining staff\nTo assist in company stationery printing\nTo back up receptionist\nTo keep the office neat and organized and monitor office safety\nTo assist in donation or charity event\nWhat we are looking for:\n\nAt least 3 years of relevant experience\nDiploma / Associate Degree graduate\nNative Cantonese, fluent English and Mandarin\nPatient, flexible, good interpersonal skills, positive attitude, willing to go extra miles\nAssertive character to deal with all levels\nProficient in MS Office Word, Excel, PowerPoint and Chinese Word Processing\n\nWe offer attractive remuneration package to the right candidate including 5-day work.\n\nInterested parties please apply with full resume with\u00a0expected salary\u00a0and current salary\u00a0to\u00a0Human Resources\u00a0Department.\u00a0For company details, please visit our\u00a0website.\n\nAll data collected is for recruitment purpose only. Candidates not invited for interview within 8 weeks from the date of this posting may consider their applications unsuccessful. Unsuccessful applications will be destroyed after 6 months.\u00a0", "employment_types": ["Full Time", "Temporary", "Contract"], "selling_points": ["5-day work", "5 minutes walk from Olympic Station", "The Global leader in Small Domestic Appliances"], "locations": ["Yau Tsim Mong Area"], "categories": ["Admin & HR", "Administration / Operation Manager", "Clerical / Admin Staff", "Receptionist"], "post_time": "2022-01-14T06:39:11Z", "salary": {"currency": null, "max": null, "min": null, "period": "monthly", "term": null}, "salary_visible": false, "title_keywords": ["administration officer"], "responsibilities": ["invoices", "maintenance", "file storage", "inventory", "renovation", "coordinate with", "stationery", "monitor", "purchase", "cleaning", "administration"], "requirements": {"degrees": ["associate degree", "diploma"], "majors": [], "languages": ["cantonese", "english", "chinese", "mandarin"], "language_level": ["native", "proficient", "fluent"], "hard_skills": ["excel", "chinese word processing", "maintenance", "word", "charity", "powerpoint", "go", "ms office"], "soft_skills": ["flexible", "organized", "assertive", "positive attitude", "interpersonal skills", "patient"], "languages_combined": [{"language": "cantonese", "language_level": ["native", "fluent"]}, {"language": "english", "language_level": ["native", "fluent"]}, {"language": "chinese", "language_level": ["proficient"]}, {"language": "mandarin", "language_level": ["native", "fluent"]}]}, "experience_required": {"duration": ["at least 3 years"], "field": ["relevant experience"]}}, {"job_id": "100003009041709", "location_code": "hk", "company": "Devon Beauty Centre Limited", "job_title": "\u5168\u8077 \u7f8e\u5bb9\u9662\u63a5\u5f85\u54e1 (Full-Time Receptionist)-\u6cb9\u5c16\u65fa/\u9285\u947c\u7063", "description": "\n\u8aa0\u9080 \u5168\u8077\u7f8e\u5bb9\u9662\u63a5\u5f85\u54e1 *\u7121\u7f8e\u5bb9\u76f8\u95dc\u7d93\u9a57\u4e5f\u53ef\u7533\u8acb*\n\u6708\u85aa $12000-$16000- \u8996\u4e4e\u5de5\u4f5c\u7d93\u9a57 (\u53ef\u9762\u8b70)\n(\u6b61\u8fce\u7f8e\u5bb9\u540c\u884c/\u96f6\u552e/\u9152\u5e97/\u670d\u52d9\u696d\u7b49\u524d\u7dda\u5de5\u4f5c\u8005\u7533\u8acb)\n\n\u5de5\u4f5c\u5730\u9ede \uff1a \u65fa\u89d2 \u2022 \u9285\u947c\u7063 \u2022 \u5c16\u6c99\u5480\n\u2022 \u516c\u53f8\u4ee5\u670d\u52d9\u70ba\u5148\u3001NO\u5c0f\u5708\u5b50! NO\u4eba\u4e8b\u8907\u96dc! \u6e96\u6642\u51fa\u7ce7\n\n\u2022 8\u5c0f\u6642\u5de5\u4f5c\uff0c1\u5c0f\u6642\u5348\u98ef\u4f11\u606f\u6642\u9593\n\n\u2022 \u7121\u9700\u8f2a\u66f4 \u3001\u7121\u9700Cold Call/\u92b7\u552e\u3001\u6bcf\u6708\u52e4\u5de5\u53ca\u8868\u73fe\u734e\n\n\u2022 \u6bcf\u67086\u65e5\u5047\uff0c8\u65e5\u5927\u5047\u300113\u5929\u6cd5\u5b9a\u5047\n\n\u2022 \u91ab\u7642\u6d25\u8cbc \u3001\u5de5\u4f5c\u8d85\u6642\u88dc\u9418\u3001\u54e1\u5de5\u512a\u60e0\u53ca\u514d\u8cbb\u7642\u7a0b\n\n\u5de5\u4f5c\u5167\u5bb9\uff1a\n\u2022 \u524d\u53f0\u63a5\u5f85\u9867\u5ba2\n(\u767b\u8a18\u3001\u63a5\u807d\u96fb\u8a71\u3001\u843dbooking & Confirm booking..)\n\u2022 \u5354\u52a9\u524d\u53f0\u53ca\u5e97\u92ea\u65e5\u5e38\u71df\u904b\n(eg: \u73fe\u91d1\u53ca\u4fe1\u7528\u5361\u4ea4\u6613\u5de5\u4f5c\u3001\u6253\u55ae\u53ca\u57cb\u6578\u7b49)\n\u2022 \u8655\u7406\u4e00\u822c\u6587\u66f8\u4e8b\u52d9\u53ca\u6e96\u5099\n(\u6587\u4ef6Update/Filling/\u65e5\u5e38Reports)\n\n**\u5982\u6709\u76f8\u95dc\u524d\u53f0\u5de5\u4f5c\u7d93\u9a57\u6216\u61c2\u904b\u7528B2B\u8005\u5c07\u512a\u5148\u8003\u616e**\n\n\u7533\u8acb\u689d\u4ef6\uff1a\n\u2022 \u4e2d\u4e94\u7a0b\u5ea6, \u61c2\u57fa\u672c\u4e2d\u82f1\u6587\u8f38\u5165\u6cd5\u53ca\u96fb\u8166\u77e5\u8b58\n\n\u2022 \u8655\u4e8b\u6709\u689d\u7406\u3001\u5b88\u6642\u3001\u52e4\u596e\u53ca\u5177\u8cac\u4efb\u611f\n\n\u2022 \u8010\u5fc3,\u6709\u79ae\u3001\u7a4d\u6975\u4e3b\u52d5\u5b78\u7fd2\n\n\u2022 \u6d41\u5229\u5ee3\u6771\u8a71\u3001\u4e00\u822c\u82f1\u8a9e& \u666e\u901a\u8a71\u53ca\u826f\u597d\u6e9d\u901a\u6280\u5de7\n\u6709\u610f\u8005\u53ef\u5c07\u500b\u4eba\u5c65\u6b77\u53ca\u85aa\u91d1\u8981\u6c42\u96fb\u90f5\u81f3\u672c\u516c\u53f8 ( Apply Now )\n\u6216 WhatsApp 97216648 \u62db\u8058\u5c08\u7dda \u67e5\u8a62\u53ca\u9810\u7d04\n(\u7533\u8acb\u4eba\u63d0\u4f9b\u4e4b\u5168\u90e8\u8cc7\u6599\u7d55\u5c0d\u4fdd\u5bc6\u53ca\u53ea\u4f5c\u62db\u8058\u7528\u9014)\n\u6bcf\u6708\u52e4\u5de5, \u5de5\u4f5c\u5408\u4f5c\u734e\u91d1 \u3001\u7121\u9700\u8f2a\u66f4, \u6bcf\u67086\u65e5\u5047 \u3001\u751f\u65e5\u734e\u8cde\u3001 \u6709\u85aa\u5e74\u50478\u5929 \u300112\u5929\u6cd5\u5b9a\u5047\u3001\u5a5a\n\u4eba\u4e8b\u90e8\u96fb\u90f5 Apply Now\nWhatsApp 97216648 \u62db\u8058\u5c08\u7dda\n\n", "employment_types": ["Full Time"], "selling_points": [], "locations": ["Not Specified"], "categories": ["Admin & HR", "Clerical / Admin Staff", "Receptionist", "Others"], "post_time": "2022-01-12T04:15:01Z", "salary": {"currency": null, "max": null, "min": null, "period": "monthly", "term": null}, "salary_visible": false, "title_keywords": ["receptionist", "\u7f8e\u5bb9\u9662\u63a5\u5f85\u54e1"], "responsibilities": ["booking"], "requirements": {"degrees": [], "majors": [], "languages": [], "language_level": [], "hard_skills": ["whatsapp"], "soft_skills": [], "languages_combined": []}, "experience_required": {"duration": [], "field": []}}, {"job_id": "100003009045540", "location_code": "hk", "company": "Link Business Centre Limited", "job_title": "\u9ad8\u7d1a\u63a5\u5f85\u54e1", "description": "\n\u8077\u8cac :\u63a5\u5f85\u53ca\u6587\u66f8\u5de5\u4f5c\uff0c\u8655\u7406\u90f5\u4ef6\u3001\u5feb\u905e\u53ca\u50b3\u771f\n\n\u8cc7\u6b77 :\u4e2d\u4e94\u7a0b\u5ea6; 1\u5e74\u7d93\u9a57; \u826f\u597d\u7cb5\u8a9e; \u826f\u597d\u666e\u901a\u8a71; \u826f\u597d\u82f1\u8a9e; \u61c2\u8b80\u5beb\u4e2d\u6587; \u61c2\u8b80\u5beb\u82f1\u6587; \u61c2Microsoft Office; \u61c2\u82f1\u6587\u6253\u5b57; \u61c2\u4e2d\u82f1\u6587\u96fb\u8166\u64cd\u4f5c; \u61c2\u4e2d\u6587\u6253\u5b57; \u826f\u597d\u96fb\u8a71\u6e9d\u901a\u53ca\u8868\u9054\u6280\u5de7, \u5de5\u4f5c\u6709\u689d\u7406, \u5b88\u6642, \u6709\u8cac\u4efb\u611f, \u6709\u79ae\u8c8c\n\n\u5f85\u9047 :\u6bcf\u6708$12,000 - $14,000, \u6709\u9280\u884c\u5047\u671f \u53ca\u91ab\u7642\u798f\u5229, \u661f\u671f\u4e00\u81f3\u4e94: \u4e0a\u53489\u6642\u81f3\u4e0b\u53486\u6642\u53ca\u661f\u671f\u516d: \u4e0a\u53489\u6642\u81f3\u4e0b\u53481\u6642, \u6bcf\u9031\u5de5\u4f5c5\u5929\u81f35\u5929\u534a\n\n\u7533\u8acb\u9808\u77e5 :\u6c42\u8077\u8005\u53ef\u96fb\u90f5(Apply Now)\u5c65\u6b77\u8868\u7d66\u9818\u9054\u5546\u52d9\u4e2d\u5fc3\u6709\u9650\u516c\u53f8\u3002\u5982\u8981\u7d22\u53d6\u6536\u96c6\u500b\u4eba\u8cc7\u6599\u8072\u660e, \u8acb\u8207\u5468\u5c0f\u59d0(Email)\u806f\u7d61\u3002\n\n", "employment_types": ["Full Time"], "selling_points": [], "locations": ["Tsim Sha Tsui"], "categories": ["Admin & HR", "Clerical / Admin Staff", "Receptionist", "Others"], "post_time": "2022-01-13T08:03:24Z", "salary": {"currency": null, "max": null, "min": null, "period": "monthly", "term": null}, "salary_visible": false, "title_keywords": [], "responsibilities": [], "requirements": {"degrees": [], "majors": [], "languages": [], "language_level": [], "hard_skills": [], "soft_skills": [], "languages_combined": []}, "experience_required": {"duration": [], "field": []}}, {"job_id": "100003009048399", "location_code": "hk", "company": "The Peninsula Hotel Limited", "job_title": "Concierge Agent", "description": "We are looking for talented applicants with enthusiasm, passion, positive service attitude and outstanding interpersonal and communications skills to fill this exciting position.\n\n\n\n17 paid statutory holidays\nExceptional market leading benefits such as comprehensive family medical insurance (including dependents),\nOption of MPF or ORSO retirement scheme\n\nJob Responsibilities:\n\nGreets consistently and professionally to our guests to provide a warm welcoming experience\nProvides guests with information on facilities, services, events and attractions, tours, travel routes and transportation schedules\nProvides restaurant information, gives recommendations and makes restaurant bookings per guests\u2019 preference\nKeeps updating on sightseeing attractions, dining venues and shopping suggestions within the city but not limited to it\nArranges flight tickets, flight reconfirmation, on-line check in and flight schedule updates for our guests\nArranges transportation according to guest needs including hotel limousine and other fleet from contract-out agent\nHandles all incoming couriers and mails on behalf of our guests in a prompt and efficient manner\nAssists in providing mailing services to our guests including postcards/ letters, speedpost/ air / surface mail through Hong Kong Post, FedEx and DHL\nRequirements:\n\nDiploma or degree holder in Hotel Management\nTwo years of related experience in the hotel industry is preferred\nExcellent verbal and written English, Cantonese and Mandarin\nPassionate towards hospitality and concierge business\nFresh graduates are also welcome to apply\nWhat\u2019s in it for you?\n\n\nIn return to your hard-work, dedication and professionalism, we offer:\n\nAn attractive remuneration with discretionary bonus\nAnnual leave and statutory leave\n5 days of work a week\nOption of MPF or ORSO scheme\nLife and Medical insurance\nOpportunity for internal transfer\nWide range of training and development programmes\nPlease send your full resume with present and expected salary to\n\nHuman Resources Department\u00a0\nThe Peninsula Hong Kong\nSalisbury Road, Kowloon, Hong Kong\nTel: 2696 6800\u00a0 WhatsApp & WeChat: 9023 9509\n\nPersonal data collected will be used for recruitment purposes only and may be retained for up to 2 years as per our Job Candidacy Privacy Notice listed on our company website\u00a0.\n", "employment_types": ["Full Time", "Permanent"], "selling_points": ["17 paid statutory holidays", "Exceptional market leading benefits", "Option of MPF or ORSO retirement scheme"], "locations": ["Not Specified"], "categories": ["Admin & HR", "Receptionist", "Hospitality / F & B", "Hospitality / Hotel Services", "Others"], "post_time": "2022-01-14T06:28:09Z", "salary": {"currency": null, "max": null, "min": null, "period": "monthly", "term": null}, "salary_visible": false, "title_keywords": [], "responsibilities": [], "requirements": {"degrees": [], "majors": [], "languages": [], "language_level": [], "hard_skills": [], "soft_skills": [], "languages_combined": []}, "experience_required": {"duration": [], "field": []}}, {"job_id": "100003009045474", "location_code": "hk", "company": "Hang Seng Bank Ltd", "job_title": "Assistant Services Support Manager", "description": "Private Banking and Trust Services \u2013 Private Banking Department\n\nWe are seeking a high caliber to join our department as\u00a0Assistant Services Support Manager\n\nPrincipal responsibilities\n\nGreet, welcome and direct visitors\nProvide administrative and client servicing support to Private Banking customers and relationship managers\nAdhere to relevant operational guidelines and procedures so as to ensure smooth operation and deliver excellent customer service to Private Banking customers and prospects\nAssist in formulation of service enhancement/ streaming initiatives to enhance customer experience and satisfaction\nRequirements\nTertiary education OR other relevant qualifications\nMinimum 3 years\u2019 relevant experience, preferably with exposure to client servicing\nStrong self-motivation, attentiveness to details and ability to work independently and under pressure\nAbility to communicate effectively, embrace change and overcome challenges\nStrong desire to learn and able to work in Agile environment\nProficiency in English, Chinese and Putonghua\nGreat sense of ownership and servicing mindset with good communication skill\n\n\u00a0\nIf you would like to explore other opportunities at Hang Seng Hong Kong, please visit\u00a0www.hangseng.com/careers/\u00a0for details.\n\nThe health and safety of our employees and candidates is very important to us. Due to the current situation related to the Novel Coronavirus (2019-nCoV), we\u2019re leveraging our digital capabilities to ensure we can continue to recruit top talent at the HSBC Group. \u00a0As your application progresses, you may be asked to use one of our digital tools to help you through your recruitment journey. \u00a0If so, one of our \u00a0Resourcing colleagues will explain how our video-interviewing technology will be used throughout the recruitment process and will be on hand to answer any questions you might have.\n\nAll information provided by applicants will be used only for recruitment purposes and will be used strictly in accordance with the Bank's personal data policies, a copy of which may be obtained by the applicant upon request. Unless otherwise instructed in writing by the applicant concerned, applicants may be considered for other suitable positions within the Bank and its related companies. The personal data of unsuccessful job applicants may be retained for a maximum of two years from the date when the job application is rejected and such data may be retained for a longer period if there is a subsisting reason that obliges the Bank to do so, after which the personal data will be destroyed.", "employment_types": ["Full Time", "Permanent"], "selling_points": [], "locations": ["Not Specified"], "categories": ["Admin & HR", "Receptionist", "Banking / Finance", "Private Banking", "Financial Services"], "post_time": "2022-01-14T02:10:46Z", "salary": {"currency": null, "max": null, "min": null, "period": "monthly", "term": null}, "salary_visible": false, "title_keywords": ["manager", "assistant"], "responsibilities": ["guidelines", "customer service", "procedures", "banking"], "requirements": {"degrees": [], "majors": [], "languages": ["putonghua", "english", "chinese"], "language_level": ["proficiency"], "hard_skills": ["agile", "reason"], "soft_skills": ["work independently", "under pressure", "agile", "communication skill", "self-motivation", "novel"], "languages_combined": [{"language": "putonghua", "language_level": ["proficiency"]}, {"language": "english", "language_level": ["proficiency"]}, {"language": "chinese", "language_level": ["proficiency"]}]}, "experience_required": {"duration": ["minimum 3 years"], "field": ["relevant experience"]}}, {"job_id": "100003009042322", "location_code": "hk", "company": "Marvelconnect Technology Limited", "job_title": "Administrative Assistant", "description": "Responsibilities:\n\n- Act as a Receptionist, greet visitors and guests and handle telephone enquiries.\n\n- Provide general office administrative support including procurement of stationery and office supplies, courier arrangement, etc.\n\n- Perform conference room booking\n\n- Assist in drafting business / sales agreements and quotation\n\n- Perform in other and hoc tasks as assigned\n\nRequirements:\n\n- Higher Diploma or above in HR or Business Administration\n\n- 1-2 years working experience\n\n- Good communication, writing and presentation skills\n\n- Good in spoken and written Cantonese and English\n\n- High responsibility, proactive and independent\n\n- Immediate available is highly preferred", "employment_types": ["Full Time"], "selling_points": ["5 days work", "Year end bonus", "Medical Insurance"], "locations": ["Kowloon Bay"], "categories": ["Admin & HR", "Clerical / Admin Staff", "Receptionist", "Secretary"], "post_time": "2022-01-12T07:01:22Z", "salary": {"currency": null, "max": null, "min": null, "period": "monthly", "term": null}, "salary_visible": false, "title_keywords": ["administrative assistant"], "responsibilities": ["administrative support", "office supplies", "quotation", "stationery", "booking"], "requirements": {"degrees": ["higher diploma or above"], "majors": ["business administration"], "languages": ["cantonese", "english"], "language_level": ["good"], "hard_skills": [], "soft_skills": ["communication", "presentation skills", "proactive", "independent"], "languages_combined": [{"language": "cantonese", "language_level": ["good"]}, {"language": "english", "language_level": ["good"]}]}, "experience_required": {"duration": ["1-2 years"], "field": []}}, {"job_id": "100003009040555", "location_code": "hk", "company": "Chinese Pharmaceuticals (HK) Co., Limited", "job_title": "Receptionist \u63a5\u5f85\u54e1", "description": "\n\u5de5\u4f5c\u7bc4\u570d:\n\u2022 \u8ca0\u8cac\u5728\u5e97\u92ea\u63a5\u5f85\u9867\u5ba2\n\u2022 \u63a5\u807d\u96fb\u8a71\u53ca\u5b89\u6392\u5ba2\u4eba\u9810\u7d04\u7642\u7a0b\u6642\u9593\n\u2022 \u8655\u7406\u4e00\u822c\u6587\u66f8\u5de5\u4f5c\u53ca\u5354\u52a9\u65e5\u5e38\u5e97\u8216\u904b\u4f5c\n\u8981\u6c42:\n\u2022 \u4e2d\u4e94\u6216\u4ee5\u4e0a\u7a0b\u5ea6\n\u2022 1\u5e74\u6216\u4ee5\u4e0a\u76f8\u95dc\u5de5\u4f5c\u7d93\u9a57\n\u2022 \u6d41\u5229\u5ee3\u6771\u8a71,\u7565\u61c2\u82f1\u8a9e\n\u2022 \u57fa\u672c\u96fb\u8166\u64cd\u4f5c\u53ca\u61c2\u4e2d\u82f1\u6587\u6253\u5b57\n\u2022 \u7d30\u5fc3\u3001\u6709\u8cac\u4efb\u5fc3\u3001\u5de5\u4f5c\u4fdd\u6301\u7b11\u5bb9\n\u2022 \u5177\u7f8e\u5bb9\u4e2d\u5fc3\u6216\u8a3a\u6240\u524d\u53f0\u63a5\u5f85\u7d93\u9a57\u66f4\u4f73\n\u2022 \u53ef\u5373\u6642\u4e0a\u73ed\u8005\u512a\u5148\n\u5de5\u4f5c\u985e\u578b: \u5168\u8077\n\u85aa\u916c: \u6bcf\u6708 $12,000.00 \u8d77\n\u6642\u9593:\n\u2022 \u65e5\u73ed\n\n", "employment_types": ["Full Time"], "selling_points": [], "locations": ["Not Specified"], "categories": ["Admin & HR", "Clerical / Admin Staff", "Receptionist", "Others"], "post_time": "2022-01-12T02:46:35Z", "salary": {"currency": null, "max": null, "min": null, "period": "monthly", "term": null}, "salary_visible": false, "title_keywords": ["receptionist"], "responsibilities": [], "requirements": {"degrees": [], "majors": [], "languages": [], "language_level": [], "hard_skills": [], "soft_skills": [], "languages_combined": []}, "experience_required": {"duration": [], "field": []}}, {"job_id": "100003009043635", "location_code": "hk", "company": "ASC Fine Wines (Hong Kong) Trading Corp Ltd", "job_title": "HR & Admin Assistant", "description": "This position is designated to assist overall HR & Admin department daily operations in coping with business needs and managing the transaction challenges effectively.\n\nResponsibilities\n\nReport to the HR & Admin Manager\nPerform all-round HR and administrative functions\nPerform receptionist duties, handling phone calls, greeting visitors, managing incoming and outgoing courier/mail\nHandle daily administrative duties, i.e. regular housekeeping, replenishment of office supplies, communicate with vendors, coordinate with IT and handle repair and maintenance issues\nPerform full cycle of employee on-boarding process and off-boarding process, maintaining physical and digital personnel records\nCoordinate and organize company event and staff activities\nAssist in ad hoc duties as required\n\nRequirements:\n\nHigher Diploma holder or above in Human Resources or related discipline\n1-2 years' relevant working experience.\u00a0 Candidate with accounting background would be an advantage\nGood telephone manner with pleasant personality\nGood interpersonal and communication skills\nStrong sense of confidentiality, responsibility and commitment\nProficient in MS Word and Excel, good at MS excel functions and tools\nGood command of written and spoken English, Chinese and Mandarin\nCandidates with more experience will be considered as HR Administrator\nWe offer attractive remuneration package, benefits packages as well as excellent opportunities for career advancement and development. Please send your application letter with FULL RESUME with PRESENT and EXPECTED SALARY\u00a0by clicking the\u00a0Apply Now\u00a0button.\u00a0\n\nFor more information about us, please visit our website at\u00a0www.asc-wines.com.\n\nData collected will only be used for job application processing.\u00a0 Applicants not being invited for interview within\u00a08 weeks from the submission date may assume their applications unsuccessful.\u00a0 All related information will be kept up to 24 months and all personal data will be destroyed afterwards.\n\n", "employment_types": ["Full Time", "Permanent"], "selling_points": ["1 years' exp. in HR & Admin", "good telephone manner with pleasant personality", "all round HR & Admin functions"], "locations": ["Hung Hom"], "categories": ["Admin & HR", "Clerical / Admin Staff", "Receptionist", "Hospitality / F & B", "Food & Beverage"], "post_time": "2022-01-13T01:09:43Z", "salary": {"currency": null, "max": null, "min": null, "period": "monthly", "term": null}, "salary_visible": false, "title_keywords": ["hr & admin assistant"], "responsibilities": ["communicate with", "ad hoc duties", "maintenance", "maintaining", "housekeeping", "office supplies", "hr", "personnel records", "coordinate with", "replenishment", "coordinate", "repair", "administrative duties", "report", "phone calls", "greeting visitors"], "requirements": {"degrees": ["higher diploma holder"], "majors": [], "languages": ["english", "chinese", "mandarin"], "language_level": ["good command"], "hard_skills": ["excel", "ms excel", "ms word"], "soft_skills": ["communication skills", "telephone manner", "interpersonal", "pleasant"], "languages_combined": [{"language": "english", "language_level": ["good command"]}, {"language": "chinese", "language_level": ["good command"]}, {"language": "mandarin", "language_level": ["good command"]}]}, "experience_required": {"duration": ["1-2 years"], "field": ["hr", "relevant working experience"]}}, {"job_id": "100003009043394", "location_code": "hk", "company": "Medtimes Medical Group Limited", "job_title": "Clinic Receptionist \u8a3a\u6240\u63a5\u5f85\u54e1", "description": "\u4e3b\u8981\u8077\u8cac:\n\n\u8ca0\u8cac\u767b\u8a18\u53ca\u9810\u7d04\uff0c\u63a5\u807d\u96fb\u8a71\u53ca\u6536\u9280\n\u884c\u653f\u548c\u5de5\u4f5c\u6587\u66f8\u652f\u63f4\n\u63a5\u5f85\u5ba2\u4eba\n\u5de5\u4f5c\u5730\u9ede\uff1a\u5c16\u6c99\u5480\n\n\u00a0\u8077\u4f4d\u8981\u6c42:\n\n\u4e2d\u4e94\u7a0b\u5ea6\u53ca\u5177\u6709\u81f3\u5c11\u4e00\u5e74\u76f8\u95dc\u5de5\u4f5c\u7d93\u9a57\n\u5177\u5ba2\u6236\u670d\u52d9\u7d93\u9a57\u53ca\u524d\u53f0\u63a5\u5f85\u6280\u5de7\u512a\u5148\n\u53cb\u5584\u614b\u5ea6\u3001\u6613\u65bc\u6e9d\u901a\n\u826f\u597d\u7cb5\u8a9e\u3001\u4e00\u822c\u82f1\u8a9e\u53ca\u666e\u901a\u8a71\n\n\u61c2\u4e2d\u82f1\u8f38\u5165\u6cd5\n\n\u6bcf\u9031\u5de5\u4f5c44\u5c0f\u6642\n\n\u6bcf\u6708\u81b3\u98df\u4ea4\u901a\u798f\u5229\u300111\u5929\u6709\u85aa\u5e74\u5047\u3001\u751f\u65e5\u5047\u3001\u91ab\u7642\u798f\u5229\u3001\u514d\u8cbb\u75ab\u82d7\u6ce8\u5c04\u3001\u6bcf\u5e74\u514d\u8cbb\u8eab\u9ad4\u6aa2\u67e5\u3001\u5916\u9593\u57f9\u8a13\u8cc7\u52a9\u8a08\u5283\u3001\u5728\u8077\u57f9\u8a13\u3001\u6649\u5347\u6a5f\u6703\n\n\u6709\u95dc\u8a73\u60c5\uff0c\u8acb\u700f\u89bd\u6211\u5011\u7684\u7db2\u7ad9\uff1awww.medtimes.com.hk\n\n\u6709\u610f\u8005\u8acb\u5c07\u500b\u4eba\u5c65\u6b77\u53ca\u8981\u6c42\u5f85\u9047\u96fb\u90f5\u81f3APPLY NOW\u00a0\n\n\u6c42\u8077\u8005\u63d0\u4f9b\u7684\u500b\u4eba\u8cc7\u6599\u5c07\u56b4\u683c\u6309\u7167\u50f1\u4e3b\u7684\u500b\u4eba\u8cc7\u6599\u653f\u7b56\u4f7f\u7528\uff0c\u50c5\u4f9b\u62db\u8058\u7528\u9014\u3002", "employment_types": ["Full Time", "Permanent"], "selling_points": ["\u6bcf\u6708\u81b3\u98df\u4ea4\u901a\u798f\u5229\u3001\u91ab\u7642\u798f\u5229\u300111\u5929\u6709\u85aa\u5e74\u5047", "\u8ca0\u8cac\u767b\u8a18\u53ca\u9810\u7d04\uff0c\u63a5\u807d\u96fb\u8a71\u53ca\u6536\u9280", "\u53cb\u5584\u614b\u5ea6\u3001\u6613\u65bc\u6e9d\u901a"], "locations": ["Not Specified"], "categories": ["Admin & HR", "Receptionist", "Beauty Care / Health", "Others", "Medical Services", "Others"], "post_time": "2022-01-12T11:26:50Z", "salary": {"currency": null, "max": null, "min": null, "period": "monthly", "term": null}, "salary_visible": false, "title_keywords": ["receptionist"], "responsibilities": [], "requirements": {"degrees": [], "majors": [], "languages": [], "language_level": [], "hard_skills": [], "soft_skills": [], "languages_combined": []}, "experience_required": {"duration": [], "field": []}}]