[{"job_id": "100003009053497", "location_code": "hk", "company": "Automated Systems (HK) Ltd", "job_title": "Recruiter", "description": "We are looking for a young and ambitious talent to join our in-house recruitment team. You will work closely with the HR team and Hiring Managers in delivering excellent services.\n\n\nJob Responsibilities:\n\n\nDevelop and implement creative recruitment strategies including job advertisements, conducting proactive search.\nWork with hiring managers to develop strategies for talent search.\nPerform end-to-end recruitment process from sourcing to offer negotiation.\nSource candidates from different channels.\nExplore new and effective sourcing channels.\nEnhance and maintain relationship with candidates and internal client.\nEstablish and maintain a database of candidates.\nDeal with the related procedure of talent engagement.\n\nJob Requirements:\n\n\nDegree in in Business Administration, Human Resources or any related field.\nMinimum 1 years\u2019 experience in recruitment agencies or in IT companies.\nIT related recruiting experience will be preferred.\nProficient in English and Chinese is a MUST.\nStrong communication skills to collaborate with team members.\nSelf-driven and result-oriented personality.\nProactive, strong sense of responsibility, detail-oriented.\nAble to be multi-tasking in a tight schedule.\nImmediately available or short notice period is preferred\n\n\nWe offer 5-day week, public holidays, medical benefits, excellent career opportunities, considerable remuneration to the right candidates.\n\u201cIf you have the desire for an exciting and rewarding career, please send us your resume, stating your notice period, present and expected salary to Human Resources Department by clicking \"Apply Now\".\nTo learn us more, please visit our website:\u00a0www.asl.com.hk\nWe are an equal opportunity employer. All applications will be treated in strict confidence. We regret that only shortlisted candidates will be notified. All personal data will be destroyed within six months after the selection process.", "employment_types": ["Full Time"], "selling_points": ["Degree in in Business Administration", "1 years\u2019 experience in recruitment", "Attractive Commission Scheme"], "locations": ["Shatin Area"], "categories": ["Admin & HR", "Others", "HR Supporting Staff", "Recruitment / Executive Search"], "post_time": "2022-01-17T07:03:26Z", "salary": {"currency": null, "max": null, "min": null, "period": "monthly", "term": null}, "salary_visible": false, "title_keywords": [], "responsibilities": ["develop strategies", "advertisements", "develop", "maintain", "recruitment", "database", "recruitment process"], "requirements": {"degrees": ["degree"], "majors": ["business administration"], "languages": ["english", "chinese"], "language_level": ["proficient"], "hard_skills": [], "soft_skills": ["communication skills", "sense of responsibility", "driven", "detail-oriented", "multi-tasking", "proactive", "result-oriented"], "languages_combined": [{"language": "english", "language_level": ["proficient"]}, {"language": "chinese", "language_level": ["proficient"]}]}, "experience_required": {"duration": ["minimum 1 years"], "field": ["related", "it", "recruitment"]}}, {"job_id": "100003009054565", "location_code": "hk", "company": "Compass Group Hong Kong Ltd", "job_title": "Senior/ Human Resources Officer - Recruitment", "description": "Responsibilities\n\nWork with a team to support full recruitment cycle and provide one-stop recruitment services\nExplore different recruitment channels and monitor the effectiveness\nLiaise with external parties for recruitment activities and participate in recruitment events\nPrepare HR reports and analysis for management review\nFormulate, implement and standardize HR manuals, policies and procedures\nHandle ad-hoc projects as assigned\n\nRequirements\n\nDegree or above in Human Resources\u00a0Management or related\u00a0disciplines\u00a0\nMinimum 3 years of relevant work experience. Experience in\u00a0Retail,\u00a0F&B or Hospitality industry is definitely an advantage\nIndependent &\u00a0well-organized\u00a0with good communication skills\nExcellent command of spoken and written English and Chinese\n\nImmediately available is preferable\n\nInterested\u00a0candidates,\u00a0please send e-mail with full details of academic qualifications, work experience, date of available, present and expected salary by clicking \"APPLY NOW\" button.\n\nWe offer an attractive remuneration package and excellent career prospects to the right candidate.\n\nWe are an equal opportunity employer and welcome applications from all qualified candidates.\nPersonal data collected would be used for recruitment purposes only.", "employment_types": ["Full Time", "Permanent"], "selling_points": ["F&B Industry", "Degree or above in HRM or related disciplines", "Human Resources"], "locations": ["Mong Kok"], "categories": ["Admin & HR", "Clerical / Admin Staff", "Recruitment / Executive Search"], "post_time": "2022-01-17T10:01:15Z", "salary": {"currency": null, "max": null, "min": null, "period": "monthly", "term": null}, "salary_visible": false, "title_keywords": ["human resources officer"], "responsibilities": ["policies", "analysis", "external parties", "monitor", "hr reports", "hr", "procedures", "recruitment", "liaise with", "ad-hoc projects", "management review"], "requirements": {"degrees": ["degree or above"], "majors": ["related disciplines"], "languages": ["english", "chinese"], "language_level": ["excellent"], "hard_skills": [], "soft_skills": ["communication skills", "independent", "well-organized"], "languages_combined": [{"language": "english", "language_level": ["excellent"]}, {"language": "chinese", "language_level": ["excellent"]}]}, "experience_required": {"duration": ["minimum 3 years"], "field": ["hospitality industry", "f&b", "retail"]}}, {"job_id": "100003009052274", "location_code": "hk", "company": "Lubuds F&B Group", "job_title": "Talent Acquisition Specialist", "description": "Responsibilities:\nDesign and implement overall recruiting strategy.\nDevelop and update job descriptions and job specifications.\nPreparing and post jobs to appropriate recruitment channels.\nSource and attract candidates by using databases and social media.\nScreen candidates resumes and job applications.\nConduct interviews, assess applicants\u2019 relevant knowledge, skills, soft skills, experience and aptitudes.\nMonitor and apply HR recruiting best practices.\nDevelop and maintain a candidate data base to facilitate the recruitment process\u00a0\u00a0\nAct as a point of contact and build influential candidate relationships during the selection process.\nPromote company\u2019s reputation as \u201cbest place to work\u201d.\nRequirements:\nDegree in Human Resources Management or relevant disciplines\n3 years of relevant experience in recruitment, preferably in F&B industry\nWith HR experience in F&B industry is an advantage\nWell-versed in Hong Kong Employment Ordinance, MPF regulations and other related\u00a0legislation\nGood command of spoken and written in English and Chinese\nProficiency in\u00a0Excel and Chinese\u00a0word processing\nImmediate Available\n\n\n\nWe offer attractive remuneration package and excellent career opportunities to the right candidate. Interested parties, please click on below button \u201cApply Now\u201d.\n\nInformation collected will be treated in strict confidence and used for recruitment purposes only. Only suitable candidates will be notified.", "employment_types": ["Full Time", "Permanent"], "selling_points": [], "locations": ["Aberdeen"], "categories": ["Admin & HR", "Others", "HR Supporting Staff", "Recruitment / Executive Search"], "post_time": "2022-01-17T02:37:34Z", "salary": {"currency": null, "max": null, "min": null, "period": "monthly", "term": null}, "salary_visible": false, "title_keywords": ["specialist"], "responsibilities": ["social media", "data", "hr", "monitor", "design", "develop", "specifications", "recruitment", "maintain", "databases", "contact", "recruitment process"], "requirements": {"degrees": ["degree"], "majors": [], "languages": ["english", "chinese"], "language_level": ["proficiency", "good command"], "hard_skills": ["excel", "chinese word processing", "hong kong employment ordinance", "mpf regulations"], "soft_skills": [], "languages_combined": [{"language": "english", "language_level": ["good command"]}, {"language": "chinese", "language_level": ["proficiency", "good command"]}]}, "experience_required": {"duration": ["3 years"], "field": ["recruitment", "f&b", "relevant experience", "hr"]}}, {"job_id": "100003009054250", "location_code": "hk", "company": "CHOW TAI FOOK JEWELLERY CO LTD", "job_title": "Assistant Officer, Recruitment", "description": "What You Own\nResponsible for the whole recruitment process including job advertisement posting, sourcing, screening, arranging & conducting interview, preparing hiring proposal and making offer\nFormulate and implement recruitment strategies & initiatives to attract talents\nWork proactively to develop close working relationships with both frontline / different departments to identify the manpower needs & requirements\nExplore potential and evaluate the effectiveness of advertising, social media, job fair, recruitment day and recruitment channels, etc.\nPrepare statistics, reports and presentation materials\nPerform other ad-hoc projects and tasks as assigned\nWho Will Thrive\nDegree holder in Human Resources Management, Psychology or any other disciplines are also welcome\nMinimum 3 years' experience in HR field with emphasis on recruitment, preferably in retail business\nFamiliar with HK Employment Ordinance, related regulations & HR practice\nIndependent, detail-minded, self-motivated, able to work in a fast-paced environment and a good team player\nMature with positive mind-set as well as strong interpersonal, communication & analytical skills\nWell-versed in using MS Office including Word, Excel and PowerPoint\nGood command of written and spoken English, Cantonese & Mandarin\nCandidate with more experience will be considered as Officer\nBenefits\n5-day work\nCompetitive salary, staff meal,\u00a0medical and dental insurance, life insurance\nVarious types of leave, e.g. Family-friendly leave, self-development leave,\u00a0Examination leave, marriage leave, birthday\u00a0leave, volunteer service leave, etc\nWe offer excellent career opportunities, attractive remuneration package & benefits to the right candidate.\u00a0Interested parties please apply by clicking \"Apply Now\" with a full resume stating the latest and expected salary.\nAll information collected will be used for recruitment purposes only", "employment_types": ["Full Time"], "selling_points": ["Talent Acquisition", "Identify and response to the hiring needs", "5-day work"], "locations": ["Mong Kok"], "categories": ["Admin & HR", "HR Supporting Staff", "Recruitment / Executive Search"], "post_time": "2022-01-17T08:57:32Z", "salary": {"currency": null, "max": null, "min": null, "period": "monthly", "term": null}, "salary_visible": false, "title_keywords": ["assistant officer"], "responsibilities": ["regulations", "social media", "management", "advertising", "job advertisement", "hr", "develop", "evaluate", "communication", "recruitment", "reports", "working relationships", "recruitment process", "ad-hoc projects"], "requirements": {"degrees": ["degree holder"], "majors": ["psychology"], "languages": ["cantonese", "english", "mandarin"], "language_level": ["good command"], "hard_skills": ["excel", "word", "powerpoint", "analytical skills", "ms office"], "soft_skills": ["detail-minded", "self-motivated", "good team player", "independent", "responsible", "fast-paced environment", "mature", "analytical skills", "communication", "interpersonal", "presentation", "positive"], "languages_combined": [{"language": "cantonese", "language_level": ["good command"]}, {"language": "english", "language_level": ["good command"]}, {"language": "mandarin", "language_level": ["good command"]}]}, "experience_required": {"duration": ["minimum 3 years"], "field": ["business", "hr", "retail", "recruitment"]}}, {"job_id": "100003009054577", "location_code": "hk", "company": "IKEA", "job_title": "Resourcing Leader, North Asia", "description": "WHY YOU WILL LOVE US\n\nWe\u2019re a diverse group of down-to-earth, straightforward people with a passion for home furnishing. We come from all over the world, but we share an inspiring vision: \u201cto create a better everyday life for the many people\u201d. How we realize this vision is based on our shared humanistic values. These values guide our work and build our inclusive, open and honest culture. It\u2019s all based on a spirit of togetherness and enthusiasm. We work hard, but we have fun doing it. We\u2019re always looking for people who share our positive attitude and values.\n\nWHY WE WILL LOVE YOU\n\nYou have minimum 5 years recruitment and HR related working experience\nYou have the competence and experience of leading recruitment processes in a retail / service industry\nYou have experience in building and sustaining talent sourcing strategies\nYou are familiar with labour laws and market practices in recruitment\nYou have proven ability to communicate with, coach and influence key stakeholders, with confidence and credibility\nYou have proven ability to implement strategic plans as well as extracting it into tactics and action plans\nAbility to gather and analyse facts and statistics and to develop comprehensible reports, materials, conclusions and facts for decisions\nYou are experience in maintaining expert specialist knowledge by keeping up to date with published materials, competitor practice, external market developments and trends and legislative and regulatory developments\nYou are attentive to details and highly organized\nYou are experience of working in a fast-paced environment\nYou are a good observer and listener\nYou are a proven problem solver\nYou are proficient in both written and oral English\n\nWHAT YOU WILL BE DOING DAY TO DAY\n\nSupport the implementation of the IKEA Talent approach in the organization by aligning the company recruitment strategy accordingly\nSecure recruitment actions are aligned with our business direction and processes both globally and locally (e.g. Company direction, Business Plans, Market Penetrating Plan and Competence Level)\nLead the recruitment process through various channels to support our employer branding, in order to create an outstanding candidate experience from initial candidate contact to job offer -efficient, align with our values and ensure IKEA is seen as the employer of choice\nDevelop, lead and facilitate recruitment strategies, activities or specific selection process (e.g. internship program, mass recruitment event and etc.) on organizational and individual level to identify, access, select and hire suitable candidate\nLocal responsibility for on-boarding package: monitors new co-worker orientation and on-boarding programs, advises and provides expertise to unit in executing on-boarding activities\nContribute to competence development in the area of recruitment for the country, ensuring an aligned approach in IKEA e.g. Facilitating Value Based Recruitment workshop\nCoach, influence and support business partners in service office, stores and central fulfilment unit regarding the recruitment strategies, process and tools in order to ensure high quality of recruitment process\nAnalyses data, follow up performance on recruitment strategies and actions for process improvements in the resourcing function. We also partner with other teams in the North Asia IKEA organization, Dairy Farm HR Team, stores and central fulfilment unit to gather and share good examples and proven solutions\nIntegrates the Diversity, Equality and Inclusion approach and knowledge into the recruitment to secure a broad diverse work force as well as being an attractive employer\nMonitor market trends and leverage for adaptation of recruitment, attraction and sourcing strategies at country level.\n\nTOGETHER AS A TEAM\n\nAt the heart of our business are people. We create a better everyday life together by living our shared values and safeguarding our unique culture. To create an inspiring IKEA experience we need to make sure our co-workers have the preconditions to meet our customers in the best possible way.\n\nSTAFF BENEFITS\n\nAnnual Fixed Bonus, 5-Day Work Week, 17 days Public Holiday, Paid Leave (Paid Annual Leave, 14 weeks Maternity Leave, 5 days Paternity Leave, 1 week Marriage Leave), Employee Medical Coverage, Non-Contributory Retirement Plan, Staff Purchase Discount, Birthday Coupon, Referral Bonus, Excellent Career Path\n\nPersonal data collected will be kept and handled confidentially by authorized personnel for recruitment purposes only. It might also be disclosed to our subsidiaries, associates and agencies authorized to process the information for appointment. The Company will retain the applications of candidates not selected for a maximum period of 24 months after the selection process is finalized. Our Personal Information Collection Statement (PICS) is available at our career site and can be provided upon request by contacting our Human Resources Department. Applicants not heard from us within six weeks may consider their applications filed for future reference.\n\nIssued by The Dairy Farm Company, Limited\n\n\n", "employment_types": ["Full Time", "Permanent"], "selling_points": ["Lead the recruitment process", "Develop, lead & facilitate recruitment strategies", "Coach, influence and support business partners"], "locations": ["Shatin Area"], "categories": ["Admin & HR", "Others", "Recruitment / Executive Search"], "post_time": "2022-01-17T10:05:13Z", "salary": {"currency": null, "max": null, "min": null, "period": "monthly", "term": null}, "salary_visible": false, "title_keywords": [], "responsibilities": ["data", "quality", "business plans", "recruitment strategy", "plan", "plans", "maintaining", "teams", "implementation", "monitor", "develop", "reports", "workshop", "executing", "contact", "recruitment process", "communicate with", "strategic plans", "hr", "recruitment", "analyse"], "requirements": {"degrees": [], "majors": [], "languages": ["english"], "language_level": ["proficient"], "hard_skills": ["make", "fun"], "soft_skills": ["organized", "oral", "confidence", "problem solver", "attentive to details", "passion for", "fast-paced environment", "organizational", "unique", "positive attitude", "diverse", "inspiring", "honest"], "languages_combined": [{"language": "english", "language_level": ["proficient"]}]}, "experience_required": {"duration": ["minimum 5 years"], "field": ["related", "hr", "service industry", "recruitment", "retail"]}}, {"job_id": "100003009054802", "location_code": "hk", "company": "Aigniter Holdings Limited", "job_title": "(Senior/Junior) Human Resources Officer", "description": "At Jarvix (Aigniter), we are on a mission to build a next-gen internet economic infrastructure that can really embed technology into everybody\u2019s day-to-day life. We firmly believe that technology shouldn\u2019t be a luxury that can only be accessed by large corporations, but a commodity that can be enjoyed by everyone. Since 2017, we have been working hard on leveraging technology to facilitate transactions of business of all sizes, and improve end consumer\u2019s quality of life. Right now, Jarvix is providing applications and services across different sectors, from e-payment, e-logistics, to e-groceries.\u00a0\n\nWe\u2019re a small, focused, and rapidly growing team with an abundance of opportunities. If you want to make a real impact and you\u2019re up for challenges, Jarvix is the ideal place for you.\n\n\n\n\nJob Description:\n\nHuman Resources Officer will be responsible for our company\u2019s Human Resources tasks such as recruitment, people management, team building and HR administration related matters. This position will also be the main driver of shaping our company culture and cultivating talents.\n\nResponsibilities:\n\nManage the recruitment pipeline, candidate interview and selection process\nManage staff onboarding and offboarding logistics\nCoordinate company team building activities\nCompile and review HR reports and HR related legal documents to ensure compliance with local regulations\nMaintain HR systems for handling payrolls, MPF, leave records and insurance\nAny other ad hoc tasks related to HR\u00a0\n\nRequirements:\n\nBachelor\u2019s Degree in Human Resources Management or related disciplines\nAt least 3 years of HR experience\nExcellent interpersonal and communication skills with good command of written/spoken Chinese and English\nExcellent attention to detail and organisational skills\nKnowledge of any kinds of HRIS (e.g. BambooHR/Workday)\nKnowledge of HR processes and general practices\nKnowledge of Hong Kong Employment Ordinance and other HR related regulations\nProficient in computer applications\nFluent in speaking Cantonese is a MUST\nStrong problem solving skills, able to face challenges with a positive and can-do attitude\nA good team player, independent, self-disciplined, responsible, self-motivated and willing to learn\n\nCompensation package:\n\nSalary ranges from HKD17,000 to HKD27,000 per month depending on experience\nMedical benefits\n\nPerks:\n\nSharp, talented and motivated co-workers\nFun and relaxed office environment\nSense of ownership\nFree snacks and drinks", "employment_types": ["Full Time", "Permanent"], "selling_points": ["HKD17,000 to HKD27,000 per month", "Medical benefits", "Fast growing tech company"], "locations": ["Wong Tai Sin Area"], "categories": ["Admin & HR", "HR Director / Manager", "HR Supporting Staff", "Recruitment / Executive Search"], "post_time": "2022-01-17T11:09:46Z", "salary": {"currency": "HKD", "max": 29999, "min": 17000, "period": "monthly", "term": null}, "salary_visible": true, "title_keywords": ["human resources officer", "junior"], "responsibilities": ["regulations", "management", "mpf", "hr", "review", "systems", "hr reports", "ad hoc tasks", "ensure compliance", "coordinate", "maintain", "logistics", "recruitment", "insurance", "administration"], "requirements": {"degrees": ["degree", "bachelor"], "majors": ["related disciplines"], "languages": ["cantonese", "english", "chinese"], "language_level": ["excellent", "good command", "fluent"], "hard_skills": ["problem solving skills", "hong kong employment ordinance"], "soft_skills": ["communication skills", "good team player", "self-motivated", "independent", "responsible", "can-do attitude", "willing to learn", "organisational skills", "attention to detail", "problem solving skills", "interpersonal", "positive"], "languages_combined": [{"language": "cantonese", "language_level": ["fluent"]}, {"language": "english", "language_level": ["excellent", "good command"]}, {"language": "chinese", "language_level": ["excellent", "good command"]}]}, "experience_required": {"duration": ["at least 3 years"], "field": ["hr"]}}, {"job_id": "100003009051795", "location_code": "hk", "company": "CIAO International Limited (Best Mart 360\u00b0)", "job_title": "Senior Recruitment Officer", "description": "Responsibilities\n\nPlan, implement and manage the overall recruitment strategy\nSet hiring goals including timeframes and deliverables\nConducting interviews and sorting through applicants to fill open positions\nAssessing applicants' knowledge, skills, and experience to best suit open positions\nExplore potential and evaluate the effectiveness of advertising, social media, job fair, recruitment day and recruitment channels, etc.\nOrganize HR events (job fairs, career days, in-house recruitment events)\nAnalyze recruitment metrics, like time-to-hire and source of hire\nAssists HR Manager to drive People Development Programme including Management Trainee and Internship Programmes\nHandle ad hoc projects as required\n\nRequirements\n\nDegree holder in HR / business related disciplines\nWith at least 5 years of relevant HR generalist experience gained in sizable organization, FMCG experience is preferred\nGood interpersonal, communication and relationship management skills\nSelf-starter and with an ability to operate independently across a complex and matrix structure\nFamiliarity with social media recruiting\nWell versed in Excel and Chinese Word Processing\nImmediately available is highly preferred\nLess experience will be considered as\u00a0Recruitment Officer\n\nWe offer competitive package including 5-day work week, medical insurance and staff discount, etc.\u00a0 Interest parties, please send full resume with current and expected salary and date of availability by clicking \"Apply Now\".\n\n(Data collected will be used for recruitment purpose only)", "employment_types": ["Full Time"], "selling_points": ["Frontline Recruitment Focus", "Drive People Development Programme", "FMCG experience is preferred"], "locations": ["Ngau Tau Kok"], "categories": ["Admin & HR", "HR Supporting Staff", "Recruitment / Executive Search"], "post_time": "2022-01-17T01:13:11Z", "salary": {"currency": null, "max": null, "min": null, "period": "monthly", "term": null}, "salary_visible": false, "title_keywords": ["recruitment officer"], "responsibilities": ["social media", "management", "advertising", "hr", "evaluate", "recruitment strategy", "conducting interviews", "recruitment", "ad hoc projects", "plan"], "requirements": {"degrees": ["degree holder"], "majors": ["related disciplines", "business"], "languages": ["chinese"], "language_level": [], "hard_skills": ["excel", "chinese word processing"], "soft_skills": ["communication", "independently", "interpersonal"], "languages_combined": [{"language": "chinese", "language_level": []}]}, "experience_required": {"duration": ["at least 5 years"], "field": ["sizable organization", "fmcg", "recruitment", "hr generalist"]}}, {"job_id": "100003009052188", "location_code": "hk", "company": "SCOR Reinsurance Co (Asia) Ltd", "job_title": "Human Resources Information System - Talent Acquisition Internship", "description": "Job Summary\n\nWe are looking for an intern to start immediately and finish in May 2022, with minimum commitment of three working days per week. You will visit the office if work activity is required, or you will be by default working from home.\n\nYou will work with the globally teams to deliver a new recruitment system in this internship.\n\nThe role will work closely with the project team through the submission and UAT (User Acceptance Testing) phases of the Human Resources Information System \u2013 Talent Acquisition stream project. Reporting to the project owner directly, you will support the UAT coordination and run part of the UAT.\n\nIn this internship, you will learn Talent Acquisition process, HRIS system \u2013 Oracle and have the experience to work with an international team across Asia, Europe, UK and US.\n\nTo be qualified, you will need to be available for three days or more per working week. The internship period is from January 2022 to May 2022.\n\nResponsibilities\n\nLearning of Talent Acquisition operational process\n\nLearn and understand the end-to-end recruitment process in Scor\nGet familiar with the workflow to be effective in UAT period\n\nUser Acceptance Testing\n\nAssist Project Owner to organize the testing period\nPerform UAT tasks as part of the testing team\nRecord testing results and follow up on tickets with the process owner and consultants\n\nProject Coordination\n\nAttend project meetings and workshops with the global project team to better understand the project\nCommunicate with neccesary parties to facilitate project flow\n\nRequired experience & competencies\n\nExperience:\nPrior Human Resources or User Acceptance Testing internship experience is beneficial\n\nPersonal Competences:\nResponsible, logical, meticulous\nStrong interpersonal and communication skills\nGood knowledge of MS Office applications\n\nRequired Education\n\nUndergraduate in Human Resources Management or Information System degree\n\nJob Type: Internship\n\n\u6709\u610f\u7533\u8acb\u8005\u8acb \u6309 APPLY NOW\u7533\u8acb", "employment_types": ["Internship"], "selling_points": [], "locations": ["Not Specified"], "categories": ["Admin & HR", "Clerical / Admin Staff", "HR Supporting Staff", "Recruitment / Executive Search"], "post_time": "2022-01-17T02:24:13Z", "salary": {"currency": null, "max": null, "min": null, "period": "monthly", "term": null}, "salary_visible": false, "title_keywords": ["human resources", "internship"], "responsibilities": ["communicate with", "reporting", "management", "uat", "project coordination", "teams", "testing", "communication", "team across", "recruitment", "coordination", "recruitment process"], "requirements": {"degrees": ["degree"], "majors": [], "languages": [], "language_level": [], "hard_skills": ["workshops", "ms office", "information system", "oracle"], "soft_skills": ["meticulous", "communication skills", "responsible", "learning", "coordination", "interpersonal"], "languages_combined": []}, "experience_required": {"duration": [], "field": ["testing", "human resources", "team"]}}, {"job_id": "100003009054586", "location_code": "hk", "company": "David James Recruitment Limited", "job_title": "Recruitment Consultants - Experienced IT Desk \u2013 Fresh Graduates Welcome", "description": "Who are we?\nDavid James Recruitment is a leader in IT recruitment, with directors who have a long track record and great success in our field. Our goal is to be outstanding - for service, knowledge, network, and quality delivery to our candidates and clients.\u00a0 Our team combines IT recruitment experience from major global cities across APAC and Europe, coupled with excellent knowledge in the HK and Asia markets.\nAt David James we are regard ourselves as \u201cold school\u201d \u2013we are keen on training and building consultants from trainee level so that we are consistent with our methods, as well as encouraging loyalty, teamwork and promoting a positive company culture with a real sense of fun and humour.\nWith Directors that are hands on and having many years of genuine end to end recruitment experience, we will provide an in depth insight of the industry in a short time, helping you to learn and pick things up quickly. We want to encourage and support people into bigger roles and more money. There is no hire/fire mentality here - consultants are given fair chances to learn, try hard, and make it happen, with senior staff supporting you every step of the way.\nWe have a particularly strong emphasis on quality service, end to end recruitment, work hard play hard mentality, fairness, loyalty and teamwork.\nThe right candidate will be:\u00a0\n\n\nNaturally sales driven and customer driven\nFearless and outgoing\nPositive and passionate\nHave a great sense of humour\nAble to think outside the box\nBe a fantastic communicator\nFocused and disciplined\nFluent in English and preferably Chinese (Cantonese or Mandarin)\nAmbitious and impatient for success\nYou will not need knowledge of IT, with all training provided, and hard work and application, you will be able to pick things up quickly\nContact us now if you are keen to have an informal chat to hear more at +852 3619 9860 or send us your CV for our reference.", "employment_types": ["Full Time", "Permanent"], "selling_points": ["Fresh Graduates / Experienced Hires Welcome", "On The Job Training Provided", "Competitive Basic Salary & Commission Scheme"], "locations": ["Sheung Wan"], "categories": ["Admin & HR", "Recruitment / Executive Search", "Information Technology (IT)", "Technical / Functional Consulting", "Management", "Management Trainee"], "post_time": "2022-01-17T10:07:32Z", "salary": {"currency": null, "max": null, "min": null, "period": "monthly", "term": null}, "salary_visible": false, "title_keywords": ["consultants"], "responsibilities": [], "requirements": {"degrees": [], "majors": [], "languages": [], "language_level": [], "hard_skills": [], "soft_skills": [], "languages_combined": []}, "experience_required": {"duration": [], "field": []}}, {"job_id": "100003009052022", "location_code": "hk", "company": "Multisoft Limited", "job_title": "Senior Human Resources Officer", "description": "Responsibilities:\n\n\nHandle end-to-end recruitment process and follow up all on-boarding / off-boarding procedures including conduct induction program and exit interview\nAssist in C&B functions including leave & attendance management, personal data update, payroll calculation and benefit administration\nPlan, develop, implement and review HR policies and procedures to support the Company\u2019s needs & cope with the overall business strategies\nPrepare HR and management reports e.g. salary scales, manning guide and turnover rate etc.\nIdentify and implement employee engagement opportunities and activities\nAd hoc project as assigned\n\nRequirements:\n\nBachelor\u2019s degree in human resources management or other related disciplines\nMinimum 4 years experiences in HR related discipline\nExperience in IT industry is highly preferred\nGood command of both spoken and written English and Chinese (Cantonese and Mandarin)\nAdvanced Excel, PowerPoint and database management skills\nGood stakeholder management and interpersonal skills\nStrong analytical skills and detail minded with high sensitivity to numbers\nStrong influencing relationships with different levels of management\u00a0and problem-solving skills\nIndependent, proactive with positive attitude, enjoy working in a dynamic and fast-paced environment\nCandidate with more experiences will consider as Assistant Human Resources Manager\nImmediate available is preferred\n\nJoin us, sketch the future with digitalization!\n\nInterested parties please send us your detailed resume with\u00a0current and\u00a0expected salary\u00a0by clicking the link\u00a0\"APPLY NOW\".\n\nAll information provided by applicants will be used for recruitment-related purposes and handled in strict confidence by authorized personnel. The personal data collected will be destroyed after three months.\n\nFor more information about Multisoft, please visit http://www.multisoft.com.hk/ or follow us on:\u00a0\nFacebook:\u00a0https://www.facebook.com/MultisoftLimited/\nYoutube:\u00a0https://www.youtube.com/user/MultisoftLimited\nLinkedin:\u00a0https://www.linkedin.com/company/multisoft-limited/", "employment_types": ["Full Time", "Permanent"], "selling_points": ["End-to-end recruitment process", "HRBP", "Friendly and dynamic working environment"], "locations": ["Kwun Tong"], "categories": ["Admin & HR", "HR Director / Manager", "Recruitment / Executive Search", "Training & Development"], "post_time": "2022-01-17T01:51:47Z", "salary": {"currency": null, "max": null, "min": null, "period": "monthly", "term": null}, "salary_visible": false, "title_keywords": ["senior human resources officer"], "responsibilities": ["attendance", "management", "ad hoc", "policies", "hr", "review", "procedures", "develop", "management reports", "plan", "recruitment process", "personal data", "payroll", "administration"], "requirements": {"degrees": ["degree", "bachelor"], "majors": ["related disciplines"], "languages": ["cantonese", "english", "chinese", "mandarin"], "language_level": ["good command"], "hard_skills": ["excel", "powerpoint", "analytical skills", "dynamic", "problem-solving skills"], "soft_skills": ["independent", "advanced", "fast-paced environment", "sensitivity", "enjoy working", "analytical skills", "positive attitude", "dynamic", "interpersonal skills", "problem-solving skills", "proactive"], "languages_combined": [{"language": "cantonese", "language_level": ["good command"]}, {"language": "english", "language_level": ["good command"]}, {"language": "chinese", "language_level": ["good command"]}, {"language": "mandarin", "language_level": ["good command"]}]}, "experience_required": {"duration": ["minimum 4 years"], "field": ["related", "hr", "it", "human resources"]}}, {"job_id": "100003009051916", "location_code": "hk", "company": "Wong\u2019s International Holdings Limited", "job_title": "Human Resources Officer", "description": "Job Description:\n\n\nProvide full spectrum of human resources supports including but not limited to recruitment, on-boarding arrangement, leave and payroll administration, staff benefit projects, employee relations activities etc.;\nEnsure accurate and updated staff records are maintained;\nPrepare periodical management reports and organization charts;\nAssist in ad-hoc projects as required.\nRequirement:\n\nDegree holder in Human Resources Management or related discipline;\nAt least 2 years\u2019 relevant experience preferable in sizable companies;\nGood interpersonal skill and able to deal with different levels of people;\nStrong command of both spoken and written English, Chinese and Mandarin;\nIndependent, committed, responsible, self-motivated, detailed-minded and proactive;\nImmediate available is preferred.\u00a0", "employment_types": ["Full Time", "Permanent"], "selling_points": ["Minimum 2 years experience", "Full spectrum of recruitment", "Immediate available"], "locations": ["Ngau Tau Kok"], "categories": ["Admin & HR", "HR Supporting Staff", "Recruitment / Executive Search"], "post_time": "2022-01-17T01:31:47Z", "salary": {"currency": null, "max": null, "min": null, "period": "monthly", "term": null}, "salary_visible": false, "title_keywords": ["human resources officer"], "responsibilities": ["management reports", "recruitment", "ad-hoc projects", "payroll", "administration"], "requirements": {"degrees": ["degree holder"], "majors": [], "languages": ["english", "chinese", "mandarin"], "language_level": [], "hard_skills": ["sizable companies"], "soft_skills": ["self-motivated", "independent", "responsible", "interpersonal skill", "committed", "proactive", "detailed"], "languages_combined": [{"language": "english", "language_level": []}, {"language": "chinese", "language_level": []}, {"language": "mandarin", "language_level": []}]}, "experience_required": {"duration": ["at least 2 years"], "field": ["relevant experience"]}}, {"job_id": "100003009053028", "location_code": "hk", "company": "EC Healthcare", "job_title": "Human Resources Manager / Assistant Manager - Talent Acquisition", "description": "We are looking for talent with solid talent acquisition experiences to help our company find and retain excellent talent. \u00a0This position is responsible for the full recruitment cycle, which includes developing job profiles, implementing recruitment strategies, sourcing candidates through digital platforms, coordinating the interview process, and assisting with new employee paperwork. Our ideal candidate is someone who can forecast our future talent needs and budget for the costs of talent recruitment. Applicants must have prior HR experience, and you should be familiar with applicant tracking systems.\n\nResponsibilities\n\nDetermine current staffing needs and produce forecasts\nCollaborate with hiring managers to develop job profiles\nSource potential candidates through hiring events and digital marketing campaigns, including on social media platforms\nCoordinate candidate interviews and assessments\nUpdate our applicant tracking system\nAssist with employee onboarding\nForecast future talent or staffing needs\nBudget for recruitment costs\nOrganize and/or attend career fairs, assessment centers or other events\nUse metrics to create reports and identify areas of improvement\n\nRequirements\n\nHeld a position at talent acquisition supervisory level for at least 3 yrs\nExperience in full-cycle recruiting, sourcing and employment branding\nUnderstanding of all selection methods and techniques\nProficient in the use of social media and job boards\nWillingness to understand the duties and competencies of different roles\nExcellent communicator in Cantonese, English and Mandarin in both written and spoken\nDegree holder in business administration, human resources or relevant field", "employment_types": ["Full Time"], "selling_points": ["Determine staffing needs and produce forecasts", "Forecast future talent or staffing needs", "Budget for recruitment costs"], "locations": ["Mong Kok"], "categories": ["Admin & HR", "Administration / Operation Manager", "HR Director / Manager", "Recruitment / Executive Search"], "post_time": "2022-01-17T05:12:27Z", "salary": {"currency": null, "max": null, "min": null, "period": "monthly", "term": null}, "salary_visible": false, "title_keywords": ["assistant manager", "manager", "human resources"], "responsibilities": ["collaborate with", "digital marketing campaigns", "social media platforms", "budget", "develop", "coordinate", "recruitment", "reports", "forecast", "costs", "tracking"], "requirements": {"degrees": ["degree holder"], "majors": ["business administration"], "languages": ["cantonese", "english", "mandarin"], "language_level": ["excellent"], "hard_skills": [], "soft_skills": ["communicator"], "languages_combined": [{"language": "cantonese", "language_level": ["excellent"]}, {"language": "english", "language_level": ["excellent"]}, {"language": "mandarin", "language_level": ["excellent"]}]}, "experience_required": {"duration": [], "field": []}}, {"job_id": "100003009052553", "location_code": "hk", "company": "Chinese Estates Holdings Limited", "job_title": "Senior Human Resources Officer / Human Resources Officer", "description": "About the Role & Responsibilities:\n\nExecute full spectrum of HR functions including but not limited to recruitment, staff movement, leave management,\u00a0compensation & benefits and employee relations\nProvide end-to-end HR support for our office & site staff and ensure smooth running of day-to-day HR operations\nHandle all aspects of payroll administration including salary calculation, final payment, cost allocation, salaries tax and MPF administration, etc.\nMaintains accurate and timely data entry to HRIS and other related systems\u00a0and prepare reports on a regular basis\nHandles ad-hoc projects\nWhat we are looking for:\n\nDegree holder in Human Resources Management, Business Administration or related disciplines\nMinimum 5 years HR generalist experience with focus on C&B/payroll\nWell versed in HK Employment / MPF Ordinance and labour related ordinance/regulations\nExperience/Knowledge in PeopleSoft is an advantage\nAble to work under pressure and with positive attitude towards changes & challenges\nGood command in both written and spoken English and Chinese\nProficient in MS Office and Chinese Word Processing\nAttractive compensation package including competitive salary, up to 22 days Annual Leave, 5 days work as well as\u00a0excellent career prospects will be offered.\u00a0Interested parties please send full resume including your present and expected salaries by clicking \"Apply Now\".\n\n\n(Personal data collected would be used in accordance with our\u00a0Statement on Employment-Related Data Usage, which\u00a0is available at \u00a0http://www.chineseestates.com \u00a0or upon request made to the Company\u2019s Human Resources Manager. \u00a0Applicants who are not invited for interview within six weeks may consider their applications unsuccessful. \u00a0All personal data of unsuccessful candidates will be destroyed after six months.)\u00a0", "employment_types": ["Full Time", "Permanent"], "selling_points": ["Degree holder in Human Resources Management", "5 years' relevant experience", "Knowledge and experience in using PeopleSoft"], "locations": ["Causeway Bay"], "categories": ["Admin & HR", "Compensation & Benefits", "HR Supporting Staff", "Recruitment / Executive Search"], "post_time": "2022-01-17T03:24:16Z", "salary": {"currency": null, "max": null, "min": null, "period": "monthly", "term": null}, "salary_visible": false, "title_keywords": ["senior human resources officer", "human resources officer"], "responsibilities": ["tax", "regulations", "management", "cost", "mpf", "data entry", "work under pressure", "operations", "hr", "systems", "payment", "recruitment", "prepare reports", "ad-hoc projects", "payroll", "administration"], "requirements": {"degrees": ["degree holder"], "majors": ["related disciplines", "business administration"], "languages": ["english", "chinese"], "language_level": ["good command", "proficient"], "hard_skills": ["focus", "chinese word processing", "ms office"], "soft_skills": ["timely", "positive attitude", "smooth", "focus", "accurate", "work under pressure"], "languages_combined": [{"language": "english", "language_level": ["good command"]}, {"language": "chinese", "language_level": ["good command", "proficient"]}]}, "experience_required": {"duration": ["minimum 5 years"], "field": ["payroll", "hr generalist"]}}, {"job_id": "100003009054909", "location_code": "hk", "company": "Cathay Pacific Services Limited", "job_title": "People Officer", "description": "Responsibilities:\nSupport full spectrum of HR functions included but not limited to recruitment,\u00a0compensation and benefit, communication, employee relations, and etc.\u00a0Main duties are:\nrecruitment logistics arrangement\nstaff event coordination & support\u00a0\nuniform and locker management\nstaff profile and personnel files handling\u00a0\nmedical scheme administration\nHR reports preparation\nHandle ad hoc project as assigned by immediate supervisor\u00a0\n\u00a0Less experience will be considered as People Assistant\u00a0\n\n\u00a0Requirements:\n\nDiploma holder in Human Resources Management or related discipline and above\n1- 2 years working experience in Human Resources field is preferable, fresh graduates are also welcome\u00a0\n\u00a0Well conversant in Employment Ordinance and other related legislation\n\u00a0Proficient in both written and spoken English and Chinese\n\u00a0Able to work independently be proactive and be a good team player\n\u00a0Good interpersonal and communication skills\n\u00a0Customer-focused, detailed minded and outgoing\n\u00a0Proficient in MS Office applications\n\n\n\nTo apply,\u00a0you may\u00a0email your confidential resume with date of availability, current and expected salary to\u00a0recruitment @cpsl.com.hk.\u00a0Applicants not contacted within 6 weeks may consider their applications unsuccessful.\n\nCathay Pacific Services Limited is an Equal Opportunities Employer. Personal data provided by job applicants will be used strictly in accordance with our personal data policy and for recruitment purposes only. Candidates not notified within six weeks may consider their application unsuccessful. All related information will be kept in our file for up to 24 months.\n\n\n\n", "employment_types": ["Full Time", "Permanent"], "selling_points": ["Provide support to full spectrum of HR functions", "Wider exposures in air cargo industry", "Fresh graduates are also welcome"], "locations": ["Airport Area"], "categories": ["Admin & HR", "Compensation & Benefits", "HR Supporting Staff", "Recruitment / Executive Search"], "post_time": "2022-01-17T13:34:02Z", "salary": {"currency": null, "max": null, "min": null, "period": "monthly", "term": null}, "salary_visible": false, "title_keywords": ["officer"], "responsibilities": ["management", "ad hoc", "logistics arrangement", "hr", "hr reports", "communication", "recruitment", "coordination", "administration"], "requirements": {"degrees": ["diploma holder"], "majors": [], "languages": ["english", "chinese"], "language_level": ["proficient"], "hard_skills": ["ms office"], "soft_skills": ["outgoing", "communication skills", "good team player", "work independently", "customer-focused", "proactive", "interpersonal", "detailed"], "languages_combined": [{"language": "english", "language_level": ["proficient"]}, {"language": "chinese", "language_level": ["proficient"]}]}, "experience_required": {"duration": ["1- 2 years"], "field": ["human resources"]}}, {"job_id": "100003009054569", "location_code": "hk", "company": "RecruitFirst Limited", "job_title": "HR Business Partner / HR Executive", "description": "RecruitFirst is part of HRnetGroup - A Singapore listed company with offices in 13 Asian cities.\n\nAs the Group HRBP, you will:\n\n\nHandle end-to-end local or regional recruitment by matching talents to our recruitment brands\nPerform full spectrum of internal recruitment process includes sourcing of candidates, interview assessments and on-boarding process\nDrive internship programs and campus recruitment to achieve the hiring goals of the Group\nConduct orientation and training on a regular basis and to support annual performance evaluation\nEnhance employer branding through participation in marketing activities such as CSR events, career fairs etc\nAssist in HR administration and support in various HR projects and functions\n\nRequirements:\n\nBachelor\u2019s degree with minimum 3 years of experience, previous experience in recruitment agency or human resources is preferred\nIndependent, proactive, good communication and possess strong problem-solving skills\nPassionate, organized with a positive attitude and is able to work under pressure\nGood communication skills and fluent in English & Chinese\nCandidate with less experience maybe considered as HR Executive", "employment_types": ["Full Time", "Permanent"], "selling_points": [], "locations": ["Wan Chai"], "categories": ["Sales, CS & Business Devpt", "Customer Service - Supervisor / Officer", "Admin & HR", "HR Supporting Staff", "Recruitment / Executive Search"], "post_time": "2022-01-17T10:06:54Z", "salary": {"currency": null, "max": null, "min": null, "period": "monthly", "term": null}, "salary_visible": false, "title_keywords": ["hr", "executive"], "responsibilities": ["work under pressure", "hr", "communication", "recruitment", "evaluation", "recruitment process", "administration"], "requirements": {"degrees": ["degree", "bachelor"], "majors": [], "languages": ["english", "chinese"], "language_level": ["fluent", "good"], "hard_skills": ["problem-solving skills"], "soft_skills": ["passionate", "organized", "communication skills", "independent", "communication", "positive attitude", "problem-solving skills", "proactive", "work under pressure"], "languages_combined": [{"language": "english", "language_level": ["fluent", "good"]}, {"language": "chinese", "language_level": ["fluent", "good"]}]}, "experience_required": {"duration": ["minimum 3 years"], "field": ["agency", "hr", "recruitment", "human resources"]}}, {"job_id": "100003009054872", "location_code": "hk", "company": "Nu Skin Enterprises Hong Kong, LLC", "job_title": "HR Officer / Senior HR Officer (HR Generalist)", "description": "Your Responsibilities:\n\nAct as a Business Partner to work closely with internal stakeholders in providing full spectrum of HR services including but not limited to talent acquisition, staff development, staff engagement, and etc.\nExplore sourcing network to build a robust talent pipeline, manage all talent sourcing activities including but not limited to sourcing, screening, interviewing, stakeholder engagement and offering.\nParticipate in identifying training needs to foster a supportive learning culture.\nParticipate in coordinating related staff events to enhance employee morale and maintain their awareness of company core value and engagement.\nParticipate in ad-hoc HR projects and new initiatives as assigned.\n\nOur Requirements:\n\nBachelor degree holder in Human Resources Management or any related qualification.\n3-4 years of relevant experience in Human Resources. Experience in recruitment agent will be an advantage.\nWell-versed in Employment Ordinance and other HR related regulations in Hong Kong.\nFlexible, proactive and detail-minded with strong communication skill.\nStrong sense of responsibilities and able to work independently and be a good team player.\nPerformance driven with can-do attitude and able to work under pressure.\nProficiency in both written and spoken English and Chinese. Putonghua is an advantage.;\nImmediately available is highly preferred\n\nWhat We Offer?\n\n\nFlexi-work\nMonthly product allowance\nQuarterly incentive bonus & annual performance bonus\nAnnual body checkup,\nFull protection of medical benefits (including dental),\nLife & accidental insurance,\nAnnual leave and other caring leaves.\nIf you are ready for a new challenge in your career, please click\u00a0\"Apply Now\"\u00a0to submit your application with expected salary.\n\n\n\nALL PERSONAL INFORMATION WE COLLECTED IS FOR THE PURPOSE OF RECRUITMENT ONLY\n\nPlease visit www.nuskin.com to find out more about us!", "employment_types": ["Full Time", "Permanent"], "selling_points": ["Flexi-working hours & work from home arrangement", "Caring Culture", "HR Business Partner"], "locations": ["Causeway Bay"], "categories": ["Admin & HR", "HR Supporting Staff", "Recruitment / Executive Search", "Training & Development"], "post_time": "2022-01-17T12:14:09Z", "salary": {"currency": null, "max": null, "min": null, "period": "monthly", "term": null}, "salary_visible": false, "title_keywords": ["hr", "hr officer"], "responsibilities": ["ad-hoc", "hr", "maintain"], "requirements": {"degrees": ["bachelor degree holder"], "majors": [], "languages": ["putonghua", "english", "chinese"], "language_level": ["advantage", "proficiency"], "hard_skills": [], "soft_skills": ["flexible", "detail-minded", "work independently", "good team player", "can-do attitude", "work under pressure", "communication skill", "proactive", "driven", "sense of responsibilities"], "languages_combined": [{"language": "putonghua", "language_level": ["advantage"]}, {"language": "english", "language_level": ["proficiency"]}, {"language": "chinese", "language_level": ["proficiency"]}]}, "experience_required": {"duration": ["3-4 years"], "field": ["recruitment", "relevant experience", "human resources"]}}, {"job_id": "100003009053015", "location_code": "hk", "company": "TR at CUHK Company Limited", "job_title": "Human Resources Assistant", "description": "ROLES & RESPONSIBILITIES:\n\nResponsible for recruitment process including interview and selection, handle employees on-boarding to off-boarding, verification of candidate's qualification and visa application procedures;\nResponsible for issuing employment contract and other personnel letters;\nPerform payroll functions including monthly payroll, MPF, and filing of tax return;\nLiaise with the Government departments to ensure compliance with Employment Ordinance, Inland Revenue Ordinances, etc;\nLiaise with different services providers such as broker, insurers and MPF trustee for HR operations;\nSupport the development and implementation HR policies, procedures and HR system;\nTo maintain accurate employee record in HR system and filing system;\nResponsible for daily HR operations and general staff enquiries; and\nHandle ad-hoc projects as assigned.\n\nREQUIREMENTS:\n\nHigher diploma or above in Human Resources Management or related disciplines;\nBe well-versed in Employment Ordinance and human resource business functions;\nAt least 1 year of human resources experience;\nHave self-motivation, strong analytical and coordination skills;\nAble to handle sensitive information with confidentiality;\nAble to work under pressure and finish tasks with tight deadline; and\nPossess excellent command written and spoken English and Chinese languages (including Putonghua).\n\nAppointment will initially be made on contract basis for up to two years, renewable subject to performance.", "employment_types": ["Full Time", "Contract"], "selling_points": [], "locations": ["Shatin Area"], "categories": ["Admin & HR", "Personal / Executive Assistant", "Compensation & Benefits", "Recruitment / Executive Search"], "post_time": "2022-01-17T05:04:55Z", "salary": {"currency": null, "max": null, "min": null, "period": "monthly", "term": null}, "salary_visible": false, "title_keywords": ["human resources assistant"], "responsibilities": ["tax", "mpf", "operations", "hr", "policies", "letters", "procedures", "implementation", "ensure compliance", "maintain", "liaise with", "recruitment process", "ad-hoc projects", "payroll"], "requirements": {"degrees": ["higher diploma or above"], "majors": ["related disciplines"], "languages": ["putonghua", "english", "chinese"], "language_level": ["excellent"], "hard_skills": [], "soft_skills": ["work under pressure", "self-motivation", "coordination skills", "sensitive"], "languages_combined": [{"language": "putonghua", "language_level": ["excellent"]}, {"language": "english", "language_level": ["excellent"]}, {"language": "chinese", "language_level": ["excellent"]}]}, "experience_required": {"duration": ["at least 1 year"], "field": ["human resources"]}}, {"job_id": "100003009052749", "location_code": "hk", "company": "Silverstrand Executive Search Limited", "job_title": "\u62db\u8058  \u4eba\u4e8b\u987e\u95ee / \u730e\u5934\u987e\u95ee Recruitment Consultant / Recruitment Researcher", "description": "Job Highlights\n\u00a0\u5e94\u5f81\u8005\u5fc5\u987b\u80fd\u64cd\u6d41\u5229\u56fd\u8bed\n\u00a0\u730e\u5934\u516c\u53f8 - \u91d1\u878d\u670d\u52a1\u4e1a\n\u00a0\u5177\u5907\u91d1\u878d\u3001\u79d1\u6280\u6216\u91d1\u878d\u79d1\u6280\u9886\u57df\u7684\u77e5\u8bc6/\u7ecf\u9a8c\u5c06\u4f1a\u83b7\u4f18\u5148\u8003\u8651\u3002\nJob Description\n\u6211\u4eec\u662f\u4e00\u5bb6\u5c61\u83b7\u6b8a\u8363\u7684\u7cbe\u54c1\u730e\u5934\u516c\u53f8\uff0c\u603b\u90e8\u8bbe\u5728\u9999\u6e2f\uff0c\u4e13\u6ce8\u5728\u91d1\u878d\u670d\u52a1\u884c\u4e1a\uff0c\u5305\u62ec\u4e70\u5356\u53cc\u65b9\u3002\n\u73b0\u5728\u6211\u4eec\u6b63\u5728\u5bfb\u627e\u4e00\u4f4d\u62e5\u6709\u4e30\u5bcc\u7ecf\u9a8c\u7684\u62db\u8058\u730e\u5934\u987e\u95ee\uff0c\u7279\u522b\u5728\u91d1\u878d\u9886\u57df\u3002\u6211\u4eec\u4e5f\u6b22\u8fce\u6709\u7ecf\u9a8c\u7684\u62db\u8058\u7814\u7a76\u5458\u6216\u5bf9\u4eba\u4e8b\u987e\u95ee\u884c\u4e1a\u5177\u6709\u6d53\u539a\u5174\u8da3\u7684\u672c\u79d1\u6bd5\u4e1a\u751f\u3002\u00a0\n\u5728 Silverstrand\uff0c\u6211\u4eec\u9f13\u52b1\u6211\u4eec\u7684\u987e\u95ee\u5229\u7528\u73b0\u6709\u548c\u65b0\u5174\u6280\u672f\u6765\u6539\u8fdb\u4ed6\u4eec\u7684\u5de5\u4f5c\u6d41\u7a0b\u3002\n\u900f\u8fc7\u56e2\u961f\u7d27\u5bc6\u8054\u7cfb\uff0c\u79ef\u6781\u9f13\u52b1\u5408\u4f5c\u548c\u4ea4\u53c9\u9500\u552e\uff0c\u540c\u65f6\u4ecd\u7136\u4f7f\u6211\u4eec\u7684\u987e\u95ee\u80fd\u591f\u6839\u636e\u81ea\u5df1\u7684\u8d21\u732e\u83b7\u5f97\u884c\u4e1a\u9886\u5148\u7684\u4f63\u91d1\u3002\n\u6211\u4eec\u7684\u5ba2\u6237\u540d\u5355\u5305\u62ec\u56fd\u9645\u548c\u533a\u57df\u5bf9\u51b2\u57fa\u91d1\u3001\u6295\u8d44\u94f6\u884c\u3001\u8d44\u4ea7\u7ba1\u7406\u516c\u53f8\u548c\u91d1\u878d\u79d1\u6280\u521d\u521b\u516c\u53f8\u3002\n\u6211\u4eec\u5e0c\u671b\u7ee7\u7eed\u53d1\u5c55\u9999\u6e2f\u7684\u56e2\u961f\u3002\u9700\u8981\u5177\u5907\u6d41\u5229\u82f1\u8bed\u548c\u56fd\u8bed\u8bed\u8a00\u80fd\u529b\uff0c\u5177\u6709\u521b\u4e1a\u7cbe\u795e\u3002\u5177\u5907\u91d1\u878d\u3001\u79d1\u6280\u6216\u91d1\u878d\u79d1\u6280\u9886\u57df\u7684\u77e5\u8bc6/\u7ecf\u9a8c\u5c06\u4f1a\u83b7\u4f18\u5148\u8003\u8651\u3002", "employment_types": ["Full Time"], "selling_points": ["\u4eba\u4e8b\u987e\u95ee", "\u730e\u5934\u987e\u95ee", "Executive Search"], "locations": ["Sheung Wan"], "categories": ["Admin & HR", "Recruitment / Executive Search"], "post_time": "2022-01-17T03:55:12Z", "salary": {"currency": null, "max": null, "min": null, "period": "monthly", "term": null}, "salary_visible": false, "title_keywords": ["recruitment consultant", "researcher"], "responsibilities": [], "requirements": {"degrees": [], "majors": [], "languages": [], "language_level": [], "hard_skills": [], "soft_skills": [], "languages_combined": []}, "experience_required": {"duration": [], "field": []}}, {"job_id": "100003009052987", "location_code": "hk", "company": "ABS (HK) Limited", "job_title": "Human Resources Officer", "description": "This position is designed to provide comprehensive HR operations services across the board in different countries in ABS.\u00a0 We are inviting a high caliber candidate to grow with us on this dynamic role:\n\nKEY RESPONSIBILITIES:\n\nProvide full spectrum of HR operations services such as employment & benefits administration, payroll, taxation, visa management, recruitment support for countries across ABS\nAssist in preparing regular reports, documentation and HR analytics\nParticipate in HR budgeting processes, HR database development and processes streamlined\nSupport HR services enhancement under direction of HR Management\nHandle employees\u2019 enquiries in timely and professional manner, maintain communication / relationship network for staff community, participate in employee engagement initiatives\nPerform ad-hoc assignments and support HR initiatives when required\nREQUIREMENTS:\n\nDegree holder in Human Resources or related disciplines\n4 years\u2019 all-rounded HR operations experience in multi-national company with cross countries exposure, lesser experience may be considered as Assistant Human Resources Officer\nWell-versed in labor laws and HR practices, multi-countries exposure advantage\nSelf-motivated, meticulous, analytical with good interpersonal and communication skills\nGood command of both written and spoken English\nImmediate available highly preferred", "employment_types": ["Full Time"], "selling_points": ["Full spectrum of HR operations services", "Experience in multi-national company", "5 days work"], "locations": ["Wan Chai"], "categories": ["Admin & HR", "Compensation & Benefits", "HR Supporting Staff", "Recruitment / Executive Search"], "post_time": "2022-01-17T04:56:52Z", "salary": {"currency": null, "max": null, "min": null, "period": "monthly", "term": null}, "salary_visible": false, "title_keywords": ["human resources officer"], "responsibilities": ["taxation", "management", "operations", "hr", "budgeting", "professional manner", "ad-hoc assignments", "communication", "maintain", "recruitment", "reports", "database", "documentation", "payroll", "administration"], "requirements": {"degrees": ["degree holder"], "majors": ["related disciplines"], "languages": ["english"], "language_level": ["good command"], "hard_skills": [], "soft_skills": ["communication skills", "meticulous", "self-motivated", "interpersonal"], "languages_combined": [{"language": "english", "language_level": ["good command"]}]}, "experience_required": {"duration": ["4 years"], "field": ["hr", "human resources"]}}, {"job_id": "100003009054362", "location_code": "hk", "company": "ATAL Engineering Ltd", "job_title": "Senior Human Resources Officer (Ref no.: SHRO-AS)", "description": "Responsibilities:\n\nTo provide HR account services to designated Business Units/Corporate Units, including recruitment, staff retention, staff relations, disciplinary and performance management.\nTo maintain HR related records, such as headcount summary and HRIS staff record etc.;\nTo prepare monthly management reports and analysis;\nTo perform ad hoc projects or duties as assigned by supervisor\n\nRequirements:\n\nDegree holder in Human Resources Management or related disciplines;\nMinimum 6 years working experience in human resources;\nProficiency in MS Excel, Word PowerPoint and Chinese Word Processing;\nGood command of both spoken and written English and Chinese;\nGood communication and interpersonal skills;\nWilling to learn and a good team player.\nImmediate available is an advantage\n\nWe offer an attractive remuneration & benefit package and 5-day work.\u00a0 Please click the Apply Now button to send your full resume stating relevant job reference, present and expected salary and availability.\n\nPersonal data collected will be treated in strict confidence and used for recruitment related purposes only.", "employment_types": ["Permanent"], "selling_points": ["Degree Holder in Human Resources Management", "Min. 6 years working experience", "Good command of computer knowledge"], "locations": ["North Point"], "categories": ["Admin & HR", "Clerical / Admin Staff", "HR Supporting Staff", "Recruitment / Executive Search"], "post_time": "2022-01-17T09:16:52Z", "salary": {"currency": null, "max": null, "min": null, "period": "monthly", "term": null}, "salary_visible": false, "title_keywords": ["senior human resources officer"], "responsibilities": ["management", "hr", "analysis", "management reports", "maintain", "recruitment", "ad hoc projects"], "requirements": {"degrees": ["degree holder"], "majors": ["related disciplines"], "languages": ["english", "chinese"], "language_level": ["proficiency", "good command"], "hard_skills": ["ms excel", "chinese word processing", "word", "powerpoint"], "soft_skills": ["good team player", "communication and interpersonal skills", "willing to learn"], "languages_combined": [{"language": "english", "language_level": ["good command"]}, {"language": "chinese", "language_level": ["proficiency", "good command"]}]}, "experience_required": {"duration": ["minimum 6 years"], "field": ["human resources"]}}, {"job_id": "100003009051048", "location_code": "hk", "company": "Rentokil Initial Hong Kong Ltd", "job_title": "Recruiter (6 months' contract)(Monthly salary package HK$14,000 up)", "description": "PRINCIPAL DUTIES & RESPONSIBILITIES\n\n\nResponsible to support recruitment and hiring process such as conducting recruitment from posting job ads, etc.\nParticipate in job fair, recruitment day and other recruitment activities\nExplore potential and evaluate the effectiveness of advertising, social media, job fair and recruitment channels, etc.\nProvide administrative support to the HR team including data entry, document filing and secretarial support\nHandle ad hoc projects as assigned\nPERSON SPECIFICATION\n\nDiploma in human resources management or related disciplines is an advantage\n1-2 years of relevant working experience\u00a0in recruitment, preferably in MNC or sizable organization\nGood problem solving & communication skills\nAble to work independently and multi-tasking\nProficient in Photoshop software is preferable\nProficient in PC skills \u2013 MS Excel, MS word & PowerPoint\nGood command of both spoken and written English and Chinese\nImmediate available is highly preferred\n\nAre you interested? Here's what you can expect when you join us\n\nCompetitive salary package\nOffer learning & development and Training program\nExcellent company culture\nExcellent promotion opportunities\n5-day work week\nService leads incentive opportunity\n\nIf you are interested in applying, please enclose your resume with email address & contact number. Thank you.", "employment_types": ["Full Time"], "selling_points": ["Monthly salary package HK$14,000 up", "5-day work week", "Service leads incentive opportunity"], "locations": ["Kwun Tong"], "categories": ["Admin & HR", "Secretary", "HR Supporting Staff", "Recruitment / Executive Search"], "post_time": "2022-01-15T01:31:32Z", "salary": {"currency": null, "max": null, "min": null, "period": "monthly", "term": null}, "salary_visible": false, "title_keywords": [], "responsibilities": ["social media", "document filing", "management", "advertising", "software", "data entry", "hr", "evaluate", "communication", "recruitment", "secretarial support", "ad hoc projects", "contact", "provide administrative support"], "requirements": {"degrees": ["diploma"], "majors": ["related disciplines"], "languages": ["english", "chinese"], "language_level": ["good command"], "hard_skills": ["powerpoint", "problem solving", "ms excel", "photoshop", "pc skills", "ms word"], "soft_skills": ["communication skills", "work independently", "responsible", "interested in", "problem solving", "multi-tasking", "learning"], "languages_combined": [{"language": "english", "language_level": ["good command"]}, {"language": "chinese", "language_level": ["good command"]}]}, "experience_required": {"duration": ["1-2 years"], "field": ["sizable organization", "recruitment", "relevant working experience"]}}, {"job_id": "100003009052927", "location_code": "hk", "company": "Swing Consulting Limited", "job_title": "Recruitment Assistant", "description": "Responsibilities:\n\nHandle recruitment and selection process, including job posting, candidates sourcing, CVs screening, interviewing, etc.\nReview CVs and credentials for suitability of skills, experience and knowledge in relation to position requirements using appropriate selection techniques\nBrief candidates on suitable positions and prepare them for interview with clients\nPrepare regular advertisement postings on different channels\nHandle other ad-hoc projects and assignments\n\n\u00a0Requirements:\n\nDiploma or above.\nSelf-disciplined, hardworking and able to work independently.\nStrong organization skills, independent, professional.\nGood command of both written and spoken English and Chinese.\nImmediate available will be an advantage.\nFresh Graduate is welcome.\nWorking Hour: 9:30am - 6:00pm (Mon to Fri)\n\nTo apply, you may click the\u00a0Apply Now\u00a0button below\u00a0or\u00a0send your full resume to\u00a0fax: 3426 2763\n\nFor other vacancies, please visit our website www.swing-hk.com\n\nJoin us on facebook \u2013 www.facebook.com/swinghk\n\nAll information provided will be treated in strict confidence and used for recruitment purposes only.", "employment_types": ["Full Time", "Permanent"], "selling_points": ["Handle recruitment and selection process", "Candidates sourcing, CVs screening, Interviewing", "5-day work 9:30am to 6pm, good career development"], "locations": ["Kwun Tong"], "categories": ["Admin & HR", "HR Supporting Staff", "Recruitment / Executive Search", "Sales, CS & Business Devpt", "Sales Administration"], "post_time": "2022-01-17T04:34:17Z", "salary": {"currency": "HKD", "max": 19999, "min": 14000, "period": "monthly", "term": null}, "salary_visible": true, "title_keywords": ["assistant"], "responsibilities": ["ad-hoc projects", "review", "recruitment"], "requirements": {"degrees": ["fresh graduate", "diploma or above"], "majors": [], "languages": ["english", "chinese"], "language_level": ["good command"], "hard_skills": ["facebook"], "soft_skills": ["work independently", "confidence", "independent", "organization skills", "hardworking"], "languages_combined": [{"language": "english", "language_level": ["good command"]}, {"language": "chinese", "language_level": ["good command"]}]}, "experience_required": {"duration": [], "field": []}}, {"job_id": "100003009054257", "location_code": "hk", "company": "CMA CGM (Hong Kong) Limited", "job_title": "HR Executive (6-months)", "description": "The ideal candidate will need to have experiences in account services as a temporary HR Executive.\u00a0\u00a0\n\nMain Responsibilities:\n\nAssist in projects related to human resources development, e.g. full spectrum of HR functions, including but not limited to HRIS System, selection & planning, performance management, remuneration management, etc.;\nResponsible for the full spectrum of Talent Acquisition, from shortlisting resumes, interviewing, making an offer before the candidates\u2019 onboarding and related recruitment aspects;\nReview and implement organizational charts, HR policies, procedures, and practices from time to time;\nWork closely with relevant parties internally and externally to meet the business needs;\nProvide support to employees in various HR-related topics such as leaves, ER or any issues that may arise;\nOther ad-hoc projects when necessary.\n\nJob Requirements:\n\nDegree in Human Resources or related fields;\n2 - 5 years of experience in a HR Generalist role;\nProficient in both written and spoken Chinese, Mandarin and\u00a0English;\nKnowledge in Recruitment, Employee Relations, Performance Management, Compensation and HK Labour Ordinance;\nExperience in using any HRIS systems will be an advantage;\nGood at interpersonal and communication skills;\nImmediate available is preferred.\n\nRemuneration will commensurate with candidate\u2019s qualification and experience. Interested candidates please send your detailed resume with\u00a0present & expected salary\u00a0to\u00a0Human Resources Department,\u00a018/F, Tower B, 223 \u2013 231 Wai Yip Street, Kwun Tong, Kowloon, Hong Kong\n\nPlease complete the standard application procedure by\u00a0clicking the Apply Now button.\n\nThe information provided will be kept confidential and used for recruitment purposes only. Applicants not contacted within three months may consider their applications unsuccessful. The company will retain all applications for a maximum period of one year.", "employment_types": ["Full Time", "Temporary"], "selling_points": ["HR Executive", "2 - 5 years of experience", "Project based role"], "locations": ["Kwun Tong Area"], "categories": ["Admin & HR", "Compensation & Benefits", "HR Supporting Staff", "Recruitment / Executive Search"], "post_time": "2022-01-17T08:58:43Z", "salary": {"currency": null, "max": null, "min": null, "period": "monthly", "term": null}, "salary_visible": false, "title_keywords": ["hr", "executive"], "responsibilities": ["management", "provide support", "policies", "hr", "review", "procedures", "recruitment", "ad-hoc projects", "planning"], "requirements": {"degrees": ["degree"], "majors": [], "languages": ["english", "chinese", "mandarin"], "language_level": ["proficient"], "hard_skills": [], "soft_skills": ["communication skills", "interpersonal"], "languages_combined": [{"language": "english", "language_level": ["proficient"]}, {"language": "chinese", "language_level": ["proficient"]}, {"language": "mandarin", "language_level": ["proficient"]}]}, "experience_required": {"duration": ["2 - 5 years"], "field": ["hr generalist"]}}, {"job_id": "100003009054444", "location_code": "hk", "company": "Horizon Technology Recruitment", "job_title": "Senior / Recruitment Consultant - APAC", "description": "Who you are?\nAfter having an incredible year thus far across Europe and in Asia,\u00a0\nThe new Hong Kong office is looking to further expand and needs highly enthusiastic sales fanatics with an entrepreneurial mindset. As a 360 Recruiter you should be able to hunt down the most exciting companies and build a credible network within your space with the most suitable candidates. Are you ready to grow as a professional and take charge?\n\nWhat is offered?\nYou will be part of the Hong Kong team in our brand new office in Harbour City with an amazing view. In addition, you will be offered:\n\nBasic salary with a competitive commission structure\nExciting incentives and special perks for high performers\nExcellent Career Growth Options suitable for every individual\nTailor-made training and development program\u00a0\nInternational working environment\u00a0\n\nWhat is expected of you?\n\nBe persistent with a \u2018Winners\u2019 mentality.\nCan speak business level English and Cantonese\u00a0\u00a0\nHave an entrepreneurial mindset (Think outside the box).\nHave up to 2 years of working experience in the Recruitment industry.\n\nFor more information, please feel free to call +852 3180 9295 and speak with our Talent Acquisition team or click APPLY NOW and take charge of your career!", "employment_types": ["Full Time"], "selling_points": ["International Company, Uncapped Commission", "Work hard, Play hard", "Salary OTE 50,000 - 65,000 HKD per month"], "locations": ["Tsim Sha Tsui"], "categories": ["Admin & HR", "Recruitment / Executive Search"], "post_time": "2022-01-17T09:34:46Z", "salary": {"currency": "HKD", "max": 54999, "min": 45000, "period": "monthly", "term": null}, "salary_visible": true, "title_keywords": ["recruitment consultant"], "responsibilities": [], "requirements": {"degrees": [], "majors": [], "languages": [], "language_level": [], "hard_skills": [], "soft_skills": ["enthusiastic"], "languages_combined": []}, "experience_required": {"duration": [], "field": []}}, {"job_id": "100003009054133", "location_code": "hk", "company": "China Life Insurance (Overseas) Company Limited", "job_title": "Senior Human Resources Manager /Human Resources Manager", "description": "Responsibilities\n\nProvide value-added HR services and advisory support on manpower planning, recruitment and selection, talent management and staff relations\nMaintain the professional standard of recruitment services for both internal and external parties\nSupport end-to-end recruitment from sourcing, screening, interviewing to salary negotiation\nReview and streamline recruitment process and workflow to enhance productivity and efficiency\nPlan and coordinate campus recruitment events and activities, such as job fairs and recruitment talks\nDesign, implement and sustain talent management programs including career and leadership development, succession planning, performance management, and organization development plan\nUndertake HR projects and initiatives as required\n\nRequirement\n\nUniversity degree in HR Management, Business Administration or a related discipline\nMinimum of 8 years of relevant HR experience in sizeable company, preferably in Insurance industry\nStrong self-motivation and attention to details with high quality\nAbility to work under pressure with strong multi-tasking skills\nStrong communication, interpersonal and project management skills\nProficiency in both English and Chinese (Cantonese and Mandarin)", "employment_types": ["Full Time", "Permanent"], "selling_points": ["Business Partner role", "Talent Management", "Manpower planning"], "locations": ["Hung Hom"], "categories": ["Admin & HR", "HR Director / Manager", "Recruitment / Executive Search", "Insurance", "Others"], "post_time": "2022-01-17T08:30:57Z", "salary": {"currency": null, "max": null, "min": null, "period": "monthly", "term": null}, "salary_visible": false, "title_keywords": ["manager", "human resources"], "responsibilities": ["management", "hr", "internal and external parties", "review", "plan and coordinate", "design", "maintain", "recruitment", "plan", "recruitment process", "planning"], "requirements": {"degrees": ["university degree"], "majors": ["business administration"], "languages": ["cantonese", "english", "chinese", "mandarin"], "language_level": ["proficiency"], "hard_skills": ["project management"], "soft_skills": ["project management skills", "communication", "self-motivation", "attention to details", "multi-tasking skills", "interpersonal", "work under pressure"], "languages_combined": [{"language": "cantonese", "language_level": []}, {"language": "english", "language_level": ["proficiency"]}, {"language": "chinese", "language_level": ["proficiency"]}, {"language": "mandarin", "language_level": []}]}, "experience_required": {"duration": ["minimum of 8 years"], "field": ["hr", "insurance industry"]}}, {"job_id": "100003009051757", "location_code": "hk", "company": "Yau Lee Holdings Limited", "job_title": "Admin Officer (Property)", "description": "Reporting to the Administration Manager of the Group, the position will supervise and manage the leasing matters and operation of an industrial property\n\n\nJob Responsibilities:\nSupervise and execute all administrative matter\nAssist in formulating and implementing administrative policies and procedures\nNegotiate with potential and existing tenants for new lease and tenancy renewal issues\nResponsible for the full set book keeping of the company\nPerform daily operation of HR functions including recruitment, staff attendance and leave record, roster arrangement, payroll calculation, taxation filing and MPF contribution\nOversee property maintenance\nPerform other ad-hoc projects as assigned by manager\nJob Requirements:\nCertificate / Diploma or above in related disciplines\nMinimum 5 years\u2019 solid experience\nGood command in written and spoken English and Chinese\nIndependent, mature, self-motivated, detail-minded, well-organized and multi-tasking ability\nProficiency in MS Word, Excel, PowerPoint & Chinese Word Processing\nImmediate availability is highly preferred\nWe offer competitive remuneration package with comprehensive fringe benefits to the right candidate. Interested parties, please send your full resume, with current and expected salary, date of availability to email by clicking \"Apply Now\"", "employment_types": ["Full Time", "Permanent"], "selling_points": ["Supervise and execute all administrative matter", "Oversee property maintenance", "Minimum 5 years\u2019 solid experience"], "locations": ["Not Specified"], "categories": ["Admin & HR", "Clerical / Admin Staff", "Compensation & Benefits", "Recruitment / Executive Search"], "post_time": "2022-01-17T00:42:16Z", "salary": {"currency": null, "max": null, "min": null, "period": "monthly", "term": null}, "salary_visible": false, "title_keywords": ["officer", "admin"], "responsibilities": ["attendance", "taxation", "mpf", "maintenance", "policies", "hr", "daily operation", "procedures", "recruitment", "ad-hoc projects", "payroll"], "requirements": {"degrees": ["certificate", "diploma or above"], "majors": ["related disciplines"], "languages": ["english", "chinese"], "language_level": ["proficiency", "good command"], "hard_skills": ["excel", "chinese word processing", "powerpoint", "ms word"], "soft_skills": ["detail-minded", "self-motivated", "independent", "well-organized", "mature", "multi-tasking"], "languages_combined": [{"language": "english", "language_level": ["good command"]}, {"language": "chinese", "language_level": ["proficiency", "good command"]}]}, "experience_required": {"duration": ["minimum 5 years"], "field": []}}, {"job_id": "100003009054093", "location_code": "hk", "company": "Taste of Asia Group Limited", "job_title": "HR & Admin Assistant", "description": "Job Description:\n\nResponsible for performing all-round Human Resources duties mainly on compensation & benefits and recruitment & selection\nMaintain staff record and HR system including payroll calculation\nHandle work injury case, MPF and taxation independently\nExecute recruitment activities including career fair, recruitment day, remaining contact with NGO and others\nAssist to develop and implement HR policies and procedures\nPerform other ad hoc duties as assigned\n\nRequirement:\n\nDiploma in Human Resources Management\u00a0or related discipline\nAt least\u00a01\u00a0year experience, preferably in F&B industry\nWilling to accept challenge\nWell-versed in Hong Kong Employment Ordinance, MPF regulations and other related legislation would be an advantage\nProficient in MS Office applications and Chinese Word Processing\nGood command of spoken and written English & Chinese\nMature team player with strong communication and interpersonal skills\nFresh graduates will also be considered\nImmediate available is highly preferred\n\n\u00a0Job location: San Po Kong\n\nCompetitive remuneration package and benefits as below:\n\nFive-day work week\n\nMarriage leave\n\nStaff discount\n\nMedical & dental allowance\n\nPerformance bonus\n\nIn-service training course\n\n5 days paternity leave\n\nCompassionate Leave\n\nPromotion opportunities\n\nInterested parties may send your detailed resume with\u00a0expected salary\u00a0and\u00a0notice period\u00a0by\u00a0clicking \"Apply Now\"\n\nAll information collected will be used for recruitment purpose only.", "employment_types": ["Full Time"], "selling_points": ["Five-day work week", "Medical & dental allowance", "Performance bonus"], "locations": ["Wong Tai Sin Area"], "categories": ["Admin & HR", "Others", "HR Supporting Staff", "Recruitment / Executive Search"], "post_time": "2022-01-17T08:22:19Z", "salary": {"currency": null, "max": null, "min": null, "period": "monthly", "term": null}, "salary_visible": false, "title_keywords": ["hr & admin assistant"], "responsibilities": [], "requirements": {"degrees": [], "majors": [], "languages": [], "language_level": [], "hard_skills": [], "soft_skills": [], "languages_combined": []}, "experience_required": {"duration": [], "field": []}}, {"job_id": "100003009053026", "location_code": "hk", "company": "EC Healthcare", "job_title": "Human Resources Officer \u2013 Talent Acquisition", "description": "We are looking for a Human Resources, Talent Acquisition to join our Human Resources department and oversee our full-cycle recruiting.\n\nTalent Acquisition responsibilities include sourcing candidates through various channels, planning interview and selection procedures and hosting or participating in career events. To be successful in this role, you should be able to develop long-term recruiting strategies and nurture trusting relationships with potential hires.\n\nUltimately, you will create strong talent pipelines for our company\u2019s current and future hiring needs.\n\nResponsibilities\n\nCoordinate with hiring managers to identify staffing needs\nDetermine selection criteria\nSource potential candidates through online channels (e.g. social platforms and professional networks)\nPlan interview and selection procedures, including screening calls, assessments and in-person interviews\nAssess candidate information, including resumes and contact details\nDesign job descriptions and interview questions that reflect each position\u2019s requirements\nLead employer branding initiatives\nOrganize and attend job fairs and recruitment events\nForecast quarterly and annual hiring needs by department\nFoster long-term relationships with past applicants and potential candidates\n\nRequirements\n\nProven work experience as a Talent Acquisition or similar role\nFamiliarity with social media, resume databases and professional networks\nHands-on experience with full-cycle recruiting using various interview techniques and evaluation methods\nA keen understanding of the differences between various roles within organizations\nDegree holder in Human Resources Management or relevant field\nProactive, self-motivated, detail-minded, strong sense of responsibility and independent\nGood command of spoken and written English, Chinese and Mandarin\nFamiliar with MS Office applications including Word, PowerPoint & Excel\nImmediate available is highly preferred. \u00a0Candidate with retail industry will be an advantage.", "employment_types": ["Full Time"], "selling_points": ["Determine selection criteria", "Plan interview and selection procedures", "Lead employer branding initiatives"], "locations": ["Mong Kok"], "categories": ["Admin & HR", "Clerical / Admin Staff", "HR Supporting Staff", "Recruitment / Executive Search"], "post_time": "2022-01-17T05:12:12Z", "salary": {"currency": null, "max": null, "min": null, "period": "monthly", "term": null}, "salary_visible": false, "title_keywords": ["human resources officer"], "responsibilities": ["online channels", "coordinate with", "procedures", "design", "recruitment", "contact", "plan", "forecast"], "requirements": {"degrees": ["degree holder"], "majors": [], "languages": ["english", "chinese", "mandarin"], "language_level": ["good command"], "hard_skills": ["excel", "word", "powerpoint", "databases", "ms office"], "soft_skills": ["detail-minded", "self-motivated", "independent", "sense of responsibility", "keen", "hands-on", "proactive"], "languages_combined": [{"language": "english", "language_level": ["good command"]}, {"language": "chinese", "language_level": ["good command"]}, {"language": "mandarin", "language_level": ["good command"]}]}, "experience_required": {"duration": [], "field": []}}, {"job_id": "100003009053986", "location_code": "hk", "company": "Kee Wah Group Limited", "job_title": "Human Resources Assistant", "description": "Responsibilities\n\nPerform Human Resources functions including but not limited to recruitment, manpower planning, compensation & benefits administration, employee relation and other related HR services\nParticipate in the full cycle of front line\u00a0recruitment process such as exploring new recruitment channels, preparing recruitment advertisement, screening, interviewing, selecting, on-boarding arrangements and induction for new joiners\nAssist in company events and activities\nPrepare and consolidate HR reports timely & accurately\nMaintain systematic personnel records and document filings\nHandle ad hoc assignments as assigned\nRequirements\n\nHigher diploma or above in Human Resources Management, Business Administration or related disciplines\n1-2 years relevant experience\nSelf-motivated, mature and can work independently\nGood command in both written and spoken English and Chinese\nFamiliar with MS Office applications, especially in Excel\u00a0(e.g. VLOOKUP\u00a0and Pivot table etc.) and Chinese Word Processing\nCandidate with more experience will be considered as\u00a0Assistant Human Resources Officer\u00a0\nPlease apply with detailed resume, stating current and expected salary, availability and quoting the Employer Reference Number.\n(Personal data\u00a0relating to employment applications will be used for recruitment only)", "employment_types": ["Full Time", "Permanent"], "selling_points": ["Excellent career development opportunity", "Leading brand and sizable company", "Competitive pay and benefits"], "locations": ["Not Specified"], "categories": ["Admin & HR", "Others", "HR Supporting Staff", "Recruitment / Executive Search"], "post_time": "2022-01-17T07:55:44Z", "salary": {"currency": null, "max": null, "min": null, "period": "monthly", "term": null}, "salary_visible": false, "title_keywords": ["human resources assistant"], "responsibilities": ["hr", "personnel records", "hr reports", "planning", "recruitment", "maintain", "ad hoc assignments", "recruitment process", "human resources functions", "administration"], "requirements": {"degrees": ["higher diploma or above"], "majors": ["related disciplines", "business administration"], "languages": ["english", "chinese"], "language_level": ["good command"], "hard_skills": ["excel", "chinese word processing", "pivot table", "vlookup", "ms office"], "soft_skills": ["self-motivated", "work independently", "mature", "detailed"], "languages_combined": [{"language": "english", "language_level": ["good command"]}, {"language": "chinese", "language_level": ["good command"]}]}, "experience_required": {"duration": ["1-2 years"], "field": ["relevant experience", "human resources"]}}, {"job_id": "100003009054579", "location_code": "hk", "company": "Synergis Management Services Limited", "job_title": "Assistant Human Resources Officer (Generalist) (Ref: AHRO-HR)", "description": "Job Responsibilities\n\n\nResponsible for daily HR operations including recruitment, on-boarding and off-boarding arrangement, staff movement handling, compensation & benefits,\u00a0employee relations etc.\nJob advertisement posting, sourcing, offer and contract preparation\nHandle work injury cases and labour dispute cases\nLiaise and maintain good relationship with all internal and external parties and handle HR related enquiries\nAssist in handle ad-hoc HR related projects or assignments, and prepare regular reports for management review\n\nRequirements\n\n\nDegree or above in Human Resources Management or related disciplines\nAround 1-2 years' relevant working experiences, preferably gained in a sizable organization operating in a dynamic, high volume industries\nExperiences in handling EC and labour dispute cases is a must\nMature, detail-minded, willing-to-learn and fast paced\nShow strong interest in developing career as HR Generalist\nFamiliar with Hong Kong Employment Ordinance & other related legal requirements\nGood command of both written and spoken English and Chinese\nProficiency in MS Office is essential\u00a0\n\nFor interested applicants, please send your full resume with availability, present and expected salary by clicking \u201cApply Now\u201d. (Personal Data collected will be used for recruitment purpose only.)\n", "employment_types": ["Full Time", "Permanent"], "selling_points": ["Around 1-2 yrs' experiences in large-scale co.", "Mature, willing-to-learn, fast-paced", "HR Generalist"], "locations": ["Ngau Tau Kok"], "categories": ["Admin & HR", "Compensation & Benefits", "HR Supporting Staff", "Recruitment / Executive Search"], "post_time": "2022-01-17T10:05:31Z", "salary": {"currency": null, "max": null, "min": null, "period": "monthly", "term": null}, "salary_visible": false, "title_keywords": ["assistant human resources officer", "hr"], "responsibilities": ["liaise", "ad-hoc", "job advertisement", "operations", "hr", "internal and external parties", "review", "maintain good relationship", "recruitment", "regular reports for management"], "requirements": {"degrees": ["degree or above"], "majors": ["related disciplines"], "languages": ["english", "chinese"], "language_level": ["good command"], "hard_skills": ["dynamic", "hong kong employment ordinance", "ms office"], "soft_skills": ["detail-minded", "dynamic", "mature"], "languages_combined": [{"language": "english", "language_level": ["good command"]}, {"language": "chinese", "language_level": ["good command"]}]}, "experience_required": {"duration": ["1-2 years"], "field": ["sizable organization"]}}, {"job_id": "100003009051361", "location_code": "hk", "company": "Raze Technology Limited", "job_title": "Human Resources Officer (Recruitment Focus)", "description": "The Role\nTo cope with our aggressive growth and expansion plan, we are inviting high caliber individuals to join our fast growth team.\u00a0 You will have a chance to work at a fast-paced mission driven company that brings material science to life and benefit the mass.\u00a0 We are bringing business disruption and new hygiene standard to the world with the introduction of new photocatalyst products and services. With the continuous R&D and business innovation, we are thrilled to develop the next generation technology that safeguards everyday life.\u00a0\u00a0\n\nResponsibilities\n\nCommunicate and manage the recruitment requests of BUs/Hiring Managers;\nDevelop and manage recruitment process effectively from posting job advertisements, screening resumes, conducting interviews, confirming offer and recruitment project management;\nProvide end-to-end recruitment process to ensure hiring needs are fulfilled timely and effectively, support hiring managers to further develop and strengthen the talent pool;\nDevelop effective hiring channels and methodologies for recruitment pipeline;\nPrepare hiring tracking reports and liaise with hiring manager on the progress;\nPrepare HR reports and data analysis on staff turnover, retention, career development, etc;\nAssist in any other HR duties as assigned.\nRequirements\n\nDegree in Human Resources Management, Business Management or related disciplines;\nMinimum 3 years of solid recruiting experience in fast-paced business environment with proven expertise from FMCG or consumer healthcare market is a MUST;\nMature, self-motivated, ability to prioritize multiple tasks and work under pressure;\nStrong PC skills, well-versed in Microsoft applications and Chinese word processing\nImmediate available is highly preferred;\nFluent in written and spoken English, Cantonese and Mandarin.\nWe offer the right candidate attractive remuneration package and outstanding prospects for career advancement and development.\u00a0 The right candidate will progress career in a forward thinking and dynamic business with exciting growth plans.\u00a0 If you are qualified and interested, please send your full resume with current & expected salary and availability by clicking \"APPLY\".\n\nAll information collected will be treated as strictly confidential and used for recruitment purposes only. (Only shortlisted candidates will be notified)", "employment_types": ["Full Time", "Permanent"], "selling_points": [], "locations": ["Southern Area"], "categories": ["Admin & HR", "HR Supporting Staff", "Recruitment / Executive Search"], "post_time": "2022-01-15T11:09:02Z", "salary": {"currency": null, "max": null, "min": null, "period": "monthly", "term": null}, "salary_visible": false, "title_keywords": ["human resources officer"], "responsibilities": ["confirming offer", "recruitment project management", "advertisements", "hr reports", "hr duties", "develop", "data analysis", "screening resumes", "conducting interviews", "recruitment", "reports", "career development", "liaise with", "recruitment process", "tracking"], "requirements": {"degrees": ["degree"], "majors": ["related disciplines", "business"], "languages": ["cantonese", "english", "chinese", "mandarin"], "language_level": ["fluent"], "hard_skills": ["business management", "pc skills", "chinese word processing", "microsoft applications"], "soft_skills": ["self-motivated", "multiple tasks", "prioritize", "mature", "business environment", "work under pressure"], "languages_combined": [{"language": "cantonese", "language_level": ["fluent"]}, {"language": "english", "language_level": ["fluent"]}, {"language": "chinese", "language_level": []}, {"language": "mandarin", "language_level": ["fluent"]}]}, "experience_required": {"duration": ["minimum 3 years"], "field": ["healthcare", "business", "fmcg"]}}, {"job_id": "100003009051290", "location_code": "hk", "company": "Hutchison Telecommunications (Hong Kong) Limited", "job_title": "Senior / Human Resources Specialist (Talent Acquisition)", "description": "Reporting to the Senior HR Manager, talent acquisition function is responsible for supporting the overall strategic talent sourcing by providing market intelligence and direct sourcing strategies to identify and attract suitable candidates across different divisions and functions.\n\n\nResponsibilities:\n\nDirect source and engage talent through social media, networks, competitive intelligence and other innovative channels\nSet up direct candidate sourcing strategies and candidate outreach to fulfil current sourcing requirements and ongoing workforce plans\nWork closely with HRBP and line managers to ensure the understanding of sourcing requirements, and keep track on feedbacks, priorities and challenges to ensure sourcing effectiveness\nProactively develop and manage talent pipelines and databases for current and future business initiatives\nProvide and research for market intelligence and industry trends\nApply HR principles, concepts and industry practices in relation to HR initiatives and projects\nPrepare analytical reports and other ad hoc projects as assigned\n\nRequirements:\n\nA tertiary qualification ideally in HR discipline\nAt least 4 years\u2019 hands-on direct candidate sourcing experience in sizable company\nCapability on passive candidates\u2019 direct outreach, engagement and cultivation\nExcellent communication skills in English and Chinese\nStrong analytical skills, detail-minded, agile with positive mindset\n\nApart from competitive remuneration package and exciting opportunity for career development within the Group, we provide attractive employee benefits such as free company shuttle, free company SIM card and preferential SIM plan offers, comprehensive medical & insurance schemes, as well as full range of other employee well-being provisions.\u00a0\n\nInterested parties, please send in your profile with your salary expectation to connie.chong@ hthk.com\u00a0\n\nWe are an equal opportunity employer and welcome applications from all qualified candidates. Personal data collected will be treated in the strictest confidence and handled confidentially by authorised personnel for recruitment-related purposes only within the CK Hutchison Group of companies. The personal data of unsuccessful applicants will be destroyed after the recruitment exercise pursuant to the requirements of the Personal Data (Privacy) Ordinance in Hong Kong.", "employment_types": ["Full Time", "Permanent", "Temporary", "Contract"], "selling_points": [], "locations": ["Kwai Tsing Area"], "categories": ["Admin & HR", "Compensation & Benefits", "Recruitment / Executive Search", "Training & Development"], "post_time": "2022-01-15T07:19:00Z", "salary": {"currency": null, "max": null, "min": null, "period": "monthly", "term": null}, "salary_visible": false, "title_keywords": ["human resources specialist"], "responsibilities": ["social media", "business initiatives", "hr", "develop", "reports", "ad hoc projects", "databases", "plans"], "requirements": {"degrees": [], "majors": [], "languages": ["english", "chinese"], "language_level": ["excellent"], "hard_skills": ["agile", "analytical skills"], "soft_skills": ["detail-minded", "communication skills", "agile", "positive mindset", "analytical skills", "hands-on", "comprehensive"], "languages_combined": [{"language": "english", "language_level": ["excellent"]}, {"language": "chinese", "language_level": ["excellent"]}]}, "experience_required": {"duration": ["at least 4 years"], "field": []}}, {"job_id": "100003009051768", "location_code": "hk", "company": "Earth Products China Limited", "job_title": "Senior Human Resources & Administration Officer / Manager", "description": "Benefits\n\n12-day Annual Leave\n5-day Work Week, 9 am to 6 pm\nBank Holidays\nMedical Benefits\nDental Benefits\nFlat structure, Rewarding and Casual corporate culture\n\nResponsibilities\n\nResponsible for the full spectrum of HR functions including recruitment and retention, compensation & benefits, employee relations, training and development, performance management\nTo formulate and implement HR strategies\nPlanning, organizing, and controlling the activities and actions of the HR department\nProactively provide professional HR advice and support on HR issues, policies, and projects\nEnsure HR policies are in compliance with Hong Kong Labour Ordinance and local regulations\nLead a team in providing general office administration support\n\nRequirements\n\nDegree or diploma in human resources or related disciplines\n5-year experience in HR field with supervisory role preferred\nWell-versed in Employment Ordinance and other related legislation in Hong Kong\nHands on PC knowledge (MS Word, Excel, PowerPoint)\nExcellent communication & interpersonal skills\nGood\u00a0command of both oral and written English and Chinese\nImmediately available is highly preferred\nCandidate with more experience will be considered as HR Manager\n*All personal data provided will be used for recruitment purpose only", "employment_types": ["Full Time", "Permanent"], "selling_points": [], "locations": ["Kwai Hing"], "categories": ["Admin & HR", "HR Director / Manager", "Recruitment / Executive Search", "Training & Development"], "post_time": "2022-01-17T00:59:32Z", "salary": {"currency": null, "max": null, "min": null, "period": "monthly", "term": null}, "salary_visible": false, "title_keywords": ["administration officer", "manager", "human resources"], "responsibilities": [], "requirements": {"degrees": [], "majors": [], "languages": [], "language_level": [], "hard_skills": [], "soft_skills": [], "languages_combined": []}, "experience_required": {"duration": [], "field": []}}, {"job_id": "100003009054495", "location_code": "hk", "company": "\u5b8f\u5de5\u6709\u9650\u516c\u53f8", "job_title": "Administrative Assistant/ Officer", "description": "Office Location: Tsim Sha Tsui\n\nJob Description\n\nThe position is directed to Branch/ Division managers,\n\n1)\u00a0\u00a0\u00a0\u00a0\u00a0 Provide all-round secretarial and administrative support in a timely, accurate and complete manner, including but not limited to:\n\n-\u00a0\u00a0\u00a0\u00a0\u00a0\u00a0\u00a0\u00a0\u00a0 Assist in preparing presentation materials\n\n-\u00a0\u00a0\u00a0\u00a0\u00a0\u00a0\u00a0\u00a0\u00a0 Assist in planning team engagement activities as requested\n\n-\u00a0\u00a0\u00a0\u00a0\u00a0\u00a0\u00a0\u00a0\u00a0 Maintain good relationship with internal and external parties\n\n2)\u00a0\u00a0\u00a0\u00a0\u00a0 Pre-job and onboard arrangement to associates, including but not limited to:\n\n-\u00a0\u00a0\u00a0\u00a0\u00a0\u00a0\u00a0\u00a0\u00a0 Initiate and monitor recruitment schemes\n\n-\u00a0\u00a0\u00a0\u00a0\u00a0\u00a0\u00a0\u00a0\u00a0 Arrange meetings and appointments with candidates and managers\n\n-\u00a0\u00a0\u00a0\u00a0\u00a0\u00a0\u00a0\u00a0\u00a0 Assist in planning team engagement activities as requested\n\nJob Requirement\n\n-\u00a0\u00a0\u00a0\u00a0\u00a0\u00a0\u00a0\u00a0\u00a0 Degree in any discipline\n\n-\u00a0\u00a0\u00a0\u00a0\u00a0\u00a0\u00a0\u00a0\u00a0 2 years' experience or above\n\n-\u00a0\u00a0\u00a0\u00a0\u00a0\u00a0\u00a0\u00a0\u00a0 Proficient use of Microsoft Office/ Excel/ PowerPoint and other illustration tools\n\n-\u00a0\u00a0\u00a0\u00a0\u00a0\u00a0\u00a0\u00a0\u00a0 Very strong sense of responsibility\n\n-\u00a0\u00a0\u00a0\u00a0\u00a0\u00a0\u00a0\u00a0\u00a0 Efficient, detail and performance oriented\n\n-\u00a0\u00a0\u00a0\u00a0\u00a0\u00a0\u00a0\u00a0\u00a0 Independent and self-motivated\n\n-\u00a0\u00a0\u00a0\u00a0\u00a0\u00a0\u00a0\u00a0\u00a0 Good command of spoken and written Chinese (both Cantonese and Mandarin), and English", "employment_types": ["Full Time", "Permanent", "Contract"], "selling_points": ["5-day-work", "Considerable salary with development bonus", "Career path to Office Manager"], "locations": ["Tsim Sha Tsui"], "categories": ["Admin & HR", "Personal / Executive Assistant", "Recruitment / Executive Search", "Sales, CS & Business Devpt", "Sales Administration"], "post_time": "2022-01-17T09:47:28Z", "salary": {"currency": "HKD", "max": 19999, "min": 14000, "period": "monthly", "term": null}, "salary_visible": true, "title_keywords": ["administrative assistant", "officer"], "responsibilities": ["administrative support", "internal and external parties", "monitor", "maintain good relationship", "recruitment", "arrange meetings", "planning"], "requirements": {"degrees": ["degree"], "majors": [], "languages": ["cantonese", "english", "chinese", "mandarin"], "language_level": ["good command"], "hard_skills": ["excel", "illustration", "powerpoint", "microsoft office"], "soft_skills": ["efficient", "self-motivated", "independent", "sense of responsibility"], "languages_combined": [{"language": "cantonese", "language_level": ["good command"]}, {"language": "english", "language_level": ["good command"]}, {"language": "chinese", "language_level": ["good command"]}, {"language": "mandarin", "language_level": ["good command"]}]}, "experience_required": {"duration": ["2 years"], "field": []}}, {"job_id": "100003009051576", "location_code": "hk", "company": "Knight Recruitment Services Limited", "job_title": "Recruitment HR & Admin (Recent Graduate welcome!) Central, 5day!", "description": "Recruitment HR & Admin (Recent Graduate welcome!) Central, 5day!\n\nLocation: Central;\u00a05 day work!\u00a0\n\nKnight Recruitment is a boutique recruitment firm that provides customised staffing solutions to MNCs across the Asia Pacific. We are currently looking for a Recruitment HR & Admin (Recent Graduate Welcome to apply) to add to our growing team:\u00a0\n\nIf you are a cheerful, determined, result-driven person with passionate about people, a career at Knight could be just the move for you.\n\nWe offer a fun innovative working environment and a platform for you to grow and develop with excellent rewarding incentive scheme.\n\nAs a Recruitment HR & Admin (Researcher) your key duties are:\n\nProvide admin support to the small team\nMake Candidate profiles when required\nEstablish and maintain strong relationships with clients and candidates\nHandle recruitment assignments for the junior & middle positions\u00a0\nSource, shortlist and interview best suited candidates for required roles\nManage the job offer process, handling compensation negotiations with clients and candidates\nProvide career advisory services to candidates\nUpdate/Post latest job vacancies in different channels\nKeep abreast with market information, employment trends and industry knowledge\nWork as part of a team to achieve team goals and objectives\u00a0\n\nRequirements\n\nUniversity Graduate in any discipline with strong language skills with passion and ambition in recruitment industry. (Recent grad welcome!)\nFluent in English, Cantonese, Mandarin; both written and spoken\nPossess passion, enthusiasm and ambition to the recruitment industry\nMust be result driven, positive, self-motivated and able to work under pressure\nMust possess excellent client services and negotiation skills\nStrong computer skills in Word and Excel\nImmediate Available is an advantage\n\n5 day Work in Central, 8 minute walk from Central MTR Station. Excellent basic and rewarding incentive scheme.\u00a0\n\nFor more information, please email your\u00a0RESUME and Expected Salary\u00a0to bethany.lam@ knightrecruits.com \u00a0\u00a0\n\n\nData collected will be used for recruitment purposes only. Personal data provided by job applicants will be used strictly in accordance with the Personal Data (Privacy) Ordinance. We regret that only the shortlisted candidates will be notified.", "employment_types": ["Full Time", "Permanent"], "selling_points": ["5day work in Central, 8 min walk from Central MTR", "Recruitment HR & Admin, Recent Graduate welcome!", "Fun working friendly environment"], "locations": ["Central"], "categories": ["Sales, CS & Business Devpt", "Business Development", "Admin & HR", "Recruitment / Executive Search", "Marketing / Public Relations", "Marketing - General / Support"], "post_time": "2022-01-17T02:55:15Z", "salary": {"currency": null, "max": null, "min": null, "period": "monthly", "term": null}, "salary_visible": false, "title_keywords": ["hr", "admin"], "responsibilities": ["hr", "recruitment"], "requirements": {"degrees": [], "majors": [], "languages": [], "language_level": [], "hard_skills": [], "soft_skills": ["cheerful", "driven", "determined", "passionate about"], "languages_combined": []}, "experience_required": {"duration": [], "field": []}}, {"job_id": "100003009051906", "location_code": "hk", "company": "PwC", "job_title": "HR Transformation and Change Management Senior Manager", "description": "Job Description & Summary\n\nReporting to the PwC China Human Capital Strategy and Transformation CoE Lead, the HR Transformation and Change Management Lead is responsible for end-to-end implementation of the new target operating model and leading the change management work stream, proactively balancing scope, schedule, budget, risk, project team, outcomes, and benefits.\n\nKey responsibilities include:\n\nTarget Operating Model for the People Organisation\n\n\u2022With the high-level design of the future state Target Operating model confirmed, the HR Tranformation Project Lead will engage key stakeholders to design the detailed team structure, scope, roles and responsibilities of the future state HR teams.\n\n\u2022Leverage past HC transformation experience, leading practices, and connections with other PwC network firms to apply key learnings to develop implementation and workforce transition and change management plan to ensure a successful transformation\n\n\u2022Post implementation, conduct HR activity analysis and other satisfaction surveys to gather input on the impact and effectiveness of the new TOM model, and provide recommendations for further improvements to ensure maximum benefit realisation\n\nChange Management, Culture and Values\n\n\u2022Own and drive the change management strategy and plans for the continuous transformation of the People Organisation\n\n\u2022Work closely with key stakeholders to design change strategy and plan to implement key People Priorities\n\n\u2022Work with a small team to implement change management plans for key people priorities and provide advisory support to other people initiatives\n\n\u2022Design and implement ongoing initiatives to further promote the PwC Culture and Values and continue to drive the right behaviours\n\nWays of working\n\n\u2022Collaborate with key stakeholders (e.g. business and HC leadership) to understand business requirements and objectives\n\n\u2022Support HC Strategy and Transformation CoE Lead to coordinate the delivery of the end to end new target operating model\n\n\u2022Motivate and lead the project team with enthusiasm and drive team effectiveness\n\nRequirements\n\n\u202212+ years of experience in HR Transformation and Change Management, having implemented a new target operating model (operating model, structure, process, ways of working and governance) for one or more organizations\n\n\u2022Previous HR Transformation experience to include but not limited to: HR activity analysis, detailed HR organisation design, capability reviews, change management, and workforce transition planning\n\n\u2022Previous change management experience to include but not limited to: Stakeholder and change impact assessment, change management, communications, training and workforce transition plan design\n\n\u2022Flexible and capable to manage the end to end HR transformation workstreams in a complex global/territory capacity\n\n\u2022Ability to work with different levels of stakeholders to develop relationships, establish credibility and instill confidence\n\n\u2022Ability to identify and solve problems objectively using analysis, leading practices, and experience\n\n\u2022Excellent analytical, articulation, project management, and communication skills\n\n\u2022Prior experience and/or familiarity with agile strategies and some of the relevant HC technologies would be of benefit\n\n\u6709\u610f\u7533\u8acb\u8005\u8acb \u6309 APPLY NOW\u7533\u8acb\n\n", "employment_types": ["Full Time"], "selling_points": [], "locations": ["Not Specified"], "categories": ["Admin & HR", "HR Director / Manager", "Recruitment / Executive Search", "Management", "Top Executives (CEO, CFO, CTO, GM, MD etc.)"], "post_time": "2022-01-17T01:30:03Z", "salary": {"currency": null, "max": null, "min": null, "period": "monthly", "term": null}, "salary_visible": false, "title_keywords": ["senior manager", "hr"], "responsibilities": ["reporting", "change management", "hr", "budget", "teams", "implementation", "design", "develop", "analysis", "coordinate", "provide recommendations", "schedule", "plan", "plans"], "requirements": {"degrees": [], "majors": [], "languages": [], "language_level": [], "hard_skills": ["project management", "analysis", "agile"], "soft_skills": ["communication skills", "confidence", "capable", "agile", "solve problems", "project management", "organisation", "detailed"], "languages_combined": []}, "experience_required": {"duration": [], "field": ["management", "training", "hr", "design", "planning"]}}, {"job_id": "100003009054726", "location_code": "hk", "company": "AXA China Region Insurance Company Limited", "job_title": "Financial Consultant/ Management Trainee", "description": "Conqueror Team\u00a0/\u00a0Dare to Dream\u00a0\n\nWe are looking to partner up with success driven, strong and willing to conqueror challenges. If you are THE 1 and want to come out of your comfort zone and have growth\u00a0 JOIN US!!! We Will Welcome You With all our HEART!!!\u00a0\n\nJob Highlights\nFast track career path\nfrom HK$25,000 above + Quarterly AND Year-End Bonus\nWork-Life Balance\n\nJob Description\nPersonal GROWTH, understanding oneself better and others.\u00a0\nLearning from lots of experienced MANAGERS who have excel in this industry.\u00a0\nWorking together with the team to learn ways of making opportunities (cross- selling)Wealth management, Financial Planning, Fund investments, Retirement planning, Non-life commercial insurance etc.\u00a0\nMaintaining and providing services to the client to enhance the relation.\nThrough extensive training and experience building\u00a0your own BRAND and TEAM.\u00a0\u00a0\n\nRequirements\n\nBachelor\u2019s degree or above or Fresh graduates (will be considered)\u00a0\nInterpersonal skills, self-motivated, open-minded, eager to learn, crave for success, responsible\nFluent in English or Cantonese\u00a0\nMUST HAVE PERMANENT HKID or DEPENDENT VISA\n\nWe Offer\n\nOverseas trip incentives ( Rookies convention, Top Producers Convention etc)\u00a0\nAttractive allowance and high\u00a0\nSpecial Training ( both 1 on 1 and group trainings), comprehensive trainings to make you competitive in the market.\u00a0\nGet to learn from\u00a0experienced professional mentors.\u00a0\nShowing ways where to find opportunities and handling the client objections.\nTrain to be MDRT!! (million dollar round table)\n\nBenefits and packages\n\n\n5 Days working\u00a0\nfrom HK$25K above+ 4 Quarterly Bonus +1 Year End Bonus\nFREE Medical insurance\u00a0\nFlexible working hours\u00a0\nTrainings to prepare you to be THE FUTURE LEADER (CAREER DEVELOPMENT)\u00a0\nAbout us\nAXA Hong Kong\n\nAXA Hong Kong and Macau, a member of the AXA Group, prides itself on serving over 1.5 million customers1\u00a0with our superior products and services. AXA is the top-tier life insurer in Hong Kong with the longest history2. In addition to being the No. 1 global Property & Casualty commercial lines insurer3, we are the No. 1 most considered insurance brand in Hong Kong4. We are also one of the largest health protection providers in Hong Kong and Macau.\n\nAXA is one of the most diversified insurers, providing a full range of coverage for individual and commercial customers. We offer all-round, integrated solutions across Life, Health and Property & Casualty to address all of our customers\u2019 insurance needs. In keeping with our brand promise \u201cKnow You Can\u201d, AXA strives to be a lifelong partner to our customers by empowering them to achieve their goals and live better lives.\n\nIf you would like to know more about OUR TEAM do email us.", "employment_types": ["Full Time"], "selling_points": [], "locations": ["Kwun Tong"], "categories": ["Hospitality / F & B", "Others", "Admin & HR", "Recruitment / Executive Search", "Banking / Finance", "Asset Management"], "post_time": "2022-01-17T10:47:00Z", "salary": {"currency": null, "max": null, "min": null, "period": "monthly", "term": null}, "salary_visible": false, "title_keywords": ["management trainee", "consultant"], "responsibilities": ["management", "insurance", "maintaining", "planning"], "requirements": {"degrees": ["degree or above", "bachelor"], "majors": [], "languages": ["cantonese", "english"], "language_level": ["fluent"], "hard_skills": [], "soft_skills": ["self-motivated", "responsible", "open-minded", "eager to learn", "interpersonal skills"], "languages_combined": [{"language": "cantonese", "language_level": ["fluent"]}, {"language": "english", "language_level": ["fluent"]}]}, "experience_required": {"duration": [], "field": []}}, {"job_id": "100003009054243", "location_code": "hk", "company": "Social Big Data Limited", "job_title": "HR Executive / Senior HR Executive", "description": "Job responsibilities\n\nHandle full spectrum of HR functions including recruitment, C&B, performance management, employee relations and training\u00a0\nDevelop and execute HR initiatives and programs to support the business needs\nResponsible for HR data analysis and reports and ensure compliance are met in all HR areas\nAdminister monthly payroll, attendance and leave management, insurance and pension scheme, and tax returns\nParticipate in ad-hoc tasks and other HR related projects as required\nJob\u00a0Requirement\n\nDegree holder in\u00a0Business Administration/HR Management or related disciplines\nMinimum 3 years of HR & Admin experience\nMore relevant experience in will be considered as Senior HR Executive\nExcellent leadership with practical knowledge and strong problem-solving skills\nSound knowledge in HK Employment Ordinance and related regulations and laws\nSelf-motivated and proactive with good communication and interpersonal skills\nGood command of written and spoken English and Chinese\nShort notice period or immediate available is highly preferred\nCV without expected salary will not be considered\n\n", "employment_types": ["Full Time", "Permanent"], "selling_points": ["Minimum 3 years experience of working in HR", "All round HR & Admin experience", "5-day work week"], "locations": ["Kwun Tong"], "categories": ["Admin & HR", "Compensation & Benefits", "HR Supporting Staff", "Recruitment / Executive Search"], "post_time": "2022-01-17T08:57:31Z", "salary": {"currency": null, "max": null, "min": null, "period": "monthly", "term": null}, "salary_visible": false, "title_keywords": ["hr", "executive"], "responsibilities": ["tax", "attendance", "management", "hr", "ad-hoc tasks", "develop", "data analysis", "ensure compliance", "recruitment", "reports", "insurance", "payroll"], "requirements": {"degrees": ["degree holder"], "majors": ["related disciplines", "business administration"], "languages": ["english", "chinese"], "language_level": ["good command"], "hard_skills": ["problem-solving skills"], "soft_skills": ["self-motivated", "communication and interpersonal skills", "problem-solving skills", "proactive", "leadership"], "languages_combined": [{"language": "english", "language_level": ["good command"]}, {"language": "chinese", "language_level": ["good command"]}]}, "experience_required": {"duration": ["minimum 3 years"], "field": ["hr", "admin", "relevant experience"]}}, {"job_id": "100003009042347", "location_code": "hk", "company": "Don Nelson Recruitment Limited", "job_title": "Recruitment Consultant / Senior Recruitment Consultant - Mass Recruitment Team", "description": "We are an awarded recruitment agency and keep expanding, we are currently seeking for Senior Recruitment Consultant to expand our consultancy team. We provide competitive commission scheme plus quarterly incentive, training program and fun working environment. Are you passionate in joining a\u00a0dynamic, creative & energetic team? If you are looking for a challenging, target driven and well rewarded career, please submit your resume to us:\n\nResponsibilities:\n\nManage mass recruitment process from candidate sourcing, initial interview to on-boarding\nDeliver end-to-end recruitment procedure including business development of new clients & drive new opportunities in the fast-changing market\nFacilitate in negotiations between the client and candidate within the whole hiring process\nAchieve business target of the company and develop relationship with clients and candidates\n\nRequirements:\n\nStrong passion in Recruitment industry\nMin. 2 years experience in Recruitment industry with solid supervisory experience\nExperienced in mass volume recruitment and fast paced environment\nSolid client network and candidate sources\nMust be positive, energetic, independent and result-driven\nStrong communication and negotiation skills is required\nMore experience will be considered as Senior Recruitment Consultant\n\nPersonal data provided by job applicants will be used strictly in accordance with the employer's personal data policies and for recruitment purposes only.", "employment_types": ["Full Time", "Permanent"], "selling_points": ["Dynamic, creative & energetic team", "Competitive commission plus friendly environment", "Strong passion and solid experience in recruitment"], "locations": ["Sheung Wan"], "categories": ["Admin & HR", "Others", "Recruitment / Executive Search", "Sales, CS & Business Devpt", "Others"], "post_time": "2022-01-15T03:49:14Z", "salary": {"currency": null, "max": null, "min": null, "period": "monthly", "term": null}, "salary_visible": false, "title_keywords": ["recruitment consultant"], "responsibilities": [], "requirements": {"degrees": [], "majors": [], "languages": [], "language_level": [], "hard_skills": [], "soft_skills": [], "languages_combined": []}, "experience_required": {"duration": [], "field": []}}, {"job_id": "100003009051049", "location_code": "hk", "company": "The Wharf Group", "job_title": "Human Resources Assistant", "description": "provide recruitment and on boarding support in placement advertisement, response statistics and analysis, arranging interview and tests, on boarding arrangements and training courses enrollment and preparation as well as other ad hoc assignments\nDegree holders in HRM with at least one year relevant working experience, fresh graduates with good academic and communication skills are welcome\ngood basic knowledge on HK Employment Ordinance and other employment related ordinances\nresponsible, detail-minded, accurate and a team player\ngood spoken and written English and Chinese (please state your grade/level of English Language in HKCEE / HKDSE in your c.v.)\u00a0\nproficient in Microsoft Office and Putonghua\n\nWe work 5 days per week.\n\nInterested parties, please click \"APPLY NOW\" and attach with your application letter and full resume.\n\n\nFor further information of the Wharf Group, please visit our website: www.wharfholdings.com\u00a0", "employment_types": ["Full Time", "Permanent"], "selling_points": [], "locations": ["Tsim Sha Tsui"], "categories": ["Admin & HR", "Compensation & Benefits", "HR Supporting Staff", "Recruitment / Executive Search"], "post_time": "2022-01-15T19:11:46Z", "salary": {"currency": null, "max": null, "min": null, "period": null, "term": null}, "salary_visible": false, "title_keywords": ["human resources assistant"], "responsibilities": ["enrollment", "analysis", "communication", "recruitment", "ad hoc assignments", "arranging interview"], "requirements": {"degrees": ["degree", "hkdse"], "majors": [], "languages": ["putonghua", "english", "chinese"], "language_level": ["proficient", "good"], "hard_skills": ["analysis", "c", "basic", "microsoft office"], "soft_skills": ["detail-minded", "communication skills", "responsible", "team player", "accurate"], "languages_combined": [{"language": "putonghua", "language_level": ["proficient"]}, {"language": "english", "language_level": ["good"]}, {"language": "chinese", "language_level": ["good"]}]}, "experience_required": {"duration": ["at least one year"], "field": ["relevant working experience"]}}, {"job_id": "100003009054733", "location_code": "hk", "company": "AXA China Region Insurance Company Limited", "job_title": "MANAGEMENT ASSOCIATE/ FINANCIAL MANAGER", "description": "\u00a0KNOW YOU CAN!!!\n\nWe are looking to partner up with success driven, strong and willing to conqueror challenges. If you are THE 1 and want to come out of your comfort zone and have growth\u00a0 JOIN US!!! We Will Welcome You With all our HEART!!!\u00a0\n\n\nJob Description\nPersonal GROWTH, understanding oneself better and others.\u00a0\nLearning from lots of experienced MANAGERS who have excel in this industry.\u00a0\nWorking together with the team to learn ways of making opportunities (cross- selling)Wealth management, Financial Planning, Fund investments, Retirement planning, Non-life commercial insurance etc.\u00a0\nThrough extensive training and experience building\u00a0your own BRAND and TEAM.\u00a0\u00a0\n\nRequirements\n\n\nBachelor\u2019s degree or above or Fresh graduates (will be considered)\u00a0\nInterpersonal skills, self-motivated, open-minded, eager to learn, crave for success, responsible\n\nWe Offer\n\nOverseas trip incentives ( Rookies convention, Top Producers Convention etc)\u00a0\nSpecial Training ( both 1 on 1 and group trainings), comprehensive trainings to make you competitive in the market.\u00a0\nGet to learn from\u00a0experienced professional mentors.\u00a0\nShowing ways where to find opportunities and handling the client objections.\nTrain to be MDRT!! (million dollar round table)\n\nBenefits and packages\n\n\n5 Days working\u00a0\nfrom HK$25K above+ 4 Quarterly Bonus +1 Year End Bonus\nFREE Medical insurance\u00a0\nFlexible working hours\u00a0\nTrainings to prepare you to be THE FUTURE LEADER (CAREER DEVELOPMENT)\n\n\n", "employment_types": ["Full Time"], "selling_points": [], "locations": ["Kwun Tong"], "categories": ["Banking / Finance", "Financial Services", "Admin & HR", "Recruitment / Executive Search", "Asset Management"], "post_time": "2022-01-17T10:48:50Z", "salary": {"currency": null, "max": null, "min": null, "period": "monthly", "term": null}, "salary_visible": false, "title_keywords": ["management associate", "financial manager"], "responsibilities": ["management", "insurance", "planning"], "requirements": {"degrees": ["degree or above", "bachelor"], "majors": [], "languages": [], "language_level": [], "hard_skills": [], "soft_skills": ["self-motivated", "responsible", "open-minded", "eager to learn", "interpersonal skills"], "languages_combined": []}, "experience_required": {"duration": [], "field": []}}, {"job_id": "100003009051291", "location_code": "hk", "company": "Hutchison Telecommunications (Hong Kong) Limited", "job_title": "Human Resources Manager", "description": "Being a prominent player in the communications industry and a member of CK Hutchison Holdings, we are looking for HR practitioners who have genuine interest in helping an organization and the peoples within, to grow and succeed.\u00a0 Depending on your strengths and career orientation, here is a chance to develop in our HR Team, commensurate with your experiences and potentials.\n\nCheck out the followings. Let us know your strengths and interests to contribute in our evolution journey.\n\nDiscover Yourself\nAttributes that will earn your early success here\n\n\neager to learn and grow\nwilling to share and contribute\nkeen to raise new ideas and different perspectives\nready to take up new challenges\n\nDiscover Your Job Opportunities\nUnleash your potential and stay ahead! Here you can...\n\nperform a BP role for individual career development i.e. staffing, talent acquisition, employee caring & engagement, training & development, and/or HR analytics, etc.\nliaise with business units and provide advices on all staffing matters (e.g. manpower requirements, staffing needs, etc)\u00a0\nwork closely with team members to deliver excellent HR services while enriching HR functional skills through involvement in projects\ngain cross HR functional exposures to build up networking and holistic knowledges, say in talent sourcing, staff activities, job evaluation, total rewards exercises, etc.\nbe a resilient individual ready to take up challenges in a dynamic yet rewarding industry for next career advancement\n\nDiscover More\nApart from the unique opportunity to fast track your career here, you will enjoy competitive remuneration package, attractive employee benefits such as free company shuttle, free company SIM card and preferential SIM plan offers, comprehensive medical & insurance schemes, as well as full range of other employee well-being provisions.\u00a0\u00a0\n\nInterested parties, please send\u00a0in your profile and salary expectation to connie.chong@ hthk.com\n\nWe are an equal opportunity employer and welcome applications from all qualified candidates. Personal data collected will be treated in the strictest confidence and handled confidentially by authorised personnel for recruitment-related purposes only within the CK Hutchison Group of companies. The personal data of unsuccessful applicants will be destroyed after the recruitment exercise pursuant to the requirements of the Personal Data (Privacy) Ordinance in Hong Kong.", "employment_types": ["Full Time", "Permanent"], "selling_points": [], "locations": ["Kwai Tsing Area"], "categories": ["Admin & HR", "Compensation & Benefits", "Recruitment / Executive Search", "Training & Development"], "post_time": "2022-01-15T07:19:00Z", "salary": {"currency": null, "max": null, "min": null, "period": "monthly", "term": null}, "salary_visible": false, "title_keywords": ["manager", "human resources"], "responsibilities": ["provide advices", "ideas", "evaluation", "hr", "develop", "plan", "career development", "liaise with", "insurance"], "requirements": {"degrees": [], "majors": [], "languages": [], "language_level": [], "hard_skills": ["dynamic"], "soft_skills": ["keen", "unique", "eager to learn", "dynamic", "comprehensive", "genuine"], "languages_combined": []}, "experience_required": {"duration": [], "field": ["hr", "team"]}}, {"job_id": "100003009054087", "location_code": "hk", "company": "Hong Kong Sports Institute Ltd", "job_title": "HUMAN RESOURCES ASSISTANT (APPOINTMENT)", "description": "THE JOB\n\nReporting to the Human Resources Officer (Appointment), the Human Resources Assistant (Appointment) will be responsible for the following duties:\nProvide administration support in recruitment and appointment related matters such as advertisement preparation, interview arrangement, work visa application/extension, contract renewal, annual appraisal exercise, training and development programme;\nMaintain and update personnel records in HRIS;\nAssist in annual staff cost budget;\nPrepare financial statistics and reports;\nAssist in ad-hoc/regular project; and\nPerform any other appropriate duties as assigned by supervisor.\nTHE REQUIREMENTS\nApplicants should have: (1) a minimum of 5 passes in HKCEE or 5 HKDSE subjects with at least Level 2 or equivalent, including English, Chinese and Mathematics; or (2) any post secondary qualification;\nPossess certificate/ diploma in human resources management or related discipline;\nStrong knowledge and application in Employment Ordinance, MPF regulations and other related legislations;\nStrong in numeracy and good communication skills;\nGood command of both spoken and written English and Chinese.\u00a0 Ability to speak Putonghua is an advantage; and\nProficient in HRIS system and MS-Excel.\n\n[Applicants who have responded to the previous advertisements need not re-apply. Their applications are being considered accordingly.]\n\n\n\n\nAPPLICATIONS\n\nPlease send the completed\u00a0Application Form\u00a0with indication of expected salary to\u00a0The Human Resources Manager, Hong Kong Sports Institute Ltd, 25 Yuen Wo Road, Sha Tin, New Territories\u00a0or\u00a0email:\u00a0hrdept@ hksi.org.hk\u00a0on or before 23 January 2022. Please quote reference no.\u00a0JD-20220110-HRA(APPOINTMENT) in the application.\nAppointment will be on a fixed term contract. General information is available at the website http://www.hksi.org.hk.\u00a0\nApplicants who are not invited for interview within six months may consider their applications unsuccessful.\nAll applications will be treated in the strictest confidence. Personal Data provided by appointees will be used strictly for recruitment and other employment-related purposes only.\n\n\n\nTHE HKSI IS AN EQUAL OPPORTUNITIES EMPLOYER\u00a0", "employment_types": ["Full Time", "Contract"], "selling_points": [], "locations": ["Shatin Area"], "categories": ["Admin & HR", "Others", "HR Supporting Staff", "Recruitment / Executive Search"], "post_time": "2022-01-17T08:21:26Z", "salary": {"currency": null, "max": null, "min": null, "period": "monthly", "term": null}, "salary_visible": false, "title_keywords": ["human resources assistant"], "responsibilities": ["ad-hoc", "reporting", "cost", "personnel records", "budget", "maintain", "recruitment", "reports", "interview arrangement", "administration"], "requirements": {"degrees": ["certificate", "diploma", "hkdse"], "majors": ["mathematics"], "languages": ["putonghua", "english", "chinese"], "language_level": ["advantage", "good command"], "hard_skills": ["no", "ms-excel", "hksi", "mpf regulations"], "soft_skills": ["communication skills", "confidence"], "languages_combined": [{"language": "putonghua", "language_level": ["advantage"]}, {"language": "english", "language_level": ["good command"]}, {"language": "chinese", "language_level": ["good command"]}]}, "experience_required": {"duration": [], "field": []}}, {"job_id": "100003009053013", "location_code": "hk", "company": "HR Plus Limited", "job_title": "Business Development Executive (Channel Sales, SaaS) - 25k", "description": "Highlights:\n\nExcellent Career Exposure & Opportunity\nUnlimited annual leave\nMedical covers\u00a0dependent\nAttractive medical benefit\nAbout the company:\n\nAbout HR Plus:\n\nHR Plus is an award-winning Employer Engagement firm in Hong Kong that works with the world\u2019s leading businesses to provide Employee Benefit Programmes which are designed to promote employees\u2019 wellness and help clients reduce costs associated with absenteeism, and staff turnover.\n\nOur vision is to build a better workplace in the future of work.\n\nOur purpose is to make a positive difference in employee lives. HR Plus continues to enhance our services and make our products accessible and affordable to more individuals. Making smile on your face\u2013 that\u2019s what we want to see.\n\nAbout the Role:\nMake constant improvements to the respective Partner Programs based on measurement data.\nIdentify and source partnership opportunities through various channels such as inbound lead follow-ups, emails, client visits, and attend exciting events .\nGo through demo with partners and direct users and track the progress of each lead through our sales funnel.\nDevelop and maintain positive relationships with partners.\nWork closely with the Marketing team to offer co-branding activities to selected partners.\nDeliver a great experience to our partners when working together - you will represent our brand, and be our partners' liaison internally.\nRequirements:\n\nDegree or above\nPassionate on relationship building\nPossess good communication and interpersonal skills\nExcellent spoken Cantonese and English, Mandarin is an advantage\nTo apply:\n\nInterested parties please click Apply Now to apply job.\nAll personal data collected will be kept under strictly confidential and will be only used for recruitment purpose.", "employment_types": ["Full Time", "Permanent", "Freelance"], "selling_points": ["Unlimited annual leave", "Healthy work life balance", "Promising Internal promotion opportunity"], "locations": ["Not Specified"], "categories": ["Admin & HR", "Recruitment / Executive Search", "Sales, CS & Business Devpt", "Channel / Distribution", "E-commerce", "Business Development"], "post_time": "2022-01-17T05:04:00Z", "salary": {"currency": "HKD", "max": 24999, "min": 17000, "period": "monthly", "term": null}, "salary_visible": true, "title_keywords": ["sales", "business development executive"], "responsibilities": ["data", "hr", "measurement", "develop", "communication", "maintain", "costs"], "requirements": {"degrees": ["degree or above"], "majors": [], "languages": ["cantonese", "english", "mandarin"], "language_level": ["advantage", "excellent"], "hard_skills": ["make", "plus", "go"], "soft_skills": ["passionate", "communication and interpersonal skills", "positive"], "languages_combined": [{"language": "cantonese", "language_level": ["excellent", "advantage"]}, {"language": "english", "language_level": ["advantage"]}, {"language": "mandarin", "language_level": ["advantage"]}]}, "experience_required": {"duration": [], "field": ["brand"]}}, {"job_id": "100003009050179", "location_code": "hk", "company": "Everlink HR Consulting Limited", "job_title": "Associate Consultant/ Recruitment Consultant", "description": "Responsibilities:\n\nResponsible\u00a0for recruiting front line and back office roles in FMCG, Biotech industry\nPerform business development by identifying new opportunities with the potential clients\u00a0and actively introduce the recruitment services to them\nDrive the recruitment process for the clients by actively sourcing talents\u00a0\nPerform interviews & selection process for candidates, manage and organize the internal information resources\nMaintain a close relationship with existing clients by providing professional hiring solution\n\nRequirements:\n\nDegree holder in any discipline\nMotivated, energetic and result-driven\nGood communication and interpersonal skills, and a team player\nExcellent communication and interpersonal skills and equip the ability to interact with people of all levels\nAble to multi-task and work under pressure", "employment_types": ["Full Time", "Permanent"], "selling_points": ["Recruitment process and service", "Business development with clients", "Aggressive and result oriented"], "locations": ["Not Specified"], "categories": ["Sales, CS & Business Devpt", "Business Development", "Admin & HR", "Recruitment / Executive Search", "Account Servicing"], "post_time": "2022-01-14T09:54:33Z", "salary": {"currency": null, "max": null, "min": null, "period": "monthly", "term": null}, "salary_visible": false, "title_keywords": ["recruitment consultant", "associate", "consultant"], "responsibilities": ["recruitment process", "maintain", "recruitment", "back office"], "requirements": {"degrees": ["degree holder"], "majors": [], "languages": [], "language_level": [], "hard_skills": [], "soft_skills": ["multi-task", "motivated", "communication and interpersonal skills", "team player", "energetic", "driven", "work under pressure"], "languages_combined": []}, "experience_required": {"duration": [], "field": []}}, {"job_id": "100003008209430", "location_code": "hk", "company": "Centaline Financial Services Limited", "job_title": "Recruitment & Training Assistant", "description": "Responsibilities:\n\nGenerate content for marketing & recruitment purposes;\nManage recruitment platforms and arrange recruitment interviews;\nFollow up with new recruit;\nPlan training schedule and manage the new members;\nManage and assist in all projects and tasks as assigned;\nProvide human resources support to the sales team.\n\n\u00a0Requirements:\n\n\nDiploma or above;\nMinimum 3 years of experience preferably in training or front-line business functions with Insurance or banking sector;\nFluent Cantonese and English;\nFamiliar with MS Office application (Word, Excel & Power Point);\nFamiliar with Photoshop is an advantage;\nResponsible, detail-minded & self-motivated;\nAble to work independently.\n\n\u00a0We Offer:\n\nConvenient working location: Tsim Sha Tsui;\n5 days working (9:30 A.M. - 6:00 P.M.);\nSalary with high performance bonus;\nMedical Insurance;\nPublic Holiday.\n\nWe offer 5-day work and an attractive package to the right candidate. Interested parties please send your resume with current and expected salary to us.\n(All applications received will be treated in strict confidence and solely for recruitment purpose.)", "employment_types": ["Full Time", "Permanent"], "selling_points": ["Training & Recruitment", "Insurance or Banking sector", "Min 3 years of experience preferably in training"], "locations": ["Tsim Sha Tsui"], "categories": ["Banking / Finance", "Others", "Admin & HR", "Recruitment / Executive Search", "Training & Development"], "post_time": "2022-01-15T03:49:15Z", "salary": {"currency": null, "max": null, "min": null, "period": "monthly", "term": null}, "salary_visible": false, "title_keywords": ["assistant"], "responsibilities": ["sales team", "recruitment", "schedule", "plan"], "requirements": {"degrees": ["diploma or above"], "majors": [], "languages": ["cantonese", "english"], "language_level": ["fluent"], "hard_skills": ["excel", "word", "power point", "ms office", "photoshop"], "soft_skills": ["detail-minded", "self-motivated", "work independently", "responsible"], "languages_combined": [{"language": "cantonese", "language_level": ["fluent"]}, {"language": "english", "language_level": ["fluent"]}]}, "experience_required": {"duration": ["minimum 3 years"], "field": ["business", "banking sector", "training", "insurance"]}}, {"job_id": "100003009049028", "location_code": "hk", "company": "Kerry Properties (H.K.) Limited", "job_title": "Officer, Talent Acquisition (Contract Role)", "description": "What You'll Do\n\nYou'll be responsible for full life-cycle recruitment which includes but not limited to searching, attracting, screening, interviewing and hiring suitable talent by using creative sourcing methods. You will play a critical role in ensuring that we are hiring the best suitable talent and representing KPL as employer of choice in the marketplace.\n\nSome of your responsibilities include:\n\nWork with hiring managers to analyze job requirements and provide market insight as a truly talent acquisition advisor to the business\nManage recruiting materials and job posting through various recruiting channels\nConduct proactive search for qualified candidates by using social media, database, referrals etc.\nConduct interviews and assess applicants' relevant knowledge, skills, experience and aptitudes\nArrange and coordinate interviews for hiring managers\nEnsure the communication with candidates throughout recruitment process is transparent and consistent at all stages.\nAct as a brand ambassador for KPL and help the business to develop a pool of qualified candidates in advance of need\nBuild networks to find qualified passive candidates\nBe technological savvy, utilize internet, social media and new ways of working to source candidates\nProvide analytically and well documented recruiting reports and continuously thrive for process excellence\nBuild long-term successful relationship with Hiring Managers and candidates\nProvide support on corporate and ad hoc projects as required\n\nWho You'll Work With\n\nWorking with HRBPs and CoE Talent Acquisition team, you will play a critical role in communicating with internal stakeholders and candidates to fulfill the hiring needs.\n\nWho You Are\n\nYou are a professional with the ability to understand our business strategy and key competencies of the internal positions.\n\nYou would have the following competencies and professional experiences:\n\nPossesses a minimum of 3\u00a0years work experience in end-to-end recruitment, preferably experience in Property Management / bulk recruitment, be a field specialist in talent acquisition and staying on top of the profession, keep up market trend and talent landscape\nBe a KPL's ambassador at all stages of a recruitment process by presenting a professional brand that reflects the quality and values expected of a KPL's employee\nResult driven when working under pressure and tight schedules\nDevelops solutions through working creatively and thinking out of the box in order to fulfill the hiring needs\nNegotiates effectively with internal stakeholders or candidates, ensure best outcomes that are good for all parties\nTechnologically savvy - continuously keep up new recruitment technology to streamline workflows and improve process excellence\nPersonally accountable and be open-minded for feedback\nMature, independent and able to communicate effectively in both English and Chinese", "employment_types": ["Contract"], "selling_points": ["Top-tier Property Developer", "Contract Role", "Competitive Compensation Package"], "locations": ["Quarry Bay"], "categories": ["Admin & HR", "Recruitment / Executive Search"], "post_time": "2022-01-14T07:57:02Z", "salary": {"currency": null, "max": null, "min": null, "period": "monthly", "term": null}, "salary_visible": false, "title_keywords": ["officer"], "responsibilities": ["social media", "provide support", "develop", "coordinate", "communication", "communicating with", "reports", "ad hoc projects", "database", "recruitment process"], "requirements": {"degrees": [], "majors": [], "languages": ["english", "chinese"], "language_level": [], "hard_skills": [], "soft_skills": ["under pressure", "independent", "open-minded", "accountable", "mature", "driven"], "languages_combined": [{"language": "english", "language_level": []}, {"language": "chinese", "language_level": []}]}, "experience_required": {"duration": ["minimum of 3 years"], "field": ["management", "recruitment"]}}, {"job_id": "100003009042699", "location_code": "hk", "company": "Deliveroo Hong Kong Limited", "job_title": "Recruitment Coordinator", "description": "Why Deliveroo?\n\nWhy Deliveroo? When you first think about Deliveroo, you probably think of getting great food to your house in less than half an hour. Awesome right? But behind the scenes is the real story. This story is one of high growth, huge challenges and an enormous opportunity ahead of us.\n\nWe want to be the definitive food company - the app you go to any time you have a hunger pang. We are transforming the way people think about food. We\u2019re a technology driven company at the forefront of the most rapidly expanding industry in the world, so come and join us for the ride.\n\nWhat you\u2019ll be doing:\n\nYou\u2019ll partner with the APAC recruitment team and hiring managers to ensure a best-in-class candidate experience\nYou\u2019ll need to be super organised and be able to juggle conflicting diaries & priorities across the recruitment team and hiring managers\nYou\u2019ll be solution-driven and be happy to share ideas on how we can do things better and more efficiently - you\u2019ll be able to own these projects to see them become a reality!\nIn a nutshell, you\u2019ll be scheduling interviews, organising travel as well as tracking interviewer load, interviewer onboarding, managing recruitment agencies, arranging debriefs and managing our applicant tracking system.\n\nSkills you\u2019ll need:\n\nYou\u2019ll be naturally organised: do you love planning things with friends and family? Are you the one who\u2019s pulling everyone together and suggesting dates, times and locations?\nYou\u2019ll be comfortable managing a high volume of requests: our will come from recruiters, hiring managers and candidates\nYou should look beyond day to day activity and suggest/ implement process improvements both in the recruitment team and the hiring process.\nYou\u2019ll be able to prioritise across multiple tasks with a focus on time and expectation management and to take a self-starting approach to your day\nStrong communication skills as you\u2019ll be working closely with our candidates to give them a great experience and to create a seamless recruitment process for our hiring managers/interviewers\nFluency in English and spoken Cantonese is required.\u00a0\n\nIf you have experience with an ATS, that would be beneficial. We use Greenhouse at Deliveroo.\n\nBenefits\u00a0\n\nFree delivery on Deliveroo platform\n15 days Annual Leave\nFree Friday Lunch - Deliveroo\u2019s to the office of course!\nLate-night meal allowance\nWell stocked Pantry food + drinks\n\"Fun Friday\" outgoing event every month\nGroup Medical Insurance\nMonthly gym subsidy\n\nLife at Deliveroo\n\nWe are a growing team, with very large impact, seeking to answer some of the most interesting questions out there. We move fast, we\u2019re always looking for new ideas and we\u2019re very transparent about the decisions we make and why we make them.\n\nThere are so many questions we need to answer and plenty more we haven\u2019t even encountered. How do data and technology help restaurants to grow as consumer habits change? How can we predict what someone wants to order for dinner long before the idea has even crossed their mind? At Deliveroo these are just some of the tough problems we are solving - and there is no challenge that cannot be yours. No solution is owned by a particular team, which means the scope for growth and personal impact is enormous.\n\nDiversity and Inclusion\n\nAt Deliveroo we know people are the heart of the business and we prioritise their welfare. We offer a wide range of competitive benefits in areas including health, family, finance, community, convenience, growth, time away and relocation.\n\nIn 2018 we announced our decision to give every employee equity in the company. We did this because we wanted all of our employees, regardless of location, level or role to be owners and because we believe that this is the right thing to do. We believe this helps build a culture where everyone is committed and able to share in the company\u2019s success.\n\nWe believe a great workplace is one that represents the world we live in and how beautifully diverse it can be. That means we have no judgement when it comes to any one of the things that make you who you are - your gender, race, sexuality, religion or a secret aversion to coriander. All you need is a passion for (most) food and a desire to be part of one of the fastest growing start-up\u2019s around.\n\nApply now to continue the conversation.", "employment_types": ["Full Time", "Permanent"], "selling_points": ["Partner with the APAC recruitment team", "Scheduling interviews, manage agencies", "Fun and energetic young team"], "locations": ["Central"], "categories": ["Admin & HR", "Personal / Executive Assistant", "HR Supporting Staff", "Recruitment / Executive Search"], "post_time": "2022-01-12T08:26:13Z", "salary": {"currency": null, "max": null, "min": null, "period": "monthly", "term": null}, "salary_visible": false, "title_keywords": ["coordinator"], "responsibilities": [], "requirements": {"degrees": [], "majors": [], "languages": [], "language_level": [], "hard_skills": ["go"], "soft_skills": [], "languages_combined": []}, "experience_required": {"duration": [], "field": []}}, {"job_id": "100003009051735", "location_code": "hk", "company": "Estate Agents Authority", "job_title": "ADMINISTRATIVE ASSISTANT (Human Resources) (Ref No.: EAA-2022/01)", "description": "Key Responsibilities\nThe incumbent will be posted to the Human Resources Section to handle the following:\nprovide administrative support for various human resources services, including recruitment, on-boarding and off-boarding, payroll preparation, tax reporting, MPF contributions, group medical insurance scheme, personal file management, attendance record management, leave record management etc.\nassist in the daily administrative duties within the Section\nperform ad-hoc duties as assigned\nRequirements\nA recognized university degree preferably in Human Resources or relevant discipline\nAt least 2 years\u2019 relevant work experience\nProficiency in PC operation, Word, Excel, PowerPoint etc\nFluency in English and Chinese and basic knowledge of Putonghua preferred\nMature personality, customer-oriented and be able to communicate with people of all levels\nMeticulous, analytical and can work independently under pressure\nTerms of Appointment\nCompetitive remuneration package commensurate with the selected candidate\u2019s qualifications and experience will be offered. The appointee will initially be offered a 3-year contract, subject to renewal upon satisfactory performance and the service needs of the Authority.\nApplication Procedure\nApplications with full resume indicating your current and expected salaries and your public examination results should be sent to: Human Resources Section, Estate Agents Authority, 7/F, E-Trade Plaza, 24 Lee Chung Street, Chaiwan, Hong Kong or via email by clicking \"Apply Now\"\u00a0not later than\u00a024 January 2022. Please mark \u201cPrivate and Confidential\u201d on the envelope and quote the post applied for and its reference number on the envelope.\nCandidates who are not invited to attend an interview within 6 weeks from the closing date may assume their applications unsuccessful. Applications may be considered for other suitable positions within the Authority. All applications will be treated in strict confidence. Personal data provided in the applications will only be used for recruitment-related purposes. All information on non-shortlisted applicants will be destroyed after 6 months.\u00a0\n\n\nWE ARE AN EQUAL\u00a0OPPORTUNITIES EMPLOYER", "employment_types": ["Full Time", "Permanent", "Contract"], "selling_points": [], "locations": ["Chai Wan"], "categories": ["Admin & HR", "Compensation & Benefits", "HR Supporting Staff", "Recruitment / Executive Search"], "post_time": "2022-01-16T21:51:17Z", "salary": {"currency": null, "max": null, "min": null, "period": "monthly", "term": null}, "salary_visible": false, "title_keywords": ["administrative assistant", "human resources"], "responsibilities": ["tax", "reporting", "attendance", "management", "mpf", "recruitment", "administrative duties", "insurance", "ad-hoc duties", "provide administrative support", "payroll", "file management"], "requirements": {"degrees": ["university degree"], "majors": [], "languages": ["putonghua", "english", "chinese"], "language_level": ["fluency", "basic"], "hard_skills": ["excel", "basic", "word", "powerpoint", "pc"], "soft_skills": ["meticulous", "work independently", "confidence", "under pressure", "mature", "customer-oriented"], "languages_combined": [{"language": "putonghua", "language_level": []}, {"language": "english", "language_level": ["fluency", "basic"]}, {"language": "chinese", "language_level": ["fluency", "basic"]}]}, "experience_required": {"duration": ["at least 2 years"], "field": []}}, {"job_id": "100003009052039", "location_code": "hk", "company": "HKT Services Limited", "job_title": "Human Resources Manager", "description": "Your role\n\nThe HR Partner/Manager is a role reporting to the HR VP. \u00a0You will act as a trusted partner to the business unit leadership team in all areas of HR including talent development, workforce planning, change management and retention to achieve a high performance culture. You will coach leaders around people strategies and support the strategic direction of the HR function. You need to have the capability to influence and gain credibility with leaders and managers that you may support, build relationships and their trust. You are a technical expert in the area of HR, able to provide effective advice on all matters of the employee life cycle and are comfortable working at the operational and strategic levels.\n\u00a0\n\nTo succeed in this role\n\nExcellent client relationship management skills.\n\n10 years of proven HR experience in HRBP / Generalist roles\n\nWorked in a matrixed organizational environment, across multiple business units.\n\nProject/Program management experience.\n\nExcellent communication and interpersonal skill.\n\nBachelor degree in Human Resources Management or equivalent", "employment_types": ["Full Time", "Permanent"], "selling_points": ["HRBP", "TA", "C&B"], "locations": ["Quarry Bay"], "categories": ["Admin & HR", "Compensation & Benefits", "HR Director / Manager", "Recruitment / Executive Search"], "post_time": "2022-01-17T01:55:04Z", "salary": {"currency": null, "max": null, "min": null, "period": null, "term": null}, "salary_visible": false, "title_keywords": ["manager", "human resources"], "responsibilities": ["reporting", "management", "change management", "hr", "communication", "planning"], "requirements": {"degrees": ["degree", "bachelor"], "majors": [], "languages": [], "language_level": [], "hard_skills": [], "soft_skills": ["communication", "organizational", "leadership", "interpersonal skill"], "languages_combined": []}, "experience_required": {"duration": ["10 years"], "field": ["hr", "management"]}}, {"job_id": "100003009037664", "location_code": "hk", "company": "Wai Yuen Tong Medicine Co Ltd", "job_title": "Senior HR Officer (Recruitment)", "description": "Job Role\n\n\nManage the full spectrum of Human Resources functions including but not limited to recruitment, C&B, team member movement, employee relations according to our corporate guideline\u00a0and operations objectives.\nExecute recruitment and selection process starting from job posting to staff appointment. Work closely with department heads on the manpower and hiring plan.\nOversee and manage people strategies, including talent development, employee communications, manpower planning, performance management and other HR projects\nPlan and execute HR initiatives on employee engagement\nConduct regular review on HR practice and procedure to ensure they are compliance with local legislation\nWorking as a strategic business partner to the line management.\u00a0\n\nRequirements:\n\nUniversity graduate in Human Resources Management, Business Administration or relevant discipline\nMinimum 6 years of relevant work experience in sizeable companies; with exposure in pharmaceutical manufacturer is definitely an advantage\nWell versed in Hong Kong Labor Ordinance and related regulations\nMature, flexible and able to work under pressure\nAble to work independently and meet tight deadlines\nGood command in both spoken and written English and Chinese\nCandidate with more experience will be considered as Assistant HR Manager\nWork location: Yuen Long\n\nInterested parties please send\u00a0full resume\u00a0with present and expected salary\u00a0to Human Resources Department by clicking\u00a0\"APPLY NOW\".\n\n\u00a0(All personal data provided by applicants will be treated in strict confidence and used for employment-related purpose only.)", "employment_types": ["Full Time", "Permanent"], "selling_points": ["Recruitment focus", "Mature, independent & proactive", "Strong sense of responsibility & detail-minded"], "locations": ["Yuen Long"], "categories": ["Admin & HR", "Compensation & Benefits", "HR Supporting Staff", "Recruitment / Executive Search"], "post_time": "2022-01-15T03:49:12Z", "salary": {"currency": null, "max": null, "min": null, "period": "monthly", "term": null}, "salary_visible": false, "title_keywords": ["hr officer"], "responsibilities": ["administration", "regulations", "management", "work under pressure", "operations", "hr", "compliance", "regular review", "recruitment", "plan", "human resources functions", "planning"], "requirements": {"degrees": ["university graduate"], "majors": ["business administration"], "languages": ["english", "chinese"], "language_level": ["good command"], "hard_skills": [], "soft_skills": ["flexible", "work independently", "meet tight deadlines", "mature", "team member", "work under pressure"], "languages_combined": [{"language": "english", "language_level": ["good command"]}, {"language": "chinese", "language_level": ["good command"]}]}, "experience_required": {"duration": ["minimum 6 years"], "field": ["hr"]}}, {"job_id": "100003009051023", "location_code": "hk", "company": "The Wharf Group", "job_title": "Assistant Human Resources Manager (Talent Acquisition)", "description": "The incumbent will\u00a0be involved in talent acquisition, e-performance management, employee engagement and CSR reports preparation consolidation.\u00a0\u00a0The ideal candidates\u00a0should be / possess :\n\nDegree holders in Human Resources Management or related disciplines preferred with grade C or above in English Language (Syl. B) of HKCEE or A Level Examination\n6 - 8 years\u2019 relevant experience gained at sizable organizations with exposure/experience in e-recruitment and e-performance management would be advantageous\u00a0\nsound knowledge on HK Employment Ordinance and other employment related ordinances\na team player with strong common sense, positive attitude and excellent integrity\nproactive,\u00a0organized, responsible, detail-minded and able to deliver timely and quality work under pressure and tight deadlines\ngood communication and presentation skills and highly proficient in written and spoken English and Chinese\nproficient in Excel and other Microsoft Office applications\n\nCandidates with less experience will be considered as Human Resources Officer / Senior Officer.\n\nWe work 5 days per week.\n\nInterested parties, please click \"APPLY NOW\" and attach with your application letter and full resume.\n\nFor further information of the Wharf Group, please visit our website: www.wharfholdings.com\u00a0", "employment_types": ["Full Time", "Permanent"], "selling_points": [], "locations": ["Tsim Sha Tsui"], "categories": ["Admin & HR", "Compensation & Benefits", "HR Supporting Staff", "Recruitment / Executive Search"], "post_time": "2022-01-15T01:13:31Z", "salary": {"currency": null, "max": null, "min": null, "period": null, "term": null}, "salary_visible": false, "title_keywords": ["assistant human resources manager"], "responsibilities": ["management", "quality", "communication", "recruitment", "reports", "work under pressure"], "requirements": {"degrees": ["degree"], "majors": ["related disciplines"], "languages": ["english", "chinese"], "language_level": ["proficient", "good"], "hard_skills": ["excel", "c", "microsoft office"], "soft_skills": ["detail-minded", "organized", "responsible", "work under pressure", "timely", "integrity", "positive attitude", "communication", "presentation skills", "team player", "proactive", "ideal"], "languages_combined": [{"language": "english", "language_level": ["proficient", "good"]}, {"language": "chinese", "language_level": ["proficient", "good"]}]}, "experience_required": {"duration": ["6 - 8 years"], "field": ["recruitment", "performance management", "relevant experience", "human resources"]}}, {"job_id": "100003009044849", "location_code": "hk", "company": "SearchAsia Hong Kong", "job_title": "Talent Acquisition Specialist", "description": "The Role\n\nThe core asset of a successful organization is its employees. At Recruit Express, we are in an expansion phase to strengthen our organization by hiring the best talent out there. \u00a0We\u2019re seeking to bring in a Talent Acquisition Specialist that would be a key enabler for this growth.\u00a0\n\nThe talent acquisition specialist would be the key conduit to identify the right talent by applying effective recruitment methodologies, and aligning hiring decisions with organizational goals.\u00a0 You will also be providing input into the overall hiring strategy of the organization to ensure the staffing needs of the company are being met with a long-term talent strategy in mind.\n\nThis role requires a candidate with excellent communication and interpersonal skills as you\u2019ll often be working closely with leaders across different departments in Singapore and beyond in the region.\n\nA Career Path That Is Both Meaningful And Growth-Oriented\n\nOf all the things that can boost emotions, motivation, and purpose during a workday, the single most important is making progress in meaningful work.\n\nWe pride ourselves on our team culture where leaders/mentors are invested in your career growth and we celebrate everyone\u2019s successes. As we continue our international expansion, there are unparalleled opportunities for growth \u2013 meaning that you will never stay stagnant.\n\nIndeed, you will find yourself constantly learning and growing with us. Isn\u2019t there anything more meaningful than such career growth?\n\nJob Responsibilities:\n\n\nDevise and implement sourcing strategies to build pipelines of potential applicants, such as employer branding initiatives\u00a0\nManage the applicant flow, promote employee referrals, and use your creativity to effectively position our brand to attract talents.\nIdentify potential candidates using a variety of sourcing channels, including social media and LinkedIn\nCreate and implement end-to-end candidate hiring\u00a0processes to ensure a positive experience\nInterview and assess potential candidates on their personality fit, culture fit and abilities.\nForm close relationships with hiring managers to ensure clear candidate/interviewer expectations\nImprove and guide new hires through the on-boarding program\nOrganize company events and participate in campus outreach\nJob Requirements:\n\nMin. Degree in HR Management / Business Administration / Arts / Humanities\n1 to 3 years of relevant experience\nExcellent written, communication and negotiation skills\nOpen to new knowledge and carry a willingness to learn and adapt\nGood observation skills and attention to details\nGood social media management skills\nAbout Us\n\n\nSince 1996, Recruit Express has placed highly-qualified professionals at many Fortune 500 companies in Asia and around the world. From recruiting to on-boarding, our clients enjoy a process-driven, human-centric approach to recruiting and access to a network of top-tier professionals.\n\nFor the past 20 years, we have enjoyed phenomenal growth. The Recruit Express Group of Companies is a valuable member of the publicly listed HRnetGroup on the Singapore Stock Exchange (SGX: CHZ). At present, we have close to 1,000 employees in the Asia region operating in 13 large cities, and place out more than 40,000 contractor employees every year.\n\nThe heartbeat of Recruit Express lies in our highly enthusiastic and driven business leaders and recruiters, who are motivated to make a difference in their own career as well as the careers of others. It is our people who had shaped the organisation\u2019s culture as a vibrant, nurturing and highly collaborative environment. We celebrate every small win and personal milestone of our people every day.\n\nInterested to find out more about the RE journey and be part of our heartbeat? Connect with us now!", "employment_types": ["Full Time", "Permanent"], "selling_points": ["Meaningful and growth-oriented career", "Opportunity to work in a Singapore-listed company", "Regional Exposure"], "locations": ["Tsim Sha Tsui"], "categories": ["Admin & HR", "Compensation & Benefits", "HR Supporting Staff", "Recruitment / Executive Search"], "post_time": "2022-01-13T06:27:33Z", "salary": {"currency": null, "max": null, "min": null, "period": "monthly", "term": null}, "salary_visible": false, "title_keywords": ["specialist"], "responsibilities": ["social media"], "requirements": {"degrees": ["degree"], "majors": ["business administration", "humanities"], "languages": [], "language_level": [], "hard_skills": ["small", "make", "exchange"], "soft_skills": ["collaborative", "communication", "negotiation skills", "motivated", "attention to details", "enthusiastic", "organisation", "driven"], "languages_combined": []}, "experience_required": {"duration": ["1 to 3 years"], "field": ["relevant experience"]}}, {"job_id": "100003009047620", "location_code": "hk", "company": "ICO Limited", "job_title": "Talent Acquisition Officer", "description": "Responsibilities:\n\n\n\nWork with various hiring managers to identify recruitment needs and to develop effective recruitment strategy;\nAble to source qualified candidates through a wide variety of channels;\nHandle full set of recruitment cycle from screening & interviewing to closure of offers;\nEducate candidates on the career growth potential and compensation philosophy;\nConduct professional conversations with hiring managers and candidates about feedback during the recruitment process in a timely manner;\nShare meaningful market data, employment trends and industry knowledge with hiring managers;\nUtilize the functionality of the candidate tracking system and maintain data integrity and controls; and\nWork as part of the HR and Admin Team to achieve company goal and objectives.\n\nRequirements:\n\n\nDiploma / Degree holder with any disciplines;\nMinimum 2 years of\u00a0solid\u00a0IT recruitment experience\u00a0in a fast-paced, in-house environment is essential.\nAbility to develop creative and diverse sourcing strategies, including use of technology and market mapping;\nExperience of end-to-end recruitment from interviewing to managing offer process up to middle levels of positions;\nMust be result driven, highly-motivated and able to work under pressure with a can-do attitude;\nOutstanding interpersonal skill and ability to build strong relationship with candidates;\nPrior experience in handling sensitive/confidential information; and\nFluent in English and Chinese, both written and spoken.\nLess experience will be considered as Talent Acquisition Assistant.\n\nIf interested, please send your detailed resume with\u00a0availability, current and expected salary\u00a0to us.\u00a0 All information provided will be treated in strict confidential and used solely for recruitment purposes.\n\nAll resumes will be retained for a period of two years for recruitment purpose only in accordance with the Company\u2019s Privacy Policy.", "employment_types": ["Full Time", "Permanent"], "selling_points": ["Passion in developing career in Talent Acquisition", "Handle end-to-end recruitment process", "Exposure in diversified IT recruitment projects"], "locations": ["Kwun Tong"], "categories": ["Admin & HR", "Recruitment / Executive Search"], "post_time": "2022-01-14T03:35:35Z", "salary": {"currency": null, "max": null, "min": null, "period": "monthly", "term": null}, "salary_visible": false, "title_keywords": ["officer"], "responsibilities": ["hr", "a timely manner", "develop", "recruitment strategy", "recruitment", "maintain data", "recruitment process", "market data", "tracking"], "requirements": {"degrees": ["diploma", "degree holder"], "majors": ["any disciplines"], "languages": ["english", "chinese"], "language_level": ["fluent"], "hard_skills": [], "soft_skills": ["can-do attitude", "detailed", "interpersonal skill", "diverse", "motivated", "sensitive", "creative", "driven", "work under pressure"], "languages_combined": [{"language": "english", "language_level": ["fluent"]}, {"language": "chinese", "language_level": ["fluent"]}]}, "experience_required": {"duration": ["minimum 2 years"], "field": ["it", "recruitment"]}}, {"job_id": "100003009047468", "location_code": "hk", "company": "Harbour City Estates Ltd", "job_title": "SENIOR HUMAN RESOURCES OFFICER", "description": "The successful candidate will be responsible for the provision of quality Human Resources services including recruitment & selection, compensation & benefits, planning and organizing employee wellbeing programmes and statistical reporting as well as participating in other Human Resources initiatives/projects as assigned.\n\nApplicants should be University graduate in Human Resources Management or related disciplines, with at least 7 years\u2019 relevant experience in sizable companies.\u00a0 The ideal candidate should be attentive, precise, independent with strong planning, organizing and communication skills in both written and spoken English and Chinese.\u00a0 Conversance with HK Labour Ordinance and good PC literacy in Windows applications are prerequisites. \u00a0\n\nWe offer competitive salary package that will be commensurate with experience and qualifications.\u00a0 Interested parties are invited to send full resume stating contact telephone number, date available, present and expected salary to our recruitment email address.\n\n(Personal data provided will be used strictly in accordance with the Company\u2019s personal data policy which is available upon request.)", "employment_types": ["Full Time", "Permanent"], "selling_points": ["Responsible for the provision of HR Services", "Participating in other Human Resources initiatives", "At least 7 years\u2019 relevant experience"], "locations": ["Tsim Sha Tsui"], "categories": ["Admin & HR", "Compensation & Benefits", "HR Supporting Staff", "Recruitment / Executive Search"], "post_time": "2022-01-15T03:49:45Z", "salary": {"currency": null, "max": null, "min": null, "period": null, "term": null}, "salary_visible": false, "title_keywords": ["senior human resources officer"], "responsibilities": ["reporting", "management", "quality", "communication", "recruitment", "planning"], "requirements": {"degrees": ["university graduate"], "majors": ["related disciplines"], "languages": ["english", "chinese"], "language_level": [], "hard_skills": ["pc", "sizable companies"], "soft_skills": ["attentive", "communication skills", "independent", "responsible", "precise", "ideal"], "languages_combined": [{"language": "english", "language_level": []}, {"language": "chinese", "language_level": []}]}, "experience_required": {"duration": ["at least 7 years"], "field": ["related", "management", "relevant experience", "human resources"]}}, {"job_id": "100003009047792", "location_code": "hk", "company": "Shun Hing Electric Service Centre Limited", "job_title": "Assistant Human Resources Officer", "description": "Responsibilities:\n\nHandle full spectrum of recruitment activities\u00a0such as job posting, conduct interview and on-board arrangement\nCoordinate, monitor and evaluate internal/external training programmes and maintain accurate training records\nAssist in preparing reports, agenda and minutes\nParticipate in organizing company functions and recreation activities\nProvide support in daily HR operations and administrative work\n\n\u00a0Requirements:\n\nDegree in Human Resources Management\nFamiliar with employment related ordinance and HR Practice\nProficient in MS Word and Excel\nGood communication and interpersonal skills\nSelf-motivated and attentive to details\nWorking experience preferred but fresh graduates are also welcome\nIELTS Score 6.5 or above preferable\n\nInterested parties please send full resume stating the\u00a0expected salary & date of availability.\n\nData collected will be used for recruitment purpose only. It may be transferred to other companies of the Group to see if suitable vacancies arise. Applicants not contacted within 6 weeks may consider their applications unsuccessful. The information will be destroyed.", "employment_types": ["Full Time", "Permanent"], "selling_points": [], "locations": ["Kwai Fong"], "categories": ["Admin & HR", "HR Supporting Staff", "Recruitment / Executive Search"], "post_time": "2022-01-14T03:54:37Z", "salary": {"currency": null, "max": null, "min": null, "period": "monthly", "term": null}, "salary_visible": false, "title_keywords": ["assistant human resources officer"], "responsibilities": ["provide support", "administrative work", "operations", "hr", "monitor", "coordinate", "evaluate", "maintain", "recruitment", "preparing reports"], "requirements": {"degrees": ["degree"], "majors": [], "languages": [], "language_level": [], "hard_skills": ["excel", "ms word"], "soft_skills": ["self-motivated", "communication and interpersonal skills", "attentive to details"], "languages_combined": []}, "experience_required": {"duration": [], "field": []}}, {"job_id": "100003009048144", "location_code": "hk", "company": "Isshin Group Holdings Company Limited", "job_title": "Human Resources Officer", "description": "Responsibilities\n\nResponsible for HR functions including but not limited to talent acquisitions, contract management, reporting, C&B, etc\nProvide one-stop recruitment services from screening, shortlisting, interviewing, and on / off boarding\nExplore different recruitment channels and evaluate the effectiveness such as advertising, social media, recruitment day\nFormulate and implement recruitment strategies & initiatives to attract talents\nAssist in HR policies and procedures formulation and execution\nAssist in other ad hoc projects as assigned\n\nRequirements\n\nProfessional qualifications in HR and/or any related disciplines\n2+ years\u2019 experience preferably in F&B industry\nFamiliar with HK Employment Ordinance and related regulations\nGood communication and\u00a0interpersonal skills\nMulti-tasking, pro-active\u00a0and with can-do-attitude\nProficient\u00a0in MS Word, PowerPoint, and Excel\nImmediate available is highly preferred\u00a0\n\nAll data collected will only be used for recruitment purposes.", "employment_types": ["Full Time"], "selling_points": ["Fast Growing F&B Group", "Career Development Opportunity", "Immediate Available Preferred"], "locations": ["Sheung Wan"], "categories": ["Hospitality / F & B", "Food & Beverage", "Admin & HR", "HR Supporting Staff", "Recruitment / Executive Search"], "post_time": "2022-01-14T05:19:23Z", "salary": {"currency": null, "max": null, "min": null, "period": "monthly", "term": null}, "salary_visible": false, "title_keywords": ["human resources officer"], "responsibilities": ["reporting", "social media", "advertising", "policies", "hr", "procedures", "contract management", "evaluate", "recruitment", "ad hoc projects"], "requirements": {"degrees": [], "majors": [], "languages": [], "language_level": [], "hard_skills": ["ms word", "excel", "powerpoint", "professional qualifications"], "soft_skills": ["multi-tasking", "communication and interpersonal skills", "can-do", "pro-active"], "languages_combined": []}, "experience_required": {"duration": ["2+ years"], "field": ["f&b"]}}, {"job_id": "100003009051660", "location_code": "hk", "company": "Tung Wah Group of Hospitals", "job_title": "Human Resources Manager (Appointments Unit I)/ Admin. Headquarters [REF: SHRM(P)1/HRM(AI)/JOBS]", "description": "Location: Sheung Wan\n\nRoles & responsibilities:\n\nLead an appointment unit to manage the corporate human resources matters pertaining to community services in Tung Wah including manpower planning, pay review, recruitment and appointment as well as staff discipline and complaints;\ndevelop and implement human resources policies to meet the corporate objectives and service needs;\nundertake regular review of personnel administration system and procedures as well as assigned ad hoc projects/tasks to cope with changing needs;\nprovide executive support to the secretarial office of the Human Resources Committee; and\nundertake ad hoc projects and other general administrative duties including management of departmental business, supervision of staff and organization of meetings.\n\nThe ideal candidate should possess:\n\nA recognized degree or equivalent, preferably human resources management;\nat least Grade D in English Language (Syllabus B) and Chinese Language in the HKCEE or equivalent;\nat least 4 years\u2019 post-qualification administration experience, preferably human resources management/public administration;\nproficiency in English and Chinese; and\ngood communication and interpersonal skills.\n\n(Please specify in the application form the HKCEE result and relevant working experience you have attained in detail.)\n\nCompensation & employment terms:\n\nThe successful candidate will initially be offered a 3-year contract with a remuneration package which will be commensurate with his/her background and experience.\u00a0 The continuation of employment and employment terms thereafter will be subject to mutual agreement.\u00a0 Apart from contributions to the MPF Scheme, other benefits include paid annual leave, medical services, a dental scheme and training sponsorships.\u00a0 The incumbent will normally work under a 5-day week schedule subject to operational needs and exigencies of the service.\n\nApplication:\n\nPlease send your resume and a completed application form [F601(n)] with indication of your current and expected salaries to the Head of Human Resources Division, Tung Wah Group of Hospitals at 4/F., Wong Fung Ling Memorial Building, 12 Po Yan Street, Hong Kong by 20 January\u00a02022.\u00a0 Application forms are obtainable in person or can be downloaded from http://www.tungwah.org.hk.\u00a0 The reference code should be marked both in the letter and on the envelope.\u00a0\u00a0Underpaid mail items will not be accepted by Tung Wah.\u00a0 For proper delivery of your mail items, please ensure your mail items bear sufficient postage with return address before posting.\u00a0 Personal data provided by applicants will be used strictly for recruitment purpose only and in accordance with the Tung\u00a0Wah\u2019s personal data policy.\u00a0 Applicants not invited to attend an interview by 30 April 2022 may assume that their applications are unsuccessful.\n\nWE ARE AN EQUAL OPPORTUNITIES EMPLOYER", "employment_types": ["Full Time"], "selling_points": [], "locations": ["Sheung Wan"], "categories": ["Admin & HR", "Compensation & Benefits", "Recruitment / Executive Search", "Public / Civil", "Social Services - Community / Non-profit Organization"], "post_time": "2022-01-16T21:50:34Z", "salary": {"currency": null, "max": null, "min": null, "period": "monthly", "term": null}, "salary_visible": false, "title_keywords": ["admin. headquarters", "manager", "human resources"], "responsibilities": ["administration", "management", "policies", "review", "procedures", "executive support", "develop", "regular review", "communication", "recruitment", "ad hoc projects", "administrative duties", "planning"], "requirements": {"degrees": ["degree"], "majors": [], "languages": ["english", "chinese"], "language_level": ["proficiency"], "hard_skills": ["wan"], "soft_skills": ["communication and interpersonal skills", "ideal"], "languages_combined": [{"language": "english", "language_level": ["proficiency"]}, {"language": "chinese", "language_level": ["proficiency"]}]}, "experience_required": {"duration": ["at least 4 years", "3-year"], "field": ["management", "post-qualification", "relevant working experience", "human resources", "administration"]}}, {"job_id": "100003009048804", "location_code": "hk", "company": "Chandler Macleod Group (HK) Limited", "job_title": "Specialist, Human Resources", "description": "Duties:\n\nBe responsible for all recrutiment activities in EMEA, and support the Head of HR to provide HR services to all staff in Hong Kong and overseas offices\nUtilize various recruitment channels to source qualified candidates and maintain a candidate pipeline\nDeveloping hiring strategies and procedures in line with industry trends\nWork closely with management on all diversity initiatives involving recruitment to ensure fairness in hiring practices\nOwn the end-to-end recruitment process (From demand identification to candidate verbal acceptance)\nLiaise with various stakeholders to fully understand recruitment needs and work closely throughout the process to help create and update job descriptions on various recruitment portals\nCoordinate interviews and support throughout the interview process\n\nRequirements:\n\nMinimum 5 years of experience as HR Generalist or Recruitment focused in EMEA regions\nGood to have recruitment experience in other countries as well\nStrong understanding and hands-on experience with the full lifecycle recruitment process in EMEA regions\nStrong interpersonal, communication, organisational and stakeholder management skills\nTeam player with strong collaboration skills, credibility, and ability to gain buy-in and commitment from others\nFluent in written and spoken English\nProficient in Microsoft Office, Teams, Excel, and Outlook", "employment_types": ["Full Time", "Permanent"], "selling_points": ["Global exposure", "Talent Acquisition and business partner", "Flexible working hours"], "locations": ["Not Specified"], "categories": ["Admin & HR", "Administration / Operation Manager", "HR Director / Manager", "Recruitment / Executive Search"], "post_time": "2022-01-14T07:21:04Z", "salary": {"currency": null, "max": null, "min": null, "period": "monthly", "term": null}, "salary_visible": false, "title_keywords": ["specialist", "human resources"], "responsibilities": ["management", "hr", "procedures", "developing", "coordinate", "maintain", "recruitment", "liaise with", "recruitment process"], "requirements": {"degrees": [], "majors": [], "languages": ["english"], "language_level": ["fluent"], "hard_skills": ["excel", "outlook", "microsoft office"], "soft_skills": ["focused", "communication", "hands-on", "team player", "interpersonal"], "languages_combined": [{"language": "english", "language_level": ["fluent"]}]}, "experience_required": {"duration": ["minimum 5 years"], "field": ["recruitment", "hr generalist"]}}, {"job_id": "100003009047895", "location_code": "hk", "company": "Links International", "job_title": "Campus Recruiter | MNC", "description": "Key Accountabilities\n\n\n\nWorking closely with the Campus Operations Manager to understand graduate demand and business requirements\nAssist the Client and Campus Operations Manager to develop the selection strategy for each role/scheme recruited and agree the recruitment strategy with hiring manager\nManage client presence at target universities, ensuring at all times we are getting value for money out of the agreements and our listings are positioned for maximum effectiveness; measure and own the reporting on response rates\nActively coach and up-skill Graduate Program Managers and hiring managers in best practice talent acquisition, assessment and selection techniques.\nScheduling of screening interviews and assessment centres in collaboration with Client Recruiter and inviting and confirming candidates using the ATS candidate database.\nResponsibility for preparing all necessary interview and assessment centre paperwork and ensuring this is provided to interview managers ahead of scheduled interview day.\nCo-lead the recruitment processes for the Graduate and Summer Intern programs, including providing effective selection methodologies to ensure a diverse pipeline of young talent and providing effective on-boarding processes\nBuild a good understanding of client's business and skills required by candidates to succeed within it\nBuild collaborative relationships with hiring managers and manage issues, and escalate as required\n\nSkills and Requirement:\n\n\n\nBachelor degree is required\nExperience of Campus recruiter, recruitment in RPO, Corporate or agency recruitment is preferred\nUnderstanding of the Campus Recruitment life cycle and calendar would be desirable\nSkilled at developing and delivering end-to-end campus recruitment strategies to meet client requirements. Experience of using recruitment technology and recruitment databases.\nCantonese and/or Mandarin language skills would be highly advantageous, but not essential", "employment_types": ["Full Time", "Permanent"], "selling_points": ["Campus recruitment exp is a must", "up to 60K based on experience", "Excellent communication in English and Chinese"], "locations": ["Not Specified"], "categories": ["Admin & HR", "Recruitment / Executive Search"], "post_time": "2022-01-14T04:10:02Z", "salary": {"currency": null, "max": null, "min": null, "period": "monthly", "term": null}, "salary_visible": false, "title_keywords": [], "responsibilities": ["reporting", "operations", "developing", "develop", "recruitment strategy", "scheduling", "recruitment", "database", "databases"], "requirements": {"degrees": ["degree", "bachelor"], "majors": [], "languages": ["cantonese", "mandarin"], "language_level": [], "hard_skills": ["ats", "scheme", "databases"], "soft_skills": ["diverse", "collaborative"], "languages_combined": [{"language": "cantonese", "language_level": []}, {"language": "mandarin", "language_level": []}]}, "experience_required": {"duration": [], "field": ["agency", "recruitment"]}}, {"job_id": "100003009050513", "location_code": "hk", "company": "Manpower Services (Hong Kong) Limited", "job_title": "Recruitment Consultant / Trainee/ Recruiter (Fresh Grad Welcome)", "description": "We are expanding our Information Technology Team and looking for talents who are passionate about recruitment to join us. You will be joining a team of energetic talents and work closely together.\u00a0\n\nExcellent Career Path\nWell-structured and comprehensive\u00a0on-the-job Training programs\nDevelop interpersonal and\u00a0communication skills\n\nThe Job\u00a0\u00a0\n\nConduct\u00a0search, CV screening and application\u00a0filrtering\nResponsible for all stages of the recruitment cycle for both candidate and client side\nProvide advisory and industry knowledge with candidates and clients\nUnderstand client requirements and provide one-stop recruitment solutions\n\nWho will Qualify\u00a0\u00a0\n\nBachelor's Degree / Higher Diploma / Diploma or above\u00a0\nPossess good communication and interpersonal skills\nExcellent communication skills in English, Cantonese and Mandarin\u00a0\nImmediate available is preferred", "employment_types": ["Permanent"], "selling_points": ["Good career prospect", "5-day work", "Welcome Fresh Graduate"], "locations": ["Wan Chai"], "categories": ["Admin & HR", "Recruitment / Executive Search"], "post_time": "2022-01-14T10:36:07Z", "salary": {"currency": null, "max": null, "min": null, "period": "monthly", "term": null}, "salary_visible": false, "title_keywords": ["recruitment consultant", "trainee"], "responsibilities": ["communication", "cv screening", "recruitment", "develop"], "requirements": {"degrees": ["diploma", "degree", "bachelor", "diploma or above"], "majors": [], "languages": ["cantonese", "english", "mandarin"], "language_level": ["excellent"], "hard_skills": [], "soft_skills": ["communication skills", "responsible", "comprehensive", "communication and interpersonal skills", "structured", "energetic", "interpersonal", "passionate about"], "languages_combined": [{"language": "cantonese", "language_level": ["excellent"]}, {"language": "english", "language_level": ["excellent"]}, {"language": "mandarin", "language_level": ["excellent"]}]}, "experience_required": {"duration": [], "field": []}}, {"job_id": "100003009045976", "location_code": "hk", "company": "Bluebell Hong Kong Limited", "job_title": "Temporary Human Resources Recruiter (3.5 Months Maternity Cover)", "description": "Key Responsibilities:-\nConduct full cycle recruitment activities \u2013 drafting job ads, screening CV\u2019s, recruitment, selection\nManaging the process through interview to offer stage\nProvide support in onboarding and off boarding\nPerform data entry and prepare regular reports\nTo assist various HR initiatives and projects, other ad-hoc tasks\n\n\u00a0\u00a0Other Requirements:-\n\nDiploma or above in Human Resources Management or related discipline\nOrganized and detail-oriented\nFamiliar with Excel (pivot table and vlookup functions) and Powerpoint\nWith a minimum of 1 years\u2019 relevant experience is preferred\nGood command of both Chinese & English\nEmployment Period: End of January 2022 \u2013 April 2022\n\n\u00a0We offer excellent career opportunities, attractive remuneration and generous fringe benefits to the successful candidates. Interested parties, please send your full resume\u00a0with current and expected salary\u00a0via email to\u00a0recruit.hk @bluebellgroup.com\u00a0for interview or Whatsapp us at 6823 8860.\n\n(All personal data collected will be used for recruitment purpose only.)", "employment_types": ["Temporary"], "selling_points": ["Temporary", "Human Resources", "Recruitment"], "locations": ["Quarry Bay"], "categories": ["Admin & HR", "Recruitment / Executive Search"], "post_time": "2022-01-13T09:17:37Z", "salary": {"currency": null, "max": null, "min": null, "period": "hourly", "term": null}, "salary_visible": false, "title_keywords": ["human resources"], "responsibilities": ["provide support", "data entry", "hr", "ad-hoc tasks", "recruitment", "reports"], "requirements": {"degrees": ["diploma or above"], "majors": [], "languages": ["english", "chinese"], "language_level": ["good command"], "hard_skills": ["excel", "pivot table", "vlookup", "powerpoint"], "soft_skills": ["organized", "detail-oriented"], "languages_combined": [{"language": "english", "language_level": ["good command"]}, {"language": "chinese", "language_level": ["good command"]}]}, "experience_required": {"duration": ["minimum of 1 years"], "field": ["relevant experience"]}}, {"job_id": "100003009050798", "location_code": "hk", "company": "United Christian Nethersole Community Health Service", "job_title": "Human Resources Officer", "description": "Responsibilities:\n\nProvide full spectrum of human resources support including but not limited to recruitment, payroll administration, compensation and benefits, performance management, training and staff relations;\nAble to manage monthly payroll, final payment and related calculation via system independently;\nAssist in reviewing and formulating HR policies and procedures;\nEnsure compliance with employment and related legislations;\nPrepare and maintain documentation and reports from staff onboarding to offboarding; and\nOpportunities to participate in ad hoc projects as assigned.\n\nRequirements:\n\nDiploma or Degree holder in Human Resources or related disciplines;\nMinimum 4-5 years\u2019 relevant experience with exposure in NGO will be an advantage but not a must;\nWell-versed in Hong Kong Employment Ordinance;\nDetail-minded, self-motivated and demonstrates ability to work independently and contributes as a strong team player;\nExcellent problem-solving, communication and organizational skills;\nExcellent command of both spoken and written English and Chinese;\nProficiency in MS Word, Excel and Chinese word processing;\nImmediate available is preferred;\nCandidate with more experience may be considered for a more senior role\n\nStaff Benefits:\n\nRegular Sunday and Public Holidays off\n14 to 18 days\u2019 annual leave entitlement\nMedical benefits to staff and dependent\nOn-the-job training and training sponsorship & study leave\n\nInterested parties please send full resume with last and expected salary to Human Resources Unit, United Christian Nethersole Community Health Service, L1, KEC Administrative Building, No. 2 Po Ning Lane, Hang Hau, Tseung Kwan O with job reference no. marked on the envelope or by clicking \"Apply Now\"\n\n(Applicants not invited for interview within 4 weeks from the closing date may consider their applications unsuccessful. All personal data collected will be treated in strict confidence and will only be used for recruitment related purpose.)", "employment_types": ["Full Time", "Contract"], "selling_points": [], "locations": ["Tseung Kwan O"], "categories": ["Admin & HR", "Compensation & Benefits", "Recruitment / Executive Search", "Training & Development"], "post_time": "2022-01-14T11:25:26Z", "salary": {"currency": null, "max": null, "min": null, "period": "monthly", "term": null}, "salary_visible": false, "title_keywords": ["human resources officer"], "responsibilities": ["management", "policies", "hr", "procedures", "ensure compliance", "payment", "recruitment", "reports", "ad hoc projects", "maintain documentation", "payroll", "legislations", "administration"], "requirements": {"degrees": ["diploma", "degree holder"], "majors": ["related disciplines"], "languages": ["english", "chinese"], "language_level": ["excellent", "proficiency"], "hard_skills": ["excel", "chinese word processing", "hong kong employment ordinance", "problem-solving", "ms word"], "soft_skills": ["detail-minded", "organizational skills", "self-motivated", "work independently", "problem-solving", "communication", "team player"], "languages_combined": [{"language": "english", "language_level": ["excellent"]}, {"language": "chinese", "language_level": ["excellent", "proficiency"]}]}, "experience_required": {"duration": ["minimum 4-5 years"], "field": ["relevant experience"]}}, {"job_id": "100003009051354", "location_code": "hk", "company": "Raze Technology Limited", "job_title": "Human Resources Manager", "description": "The Role\nTo cope with our aggressive growth and expansion plan, we are inviting high caliber individuals to join our fast growth team.\u00a0 You will have a chance to work at a fast-paced mission driven company that brings material science to life and benefit the mass.\u00a0 We are bringing business disruption and new hygiene standard to the world with the introduction of new photocatalyst products and services. With the continuous R&D and business innovation, we are thrilled to develop the next generation technology that safeguards everyday life.\u00a0 The ideal candidate will support the full scope of Human Resources responsibilities and partner with the organization on strategic initiatives. Maintain and enhance the organization's human resources by planning, implementing, and evaluating human resources policies, programs, and practices.\n\nResponsibilities\n\nDesign and implement human resources strategies including talent acquisition, staffing retention, employment compensation, health and welfare benefits, training and development, and labour relations, etc;\nWork closely with top management by providing human resources advice, counsel, and decisions; accountable for the performance of HR function;\nSuggest appropriate innovative measures for improving performance evaluations and employee engagement;\nTranslate the business strategy into HR strategy and provide human capital and organizational change perspectives embedded into business leadership teams;\nAlign and integrate HR strategies, goals and practices to ensure high performing culture/employees/teams;\u00a0\nDrive leadership development and address organizational issues. Professional support in all change processes.\u00a0\nRequirements\n\nDegree holder or above in Human Resources Management or related disciplines;\nAt least 10 years of solid HR experience with minimum 5 years' experience in supervisory level and HRBP role;\u00a0\nSolid HR practical experience within fast-paced business environment in FMCG or consumer healthcare industry is a MUST;\nStrong capability to work with different levels of stakeholders;\nGood negotiation, motivation, strategic and leadership skills to drive success and create win-win solutions;\nPossess good planning, organizational and time management skills;\nExcellent communication and interpersonal skills; able to interact with different levels of people;\nStrong working knowledge of employment law issues, best practice processes for disciplinary, redundancies and payroll is required, as well as experience of employee relations;\nFluent in written and spoken English, Cantonese and Mandarin.\nWe offer the right candidate attractive remuneration package and outstanding prospects for career advancement and development.\u00a0 The right candidate will progress career in a forward thinking and dynamic business with exciting growth plans.\u00a0 If you are qualified and interested, please send your full resume with current & expected salary and availability by clicking \"APPLY\".\n\nAll information collected will be treated as strictly confidential and used for recruitment purposes only. (Only shortlisted candidates will be notified)", "employment_types": ["Full Time", "Permanent"], "selling_points": [], "locations": ["Southern Area"], "categories": ["Admin & HR", "Administration / Operation Manager", "HR Director / Manager", "Recruitment / Executive Search"], "post_time": "2022-01-15T10:57:20Z", "salary": {"currency": null, "max": null, "min": null, "period": "monthly", "term": null}, "salary_visible": false, "title_keywords": ["manager", "human resources"], "responsibilities": ["hr", "management", "teams", "design"], "requirements": {"degrees": ["degree holder"], "majors": ["related disciplines"], "languages": ["cantonese", "english", "mandarin"], "language_level": ["fluent"], "hard_skills": [], "soft_skills": ["negotiation", "time management skills", "organizational", "leadership skills", "communication and interpersonal skills", "business environment"], "languages_combined": [{"language": "cantonese", "language_level": ["fluent"]}, {"language": "english", "language_level": ["fluent"]}, {"language": "mandarin", "language_level": ["fluent"]}]}, "experience_required": {"duration": ["at least 10 years", "minimum 5 years"], "field": ["healthcare industry", "fmcg", "hr", "business", "supervisory level", "payroll"]}}, {"job_id": "100003009048916", "location_code": "hk", "company": "Cathay Pacific Catering Services (H.K.) Limited", "job_title": "Human Resources Officer (Business Partner)", "description": "Responsibilities\n\nAct as an HR business partner to provide the full spectrum of HR services including recruitment, staffing, performance management and C&B\nDesign and implement different recruiting and staffing programs to recruit and retain employees\nAnalyzes wage and salary reports and data to determine competitive compensation plan\nAdministers payroll and benefits programs\nAdvises management in appropriate resolution of employee relations issues\nResponds to inquiries regarding HR policies, procedures, and programs\nPrepare HR report for management review\nRequirements\n\nDegree holder in Human Resources Management or related disciplines\n1-2\u00a0years solid HR experience in a sizable multi-national company, with mass recruitment experience will be an advantage\nWell versed in Employment Ordinance and other relevant regulations\nGood interpersonal, communication skills and analytical skills\nProactive, independent, well-organized and detail-minded\nGood command of written and spoken English and Chinese;\nProficient in MS Office application and Chinese word processing\nImmediately available is highly preferred\nWe offer a competitive remuneration package and a full range of benefits. Interested parties please send your resume with your current and expected salary to Head of People,11 Catering Road East, Hong Kong International Airport, Lantau, Hong Kong or by clicking the \"Apply Now\" button\u00a0on or before 31 January 2022.\nPersonal data collected will be treated in the strictest confidence and only be used for recruitment-related purposes. Applicants who do not receive notification for an interview within six weeks may consider their application unsuccessful.", "employment_types": ["Full Time", "Permanent"], "selling_points": ["Act as a HR business partner", "Career advancement opportunities", "On job training provided"], "locations": ["Airport Area"], "categories": ["Admin & HR", "Compensation & Benefits", "HR Supporting Staff", "Recruitment / Executive Search"], "post_time": "2022-01-14T07:41:38Z", "salary": {"currency": null, "max": null, "min": null, "period": "monthly", "term": null}, "salary_visible": false, "title_keywords": ["human resources officer"], "responsibilities": ["management", "data", "hr", "design", "recruitment", "reports", "plan"], "requirements": {"degrees": [], "majors": [], "languages": [], "language_level": [], "hard_skills": [], "soft_skills": [], "languages_combined": []}, "experience_required": {"duration": [], "field": []}}, {"job_id": "100003009046478", "location_code": "hk", "company": "Cinnox Limited", "job_title": "Human Resources Officer (Talent Acquisition) - Immediate Available", "description": "Our team\nCINNOX is made of a collective of individuals driven by success while motivating and supporting one another to cultivate an environment of encouragement and trust. We are committed to continuous improvement through innovation, curiosity and creativity to help businesses compete and win by humanising customer and employee connections. We have a team that supports each other grows together. By working together, our achievements are magnified.\u00a0\nCINNOX is an equal opportunity employer, with the belief that a diverse team creates unique potential, we strive to build a diverse and inclusive community where everyone, regardless of gender, race, religion, age, or background, can belong.\nTo cope with the rapid business growth across the globe, we are looking for ambitious, passionate and self-driven talent to join our fast growing team.\nWHAT you be doing in this role:\n\nResponsible for the end-to-end recruitment process including not limited to job advertisement, CV screening & shortlisting, hiring and onboarding process automation, talent pool management and turnover analysis\nAs a Digital HR Specialist with the skills to successfully lead the digital transformation of HR by reforming HR workflows and ERP integration and implementation\nTo play the role of business partner for manpower planning and performance management\nPrepare and compile HR reports for management review\nParticipate in other HR initiatives and ad-hoc projects as assigned\nWHO are we looking for:\nDegree or above in Human Resources, Business Management or related discipline\n4 years' of relevant working experience Independent and able to work in a fast-paced work environment\nMature with good communication and interpersonal skills\nGood command of both written and spoken English & Chinese\nPositive and proactive attitude, and with strong sense of responsibility\nWorking experience in telecommunication, internet or IT industry is preferable\nCandidates with more experience will be considered as Senior Officer\nImmediately available\n***Resume without expected salary and notice of period will NOT be considered***\nCINNOX, a new way to humanise your connections, join us now!\n\nWe offer 5 days\u2019 work, medical insurance, free lunch, competitive salary package and attractive career development opportunities to the right candidate.\u00a0Interested parties please send your full resume with date of availability, present and expected salaries by clicking \"Apply Now\".\n\nFor more information about CINNOX, please visit and subscribe the below linkage:\nCINNOX Webpage\nCINNOX LinkedIn Page\nCINNOX Youtube channel\nTo protect the privacy of personal data, all applications will be treated in strict confidence. Personal data collected will be used for recruitment purposes only. Applicants not hearing from us within 6 weeks may consider their applications unsuccessful. We may also consider their application for other or future vacancies. Personal data of unsuccessful applicants will be retained for a maximum period of 6 months.", "employment_types": ["Full Time", "Permanent"], "selling_points": ["4+ years experience in HR, TA & HR Operations", "Immediate available is preferred", "5 day work, medical benefit and free luncheon"], "locations": ["Kowloon Bay"], "categories": ["Admin & HR", "Compensation & Benefits", "HR Supporting Staff", "Recruitment / Executive Search"], "post_time": "2022-01-13T11:44:23Z", "salary": {"currency": null, "max": null, "min": null, "period": "monthly", "term": null}, "salary_visible": false, "title_keywords": ["human resources officer"], "responsibilities": ["management", "cv screening", "job advertisement", "analysis", "hr", "implementation", "hr reports", "communication", "recruitment process", "ad-hoc projects", "management review", "planning"], "requirements": {"degrees": ["degree or above"], "majors": ["business"], "languages": ["english", "chinese"], "language_level": ["good command"], "hard_skills": ["business management", "analysis", "erp", "rapid", "integration"], "soft_skills": ["passionate", "independent", "responsible", "sense of responsibility", "unique", "mature", "committed", "diverse", "communication and interpersonal skills", "proactive", "driven", "positive"], "languages_combined": [{"language": "english", "language_level": ["good command"]}, {"language": "chinese", "language_level": ["good command"]}]}, "experience_required": {"duration": ["4 years"], "field": ["it", "relevant working experience"]}}, {"job_id": "100003009046793", "location_code": "hk", "company": "Cinnox Limited", "job_title": "Assistant HR Officer / HR Assistant (Immedately available)", "description": "WHAT you be doing in this role:\n\nAssist in full spectrum of HR functions including talent acquisition, training & development, compensation & benefits and employee relations etc.;\nHandle end-to-end recruitment process and support colleagues' life cycle administration including on-boarding and off-boarding logistics arrangement\nMaintain HR database/record management, medical insurance administration, filing system\nHandle and follow up internal colleagues' inquiries\nPrepare HR reports for management review\nImplement employee engagement activities and opportunities\nAdminister online learning management system\nParticipate in other HR initiatives and ad-hoc projects as assigned\nWHO are we looking for:\nHigh Diploma or above in Human Resources Management or other related disciplines\n1 year of HR related working experience, experience in Information Technology / Telecommunication industry is highly preferred\nGood knowledge of labor laws and regulations is preferred\nMature with good communication and interpersonal skills\nGood command of both written and spoken English & Chinese\nIndependent, proactive with positive attitude, enjoy working in a dynamic and fast-paced environment\nImmediate available is preferred\n***Candidates with more experience will be considered as Assistant HR Officer***\n\nWe offer 5 days\u2019 work, medical insurance, free lunch, competitive salary package and attractive career development opportunities to the right candidate.\u00a0Interested parties please send your full resume with date of availability, present and expected salaries by clicking \"Apply Now\".\n\n\nTo protect the privacy of personal data, all applications will be treated in strict confidence. Personal data collected will be used for recruitment purposes only. Applicants not hearing from us within 6 weeks may consider their applications unsuccessful. We may also consider their application for other or future vacancies. Personal data of unsuccessful applicants will be retained for a maximum period of 6 months.", "employment_types": ["Full Time", "Permanent"], "selling_points": ["1+ year HR experience with IT/Telecom knowledge", "Familiar with HR Operation, strong in HK labor law", "5 day work, medical Benefit and free luncheon"], "locations": ["Kowloon Bay"], "categories": ["Admin & HR", "HR Supporting Staff", "Recruitment / Executive Search", "Training & Development"], "post_time": "2022-01-14T01:09:54Z", "salary": {"currency": null, "max": null, "min": null, "period": "monthly", "term": null}, "salary_visible": false, "title_keywords": ["hr officer", "hr assistant", "assistant"], "responsibilities": [], "requirements": {"degrees": [], "majors": [], "languages": [], "language_level": [], "hard_skills": [], "soft_skills": [], "languages_combined": []}, "experience_required": {"duration": [], "field": []}}, {"job_id": "100003009049535", "location_code": "hk", "company": "Charterhouse Partnership", "job_title": "Recruitment Consultant \u2013 Technology", "description": "To cope with ongoing expansion, Charterhouse HK is now looking for new talent to join our Technology discipline. The role would be a regional role with career progression & ongoing mentorship.\n\nWe are looking for candidates who are motivated to develop a career in the industry, press apply to find out more!\n\nResponsibilities:\n\nManage the end to end recruitment cycle\nUtilise various recruitment tools and technology\nSource candidates through various channels\nConsulting for candidates and clients on recruitment related matters\nConduct candidate interviews and assessment\nGrow candidate database\n\nRequirements:\n\nDegree holder\nStrong communication skills with fluent English, Cantonese & Mandarin\nRecruitment experience (In-house/agency) would be an advantage\nInterest in on-going trends in IT/Digital/Innovations\nFresh graduates would be considered for the Researcher role with progression path to Consultant\n\nIf you are interested in finding out more about this career opportunity, please email your resume to Alex Cheung, alex.cheung@ charterhouse.com.hk\u00a0 Web: www.charterhouse.com.hk\n\nCharterhouse Partnership Hong Kong is here to assist you in your job search. Our experienced recruitment consultants will provide you with career advice and assist you to develop a tailored job search strategy.", "employment_types": ["Full Time", "Permanent"], "selling_points": ["Technology focus role", "Regional role", "Attractive compensation scheme"], "locations": ["Central"], "categories": ["Admin & HR", "Recruitment / Executive Search"], "post_time": "2022-01-14T08:50:19Z", "salary": {"currency": null, "max": null, "min": null, "period": "monthly", "term": null}, "salary_visible": false, "title_keywords": ["recruitment consultant"], "responsibilities": ["recruitment", "consulting", "database"], "requirements": {"degrees": ["degree holder"], "majors": [], "languages": ["cantonese", "english", "mandarin"], "language_level": ["fluent"], "hard_skills": ["web"], "soft_skills": ["communication skills", "interested in"], "languages_combined": [{"language": "cantonese", "language_level": ["fluent"]}, {"language": "english", "language_level": ["fluent"]}, {"language": "mandarin", "language_level": ["fluent"]}]}, "experience_required": {"duration": [], "field": ["agency", "recruitment"]}}, {"job_id": "100003009048980", "location_code": "hk", "company": "Odoo Limited", "job_title": "Talent Acquisition Officer (APAC)", "description": "Responsibilities:\n\nManaging a smooth recruitment process for a wide range of positions within Odoo\nManage the job adverts, the qualification of candidates, the interview arrangements and offers to be sent out to candidates.\nWorking with the team managers to understand their need, set the interviews, and get their feedback on candidates\nSupport and develop employer branding campaigns and the relationships with external organizations (universities, job fairs or professional event coordinators etc.)\nKeeping up to date with current job market conditions by researching the Hong Kong/APAC job market and the competitors in our industry\n\nYou'll get the chance to work in a fast growing company with a fun culture and you'll get the opportunity to learn about the tech industry.\n\nRequirements:\n\nBachelor's degree or higher\nStrong interest in recruiting in IT industry\nProactive, well organized\nFluent in English is a must\n1-2 years relevant experience preferred. Fresh grads will also be considered\nChallenges:\n\nEvaluate on potential, not on experience\nA lot of different positions to fill\nWilling to contribute to great company culture", "employment_types": ["Full Time"], "selling_points": ["In-house role", "International and dynamic work environment", "APAC recruitment"], "locations": ["Sai Ying Pun"], "categories": ["Admin & HR", "Recruitment / Executive Search"], "post_time": "2022-01-14T07:49:57Z", "salary": {"currency": null, "max": null, "min": null, "period": "monthly", "term": null}, "salary_visible": false, "title_keywords": ["officer"], "responsibilities": ["recruitment process", "develop"], "requirements": {"degrees": ["degree", "bachelor"], "majors": [], "languages": ["english"], "language_level": ["fluent"], "hard_skills": [], "soft_skills": ["proactive", "well organized"], "languages_combined": [{"language": "english", "language_level": ["fluent"]}]}, "experience_required": {"duration": ["1-2 years"], "field": ["relevant experience"]}}, {"job_id": "100003009047178", "location_code": "hk", "company": "Kai Shing Management Services Ltd", "job_title": "Human Resources Assistant (Part-time)", "description": "Responsibilities:\n\nProvide a full range of administrative, HR and clerical supports to the department such as HR daily routines, data entry, record updates, interview arrangement, office administration etc.\u00a0\nMaintain an efficient filing system\nAny other duties as assigned by the immediate supervisor\n\nRequirements:\u00a0\n\nUndergraduate or post-graduate\u00a0Human\u00a0Resources Management,\u00a0Business Administration\u00a0students\nProficient in PC operations, e.g. MS Word, Excel, Outlook\nGood team player with strong communication and coordination skills\nWell-organized, self-motivated, independent, responsible and able to work under pressure\nProficient in both spoken and written Chinese and English, including Putonghua\nImmediate available will be an advantage\n\nWe offer an attractive remuneration package and long-term career prospect to the right candidates. Interested parties, please apply once with application quoting job reference number, detailed resume, contact telephone number and salary expected either by mail to: Human Resources Department, Unit 301-303, 3/F., Apec Plaza, 49 Hoi Yuen Road, Kwun Tong, Hong Kong, or clicking the \"Apply Now\" button. (Attached resume should be in MS Word for Windows)\u00a0\n\n(Data collected would be used for recruitment purpose only)", "employment_types": ["Part Time"], "selling_points": ["Diploma in Human Resources Management", "Responsible for HR clerical works", "Assist in HR Projects"], "locations": ["Kwun Tong"], "categories": ["Admin & HR", "Recruitment / Executive Search", "Property / Real Estate", "Property Management"], "post_time": "2022-01-14T02:31:34Z", "salary": {"currency": null, "max": null, "min": null, "period": "hourly", "term": null}, "salary_visible": false, "title_keywords": ["human resources assistant"], "responsibilities": ["any other duties", "data entry", "office administration", "hr", "maintain", "interview arrangement"], "requirements": {"degrees": [], "majors": [], "languages": ["putonghua", "english", "chinese"], "language_level": ["proficient"], "hard_skills": ["excel", "pc operations", "outlook", "ms word"], "soft_skills": ["good team player", "self-motivated", "independent", "coordination skills", "responsible", "well-organized", "communication", "work under pressure"], "languages_combined": [{"language": "putonghua", "language_level": ["proficient"]}, {"language": "english", "language_level": ["proficient"]}, {"language": "chinese", "language_level": ["proficient"]}]}, "experience_required": {"duration": [], "field": []}}, {"job_id": "100003009049867", "location_code": "hk", "company": "Conners Consulting Limited", "job_title": "Senior Manager / Manager - HR Department (Securities Firm Bonus Perm Job)", "description": "Our client, a well-known securities firm in Hong Kong, is looking for a high calibre to join the group.\n\n\nResponsibilities\n\nHandle the entire recruitment process from sourcing of candidates to preparing remuneration proposal\nCommunicate with line managers for recruitment needs and requirements\nParticipate in various HR projects such as compensation & benefits, tax issues, performance appraisal and other HR initiatives as required\nDevelop, review and implement human resources strategies, policies and procedures\nParticipate ad hoc projects as assigned\u00a0\u00a0\n\nRequirements\n\nDegree holder preferably in Human resources management\nMinimum 5 years\u2019 recruitment experience in securities firm / financial industry\nIndependent, self-driven and good interpersonal skills\nGood command in spoken and written Chinese (both Cantonese & Putonghua) and English\nProficient in\u00a0PC knowledge, Word and Excel\nImmediate available is preferred\n\nTo apply, please send your detailed resume or contact Timothy Wong at 3990 3179 for a confidential discussion.\n\nOnly shortlisted candidates will be notified.\n\nApplicants who are not contacted within two weeks may consider their applications unsuccessful.\n\nAll data collected will be used for recruitment purpose only & will be used strictly confidential.\n\nConners Consulting Limited 2005 Kai Tak Commercial Building 317 Des Voeux Road Central Hong Kong.\n\nTel: (852) 3996 8090\u00a0\u00a0\u00a0\u00a0\u00a0\n\nWebsite: www.connersconsulting.com", "employment_types": ["Full Time", "Permanent"], "selling_points": ["Handle the entire recruitment proccess", "Mini 5 years' experience in securities firm or FI", "Immediate available is preferred"], "locations": ["Kowloon Bay"], "categories": ["Admin & HR", "HR Director / Manager", "Recruitment / Executive Search"], "post_time": "2022-01-15T03:50:38Z", "salary": {"currency": null, "max": null, "min": null, "period": "monthly", "term": null}, "salary_visible": false, "title_keywords": ["senior manager", "hr", "manager"], "responsibilities": ["communicate with", "recruitment process", "recruitment"], "requirements": {"degrees": [], "majors": [], "languages": [], "language_level": [], "hard_skills": [], "soft_skills": [], "languages_combined": []}, "experience_required": {"duration": [], "field": []}}, {"job_id": "100003009049195", "location_code": "hk", "company": "Premier by Dead Sea", "job_title": "Senior Human Resources Officer", "description": "Job Duties:\n\nHandling full spectrum of HR functions\nResponsible for payroll calculation, reviewing supporting document\nWork with line managers to determine hiring needs and select suitable candidates for final selection\nPrepare HR reports on regular basis for management review\nAssist in ad hoc projects\n\nJob Requirements:\n\nA Degree in Human Resources Management, Business Administration or related discipline;\nAt least 5 years of working experience in HR generalist position\u00a0\nGood interpersonal & communication skills;\nFamiliar with Employment Ordinance, MPF schemes and regulations\nMulti-tasking, meticulous, organized and able to meet tight work deadlines\nPleasant, strong sense of accountability and passionate about people\nGood command of written and spoken English and Chinese\nLess experience will be considered as Human Resources Officer", "employment_types": ["Full Time", "Permanent"], "selling_points": ["Handling full spectrum of HR functions", "Work with line managers to determine hiring needs", "Responsible for payroll calculation"], "locations": ["Kwun Tong"], "categories": ["Admin & HR", "Compensation & Benefits", "HR Supporting Staff", "Recruitment / Executive Search"], "post_time": "2022-01-14T08:15:12Z", "salary": {"currency": null, "max": null, "min": null, "period": "monthly", "term": null}, "salary_visible": false, "title_keywords": ["senior human resources officer"], "responsibilities": ["hr", "hr reports", "ad hoc projects", "payroll", "management review"], "requirements": {"degrees": ["degree"], "majors": ["business administration"], "languages": ["english", "chinese"], "language_level": ["good command"], "hard_skills": [], "soft_skills": ["organized", "communication skills", "meticulous", "accountability", "pleasant", "multi-tasking", "interpersonal", "passionate about"], "languages_combined": [{"language": "english", "language_level": ["good command"]}, {"language": "chinese", "language_level": ["good command"]}]}, "experience_required": {"duration": ["at least 5 years"], "field": ["hr generalist", "human resources"]}}, {"job_id": "100003009049347", "location_code": "hk", "company": "HKBN Enterprise Solutions HK Limited", "job_title": "Officer \u2013 Talent Services (HRBP & Recruitment)", "description": "The purpose to you with this career opportunity will be\u2026\n\nHKBN provides you a unique exposure to work to Inspire and to Change! Unlike an administrator, this opportunity will help you craft your career to become a Business Driver and Advisor to provide professional Talent Engagement services to our business functions.\n\nApart from your strengths, we will help you discover your LUCA (Legal Unfair Competitive Advantage) and together you will be able to contribute to new Talent Engagement initiatives, disrupt and impact the market together to make our Home a better place to live.\n\n\nTo be part of our mission, we are looking for an Senior Officer/Officer - Talent Services to\u2026\n\nProvide full spectrum of Talent management functions such as Talent acquisition and other Talent services including but not limited to maintenance of Talent data, resolving Talent management enquires in a professional manner\nAct as business driver to offer consultative and professional talent advices and solutions to other business functions heads on all Talent management related matters and market information updates\nExecute blended Talent acquisition strategies to attract and hire top Talents that unify business goals and talent aspirations\nAssist section head in collaborating with business functions to drive business strategies and objectives by formulating new Talent Engagement practices, procedures and policies\nAssist in Talent Engagement initiatives and projects as assigned\n\n\nLet\u2019s check if you are /have\u2026\n\n\n\nBachelor\u2019s Degree holder, Degree in HRM, Business Management or relevant discipline is an advantage\nAround 4-5 years of solid Recruitment/ Account Serving / HR Business Partner experience in multinational or sizable companies is preferred\nProactive, quality-driver, organized, resourceful and a team player\nExcellent English and Chinese written and communication skills is a huge advantage\nExcellent interpersonal and communication skills and proficient in MS Office applications\nLess experience\u00a0will be considered as\u00a0Assistant\u00a0Officer \u2013 Talent Services\n\nWhat you get in return\u2026\n\nApart from competitive salary package and benefits, in HKBN, you will work flexibly under our Talent-first\u00a0culture\u00a0and we uphold Life-Work Priority. Examples of our flexible initiatives:\n\n\n\nFive-day work week and shorten working hours (8 hours including 1 hour 15 mins meal break)\nHalf Day Off Friday once a month (compensation leave for Talents who work on shift)\nHalf Day Off on Festival Eve (compensation leave for Talents who work on shift)\nUnique leaves arrangement: Family-care leave, Anniversary leave, Bonus leave, Volunteer leave, Sabbatical leave, etc.\nComprehensive medical and life insurance coverage\nUpgraded maternity leave and paternity leave\nDiscounted Talent plan offers including broadband and mobile plans and other promoted products\nEducation subsidies and Examination leave\nYear-end discretionary bonus", "employment_types": ["Full Time", "Permanent"], "selling_points": ["Offer consultative and professional talent advices", "Execute blended Talent acquisition strategies", "LIFE-Work Priority & Talent-first Culture"], "locations": ["Kowloon Bay"], "categories": ["Admin & HR", "Clerical / Admin Staff", "HR Supporting Staff", "Recruitment / Executive Search"], "post_time": "2022-01-14T08:30:58Z", "salary": {"currency": null, "max": null, "min": null, "period": "monthly", "term": null}, "salary_visible": false, "title_keywords": ["officer"], "responsibilities": ["management", "market information", "business goals", "maintenance", "data", "policies", "hr", "professional manner", "procedures", "quality", "communication", "recruitment"], "requirements": {"degrees": ["degree", "bachelor", "degree holder"], "majors": ["business"], "languages": ["english", "chinese"], "language_level": ["advantage", "excellent"], "hard_skills": ["business management", "maintenance", "sizable companies", "make", "ms office"], "soft_skills": ["organized", "communication skills", "resourceful", "unique", "team player", "proactive", "interpersonal"], "languages_combined": [{"language": "english", "language_level": ["advantage", "excellent"]}, {"language": "chinese", "language_level": ["advantage", "excellent"]}]}, "experience_required": {"duration": ["4-5 years"], "field": ["hr", "recruitment", "business partner"]}}, {"job_id": "100003009051111", "location_code": "hk", "company": "David James Recruitment  China Limited", "job_title": "Researcher / Junior Recruitment Consultant (Basic salary + Commission)", "description": "DJRecruit Asia was set up by a group of successful recruiters with strong experience in the market. Our goal is simple - to be the leading brand in Asia for our industry.\n\nResponsibilities:\n\nWork closely with Director and Consultants to determine the best sourcing directions and assist with sourcing of candidates and potential leads\nProvide administrative support in database management, marketing events (on-line and off-line) and sales report\nLiaise with internal and external parties to provide ad hoc support\nRequirements:\n\n\nDegree holder in any discipline\n1 \u2013 3 years of working experience (fresh graduates are welcome)\nGood command of English and Chinese (Cantonese and Mandarin)\nHard-working and target-oriented with good communication skills\nTo Apply\n\nInterested parties please send us your updated resume with your latest and expected salaries or please call +852 3611 7780 for a confidential discussion.", "employment_types": ["Full Time", "Permanent"], "selling_points": ["1 \u2013 3 years working exp. (fresh grads are welcome)", "Fast-paced and rewarding work environment", "Carry out research and provide admin support"], "locations": ["Central & Western Area"], "categories": ["Professional Services", "Business Consultancy", "Sales, CS & Business Devpt", "Business Development", "Admin & HR", "Recruitment / Executive Search"], "post_time": "2022-01-15T02:33:03Z", "salary": {"currency": null, "max": null, "min": null, "period": "monthly", "term": null}, "salary_visible": false, "title_keywords": ["researcher", "recruitment consultant", "junior"], "responsibilities": ["marketing events", "management", "sales report", "ad hoc", "internal and external parties", "liaise with", "database", "provide administrative support"], "requirements": {"degrees": ["degree holder"], "majors": [], "languages": ["cantonese", "english", "chinese", "mandarin"], "language_level": ["good command"], "hard_skills": [], "soft_skills": ["communication skills", "hard-working"], "languages_combined": [{"language": "cantonese", "language_level": ["good command"]}, {"language": "english", "language_level": ["good command"]}, {"language": "chinese", "language_level": ["good command"]}, {"language": "mandarin", "language_level": ["good command"]}]}, "experience_required": {"duration": ["3 years"], "field": []}}, {"job_id": "100003009050033", "location_code": "hk", "company": "Aptitude Asia Limited", "job_title": "Recruitment Consultant", "description": "Aptitude is one of Asia\u2019s leading executive search firms, providing high-level and senior recruitment solutions to the investment banking, financial services, insurance, and technology industries.\n\nExperts in the field of Investment Banking IT, Wealth management IT, Insurance IT, Management Consultancy, & Front Office recruitment. We aim to become the strongest player in the Asia Pacific market. Always looking for talented IT and Banking professionals looking for the next step for their careers. We mainly cover the Hong Kong, China, and Singapore markets.\n\nJob Description\n\nConduct search, source, screen, and identify potential candidates through various online resources and platforms to match client's hiring needs\nDevelop and maintain positive relationships with clients and candidates\nManage the full recruitment process from sourcing candidates to interview and offer stages\nConduct in-person/video/phone interviews to thoroughly evaluate candidates\nProvide support to senior consultants\n\nJob Requirement\u00a0\u00a0\u00a0\u00a0\n\nBachelor's Degree holder from a reputable university (ideally overseas)\nWork experience in a client-facing role would be beneficial\nSelf-motivated and a good team player\nExcellent interpersonal, communication, and presentation skills\nMust be fluent in English, Cantonese, and Mandarin\n\nBenefits\n\n5-days work\nFull medical benefits\n20 days annual leave\nDecent commission scheme\nWork location: Central\n\nTo apply, send resume to Stella[AT]aptitudeasia.com and Nicky[AT]aptitudeasia.com", "employment_types": ["Full Time", "Permanent"], "selling_points": ["Top boutique executive search / recruitment agency", "Dynamic team work culture", "Fresh graduates are welcomed"], "locations": ["Central"], "categories": ["Admin & HR", "Others", "HR Supporting Staff", "Recruitment / Executive Search"], "post_time": "2022-01-14T09:39:56Z", "salary": {"currency": null, "max": null, "min": null, "period": "monthly", "term": null}, "salary_visible": false, "title_keywords": ["recruitment consultant"], "responsibilities": ["provide support", "develop", "evaluate", "maintain", "recruitment process"], "requirements": {"degrees": ["bachelor", "degree holder"], "majors": [], "languages": ["cantonese", "english", "mandarin"], "language_level": ["fluent"], "hard_skills": [], "soft_skills": ["good team player", "self-motivated", "communication", "presentation skills", "interpersonal", "client-facing"], "languages_combined": [{"language": "cantonese", "language_level": ["fluent"]}, {"language": "english", "language_level": ["fluent"]}, {"language": "mandarin", "language_level": ["fluent"]}]}, "experience_required": {"duration": [], "field": ["client-facing"]}}, {"job_id": "100003009043709", "location_code": "hk", "company": "Manpower Services (Hong Kong) Limited", "job_title": "HR Specialist", "description": "Responsibilities:\n\nEnd to end recruitment cycle\nWork closely with line manager or client for the job requirement and provide suitable candidate\nUnderstand the hiring needs and provide support in recruitment\u00a0\nHandle\u00a0C&B tasks and HR administration independently e.g. MPF enrollment, medical plan enrollment, communicate with payroll team for monthly payroll and final payment\nProvide HR consultation to line manager\u00a0or client\nDevelop candidate base through different recruitment channels\nHandle\u00a0ad hoc projects and perform other duties as assigned\n\nRequirements:\n\nDiploma holder\u00a0or above, Human Resources Management is preferred\nAt least 2 years experience in Human Resources / recruitment agency\nEnergetic, responsible, detail minded, able to work multi-tasks and independently\u00a0\nExcellent interpersonal and communication skills\nFluent in oral and written English and Chinese (Cantonese and Mandarin)\nImmediately available is highly preferable\u00a0\n\nInterested parties please submit your CV with your expected salary and availability to danise.yeung@manpowegrc.hk", "employment_types": ["Permanent"], "selling_points": ["All round HR", "Work independently", "Immediately available is highly preferable"], "locations": ["Causeway Bay"], "categories": ["Admin & HR", "Compensation & Benefits", "HR Supporting Staff", "Recruitment / Executive Search"], "post_time": "2022-01-13T01:35:57Z", "salary": {"currency": null, "max": null, "min": null, "period": "monthly", "term": null}, "salary_visible": false, "title_keywords": ["hr specialist"], "responsibilities": ["communicate with", "provide support", "enrollment", "perform other duties", "mpf", "hr", "develop", "payment", "recruitment", "ad hoc projects", "plan", "payroll", "administration"], "requirements": {"degrees": ["diploma holder"], "majors": [], "languages": ["cantonese", "english", "chinese", "mandarin"], "language_level": ["fluent"], "hard_skills": [], "soft_skills": ["communication skills", "oral", "independently", "multi-tasks", "responsible", "energetic", "interpersonal"], "languages_combined": [{"language": "cantonese", "language_level": []}, {"language": "english", "language_level": ["fluent"]}, {"language": "chinese", "language_level": ["fluent"]}, {"language": "mandarin", "language_level": []}]}, "experience_required": {"duration": ["at least 2 years"], "field": ["agency", "recruitment", "human resources"]}}, {"job_id": "100003009050630", "location_code": "hk", "company": "Hip Shing Hong (Holdings) Company Limited", "job_title": "Assistant Human Resources Manager", "description": "We are an energetic work-life balanced company.\u00a0\n\nCome to join our team to take on new challenges.\n\n\u00a0We are looking for a talent to:\n\nManage end-to-end talent acquisition process from sourcing, interviewing, presenting candidates, and extending offers in a fast-paced business environment\nDemonstrate knowledge in functional HR areas such as talent management, employee relations, training and development, compensation and benefits, talent acquisition and organizational development\nOversee the hotel\u2019s team member welfare programs, ensuring that the benefits supplied are relevant and competitive in the local marketplace.\nAssist in the training of service excellence on hotel\u2019s focus and team members to train others in providing exceptional service to the hotel\u2019s external customers (guests).\nPropose and execute dynamic HR projects for company advancements\nPioneer HR technologies and contribute ideas in practical applications\nBack up for team members as well as assist in other ad-hoc tasks\n\nBasic requirements:\n\nBachelor\u2019s Degree holder or above in\u00a0Hospitality, Human Resources, Business Administration or related disciplines\nMinimum 6-8 years\u2019 in Human Resources, Talent Acquisition or Talent Development\nExperience in Hotel or service orientated organization preferred\nProactive and autonomous with the flexibility to adapt to ever-changing priorities and responsibilities\nExcellent organizational skills with the ability to work on multiple projects concurrently and take responsibility for project delivery\nGood command of written and spoken English, Cantonese, and Mandarin\n\nBenefits:\u00a0\u00a0\n\nMedical insurance\nDental insurance\nDiscretionary year-end bonus\nEducation and training allowance\nPaid marriage leave & gift\nPaid emergency leave\nPaid children's birthday leave\nPaid compassionate leave\nAcademic scholarship\n\nWe are constantly looking for talents who are proactive and dedicated to be part of our Hip Shing Hong\u2019s family.\u00a0 If you are ready for the next challenge, please apply now!\n\nFor more information, please visit our Company's website\u00a0https://www.hshd.com.hk/en/career/.\n\nAll information provided by applicants will be treated in strict confidence and be used for recruitment purpose only.\u00a0", "employment_types": ["Full Time", "Permanent"], "selling_points": ["Degree holder in Hospitality or Human Resources", "Talent acquisition and training focus", "Minimum 6-8 years relevant working experience"], "locations": ["Central"], "categories": ["Admin & HR", "HR Supporting Staff", "Recruitment / Executive Search", "Training & Development"], "post_time": "2022-01-14T11:00:49Z", "salary": {"currency": null, "max": null, "min": null, "period": "monthly", "term": null}, "salary_visible": false, "title_keywords": ["assistant human resources manager"], "responsibilities": ["hr", "management"], "requirements": {"degrees": [], "majors": [], "languages": [], "language_level": [], "hard_skills": [], "soft_skills": ["business environment", "organizational", "energetic"], "languages_combined": []}, "experience_required": {"duration": [], "field": []}}, {"job_id": "100003009050034", "location_code": "hk", "company": "Aptitude Asia Limited", "job_title": "Recruitment Consultant Trainee (No KPI)", "description": "Aptitude is one of Asia\u2019s leading executive search firms, providing high-level and senior recruitment solutions to the investment banking, financial services, insurance, and technology industries.\n\nExperts in the field of Investment Banking IT, Wealth management IT, Insurance IT, Management Consultancy, & Front Office recruitment. We aim to become the strongest player in the Asia Pacific market. Always looking for talented IT and Banking professionals looking for the next step for their careers. We mainly cover the Hong Kong, China, and Singapore markets.\n\nJob Description\n\nConduct search, source, screen, and identify potential candidates through various online resources and platforms to match client's hiring needs\nDevelop and maintain positive relationships with clients and candidates\nManage the full recruitment process from sourcing candidates to interview and offer stages\nConduct in-person/video/phone interviews to thoroughly evaluate candidates\nProvide support to senior consultants\n\nJob Requirement\u00a0\u00a0\u00a0\u00a0\n\nBachelor's Degree holder from a reputable university (ideally overseas)\nWork experience in a client-facing role would be beneficial\nSelf-motivated and a good team player\nExcellent interpersonal, communication, and presentation skills\nMust be fluent in English, Cantonese, and Mandarin\n\nBenefits\n\n5-days work\nFull medical benefits\n20 days annual leave\nDecent commission scheme\nWork location: Central\n\nTo apply, send resume to Stella[AT]aptitudeasia.com and Nicky[AT]aptitudeasia.com", "employment_types": ["Full Time", "Permanent"], "selling_points": ["Top boutique executive search / recruitment agency", "Dynamic team work culture", "Fresh graduates are welcomed"], "locations": ["Central"], "categories": ["Admin & HR", "Others", "HR Supporting Staff", "Recruitment / Executive Search"], "post_time": "2022-01-14T09:39:57Z", "salary": {"currency": null, "max": null, "min": null, "period": "monthly", "term": null}, "salary_visible": false, "title_keywords": ["recruitment consultant", "trainee"], "responsibilities": ["provide support", "develop", "evaluate", "maintain", "recruitment process"], "requirements": {"degrees": ["bachelor", "degree holder"], "majors": [], "languages": ["cantonese", "english", "mandarin"], "language_level": ["fluent"], "hard_skills": [], "soft_skills": ["good team player", "self-motivated", "communication", "presentation skills", "interpersonal", "client-facing"], "languages_combined": [{"language": "cantonese", "language_level": ["fluent"]}, {"language": "english", "language_level": ["fluent"]}, {"language": "mandarin", "language_level": ["fluent"]}]}, "experience_required": {"duration": [], "field": ["client-facing"]}}, {"job_id": "100003009049316", "location_code": "hk", "company": "Bright Future Pharmaceutical Laboratories Ltd", "job_title": "HR Officer", "description": "About Bright Future\nFounded in 1993, Bright Future is a Hong Kong research-based leading multinational pharmaceutical company focused on skin health, pediatrics, respiratory and pain management. With experience and capabilities in the development, manufacturing and commercialization of prescription medications, OTC products and health functional products, Bright Future puts quality of life first and is committed to offering excellent health solutions to make every life healthier. As is our vision:\u00a0 \u201cbrighter life better future\u201d.\nTo cope with our business expansion and new product development, we are looking for the right talent to join our growing Hong Kong office.\n\nJob Description:\nProvide HR support and services to different business units including talent acquisition, manpower planning, training & development, employee relations & engagement\nHandle\u00a0recruitment\u00a0and\u00a0selection\u00a0process including but not limited to job-ad posting, screen CV, conduct interviews, verification of candidate's qualifications and staff onboarding preparation\nAnalyze and implement the recruitment strategy and channels for R&D specialists, scientists and technicians in Greater China regions\nHandle work visa application and extension\nHandle EC cases\nProvide support to internal training activities\nUpdate and maintain recruitment reports and database to ensure accuracy\nPrepare,\u00a0review\u00a0and\u00a0analyze\u00a0manpower\u00a0related\u00a0management\u00a0reports\nTo\u00a0assist\u00a0in\u00a0reviewing\u00a0and\u00a0implementing\u00a0HR\u00a0policies,\u00a0procedures\u00a0and\u00a0practice\nAssist\u00a0in\u00a0other\u00a0ad\u00a0hoc\u00a0projects\u00a0as\u00a0assigned\nRequirements:\n\nHigh Diploma or above, major in HR is preferred\nAt least 3 years of relevant experience, with experience in applying working visa is an advantage\nHands-on\u00a0experience\u00a0in\u00a0handling\u00a0EC\u00a0cases\nGood command of written and spoken Cantonese, English and Mandarin\nProficiency in MS Office application (Word, Excel & PowerPoint)\nA good team player, a \"willing-to-do\" attitude\nGood interpersonal and communication skills with common sense and good telephone manner\nImmediate available is highly preferred\nWe offer 5-day work with good career prospects and excellent fringe benefits to the right candidates\u00a0including shuttle bus, medical insurance, free luncheon, and discretionary bonus.\n\nInterested parties please send your full resume stating your current and expected salary and date of availability to the Human Resources Department by clicking Apply NOW.\n(Data collected will be used for recruitment purposes only.)", "employment_types": ["Full Time", "Permanent"], "selling_points": ["Free shuttle bus in Yuen Long/Fanling and luncheon", "Higher Diploma holder, major in HR", "Able to work in a fast-paced environment"], "locations": ["Yuen Long"], "categories": ["Admin & HR", "HR Supporting Staff", "Recruitment / Executive Search"], "post_time": "2022-01-14T08:27:55Z", "salary": {"currency": null, "max": null, "min": null, "period": "monthly", "term": null}, "salary_visible": false, "title_keywords": ["hr officer"], "responsibilities": ["provide support", "training activities", "policies", "hr", "review", "procedures", "recruitment strategy", "management reports", "maintain", "recruitment", "reports", "database", "ad hoc projects", "planning"], "requirements": {"degrees": ["high diploma or above"], "majors": [], "languages": ["cantonese", "english", "mandarin"], "language_level": ["good command"], "hard_skills": ["excel", "word", "powerpoint", "ms office"], "soft_skills": ["communication skills", "good team player", "hands-on", "telephone manner", "interpersonal"], "languages_combined": [{"language": "cantonese", "language_level": ["good command"]}, {"language": "english", "language_level": ["good command"]}, {"language": "mandarin", "language_level": ["good command"]}]}, "experience_required": {"duration": ["at least 3 years"], "field": ["relevant experience"]}}, {"job_id": "100003009043141", "location_code": "hk", "company": "Knight Recruitment Services Limited", "job_title": "Recruitment Intern/Part-time, Central, 5day! University Student Welcome!! (Jan - Mar 2022)", "description": "Recruitment Intern/Part-time, Central, 5day! University Student Welcome!! (Jan - Mar 2022)\n\nLocation: Central; Must be available to work at least 2-3 days a week\u00a0\n\nKnight Recruitment is a boutique recruitment firm that provides customised staffing solutions to MNCs across the Asia Pacific. We are currently looking for a Recruitment Intern to add to our growing team:\u00a0\n\nIf you are a cheerful, determined, result-driven person with passionate about people, a career at Knight could be just the move for you.\n\nWe offer a fun innovative working environment and a platform for you to grow and develop with excellent rewarding incentive scheme.\n\nAs a Recruitment Intern/Part-time, your key duties are:\n\nMake Candidate profiles & provide administrative support\u00a0\nDevelop new clients and business within the industry\nHandle recruitment assignments for the junior positions\u00a0\nSource, shortlist and interview best suited candidates for required roles\nManage the job offer process, handling compensation negotiations with clients and candidates\nProvide career advisory services to candidates\nEstablish and maintain strong relationships with clients and candidates\nKeep abreast with market information, employment trends and industry knowledge\nWork as part of a team to achieve team goals and objectives\u00a0\n\nRequirements\n\nFresh Graduate or current University students with strong language skills with passion and ambition in recruitment industry\nFluent in English, Cantonese, Mandarin; both written and spoken\nPossess passion, enthusiasm and ambition to the recruitment industry\nMust be result driven, positive, self-motivated and able to work under pressure\nMust possess excellent client services and negotiation skills\nStrong computer skills in Word and Excel\nImmediate Available is highly prefer\n\n8 minute walk from Central MTR Station.\u00a0\u00a0\n\nFor more information, please email your\u00a0RESUME and Expected Salary\u00a0to bethany.lam@ knightrecruits.com \u00a0\u00a0\n\n\nData collected will be used for recruitment purposes only. Personal data provided by job applicants will be used strictly in accordance with the Personal Data (Privacy) Ordinance. We regret that only the shortlisted candidates will be notified.", "employment_types": ["Full Time", "Part Time", "Temporary", "Internship"], "selling_points": ["Central, 8 min walk from Central MTR", "Recruitment Intern (Jan - Mar 2022)", "Fun working friendly environment"], "locations": ["Central"], "categories": ["Sales, CS & Business Devpt", "Customer Service - Supervisor / Officer", "Admin & HR", "Recruitment / Executive Search", "Others", "Student / Fresh Graduate / No Experience"], "post_time": "2022-01-13T02:54:34Z", "salary": {"currency": null, "max": null, "min": null, "period": "monthly", "term": null}, "salary_visible": false, "title_keywords": ["intern"], "responsibilities": ["recruitment"], "requirements": {"degrees": [], "majors": [], "languages": [], "language_level": [], "hard_skills": [], "soft_skills": ["cheerful", "driven", "determined", "passionate about"], "languages_combined": []}, "experience_required": {"duration": [], "field": []}}, {"job_id": "100003009050082", "location_code": "hk", "company": "Urban Renewal Authority", "job_title": "Assistant Manager, Human Resources (11-month contract) (Ref. Temp_AM(HR))", "description": "Responsibilities:\n\nTo be responsible for the recruitment related activities including sourcing candidates, screening applications, conducting interviews, offer making, etc.\nTo support the implementation of new Human Resources Management System (HRMS) by setting up business processes, preparing test scenarios, conducting User Acceptance Test and developing training materials as per the agreed timeline\nTo assist the supervisor in the review and update of human resources related policies and procedures\nTo assist in designing and preparing data analysis reports / dashboards and make recommendations for enhancement to support the needs of the Authority\nTo take part in HR related ad hoc projects and other relevant duties as assigned by supervisor\n\nRequirements:\n\nDegree holder in human resources, business administration or related discipline\nMinimum 6 years\u2019 relevant experience in sizable organizations with at least 2 years\u2019 supervisory experience\nFamiliar with Employment Ordinance and other related ordinances/regulations\nGood communication, interpersonal and writing skills\nProficient in PC operation such as Microsoft Word, Excel and PowerPoint\nExperience in implementation of HRMS, especially Workday is highly preferable\n\n(Candidate will less experience will be considered for the post of Senior Officer, Human Resources)\n\nFor more information on the work of the URA, please visit the website at http://www.ura.org.hk.\n\nFull resume with present and expected salaries should be submitted via online application (please click this website address: https://careers.ura.org.hk/).\n\nClosing date for application:27 January 2022.\u00a0All applications will be treated in the strictest confidence and information provided will be used for the consideration of applications.\u00a0 Applicants not invited for interview within four weeks from the closing date may consider their applications unsuccessful.\n\nPersonal data provided by job applicants will be treated in strict confidence and used strictly in accordance with our \u201cPersonal Information Collection Statement Pertaining to Recruitment\u201d for recruitment purpose only.\u00a0 A copy of the Statement is available on our website and obtainable on request.\u00a0 Applicants may be considered for other suitable positions in the Authority and all personal data of unsuccessful applicants will be retained for a maximum of two years.", "employment_types": ["Contract"], "selling_points": ["Support the implementation of new HRMS", "Degree holder in human resources", "Minimum 6 years\u2019 relevant experience"], "locations": ["Not Specified"], "categories": ["Admin & HR", "Others", "HR Supporting Staff", "Recruitment / Executive Search"], "post_time": "2022-01-14T10:29:48Z", "salary": {"currency": null, "max": null, "min": null, "period": "monthly", "term": null}, "salary_visible": false, "title_keywords": ["assistant manager,", "human resources"], "responsibilities": ["make recommendations", "management", "policies", "hr", "review", "procedures", "developing", "implementation", "data analysis", "conducting interviews", "recruitment", "reports", "ad hoc projects", "designing"], "requirements": {"degrees": ["degree holder"], "majors": ["business administration"], "languages": [], "language_level": [], "hard_skills": ["excel", "microsoft word", "powerpoint", "writing skills", "pc"], "soft_skills": ["communication", "confidence", "interpersonal", "writing skills"], "languages_combined": []}, "experience_required": {"duration": ["at least 2 years", "minimum 6 years"], "field": ["relevant experience", "human resources", "supervisory experience"]}}, {"job_id": "100003009044745", "location_code": "hk", "company": "SGS Hong Kong Limited", "job_title": "Assistant HR Officer (Mass Recruitment)", "description": "Duties &\u00a0Responsibilities\n\nPlan, implement and manage the overall recruitment strategy\nExplore potential and evaluate the effectiveness of advertising, social media, job fair, recruitment day and recruitment channels, etc.\nCollaborating with department managers to compile a consistent list of hiring needs, developing job descriptions and specifications\nConducting interviews and sorting through applicants to fill open positions\n\u00a0Assessing applicants' knowledge, skills, and experience to best suit open positions\nCompleting paperwork for new hires\nPromoting the company's reputation and attractiveness as a good employment opportunity\nProviding recruitment status reports to management\nTo maintain retention activities - conduct regular meetings with existing selective staff; conduct exit interview and report their feedback to the management.\nHandle ad hoc projects as required\n\nRequirements/Qualification\n\nA degree/diploma holder in Human Resources or related disciplines\nWith at least 2 years HR experience,\u00a0preferably experience in mass recruitment\nExperience in job fair, mass recruitment, etc. is an advantage\nThe ability to design and implement recruiting strategies and recruitment channels\n\u00a0Self-motivated, responsible, independent and detail-oriented, good interpersonal and communication skills\nA working knowledge of employment law and legislation\nImmediate available is preferred\nCandidate with more experience will be considered as Senior post\n\n\u00a0Working Hours/Work Location\n\nWork location: Ping Shan, Yuen Long", "employment_types": ["Full Time", "Permanent"], "selling_points": ["Immediate available preferred", "Yuen Long area (Shuttle bus provided)", "Explore Recruitment Channels"], "locations": ["Yuen Long"], "categories": ["Admin & HR", "Others", "HR Supporting Staff", "Recruitment / Executive Search"], "post_time": "2022-01-13T06:05:01Z", "salary": {"currency": null, "max": null, "min": null, "period": "monthly", "term": null}, "salary_visible": false, "title_keywords": ["hr officer", "assistant"], "responsibilities": ["social media", "management", "advertising", "developing", "evaluate", "recruitment strategy", "conducting interviews", "specifications", "recruitment", "reports", "plan", "maintain", "ad hoc projects", "report"], "requirements": {"degrees": ["diploma holder", "degree"], "majors": ["related disciplines"], "languages": [], "language_level": [], "hard_skills": [], "soft_skills": ["communication skills", "self-motivated", "independent", "responsible", "detail-oriented", "interpersonal"], "languages_combined": []}, "experience_required": {"duration": ["at least 2 years"], "field": ["hr", "recruitment"]}}, {"job_id": "100003009050822", "location_code": "hk", "company": "Cinnox Limited", "job_title": "Officer, Internal Audit (Immedately available)", "description": "Our team\nCINNOX is made of a collective of individuals driven by success while motivating and supporting one another to cultivate an environment of encouragement and trust. We are committed to continuous improvement through innovation, curiosity and creativity to help businesses compete and win by humanising customer and employee connections. We have a team that supports each other grows together. By working together, our achievements are magnified.\u00a0\nCINNOX is an equal opportunity employer, with the belief that a diverse team creates unique potential, we strive to build a diverse and inclusive community where everyone, regardless of gender, race, religion, age, or background, can belong.\nTo cope with the rapid business growth across the globe, we are looking for ambitious, passionate and self-driven talent to join our fast growing team.\nWHAT you be doing in this role:\n\nAssist in full spectrum of HR functions including talent acquisition, training & development, compensation & benefits and employee relations etc.;\nReview business processes, assess key risks and evaluate effectiveness as well as adequacy of internal controls system\nLiaise with various management to drive the improvement of internal controls system\nPerform regular follow up of the implementation of improvement plans\nCoordinate with relevant stakeholders on the implementation of risk management enhancment program\nPerform ad hoc internal controls review\nWHO are we looking for:\nBachelor Degree holder of Accounting or equivalent\nHolder of professional qualification, e.g. HKICPA, ACCA, CIA or equivalent\nAt least 3-year audit experience.\nGood interpersonal skill with strong analytical mind, be self-initiative and well-organized\nGood command in written and spoken English and Chinese\nImmediate available is preferred\nCINNOX, a new way to humanise your connections, join us now!\n\nWe offer 5 days\u2019 work, medical insurance, free lunch, competitive salary package and attractive career development opportunities to the right candidate.\u00a0Interested parties please send your full resume with date of availability, present and expected salaries by clicking \"Apply Now\".\n\nFor more information about CINNOX, please visit and subscribe the below linkage:\nCINNOX Webpage\nCINNOX LinkedIn Page\nCINNOX Youtube channel\nTo protect the privacy of personal data, all applications will be treated in strict confidence. Personal data collected will be used for recruitment purposes only. Applicants not hearing from us within 6 weeks may consider their applications unsuccessful. We may also consider their application for other or future vacancies. Personal data of unsuccessful applicants will be retained for a maximum period of 6 months.", "employment_types": ["Full Time", "Permanent"], "selling_points": ["Internal Audit, HKICPA/ACCA/CIA holder", "3+ year experience in audit", "5 day work, medical benefit and free luncheon"], "locations": ["Kowloon Bay"], "categories": ["Admin & HR", "HR Supporting Staff", "Recruitment / Executive Search", "Training & Development"], "post_time": "2022-01-14T11:29:08Z", "salary": {"currency": null, "max": null, "min": null, "period": "monthly", "term": null}, "salary_visible": false, "title_keywords": ["officer"], "responsibilities": [], "requirements": {"degrees": [], "majors": [], "languages": [], "language_level": [], "hard_skills": ["rapid"], "soft_skills": ["passionate", "unique", "committed", "diverse", "driven"], "languages_combined": []}, "experience_required": {"duration": [], "field": []}}, {"job_id": "100003009049872", "location_code": "hk", "company": "Hays", "job_title": "HR Business Partner (Top Investment Bank, 1-year renewable)", "description": "\nYour new company\nMy client is one of the top-tier Investment Banks.\n\nYour new role\n\nProvide full spectrum of support in HR recruitment team\nSupport end-to-end recruitment process such as job advertisement posting, CV screening, interview and meeting coordination, etc\nUpdate interview pipeline information and maintain HR information system\nPerform ad hoc assignments\n\n\nWhat you'll need to succeed\n\nDegree holder in Human Resources or related disciplines\nFresh graduates majoring in Human Resources or 1-year of HR working experience preferably from sizable organizations\nExcellent communication and presentation skills\nFluent in English, Cantonese and Mandarin\n\n\nWhat you'll get in return\n\nHigh temp to perm potential\nAttractive discretionary bonus\nDevelop your career with top-tier investment banks\n\n\nWhat you need to do now\nIf you're interested in this role, please forward your updated CV to elsa.lam@hays.com.hk, or call Elsa Lam at 2230 7475 now. If this job isn't quite right for you but you are looking for a new position, please contact us for a confidential discussion on your career.", "employment_types": ["Full Time", "Temporary"], "selling_points": ["High temp to perm potential", "Attractive discretionary bonus", "Develop your career with top-tier investment banks"], "locations": ["Not Specified"], "categories": ["Admin & HR", "Others", "HR Supporting Staff", "Recruitment / Executive Search"], "post_time": "2022-01-14T09:22:05Z", "salary": {"currency": null, "max": null, "min": null, "period": "monthly", "term": null}, "salary_visible": false, "title_keywords": ["hr"], "responsibilities": ["cv screening", "job advertisement", "hr", "develop", "communication", "maintain", "recruitment", "ad hoc assignments", "coordination", "contact", "recruitment process"], "requirements": {"degrees": ["degree holder"], "majors": ["related disciplines"], "languages": ["cantonese", "english", "mandarin"], "language_level": ["fluent"], "hard_skills": ["information system"], "soft_skills": ["communication", "presentation skills", "interested in", "coordination"], "languages_combined": [{"language": "cantonese", "language_level": ["fluent"]}, {"language": "english", "language_level": ["fluent"]}, {"language": "mandarin", "language_level": ["fluent"]}]}, "experience_required": {"duration": ["1-year"], "field": ["hr", "human resources"]}}, {"job_id": "100003009049671", "location_code": "hk", "company": "P & A Consultant Limited", "job_title": "HR & Admin Officer / HR & Admin Assistant/ Executive Assistant / Secretarial - Top Urgent", "description": "HR & Admin Officer/ HR & Admin Assistant\nLocation : Hung Hom,\u00a0\u00a0Salary : 16-28K\n\nResponsibilities:\n\nProvide full support of human resources function including but not limited to recruitment, orientation and employee activities etc\nProvide clerical and administrative support to the other department & Administration Dept.\nManage and review various sourcing channels\nUpdate personal details and attendance record in HR systems\nHandle monthly payroll administration, final payments, leave management and\u00a0 MPF administration\nTravel to China office occasionally ( Once a month )\nPrepare HR reports and assist in ad hoc duties as assigned\n\nRequirements:\n\nA diploma or above with a minimum of 2-3 year relevant working experience\nAt least 2-6 years related experience\nWell versed with HK Employment Ordinance and other related legislation\nProficient in MS Office\nAble to perform in a fast-paced and dynamic environment\nCandidates with less experience will be considered as\u00a0 Human Resources and Administration Assistant\u00a0\nTravel to CHN office occasionally\nImmediate available is preferred\nExecutive Assistant/ Secretarial\nLocation : Hung Hom,\u00a0\u00a0Salary : 18-26K\nResponsibilities\n\nProvide efficient, accurate and responsive secretarial and administrative support to Director\nMaintain daily routines, coordinate and set up appointments\nPrepare minutes, reports and the presentation materials\nManage travel arrangement including flight schedule, visa, hotel and expenses claim\nAssist in other ad hoc assignments and projects if necessary\nRequirements\n\nDegree holder in Business Administration or related disciplines or formal secretarial training is preferred\nAt least 1-3 years of secretarial experience in toys industry is an advantage\nFluent in written & spoken English & Mandarin\nProficiency in Microsoft Office (e.g. Excel, Word)\nDetail-minded, Smart, FAST pace , High stress resistance , Multi-task with a strong sense of responsibility\nGood interpersonal and communication skills\nImmediate available is preferred\n\n** Personal data will be treated with strict confidential and used for recruitment purpose only.", "employment_types": ["Full Time"], "selling_points": [], "locations": ["Hung Hom"], "categories": ["Admin & HR", "Personal / Executive Assistant", "Secretary", "Recruitment / Executive Search"], "post_time": "2022-01-15T03:50:33Z", "salary": {"currency": null, "max": null, "min": null, "period": "monthly", "term": null}, "salary_visible": false, "title_keywords": ["officer", "hr", "executive assistant", "admin", "hr & admin assistant"], "responsibilities": ["ad hoc duties", "attendance", "management", "mpf", "administrative support", "hr", "review", "systems", "hr reports", "recruitment", "payments", "payroll", "administration"], "requirements": {"degrees": ["diploma or above", "degree holder"], "majors": ["related disciplines", "business administration"], "languages": ["english", "mandarin"], "language_level": ["fluent"], "hard_skills": ["excel", "microsoft office", "word", "dynamic", "ms office"], "soft_skills": ["efficient", "detail-minded", "dynamic environment", "communication skills", "multi-task", "sense of responsibility", "interpersonal", "accurate", "responsive", "presentation"], "languages_combined": [{"language": "english", "language_level": ["fluent"]}, {"language": "mandarin", "language_level": ["fluent"]}]}, "experience_required": {"duration": ["minimum of 2-3 year", "at least 1-3 years", "at least 2-6 years"], "field": ["toys", "secretarial", "related", "relevant working experience", "human resources", "administration"]}}, {"job_id": "100003009041237", "location_code": "hk", "company": "CareER Association Limited", "job_title": "NGO Recruitment Consultant (one year contract)", "description": "CareER Association Limited\n\nWorking location: Ngau Tau Kok\n\nSalary provided\n\nCompany Description\n\nCareER\u00a0is the first joint community for students and graduates of all higher education institutions in Hong Kong with disabilities and special education needs (SENs). It was established in 2013 by three founders and a group of passionate, highly educated graduates with disabilities with the aim of creating a platform for students to help one another through alumni experience sharing and a charitable job matching platform leveraging professional HR expertise. It is the first platform of its kind to bring together a group of energetic young talents with disabilities who are committed to changing the way employers and society look at people with disabilities.\u00a0\nhttps://career.org.hk/\n\nCareER\u00a0was registered as a charity in 2014 and continues its efforts to encourage the disabled to develop their careers, with a focus on the often-overlooked community of higher educated persons with disabilities and SENs. In view of our rapid expansion, we are now hiring a temporary contract position in the following capacities:\n\nMain Responsibilities\n\nReporting to Senior Manager in Recruitment Lead, this person will actively involve in the full recruitment cycle and hiring process to support CareER members and inclusive employers on a daily basis\u00a0\n\nProvide consultation to engage employers, candidates and relevant stakeholders including campus SEN offices, NGO partners, coaches and counselors in leveraging resources to promote and succeed inclusive hiring and maintain sustainable partnership\u00a0\n\nSupport in our signature Career Development Program which include summer internship job placements and hosting job skills training workshops throughout the year\n\nSupport in our annual Inclusive Recruitment Fair and Capability Building Workshop to promote workplace diversity and inclusion\n\nWork seamlessly across different project teams internally and externally to increase CareER members exposure into a wide variety of job opportunities\n\nJob Requirements\n\nDegree or above in any discipline with at least 2-3 years of relevant recruitment experience (acquired in headhunting agency preferred)\n\nCandidates with consulting or career coaching background or familiar with personality assessment tools will be highly favorable\u00a0\n\nPassionate in Diversity & Inclusion, prior experience with SEN or disabilities good to have but not a must\n\nStrong team player, well-presented with excellent communication and presentation skills\n\nBeing flexible and dynamic, open-minded, hands-on with can-do attitude\u00a0\u00a0\n\nProficient in English and Chinese \u00a0\n\nApplication deadline: 28th January 2022\u00a0\n\nInterested parties please apply with your updated resume in Word/PDF format or contact Ada at 3844 6327 for a confidential discussion.\u00a0Shortlisted candidates will be invited to attend a face-to-face interview at our office.", "employment_types": ["Full Time", "Contract"], "selling_points": ["Hands-on Recruitment and Career Support", "New Headcount and Team Expansion", "Young, Energetic and Compassionate Team"], "locations": ["Ngau Tau Kok"], "categories": ["Admin & HR", "Recruitment / Executive Search"], "post_time": "2022-01-12T03:38:01Z", "salary": {"currency": null, "max": null, "min": null, "period": "monthly", "term": null}, "salary_visible": false, "title_keywords": ["recruitment consultant"], "responsibilities": ["reporting", "workshop", "teams", "maintain", "recruitment", "career development"], "requirements": {"degrees": ["degree or above"], "majors": [], "languages": ["english", "chinese"], "language_level": ["proficient"], "hard_skills": ["dynamic"], "soft_skills": ["passionate", "flexible", "can-do attitude", "open-minded", "communication", "presentation skills", "dynamic", "hands-on", "team player"], "languages_combined": [{"language": "english", "language_level": ["proficient"]}, {"language": "chinese", "language_level": ["proficient"]}]}, "experience_required": {"duration": ["at least 2-3 years"], "field": ["agency", "recruitment"]}}, {"job_id": "100003009050859", "location_code": "hk", "company": "Williams Lea (Hong Kong) Ltd", "job_title": "HR Officer", "description": "Job Responsibilities:\n\nIdentifying, proactively sourcing, cultivating, assessing, and managing high quality candidates through the full candidate lifecycle\nBuilding talent pipelines to fill current and future roles and drive improvements in time to hire\nWork with the candidates and our interviewers to schedule interviews\nUtilizing the applicant tracking system to actively track, manage and report candidate pipelines\nSupport the conversion process for the offerees\nWork with other HR functions to prepare the related documents and process\nSupport the recruiting, training, and staffing activities\nOther ad-hoc requests as needed\n\nJob Requirement:\n\nBachelor\u2019s degree with at least 2 years of relevant experience\nProficiency in MS Office, particularly Excel, PowerPoint, Word, and Outlook\nExcellent oral and written communication skills in English, Cantonese, and Mandarin Chinese\nAble to perform well in a fast-paced, deadline driven and service-oriented environment\nStrong interpersonal skills and ability to work independently and effectively in a virtual team environment, partnering across functions, geographies, cultures, and staff levels\nTeam player, highly motivated, energetic, resourceful, and friendly\n\nWe offer attractive remuneration package to the successful candidate.\u00a0 In addition, you will have an opportunity to work in a reputable company with excellent career exposure.\u00a0 Interested parties, please click \"APPLY NOW\" to submit your application.\n\nAll information provided will be treated confidentially and used solely for recruitment purpose.\u00a0", "employment_types": ["Full Time", "Temporary", "Contract"], "selling_points": ["Work Location: Quarry Bay", "Monday to Friday 0900 - 1800", "AL 15 Days, Medical & Dental Coverage"], "locations": ["Quarry Bay"], "categories": ["Admin & HR", "HR Supporting Staff", "Recruitment / Executive Search"], "post_time": "2022-01-14T11:36:27Z", "salary": {"currency": null, "max": null, "min": null, "period": "monthly", "term": null}, "salary_visible": false, "title_keywords": ["hr officer"], "responsibilities": ["tracking", "related documents", "hr", "quality", "schedule", "ad-hoc requests", "report"], "requirements": {"degrees": ["degree", "bachelor"], "majors": [], "languages": ["cantonese", "english", "mandarin chinese"], "language_level": ["excellent"], "hard_skills": ["excel", "word", "powerpoint", "outlook", "ms office"], "soft_skills": ["communication skills", "oral", "work independently", "resourceful", "service-oriented", "motivated", "interpersonal skills", "friendly", "team player", "energetic", "driven"], "languages_combined": [{"language": "cantonese", "language_level": ["excellent"]}, {"language": "english", "language_level": ["excellent"]}, {"language": "mandarin chinese", "language_level": ["excellent"]}]}, "experience_required": {"duration": ["at least 2 years"], "field": ["relevant experience"]}}, {"job_id": "100003009049392", "location_code": "hk", "company": "Amika", "job_title": "Senior Human Resources Officer", "description": "Job Duties:\n\nHandling full spectrum of HR functions\nResponsible for payroll calculation, reviewing supporting document\nWork with line managers to determine hiring needs and select suitable candidates for final selection\nPrepare HR reports on regular basis for management review\nAssist in ad hoc projects\n\nJob Requirements:\n\nA Degree in Human Resources Management, Business Administration or related discipline;\nAt least 5 years of working experience in HR generalist position\u00a0\nGood interpersonal & communication skills;\nFamiliar with Employment Ordinance, MPF schemes and regulations\nMulti-tasking, meticulous, organized and able to meet tight work deadlines\nPleasant, strong sense of accountability and passionate about people\nGood command of written and spoken English and Chinese\nLess experience will be considered as Human Resources Officer", "employment_types": ["Full Time", "Permanent"], "selling_points": ["We put people first", "Good development opportunities", "Handling full spectrum of HR functions"], "locations": ["Kwun Tong"], "categories": ["Admin & HR", "Compensation & Benefits", "HR Supporting Staff", "Recruitment / Executive Search"], "post_time": "2022-01-14T08:36:09Z", "salary": {"currency": null, "max": null, "min": null, "period": "monthly", "term": null}, "salary_visible": false, "title_keywords": ["senior human resources officer"], "responsibilities": ["hr", "hr reports", "ad hoc projects", "payroll", "management review"], "requirements": {"degrees": ["degree"], "majors": ["business administration"], "languages": ["english", "chinese"], "language_level": ["good command"], "hard_skills": [], "soft_skills": ["organized", "communication skills", "meticulous", "accountability", "pleasant", "multi-tasking", "interpersonal", "passionate about"], "languages_combined": [{"language": "english", "language_level": ["good command"]}, {"language": "chinese", "language_level": ["good command"]}]}, "experience_required": {"duration": ["at least 5 years"], "field": ["hr generalist", "human resources"]}}, {"job_id": "100003009040746", "location_code": "hk", "company": "Edge Franchising Co. Limited", "job_title": "Human Resources Executive", "description": "APJ Hong Kong ( www.apjcorp.com.hk ) provides the highest quality software development, maintenance and testing services.\u00a0 We have cost effective service centers with highly qualified IT professionals in Hong Kong. Our clients include major enterprises and organizations in the Finance, Manufacturing, Public Utility, Retail, healthcare and Government sectors. We are looking for Solution Architect.\n\nYou will be involving\u2026\n\nTo act as the technical design leader for Azure cloud or other applications solution\nTo understand business objectives, user requirements and lead the team on solution architecture and design\nTo work closely with Solution team, IT Team and Sales Team to prepare business and technical proposals with viable solutions for clients\nTo perform system analysis, design and development of applications using Azure cloud or other technologies\nLead the PoC, technical assessment on solutions\n\nWe are looking for\u2026\n\nDegree holder in Computer Science/Computer Engineering or related discipline\nMinimum 6 years of solid experiences in application design and technical architecture, particularly Azure based cloud solutions\nStrong experience in design and implementing Webs, Mobile Applications, .NET, and DevOps\nExperience in migrating on-premise .Net solutions to Azure cloud would be an advantage\nExperience in Scaled agile framework would be an advantage\nProficient in written and spoken English and Chinese with strong communication skills\nResponsible, proactive and detail minded\n\nWe are offering\u2026\n\n5-day work\nAttractive package\nYear \u2013 end bonus\nMedical insurance\nFestival gifts\nExcellent project exposure and career development opportunities\n\nIf you are interested in sizable project and want to start a new challenging job into public institution industry, please feel free to apply with your full resume, present/expected salary, and availability by click on the 'Apply Now' button.", "employment_types": ["Full Time", "Permanent"], "selling_points": [], "locations": ["Causeway Bay"], "categories": ["Admin & HR", "Compensation & Benefits", "HR Supporting Staff", "Recruitment / Executive Search"], "post_time": "2022-01-13T18:54:31Z", "salary": {"currency": null, "max": null, "min": null, "period": "monthly", "term": null}, "salary_visible": false, "title_keywords": ["human resources executive"], "responsibilities": ["cost", "software", "maintenance", "analysis", "quality", "design", "testing", "communication", "sales team", "career development", "insurance", "architecture"], "requirements": {"degrees": ["degree holder"], "majors": ["computer engineering", "computer science"], "languages": ["english", "chinese"], "language_level": ["proficient"], "hard_skills": ["azure", "agile", "maintenance", "analysis", "devops", "mobile"], "soft_skills": ["communication skills", "agile", "responsible", "interested in", "proactive"], "languages_combined": [{"language": "english", "language_level": ["proficient"]}, {"language": "chinese", "language_level": ["proficient"]}]}, "experience_required": {"duration": ["minimum 6 years"], "field": ["design"]}}, {"job_id": "100003009047169", "location_code": "hk", "company": "G4S (Hong Kong - Holding) Limited", "job_title": "Human Resources Assistant - Recruitment", "description": "APJ Hong Kong ( www.apjcorp.com.hk ) provides the highest quality software development, maintenance and testing services. \u00a0We have cost effective service centers with highly qualified IT professionals in Hong Kong. Our clients include major enterprises and organisations in the Finance, Manufacturing, Public Utility, Retail, Healthcare and Government sectors.\n\nJob Description\n\nAs a Scrum Master you will ensure the teams following the principles of Scrum. Your key responsibilities will include:\n\nService to the Team:\n\nCoaching the team in self-organization and cross-functionality\nHelp team to create high-value increment that meets the definition of Done\nRemoving impediments to the team\u2019s progress\nEnsuring that all Scrum events take place and are positive, productive, and kept within the timebox\n\nService to the Product Owner:\n\nHelping find techniques for effective Product Goal definition and Product Backlog management\nHelping the Scrum Team understand the need for clear and concise Product Backlog items\nHelping establish empirical product planning for a complex environment\nFacilitating stakeholder collaboration as requested or needed\n\nService to the Organization:\n\nLeading, training, and coaching the organization in its Scrum adoption;\nPlanning and advising Scrum implementations within the organization;\nHelping employees and stakeholders understand and enact an empirical approach for complex work; and,\nRemoving barriers between stakeholders and Scrum Teams.\n\nQualifications:\n\nBachelor\u2019s Degree in Computer Science or relevant disciplines; or equivalent.\nOver 6 years\u2019 post qualification Information Technology (IT) related experience.\nHave 2 years\u2019 experience with agile development using Scrum.Strong agile experience is preferrable\nScrum Master, should obtained or obtaining scrum master certification (such as Profession Scrum Master I or above, or equivalent)\nSound experience in Lean-agile software and systems development at scale.\nAble to track and report progress to management with Agile Management tools and methodology\n\nWe are offering\u2026\n\n5-day work\nAttractive package\nYear \u2013 end bonus\nMedical insurance\nFestival gifts\nEducation allowance\nExcellent project exposure and career development opportunities", "employment_types": ["Full Time"], "selling_points": ["Tertiary education or above", "Minimum 1 year experience in Human Resources", "outgoing personality.willing to work long hours"], "locations": ["Lai Chi Kok"], "categories": ["Admin & HR", "Recruitment / Executive Search"], "post_time": "2022-01-14T02:30:35Z", "salary": {"currency": null, "max": null, "min": null, "period": "monthly", "term": null}, "salary_visible": false, "title_keywords": ["human resources assistant"], "responsibilities": ["cost", "management", "software", "maintenance", "systems", "quality", "teams", "agile development", "testing", "career development", "report", "insurance", "planning"], "requirements": {"degrees": ["degree", "bachelor", "master"], "majors": ["computer science"], "languages": [], "language_level": [], "hard_skills": ["goal", "lean", "agile", "maintenance"], "soft_skills": ["productive", "clear", "agile", "positive"], "languages_combined": []}, "experience_required": {"duration": ["6 years", "2 years"], "field": ["related", "development", "it", "information technology"]}}, {"job_id": "100003009048901", "location_code": "hk", "company": "Asia Satellite Telecommunications Co Ltd", "job_title": "Manager, Human Resources & Administration", "description": "Job Functions\n\n\nAssist in formulating the definition, revision and release of software development related processes, procedures and templates;\nResponsible for the promotion of processes, procedures and templates;\nDevelop a software quality assurance plan for the project;\nAudit the process and products of the project according to the software quality assurance plan. Issue an audit report to assist the project team in resolving audit findings;\nFollow up the problems found in the project audit process until the problems are solved;\nCollect improvement suggestions on processes and templates from each project team, formulate and continuously improve the software development process according to the company and project conditions;\nVerify the relevant measurement data provided by the project, identify potential project issues via data analysis.\nProvide process management and quality assurance consulting or training for related projects;\nTimely report the findings in audit of process and work product audit in the project to superiors, project managers, and ODC managers with objective insight\n\nJob Requirements\n\nMore than 3 years of software industry experience, and more than 2 years of software quality assurance experience;\nPossess basic knowledge of software development, software engineering, and quality management system;\nPossess the basic ability of technical review and process audit;\nHave statistics-related knowledge, and be able to use statistical methods well for quality analysis, control and management capabilities\nCheerful personality, teamwork spirit and good communication and coordination skills;\nHave good language organization ability and document writing ability;\nHave experience in training internal employees;\nGood level of English and Mandarin;\nFamiliar with CMMI or ISO9001 is preferred.\n\u00a0", "employment_types": ["Full Time", "Permanent"], "selling_points": ["Manage full spectrum of Human Resources services", "Min 8 years' experience in sizable establishment", "Immediate available is highly preferred"], "locations": ["Tai Po Area"], "categories": ["Admin & HR", "Compensation & Benefits", "HR Director / Manager", "Recruitment / Executive Search"], "post_time": "2022-01-14T07:40:24Z", "salary": {"currency": null, "max": null, "min": null, "period": "monthly", "term": null}, "salary_visible": false, "title_keywords": ["manager", "human resources"], "responsibilities": ["management", "control", "software", "consulting", "data", "analysis", "review", "quality", "procedures", "audit", "develop", "measurement", "data analysis", "communication", "plan", "coordination", "report"], "requirements": {"degrees": [], "majors": [], "languages": ["english", "mandarin"], "language_level": ["good"], "hard_skills": ["analysis", "basic"], "soft_skills": ["cheerful", "coordination skills", "responsible", "timely", "communication", "teamwork spirit"], "languages_combined": [{"language": "english", "language_level": ["good"]}, {"language": "mandarin", "language_level": ["good"]}]}, "experience_required": {"duration": ["3 years", "2 years"], "field": ["training", "quality assurance"]}}, {"job_id": "100003009048075", "location_code": "hk", "company": "ADECCO", "job_title": "HR Executive", "description": "Job Duties\n\n\u00b7\u00a0\u00a0\u00a0\u00a0\u00a0\u00a0\u00a0\u00a0Liaise, communicate with internal and external parties effectively\n\n\u00b7\u00a0\u00a0\u00a0\u00a0\u00a0\u00a0\u00a0\u00a0Understand stakeholders and stakeholder\u2019s material quickly and translate information verbally and in writing in readable format\n\n\u00b7\u00a0\u00a0\u00a0\u00a0\u00a0\u00a0\u00a0\u00a0Prepare presentations using PowerPoint, variety of different reports, etc.\n\n\u00b7\u00a0\u00a0\u00a0\u00a0\u00a0\u00a0\u00a0\u00a0To provide all-rounded support to the manager\n\nRequirements\n\n\u00b7\u00a0\u00a0\u00a0\u00a0\u00a0\u00a0\u00a0\u00a0Detail-minded and responsible, sensitive to numbers\n\n\u00b7\u00a0\u00a0\u00a0\u00a0\u00a0\u00a0\u00a0\u00a0Proactive, presentable, and can-do attitude\n\n\u00b7\u00a0\u00a0\u00a0\u00a0\u00a0\u00a0\u00a0\u00a0Able to work independently with minimum supervision\n\n\u00b7\u00a0\u00a0\u00a0\u00a0\u00a0\u00a0\u00a0\u00a0Excellent command of\u00a0English\n\n\u00b7\u00a0\u00a0\u00a0\u00a0\u00a0\u00a0\u00a0\u00a0Proficient in MS Word, MS Excel and MS PowerPoint\n\n\u00b7\u00a0\u00a0\u00a0\u00a0\u00a0\u00a0\u00a0\u00a03 years experience in IT industry/Business Administration preferred", "employment_types": ["Full Time", "Permanent"], "selling_points": ["Develop HR initiatives", "Talent Acquisition", "Learning & Development"], "locations": ["North Point"], "categories": ["Admin & HR", "Compensation & Benefits", "Recruitment / Executive Search", "Training & Development"], "post_time": "2022-01-14T04:41:45Z", "salary": {"currency": null, "max": null, "min": null, "period": "monthly", "term": null}, "salary_visible": false, "title_keywords": ["hr", "executive"], "responsibilities": ["liaise", "communicate with", "internal and external parties", "presentations", "reports"], "requirements": {"degrees": [], "majors": [], "languages": ["english"], "language_level": ["excellent"], "hard_skills": ["ms powerpoint", "ms excel", "ms word"], "soft_skills": ["detail-minded", "work independently", "responsible", "can-do attitude", "presentable", "sensitive to numbers", "proactive"], "languages_combined": [{"language": "english", "language_level": ["excellent"]}]}, "experience_required": {"duration": ["3 years"], "field": ["it", "business administration"]}}, {"job_id": "100003009047535", "location_code": "hk", "company": "Wealth Dimensions Consultancy Limited", "job_title": "Senior Recruitment Consultant (Banking and Finance)", "description": "APJ Hong Kong ( www.apjcorp.com.hk ) provides the highest quality software development, maintenance and testing services.\u00a0 We have cost effective service centers with highly qualified IT professionals in Hong Kong. Our clients include major enterprises and organizations in the Finance, Manufacturing, Public Utility, Retail, healthcare and Government sectors. We are looking for Project Manager.\n\nYou will be involving\u2026\n\nDevelop comprehensive project plans to be shared with clients as well as other staff members\nTo lead the entire cycle of the software development project, including but not limit to analyse business requirements and specify functional requirements of a new system, develop project plan and schedule, mange the cost and quality of works, prepare documentations\nTo effectively communicate project matters to all levels of stakeholders\nEngage with project governance on project performance and change management matters\nTo\u00a0mobilise\u00a0the project team in Hong Kong and offshore, and to supervise the work and performance of all project team members\nLead & control the project related risk management process & ad-hoc tasks as assigned\n\nWe are looking for\u2026\n\nDegree holder in Computer Science or related is preferred\nPMP cert is a must\nAt least 8 years\u2019 work experience in project management for corporate or enterprises.\nProficient in SDLC project management execution and business analysis experience\nWell-organized, attention to detail\nExcellent communication skill\nGood command of written and spoken English and Chinese as well as Putonghua\nSI Experience is an advantage\n\nWe are offering\u2026\n\n5-day work\nAttractive package\nYear \u2013 end bonus\nMedical insurance\nFestival gifts\nExcellent project exposure and career development opportunities\n\nIf you are interested in sizable project and want to start a new challenging job into public institution industry, please feel free to apply with your full resume, present/expected salary, and availability by click on the 'Apply Now' button.", "employment_types": ["Full Time", "Permanent", "Freelance"], "selling_points": ["1 year or above working experience", "360 recruitment consultant", "5 Days Work"], "locations": ["Admiralty"], "categories": ["Banking / Finance", "Others", "Sales, CS & Business Devpt", "Customer Service - Manager", "Admin & HR", "Recruitment / Executive Search"], "post_time": "2022-01-14T03:24:11Z", "salary": {"currency": null, "max": null, "min": null, "period": "monthly", "term": null}, "salary_visible": false, "title_keywords": ["recruitment consultant"], "responsibilities": ["software", "quality", "communication", "plans", "control", "testing", "develop", "schedule", "cost", "management", "change management", "career development", "maintenance", "ad-hoc tasks", "project plan", "project management", "business analysis", "insurance", "analyse"], "requirements": {"degrees": ["degree holder"], "majors": ["computer science"], "languages": ["putonghua", "english", "chinese"], "language_level": ["good command"], "hard_skills": ["maintenance", "analysis", "project management", "sdlc", "pmp", "documentations"], "soft_skills": ["communication skill", "well-organized", "interested in", "project management", "comprehensive", "attention to detail"], "languages_combined": [{"language": "putonghua", "language_level": ["good command"]}, {"language": "english", "language_level": ["good command"]}, {"language": "chinese", "language_level": ["good command"]}]}, "experience_required": {"duration": ["at least 8 years"], "field": ["business analysis", "project management"]}}, {"job_id": "100003009047377", "location_code": "hk", "company": "AP Rentals Limited", "job_title": "Administration & Human Resources Assistant", "description": "Responsibilities:\n\nTAM is the representative of the business department to provide advice to customers on service and solutions with technical aspects, assist customers to finalize the proper offering which is suitable to their needs.\nAssist the customers and cooperate with the Business Manager to go through the selling cycle, refine the sales process if needed.\nCommunicate closely with Service Delivery Team on customer requirements and our offering, to ensure the smooth transition from presales stage to delivery stage on individual project.\nMaintain close relationship with customers, response customer enquiries, monitor the project delivery status, and provide regular feedback and improvement suggestions to both Business Team and Delivery Team.\nCooperate with Business Manager as a team to generate sales leads and achieve sales target.\n\nRequirements:\n\nMinimum 8 years of relevant experiences with at least 4 years in presales, solution or service consultant, project management areas.\nAccount management and customer services experiences is highly preferred.\nGood knowledge on software development lifecycle, solid understanding on various software development technologies and platforms\nExperiences on working with offshore development team or overseas service and solution supplier is a plus\nBachelor\u2019s degree in Computer Science, Information Systems Management or relevant fields\nNumber sensitive, good analytical problem-solving skills\nStrong communication, interpersonal and presentation skills\nAggressive and passionate, customer centric and target oriented.", "employment_types": ["Full Time", "Permanent"], "selling_points": [], "locations": ["Yuen Long"], "categories": ["Admin & HR", "Clerical / Admin Staff", "HR Supporting Staff", "Recruitment / Executive Search"], "post_time": "2022-01-14T02:56:36Z", "salary": {"currency": null, "max": null, "min": null, "period": "monthly", "term": null}, "salary_visible": false, "title_keywords": ["human resources assistant"], "responsibilities": ["service delivery", "customer enquiries", "sales target", "monitor", "provide advice", "maintain", "generate sales leads", "cooperate with"], "requirements": {"degrees": ["degree", "bachelor"], "majors": ["computer science"], "languages": [], "language_level": [], "hard_skills": ["problem-solving skills", "project management", "plus"], "soft_skills": ["passionate", "communication", "project management", "presentation skills", "sensitive", "problem-solving skills", "interpersonal"], "languages_combined": []}, "experience_required": {"duration": ["minimum 8 years", "at least 4 years"], "field": ["development", "customer services", "project management", "account management", "team"]}}, {"job_id": "100003009044208", "location_code": "hk", "company": "Randstad Hong Kong Limited", "job_title": "Recruitment Consultant (Banking & Financial Services)", "description": "about the company.\n\nRandstad is the leading global professional recruiting group, experts at recruiting qualified, professional and skilled people globally. We are a Fortune 500 company, the 2nd largest recruiting specialist in the world representing more than 90 percent of the global HR services market. Randstad operates from 4587 offices in 39 countries across 20 specialisms and we send over 500,000 people to work everyday.\n\nIn Hong Kong we are expanding our banking & finance division and we are looking for a recruiter to join our driven and dynamic team, and share our vision of being the number one in the professional recruitment industry.\n\nabout the role\n\nAs a Consultant at Randstad Hong Kong you manage and develop your own list of clients and candidates. You learn your clients' requirements to gain a detailed understanding of their specific needs and build a strong, ongoing relationship. You get to know your candidates, sell the best match, and manage your talent pool by staying in regular contact and coaching and developing as appropriate.\n\nabout the job.\nResponsible for all recruitment placements within the banking & finance space covering mid to senior job profiles specializing in risk & compliance\nDevelop and build a solid up-to-date candidate database\nDeliver high quality recruitment consultancy and services to all new and existing clients\nBusiness development with new business and maintain strong relationships with existing clients\nTeam support ensure team work efficiency\nMarket mapping, understanding and expertise within line of service\nskills & experiences required.\nUniversity degree or higher education discipline\n1+ years relevant recruitment experience within banking & finance is most ideal\nMust consistently meet both individual and team targets\nStrong communication skills with solid business development acumen is essential\nMust be able to work in a fast growing pace environment\nFlexible and positive work attitude is a must\n\nInterested candidates, please send your updated resume to Prerna Bajaj at prerna.bajaj@randstad.com.hk", "employment_types": ["Full Time", "Permanent"], "selling_points": ["MNC recruitment company", "5 days work, attractive benefits", "competitve commission scheme"], "locations": ["Not Specified"], "categories": ["Banking / Finance", "Others", "Admin & HR", "HR Supporting Staff", "Recruitment / Executive Search"], "post_time": "2022-01-13T03:24:51Z", "salary": {"currency": null, "max": null, "min": null, "period": "monthly", "term": null}, "salary_visible": false, "title_keywords": ["recruitment consultant"], "responsibilities": ["hr", "compliance", "quality", "developing", "develop", "communication", "maintain", "recruitment", "contact", "database", "banking"], "requirements": {"degrees": ["university degree"], "majors": [], "languages": [], "language_level": [], "hard_skills": ["dynamic", "acumen"], "soft_skills": ["flexible", "communication skills", "responsible", "detailed", "dynamic", "positive work attitude", "driven", "ideal"], "languages_combined": []}, "experience_required": {"duration": ["1+ years"], "field": ["finance", "recruitment", "banking"]}}, {"job_id": "100003009044923", "location_code": "hk", "company": "Manrison Personnel Limited", "job_title": "Human Resources Officer (Medical industry, up to 35K)", "description": "Our client, the world\u2019s leading provider of genomic sequencing services and proteomic services, dedicated to hire an all rounded Human Resources Officer to support their daily operations.\n\nResponsibilities:\n\nPerform all rounded HR Generalist duties major in Compensation & Benefits and daily operations\nHandle MPF administration, taxation, payroll calculation and prepare final payment\nAdministrate monthly payroll for the companies\nAssist in coordinate employee relations activities, training arrangement, delivery of in-house training & seminar\nCompile regular HR related statistics and reports for management review\nParticipate in ad hoc duties as assigned\n\nRequirements\n\nDegree in Human Resources Management or related disciplines;\nAt least\u00a0 years solid experience in Human Resources, preferably in healthcare, medical industry;\nWell versed in Hong Kong Employment Ordinance and other HR related ordinances;\nPositive thinking, attentive to details, independent and good team-player;\nGood interpersonal and communication skills;\nProficient in MS Word, Excel, PowerPoint and Chinese Word Processing;\nGood commend in both written and spoken English & Chinese\n\n***Immediate available is highly preferred\n\nTo apply for this position, please simply click on the \u201cAPPLY NOW\u201d bottom to forward an up-to-date copy of your resume. All applications will be treated in strict confidence and used for recruitment purposes only. If this job isn't quite right for you but you are looking for a new position, please contact Ms. Fung at 6110-5379 for a confidential discussion on your career.", "employment_types": ["Full Time", "Permanent"], "selling_points": ["8-10 year work experience", "5-day work, Attractive Salary Package", "Dynamic work environment"], "locations": ["Tai Po Area"], "categories": ["Admin & HR", "Compensation & Benefits", "HR Supporting Staff", "Recruitment / Executive Search"], "post_time": "2022-01-13T06:38:37Z", "salary": {"currency": "HKD", "max": 34999, "min": 30000, "period": "monthly", "term": null}, "salary_visible": true, "title_keywords": ["human resources officer"], "responsibilities": [], "requirements": {"degrees": [], "majors": [], "languages": [], "language_level": [], "hard_skills": [], "soft_skills": [], "languages_combined": []}, "experience_required": {"duration": [], "field": []}}, {"job_id": "100003009043834", "location_code": "hk", "company": "Fosun Hani Securities Limited", "job_title": "HR Business Partner/Talent Acquisition  (New headcount)", "description": "Job Description\n\n-Manage end to end hiring cycle (all business line)\n-New employee orientation / staff training\n-Identify department hiring needs, and share market trend\n-To support on working visa application/renewal\n\nRequirements\n\n-Bachelor Degree or above\n-3 years of relevant recruitment experience from HH agency\n-Fluent in Mandarin, English speaking\u00a0", "employment_types": ["Full Time", "Permanent"], "selling_points": ["Exciting opportunities on BP/TA", "New headcount (recruitment team)", "Competitive Benefit package"], "locations": ["Central"], "categories": ["Banking / Finance", "Financial Services", "Others", "Admin & HR", "Recruitment / Executive Search"], "post_time": "2022-01-13T02:07:15Z", "salary": {"currency": null, "max": null, "min": null, "period": "monthly", "term": null}, "salary_visible": false, "title_keywords": ["hr"], "responsibilities": [], "requirements": {"degrees": ["degree or above"], "majors": [], "languages": ["english", "mandarin"], "language_level": [], "hard_skills": [], "soft_skills": [], "languages_combined": [{"language": "english", "language_level": []}, {"language": "mandarin", "language_level": []}]}, "experience_required": {"duration": [], "field": ["agency", "recruitment"]}}, {"job_id": "100003009047388", "location_code": "hk", "company": "Tung Chun Management Services Company Limited", "job_title": "HR & Admin Officer / Assistant HR & Admin Officer", "description": "Job Descriptions:\n\nPerform full spectrum of HR functions, including recruitment, C&B, performance management, training & development, employee relations\nWork independently in payroll, taxation and MPF administration\nAssist in executing, reviewing and formulating HR related polices and procedures\nAssist in any ad hoc projects and events as assigned\n\nRequirements\u00a0:\n\nDegree holder in Human Resources Management or Business Administration\n2-3 year\u2019s relevant working experience\nWell-versed in Employment Ordinance and Human Resources practices in Hong Kong\nSolid payroll experience in sizable organizations\nProficient in Microsoft Excel is a must\nExperience in HRIS implementation would be an advantage\nGood command of both written and spoken English and Chinese\nGood communication and organization skills\nStrong at numeric or statistical computation\nImmediate available is preferred\nCandidates with less experience would be considered as Assistant HR & Admin Officer\n\nWe offer excellent career advancement and development opportunities, not limit to provide promotion prospect plus attractive fringe benefits including\u00a0Alt Sat off,\u00a0discretionary bonus, discretionary year end bonus and medical coverage to the right candidate.\u00a0\u00a0 Interested parties, please click \"Apply Now\" and provide full particulars including qualification, working experience, earliest date available, current & expected salary.\n\nWe are equal opportunity employer and welcome applications from all qualified candidates. The\u00a0information provided will be treated in strict confidence and be used only for consideration of your application for relevant/similar post(s) within the Tung Chun Group.\n\n\nApplicants not hearing from us within four weeks from the date of advertisement may consider their applications unsuccessful. All personal date of unsuccessful applicants will be destroyed after the recruitment exercise when no longer required.", "employment_types": ["Full Time"], "selling_points": [], "locations": ["Mong Kok"], "categories": ["Admin & HR", "Compensation & Benefits", "HR Supporting Staff", "Recruitment / Executive Search"], "post_time": "2022-01-14T02:58:04Z", "salary": {"currency": null, "max": null, "min": null, "period": "monthly", "term": null}, "salary_visible": false, "title_keywords": ["officer", "hr", "admin", "assistant"], "responsibilities": ["taxation", "management", "mpf", "hr", "procedures", "recruitment", "executing", "ad hoc projects", "payroll", "administration"], "requirements": {"degrees": ["degree holder"], "majors": ["business administration"], "languages": ["english", "chinese"], "language_level": ["good command"], "hard_skills": ["plus", "microsoft excel"], "soft_skills": ["communication", "organization skills"], "languages_combined": [{"language": "english", "language_level": ["good command"]}, {"language": "chinese", "language_level": ["good command"]}]}, "experience_required": {"duration": ["2-3 year"], "field": ["admin", "hr", "payroll", "relevant working experience"]}}, {"job_id": "100003009043426", "location_code": "hk", "company": "Osmium Consulting Group Limited", "job_title": "Recruitment Coordinator", "description": "Responsibilities:\nSupporting teams with recruitment projects as required, such as preparing candidate packs and associated materials for a recruitment event\nRunning standard reports from the recruitment system to ensure an effective flow of management information to internal stakeholder\nArranging meetings/calls between the recruitment team and internal and external stakeholders\nPro-actively contributing to initiatives and/or projects across all teams as required\n\nRequirements:\n\nGood in Engish and Mandarin and Cantonese\nHold a Bachelor Degree\nExcellent communication skills (verbal and written), with an eye for detail\nPossess outstanding organizational and time management skills, with an ability to prioritize and manage multiple projects and tasks simultaneously", "employment_types": ["Full Time", "Permanent"], "selling_points": ["In-house Recruiter / HR", "Good Company Culture & Bonus", "20 - 30K"], "locations": ["Central & Western Area"], "categories": ["Admin & HR", "Others", "Recruitment / Executive Search", "Information Technology (IT)", "Others"], "post_time": "2022-01-12T11:39:05Z", "salary": {"currency": null, "max": null, "min": null, "period": "monthly", "term": null}, "salary_visible": false, "title_keywords": ["coordinator"], "responsibilities": ["recruitment", "management", "teams", "reports"], "requirements": {"degrees": ["degree", "bachelor"], "majors": [], "languages": ["cantonese", "mandarin"], "language_level": ["good"], "hard_skills": [], "soft_skills": ["communication skills", "time management skills", "organizational", "prioritize", "eye for detail"], "languages_combined": [{"language": "cantonese", "language_level": ["good"]}, {"language": "mandarin", "language_level": ["good"]}]}, "experience_required": {"duration": [], "field": []}}, {"job_id": "100003009049400", "location_code": "hk", "company": "Perrett Laver Limited", "job_title": "Research Associate (5 days)", "description": "Perrett Laver is now seeking to hire a bright, dynamic and ambitious individual to join our fast-growing team in Central Hong Kong as Research Associate.\n\n\n\nThis role draws upon the intellectual skills necessary to grasp a complex brief; the research skills to identify people who are at the highest levels in their professions; the advocacy skills to engage such candidates; the motivation to serve our clients to the best of our abilities; and the capacity to work as part of a core project team and a wider corporate team. You will have a thirst for knowledge, a methodical mind-set that will enable you to carry out a comprehensive and global search of the talent pool, and high attention to detail.\n\n\n\nResearch Associates are expected to manage the research phase of the project including background analysis, identification and securing of candidates, and candidate care. They work closely with and support the Project Management Team and the Consultant(s) in the delivery of projects through to the appointment of a preferred candidate.\n\n\n\nWe are seeking people with the following:\n\nOutstanding verbal and written communication skills in both English and Chinese;\nA Master\u2019s degree or above;\nA strong sense of service and the drive to best support our clients and candidates;\nKnowledge and passion in education and non-profit sector;\nAn intellectually curious mind-set;\nA shared commitment to the mission and values of Perrett Laver;\nSharp and rigorous analytical skills and attention to detail, particularly regarding the assessment of candidates;\nAbility to manage multiple projects and to prioritize workload;\nA willingness to work with flexible hours when needed;\nStrong appreciation and understanding of the importance of punctuality, responsibility and discretion required for this role;\nTenacious, committed and results-oriented;\nEnthusiastic and proactive;\nCollaborative, flexible and able to contribute to the development of a growing team;\nFresh graduates are welcome to apply\n\nDesirable\n\nA Graduate degree;\nFluent in Cantonese and Mandarin;\nExperience working within universities, academic organizations or schools or NGO.\n\nNo previous experience working in executive search is required. Perrett Laver will provide rigorous and systematic training for all new hires.\n\nTo Apply\n\nTo apply, please submit an up-to-date CV and Cover Letter via https://candidates.perrettlaver.com/vacancies/ , quoting reference HKPL/RES.", "employment_types": ["Full Time"], "selling_points": ["Higher Education and Research Leadership", "Senior Executive Recruitment Consultation", "Fresh graduates are welcome to apply"], "locations": ["Central"], "categories": ["Professional Services", "Business Consultancy", "Admin & HR", "Recruitment / Executive Search", "Public / Civil", "Social Services - Community / Non-profit Organization"], "post_time": "2022-01-14T08:35:13Z", "salary": {"currency": null, "max": null, "min": null, "period": "monthly", "term": null}, "salary_visible": false, "title_keywords": ["research associate"], "responsibilities": ["communication", "project management", "analysis", "manage multiple projects"], "requirements": {"degrees": ["degree or above", "degree", "master"], "majors": [], "languages": ["cantonese", "english", "chinese", "mandarin"], "language_level": ["fluent"], "hard_skills": ["no", "analysis", "analytical skills", "project management", "dynamic"], "soft_skills": ["flexible", "communication skills", "research skills", "passion in", "collaborative", "prioritize", "analytical skills", "systematic", "project management", "committed", "comprehensive", "dynamic", "enthusiastic", "attention to detail", "willingness to work", "methodical", "proactive", "tenacious"], "languages_combined": [{"language": "cantonese", "language_level": ["fluent"]}, {"language": "english", "language_level": []}, {"language": "chinese", "language_level": []}, {"language": "mandarin", "language_level": ["fluent"]}]}, "experience_required": {"duration": [], "field": []}}]