[{"job_id": "100003009053284", "location_code": "hk", "company": "OSMA Consulting Limited", "job_title": "Executive Assistant \uff08\u8463\u4e8b\u52a9\u7406\uff09", "description": "Our client is a reputable investment group with business lines across multiple industries in Asia. The high level seniors of this group are currently looking for qualified individual to assist on group's daily business and operation.\n\u6211\u4eec\u7684\u5ba2\u6237\u662f\u4e00\u5bb6\u58f0\u8a89\u5353\u8457\u7684\u6295\u8d44\u96c6\u56e2\uff0c\u4e1a\u52a1\u904d\u53ca\u4e9a\u6d32\u591a\u4e2a\u884c\u4e1a\u3002 \u8be5\u96c6\u56e2\u7684\u9ad8\u5c42\u76ee\u524d\u6b63\u5728\u5bfb\u627e\u5408\u683c\u7684\u4e2a\u4eba\u6765\u534f\u52a9\u96c6\u56e2\u7684\u65e5\u5e38\u4e1a\u52a1\u548c\u8fd0\u8425\u3002\n\nResponsibilities:\n-Coordination with internal departments (BD, IR, HR, etc) regarding daily operation;\u00a0\n-Liaising with various external parties (Clients' representatives or Guests) on business affairs;\n-Occasionally attend business meeting with senior management and take minutes ;\u00a0\n-Director's office administration work and back up other admin colleagues when needed;\n-Perform any other ad-hoc requests from management.\n\nQualifications:\n-Bachelor Degree or above;\n-Past experience in finance industry is a plus;\n-Mature and presentable;\n-Good command in English and Chinese.\n\n\n\u804c\u8d23\uff1a\n-\u4e0e\u5185\u90e8\u90e8\u95e8\uff08BD\u3001IR\u3001HR\u7b49\uff09\u5c31\u65e5\u5e38\u8fd0\u4f5c\u8fdb\u884c\u534f\u8c03\uff1b\n-\u5c31\u5546\u52a1\u4e8b\u5b9c\u4e0e\u5404\u79cd\u5916\u90e8\u5404\u65b9\uff08\u5ba2\u6237\u4ee3\u8868\u6216\u5ba2\u4eba\uff09\u8054\u7edc\uff1b\n-\u5076\u5c14\u53c2\u52a0\u4e0e\u9ad8\u7ea7\u7ba1\u7406\u4eba\u5458\u7684\u5546\u52a1\u4f1a\u8bae\u5e76\u505a\u4f1a\u8bae\u8bb0\u5f55\uff1b\n-\u4e3b\u7ba1\u529e\u516c\u5ba4\u884c\u653f\u5de5\u4f5c\uff0c\u5e76\u5728\u9700\u8981\u65f6\u652f\u6301\u5176\u4ed6\u884c\u653f\u540c\u4e8b\uff1b\n- \u6267\u884c\u6765\u81ea\u7ba1\u7406\u5c42\u7684\u4efb\u4f55\u5176\u4ed6\u4e34\u65f6\u8bf7\u6c42\u3002\n\n\u8d44\u683c\uff1a\n-\u672c\u79d1\u53ca\u4ee5\u4e0a\u5b66\u5386\uff1b\n-\u6709\u91d1\u878d\u884c\u4e1a\u7ecf\u9a8c\u8005\u4f18\u5148\uff1b\n-\u6210\u719f\u4e14\u6709\u8d23\u4efb\u5fc3\uff1b\n-\u826f\u597d\u7684\u4e2d\u82f1\u6587\u8868\u8fbe\u3002\n\n", "employment_types": ["Full Time"], "selling_points": ["Reputable investment group", "Excellent career exposure", "Attractive package"], "locations": ["Central"], "categories": ["Admin & HR", "Administration / Operation Manager", "Personal / Executive Assistant", "Secretary"], "post_time": "2022-01-17T06:47:02Z", "salary": {"currency": null, "max": null, "min": null, "period": "monthly", "term": null}, "salary_visible": false, "title_keywords": ["executive assistant"], "responsibilities": ["management", "hr", "external parties", "daily operation", "office administration work", "ad-hoc requests", "senior management"], "requirements": {"degrees": ["degree or above"], "majors": [], "languages": ["english", "chinese"], "language_level": [], "hard_skills": ["plus"], "soft_skills": ["presentable"], "languages_combined": [{"language": "english", "language_level": []}, {"language": "chinese", "language_level": []}]}, "experience_required": {"duration": [], "field": ["finance industry"]}}, {"job_id": "100003009052131", "location_code": "hk", "company": "The Hong Kong Institution of Engineers", "job_title": "Programme Planning & Special Duties Officer (5-Day Work)", "description": "We are now inviting a high caliber candidate to join us for the following position:\n\n\u00a0Executive Secretary / Secretary\n\nJob Duties:\n\nProvide all-rounded secretarial & administrative support to the Managing Director\nSort and review incoming mails/emails/correspondences\nExtensive diary management, organize all local and international travel arrangements and itineraries\nManage and assist in organizing conferences and meetings, prepare agenda, minutes taking\nMaintain filing system and business records for private and corporate projects of highly confidential nature\nBuild good relationship and act as a communication bridge with different levels\nLiaise & co-ordinate with various internal or external parties\nDraft professional all kinds of correspondence\nAssist in ad-hoc projects as required\n\n\u00a0Job Requirements:\n\nDegree holder\nAt least 5 years or above secretarial experience\nCheerful, strong sense of responsibility, team player and well organized\nExcellent spoken and written English, Cantonese and Mandarin\nProficiency in computer software applications including MS-Word, Excel, PowerPoint and Chinese Word Processing\nStrong interpersonal and communication skills\nAble to handle multi-task, priorities work load and work in a fast paced environment\nImmediate available is highly preferred.\n\nWe offer 5 days' work and attractive compensation package to suitable candidates.\u00a0 Interested candidate please send your full resume, portfolio, expected salary & available date to \u201cApply Now\u201d.\n\nAll data collected will be used for recruitment purpose only.\n\n", "employment_types": ["Full Time"], "selling_points": ["Assist in conducting seminars/webinars and events", "Assist in conducting studies/researches", "Provide secretariat support to meetings/committees"], "locations": ["Causeway Bay"], "categories": ["Admin & HR", "Clerical / Admin Staff", "Secretary", "Others"], "post_time": "2022-01-17T02:11:56Z", "salary": {"currency": null, "max": null, "min": null, "period": "monthly", "term": null}, "salary_visible": false, "title_keywords": ["officer"], "responsibilities": ["liaise", "travel arrangements", "management", "administrative support", "co-ordinate with", "review", "external parties", "good relationship", "communication", "conferences", "maintain", "ad-hoc projects"], "requirements": {"degrees": ["degree holder"], "majors": [], "languages": ["cantonese", "english", "chinese", "mandarin"], "language_level": ["excellent", "proficiency"], "hard_skills": ["powerpoint", "ms-word", "chinese word processing", "excel"], "soft_skills": ["communication skills", "cheerful", "multi-task", "sense of responsibility", "well organized", "work in a fast paced environment", "team player", "interpersonal"], "languages_combined": [{"language": "cantonese", "language_level": ["excellent"]}, {"language": "english", "language_level": ["excellent"]}, {"language": "chinese", "language_level": ["proficiency"]}, {"language": "mandarin", "language_level": ["excellent"]}]}, "experience_required": {"duration": ["at least 5 years"], "field": ["secretarial"]}}, {"job_id": "100003009052608", "location_code": "hk", "company": "Coaxial Care Limited", "job_title": "Executive Secretary / Secretary", "description": "Duties:\n\nTo provide necessary coordination and assistance to the organisation of seminars/webinars, events, learned society activities and programmes, and ad-hoc projects\nTo assist in conducting studies/researches for specific topic(s), and collate appropriate information to facilitate the Section in executing all its tasks and activities\nTo provide secretarial support to meetings and ad-hoc committees\nTo assist in the co-ordination of matters relating to membership benefits, school and publication education programmes, etc.\nTo provide documentary support in handling enquiries and complaints\n\nRequirements:\n\nUniversity Graduate, preferably with 1-2 years work experience\nExperience in handlung complaints is an added advantage\nExcellent command of written and spoken English and Chinese\nAttention to details\nStrong PC skills in MC Word, Excel and Chinese word processing\nPossess experience and knowledge of event and online seminar execution will be an advantage\n\nPlease apply in confidence with full career details and salary expectation to the Chief Executive and Secretary, The Hong Kong Institution of Engineers, 9/F Island Beverley, No 1 Great George Street, Causeway Bay, Hong Kong, or click \u201cApply Now\u201d to submit your application. Applicants should indicate clearly on the envelope and in the letter for the post they are applying.\n\nAll information provided by applicants will be treated in strict confidence and used only for recruitment purpose.\u00a0 Only shortlisted candidates will be notified.\u00a0 All personal data of unsuccessful applicants will be destroyed after completion of the recruitment exercise.", "employment_types": ["Full Time", "Permanent"], "selling_points": [], "locations": ["Hung Hom"], "categories": ["Admin & HR", "Secretary"], "post_time": "2022-01-17T03:31:53Z", "salary": {"currency": null, "max": null, "min": null, "period": "monthly", "term": null}, "salary_visible": false, "title_keywords": ["executive secretary", "secretary"], "responsibilities": ["ad-hoc", "executing", "secretarial support", "coordination", "ad-hoc projects"], "requirements": {"degrees": [], "majors": [], "languages": [], "language_level": [], "hard_skills": [], "soft_skills": [], "languages_combined": []}, "experience_required": {"duration": [], "field": []}}, {"job_id": "100003009053167", "location_code": "hk", "company": "", "job_title": "Personal Assistant", "description": "Job responsibilities:-\n\n- Provide full range of secretarial and administrative support to Chairman;\n- Manage calendars, meeting schedules, personal & family affairs including director's quarter maintenance, maids and drivers management, administrative support to the relatives of Chairman;\n- Maintain filling system and confidential information in a professional manner;\n- Closely liaise and coordinate with internal and external parties to ensure smooth business operations.\n\nJobs requirements:-\n\n- Degree holder with 3 years solid experience;\n- Excellent command in spoken and written English, Cantonese and Mandarin;\n- Proficient PC knowledge in MS Word and Excel;\n- Multi-tasking, well-organized, detail-minded with strong communication and interpersonal skills;\n- Immediately available is highly preferred.", "employment_types": ["Full Time", "Permanent"], "selling_points": [], "locations": ["Kwun Tong Area"], "categories": ["Admin & HR", "Personal / Executive Assistant", "Secretary"], "post_time": "2022-01-17T06:13:17Z", "salary": {"currency": null, "max": null, "min": null, "period": "monthly", "term": null}, "salary_visible": false, "title_keywords": ["personal assistant"], "responsibilities": ["liaise", "management", "maintenance", "administrative support", "schedules", "operations", "internal and external parties", "professional manner", "coordinate with", "maintain"], "requirements": {"degrees": ["degree holder"], "majors": [], "languages": ["cantonese", "english", "mandarin"], "language_level": ["excellent"], "hard_skills": ["excel", "pc knowledge", "ms word"], "soft_skills": ["detail-minded", "multi-tasking", "communication and interpersonal skills", "well-organized"], "languages_combined": [{"language": "cantonese", "language_level": ["excellent"]}, {"language": "english", "language_level": ["excellent"]}, {"language": "mandarin", "language_level": ["excellent"]}]}, "experience_required": {"duration": ["3 years"], "field": []}}, {"job_id": "100003009052280", "location_code": "hk", "company": "Cheung Hing Lifting Components (Hong Kong) Limited", "job_title": "Secretary", "description": "Responsibilities:\n\nPrepare quotations, tender documents and contracts\nResponsible for coordination with oversea manufacturers\nPrepare marketing materials and supporting documents\nResponsible for general office administration works\nCarry out duties and works assigned by directors\n\nRequirements:\n\nForm 7, DSE or above.\nAt least 2 years working experience at similar nature of works.\nPositive \u201ccan-do\u201d attitude.\nEager to learn and take up responsibility.\nCan work under pressure and tight deadline schedule.\nHonest and loyal to company.\nCan communicate with spoken English and Mandarin.\nImmediate availability is preferable.\nWorking on one Saturday morning for every month is required.\n\nSalary and Prospect:\n\n\nAfter successfully completion of probation period, we may offer mid year and year end bonus which makes up to totally 14 months salary per year if performance is above average.\n\nWe may also offer gratuity for working in the company after every three years if performance is above average.\n\nCandidate with good performance can be promoted to Assistant to Director.\n\nPlease send your curriculum vitae with expected salary by clicking 'Apply Now'.\n\nOnly short listed candidates will be contacted.\u00a0 All personal information will be treated with strict confidence for recruitment purpose only, and will be disposed after six months.", "employment_types": ["Full Time", "Permanent"], "selling_points": ["Responsible for preparing quotations and contracts", "Responsible for general office administration work", "."], "locations": ["Tsim Sha Tsui"], "categories": ["Admin & HR", "Clerical / Admin Staff", "Secretary", "Others"], "post_time": "2022-01-17T02:38:48Z", "salary": {"currency": null, "max": null, "min": null, "period": "monthly", "term": null}, "salary_visible": false, "title_keywords": ["secretary"], "responsibilities": ["tender documents", "contracts", "office administration", "coordination with", "prepare marketing materials"], "requirements": {"degrees": ["dse"], "majors": [], "languages": ["english", "mandarin"], "language_level": [], "hard_skills": [], "soft_skills": ["confidence", "eager to learn", "can-do", "honest", "loyal", "positive", "work under pressure"], "languages_combined": [{"language": "english", "language_level": []}, {"language": "mandarin", "language_level": []}]}, "experience_required": {"duration": ["at least 2 years"], "field": []}}, {"job_id": "100003009051935", "location_code": "hk", "company": "Octopus Holdings Limited", "job_title": "Executive Secretary", "description": "Job Responsibilities:\n\nProvide full spectrum of secretarial and administrative support to Department Head\nCoordinate and manage daily prioritization, schedule, team meetings, business appointments and travel plans\nPrepare business correspondence including meeting minutes, agendas, presentation materials and management reports in a timely manner\nHandle expense reimbursement and other professional training arrangement\nHandle, screen and redirect incoming phone calls\nHandle sensitive, personal and confidential data in a professional manner\nAssist in ad-hoc projects whenever assigned\n\nRequirements:\n\nBachelor degree holder in Business Administration or related disciplinewith formal secretarial training\nMinimum 8 years of relevant experience in sizeable companies\nProficient in PC applications including MS Outlook and MS Office\nProficient in written and spoken English and Chinese with strong communication skills\nExcellent interpersonal and collaboration skills\nWell-organized, mature, self-motivated, detail-oriented, resourceful with strong sense of responsibility\nWe offer successful candidate an attractive remuneration package and excellent career prospects. Interested parties please send your resume, present and expected salary, contact details and quoting the reference number by clicking \"Apply Now\"\n\nVisit our web site:\u00a0http://www.octopus.com.hk/\n\nThe personal data collected will be used for recruitment purposes only. If you are not contacted by us within six weeks, you may consider your application unsuccessful. Personal data with an unsuccessful applicant will be destroyed 12 months after rejection of the application. During this retention period, you have the right to request for correction or destruction of your personal data at any time. Any request for the correction or destruction of personal data should be addressed in writing to our Human Resources & Administration Department.\nWe are an equal opportunity employer and will ensure that every job applicant and staff has equal employment opportunities and will not be disadvantaged because of their sex, pregnancy, marital status, family status, disability or race.", "employment_types": ["Full Time", "Permanent"], "selling_points": ["Provide secretarial and administrative support", "Mmanage daily prioritization and schedule", "Minimum 8 years of relevant experience"], "locations": ["Kowloon Bay"], "categories": ["Admin & HR", "Secretary"], "post_time": "2022-01-17T01:32:45Z", "salary": {"currency": null, "max": null, "min": null, "period": null, "term": null}, "salary_visible": false, "title_keywords": ["executive secretary"], "responsibilities": ["administrative support", "data", "a timely manner", "incoming phone calls", "professional manner", "coordinate", "management reports", "schedule", "plans", "ad-hoc projects"], "requirements": {"degrees": ["bachelor degree holder"], "majors": ["business administration"], "languages": ["english", "chinese"], "language_level": ["proficient"], "hard_skills": ["ms office", "outlook", "pc applications"], "soft_skills": ["communication skills", "self-motivated", "resourceful", "sense of responsibility", "well-organized", "mature", "detail-oriented", "interpersonal"], "languages_combined": [{"language": "english", "language_level": ["proficient"]}, {"language": "chinese", "language_level": ["proficient"]}]}, "experience_required": {"duration": ["minimum 8 years"], "field": ["relevant experience"]}}, {"job_id": "100003009054694", "location_code": "hk", "company": "Our Hong Kong Foundation Limited", "job_title": "Secretary", "description": "Responsibilities:\n\nProvide full spectrum of secretarial support to Vice President (Operations)\nProvide secretarial and logistics support to the Board, Council, Committee and Management Meetings\nOrganize and prepare reports, meeting papers, presentation materials and minutes\nPrepare internal and external correspondences\nSupport special projects and ad-hoc administrative tasks as assigned\n\nRequirements:\n\nHolder of bachelor degree or above in Business Administration or related disciplines\nAt least 3 years\u2019 experience in executive / corporate secretarial of Board/Committee work in sizable organizations\nRelevant experience with professional firms and/or public sector organisations will be an asset\nSelf-motivated, well-organized and detail-oriented\nExcellent command of written English and Chinese\nMature team player with excellent communication and interpersonal skills\nProficient in MS Office including Word, Excel and PowerPoint.\n\nInterested parties please send:\n\nFull resume;\nCover letter;\nCopies of academic transcripts (including public examination results if applicable);\nPresent and expected salary;\nAvailability\n\nBy clicking 'Apply Now' or by post to: Our Hong Kong Foundation Limited, 19/F, Nan Fung Tower, 88 Connaught Road Central, Hong Kong. Applicants who are not invited to an interview within two months from the date of this advertisement should consider their applications unsuccessful.\u00a0\n\nAll information provided by applicants will be handled with strictest confidence and will be solely used for the purpose of recruitment.\n", "employment_types": ["Full Time", "Permanent"], "selling_points": ["Secretarial support to Vice President (Operations)", "Proficient in MS Office applications", "Growing platform with development opportunities"], "locations": ["Central & Western Area"], "categories": ["Admin & HR", "Clerical / Admin Staff", "Personal / Executive Assistant", "Secretary"], "post_time": "2022-01-17T10:36:24Z", "salary": {"currency": null, "max": null, "min": null, "period": "monthly", "term": null}, "salary_visible": false, "title_keywords": ["secretary"], "responsibilities": ["ad-hoc", "management", "operations", "logistics", "secretarial support", "prepare reports", "administrative tasks", "support special projects"], "requirements": {"degrees": ["degree or above", "bachelor"], "majors": ["related disciplines", "business administration"], "languages": ["english", "chinese"], "language_level": ["excellent"], "hard_skills": ["excel", "word", "powerpoint", "ms office"], "soft_skills": ["self-motivated", "well-organized", "mature", "detail-oriented", "communication and interpersonal skills", "team player"], "languages_combined": [{"language": "english", "language_level": ["excellent"]}, {"language": "chinese", "language_level": ["excellent"]}]}, "experience_required": {"duration": ["at least 3 years"], "field": ["secretarial", "relevant experience"]}}, {"job_id": "100003009054372", "location_code": "hk", "company": "Bright Smart Securities International (H.K.) Limited", "job_title": "Secretary", "description": "Responsibilities:\n\n\nProvide full spectrum of secretarial and administrative support to Chairman in both business affairs and personal issues;\nOrganize the daily calendars and prepare meeting materials for\u00a0internal and external\u00a0meetings and appointments;\nCoordinate with different departments and follow up on daily operation matters;\nServe as the primary point of contact for internal department and external parties on all matters pertaining to the Chairman;\nAssist Chairman to handle emails & correspondences;\nDeal with confidential matters with a high degree of professionalism and confidentiality;\nCoordinate with drivers and helpers to ensure smooth operations;\nPerform any other duties as assigned by the Chairman.\n\nRequirements:\n\n\nBachelor Degree\u00a0in Business Administration or related disciplines;\nAt least\u00a08\u00a0years\u2019 solid executive secretarial experience;\nLogical thinking, presentable,\u00a0hardworking, smart and well organized;\nProactive,\u00a0fast-paced,\u00a0self-motivated and able to work independently;\nProficient in PC applications, e.g. MS Office, Excel, PowerPoint and Chinese Word Processing is a MUST;\nImmediate available is preferred.\n\nWe Offer:\n\nCompetitive remuneration package\n5 Days Work & Bank Holidays\nAttendance Bonus\nMeal Allowance\nDiscretionary Bonus\nMedical Insurance\u00a0\u00a0\n\nWe provide attractive remuneration package and fringe benefits for the right candidate. Interested parties please send detailed resume with current and expected salaries to\u00a0Human Resources Department by clicking \"Apply Now\" or fax to: 2530 2218.\n\nAll information collected will be used for recruitment purpose only, only shortlisted candidates will be notified.\n\nWelcome to visit our website: http://www.bsgroup.com.hk/ for more information", "employment_types": ["Full Time", "Permanent"], "selling_points": [], "locations": ["Central"], "categories": ["Admin & HR", "Clerical / Admin Staff", "Personal / Executive Assistant", "Secretary"], "post_time": "2022-01-17T09:18:37Z", "salary": {"currency": null, "max": null, "min": null, "period": "monthly", "term": null}, "salary_visible": false, "title_keywords": ["secretary"], "responsibilities": ["any other duties", "administrative support", "external parties", "daily operation", "coordinate with", "contact", "ensure smooth operations"], "requirements": {"degrees": ["degree", "bachelor"], "majors": ["related disciplines", "business administration"], "languages": ["chinese"], "language_level": [], "hard_skills": ["excel", "chinese word processing", "powerpoint", "pc applications", "ms office"], "soft_skills": ["self-motivated", "work independently", "well organized", "presentable", "proactive", "hardworking"], "languages_combined": [{"language": "chinese", "language_level": []}]}, "experience_required": {"duration": ["at least 8 years"], "field": ["secretarial"]}}, {"job_id": "100003009051939", "location_code": "hk", "company": "Quantium Solutions (Hong Kong) Limited", "job_title": "Administration Executive/Personal Assistant", "description": "Quantium Solutions\n\nQS is an established eCommerce logistics services provider in the Asia Pacific Region. Headquartered in Singapore, we are ideally positioned to be the best gateway to Asia.\n\nOur serviced offices now serve the needs of enterprises and entrepreneurs across major 200 countries and 18 markets.\n\nAt QS, creating a workplace that provides opportunities for each of you and we believe in you and know you\u2019ll do great things. As an employer, our role is to empower you by bringing your true talents and best self to this dynamic digital world and people we serve.\n\n\n\n\nJob Description\n\nJob Responsibilities:\n\nPerform full spectrum of Administrative functions,\u00a0including\u00a0but not limited to repair & maintenance, procurement ( sourcing, price negotiation, suppliers evaluation & selection, delivery management and inventory control ) etc.\nHandle ISO documents update and filing, and provide assistance to ISO internal and external audits\nPlan and manage daily schedule of RGM including work, personal time, and trips;\nOrganize travel arrangement for the family including ticket and accommodation, itinerary planning, visa application etc\nAssist in any ad hoc project as\u00a0assigned\n\n\u00a0Job Requirements:\n\nCertificate, Diploma or\u00a0above\u00a0in Logistics, Procurement or related disciplines\nPossession of procurement experience is a must and ISO audit experience\u00a0would\u00a0be an added advantage\nGood\u00a0negotiation,\u00a0communication and interpersonal skills\nGood command of written and spoken English, Cantonese and Mandarin\nPC Literacy and working knowledge of MS Office\nImmediately available is preferred\n\nWe offer attractive remuneration package including medical insurance, life insurance, dental and other fringe benefits to the right candidate. Interested parties please send your full resume with date of availability, present and expected salaries to us\n\n\n", "employment_types": ["Full Time", "Permanent"], "selling_points": [], "locations": ["Wong Tai Sin Area"], "categories": ["Admin & HR", "Clerical / Admin Staff", "Personal / Executive Assistant", "Secretary"], "post_time": "2022-01-17T01:33:11Z", "salary": {"currency": null, "max": null, "min": null, "period": "monthly", "term": null}, "salary_visible": false, "title_keywords": ["administration executive", "personal assistant"], "responsibilities": ["management", "price negotiation", "ad hoc", "maintenance", "internal and external audits", "repair", "inventory control", "schedule", "plan", "evaluation", "travel arrangement", "provide assistance", "planning"], "requirements": {"degrees": ["certificate", "diploma or above"], "majors": ["related disciplines"], "languages": ["cantonese", "english", "mandarin"], "language_level": ["good command"], "hard_skills": ["pc", "ms office"], "soft_skills": ["communication and interpersonal skills", "negotiation"], "languages_combined": [{"language": "cantonese", "language_level": ["good command"]}, {"language": "english", "language_level": ["good command"]}, {"language": "mandarin", "language_level": ["good command"]}]}, "experience_required": {"duration": [], "field": ["audit experience", "procurement"]}}, {"job_id": "100003009054869", "location_code": "hk", "company": "Nu Skin Enterprises Hong Kong, LLC", "job_title": "Administrative Assistant (Part-time)", "description": "Responsibilities:\u00a0\u00a0\n\nOffice administration work such as general filing work and data input;\nManage office supplies and the smooth running of the department;\nOrganize meetings and conference calls;\nTravel arrangement and travel expenses;\nProvide day to day administrative support.\n\nRequirement:\u00a0\u00a0\n\nGood communication, interpersonal and organization skills;\nSelf-initiative and detail-minded;\nProficient in MS Office and Chinese word processing;\nGood command of spoken and written English and Chinese including Mandarin;\nAble to provide service on 2 or 3 full days a week or half day from each day.\nImmediately available is highly preferred.\n\nWe offer friendly working environment with competitive remuneration. If you are interested in joining our company, please click\u00a0\"Apply Now\"\u00a0to submit your application.\u00a0\n\nALL PERSONAL INFORMATION WE COLLECTED IS FOR THE PURPOSE OF RECRUITMENT ONLY\n\nPlease visit www.nuskin.com to find out more about us!", "employment_types": ["Part Time"], "selling_points": ["secretarial and administrative work", "Handle billings, invoices and expenses claims", "Coordinate meetings and conference calls"], "locations": ["Tin Hau"], "categories": ["Admin & HR", "Clerical / Admin Staff", "Secretary"], "post_time": "2022-01-17T12:14:08Z", "salary": {"currency": null, "max": null, "min": null, "period": "hourly", "term": null}, "salary_visible": false, "title_keywords": ["administrative assistant"], "responsibilities": ["administrative support", "office supplies", "expenses", "office administration work", "data input", "travel arrangement"], "requirements": {"degrees": [], "majors": [], "languages": ["english", "chinese", "mandarin"], "language_level": ["good command", "proficient"], "hard_skills": ["chinese word processing", "ms office"], "soft_skills": ["detail-minded", "communication", "self-initiative", "organization skills", "interpersonal"], "languages_combined": [{"language": "english", "language_level": ["good command"]}, {"language": "chinese", "language_level": ["good command", "proficient"]}, {"language": "mandarin", "language_level": ["good command"]}]}, "experience_required": {"duration": [], "field": []}}, {"job_id": "100003009053325", "location_code": "hk", "company": "Plaza Premium Group", "job_title": "Team Secretary/ Administrator", "description": "About the Company\n\nHello! Welcome to Plaza Premium Group, we're people passionate about \"Making Travel Better\". We are a global company with team members from all walks of life, together we are\u00a0#PPGFamily,\u00a0together we are building a legacy.\u00a0You don't need to be from this industry, you do need to be passionate.\n\nOur promise to you:\n\nWe will respect and value your background and perspectives\nWe will work together with integrity\nWe will share our incredible pride for job, company and industry\nWhat we ask of you:\nBring passion to all that you do\nListen, move fast and think innovatively\nSpeak up, have ideas and share them\nBelieve in customer service, and treating every person with kindness\n\nAs industry leaders in innovating global airport hospitality you will work with colleagues from all parts of the world for a truly global experience. You will help and craft services and facilities in over 200 locations in more than 60 international airports across the world.\n\nWho we are\n\nWe were established in HK in 1998 by someone who understood the value of an airport lounge and felt that the experience shouldn't just be limited to a closed-circuit group of travelers. Through the years we have worked incredibly hard to create an experience which is both accessible and quality. Almost 25 years later we now span four core business segments: airport lounges, airport terminal hotels, airport meet & greet services, and a range of airport dining concepts.\n\nIn addition to our own brands, PPG provides airport hospitality solutions to leading airlines, alliances and corporates around the world. Here are a few names you might recognize: Cathay Pacific Airways, Singapore Airlines, Lufthansa etc.\n\nWith the future of travel always in sight, we created Smart Traveler, a mobile-app rewards program underpinned by in-house technology. We are fast-moving and always evolving to drive our purpose of making travel better.\n\nJoin our family today.\nTogether, we'll make travel better.\u00a0\n\n\nWhat you'll be doing:\n\nThis is a varied and challenging role where you will be working within a multi-cultural environment, able to input, collaborate with different global teams within the group. The individual will be reporting to the Chief Financial Officer while working independently for the delegated business coverage. Some of the duties are:\n\nHelp the CFO and respective project owners prepare budget based on scope of work and resource requirements.\u00a0\u00a0\nEstablish and maintain the governance standards of project management practices, processes and templates\u00a0for managing projects consistently and efficiently to reduce project-related risk and cost.\u00a0\u00a0\nSupport Project Owner\u00a0to manage delivery of the agreed road map items, specifically as applies to the project and outlined within the charter.\u00a0\nMonitor and report completion of schedules for projects from initiation to delivery and keeps management informed of any deviations.\u00a0\n\nOrganizes any necessary meetings to progress\u00a0team work\u00a0(weekly, daily, or ad-hoc as appropriate) and executes meetings actions plans as required.\u00a0\u00a0\nCollecting and consolidating project status information for senior management\u00a0review and to support effective\u00a0decision making.\u00a0\nFacilitate implementation of the communication framework across of projects between HQ, Shared Service Centre and relevant stakeholders.\u00a0\u00a0\nBuild up a repository of project templates both technical and management to support managers and projects teams.\u00a0\u00a0\nManage issues and escalation activities and organize discussions to address issues related to projects\u00a0members\u00a0not fulfilling deliverables.\u00a0\u00a0\nProvide administrative support to\u00a0Chief Financial Officer.\n\nAbout You:\n\nThe ideal candidate will have the ability to work in a diversified, fast-paced\u00a0and collaborative environment with excellent organizational skills and great attention to details\n\nA degree of any field.\u00a0\u00a0\n\nFamiliar or exposure to Finance, management and related work i.e. basic understanding of Finance and Management. Able to understand and follow discussion about Finance, and management subjects.\u00a0\u00a0\n\nMUST be fluent on English and Cantonese- both written and spoken. Fluency in Mandarin would be an advantage.\nGood computer knowledge\u00a0and skills (MS Outlook, PowerPoint, Excel, Word, SharePoint) and Project Management system (MS Project).\u00a0", "employment_types": ["Full Time", "Permanent"], "selling_points": ["Multi-cultural and collaborative environment", "Exposure to work with top management", "Great team"], "locations": ["Tung Chung"], "categories": ["Admin & HR", "Secretary"], "post_time": "2022-01-17T06:48:38Z", "salary": {"currency": null, "max": null, "min": null, "period": "monthly", "term": null}, "salary_visible": false, "title_keywords": ["team secretary", "administrator"], "responsibilities": ["customer service", "ideas"], "requirements": {"degrees": [], "majors": [], "languages": [], "language_level": [], "hard_skills": ["airports"], "soft_skills": ["passionate", "customer service", "integrity", "passionate about"], "languages_combined": []}, "experience_required": {"duration": [], "field": []}}, {"job_id": "100003009052831", "location_code": "hk", "company": "Woo Kwan Lee & Lo", "job_title": "Junior Secretary", "description": "\u5de5\u4f5c\u5167\u5bb9\u53ca\u8077\u8cac:\n\n\u4e00\u822c\u79d8\u66f8\u8077\u52d9;\n\u5354\u8abf\u53ca\u5b89\u6392\u8463\u4e8b\u65e5\u5e38\u884c\u7a0b;\n\u7ba1\u7406\u8b70\u7a0b\u4e26\u5b89\u6392\u6703\u8b70\u53ca\u7d04\u6703,\u6703\u8b70\u8a18\u9304;\n\u5354\u52a9\u65e5\u5e38\u4eba\u529b\u8cc7\u6e90\u5de5\u4f5c:\u7c4c\u8fa6\u57f9\u8a13\u3001\u62db\u52df\u3001\u516c\u53f8\u6d3b\u52d5;\n\u5718\u968a\u696d\u7e3e\u5831\u544a\u8ffd\u8e2a\u6210\u54e1\u696d\u7e3e/\u734e\u9805;\n\u8655\u7406\u8fa6\u516c\u5ba4\u884c\u653f\u5de5\u4f5c\uff0c\u5305\u62ec\u8a02\u8cfc\u8cfc\u6587\u5177\u3001\u8fa6\u516c\u5ba4\u7528\u54c1\u3001\u540c\u4e8b\u51fa\u52e4\u53ca\u5047\u671f\u7d00\u9304\u7b49;\n\u8655\u7406\u4e0a\u7d1a\u59d4\u6d3e\u7684\u5176\u4ed6\u5de5\u4f5c\n\n\u8077\u4f4d\u8981\u6c42:\n\n\u4e00\u5e74\u7d93\u9a57\u6216\u4ee5\u4e0a\n\u5c08\u4e0a\u6559\u80b2\u6216\u5b78\u58eb\u5b78\u4f4d(\u5546\u696d/\u884c\u653f\u7ba1\u7406/\u4eba\u529b\u8cc7\u6e90/\u793e\u6703\u79d1\u5b78)\n\u826f\u597d\u7cb5\u8a9e\u3001\u826f\u597d\u666e\u901a\u8a71\u3001\u826f\u597d\u82f1\u6587\n\u61c2\u8b80\u5beb\u4e2d\u6587\u53ca\u82f1\u6587\n\u61c2Microsoft Office\u53ca\u4e2d\u82f1\u6587\u57fa\u672c\u96fb\u8166\u64cd\u4f5c\n\n\u5de5\u4f5c\u5730\u9ede: \u89c0\u5858\u5340\n\n\u798f\u5229\u5305\u62ec\uff1a\n\n\u9280\u884c\u5047\u671f\u3001\u4e94\u5929\u5de5\u4f5c\u3001\u91ab\u7642\u4fdd\u969c\u3001\u63d0\u4f9b\u54e1\u5de5\u65e9\u5348\u81b3\u300110\u5929\u6709\u85aa\u5e74\u5047\u3001\u8003\u8a66\u5047\u3001\u5a5a\u5047\u3001\u52e4\u5de5\u734e\u3002\n\n\u00a0\u6709\u610f\u61c9\u5fb5\u8005\u8acb\u628a\u8a73\u7d30\u7684\u5c65\u6b77\u767c\u9001\u7d66\u6211\u5011\uff0c\u8acb\u8a3b\u660e\u73fe\u8077\u85aa\u91d1\u548c\u671f\u671b\u85aa\u91d1\u3002", "employment_types": ["Full Time", "Permanent"], "selling_points": ["Junior Secretary", "Legal Firm", "Mature and hardworking"], "locations": ["Wan Chai Area"], "categories": ["Admin & HR", "Secretary", "Professional Services", "Legal & Compliance"], "post_time": "2022-01-17T04:13:24Z", "salary": {"currency": null, "max": null, "min": null, "period": "monthly", "term": null}, "salary_visible": false, "title_keywords": ["junior secretary"], "responsibilities": [], "requirements": {"degrees": [], "majors": [], "languages": [], "language_level": [], "hard_skills": [], "soft_skills": [], "languages_combined": []}, "experience_required": {"duration": [], "field": []}}, {"job_id": "100003009053834", "location_code": "hk", "company": "Konew Financial Express Limited \u5eb7\u696d\u4fe1\u8cb8\u5feb\u905e", "job_title": "Personal Assistant to Senior Executive", "description": "Fresh graduate (Form 6 (DSE)/Diploma of Legal Studies)\nCommand of written and spoken English, Cantonese and Mandarin\nWorking experience not required\nGood computer skills\nMature, independent and hardworking\n\n\nInterested parties please send detailed CV with expected salary by apply now.", "employment_types": ["Full Time", "Permanent"], "selling_points": ["Support personal and business activities", "Interact with people at all levels", "Proactive, flexible and detail-minded"], "locations": ["Central"], "categories": ["Admin & HR", "Clerical / Admin Staff", "Personal / Executive Assistant", "Secretary"], "post_time": "2022-01-17T07:36:07Z", "salary": {"currency": null, "max": null, "min": null, "period": "monthly", "term": null}, "salary_visible": false, "title_keywords": ["senior executive", "personal assistant"], "responsibilities": [], "requirements": {"degrees": ["diploma", "fresh graduate", "dse"], "majors": [], "languages": ["cantonese", "english", "mandarin"], "language_level": [], "hard_skills": ["computer skills"], "soft_skills": ["hardworking", "independent", "mature"], "languages_combined": [{"language": "cantonese", "language_level": []}, {"language": "english", "language_level": []}, {"language": "mandarin", "language_level": []}]}, "experience_required": {"duration": [], "field": []}}, {"job_id": "100003009054670", "location_code": "hk", "company": "Guardforce Ltd", "job_title": "Executive Secretary", "description": "Main Duties & Responsibilities:\n\n\nProvide full spectrum of personal and business support to senior executive\nLiaise with internal and external parties for business activities, project management, etc.\nManage calendar, coordinate meetings, events, organize daily schedules and travel arrangement\nHandle business correspondence, confidential documents and other administrative duties\nWilling to handle multi-tasks and ad hoc assignment is required\n\nRequirements:\n\nBachelor Degree or above\nAt least 3 years relevant working experience\nExcellent communication and interpersonal skills\nWell organized, attentive to details, able to handle multi-tasks with strong sense of responsibility\nGood\u00a0command of spoken and written\u00a0English and\u00a0Chinese\nProficiency in MS Office\n\nWe offer:\n\nDiscretionary bonus\nMedical insurance\nDental insurance\nCompetitive annual leave days\nBirthday leave\nAnniversary leave\nStudy leave\nMarriage leave\nCompassionate leave\n\nHow to apply:\n\nInterested parties, please send your resume stating your expected salary\u00a0to\u00a0Human Capital Department\u00a0by clicking\u00a0\"APPLY NOW\".\n\n(We are an equal opportunity employer.\u00a0 Personal data collected will be used for recruitment purpose only.\u00a0 The unsuccessful applications will be destroyed after 6 months.)", "employment_types": ["Full Time", "Permanent"], "selling_points": [], "locations": ["Hung Hom"], "categories": ["Admin & HR", "Secretary", "Professional Services", "Business Analysis / Data Analysis", "Sales, CS & Business Devpt", "Others"], "post_time": "2022-01-17T10:29:00Z", "salary": {"currency": null, "max": null, "min": null, "period": "monthly", "term": null}, "salary_visible": false, "title_keywords": ["executive secretary"], "responsibilities": ["schedules", "ad hoc assignment", "internal and external parties", "coordinate", "project management", "administrative duties", "travel arrangement", "liaise with", "business activities"], "requirements": {"degrees": ["degree or above", "bachelor"], "majors": [], "languages": ["english", "chinese"], "language_level": ["good command"], "hard_skills": ["ms office"], "soft_skills": ["multi-tasks", "attentive to details", "sense of responsibility", "well organized", "communication and interpersonal skills"], "languages_combined": [{"language": "english", "language_level": ["good command"]}, {"language": "chinese", "language_level": ["good command"]}]}, "experience_required": {"duration": ["at least 3 years"], "field": ["relevant working experience"]}}, {"job_id": "100003009052557", "location_code": "hk", "company": "High Fashion Group", "job_title": "Executive Secretary", "description": "Position: Executive Secretary\n\nStationed in the Head Office of Guardforce Group, this position will report directly to the Group Chief Executive Officer (the Group CEO) and is responsible for providing all-rounded and professional secretarial and business support.\n\nResponsibilities\n\nProvide administrative, secretarial and business support to the Group CEO\nAssist in reviewing the management and financial reports and preparing summary reports for the Group CEO\u2019s review\nWork closely with functional teams across local and overseas operating entities to monitor business performances\nWork diligently and proactively in coordinating business development initiatives and projects by means of market research and data analysis, business presentation and report generation\nPlay a key role in liaising and coordinating business activities and meetings with both internal and external stakeholders\nPerform any other duties as assigned by the Group CEO\n\nRequirements\n\nBachelor's degree holder in any discipline\nAt least 5 years of work experience\nSolid experience of working with senior management is a definite advantage\nPrevious experience of working in a multinational and/or sizable company is also preferable\nOutgoing, proactive and mature, with a positive can-do attitude and willingness to learn\nCan work under pressure and meet tight deadlines\nStrong numerical sense and excellent data interpretation and analytical skills\nExcellent presentation and communication skills\nStrong business acumen, interpersonal and coordination skills\n\nGood command of both spoken and written English, Chinese and Mandarin\n\n\n\n\nCome & Join Us!\u00a0\u00a0Attractive remuneration packages will be offered to the right candidate.\n\nInterested parties, please send your application together with a full resume stating your\u00a0present and expected salary\u00a0& date availability via \"Apply Now\", by email to hr(@)guardforcegroup.com or by mail to Room 806, Guardforce Centre, 3 Hok Yuen Street East, Hung Hom, Kowloon.\u00a0Please quote the reference number on the application letter.\n\nPersonal data provided in your application will be kept in the strictest confidence. It will only be used for employment-related purposes by any entity within our Group. Applicants not notified within 1 month will be considered as unsuccessful. Unsuccessful application may be kept for another 3 months for new openings or consideration by another entity within our Group before properly shredded.\n\nSecurity Licence No.: 0092", "employment_types": ["Full Time", "Permanent"], "selling_points": ["Works in Central", "Double-pay, medical insurance and birthday leave", "5 day work week (9am-6pm)"], "locations": ["Central"], "categories": ["Accounting", "Accounting Clerk / Supervisor", "Admin & HR", "Administration / Operation Manager", "Secretary"], "post_time": "2022-01-17T03:24:49Z", "salary": {"currency": "HKD", "max": 34999, "min": 25000, "period": "monthly", "term": null}, "salary_visible": true, "title_keywords": ["executive secretary"], "responsibilities": ["any other duties", "management", "financial reports", "review", "teams", "monitor", "market research", "data analysis", "reports", "business activities", "report"], "requirements": {"degrees": ["bachelor", "degree holder"], "majors": [], "languages": ["english", "chinese", "mandarin"], "language_level": ["good command"], "hard_skills": ["acumen", "analytical skills"], "soft_skills": ["outgoing", "communication skills", "meet tight deadlines", "coordination skills", "can-do attitude", "interpersonal", "mature", "analytical skills", "business acumen", "proactive", "presentation", "positive", "work under pressure"], "languages_combined": [{"language": "english", "language_level": ["good command"]}, {"language": "chinese", "language_level": ["good command"]}, {"language": "mandarin", "language_level": ["good command"]}]}, "experience_required": {"duration": ["at least 5 years"], "field": ["management"]}}, {"job_id": "100003009051614", "location_code": "hk", "company": "Lo Lo's Workshop", "job_title": "Secretary", "description": "We are looking to hire an Executive Secretary for our business division which is a Family Investment Office that invest\u00a0mainly in property, equity and bonds. Candidates with property investment working experience is preferred.\u00a0We provide a stable and flexible career path for the right candidates.\u00a0\n\n\nResponsibilities:\u00a0\n\nProvide Secretarial support to CEO\nHandle business correspondence, minutes, reports, proposals and confidential documents as required\nPerform general clerical work, data entry and administration and HR support to the teams\nAct as personal assistant and attend business meetings\nManage and coordinate both internal and external issues including but not limited to i.e. private teacher, driver and domestic helper\nCarry out ad hoc assignments directed by management\n\nRequirements:\n\nUniversity Graduated is preferred\n3 years or above working experience\nProficiency in Microsoft Word, Excel, Power point\u00a0and Chinese typing\nProficiency in software related to graphic design will be an advantage\nFluent in Cantonese and English, fair in Mandarin\nGood\u00a0communication skill,\u00a0self-initiative, well-organized, responsible and able to work under pressure\nImmediate available is preferred\n\nWe offer an attractive package, good prospects and fringe benefits to the right candidate. Interested parties, please apply with full resume, current and expected salary to: Group Human Resources Manager of High Fashion Group. By Email: Click below \"Apply now\" button\u00a0(in MS Word format), or by mail: 11/F., High Fashion Centre, 1-11 Kwai Hei Street, Kwai Chung, New Territories\n\n\u00a0(The information received will be used for consideration of employment only and all personal data supplied will be destroyed within 6 months.)", "employment_types": ["Full Time", "Permanent"], "selling_points": [], "locations": ["Kwun Tong Area"], "categories": ["Admin & HR", "Secretary", "Insurance", "Others", "Sales, CS & Business Devpt", "Sales Administration"], "post_time": "2022-01-16T14:33:51Z", "salary": {"currency": null, "max": null, "min": null, "period": "monthly", "term": null}, "salary_visible": false, "title_keywords": ["secretary"], "responsibilities": [], "requirements": {"degrees": [], "majors": [], "languages": [], "language_level": [], "hard_skills": [], "soft_skills": [], "languages_combined": []}, "experience_required": {"duration": [], "field": []}}, {"job_id": "100003009052048", "location_code": "hk", "company": "Swire Hotels", "job_title": "Administrative Assistant", "description": "Responsibilities\n\nTo provide secretarial support to Senior Manager in insurance\u00a0company agency office\nPrepare agenda & minutes\nPrepare meeting clients' documents, scheduling meetings and appointments and so on\nAssist in monitoring admin progress and preparing status report\nMaintain up-to-date and systematic filing system; Administer and monitor clients calls\nAlso responsible for team administration\nNO SALES job and DON'T need to meet clients\n\nRequirements\n\nForm 7 or above with\u00a0secretarial or business training\u00a0\nOver\u00a05 years secretarial and administrative experience, advantageous to have relevant secretarial experience in insurance company / bank\nFamiliar with PC applications including MS Excel, Word and Chinese Word Processing ( Excel is important in this job post )\nGood command of both written and spoken English and Cantonese, Mandarin is a plus\nMature and independent, detail-minded, with initiatives and positive attitude\n\nPlease apply with full resume including expected salary and date availability\n\n\nAll applications will be treated in strict confidence.", "employment_types": ["Full Time", "Permanent"], "selling_points": ["Provide overall administrative assistance", "Arrange meeting & office pantry", "Dynamic working environment"], "locations": ["Tai Koo"], "categories": ["Admin & HR", "Administration / Operation Manager", "Clerical / Admin Staff", "Secretary"], "post_time": "2022-01-17T02:03:50Z", "salary": {"currency": null, "max": null, "min": null, "period": null, "term": null}, "salary_visible": false, "title_keywords": ["administrative assistant"], "responsibilities": ["administration", "monitoring", "monitor", "scheduling", "maintain", "secretarial support", "insurance", "report"], "requirements": {"degrees": [], "majors": [], "languages": ["cantonese", "english", "chinese", "mandarin"], "language_level": ["good command"], "hard_skills": ["excel", "plus", "chinese word processing", "word", "pc applications", "ms excel"], "soft_skills": ["detail-minded", "confidence", "independent", "mature", "positive attitude"], "languages_combined": [{"language": "cantonese", "language_level": ["good command"]}, {"language": "english", "language_level": ["good command"]}, {"language": "chinese", "language_level": []}, {"language": "mandarin", "language_level": ["good command"]}]}, "experience_required": {"duration": ["5 years"], "field": ["secretarial", "administrative", "insurance"]}}, {"job_id": "100003009052206", "location_code": "hk", "company": "Gemini Personnel Limited", "job_title": "Personal Assistant (22 day annual leave) PRC-J078023", "description": "Job Description:\n\nProvide secretarial services and administrative support for Directors and Senior Secretaries by maintaining filing systems, coordinating schedule for meetings and travel arrangement, handling reports and correspondences, drafting minutes etc\nDraft general correspondence, including letters, memos, faxes and reports etc.\nAssist in organizing travel itineraries, including booking flights, hotels, restaurants etc.\nHandle ad hoc projects as required\n\nJob Requirements:\n\nDegree / High Diploma holder, preferably in Business Administration\nMinimum 1 year relevant experience\nGood command of both spoken and written English, Chinese and Mandarin\nExcellent interpersonal skills, independent, meticulous, well-organized, proactive and eager to learn\nPositive working attitude and able to work under pressure\nProficient in MS office including MS Word, Excel, Powerpoint & Chinese Word Processing\nCandidate with more experience will be considered as Administrative Executive\nWe\u00a0offer\u00a0attractive remuneration package to the right candidate. Interested parties please click the \"APPLY NOW\" button below and send your application together with a detailed resume including current & expected salary and availability to Human Resources Department.\nCompany website:\u00a0https://www.lawsgroup.com\n(Data collected will be treated in strict confidence and used for recruitment purpose only)", "employment_types": ["Full Time", "Permanent"], "selling_points": ["Provide full secretarial to Senior Management", "Handling confidential information & document", "Fluent English and Mandarin"], "locations": ["Causeway Bay"], "categories": ["Admin & HR", "Personal / Executive Assistant", "Secretary"], "post_time": "2022-01-17T02:28:02Z", "salary": {"currency": null, "max": null, "min": null, "period": "monthly", "term": null}, "salary_visible": false, "title_keywords": ["personal assistant"], "responsibilities": ["maintaining", "administrative support", "systems", "letters", "reports", "schedule", "travel arrangement", "booking", "ad hoc projects"], "requirements": {"degrees": ["high diploma", "degree"], "majors": ["business administration"], "languages": ["english", "chinese", "mandarin"], "language_level": ["good command", "proficient"], "hard_skills": ["excel", "chinese word processing", "powerpoint", "ms office", "ms word"], "soft_skills": ["meticulous", "independent", "well-organized", "eager to learn", "positive working attitude", "interpersonal skills", "proactive", "work under pressure"], "languages_combined": [{"language": "english", "language_level": ["good command"]}, {"language": "chinese", "language_level": ["good command", "proficient"]}, {"language": "mandarin", "language_level": ["good command"]}]}, "experience_required": {"duration": ["minimum 1 year"], "field": ["administrative", "relevant experience"]}}, {"job_id": "100003009054748", "location_code": "hk", "company": "Peninsula Merchandising Limited", "job_title": "Administration Officer", "description": "My client, one of the leading property developers and focus on property investment nd development in Hong\u00a0 Kong. They are looking for a Personal Assistant.\n\n\n\nResponsibilities:\n\nProvide full spectrum of secretarial and administrative support to Senior Management\u00a0\nHandle business correspondence, other confidential and professional documents as instructed\nAssist to draft various English and Chinese business correspondences in a professional manner\nResponsible for arranging and monitoring the day-to-day operation for the whole family household\nManage and supervise the domestic helpers, drivers, chef, securities, etc.\nResponsible for property and facilities management and maintenance, renovation, repair, etc.\nAd hoc tasks assigned by the Management\n\nRequirements:\n\nDegree holder in any disciplines\nAt least 2 years secretary / personal assistant experience in Property, Finance or Investment industry\nGood command of both written and spoken in English and Chinese\nPC knowledge of\u00a0 MS Word, Excel and Chinese Word Processing\nImmediate availability would be an advantage\nBenefits:\n\nAnnual Leave 22 days\nBonus\nLife Insurance\nMedical Insurance\neducation Allowance\nFive day work per week\n\nInterested parties, please send your resume with expected salary submit by APPLY NOW or contact with Miss Priscilla Cheng at 35529110 WhatsApp +852 98651325 for discussion.", "employment_types": ["Full Time", "Permanent"], "selling_points": ["Join a highly prestigious retail brand", "At least 5 years of relevant experience", "Competitive benefits with family medical coverage"], "locations": ["Tsim Sha Tsui"], "categories": ["Admin & HR", "Clerical / Admin Staff", "Personal / Executive Assistant", "Secretary"], "post_time": "2022-01-17T10:53:09Z", "salary": {"currency": null, "max": null, "min": null, "period": "monthly", "term": null}, "salary_visible": false, "title_keywords": ["administration officer"], "responsibilities": ["management", "maintenance", "administrative support", "monitoring", "professional manner", "renovation", "ad hoc tasks", "repair", "senior management", "day-to-day operation"], "requirements": {"degrees": ["degree holder"], "majors": ["any disciplines"], "languages": ["english", "chinese"], "language_level": ["good command"], "hard_skills": ["excel", "pc knowledge", "chinese word processing", "ms word"], "soft_skills": [], "languages_combined": [{"language": "english", "language_level": ["good command"]}, {"language": "chinese", "language_level": ["good command"]}]}, "experience_required": {"duration": ["at least 2 years"], "field": ["finance", "investment"]}}, {"job_id": "100003009052012", "location_code": "hk", "company": "Phonak Hearing Centre Hong Kong Ltd", "job_title": "Personnel & Administration Assistant", "description": "Reporting to General Manager, you will be responsible for secretarial supports to the General Manager and managing the office administration to ensure office efficiency, cleanness and safety.\u00a0\n\nExceptional market leading benefits such as comprehensive family medical insurance (including dependents), 17 paid statutory holidays,\u00a012 vacation days and\u00a03 days paid carers leave.\n\nKey Responsibilities:\n\nManage schedule, travel arrangements, appointments, document signing and administrative tasks for General Manager, and for ExCom team if required.\nPrepare reports, presentations or other documents as assigned by General Manager.\nSupport the General Manager on coordinating meetings, taking meeting minutes, filtering phone calls and supporting on internal and external communication.\nAct as office manager to manage office administrative tasks to ensure efficiency, tidiness, safety and compliance on company policies & regulatory requirements on health & safety.\nKeep stock of office supplies and place orders when necessary to ensure sufficient supply. Source office supplies to meet the business needs.\nCoordinate office cleaning staff/vendor, manage maintenance tasks, allocate office storage space and other consumables.\nCoordinate among all departments, sister companies, property management office and vendors for office activities such as maintenance, office regular cleaning, fire drills, office orientation, office supplies, office tidiness etc.\nSupport from administrative perspective on office activities such as internal seeding, staff gifting, monthly meeting and other company staff events.\nHandle incoming phone calls, receive walk-in visitors and handle internal & external couriers for office.\n\nRequirements:\n\nMinimum of 5 years of related experience.\nHigher diploma or above in any related disciplines.\nExperience in providing secretarial support to senior executives and managing office administration is a must.\nAttention to details, great communication skill and excellent interpersonal skill.\nPolite, presentable, able to work independently.\nFluent in oral English, Cantonese and Mandarin.\nStrong command in written English and Chinese.\nGood command in MS Office, including PowerPoint, Excel, Word and Outlook.\n\nWe are delighted to receive your application for further consideration. Click apply now with your latest CV and salary information.", "employment_types": ["Full Time", "Permanent"], "selling_points": ["Attractive Salary Package & Benefit, 5 day work", "Diploma/Associate Degree or Above in HR & Admin", "1-2 years working experience in HR & Admin"], "locations": ["Tsim Sha Tsui"], "categories": ["Admin & HR", "Clerical / Admin Staff", "Secretary", "HR Supporting Staff"], "post_time": "2022-01-17T01:50:09Z", "salary": {"currency": null, "max": null, "min": null, "period": "monthly", "term": null}, "salary_visible": false, "title_keywords": ["administration assistant"], "responsibilities": ["travel arrangements", "management", "prepare reports", "coordinating meetings", "maintenance", "office supplies", "policies", "regulatory requirements", "compliance", "incoming phone calls", "presentations", "maintenance tasks", "communication", "coordinate", "schedule", "cleaning", "administrative tasks", "phone calls"], "requirements": {"degrees": ["higher diploma or above"], "majors": ["related disciplines"], "languages": ["cantonese", "english", "chinese", "mandarin"], "language_level": ["fluent"], "hard_skills": ["excel", "word", "powerpoint", "outlook", "ms office"], "soft_skills": ["work independently", "oral", "polite", "communication skill", "presentable", "interpersonal skill", "attention to details"], "languages_combined": [{"language": "cantonese", "language_level": ["fluent"]}, {"language": "english", "language_level": ["fluent"]}, {"language": "chinese", "language_level": []}, {"language": "mandarin", "language_level": ["fluent"]}]}, "experience_required": {"duration": ["minimum of 5 years"], "field": ["related", "office administration", "secretarial"]}}, {"job_id": "100003009053784", "location_code": "hk", "company": "Hysan Development Co Ltd", "job_title": "Administrator, Projects", "description": "KAM HEALTHCARE GROUP\n\n\u7518\u5cf0\u91ab\u7642\u4fdd\u5065\u96c6\u5718\n\nPhonak Hearing Centre HK Ltd\n\nA leading professional hearing centre in TST is seeking an applicant for the post of :\n\nPersonnel & Administration\u00a0Assistant\n\nJOB DUTIES\n\nTo be responsible for Personnel duties such as recruitment, selection and interview of new employees.\nTo be responsible for duties of payroll, leave management, attendance management, MPF/ORSO, updating staff handbook and IR56b submission.\nTo be responsible for maintaining HR Pro Personnel system by recording personal information, termination and job classifications etc.\nTo assist in preparing the work of staff appraisal and staff training and development.\nTo be responsible for duties of administration includingmedical insurance, office supplies, office machine repair and maintenance, petty cash management, whatsApp group updating etc.\nTo be responsible for additional work related to Secretary, Personnel and Administration.\nJob Requirements:\n\nDiploma/ Associate Degree or above in HR/Admin\u00a0preferred\n1-2 years working experience in HR & Admin\u00a0preferred\nGood command of spoken English & Chinese\nPC knowledge such as Microsoft Word, Excel & Chinese Word Processing\n\nWe offer attractive salary and fringe benefits including upto 20 days\u2019 annual leave, 5 day work week, year-end bonus, medical insurance, provident fund, educational assistance to the right person. Interest candidates please fax resume to 28450299 Or E-mail\u00a0", "employment_types": ["Full Time", "Permanent"], "selling_points": ["Provide administrative support to Projects Dept.", "HKDSE or above, with 3 years\u2019 relevant exp", "5-day work, 12-day AL, Dental, Double Pay + Bonus"], "locations": ["Causeway Bay"], "categories": ["Admin & HR", "Clerical / Admin Staff", "Secretary", "Property / Real Estate", "Others"], "post_time": "2022-01-17T07:30:50Z", "salary": {"currency": null, "max": null, "min": null, "period": "monthly", "term": null}, "salary_visible": false, "title_keywords": ["administrator"], "responsibilities": ["attendance", "management", "mpf", "maintaining", "maintenance", "office supplies", "hr", "repair", "recruitment", "insurance", "payroll", "administration"], "requirements": {"degrees": ["diploma", "degree or above"], "majors": [], "languages": ["english", "chinese"], "language_level": ["good command"], "hard_skills": ["excel", "pc knowledge", "microsoft word", "chinese word processing"], "soft_skills": [], "languages_combined": [{"language": "english", "language_level": ["good command"]}, {"language": "chinese", "language_level": ["good command"]}]}, "experience_required": {"duration": ["1-2 years"], "field": ["hr", "admin"]}}, {"job_id": "100003009051894", "location_code": "hk", "company": "Hospital Authority (Hong Kong East Cluster)", "job_title": "Secretarial Assistant", "description": "Our client is a fast-growing global e-commerce business that is planning to double the team by the end of 2022. They are looking for an organised and disciplined individual to help with the C-suite's increasing administrative and communication tasks.\n\n\n\nResponsibilities\n\nProvide all-rounded secretarial assistance and administrative support to C-level executives\nCalendar management and logistical coordination of internal and external meetings\nPrepare meeting minutes, reports, presentations, and other business correspondences\nOrganize and file expense reports, daily mail, and meeting materials\nCoordinate and act as a liaison between internal and external parties\nAdministrative and communication project management\nAssisting with other ad hoc requests as required\n\nRequirements\n\nBachelor's degree holder, with formal secretarial experience would be an advantage\nExcellent prioritization and organizational skills to meet the deadlines of multiple concurrent projects under pressure\nProactively solves problems and look for ways to make systems more efficient\nOutstanding communication and interpersonal skills\nExcellent command of spoken and written English, Cantonese, and Mandarin", "employment_types": ["Full Time", "Contract"], "selling_points": [], "locations": ["Eastern Area"], "categories": ["Admin & HR", "Secretary"], "post_time": "2022-01-17T01:27:34Z", "salary": {"currency": null, "max": null, "min": null, "period": "monthly", "term": null}, "salary_visible": false, "title_keywords": ["assistant"], "responsibilities": ["management", "administrative support", "ad hoc requests", "prepare meeting minutes", "internal and external parties", "presentations", "coordinate", "communication", "project management", "reports", "coordination"], "requirements": {"degrees": ["bachelor", "degree holder"], "majors": [], "languages": ["cantonese", "english", "mandarin"], "language_level": ["excellent"], "hard_skills": ["make"], "soft_skills": ["efficient", "organizational skills", "communication and interpersonal skills", "under pressure"], "languages_combined": [{"language": "cantonese", "language_level": ["excellent"]}, {"language": "english", "language_level": ["excellent"]}, {"language": "mandarin", "language_level": ["excellent"]}]}, "experience_required": {"duration": [], "field": ["secretarial"]}}, {"job_id": "100003009054816", "location_code": "hk", "company": "Essence International Financial Holdings Limited", "job_title": "\u516c\u53f8\u8463\u4e8b\u8fa6\u516c\u5ba4\u79d8\u66f8 \uff08\u8077\u7d1a\uff1a\u9ad8\u7d1a\u4e3b\u4efb\uff09", "description": "Rank :\u00a0Executive Assistant II\n\nOffice :\u00a0Human Resources Division / Hong Kong East Cluster\n\nPay :\u00a0HK$17,888 - HK$21,743 per month\n\nKey Responsibilities:\n\nProvide full spectrum of secretarial and administrative support to Senior Human Resources Managers.\nProvide support to meetings including scheduling of meetings, venue set up, preparation of meeting minutes etc.\nPerform filing, scanning and record management.\nAnswer enquiries from staff members and / or public.\nPerform other duties as assigned by supervisors.\n\nEntry Requirements:\n\nCompleted F.5/S.5 with:\n\ni. \u00a0\u00a0\u00a0\u00a0 Passes in 5 subjects in the HKCEE, including English Language (Syl B) and Chinese Language, or equivalent;\u00a0OR\n\nii. \u00a0\u00a0\u00a0 5 subjects in the HKDSE attaining the level specified below:\n\n\u2022\u00a0Level 2 in English Language and Chinese Language;\n\nand\n\n\u2022\u00a0Level 2 in New Senior Secondary subjects / \u201cAttained\u201d in Applied Learning subjects (subject to a maximum of\u00a02 subjects under this category) / Grade E in other\u00a0Language subjects; or equivalent\n\nAND\u00a0diploma in a specialized function; OR\n\nCompleted F.5 /S.5\u00a0AND\u00a0diploma in a specialized function with experience.\n\nPreferred Attributes/Exposure:\n\nKnowledge in using common office equipment, MS Office applications (such as Word, Excel, PowerPoint, Access and Outlook).\nGood interpersonal, communication, organizational and writing skills.\nAbility of working independently with minimal supervision.\nPossession of a post-secondary educational qualification in human resources management or secretarial studies.\n\nRemarks:\n\n1. Appointment will be on contract terms for up to 3 years. 5% of total basic salary as contract-end gratuity may be offered subject to completion of contract with satisfactory performance.\u00a0\n2. Retiring / retired HA staff who wish to continue working for HA after their normal retirement may also apply. If selected, the terms and conditions of employment will be offered in accordance with prevailing policies of the Retired and Rehire Mechanism of HA.\n3. May be required to work in another work location to meet service needs of the HA.\n4. The renewal/extension of appointment will be subject to service needs, availability of funding and job performance.\n5. Please submit on-line application on or before\u00a027 January\u00a02022. For enquiries, please telephone 2595\u00a05860.", "employment_types": ["Full Time", "Permanent"], "selling_points": ["\u5206\u6790\u3001\u6574\u7406\u53ca\u7de8\u5beb\u5de5\u4f5c\u5831\u544a", "\u8207\u6bcd\u516c\u53f8\u63a5\u6d3d\uff0c\u5b8c\u6210\u6709\u95dc\u5de5\u4f5c", "\u5177\u50993-5\u5e74\u4ee5\u4e0a\u6709\u95dc\u8463\u79d8\u6216\u76f8\u95dc\u5de5\u4f5c\u7d93\u9a57"], "locations": ["Central"], "categories": ["Admin & HR", "Administration / Operation Manager", "Secretary", "Banking / Finance", "Financial Services"], "post_time": "2022-01-17T11:21:22Z", "salary": {"currency": null, "max": null, "min": null, "period": "monthly", "term": null}, "salary_visible": false, "title_keywords": [], "responsibilities": ["scanning", "provide support", "management", "perform other duties", "administrative support", "scheduling of meetings"], "requirements": {"degrees": ["diploma", "hkdse"], "majors": [], "languages": ["english", "chinese"], "language_level": [], "hard_skills": ["excel", "basic", "word", "powerpoint", "writing skills", "outlook", "ms office"], "soft_skills": ["independently", "organizational", "writing skills", "communication", "learning", "interpersonal"], "languages_combined": [{"language": "english", "language_level": []}, {"language": "chinese", "language_level": []}]}, "experience_required": {"duration": [], "field": []}}, {"job_id": "100003009054583", "location_code": "hk", "company": "Value Partners Ltd", "job_title": "Junior Executive Assistant (Fresh Graduates Welcome)", "description": "\u5d17\u4f4d\u8077\u8cac\uff1a\n\n\n\u5206\u6790\u3001\u6574\u7406\u53ca\u7de8\u5beb\u516c\u53f8\u6708\u5ea6\u3001\u5b63\u5ea6\u3001\u5e74\u5ea6\u5de5\u4f5c\u7e3d\u7d50\u3002\n\u8ca0\u8cac\u6703\u8b70\u7ba1\u7406\uff0c\u5305\u62ec\u4f46\u4e0d\u9650\u65bc\u6703\u8b70\u901a\u77e5\u3001\u6703\u8b70\u8a18\u9304\u3001\u6574\u7406\u6703\u8b70\u7d00\u8981\u3002\n\u516c\u53f8\u5927\u4e8b\u8a18\u3001\u516c\u53f8\u767c\u5c55\u898f\u5283\u8abf\u7814\u3001\u6536\u96c6\u7d93\u71df\u8cc7\u6599\u914d\u5408\u6bcd\u516c\u53f8\u9700\u8981\u9032\u884c\u696d\u52d9\u6230\u7565\u5206\u6790\u53ca\u540c\u696d\u6bd4\u8f03\u5206\u6790\u3002\n\u6bcd\u516c\u53f8\u4e0b\u767c\u7684\u5176\u4ed6\u5404\u985e\u6587\u5b57\u6750\u6599\u6574\u7406\u3001\u8d77\u8349\u53ca\u532f\u7e3d\u5de5\u4f5c\uff0c\u4e26\u5f62\u6210\u5831\u544a\u3002\n\u4e0a\u7d1a\u4ea4\u8fa6\u7684\u81e8\u6642\u6027\u5de5\u4f5c\u7684\u57f7\u884c\u8207\u56de\u994b\uff0c\u53ca\u5b8c\u6210\u9818\u5c0e\u4ea4\u8fa6\u7684\u5176\u4ed6\u5de5\u4f5c\n\n\u4efb\u8077\u8981\u6c42\uff1a\n\n\u5de5\u5546\u7ba1\u7406\u3001\u6cd5\u5f8b\u3001\u91d1\u878d\u3001\u8ca1\u52d9\u7b49\u6709\u95dc\u5c08\u696d\u672c\u79d1\u6216\u7814\u7a76\u751f\u4ee5\u4e0a\u5b78\u6b77\uff1b\n\u8f03\u597d\u7684\u6587\u5b57\u5beb\u4f5c\u80fd\u529b\uff0c\u80fd\u5920\u64b0\u5beb\u5404\u985e\u8fa6\u516c\u6587\u4ef6\u53ca\u5354\u52a9\u7de8\u5236\u5206\u6790\u5831\u544a\uff1b\u80fd\u5920\u719f\u7df4\u904b\u7528\u8fa6\u516c\u8edf\u9ad4\u53caOFFICE\u8fa6\u516c\u8edf\u9ad4\uff0c\u5c24\u5176PPT\uff1b\n\u5177\u5099\u826f\u597d\u7684\u7406\u89e3\u529b\u548c\u6e9d\u901a\u8868\u9054\u80fd\u529b\uff0c\u5177\u8cac\u4efb\u611f\uff0c\u4e0d\u4ecb\u610f\u52a0\u73ed\u5de5\u4f5c\uff1b\n\u5177\u6709\u8f03\u5f37\u7684\u7d9c\u5408\u5206\u6790\u3001\u7d44\u7e54\u5354\u8abf\u3001\u6e9d\u901a\u53ca\u7368\u7acb\u601d\u8003\u80fd\u529b\uff0c\u53c3\u8b00\u7b56\u5283\u53ca\u5354\u52a9\u9818\u5c0e\u4e3b\u6301\u8d77\u8349\u6709\u95dc\u5de5\u4f5c\u898f\u5283\u3001\u5236\u5ea6\u3001\u8fa6\u6cd5\u3001\u7a0b\u5e8f\u7684\u80fd\u529b\uff1b\n\u5177\u50993-5\u5e74\u4ee5\u4e0a\u6709\u95dc\u8463\u79d8\u6216\u76f8\u95dc\u5de5\u4f5c\u7d93\u9a57\uff0c\u64c1\u6709\u4e2d\u8cc7\u9280\u884c\u6216\u91d1\u878d\u6a5f\u69cb\u5de5\u4f5c\u53ca\u4e2d\u5927\u578b\u516c\u53f8\u8463\u4e8b\u6703\u8fa6\u516c\u5ba4\u3001\u76e3\u4e8b\u6703\u8fa6\u516c\u5ba4\u5de5\u4f5c\u7d93\u9a57\u512a\u5148\u8003\u616e\u3002\n\u7d93\u9a57\u8c50\u5bcc\u8005\uff0c\u8077\u7d1a\u53ef\u8003\u616e\u70ba\u52a9\u7406\u7d93\u7406\u3002\n\n\nWe offer attractive package to the right candidate. Interested parties please apply with full resume both in English and Chinese (including current and expected salary) to\u00a0us.\u00a0\n\nPersonal data collected will be used for recruitment-related purposes only.", "employment_types": ["Full Time"], "selling_points": ["Personal Assistant to Leadership Committee Member", "Fresh Graduates Welcome", "Fluent in English"], "locations": ["Central"], "categories": ["Admin & HR", "Personal / Executive Assistant", "Secretary"], "post_time": "2022-01-17T10:06:54Z", "salary": {"currency": null, "max": null, "min": null, "period": "monthly", "term": null}, "salary_visible": false, "title_keywords": ["junior executive", "assistant"], "responsibilities": [], "requirements": {"degrees": [], "majors": [], "languages": [], "language_level": [], "hard_skills": [], "soft_skills": [], "languages_combined": []}, "experience_required": {"duration": [], "field": []}}, {"job_id": "100003009047634", "location_code": "hk", "company": "Hong Huan Group Limited", "job_title": "Personal Assistant (Family Focus)", "description": "Job Description:\n\nAssist Senior Personal Assistant to provide full spectrum of personal and business support to senior executive\nLiaise with internal and external parties for business activities, project management, etc.\nManage calendar, coordinate meetings, events, organize daily schedules and travel arrangement\nHandle business correspondence, confidential documents and other administrative duties\nWilling to handle multi-tasks and ad hoc assignment is required\nBe prepared for fieldwork, overtime and flexible working hours may be required\nOther ad-hoc personal matters as required\n\nJob Requirement:\n\nBachelor Degree or above\nFresh graduates are welcome\nExcellent command of spoken and written English and Mandarin\nWell versed in MS Office (Word, Excel and PowerPoint), Chinese word processing and familiar\u00a0with IOS device setting\nStrong sense of responsibility with handling of confidential information is a must\nGood time management, strong interpersonal and communication skills is required\nAbility to work and be highly organized under pressure, able to prioritize and handle multiple\u00a0tasks\nIndependent, meticulous, detail-oriented and be self-initiated\nWilling to travel occasionally\nInterested candidates please send your full resume with current and expected salary in MS Word Format. Personal data will be used for recruitment purpose only.\n\nOnly shortlisted candidates will be notified.", "employment_types": ["Full Time", "Permanent"], "selling_points": [], "locations": ["Ngau Tau Kok"], "categories": ["Admin & HR", "Clerical / Admin Staff", "Secretary", "Others"], "post_time": "2022-01-15T03:49:45Z", "salary": {"currency": null, "max": null, "min": null, "period": "monthly", "term": null}, "salary_visible": false, "title_keywords": ["personal assistant"], "responsibilities": ["ad-hoc", "schedules", "ad hoc assignment", "internal and external parties", "coordinate", "project management", "administrative duties", "travel arrangement", "liaise with", "business activities"], "requirements": {"degrees": ["degree or above", "bachelor"], "majors": [], "languages": ["english", "chinese", "mandarin"], "language_level": ["excellent"], "hard_skills": ["excel", "chinese word processing", "word", "powerpoint", "ms office"], "soft_skills": ["organized", "communication skills", "meticulous", "under pressure", "independent", "able to prioritize", "sense of responsibility", "detail-oriented", "handle multiple tasks", "time management", "interpersonal"], "languages_combined": [{"language": "english", "language_level": ["excellent"]}, {"language": "chinese", "language_level": []}, {"language": "mandarin", "language_level": ["excellent"]}]}, "experience_required": {"duration": [], "field": []}}, {"job_id": "100003009052943", "location_code": "hk", "company": "The Coffee Academics", "job_title": "Administrative Manager (F&B)", "description": "Job Description\n\nProviding full spectrum of secretarial, personal and family support to the Senior Executive;\nCoordinate family and household affairs including license and contract renewal;\nFollow up school matters, social functions and private activities with both internal and external parties;\nTutor/ nanny for children attending kindergarten, be able to manage all communications with school in terms of homework, school notices and school projects for all subjects.\u00a0 Report to parents on a daily basis on children progress both on homework and behavior.\u00a0\nPromote good manners and behavior through positive methods; develop their interest in learning, ability to be independent and a good sense of responsibility.\nPlan daily schedule including work and play time.\u00a0\u00a0\nMaintain the Executives\u2019 complex daily schedule and keep a good system of calendar arrangement;\nOrganize all travel arrangement for the family including ticket and accommodation, itinerary planning, visa application etc.;\nHandle ad-hoc projects and assignments assigned independently and professionally.\n\nJob Requirements\n\n\nDegree holder or above, business administration/public relations related discipline will be an advantage;\nOrganized and able to communicate effectively to all personnel;\nMinimum 3-5 years or above relevant personal assistant experience is highly preferable;\nVery high integrity, self-motivated, well-organized and good interpersonal skill;\nAble to deal with multi-cultural environment;\nGood ethics, mature, proactive, meticulous and professional;\nAttention to details, fast pace, strong communication and organizations skills are must;\nGood command in MS applications or other related tools;\nGood work references from previous employers are strongly desirable;\nFluency in both English and Chinese (Cantonese and Mandarin), written and verbal, are important.\nImmediate available will be an advantage.\n\nWe offer competitive remuneration package to the right candidates. Interested parties, please submit your resume (in both English and Chinese), with stating current and expected salary, availability, contact phone number by\u00a0APPLY NOW.\n\nAll applications and personal information collected will be treated in strict confidence and only be used for the purpose of recruitment and selection. The information collected will be accessed by our authorized personnel only. Unsuccessful applications will be retained for six months of possible future job matching, and will be destroyed after the expiry of six months.", "employment_types": ["Full Time", "Permanent"], "selling_points": [], "locations": ["Wan Chai"], "categories": ["Admin & HR", "Secretary", "Hospitality / F & B", "Food & Beverage", "Others"], "post_time": "2022-01-17T04:38:59Z", "salary": {"currency": null, "max": null, "min": null, "period": "monthly", "term": null}, "salary_visible": false, "title_keywords": ["administrative manager"], "responsibilities": ["communications with", "internal and external parties", "develop", "coordinate", "maintain", "planning", "schedule", "plan", "travel arrangement", "ad-hoc projects", "report"], "requirements": {"degrees": ["degree holder"], "majors": ["business administration"], "languages": ["cantonese", "english", "chinese", "mandarin"], "language_level": ["fluency"], "hard_skills": ["ms applications"], "soft_skills": ["organized", "self-motivated", "meticulous", "integrity", "well-organized", "mature", "interpersonal skill", "communication", "attention to details", "proactive"], "languages_combined": [{"language": "cantonese", "language_level": []}, {"language": "english", "language_level": ["fluency"]}, {"language": "chinese", "language_level": ["fluency"]}, {"language": "mandarin", "language_level": []}]}, "experience_required": {"duration": ["minimum 3-5 years"], "field": []}}, {"job_id": "100003009052778", "location_code": "hk", "company": "PCC Asia Limited", "job_title": "Administrative Assistant", "description": "We are hiring a smart and energetic\u00a0Administrative Manager to join The Coffee Academ\u00efcs group.\u00a0\n\nJob Descriptions:\n\nManage full spectrum of daily office operation.\nCoordinate office/factory/ outlets\u2019 license renewal, decoration, and renovation projects.\nCommunicate with external vendors related to insurance, lease and housekeeping matters and review all suppliers' contracts regularly.\nHandle the procurement of office and outlets\u2019 supplies, furniture and equipment and maintain an up-to date inventory record.\u00a0\nAny ad hoc tasks as required.\n\nRequirements:\n\nBachelor degree in Business Administration or related discipline.\nAt least 5 years in managerial grade position, preferably in F&B or retail industry.\nCreative, smart, passionate, diligent and pleasant characteristics.\nFluency in written and spoken English and Chinese.\nGood knowledge in MS Office application.\nImmediate availability is an advantage.\n\nAttractive remuneration package with comprehensive fringe benefits (including but not limited to medical insurance, paid marriage leave, paid condolence leave, staff discount and eWallet dollars) offered to the right candidate.\n\nInterested parties who would like to join us shall send detailed resume with current and expected salary to us.", "employment_types": ["Full Time", "Permanent"], "selling_points": [], "locations": ["Kwun Tong"], "categories": ["Admin & HR", "Clerical / Admin Staff", "Receptionist", "Secretary"], "post_time": "2022-01-17T05:15:56Z", "salary": {"currency": null, "max": null, "min": null, "period": "monthly", "term": null}, "salary_visible": false, "title_keywords": ["administrative assistant"], "responsibilities": ["communicate with", "housekeeping", "contracts", "renovation", "review", "inventory record", "ad hoc tasks", "coordinate", "maintain", "insurance"], "requirements": {"degrees": ["degree", "bachelor"], "majors": ["business administration"], "languages": ["english", "chinese"], "language_level": ["fluency"], "hard_skills": ["ms office"], "soft_skills": ["passionate", "diligent", "pleasant", "comprehensive", "creative"], "languages_combined": [{"language": "english", "language_level": ["fluency"]}, {"language": "chinese", "language_level": ["fluency"]}]}, "experience_required": {"duration": [], "field": []}}, {"job_id": "100003009054941", "location_code": "hk", "company": "Sun Hung Kai Properties Ltd", "job_title": "PERSONAL ASSISTANT", "description": "Requirements:\n\n\nHigher Diploma or above with secretarial training preferred\nMinimum 10 years\u2019 working experience in secretarial/administrative field\nProven English and Chinese proficiency\nGood interpersonal and communication skills\nFamiliar with PC software e.g. MS Word, Excel, PowerPoint & Chinese Word Processing\nOrganized, efficient & detail-minded\nPatient, Pleasant & a good team player\n\nResponsibilities:\n\n\nProvide secretarial support and handle personal family matters of the manager\nPerform administrative support to a team of senior executives\nCoordinate & schedule internal & external meetings\nHandle business correspondences and provide daily administrative support\n\nGood remuneration and attractive fringe benefits will be offered to the successful applicant. Interested parties please apply with full resume, present and expected salary, available date by clicking \"Apply Now\".\n\nFor further information, please visit our company website: http://www.shkp.com/.\n\nWe are an equal opportunity employer and welcome applications from all qualified candidates. All personal data collected will be used for recruitment purpose only.\u00a0 Applicants not hearing from us within 3 months may consider their applications unsuccessful.\u00a0 All personal data collected will be destroyed within 24 months.", "employment_types": ["Full Time", "Permanent"], "selling_points": ["Higher Diploma or above with secretarial training", "10 years\u2019 working exp in secretarial/admin field", "Familiar with PC software"], "locations": ["Wan Chai"], "categories": ["Admin & HR", "Clerical / Admin Staff", "Personal / Executive Assistant", "Secretary"], "post_time": "2022-01-17T14:32:28Z", "salary": {"currency": null, "max": null, "min": null, "period": null, "term": null}, "salary_visible": false, "title_keywords": ["personal assistant"], "responsibilities": ["coordinate", "schedule", "secretarial support", "administrative support"], "requirements": {"degrees": ["higher diploma or above"], "majors": [], "languages": ["english", "chinese"], "language_level": ["proficiency"], "hard_skills": ["excel", "chinese word processing", "powerpoint", "pc", "ms word"], "soft_skills": ["detail-minded", "organized", "communication skills", "efficient", "good team player", "pleasant", "patient", "interpersonal"], "languages_combined": [{"language": "english", "language_level": ["proficiency"]}, {"language": "chinese", "language_level": ["proficiency"]}]}, "experience_required": {"duration": ["minimum 10 years"], "field": ["secretarial", "administrative"]}}, {"job_id": "100003009051610", "location_code": "hk", "company": "Charven Development Limited", "job_title": "\u9ad8\u7d1a\u884c\u653f\u53ca\u4eba\u4e8b\u52a9\u7406 Senior Administrative and HR Assistant", "description": "\u5de5\u4f5c\u5167\u5bb9\u53ca\u8077\u8cac:\n\n\u4e00\u822c\u79d8\u66f8\u8077\u52d9;\n\u5354\u8abf\u53ca\u5b89\u6392\u8463\u4e8b\u65e5\u5e38\u884c\u7a0b;\n\u7ba1\u7406\u8b70\u7a0b\u4e26\u5b89\u6392\u6703\u8b70\u53ca\u7d04\u6703,\u6703\u8b70\u8a18\u9304;\n\u5354\u52a9\u65e5\u5e38\u4eba\u529b\u8cc7\u6e90\u5de5\u4f5c:\u7c4c\u8fa6\u57f9\u8a13\u3001\u62db\u52df\u3001\u516c\u53f8\u6d3b\u52d5;\n\u5718\u968a\u696d\u7e3e\u5831\u544a\u8ffd\u8e2a\u6210\u54e1\u696d\u7e3e/\u734e\u9805;\n\u8655\u7406\u8fa6\u516c\u5ba4\u884c\u653f\u5de5\u4f5c\uff0c\u5305\u62ec\u8a02\u8cfc\u8cfc\u6587\u5177\u3001\u8fa6\u516c\u5ba4\u7528\u54c1\u3001\u540c\u4e8b\u51fa\u52e4\u53ca\u5047\u671f\u7d00\u9304\u7b49;\n\u8655\u7406\u4e0a\u7d1a\u59d4\u6d3e\u7684\u5176\u4ed6\u5de5\u4f5c\n\n\u8077\u4f4d\u8981\u6c42:\n\n\u4e00\u5e74\u7d93\u9a57\u6216\u4ee5\u4e0a\n\u5c08\u4e0a\u6559\u80b2\u6216\u5b78\u58eb\u5b78\u4f4d(\u5546\u696d/\u884c\u653f\u7ba1\u7406/\u4eba\u529b\u8cc7\u6e90/\u793e\u6703\u79d1\u5b78)\n\u826f\u597d\u7cb5\u8a9e\u3001\u826f\u597d\u666e\u901a\u8a71\u3001\u826f\u597d\u82f1\u6587\n\u61c2\u8b80\u5beb\u4e2d\u6587\u53ca\u82f1\u6587\n\u61c2Microsoft Office\u53ca\u4e2d\u82f1\u6587\u57fa\u672c\u96fb\u8166\u64cd\u4f5c\n\n\u5de5\u4f5c\u5730\u9ede: \u89c0\u5858\u5340\n\n\u798f\u5229\u5305\u62ec\uff1a\n\n\u9280\u884c\u5047\u671f\u3001\u4e94\u5929\u5de5\u4f5c\u3001\u91ab\u7642\u4fdd\u969c\u3001\u63d0\u4f9b\u54e1\u5de5\u65e9\u5348\u81b3\u300110\u5929\u6709\u85aa\u5e74\u5047\u3001\u8003\u8a66\u5047\u3001\u5a5a\u5047\u3001\u52e4\u5de5\u734e\u3002\n\n\u00a0\u6709\u610f\u61c9\u5fb5\u8005\u8acb\u628a\u8a73\u7d30\u7684\u5c65\u6b77\u767c\u9001\u7d66\u6211\u5011\uff0c\u8acb\u8a3b\u660e\u73fe\u8077\u85aa\u91d1\u548c\u671f\u671b\u85aa\u91d1\u3002", "employment_types": ["Full Time"], "selling_points": ["\u52e4\u5de5\u734e", "10\u5929\u5927\u5047", "\u4e94\u5929\u5de5\u4f5c"], "locations": ["Kwun Tong"], "categories": ["Admin & HR", "Administration / Operation Manager", "Clerical / Admin Staff", "Secretary"], "post_time": "2022-01-16T21:50:30Z", "salary": {"currency": null, "max": null, "min": null, "period": "monthly", "term": null}, "salary_visible": false, "title_keywords": ["senior administrative", "hr assistant"], "responsibilities": [], "requirements": {"degrees": [], "majors": [], "languages": [], "language_level": [], "hard_skills": [], "soft_skills": [], "languages_combined": []}, "experience_required": {"duration": [], "field": []}}, {"job_id": "100003009051885", "location_code": "hk", "company": "LAWSGROUP", "job_title": "Administrative Assistant", "description": "Job Description:\n\nProvide secretarial services and administrative support for Directors and Senior Secretaries by maintaining filing systems, coordinating schedule for meetings and travel arrangement, handling reports and correspondences, drafting minutes etc\nDraft general correspondence, including letters, memos, faxes and reports etc.\nAssist in organizing travel itineraries, including booking flights, hotels, restaurants etc.\nHandle ad hoc projects as required\n\nJob Requirements:\n\nDegree / High Diploma holder, preferably in Business Administration\nMinimum 1 year relevant experience\nGood command of both spoken and written English, Chinese and Mandarin\nExcellent interpersonal skills, independent, meticulous, well-organized, proactive and eager to learn\nPositive working attitude and able to work under pressure\nProficient in MS office including MS Word, Excel, Powerpoint & Chinese Word Processing\nCandidate with more experience will be considered as Administrative Executive\nWe\u00a0offer\u00a0attractive remuneration package to the right candidate. Interested parties please click the \"APPLY NOW\" button below and send your application together with a detailed resume including current & expected salary and availability to Human Resources Department.\nCompany website:\u00a0https://www.lawsgroup.com\n(Data collected will be treated in strict confidence and used for recruitment purpose only)", "employment_types": ["Full Time", "Permanent"], "selling_points": ["Higher Diploma or above in Business Administration", "At least 1 year relevant experience", "Provide secretarial services and admin support"], "locations": ["Lai Chi Kok"], "categories": ["Admin & HR", "Clerical / Admin Staff", "Secretary", "Others"], "post_time": "2022-01-17T01:26:49Z", "salary": {"currency": null, "max": null, "min": null, "period": "monthly", "term": null}, "salary_visible": false, "title_keywords": ["administrative assistant"], "responsibilities": ["maintaining", "administrative support", "systems", "letters", "reports", "schedule", "travel arrangement", "booking", "ad hoc projects"], "requirements": {"degrees": ["high diploma", "degree"], "majors": ["business administration"], "languages": ["english", "chinese", "mandarin"], "language_level": ["good command", "proficient"], "hard_skills": ["excel", "chinese word processing", "powerpoint", "ms office", "ms word"], "soft_skills": ["meticulous", "independent", "well-organized", "eager to learn", "positive working attitude", "interpersonal skills", "proactive", "work under pressure"], "languages_combined": [{"language": "english", "language_level": ["good command"]}, {"language": "chinese", "language_level": ["good command", "proficient"]}, {"language": "mandarin", "language_level": ["good command"]}]}, "experience_required": {"duration": ["minimum 1 year"], "field": ["administrative", "relevant experience"]}}, {"job_id": "100003009052602", "location_code": "hk", "company": "NAHC Limited", "job_title": "Executive Assistant", "description": "Our client is a fast-growing global e-commerce business that is planning to double the team by the end of 2022. They are looking for an organised and disciplined individual to help with the C-suite's increasing administrative and communication tasks.\n\n\n\nResponsibilities\n\nProvide all-rounded secretarial assistance and administrative support to C-level executives\nCalendar management and logistical coordination of internal and external meetings\nPrepare meeting minutes, reports, presentations, and other business correspondences\nOrganize and file expense reports, daily mail, and meeting materials\nCoordinate and act as a liaison between internal and external parties\nAdministrative and communication project management\nAssisting with other ad hoc requests as required\n\nRequirements\n\nBachelor's degree holder, with formal secretarial experience would be an advantage\nExcellent prioritization and organizational skills to meet the deadlines of multiple concurrent projects under pressure\nProactively solves problems and look for ways to make systems more efficient\nOutstanding communication and interpersonal skills\nExcellent command of spoken and written English, Cantonese, and Mandarin", "employment_types": ["Full Time", "Permanent"], "selling_points": ["Fast Growing Global E-commerce Business", "Trilingual Executive Assistant", "Confident, organised and proactive team player"], "locations": ["Tsuen Wan Area"], "categories": ["Admin & HR", "Administration / Operation Manager", "Personal / Executive Assistant", "Secretary"], "post_time": "2022-01-17T03:30:46Z", "salary": {"currency": null, "max": null, "min": null, "period": "monthly", "term": null}, "salary_visible": false, "title_keywords": ["executive assistant"], "responsibilities": ["management", "administrative support", "ad hoc requests", "prepare meeting minutes", "internal and external parties", "presentations", "coordinate", "communication", "project management", "reports", "coordination"], "requirements": {"degrees": ["bachelor", "degree holder"], "majors": [], "languages": ["cantonese", "english", "mandarin"], "language_level": ["excellent"], "hard_skills": ["make"], "soft_skills": ["efficient", "organizational skills", "communication and interpersonal skills", "under pressure"], "languages_combined": [{"language": "cantonese", "language_level": ["excellent"]}, {"language": "english", "language_level": ["excellent"]}, {"language": "mandarin", "language_level": ["excellent"]}]}, "experience_required": {"duration": [], "field": ["secretarial"]}}, {"job_id": "100003008017686", "location_code": "hk", "company": "Exceed Consulting Limited", "job_title": "Executive Assistant to Management (Confidential Role)", "description": "Our client, is a reputable conglomerate with a diverse businesses around APAC. They are looking for an Executive Assistant to report to a senior management in Hong Kong to look after the business and personal matters.\u00a0\n\nJob Description\u00a0\n\n\nProvide full spectrum of secretarial support\nMaintain an accurate and detailed calendar, manage and log incoming scheduling requests\nManage international & local travel scheduling and arrangement\nLiaise with other senior management's executive assistant to coordinate the meetings/conference calls and customers visit\nOrganize internal and external meetings and draft replies and calls, including logistics and preparation\n\nRequirement\n\n8-10 years of experience in serving C-level or top management\nCandidate with experience working in legal services or giant corporations will be highly preferred\nExcellent spoken and written English and Mandarin\nGreat organizational Skills\nInterpersonal and communication skills Active listening skills\nProductivity and initiative\nKeeping calm under pressure\nAccuracy and attention to detail\nTrustworthiness, discretion, confidentiality and responsibility\nAlternative Saturday Morning, Flexible to work on Public Holidays (Compensation Leave)", "employment_types": ["Full Time", "Permanent"], "selling_points": ["Reputable Conglomerate (45K - 50K per month)", "Attractive Year End Bonus", "Excellent Fringe Benefits"], "locations": ["Eastern Area"], "categories": ["Admin & HR", "Personal / Executive Assistant", "Secretary"], "post_time": "2022-01-17T06:59:14Z", "salary": {"currency": null, "max": null, "min": null, "period": "monthly", "term": null}, "salary_visible": false, "title_keywords": ["executive assistant"], "responsibilities": ["coordinate", "scheduling", "maintain", "logistics", "secretarial support", "liaise with", "senior management"], "requirements": {"degrees": [], "majors": [], "languages": ["english", "mandarin"], "language_level": ["excellent"], "hard_skills": ["c"], "soft_skills": ["flexible", "communication skills", "organizational skills", "under pressure", "interpersonal", "calm", "attention to detail", "active", "initiative"], "languages_combined": [{"language": "english", "language_level": ["excellent"]}, {"language": "mandarin", "language_level": ["excellent"]}]}, "experience_required": {"duration": ["8-10 years"], "field": ["management", "legal"]}}, {"job_id": "100003009052717", "location_code": "hk", "company": "Delken Group Limited", "job_title": "Secretary (5-day work)", "description": "Our client is a Leading Financial\u00a0Institution\u00a0,\u00a0they are currently seeking for a Secretary to join their team.\n\n\nResponsibilities\n\nProvide professional secretarial support to the supervisor\u00a0\nWork independently on administration and logistics for arranging internal and external meetings, seminars, conferences, training classes and other events in physical and online format.\u00a0\nPropose and prepare administrative documents and correspondences for meetings / events and office management\nMaintain amicable and close relationship with external parties, such as executive of senior executives and directors of commercial and government organisations, and internal departments\u00a0\nPlan travel, including flights, accommodation and ground transportation for business visits\u00a0\nManage the database and systems for records\u00a0\nMaintain office supplies\u00a0\nUndertake data inputting and other duties as assigned\u00a0\n\nRequirements:\n\nUniversity degree preferred, or equivalent combination of education, training and experience, with 5 subjects passed including Chinese Lang & Eng. Lang in\u00a0 HKDSE/HKCEE result\nAt least five years' relevant experience in sizable organisations\u00a0\nGood command of both written and spoken English and Chinese\u00a0\nGood communication, time-management and organisational skills\u00a0\nExcellent knowledge of software applications, including Microsoft Office, Chinese word-processing, Powerpoint, Excel and software applications in relation to photo editing and graphics\u00a0\nInterested candidates, please send your resume (MS Word document) including employment history, present and expected salary to us.\n\n\n\u00a0\nFor more jobs, please visit our website:\u00a0www.delken.com.hk.\n\n(All personal data submitted will be treated in strict confidential and used for recruitment purposes only.)", "employment_types": ["Full Time", "Permanent"], "selling_points": ["5 years of rel exp in sizable organisations", "Work independently on Secretarial; /Admin support", "5-days work, good benefit"], "locations": ["Central"], "categories": ["Admin & HR", "Clerical / Admin Staff", "Secretary", "Banking / Finance", "Others"], "post_time": "2022-01-17T03:47:18Z", "salary": {"currency": null, "max": null, "min": null, "period": "monthly", "term": null}, "salary_visible": false, "title_keywords": ["secretary"], "responsibilities": ["management", "other duties", "data", "office supplies", "external parties", "systems", "conferences", "maintain", "logistics", "secretarial support", "plan", "manage the database", "administration"], "requirements": {"degrees": ["university degree", "hkdse"], "majors": [], "languages": ["english", "chinese"], "language_level": ["excellent", "good command"], "hard_skills": ["graphics", "excel", "chinese word-processing", "microsoft office", "powerpoint"], "soft_skills": ["communication", "organisational skills"], "languages_combined": [{"language": "english", "language_level": ["good command"]}, {"language": "chinese", "language_level": ["excellent", "good command"]}]}, "experience_required": {"duration": ["at least five years"], "field": ["relevant experience", "training", "education"]}}, {"job_id": "100003009052183", "location_code": "hk", "company": "The Hong Kong Girl Guides Association", "job_title": "Assistant Administrative Officer", "description": "To cope with our development, HKGGA is now looking for candidates of high caliber to join us:\n\n\nResponsibilities:\n\n\nProvide administrative and secretarial support, such as writing minutes, letters and reports for Administration Department as well as senior management.\nAnswer telephone enquiries and perform daily routine administration tasks.\nAssist senior executives to organize events and projects as required.\nIrregular working hours in weekends and public holidays is required if necessary.\n\nRequirements:\n\n\n\nBachelor of Arts or equivalent;\nAt least 2 year\u2019s administrative work experience, social service sector or NGOs is highly preferred\nProficient in spoken and written English language\nProficient in Putonghua is preferable\nWell-versed in Microsoft Office and Chinese word processing e.g. \u901f\u6210or\u5009\u9821\nAble to communicate with all levels of people\nMeticulous, patient and work under pressure\nCandidate with more experience will be considered as Administrative Officer\u00a0\n\nPlease send r\u00e9sum\u00e9 with Ref. Code and expected salary by clicking \"Apply Now\" or to Human Resources Department, 8 Gascoigne Road, Kowloon. Please mark \u201cPrivate & Confidential\u201d on the envelope.\n\nProspective employees are required to undergo Sexual Conviction Record Check.\n\u672c\u6703\u5c07\u8981\u6c42\u6e96\u50f1\u54e1\u9032\u884c\u6027\u7f6a\u884c\u5b9a\u7f6a\u7d00\u9304\u67e5\u6838\u3002\n\nPersonal data provided will be used for recruitment purpose only. All personal data of unsuccessful applicants will be destroyed on completion of the recruitment exercise.", "employment_types": ["Full Time", "Permanent"], "selling_points": [], "locations": ["Yau Tsim Mong Area"], "categories": ["Admin & HR", "Clerical / Admin Staff", "Secretary", "Public / Civil", "Social Services - Community / Non-profit Organization"], "post_time": "2022-01-17T02:22:27Z", "salary": {"currency": null, "max": null, "min": null, "period": "monthly", "term": null}, "salary_visible": false, "title_keywords": ["administrative officer", "assistant"], "responsibilities": ["letters", "reports", "secretarial support", "senior management", "administration"], "requirements": {"degrees": ["bachelor"], "majors": [], "languages": ["putonghua", "english", "chinese"], "language_level": ["proficient"], "hard_skills": ["code", "chinese word processing", "microsoft office"], "soft_skills": ["meticulous", "patient", "work under pressure"], "languages_combined": [{"language": "putonghua", "language_level": ["proficient"]}, {"language": "english", "language_level": []}, {"language": "chinese", "language_level": []}]}, "experience_required": {"duration": ["at least 2 year"], "field": ["administrative"]}}, {"job_id": "100003009052650", "location_code": "hk", "company": "Talent Preneur Management Consultancy Co. Limited", "job_title": "Personal Assistant (\u79c1\u4eba\u52a9\u7406)", "description": "\u8077\u8cac\uff1a\n\n\u70ba\u8463\u4e8b\u9577\u63d0\u4f9b\u5168\u65b9\u4f4d\u7684\u79c1\u4eba\u52a9\u7406\u652f\u63f4\uff0c\u5982\u652f\u4ed8\u6c34\u96fb\u7164\u55ae\uff0c\u8cfc\u8cb7\u7269\u8cc7\u7b49\n\u8ca0\u8cac\u8463\u4e8b\u9577\u65e5\u5e38\u9910\u98f2\u7684\u5b89\u6392\u53ca\u7dad\u6301\u5730\u65b9\u6574\u6f54\n\u5b89\u6392\u8463\u4e8b\u9577\u7684\u65e5\u7a0b\uff0c\u65e5\u5e38\u6703\u5ba2\u53ca\u6d3b\u52d5\u7684\u9810\u5831\n\u8655\u7406\u548c\u7dad\u8b77\u6a5f\u5bc6\u6587\u4ef6\n\u4e00\u822c\u79ae\u7269\u53ca\u7bc0\u65e5\u79ae\u54c1\u7684\u4e00\u5207\u5b89\u6392\n\u5354\u8abf\u5404\u9805\u516c\u53f8\u884c\u653f\u3001\u6d3b\u52d5\u7b49\u76f8\u95dc\u5de5\u4f5c\n\u6839\u64da\u9700\u8981\u9032\u884c\u6236\u5916\u5de5\u4f5c\u53ca\u57f7\u884c\u81e8\u6642\u4efb\u52d9\n\u8981\u6c42\uff1a\n\n\u5b78\u58eb\u5b78\u4f4d\u6216\u4ee5\u4e0a\u5b78\u6b77\uff0c\u6216\u5177\u5099\u79d8\u66f8\u3001\u79c1\u4eba\u52a9\u7406\u7b49\u76f8\u95dc\u7d93\u9a57\n\u61c2\u807d\u5beb\u8aaa\u5ee3\u6771\u8a71\u548c\u666e\u901a\u8a71\n\u59a5\u5584\u5730\u8655\u7406\u5404\u7a2e\u7a81\u767c\u4e8b\u4ef6\uff0c\u80fd\u5920\u7d55\u5c0d\u4fdd\u5bc6\n\u505a\u4e8b\u4ed4\u7d30\u8a8d\u771f\uff0c\u6297\u58d3\u529b\u5f37\n\u80fd\u5920\u81ea\u5f8b\u53ca\u4e3b\u52d5\u532f\u5831\u5de5\u4f5c\u9032\u5ea6\uff0c\u4e26\u53ca\u6642\u4f5c\u51fa\u56de\u61c9\n\u51fa\u8272\u7684\u4eba\u969b\u95dc\u4fc2\uff0c\u5354\u8abf\u548c\u7d44\u7e54\u80fd\u529b\n\u53ef\u5373\u6642\u4e0a\u73ed\u8005\u53ef\u512a\u5148\u8003\u616e\n\u6b61\u8fce\u6709\u5167\u5730\u80cc\u666f\u4eba\u58eb\u7533\u8acb", "employment_types": ["Full Time", "Part Time", "Permanent"], "selling_points": [], "locations": ["Shatin Area"], "categories": ["Admin & HR", "Administration / Operation Manager", "Personal / Executive Assistant", "Secretary"], "post_time": "2022-01-17T03:38:42Z", "salary": {"currency": "HKD", "max": 29999, "min": 25000, "period": "monthly", "term": null}, "salary_visible": true, "title_keywords": ["\u79c1\u4eba\u52a9\u7406", "personal assistant"], "responsibilities": [], "requirements": {"degrees": [], "majors": [], "languages": [], "language_level": [], "hard_skills": [], "soft_skills": [], "languages_combined": []}, "experience_required": {"duration": [], "field": []}}, {"job_id": "100003008980854", "location_code": "hk", "company": "Shun Lee Building Materials and Sanitary Wares Ltd", "job_title": "Project Sales Coordinator", "description": "Responsibilities:\n\nAssist Project Sales Team on order management\nHandle sales documents such as quotations, purchasing orders, sales invoices and delivery notes\nManage the distribution of inventory control\nLiaise with customers and logistic parties\nFollow up shipping schedule, delivery and outstanding payment\nProvide administrative support to the team and perform ad hoc duties as assigned\n\nRequirements:\n\nDiploma or above in any discipline\n1-2 years relevant working experience on sales administration or related field\nGood communication skills and interpersonal skills\nGood command of written and spoken English, Chinese and Putonghua\nProficient in MS Word, Excel, PowerPoint and Chinese Word Processing\nSelf-motivated, well-organized, able to work under pressure and willing to work overtime\nImmediate available is an advantage\nCandidate with more experience will be considered as Sales Administrator\n\nWe offer a 5-day work week, competitive salary, attractive commission, discretionary performance bonus, medical benefits, marriage leave, compassionate leave, staff purchase discount and excellent career prospects.\n\nInterested parties please send your application letter and full resume with current / expected salary and availability to Human Resources Department by clicking APPLY NOW.\n\n\nFor more information about our Company, please visit our website at\u00a0https://shunlee.com.hk\u00a0\n\u00a0\nInformation collected will be treated in strict confidence and only be used for recruitment purpose.", "employment_types": ["Full Time", "Permanent"], "selling_points": [], "locations": ["Lai Chi Kok"], "categories": ["Admin & HR", "Secretary", "Merchandising & Purchasing", "Others", "Sales, CS & Business Devpt", "Sales Administration"], "post_time": "2022-01-16T21:50:05Z", "salary": {"currency": null, "max": null, "min": null, "period": "monthly", "term": null}, "salary_visible": false, "title_keywords": ["sales coordinator"], "responsibilities": ["shipping schedule", "ad hoc duties", "order management", "invoices", "payment", "inventory control", "sales team", "liaise with", "provide administrative support"], "requirements": {"degrees": ["diploma or above"], "majors": [], "languages": ["putonghua", "english", "chinese"], "language_level": ["good command", "proficient"], "hard_skills": ["excel", "chinese word processing", "powerpoint", "ms word"], "soft_skills": ["communication skills", "self-motivated", "work overtime", "well-organized", "interpersonal skills", "work under pressure"], "languages_combined": [{"language": "putonghua", "language_level": ["good command"]}, {"language": "english", "language_level": ["good command"]}, {"language": "chinese", "language_level": ["good command", "proficient"]}]}, "experience_required": {"duration": ["1-2 years"], "field": ["related", "sales administration", "relevant working experience"]}}, {"job_id": "100003009047698", "location_code": "hk", "company": "Moore Associates Limited", "job_title": "Secretary", "description": "Responsibilities:\n\nReport to Directors and Team Executives\nProvide comprehensive secretarial and administrative support\nSchedule, co-ordinate and organize meetings\nArrange travel and accommodation\nPrepare correspondences\nHandle and maintain records and documents\nAd-hoc tasks and other duties as assigned\n\nRequirements: \u00a0\n\nTertiary educated\nRelevant experience in professional services firm is preferred\nProficient in Microsoft office and Chinese word processing\nStrong language skills in English and Chinese\nFluent in Mandarin\nStrong organizational, interpersonal and communication skills\n\nCompetitive package will be offered to the right candidate(s), including 5 day work week, paid examination & study leave, birthday leave & medical insurance coverage. Interested parties please send full resume with working experience, academic and professional qualifications, including present & expected salary by clicking the \"Apply Now\" button.\u00a0 Personal data collected will be used for recruitment purposes only.\n\nSimply click the \u201cApply Now\u201d button\n\nPlease visit our website at\u00a0www.moore.hk\u00a0to know more about us.", "employment_types": ["Full Time", "Permanent"], "selling_points": ["Secretarial and administrative support", "Tertiary educated", "Schedule, co-ordinate and organize meetings"], "locations": ["Tsim Sha Tsui"], "categories": ["Accounting", "Others", "Admin & HR", "Secretary"], "post_time": "2022-01-15T03:49:49Z", "salary": {"currency": null, "max": null, "min": null, "period": "monthly", "term": null}, "salary_visible": false, "title_keywords": ["secretary"], "responsibilities": ["other duties", "administrative support", "ad-hoc tasks", "maintain", "schedule", "report"], "requirements": {"degrees": [], "majors": [], "languages": ["english", "chinese", "mandarin"], "language_level": ["fluent", "proficient"], "hard_skills": ["chinese word processing", "microsoft office"], "soft_skills": ["communication skills", "organizational", "interpersonal"], "languages_combined": [{"language": "english", "language_level": []}, {"language": "chinese", "language_level": ["proficient"]}, {"language": "mandarin", "language_level": ["fluent"]}]}, "experience_required": {"duration": [], "field": ["relevant experience"]}}, {"job_id": "100003009046936", "location_code": "hk", "company": "Champion Land Properties Limited", "job_title": "Secretary (Ref: S/BD/JDB)", "description": "The successful candidate will provide full spectrum of secretarial and business administrative support to a designated senior executive including meeting and travel arrangements, handling correspondence, departmental administration, preparation on reports and presentation materials, liaising with internal and external parties, assisting in various projects and performing ad hoc duties as assigned.\nRequirements:\nUniversity graduates in any discipline\nMinimum 5 years of relevant experience in sizeable organizations to senior executive\nExcellent command of spoken and written English and Chinese, including Putonghua\nStrong communication and interpersonal skills, well organized and detail-minded\nReliable, helpful, self-motivated with pleasant personality and able to work as a team\nAble to work under pressure and handle multi-tasks with strong sense of responsibility\nProficient in Microsoft Office including MS Word, Excel and PowerPoint; Chinese Word Processing and Outlook\nWe offer attractive remuneration packages commensurate with experience and qualifications. If you aspire to an exciting and rewarding career, send your resume immediately, quoting your present and expected salaries by clicking the button\u00a0\u201cApply Now\u201d.\nIf the applicant does not receive a response by\u00a013 February 2022, the application will be considered unsuccessful.\u00a0 Please read our Personal Information Collection Statement at\u00a0https://www.sino.com/en-US/Careers/Personal-Information-Collection-Statement\u00a0before submitting your application. Information provided by applicants will be treated in strict confidence and used for recruitment purposes only.", "employment_types": ["Full Time"], "selling_points": [], "locations": ["Not Specified"], "categories": ["Admin & HR", "Clerical / Admin Staff", "Secretary", "Others"], "post_time": "2022-01-14T01:48:28Z", "salary": {"currency": null, "max": null, "min": null, "period": "monthly", "term": null}, "salary_visible": false, "title_keywords": ["secretary"], "responsibilities": ["ad hoc duties", "travel arrangements", "administrative support", "work under pressure", "internal and external parties", "liaising with", "communication", "reports", "administration"], "requirements": {"degrees": [], "majors": [], "languages": ["putonghua", "english", "chinese"], "language_level": ["excellent"], "hard_skills": ["excel", "chinese word processing", "microsoft office", "powerpoint", "outlook", "ms word"], "soft_skills": ["detail-minded", "self-motivated", "work as a team", "multi-tasks", "sense of responsibility", "well organized", "pleasant", "communication and interpersonal skills", "reliable", "presentation", "work under pressure"], "languages_combined": [{"language": "putonghua", "language_level": ["excellent"]}, {"language": "english", "language_level": ["excellent"]}, {"language": "chinese", "language_level": ["excellent"]}]}, "experience_required": {"duration": ["minimum 5 years"], "field": ["relevant experience"]}}, {"job_id": "100003009054203", "location_code": "hk", "company": "Global Union Ltd", "job_title": "Admin Assistant", "description": "Responsibilities:\n\nUpdating reports and filing documents\nFollow up the project progress\nAnalysis market data\nProvide general admin support\nAny other personal duties as may reasonably be required by the Director\nPerform ad-hoc assignments\n\n\u00a0Requirements:\u00a0\n\nDiploma holder or equivalent or above\nGood command of written and spoken English and Cantonese\nKnowledge in Word and Excel\nIndependent, well-organized, self-motivated with strong sense of responsibility\nFresh graduates or less working experience will be more preferred\nImmediate available is highly preferred\n\n\u00a0We offer attractive salaries and benefits for the right candidates.\n(Personal data collected will be used for recruitment purpose)\n", "employment_types": ["Full Time"], "selling_points": [], "locations": ["Kwai Fong"], "categories": ["Admin & HR", "Clerical / Admin Staff", "Receptionist", "Secretary"], "post_time": "2022-01-17T08:49:08Z", "salary": {"currency": null, "max": null, "min": null, "period": "monthly", "term": null}, "salary_visible": false, "title_keywords": ["admin assistant"], "responsibilities": ["ad-hoc assignments", "analysis", "project progress", "admin support", "reports", "market data"], "requirements": {"degrees": ["diploma holder"], "majors": [], "languages": ["cantonese", "english"], "language_level": ["good command"], "hard_skills": ["excel", "word"], "soft_skills": ["self-motivated", "independent", "well-organized", "sense of responsibility"], "languages_combined": [{"language": "cantonese", "language_level": ["good command"]}, {"language": "english", "language_level": ["good command"]}]}, "experience_required": {"duration": [], "field": []}}, {"job_id": "100003009051450", "location_code": "hk", "company": "Optimum Solutions (Hong Kong) Limited", "job_title": "Administrator / Administrative Assistant", "description": "-\u00a0\u00a0\u00a0\u00a0\u00a0\u00a0\u00a0\u00a0 Plan meetings and take detailed minutes\n\n-\u00a0\u00a0\u00a0\u00a0\u00a0\u00a0\u00a0\u00a0 Write and distribute internal communication\n\n-\u00a0\u00a0\u00a0\u00a0\u00a0\u00a0\u00a0\u00a0 Responsible for the preparation of regularly scheduled reports\n\n-\u00a0\u00a0\u00a0\u00a0\u00a0\u00a0\u00a0\u00a0 Update and maintain PMO policies and procedures\n\n-\u00a0\u00a0\u00a0\u00a0\u00a0\u00a0\u00a0\u00a0 Act as the point of contact for all Project Managers\n\n-\u00a0\u00a0\u00a0\u00a0\u00a0\u00a0\u00a0\u00a0 Responsible for consolidating reports for all Programs\n\nRequirements:\n\n-\u00a0\u00a0\u00a0\u00a0\u00a0\u00a0\u00a0\u00a0 Proven experience as an Administrative Assistant\n\n-\u00a0\u00a0\u00a0\u00a0\u00a0\u00a0\u00a0\u00a0 Proficiency in MS Office (MS Excel and MS PowerPoint, in particular), Microsoft Project\n\u00a0 \u00a0 \u00a0 \u00a0\n\n-\u00a0 \u00a0 \u00a0 \u00a0 \u00a0Good time management, attention to details\n\n-\u00a0 \u00a0 \u00a0 \u00a0 \u00a0Good\u00a0\u00a0written and verbal communication skills in English\n\n-\u00a0 \u00a0 \u00a0 \u00a0 \u00a0With knowledge in Sharepoint is highly preferred\n\n\n", "employment_types": ["Full Time", "Permanent", "Contract"], "selling_points": ["3 years or above admin or secretarial experience", "Good communication skills, fluent in English", "Serve IT Project Managers"], "locations": ["Others"], "categories": ["Admin & HR", "Administration / Operation Manager", "Clerical / Admin Staff", "Secretary"], "post_time": "2022-01-16T03:46:36Z", "salary": {"currency": null, "max": null, "min": null, "period": "monthly", "term": null}, "salary_visible": false, "title_keywords": ["administrative assistant", "administrator"], "responsibilities": ["management", "policies", "procedures", "communication", "maintain", "reports", "contact", "plan"], "requirements": {"degrees": [], "majors": [], "languages": ["english"], "language_level": ["good"], "hard_skills": ["ms powerpoint", "ms excel", "microsoft project", "ms office"], "soft_skills": ["communication skills", "responsible", "communication", "attention to details", "time management", "detailed"], "languages_combined": [{"language": "english", "language_level": ["good"]}]}, "experience_required": {"duration": [], "field": ["administrative"]}}, {"job_id": "100003009046608", "location_code": "hk", "company": "MTR Corporation Limited", "job_title": "Temporary Administrative Assistant (HK Transport Services Business Unit) (Ref.: 2100018R)", "description": "Responsibilities\n\u2022\u00a0\u00a0 \u00a0Provide general clerical support, such as record filing, data entry, reporting, meeting coordination, handle enquiry and other administrative duties as assigned\n\nRequirements\n\u2022\u00a0\u00a0 \u00a0Grade E / Level 2 / \"Attained\" or above in 5 subjects of HKCEE / HKDSE, including English and Chinese Languages\n\u2022\u00a0\u00a0 \u00a0A minimum 4 years' relevant experience\n\u2022\u00a0\u00a0 \u00a0Hands-on experience in various software applications such as Excel, PowerPoint and Chinese and English word processing\n\u2022\u00a0\u00a0 \u00a0Be meticulous and able to work independently\n\u00a0\n\nRemarks\n\u2022\u00a0\u00a0 \u00a0Appointment will be made on six-month temporary contract terms\n\nApplications\nYou are invited to apply online via\u00a0http://www.mtr.com.hk/mtr_job_en\u00a0or send in your CV stating the position (with reference number) you are applying for by mail to Human Resource Management Department, MTR Corporation, G.P.O. Box 9916, Hong Kong\u00a0on or before 27 January 2022.\n\nFor other job openings, please visit MTR Corporation's website for more details.\n\nAll information provided by applicants will be treated in strict confidence and used for recruitment purpose only. All personal data of unsuccessful applicants will be retained for 12 months for future recruitment purpose and will then be destroyed.", "employment_types": ["Contract"], "selling_points": ["Provide general clerical support", "Grade E / Level 2 / \"Attained\" or above", "A minimum 4 years' relevant experience"], "locations": ["Hung Hom"], "categories": ["Admin & HR", "Clerical / Admin Staff", "Secretary"], "post_time": "2022-01-13T16:26:16Z", "salary": {"currency": null, "max": null, "min": null, "period": "monthly", "term": null}, "salary_visible": false, "title_keywords": ["temporary administrative assistant"], "responsibilities": ["reporting", "data entry", "handle enquiry", "clerical support", "administrative duties", "coordination"], "requirements": {"degrees": ["hkdse"], "majors": [], "languages": ["english", "chinese"], "language_level": [], "hard_skills": ["chinese and english word processing", "excel", "powerpoint"], "soft_skills": ["meticulous", "hands-on", "confidence", "work independently"], "languages_combined": [{"language": "english", "language_level": []}, {"language": "chinese", "language_level": []}]}, "experience_required": {"duration": ["minimum 4 years"], "field": ["relevant experience"]}}, {"job_id": "100003009052912", "location_code": "hk", "company": "Asiasec Properties Limited", "job_title": "Company Secretarial Assistant", "description": "\u00a0Responsibilities\n\nTo handle full spectrum of company secretarial duties for a listed company and its subsidiaries in compliance with the relevant statutory and regulatory requirements\nTo assist in organising committees, board and shareholders meetings and preparation of minutes\nTo assist in drafting and preparation of announcements, circulars and annual/interim reports\nAssist in ad-hoc projects and tasks as assigned\n\nRequirements\n\nMinimum 2 years working experience (related knowledge and experience is an advantage)\nEager to learn, responsible, detail-minded, well-organised, good communication and interpersonal skills\nAbility to work under pressure and tight schedule\nGood typing skill and solid PC skills (MS Word, Excel, Powerpoint, Outlook, CSA) and Chinese Word Processing\nGood command of written and spoken English and Chinese (in Cantonese & Putonghua)\n\nCompetitive remuneration package will be offered to the right candidate.\u00a0 Interested parties please apply with full resume stating present & expected salary, date available and day-time contact phone number by clicking the Apply Now Button.\n\n\n(Data collected will be used for recruitment purpose only.)", "employment_types": ["Full Time", "Permanent"], "selling_points": ["Company Secretarial knowledge is an advantage", "2 years working experience", "5-day work"], "locations": ["Wan Chai"], "categories": ["Admin & HR", "Secretary", "Professional Services", "Company Secretary"], "post_time": "2022-01-17T04:30:50Z", "salary": {"currency": null, "max": null, "min": null, "period": "monthly", "term": null}, "salary_visible": false, "title_keywords": ["company secretarial assistant"], "responsibilities": ["regulatory requirements", "ad-hoc projects", "compliance", "reports"], "requirements": {"degrees": [], "majors": [], "languages": ["cantonese", "putonghua", "english", "chinese"], "language_level": ["good command", "good"], "hard_skills": ["excel", "chinese word processing", "typing", "powerpoint", "outlook", "pc skills", "ms word"], "soft_skills": ["detail-minded", "responsible", "eager to learn", "communication and interpersonal skills", "well-organised", "work under pressure"], "languages_combined": [{"language": "cantonese", "language_level": ["good command", "good"]}, {"language": "putonghua", "language_level": ["good command", "good"]}, {"language": "english", "language_level": ["good command", "good"]}, {"language": "chinese", "language_level": ["good command", "good", "good"]}]}, "experience_required": {"duration": ["minimum 2 years"], "field": ["related"]}}, {"job_id": "100003009053078", "location_code": "hk", "company": "Spidernet Recruitment Services", "job_title": "Receptionist and Administration Assistant", "description": "Receptionist and Administration Assistant\n\nSalary: HK$18-22k\n\nResponsibilities:\n\nHandle incoming calls and greeting visitors in a professional and polite manner\nAssist in the office administration function including office and facilities maintenance, ordering stationery & pantry supplies, maintain the cleanliness and tidiness of the office area, booking and monitoring the use of conference rooms and company cars and drivers\nHandle courier services, coordinate the dispatch and distribution of local & overseas parcels/documents\n\u00adProcessing of the expenses claims through systems\n\nRequirements:\n\nFluency in spoken Mandarin (a must), Cantonese and English is essential\nAt least 3-5 years Receptionist and Office Administration experience in sizable, preferable have experience in China-based company\nGood interpersonal and communications skills\nProficient with MS Word, Excel & Chinese Word Processing\n\u00adCustomer Focus and Service Oriented\nHard working with strong sense of responsibility\n\u00adDetail-orientated and resourceful\nOrganized, self-motivated and a good team player\n\nAttractive remuneration and fringe benefits will be offered to the successful candidate.\n\nInterested candidates should apply with detailed resume, present and expected salaries by clicking the Apply Now button.\n\nAll information received will be treated in strict confidence and used for recruitment purpose only.\n\nOnly shortlisted candidates will be notified.", "employment_types": ["Full Time", "Permanent"], "selling_points": ["Fluent spoken of Mandarin is a must", "3-5 yrs Receptionist and Administration exp.", "Immediately available is preferable"], "locations": ["Central & Western Area"], "categories": ["Admin & HR", "Clerical / Admin Staff", "Receptionist", "Secretary"], "post_time": "2022-01-17T05:40:00Z", "salary": {"currency": null, "max": null, "min": null, "period": "monthly", "term": null}, "salary_visible": false, "title_keywords": ["receptionist", "administration assistant"], "responsibilities": ["maintenance", "office administration", "monitoring", "expenses", "stationery", "systems", "coordinate", "maintain", "booking", "greeting visitors"], "requirements": {"degrees": [], "majors": [], "languages": ["cantonese", "english", "chinese", "mandarin"], "language_level": ["fluency", "proficient"], "hard_skills": ["excel", "focus", "chinese word processing", "ms word"], "soft_skills": ["organized", "self-motivated", "good team player", "resourceful", "sense of responsibility", "hard working", "focus", "interpersonal"], "languages_combined": [{"language": "cantonese", "language_level": []}, {"language": "english", "language_level": []}, {"language": "chinese", "language_level": ["proficient"]}, {"language": "mandarin", "language_level": ["fluency"]}]}, "experience_required": {"duration": ["at least 3-5 years"], "field": ["office administration"]}}, {"job_id": "100003009049833", "location_code": "hk", "company": "Tin Ching Industrial Company Limited", "job_title": "Personal Assistant", "description": "Responsibilities:\n\n\nProvide\u00a0 secretarial and administrative support to Senior Management in both business activities and personal matters\nResponsible for scheduling meeting, travel arrangement, calendar management, as well as prepare documents\u00a0\nTo coordinate with internal and external parties on personal matters and business operations\nAd hoc tasks assigned by the Management\n\nRequirements:\n\nDegree holder\u00a0with 2 years or more relevant working experience\nHigh proficiency in MS Office\nExcellent research and analytical skills\nWell organized, attentive to details, able to handle multi-tasks with strong sense of responsibility\nImmediately available is preferred\nFresh graduate will be considered", "employment_types": ["Full Time"], "selling_points": ["Secretarial and administrative support", "Calendar management, prepare documents", "To coordinate with internal and external parties"], "locations": ["Admiralty"], "categories": ["Admin & HR", "Personal / Executive Assistant", "Secretary"], "post_time": "2022-01-14T09:18:20Z", "salary": {"currency": null, "max": null, "min": null, "period": "monthly", "term": null}, "salary_visible": false, "title_keywords": ["personal assistant"], "responsibilities": ["management", "administrative support", "operations", "internal and external parties", "coordinate with", "ad hoc tasks", "scheduling", "travel arrangement", "senior management", "prepare documents", "business activities"], "requirements": {"degrees": ["fresh graduate", "degree holder"], "majors": [], "languages": [], "language_level": [], "hard_skills": ["analytical skills", "ms office"], "soft_skills": ["multi-tasks", "sense of responsibility", "attentive to details", "well organized", "analytical skills"], "languages_combined": []}, "experience_required": {"duration": ["2 years"], "field": ["relevant working experience"]}}, {"job_id": "100003009051522", "location_code": "hk", "company": "Pirata Group", "job_title": "Personal Assistant to the CEO", "description": "The Pirata Group is one of Hong Kong's most dynamic and innovative restaurant businesses. We operate several market-leading brands across our growing portfolio of restaurants. We are currently looking for an exceptional individual to join us as the PA to our CEO.\nIn this role, you will support the CEO in all aspects of his daily duties, including diary and correspondence management. You will also be required to attend off-site meetings with him at our venues and prepare presentations and reports.\u00a0\nIt is a fantastic first time PA opportunity for an ambitious and driven individual interested in the restaurant business. A hospitality-related degree prefered but not essential.\u00a0\u00a0\nThe ideal candidate will also be tech-savvy, highly organised, and an outgoing and positive people person.\u00a0\nA competitive package includes a performance-related bonus, medical and dental insurance, and 50% off at all our venues.\u00a0", "employment_types": ["Full Time", "Permanent"], "selling_points": ["Growing and Dynamic Business", "Great Career Development Opportunities", "Modern and Collaborative Working Environment"], "locations": ["Southern Area"], "categories": ["Admin & HR", "Secretary"], "post_time": "2022-01-16T07:56:02Z", "salary": {"currency": "HKD", "max": 29999, "min": 25000, "period": "monthly", "term": null}, "salary_visible": true, "title_keywords": ["personal assistant", "ceo"], "responsibilities": ["management", "site meetings", "presentations", "reports", "insurance"], "requirements": {"degrees": ["degree"], "majors": ["hospitality"], "languages": [], "language_level": [], "hard_skills": ["dynamic", "presentations"], "soft_skills": ["outgoing", "interested in", "dynamic", "organised", "innovative", "driven", "positive", "ideal"], "languages_combined": []}, "experience_required": {"duration": [], "field": []}}, {"job_id": "100003009050032", "location_code": "hk", "company": "Grand Cru Cellar International Limited", "job_title": "Secretary / Personal Assistant", "description": "Duties:\n\nProvide all-round administrative and secretarial support to Director/Senior Management\nHandle calendar management and travel logistics arrangement\nWork and communicate closely with driver\nMaintain an efficient administrative and filing system\nAssist to organizing company events and office procurement\nUndertake ad hoc duties as assigned\n\n\u00a0Requirements:\n\nDegree holder or equivalent, with formal secretarial training would be an advantage\n3 years or above of \u00a0relevant working experience\nFamiliar with MS applications (MS Word, Excel, PowerPoint)\nGood command of both spoken & written English, Mandarin & Cantonese\nExcellent team player with strong motivation, proactive, able to work in fast paced, tight deadlines and results-driven environment\nImmediate available would be an advantage\nFresh graduate will also be considered\u00a0as Junior Secretary", "employment_types": ["Permanent"], "selling_points": ["Secretary Personal Assistant", "Provide all-round administrative", "Degree holder or equivalent"], "locations": ["Not Specified"], "categories": ["Admin & HR", "Clerical / Admin Staff", "Personal / Executive Assistant", "Secretary"], "post_time": "2022-01-14T09:39:48Z", "salary": {"currency": null, "max": null, "min": null, "period": "monthly", "term": null}, "salary_visible": false, "title_keywords": ["secretary", "personal assistant"], "responsibilities": ["ad hoc duties", "management", "logistics arrangement", "maintain", "secretarial support", "office procurement", "senior management"], "requirements": {"degrees": ["fresh graduate", "degree holder"], "majors": [], "languages": ["cantonese", "english", "mandarin"], "language_level": ["good command"], "hard_skills": ["excel", "ms applications", "powerpoint", "ms word"], "soft_skills": ["team player", "proactive", "driven"], "languages_combined": [{"language": "cantonese", "language_level": ["good command"]}, {"language": "english", "language_level": ["good command"]}, {"language": "mandarin", "language_level": ["good command"]}]}, "experience_required": {"duration": ["3 years"], "field": ["relevant working experience"]}}, {"job_id": "100003009052034", "location_code": "hk", "company": "ProJob21.com Limited", "job_title": "Executive Assistant for Principal Partner, Global Private Equity & Asset Management", "description": "World class and global industry leaders of alternative and asset managers are in search for Executive Assistant for Principal Partner for Asia Pacific region.\n\n\nGlobal Industry Leader in Alternative & Asset Mgmt\n1 to 1 PA/Biz support to Asia Principal Partner\nHybrid work mode & Multi-cultural Environment\n\nAccountabilities:\n\nReport to Regional Principal Partner\nResponsible for full spectrum of business support including calendar management and complex schedule arrangement that called for extensive liaison with global institutional investors/senior management across the region/headquarters\nPrepare presentation material; fund raising logistic and on-going investment management meetings\nFacilitate the planning & arrangement of personal & family schedules\n\nRequirements:\n\nDegree holder with 8-10years+ relevant experience supporting regional senior executives in charge of front office ideally from investment, deal and strategic business development\nRelevant industry experience ideally from asset management, private equity or alternative investment is highly desirable\nProactive team player with proven competency to working in a dynamic multicultural environment\nProfessional, Efficient and multi-tasked with seasoned communication skill in English, Mandarin and Cantonese\nHighly proficient in Excel/PowerPoint\n\n\n\nInterested candidates, please email your update resume (in MS WORD format) with current and expected salary to us soonest.\n\nAlso come visit ProJOB21 www.ProJob21.com to discover other exciting career opportunities!\n\nAll information received will be kept in strict confidence and used for employment-related purposes only.", "employment_types": ["Full Time"], "selling_points": [], "locations": ["Not Specified"], "categories": ["Admin & HR", "Personal / Executive Assistant", "Secretary", "Banking / Finance", "Asset Management"], "post_time": "2022-01-17T02:50:51Z", "salary": {"currency": null, "max": null, "min": null, "period": "monthly", "term": null}, "salary_visible": false, "title_keywords": ["executive assistant", "asset management"], "responsibilities": ["management", "schedules", "communication", "asset management", "schedule", "report", "senior management", "planning"], "requirements": {"degrees": ["degree holder"], "majors": ["business"], "languages": ["cantonese", "english", "mandarin"], "language_level": [], "hard_skills": ["excel", "dynamic", "private equity", "powerpoint"], "soft_skills": ["efficient", "responsible", "communication skill", "dynamic", "multi-tasked", "team player", "proactive", "extensive", "presentation"], "languages_combined": [{"language": "cantonese", "language_level": []}, {"language": "english", "language_level": []}, {"language": "mandarin", "language_level": []}]}, "experience_required": {"duration": [], "field": ["business development", "relevant experience", "investment", "asset management"]}}, {"job_id": "100003009049146", "location_code": "hk", "company": "Hong Kong Interbank Clearing Ltd", "job_title": "Secretary", "description": "Major Responsibilities\n\nProvide secretarial support to the management office which includes drafting meeting minutes, scheduling and coordinating meetings/appointments and preparing related documents, etc.\nAssist in drafting and preparing business documents such as business correspondence, reports, proposals and presentations\nPerform general administrative duties including handling telephone calls/visitors and maintaining an organized filing system for confidential files and records\nLiaise and coordinate with both internal and external parties for work arrangement as and when required\nPerform any other duties or projects as assigned\nRequirements\n\nSecondary education with minimum 3 years of secretarial service and office administration experience preferably gained from sizable organizations in the banking or financial sector\nProficient in MS Word, Excel, PowerPoint, Outlook and Chinese word processing\nResponsible, independent, self-motivated, well-organized with good interpersonal and communication skills\nGood command of written and spoken English, proficiency in Putonghua is an advantage\nHow to Apply\nInterested parties please send your curriculum vitae stating your current and expected salaries, and the contact phone number to the Human Resources Division, Unit B, 25/F, MG Tower, 133 Hoi Bun Road, Kwun Tong, Kowloon\u00a0\u00a0by clicking the \"Apply Now\" button below.\nAll applications and personal information collected will be treated in strict confidence and only be used for the purpose of recruitment and selection.\u00a0 The information collected will be accessed by our authorized personnel only.\u00a0 Those applicants not contacted by the Human Resources Division within two months from their application date should consider their applications filed for future reference which will be retained for one year for possible future job matching, and will be destroyed after the expiry of one year.", "employment_types": ["Full Time", "Permanent"], "selling_points": [], "locations": ["Ngau Tau Kok"], "categories": ["Admin & HR", "Secretary", "Banking / Finance", "Financial Services", "Others"], "post_time": "2022-01-14T08:10:59Z", "salary": {"currency": null, "max": null, "min": null, "period": null, "term": null}, "salary_visible": false, "title_keywords": ["secretary"], "responsibilities": ["liaise", "any other duties", "management", "coordinating meetings", "maintaining", "related documents", "internal and external parties", "coordinate with", "presentations", "scheduling", "reports", "secretarial support", "administrative duties"], "requirements": {"degrees": ["secondary education"], "majors": [], "languages": ["putonghua", "english", "chinese"], "language_level": ["advantage", "proficiency", "good command", "proficient"], "hard_skills": ["excel", "chinese word processing", "powerpoint", "outlook", "ms word"], "soft_skills": ["communication skills", "self-motivated", "independent", "responsible", "well-organized", "interpersonal"], "languages_combined": [{"language": "putonghua", "language_level": ["proficiency", "advantage", "good command"]}, {"language": "english", "language_level": ["proficiency", "advantage", "good command"]}, {"language": "chinese", "language_level": ["proficient"]}]}, "experience_required": {"duration": ["minimum 3 years"], "field": ["secretarial", "office administration", "education", "banking", "financial"]}}, {"job_id": "100003009046300", "location_code": "hk", "company": "Television Broadcasts Limited (TVB)", "job_title": "Secretary", "description": "Responsibilities:\n\nProvide all-round secretarial and administrative support to Controller\nCoordinate with internal and external parties on business operations\nManage travel and business trip arrangement\nAble to work under pressure and can be a good team player\nAble to handle multi-tasks and prioritize work in a fast-paced environment\n\n\u00a0Requirement:\n\nTertiary education in any disciplines\n1-3 years\u2019 relevant secretarial experience\nProficiency in MS Office (e.g. Word, Excel and Chinese word processing)\nProficiency in spoken Cantonese, Putonghua and English\nSelf-motivated, detail-oriented and hardworking\nImmediate available is preferred\nWorking Location in Tseung Kwan O\n\nPlease apply, quoting the appropriate reference number, with details of your qualifications and experience, expected salary and a contact telephone number to The\u00a0Senior Manager, Personnel Department, Television Broadcasts Limited, TVB City, 77 Chun Choi Street, Tseung Kwan O Industrial Estate, Tseung Kwan O, Kowloon.\n\nApplications received are solely for selection purpose.\u00a0 Those not invited for an interview within 4 weeks may consider their applications unsuccessful and their applications will be filed for another 3 months for future selection.\u00a0 Afterwards, all applications would be destroyed.", "employment_types": ["Full Time", "Permanent"], "selling_points": [], "locations": ["Tseung Kwan O"], "categories": ["Admin & HR", "Administration / Operation Manager", "Secretary", "Others"], "post_time": "2022-01-14T01:17:00Z", "salary": {"currency": null, "max": null, "min": null, "period": "monthly", "term": null}, "salary_visible": false, "title_keywords": ["secretary"], "responsibilities": ["administrative support", "operations", "internal and external parties", "coordinate with", "business trip", "work under pressure"], "requirements": {"degrees": [], "majors": [], "languages": ["cantonese", "putonghua", "english", "chinese"], "language_level": ["proficiency"], "hard_skills": ["excel", "chinese word processing", "word", "ms office"], "soft_skills": ["self-motivated", "hardworking", "detail-oriented"], "languages_combined": [{"language": "cantonese", "language_level": ["proficiency"]}, {"language": "putonghua", "language_level": ["proficiency"]}, {"language": "english", "language_level": ["proficiency"]}, {"language": "chinese", "language_level": []}]}, "experience_required": {"duration": ["1-3 years"], "field": ["secretarial"]}}, {"job_id": "100003009047250", "location_code": "hk", "company": "Asia Allied Infrastructure Holdings Limited", "job_title": "Secretary", "description": "Responsibilities\n\nProvide a wide range of comprehensive secretarial support to Management;\nLiaise with different internal and external parties to arrange various events/meetings and support on meeting materials preparation and taking meeting minutes;\nHandle and maintain confidential information and document management;\nArrange travel reservations and accommodations for ensuring the arrangement are made in advance and in accordance with company policy;\nPerform day-to-day and ad hoc assignments.\n\nRequirements\n\nDegree/Diploma holder with minimum 3 years of relevant secretarial experience\nExperience in sizable company is preferable\nFluent in both written and spoken English and Mandarin\nProficient in MS Office and Chinese typing\nStrong communication and interpersonal skills\nMature, independent, reliable, detailed-minded, presentable, self-motivated\nWell organized with good time management\nImmediately Available is highly preferred\u00a0\n\nWe offer competitive remuneration package with comprehensive fringe benefits to the right candidates:\n\n- Birthday Leave / Marriage Leave / Paternity Leave / Examination Leave\n- Staff Care Programme\n- Career Development Programme\n\nContact us\n\nQualified candidate, please email your full resume with academic credentials, working experience, expected salary and availability by clicking the \"apply now\" button as below.", "employment_types": ["Full Time", "Permanent"], "selling_points": ["Provide comprehensive secretarial support", "Liaise with different internal & external parties", "Immediately Available is highly preferred"], "locations": ["Cheung Sha Wan"], "categories": ["Admin & HR", "Secretary"], "post_time": "2022-01-14T02:39:49Z", "salary": {"currency": null, "max": null, "min": null, "period": "monthly", "term": null}, "salary_visible": false, "title_keywords": ["secretary"], "responsibilities": ["management", "internal and external parties", "maintain", "secretarial support", "ad hoc assignments", "liaise with"], "requirements": {"degrees": ["diploma holder", "degree"], "majors": [], "languages": ["english", "chinese", "mandarin"], "language_level": ["proficient", "fluent"], "hard_skills": ["typing", "ms office"], "soft_skills": ["self-motivated", "independent", "well organized", "mature", "presentable", "time management", "communication and interpersonal skills", "reliable", "detailed"], "languages_combined": [{"language": "english", "language_level": ["fluent"]}, {"language": "chinese", "language_level": ["proficient"]}, {"language": "mandarin", "language_level": ["fluent"]}]}, "experience_required": {"duration": ["minimum 3 years"], "field": ["secretarial"]}}, {"job_id": "100003009050010", "location_code": "hk", "company": "Qookia Limited", "job_title": "Personal Assistant", "description": "Job Responsibilities\n\nProvide full range of secretarial and administrative support to Management.\nAssistant in handling office administration duties, organizing files, records, and other materials.\nLiaise and coordinate with all internal and external parties\nManage calendars including meeting schedules, personal & family affairs, and travel arrangements\nMaintain filing system and confidential information.\nClosely liaise and coordinate with internal and external parties to ensure smooth business operations.\nPerform ad hoc task as required and other duties as assigned\n\nRequirement:\u00a0\n\nBachelor\u2019s degree or equivalent experience with Business Management or legal background.\n3-5 years\u2019 experience of providing support for upper-level management in a related organization\nStrong organizational skills that reflect ability to perform and prioritize multiple tasks seamlessly with excellent attention to detail.\nExcellent written (English, Traditional and simplified Chinese)\nEnjoy to work with team of diversities. People oriented mindset.\nWork in fast-paced environment and flexibility.\nDriving license is an advantage\n\nBenefits:\n\n5-day work and bank holiday\nPaid birthday leave\nBirthday pocket money\nPerformance bonus\nMedical insurance\nFriendly working environment\n\nInterested parties please apply with the following details:\n\nResume/ CV\nExpected Salary\nEarliest Availability\n\nPlease ensure ALL of the information above are true and up-to-date. All information collected will be used for recruitment purposes only.", "employment_types": ["Full Time", "Permanent"], "selling_points": ["Birthday Leave + pocket money", "Joyful working environment with free snacks/drinks", "Flexible working hours"], "locations": ["Kwai Fong"], "categories": ["Admin & HR", "Clerical / Admin Staff", "Personal / Executive Assistant", "Secretary"], "post_time": "2022-01-14T09:37:50Z", "salary": {"currency": null, "max": null, "min": null, "period": "monthly", "term": null}, "salary_visible": false, "title_keywords": ["personal assistant"], "responsibilities": ["liaise", "management", "travel arrangements", "ad hoc", "other duties", "administrative support", "schedules", "operations", "internal and external parties", "coordinate with", "maintain", "office administration duties"], "requirements": {"degrees": ["degree", "bachelor"], "majors": ["business"], "languages": ["english", "chinese"], "language_level": ["excellent"], "hard_skills": ["business management"], "soft_skills": ["organizational skills", "prioritize multiple tasks seamlessly", "work in fast-paced environment", "attention to detail"], "languages_combined": [{"language": "english", "language_level": ["excellent"]}, {"language": "chinese", "language_level": ["excellent"]}]}, "experience_required": {"duration": ["3-5 years"], "field": ["related", "management", "business", "legal"]}}, {"job_id": "100003009047825", "location_code": "hk", "company": "C-Mer Dennis Lam & Partners Eye Center", "job_title": "Executive Assistant", "description": "Responsibilities:\n\nHandle internal & external delivery/filing of marketing materials\nCoordinate and manage the office administrative affairs & office equipment\nSupport for organizing department events, meetings and take meeting notes\nProvide full range administration support, including filing, documentation, data entry and reports preparation\nProvide a wide range of administrative & clerical duties to support Marketing Director\nWork on marketing related admin jobs\nOther ad hoc duties assigned by the management\n\nRequirements:\n\nDiploma holder or above\nAt least 1 year experience in administrative work. Fresh graduates will also be considered\nCandidates with aviation/hotel industry experience will be a plus\nSelf-motivated, proactive, well-organized, detail-minded, and independent with strong interpersonal skills\nAble to work independently and multi-task effectively in a fast-paced environment\nComputer literacy in Microsoft Word, Excel, PowerPoint and Chinese Word Processing\nImmediate available is preferred\n*Please include a recent photo and your expected salary in the CV for the application*", "employment_types": ["Full Time"], "selling_points": ["Support administrative duties of Marketing team", "5-day work, Monday to Friday", "Candidates with aviation/hotel exp will be a plus"], "locations": ["Central"], "categories": ["Admin & HR", "Clerical / Admin Staff", "Personal / Executive Assistant", "Secretary"], "post_time": "2022-01-14T03:58:00Z", "salary": {"currency": null, "max": null, "min": null, "period": "monthly", "term": null}, "salary_visible": false, "title_keywords": ["executive assistant"], "responsibilities": ["ad hoc duties", "management", "documentation", "data entry", "coordinate", "reports", "marketing materials", "administration"], "requirements": {"degrees": ["diploma holder"], "majors": [], "languages": ["chinese"], "language_level": [], "hard_skills": ["excel", "plus", "microsoft word", "chinese word processing", "powerpoint"], "soft_skills": ["detail-minded", "self-motivated", "work independently", "independent", "multi-task", "fast-paced environment", "well-organized", "computer literacy", "interpersonal skills", "proactive"], "languages_combined": [{"language": "chinese", "language_level": []}]}, "experience_required": {"duration": ["at least 1 year"], "field": ["administrative", "hotel industry"]}}, {"job_id": "100003009047062", "location_code": "hk", "company": "TCM Healthcare (London) Ltd", "job_title": "Administrative Secretary (5 days week)", "description": "Job Responsibilities:\n\n\n\nHandle all office administration duties.\nClosely coordinate with other departments and provide administrative support to ensure smooth business operation.\nCommunicate with all company external parties including rental, renovation and maintenance issues.\nManage Administrative Director\u2019s meeting schedules, personal & family affairs and travel arrangements.\n\nJob Requirements:\u00a0\n\nDegree holder.\nExcellent command in written and verbal English, Mandarin and Cantonese.\nMinimum 10 years relevant experience.\n\n\u00a0Benefits:\n\n\u00a0\u00a0 \u00a0 \u00a0 \u00a0 5 days week\n\u00a0 \u00a0 \u00a0 \u00a0 \u00a0Maximum 16 days annual leave\n\u00a0 \u00a0 \u00a0 \u00a0 \u00a0Birthday holiday\n\u00a0 \u00a0 \u00a0 \u00a0 \u00a0Christmas bonus\n\u00a0 \u00a0 \u00a0 \u00a0 \u00a0Dental allowance\n\u00a0 \u00a0 \u00a0 \u00a0 \u00a0Performance bonus\n\u00a0 \u00a0 \u00a0 \u00a0 \u00a0Staff purchase discount\n\nPlease send resume, date available, present salary & salary expected by clicking \u201cAPPLY NOW\u201d.", "employment_types": ["Full Time", "Permanent"], "selling_points": ["5 days week", "Maximum 16 days annual leave", "22 years established company"], "locations": ["Lai Chi Kok"], "categories": ["Admin & HR", "Personal / Executive Assistant", "Secretary"], "post_time": "2022-01-14T02:13:14Z", "salary": {"currency": null, "max": null, "min": null, "period": "monthly", "term": null}, "salary_visible": false, "title_keywords": ["administrative secretary"], "responsibilities": ["communicate with", "business operation", "travel arrangements", "maintenance", "schedules", "external parties", "coordinate with", "renovation", "provide administrative support", "office administration duties"], "requirements": {"degrees": ["degree holder"], "majors": [], "languages": ["cantonese", "english", "mandarin"], "language_level": ["excellent"], "hard_skills": [], "soft_skills": [], "languages_combined": [{"language": "cantonese", "language_level": ["excellent"]}, {"language": "english", "language_level": ["excellent"]}, {"language": "mandarin", "language_level": ["excellent"]}]}, "experience_required": {"duration": ["minimum 10 years"], "field": ["relevant experience"]}}, {"job_id": "100003009052504", "location_code": "hk", "company": "Job-Hunter Employment Agency", "job_title": "Legal Officer", "description": "About Our Client\n\nA global renowned group engaging in smart consumer home appliance and small electrical products with headquarter in Germany.\n\nRequirements\n\nUniversity graduate, preferably in Legal Studies\n3 years or above relevant experience in intellectual property\nExperience in trademark application & renewal and reviewing contract\nPrevious experience in legal or professional firm will also be considered\nDetail-minded, dynamics, well-organized with good interpersonal skills\nProficient in using MS Office including Word, Excel, Chinese WP\nGood communication of English and conversational Putonghua\nImmediate available is a definite advantage\n\nResponsibilities\n\nAssist Legal Counsel on general legal administration support including but not limited to intellectual property, trademark application and maintaining IP database\nCoordinate with external parties and professional advisors on daily smooth operation\nSupport on drafting documents to Trademark Registry and conducting online search\nAssist in reviewing commercial contracts including licenses, supplier contracts etc\n\nInterested parties, please apply with full resume stating date of available, expected and last salary to charmaine@job-hunter.com.hk\nAll personal information will be treated strictly confidential and solely for recruitment purpose", "employment_types": ["Full Time", "Permanent"], "selling_points": [], "locations": ["Not Specified"], "categories": ["Admin & HR", "Secretary", "Professional Services", "Legal & Compliance"], "post_time": "2022-01-17T06:14:34Z", "salary": {"currency": null, "max": null, "min": null, "period": "monthly", "term": null}, "salary_visible": false, "title_keywords": ["officer"], "responsibilities": ["maintaining", "contracts", "external parties", "coordinate with", "database", "administration"], "requirements": {"degrees": ["university graduate"], "majors": [], "languages": ["putonghua", "english", "chinese"], "language_level": ["good", "conversational", "proficient"], "hard_skills": ["excel", "chinese wp", "word", "ms office"], "soft_skills": ["detail-minded", "well-organized", "communication", "interpersonal skills"], "languages_combined": [{"language": "putonghua", "language_level": ["good"]}, {"language": "english", "language_level": ["conversational", "good"]}, {"language": "chinese", "language_level": ["proficient"]}]}, "experience_required": {"duration": ["3 years"], "field": ["relevant experience", "legal"]}}, {"job_id": "100003009046410", "location_code": "hk", "company": "Harriman Property Management Limited", "job_title": "Secretary", "description": "Responsibilities\n\n\nRender secretarial and administrative support for the team\nPlan and schedule meetings and appointments\nHandle correspondences and documents, prepare reports and meeting papers\nAssist in research and maintain market database\nPerform ad hoc assignments\nRequirements\n\nDegree/DSE or above with formal secretarial training is preferred\nAt least 5 years of relevant experience\nExperience gained from property developer or sizable company is an advantage\nResponsible, self-initiated, meticulous and well-organized\nAble to handle multi tasks and work independently\nGood communication and interpersonal skills\nGood command of spoken and written English and Chinese, including Putonghua\nProficient in MS Office applications including Excel and PowerPoint\nWe offer ample opportunities for career development and attractive salary package commensurate with experience and qualifications. \u00a0Interested parties please apply with full resume via\u00a0\u201cAPPLY NOW\u201d.\u00a0\n\n\nFor further information on Wheelock Properties (Hong Kong) Limited, please visit our website:\u00a0www.wheelockpropertieshk.com.\n\nWe are an equal opportunities employer and invite applications from all qualified candidates. Personal data collected will be treated in strict confidence and handled by authorized persons for recruitment-related purposes only within The Wheelock & Wharf Group. Applicants not hearing from us within 2 months may consider their applications unsuccessful.\u00a0", "employment_types": ["Full Time", "Permanent"], "selling_points": [], "locations": ["Kwun Tong"], "categories": ["Admin & HR", "Clerical / Admin Staff", "Personal / Executive Assistant", "Secretary"], "post_time": "2022-01-13T18:55:21Z", "salary": {"currency": null, "max": null, "min": null, "period": null, "term": null}, "salary_visible": false, "title_keywords": ["secretary"], "responsibilities": ["administrative support", "maintain", "schedule", "plan", "database", "prepare reports", "ad hoc assignments"], "requirements": {"degrees": ["degree", "dse"], "majors": [], "languages": ["putonghua", "english", "chinese"], "language_level": ["good command"], "hard_skills": ["excel", "powerpoint", "ms office"], "soft_skills": ["meticulous", "work independently", "responsible", "well-organized", "communication and interpersonal skills"], "languages_combined": [{"language": "putonghua", "language_level": ["good command"]}, {"language": "english", "language_level": ["good command"]}, {"language": "chinese", "language_level": ["good command"]}]}, "experience_required": {"duration": ["at least 5 years"], "field": ["developer", "relevant experience"]}}, {"job_id": "100003009044317", "location_code": "hk", "company": "Jones Lang LaSalle Management Services Ltd", "job_title": "Secretary", "description": "Responsibilities:\n\n\n\nProvide efficient, accurate and responsive secretarial and administrative support to the team\nAssist the team on budgeting and monthly invoicing\nHandle incoming and outgoing correspondence and telephone calls\nHelp to coordinate meetings and meeting room bookings/arrangements\nHandle travel bookings including flight, hotel and car pick up arrangements\nPrepare reports and\u00a0expenses claims and perform ad hoc tasks as required\nParticipate in ad-hoc tasks and projects assigned\n\nRequirements:\n\nHigher Diploma graduate with recognized secretarial qualification is highly preferred\nAt least 3-5 years of relevant experience of Secretary in Property Management\nMust work independently and work under pressure\nPresentable with good interpersonal and communication skill\nExcellent verbal and written communication skills in English, Mandarin and Cantonese\nExcellent interpersonal skill\nStrong PC skills and proficient in MS Office applications of Word, Excel, Outlook and PowerPoint\n\nWe offer 5-day work week, attractive remuneration packages and good career prospects for the right applicant. Please apply by clicking the\u00a0\"APPLY NOW\"\u00a0button, or submit full resume and expected salary by mail to\u00a0PM-HR Department, Room 1402, Dorset House, Taikoo Place, 979 King's Road, Quarry Bay, HK \u00a0or by fax\u00a0to 2968-4177.\u00a0(Please quote the reference number on the envelope/subject of email)\n\nApplicants not invited for interview within 6 weeks may consider their applications unsuccessful. Information provided will be treated with strict confidence and used for the purpose of employment only.", "employment_types": ["Full Time", "Permanent"], "selling_points": ["HD grad w/ recognized secretarial qualification", "3-5 yrs experience of Secretary in Property Mgt", "Must work independently and work under pressure"], "locations": ["Quarry Bay"], "categories": ["Admin & HR", "Clerical / Admin Staff", "Secretary", "Property / Real Estate", "Property Management"], "post_time": "2022-01-13T18:54:56Z", "salary": {"currency": null, "max": null, "min": null, "period": null, "term": null}, "salary_visible": false, "title_keywords": ["secretary"], "responsibilities": ["administrative support", "budgeting", "ad-hoc tasks", "expenses", "ad hoc tasks", "invoicing", "coordinate", "prepare reports"], "requirements": {"degrees": ["diploma"], "majors": [], "languages": ["cantonese", "english", "mandarin"], "language_level": ["excellent"], "hard_skills": ["excel", "word", "powerpoint", "outlook", "pc skills", "ms office"], "soft_skills": ["communication skills", "work independently", "communication skill", "presentable", "interpersonal skill", "interpersonal", "work under pressure"], "languages_combined": [{"language": "cantonese", "language_level": ["excellent"]}, {"language": "english", "language_level": ["excellent"]}, {"language": "mandarin", "language_level": ["excellent"]}]}, "experience_required": {"duration": ["at least 3-5 years"], "field": ["management", "relevant experience"]}}, {"job_id": "100003009051591", "location_code": "hk", "company": "Global Select Executive Search Limited", "job_title": "Administrative Officer - Banking, 15k-17k", "description": "Responsibilities:\nAdministrative support to Credit Department\nMaintains close contact with other departments\u00a0\nprepare reports\nMaintains data, statements, correspondence etc. in proper order\nPerforms any other duties as assigned by supervisors\n\u00a0Requirements:\nDiploma or above\n1 year or above clerical experience will be an advantage\u00a0\nGood interpersonal communication skills\u00a0\nGood Mandarin is a must\nFresh graduate are also welcomed", "employment_types": ["Full Time"], "selling_points": ["Good Mandarin is a must", "Fresh Graduate are welcomed", "Admin"], "locations": ["Central"], "categories": ["Admin & HR", "Clerical / Admin Staff", "Secretary", "Banking / Finance", "Others"], "post_time": "2022-01-16T13:29:35Z", "salary": {"currency": null, "max": null, "min": null, "period": "monthly", "term": null}, "salary_visible": false, "title_keywords": ["administrative officer"], "responsibilities": ["any other duties", "data", "administrative support", "contact", "prepare reports"], "requirements": {"degrees": ["fresh graduate", "diploma or above"], "majors": [], "languages": ["mandarin"], "language_level": ["good"], "hard_skills": [], "soft_skills": ["communication skills", "interpersonal"], "languages_combined": [{"language": "mandarin", "language_level": ["good"]}]}, "experience_required": {"duration": ["1 year"], "field": ["clerical"]}}, {"job_id": "100003009046414", "location_code": "hk", "company": "BlessVision Foundation Limited", "job_title": "Personal Assistant to Senior Management", "description": "BlessVision Foundation is a registered charitable organization in HK. We based on Christian values to provide charitable works, life education and humanitarian care. Through media productions, to spread Jesus\u2019 love and support to those are vulnerable from different nationalities. To promote human wellness in body, mind, society and spirit levels. To cope with our continued growth, we are looking for a right candidate to join us.\n\nResponsibilities:\n\nTo provide all-rounded of secretarial support to the Senior Management regarding both organization and personal matters\nExcellent written and verbal communication skills\nStrong interpersonal skills - closely liaise with external parties (Christian media and Christian caring organizations etc.) to ensure smooth ministries\u2019 development /operations\nAssist the Senior Management to handle general correspondences, phone, emails, presentations etc. as required\nManage the Senior Management\u2019s appointments/calendar by planning and scheduling meetings.\nSpecial Projects assistance/coordination/lead\n\nRequirements:\n\nMinimum 2 years of relevant secretary experience\nDisplay strong communication skills to different parties and ad-hoc matters\nExcellent command of written English and Chinese; fluent in spoken English, Cantonese and Putonghua preferred.\nProficient in MS applications and Google-powered business tools (email, calendar, docs)\nWith caring heart by Jesus\u2019 love\nMature, organized, confidential, cheerful and positive attitude\nDedicated and willing to work to irregular time schedules\nStrong commitment to the mission, vision and values of BlessVision Foundation\n\nInterest parties please email your full resume with present & expected salary and state the date of availability.", "employment_types": ["Full Time"], "selling_points": ["Excellent written and verbal communication skills", "Mature, organized, cheerful and positive attitude", "With caring heart by Jesus\u2019 love"], "locations": ["Ngau Tau Kok"], "categories": ["Admin & HR", "Personal / Executive Assistant", "Secretary"], "post_time": "2022-01-14T06:27:36Z", "salary": {"currency": null, "max": null, "min": null, "period": "monthly", "term": null}, "salary_visible": false, "title_keywords": ["personal assistant"], "responsibilities": ["operations", "external parties", "presentations", "communication", "scheduling", "secretarial support", "coordination", "liaise with", "senior management", "planning"], "requirements": {"degrees": [], "majors": [], "languages": ["cantonese", "putonghua", "english", "chinese"], "language_level": ["excellent", "fluent"], "hard_skills": ["ms applications"], "soft_skills": ["organized", "communication skills", "cheerful", "mature", "positive attitude"], "languages_combined": [{"language": "cantonese", "language_level": ["fluent"]}, {"language": "putonghua", "language_level": ["fluent"]}, {"language": "english", "language_level": ["excellent", "fluent"]}, {"language": "chinese", "language_level": ["excellent"]}]}, "experience_required": {"duration": ["minimum 2 years"], "field": []}}, {"job_id": "100003009048699", "location_code": "hk", "company": "Henderson Land Development Company Limited", "job_title": "SENIOR SECRETARY", "description": "Ref. No.: JDB/SS\n\nUniversity graduate from overseas university\nExcellent in both written and spoken English and Chinese including Putonghua\nGood command of PC knowledge\nMinimum 10 years' relevant experience in supporting the top management with formal secretarial training\nAble to handle business correspondence, arrange tight schedule professionally\nAble to work independently and under pressure, with initiative and flexible with good working attitude\nHigh professional standard of integrity and confidentiality\n\nAttractive salary and fringe benefits will be offered to the successful candidates. Please apply with full resume by mail to\u00a0Human Resources Department, Henderson Land Development Co. Ltd., 71/F, Two International Finance Centre, 8 Finance Street, Central, Hong Kong\u00a0or by fax at\u00a02905 1855\u00a0or visit our homepage at\u00a0http://www.hld.com\u00a0or\u00a0by clicking \"Apply Now\".\n\n(Please quote the ref. no. on letter)\u00a0\n\nPersonal data provided by job applicants will be used for recruitment purpose only.\u00a0", "employment_types": ["Full Time", "Permanent"], "selling_points": ["Medical Allowance", "Education Allowance", "Free Lunch"], "locations": ["Central"], "categories": ["Admin & HR", "Personal / Executive Assistant", "Secretary", "Property / Real Estate", "Others"], "post_time": "2022-01-14T07:04:08Z", "salary": {"currency": null, "max": null, "min": null, "period": "monthly", "term": null}, "salary_visible": false, "title_keywords": ["senior secretary"], "responsibilities": ["management", "schedule"], "requirements": {"degrees": ["university graduate"], "majors": [], "languages": ["putonghua", "english", "chinese"], "language_level": ["excellent"], "hard_skills": ["no", "pc knowledge"], "soft_skills": ["flexible", "good working attitude", "work independently", "under pressure", "integrity", "initiative"], "languages_combined": [{"language": "putonghua", "language_level": []}, {"language": "english", "language_level": ["excellent"]}, {"language": "chinese", "language_level": ["excellent"]}]}, "experience_required": {"duration": ["minimum 10 years"], "field": ["management", "relevant experience", "training", "secretarial"]}}, {"job_id": "100003009050551", "location_code": "hk", "company": "Paul Y. Engineering Group", "job_title": "Administrator", "description": "Main Responsibilities:\n\nProvide a full spectrum of administrative and clerical duties to the department\nProvide secretarial service to the management\nResponsible for meeting scheduling and appointment arrangements\nPrepare meeting materials and reports\nHandle the incoming emails and phone calls\nOrganize and maintain the filing system\nCoordinate with relevant departments for the logistics arrangement for new hires\nParticipate in ad hoc tasks as assigned\n\n\u00a0Requirements:\n\nTertiary education or above, preferably with business-related discipline\nMinimum 5 years of relevant experience preferably in sizable companies\nGood command of both spoken and written English and Chinese (Cantonese & Putonghua)\nGood interpersonal and communication skills\nPUNCTUAL, attentive to details, hardworking, self-motivated\nProficiency in MS Office (Word, Excel & PowerPoint)\n\n\u00a0***What we offer?\n\nCompetitive remuneration package\nAdditional leave (Family Care Leave, Exam Leave, Qualification Leave, etc.)\nDiscretionary bonus\nStudy Subsidies\nComprehensive training and professional career development\n\nInterested parties please apply with a detailed resume stating expected salary and date of availability to the HR Manager through fax at 2833 5441 or e-mail by clicking \"APPLY NOW\".\n\nCompany Website: http://www.pyengineering.com/\n\nAll personal data provided will be used strictly in accordance with our \u201cPersonal Information Collection Statement Pertaining to Recruitment\u201d, a copy of which is available upon written request to us by E-mail.", "employment_types": ["Full Time", "Permanent"], "selling_points": ["Provide administrative and secretarial support", "Min. 5 years of relevant experience", "Attractive remuneration package"], "locations": ["Kwun Tong"], "categories": ["Admin & HR", "Clerical / Admin Staff", "Secretary"], "post_time": "2022-01-14T10:42:10Z", "salary": {"currency": null, "max": null, "min": null, "period": "monthly", "term": null}, "salary_visible": false, "title_keywords": ["administrator"], "responsibilities": ["management", "logistics arrangement", "coordinate with", "ad hoc tasks", "secretarial service", "scheduling", "maintain", "reports", "phone calls"], "requirements": {"degrees": [], "majors": [], "languages": ["cantonese", "putonghua", "english", "chinese"], "language_level": ["good command"], "hard_skills": ["excel", "sizable companies", "word", "powerpoint", "ms office"], "soft_skills": ["communication skills", "self-motivated", "attentive to details", "interpersonal", "hardworking"], "languages_combined": [{"language": "cantonese", "language_level": ["good command"]}, {"language": "putonghua", "language_level": ["good command"]}, {"language": "english", "language_level": ["good command"]}, {"language": "chinese", "language_level": ["good command"]}]}, "experience_required": {"duration": ["minimum 5 years"], "field": ["relevant experience"]}}, {"job_id": "100003009047089", "location_code": "hk", "company": "WPG Electronics (HK) Limited", "job_title": "Administration Officer", "description": "Responsibilities\u00a0\n\n\nSupervise a small team to handle all around of office administrative duties including office supplies procurement & office maintenance\nHandle extensive renovation projects in Hong Kong\nSourcing & maintaining vendors for offices supplies, facilities & traveling\nFormulate and implement\u00a0administrative\u00a0 policies and procedures.\n\n\u00a0\u00a0 \u00a0Requirements\u00a0\n\nHigh Diploma / Degree holder in Business administration or other related\u00a0discipline.\nAt least 5 years related working experience in sizeable company\nStrong project management skills, mature, independent and detail minded\nGood command of spoken and written English and Mandarin\nProficient in PC knowledge and familiar with MS Office applications as well as Chinese Word Processing.\nImmediate available preferred\n\n\u00a0Benefits & package\n\nDouble pay &\u00a0Performance bonus\nMedical , Dental &\u00a0Life insurance\nMarriage Leave\n\nWPG Electronics (HK) Limited is an equal opportunity employer and welcomes applications from all qualified candidates. Information provided will be treated in strict confidence and only be used for recruitment related purposes. Applicants who are not contacted within 6 weeks may consider their application unsuccessful. Unsuccessful applications may be kept for another 3 months for being considered for other suitable positions available in our Company. The unsuccessful applications will be destroyed after the said period of retention.", "employment_types": ["Full Time", "Permanent"], "selling_points": ["Work in a vibrant, flexible and caring culture", "Perform all rounded Administration functions", "Attractive remuneration (with 13 months and bonus)"], "locations": ["Tsuen Wan Area"], "categories": ["Admin & HR", "Administration / Operation Manager", "Clerical / Admin Staff", "Secretary"], "post_time": "2022-01-15T03:49:35Z", "salary": {"currency": null, "max": null, "min": null, "period": "monthly", "term": null}, "salary_visible": false, "title_keywords": ["administration officer"], "responsibilities": ["maintaining", "maintenance", "office supplies", "policies", "renovation", "procedures", "administrative duties"], "requirements": {"degrees": ["high diploma", "degree holder"], "majors": ["business administration"], "languages": ["english", "chinese", "mandarin"], "language_level": ["good command", "proficient"], "hard_skills": ["project management", "pc knowledge", "chinese word processing", "ms office"], "soft_skills": ["project management skills", "independent", "mature"], "languages_combined": [{"language": "english", "language_level": ["good command"]}, {"language": "chinese", "language_level": ["proficient"]}, {"language": "mandarin", "language_level": ["good command"]}]}, "experience_required": {"duration": ["at least 5 years"], "field": ["related"]}}, {"job_id": "100003009049647", "location_code": "hk", "company": "Strategic Financial Relations (China) Ltd.", "job_title": "Coordinator", "description": "\u00a0General\n\nUpdate the database of business contacts\nType English and Chinese proposals\nPrepare PowerPoint presentation slides\nComplete expense claim forms\nCoordinate with client servicing teams and other departments\nHandle general office work\n\nEvent / Client Support\n\nPrepare news monitoring reports and monthly / project reports\nModify PowerPoint presentation slides and press releases\nPrepare and send invitations and make RSVP calls\nDisseminate press release and other client information to media and investors and follow up\nLogistics arrangement (hotel/function room or restaurant booking, ticketing, car rental, etc)\nVenue set-up and on-site support of events\n\nRequirements:\n\nHolder of University Degree, Associate Degree or Diploma with formal secretarial training\nPreferably with 2 to 4 years of working experience, but fresh graduates may also be considered\nGood computer skills, proficient in MS office including Word Processing, PowerPoint and Excel\nGood language skills, proficient in English & Mandarin\nWell-organized,\u00a0detail-minded, responsible\u00a0& independent\nImmediate availability is preferred\nInterested parties please complete the standard application form by clicking the\u00a0Apply now\u00a0button. You can also attach your tailored CV and Cover letter with your current and expected salary which we will use to review applications.\n\n\n\u00a0It is Our Company policy to comply with the requirements of the Personal Data (Privacy) Ordinance (Cap. 486) of the Laws of the Hong Kong Special Administrative Region. Any personal data which is collected shall be handled in accordance with this Personal Information Collection Statement (\u201cPICS\u201d).\n\nThe personal data collected from you will be used for purposes relating to your application for employment with the Company. You must ensure that all personal data provided to the Company are accurate, complete and up-to-date. For correction of or access to personal data after submission of the job application or enquiries on recruitment matters, please contact the HR or subject officer as specified in the recruitment advertisement.\n\nWebsite:\u00a0\u00a0www.sprg.com.hk\u00a0/\u00a0www.sprg.asia\n\nFacebook:\u00a0\u00a0https://www.facebook.com/SPRGAsia /\u00a0https://www.facebook.com/CSR.SPRG", "employment_types": ["Full Time", "Permanent"], "selling_points": ["with formal secretarial training", "5 Days Work / Bank Holiday", "12 Days AL/B-day Leave/Medical&Life Insurance"], "locations": ["Admiralty"], "categories": ["Admin & HR", "Clerical / Admin Staff", "Personal / Executive Assistant", "Secretary"], "post_time": "2022-01-14T09:01:01Z", "salary": {"currency": null, "max": null, "min": null, "period": "monthly", "term": null}, "salary_visible": false, "title_keywords": ["coordinator"], "responsibilities": ["logistics arrangement", "monitoring", "teams", "coordinate with", "client information", "project reports", "reports", "booking", "database"], "requirements": {"degrees": ["associate degree", "university degree", "diploma"], "majors": [], "languages": ["english", "chinese", "mandarin"], "language_level": ["proficient", "good"], "hard_skills": ["excel", "word processing", "powerpoint", "make", "computer skills", "ms office"], "soft_skills": ["detail-minded", "independent", "responsible", "well-organized", "presentation"], "languages_combined": [{"language": "english", "language_level": ["proficient", "good"]}, {"language": "chinese", "language_level": []}, {"language": "mandarin", "language_level": ["proficient", "good"]}]}, "experience_required": {"duration": ["2 to 4 years"], "field": []}}, {"job_id": "100003009048063", "location_code": "hk", "company": "David S. K. Au & Associates Ltd", "job_title": "Junior Secretary", "description": "Job Duties:\u00a0\nProvide full range of secretarial & administrative support\nManage daily workflows, business correspondence, filing and reports independently\nTake up ad-hoc assignments\nJob Requirements:\u00a0\n\nDiploma holder or above\nGood interpersonal and communication skills\nFluent in both written & spoken English and Cantonese\nAbility to manage sensitive and confidential information with discretion\nProficient in Microsoft Office applications including MS-Word, Excel and Chinese Word Processing\n\nPrevious exposure in architect, engineer/surveyor firms advantageous\n\nPlease\u00a0send application with detailed resume, availability, present and expected salary by Fax:2513-1828 / Email\u00a0/ mail to 15/F, 633 King\u2019s Rd,\u00a0North Point, H.K.\u00a0\nWebsite:\u00a0 www.daal.com.hk", "employment_types": ["Full Time", "Permanent"], "selling_points": [], "locations": ["North Point"], "categories": ["Admin & HR", "Secretary"], "post_time": "2022-01-14T04:38:15Z", "salary": {"currency": null, "max": null, "min": null, "period": "monthly", "term": null}, "salary_visible": false, "title_keywords": ["junior secretary"], "responsibilities": ["ad-hoc assignments", "reports", "administrative support"], "requirements": {"degrees": ["diploma holder"], "majors": [], "languages": ["cantonese", "english", "chinese"], "language_level": ["proficient", "fluent"], "hard_skills": ["ms-word", "chinese word processing", "excel", "microsoft office"], "soft_skills": ["communication skills", "interpersonal", "detailed", "sensitive"], "languages_combined": [{"language": "cantonese", "language_level": ["fluent"]}, {"language": "english", "language_level": ["fluent"]}, {"language": "chinese", "language_level": ["proficient"]}]}, "experience_required": {"duration": [], "field": []}}, {"job_id": "100003009043524", "location_code": "hk", "company": "OPS Interior Design Consultant Limited", "job_title": "Project Secretary", "description": "Responsibilities:\n\nTo provide full spectrum of secretarial and clerical support to Project Team\nTo assist Project Team in project administration\nTo liaise with customers /\u00a0designers and sub-contractors\nTo\u00a0handle document submission and correspondences among customers / designers and sub-contractors\n\n\u00a0Requirements:\n\nUniversity graduate is preferable\nExperience in\u00a0construction / interior design / interior contracting\u00a0company preferred\nExcellent in documentation and administrative work\nDetail-minded, self-motivated and with strong sense of responsibility", "employment_types": ["Full Time"], "selling_points": ["Min. 5 years secretarial experience", "5 days work, double pay, discretionary bonus", "Medical claim, 12 annual leave"], "locations": ["Kowloon Bay"], "categories": ["Admin & HR", "Secretary"], "post_time": "2022-01-12T15:57:24Z", "salary": {"currency": null, "max": null, "min": null, "period": "monthly", "term": null}, "salary_visible": false, "title_keywords": ["project secretary"], "responsibilities": ["liaise with", "project administration", "clerical support"], "requirements": {"degrees": ["university graduate"], "majors": [], "languages": [], "language_level": [], "hard_skills": ["documentation"], "soft_skills": ["detail-minded", "self-motivated", "sense of responsibility"], "languages_combined": []}, "experience_required": {"duration": [], "field": ["construction", "design"]}}, {"job_id": "100003009049113", "location_code": "hk", "company": "Hong Kong Interbank Clearing Ltd", "job_title": "Assistant Management Executive", "description": "Major Responsibilities\n\nProviding high standards of secretariat services for the senior executive office, the HKICL Board and its Sub-Committees\nAssisting in organizing and coordinating Board and Committee meetings involving the senior executive office\nDrafting, reviewing and coordinating different types of business documents, including meeting agendas, papers, minutes, reports, proposals, presentations and letters, etc.\nAssisting in following up to matters raised at meetings to ensure appropriate follow-up actions are taken\nAssisting in managing protocols between the Board and the senior executive office\nCoordinating committee work and liaising with both internal and external parties in a professional manner\nCoordinating with departmental secretariat regarding secretarial issues\nMaintaining an organized and effective document management system for confidential files and records\n\nRequirements\n\nUniversity education in finance, business management or related disciplines\nAt least 5 years\u2019 working experience in committee work, preferably in the banking, finance, public or government sector\nExcellent writing skills in both English and Chinese\nGood command of spoken English and Chinese (Cantonese and Putonghua)\nCapable of dealing with internal and external business executives and officials\nResponsible, independent, well-organized and self-motivated with strong communication and interpersonal skills\nHow to Apply\nInterested parties please send your curriculum vitae stating your current and expected salaries, and the contact phone number to the Human Resources Division, Unit B, 25/F, MG Tower, 133 Hoi Bun Road, Kwun Tong, Kowloon\u00a0\u00a0by clicking the \"Apply Now\" button below.\nAll applications and personal information collected will be treated in strict confidence and only be used for the purpose of recruitment and selection.\u00a0 The information collected will be accessed by our authorized personnel only.\u00a0 Those applicants not contacted by the Human Resources Division within two months from their application date should consider their applications filed for future reference which will be retained for one year for possible future job matching, and will be destroyed after the expiry of one year.", "employment_types": ["Full Time", "Permanent"], "selling_points": [], "locations": ["Ngau Tau Kok"], "categories": ["Admin & HR", "Secretary", "Banking / Finance", "Financial Services", "Professional Services", "Company Secretary"], "post_time": "2022-01-14T08:08:15Z", "salary": {"currency": null, "max": null, "min": null, "period": null, "term": null}, "salary_visible": false, "title_keywords": ["assistant management executive"], "responsibilities": ["management", "maintaining", "internal and external parties", "letters", "liaising with", "presentations", "professional manner", "reports", "committee work"], "requirements": {"degrees": [], "majors": [], "languages": ["cantonese", "putonghua", "english", "chinese"], "language_level": ["excellent", "good command"], "hard_skills": ["business management", "writing skills"], "soft_skills": ["self-motivated", "independent", "capable", "responsible", "well-organized", "writing skills", "communication and interpersonal skills"], "languages_combined": [{"language": "cantonese", "language_level": ["good command"]}, {"language": "putonghua", "language_level": ["good command"]}, {"language": "english", "language_level": ["excellent", "good command"]}, {"language": "chinese", "language_level": ["excellent", "good command"]}]}, "experience_required": {"duration": ["at least 5 years"], "field": ["finance", "banking"]}}, {"job_id": "100003009046922", "location_code": "hk", "company": "DKNT CPA Limited", "job_title": "Junior Secretary", "description": "Requirements:\n\nPost-secondary graduate\nGood command of spoken English a must\nStrong\u00a0organizational\u00a0and self management skills\nProactive and client focused\nEager to learn, thrive under pressure\n1 - 2 years' experience / candidates with no experience will also be considered", "employment_types": ["Full Time"], "selling_points": ["5-day week", "study leaves, examination support", "good promotion prospect"], "locations": ["Wan Chai"], "categories": ["Admin & HR", "Clerical / Admin Staff", "Personal / Executive Assistant", "Secretary"], "post_time": "2022-01-14T01:43:58Z", "salary": {"currency": null, "max": null, "min": null, "period": "monthly", "term": null}, "salary_visible": false, "title_keywords": ["junior secretary"], "responsibilities": ["management"], "requirements": {"degrees": [], "majors": [], "languages": ["english"], "language_level": ["good command"], "hard_skills": ["no"], "soft_skills": ["under pressure", "focused", "organizational", "eager to learn", "proactive"], "languages_combined": [{"language": "english", "language_level": ["good command"]}]}, "experience_required": {"duration": ["1 - 2 years"], "field": []}}, {"job_id": "100003009048048", "location_code": "hk", "company": "Manpower Services (Hong Kong) Limited", "job_title": "HR,& Admin Officer/AM_ Professional Association", "description": "Jot Duties:\n\nSupervise the Office Assistants daily\nPerform the duties of the office, warehouse facilities, and security\nArrange the renovation and relocation work\nPerform the duties of recruitment, logistical arrangements for incoming and outgoing staff\nAdminister the personnel record, e.g., attendance, leave records, emergency contact, organization chart, etc.\nAssist in Compensation & Benefits administration\nAssist in preparing and monitoring the Administration and Human Resources Annual Budget and Expenses\nReview and update various AHR policies, procedures, and regulations to ensure compliance with legal requirements\nAssist in the organization of staff events including Staff Dinner, Annual Christmas Dinner, and Spring Dinner, training, and seminar, etc.\nReport to the Assistant Director, Administration, and Human Resources regularly (as the case may be) to the above matters\nUndertake any other duties as may be assigned by the Assistant Director, Administration, and Human Resources and/or the Secretary-General or their duly authorized representatives.\nResponsible to prepare a simple staff newsletter (e.g., Put short description + photos)\u00a0\n\nRequirements:\n\nA degree holder with at least 7 years or above relevant experiences in NGO, Professional Association, Government\nGood command of written and spoken English and Chinese, including proficiency in Mandarin\nIndependent, strong communication skills, and able to multi-task and work under pressure\n\nInterested parties, please send your resume in MS WORD format with current and expected salary and notice period to\u00a0charlton.chan@manpowergrc.hk", "employment_types": ["Permanent"], "selling_points": ["NGO/Professional Asso/HKGovt/Newspaper Experiences", "Experiences in Administration and Human Resources", "Excellent in English and Chinese"], "locations": ["Central & Western Area"], "categories": ["Admin & HR", "Secretary", "Management", "General Management", "HR Supporting Staff"], "post_time": "2022-01-14T04:36:25Z", "salary": {"currency": null, "max": null, "min": null, "period": "monthly", "term": null}, "salary_visible": false, "title_keywords": ["officer", "hr", "admin"], "responsibilities": ["logistical arrangements", "renovation", "recruitment"], "requirements": {"degrees": [], "majors": [], "languages": [], "language_level": [], "hard_skills": [], "soft_skills": [], "languages_combined": []}, "experience_required": {"duration": [], "field": []}}, {"job_id": "100003009040614", "location_code": "hk", "company": "Pacific Building Material (Project) Limited", "job_title": "Secretary", "description": "Job Descriptions :\n\nPurchase and shipping experience\nLiaise with overseas vendor for pricing and negotiation\nAssists Inventory control and forecast report\nHandle purchase order and full set import & export document\nAble to work independently and self motivated\u00a0\n\nRequirements :\n\nForm 5 or above with minimum 2 years\u00a0\u00a0relevant working experience\nGood command of spoken and written English and Mandarin\nImmediate available is preferable\u00a0", "employment_types": ["Full Time"], "selling_points": [], "locations": ["Wan Chai"], "categories": ["Admin & HR", "Secretary", "Merchandising & Purchasing", "Others", "Sales, CS & Business Devpt", "Sales Administration"], "post_time": "2022-01-12T02:51:37Z", "salary": {"currency": null, "max": null, "min": null, "period": "monthly", "term": null}, "salary_visible": false, "title_keywords": ["secretary"], "responsibilities": ["shipping", "purchase", "inventory control", "forecast", "liaise with", "report"], "requirements": {"degrees": ["form 5 or above"], "majors": [], "languages": ["english", "mandarin"], "language_level": ["good command"], "hard_skills": [], "soft_skills": [], "languages_combined": [{"language": "english", "language_level": ["good command"]}, {"language": "mandarin", "language_level": ["good command"]}]}, "experience_required": {"duration": ["minimum 2 years"], "field": ["relevant working experience"]}}, {"job_id": "100003009044212", "location_code": "hk", "company": "FC Packaging (Hong Kong) Ltd.", "job_title": "Administrative Assistant", "description": "Responsibilities\n\nProvide\u00a0comprehensive\u00a0administrative and central filing support\nSupervise driver and assist in family social matters\nPerform other office ad hoc duties\n\nRequirements\n\nSolid secondary school record\nMinimum 3 years working experiences\nOrganized and detail-minded with good communication and feedback skills\nProficiency in Office, IOS, English and Chinese word processing\nKnowledge in book keeping and advantage\nGood command of English, Cantonese and Mandarin.\n\nWe offer an attractive remuneration package & benefits including 5-day work week, transportation and meal subsidies, medical benefits and study allowance.\n\nPlease send your resume, expected salary and optional cover letter to us or click \"Apply Now\".\n\n(Personal data collected is solely for recruitment purposes and will be treated in strict confidential)", "employment_types": ["Full Time", "Permanent"], "selling_points": [], "locations": ["Sheung Wan"], "categories": ["Admin & HR", "Clerical / Admin Staff", "Personal / Executive Assistant", "Secretary"], "post_time": "2022-01-13T03:25:28Z", "salary": {"currency": null, "max": null, "min": null, "period": "monthly", "term": null}, "salary_visible": false, "title_keywords": ["administrative assistant"], "responsibilities": ["ad hoc duties"], "requirements": {"degrees": [], "majors": [], "languages": ["cantonese", "english", "chinese", "mandarin"], "language_level": ["proficiency", "good command"], "hard_skills": ["chinese word processing"], "soft_skills": ["detail-minded", "organized", "communication"], "languages_combined": [{"language": "cantonese", "language_level": ["good command"]}, {"language": "english", "language_level": ["proficiency", "good command"]}, {"language": "chinese", "language_level": ["proficiency"]}, {"language": "mandarin", "language_level": ["good command"]}]}, "experience_required": {"duration": ["minimum 3 years"], "field": []}}, {"job_id": "100003009051210", "location_code": "hk", "company": "One Recruitment Limited", "job_title": "Legal Secretary, Corporate", "description": "Our client, a prestigious international law firm is looking for a\u00a0Legal Secretary, Corporate\u00a0to join dynamic operations.\u00a0\n\nJob\u00a0Responsibilities:\n\nProvide full range of secretarial support to a Partner and Associates in the Corporate Division\nDraft & prepare legal documents & correspondence\nHandle travel arrangement, prepare expenses reports and personal issues\nSchedule business meetings & manage the diaries\u00a0for Associates and Partners\n\u00a0Assist on partner's personal matters\n\u00a0Organize and maintain filing system\nHandle matters openings and conflict search duties\u00a0\nPrepare bills to clients\nAssist in ad-hoc projects\n\nJob\u00a0Requirements:\n\nHKCEE or above\u00a0\nAt least 2 year secretarial experience\u00a0within corporate areas within law firms\nAdvance\u00a0levels\u00a0in using MS Word and Chinese Word Processing\nFluency of Mandarin & English\u00a0is required\nDetail-oriented, independent with strong sense of responsibility\nGood communication & interpersonal skills\n\u00a0Fresh\u00a0graduates\u00a0will be considered as a junior legal secretary", "employment_types": ["Full Time", "Permanent"], "selling_points": ["Competitive Fringe Benefit", "Good Job Prospects", "Stable Working Envronment"], "locations": ["Central"], "categories": ["Admin & HR", "Secretary", "Banking / Finance", "Financial Services", "Professional Services", "Legal & Compliance"], "post_time": "2022-01-15T04:52:46Z", "salary": {"currency": "HKD", "max": 44999, "min": 25000, "period": "monthly", "term": null}, "salary_visible": true, "title_keywords": ["legal secretary"], "responsibilities": ["expenses", "diaries", "maintain", "reports", "secretarial support", "travel arrangement", "schedule", "ad-hoc projects"], "requirements": {"degrees": [], "majors": [], "languages": ["english", "chinese", "mandarin"], "language_level": ["fluency"], "hard_skills": ["chinese word processing", "ms word"], "soft_skills": ["independent", "sense of responsibility", "detail-oriented", "communication", "interpersonal skills"], "languages_combined": [{"language": "english", "language_level": ["fluency"]}, {"language": "chinese", "language_level": []}, {"language": "mandarin", "language_level": ["fluency"]}]}, "experience_required": {"duration": ["at least 2 year"], "field": ["secretarial"]}}, {"job_id": "100003009051333", "location_code": "hk", "company": "Assurance Education Limited", "job_title": "Education Consultant, Full Time", "description": "Job Description: Education Consultant\n\nOrganization\n\nAssurance aims to help students make blossom and make the most out of high school. Assurance is headquartered in Hong Kong and maintains offices in Shenzhen and Shanghai. All of our consultants are from top universities such as Wharton, Harvard, UPenn and UChicago. For more information, please visit www.assuranceedu.com.\n\nPosition\n\nEducation Consultant, Full Time\n\nLocation\n\nCauseway Bay\n\nHours\n\n5 days work week\nTuesday to Saturday\n9.30am to 6.30pm\n\nResponsibilities\n\nProvide administrative support\nHandle correspondence\nManage school application forms\nAssist in seminars and events\n\nRequirements\n\nFluency in Cantonese, English and Mandarin\nProficient in Word, Excel, and word processing in English & Chinese\n1 year of experience as administrative assistant/secretary\nDegree holder in any discipline\n\nCompensation\n\nWe offer a starting salary of $15000-$17,000/month. Please state your expected salary.\n\nApplication\n\nInterested parties please submit your resume and cover letter to Ms. Tiffany Cheung at admin @ AssuranceEDU.com\u00a0with \u201c[Name] Assurance Recruitment]\u201d in the email title. Please state your expected salary.", "employment_types": ["Full Time"], "selling_points": ["Proficiency in English, Cantonese & Mandarin", "Degree holder, 1 year of experience", "Salary $15-17K, 5 days working"], "locations": ["Causeway Bay"], "categories": ["Admin & HR", "Personal / Executive Assistant", "Secretary", "Education", "Others"], "post_time": "2022-01-15T09:22:56Z", "salary": {"currency": "HKD", "max": 16999, "min": 14000, "period": "monthly", "term": null}, "salary_visible": true, "title_keywords": ["education consultant"], "responsibilities": ["provide administrative support"], "requirements": {"degrees": ["degree holder"], "majors": [], "languages": ["cantonese", "english", "chinese", "mandarin"], "language_level": ["fluency", "proficient"], "hard_skills": ["excel", "word processing", "word"], "soft_skills": [], "languages_combined": [{"language": "cantonese", "language_level": ["fluency"]}, {"language": "english", "language_level": ["fluency", "proficient"]}, {"language": "chinese", "language_level": ["fluency", "proficient"]}, {"language": "mandarin", "language_level": ["fluency"]}]}, "experience_required": {"duration": ["1 year"], "field": ["administrative"]}}, {"job_id": "100003009042206", "location_code": "hk", "company": "CTS Limited", "job_title": "Administrator Assistant/ Secretary", "description": "Requirements:\n\nDegree holder / Diploma with\u00a0secretarial/administrative training preferred\nMinimum\u00a02\u00a0years working experience in the capacity of Executive Assistant\nStrong analytical and communication skills\nMature, reliable, well organized and systematic\nResponsible, self-initiated, meticulous and well-organized\nAble to\u00a0handle multi tasks and work independently\n\nResponsibilities:\n\n\u00a0Deliver full secretarial and administration support to Business Director\nOverall administrative and secretarial supports (including typing, filing, taking minutes, scheduling meetings, screening phone calls, handling correspondence)\nHandle calendar management, travel booking and business meetings arrangement\nLiaising with internal staffs, external clients and business partners\n\u00a0Co-ordinate projects and function\nOrganize and prepare presentation materials, proposals, reports, taking minutes and other correspondences including drafting emails and letters", "employment_types": ["Full Time"], "selling_points": ["Secretarial", "Administrative", "HR"], "locations": ["Kwun Tong"], "categories": ["Admin & HR", "Administration / Operation Manager", "Personal / Executive Assistant", "Secretary"], "post_time": "2022-01-12T06:36:02Z", "salary": {"currency": null, "max": null, "min": null, "period": "monthly", "term": null}, "salary_visible": false, "title_keywords": ["administrator", "secretary", "assistant"], "responsibilities": ["management", "letters", "liaising with", "scheduling", "reports", "booking", "phone calls", "administration"], "requirements": {"degrees": ["diploma", "degree holder"], "majors": [], "languages": [], "language_level": [], "hard_skills": [], "soft_skills": ["communication skills", "meticulous", "work independently", "responsible", "well organized", "well-organized", "systematic", "mature", "reliable"], "languages_combined": []}, "experience_required": {"duration": ["minimum 2 years"], "field": []}}, {"job_id": "100003009042578", "location_code": "hk", "company": "FANCL (Fantastic Natural Cosmetics Limited)", "job_title": "Secretary", "description": "Our Strategic Procurement and Logistics Department is comprised of highly engaged individuals who share the same vision of continuously offering high service quality to satisfy the supply chain requirement of over 200 retail outlets spread over Hong Kong and China. We continuously innovate our business process to deliver integrated logistics solutions that create value and help building competitive advantage. We count professionalism, automation and customer satisfaction as hallmarks of our team. If you are looking for dynamic, and challenging work in a pleasant working environment, you should join our team without hesitation.\n\nThe incumbent will be responsible for providing full spectrum professional secretarial and administrative support to Department Head and ad-hoc support to the team.\n\nResponsibilities:\n\nProvide full spectrum of daily supports to Department Head\u00a0and the team\nAssist procurement team to source and purchase items that assigned\nCoordinate and organize meetings for the departments and manage the business calendar for Department Head\nPrepare reports, presentation materials, agenda, minutes etc. accurately and efficiently\nMaintain and update information in different internal systems\nHandle ad hoc tasks as assigned\nRequirements:\n\nUniversity Graduate with formal secretarial training\nMinimum 3 years of experience in providing secretarial support to management\nExperienced in Retail or FMCG industries would be an advantage\nDetail-minded, organized and able to prioritize tasks\nResponsible, independent with good communication and interpersonal skills\nProficient in MS Word, Excel, PowerPoint and Chinese Word Processing\nGood command of both written and spoken English and Chinese (Cantonese and Mandarin)\nWhat We Offer\nA 5-day work week\nCompetitive Salary Package\nGuaranteed 13 Months\u2019 Pay & Year End Discretionary Bonus\nOn the Job Training & Training Sponsorship\nFull Paid Sick Leave, Annual Leave, Maternity Leave, Paternity Leave\nStaff Benefits e.g. Staff Purchase Discounts, Free Product, Sponsor of Gym Membership, Comprehensive Medical Benefits Coverage, etc.\nStaff Activities & Events e.g. Mid-Autumn Festival Gathering, New Joiner Gathering, Annual Dinner, Christmas Parties, Health Talks, Sports Activities, Interests Classes etc.\u00a0\u00a0\nInterested applicants please click 'Apply Now'\u00a0and send your r\u00e9sum\u00e9 with expected salary to us.\u00a0For internal reference purpose, please also state your public examination results on your attached r\u00e9sum\u00e9.\nPersonal data collected will be used for recruitment purposes only.", "employment_types": ["Full Time", "Permanent"], "selling_points": ["Full spectrum secretarial support to Dept Head", "Organize meetings, prepare reports, update system", "5-day work,13 mth pay and year end bonus"], "locations": ["Tsim Sha Tsui"], "categories": ["Admin & HR", "Clerical / Admin Staff", "Personal / Executive Assistant", "Secretary"], "post_time": "2022-01-12T08:04:03Z", "salary": {"currency": null, "max": null, "min": null, "period": "monthly", "term": null}, "salary_visible": false, "title_keywords": ["secretary"], "responsibilities": ["ad hoc tasks", "coordinate", "purchase", "maintain", "prepare reports", "internal systems"], "requirements": {"degrees": ["university graduate"], "majors": [], "languages": ["cantonese", "english", "chinese", "mandarin"], "language_level": ["good command", "proficient"], "hard_skills": ["excel", "chinese word processing", "powerpoint", "ms word"], "soft_skills": ["detail-minded", "organized", "independent", "able to prioritize", "responsible", "communication and interpersonal skills"], "languages_combined": [{"language": "cantonese", "language_level": ["good command"]}, {"language": "english", "language_level": ["good command"]}, {"language": "chinese", "language_level": ["good command", "proficient"]}, {"language": "mandarin", "language_level": ["good command"]}]}, "experience_required": {"duration": ["minimum 3 years"], "field": ["secretarial", "management"]}}, {"job_id": "100003009038195", "location_code": "hk", "company": "\u5fb7\u6210\u96fb\u696d\u5de5\u7a0b\u6709\u9650\u516c\u53f8", "job_title": "\u79d8\u66f8\u6587\u54e1 Secretary/Clerk", "description": "\u6709\u7559\u5b78\u7d93\u9a57\u512a\u5148\n\u6d41\u5229\u82f1\u8a9e\u5c0d\u7b54.\u82f1\u6587\u4e2d\u6587\u56de\u8986\u96fb\u90f5,\u4e00\u822c\u6587\u8077\u5de5\u4f5c.\n\n\u8fd4\u5de5\u6642\u9593:\u661f\u671f1-5\u5929\n\u52de\u5de5\u5047\u671f,9:00-18:00,\u5e74\u5047,\u5927\u5047,\u96d9\u7ce7,\u65c5\u904a,\u806f\u6b61\u805a\u6703\u7b49\n", "employment_types": ["Full Time"], "selling_points": [], "locations": ["Shatin Area"], "categories": ["Admin & HR", "Clerical / Admin Staff", "Secretary", "Others"], "post_time": "2022-01-13T04:40:55Z", "salary": {"currency": null, "max": null, "min": null, "period": "monthly", "term": null}, "salary_visible": false, "title_keywords": ["secretary", "clerk"], "responsibilities": [], "requirements": {"degrees": [], "majors": [], "languages": [], "language_level": [], "hard_skills": [], "soft_skills": [], "languages_combined": []}, "experience_required": {"duration": [], "field": []}}, {"job_id": "100003009048023", "location_code": "hk", "company": "The Hong Kong Polytechnic University", "job_title": "Executive Assistant", "description": "DEPARTMENT OF ELECTRICAL ENGINEERING\n\nExecutive\u00a0Assistant (Ref. 22011404-E)\n\nDuties\n\nThe appointee will be required to:\n\n(a) provide administrative support to both academic and research programmes;\n\n(b) support a wide range of activities of the Unit, including administration of student-related matters (e.g. admission, registration, examination, timetabling and student record), and various student-related events and projects;\n\n(c) provide secretarial support to meetings and committees;\n\n(d) compile statistical reports and maintain database;\n\n(e) support general office administration; and\n\n(f) perform any other duties as assigned by the Head of the Unit or his delegates.\nThe appointee may be required to work outside office hours.\n\nQualifications\n\nApplicants should have:\n\n(a) a recognized degree or an equivalent qualification;\n\n(b) at least two years of relevant post-qualification experience;\n\n(c) a good command of both English and Chinese, with fluency in Putonghua being an advantage;\n\n(d) proficiency in computer software applications including MS office (e.g. MS Excel, Word, PowerPoint) and Chinese word processing;\n\n(e) good communication, interpersonal and time management skills; and\n\n(f) self-motivation and the ability to work independently and proactively.\n\nPreference will be given to those with experience in tertiary institutions/similar organizations.\n\nShortlisted candidates may be invited to sit for a written test and a computer test.\n\nRemuneration and Conditions of Service\n\nA highly competitive remuneration package will be offered. Initial appointment will be on a fixed-term one-year gratuity-bearing contract. Re-engagement thereafter is subject to mutual agreement. Applicants should state their current and expected salary in the application.\n\nApplication\n\nPlease send a completed application form by post to Human Resources Office, 13/F, Li Ka Shing Tower, The Hong Kong Polytechnic University, Hung Hom, Kowloon, Hong Kong or via email by clicking \"Apply Now\".\u00a0 Application forms can be downloaded from https://www.polyu.edu.hk/hro/careers/guidelines_and_forms/forms.\u00a0 If a separate curriculum vitae is to be provided, please still complete the application form which will help speed up the recruitment process.\u00a0 Consideration of applications will commence on 26 January 2022 until the position is filled.\u00a0 The University\u2019s Personal Information Collection Statement for recruitment can be found at https://www.polyu.edu.hk/hro/careers/guidelines_and_forms/pics_for_recruitment.\n\nPolyU is an equal opportunity employer committed to diversity and inclusivity.\u00a0 All qualified applicants will receive consideration for employment without regard to gender, ethnicity, nationality, family status or physical or mental disabilities.", "employment_types": ["Full Time"], "selling_points": [], "locations": ["Not Specified"], "categories": ["Admin & HR", "Clerical / Admin Staff", "Personal / Executive Assistant", "Secretary"], "post_time": "2022-01-14T04:34:07Z", "salary": {"currency": null, "max": null, "min": null, "period": "monthly", "term": null}, "salary_visible": false, "title_keywords": ["executive assistant"], "responsibilities": ["any other duties", "management", "software", "office administration", "communication", "maintain", "reports", "secretarial support", "database", "recruitment", "provide administrative support", "recruitment process", "administration"], "requirements": {"degrees": ["degree"], "majors": [], "languages": ["putonghua", "english", "chinese"], "language_level": ["fluency", "advantage", "good command"], "hard_skills": ["chinese word processing", "word", "powerpoint", "ms excel", "c", "ms office"], "soft_skills": ["work independently", "time management skills", "communication", "committed", "self-motivation", "interpersonal"], "languages_combined": [{"language": "putonghua", "language_level": ["fluency", "advantage", "good command"]}, {"language": "english", "language_level": ["advantage", "good command"]}, {"language": "chinese", "language_level": ["advantage", "good command"]}]}, "experience_required": {"duration": ["at least two years"], "field": ["post-qualification"]}}, {"job_id": "100003009044243", "location_code": "hk", "company": "\u83ef\u5275\u570b\u969b\u5be6\u696d\u6709\u9650\u516c\u53f8", "job_title": "\u8463\u4e8b\u9577\u52a9\u7406", "description": "\u8077\u4f4d\u63cf\u8ff0:\n\n\u8ca0\u8cac\u8463\u4e8b\u9577\u7684\u65e5\u5e38\u5de5\u4f5c\u200b\u200b\u5b89\u6392\uff0c\u505a\u597d\u9810\u7d04\u5de5\u4f5c\u3001\u5b89\u6392\u5546\u52d9\u884c\u7a0b\u3001\u4f86\u96fb\u4f86\u51fd\u7b49\u76f8\u95dc\u4e8b\u5b9c;\n\u5354\u52a9\u8463\u4e8b\u9577\u8655\u7406\u5404\u985e\u6587\u4ef6\uff0c\u4e3b\u6301\u8d77\u8349\u5404\u7a2e\u6587\u7a3f\u3001\u7e3d\u7d50\u548c\u5176\u4ed6\u6b63\u5f0f\u6587\u4ef6\uff1b\n\u5354\u52a9\u8463\u4e8b\u9577\u62d3\u5c55\u548c\u7dad\u8b77\u516c\u53f8\u5ba2\u6236\uff0c\u53c3\u8207\u516c\u53f8\u76f8\u95dc\u5546\u52d9\u6d3b\u52d5\uff1b\n\u8655\u7406\u516c\u53f8\u7684\u516c\u5171\u4e8b\u52d9\uff0c\u8ca0\u8cac\u63a5\u5f85\u5ba2\u6236\u3001\u5ba2\u4eba\u53ca\u516c\u53f8\u5c0d\u5916\u7684\u806f\u8abc\u806f\u7d61\u5de5\u4f5c\uff1b\n\u5b8c\u6210\u8463\u4e8b\u9577\u4ea4\u8fa6\u7684\u5176\u4ed6\u5de5\u4f5c\u7684\u7763\u8fa6\u3001\u5354\u8abf\u53ca\u843d\u5be6\u4efb\u52d9\uff1b\n\u8207\u96c6\u5718\u7e3d\u90e8\u53ca\u5b50\u516c\u53f8\u4e4b\u4eba\u529b\u8cc7\u6e90\u53ca\u884c\u653f\u90e8\u9580\u7dca\u5bc6\u5408\u4f5c\uff0c\u672a\u4f86\u53ef\u5411\u4eba\u529b\u8cc7\u6e90\u53ca\u884c\u653f\u90e8\u9580\u767c\u5c55\u3002\n\n\n\u4efb\u8077\u8cc7\u683c\uff1a\n\n\u672c\u79d1\u7562\u696d\uff0c\u5de5\u5546\u7ba1\u7406\u3001\u6cd5\u5f8b\u3001\u7406\u5de5\u79d1\u53ca\u82f1\u6587\u5c08\u696d\u512a\u5148\uff1b\n\u82f1\u8a9e\u826f\u597d\uff0c\u570b\u8a9e\u6d41\u5229\uff1b\u76f8\u8c8c\u7aef\u6b63\uff1b\n\u512a\u79c0\u61c9\u5c46\u7562\u696d\u751f\u4e5f\u6703\u8003\u616e\uff1b\n\u4eba\u54c1\u5584\u826f\uff0c\u6027\u683c\u958b\u6717\u3001\u7a69\u91cd\uff1b\u8cac\u4efb\u5fc3\u3001\u80fd\u627f\u53d7\u5de5\u4f5c\u58d3\u529b\uff0c\u5718\u968a\u5354\u4f5c\u80fd\u529b\u4f73\uff1b\n\u5177\u5099\u826f\u597d\u7684\u6e9d\u901a\u5354\u8abf\u80fd\u529b\uff0c\u793e\u4ea4\u61c9\u916c\u80fd\u529b\uff0c\u516c\u6587\u5beb\u4f5c\u529f\u5e95\u624e\u5be6\uff1b\n\u6709\u56b4\u5bc6\u7684\u908f\u8f2f\u601d\u7dad\u80fd\u529b\u548c\u5168\u9762\u7684\u5206\u6790\u5224\u65b7\u80fd\u529b\uff0c\u8f03\u5f37\u7684\u7d71\u7c4c\u5354\u8abf\u80fd\u529b\uff0c\u66f8\u9762\u53ca\u53e3\u982d\u8868\u9054\u80fd\u529b\u512a\u79c0\uff1b\n\n\n\u6709\u610f\u8005\u8acb\u5c07\u500b\u4eba\u5c65\u6b77\u3001\u6700\u8fd1\u85aa\u91d1\u3001\u8981\u6c42\u85aa\u91d1\u53ca\u53ef\u5230\u8077\u65e5\u671f\u81f3Apply Now\n\n\u7533\u8acb\u4eba\u6240\u63d0\u4f9b\u7684\u8cc7\u6599\u5c07\u4e88\u4fdd\u5bc6\u53ca\u53ea\u505a\u62db\u8058\u6709\u95dc\u8077\u4f4d\u7528\u9014", "employment_types": ["Full Time"], "selling_points": ["\u8ca0\u8cac\u8463\u4e8b\u9577\u7684\u65e5\u5e38\u5de5\u4f5c\u200b\u200b\u5b89\u6392", "\u5354\u52a9\u8463\u4e8b\u9577\u62d3\u5c55\u548c\u7dad\u8b77\u516c\u53f8\u5ba2\u6236\uff0c\u53c3\u8207\u516c\u53f8\u76f8\u95dc\u5546\u52d9\u6d3b\u52d5", "\u672c\u79d1\u7562\u696d\uff0c\u5de5\u5546\u7ba1\u7406\u3001\u6cd5\u5f8b\u3001\u7406\u5de5\u79d1\u53ca\u82f1\u6587\u5c08\u696d\u512a\u5148"], "locations": ["Not Specified"], "categories": ["Admin & HR", "Clerical / Admin Staff", "Personal / Executive Assistant", "Secretary"], "post_time": "2022-01-13T03:33:24Z", "salary": {"currency": "HKD", "max": 34999, "min": 20000, "period": "monthly", "term": null}, "salary_visible": true, "title_keywords": ["\u8463\u4e8b\u9577\u52a9\u7406"], "responsibilities": [], "requirements": {"degrees": [], "majors": [], "languages": [], "language_level": [], "hard_skills": [], "soft_skills": [], "languages_combined": []}, "experience_required": {"duration": [], "field": []}}, {"job_id": "100003009044207", "location_code": "hk", "company": "Lorence & Company Limited", "job_title": "Senior Administration Officer", "description": "Responsibilities:\n\nHandle the daily operation including monitoring of office and Warehouse maintenance;\nAttend meetings, taking minutes and handling related documents.\nProvide full spectrum of corporate and office administration duties, such as data input, filing and clerical works, office equipment maintenance and repair coordination.\nHandle and monitor the attendance system for all staff\nPerform ad-hoc projects as required.\n\n\u00a0Requirements:\n\nHigher Diploma or above in business administration or related disciplines;\nGood command of spoken and written English and Chinese\n5 - 10 years of secretarial and administrative experience\nBe pro-active, presentable, responsible, discreet and trustworthy, with people skills strong enough to cope with a dynamic environment.\nImmediately Available is preferred", "employment_types": ["Full Time", "Permanent"], "selling_points": ["5 - 10 years of secretarial & administrative exp.", "Higher Diploma or above", "5 Day work week"], "locations": ["Kwun Tong"], "categories": ["Admin & HR", "Administration / Operation Manager", "Secretary"], "post_time": "2022-01-13T03:24:36Z", "salary": {"currency": null, "max": null, "min": null, "period": "monthly", "term": null}, "salary_visible": false, "title_keywords": ["senior administration officer"], "responsibilities": ["attendance", "maintenance", "related documents", "monitoring", "daily operation", "data input", "monitor", "repair", "office equipment maintenance", "coordination", "attend meetings", "office administration duties", "ad-hoc projects"], "requirements": {"degrees": ["higher diploma or above"], "majors": ["related disciplines", "business administration"], "languages": ["english", "chinese"], "language_level": ["good command"], "hard_skills": ["dynamic"], "soft_skills": ["dynamic environment", "trustworthy", "responsible", "presentable", "pro-active"], "languages_combined": [{"language": "english", "language_level": ["good command"]}, {"language": "chinese", "language_level": ["good command"]}]}, "experience_required": {"duration": ["5 - 10 years"], "field": ["secretarial", "administrative"]}}, {"job_id": "100003009045559", "location_code": "hk", "company": "International Christian Assembly of God, Limited", "job_title": "Personal Assistant", "description": "to the Head of Hong Kong School of Supernatural Ministry (\u2018HKSSM\u2019),The Healing Rooms and Encounter Inner Healing Ministry.\nThis is a full-time position in the Church Office and responsibilities will include:\n\nFull support and assistance to the Ministry Head in ensuring the smooth operation of the three ministries\nAdministrative duties of the school (HKSSM) including student enrolment, compiling lecture notes & teaching materials, monitoring of attendance & student assignments and organizing outreach trips\nAdministrative duties of The Healing Rooms such as maintaining duty rosters, attendance, client records, etc.\n\n\u00a0Requirements\n\nAble to operate independently and also work with a team\nOrganized, self-motivated, able to prioritize and handle multiple tasks in a fast-paced environment\nExcellent customer service, effective interpersonal and communication skills\nProficient in Microsoft applications (Excel, Word and Outlook)\nUniversity Degree or Diploma with minimum 2 years\u2019 experience in office or school administration preferred\nFluent in spoken and written English (Proficiency in Cantonese would be an advantage)\nFlexibility in working hours\n\n\u00a0To apply for this position, please send with full resume and expected salary to\u00a0International Christian Assembly\u00a0\n", "employment_types": ["Full Time"], "selling_points": ["2 years administration & secretarial experience", "Minimum 2 years Coordinator experience", "Microsoft proficiency"], "locations": ["North Point"], "categories": ["Admin & HR", "Clerical / Admin Staff", "Secretary"], "post_time": "2022-01-13T08:04:49Z", "salary": {"currency": null, "max": null, "min": null, "period": "monthly", "term": null}, "salary_visible": false, "title_keywords": ["personal assistant"], "responsibilities": ["attendance", "maintaining", "monitoring", "communication", "customer service", "administrative duties", "teaching materials", "administration"], "requirements": {"degrees": ["university degree", "diploma"], "majors": [], "languages": ["cantonese", "english"], "language_level": ["advantage", "proficiency", "fluent"], "hard_skills": ["excel", "outlook", "word", "microsoft applications"], "soft_skills": ["organized", "self-motivated", "independently", "communication skills", "able to prioritize", "fast-paced environment", "handle multiple tasks", "customer service", "smooth", "interpersonal"], "languages_combined": [{"language": "cantonese", "language_level": ["proficiency", "advantage", "fluent"]}, {"language": "english", "language_level": ["proficiency", "advantage", "fluent"]}]}, "experience_required": {"duration": ["minimum 2 years"], "field": ["administration"]}}, {"job_id": "100003009047910", "location_code": "hk", "company": "Links International", "job_title": "Personal Assistant (Personal/ Family support) - up to50K", "description": "\nResponsibilities:\n\n\n\nProvide full spectrum of Personal and family support the boss\nAssist for family support, working closely with the butler, drivers, helpers and private tutor\nResponsible for inventory management, stock arrangement, household admin work etc\nAssist for kid's arrangement, such as school activities, after school tutor, enrolment etc\nArranging family event and public events, invite guest, prepare materials and follow up the logistic etc\nBack up for family matters when the butler is on leave, such as payroll, assign helper's duties, furniture repairs, household expense etc\nHandle ad-hoc tasks are assigned\n\nSkills and requirements:\n\n\n\nMin 5 years' experience in hospitality, family PA or other relevant work experience\nPrevious working experience in Personal Assistant or Secretary is an advantage\nStrong organizational, communication and interpersonal skills\nExcellent command in both written and spoken English & Chinese\nGood computer literacy (Microsoft Word, Excel, PowerPoint, Chinese Word Processing and Outlook)\nImmediate available is preferred\n\n\nInterested parties please submit your application by clicking 'apply now' below and upload your updated resume.\n\n", "employment_types": ["Full Time", "Permanent"], "selling_points": ["Support personal, family and kids schedule", "Work at client's home", "5 days office work (Mon - Sat Altn)"], "locations": ["Not Specified"], "categories": ["Admin & HR", "Personal / Executive Assistant", "Secretary"], "post_time": "2022-01-14T04:13:03Z", "salary": {"currency": "HKD", "max": 54999, "min": 30000, "period": "monthly", "term": null}, "salary_visible": true, "title_keywords": ["personal", "personal assistant"], "responsibilities": ["inventory management", "ad-hoc tasks", "payroll"], "requirements": {"degrees": [], "majors": [], "languages": ["english", "chinese"], "language_level": ["excellent", "good"], "hard_skills": ["excel", "microsoft word", "chinese word processing", "powerpoint", "outlook"], "soft_skills": ["organizational", "communication and interpersonal skills", "computer literacy"], "languages_combined": [{"language": "english", "language_level": ["excellent"]}, {"language": "chinese", "language_level": ["excellent", "good"]}]}, "experience_required": {"duration": ["min 5 years"], "field": []}}, {"job_id": "100003009046990", "location_code": "hk", "company": "Andrew Lee King Fun & Associates Architects Ltd", "job_title": "Secretary(also for fresh graduate to apply)", "description": "Responsibilities:\n\nHandle architectural tender and prepare related documents\nResponsible for all correspondences with contractors, sub-contractors and clients\nManage document control processes for assigned projects\nProvide full secretarial and administration support to project team\nPrepare monthly reports with tight deadlines\nHandle project administration works\n\nRequirements:\n\n1-2 years working experience preferred and fresh graduates are welcome to apply.\nMust be attention to details, able to cope with multiple projects and tight deadlines\nMature personality, proactive, willing to work with a team and deliver results under minimum supervision\nGood in English and Chinese\nGood PC skills with proficiency in Microsoft Word, Excel, PowerPoint and Chinese Word processing\n\nInterested parties please send resume with expected salary to Head of Human Resources at recruit @ alkf.com\n\nAll information collected will be used for recruitment purpose only.\n\nANDREW LEE KING FUN & ASSOCIATE ARCHITECTS LIMITED\n\n19/F, Universal Trade Centre, 3 Arbuthnot Road, Central, Hong Kong\n\nTel: (852) 2525-0008 Fax: (852) 2868-5371 E-mail : recruit @ alkf.com\n\nWebsite: www.alkf.com", "employment_types": ["Full Time"], "selling_points": ["Mature personality", "Manage document control processes", "Good command in English and Chinese"], "locations": ["Central"], "categories": ["Admin & HR", "Administration / Operation Manager", "Secretary", "Others"], "post_time": "2022-01-14T01:57:20Z", "salary": {"currency": null, "max": null, "min": null, "period": "monthly", "term": null}, "salary_visible": false, "title_keywords": [], "responsibilities": ["control", "handle project administration", "monthly reports", "related documents", "tender", "administration"], "requirements": {"degrees": [], "majors": [], "languages": ["english", "chinese"], "language_level": ["proficiency", "good"], "hard_skills": ["excel", "microsoft word", "chinese word processing", "powerpoint", "pc skills"], "soft_skills": ["mature", "proactive", "attention to details"], "languages_combined": [{"language": "english", "language_level": ["good"]}, {"language": "chinese", "language_level": ["good", "proficiency"]}]}, "experience_required": {"duration": ["1-2 years"], "field": []}}, {"job_id": "100003009039386", "location_code": "hk", "company": "Easy Property Co Ltd", "job_title": "Assistant to Director \u8463\u4e8b\u52a9\u7406", "description": "\u4e3b\u8981\u8077\u8cac\n\n\u5354\u52a9\u8463\u4e8b\u505a\u597d\u516c\u53f8\u6838\u5fc3\u7ba1\u7406\u5de5\u4f5c\uff0c\u5305\u62ec\u71df\u92b7\u3001\u4eba\u529b\u8cc7\u6e90\u3001\u884c\u653f\u53ca\u5176\u4ed6\u6709\u8da3\u6709\u6311\u6230\u6027\u7684\u5de5\u4f5c\n\u8ca0\u8cac\u7269\u696d\u7ba1\u7406 (\u7ba1\u7406\u516c\u53f8\u65d7\u4e0b\u6578\u5341\u500b\u7269\u696d)\u3001\u6cd5\u5f8b\u4e8b\u52d9 (\u5b89\u6392\u6cd5\u5f8b\u884c\u52d5\u70ba\u516c\u53f8\u8ffd\u8a0e\u6b20\u4f63\u6b20\u79df) \u53ca\u5e02\u5834\u63a8\u5ee3 (\u5305\u62ec\u516c\u53f8\u7db2\u9801\u3001\u5831\u520a\u5ee3\u544a\u53ca\u5ba3\u50b3\u55ae\u5f35\u7b49)\u7684\u5de5\u4f5c\n\u70ba\u8463\u4e8b\u63d0\u4f9b\u79d8\u66f8\u670d\u52d9\n\u5982\u6709\u9700\u8981\uff0c\u516c\u53f8\u6703\u70ba\u65b0\u540c\u4e8b\u63d0\u4f9b\u57f9\u8a13\n\u516c\u53f8\u4ecd\u5728\u767c\u5c55\u4e2d\uff0c\u898f\u7ae0\u5236\u5ea6\u53ca\u5404\u7a2e\u65e5\u5e38\u904b\u4f5c\u4ecd\u6709\u6539\u5584\u7a7a\u9593\uff0c\u70ba\u65b0\u540c\u4e8b\u500b\u4eba\u624d\u80fd\u7684\u767c\u63ee\u63d0\u4f9b\u4e86\u7121\u9650\u7a7a\u9593\n\n\u5165\u8077\u689d\u4ef6\n\n\u4e2d\u4e03\u6216\u4ee5\u4e0a\u7a0b\u5ea6\u512a\u5148\u8003\u616e\n\n\u6700\u5c11\u5169\u5e74\u884c\u653f\u53ca\u4eba\u4e8b\u5de5\u4f5c\u7d93\u9a57\n\u6709\u7269\u696d\u7ba1\u7406\u3001\u5e02\u5834\u63a8\u5ee3\u6216\u6cd5\u5f8b\u4e8b\u52d9\u7d93\u9a57\u7684\uff0c\u512a\u5148\u8003\u616e\n\u6709\u80fd\u529b\u7368\u7acb\u5730\u540c\u6642\u8655\u7406\u591a\u9805\u4e8b\u52d9\n\u4e2d\u82f1\u6587 (\u7279\u5225\u662f\u66f8\u5beb\u80fd\u529b) \u826f\u597d\n\u5177\u6709\u826f\u597d\u7684\u601d\u8003\u80fd\u529b\u548c\u4eba\u969b\u6e9d\u901a\u6280\u5de7\n\u7cbe\u901aMS Office applications, Excel\u53caPowerPoint\n\nInterested parties please send your CV together with your\u00a0expected salary\u00a0and\u00a0date of availability\u00a0to the Human Resources and Administration Department by simply clicking the \"Apply Now\" button below\n\n\u00a0(Personal data collected would be used for recruitment purpose only.)", "employment_types": ["Full Time", "Permanent"], "selling_points": [], "locations": ["Tsim Sha Tsui"], "categories": ["Admin & HR", "Personal / Executive Assistant", "Secretary", "HR Supporting Staff"], "post_time": "2022-01-11T16:01:51Z", "salary": {"currency": null, "max": null, "min": null, "period": "monthly", "term": null}, "salary_visible": false, "title_keywords": ["director", "assistant"], "responsibilities": [], "requirements": {"degrees": [], "majors": [], "languages": [], "language_level": [], "hard_skills": ["office applications"], "soft_skills": [], "languages_combined": []}, "experience_required": {"duration": [], "field": []}}, {"job_id": "100003009042103", "location_code": "hk", "company": "27 District Management Limited", "job_title": "ADMINISTRATIVE ASSISTANT / RECEPTIONIST", "description": "RESPONSIBILITIES\n\n-\u00a0Perform general reception duties including handling phone calls and greeting / serving clients\n\n- Assist in general routine administrative duties such as preparing and filling daily report, arrange maintenance of office machineries etc.\n\n- Responsible for managing and coordinating meeting rooms reservations across different business\u00a0units in the office\n\n- Provide general office administrative support and handle any ad-hoc assignments as required.\n\nREQUIREMENT\n\n- Form\u00a05 or above\n\n- At least 2 years relevant experience in receptionist or office administration duties\n\n- Good interpersonal skills, telephone manner and communication skills\n\n- Pleasant, mature, presentable, self-motivated and responsible\n\n- Proficiency in MS Office, Chinese and English typing\n\n- Fluency in Cantonese, English and Mandarin\n\n- Insurance license paper 1 & 3 holder will be an advantage\n\n- Immediate availability is preferred\n\nWe offer an attractive salary and benefits for the right candidate. \u00a0Interested parties, please send CV with expected salary\u00a0for application. \u00a0Personal data collected will be used solely for recruitment & employment purposes.", "employment_types": ["Full Time"], "selling_points": [], "locations": ["Tsim Sha Tsui"], "categories": ["Admin & HR", "Clerical / Admin Staff", "Receptionist", "Secretary"], "post_time": "2022-01-12T06:09:31Z", "salary": {"currency": null, "max": null, "min": null, "period": "monthly", "term": null}, "salary_visible": false, "title_keywords": ["administrative assistant", "receptionist"], "responsibilities": ["maintenance", "administrative support", "ad-hoc assignments", "administrative duties", "daily report", "phone calls"], "requirements": {"degrees": ["form 5 or above"], "majors": [], "languages": ["cantonese", "english", "chinese", "mandarin"], "language_level": ["fluency", "proficiency"], "hard_skills": ["typing", "ms office"], "soft_skills": ["communication skills", "self-motivated", "responsible", "mature", "pleasant", "presentable", "interpersonal skills", "telephone manner"], "languages_combined": [{"language": "cantonese", "language_level": ["fluency"]}, {"language": "english", "language_level": ["fluency", "proficiency"]}, {"language": "chinese", "language_level": ["proficiency"]}, {"language": "mandarin", "language_level": ["fluency"]}]}, "experience_required": {"duration": ["at least 2 years"], "field": ["office administration", "relevant experience"]}}, {"job_id": "100003009040218", "location_code": "hk", "company": "Chinese Estates Holdings Limited", "job_title": "Secretary", "description": "Provide full spectrum of secretarial support to senior executive\nManage calendar, arrange business meetings and daily appointments\nHandle memo, reports, news clippings and other documents\nProvide administrative and clerical support to marketing department\nHandle ad hoc projects or duties as assigned\nRequirements:\n\nDegree holder in any discipline, preferably with formal secretarial training\nAt least 3 years' relevant experience, preferably in sizeable organization\nExperience in serving senior management\nMeticulous, well-organized, reliable and able to work independently\nMature, self-motivated with excellent interpersonal and communication skills\nGood command of both written and spoken English and Chinese. Mandarin in advantage.\nProficient in MS Word, Excel, Chinese Word Processing and PowerPoint\nImmediate available is an advantage\nAttractive compensation package including competitive salary, up to 22 days Annual Leave and 5 days work as well as excellent career prospects will be offered. Interested parties please send full resume including your present and expected salaries by clicking \"Apply Now\".\n\n(Personal data collected would be used in accordance with our Statement on Employment-Related Data Usage, which is available at http://www.chineseestates.com or upon request made to the Company\u2019s Human Resources Manager. Applicants who are not invited for interview within six weeks may consider their applications unsuccessful. All personal data of unsuccessful candidates will be destroyed after six months.)", "employment_types": ["Full Time", "Permanent"], "selling_points": ["3 yrs exp, preferably in sizeable organization", "Experience in serving senior management", "Meticulous,well-organized,mature & self-motivated"], "locations": ["Causeway Bay"], "categories": ["Admin & HR", "Clerical / Admin Staff", "Personal / Executive Assistant", "Secretary"], "post_time": "2022-01-12T01:55:15Z", "salary": {"currency": null, "max": null, "min": null, "period": "monthly", "term": null}, "salary_visible": false, "title_keywords": ["secretary"], "responsibilities": ["memo", "communication", "ad hoc projects", "reports", "secretarial support", "administrative and clerical support", "senior management"], "requirements": {"degrees": ["degree holder"], "majors": [], "languages": ["english", "chinese", "mandarin"], "language_level": ["advantage", "good command", "proficient"], "hard_skills": ["excel", "chinese word processing", "powerpoint", "ms word"], "soft_skills": ["meticulous", "work independently", "self-motivated", "communication skills", "well-organized", "mature", "reliable", "interpersonal"], "languages_combined": [{"language": "english", "language_level": ["good command"]}, {"language": "chinese", "language_level": ["good command", "proficient"]}, {"language": "mandarin", "language_level": ["advantage"]}]}, "experience_required": {"duration": ["at least 3 years"], "field": ["management", "relevant experience"]}}, {"job_id": "100003009042596", "location_code": "hk", "company": "Manfield Limited", "job_title": "URGENT - Executive Secretary", "description": "Responsibilities:\n\nReporting to a Director\nProvide full range of good quality secretarial and administrative support;\nManage all business and personal issues for the Director in professional manner, including but not limited to meeting and travel schedules, social events and functions co-ordination etc.;\nPrepare business correspondences, presentation materials, compile reports and meeting minutes in a variety of formats independently and professionally;\nLiaise with internal and external parties to ensure smooth business operations;\nManage payments, claims and reimbursements;\nHandle sensitive and confidential data and documents in professional manner;\nAssist in ad-hoc duties as assigned.\n\n\nRequirements:\u00a0 \u00a0 \u00a0 \u00a0 \u00a0 \u00a0\n\nUniversity Graduate or equivalent;\nMinimum 8 years\u2019 relevant experience with proven track record in serving senior executives or directors, preferably in sizeable companies;\nAbility of maintaining sensitive and confidential information with strictest confidence;\nProficient in MS Office applications with Chinese word processing;\nStrong inter-personal and communication skills;\nExcellent command of spoken and written English, Cantonese and Mandarin;\nMature, self-motivated, meticulous and able to handle multiple tasks with discretion.", "employment_types": ["Full Time", "Permanent"], "selling_points": [], "locations": ["Tsuen Wan Area"], "categories": ["Admin & HR", "Personal / Executive Assistant", "Secretary", "Others"], "post_time": "2022-01-12T10:02:23Z", "salary": {"currency": null, "max": null, "min": null, "period": "monthly", "term": null}, "salary_visible": false, "title_keywords": ["executive secretary"], "responsibilities": ["reporting", "administrative support", "schedules", "compile reports", "operations", "internal and external parties", "quality", "professional manner", "data", "payments", "ad-hoc duties", "liaise with"], "requirements": {"degrees": ["university graduate"], "majors": [], "languages": ["cantonese", "english", "chinese", "mandarin"], "language_level": ["excellent", "proficient"], "hard_skills": ["chinese word processing", "ms office"], "soft_skills": ["communication skills", "self-motivated", "confidence", "meticulous", "inter-personal", "mature", "handle multiple tasks", "sensitive"], "languages_combined": [{"language": "cantonese", "language_level": ["excellent"]}, {"language": "english", "language_level": ["excellent"]}, {"language": "chinese", "language_level": ["proficient"]}, {"language": "mandarin", "language_level": ["excellent"]}]}, "experience_required": {"duration": ["minimum 8 years"], "field": ["relevant experience"]}}, {"job_id": "100003009043992", "location_code": "hk", "company": "Optimum Solutions (Hong Kong) Limited", "job_title": "Administrative Assistant - IT Project", "description": "Responsibilities:\n\nOrganize and schedule appointments\nPlan meetings and take detailed minutes\nWrite and distribute internal communication\nResponsible for the preparation of regularly scheduled reports\nUpdate and maintain PMO policies and procedures\nAct as the point of contact for all Project Managers\nResponsible for consolidating reports for all Programs\n\nRequirements:\n\nProven experience as an Administrative Assistant\nProficiency in MS Office (MS Excel and MS PowerPoint, in particular), MS Project and SharePoint\nExcellent time management skills and ability to prioritize work\nAttention to detail and problem-solving skills\nExcellent written and verbal communication skills\nStrong organizational skills with the ability to multi-task\nExcellent command of English\nUnderstanding and being Interested in I.T and technologies would be a definite advantage", "employment_types": ["Contract"], "selling_points": ["Administrative", "IT Project", "Fluency in English"], "locations": ["Southern Area"], "categories": ["Admin & HR", "Administration / Operation Manager", "Secretary", "Information Technology (IT)", "Others"], "post_time": "2022-01-13T02:43:07Z", "salary": {"currency": null, "max": null, "min": null, "period": "monthly", "term": null}, "salary_visible": false, "title_keywords": ["administrative assistant"], "responsibilities": ["policies", "procedures", "communication", "maintain", "reports", "schedule", "plan", "contact"], "requirements": {"degrees": [], "majors": [], "languages": ["english"], "language_level": ["excellent"], "hard_skills": ["problem-solving skills", "ms powerpoint", "ms excel", "ms office"], "soft_skills": ["communication skills", "organizational skills", "multi-task", "time management skills", "interested in", "prioritize", "attention to detail", "problem-solving skills"], "languages_combined": [{"language": "english", "language_level": ["excellent"]}]}, "experience_required": {"duration": [], "field": ["administrative"]}}, {"job_id": "100003009043531", "location_code": "hk", "company": "Asia Satellite Telecommunications Co Ltd", "job_title": "Administration Officer", "description": "Responsibilities:\n\nProvide a full spectrum of administrative and secretarial support to the Department / Team\nPrepare minutes and reports, presentation and meeting materials including translation\nDiary management; schedule and coordinate meetings, conference calls and video- conference.\nHandle travel arrangement, flight and accommodation booking and expense reimbursement\nAssist in the office administration duties including manage receptionist duties, stationery and printing, office equipment maintenance, office supplies, fixed assets management, incoming and outgoing couriers/mails and etc.\nHandle procurement related activities including sourcing, issue PO, follow up order delivery as well as billing and invoice settlement.\nHandle Import license application and Export / Import declaration\nResponsible for inventory control, such as stationery, consumables and equipment, etc.\n\nRequirements:\u00a0\n\nDegree holder in\u00a0Business Administration or related discipline\nMinimum 5 years' relevant experience \u00a0in administrative / secretarial field\nPossess a customer-service orientated approach to problem resolution and sustainable in high demanding working environment;\nHighly organized, detail-minded, multi-tasking and able to meet tight deadlines\nIndependent, a good team player with positive, proactive and flexible attitude\nGood command of written & spoken English & Chinese including Putonghua\nProficient in MS Office including Word, Excel, PowerPoint and Chinese Word Processing\nImmediate available is highly preferred\n\nA competitive package will be offered to the right candidate.\u00a0\u00a0Interested parties please email their resume with expected salary to Human Resources Department by clicking \"Apply Now\".\n\nAsiaSat is an Equal Opportunities Employer. \u00a0Personal data collected will be used for recruitment purpose only.\u00a0", "employment_types": ["Full Time", "Permanent"], "selling_points": ["Office management", "Administrative & Secretarial support", "Min. 5 years' relevant experience"], "locations": ["Tai Po Area"], "categories": ["Admin & HR", "Administration / Operation Manager", "Personal / Executive Assistant", "Secretary"], "post_time": "2022-01-12T16:40:57Z", "salary": {"currency": null, "max": null, "min": null, "period": "monthly", "term": null}, "salary_visible": false, "title_keywords": ["administration officer"], "responsibilities": ["management", "office supplies", "invoice", "stationery", "coordinate", "fixed assets management", "office equipment maintenance", "reports", "secretarial support", "schedule", "travel arrangement", "booking", "office administration duties", "license application", "inventory control"], "requirements": {"degrees": ["degree holder"], "majors": ["business administration"], "languages": ["putonghua", "english", "chinese"], "language_level": ["good command", "proficient"], "hard_skills": ["excel", "chinese word processing", "word", "powerpoint", "ms office"], "soft_skills": ["detail-minded", "organized", "meet tight deadlines", "good team player", "independent", "flexible", "multi-tasking", "proactive", "positive"], "languages_combined": [{"language": "putonghua", "language_level": ["good command"]}, {"language": "english", "language_level": ["good command"]}, {"language": "chinese", "language_level": ["good command", "proficient"]}]}, "experience_required": {"duration": ["minimum 5 years"], "field": ["secretarial", "administrative", "relevant experience"]}}, {"job_id": "100003009047328", "location_code": "hk", "company": "Zeal Technology Solutions Limited", "job_title": "Executive Assistant, COO Office - Fintech (Trading Platform)", "description": "Key Objective of the Role:\nAs an Executive Assistant, your key responsibility is to manage & coordinate the in-house sales-related projects across the regions. Ensure successful planning, executing, monitoring, controlling, and closing of projects. As well as, to make sure the requirements from stakeholders are fulfilled, control project schedules, allocate resources and ensure that all projects are delivered on time.\n\nJob Description:\n\nDirect report to Chief Operating Officer and manage the in-house sales-related projects across the regions independently\nWork closely with COO and his management team, to keep all parties well informed of upcoming commitments and responsibilities, following up appropriately\nManaging COO's work schedule prioritization with a certain level of flexibility and people skills\nScope project requirements and prepare specifications and supporting documentation\nIdentify the quality requirements and standards for projects, audit the quality requirements, monitoring and record the result of quality activities to assess the performance\nImplementation and maintenance of procedure and process documentation\nExecute and monitor the project and ensure it is delivered on time\nCommunicate and collaborate with external & internal teams and departments to optimize project progress\nAssist to conduct in-house training and perform professional knowledge quality checking\nCompiling and preparing reports, presentations, and correspondence\nPerform other ad hoc duties as assigned by COO & support Sales Department\nRequirements:\n\nDegree holder in Business Administration or related disciplines\nMinimum 3 - 5 years of experience as Executive Assistant and Support, with extensive and hands-on project management experience\nExperience gained from Fintech / Digital Asset\u00a0 / Financial industry is highly preferred\nGood knowledge of software packages and PMS (Jira, Confluence)\nFast learner with an ability to adopt various software and system if required\nOrganized, well-planned, and detail-oriented\nExcellent time management skills with the ability to meet deadlines\nStrong flexibility and adaptability\nExcellent analytical skills and able to work independently\nGood people skill with an outgoing personality\nExcellent oral and written communication skills in English and Chinese (Mandarin)\nIf you believe you have the right skills, attitude, and experience, please click \"Apply Now\" and upload your updated resume with your current and expected salary.\u202f Only shortlisted candidates will be contacted.\u00a0\n\n(Personal details collected are for recruitment purposes only and kept confidential.)\u00a0", "employment_types": ["Full Time"], "selling_points": ["International Fintech Digital Asset Firm", "Regional Project Management Exposure", "Excellent Learning Opportunity"], "locations": ["Sheung Wan"], "categories": ["Admin & HR", "Secretary", "Sales, CS & Business Devpt", "Business Development"], "post_time": "2022-01-14T02:50:56Z", "salary": {"currency": null, "max": null, "min": null, "period": "monthly", "term": null}, "salary_visible": false, "title_keywords": ["executive assistant"], "responsibilities": ["collaborate with", "project requirements", "quality", "audit", "ad hoc duties", "management team", "monitor", "implementation", "teams", "project progress", "presentations", "schedule", "report", "quality checking", "monitoring", "specifications", "preparing reports", "documentation", "maintenance"], "requirements": {"degrees": ["degree holder"], "majors": ["related disciplines", "business administration"], "languages": ["english", "chinese", "mandarin"], "language_level": ["excellent"], "hard_skills": ["project management", "analytical skills"], "soft_skills": ["outgoing personality", "organized", "work independently", "oral", "communication skills", "time management skills", "fast learner", "detail-oriented", "analytical skills", "project management", "hands-on", "adaptability", "meet deadlines", "extensive"], "languages_combined": [{"language": "english", "language_level": ["excellent"]}, {"language": "chinese", "language_level": ["excellent"]}, {"language": "mandarin", "language_level": ["excellent"]}]}, "experience_required": {"duration": ["minimum 3 - 5 years"], "field": ["project management", "financial industry", "digital"]}}, {"job_id": "100003009042350", "location_code": "hk", "company": "Chance Max Limited", "job_title": "Administrative Assistant / Secretary", "description": "RESPONSIBILITIES\n\nProviding full spectrum secretarial and routine clerical assistance to Manager, both personal and business matters\nDaily office work, including procurement and management of office supplies and equipment, deliveries, conference arrangement and reception help desks\nMaintain and handle the record, agenda, resolutions and prepare documents such as minutes and confidential documents,\nAssist in Company\u2019s projects and acting as project assistant for liaising with various internal and external parties\nUndertaking ad hoc tasks as assigned\n\n\u00a0REQUIREMENT\n\nDiploma or above in Secretarial or Business Administration qualifications will be an advantage\u00a0\nWell organized, detail-oriented, self-motivated with a strong sense of responsibility and multi-tasking\nHigh proficiency in MS Office (including Chinese typing)\nExcellent communication skills in both written and spoken English and Putonghua\nFresh graduates are welcome\nImmediate available preferred\nWe offer competitive remuneration package including 5-day work, performance bonus to the right candidate. Interested parties please send full resume with current and expected salary, availability in WORD format by email or by clicking \"Apply Now\".\n\n(Personal data collected will be used for recruitment purposes only)\n\n", "employment_types": ["Full Time", "Permanent"], "selling_points": [], "locations": ["Tsuen Wan Area"], "categories": ["Admin & HR", "Clerical / Admin Staff", "Secretary", "Others"], "post_time": "2022-01-12T07:09:08Z", "salary": {"currency": null, "max": null, "min": null, "period": "monthly", "term": null}, "salary_visible": false, "title_keywords": ["administrative assistant", "secretary"], "responsibilities": ["management", "office supplies", "internal and external parties", "ad hoc tasks", "liaising with", "maintain", "prepare documents"], "requirements": {"degrees": ["diploma or above"], "majors": ["business administration"], "languages": ["putonghua", "english", "chinese"], "language_level": ["proficiency", "excellent"], "hard_skills": ["typing", "ms office"], "soft_skills": ["communication skills", "self-motivated", "sense of responsibility", "well organized", "detail-oriented", "multi-tasking"], "languages_combined": [{"language": "putonghua", "language_level": ["excellent"]}, {"language": "english", "language_level": ["excellent"]}, {"language": "chinese", "language_level": ["proficiency"]}]}, "experience_required": {"duration": [], "field": []}}, {"job_id": "100003009043770", "location_code": "hk", "company": "Arup", "job_title": "Secretary / Assistant Secretary (2-year contract)", "description": "Responsibilities:\n\nProvide full spectrum of secretarial support to the team\nOrganize and participate in meetings, and assist in post-meeting follow up\nPerform any administrative duties assigned by supervisor\nAssist in ad-hoc duties as assigned\n\nQualifications & Experience required:\n\nF.5 or DSE, with recognised secretarial qualifications is preferable\nAt least 4 years of relevant experience for the position of Secretary and at least 2 years of relevant experience for the position of Assistant Secretary. Experience gained from construction / engineering industry will be an advantage\nProactive, mature, detail-minded coupled with strong interpersonal, organizational and communication skills\nProficiency in Microsoft Office applications including Word, Excel, PowerPoint and Chinese Word Processing\nProficiency in both written and spoken English and Chinese\nFresh university graduates will also be considered\nImmediate available is highly preferred\n\nWe offer a competitive remuneration package commensurate with qualifications and experience to the right candidate.\n\nFor interested applicants, please click \u201cApply Now\u201d to submit your online application.\n\nPersonal\u00a0data collected will be used for recruitment purpose only. Applicants not contacted within 8 weeks may consider their applications unsuccessful.", "employment_types": ["Full Time", "Contract"], "selling_points": [], "locations": ["Kowloon City Area"], "categories": ["Admin & HR", "Clerical / Admin Staff", "Secretary", "Others"], "post_time": "2022-01-13T01:54:12Z", "salary": {"currency": null, "max": null, "min": null, "period": null, "term": null}, "salary_visible": false, "title_keywords": ["secretary", "assistant"], "responsibilities": ["communication", "administrative duties", "secretarial support", "ad-hoc duties"], "requirements": {"degrees": ["dse"], "majors": [], "languages": ["english", "chinese"], "language_level": ["proficiency"], "hard_skills": ["excel", "chinese word processing", "microsoft office", "word", "powerpoint"], "soft_skills": ["detail-minded", "communication skills", "organizational", "mature", "ad-hoc duties", "proactive", "interpersonal"], "languages_combined": [{"language": "english", "language_level": ["proficiency"]}, {"language": "chinese", "language_level": ["proficiency"]}]}, "experience_required": {"duration": ["at least 2 years", "at least 4 years"], "field": ["relevant experience", "construction", "engineering"]}}, {"job_id": "100003009046032", "location_code": "hk", "company": "Airport Authority Hong Kong", "job_title": "Projects Administration Officer", "description": "This is a fixed-term contract position of minimum 2 years with possibility for renewal subject to organization need and individual performance. Responsibilities:\nProviding all-rounded secretarial and administration service to the team including but not limited to managing daily appointments, calendar, travel itinerary and meetings; and preparing business correspondence;\nHandling project documents and maintaining effective filing / database management systems;\nAssisting in managing project documentation using project management software systems;\nHandling enquiries and maintaining effective communication with internal and external customers; and\nAssisting in ad hoc projects and assignments as required.\n\nRequirements:\n\nDiploma or above in Business Administration, Secretarial Studies or other related disciplines with at least 5 years' relevant working experience in project administration, work process management and/or document control; or Secondary level with at least 6 years' relevant working experience and formal secretarial training will also be considered\nGood command of spoken and written English and Chinese. Knowledge of Putonghua is an advantage\nProficient in MS Office applications and project management software tools", "employment_types": ["Full Time"], "selling_points": ["Fixed term contract", "Provide secretarial and admin support", "Diploma with 5+ yrs relevant experience"], "locations": ["Airport Area"], "categories": ["Admin & HR", "Personal / Executive Assistant", "Secretary"], "post_time": "2022-01-13T09:27:39Z", "salary": {"currency": null, "max": null, "min": null, "period": "monthly", "term": null}, "salary_visible": false, "title_keywords": ["administration officer"], "responsibilities": ["internal and external customers", "management", "software", "maintaining", "systems", "communication", "project management", "project documents", "ad hoc projects", "database", "project documentation", "administration"], "requirements": {"degrees": ["diploma or above"], "majors": ["related disciplines", "business administration"], "languages": ["putonghua", "english", "chinese"], "language_level": ["advantage", "good command"], "hard_skills": ["project management", "ms office"], "soft_skills": ["project management"], "languages_combined": [{"language": "putonghua", "language_level": ["advantage"]}, {"language": "english", "language_level": ["good command"]}, {"language": "chinese", "language_level": ["good command"]}]}, "experience_required": {"duration": ["at least 6 years", "at least 5 years"], "field": ["secretarial", "management", "business administration", "training", "related", "relevant working experience", "administration"]}}, {"job_id": "100003009051332", "location_code": "hk", "company": "Assurance Education Limited", "job_title": "Administrative Assistant/Secretary, Full Time", "description": "Job Description: Administrative Assistant/Secretary\n\nOrganization\n\nAssurance aims to help students make blossom and make the most out of high school. Assurance is headquartered in Hong Kong and maintains offices in Shenzhen and Shanghai. Our managing director and founder undertook undergraduate education in law at the University of Cambridge. He has taught English for more than ten years. All of our consultants are from top universities such as Wharton, Harvard, UPenn and UChicago. For more information, please visit www.assuranceedu.com.\n\nPosition\n\nAdministrative Assistant/Secretary, Full Time\n\nLocation\n\nCauseway Bay\n\nHours\n\n5 days work week\nTuesday to Saturday\n9.30am to 6.30pm\n\nResponsibilities\n\nProvide administrative support\nHandle correspondence\nManage school application forms\nAssist in seminars and events\n\nRequirements\n\nFluency in Cantonese, English and Mandarin\nProficient in Word, Excel, and word processing in English & Chinese\n1 year of experience as administrative assistant/secretary\nDegree holder in any discipline\n\nCompensation\n\nWe offer a starting salary of $15000-$17,000/month. Please state your expected salary.\n\nApplication\n\nInterested parties please submit your resume and cover letter to Ms. Tiffany Cheung at admin @ AssuranceEDU.com\u00a0with \u201c[Name] Assurance Recruitment]\u201d in the email title. Please state your expected salary.", "employment_types": ["Full Time"], "selling_points": ["Proficiency in English, Cantonese & Mandarin", "Degree holder, 1 year of experience", "Salary $15-17K, 5 days working"], "locations": ["Causeway Bay"], "categories": ["Admin & HR", "Personal / Executive Assistant", "Receptionist", "Secretary"], "post_time": "2022-01-15T09:22:29Z", "salary": {"currency": "HKD", "max": 16999, "min": 14000, "period": "monthly", "term": null}, "salary_visible": true, "title_keywords": ["administrative assistant", "secretary"], "responsibilities": ["provide administrative support"], "requirements": {"degrees": ["degree holder"], "majors": [], "languages": ["cantonese", "english", "chinese", "mandarin"], "language_level": ["fluency", "proficient"], "hard_skills": ["excel", "word processing", "word"], "soft_skills": [], "languages_combined": [{"language": "cantonese", "language_level": ["fluency"]}, {"language": "english", "language_level": ["fluency", "proficient"]}, {"language": "chinese", "language_level": ["fluency", "proficient"]}, {"language": "mandarin", "language_level": ["fluency"]}]}, "experience_required": {"duration": ["1 year"], "field": ["administrative"]}}, {"job_id": "100003009043518", "location_code": "hk", "company": "Prowess Recruitment Consulting Limited", "job_title": "Personal Assistant", "description": "Our client, is a family investment company in China and Hong Kong, they are looking for high caliber candidate to support the Director and the office operation as Personal Assistant.\n\nResponsibilities :-\n\nReports to the Director and provides full spectrum of secretarial and business development and marketing support;\nProvides administration support to the Company and Director\u2019s Family, including but not limit to organizing meeting with agenda and minutes, following-up actions, travel planning/ booking, expense report, market research and account servicing , etc;\nPrepares various correspondences, documents, reports and meeting materials and presentations in professional manner from time to time;\nLiaises with internal and external parties on business proactively and independently;\nHandles and maintains confidential and sensitive information and contracts;\nBuilds and maintains efficient filing system and record management;\nFamiliar with accounting data entry and office administration\nAssists in ad-hoc projects and tasks when required\u00a0\n\nRequirements :-\n\nDegree in any discipline or relevant qualifications\nOver 5 years relevant experience supporting senior management\nStrong planning, analytical and reporting skills\nExcellent command of written English and Chinese; fluent in spoken English, Cantonese, and Putonghua\nProficient in MS Office \u2013 Excel, Powerpoint, Outlook, Word and Chinese Word Processing\nMature, energetic, self-motivated, well-organized, good team player, fast learner and eager to take on new challenges\nExcellent planning and organizational skills and able to handle multiple projects and changing priorities with professionalism\nExcellent communication and interpersonal skill, able to work effectively and efficiently with all levels;\nAble to adapt to a fast environment and able to meet deadline on a timely manner\nGood interpersonal skill, well organized and able to work under pressure\u00a0 \u00a0\n\nMORE POSITIONS PLEASE VISIT OUR WEBSITE AT:\u00a0http://www.prowess.hk\n\nPriority Application through our website will be firstly considered and it also enhances our efficiency. For interested candidates, please fill in the on-line Resume in\u00a0http://www.prowess.hk/submitresume.asp\u00a0. You can attach other document, certificate and reference letter through the website or email to us.\u00a0\n\nFor interested candidates, please submit your full resume with expected salary in MS Word format to us through the above email\u00a0to our consultant\u00a0\u00a0or contact us at\u00a0+852\u00a0 2838 9621 for more information of the position.", "employment_types": ["Permanent"], "selling_points": ["Relevant experience supporting senior management", "Fluent in English and Mandarin is a MUST", "Willing to work flexible hours upon requested"], "locations": ["Admiralty"], "categories": ["Admin & HR", "Personal / Executive Assistant", "Secretary"], "post_time": "2022-01-12T15:42:13Z", "salary": {"currency": "HKD", "max": 34999, "min": 30000, "period": "monthly", "term": null}, "salary_visible": true, "title_keywords": ["personal assistant"], "responsibilities": ["administration", "management", "data entry", "contracts", "office administration", "internal and external parties", "professional manner", "market research", "presentations", "planning", "reports", "booking", "ad-hoc projects", "report"], "requirements": {"degrees": ["degree"], "majors": [], "languages": ["cantonese", "putonghua", "english", "chinese"], "language_level": ["proficient", "excellent", "fluent"], "hard_skills": ["excel", "chinese word processing", "word", "powerpoint", "outlook", "ms office"], "soft_skills": ["work effectively", "organizational skills", "good team player", "self-motivated", "timely", "well-organized", "well organized", "mature", "interpersonal skill", "communication", "energetic", "fast learner", "work under pressure"], "languages_combined": [{"language": "cantonese", "language_level": ["fluent"]}, {"language": "putonghua", "language_level": ["fluent"]}, {"language": "english", "language_level": ["excellent", "fluent"]}, {"language": "chinese", "language_level": ["proficient", "excellent"]}]}, "experience_required": {"duration": ["5 years"], "field": ["management", "relevant experience"]}}, {"job_id": "100003009043085", "location_code": "hk", "company": "The Hong Kong Polytechnic University", "job_title": "Senior Secretary", "description": "FINANCE OFFICE\n\nSenior Secretary (Ref. 22011230-IE)\n\nDuties\n\nThe appointee will be required to:\n\n(a) provide secretarial service to the Director of Finance and the Deputy Director of Finance, including arranging/coordinating departmental activities and committee meetings, maintaining calendar, scheduling appointments and making arrangements for off-campus meetings, travel and accommodation arrangements;\n\n(b) provide administrative support to the day-to-day operation of the Finance Office, including recruitment and human resources matters, planning and arranging visits and events;\n\n(c) manage meeting papers and materials of relevant University committees including compilation, distribution and record-keeping;\n\n(d) handle information flow and maintain an effective record and filing system;\n\n(e) handle sensitive and confidential matters in a professional manner;\n\n(f) liaise with internal and external parties in a personable manner; and\n\n(g) perform any other duties as assigned by the Director of Finance or her delegates.\n\nQualifications\u00a0\n\nApplicants should:\n\n(a) have a recognized degree plus at least three years of relevant post-qualification secretarial/administrative experience;\u00a0\n\n(b) be able to communicate effectively in both written and spoken English and Chinese, with fluency in Putonghua being an advantage;\n\n(c) have good computer literacy including Microsoft Word, Excel, PowerPoint and Chinese word processing;\n\n(d) have good communication and interpersonal skills;\n\n(e)\u00a0 be well-organized and attentive to details; and\n\n(f) be able to initiate appropriate actions, work independently and handle sensitive matters with alertness and care.\n\nShortlisted candidates will be invited to sit for a written test.\n\nRemuneration and Conditions of Service\n\nA highly competitive remuneration package will be offered.\u00a0 Initial appointment will be on a fixed-term gratuity-bearing contract.\u00a0 Re-engagement thereafter is subject to mutual agreement.\u00a0 Applicants should state their current and expected salary in the application.\n\n\n\n\nApplication\n\nPlease send a completed application form by post to Human Resources Office, 13/F, Li Ka Shing Tower, The Hong Kong Polytechnic University, Hung Hom, Kowloon, Hong Kong or via email by clicking \"Apply Now\".\u00a0 Application forms can be downloaded from https://www.polyu.edu.hk/hro/careers/guidelines_and_forms/forms.\u00a0 If a separate curriculum vitae is to be provided, please still complete the application form which will help speed up the recruitment process. The closing date for application is Wednesday, 19 January 2022.\u00a0 Applicants who are not invited to an interview within two months from the closing date should consider their applications unsuccessful. The University\u2019s Personal Information Collection Statement for recruitment can be found at https://www.polyu.edu.hk/hro/careers/guidelines_and_forms/pics_for_recruitment.\n\nPolyU is an equal opportunity employer committed to diversity and inclusivity.\u00a0 All qualified applicants will receive consideration for employment without regard to gender, ethnicity, nationality, family status or physical or mental disabilities.", "employment_types": ["Full Time"], "selling_points": [], "locations": ["Not Specified"], "categories": ["Admin & HR", "Clerical / Admin Staff", "Personal / Executive Assistant", "Secretary"], "post_time": "2022-01-12T09:48:09Z", "salary": {"currency": null, "max": null, "min": null, "period": null, "term": null}, "salary_visible": false, "title_keywords": ["senior secretary"], "responsibilities": ["any other duties", "maintaining", "internal and external parties", "professional manner", "secretarial service", "scheduling", "liaise with", "maintain", "recruitment", "communication", "provide administrative support", "recruitment process", "day-to-day operation", "planning"], "requirements": {"degrees": ["degree"], "majors": [], "languages": ["putonghua", "english", "chinese"], "language_level": ["fluency", "advantage", "good"], "hard_skills": ["excel", "plus", "microsoft word", "chinese word processing", "powerpoint", "c"], "soft_skills": ["work independently", "personable", "attentive to details", "well-organized", "computer literacy", "committed", "communication and interpersonal skills", "sensitive"], "languages_combined": [{"language": "putonghua", "language_level": ["fluency", "advantage"]}, {"language": "english", "language_level": ["advantage"]}, {"language": "chinese", "language_level": ["advantage", "good"]}]}, "experience_required": {"duration": ["at least three years"], "field": ["secretarial", "administrative", "post-qualification"]}}, {"job_id": "100003009044583", "location_code": "hk", "company": "Honour Lane Shipping Ltd", "job_title": "Admin & HR Assistant / Executive", "description": "Staff Benefits:\n\n5-day work per week\nMonthly Attendance Incentive\nHalf-year Attendance Incentive\nOvertime Allowance\nPaid Annual Leave\nYear-end Bonus\nPerformance Bonus\nLong Service Award\nStaff Wellness Programme\nGood career path\n\n\n\nResponsibilities:\n\nResponsible for full spectrum of Administration and Human Resources functions of the group but not limited to recruitment, general office management, service contract and business license renewal,\u00a0fixed asset management,\u00a0procurement and payment, etc.\nAssist in payroll preparation\nLiaise with internal and external parties for daily administration & HR operations;\nSupport reception duties\nTo arrange company event and assist in ad-hoc assignment when required\n\nJob Requirements:\n\nDegree holder in Business administration, Human Resources and or any disciplines;\nAt least 2-years' working experience;\nWell organized, strong sense of responsibility, attention to details and eager to learn;\nGood command of written and spoken English and Mandarin\nProficient in MS Word, Excel and Chinese Word Processing;\nFresh graduate is welcome and immediately available is highly preferred\u00a0\nCandidate with less experience will be considered as junior position\u00a0\n\nInterested parties please submit your resume, present and expected salary at \"Apply Now\" at JobsDB. Personal data collected will be used for recruitment purpose only.", "employment_types": ["Full Time", "Permanent"], "selling_points": ["Full spectrum of Administration and HR duties", "5 days work", "Year End Payment, Discretionary Bonus"], "locations": ["Tsuen Wan Area"], "categories": ["Admin & HR", "Personal / Executive Assistant", "Secretary", "HR Supporting Staff"], "post_time": "2022-01-13T04:38:41Z", "salary": {"currency": null, "max": null, "min": null, "period": "monthly", "term": null}, "salary_visible": false, "title_keywords": ["admin & hr assistant", "executive"], "responsibilities": [], "requirements": {"degrees": [], "majors": [], "languages": [], "language_level": [], "hard_skills": [], "soft_skills": [], "languages_combined": []}, "experience_required": {"duration": [], "field": []}}, {"job_id": "100003009042134", "location_code": "hk", "company": "MHK Restaurants Limited", "job_title": "Executive Secretary to Director", "description": "Accountabilities:\n\nProvide full spectrum of professional\u00a0secretarial and administrative support to senior management regarding both business and personal matters\nManage daily schedule, business appointments and travel itineraries for senior management\nPrepare presentation materials for meetings and business reports\nPerform translation in English & Chinese\nDraft various correspondences in English and Chinese\nSort and review incoming mails/ emails/ correspondences\nHandle and maintain confidential information and document management\nAssist in any ad hoc assignments if required\n\nProfessional should \u00a0\n\nDegree Holder is required\nMinimum 10 years\u2019 relevant experience; Experienced in serving senior executives in sizable companies or with customer service experience is highly preferred\nExcellent command of spoken and written English and Chinese (Cantonese & Mandarin)\nFamiliar with MS Outlook, Excel, PowerPoint and Chinese Word Processing\nExcellent interpersonal, coordination and organization skills\nHigh flexibility, reliable, possess integrity and respect for confidentiality\nWell organized, cheerful, service-oriented, with strong sense of responsibility and is a team player\nAble to adapt to fast-paced and ad-hoc working environment\u00a0\n\nApplicants have not been invited for an interview within 6 weeks may consider their applications as unsuccessful.\n\nPersonal data collected will be kept and handled confidentially by authorized personnel for recruitment purposes only. We will retain the applications of candidates not selected for a period of no more than 12 months.", "employment_types": ["Full Time"], "selling_points": ["Administrative & executive secretarial support", "Meticulous,well-organized,mature & self-motivated", "Family & friend working environment"], "locations": ["Quarry Bay"], "categories": ["Admin & HR", "Secretary", "Professional Services", "Company Secretary", "Sales, CS & Business Devpt", "Customer Service - Supervisor / Officer"], "post_time": "2022-01-12T06:20:36Z", "salary": {"currency": null, "max": null, "min": null, "period": "monthly", "term": null}, "salary_visible": false, "title_keywords": ["executive secretary", "director"], "responsibilities": ["ad-hoc", "management", "administrative support", "review", "customer service experience", "personal data", "maintain", "reports", "schedule", "ad hoc assignments", "coordination", "recruitment", "senior management"], "requirements": {"degrees": ["degree holder"], "majors": [], "languages": ["cantonese", "english", "chinese", "mandarin"], "language_level": ["excellent"], "hard_skills": ["excel", "no", "chinese word processing", "sizable companies", "powerpoint", "outlook", "translation"], "soft_skills": ["cheerful", "sense of responsibility", "service-oriented", "integrity", "well organized", "customer service", "reliable", "coordination", "organization skills", "team player", "interpersonal", "presentation"], "languages_combined": [{"language": "cantonese", "language_level": ["excellent"]}, {"language": "english", "language_level": ["excellent"]}, {"language": "chinese", "language_level": ["excellent"]}, {"language": "mandarin", "language_level": ["excellent"]}]}, "experience_required": {"duration": ["minimum 10 years"], "field": ["customer service", "relevant experience"]}}, {"job_id": "100003009041574", "location_code": "hk", "company": "Hearts on Fire Company Hong Kong Limited", "job_title": "Executive Secretary", "description": "Executive Secretary\n\nWhat You Will Own\n\n\nDelivering efficient and high quality secretarial and administrative assistance to Executive Director and Executive Assistant.\nServing as one of the key point of contacts for designated business units on coordinating cross-regional matters, and facilitating communications with internal and external stakeholders, as well as guests and industry networks.\nAssist Executive Assistant in managing the executive schedule; keeping track of key agendas, actions, appointments and travels; supporting gifting arrangements as well as team events, such as birthdays, anniversaries and festive.\nOrganizing and coordinating local and regional meetings, executive travel plans and visits.\nPreparing meeting agendas and minutes, and keeping track of post-meeting follow-ups; consolidating business presentations, preparing and distributing correspondences, maintaining records and reports.\nFacilitating VIP invites and maintaining guests directory and customer database.\nCoordinating networking events, team-building activities as well as other company-wide initiatives, charity and private events.\nProcessing invoices, payments and claims; tracking and supporting the approval of expenses and reimbursements.\nMaintaining confidential information and ensuring sensitive information is handled appropriately with strict confidence.\nAssisting in projects and performing ad-hoc duties as assigned.\n\n\u00a0Who Will Thrive\n\n\nPreferable with Degree in Business Administration or Secretarial Studies.\nAt least 8 years of relevant experience in administrative/secretarial support, preferably in MNC; experience in international luxury retail/ jewellery and watches industry is an advantage.\nExperience in collaborating with stakeholders across regions; cross-culture exposure is a plus.\nStrong awareness of maintaining highest degree of confidentiality with integrity and sensitivity.\nWell-polished in stakeholder management. Excellent interpersonal skills and ability to interact with stakeholders at all levels in a professional manner.\nApproachable with a service mindset; competent in working independently and collaboratively as a team player.\nWell organized with attention to detail; highly capable of working effectively with multiple timelines.\nCapable of addressing challenges and offering solutions/ alternatives with creativity, flexibility and an open-mind.\nProficient in MS Office. Knowledge in Salesforce is a plus.\nExcellent communication in verbal and written English and Chinese.", "employment_types": ["Full Time"], "selling_points": ["Administrative & executive secretarial support", "Experienced in handling payment & claims", "Maintenance of guest directory & correspondence"], "locations": ["Quarry Bay"], "categories": ["Admin & HR", "Clerical / Admin Staff", "Personal / Executive Assistant", "Secretary"], "post_time": "2022-01-12T04:03:16Z", "salary": {"currency": null, "max": null, "min": null, "period": "monthly", "term": null}, "salary_visible": false, "title_keywords": ["executive secretary"], "responsibilities": ["quality", "professional manner", "communication", "administrative assistance", "secretarial support", "database", "plans", "administration", "communications with", "invoices", "maintaining", "expenses", "presentations", "reports", "schedule", "management", "ad-hoc duties", "tracking", "payments"], "requirements": {"degrees": ["degree"], "majors": ["business administration"], "languages": ["english", "chinese"], "language_level": ["excellent"], "hard_skills": ["plus", "salesforce", "charity", "presentations", "processing", "ms office"], "soft_skills": ["efficient", "confidence", "approachable", "independently", "capable", "competent", "sensitivity", "integrity", "well organized", "communication", "interpersonal skills", "attention to detail", "ad-hoc duties", "team player", "sensitive"], "languages_combined": [{"language": "english", "language_level": ["excellent"]}, {"language": "chinese", "language_level": ["excellent"]}]}, "experience_required": {"duration": ["at least 8 years"], "field": ["luxury retail", "secretarial", "administrative", "relevant experience"]}}, {"job_id": "100003009036124", "location_code": "hk", "company": "Ample Success Consultants Limited", "job_title": "Personal Assistant to Chairman", "description": "Our company is a well-established local brokerage house in Hong Kong. To cope with our continued growth, we are looking for a right candidate to join us.\n\nResponsibilities:\n\nTo provide full spectrum of secretarial support to the Chairman regarding both business and personal matters\nManage daily schedule, business appointments, and travel itineraries\nAssist in minute taking, handle general correspondence, emails, memos, letters, presentations, and reports as required\nRequirements:\n\nDiploma or Degree in Business Administration or formal secretarial training\nMinimum 5 years of relevant experience\nGood communication skills to manage personal and ad-hoc business matters\nExcellent command of written English and Chinese; fluent in spoken English, Cantonese and Putonghua\nProficient in MS applications and Google-powered business tools (email, calendar, docs)\nDedicated and willing to work to irregular time schedules\nSelf-motivated, mature, and presentable\nImmediately available is a plus\nInterest parties please email your full resume with present & expected salary and state the date of availability by clicking \"Apply Now\".", "employment_types": ["Full Time"], "selling_points": ["Excellent command of written English and Chinese", "Proficient in MS applications & Google tools", "Self-motivated, mature, and presentable"], "locations": ["Central"], "categories": ["Admin & HR", "Personal / Executive Assistant", "Secretary"], "post_time": "2022-01-10T16:52:46Z", "salary": {"currency": null, "max": null, "min": null, "period": "monthly", "term": null}, "salary_visible": false, "title_keywords": ["personal assistant"], "responsibilities": ["letters", "presentations", "reports", "secretarial support", "schedule"], "requirements": {"degrees": ["diploma", "degree"], "majors": ["business administration"], "languages": ["cantonese", "putonghua", "english", "chinese"], "language_level": ["excellent", "fluent"], "hard_skills": ["plus", "ms applications"], "soft_skills": ["communication skills", "self-motivated", "mature", "presentable"], "languages_combined": [{"language": "cantonese", "language_level": ["fluent"]}, {"language": "putonghua", "language_level": ["fluent"]}, {"language": "english", "language_level": ["excellent", "fluent"]}, {"language": "chinese", "language_level": ["excellent"]}]}, "experience_required": {"duration": ["minimum 5 years"], "field": ["relevant experience"]}}, {"job_id": "100003009043898", "location_code": "hk", "company": "Pan Lloyds Publishers Limited", "job_title": "Administration Assistant (Editorial)", "description": "Job Responsibilities:\n\nProvide secretarial & administrative support to Publishing Department\nMaintain effective internal document system\nAssist in daily operations including data input, report and other editing & clerical duties\u00a0\nSupport ad-hoc projects and assignments\nAny other works assigned\n\nJob Requirements:\n\nPost secondary education or above with administrative experience\u00a0\nProficiency in MS Office applications including Word, Excel, Powerpoint & Eng/Chi word processing\nGood command of both English and Chinese\u00a0\u00a0\nGood communication skills and well-organized\nAttention to details, responsible and self-motivated\n\nInterested parties please click\u00a0\"Apply Now\"\u00a0to submit your full resume stating present and expected salary.\n\nPersonal data provided by job applicants will be kept strictly confidential and will be used solely for employment related purposes. Only short-listed candidates will be contacted.\n\nYou are welcome to visit our website to know more about us:\u00a0\nhttp://www.popular.com.hk\u00a0/\u00a0\nhttp://pl.popularworldhk.com\u00a0/\nhttp://jp.popularworldhk.com\u00a0", "employment_types": ["Full Time", "Permanent"], "selling_points": ["Five-day work week, Medical & Dental insurance", "Bonus and staff purchase discount", "Administrative support to editorial team"], "locations": ["Tsuen Wan Area"], "categories": ["Admin & HR", "Clerical / Admin Staff", "Secretary", "Education", "Others"], "post_time": "2022-01-13T02:22:14Z", "salary": {"currency": null, "max": null, "min": null, "period": "monthly", "term": null}, "salary_visible": false, "title_keywords": ["administration assistant"], "responsibilities": ["ad-hoc projects", "administrative support", "data input", "daily operations", "maintain", "editing", "report"], "requirements": {"degrees": ["secondary education"], "majors": [], "languages": ["english", "chinese"], "language_level": ["good command"], "hard_skills": ["excel", "word", "powerpoint", "chi word processing", "ms office"], "soft_skills": ["communication skills", "self-motivated", "responsible", "well-organized", "attention to details"], "languages_combined": [{"language": "english", "language_level": ["good command"]}, {"language": "chinese", "language_level": ["good command"]}]}, "experience_required": {"duration": [], "field": ["administrative", "education"]}}, {"job_id": "100003009046800", "location_code": "hk", "company": "Rod and Staff Recruitment Group (Hong Kong) Limited", "job_title": "Executive Assistant / Office Manager", "description": "Our client, a leading global club, is currently on the lookout for a zestful Office Manager and Executive Assistant to provide administrative support to the group in its headquarters in Hong Kong. We are looking for a confident, trustworthy, detail-oriented individual to work with talented people in a small and dynamic corporate environment. This is a great opportunity for anyone who has a real interest in football.\u00a0\n\nOffice Manager / Executive Assistant\n\n\n\nSchedule and organize meetings and conference calls for office agenda\nReception duties: welcoming clients/visitors and determining access to appropriate parties\u00a0\nResponsible for handling accounts: processing invoices, payroll, budget & forecasting etc.\u00a0\nRecord office expenditure and managing budget: Coordinate finances, assist with budget preparation.\u00a0\nOrganising the office layout and maintaining supplies of stationery, equipment and pantry supplies\u00a0\nMaintaining the condition of the office and arranging for necessary repairs;\u00a0\nClose communication with HQ office on operations, accounts and technology related issues\nProvide secretarial and executive support to the MD\nResponsible for travel arrangements, meetings and conferences for MD and staff\n\nREQUIREMENTS\u00a0\n\n\nUniversity degree\n5 to 8 years\u2019 experience as an office manager and executive assistant within corporate office\u00a0\nHigh\u00a0proficiency in English, Cantonese and Mandarin, both spoken and written\n\nAn ability to multitask and handle documentation and reports with the highest level of confidentiality\nSelf-starter and able to work in a dynamic and team-oriented environment\nGreat interest and passion in sports", "employment_types": ["Full Time"], "selling_points": ["Global opportunity", "Energetic environment", "Competitive Perks"], "locations": ["Central"], "categories": ["Admin & HR", "Administration / Operation Manager", "Personal / Executive Assistant", "Secretary"], "post_time": "2022-01-14T01:13:03Z", "salary": {"currency": null, "max": null, "min": null, "period": "monthly", "term": null}, "salary_visible": false, "title_keywords": ["executive assistant", "office manager"], "responsibilities": ["forecasting", "travel arrangements", "documentation", "invoices", "maintaining", "operations", "budget", "stationery", "executive support", "coordinate", "communication", "conferences", "reports", "schedule", "provide administrative support", "payroll"], "requirements": {"degrees": ["university degree"], "majors": [], "languages": ["cantonese", "english", "mandarin"], "language_level": ["proficiency"], "hard_skills": ["small", "documentation", "dynamic", "processing"], "soft_skills": ["confident", "responsible", "trustworthy", "passion in", "detail-oriented", "communication", "dynamic", "ability to multitask"], "languages_combined": [{"language": "cantonese", "language_level": ["proficiency"]}, {"language": "english", "language_level": ["proficiency"]}, {"language": "mandarin", "language_level": ["proficiency"]}]}, "experience_required": {"duration": ["5 to 8 years"], "field": []}}, {"job_id": "100003009039357", "location_code": "hk", "company": "Easy Property Co Ltd", "job_title": "Executive Secretary to Director", "description": "Duties & Responsibilities:\n\nProviding secretarial support to the Managing Director\nOrganising the Managing Director\u2019s diary and making appointments\nArranging meetings and taking notes at meetings\nOrganising and maintaining office systems\nPerforming daily HR and administrative works\nAssisting in handling property management & related promotion works\nPerforming other tasks as assigned\n\nRequirements:\n\nForm 7 or above, with formal secretarial training or qualification in business administration is an advantage\nMinimum 5 years of executive or secretarial experience\nGood command of both written and spoken English and Chinese (including Putonghua)\nActive listening, and with excellent communication and interpersonal skills\nExcellent administrative and organisational skills\nStrong problem-solving and multitasking skills\nThe ability to prioritise tasks and remain calm under pressure\nKnowledge of general office procedures and organising an office\u2019s filing system\nProficient in relevant computer and software programs such as MS word, Excel, PowerPoint & Chinese word processing\n\n\n\nInterested parties please send your CV together with your expected salary and date of availability to the Human Resources and Administration Department by simply clicking the \"Apply Now\" button below\n\n\u00a0(Personal data collected would be used for recruitment purpose only.)\n\n\n", "employment_types": ["Full Time", "Permanent"], "selling_points": [], "locations": ["Tsim Sha Tsui"], "categories": ["Admin & HR", "Personal / Executive Assistant", "Secretary"], "post_time": "2022-01-11T16:01:50Z", "salary": {"currency": null, "max": null, "min": null, "period": "monthly", "term": null}, "salary_visible": false, "title_keywords": ["executive secretary", "director"], "responsibilities": ["management", "maintaining", "hr", "systems", "providing secretarial support", "other tasks"], "requirements": {"degrees": [], "majors": [], "languages": ["putonghua", "english", "chinese"], "language_level": ["good command", "proficient"], "hard_skills": ["excel", "chinese word processing", "problem-solving", "powerpoint", "ms word"], "soft_skills": ["under pressure", "problem-solving", "prioritise", "calm", "organisational skills", "communication and interpersonal skills", "active"], "languages_combined": [{"language": "putonghua", "language_level": ["good command"]}, {"language": "english", "language_level": ["good command"]}, {"language": "chinese", "language_level": ["good command", "proficient"]}]}, "experience_required": {"duration": ["minimum 5 years"], "field": ["secretarial"]}}]