[{"job_id": "100003009054902", "location_code": "hk", "company": "Cathay Pacific Services Limited", "job_title": "Training Officer", "description": "Responsibilities\nTo design, develop and conduct training programmes to ensure trainees obtain adequate skills and knowledge to provide quality services to the customers including but not restricted to classroom, on-site, systems-related or e-learning operational training;\nTo evaluate and review the training programmes to ensure training requirements and effectiveness are met;\nTo train the trainers appointed by both internal and external parties including operations contractors, Cargo Agents, and Government parties;\nTo maintain and update all training materials in line with the latest operating procedures and instructions;\nTo conduct assessment on the proficiency of trainees under probation as and when required;\nTo ensure training records of all trainees are complete and up-to-date;\nTo support Quality Control and conduct inspections for improving the operations quality;\nTo complete special projects and other requirements assigned by supervisor.\n\n\u00a0Requirement\n\nF.7 or tertiary education preferably in Logistics, Aviation Management, Training and Development or related discipline.\nMinimum 3 years of solid working experience in aviation industry, air cargo terminal, logistics company, warehouse or freight forwarding Company, of which minimum 2 years in providing staff training or performing supervisory duties;\nHands-on experience in the air-cargo terminal operations would be beneficial;\nDG license (Cat. 6) holder is preferable;\nKnowledge and experience in e-learning is an advantage;\nGood command of written and spoken English and Chinese;\nStrong planning, organising and analytical skills;\nGood interpersonal & communication skills with proactive, tactful & result-oriented personality;\nAble to work independently and under pressure;\nCandidate with more experience will be considered as Training Specialist\u00a0\nTo apply,\u00a0you may\u00a0email your confidential resume with date of availability, current and expected salary to\u00a0recruitment @cpsl.com.hk.\u00a0Applicants not contacted within 6 weeks may consider their applications unsuccessful.\nCathay Pacific Services Limited is an Equal Opportunities Employer. Personal data provided by job applicants will be used strictly in accordance with our personal data policy and for recruitment purposes only. Candidates not notified within six weeks may consider their application unsuccessful. All related information will be kept in our file for up to 24 months.", "employment_types": ["Full Time", "Permanent"], "selling_points": ["Design, develop and conduct training programmes", "Maintain and update all training materials", "Conduct assessment on the proficiency of trainees"], "locations": ["Airport Area"], "categories": ["Transportation & Logistics", "Aviation Services", "Admin & HR", "Training & Development"], "post_time": "2022-01-17T13:23:01Z", "salary": {"currency": null, "max": null, "min": null, "period": "monthly", "term": null}, "salary_visible": false, "title_keywords": ["officer"], "responsibilities": ["operations", "systems", "quality", "review", "design", "develop", "evaluate", "internal and external parties", "procedures", "maintain", "quality control"], "requirements": {"degrees": [], "majors": [], "languages": ["english", "chinese"], "language_level": ["good command"], "hard_skills": ["analytical skills"], "soft_skills": ["result-oriented", "communication skills", "work independently", "under pressure", "analytical skills", "hands-on", "learning", "proactive", "tactful", "interpersonal"], "languages_combined": [{"language": "english", "language_level": ["good command"]}, {"language": "chinese", "language_level": ["good command"]}]}, "experience_required": {"duration": ["minimum 2 years", "minimum 3 years"], "field": ["supervisory", "logistics", "training"]}}, {"job_id": "100003009053509", "location_code": "hk", "company": "Bape Hong Kong Limited", "job_title": "Training Manager", "description": "KEY RESPONSIBILITIES\n\n\n\nIdentify\u00a0training needs and develop training plans for frontline staff to help establish the values, spirit and culture of the company\nConduct and update various training programs to enhance technical competences, work knowledge and soft skills development\nTo plan and design training and operations manuals across all company brands, making sure all procedures are well documented and put into practice.\nOrganize Mystery Shopper Program to enhance the service standard\nDevelop and organize staff relations / team building projects\nMonitor and evaluate training effectiveness through effective field coaching and regular shop visits\nReview and maintain training database and consolidate training reports for management review\n\nREQUIREMENTS\n\n\n\nDegree holder with at least 6 - 7 years\u2019 solid experience in training and development preferably gained from fashion retail chains or hotel industries.\nProven track record in developing and conducting training programs for frontline staff, as well as shaping customer service culture\nExcellent presentation and interpersonal skills, able to communicate well with different levels of employees\nExcellent command of both written and spoken English and Chinese\nProficiency in Microsoft Office and Chinese Word Processing", "employment_types": ["Full Time", "Permanent"], "selling_points": ["With 6 - 7 years\u2019 solid experience in training", "To plan and design training and operations manuals", "Conduct and update various training programs"], "locations": ["Southern Area"], "categories": ["Admin & HR", "Others", "Training & Development"], "post_time": "2022-01-17T07:04:30Z", "salary": {"currency": null, "max": null, "min": null, "period": "monthly", "term": null}, "salary_visible": false, "title_keywords": ["manager"], "responsibilities": ["service standard", "operations", "review", "procedures", "monitor", "design", "develop", "evaluate", "maintain", "reports", "plan", "database", "plans", "management review"], "requirements": {"degrees": ["degree holder"], "majors": ["hotel"], "languages": ["english", "chinese"], "language_level": ["excellent", "proficiency"], "hard_skills": ["chinese word processing", "microsoft office"], "soft_skills": ["customer service", "interpersonal skills", "presentation"], "languages_combined": [{"language": "english", "language_level": ["excellent"]}, {"language": "chinese", "language_level": ["excellent", "proficiency"]}]}, "experience_required": {"duration": ["at least 6 - 7 years"], "field": ["development", "retail", "training"]}}, {"job_id": "100003009054273", "location_code": "hk", "company": "Descente China Investment Limited", "job_title": "Senior Training Officer", "description": "Responsibilities:\n\nReport to the Training Manager to identify training needs of store operations\u00a0for designing the annual training plan and delivering training to drive for business result.\nDesign and deliver in-house shop training programs for all frontline staff levels\u00a0to enhance and polish shop sales\u2019 skill, sales and product knowledge, and attitude covering Product, Service, Business, and drive the culture.\nMonitor the sales performance to ensure that the deliverables are aligned with the training goals.\u00a0\nProvide performance feedback on shop staff to facilitate on-going staff performance review.\nTo align with the headquarter to implement and executive the group training programs/on-line training modules into a local practice such as classroom training, shop visit, face to face demonstration and case sharing.\nConduct the sales orientation to all retail new hires.\nOrganize various projects / events to align with the headquarter and corporate brand building.\nHandle all training related logistics, materials preparation, training evaluation, updating related records & logistics for the team.\nMonitor the shop training budget and actual expense.\n\nRequirements:\n\nBachelor\u2019s Degree in Training & Development, Human Resources Management or related disciplines.\nMinimum 6 years of solid training delivery experience preferably in\u00a0retail, ladies fashion, sports industry. \u00a0\nGood understanding of retail operational details is an advantage.\nGood attitude, positive, energetic and proactive for problem-solving & detailed-minded\nStrong presentation and interpersonal skills.\nExcellent planning and organizing skills.\nProficient in using MS Office, Excel, Chinese Word Processing, preferably with knowledge in Video shooting/editing experience.\nGood command of both spoken and written English and Chinese (Cantonese and Putonghua).\nOccasional travel is required.", "employment_types": ["Full Time", "Permanent"], "selling_points": ["Retail Training", "Bachelor\u2019s Degree", "6 years\u2019 relevant working experience"], "locations": ["Kowloon Bay"], "categories": ["Admin & HR", "Training & Development", "Sales, CS & Business Devpt", "Others"], "post_time": "2022-01-17T09:00:19Z", "salary": {"currency": null, "max": null, "min": null, "period": "monthly", "term": null}, "salary_visible": false, "title_keywords": ["officer"], "responsibilities": ["evaluation", "operations", "sales performance", "review", "monitor", "budget", "design", "logistics", "plan", "designing", "report"], "requirements": {"degrees": ["degree", "bachelor"], "majors": ["related disciplines"], "languages": ["cantonese", "putonghua", "english", "chinese"], "language_level": ["good command", "proficient"], "hard_skills": ["excel", "problem-solving", "chinese word processing", "ms office"], "soft_skills": ["proactive", "problem-solving", "interpersonal skills", "energetic", "presentation", "positive", "detailed"], "languages_combined": [{"language": "cantonese", "language_level": ["good command"]}, {"language": "putonghua", "language_level": ["good command"]}, {"language": "english", "language_level": ["good command"]}, {"language": "chinese", "language_level": ["good command", "proficient"]}]}, "experience_required": {"duration": ["minimum 6 years"], "field": ["video shooting", "editing", "retail", "training"]}}, {"job_id": "100003009054655", "location_code": "hk", "company": "Chanel Hong Kong Limited", "job_title": "Retail Learning & Development Partner", "description": "We are looking for individuals with a strong passion for people development and belief in investing in personalized learning paths for employees! As our Learning and Development Partner, you will enable our Fashion Advisors to be the Front Face of Chanel by building their confidence and strengthening their ability to create an emotional connection with the clients to the brand\nYou will play the role of an active coach in engaging our Fashion Advisors by enhancing their learning and development to drive loyalty and sustaining the speed and depth of Chanel\u2019s business growth.\n\nLeveraging your unique experiences, Chanel will enable you to\u2026\n\n\u00a0Customize learning solutions and individualized coaching methods\n\u00a0Be the Fashion Advisors\u2019 trusted \u201cgo-to\u201d advisor in Learning and Development\n\u00a0Partner with Head of Boutique to strategize and develop a comprehensive people development plan\n\u00a0Onboard new hires in the boutique\n\u00a0Proactively provide new people intelligence or pulse of the retail teams to the leadership team\nYou are energized by\u2026\n\n\u00a0Bringing out the best of our Fashion Advisors\n\u00a0People development and coaching\n\u00a0Customizing and delivering training using blended learning approach\n\u00a0Having close observations of Fashion Advisors\u2019 interactions with clients and identifying areas of improvement\n\u00a0Creating a personalized developmental action plan\nWhat you can bring to the team\u2026\n\n\u00a0Least 3 years\u2019 work experience in a coaching or training role\n\u00a0Excellent interpersonal and coaching skills\n\u00a0Strong passion for people development and client service excellence\n\u00a0High energy level, ability to exercise assertiveness when required\n\u00a0Ability to work at the boutique and retail hours\n\n\nAt Chanel, we are focused on creating an inclusive culture that nurtures personal growth, contributing to collective progress. We believe the uniqueness of each individual increases the diversity, complementarity and effectiveness of our teams. We strongly encourage your application, as we value the perspective, experience and potential you could bring to CHANEL", "employment_types": ["Full Time", "Permanent"], "selling_points": ["Ultimate House of Luxury", "Learning and Development for Retail Frontline", "Dynamic working environment and culture"], "locations": ["Not Specified"], "categories": ["Admin & HR", "Training & Development"], "post_time": "2022-01-17T10:25:10Z", "salary": {"currency": null, "max": null, "min": null, "period": "monthly", "term": null}, "salary_visible": false, "title_keywords": [], "responsibilities": ["teams", "plan", "develop"], "requirements": {"degrees": [], "majors": [], "languages": [], "language_level": [], "hard_skills": ["go"], "soft_skills": ["confidence", "focused", "passion for", "unique", "learning", "comprehensive", "active", "leadership", "interpersonal"], "languages_combined": []}, "experience_required": {"duration": ["least 3 years"], "field": ["training"]}}, {"job_id": "100003009053846", "location_code": "hk", "company": "Konew Financial Express Limited \u5eb7\u696d\u4fe1\u8cb8\u5feb\u905e", "job_title": "Assistant Manager, Learning and Development", "description": "Main Duties & Responsibilities:\u00a0\n\nIdentify and analyze training needs and formulate training strategies to meet people development and business needs\nDesign and deliver training programs including classroom training and e-learning courses\nAdminister and support the whole training process in relation to course enrollment, attendance, evaluation records as well as relevant coordination duties\nReview course evaluation for further enhancement or improvement\nPrepare regular reports on training activities\nSource and liaise with external training institutes, consultants or vendors\nRequirements:\n\nBachelor Degree in\u202fHuman Resources, Business Management\u202for related disciplines\nMinimum 6 years\u2019 solid experience in developing new training programs and delivering soft skills programs\nExperienced in delivering video sales related training would be added advantage\nTrainer background is highly preferred\nGood presentation, communications, and interpersonal skills\nStrong\u202fself-motivation, able to work independently under pressure and tight deadline\u202f\nExcellent command of spoken and written\u00a0English and\u00a0Chinese\nProficiency in MS Office\n\nWe offer:\n\nDiscretionary bonus\nMedical insurance\nDental insurance\nHardship allowance\nCompetitive annual leave days\nBirthday leave\nAnniversary leave\nStudy leave\nMarriage leave\nCompassionate leave\n\nHow to apply:\n\nInterested parties, please send your resume stating your expected salary to Human Capital Department\u00a0by clicking \"APPLY NOW\".\n\n(We are an equal opportunity employer.\u00a0 Personal data collected will be used for recruitment purpose only.\u00a0 The unsuccessful applications will be destroyed after 6 months.)\u00a0", "employment_types": ["Full Time", "Permanent"], "selling_points": ["Design and deliver training programs", "Administer and support the whole training process", "5 days work, birthday leave, anniversary leave"], "locations": ["Central"], "categories": ["Education", "Tutor / Instructor", "Admin & HR", "HR Supporting Staff", "Training & Development"], "post_time": "2022-01-17T07:37:01Z", "salary": {"currency": null, "max": null, "min": null, "period": "monthly", "term": null}, "salary_visible": false, "title_keywords": ["assistant manager,"], "responsibilities": ["attendance", "enrollment", "training activities", "review", "design", "reports", "coordination", "evaluation", "liaise with"], "requirements": {"degrees": ["degree", "bachelor"], "majors": ["related disciplines", "business"], "languages": ["english", "chinese"], "language_level": ["excellent"], "hard_skills": ["business management", "ms office"], "soft_skills": ["work independently", "under pressure", "self-motivation", "interpersonal skills", "presentation"], "languages_combined": [{"language": "english", "language_level": ["excellent"]}, {"language": "chinese", "language_level": ["excellent"]}]}, "experience_required": {"duration": ["minimum 6 years"], "field": ["training", "developing"]}}, {"job_id": "100003009054168", "location_code": "hk", "company": "ImagineX Management Co Ltd", "job_title": "Learning & Development Assistant / Officer", "description": "Are you a passionate and yet creative talent who can think out of the box to driving the people agenda with a new approach?\n\nImagineX Group is a premier retail, brand management and distribution company. We build luxury, designer and premium contemporary fashion, beauty and lifestyle businesses with an entrepreneurial approach and the passion and flair of a brand owner.\nWe are now inviting a creative, self-motivated, energetic and talented\u00a0Learning and Development Assistant / Officer to join us.\n\n\n\nWHAT YOU WILL BE DOING?\n\n\nDesign, deliver and evaluate learning effectiveness for various kinds of retail training programs for different retail brands\nCommunicate closely with internal and external stakeholders to understand brands' training needs and develop suitable training programs\nManage service and sales enhancement projects such as mystery shopper program\nCompile monthly training reports for management review\nSupport staff communications activities when necessary\n\nYOU NEED TO BE\u2026\n\n\nDegree holder in any relevant disciplines\nAt least 1 year of learning and development experience in service or retail business. Exposure to fashion and beauty is highly preferred.\nPleasant, mature and positive with a \u201ccan-do\u201d mindset\nAbility to organize and prioritize tasks systematically in a fast-pace environment\nExcellent presentation & interpersonal skills\nGood written and verbal language skills in Chinese and English\nCandidates with more experiences may consider as Learning and Development Officer\nWE OFFER YOU\u2026\nUp to 16 days annual leave\nPublic holidays\nBirthday leave\n5-day marriage leave\nDental care\nMedical insurance\nProfessional retail training\nAnnual discretionary bonus\nStaff purchase discount\nMonthly\u00a0MPF contribution up to 10% of salary", "employment_types": ["Full Time", "Permanent"], "selling_points": ["Training and Development", "Identify training needs for business units", "Minimum 1 year relevant experience"], "locations": ["Southern Area"], "categories": ["Admin & HR", "Training & Development"], "post_time": "2022-01-17T08:39:24Z", "salary": {"currency": null, "max": null, "min": null, "period": "monthly", "term": null}, "salary_visible": false, "title_keywords": ["officer", "assistant"], "responsibilities": ["management", "design", "develop", "evaluate", "reports", "enhancement projects", "management review"], "requirements": {"degrees": ["degree holder"], "majors": [], "languages": ["english", "chinese"], "language_level": ["good"], "hard_skills": [], "soft_skills": ["passionate", "self-motivated", "mature", "pleasant", "prioritize", "energetic", "learning", "interpersonal skills", "can-do", "creative", "presentation", "positive"], "languages_combined": [{"language": "english", "language_level": ["good"]}, {"language": "chinese", "language_level": ["good"]}]}, "experience_required": {"duration": ["at least 1 year"], "field": ["business", "development", "retail"]}}, {"job_id": "100003009054604", "location_code": "hk", "company": "Pure Search International Limited", "job_title": "Learning & Development (Assistant Manager/ Manager)", "description": "Our client is looking for a experienced L&D professional in Hong Kong to manage full function of training, employee engagement and communication. The organization has a global headcount of over 15,000.\n\nYou will partner closely with department heads and HR counterparts in driving a learning culture and in identifying training gaps and needs, and be responsible for the design, launch and implementation of the group wide training and development programs. You will be leading evaluation of existing training programs, recommending and driving modification/change to meet business challenges.\u00a0You will also launch digital training programs.\n\nYou will also be tracking and analysing training effectiveness; as well as measuring\u00a0the impact of training programs against business results.\u00a0\n\nRequirements:\n\nBachelor\u2019s Degree with a minimum of 10 years of training and development experience.\n\nAll-rounded and broad training and development experience ideally sizeable multinational companies.\u00a0\n\nStrong communication and presentation skills is important and someone with strong ability to build rapport across all levels will be ideal. You will also be able to manage priorities and execute multiple projects to cope with the business timelines.\n\nFluency in both English and Chinese (including Mandarin) and experience in working with senior business leaders is paramount.\n\nGood facilitation and training skills, and strong project management skills.", "employment_types": ["Full Time"], "selling_points": ["Strategic Learning & Development role", "Great exposure at Group/Corporate level", "Competitive package with attractive benefits"], "locations": ["Others"], "categories": ["Admin & HR", "Training & Development"], "post_time": "2022-01-17T10:13:22Z", "salary": {"currency": null, "max": null, "min": null, "period": "monthly", "term": null}, "salary_visible": false, "title_keywords": ["assistant manager", "manager"], "responsibilities": ["development programs", "hr", "implementation", "design", "communication", "project management", "evaluation", "multiple projects", "tracking"], "requirements": {"degrees": ["degree", "bachelor"], "majors": [], "languages": ["english", "chinese", "mandarin"], "language_level": ["fluency"], "hard_skills": ["project management"], "soft_skills": ["responsible", "project management skills", "communication", "presentation skills", "learning", "ideal"], "languages_combined": [{"language": "english", "language_level": ["fluency"]}, {"language": "chinese", "language_level": ["fluency"]}, {"language": "mandarin", "language_level": []}]}, "experience_required": {"duration": ["minimum of 10 years"], "field": ["development", "business", "training"]}}, {"job_id": "100003009054044", "location_code": "hk", "company": "Hermes Asia Pacific Limited", "job_title": "HR Intern (Training Focus)", "description": "Position Overview\n\nReporting to the Retail Training Manager, the HR Intern is responsible for a full spectrum support for training and development functions.\n\n\nResponsibilities:\nTo provide full spectrum of training administrative support including but not limited to filing, updating training data, venue booking and set up, etc\nProvide logistic support on training programs\nAssist in preparing classroom training & e-learning materials\nAssist to prepare training statistics and report in regular basis\nAssist in coordinating internal staff activities/ events\n\nRequirements:\n\nYear 2 / 3 of University student in Business Management or related disciplines\nPassion in French culture / art / luxury retail is a plus\nExcellent in communication skills with good command in English and Chinese\nProactive and eager to take up new challenges\nConscientious and detail-minded\nPleasant personality and a team player\nAbility to work in a fast-paced environment and adapt to changes quickly\nBasic computer knowledge\nAble to work on flexible schedule\n\nInterested parties, please send your resume with expected salary and date of availability to:\u00a0recruitment.hap.hk@ hermes.com\u00a0or by clicking\u00a0\"Apply Now\"\n\n(Data collected will be treated in strict confidence and used for recruitment purpose only.)", "employment_types": ["Internship"], "selling_points": ["Pleasant personality and a team player", "Conscientious and detail-minded", "Excellent in communication skills"], "locations": ["Causeway Bay"], "categories": ["Admin & HR", "HR Supporting Staff", "Training & Development"], "post_time": "2022-01-17T08:11:21Z", "salary": {"currency": null, "max": null, "min": null, "period": "monthly", "term": null}, "salary_visible": false, "title_keywords": ["hr intern"], "responsibilities": ["data", "administrative support", "logistic support", "booking", "report"], "requirements": {"degrees": [], "majors": [], "languages": ["english", "french", "chinese"], "language_level": ["excellent", "good command"], "hard_skills": ["business management", "plus", "basic"], "soft_skills": ["detail-minded", "communication skills", "flexible", "passion in", "fast-paced environment", "pleasant", "conscientious", "team player", "proactive"], "languages_combined": [{"language": "english", "language_level": ["excellent", "good command"]}, {"language": "french", "language_level": []}, {"language": "chinese", "language_level": ["excellent", "good command"]}]}, "experience_required": {"duration": [], "field": []}}, {"job_id": "100003009051570", "location_code": "hk", "company": "A.S. Watson Industries", "job_title": "Assistant Organization & Talent Development Manager", "description": "Manage the Organizational and People Development in driving organizational effectiveness and in attracting, developing, motivating and retaining the right people, delivering satisfactory internal customer services, as well as facilitating the Corporate Culture to build high performance teams for the Company\nAssist in all development, execution and implementation of Leadership Pipeline to ensure a continuous supply of talent for business ongoing expansion\nOversee and manage Management Trainee Program\nIdentify learning and development needs of business units to cope with organizational changes\nWork with business units to design learning programs that enable the accomplishment of business objectives\nDesign the learning curriculum and monitor training budgets\nEvaluate the learning effectiveness and ensure the needs have been successfully met\nSource and evaluate external consultants to provide suitable learning programs\nDevelop training tools/e-learning with different format such as video editing, interactive e-learning production, etc.\nJob Requirements\n\nDegree holder in Human Resources Management or other related disciplines\nAt least 8 years relevant solid working experience in organizational development or people development\nExperience in sizeable manufacturing or FMCG companies would be an advantage\nStrong passion in organization and talent development\nStrong project management skills with a focus on detailed execution\nEnergetic, well-organized, detail-minded, strong sense of responsibility, able to work independently & multi-task\nGood communication, presentation and interpersonal skill\nGood command of written and spoken English, Chinese and Mandarin\nPC knowledge in MS Excel, Word & PowerPoint and Chinese Processing\n\nWe offer competitive salary\u00a0discretionary performance bonus, medical and retirement benefits, free company coach services and excellent career prospects. Please your resume together with salary expectation via APPLY NOW.\n\nFor more information, please visit our website at\u00a0www.aswatson.com\u00a0\u00a0\n\nWe are an equal opportunity employer. The information provided will be treated in strict confidence and only be used for consideration of application for similar posts within the A.S. Watson Group of Companies.\n\nApplicants not hearing from us within 6 weeks from the date of advertisement may consider their application unsuccessful.\u00a0 All personal data of unsuccessful applicants will be destroyed within 12 months.\n\nAll information collected is for recruitment purpose only.", "employment_types": ["Full Time", "Permanent"], "selling_points": ["Organizational Development", "Learning & Development", "8 years relevant solid working experience"], "locations": ["Tai Po Area"], "categories": ["Admin & HR", "Others", "HR Supporting Staff", "Training & Development"], "post_time": "2022-01-16T11:05:41Z", "salary": {"currency": null, "max": null, "min": null, "period": "monthly", "term": null}, "salary_visible": false, "title_keywords": ["manager", "assistant"], "responsibilities": ["budgets", "management", "teams", "implementation", "developing", "customer services", "design", "monitor", "evaluate", "develop", "video editing", "project management", "communication", "website", "recruitment", "personal data"], "requirements": {"degrees": ["degree holder"], "majors": ["related disciplines"], "languages": ["english", "chinese", "mandarin"], "language_level": ["good command"], "hard_skills": ["word", "powerpoint", "video editing", "project management", "ms excel", "pc knowledge", "focus", "processing"], "soft_skills": ["detail-minded", "work independently", "confidence", "multi-task", "passion in", "sense of responsibility", "organizational", "project management skills", "well-organized", "interpersonal skill", "communication", "learning", "focus", "energetic", "leadership", "presentation", "detailed"], "languages_combined": [{"language": "english", "language_level": ["good command"]}, {"language": "chinese", "language_level": ["good command"]}, {"language": "mandarin", "language_level": ["good command"]}]}, "experience_required": {"duration": ["at least 8 years"], "field": ["development", "manufacturing", "fmcg"]}}, {"job_id": "100003009051793", "location_code": "hk", "company": "Compass Group Hong Kong Ltd", "job_title": "Training Manager", "description": "Job Responsibilities\n\nResponsible for handling full spectrum of Training & Development functions.\nIdentify Company\u2019s training needs in alignment with Company\u2019s business goal and legal requirements. Formulate training strategies and budgets.\nLaunch APAC training program.\nDeliver in-house training classes to various levels of staff.\nDevelop and review training materials for training sessions.\nSource and liaise with training institutes/ vendors for external training when necessary\nAdminister the e-learning platform including communications to learners, course content update and upload, tracking of learners\u2019 progress, etc.\nContinuously review and evaluate the effectiveness of training and development programs and make recommendations for enhancement.\nWork closely with different internal departments for coordination of training issues.\nAssist in ad hoc project/ tasks as required.\n\nRequirements\n\nDegree or above in Human Resources Management, BBA\u00a0or other related disciplines\nMin. 5 years of solid training and development experience. Experience in F&B or retail industry is absolutely an advantage\nCandidate with less experience will be considered as Assistant Training Manager\nPossesses exceptional communication and presentation skills\u00a0\nExcellent command of both written and spoken Chinese and English is a must\nHands on\u00a0PC skills\n\nWe offer good career prospects with competitive salary and fringe benefits to the right candidate.\n\nYou can apply with your resume including your current and expected salary by clicking \"APPLY NOW\" button.\u00a0We are an equal opportunity employer and welcome applications from all qualified candidates.\n\nTo find out more about us, you are welcome to visit our website:\u00a0www.compass-hk.com\n\nAll applications received will be used exclusively for recruitment purposes only. Applicants who are not contacted within 8 weeks should consider their application unsuccessful.", "employment_types": ["Full Time", "Permanent"], "selling_points": ["Full spectrum of Training & Development functions", "Degree in HR or related field, 5 yrs' rel. exp.", "F&B Industry"], "locations": ["Mong Kok"], "categories": ["Admin & HR", "Others", "HR Director / Manager", "Training & Development"], "post_time": "2022-01-17T01:12:38Z", "salary": {"currency": null, "max": null, "min": null, "period": "monthly", "term": null}, "salary_visible": false, "title_keywords": ["manager"], "responsibilities": ["make recommendations", "budgets", "ad hoc", "development programs", "review", "develop", "evaluate", "coordination", "liaise with", "tracking"], "requirements": {"degrees": ["degree or above"], "majors": ["related disciplines", "bba"], "languages": ["english", "chinese"], "language_level": ["excellent"], "hard_skills": ["pc skills"], "soft_skills": ["communication", "presentation skills", "hands on"], "languages_combined": [{"language": "english", "language_level": ["excellent"]}, {"language": "chinese", "language_level": ["excellent"]}]}, "experience_required": {"duration": ["5 years"], "field": ["retail industry", "development", "f&b", "training"]}}, {"job_id": "100003009054834", "location_code": "hk", "company": "KPMG", "job_title": "Administrator, Organisation & Talent Development (OTD)", "description": "About the role\n\nThe main role of this position is to enable the successful execution and delivery of talent and performance solutions.\u00a0 This role will be responsible for the planning, implementation and data analytics of talent and performance solution projects, including setting-up and producing workshops both physically and virtually, following up on post-solution user interactions and reporting. \u00a0With good performance and potential, this role could be developed to become future project owner or learning facilitator in due\u00a0 course.\n\nResponsibilities\n\nSupport project owners in the project management and execution of solutions.\nCreate effective programme communications and manage registration process\nExecute multiple projects and deliver high quality services on time and within budget of all resources including monetary, time, human resources\nApply innovative techniques in suggesting and implementing process improvements to processes and procedures\nMaintain collaborative relationships across different teams and build internal networks\n\nCompetencies and requirements\n\nBachelor\u2019s degree in psychology, human resources, organisational development or related field\nStrong project management and project execution skills, including work planning, reporting, risk and issue resolution, budget management, etc.\nStrong communication skills, including written and verbal English and Mandarin\nStrong data & analytics skills\n\nWe offer successful candidates an attractive remuneration package and the opportunity to work in a dynamic and exciting environment.\n\nPersonal data collected will be used for recruitment purposes only.", "employment_types": ["Full Time"], "selling_points": ["Talent and Performance Solution", "Data & Analytics Skills", "Client Service Orientation"], "locations": ["Southern Area"], "categories": ["Admin & HR", "Clerical / Admin Staff", "Others", "Training & Development"], "post_time": "2022-01-17T11:29:05Z", "salary": {"currency": null, "max": null, "min": null, "period": "monthly", "term": null}, "salary_visible": false, "title_keywords": ["administrator"], "responsibilities": ["budget", "quality", "procedures", "teams", "project management", "maintain", "multiple projects"], "requirements": {"degrees": ["degree", "bachelor"], "majors": ["psychology"], "languages": ["english", "mandarin"], "language_level": [], "hard_skills": ["project management", "budget management"], "soft_skills": ["communication skills", "project management"], "languages_combined": [{"language": "english", "language_level": []}, {"language": "mandarin", "language_level": []}]}, "experience_required": {"duration": [], "field": []}}, {"job_id": "100003009044912", "location_code": "hk", "company": "Harbour City Estates Ltd", "job_title": "TRAINING SPECIALIST", "description": "Responsibilities:\n\n\n\nAssist manager in developing and implementing various training initiatives to enhance the service standard\nResponsible for developing, organizing, and delivering training programs to frontline staff, including the Mystery Shopper Program\nEvaluate the training effectiveness and conduct follow-up activities\nDesign and develop e-learning programs\nProvide administrative support on training\n\nRequirements:\n\nUniversity graduate with minimum 3 years\u2019 training experiences, preferably gained from property management or hospitality industries\nFamiliarize with Articulate 360 storyline is an added advantage\nStrong knowledge in customer service and leadership training\nGood presentation and facilitation skills\nGood command in both written and spoken English and Chinese, proficiency in Putonghua is highly preferable\nBe a team player with good interpersonal and project management skills\nOccasional travel to Mainland China will be required\n\nWe offer competitive remuneration package that commensurate with experience and qualifications. Interested parties are invited to send full resume stating contact telephone number, date available, present and expected salary to our recruitment email address.\n\n(Personal data provided will be used strictly in accordance with the Company's personal data policy which is available upon request.)", "employment_types": ["Full Time", "Permanent"], "selling_points": ["University graduate with 3 years\u2019 experiences", "Familiarize with Articulate 360 storyline", "Strong knowledge in customer service"], "locations": ["Tsim Sha Tsui"], "categories": ["Admin & HR", "Training & Development", "Property / Real Estate", "Property Management"], "post_time": "2022-01-15T03:49:23Z", "salary": {"currency": null, "max": null, "min": null, "period": null, "term": null}, "salary_visible": false, "title_keywords": ["specialist"], "responsibilities": ["service standard", "design and develop", "developing", "evaluate", "provide administrative support"], "requirements": {"degrees": ["university graduate"], "majors": ["hospitality"], "languages": ["putonghua", "english", "chinese"], "language_level": ["proficiency", "good command"], "hard_skills": ["project management"], "soft_skills": ["project management skills", "customer service", "articulate", "team player", "interpersonal", "leadership", "presentation"], "languages_combined": [{"language": "putonghua", "language_level": ["proficiency", "good command"]}, {"language": "english", "language_level": ["good command"]}, {"language": "chinese", "language_level": ["good command"]}]}, "experience_required": {"duration": ["minimum 3 years"], "field": ["hospitality industries", "management", "training"]}}, {"job_id": "100003009052951", "location_code": "hk", "company": "Cathay Pacific Airways Ltd", "job_title": "Assistant Learning Manager - Airport & Cargo Operations", "description": "Reports to:\u00a0Learning Manager \u2013 Airport & Cargo\nDepartment: The Learning Academy (TLA)\n\nRole Introduction\nThe person is responsible for managing the delivery of learning modules / programmes for Airport, Cargo and Freighter Operations. Lead, enable and support a team of training professionals to ensure ramp (passenger aircraft and freighter), baggage, cargo operations staff have the required knowledge, skills and attributes to be safe, operationally competent, service minded and regulatory compliant. The job holder is to manage course content development, updates and evaluations as well as daily operations of the courses.\n\nKey Responsibilities\n\nManage the deployment and delivery of regulatory, functional, system and service learning modules / programmes for airport, cargo and freighter operations\nManage the course training delivery team, including performance reviews and development of trainers (including outport GHA trainers)\nBe responsible for course content development, updates and evaluations\nManage the daily operations of courses, including ensuring compliance to policies, procedures and processes\nPlan and facilitate formal and informal, social and collaborative learning development strategies that are in support of operational and service excellence\nSupport training projects, cutovers and be a part of the training delivery team to deliver training (10-20%)\n\nRequirements\n\nAt least 5 years airport ramp or cargo / freighter operations experience in the airline industry\nProven Supervisory track record with team leadership experience. 3 years minimum experience required\nIn-depth subject matter knowledge in either airport operations (passenger aircraft ramp handling), cargo operations (freighter ramp handling) or cargo services (dangerous goods handling and regulations, tariff, warehouse & ramp operations)\nRole model of customer service and operational excellence\nStrong personal presence and verbal / non-verbal communication skills\nExcellent verbal and written communication skills in English\nFlexible and adaptable\nStrong planning and organising skills\nSound project management skills with sound analytical skills\nFacilitation skills to deliver learning sessions\nGreat team lead and ability to manage trainers\nEmbrace learning technology and be a passionate learner\nWillingness to travel extensively\n\n\n\nApplication Deadline:\u00a031 January 2022\n\nPersonal & Application Information\nCathay Pacific is an Equal Opportunities Employer. Personal data provided by job applicants will be used strictly in accordance with our personal data policy and for recruitment purposes only. Candidates not notified within eight weeks may consider their application unsuccessful. All related information will be kept in our file for up to 24 months. A copy of our Personal Information Collection Statement will be provided upon request by contacting our Data Protection Officer.\n\nPlease note that with effect from 1 December 2021, all employees must be vaccinated in order to access Cathay City and all other Cathay Group Company premises in Hong Kong. Consideration will be given to those who are unable to get vaccinated for valid medical reasons.", "employment_types": ["Full Time", "Permanent"], "selling_points": ["5 years airport ramp / cargo operations experience", "In-depth knowledge in airport / cargo operations", "Travel Benefits, 5-day work, Medical Benefits"], "locations": ["Lantau Island"], "categories": ["Transportation & Logistics", "Aviation Services", "Admin & HR", "Training & Development"], "post_time": "2022-01-17T05:07:41Z", "salary": {"currency": null, "max": null, "min": null, "period": "monthly", "term": null}, "salary_visible": false, "title_keywords": ["operations", "manager", "assistant"], "responsibilities": ["operations", "policies", "compliance", "procedures", "daily operations", "plan"], "requirements": {"degrees": [], "majors": [], "languages": ["english"], "language_level": ["excellent"], "hard_skills": ["project management", "airline", "aircraft", "analytical skills"], "soft_skills": ["flexible", "communication skills", "passionate", "adaptable", "project management skills", "analytical skills", "customer service", "learning", "leadership"], "languages_combined": [{"language": "english", "language_level": ["excellent"]}]}, "experience_required": {"duration": ["3 years", "at least 5 years"], "field": ["supervisory", "team"]}}, {"job_id": "100003009051901", "location_code": "hk", "company": "Senior Citizen Home Safety Association", "job_title": "Assistant Manager, Workshop & Training", "description": "Responsibilities:\n\nSupervise a small team\nDevelop and arrange different in-house training programs/workshops for our users and external participants in according to their needs\nLiaise with various stakeholders, such as private or public companies, schools, tutors, and vendors\nManage active aging services and carer support services, reach out target service recipients in the community through diversified trainings and programs\nPrepare reports, budget, operation plans and analysis for services development\n\nQualifications:\n\nMore than 5yrs experience with at least 2 years in supervisory level\nHigher Diploma / Associate degree holder or above in Social Work or related disciplines\nConduct training experience and/or with medical background is in advantage\nPrevious working experience in NGO setting is an asset but not a must\nWell organized, active, good interpersonal skills and manner\nGood command of written & spoken English and Chinese\n\nInterested parties please send your full CV with expected salary, date available and contact number via clicking \"Apply Now\"\u00a0(please state the position applied)\n\nInformation provided will only be used for the purpose of recruitment and selection within the Association and treated in strictly confidential. Only short-listed candidates will be contacted.", "employment_types": ["Full Time", "Permanent"], "selling_points": [], "locations": ["Kowloon City Area"], "categories": ["Admin & HR", "Training & Development", "Public / Civil", "Social Services - Community / Non-profit Organization", "Others"], "post_time": "2022-01-17T01:28:54Z", "salary": {"currency": null, "max": null, "min": null, "period": "monthly", "term": null}, "salary_visible": false, "title_keywords": ["assistant manager,"], "responsibilities": ["prepare reports", "analysis", "support services", "budget", "develop", "liaise with", "plans"], "requirements": {"degrees": ["associate degree", "diploma"], "majors": ["social work", "related disciplines"], "languages": ["english", "chinese"], "language_level": ["good command"], "hard_skills": ["small", "workshops", "analysis"], "soft_skills": ["active", "well organized", "interpersonal skills"], "languages_combined": [{"language": "english", "language_level": ["good command"]}, {"language": "chinese", "language_level": ["good command"]}]}, "experience_required": {"duration": ["at least 2 years"], "field": ["supervisory level", "training", "medical"]}}, {"job_id": "100003009047768", "location_code": "hk", "company": "Public Bank (Hong Kong) Limited", "job_title": "Senior/ Training & Development Officer (Ref: JD-TO)", "description": "Coordinate internal and external training and development activities of the Bank\nDevelop, design and deliver training programs to staff\nAdminister training subsidies, incentive programs and accurate staff training records\nPossess banking knowledge and solid experience in retail banking operations\nExperience in CPD / CPT reporting and administration\nDiploma holder or above with minimum 2 years of relevant experience in banking industry\nStrong interpersonal skill and self-motivated\nHands-on experience of MS office applications\nProficiency in spoken and written English and Chinese\n\nTo apply, interested parties please follow the application methods available in the Bank\u2019s career website https://www.publicbank.com.hk/en/aboutus/careeropportunities. You can send us your resume quoting our job reference number together with present & expected salary (a must) to the Human Resources Department by email or fax at 2815 3157 or by post to Human Resources Department, 12/F, Public Bank Centre, 120 Des Voeux Road Central, Hong Kong. You may also visit our career website for other career opportunities available within our Group.\n\nPersonal data collected will be used for recruitment purpose only and will be treated in accordance with the Bank\u2019s Personal Information Collection Statement, a copy of which has been available in the Bank\u2019s career website.", "employment_types": ["Full Time", "Permanent"], "selling_points": [], "locations": ["Not Specified"], "categories": ["Banking / Finance", "Others", "Admin & HR", "HR Supporting Staff", "Training & Development"], "post_time": "2022-01-15T03:49:06Z", "salary": {"currency": null, "max": null, "min": null, "period": null, "term": null}, "salary_visible": false, "title_keywords": ["officer"], "responsibilities": ["reporting", "operations", "design", "develop", "coordinate", "banking", "administration"], "requirements": {"degrees": ["diploma holder"], "majors": [], "languages": ["english", "chinese"], "language_level": ["proficiency"], "hard_skills": ["ms office"], "soft_skills": ["self-motivated", "accurate", "hands-on", "interpersonal skill"], "languages_combined": [{"language": "english", "language_level": ["proficiency"]}, {"language": "chinese", "language_level": ["proficiency"]}]}, "experience_required": {"duration": ["minimum 2 years"], "field": ["banking industry", "retail banking", "relevant experience", "banking", "administration"]}}, {"job_id": "100003009048629", "location_code": "hk", "company": "Unicorn Stores (HK) Limited", "job_title": "Learning & Development Manager", "description": "Job Descriptions\n\nPartner with department heads and senior management in analyzing training needs\nDesign and implement learning and development programs for frontline staff, including training materials and facilitator guides\nLead the mystery shopper program in retail stores\nConduct training to develop staff\u2019s soft skills, technical skills, coaching skills, management skills, etc.\nDevelop and design KPIs for learning and development program and monitor staff\u2019s learning effectiveness\nWork with the management team to create succession planning to ensure the sustainability of the organization\nLess experience candidate will be considered as Assistant Manager\n\nRequirements and Qualifications\n\nUniversity graduates with 5+ years of Learning and Development or Talent Management related experience\nExperience in FMCG / Supermarket / Retail Industry is highly preferred\nExcellent command of both written and spoken Cantonese, English, and Mandarin\nMature, independent at work with high learning agility\nImmediate availability is highly preferred", "employment_types": ["Full Time", "Permanent"], "selling_points": ["FMCG / Supermarket Industry", "Double Pay, Discretionary Bonus", "Immediate availability is preferred"], "locations": ["Tai Koo"], "categories": ["Admin & HR", "Training & Development"], "post_time": "2022-01-14T06:55:26Z", "salary": {"currency": null, "max": null, "min": null, "period": "monthly", "term": null}, "salary_visible": false, "title_keywords": ["manager"], "responsibilities": ["management team", "management", "development programs", "monitor", "design", "develop", "kpis", "senior management", "planning"], "requirements": {"degrees": [], "majors": [], "languages": ["cantonese", "english", "mandarin"], "language_level": ["excellent"], "hard_skills": [], "soft_skills": ["learning", "independent", "mature"], "languages_combined": [{"language": "cantonese", "language_level": ["excellent"]}, {"language": "english", "language_level": ["excellent"]}, {"language": "mandarin", "language_level": ["excellent"]}]}, "experience_required": {"duration": ["5+ years"], "field": ["retail industry", "management", "fmcg", "related", "development"]}}, {"job_id": "100003009047674", "location_code": "hk", "company": "Forsters & Company", "job_title": "Senior Training Specialist", "description": "Requirements\n\nBachelor Degree in HR Studies, Training or related disciplines\n6-7 years working experience in managing corporate training programs\nExperience in training program development, preferably in multinational company\nSolid experience in delivery of customer service skills and soft skills programs\nPrior exposure in developing e-Learning programs would be a great advantage\nDetail-oriented, energetic, self-initiative with good influencing and interpersonal skills\nProficient in using MS Office including Word, Excel, PowerPoint and HR system\nGood communication of English and conversational Putonghua\nImmediate available would be an advantage\n\nResponsibilities\n\nIdentify training needs and design training development programs to meet business goals\nResponsible for developing training plans and delivery customer service and soft skills programs\nProvide support on the development of e-Learning programs and preparing training calendar\nCoordinate with external consultants and overseas offices on the selection of training programs\nHandle learning materials development, schedule arrangement and record maintenance\nEvaluate the effectiveness of training programs and perform ad hoc projects as assigned\n\nWe offer attractive remuneration package and promising career prospect to the right candidates. Interested parties please send full resume with expected/last salary and date of available by clicking \u2018Apply Now\u2019", "employment_types": ["Full Time", "Permanent"], "selling_points": [], "locations": ["Not Specified"], "categories": ["Admin & HR", "HR Director / Manager", "HR Supporting Staff", "Training & Development"], "post_time": "2022-01-15T01:55:18Z", "salary": {"currency": null, "max": null, "min": null, "period": "monthly", "term": null}, "salary_visible": false, "title_keywords": ["specialist"], "responsibilities": ["business goals", "provide support", "development programs", "maintenance", "coordinate with", "developing", "design", "evaluate", "customer service", "ad hoc projects", "schedule", "plans"], "requirements": {"degrees": ["degree", "bachelor"], "majors": ["related disciplines"], "languages": ["putonghua", "english"], "language_level": ["conversational", "good"], "hard_skills": ["excel", "word", "powerpoint", "ms office"], "soft_skills": ["customer service skills", "detail-oriented", "communication", "learning", "self-initiative", "interpersonal skills", "energetic"], "languages_combined": [{"language": "putonghua", "language_level": ["good"]}, {"language": "english", "language_level": ["conversational", "good"]}]}, "experience_required": {"duration": ["6-7 years"], "field": ["development", "customer service", "multinational company", "training"]}}, {"job_id": "100003009054872", "location_code": "hk", "company": "Nu Skin Enterprises Hong Kong, LLC", "job_title": "HR Officer / Senior HR Officer (HR Generalist)", "description": "Your Responsibilities:\n\nAct as a Business Partner to work closely with internal stakeholders in providing full spectrum of HR services including but not limited to talent acquisition, staff development, staff engagement, and etc.\nExplore sourcing network to build a robust talent pipeline, manage all talent sourcing activities including but not limited to sourcing, screening, interviewing, stakeholder engagement and offering.\nParticipate in identifying training needs to foster a supportive learning culture.\nParticipate in coordinating related staff events to enhance employee morale and maintain their awareness of company core value and engagement.\nParticipate in ad-hoc HR projects and new initiatives as assigned.\n\nOur Requirements:\n\nBachelor degree holder in Human Resources Management or any related qualification.\n3-4 years of relevant experience in Human Resources. Experience in recruitment agent will be an advantage.\nWell-versed in Employment Ordinance and other HR related regulations in Hong Kong.\nFlexible, proactive and detail-minded with strong communication skill.\nStrong sense of responsibilities and able to work independently and be a good team player.\nPerformance driven with can-do attitude and able to work under pressure.\nProficiency in both written and spoken English and Chinese. Putonghua is an advantage.;\nImmediately available is highly preferred\n\nWhat We Offer?\n\n\nFlexi-work\nMonthly product allowance\nQuarterly incentive bonus & annual performance bonus\nAnnual body checkup,\nFull protection of medical benefits (including dental),\nLife & accidental insurance,\nAnnual leave and other caring leaves.\nIf you are ready for a new challenge in your career, please click\u00a0\"Apply Now\"\u00a0to submit your application with expected salary.\n\n\n\nALL PERSONAL INFORMATION WE COLLECTED IS FOR THE PURPOSE OF RECRUITMENT ONLY\n\nPlease visit www.nuskin.com to find out more about us!", "employment_types": ["Full Time", "Permanent"], "selling_points": ["Flexi-working hours & work from home arrangement", "Caring Culture", "HR Business Partner"], "locations": ["Causeway Bay"], "categories": ["Admin & HR", "HR Supporting Staff", "Recruitment / Executive Search", "Training & Development"], "post_time": "2022-01-17T12:14:09Z", "salary": {"currency": null, "max": null, "min": null, "period": "monthly", "term": null}, "salary_visible": false, "title_keywords": ["hr", "hr officer"], "responsibilities": ["ad-hoc", "hr", "maintain"], "requirements": {"degrees": ["bachelor degree holder"], "majors": [], "languages": ["putonghua", "english", "chinese"], "language_level": ["advantage", "proficiency"], "hard_skills": [], "soft_skills": ["flexible", "detail-minded", "work independently", "good team player", "can-do attitude", "work under pressure", "communication skill", "proactive", "driven", "sense of responsibilities"], "languages_combined": [{"language": "putonghua", "language_level": ["advantage"]}, {"language": "english", "language_level": ["proficiency"]}, {"language": "chinese", "language_level": ["proficiency"]}]}, "experience_required": {"duration": ["3-4 years"], "field": ["recruitment", "relevant experience", "human resources"]}}, {"job_id": "100003009050147", "location_code": "hk", "company": "ATAL Engineering Ltd", "job_title": "Training Assistant (REF: TND/TA)", "description": "Responsibilities:\n\nTo assist in administration of the internal training programmes including course promotion, enrolment, logistics arrangement, training materials preparation, training evaluation summary, etc.\nTo administer the external training sponsorship programme including sponsorship and reimbursement application\nTo prepare the various training progress reports and other ad-hoc reports\nTo assist in preparation of the training promotion events\nTo handle the operation works of the training centre such as purchasing, room set-up, maintenance works, etc.\nTo carry out any other reasonable duties as necessary from time to time\n\nRequirements:\n\nDiploma in Human Resources Management, Training, Psychology, English Language, or related disciplines\n1 year relevant experience in training & development or administration\nGood time management and multi-tasking capability\nStrong sense of responsibility, good team player and customer-focused\nProactive, self-motivated, well-organised and independent\nGood command in both written and spoken English and Chinese\nExposure in the construction industry an advantage\nWell-versed in MS Office applications, including Word, Excel and Powerpoint\nExperience in using design and video-editing software will be an advantage\nGood team player, self-initiated and willing to learn\nFresh graduates will also be considered\n\nPlease click the Apply Now button to send your full resume stating relevant job reference, present and expected salary and availability.\n\nPersonal data collected will be treated in strict confidence and used for recruitment related purposes only.", "employment_types": ["Full Time", "Permanent"], "selling_points": ["internal training programmes", "external training sponsorship programme", "training progress reports"], "locations": ["North Point"], "categories": ["Admin & HR", "Training & Development"], "post_time": "2022-01-15T03:50:51Z", "salary": {"currency": null, "max": null, "min": null, "period": "monthly", "term": null}, "salary_visible": false, "title_keywords": ["assistant"], "responsibilities": ["ad-hoc", "maintenance", "progress reports", "logistics arrangement", "reports", "evaluation", "administration"], "requirements": {"degrees": ["diploma"], "majors": ["related disciplines", "psychology"], "languages": ["english", "chinese"], "language_level": ["good command"], "hard_skills": ["excel", "word", "powerpoint", "ms office"], "soft_skills": ["good team player", "proactive", "customer-focused", "self-motivated", "independent", "sense of responsibility", "confidence", "willing to learn", "multi-tasking", "well-organised", "time management"], "languages_combined": [{"language": "english", "language_level": ["good command"]}, {"language": "chinese", "language_level": ["good command"]}]}, "experience_required": {"duration": ["1 year"], "field": ["video", "training", "development", "design", "relevant experience", "editing", "administration"]}}, {"job_id": "100003009051883", "location_code": "hk", "company": "Olympus Corporation of Asia Pacific Limited", "job_title": "Assistant Human Resources Manager (1-Year Contract renewable)", "description": "At Olympus, our shared aim is to use our innovative optical and digital solutions in medical technologies, life sciences and industrial solutions to making people\u2019s lives healthier, safer, and more fulfilling, which consists of our Core Values of Integrity, Empathy, Long-Term View, Agility and Unity forming the strong foundations and commitment to our people-focused culture and guide the way we think and behave, every day.\u00a0 You can look forward to exciting challenges in an international working environment, in which you will be constantly developing on both a professional and personal level. We are currently looking for an Assistant Manager, Human Resources (1-Year contract) to join our Human Resources Department in our Hong Kong office.\n\nResponsibilities:\n\n\nManage full spectrum of HR services including day-to-day HR operations including talent acquisition, compensation and benefits, performance management, learning and development, and employee engagement activities\nSupport in formulating and executing learning and engagement plan aligned with business strategies, organizational objectives and strengthen the corporate core values awareness\nSupport in talent acquisition for strategic sourcing and handle all relevant transactional activities\nPromote and coordinate all learning and engagement activities across functions/departments, and prepare the comprehensive evaluation summary report to management review\nWork closely with team members to deliver excellent HR services and enhance employee engagement and experience\u00a0\u00a0\nPerform any other ad hoc assignments as assigned\nRequirements:\n\nBachelor\u2019s degree in Human Resources Management or related disciplines\n8 years relevant experience with prior experience in consulting or L&D/ER background will be highly favourable\nFully conversant in HR operations and HK Ordinances\nAble to work in fast-paced environment and manage change with resilience\nStrong productivity, prioritization, and accurate skills\u00a0\nExcellent command of MS Office application, especially PowerPoint/Excel\nExcellent presentation skills with fluency in English and Cantonese/Mandarin\u00a0\nCandidate with less experience will consider as Senior Human Resources Executive\n\n\nWe offer attractive remuneration and career development opportunity.\u00a0 Interested parties, please send your resume together with availability, present and expected salaries by \u201cApply Now\u201d.\n\nAll personal information collected will be treated in strict confidence and used for recruitment purpose only.", "employment_types": ["Full Time", "Contract"], "selling_points": ["Stable & fast-paced MNC with flexible working", "All rounded HR duties", "Permanent role opportunity after 1-year"], "locations": ["Kwai Hing"], "categories": ["Admin & HR", "Others", "HR Director / Manager", "Training & Development"], "post_time": "2022-01-17T01:26:30Z", "salary": {"currency": null, "max": null, "min": null, "period": "monthly", "term": null}, "salary_visible": false, "title_keywords": ["assistant human resources manager"], "responsibilities": ["management", "operations", "hr", "coordinate", "executing", "ad hoc assignments", "plan", "evaluation", "management review", "report"], "requirements": {"degrees": ["degree", "bachelor"], "majors": ["related disciplines"], "languages": ["cantonese", "english", "mandarin"], "language_level": ["fluency", "excellent"], "hard_skills": ["excel", "powerpoint", "ms office"], "soft_skills": ["presentation skills", "accurate", "work in fast-paced environment"], "languages_combined": [{"language": "cantonese", "language_level": ["fluency", "excellent"]}, {"language": "english", "language_level": ["fluency", "excellent"]}, {"language": "mandarin", "language_level": ["fluency", "excellent"]}]}, "experience_required": {"duration": ["8 years"], "field": ["human resources", "relevant experience", "consulting"]}}, {"job_id": "100003009054489", "location_code": "hk", "company": "Pure Search International Limited", "job_title": "Talent Management Lead (Assistant Manager/ Manager/Senior Manager)", "description": "Our client is looking for a capable and proactive Talent Management professional to drive, develop and implement the Group's talent management initiatives:\n- Collaborate with both internal stakeholders as well as external vendors/ consultants\n- Manage and support the development and delivery of talent initiatives\n- Facilitate annual performance review, Hi-Po identification and succession planning\n- Manage the Hi-Po program and use existing talent frameworks to support their growth\n- Review data from HCM to provide insights and use information for future decisions/ recommendations\u00a0\n- Identify and develop competency assessment tools and models for talent development\n- Ad hoc projects\n\nRequirements:\n- Bachelor Degree in Human Resources Management or related discipline\n- 7 to 12 years of relevant experience gained sizable organizations\n- Analytical and data savvy\n- Strong stakeholder management and interpersonal skills\n- Strong project management skills and able to multi task effectively\n- Excellent command of both spoken and written English and Chinese", "employment_types": ["Full Time"], "selling_points": ["Group level exposure", "Broad geographical coverage", "Competitive package"], "locations": ["Others"], "categories": ["Admin & HR", "Others", "Training & Development"], "post_time": "2022-01-17T09:45:47Z", "salary": {"currency": null, "max": null, "min": null, "period": "monthly", "term": null}, "salary_visible": false, "title_keywords": ["senior manager", "assistant manager", "manager", "lead"], "responsibilities": ["collaborate with", "provide insights", "management", "data", "review", "develop", "project management", "ad hoc projects", "planning"], "requirements": {"degrees": ["degree", "bachelor"], "majors": [], "languages": ["english", "chinese"], "language_level": ["excellent"], "hard_skills": ["project management"], "soft_skills": ["project management skills", "proactive", "interpersonal skills", "capable"], "languages_combined": [{"language": "english", "language_level": ["excellent"]}, {"language": "chinese", "language_level": ["excellent"]}]}, "experience_required": {"duration": ["7 to 12 years"], "field": ["relevant experience"]}}, {"job_id": "100003009053226", "location_code": "hk", "company": "Crocodile Garments Limited", "job_title": "Assistant Human Resources & Administration Officer", "description": "Responsibilities:\n\nTo provide HR and office administration support\n\u00a0To handle the recruitment and selection process, especially for retail staff\nTo assist in payroll calculation and MPF administration\u00a0for retail staff\nTo provide office administration support such as general insurance, license renewal and office maintenance\nTo handle ad-hoc duties as assigned\nRequirements:\n\nDiploma holder or above in Human Resources Management\nMinimum 1-2 years\u2019 relevant experience, especially in retail industry is preferable\nWell-versed with Hong Kong Employment Ordinance\nGood communication and presentation skills\nImmediate available is preferable\nApplicants with less experience will be considered as Human Resources & Administration Assistant\n\n\n\nInterested parties, please apply with full resume, stating date available, present and expected salary to\u00a0Human Resources & Administration Department by clicking 'Apply Now'.\n\nPersonal Data provided in the employment applications will be treated as strictly confidential and used only for recruitment purpose.\u00a0 All unsuccessful applications will be destroyed upon completion of the selection process.", "employment_types": ["Full Time", "Permanent"], "selling_points": ["Provide HR and office administration support", "Assist in recruitment and payroll calculation", "Diploma in HRM with min.1 year exp."], "locations": ["Kwun Tong"], "categories": ["Admin & HR", "Compensation & Benefits", "HR Supporting Staff", "Training & Development"], "post_time": "2022-01-17T06:29:23Z", "salary": {"currency": null, "max": null, "min": null, "period": "monthly", "term": null}, "salary_visible": false, "title_keywords": ["human resources", "administration officer", "assistant"], "responsibilities": ["office administration support", "mpf", "maintenance", "hr", "recruitment", "insurance", "ad-hoc duties", "payroll", "administration"], "requirements": {"degrees": ["diploma holder"], "majors": [], "languages": [], "language_level": [], "hard_skills": ["hong kong employment ordinance"], "soft_skills": ["communication", "presentation skills"], "languages_combined": []}, "experience_required": {"duration": ["minimum 1-2 years"], "field": ["retail industry", "relevant experience", "human resources", "administration"]}}, {"job_id": "100003009047969", "location_code": "hk", "company": "Convoy Global Holdings Limited", "job_title": "Officer, Learning & Talent Development", "description": "We are looking for a high calibre candidate to join our Learning and Talent Development team.\n\nResponsibilities:\n\nPrepare onboarding training for new employees.\nSupport the facilitation of the in-house training and conferences.\nConduct thorough needs assessments to gauge training needs.\nCreate training programs and prepare any learning materials needed.\nConduct surveys to judge how programs are received and if changes are needed.\nSupport the evaluation on employee performance and gauge where skills need improvement.\nCoordinate overall training logistics arrangement.\nMaintain training database, consolidate training reports and prepare training need analysis.\u00a0\nAssist in any ad-hoc training projects.\nRequirements:\n\nDegree holder with minimum of 2 years of relevant working experience.\nStrong in facilitation, presentation and interpersonal skills.\nEnergetic, determined, and highly capable disposition.\nKnowledge of all relevant learning software and indices.\nExcellent written and spoken in both English and Chinese including Putonghua.\nProficient in video editing, Excel, PowerPoint, Chinese word processing.\nQualification in Instruction and/or learning design is advantageous.\n\nWe offer competitive remuneration including career prospects to the right candidate. Interested parties please send detailed resume with availability, current and expected salaries to\u00a0Human Resources Department, Convoy Global Holdings Limited, Trust Tower, 68 Johnston Road, Wan Chai, Hong Kong\u00a0or by clicking the\u00a0Apply Now\u00a0button and upload your CV and cover letter.\n\n(All applications will be treated in strict confidence and used for recruitment purpose within Convoy Global Holdings Limited only. All applicants are kept on file six months from the date of the application.)", "employment_types": ["Full Time", "Permanent"], "selling_points": ["Facilitate in-house training", "Create training program", "Good presentation"], "locations": ["Wan Chai"], "categories": ["Admin & HR", "Training & Development"], "post_time": "2022-01-14T04:24:22Z", "salary": {"currency": null, "max": null, "min": null, "period": "monthly", "term": null}, "salary_visible": false, "title_keywords": ["officer"], "responsibilities": ["ad-hoc", "logistics arrangement", "analysis", "coordinate", "conferences", "maintain", "reports", "database", "evaluation"], "requirements": {"degrees": ["degree holder"], "majors": [], "languages": ["putonghua", "english", "chinese"], "language_level": ["excellent", "proficient"], "hard_skills": ["video editing", "excel", "chinese word processing", "powerpoint"], "soft_skills": ["capable", "determined", "learning", "interpersonal skills", "energetic", "presentation"], "languages_combined": [{"language": "putonghua", "language_level": ["excellent"]}, {"language": "english", "language_level": ["excellent"]}, {"language": "chinese", "language_level": ["excellent", "proficient"]}]}, "experience_required": {"duration": ["minimum of 2 years"], "field": ["relevant working experience"]}}, {"job_id": "100003009048573", "location_code": "hk", "company": "IKEA", "job_title": "Learning & Development Specialist", "description": "WHY YOU WILL LOVE US\n\nWe\u2019re a diverse group of down-to-earth, straightforward people with a passion for home furnishing. We come from all over the world, but we share an inspiring vision: \u201cto create a better everyday life for the many people\u201d. How we realize this vision is based on our shared humanistic values. These values guide our work and build our inclusive, open and honest culture. It\u2019s all based on a spirit of togetherness and enthusiasm. We work hard, but we have fun doing it. We\u2019re always looking for people who share our positive attitude and values.\n\nWHY WE WILL LOVE YOU\n\n\n\nYou have more than 3 years professional L&D experience preferably in retail and/or services environment\nYou have basic business and operation knowledge and a background with the customer in focus\nYou have good analytical and numerical skills\nComputer aptitude \u2013previous experience with Microsoft applications and online learning tool/platform\nYou are fluent in English (written and verbal skills)\nYou can strike a balance between keeping a good overview and paying good attention to detail\nYou are self-reliant and motivated with proven ability to work as part of a team as well as independently\nYou have the knowledge and practice of adult learning\nYou have good facilitation skills\nYou have proven track record in executing Learning & Development related assignments in multinational organisation\nYou have good communication, administration, and stakeholder management skill\nYou have the ability to do translation for learning materials (English to local language or local language to English) in a timely manner\nYou have experience of being a trainer and/or facilitator\nYou have the eagerness to work in collaboration in the fast moving/changing environment\n\nWHAT YOU WILL BE DOING DAY TO DAY\n\n\nWork with Learning & Development Manager, SO functions and Store/Warehouse partners to contribute to the creation, update and implementation of central training plan\nCoordinate annual training budget planning process with SO functions, store HR and SO Finance. Manage training policies and procedure to ensure it up-to-date, accurate and compliant with audit procedures\nBeing super user of training related systems. Lead the execution of training administration system and processes which includes training venues arrangement, registration flow, materials preparation, facilities set-up, evaluation, training record, make sure it accurate and compliant with audit procedures. Meanwhile, keep related stakeholders informed as needed. (i.e. Mylearning, Soar Clound)\nResponsible for procurement and payment process in L&D function which includes vendor quotation/management, stationary, incentive for country level facilitators, expense management and so on\nTogether with IISBV, DF, SO, Store & Warehouse partners and external resources to develop efficient and helpful L&D material/resources. Meanwhile, make sure its up-to-date, best use of them and ensure the quality. (i.e. Store Introduction, Buddy TTT, Mylearning Administration, IKEA/DF Code of Conduct, Health & Safety...etc.)\nWork with Learning & Development Manager to maintain Talent Management system (Talent Central) by setting up succession organisation chart, annual individual development plan form and make sure it accurate and up-to-date all the time\nWork with IT and Store/Warehouse partners to ensure the account of digital learning solutions and system is accurate and available for our colleagues. Meanwhile, act as L&D contact window to deal with the system issues with counter partner while occurred\nSupport Learning & Development Manager to develop, implement and maintain L&D report and projects based on our Business/People strategy and individual development needs to strengthen IKEA Culture & Values and build up business and leadership competence. (i.e. L&D KPI report)\nSupport and advise managers and store partners on HR issues, regulations and responsibilities and proper administration of the corrective action processes\nAct as a cultural role model in ways that demonstrate the IKEA values within and outside IKEA, which also includes safeguarding and promoting the IKEA culture and IKEA Brand\n\nTOGETHER AS A TEAM\n\nAt the heart of our business are people. We create a better everyday life together by living our shared values and safeguarding our unique culture. To create an inspiring IKEA experience, we need to make sure our co-workers have the preconditions to meet our customers in the best possible way.\n\n\nSTAFF BENEFITS\n\nAnnual Fixed Bonus, 5-Day Work Week, 17 days Public Holiday, Paid Leave (Paid Annual Leave, 14 weeks Maternity Leave, 5 days Paternity Leave, 1 week Marriage Leave), Employee Medical Coverage, Non-Contributory Retirement Plan, Staff Purchase Discount, Birthday Coupon, Referral Bonus, Excellent Career Path\n\nPersonal data collected will be kept and handled confidentially by authorized personnel for recruitment purposes only. It might also be disclosed to our subsidiaries, associates and agencies authorized to process the information for appointment. The Company will retain the applications of candidates not selected for a maximum period of 24 months after the selection process is finalized. Our Personal Information Collection Statement (PICS) is available at our career site and can be provided upon request by contacting our Human Resources Department. Applicants not heard from us within six weeks may consider their applications filed for future reference.\n\nIssued by The Dairy Farm Company, Limited\n\nIssued by The Dairy Farm Company, Limited\n\n\n", "employment_types": ["Full Time", "Permanent"], "selling_points": ["Coordinate annual training budget planning process", "Update and implementation of central training plan", "Lead the execution of training system and process"], "locations": ["Shatin Area"], "categories": ["Admin & HR", "Training & Development"], "post_time": "2022-01-14T06:49:43Z", "salary": {"currency": null, "max": null, "min": null, "period": "monthly", "term": null}, "salary_visible": false, "title_keywords": ["specialist"], "responsibilities": ["regulations", "quotation", "quality", "audit", "communication", "maintain", "plan", "evaluation", "administration", "budget planning", "implementation", "develop", "report", "management", "procedures", "executing", "contact", "policies", "hr", "systems", "a timely manner", "coordinate", "payment process"], "requirements": {"degrees": [], "majors": [], "languages": ["english"], "language_level": ["fluent"], "hard_skills": ["basic", "microsoft applications", "fun", "vendor", "code", "make", "numerical skills", "translation", "focus"], "soft_skills": ["efficient", "independently", "responsible", "passion for", "timely", "unique", "positive attitude", "diverse", "communication", "learning", "motivated", "inspiring", "honest", "attention to detail", "organisation", "focus", "accurate", "leadership"], "languages_combined": [{"language": "english", "language_level": ["fluent"]}]}, "experience_required": {"duration": ["3 years"], "field": ["retail"]}}, {"job_id": "100003009049249", "location_code": "hk", "company": "S.F. Express (Hong Kong) Limited", "job_title": "Assistant Learning & Development Manager", "description": "Our HR team is looking for a high caliber candidate to join us as the Assistant\u00a0Learning & Development Manager. This role reports to Team Lead, Learning and Development, responsible for formulating talent development solutions in support of our strategic people agenda.\n\nResponsibilities\n\n\n\nDevelop, review and update talent review and succession planning processes\nEnsure all talent management planning / activities are in line with the corporate development strategy, policies and culture\u00a0\nDesign, develop and deliver training programs to frontline staff to enhance the products knowledge and service standards\u00a0 \u00a0 \u00a0 \u00a0 \u00a0 \u00a0\nMaintain and update all training materials in line with the latest operations development and employee training records\u00a0 \u00a0 \u00a0 \u00a0 \u00a0\nCoordinate the pre and post-training logistics with internal or external parties to enable smooth delivery of training course\u00a0 \u00a0 \u00a0 \u00a0\u00a0\nAnalyze, monitor and evaluate the effectiveness of the training programs\nPrepare and monitor the training budgets and resources allocation\n\nJob Requirements\n\n\nDegree holder in Training/Learning Development or related discipline \u00a0 \u00a0 \u00a0 \u00a0 \u00a0\u00a0\n5 years' relevant experience\u00a0\u00a0\u00a0\u00a0\u00a0\u00a0\u00a0\u00a0\u00a0\nInterpersonal skills that enable you to work with people at all levels, motivate others and change people's attitudes when necessary\nInitiative and the ability to offer new ideas\nOrganizational and planning skills to manage your time and to meet deadlines and objectives\nGood time-keeping skills to enable you to effectively manage training schedules\nPersonal commitment to improving your own knowledge and skills\nProficient in both written and spoken English and Chinese, Putonghua is an advantage;\nProficient in MS Office, Excel, PowerPoint\u00a0& Chinese Word Processing\u00a0\nCandidates with less\u00a0experience will be considered as Senior Human Resources Officer\nWe offer attractive remuneration package and fringe benefits to the suitable candidates. Interested parties, please submit your application to us. If you do not want to apply as a JobsDB member, you may send your full resume with your availability, current and expected salaries to recruit01 at sf-express.com\nYou are welcome to visit our website at\u00a0https://htm.sf-express.com/hk/tc/\u00a0for more information about us.\n\nCandidates who are not invited for an interview within 1-month may consider their applications unsuccessful.\nAll personal data provided by job applicants will be used only for recruitment purposes and will be treated strictly confidential. Unsuccessful applications will be retained for a maximum period of 24-month.", "employment_types": ["Full Time", "Permanent"], "selling_points": ["Free shuttle bus coverage", "2 months or above performance bonus", "Attractive basic salary"], "locations": ["Tsing Yi"], "categories": ["Admin & HR", "Others", "HR Director / Manager", "Training & Development"], "post_time": "2022-01-14T08:18:49Z", "salary": {"currency": null, "max": null, "min": null, "period": "monthly", "term": null}, "salary_visible": false, "title_keywords": ["manager", "assistant"], "responsibilities": ["budgets", "management", "policies", "operations", "review", "external parties", "monitor", "design", "develop", "coordinate", "evaluate", "service standards", "maintain", "logistics", "planning"], "requirements": {"degrees": ["degree holder"], "majors": [], "languages": ["putonghua", "english", "chinese"], "language_level": ["advantage", "proficient"], "hard_skills": ["excel", "chinese word processing", "powerpoint", "ms office"], "soft_skills": ["organizational and planning skills", "learning", "interpersonal skills", "meet deadlines", "initiative"], "languages_combined": [{"language": "putonghua", "language_level": ["advantage", "proficient"]}, {"language": "english", "language_level": ["proficient"]}, {"language": "chinese", "language_level": ["proficient", "proficient"]}]}, "experience_required": {"duration": ["5 years"], "field": ["relevant experience", "human resources"]}}, {"job_id": "100003009051187", "location_code": "hk", "company": "Mindset Asia Limited", "job_title": "General Manager - Learning Center", "description": "Our client is an established Learning center, with an objective to provide continuing education for the professional preparatory programs, including ACCA, LCCI, MYOB, Secretarial and etc..\n\nResponsibilities\n\nLead the continuous development and provide strategic direction for the long term growth plan of the Learning Center for 3 to 5 years\nAssist in program development and promote the quality and standard of the programs\nFully responsible for the management of day-to-day operation, financial matters, forecasts, audit and maintain a strong culture of risk management\nEnsure that the effective operation and have the right governance structure to deliver program growth with full compliance\nEstablish and maintain regular communication with various government authorities for a better understanding of legal and regulatory requirements\nMaintain good partnership with internal management (including the Board members, management team and tutors) and external organisations, such as the Education department, HKSAR Re-training Board, Continuing Education Fund and other co-operative partners\nExplore and expand the partnership with different organisations to look for collabrative partnership\nRequirements\nProfessionally qualified with ACCA/HKICPA or Master degree in Education or related disciplines\nOver 15 years experience in the education/learning centre\nDemonstrate effective leadership and passionate in education development\nSolid experience in leading, coaching, driving and inspiring team members\nProven organisation skill and ability to priortise\nExcellent in communication and presentation skill\nGood in English and Chinese, verbal and written\nInterested parties can apply online by forwarding your resume and quoting the job reference. All applications will be strictly confidential and used for recruitment purposes only.\n", "employment_types": ["Full Time", "Permanent"], "selling_points": [], "locations": ["Not Specified"], "categories": ["Education", "Others", "Management", "General Management", "Admin & HR", "Training & Development"], "post_time": "2022-01-15T04:21:46Z", "salary": {"currency": null, "max": null, "min": null, "period": "monthly", "term": null}, "salary_visible": false, "title_keywords": ["general manager"], "responsibilities": ["management team", "management", "regulatory requirements", "compliance", "quality", "audit", "communication", "maintain", "plan", "day-to-day operation"], "requirements": {"degrees": ["master degree"], "majors": ["related disciplines"], "languages": ["english", "chinese"], "language_level": ["good"], "hard_skills": ["presentation skill", "acca", "hkicpa"], "soft_skills": ["passionate", "presentation skill", "organisation skill", "communication", "learning", "inspiring", "leadership"], "languages_combined": [{"language": "english", "language_level": ["good"]}, {"language": "chinese", "language_level": ["good"]}]}, "experience_required": {"duration": ["15 years"], "field": ["team", "education"]}}, {"job_id": "100003009050182", "location_code": "hk", "company": "Belle Worldwide (Talent Management) Limited", "job_title": "Training Officer", "description": "Role & Responsibilities:\n\nResponsible for handling full spectrum of Learning & Development functions including training delivery, e-learning and external training co-ordination.\nPromote learning culture in the company\nPartner with Operations team to develop retail training initiatives and conduct field coaching in order to achieve the sales and service targets\nReview and maintain training database and consolidate training reports for management review\nPerform ad hoc assignments or projects as assigned\n\nRequirements:\n\nDegree holder in Training, HR Management, or business related disciplines\nAt least\u00a03 years'\u00a0solid\u00a0training\u00a0experience and hands-on training experience in Retail Industry will be definitely an advantage\nSelf-motivated, well-organized, independent and good team player\nStrong in facilitation, presentation and interpersonal skills\nProficient in MS Office and video editing\n\n\n\n\nInterested parties, please \"APPLY NOW\" or send your full resume with current and expected salary to Head of Human Resources Department, 6/F, The Edge, 30-34 Kwai Wing Road, Kwai Chung, N.T., Hong Kong\n\nFor more information, please contact Ms. Wan at 39290621.\n\nAll information received will be kept strictly confidential and only for employment-related purposes.", "employment_types": ["Full Time", "Permanent"], "selling_points": ["Seasoned Trainer", "Good Team Player", "Strong in facilitation and presentation skills"], "locations": ["Kwai Hing"], "categories": ["Admin & HR", "Training & Development"], "post_time": "2022-01-14T09:54:42Z", "salary": {"currency": null, "max": null, "min": null, "period": "monthly", "term": null}, "salary_visible": false, "title_keywords": ["officer"], "responsibilities": ["operations", "review", "develop", "maintain", "reports", "ad hoc assignments", "database", "management review"], "requirements": {"degrees": ["degree holder"], "majors": ["related disciplines", "business"], "languages": [], "language_level": [], "hard_skills": ["video editing", "ms office"], "soft_skills": ["good team player", "self-motivated", "independent", "well-organized", "hands-on", "interpersonal skills", "presentation"], "languages_combined": []}, "experience_required": {"duration": ["at least 3 years"], "field": ["retail industry", "training"]}}, {"job_id": "100003009054229", "location_code": "hk", "company": "", "job_title": "Senior HR and Admin Officer", "description": "Job Description\n\nIndependently handle of C&B, recruitment and administration matters\nAssist the head of HR to plan, formulate and execute people related policies\nDeveloped training and staffing materials, KPI management align to brands requirement\nDrive company initiatives and manage projects\nFacilitate on-going communication across all levels and promote employee engagement\nResponsible for general administrative duties and office support including procurement and maintenance of office equipment / facilities, regular housekeeping, replenishment of office supplies, licenses renewal & etc.\nCo-ordinate and organize company activities and event\n\nRequirement\n\nDegree holder in Human Resources Management, Administration or related disciplines\nAt least 2 to 5 years relevant working preferably in FMCG field\nFluent in spoken and written English and Chinese\nKnowledge in Employment Ordinance and other HR related legislations\nHardworking, responsible, self-organized with good sense of judgement\nImmediate available preferred\n\nInterested parties please click apply and attach your full resume with current and expected salary and your availability.\n\nInformation provided will be treated in strict confidence and only be used for recruitment purpose. The Company may refer suitable applicants to other vacancies within the associated Group of companies. Applicants who are not invited for interview within 1 month may consider their applications unsuccessful.", "employment_types": ["Full Time", "Permanent"], "selling_points": ["C&B, staffing and training", "FMCG", "Young team, energetic"], "locations": ["Kwun Tong"], "categories": ["Admin & HR", "Administration / Operation Manager", "Compensation & Benefits", "Training & Development"], "post_time": "2022-01-17T08:51:40Z", "salary": {"currency": null, "max": null, "min": null, "period": "monthly", "term": null}, "salary_visible": false, "title_keywords": ["hr and admin officer"], "responsibilities": ["management", "housekeeping", "policies", "hr", "maintenance of office equipment", "office supplies", "office support", "replenishment", "communication", "recruitment", "manage projects", "plan", "administrative duties", "administration"], "requirements": {"degrees": ["degree holder"], "majors": ["related disciplines"], "languages": ["english", "chinese"], "language_level": ["fluent"], "hard_skills": [], "soft_skills": ["organized", "hardworking", "responsible"], "languages_combined": [{"language": "english", "language_level": ["fluent"]}, {"language": "chinese", "language_level": ["fluent"]}]}, "experience_required": {"duration": [], "field": []}}, {"job_id": "100003009054681", "location_code": "hk", "company": "Haitong International Securities Group Limited", "job_title": "Human Resources Manager (Training & Development), Human Resources (Ref.: JDB/HR/HRM_T&D)", "description": "The Job :\u00a0\n\nAssist in the design and implementation of effective corporate training and development programs, including Management Trainee Program and Talent Programs to groom talents and future leaders.\nConduct training needs analysis to identify trainings for employees and design training curriculum.\nPropose training solutions that meet business needs, source external vendors, and evaluate training effectiveness based on the feedback from internal users.\nCoordinate and collaborate with internal and external stakeholders to develop and deliver training for employees, manage external vendors well and maintain good relationship.\nPrepare periodic training reports and analyze training data to review the trend and future training needs.\nOrganize training classes or coordinate online training, handle course enrolment, registration, email notification, and logistics arrangement of training venue.\nAssist in developing and reviewing operation procedure manuals and other necessary control documents. Review training processes to enhance efficiency.\nWork together with Compliance Department on managing CPT/D training to meet compliance requirements for all license holders.\nMaintain proper and accurate training record for all staff and license holders; handle LMS administration.\nAddress staff enquires related to training.\nPerform any other ad hoc duties as required.\n\nRequirements:\u00a0\nWe support local hire with solid relevant working experience in HK.\n\n\nUniversity degree in Human Resources Management or related disciplines;\nA minimum of 7 years\u2019 relevant experience training and development roles in financial industry;\nGood command of written and spoken Chinese and English;\nDetailed minded with strong analytical, problem solving and project management skills;\nFlexible and able to work in a fast-pace, result-oriented environment;\nExcellent communication and interpersonal skills\n\nApplication Method:\n\nWe are committed to build a team of competence individuals who have acquired relevant local solid working experience and with diversified exposure to work together with us. Applicants who do not hear from us within 6 weeks may consider their applications unsuccessful.\n\nWe provide attractive remuneration package and fringe benefits for the right candidate.\u00a0Interested parties please send detailed resume with current and expected salaries to\u00a0Human Resources Department\u00a0i) by mail: 22/F, Li Po Chun Chambers, 189 Des Voeux Road Central, HK;\u00a0ii) by fax:2537 5431; or\u00a0iii) by using\u00a0\u201cApply Now\u201d.\n\nPlease quote the reference in the application.If application is submitted in hard copy format, it should be placed in a sealed envelope marked \u201cConfidential\u201d.\u00a0 All applications will be treated in strict confidence and personal data provided by job applications will be used for recruitment purposes only.\u00a0 A copy of our Personal Information Collection Statement will be available upon request.", "employment_types": ["Full Time", "Permanent"], "selling_points": [], "locations": ["Southern Area"], "categories": ["Admin & HR", "Others", "HR Supporting Staff", "Training & Development"], "post_time": "2022-01-17T10:32:56Z", "salary": {"currency": null, "max": null, "min": null, "period": null, "term": null}, "salary_visible": false, "title_keywords": ["hr", "manager", "human resources"], "responsibilities": ["collaborate with", "data", "design", "maintain", "administration", "ad hoc duties", "control", "compliance", "implementation", "developing", "develop", "maintain good relationship", "reports", "management", "logistics arrangement", "review", "development programs", "analysis", "evaluate", "coordinate"], "requirements": {"degrees": ["university degree"], "majors": ["related disciplines"], "languages": ["english", "chinese"], "language_level": ["good command"], "hard_skills": ["problem solving", "project management"], "soft_skills": ["flexible", "project management skills", "problem solving", "committed", "communication and interpersonal skills", "result-oriented", "detailed"], "languages_combined": [{"language": "english", "language_level": ["good command"]}, {"language": "chinese", "language_level": ["good command"]}]}, "experience_required": {"duration": ["minimum of 7 years"], "field": ["training", "development", "financial industry", "relevant working experience", "relevant experience", "team"]}}, {"job_id": "100003009049053", "location_code": "hk", "company": "Parfums Christian Dior Asia Pacific", "job_title": "Regional Talent Development Manager", "description": "MISSION STATEMENT\n\nBased in Hong Kong, the Regional Talent Development Manager will be in charge of the Talent Learning & Development, Career Management and Organization Development in North Asia (Taiwan, Hong Kong and Korea). He / She will also be in charge of ensuring the cascading of all the talent development actions within the region.\u00a0\n\n\u00a0Key responsibilities:\n\n\u00a0Talent Development:\n\nTo enhance development of PCD employees and manage the programs in a more strategic manner, to increase people and organization capability by working closely with PCD HR Business Partners\nIdentify and grasp development needs, and propose the programs that manage operations of the local program including setting criteria\nDevelop training vendors to support the design and implementation of the local programs\nMonitor the progress of the training participants, and assess the programs to make sure both are well matched in achieving our goals\nImprove and support training nomination processes, including LVMH programs aligned with individual development needs by working with HR Business Partners\nEnsure the implementation of the global PCD learning and development action plan across the region\n\n\u00a0Career Management:\n\nEndure a smooth and affective induction process for all newcomers\nIdentify key talents within the organization, create and follow up dedicated action plans for key talents to make them grow within the organization\nGrow people within the organization, promoting internal mobility and offering motivational career paths\n\n\u00a0Organization Development:\n\nLead and manage projects and sessions related to HR and the organization both locally and globally\nIdentify the areas of opportunities in the organization, generate and implement necessary action plans for improvement and better workplace for the employees\nPlan and lead ad-hoc projects and initiatives considering the organization needs and changes. (i.e. Diversity & Inclusion)\n\n\u00a0Talent Acquisition:\n\nIn collaboration with HQ, develop strong and attractive employer brand across the region\nIdentify a talent pool of talents at all levels and in all functions\nBuild strong partnership with top schools in the region to attract the best in class young graduates\nEnsure the implementation of the Excellence in recruitment mindsets and guidelines within the HR community\nCampus Management: set up internships with schools (in order to reach our localization targets)\n\n\u00a0Project Management:\n\nSupport all the annual LVMH / Parfums Christian Dior key HR processes\nPerformance and Career Reviews /\u00a0Individual Compensation Reviews / Organization Management Reviews\nIn charge of CSR activities including proposing new activities\n\nPROFILE\n\n8 years+ HR related experiences in sizable MNC especially in learning and development function\nBachelor\u2019s degree or above and MBA is preferred\nFocused on delivering excellence\nFlexibility, agility, and ability to multi-task\nAppreciation of luxury universe\nIndependent highly motivated fast learner\nPositive attitude with excellent communication skills\nEnjoy teamwork, maintain good relationship with office and field team members", "employment_types": ["Full Time", "Permanent"], "selling_points": ["LVMH, Dior, Luxury", "Regional, MNC, HR", "Talent Development, Learning & Development"], "locations": ["Quarry Bay"], "categories": ["Admin & HR", "Training & Development"], "post_time": "2022-01-14T07:59:49Z", "salary": {"currency": null, "max": null, "min": null, "period": "monthly", "term": null}, "salary_visible": false, "title_keywords": ["manager"], "responsibilities": ["management", "guidelines", "operations", "hr", "monitor", "implementation", "design", "develop", "communication", "project management", "maintain good relationship", "recruitment", "manage projects", "plan", "plans", "ad-hoc projects"], "requirements": {"degrees": ["degree or above", "bachelor"], "majors": [], "languages": [], "language_level": [], "hard_skills": ["make", "project management"], "soft_skills": ["communication skills", "multi-task", "independent", "focused", "teamwork", "positive attitude", "project management", "learning", "motivated", "smooth", "fast learner", "mobility"], "languages_combined": []}, "experience_required": {"duration": [], "field": ["related", "development", "hr"]}}, {"job_id": "100003009052074", "location_code": "hk", "company": "The Edge Partnership Holdings Limited", "job_title": "Education Executive", "description": "About the Role & Responsibilities:\n\nExecute full spectrum of HR functions including but not limited to recruitment, staff movement, leave management,\u00a0compensation & benefits and employee relations\nProvide end-to-end HR support for our office & site staff and ensure smooth running of day-to-day HR operations\nHandle all aspects of payroll administration including salary calculation, final payment, cost allocation, salaries tax and MPF administration, etc.\nMaintains accurate and timely data entry to HRIS and other related systems\u00a0and prepare reports on a regular basis\nHandles ad-hoc projects\nWhat we are looking for:\n\nDegree holder in Human Resources Management, Business Administration or related disciplines\nMinimum 5 years HR generalist experience with focus on C&B/payroll\nWell versed in HK Employment / MPF Ordinance and labour related ordinance/regulations\nExperience/Knowledge in PeopleSoft is an advantage\nAble to work under pressure and with positive attitude towards changes & challenges\nGood command in both written and spoken English and Chinese\nProficient in MS Office and Chinese Word Processing\nAttractive compensation package including competitive salary, up to 22 days Annual Leave, 5 days work as well as\u00a0excellent career prospects will be offered.\u00a0Interested parties please send full resume including your present and expected salaries by clicking \"Apply Now\".\n\n\n(Personal data collected would be used in accordance with our\u00a0Statement on Employment-Related Data Usage, which\u00a0is available at \u00a0http://www.chineseestates.com \u00a0or upon request made to the Company\u2019s Human Resources Manager. \u00a0Applicants who are not invited for interview within six weeks may consider their applications unsuccessful. \u00a0All personal data of unsuccessful candidates will be destroyed after six months.)\u00a0", "employment_types": ["Full Time"], "selling_points": ["Wholesale / Retail", "Admin & HR", "Training & Development"], "locations": ["Not Specified"], "categories": ["Admin & HR", "Training & Development"], "post_time": "2022-01-17T02:02:18Z", "salary": {"currency": null, "max": null, "min": null, "period": "monthly", "term": null}, "salary_visible": false, "title_keywords": ["executive"], "responsibilities": ["tax", "regulations", "management", "cost", "mpf", "data entry", "work under pressure", "operations", "hr", "systems", "payment", "recruitment", "prepare reports", "ad-hoc projects", "payroll", "administration"], "requirements": {"degrees": ["degree holder"], "majors": ["related disciplines", "business administration"], "languages": ["english", "chinese"], "language_level": ["good command", "proficient"], "hard_skills": ["focus", "chinese word processing", "ms office"], "soft_skills": ["timely", "positive attitude", "smooth", "focus", "accurate", "work under pressure"], "languages_combined": [{"language": "english", "language_level": ["good command"]}, {"language": "chinese", "language_level": ["good command", "proficient"]}]}, "experience_required": {"duration": ["minimum 5 years"], "field": ["payroll", "hr generalist"]}}, {"job_id": "100003009051768", "location_code": "hk", "company": "Earth Products China Limited", "job_title": "Senior Human Resources & Administration Officer / Manager", "description": "Responsibilities:\n\nProvide full spectrum of secretarial and administrative support to Senior Management in both business activities and personal matters\nHandle business correspondence, other confidential and professional documents as instructed\nAssist to draft various English and Chinese business correspondences in a professional manner\nResponsible for arranging and monitoring the day-to-day operation for the whole family household\nManage and supervise the domestic helpers, drivers, chef, securities, etc.\nResponsible for property and facilities management and maintenance, renovation, repair, etc.\nAd hoc tasks assigned by the Management\n\nRequirements:\n\nDegree holder in any disciplines\nAt least 4 years' relevant working experience\u00a0\nGood command of both written and spoken in English and Chinese\nEthical and proper handling of confidential information is a must\nIndependent, well-organized, strong sense of responsibility and able to work under pressure\nFamiliar with MS Word, Excel and Chinese Word Processing\nImmediate availability would be an advantage\nAttractive compensation package including competitive salary, up to 22 days Annual Leave, 5-day work as well as excellent career prospects will be offered. Interested parties please send full resume including your recent photo, present and expected salaries by clicking \u201cApply Now\u201d.\n\n\n(Personal data collected would be used in accordance with our Statement on Employment-Related Data Usage, which is available at\u00a0www.chineseestates.com\u00a0or upon request made to the Company\u2019s Human Resources Manager. Applicants who are not invited for interview within six weeks may consider their applications unsuccessful. All personal data of unsuccessful candidates will be destroyed after six months.)", "employment_types": ["Full Time", "Permanent"], "selling_points": [], "locations": ["Kwai Hing"], "categories": ["Admin & HR", "HR Director / Manager", "Recruitment / Executive Search", "Training & Development"], "post_time": "2022-01-17T00:59:32Z", "salary": {"currency": null, "max": null, "min": null, "period": "monthly", "term": null}, "salary_visible": false, "title_keywords": ["administration officer", "manager", "human resources"], "responsibilities": ["management", "day-to-day operation", "administrative support", "maintenance", "monitoring", "professional manner", "renovation", "ad hoc tasks", "repair", "senior management", "business activities"], "requirements": {"degrees": ["degree holder"], "majors": ["any disciplines"], "languages": ["english", "chinese"], "language_level": ["good command"], "hard_skills": ["excel", "chinese word processing", "ms word"], "soft_skills": ["independent", "sense of responsibility", "well-organized", "ethical", "work under pressure"], "languages_combined": [{"language": "english", "language_level": ["good command"]}, {"language": "chinese", "language_level": ["good command"]}]}, "experience_required": {"duration": ["at least 4 years"], "field": ["relevant working experience"]}}, {"job_id": "100003009046975", "location_code": "hk", "company": "Centaline Property Agency Ltd", "job_title": "Assistant Training Officer", "description": "Responsibilities:\n\nReport to Technical Manager / Assistant Technical Manager, the incumbent is responsible for R&M (Repair & Maintenance) of commercial, industrial, residential and office properties in compliance with relevant statutory requirements\nPrepare & arrange tender/quotation documents & sketches, job orders, payment settlements, etc. via computer systems\nFollow up on liaison, coordination, supervision, monitoring, T&C (Testing and Commissioning) with site technicians, management colleagues, outsource contractors & consultants of various works till completion and payment settlement\nCoordinate with tenants, landlords, occupiers, Leasing team, Marketing team, management team, Public Utilities and Government Authority in related to fitting out control\nPerform project management duties on fitting-out, A&A works, improvement works & feasibility studies, etc.\nRequirements:\nDegree / Higher Diploma in Building Services Engineering, Electrical Engineering, Mechanical Engineering or related discipline\n2 years' or above relevant experience in Government Authorities, Institutions, Public Organizations, Developers, property management company, consultant or contractor firm\nExperience in working at sizable high-end commercial properties including office and shopping arcade is an advantage\u00a0\nAdvanced knowledge of Excel, PowerPoint, Word, Chinese Word Processing is essential\nKnowledgeable in AutoCAD would be an advantage\n(Candidates with less experience will be considered as Assistant Technical Officer)\n\n\u00a0Attractive compensation package including competitive salary, up to 22 days Annual Leave, 5-day work as well as excellent career prospects will be offered. Interested parties please send full resume including your present and expected salaries by clicking \u201cApply Now\u201d.\n\n(Personal data collected would be used in accordance with our Statement on Employment-Related Data Usage, which is available at\u00a0www.chineseestates.com\u00a0or upon request made to the Company\u2019s Human Resources Manager. Applicants who are not invited for interview within six weeks may consider their applications unsuccessful. All personal data of unsuccessful candidates will be destroyed after six months.)", "employment_types": ["Full Time", "Permanent"], "selling_points": ["University graduate", "training experience", "induction course"], "locations": ["Tsim Sha Tsui"], "categories": ["Admin & HR", "HR Supporting Staff", "Training & Development"], "post_time": "2022-01-14T01:55:00Z", "salary": {"currency": null, "max": null, "min": null, "period": "monthly", "term": null}, "salary_visible": false, "title_keywords": ["officer", "assistant"], "responsibilities": ["quotation", "statutory requirements", "payment", "management team", "control", "compliance", "testing", "tender", "report", "management", "commissioning", "monitoring", "coordinate with", "sketches", "maintenance", "computer systems", "project management", "repair", "coordination"], "requirements": {"degrees": ["diploma", "degree"], "majors": ["mechanical engineering", "building services", "engineering", "electrical engineering"], "languages": ["chinese"], "language_level": [], "hard_skills": ["excel", "chinese word processing", "word", "powerpoint", "autocad"], "soft_skills": ["advanced"], "languages_combined": [{"language": "chinese", "language_level": []}]}, "experience_required": {"duration": ["2 years"], "field": ["commercial", "management", "relevant experience"]}}, {"job_id": "100003009050695", "location_code": "hk", "company": "Page Personnel", "job_title": "Senior e-Learning Officer - Technology Company", "description": "About the Role & Responsibilities:\n\nProvide comprehensive property management services for the Group's designated properties\nAssist in handling complaints and inquiries from authorizers/tenants and occupiers\nResponsible for inventory control, tendering and liaise with relevant government authorities\nMonitor the site operation and performance of contractors and subordinates to ensure the compliance of statutory requirements\nOther ad-hoc assignments\n\nWhat we are looking for:\n\nTertiary education preferably in Property Management / Facility Management or relevant disciplines\n3-5 years' relevant experience in property management with experience in prestigious shopping mall is an\u00a0advantage\nGood command of English and Cantonese\nProficient in MS Office\n\nAttractive compensation package including competitive salary, up to 22\u00a0days Annual Leave, 5-day work as well as\u00a0excellent career prospects will be offered.\u00a0 Interested parties please send full resume including your present and expected salaries by clicking \u201cApply Now\u201d.\n\n(Personal data collected would be used in accordance with our\u00a0Statement on Employment-Related Data Usage, which is available at\u00a0www.chineseestates.com\u00a0or upon request made to the Company\u2019s Human Resources Manager. \u00a0Applicants who are not invited for interview within six weeks may consider their applications unsuccessful. \u00a0All personal data of unsuccessful candidates will be destroyed after six months.)", "employment_types": ["Full Time", "Permanent"], "selling_points": ["U.S. listed company", "Develop Learning Management System (Workday)", "APAC exposure"], "locations": ["Shatin Area"], "categories": ["Admin & HR", "Training & Development"], "post_time": "2022-01-14T11:12:05Z", "salary": {"currency": null, "max": null, "min": null, "period": "monthly", "term": null}, "salary_visible": false, "title_keywords": ["officer"], "responsibilities": ["management", "ad-hoc assignments", "compliance", "monitor", "tendering", "statutory requirements", "inventory control", "liaise with"], "requirements": {"degrees": [], "majors": [], "languages": ["cantonese", "english"], "language_level": ["good command"], "hard_skills": ["ms office"], "soft_skills": ["comprehensive", "responsible"], "languages_combined": [{"language": "cantonese", "language_level": ["good command"]}, {"language": "english", "language_level": ["good command"]}]}, "experience_required": {"duration": ["3-5 years"], "field": ["management", "relevant experience"]}}, {"job_id": "100003009050620", "location_code": "hk", "company": "EC Healthcare", "job_title": "Training Assistant (Fresh graduates are also welcome)", "description": "Responsibilities:\n\nCreate and implement innovative marketing strategies for shopping malls\nAssist in planning, organizing, implementing and evaluating marketing events and promotions\nLiaise and co-ordinate with internal and external parties on marketing events\nCopywriting & proof reading marketing collaterals\nManage and maintain the social media platforms and multi-channel marketing campaigns\nKnowledge of digital marketing and drive online traffic\u00a0\u00a0\nManage the budget and develop cost-effective events and promotions\nConduct market intelligence research and survey\nOther ad-hoc tasks as assigned\nRequirements:\n\nDegree holder in Marketing/ Journalism / Communications or related disciplines\nMinimum 2 years of relevant experience in Marketing, preferably in property industry, shopping mall, PR or advertising agency\nStrong in event management and detail-minded\nSelf-motivated, able to work independently and handle multi-tasks;\nCreative and strong organizational skills;\nAble to work under high pressure and meet tight deadline;\nGood communication skills and good command in written and spoken Chinese, English and Putonghua\n\nAttractive compensation package including competitive salary,\u00a0up to\u00a022 days Annual Leave and 5 days work as well as excellent career prospects will be offered. Interested parties please send full resume including your present and expected salaries by clicking \"Apply Now\"\n\n(Personal data collected would be used in accordance with our Statement on Employment-Related Data Usage, which is available at\u00a0http://www.chineseestates.com\u00a0or upon request made to the Company\u2019s Human Resources Manager. Applicants who are not invited for interview within six weeks may consider their applications unsuccessful. All personal data of unsuccessful candidates will be destroyed after six months.)", "employment_types": ["Full Time", "Permanent"], "selling_points": ["Fresh graduate (intern experience)", "Training administrative support", "Familiar with PowerPoint"], "locations": ["Mong Kok"], "categories": ["Admin & HR", "HR Supporting Staff", "Training & Development", "Sales, CS & Business Devpt", "Others"], "post_time": "2022-01-14T10:58:59Z", "salary": {"currency": null, "max": null, "min": null, "period": "monthly", "term": null}, "salary_visible": false, "title_keywords": ["assistant"], "responsibilities": ["liaise", "marketing events", "cost", "marketing strategies", "co-ordinate with", "ad-hoc tasks", "internal and external parties", "marketing collaterals", "social media platforms", "budget", "develop", "maintain", "digital marketing", "marketing campaigns", "planning"], "requirements": {"degrees": ["degree holder"], "majors": ["journalism", "related disciplines", "marketing", "communications"], "languages": ["putonghua", "english", "chinese"], "language_level": ["good command", "good"], "hard_skills": [], "soft_skills": ["detail-minded", "organizational skills", "self-motivated", "work independently", "communication skills", "multi-tasks", "work under high pressure", "meet tight deadline", "creative"], "languages_combined": [{"language": "putonghua", "language_level": ["good command", "good"]}, {"language": "english", "language_level": ["good command", "good"]}, {"language": "chinese", "language_level": ["good command", "good"]}]}, "experience_required": {"duration": ["minimum 2 years"], "field": ["pr", "marketing", "relevant experience", "advertising agency"]}}, {"job_id": "100003008209430", "location_code": "hk", "company": "Centaline Financial Services Limited", "job_title": "Recruitment & Training Assistant", "description": "We are expanding our team and looking for a number of passionate and talented IT professionals to join us and support our business to grow innovatively.\n\nResponsibilities:\n\nParticipate in backend, web and/or mobile software development\nWork closely with the team in software development cycle, including user requirement study, system analysis, development, implementation and testing\nPrepare system design, documentation and test plan\nSupport and enhance existing application systems to meet business needs, driven by the corporate strategies\n\nRequirements:\n\nBachelor Degree in Computer Science/Computer Engineering/Information Technology\nExperience with web application and mobile app developments with\u00a0.NET\u00a0technologies would be a plus\nExperience with\u00a0any\u00a0of the following technologies would be an advantage\n.NET\nMS SQL Server and Reporting Service\nAngularJS and Node.js\nReact\nFirebase\nGIT\nNative iOS (Swift / Objective-C) and Android (Kotlin / Java)\nSharePoint\nMicrosoft Azure / Amazon Web Service\nR Programming\nRPA\n\n(Fresh graduates will also be considered)\n\nAttractive compensation package including competitive salary,\u00a0up to\u00a022 days Annual Leave and 5 days work as well as excellent career prospects will be offered. Interested parties please send full resume including your present and expected salaries by clicking \"Apply Now\"\n\n(Personal data collected would be used in accordance with our Statement on Employment-Related Data Usage, which is available at\u00a0http://www.chineseestates.com\u00a0or upon request made to the Company\u2019s Human Resources Manager. Applicants who are not invited for interview within six weeks may consider their applications unsuccessful. All personal data of unsuccessful candidates will be destroyed after six months.)", "employment_types": ["Full Time", "Permanent"], "selling_points": ["Training & Recruitment", "Insurance or Banking sector", "Min 3 years of experience preferably in training"], "locations": ["Tsim Sha Tsui"], "categories": ["Banking / Finance", "Others", "Admin & HR", "Recruitment / Executive Search", "Training & Development"], "post_time": "2022-01-15T03:49:15Z", "salary": {"currency": null, "max": null, "min": null, "period": "monthly", "term": null}, "salary_visible": false, "title_keywords": ["assistant"], "responsibilities": ["user requirement", "software", "analysis", "implementation", "testing", "system design", "plan", "documentation", "application systems"], "requirements": {"degrees": ["degree", "bachelor"], "majors": ["computer engineering", "computer science", "information technology"], "languages": [], "language_level": [], "hard_skills": ["plus", "git", "java", "azure", "web", "react", "ms sql server", "amazon", "objective-c", "rpa", "mobile", "programming", "swift", "r", "kotlin", "android"], "soft_skills": [], "languages_combined": []}, "experience_required": {"duration": [], "field": []}}, {"job_id": "100003009052022", "location_code": "hk", "company": "Multisoft Limited", "job_title": "Senior Human Resources Officer", "description": "Responsibilities:\n\nSupervise a team of customer service to provide high quality customer service and efficient information counter services to the mall tenants and visitors\nCoordinate with Marketing team on promotional events and customer service matters\nDesign and plan the customer service strategies to align with the mall requirements\nHandle enquiries and complaints in a professional manner\nLiaise with service contractors to ensure quality services are provided\nReviewing work schedules when necessary\nAd hoc tasks assigned by the Management\n\nRequirements:\n\nDegree or above in Hospitality Management, Public Relations or any related disciplines\nMinimum 5 years\u2019 relevant experience with 2 years\u2019 in supervisory level, exposure in hospitality, customer services or aviation service industry is highly preferable\nExperience in preparing tenders and operations manual\nExperience in handling marketing promotion and events are an advantage\nIndependent with good communication skills and able to work under pressure\nAdvanced knowledge of Excel, PowerPoint, Word, Chinese Word Processing is essential\nGood command of both written and spoken English and Cantonese\nAttractive compensation package including competitive salary,\u00a0up to\u00a022 days Annual Leave and 5 days work as well as excellent career prospects will be offered. Interested parties please send full resume including your present and expected salaries by clicking \"Apply Now\".\n\n(Personal data collected would be used in accordance with our Statement on Employment-Related Data Usage, which is available at\u00a0http://www.chineseestates.com\u00a0or upon request made to the Company\u2019s Human Resources Manager. Applicants who are not invited for interview within six weeks may consider their applications unsuccessful. All personal data of unsuccessful candidates will be destroyed after six months.)", "employment_types": ["Full Time", "Permanent"], "selling_points": ["End-to-end recruitment process", "HRBP", "Friendly and dynamic working environment"], "locations": ["Kwun Tong"], "categories": ["Admin & HR", "HR Director / Manager", "Recruitment / Executive Search", "Training & Development"], "post_time": "2022-01-17T01:51:47Z", "salary": {"currency": null, "max": null, "min": null, "period": "monthly", "term": null}, "salary_visible": false, "title_keywords": ["senior human resources officer"], "responsibilities": ["management", "schedules", "quality", "coordinate with", "design", "handle enquiries and complaints", "professional manner", "ad hoc tasks", "customer service", "plan", "liaise with"], "requirements": {"degrees": ["degree or above"], "majors": ["hospitality management", "related disciplines"], "languages": ["cantonese", "english", "chinese"], "language_level": ["good command"], "hard_skills": ["excel", "chinese word processing", "word", "powerpoint"], "soft_skills": ["communication skills", "independent", "advanced", "work under pressure"], "languages_combined": [{"language": "cantonese", "language_level": ["good command"]}, {"language": "english", "language_level": ["good command"]}, {"language": "chinese", "language_level": []}]}, "experience_required": {"duration": ["2 years", "minimum 5 years"], "field": ["service industry", "customer services", "marketing", "relevant experience", "supervisory level"]}}, {"job_id": "100003009046491", "location_code": "hk", "company": "HKIA Services Holdings Limited", "job_title": "Assistant Learning & Development Manager", "description": "Responsibilities:\n\nProvide quality property management service for a portfolio of residential properties\u00a0\nMonitor the maintenance, security and cleaning services of the properties\nHandle enquiries, complaints and emergency incidents\nPerform administrative duties and ad-hoc assignments\n\nRequirements:\n\nDiploma or above in any disciplines, preferably in Property & Facility Management or relevant disciplines\nAt least 2 years\u2019 experiences in property management\nIndependent with good communication skill and able to work under pressure\nGood customer service skill\nAdvanced knowledge of Excel, Word, PowerPoint and Chinese Word Processing is essential\nGood command of both written and spoken English and Cantonese\nAttractive compensation package including competitive salary,\u00a0up to\u00a022 days Annual Leave and 5 days work as well as excellent career prospects will be offered. Interested parties please send full resume including your present and expected salaries by clicking \"Apply Now\".\n\n(Personal data collected would be used in accordance with our Statement on Employment-Related Data Usage, which is available at\u00a0http://www.chineseestates.com\u00a0or upon request made to the Company\u2019s Human Resources Manager. Applicants who are not invited for interview within six weeks may consider their applications unsuccessful. All personal data of unsuccessful candidates will be destroyed after six months.)", "employment_types": ["Full Time", "Permanent"], "selling_points": ["Training & Development", "Training Programs", "Attractive Package"], "locations": ["Airport Area"], "categories": ["Admin & HR", "Others", "Education", "Others", "Training & Development"], "post_time": "2022-01-13T12:00:20Z", "salary": {"currency": null, "max": null, "min": null, "period": "monthly", "term": null}, "salary_visible": false, "title_keywords": ["manager", "assistant"], "responsibilities": ["management", "maintenance", "ad-hoc assignments", "quality", "monitor", "handle enquiries", "administrative duties", "cleaning"], "requirements": {"degrees": ["diploma or above"], "majors": ["any disciplines"], "languages": ["cantonese", "english", "chinese"], "language_level": ["good command"], "hard_skills": ["excel", "chinese word processing", "word", "powerpoint"], "soft_skills": ["independent", "advanced", "communication skill", "customer service", "work under pressure"], "languages_combined": [{"language": "cantonese", "language_level": ["good command"]}, {"language": "english", "language_level": ["good command"]}, {"language": "chinese", "language_level": []}]}, "experience_required": {"duration": ["at least 2 years"], "field": ["management"]}}, {"job_id": "100003009045583", "location_code": "hk", "company": "Uni-China (Business) Management Limited", "job_title": "Senior People Culture Development Officer / Training Officer", "description": "Provide full spectrum of secretarial support to senior executive\nManage calendar, arrange business meetings and daily appointments\nHandle memo, reports, news clippings and other documents\nProvide administrative and clerical support to department\nHandle ad hoc projects or duties as assigned\nRequirements:\n\nTertiary education or above with formal secretarial training\nAt least 3 years' relevant experience, preferably in sizeable organization\nExperience in serving senior management\nMeticulous, well-organized, reliable and able to work independently\nMature, self-motivated with excellent interpersonal and communication skills\nGood command of both written and spoken English and Chinese. Mandarin in advantage.\nProficient in MS Word, Excel, Chinese Word Processing and PowerPoint\nImmediate available is an advantage\nAttractive compensation package including competitive salary, up to 22 days Annual Leave and 5 days work as well as excellent career prospects will be offered. Interested parties please send full resume including your present and expected salaries by clicking \"Apply Now\".\n\n(Personal data collected would be used in accordance with our Statement on Employment-Related Data Usage, which is available at http://www.chineseestates.com or upon request made to the Company\u2019s Human Resources Manager. Applicants who are not invited for interview within six weeks may consider their applications unsuccessful. All personal data of unsuccessful candidates will be destroyed after six months.)", "employment_types": ["Full Time", "Permanent"], "selling_points": ["Engage in all employer branding programs", "Classroom trainings, on-site guidance & briefing", "Manage presentation reflecting company values"], "locations": ["Lai Chi Kok"], "categories": ["Admin & HR", "Others", "HR Director / Manager", "Training & Development"], "post_time": "2022-01-13T08:08:02Z", "salary": {"currency": null, "max": null, "min": null, "period": "monthly", "term": null}, "salary_visible": false, "title_keywords": ["officer"], "responsibilities": ["memo", "communication", "ad hoc projects", "reports", "secretarial support", "administrative and clerical support", "senior management"], "requirements": {"degrees": [], "majors": [], "languages": ["english", "chinese", "mandarin"], "language_level": ["advantage", "good command", "proficient"], "hard_skills": ["excel", "chinese word processing", "powerpoint", "ms word"], "soft_skills": ["meticulous", "work independently", "self-motivated", "communication skills", "well-organized", "mature", "reliable", "interpersonal"], "languages_combined": [{"language": "english", "language_level": ["good command"]}, {"language": "chinese", "language_level": ["good command", "proficient"]}, {"language": "mandarin", "language_level": ["advantage"]}]}, "experience_required": {"duration": ["at least 3 years"], "field": ["management", "relevant experience"]}}, {"job_id": "100003009045806", "location_code": "hk", "company": "Beijing Tong Ren Tang Chinese Medicine Company Limited", "job_title": "HR Officer", "description": "Oversee and manage security activities for the Group\u2019s designated properties\nEnsure the day-to-day security service meets the specification and supervise contractors to improve the security standards\nChecking on security contractor\u2019s KPI\nEnsure the day-to-day site control meets safety standards and client\u2019s expectations\nManage the contractors from end to end including service and pricing\nResponsible for team establishment and recruit new team members\nTraining of security guards and frontline staff\nReviewing work schedules when necessary\nAd hoc tasks assigned by the management\n\n\u00a0What we are looking for:\n\nTertiary education\nMinimum 5 years work experience in Security Services with management experience\nExperience in preparing tenders and operations manual\nIndependent with good communication skills and able to work under pressure\nA valid Hong Kong driving license is an advantage\nAdvanced knowledge of Excel, Word, PowerPoint and Chinese Word Processing is essential\nGood command of both written and spoken English and Cantonese\nCandidates with less experience will be considered as Guard Trainer & Site Inspector\n\nAttractive compensation package including competitive salary, up to 22 days Annual Leave, 5-day work as well as\u00a0excellent career prospects will be offered.\u00a0 Interested parties please send full resume including your present and expected salaries by clicking \u201cApply Now\u201d.\n\n(Personal data collected would be used in accordance with our\u00a0Statement on Employment-Related Data Usage, which is available at\u00a0www.chineseestates.com\u00a0or upon request made to the Company\u2019s Human Resources Manager. \u00a0Applicants who are not invited for interview within six weeks may consider their applications unsuccessful. \u00a0All personal data of unsuccessful candidates will be destroyed after six months.)", "employment_types": ["Full Time"], "selling_points": [], "locations": ["Wan Chai"], "categories": ["Admin & HR", "HR Supporting Staff", "Recruitment / Executive Search", "Training & Development"], "post_time": "2022-01-13T08:45:56Z", "salary": {"currency": null, "max": null, "min": null, "period": "monthly", "term": null}, "salary_visible": false, "title_keywords": ["hr officer"], "responsibilities": ["control", "management", "supervise contractors", "schedules", "operations", "ad hoc tasks", "checking", "communication", "safety standards", "work under pressure"], "requirements": {"degrees": [], "majors": [], "languages": ["cantonese", "english", "chinese"], "language_level": ["good command"], "hard_skills": ["excel", "chinese word processing", "word", "powerpoint"], "soft_skills": ["communication skills", "independent", "advanced", "responsible", "work under pressure"], "languages_combined": [{"language": "cantonese", "language_level": ["good command"]}, {"language": "english", "language_level": ["good command"]}, {"language": "chinese", "language_level": []}]}, "experience_required": {"duration": ["minimum 5 years"], "field": ["management", "security"]}}, {"job_id": "100003009051290", "location_code": "hk", "company": "Hutchison Telecommunications (Hong Kong) Limited", "job_title": "Senior / Human Resources Specialist (Talent Acquisition)", "description": "Reporting to the Senior HR Manager, talent acquisition function is responsible for supporting the overall strategic talent sourcing by providing market intelligence and direct sourcing strategies to identify and attract suitable candidates across different divisions and functions.\n\n\nResponsibilities:\n\nDirect source and engage talent through social media, networks, competitive intelligence and other innovative channels\nSet up direct candidate sourcing strategies and candidate outreach to fulfil current sourcing requirements and ongoing workforce plans\nWork closely with HRBP and line managers to ensure the understanding of sourcing requirements, and keep track on feedbacks, priorities and challenges to ensure sourcing effectiveness\nProactively develop and manage talent pipelines and databases for current and future business initiatives\nProvide and research for market intelligence and industry trends\nApply HR principles, concepts and industry practices in relation to HR initiatives and projects\nPrepare analytical reports and other ad hoc projects as assigned\n\nRequirements:\n\nA tertiary qualification ideally in HR discipline\nAt least 4 years\u2019 hands-on direct candidate sourcing experience in sizable company\nCapability on passive candidates\u2019 direct outreach, engagement and cultivation\nExcellent communication skills in English and Chinese\nStrong analytical skills, detail-minded, agile with positive mindset\n\nApart from competitive remuneration package and exciting opportunity for career development within the Group, we provide attractive employee benefits such as free company shuttle, free company SIM card and preferential SIM plan offers, comprehensive medical & insurance schemes, as well as full range of other employee well-being provisions.\u00a0\n\nInterested parties, please send in your profile with your salary expectation to connie.chong@ hthk.com\u00a0\n\nWe are an equal opportunity employer and welcome applications from all qualified candidates. Personal data collected will be treated in the strictest confidence and handled confidentially by authorised personnel for recruitment-related purposes only within the CK Hutchison Group of companies. The personal data of unsuccessful applicants will be destroyed after the recruitment exercise pursuant to the requirements of the Personal Data (Privacy) Ordinance in Hong Kong.", "employment_types": ["Full Time", "Permanent", "Temporary", "Contract"], "selling_points": [], "locations": ["Kwai Tsing Area"], "categories": ["Admin & HR", "Compensation & Benefits", "Recruitment / Executive Search", "Training & Development"], "post_time": "2022-01-15T07:19:00Z", "salary": {"currency": null, "max": null, "min": null, "period": "monthly", "term": null}, "salary_visible": false, "title_keywords": ["human resources specialist"], "responsibilities": ["social media", "business initiatives", "hr", "develop", "reports", "ad hoc projects", "databases", "plans"], "requirements": {"degrees": [], "majors": [], "languages": ["english", "chinese"], "language_level": ["excellent"], "hard_skills": ["agile", "analytical skills"], "soft_skills": ["detail-minded", "communication skills", "agile", "positive mindset", "analytical skills", "hands-on", "comprehensive"], "languages_combined": [{"language": "english", "language_level": ["excellent"]}, {"language": "chinese", "language_level": ["excellent"]}]}, "experience_required": {"duration": ["at least 4 years"], "field": []}}, {"job_id": "100003009044759", "location_code": "hk", "company": "Macleans Consulting International Limited", "job_title": "Senior Manager - Learning and People Development (HR L&D) [Biotechnology]", "description": "About our client\nA Fast-growing Global Biotechnology company, its headquarter is in Hong Kong with offices in APAC & Europe, who is seeking a NEW Team Head about Learning & People Development, reports to the Chief People Officer (Global).\n\nEnergetic, move fast and develop a lot of ideas\nCorporate experience with regional exposure\nAnalyze & Design Training programs\nFluent English and Chinese Speaking\nComfortable with hands-on operations\n\nResponsibilities\n\n\nOversee the company\u2019s people development plan and support culture building roadmap;\nBuild up the team and function in learning and development area for the company;\nFormulate strategy and drive initiatives on leadership development and performance enhancement;\nAdvise leadership team on functional development needs;\nStrengthen the communication among all regions through establishing regular and effective channels.\nRequirements\n8+ years of relevant experience and recent people management experience;\nTrack record in building L&D function and leading culture change, experience in consulting capacity is a plus;\nRich experience in implementing L&D initiatives as facilitator and project manager;\nAbility to drive projects and navigate in dynamic and regional set up, preferably hyper-speed growth environment;\nProactive and highly tactful in stakeholder management;\nExcellent presentation and audience engagement skills;\nHigh proficiency in speaking and writing Chinese and English;\nComfortable with hands-on tasks and fast-paced working environment.\nTo apply, please click on the \u2018Apply Now\u2019 button or contact Nick Chow at (852) 3502-2637 for a confidential discussion. Alternatively, email your resume (with your notice period, current and expected salary) to\u00a0nick.chow@macleansgroup .com\n\nYour interest will be treated in strict confidence and only shortlisted candidates will be notified.\n", "employment_types": ["Full Time", "Permanent"], "selling_points": ["Biotechnology, Energetic Team; Fast-growing", "Regional exposure; Corporate exp. is prefer", "Fluent English & Chinese Speaking"], "locations": ["Not Specified"], "categories": ["Admin & HR", "Administration / Operation Manager", "Others", "Training & Development"], "post_time": "2022-01-13T06:10:29Z", "salary": {"currency": null, "max": null, "min": null, "period": "monthly", "term": null}, "salary_visible": false, "title_keywords": ["senior manager", "hr"], "responsibilities": ["communication", "plan"], "requirements": {"degrees": [], "majors": [], "languages": ["english", "chinese"], "language_level": ["proficiency"], "hard_skills": ["plus", "dynamic"], "soft_skills": ["confidence", "hands-on", "dynamic", "proactive", "tactful", "presentation"], "languages_combined": [{"language": "english", "language_level": ["proficiency"]}, {"language": "chinese", "language_level": ["proficiency"]}]}, "experience_required": {"duration": ["8+ years"], "field": ["people management", "relevant experience", "consulting"]}}, {"job_id": "100003009042664", "location_code": "hk", "company": "China Telecom Global Limited", "job_title": "Assistant/Deputy Training & Development Manager", "description": "Key Responsibilities:\n\nPartner with business leaders to analyze current and future capability development needs and figure out effective training interventions, not only close the current performance gaps, but also prepare for future business development\nLead annual/additional functional training needs survey, design and execute the relevant learning plan and activities\nDesign global-level leadership development architecture for all level leaders, formulate annual training plan and suggest solutions, effectiveness measurement methodology and execute the specific learning programs\nAssist in company-level large business capability development program to support organizational digital transformation and business revolution\nSource, consult, and work together with a range of external consultants to design and deliver right corporate training programs\nSupport organization and talent development program if needed\nPartner with other regions colleagues to organize global-level training activities and share best practices\nAssist in other large-scale T&D program delivering and ad hoc projects as assigned\n\nRequirements:\n\nDegree or above in Human Resources Management, or related disciplines\nMinimum 5\u00a0years\u2019 training experience in sizable company, with hands-on experience in talent/ training management\nAble to work independently under pressure and prioritize work\nStrong project management skills with a focus on detailed execution.\nGood facilitating and presenting skills to large/diverse audience, good training needs survey/analysis and course design ability\nGood team player with super-collaboration mindset\nGood command of both English and Chinese (fluency in spoken Mandarin), and good at writing small articles\nProficient in Microsoft Office (Word, Excel, PPT) and Chinese Word Processing\n\n\n\nWe offer 5 days work, competitive salary package and attractive career development opportunities to the right candidate.\u00a0\n\nInterested parties please email your full resume with your current & expected salary to us.\n\nApplicants not invited for interview within 3 months may assume their applications unsuccessful.\u00a0\n\nIf you are interested in other job opportunities, please check with below career website.\n\nPersonal data collected would be used for recruitment purpose only.", "employment_types": ["Full Time", "Permanent"], "selling_points": ["Min 5 years\u2019 training exp in sizable company", "Long term career path and development", "Competitive Salary/Double Pay/Bonus/Medical"], "locations": ["Wan Chai"], "categories": ["Admin & HR", "Others", "Training & Development"], "post_time": "2022-01-12T08:19:00Z", "salary": {"currency": null, "max": null, "min": null, "period": "monthly", "term": null}, "salary_visible": false, "title_keywords": ["manager", "assistant"], "responsibilities": ["training activities", "measurement", "design", "ad hoc projects", "plan", "architecture"], "requirements": {"degrees": ["degree or above"], "majors": ["related disciplines"], "languages": ["english", "chinese", "mandarin"], "language_level": ["fluency", "proficient", "good command", "good"], "hard_skills": ["small", "excel", "chinese word processing", "microsoft office", "analysis", "word", "project management", "focus"], "soft_skills": ["work independently", "good team player", "under pressure", "project management skills", "prioritize", "diverse", "hands-on", "focus", "detailed"], "languages_combined": [{"language": "english", "language_level": ["fluency", "good command", "good"]}, {"language": "chinese", "language_level": ["fluency", "proficient", "good command", "good"]}, {"language": "mandarin", "language_level": ["fluency", "good command", "good"]}]}, "experience_required": {"duration": ["minimum 5 years"], "field": ["management", "training"]}}, {"job_id": "100003009040036", "location_code": "hk", "company": "Hong Yip Service Company Limited", "job_title": "Training Officer (5-day work) (1-year Contract)", "description": "Job Responsibilities:\n\n\nDesign and develop training programs to enhance knowledge, skills as well as service standards of staff\nSupport on the launch of a new Training Management System and enhancement of e-Learning platform/mobile app learning platform\nFormulate, maintain and update all training materials, including in-class training and e-learning / mobile app learning materials in alignment with the prevailing operational developments and corporate training directives\nCoordinate the pre- and post-training logistics with internal or external parties to ensure smooth delivery of training initiatives\nEngage in the conduct of Internal audit exercises, the evaluation of the effectiveness of Training and Development activities and follow-up actions\nHandle training administration work\nInvolve in other ad-hoc projects as assigned by superior\n\nJob Requirements:\n\n\nHolder of Degree/ Higher Diploma in Human Resources Management or related discipline\nAt least 3 years\u2019 solid experience in training and development field, preferably gained in sizeable companies\nA good team player with the ability to build and maintain cohesive working relationship with internal stakeholders\nDetail-oriented, well-organized with excellent inter-personal, communication and presentation skills\nGood command of written and spoken English & Chinese\nProficient in MS Excel, Word and PowerPoint\nImmediate availability would be a definite advantage\n\n\u00a0Candidates with less experience will be considered as Assistant Training Officer.\n\n\u00a0We provide attractive remuneration package and fringe benefits for the right candidate.\u00a0 Interested parties please send detailed resume with current & expected salaries via\u00a0\u201cApply Now\u201d\u00a0or send in your application through the Careers section in our Corporate Website:\u00a0http://www.hongyip.com/Careers.\n\nHong Yip is an Equal Opportunity Employer.\u00a0 Personal data collected will be used for recruitment purpose only.\u00a0", "employment_types": ["Contract"], "selling_points": ["Wholly owned subsidiary of Sun Hung Kai Properties", "At least 3 years\u2019 solid experience in T&D field", "Holder of Degree/ Higher Diploma in HRM"], "locations": ["Kwai Fong"], "categories": ["Admin & HR", "Clerical / Admin Staff", "HR Supporting Staff", "Training & Development"], "post_time": "2022-01-12T00:58:43Z", "salary": {"currency": null, "max": null, "min": null, "period": "monthly", "term": null}, "salary_visible": false, "title_keywords": ["officer"], "responsibilities": ["management", "mobile app", "internal audit", "external parties", "design and develop", "coordinate", "service standards", "maintain", "logistics", "evaluation", "ad-hoc projects", "administration"], "requirements": {"degrees": ["diploma", "degree"], "majors": [], "languages": ["english", "chinese"], "language_level": ["good command"], "hard_skills": ["ms excel", "word", "powerpoint"], "soft_skills": ["good team player", "inter-personal", "well-organized", "cohesive", "detail-oriented", "communication", "presentation skills"], "languages_combined": [{"language": "english", "language_level": ["good command"]}, {"language": "chinese", "language_level": ["good command"]}]}, "experience_required": {"duration": ["at least 3 years"], "field": ["development", "training"]}}, {"job_id": "100003009050798", "location_code": "hk", "company": "United Christian Nethersole Community Health Service", "job_title": "Human Resources Officer", "description": "Responsibilities:\n\nProvide full spectrum of human resources support including but not limited to recruitment, payroll administration, compensation and benefits, performance management, training and staff relations;\nAble to manage monthly payroll, final payment and related calculation via system independently;\nAssist in reviewing and formulating HR policies and procedures;\nEnsure compliance with employment and related legislations;\nPrepare and maintain documentation and reports from staff onboarding to offboarding; and\nOpportunities to participate in ad hoc projects as assigned.\n\nRequirements:\n\nDiploma or Degree holder in Human Resources or related disciplines;\nMinimum 4-5 years\u2019 relevant experience with exposure in NGO will be an advantage but not a must;\nWell-versed in Hong Kong Employment Ordinance;\nDetail-minded, self-motivated and demonstrates ability to work independently and contributes as a strong team player;\nExcellent problem-solving, communication and organizational skills;\nExcellent command of both spoken and written English and Chinese;\nProficiency in MS Word, Excel and Chinese word processing;\nImmediate available is preferred;\nCandidate with more experience may be considered for a more senior role\n\nStaff Benefits:\n\nRegular Sunday and Public Holidays off\n14 to 18 days\u2019 annual leave entitlement\nMedical benefits to staff and dependent\nOn-the-job training and training sponsorship & study leave\n\nInterested parties please send full resume with last and expected salary to Human Resources Unit, United Christian Nethersole Community Health Service, L1, KEC Administrative Building, No. 2 Po Ning Lane, Hang Hau, Tseung Kwan O with job reference no. marked on the envelope or by clicking \"Apply Now\"\n\n(Applicants not invited for interview within 4 weeks from the closing date may consider their applications unsuccessful. All personal data collected will be treated in strict confidence and will only be used for recruitment related purpose.)", "employment_types": ["Full Time", "Contract"], "selling_points": [], "locations": ["Tseung Kwan O"], "categories": ["Admin & HR", "Compensation & Benefits", "Recruitment / Executive Search", "Training & Development"], "post_time": "2022-01-14T11:25:26Z", "salary": {"currency": null, "max": null, "min": null, "period": "monthly", "term": null}, "salary_visible": false, "title_keywords": ["human resources officer"], "responsibilities": ["management", "policies", "hr", "procedures", "ensure compliance", "payment", "recruitment", "reports", "ad hoc projects", "maintain documentation", "payroll", "legislations", "administration"], "requirements": {"degrees": ["diploma", "degree holder"], "majors": ["related disciplines"], "languages": ["english", "chinese"], "language_level": ["excellent", "proficiency"], "hard_skills": ["excel", "chinese word processing", "hong kong employment ordinance", "problem-solving", "ms word"], "soft_skills": ["detail-minded", "organizational skills", "self-motivated", "work independently", "problem-solving", "communication", "team player"], "languages_combined": [{"language": "english", "language_level": ["excellent"]}, {"language": "chinese", "language_level": ["excellent", "proficiency"]}]}, "experience_required": {"duration": ["minimum 4-5 years"], "field": ["relevant experience"]}}, {"job_id": "100003009048008", "location_code": "hk", "company": "OnePlatform Wealth Management Limited", "job_title": "Asst./ Manager, Training (Insurance Agency and Distributor Training - Funds and Securities focus)", "description": "Due to our business expansion, we are looking for high calibre candidates to share our vision and venture our success.\n\nThe function of the department will be focus on the insurance agency and distributor training.\n\nResponsibilities:\n1. Develop and train consultancy leaders / recruiters across teams in leadership and management skills\n\nPlan, develop, deliver and evaluate leaders/recruiters training initiatives, including collaboration with teams to develop training plans with timelines, identify training participants and stakeholders, implement, evaluate, and revamp training programs; provide refresher trainings whenever necessary.\nPlan, deliver and evaluate train-the-trainers (TTT) programs for leadership and management skills, in order to develop a cadre of leadership and management trainers across teams.\nLead the process of ensuring ongoing uptake and transfer of leadership and management skills and best practices to the job.\nExpand company\u2019s current efforts to develop and support a mentoring program for leadership and management skills, as well as mentoring skills training.\n2. Create training curricula and other capacity building tools for leadership and management skills building\n\nCreate and revise training curricula and other capacity building tools for leadership and management skills in collaboration with various teams. This involves assessing needs, defining learning objectives, writing and editing content, tailoring content to the local context, conceptualizing content into the appropriate medium, and developing methods of assessment. Outputs include facilitator manuals, participant handbooks, slide presentations, flip charts, job aids, pre- and post-tests, and other materials.\nReview and edit curricula and other tools created by consultants and external partners to ensure consistent quality, content, methodologies, approach, and style.\nDevelop and manage surveys and other tools and processes to assess ongoing needs for leadership development.\n\nRequirements:\n\n\nUniversity graduate in Investment, Economics, Finance, Business, Management or relevant discipline.\nMinimum 10 years training experience in financial institutions, experience in designing, developing, and editing professional-level training materials for adults is an advantage.\nExperience in Investment Training (funds and securities) would be an advantage.\nFLMI / LUTCF/ CFP/ CFA/ RFP qualifications are a must.\nExperience delivering training to a range of audiences (lower and higher-level professionals, training of trainers, etc.)\nDemonstrated understanding of adult learning theory, interactive skill building, and appropriate participatory methodologies for culturally diverse communities and a variety of literacy levels.\nDemonstrated possession of excellent interpersonal and organizational skills; written and oral communication skills.\nDemonstrated ability managing complexity and prioritizing multiple tasks.\nAbility to work productively in highly collaborative settings while also able to function independently.\nDemonstrated ability to interact professionally with culturally diverse staff, clients, and consultants.\nFamiliarity with traditional and modern training methods (mentoring, coaching, on-the-job or in classroom training, e-learning, zoom, workshops, simulations, etc.).\nKnowledge on investment and insurance products and financial markets.\nAnalytical with excellent problem-solving skill and strategic mindset\nMature, responsible with good communication and interpersonal skills.\nGood command of written and spoken English, Cantonese and Mandarin.\nProficient in MS Office applications.\nExcellent command of written and spoken English and Chinese.\nCandidate with less experience will be considered as Assistant Manager.\n\nWe offer competitive remuneration including career prospects to the right candidate. Interested parties please send detailed resume with availability, current and expected salaries to\u00a0Human Resources Department, OnePlatform Wealth Management Limited, Trust Tower, 68 Johnston Road, Wan Chai, Hong Kong\u00a0or by clicking the\u00a0Apply Now\u00a0button and upload your CV and cover letter.\n\n(All applications will be treated in strict confidence and used for recruitment purpose within OnePlatform Wealth Management Limited only. All applicants are kept on file 6 months from the date of the application.)", "employment_types": ["Full Time", "Permanent"], "selling_points": ["Develop and train consultancy leaders / recruiters", "Plan train-the-trainers (TTT) programs", "Create training curricula"], "locations": ["Wan Chai"], "categories": ["Banking / Finance", "Financial Services", "Fund Management", "Admin & HR", "Training & Development"], "post_time": "2022-01-14T04:28:20Z", "salary": {"currency": null, "max": null, "min": null, "period": "monthly", "term": null}, "salary_visible": false, "title_keywords": ["manager"], "responsibilities": ["management", "revamp", "review", "teams", "developing", "presentations", "develop", "evaluate", "quality", "plan", "plans", "editing", "conceptualizing"], "requirements": {"degrees": ["university graduate"], "majors": ["business", "finance", "economics"], "languages": ["cantonese", "english", "chinese", "mandarin"], "language_level": ["excellent", "good command"], "hard_skills": ["workshops", "cfa", "problem-solving", "ms office"], "soft_skills": ["organizational skills", "oral", "communication skills", "independently", "responsible", "multiple tasks", "problem-solving", "collaborative", "mature", "diverse", "learning", "communication and interpersonal skills", "interpersonal", "prioritizing"], "languages_combined": [{"language": "cantonese", "language_level": ["good command"]}, {"language": "english", "language_level": ["excellent", "good command"]}, {"language": "chinese", "language_level": ["excellent"]}, {"language": "mandarin", "language_level": ["good command"]}]}, "experience_required": {"duration": ["minimum 10 years"], "field": ["training", "editing", "securities", "developing", "investment", "financial institutions"]}}, {"job_id": "100003009046921", "location_code": "hk", "company": "Harbour City Estates Ltd", "job_title": "PERSONNEL ASSISTANT (TEMPORARY)", "description": "Job Responsibilities:\n\nHandle attendance administration, overtime and part-time payment calculation as well as prepare related reports\nPerform HRMS input and prepare on-boarding and off-boarding formalities\nProvide administrative and clerical support in training and development initiatives, implementation of HR systems and ad hoc duties as assigned\nRequirements:\n\nDegree holder with 1 year's relevant experience, preferably gained in sizeable organization\nKnowledge of Employment Ordinance and related regulations\nPleasant with good interpersonal and communication skills\nOrganized, attentive to details and of high work accuracy\nProficient in MS Word, Excel and Chinese word processing\nGood command of written and spoken English and Chinese\nImmediate availability is highly preferred\nWe offer 5-day week and competitive salary package that commensurate with experience and qualifications. Interested parties are invited to send full resume stating contact telephone number, date available, present and expected salary to our recruitment email address\n(Personal data provided will be used strictly in accordance with the Company\u2019s personal data policy which is available upon request.)", "employment_types": ["Full Time", "Temporary"], "selling_points": ["Attendance administration & payment calculation", "Provide administrative and clerical support", "1 year's relevant experience"], "locations": ["Tsim Sha Tsui"], "categories": ["Admin & HR", "Clerical / Admin Staff", "HR Supporting Staff", "Training & Development"], "post_time": "2022-01-15T03:49:33Z", "salary": {"currency": null, "max": null, "min": null, "period": null, "term": null}, "salary_visible": false, "title_keywords": ["assistant"], "responsibilities": ["ad hoc duties", "attendance", "hr", "systems", "implementation", "payment", "reports", "administrative and clerical support", "administration"], "requirements": {"degrees": ["degree holder"], "majors": [], "languages": ["english", "chinese"], "language_level": ["good command", "proficient"], "hard_skills": ["excel", "chinese word processing", "ms word"], "soft_skills": ["organized", "communication skills", "attentive to details", "pleasant", "interpersonal"], "languages_combined": [{"language": "english", "language_level": ["good command"]}, {"language": "chinese", "language_level": ["good command", "proficient"]}]}, "experience_required": {"duration": ["1 year"], "field": ["relevant experience"]}}, {"job_id": "100003009046793", "location_code": "hk", "company": "Cinnox Limited", "job_title": "Assistant HR Officer / HR Assistant (Immedately available)", "description": "WHAT you be doing in this role:\n\nAssist in full spectrum of HR functions including talent acquisition, training & development, compensation & benefits and employee relations etc.;\nHandle end-to-end recruitment process and support colleagues' life cycle administration including on-boarding and off-boarding logistics arrangement\nMaintain HR database/record management, medical insurance administration, filing system\nHandle and follow up internal colleagues' inquiries\nPrepare HR reports for management review\nImplement employee engagement activities and opportunities\nAdminister online learning management system\nParticipate in other HR initiatives and ad-hoc projects as assigned\nWHO are we looking for:\nHigh Diploma or above in Human Resources Management or other related disciplines\n1 year of HR related working experience, experience in Information Technology / Telecommunication industry is highly preferred\nGood knowledge of labor laws and regulations is preferred\nMature with good communication and interpersonal skills\nGood command of both written and spoken English & Chinese\nIndependent, proactive with positive attitude, enjoy working in a dynamic and fast-paced environment\nImmediate available is preferred\n***Candidates with more experience will be considered as Assistant HR Officer***\n\nWe offer 5 days\u2019 work, medical insurance, free lunch, competitive salary package and attractive career development opportunities to the right candidate.\u00a0Interested parties please send your full resume with date of availability, present and expected salaries by clicking \"Apply Now\".\n\n\nTo protect the privacy of personal data, all applications will be treated in strict confidence. Personal data collected will be used for recruitment purposes only. Applicants not hearing from us within 6 weeks may consider their applications unsuccessful. We may also consider their application for other or future vacancies. Personal data of unsuccessful applicants will be retained for a maximum period of 6 months.", "employment_types": ["Full Time", "Permanent"], "selling_points": ["1+ year HR experience with IT/Telecom knowledge", "Familiar with HR Operation, strong in HK labor law", "5 day work, medical Benefit and free luncheon"], "locations": ["Kowloon Bay"], "categories": ["Admin & HR", "HR Supporting Staff", "Recruitment / Executive Search", "Training & Development"], "post_time": "2022-01-14T01:09:54Z", "salary": {"currency": null, "max": null, "min": null, "period": "monthly", "term": null}, "salary_visible": false, "title_keywords": ["hr officer", "hr assistant", "assistant"], "responsibilities": [], "requirements": {"degrees": [], "majors": [], "languages": [], "language_level": [], "hard_skills": [], "soft_skills": [], "languages_combined": []}, "experience_required": {"duration": [], "field": []}}, {"job_id": "100003009043897", "location_code": "hk", "company": "Hong Kong Sheng Kung Hui Welfare Council Limited", "job_title": "\u52a9\u7406\u8a08\u5283\u4e3b\u4efb Assistant Project Officer (Ref\uff1aMOSS/APO/20211203-2)", "description": "\u689d\u4ef6\ufe30\n\n\u4e2d\u5b78\u6703\u8003\u4e2d\u6587\u53ca\u82f1\u6587(\u8ab2\u7a0b\u4e59)\u5408\u683c\u6216\u4e2d\u5b78\u6587\u6191\u8003\u8a66\u540c\u7b49\u7b49\u7d1a\n\u9808\u638c\u63e1\u4e2d\u82f1\u6587\u96fb\u8166\u6587\u66f8\u8655\u7406\uff0c\u719f\u6089\u8edf\u4ef6(Word\u3001Excel\u53caPowerPoint)\u4e4b\u61c9\u7528\u53ca\u5177\u6587\u4ef6\u6574\u7406\u80fd\u529b\n\u5177\u5169\u5e74\u6216\u4ee5\u4e0a\u5f71\u7247\u62cd\u651d\u526a\u63a5\u3001\u7db2\u4e0a\u8a2d\u8a08\u3001\u7e6a\u5716\u5de5\u4f5c\u7d93\u9a57\u8005\u512a\u5148\n\n\u8077\u8cac\ufe30\n\u8ca0\u8cac\u5354\u52a9\u4e2d\u5fc3\u8655\u7406\u651d\u9304\u5f71\u7247\u3001\u7db2\u9801\u88fd\u4f5c\u53ca\u8ddf\u9032\uff0c\u53ca\u5354\u52a9\u9752\u5e74\u6d3b\u52d5\u7b49\u5de5\u4f5c\u3002\u9700\u5e73\u65e5\u665a\u4e0a\u6216\u661f\u671f\u516d\u3001\u65e5\u7576\u503c\u6216\u5916\u51fa\u5de5\u4f5c\u3002\n\n\n\u6b64\u8077\u4f4d\u540c\u5de5\u6703\u5148\u4ee51\u5e74\u5408\u7d04\u8058\u7528\uff0c\u518d\u7e8c\u8a021\u5e74\u5408\u7d04\uff0c\u5728\u5b8c\u62102\u5e74\u5408\u7d04\u671f\u53ca\u8868\u73fe\u826f\u597d\u8005\uff0c\u6703\u6539\u8058\u70ba\u9577\u671f\u5408\u7d04\u540c\u5de5\u3002\n\n\u5168\u8077\u54e1\u5de5\u53ef\u4eab\u6709\u4ee5\u4e0b\u5b8c\u5584\u798f\u5229\uff1a\n\u53ef\u4eab\u6709\u6709\u85aa\u5e74\u504717\u5929\u3001\u516c\u773e\u5047\u671f17\u5929\u3001\u5a5a\u5047\u3001\u5206\u5a29\u5047\u3001\u6069\u6064\u5047\u3001\u4f8d\u7522\u5047\u3001\u8d85\u6642\u5de5\u4f5c\u88dc\u5047\u3001\u514d\u8cbb\u9ad4\u6aa2\u3001\u91ab\u7642\u4fdd\u96aa\u3001\u4eba\u58fd\u4fdd\u96aa\u3001\u91ab\u7642\u512a\u60e0\u3001\u50f1\u4e3b\u5f37\u7a4d\u91d1\u4f9b\u6b3e\u6309\u5e74\u8cc7\u6700\u9ad8\u53ef\u905e\u589e\u81f315%\u3001\u5728\u8077\u57f9\u8a13\u53ca\u826f\u597d\u6649\u5347\u968e\u68af\u7b49\u3002\n\n\n\u6709\u610f\u8005\u8acb\u5177\u5c65\u6b77\u5bc4(\u4fe1\u5c01\u9762\u53ca\u4fe1\u5167\u8acb\u8a3b\u660e\u8077\u4f4d\u7de8\u865f)\ufe30\u65b0\u754c\u6c99\u7530\u99ac\u978d\u5c71\u8000\u5b89\u90a8\u8000\u548c\u6a13\u5730\u4e0b \u2013 \u9999\u6e2f\u8056\u516c\u6703\u99ac\u978d\u5c71\uff08\u5357\uff09\u9752\u5c11\u5e74\u7d9c\u5408\u670d\u52d9\u4e2d\u5fc3\u7763\u5c0e\u4e3b\u4efb\u6536\u6216\u6309\"Apply Now\"\u3002\u4e00\u5207\u7533\u8acb\u8cc7\u6599\u7d55\u5c0d\u4fdd\u5bc6\u53ca\u53ea\u7528\u4f5c\u62db\u8058\u6709\u95dc\u8077\u4f4d\u3002\u5982\u65bc\u5ee3\u544a\u520a\u767b\u5f8c\u516d\u500b\u6708\u5167\u4ecd\u672a\u7372\u672c\u6703\u56de\u8986\uff0c\u5373\u5176\u7533\u8acb\u672a\u7372\u8003\u616e\uff0c\u800c\u7533\u8acb\u4eba\u4e4b\u500b\u4eba\u8cc7\u6599\u4ea6\u5c07\u5728\u5b8c\u6210\u62db\u8058\u7a0b\u5e8f\u5f8c\u92b7\u6bc0\u3002\u5982\u6b32\u53c3\u8003\u5354\u6703\u8cc7\u6599\uff0c\u8acb\u767b\u5165\u7db2\u5740\ufe30http://www.skhwc.org.hk", "employment_types": ["Full Time", "Contract"], "selling_points": [], "locations": ["Shatin Area"], "categories": ["Admin & HR", "Training & Development", "Public / Civil", "Social Services - Community / Non-profit Organization"], "post_time": "2022-01-13T18:54:54Z", "salary": {"currency": null, "max": null, "min": null, "period": "monthly", "term": null}, "salary_visible": false, "title_keywords": ["assistant project officer"], "responsibilities": [], "requirements": {"degrees": [], "majors": [], "languages": [], "language_level": [], "hard_skills": [], "soft_skills": [], "languages_combined": []}, "experience_required": {"duration": [], "field": []}}, {"job_id": "100003009044736", "location_code": "hk", "company": "Chandler Macleod Group (HK) Limited", "job_title": "Regional Retail Trainer (Luxury retail) 30k - 38K", "description": "Job Duties:\n\nAssist APAC Training Manager to deploy corporate training activities\nImplement and localize training Initiatives from headquarter for program delivery\nSelect, brief and monitor external providers/facilitators when necessary\nEnsure induction sessions for all new hires (retail and office) within appropriate formats\nDelivery of focused training sessions for the store based on local needs (with focus on Brand, Products, Selling, Customer Service & CRM topics)\nManage training logistics process (classroom settings, venue rental and its logistic, electronic equipments, training material interpretation & preparation)\nPromote and follow-up on digital training platform and relevant initiatives\nDevelop follow-up tools for the participants and on-the-job check\nCoach retail team in delivering constructive training feedback and implementations\nConduct regular store visit and attachment for preparing quick-fix workshop\nMonitor the usage of training and information material\nConsolidate and update training databases (attendance, participant name, training dates, programs, records, evaluations etc.)\n\nTRAINING NEEDS ANALYSIS\n\nWork with APAC Training Manager and local HR Managers to understand and identify the training needs from retail team\nComplete the annual training schedule on a monthly basis according to field visits and in depth observation and discussions with the teams\n\nRequirements:\n\n3 to 5 years training experience preferably in the retail industry or consultancy company with exposure in facilitation and content development\nOpen minded, inspiring, adaptable, energetic and passionate\nStrong communication and coordination skills\nExcellent time and task management skills\nAble to work independently\nFluent in English and Mandarin\nProficient in MS Office functionalities & e-learning platform\nTraveling is required", "employment_types": ["Full Time", "Permanent"], "selling_points": ["Immediately start", "Genuine development opportunity", "Multinational working environment"], "locations": ["Not Specified"], "categories": ["Education", "Others", "Admin & HR", "Training & Development"], "post_time": "2022-01-13T05:59:50Z", "salary": {"currency": null, "max": null, "min": null, "period": "monthly", "term": null}, "salary_visible": false, "title_keywords": [], "responsibilities": ["attendance", "training activities", "workshop", "analysis", "monitor", "hr", "teams", "develop", "customer service", "logistics", "schedule", "databases", "deploy"], "requirements": {"degrees": [], "majors": [], "languages": ["english", "mandarin"], "language_level": ["fluent"], "hard_skills": ["ms office"], "soft_skills": ["passionate", "work independently", "coordination skills", "adaptable", "communication", "learning", "inspiring", "open minded", "energetic"], "languages_combined": [{"language": "english", "language_level": ["fluent"]}, {"language": "mandarin", "language_level": ["fluent"]}]}, "experience_required": {"duration": ["3 to 5 years"], "field": ["retail industry", "content development", "training"]}}, {"job_id": "100003009042244", "location_code": "hk", "company": "Fairwood Fast Food Ltd", "job_title": "Senior Learning & Development Officer", "description": "Responsibilities:\n\n\nConduct & deliver field coaching for specialty restaurant front-line staff\nDesign, develop & deliver training programs, particularly on Management, Customer Services, Food Safety, Quality as well as Soft Skills\nConduct training needs analysis to align with business development\nEvaluate the effectiveness of the training activities & the learning progress\nSupport ad hoc projects & motivational events\n\nRequirements:\n\n\nDiploma/Degree holder in Human Resources Management or Hotel & Catering related disciplines\nMinimum 3-year solid training experience in F&B or Hospitality industry\nIndependent, well organized & with good interpersonal skills\nGood command spoken & written English & Chinese\nProficiency in MS Office & Chinese word processing\n\nCompetitive remuneration package will be offered to the right candidate. Interested parties please click\u00a0\"Apply Now\"\u00a0or send full resume with expected salary by 1) email to\u00a0 recruitoffice@ fairwood.com.hk\u00a0or 2) direct mail to HR Manager, 2/F TRP Commercial Centre, 18 Tanner Road, North Point, Hong Kong.\n\n\n(Data collected will be used for recruitment purpose only)", "employment_types": ["Full Time", "Permanent"], "selling_points": ["Design, develop & deliver training to front-line", "Conduct field coaching & TNA in line with business", "Diploma/Degree w/3-yr exp, exp in F&B/Hospitality"], "locations": ["North Point"], "categories": ["Hospitality / F & B", "Food & Beverage", "Admin & HR", "HR Supporting Staff", "Training & Development"], "post_time": "2022-01-12T06:43:16Z", "salary": {"currency": null, "max": null, "min": null, "period": "monthly", "term": null}, "salary_visible": false, "title_keywords": ["officer"], "responsibilities": ["management", "food safety", "training activities", "analysis", "quality", "design", "customer services", "develop", "evaluate", "ad hoc projects"], "requirements": {"degrees": ["diploma", "degree holder"], "majors": ["related disciplines", "hotel"], "languages": ["english", "chinese"], "language_level": ["proficiency", "good command"], "hard_skills": ["chinese word processing", "ms office"], "soft_skills": ["independent", "well organized", "interpersonal skills"], "languages_combined": [{"language": "english", "language_level": ["good command"]}, {"language": "chinese", "language_level": ["proficiency", "good command"]}]}, "experience_required": {"duration": ["minimum 3-year"], "field": ["hospitality industry", "f&b", "training"]}}, {"job_id": "100003009040229", "location_code": "hk", "company": "Randstad Hong Kong Limited", "job_title": "Senior Learning & Development Manager, Digital", "description": "about the company.\n\nOur client is a well known Leading Conglomerate with growing business. They are looking for a Senior Learning & Development Manager, Digital to join their HR team, they are expanding their team.\n\nabout the team.\n\nReports to the L&D Team Head within a team of 4.\n\nabout the job.\n\nUnderstand and identify the learning needs for business units and the team\nCurate and facilitate a development strategy for course contents and journey path for specific staff groups\nDesign and implement eLearning Platform aligning with LMS system\nCreate a holistic online learning experience for employees of all levels\nMonitor vendor performance and partner closely with vendors on course and content development\nBuild learning culture for employees and ensure they are adapting to it\nKeep update to date of the market trend for learning platforms and content\nFacilitate Group HR and Business units to monitor the implication of the eLearning scheme\nMaintain relationships with internal and external stakeholders\nPerform ad hoc projects as required\n\nskills & experiences required.\n\nBachelor degree in Human Resources or related field\n8+ years of solid experience in Training & Development, eLearning and online platform development experiences are essential\nOverall solid experience with digital systems\nStrong project management experience, excellent reporting skills\nFluent in English, Cantonese and Mandarin\nAble to work as an individual contributor & great communicator\n\n\nInterested parties please apply for the job by clicking the appropriate link with your updated resume, project lists, portfolio and salary details to sum.cheung@randstad.com.hk. We regret only shortlisted candidates will be contacted.", "employment_types": ["Full Time", "Permanent"], "selling_points": ["Conglomerate", "Location: Hong Kong Island", "20 days annual leave"], "locations": ["Quarry Bay"], "categories": ["Admin & HR", "Others", "HR Director / Manager", "Training & Development"], "post_time": "2022-01-12T01:56:51Z", "salary": {"currency": "HKD", "max": 54999, "min": 45000, "period": "monthly", "term": null}, "salary_visible": true, "title_keywords": ["manager"], "responsibilities": ["maintain relationships", "reporting", "hr", "systems", "monitor", "design", "project management", "reports", "ad hoc projects", "contents"], "requirements": {"degrees": ["degree", "bachelor"], "majors": [], "languages": ["cantonese", "english", "mandarin"], "language_level": ["fluent"], "hard_skills": ["project management", "vendor", "scheme"], "soft_skills": ["project management", "communicator", "learning"], "languages_combined": [{"language": "cantonese", "language_level": ["fluent"]}, {"language": "english", "language_level": ["fluent"]}, {"language": "mandarin", "language_level": ["fluent"]}]}, "experience_required": {"duration": ["8+ years"], "field": ["development", "project management", "training", "digital"]}}, {"job_id": "100003009048979", "location_code": "hk", "company": "Tiptop Consultants Ltd", "job_title": "Account Executive", "description": "Responsibilities:\nPerform professional account servicing, including preparing project track/project schedules, conducting desktop research/site visits, attending meetings with consultants, arranging and monitoring all logistics details of projects\nTake ownership of accounts and coordinate/ follow-up with clients, consultants and research team to ensure that project deliverables are met on time\nPrepare presentation slides and other training materials\nProvide on-site workshop support when required\nDevelop and maintain long-term relationships with clients\nUndertake preliminary business development work including lead generation, proposal and agreement preparation and sales follow up\n\u00a0Requirements:\nUniversity graduate\nHave 1 to 2 years\u2019 working experience is preferred.\nStrong oral and written communication skills, both in English and Chinese\nGood command of Mandarin is an advantage\nProficient in Microsoft Office\nProactive, self-motivated, positive attitude, detail-minded, good interpersonal and communication skills, team player who is eager to grow with the role\nMature in interacting with different levels of people from different industries and backgrounds", "employment_types": ["Full Time"], "selling_points": ["Account servicing", "Support consultancy and training projects", "Preliminary business development work"], "locations": ["Lai Chi Kok"], "categories": ["Sales, CS & Business Devpt", "Business Development", "Admin & HR", "Training & Development", "Account Servicing"], "post_time": "2022-01-14T07:53:41Z", "salary": {"currency": null, "max": null, "min": null, "period": "monthly", "term": null}, "salary_visible": false, "title_keywords": ["account executive"], "responsibilities": ["project deliverables", "schedules", "workshop", "monitoring", "develop", "coordinate", "maintain", "logistics", "follow-up with clients"], "requirements": {"degrees": ["university graduate"], "majors": [], "languages": ["english", "chinese", "mandarin"], "language_level": ["advantage", "good command"], "hard_skills": ["microsoft office"], "soft_skills": ["detail-minded", "communication skills", "oral", "self-motivated", "mature", "positive attitude", "team player", "proactive", "interpersonal"], "languages_combined": [{"language": "english", "language_level": []}, {"language": "chinese", "language_level": []}, {"language": "mandarin", "language_level": ["advantage", "good command"]}]}, "experience_required": {"duration": ["1 to 2 years"], "field": []}}, {"job_id": "100003009040016", "location_code": "hk", "company": "Evolution Wellness (Hong Kong) Limited", "job_title": "Training Executive (in-House)", "description": "Responsibilities:\n\nCreating training programmes that are aligned with the organisation's objectives and having a strong understanding of what these are\nActing as the go to within the business for anyone with questions or queries regarding training and development plans\nWorking closely with various leaders across the organisation and having a full understanding of their units and training requirements\nEmbracing different styles of training techniques, including e-learning, tutorial sessions or coaching\nHaving an awareness of the allocated budget and an ability to find solutions in order to implement the required training\nBuilding relationships with 3rd party training providers\nManaging the development of the HR team from a training perspective\n\nRequirements:\n\nDegree Holder in any disciplines\nAt least 3-5 years of relevant experience in L&D is highly oreferred\nExperience in Retail / Fitness / Wellness industry is an advantage\nOrganized, responsible and energetic\nTeam-player with good interpersonal skills\nProficient in E-learning is a plus\nExcellent command of spoken and written English and Chinese", "employment_types": ["Full Time"], "selling_points": [], "locations": ["Tsim Sha Tsui"], "categories": ["Beauty Care / Health", "Athletics / Fitness / Sports & Recreation", "Admin & HR", "Training & Development"], "post_time": "2022-01-12T00:25:50Z", "salary": {"currency": null, "max": null, "min": null, "period": "monthly", "term": null}, "salary_visible": false, "title_keywords": ["training executive"], "responsibilities": ["plans", "hr", "budget"], "requirements": {"degrees": ["degree holder"], "majors": ["any disciplines"], "languages": ["english", "chinese"], "language_level": ["excellent"], "hard_skills": ["plus"], "soft_skills": ["organized", "responsible", "team-player", "learning", "interpersonal skills", "energetic"], "languages_combined": [{"language": "english", "language_level": ["excellent"]}, {"language": "chinese", "language_level": ["excellent"]}]}, "experience_required": {"duration": ["at least 3-5 years"], "field": ["retail", "relevant experience"]}}, {"job_id": "100003009051291", "location_code": "hk", "company": "Hutchison Telecommunications (Hong Kong) Limited", "job_title": "Human Resources Manager", "description": "Being a prominent player in the communications industry and a member of CK Hutchison Holdings, we are looking for HR practitioners who have genuine interest in helping an organization and the peoples within, to grow and succeed.\u00a0 Depending on your strengths and career orientation, here is a chance to develop in our HR Team, commensurate with your experiences and potentials.\n\nCheck out the followings. Let us know your strengths and interests to contribute in our evolution journey.\n\nDiscover Yourself\nAttributes that will earn your early success here\n\n\neager to learn and grow\nwilling to share and contribute\nkeen to raise new ideas and different perspectives\nready to take up new challenges\n\nDiscover Your Job Opportunities\nUnleash your potential and stay ahead! Here you can...\n\nperform a BP role for individual career development i.e. staffing, talent acquisition, employee caring & engagement, training & development, and/or HR analytics, etc.\nliaise with business units and provide advices on all staffing matters (e.g. manpower requirements, staffing needs, etc)\u00a0\nwork closely with team members to deliver excellent HR services while enriching HR functional skills through involvement in projects\ngain cross HR functional exposures to build up networking and holistic knowledges, say in talent sourcing, staff activities, job evaluation, total rewards exercises, etc.\nbe a resilient individual ready to take up challenges in a dynamic yet rewarding industry for next career advancement\n\nDiscover More\nApart from the unique opportunity to fast track your career here, you will enjoy competitive remuneration package, attractive employee benefits such as free company shuttle, free company SIM card and preferential SIM plan offers, comprehensive medical & insurance schemes, as well as full range of other employee well-being provisions.\u00a0\u00a0\n\nInterested parties, please send\u00a0in your profile and salary expectation to connie.chong@ hthk.com\n\nWe are an equal opportunity employer and welcome applications from all qualified candidates. Personal data collected will be treated in the strictest confidence and handled confidentially by authorised personnel for recruitment-related purposes only within the CK Hutchison Group of companies. The personal data of unsuccessful applicants will be destroyed after the recruitment exercise pursuant to the requirements of the Personal Data (Privacy) Ordinance in Hong Kong.", "employment_types": ["Full Time", "Permanent"], "selling_points": [], "locations": ["Kwai Tsing Area"], "categories": ["Admin & HR", "Compensation & Benefits", "Recruitment / Executive Search", "Training & Development"], "post_time": "2022-01-15T07:19:00Z", "salary": {"currency": null, "max": null, "min": null, "period": "monthly", "term": null}, "salary_visible": false, "title_keywords": ["manager", "human resources"], "responsibilities": ["provide advices", "ideas", "evaluation", "hr", "develop", "plan", "career development", "liaise with", "insurance"], "requirements": {"degrees": [], "majors": [], "languages": [], "language_level": [], "hard_skills": ["dynamic"], "soft_skills": ["keen", "unique", "eager to learn", "dynamic", "comprehensive", "genuine"], "languages_combined": []}, "experience_required": {"duration": [], "field": ["hr", "team"]}}, {"job_id": "100003009042834", "location_code": "hk", "company": "HKT Teleservices, Asia", "job_title": "Training Officer", "description": "Responsibilities:\n\nTo identify training needs and develop frontline/dedicate training.\nTo conduct training courses on products and services, customer service soft-skill & system training.\nTo work closely with internal and/or external parties on implementation of training infrastructure for programs.\nTo achieve the expected training and call quality outcome.\nTo review the frontline agents call quality and QA performance.\nTo undertake ad-hoc projects / tasks as assigned.\n\nRequirements:\n\nWith 2 years of proven working experience in staff Training, development and call monitoring fields.\nWith experience in working in contact centre is an added advantage.\nStrong customer service / sales mindset, assertive and result-oriented with Customer Service experience.\nSensitive, open-minded and flexible to face and manage challenges.\nGood communication and interpersonal skills.\nSelf-motivated, can work independently and team-worker.\nExcellent command of both spoken and written English and Chinese (Cantonese / Mandarin).\nWorking knowledge of Microsoft Office applications.\n\nInterested parties please\u00a0WhatsApp\u00a09020 1238\u00a0for enquiries or click \"Apply Now\" button.", "employment_types": ["Full Time"], "selling_points": [], "locations": ["Kowloon Bay"], "categories": ["Education", "Tutor / Instructor", "Engineering", "Telecommunication / Wireless / Radio", "Admin & HR", "Training & Development"], "post_time": "2022-01-12T08:57:18Z", "salary": {"currency": null, "max": null, "min": null, "period": "monthly", "term": null}, "salary_visible": false, "title_keywords": ["officer"], "responsibilities": ["external parties", "infrastructure", "implementation", "quality", "develop", "review", "customer service", "ad-hoc projects"], "requirements": {"degrees": [], "majors": [], "languages": ["cantonese", "english", "chinese", "mandarin"], "language_level": ["excellent"], "hard_skills": ["microsoft office"], "soft_skills": ["flexible", "self-motivated", "work independently", "assertive", "open-minded", "customer service", "communication and interpersonal skills", "sensitive", "result-oriented"], "languages_combined": [{"language": "cantonese", "language_level": ["excellent"]}, {"language": "english", "language_level": ["excellent"]}, {"language": "chinese", "language_level": ["excellent"]}, {"language": "mandarin", "language_level": ["excellent"]}]}, "experience_required": {"duration": ["2 years"], "field": ["development", "customer service", "training"]}}, {"job_id": "100003009044087", "location_code": "hk", "company": "Bravo Transport Services Limited", "job_title": "Training Specialist (ENG) (Ref: JD/TS(ENG)/03/2022)", "description": "Position Description:\nThe Training Specialist (ENG) responsible to deliver good quality training courses to the colleagues and properly manage apprentice matters which includes but not limited to the areas as listed in the Duties & Responsibilities.\nWhat are we looking for?\nMandatory Requirements:\nHigher certificate or above in Motor Vehicle Engineering\nCertificate or above in Health & Safety\nHands on experiences in motor vehicle repair, preferable in bus or heavy vehicle\nCompletion in motor vehicle apprenticeship training is an advantage\nKnowledge of Motor Vehicle Engineering and Safety in Motor Vehicle Repair & Workplace\nGood team-player with interpersonal skills\nGood command of spoken and written Chinese and English\nDuties & Responsibilities include, but not limited to:\nFormulate good training materials/contents & conduct regular review\nDeliver good quality Engineering technical and safety training courses\nTake part in the regular bus captain refresher course\nTake part in the recruitment process of apprentice and prepare training schedule\nAssess apprentices\u2019 practical work done in the assignment & submit the result to VTC\nTake part in the engineering frontline staff promotion skill assessment\nRegularly review & update on the \u201cH&S Manual for Vehicle Repair\u201d\nSubmit appropriate reports to the manager on time\nAssist the manager to handle special projects & assignments when required\nWe will offer competitive remuneration package to the right candidate. Applications, with detailed qualifications, employment history, present and expected salary, and contact information, should be sent to the Head of People & Culture, Bravo Transport, 5/F., No. 8 Chong Fu Road, Chai Wan, Hong Kong.\u00a0 Applications can also be e-mailed to us. (Please quote the ref. number on your application.)\u00a0\nApplicants not contacted within 2 months from the posting date may consider their applications unsuccessful. \u00a0We are an equal opportunities employer and welcome all qualified applications.\u00a0 Personal data collected will be treated in strictly confidential and used for recruitment related purpose only.\nAll applications will be kept for a maximum period of\u00a012 months after the completion of recruitment process.", "employment_types": ["Full Time", "Permanent"], "selling_points": ["Motor Vehicle Engineering", "Health & Safety", "Training"], "locations": ["Chai Wan"], "categories": ["Engineering", "Others", "Admin & HR", "Training & Development", "Others", "Others"], "post_time": "2022-01-13T03:04:31Z", "salary": {"currency": null, "max": null, "min": null, "period": "monthly", "term": null}, "salary_visible": false, "title_keywords": ["specialist"], "responsibilities": ["review", "quality", "regular review", "repair", "reports", "schedule", "contact", "contents", "recruitment", "recruitment process", "personal data"], "requirements": {"degrees": ["certificate", "higher certificate"], "majors": ["engineering"], "languages": ["english", "chinese"], "language_level": ["good command"], "hard_skills": [], "soft_skills": ["team-player", "hands on", "interpersonal skills"], "languages_combined": [{"language": "english", "language_level": ["good command"]}, {"language": "chinese", "language_level": ["good command"]}]}, "experience_required": {"duration": [], "field": []}}, {"job_id": "100003009048075", "location_code": "hk", "company": "ADECCO", "job_title": "HR Executive", "description": "Our Hong Kong team has an exciting new opportunity for an energetic individual to join us as a HR Executive. If you enjoy working in a fast-paced and high-performance environment, we would love to speak to yo today!\n\nJob Responsibilities:\n\nProvide full spectrum of human resources support and develop of HR initiatives, including but not limited to talent acquisition, compensation & benefits, learning & development and staff engagement\nResponsible for all compensation and benefits administration matters, such as processing monthly payroll calculations, final payment, leave record management and medical insurance administration for HK & Macau\nAdminister the Mandatory Provident Fund Scheme, such as enrolment and termination of members and preparing for monthly contribution\nSupport in recruitment process, including but not limited to job ads posting, screening, interviewing and preparing documents for onboarding\nTo maintain and update HRIS and participate in HRIS enhancement\nEngage in the preparation of all HR related reports and analysis\nPerform ad hoc assignments as required\n\nRequirement:\n\nBachelor's degree preferably in human resources or business administration\n2-3 years relevant experiences gained in sizeable company is preferred\nWell-versed in both HK and Macau employment ordinance and MPF regulations\nProficient in MS Office applications (Excel, Word, PowerPoint and Chinese Word Processing)\u00a0\nExcellent interpersonal and communication skills\nDetail-mined, mature and good team player\n\nFresh Graduate will also be considered for HR Assistant\n\nPlease note that only shortlisted candidates will be notified. All information gathered will be treated in strict confidential and solely used for recruitment purposes.", "employment_types": ["Full Time", "Permanent"], "selling_points": ["Develop HR initiatives", "Talent Acquisition", "Learning & Development"], "locations": ["North Point"], "categories": ["Admin & HR", "Compensation & Benefits", "Recruitment / Executive Search", "Training & Development"], "post_time": "2022-01-14T04:41:45Z", "salary": {"currency": null, "max": null, "min": null, "period": "monthly", "term": null}, "salary_visible": false, "title_keywords": ["hr", "executive"], "responsibilities": ["management", "hr", "analysis", "develop", "payment", "maintain", "reports", "ad hoc assignments", "insurance", "recruitment process", "payroll", "administration"], "requirements": {"degrees": ["degree", "bachelor", "fresh graduate"], "majors": ["business administration"], "languages": ["chinese"], "language_level": ["proficient"], "hard_skills": ["excel", "chinese word processing", "word", "powerpoint", "mpf regulations", "ms office"], "soft_skills": ["communication skills", "good team player", "interpersonal", "mature"], "languages_combined": [{"language": "chinese", "language_level": ["proficient"]}]}, "experience_required": {"duration": ["2-3 years"], "field": []}}, {"job_id": "100003002269898", "location_code": "hk", "company": "China State Construction Engineering (Hong Kong) Limited", "job_title": "Human Resources Officer (Training)", "description": "Responsibilities:\n\n\n\u00a0Assist in developing, delivering and implementing training and development initiatives and solutions to fulfill the training needs and staff development strategies\n\u00a0Coordinate and liaise with internal and external parties for the design of training and development programs\nAdminister the training documentations & materials and update the database\nProvide administrative supports including training course enrollment, training resources, logistics and schedule arrangement\nPrepare regular management reports and training performance analysis\n\nRequirements:\n\n\nDegree in Human Resources Management /Training and Development or other related disciplines\nMinimum 3\u00a0years of relevant work experience in sizable organization with solid experience in corporate training delivery\nAbility to build rapport with different levels in a fast-paced environment and to work independently and under pressure\nExcellent interpersonal, communication and presentation skills\nSelf-motivated, people-oriented and attentive to details\nGood command of spoken and written English, Chinese and Mandarin\nProficiency in MS Office and Chinese word processing\nImmediate availability is preferred\n\n\nWe offer attractive remuneration package with comprehensive fringe benefits to the right candidates. Interested parties please send resume with\u00a0day-time contact number, expected salary and quoting Ref. No.\u00a0to Human Resources Manager, 29/F., China Overseas Building, 139 Hennessy Road, Wanchai, Hong Kong or e-mail or fax to 2528 2840.\n\nInterested parties are invited to visit our website (www.cscechk.com/en) for more information.\n\nApplicants who are not invited within 2 months may consider their applications unsuccessful. All information provided by applicants will be treated in strict confidence and used only for recruitment purposes. Applicants may be considered for other suitable positions within the China Overseas Group and its related companies for one-year period, thereafter which their personal data will be destroyed.\n\nServing The Community\u00a0\u3002\u00a0Prospering Hong Kong", "employment_types": ["Full Time", "Permanent"], "selling_points": ["Training and development", "staff development", "3 years work experience"], "locations": ["Wan Chai"], "categories": ["Admin & HR", "Training & Development"], "post_time": "2022-01-11T06:49:37Z", "salary": {"currency": null, "max": null, "min": null, "period": "monthly", "term": null}, "salary_visible": false, "title_keywords": ["human resources officer"], "responsibilities": ["enrollment", "development programs", "analysis", "internal and external parties", "developing", "design", "coordinate", "management reports", "logistics", "schedule", "database", "liaise with"], "requirements": {"degrees": ["degree"], "majors": ["related disciplines"], "languages": ["english", "chinese", "mandarin"], "language_level": ["proficiency", "good command"], "hard_skills": ["chinese word processing", "ms office"], "soft_skills": ["work independently", "self-motivated", "under pressure", "attentive to details", "fast-paced environment", "communication", "presentation skills", "people-oriented", "interpersonal"], "languages_combined": [{"language": "english", "language_level": ["good command"]}, {"language": "chinese", "language_level": ["proficiency", "good command"]}, {"language": "mandarin", "language_level": ["good command"]}]}, "experience_required": {"duration": ["minimum 3 years"], "field": ["sizable organization", "training"]}}, {"job_id": "100003009043713", "location_code": "hk", "company": "Chong Hing Bank Ltd", "job_title": "ZPCS - Senior Officer / Assistant Manager, Payment Services & Cash Management", "description": "Responsibilities:\nLead the Corporate Banking and Financial Markets Training section\nFormulate, plan and deploy training initiatives and projects in alignment with the Bank's business goals and direction\nBuild effective relationship with Division / Department Heads, and offer consultancy and advice of training solutions\nKeep abreast of the latest CPT/CPD requirement, arrange relevant training and monitor the status of all relevant individuals\nMonitor the fulfilment of the continuous professional development under the industry-wide Enhanced Competency Framework\nSource and work with external training vendors in providing training solutions based on the identified needs\nManage the staff education sponsorship scheme\nSupport ad-hoc training projects as assigned\nRequirements:\nBachelor degree with at least 10 years of Learning & Development experience preferably gained from the banking and financial service industry\nKnowledge of the banking products and services would be an advantage\nGood knowledge of the regulatory requirements on the continuous professional training and development\nStrong sense of ownership, stakeholder management, organization and execution skills\nStrong problem solving ability, communication and analytical skills\nWell-versed in written English and Chinese; Putonghua would be an advantage", "employment_types": ["Full Time"], "selling_points": ["Manage the staff education sponsorship scheme", "Support ad-hoc training projects as assigned", "Bachelor degree"], "locations": ["Not Specified"], "categories": ["Admin & HR", "Others", "Training & Development"], "post_time": "2022-01-13T01:37:44Z", "salary": {"currency": null, "max": null, "min": null, "period": "monthly", "term": null}, "salary_visible": false, "title_keywords": ["senior officer", "assistant manager,", "cash management"], "responsibilities": ["ad-hoc", "business goals", "monitor", "banking", "plan", "deploy"], "requirements": {"degrees": ["degree", "bachelor"], "majors": [], "languages": ["putonghua", "english", "chinese"], "language_level": ["advantage"], "hard_skills": ["problem solving", "analytical skills"], "soft_skills": ["problem solving", "learning", "communication", "analytical skills"], "languages_combined": [{"language": "putonghua", "language_level": ["advantage"]}, {"language": "english", "language_level": []}, {"language": "chinese", "language_level": []}]}, "experience_required": {"duration": ["at least 10 years"], "field": ["learning & development", "service industry", "financial", "banking"]}}, {"job_id": "100003009037333", "location_code": "hk", "company": "Jebsen & Co Ltd", "job_title": "Group Human Resources Executive - L&D (Ref: B0T0)", "description": "Purpose of the Job:\n\nThis position will support the development of organisational capability and enhancement of people competency with end to end responsibility from developing, implementing and monitoring learning and development initiatives as well as supporting the talent management and leadership development projects.\n\nResponsibilities:\n\nAssist in developing learning materials (both instructor-led and eLearning courses) based on the identified needs from Group and Business Lines\nManage learning and development initiatives with the end-to-end responsibilities, including but not limited to:\nSource vendors and provide advice in the selection process based on certain criteria\nGenerate effective marketing ideas and execute the plan to promote learning and development initiatives\nCoordinate overall training logistics arrangement, such as, administering the nomination process, setting up training venues, maintaining accurate training records and etc\nEvaluate learning and development initiatives effectiveness and provide data-driven suggestions for continuous improvement\nHandle and analyse external training applications and training records for management\u2019s review\nDeliver learning and development programmes, such as, Group Orientation Programmes and facilitate in other soft skills related training programmes\nManage external training applications and prepare reports/analysis regularly\nSupport in Organisational Development/ Talent Management projects as needed\nResearch, gather, compile and provide information related to human resources development, such as market intelligence on learning & development needs, learning resources, learning investment, trainers/ speakers for learning events, etc.\nAssist in planning and execution of various HR activities, including but not limited to talent acquisition, recruitment and employment engagement.\nParticipate in ad-hoc HR projects and new initiatives as assigned.\n\nRequirements:\n\nDegree holder with 2-3 years\u2019 experience in human resources development or related disciplines.\nEffective communication and interpersonal skills, good project management & analytical skills with a strong interest in people development.\nGood command of both spoken and written English and Chinese (Cantonese and Putonghua).\nExcellent computer literacy, including MS Word, Excel, PowerPoint and Chinese Word Processing.\nWilling to travel to PRC.\nImmediately available is highly preferred.\nInterested parties please submit your application to our mailbox by clicking \"Apply Now\" below.\n\nFor more information about Jebsen Group, please visit\u00a0www.jebsen.com\u00a0or follow us on:\nSina Weibo \u00a0\u00a0\u00a0\u00a0\u00a0http://weibo.com/jebsengroup\nWeChat\u00a0\u00a0\u00a0\u00a0\u00a0\u00a0\u00a0\u00a0\u00a0\u00a0 ID: jebsen1895\nLinkedIn\u00a0\u00a0\u00a0\u00a0\u00a0\u00a0\u00a0\u00a0\u00a0\u00a0 Jebsen Group\n\nAll information provided by applicants will be used for recruitment purposes only.\n\nAt Jebsen, success breeds success.\u00a0", "employment_types": ["Full Time", "Permanent"], "selling_points": ["L&D focus with other HR exposure", "2-3 years of HR experience", "Dynamic Business Exposure"], "locations": ["Causeway Bay"], "categories": ["Admin & HR", "HR Supporting Staff", "Recruitment / Executive Search", "Training & Development"], "post_time": "2022-01-11T02:31:24Z", "salary": {"currency": null, "max": null, "min": null, "period": "monthly", "term": null}, "salary_visible": false, "title_keywords": ["human resources executive"], "responsibilities": ["ad-hoc", "ideas", "data", "plan", "maintaining", "developing", "analyse", "management", "logistics arrangement", "monitoring", "review", "analysis", "hr", "coordinate", "evaluate", "provide advice", "recruitment", "prepare reports", "planning"], "requirements": {"degrees": ["degree holder"], "majors": ["related disciplines"], "languages": ["cantonese", "putonghua", "english", "chinese"], "language_level": ["excellent", "good command"], "hard_skills": ["excel", "chinese word processing", "powerpoint", "analytical skills", "project management", "ms word"], "soft_skills": ["project management", "communication and interpersonal skills", "computer literacy", "analytical skills"], "languages_combined": [{"language": "cantonese", "language_level": ["good command"]}, {"language": "putonghua", "language_level": ["good command"]}, {"language": "english", "language_level": ["good command"]}, {"language": "chinese", "language_level": ["excellent", "good command"]}]}, "experience_required": {"duration": ["2-3 years"], "field": ["related", "development", "human resources"]}}, {"job_id": "100003009047416", "location_code": "hk", "company": "Tai Hing Catering Group Limited", "job_title": "Assistant Officer - Occupational Safety & Hygiene \u4e94\u5e38\u90e8\u526f\u4e3b\u4efb (\u8077\u696d\u5b89\u5168\u53ca\u74b0\u5883\u885e\u751f)", "description": "Responsibilities\n\nSupport the implementation of \u201c5-S\u201d management system and perform on-site audit in restaurants;\nMaintain environmental, health & safety record and documents;\nFollow up work injury case and prepare related reports and documents;\nOrganize the occupational safety training and modify & update the training materials from time to time;\nEnsure the operations in restaurants are in compliance with safety regulations and corporate requirements;\nPerform ad-hoc duties as assigned\n\nRequirements:\n\nDiploma holder or above in related disciplines;\nA minimum of 1 year\u2019s working experience in clerical support, recent graduates will be also considered;\nExperience in F&B operations and restaurant group is preferable;\nKnowledge in Safety and Health Ordinance is an advantage;\nStrong presentation and communications skills;\nGood inter-personal skills & able to work independently;\nGood written and spoken English and Chinese;\nProficiency in Microsoft Word, Excel, and PowerPoint\nWorking Location : Fotan\n\n\n\nWe offer\u00a0competitive\u00a0package and benefits:\n\n\u00a0\u00a0\u00a0\u00a0\u00a0\u00a0\u00a0\u00a0 Five-Day work week\n\u00a0\u00a0\u00a0\u00a0\u00a0\u00a0\u00a0\u00a0 3 Days Marriage Leave\n\u00a0\u00a0\u00a0\u00a0\u00a0\u00a0\u00a0\u00a0 5 Days Full Pay Paternity Leave\n\u00a0\u00a0\u00a0\u00a0\u00a0\u00a0\u00a0\u00a0 Family-Friendly Leave\n\u00a0\u00a0\u00a0\u00a0\u00a0\u00a0\u00a0\u00a0 Birthday Leave\n\u00a0\u00a0\u00a0\u00a0\u00a0\u00a0\u00a0\u00a0 Free Duty Meal\n\u00a0\u00a0\u00a0\u00a0\u00a0\u00a0\u00a0\u00a0 Staff Discount\n\u00a0\u00a0\u00a0\u00a0\u00a0\u00a0\u00a0\u00a0 Medical Allowance\n\u00a0\u00a0\u00a0\u00a0\u00a0\u00a0\u00a0\u00a0 Insurance Plan\n\u00a0\u00a0\u00a0\u00a0\u00a0\u00a0\u00a0\u00a0 Promotion Opportunities\n\nFor more company information, please visit our web site at\u00a0www.taihing.com\n\nInterested parties please send\u00a0full resume with expected salary\u00a0and availability\u00a0to the\u00a0Human Resources Department via email.\n\nAll information received will be kept in strict confidence and only used for employment-related purposes. Applicants who are not invited for interview within 6 weeks may consider their applications unsuccessful.", "employment_types": ["Full Time", "Permanent"], "selling_points": [], "locations": ["Shatin Area"], "categories": ["Hospitality / F & B", "Food & Beverage", "Sciences, Lab, R&D", "Food Science", "Admin & HR", "Training & Development"], "post_time": "2022-01-14T03:01:51Z", "salary": {"currency": null, "max": null, "min": null, "period": "monthly", "term": null}, "salary_visible": false, "title_keywords": ["assistant officer"], "responsibilities": ["regulations", "management", "operations", "compliance", "implementation", "audit", "maintain", "reports", "ad-hoc duties"], "requirements": {"degrees": ["diploma holder"], "majors": ["related disciplines"], "languages": ["english", "chinese"], "language_level": ["good"], "hard_skills": ["excel", "microsoft word", "powerpoint"], "soft_skills": ["inter-personal skills", "work independently", "presentation"], "languages_combined": [{"language": "english", "language_level": ["good"]}, {"language": "chinese", "language_level": ["good"]}]}, "experience_required": {"duration": ["minimum of 1 year"], "field": ["f&b", "restaurant", "clerical"]}}, {"job_id": "100003009043626", "location_code": "hk", "company": "Pfizer Corporation Hong Kong Limited", "job_title": "Hong Kong Trainer", "description": "Why Patients Need You\u00a0\n\nWe expect our sales team to be experts on our product lines and the conditions the drugs have been developed to treat. As Hong Kong Trainer, you'll be responsible for ensuring the seamless delivery of evolved and enhanced learning experiences for Pfizer customer facing colleagues to create and sustain a competitive advantage for Pfizer.\u00a0 You will also collaborate with their Digital Client Partner to effectively engage with Business Unit clients to define and deliver learning initiatives that have quantifiable value and impact.\n\nWhat You Will Achieve\n\nYou will provide support to sales representatives(sales staff and sales management) and channel partners by developing,\u00a0planning,\u00a0and conducting training on techniques of selling the organization's products and services. You will be responsible for developing and delivering training programs that focus on sales techniques and presentations, product information, group referencing\u00a0\u00a0and role play. You may also work with Product Managers or marketing teams to develop a sales strategy and incorporate this strategy into the training programs.\u00a0\n\nHow You Will Achieve It\n\u00a0\nYou will be accountable for implementing Learning at local level by:\n\n\nCollaborating with the Digital Client Partner to effectively engage with Business Unit clients to define and deliver learning initiatives that have quantifiable value and impact\nEnsuring the uniform delivery of learning at country level (including product knowledge, marketing and selling skills training, sustainability programs, innovative learning assets, virtual tools, etc.)\nMonitoring the adherence to streamlined local review and approval of learning materials\nCollecting and providing country specific learnings and performance metrics that support continuous improvement\u00a0\u00a0\n\nQualifications\u00a0\n\nA recognized Bachelor\u2019s degree\nAt least 5 years' relevant experience; people leadership experience with evidence of high emotional intelligence would be an advantage\nCommercial training experience including delivery of blended and distance learning curricula and content is essential\nUnderstanding of the pharma industry / Pfizer\u2019s business\nExperience in evaluating Learning programs and materials to ensure client and learner needs are met\nAbility to work on multiple projects simultaneously and manage competing priorities\nCross-functional working experience and collaboration\nMinimum of a Bachelor\u2019s degree required", "employment_types": ["Full Time", "Permanent"], "selling_points": ["At least 5 years' relevant experience", "Ability to work on multiple projects simultaneous", "Cross-functional working experience"], "locations": ["Quarry Bay"], "categories": ["Admin & HR", "Training & Development", "Medical Services", "Pharmaceutical"], "post_time": "2022-01-13T01:05:07Z", "salary": {"currency": null, "max": null, "min": null, "period": "monthly", "term": null}, "salary_visible": false, "title_keywords": [], "responsibilities": ["collaborate with", "provide support", "monitoring", "teams", "developing", "presentations", "develop", "review", "performance metrics", "sales team", "multiple projects", "sales management", "planning"], "requirements": {"degrees": ["degree", "bachelor"], "majors": [], "languages": [], "language_level": [], "hard_skills": ["focus", "presentations"], "soft_skills": ["responsible", "accountable", "learning", "focus", "innovative", "leadership"], "languages_combined": []}, "experience_required": {"duration": ["at least 5 years"], "field": ["commercial", "relevant experience", "training"]}}, {"job_id": "100003009049544", "location_code": "hk", "company": "TDK Electronics Hong Kong Limited", "job_title": "HR Officer (Temporary for 6 months)", "description": "Job Duties:\n\nSupport the HR team in performing the HR functions for GC regions\nPrepare regular HR reports and presentation meeting materials\nAssist to translate HR system guideline from English to Chinese\nSupport the meetings /on-line training logistics\nSupport the HR system enhancement / data management\nAd hoc tasks as assigned by supervisor\nQualification:\n\nA degree in Business Administration with major in Human Resources Management is preferred\nGood command of spoken and written in English and Mandarin\nProficiency in PC applications including MS Word, Excel, PowerPoint, etc.\u00a0\nWilling to learn, detail-minded, good communication and interpersonal skill, able to work under a tight schedule\n3 years or above relevant working experience.\nFlexible working hour is applicable\n\nOur office is located in Hong Kong Science Park, Shatin. All data collected will be used for recruitment purpose only.", "employment_types": ["Full Time", "Temporary", "Contract"], "selling_points": [], "locations": ["Shatin Area"], "categories": ["Admin & HR", "Others", "HR Supporting Staff", "Training & Development"], "post_time": "2022-01-14T08:51:15Z", "salary": {"currency": null, "max": null, "min": null, "period": "monthly", "term": null}, "salary_visible": false, "title_keywords": ["hr officer"], "responsibilities": ["management", "data", "hr", "ad hoc tasks", "hr reports", "communication", "logistics", "schedule", "recruitment", "administration"], "requirements": {"degrees": ["degree"], "majors": ["business administration"], "languages": ["english", "chinese", "mandarin"], "language_level": ["good command"], "hard_skills": ["excel", "data management", "powerpoint", "pc applications", "ms word"], "soft_skills": ["detail-minded", "flexible", "willing to learn", "interpersonal skill", "communication", "presentation"], "languages_combined": [{"language": "english", "language_level": ["good command"]}, {"language": "chinese", "language_level": []}, {"language": "mandarin", "language_level": ["good command"]}]}, "experience_required": {"duration": ["3 years"], "field": ["relevant working experience"]}}, {"job_id": "100003009037959", "location_code": "hk", "company": "CITIC Telecom International CPC Limited", "job_title": "Assistant Manager, Training", "description": "The Challenge We Pose to You:\n\n\nTake lead in formulating, implementing and improving Company\u2019s training strategies and training plan of all regions across Hong Kong and other regional offices\nArrange training activities which includes sourcing training providers and suitable courses, enrollment and payment; follow up with staff and providers on the courses status and conduct staff evaluation\nReview and improve the Company training policies, workflow and procedures to increase the productivity and efficiency in all regions\nManage e-learning platforms including training system, Learning Management System (LMS), online training\nConduct internal trainings including orientation sessions for new joiners\nKeep detail record of training data, budgets and documents.\nCompile reports, presentation materials and in timely manner\nPrepare ISO documents for the department\nAny ad hoc HR tasks as assigned\n\n\u00a0What You Bring to Us:\n\nUniversity graduate in Human Resources Management, Business Administration or equivalent\nMinimum of 5 years relevant experience in sizable companies\nDetail oriented, keep all records up to date with learning systems and folders\nGood interpersonal and communication skills at all levels\nGood command of English, Chinese and Putonghua\nProficient in Microsoft Office such as Word, Excel and PowerPoint\nInitiative, meticulous and responsible\nAble to work in a fast-paced, dynamic and team environment\nAble to work independently and under pressure\nExcellent command of both written and spoken English, Cantonese and Mandarin\nCandidates with less experiences can be considered as Senior Officer\n\nOur Offer:\u00a0\n\n5-day work, 14 days annual leave,\u00a0a competitive remuneration package, comprehensive medical and dental plan, local and regional training and rewarding career opportunities.\n\nPlease send your\u00a0complete resume (in MS word format), inclusive of\u00a0your available date, current and expected salary\u00a0by clicking\u00a0'Apply Now'\u00a0or\u00a0by\u00a0mail to:\u00a0Human Resources and Administration Department,\u00a0CITIC Telecom International CPC\u00a0Limited,\u00a020/F, Lincoln House, Taikoo Place, 979 King's Road, Quarry Bay, Hong Kong.\u00a0\n\nWebsite:\u00a0 www.citictel-cpc.com\n\nAll information received will be kept in strict confidence and for employment-related purpose only.", "employment_types": ["Full Time", "Permanent"], "selling_points": ["Min. 5 years\u2019 training exp. in sizable company", "Plan and design training programs", "Identify the capability gaps and training needs"], "locations": ["Quarry Bay"], "categories": ["Admin & HR", "Training & Development"], "post_time": "2022-01-11T04:26:03Z", "salary": {"currency": null, "max": null, "min": null, "period": "monthly", "term": null}, "salary_visible": false, "title_keywords": ["assistant manager,"], "responsibilities": ["budgets", "enrollment", "management", "ad hoc", "data", "training activities", "policies", "compile reports", "review", "procedures", "hr", "systems", "website", "communication", "payment", "plan", "evaluation", "administration"], "requirements": {"degrees": ["university graduate"], "majors": ["business administration"], "languages": ["cantonese", "english", "mandarin", "putonghua", "chinese"], "language_level": ["excellent", "good command"], "hard_skills": ["excel", "microsoft office", "sizable companies", "word", "powerpoint", "dynamic", "ms word"], "soft_skills": ["initiative", "communication skills", "meticulous", "work independently", "under pressure", "confidence", "responsible", "detail oriented", "timely", "learning", "dynamic", "comprehensive", "interpersonal", "presentation"], "languages_combined": [{"language": "cantonese", "language_level": ["excellent"]}, {"language": "english", "language_level": ["excellent", "good command"]}, {"language": "mandarin", "language_level": ["excellent"]}, {"language": "putonghua", "language_level": ["good command"]}, {"language": "chinese", "language_level": ["good command"]}]}, "experience_required": {"duration": ["minimum of 5 years"], "field": ["relevant experience"]}}, {"job_id": "100003009022759", "location_code": "hk", "company": "Aesop", "job_title": "Retail Trainer", "description": "POSITION PURPOSE\n\nRetail Trainer is responsible for planning, coordinating and implementing our customer service and product training for Hong Kong and Macau. This position is one of consistent leadership and communication, and by all Aesop employees is viewed as the exemplary ideal of what customer service, product knowledge, and integrity should be. As a key interface with new and existing employees, this position is occupied by an intelligent, curious and adaptable individual who can deliver comprehensive training modules with warmth and authority.\n\nAs an engaging individual who is representing the brand, the ability to adapt and challenge multiple learning styles and behaviours is crucial. This position has a clear purpose of upholding and delivering best practice service, and ensuring those surrounding are able to identify and replicate these standards.\n\nMAIN RESPONSIBILITIES\n\nClassroom Training and Field Coaching\n\n\nSupport in the organization and implementation of classroom training for both office and retail level, such as Induction Training, New Product Training, Customer Service Training, etc.\nIn line with training facilitation; coordinate all workshop administration and preparation and ensure all pre and post workshop activities are completed by attendees.\nArrange regular store visit with the purpose of analysis and observation of performance and mentor and coach retail staff as required to ensure the highest standard of staff performance.\nConduct Train-the-Trainer Program to upkeep product knowledge and skills-set of in-store trainer\nTrack retail staff performance, measure the outcomes and effectiveness of the overall training plan and recommend changes to management to ensure all retail staff are progressing in accordance with company strategy and agreed learning outcomes.\nTo lead by example in customer service, product prescription, Aesop demonstration techniques and personal presentation and grooming.\nSupport Marketing Team in Skin Care Event and New Product Campaign.\n\nCommunication and Administration\n\n\nWork closely with Training & Performance Manager to optimize customer service and product knowledge. Collect and analyze feedback from existing training programs and review sales performance.\nMonitor the sales performance of new product during campaigns and offer innovative suggestions for improvement\nManage and review the Mystery Shopper Program to ensure excellent customer service level.\nCommunicate and celebrate customer compliments to motivate and encourage the retail teams.\nDeliver regular Training reports to inform store performance, gaps and challenges.\nParticipate in ad hoc projects as assigned (e.g. translation of training materials)\n\nWho We Are Looking For\n\n\nDegree holder with minimum 5 years' solid experience in training and development preferably gained from retail industry\nExperience in retail frontline is definitely an advantage\nProven track record in developing and conducting training programs for retail staff\nExcellent presentation and interpersonal skills, able to communicate with different levels of employees\nPositive attitude, detailed minded, good organization and problem solving skills\nA commitment to and passion for Aesop's retail environment, customer service and teams\nStrong and sympathetic written and verbal communication skills (including English and Chinese)", "employment_types": ["Full Time", "Permanent"], "selling_points": ["Supportive and entrepreneurial spirit", "Cultivate a professional environment", "Training and performance"], "locations": ["Central"], "categories": ["Admin & HR", "Training & Development"], "post_time": "2022-01-11T16:01:57Z", "salary": {"currency": null, "max": null, "min": null, "period": "monthly", "term": null}, "salary_visible": false, "title_keywords": [], "responsibilities": ["communication", "customer service", "plan", "administration", "sales performance", "monitor", "implementation", "teams", "developing", "reports", "management", "representing the brand", "workshop", "review", "communicate with", "analysis", "coordinate", "ad hoc projects", "planning"], "requirements": {"degrees": ["degree holder"], "majors": [], "languages": ["english", "chinese"], "language_level": [], "hard_skills": ["translation", "analysis", "inform", "problem solving skills"], "soft_skills": ["communication skills", "responsible", "passion for", "adaptable", "integrity", "detailed", "communication", "clear", "positive attitude", "customer service", "comprehensive", "learning", "interpersonal skills", "problem solving skills", "innovative", "leadership", "presentation", "ideal"], "languages_combined": [{"language": "english", "language_level": []}, {"language": "chinese", "language_level": []}]}, "experience_required": {"duration": ["minimum 5 years"], "field": ["retail industry", "development", "retail", "training"]}}, {"job_id": "100003009039805", "location_code": "hk", "company": "Jointed-Heart Limited", "job_title": "Operations Training Manager", "description": "Responsibilities:\n\nIdentify company training needs, formulate and develop training strategies and implement plans for all frontline staff;\nManage training budget, course development, training need analysis and program review\nDesign rundown, prepare training hand-outs, materials, tools and samples before training classes;\nDeliver customer service, selling skills and supervisory training to front-line staff;\nExecute field work in shops to evaluate front-line staff\u2019s performance;\nConduct Train The Trainer sessions and provide\u00a0coaching and development when appropriate.\n\nRequirements:\n\nBachelor Degree in Human Resources Management, Training or related disciplines;\nMinimum 8 years of solid experience in training and development especially in F&B industry;\nSelf-motivated, well organized and a good team player;\nStrong communication, presentation and interpersonal skills;\nProficiency in using MS Office applications including Word, PowerPoint, Excel and Chinese Word Processing;\nCandidates with more experience will be considered as Senior Operations Training Manager\n\nWe offer 5-day work week, on-the-job development program and rewarding career opportunities for ambitious individuals who are looking for challenges.\n\n(All personal data collected will be used for recruitment purpose only.)", "employment_types": ["Full Time", "Permanent"], "selling_points": ["Minimum 8 yrs experience in F&B industry", "Experience in Food Chain Stores is an advantage", "Strong in staff development programme"], "locations": ["Lai Chi Kok"], "categories": ["Admin & HR", "Training & Development"], "post_time": "2022-01-11T11:29:52Z", "salary": {"currency": null, "max": null, "min": null, "period": "monthly", "term": null}, "salary_visible": false, "title_keywords": ["operations", "manager"], "responsibilities": ["analysis", "review", "budget", "design", "develop", "evaluate", "customer service", "plans"], "requirements": {"degrees": ["degree", "bachelor"], "majors": ["related disciplines"], "languages": ["chinese"], "language_level": ["proficiency"], "hard_skills": ["excel", "chinese word processing", "word", "powerpoint", "ms office"], "soft_skills": ["good team player", "self-motivated", "well organized", "communication", "interpersonal skills", "presentation"], "languages_combined": [{"language": "chinese", "language_level": ["proficiency"]}]}, "experience_required": {"duration": ["minimum 8 years"], "field": ["development", "f&b", "training"]}}, {"job_id": "100003009034098", "location_code": "hk", "company": "I.T Apparels Limited", "job_title": "Training Officer (REF : JDB-IT-TO)", "description": "Responsibilities:\n\n\nIdentify training needs and develop training plans for frontline staff to help establish the values, spirit and culture of the company\nConduct various training programs to enhance technical competences, work knowledge and soft skills development\nDevelop and organize staff relations / team building projects\nMonitor and evaluate training effectiveness through effective field coaching and regular shop visits\nReview and maintain training database and consolidate training reports for management review\nRequirements:\n\nDegree holder with at least 1-2 years\u2019 solid experience in training and development preferably gained from retail chains\nProven track record in developing and conducting training programs for frontline staff, as well as shaping customer service culture\nExcellent presentation and interpersonal skills, able to communicate well with different levels of employees\n\nCompetitive remuneration and benefit package will be offered to the right candidate. Please submit your application by clicking \"Apply Now\" below.\n", "employment_types": ["Full Time", "Permanent"], "selling_points": ["Identify training needs and develop training plans", "Monitor and evaluate training effectiveness", "Degree holder with at least 1-2 yrs experience"], "locations": ["Southern Area"], "categories": ["Sales, CS & Business Devpt", "Customer Service - Supervisor / Officer", "Education", "Teacher", "Admin & HR", "Training & Development"], "post_time": "2022-01-10T02:40:26Z", "salary": {"currency": null, "max": null, "min": null, "period": "monthly", "term": null}, "salary_visible": false, "title_keywords": ["officer"], "responsibilities": ["review", "monitor", "develop", "evaluate", "maintain", "reports", "database", "plans", "management review"], "requirements": {"degrees": ["degree holder"], "majors": [], "languages": [], "language_level": [], "hard_skills": [], "soft_skills": ["customer service", "interpersonal skills", "presentation"], "languages_combined": []}, "experience_required": {"duration": ["at least 1-2 years"], "field": ["development", "retail", "training"]}}, {"job_id": "100003009042061", "location_code": "hk", "company": "The Association of Electrical and Mechanical Engineering (Hong Kong) Limited", "job_title": "\u57f9\u8a13\u4e3b\u4efbTraining Officer", "description": "\u8077\u8cac\uff1a\n\u8ab2\u7a0b\u767c\u5c55\u5de5\u4f5c\n\u8ddf\u9032\u5b78\u54e1\u5c31\u696d\n\u9700\u8f2a\u73ed\u5de5\u4f5c\n\n\u8981\u6c42\uff1a\n\u5927\u5c08\u7a0b\u5ea6\u53ca5\u5e74\u4ee5\u4e0a\u57f9\u8a13\u6216\u7763\u5c0e\u7d93\u9a57\n\u826f\u597d\u6e9d\u901a\u80fd\u529b\n\u5c0d\u300c\u8cc7\u6b77\u67b6\u69cb\u300dQF\u8ab2\u7a0b\u6709\u8a8d\u8b58\u8005\u512a\u5148\u8003\u616e\n\n5\u5929\u5de5\u4f5c\u3001\u9032\u4fee\u6d25\u8cbc\u3001\u734e\u52f5\u6027\u82b1\u7d05\u3001\u91ab\u7642\u6d25\u8cbc\n\n\u6708\u85aa$19,000\u8d77\n\n\u5982\u5728\u4e09\u500b\u6708\u5167\u4ecd\u672a\u7372\u7d04\u898b\uff0c\u5247\u4f5c\u843d\u9078\u8ad6\uff0c\u6055\u4e0d\u53e6\u884c\u901a\u77e5\uff0c\u6240\u6709\u843d\u9078\u8005\u8cc7\u6599\u6703\u4f5c\u92b7\u6bc0\u3002", "employment_types": ["Full Time"], "selling_points": [], "locations": ["Yau Ma Tei"], "categories": ["Education", "Others", "Admin & HR", "Training & Development"], "post_time": "2022-01-12T05:47:43Z", "salary": {"currency": null, "max": null, "min": null, "period": "monthly", "term": null}, "salary_visible": false, "title_keywords": ["officer"], "responsibilities": [], "requirements": {"degrees": [], "majors": [], "languages": [], "language_level": [], "hard_skills": [], "soft_skills": [], "languages_combined": []}, "experience_required": {"duration": [], "field": []}}, {"job_id": "100003009050630", "location_code": "hk", "company": "Hip Shing Hong (Holdings) Company Limited", "job_title": "Assistant Human Resources Manager", "description": "We are an energetic work-life balanced company.\u00a0\n\nCome to join our team to take on new challenges.\n\n\u00a0We are looking for a talent to:\n\nManage end-to-end talent acquisition process from sourcing, interviewing, presenting candidates, and extending offers in a fast-paced business environment\nDemonstrate knowledge in functional HR areas such as talent management, employee relations, training and development, compensation and benefits, talent acquisition and organizational development\nOversee the hotel\u2019s team member welfare programs, ensuring that the benefits supplied are relevant and competitive in the local marketplace.\nAssist in the training of service excellence on hotel\u2019s focus and team members to train others in providing exceptional service to the hotel\u2019s external customers (guests).\nPropose and execute dynamic HR projects for company advancements\nPioneer HR technologies and contribute ideas in practical applications\nBack up for team members as well as assist in other ad-hoc tasks\n\nBasic requirements:\n\nBachelor\u2019s Degree holder or above in\u00a0Hospitality, Human Resources, Business Administration or related disciplines\nMinimum 6-8 years\u2019 in Human Resources, Talent Acquisition or Talent Development\nExperience in Hotel or service orientated organization preferred\nProactive and autonomous with the flexibility to adapt to ever-changing priorities and responsibilities\nExcellent organizational skills with the ability to work on multiple projects concurrently and take responsibility for project delivery\nGood command of written and spoken English, Cantonese, and Mandarin\n\nBenefits:\u00a0\u00a0\n\nMedical insurance\nDental insurance\nDiscretionary year-end bonus\nEducation and training allowance\nPaid marriage leave & gift\nPaid emergency leave\nPaid children's birthday leave\nPaid compassionate leave\nAcademic scholarship\n\nWe are constantly looking for talents who are proactive and dedicated to be part of our Hip Shing Hong\u2019s family.\u00a0 If you are ready for the next challenge, please apply now!\n\nFor more information, please visit our Company's website\u00a0https://www.hshd.com.hk/en/career/.\n\nAll information provided by applicants will be treated in strict confidence and be used for recruitment purpose only.\u00a0", "employment_types": ["Full Time", "Permanent"], "selling_points": ["Degree holder in Hospitality or Human Resources", "Talent acquisition and training focus", "Minimum 6-8 years relevant working experience"], "locations": ["Central"], "categories": ["Admin & HR", "HR Supporting Staff", "Recruitment / Executive Search", "Training & Development"], "post_time": "2022-01-14T11:00:49Z", "salary": {"currency": null, "max": null, "min": null, "period": "monthly", "term": null}, "salary_visible": false, "title_keywords": ["assistant human resources manager"], "responsibilities": ["hr", "management"], "requirements": {"degrees": [], "majors": [], "languages": [], "language_level": [], "hard_skills": [], "soft_skills": ["business environment", "organizational", "energetic"], "languages_combined": []}, "experience_required": {"duration": [], "field": []}}, {"job_id": "100003009041657", "location_code": "hk", "company": "GP Strategies (Hong Kong) Limited", "job_title": "Senior Staff Training Coordinator", "description": "Purpose of the role :\n\nTo provide administrative support to the Learning Administration Operations of both GP Strategies and client.\u00a0 This include tasks involved in contracting of learners to provide training information and class reminders, tracking progress through specific learning programs, administering records keeping and creating various types of reports.\n\nEssential Duties and Responsibilities:\n\n\n\nManage training center facilities to ensure a professional condition to support classroom training.\u00a0 Tasks include but not limited to: cross-site training center management, security access for visitors/users of the training facilities, catering arrangement for onsite training, training equipment & supplies management, room booking system management.\nTeam supervision and coaching provided to the Hong Kong project administration team members\nWork with GP Learning Consultants (LC) and GP Professional Services Team Lead\nAdminister training nomination, registration and follow up for classes as instructed.\nGenerate data from veracious systems, analyze the data as needed and create standard reports as and when require.\u00a0 Ad hoc report for L&D department according to specified reporting timeline.\nAdminister HR support processes on behalf of the L&D department\nMaintain data in the system in accordance with pre-set time frame\nEnsure payment to vendors by processing invoices accurately and in a timely manner\nMaintain monthly accrual to ensure accurate training budget tracking\nOther duties as assign by GP Strategies LC and confirmed by GP Professional Services Team Lead or Regional LAO Manager\nEssential Requirement:\n\nUniversity graduate\n3 - 5 years experiences as a learning administrator or other similar operational role related to learning and development\nProficient in MS office applications, specifically Excel functionality and Powerpoint preparation\nFamiliarity with Success Factors and Microsoft (CRM) Dynamics is desirable\nWorking knowledge of operational systems, including GLMS, HR Direct, People insights, employee Central, LRM and various Sharepoint sites and local drive\nExperience in handling enquires via a shared mailbox and within Service Level Agreements would be valuable\nBuild good work relationship with internal and external stakeholder\nAble to adapt to changes in a fast pace environment", "employment_types": ["Full Time", "Permanent", "Contract"], "selling_points": ["Open Work Culture", "Dynamic and Fast Moving Environment", "Energetic & Passionate"], "locations": ["Kowloon City Area"], "categories": ["Admin & HR", "Administration / Operation Manager", "HR Supporting Staff", "Training & Development"], "post_time": "2022-01-12T04:10:26Z", "salary": {"currency": null, "max": null, "min": null, "period": "monthly", "term": null}, "salary_visible": false, "title_keywords": ["coordinator", "staff"], "responsibilities": ["data", "ad hoc report", "budget", "payment", "maintain", "project administration", "invoices", "other duties", "reports", "reporting", "management", "booking", "maintain data", "accrual", "tracking", "hr", "systems", "a timely manner", "catering"], "requirements": {"degrees": ["university graduate"], "majors": [], "languages": [], "language_level": [], "hard_skills": ["excel", "powerpoint", "ms office"], "soft_skills": ["learning"], "languages_combined": []}, "experience_required": {"duration": ["3 - 5 years"], "field": ["related", "development"]}}, {"job_id": "100003009049281", "location_code": "hk", "company": "Anchor Communications Limited", "job_title": "Student Affairs Co-ordinator \u5b78\u54e1\u4e8b\u52d9\u52a9\u7406", "description": "Job description:\n\n\nAssisting in the delivery of training programs & workshops\nHandling student enrollment affairs, sales & customer services\nFollow up potential and update current students for promotion and new courses\nHandling incoming inquiries including emails, phone calls, and WhatsApp\n\nJob Requirements:\n\nDegree holder\nGood command of written Chinese\nGood communication skills and manner\nEnjoy dealing with people from all walks of life\n\nRemuneration:\n\nMedical scheme\nFlexible working hours\nOn-the-job training & training courses will be provided\n\nInterested participants, please send your Cover Letter, CV with current & expected salaries to us. Potential candidates will be invited for an interview shortly.", "employment_types": ["Full Time"], "selling_points": ["Flexible working hours", "On-the-job training and training courses provided", "Meeting people from all walks of life"], "locations": ["Tsim Sha Tsui"], "categories": ["Admin & HR", "Training & Development", "Sales, CS & Business Devpt", "Sales Administration"], "post_time": "2022-01-14T08:22:20Z", "salary": {"currency": null, "max": null, "min": null, "period": "monthly", "term": null}, "salary_visible": false, "title_keywords": [], "responsibilities": ["enrollment", "phone calls", "customer services"], "requirements": {"degrees": ["degree holder"], "majors": [], "languages": ["chinese"], "language_level": ["good command"], "hard_skills": ["scheme"], "soft_skills": ["flexible", "communication skills"], "languages_combined": [{"language": "chinese", "language_level": ["good command"]}]}, "experience_required": {"duration": [], "field": []}}, {"job_id": "100003009042864", "location_code": "hk", "company": "New Media Group", "job_title": "Senior Human Resources Officer/ Human Resources Officer(Training & Recruitment Focus)", "description": "Responsibilities\n\n\nResponsible for full cycle of talent recruitment process from candidates sourcing, shortlisting, conducting interview, offering to on-boarding process\nExplore and manage all potential sourcing channels of talent, e.g. LinkedIn, online job posting, social media, campus recruitment, employee referrals and other active searching channels\nFollow right recruitment and screening procedures to ensure the right candidates are shortlisted and recruited\u00a0\nAssist in design and implement creative talent program for smooth induction and ensure they are effectively equipped with right skills for future development\nAssist in Identify and assess future and current training needs through job analysis, career paths, annual performance appraisals and consultation\nEnsure smooth delivery of training, with right attendance and passing rate\nSupport and assist in other ad-hoc tasks or projects, as required\n\nRequirements\n\n\nDegree holder in any disciplines\nMinimum 1 year of relevant experience\u00a0\nExcellent communication skills\nProactive, well-organized, responsible team player with positive work attitude\nHighly organized, attention to details and follow through execution\nAbility to plan, multi-task and manage time effectively\nAbility and desire to work in a team environment\nPassionate about people development and result-oriented\nGood excel skills and document preparation, familiar with MS Word & Excel\nCreative and innovative thinking\nImmediately available is definitely advantageous.\n\nWe offer competitive salary and benefits package( 5 days work, 14 days AL up, birthday leave, medical & dental insurance) with great opportunity for career development to the successful candidate.\n\nPlease send your detailed resume and expected salary to our Human Resources Department by clicking \"Apply Now\" (please put position applied on subject line).\n", "employment_types": ["Full Time", "Permanent"], "selling_points": ["Responsible for full cycle of talent recruitment", "Self motivated showing strong sense of ownership", "Great development opportunity, competitive package"], "locations": ["Kwun Tong"], "categories": ["Admin & HR", "Others", "Recruitment / Executive Search", "Training & Development"], "post_time": "2022-01-12T09:03:02Z", "salary": {"currency": null, "max": null, "min": null, "period": "monthly", "term": null}, "salary_visible": false, "title_keywords": ["senior human resources officer", "human resources"], "responsibilities": ["social media", "attendance", "analysis", "ad-hoc tasks", "procedures", "design", "recruitment", "recruitment process"], "requirements": {"degrees": ["degree holder"], "majors": ["any disciplines"], "languages": [], "language_level": [], "hard_skills": ["excel", "ms word"], "soft_skills": ["communication skills", "organized", "multi-task", "creative", "responsible", "well-organized", "innovative", "attention to details", "team player", "proactive", "positive work attitude", "result-oriented", "passionate about", "detailed"], "languages_combined": []}, "experience_required": {"duration": ["minimum 1 year"], "field": ["relevant experience"]}}, {"job_id": "100003009050822", "location_code": "hk", "company": "Cinnox Limited", "job_title": "Officer, Internal Audit (Immedately available)", "description": "Our team\nCINNOX is made of a collective of individuals driven by success while motivating and supporting one another to cultivate an environment of encouragement and trust. We are committed to continuous improvement through innovation, curiosity and creativity to help businesses compete and win by humanising customer and employee connections. We have a team that supports each other grows together. By working together, our achievements are magnified.\u00a0\nCINNOX is an equal opportunity employer, with the belief that a diverse team creates unique potential, we strive to build a diverse and inclusive community where everyone, regardless of gender, race, religion, age, or background, can belong.\nTo cope with the rapid business growth across the globe, we are looking for ambitious, passionate and self-driven talent to join our fast growing team.\nWHAT you be doing in this role:\n\nAssist in full spectrum of HR functions including talent acquisition, training & development, compensation & benefits and employee relations etc.;\nReview business processes, assess key risks and evaluate effectiveness as well as adequacy of internal controls system\nLiaise with various management to drive the improvement of internal controls system\nPerform regular follow up of the implementation of improvement plans\nCoordinate with relevant stakeholders on the implementation of risk management enhancment program\nPerform ad hoc internal controls review\nWHO are we looking for:\nBachelor Degree holder of Accounting or equivalent\nHolder of professional qualification, e.g. HKICPA, ACCA, CIA or equivalent\nAt least 3-year audit experience.\nGood interpersonal skill with strong analytical mind, be self-initiative and well-organized\nGood command in written and spoken English and Chinese\nImmediate available is preferred\nCINNOX, a new way to humanise your connections, join us now!\n\nWe offer 5 days\u2019 work, medical insurance, free lunch, competitive salary package and attractive career development opportunities to the right candidate.\u00a0Interested parties please send your full resume with date of availability, present and expected salaries by clicking \"Apply Now\".\n\nFor more information about CINNOX, please visit and subscribe the below linkage:\nCINNOX Webpage\nCINNOX LinkedIn Page\nCINNOX Youtube channel\nTo protect the privacy of personal data, all applications will be treated in strict confidence. Personal data collected will be used for recruitment purposes only. Applicants not hearing from us within 6 weeks may consider their applications unsuccessful. We may also consider their application for other or future vacancies. Personal data of unsuccessful applicants will be retained for a maximum period of 6 months.", "employment_types": ["Full Time", "Permanent"], "selling_points": ["Internal Audit, HKICPA/ACCA/CIA holder", "3+ year experience in audit", "5 day work, medical benefit and free luncheon"], "locations": ["Kowloon Bay"], "categories": ["Admin & HR", "HR Supporting Staff", "Recruitment / Executive Search", "Training & Development"], "post_time": "2022-01-14T11:29:08Z", "salary": {"currency": null, "max": null, "min": null, "period": "monthly", "term": null}, "salary_visible": false, "title_keywords": ["officer"], "responsibilities": [], "requirements": {"degrees": [], "majors": [], "languages": [], "language_level": [], "hard_skills": ["rapid"], "soft_skills": ["passionate", "unique", "committed", "diverse", "driven"], "languages_combined": []}, "experience_required": {"duration": [], "field": []}}, {"job_id": "100003009043653", "location_code": "hk", "company": "Construction Industry Council", "job_title": "Interpreter / Translator for Trade Testing Services to Ethnic Minorities Groups (Part-time)", "description": "Company Description\n\nOur client is a well-known restaurant chain. Due to business expansion, they are currently looking for an Assistant System Manager.\n\nResponsibilities\n\nManage the group\u2019s IT system, platforms and operations.\nWork with vendors and support staff to ensure optimal operation and stability of servers and storages.\nResponsible for day-to-day operations, administration and support on system operation workflows.\nProvide 1st tier system support and manage incident control.\nPrepare and maintain documentations for on infrastructure, systems build, modification and operations.\nManage project planning, process design, UAT, master data maintenance, training and report to Management\nResponsible for infrastructure projects with team members to achieve goals and ensure the projects are delivered to meet the expected outcome.\n\nRequirements\n\nBachelor Degree in Computer Science, Information System or related disciplines\nMinimum 3 years\u2019 working experience in system management and support\nGood knowledge in Azure cloud platform, Microsoft Dynamic 365 and SQL server.\nSolid experience in IT system implementation, service deployment and master data planning.\nExperience in Retail / F&B business would be an advantage.\nStrong user support service experience, solid problem-solving skills, detail-minded, self-motivated and able to work independently.\nGood command of both spoken and written English and Chinese\nInterested parties please send your updated resume in WORD format with current and expected salaries (quoting Employer Ref:)", "employment_types": ["Part Time", "Contract"], "selling_points": ["a recognised degree", "a minimum of 3 years\u2019 post-qualification work exp.", "to provide interpretation and translation services"], "locations": ["Not Specified"], "categories": ["Admin & HR", "Training & Development", "Professional Services", "Translation", "Building & Construction", "Others"], "post_time": "2022-01-13T01:20:21Z", "salary": {"currency": null, "max": null, "min": null, "period": null, "term": null}, "salary_visible": false, "title_keywords": ["translator"], "responsibilities": ["manage project planning", "control", "management", "uat", "maintenance", "data", "operations", "infrastructure", "day-to-day operations", "systems", "design", "maintain", "report", "administration"], "requirements": {"degrees": ["degree", "bachelor", "master"], "majors": ["related disciplines", "it", "computer science"], "languages": ["english", "chinese"], "language_level": ["good command"], "hard_skills": ["azure", "information system", "system implementation", "sql", "dynamic", "deployment", "server", "problem-solving skills"], "soft_skills": ["detail-minded", "self-motivated", "work independently", "dynamic", "problem-solving skills"], "languages_combined": [{"language": "english", "language_level": ["good command"]}, {"language": "chinese", "language_level": ["good command"]}]}, "experience_required": {"duration": ["minimum 3 years"], "field": ["management", "f&b", "it", "business", "retail", "planning"]}}, {"job_id": "100003009035082", "location_code": "hk", "company": "Hong Kong Aircraft Engineering Co Ltd", "job_title": "Assistant Manager, Talent Management", "description": "Scope of Duties:\u00a0\n\nWork collaboratively and in strong partnership with Learning and Development Manager/ Line Managers/ Local HR to drive HAECO Group talent management initiatives, e.g. succession planning;\nLead and manage the talent management team;\nManage and support the development and delivery of talent initiatives;\nNurture the High Flyers within the relevant business area and use existing talent frameworks to support their growth;\nLeverage data from SuccessFactors to provide insights and help inform decisions;\nIdentify and develop competency assessment models for talent development;\nPerform other relevant duties as assigned\n\nRequirements:\u00a0\n\nDegree in Training & Development, Human Resources Management or related discipline;\n5 years of relevant experience in a sizable organization;\nAdvanced project management skills, data savvy, and strong systems thinking and understanding;\nProficiency in MS Office applications e.g. PowerPoint, Excel, and Chinese Word Processing\nStrong supervisory skills and analytical abilities;\nGood team player and people skills to develop rapport with line managers and all levels of employees;\nPositive attitude and able to deal with multi-tasks effectively;\nExcellent command of English and Chinese, both spoken and written. Fluency in Putonghua\n\nHow to Apply:\n\nPlease send your resume with expected salary, quoting the employer's reference no., to: Human Resources Department - Resourcing Team, Hong Kong Aircraft Engineering Company Limited, 80 South Perimeter Road, Hong Kong International Airport, Lantau, Hong Kong OR submit your application via\u00a0https://careers.haeco.com/hkg/job-openings/\n\nCandidates not contacted 4-6 weeks after submission of applications and/or interviews may consider their application unsuccessful.\n\nAll information provided by candidates will be treated in strict confidence and will be used for employment purpose only.", "employment_types": ["Full Time", "Permanent"], "selling_points": ["5 years of relevant experience", "Degree in Training & Development / HRM", "Proficiency in MS Office applications"], "locations": ["Airport Area"], "categories": ["Admin & HR", "Others", "Recruitment / Executive Search", "Training & Development"], "post_time": "2022-01-10T05:53:11Z", "salary": {"currency": null, "max": null, "min": null, "period": "monthly", "term": null}, "salary_visible": false, "title_keywords": ["assistant manager,"], "responsibilities": ["management team", "management", "provide insights", "data", "hr", "develop", "planning"], "requirements": {"degrees": ["degree"], "majors": [], "languages": ["putonghua", "english", "chinese"], "language_level": ["fluency", "excellent"], "hard_skills": ["excel", "no", "chinese word processing", "aircraft", "powerpoint", "project management", "ms office"], "soft_skills": ["good team player", "confidence", "advanced", "multi-tasks", "project management skills", "positive attitude"], "languages_combined": [{"language": "putonghua", "language_level": ["fluency"]}, {"language": "english", "language_level": ["excellent"]}, {"language": "chinese", "language_level": ["excellent"]}]}, "experience_required": {"duration": ["5 years"], "field": ["sizable organization", "relevant experience"]}}, {"job_id": "100003009036374", "location_code": "hk", "company": "Brink's Asia Pacific Limited", "job_title": "HR Coordinator, APAC", "description": "Responsibilities:\n\nTo assist the HR Director, APAC with key initiatives across the APAC region.\n\nAdministrate Monthly Payroll\nDesign, develop and coordinate training programs including but not limited to Leadership training program, for regional offices\nManage the entire performance management process\nCoordinate and implement Staff recognition program\nWork closely with regional offices to collect regional information per country\nAssist in regional HR Project and ad-hoc project assigned by HR Director, APAC\n\nRequirements:\n\nDegree holder in Human Resources Management\nExperience in MNC or sizeable organization preferred\nExcellent command of spoken and written English\nExcellent presentation, facilitation & communication skills\nGood interpersonal skills and able to work with people at different levels\nProficiency in MS Word, Excel and PowerPoint\nImmediate available is highly preferred\n\nFull training will be given. All initiatives are well supported with first class material. We offer attractive remuneration package fringe benefits including Banking Holiday, Annual Leaves, Discretionary Bonus, Additional Pension Contribution from Company &\u00a0Medical Insurance, etc. If you have the desire to join us, please send us your resume immediately with your present and expected salary by clicking \"Apply Now\"\n\n", "employment_types": ["Full Time"], "selling_points": ["Regional role opens to all nationalities", "Full training will be given", "MNC, Good Benefit"], "locations": ["Kwai Fong"], "categories": ["Admin & HR", "Others", "HR Supporting Staff", "Training & Development"], "post_time": "2022-01-11T07:45:23Z", "salary": {"currency": null, "max": null, "min": null, "period": "monthly", "term": null}, "salary_visible": false, "title_keywords": ["hr", "coordinator"], "responsibilities": ["ad-hoc", "management", "hr", "design", "develop", "coordinate", "payroll"], "requirements": {"degrees": ["degree holder"], "majors": [], "languages": ["english"], "language_level": ["excellent"], "hard_skills": ["excel", "powerpoint", "ms word"], "soft_skills": ["communication skills", "interpersonal skills", "presentation"], "languages_combined": [{"language": "english", "language_level": ["excellent"]}]}, "experience_required": {"duration": [], "field": []}}, {"job_id": "100003009038738", "location_code": "hk", "company": "Randstad Hong Kong Limited", "job_title": "Insurance Training Academy Coordinator", "description": "about the company\n\nYou will join a premier wealth solutions provider with teams of global experts and presences across hubs in Asia.\n\nabout the job\n\nYou will coordinate and liaise with internal and external parties for training activities\nYou will provide support to trainer for conducting virtual and onsite training programs\nYou will prepare PowerPoint presentations, training reports and keep all training records\nYou will assist to build marketing programs through different social media platforms\nYou will perform ad hoc tasks or projects as required\n\nskills & experiences required\n\nYou are a Tertiary Education Holder in Training, Business or related disciplines\nYou have 2+ years of administrative support working experience preferably in insurance industry\nYou are well-organized and able to work independently with attention to details\nYou are fluent in Cantonese, Mandarin and English\nYou are proficient in MS Office applications (Word, Excel, PowerPoint, etc.)\n\nTo apply online, please click on the link. Alternatively, for a confidential discussion please contact Jeremy Wong on + 852 2232 3468 or email: jeremy.wong@randstad.com.hk", "employment_types": ["Full Time", "Permanent"], "selling_points": [], "locations": ["Not Specified"], "categories": ["Admin & HR", "Training & Development", "Sales, CS & Business Devpt", "Sales - Sales Management"], "post_time": "2022-01-11T07:42:26Z", "salary": {"currency": "HKD", "max": 29999, "min": 25000, "period": "monthly", "term": null}, "salary_visible": true, "title_keywords": ["coordinator"], "responsibilities": ["provide support", "administrative support", "training activities", "internal and external parties", "teams", "social media platforms", "presentations", "ad hoc tasks", "coordinate", "reports", "contact", "liaise with", "insurance"], "requirements": {"degrees": [], "majors": [], "languages": ["cantonese", "english", "mandarin"], "language_level": ["fluent"], "hard_skills": ["excel", "word", "presentations", "powerpoint", "ms office"], "soft_skills": ["work independently", "well-organized", "attention to details"], "languages_combined": [{"language": "cantonese", "language_level": ["fluent"]}, {"language": "english", "language_level": ["fluent"]}, {"language": "mandarin", "language_level": ["fluent"]}]}, "experience_required": {"duration": ["2+ years"], "field": ["administrative", "insurance industry"]}}, {"job_id": "100003009037387", "location_code": "hk", "company": "WilliamSELECT", "job_title": "Retail Training Manager - Skincare Beauty", "description": "My client is an International Beauty Skincare brand and they are looking for a seasoned leader for training team.\n\nResponsibilities:\n\nOversees and identify retail training strategy, direction and needs\nDevelop training program and lead the training for all front line staffs\nIdentify training needs and create strategies\nAlign the training requirement with HQ and global\nMotivate and coach frontline team, maintain the quality standards\nConduct field coaching\nPrepare training materials\nMaintain regular communication with staff and monitor performance\nPromote customer-centric culture\n\nRequirements:\n\nBachelor Degree holder\nAt least 8 years of retail training experience\nStrong leadership and coaching skills\u00a0\nAbility to work under pressure\nSelf-motivated and detail oriented\nExcellent English and Chinese\u00a0\u00a0", "employment_types": ["Full Time"], "selling_points": ["From training framework to delivery from scratch", "Training strategy, program and field coaching", "Premium Skincare brand"], "locations": ["Not Specified"], "categories": ["Sales, CS & Business Devpt", "Customer Service - Manager", "Admin & HR", "Training & Development", "Retail Sales"], "post_time": "2022-01-11T02:41:02Z", "salary": {"currency": "HKD", "max": 69999, "min": 45000, "period": "monthly", "term": null}, "salary_visible": true, "title_keywords": ["manager"], "responsibilities": ["monitor performance", "quality", "develop", "communication", "maintain"], "requirements": {"degrees": ["bachelor degree holder"], "majors": [], "languages": ["english", "chinese"], "language_level": ["excellent"], "hard_skills": [], "soft_skills": ["detail oriented", "self-motivated", "leadership", "work under pressure"], "languages_combined": [{"language": "english", "language_level": ["excellent"]}, {"language": "chinese", "language_level": ["excellent"]}]}, "experience_required": {"duration": ["at least 8 years"], "field": ["retail", "training"]}}, {"job_id": "100003009021452", "location_code": "hk", "company": "Abercrombie&Fitch", "job_title": "MIT - Store Management - Hollister / Abercrombie & Fitch", "description": "The Career Progression\n\nThe MIT must complete the training to be moved on into the Assistant Manager role. Successful completion of the program is the first step for leadership. The MIT program is a blended-learning, 90 days program focused on immersing a manager in all aspects involved in running a multi-million dollar business. Training takes place in store locations. The program trains you on the necessary principles of management including creating the best In-store Customer Experience, Store Operations, Business Management, Floor Supervision and Talent Management.\n\nSuccessful completion of the program is the first step for leadership. The company strongly advocates philosophy of growth from within. All of our District Managers, Regional Managers, Directors, even our Vice President of Stores have gone through the MIT Program.\n\nWhy Us\u00a0\u00a0\n\nAbercrombie & Fitch Co. Named to the 2021 Best Workplaces in Retail List by Fortune Magazine and Great Place to Work\u00ae\nWe provide you an access to various me**tal health resources: Associates Assistant Program, headspace, CARORRT and associate resource group\u2026etc\nA Global Team of People Who'll Celebrate you for Being YOU\nOur culture is inclusive, warm and authentic\nWe value individual differences\u00a0\nWe inspire, support and encourage you to be the best they can\nWe provide you an Always Forward journey\nWe believe Diversity and Inclusion are the keys to the company\u2019s success\nWe put the customer at the center of everything we do\n\u00a0\n\nWhat You\u2019ll Get\n\nSalary $240 - 270K annually\n13th month bonus\nMonthly Sale Incentive Bonus Program\nGeneralist paid time off\nPaid Volunteer Day per Year, allowing you to give back to your community Staff\nMerchandise Discount in all brands\u00a0\nMedical and Dental Insurance\nParental leave\nLeadership Training and Development\nOpportunities for Career Advancement, promoting from within\n\nWhat it Takes\n\nBachelor\u2019s degree from an accredited university\nCustomer focused\nStrong interpersonal and communication skills\nTeam building skills\nStrong analytical and problem-solving skills\nSelf-starter\nDrive to achieve results\nInclusion & Diversity awareness\nInterest in fashion and retail\nAbility to work in a fast-paced and challenging environment\n\nFIND A STORE IN YOUR AREA\n\nHarbour City\u00a0\u00a02770 3618\nHysan Place\u00a0\u00a0\u00a02524 0913\nFestival Walk\u00a02567 5023\nYOHO Mall\u00a0\u00a0\u00a0\u00a0\u00a02527 0210\n\nAPPLY AT\n\nCAREERS.HOLLISTERCO.COM\n\nCAREERS.ABERCROMBIE.COM\n\nSEE WHAT IT\u2019S LIKE TO #WORKATHCO (#WORKATANF) - FOLLOW US ON INSTAGRAM @WORKATHK_ANFHCO\n\nAny job offers for this role could be subject to and conditional upon the applicant carrying out applicable work visa formalities. You could be contacted by the company to find out which documents you will need to provide.\n\nAbercrombie & Fitch Co. is an Equal Opportunity/Affirmative Action employer", "employment_types": ["Full Time"], "selling_points": ["Bachelor Degree", "Entry Level", "$240 - 270K annually/13th month bonus/Sales Bonus"], "locations": ["Not Specified"], "categories": ["Management", "General Management", "Admin & HR", "Training & Development", "Sales, CS & Business Devpt", "Sales - Sales Management"], "post_time": "2022-01-10T06:04:35Z", "salary": {"currency": "HKD", "max": 24999, "min": 17000, "period": "monthly", "term": null}, "salary_visible": true, "title_keywords": [], "responsibilities": ["operations", "management"], "requirements": {"degrees": [], "majors": [], "languages": [], "language_level": [], "hard_skills": ["business management"], "soft_skills": ["learning", "leadership", "focused"], "languages_combined": []}, "experience_required": {"duration": [], "field": ["management", "business"]}}, {"job_id": "100003009043261", "location_code": "hk", "company": "Michael Page", "job_title": "People Analytics Lead - MNC", "description": "Our client is a well-established conglomerate, with group office in Hong Kong and a strong international presence. They have offices across the globe, multiple locations in America, Asia, and Europe. They provide quality products with a strong reputation and have excellent business performance in recent years. They are currently looking for an HR Data Analytics Manager for the Hong Kong Group office.\n\nClient Details\n\nOur client is a well-established conglomerate, with group office in Hong Kong and a strong international presence. They have offices across the globe, multiple locations in America, Asia, and Europe. They provide quality products with a strong reputation and have excellent business performance in recent years. They are currently looking for an HR Data Analytics Manager for the Hong Kong Group office.\n\nCompany Culture:\n\nFlexible work arrangement\nInternational team, lean structure\nYoung and energetic\nNice and friendly working environment\nEncourage internal mobility\n\nDescription\n\nBe the people analytics champion, responsible for development of our future strategy data analysis, providing people insights through HR data, related to talent acquisition, talent mgmt. and dev., staff retention, engagement, etc.\nBe a strategic advisor to identify gaps, business needs from HR data perspectives\nDefine HR analytics to identify productivity improvement opportunities and drive HR governance and ensure the programs/changes/transitions are delivered effectively\nPartner closely with other HR leads to support pay/incentive structure, salary benchmark & related analysis through consultation and advisory\nLead a variety of HR data programs. Create and design implementation of common methodologies and tools for data audit, process compliance and project management\n\nProfile\n\nBachelor's degree in relevant disciplines\nAt least 8 years' experience in planning and running HR Data Analytics programs / projects from multinational company background\nCapable in executing HR projects, and implementing various programs through regular communication with group HR team\nFlexible, Detail-minded, good team player, well-organized with good interpersonal skills\nFluent English and Chinese, both written and spoken\nStrong computer skills, using MS Office\n\nJob Offer\n\nPermanent opportunity\n5 days' work\nWork from home policy in place\nGreat Discretionary Bonus\nComprehensive medical coverage for staff and dependant\nDental insurance\nAnnual Body Check Up\nExciting Project Exposure\nWork life balance\nMNC Working environment\nRegional Exposure", "employment_types": ["Full Time", "Permanent"], "selling_points": ["Well established Business", "Flexi Work Arrangement", "Friendly and team-based culture"], "locations": ["Not Specified"], "categories": ["Admin & HR", "Others", "HR Director / Manager", "Training & Development"], "post_time": "2022-01-12T10:24:41Z", "salary": {"currency": null, "max": null, "min": null, "period": "monthly", "term": null}, "salary_visible": false, "title_keywords": ["lead"], "responsibilities": ["data", "hr", "analysis", "quality", "implementation", "design", "audit", "data analysis", "compliance", "project management", "communication", "executing", "insurance", "planning"], "requirements": {"degrees": ["degree", "bachelor"], "majors": [], "languages": ["english", "chinese"], "language_level": ["fluent"], "hard_skills": ["lean", "data analytics", "analysis", "nice", "project management", "computer skills", "ms office"], "soft_skills": ["flexible", "detail-minded", "good team player", "capable", "responsible", "well-organized", "communication", "project management", "comprehensive", "friendly", "interpersonal skills", "energetic", "mobility"], "languages_combined": [{"language": "english", "language_level": ["fluent"]}, {"language": "chinese", "language_level": ["fluent"]}]}, "experience_required": {"duration": ["at least 8 years"], "field": ["hr", "multinational company", "planning"]}}, {"job_id": "100003009032789", "location_code": "hk", "company": "Trade Connects (Asia) Company", "job_title": "Senior Training Development Officer", "description": "Job Requirements\u00a0\n\nDegree holder in Training, HR Management or related disciplines\u00a0\n6 years or above experience in learning program development and delivery\u00a0\nPrevious experience developing soft skills and customer service program\u00a0\nExperience in e-Learning program development, preferably in sizable MNCs\u00a0\nSelf-motivated, efficient, detail-minded, energetic with good presentation skills\u00a0\nConversant with computer skills in MS Word, Excel, PowerPoint and HR system\u00a0\nGood communication of spoken & written English, Mandarin is a plus\u00a0\nImmediate available is a great advantage\u00a0\n\nJob Responsibilities\u00a0\n\nResponsible for planning, designing and managing training & development programs\u00a0\nAct as key trainer to develop and deliver quality soft-skills and customer service programs\u00a0\nFormulate and execute appropriate training programs to align with business objectives\u00a0\nDevelop and prepare training materials and maintain proper training record in the system\u00a0\nEstablish the evaluation and follow-up system to ensure the effectiveness of training programs\u00a0\n\nExcellent development prospects and attractive fringe benefits will be offered to the right candidates. Interested parties, please send full resume with last & expected salary and date of available by clicking \u2018Apply Now\u2019\u00a0", "employment_types": ["Full Time", "Permanent"], "selling_points": [], "locations": ["Not Specified"], "categories": ["Admin & HR", "HR Director / Manager", "HR Supporting Staff", "Training & Development"], "post_time": "2022-01-07T17:19:35Z", "salary": {"currency": null, "max": null, "min": null, "period": "monthly", "term": null}, "salary_visible": false, "title_keywords": ["officer"], "responsibilities": ["evaluation", "development programs", "quality", "develop", "customer service", "maintain", "designing", "planning"], "requirements": {"degrees": ["degree holder"], "majors": ["related disciplines"], "languages": ["english", "mandarin"], "language_level": ["good"], "hard_skills": ["excel", "plus", "powerpoint", "computer skills", "ms word"], "soft_skills": ["efficient", "detail-minded", "self-motivated", "communication", "presentation skills", "learning", "customer service", "energetic"], "languages_combined": [{"language": "english", "language_level": ["good"]}, {"language": "mandarin", "language_level": ["good"]}]}, "experience_required": {"duration": ["6 years"], "field": ["development", "customer service", "developing"]}}, {"job_id": "100003009043411", "location_code": "hk", "company": "Michael Page", "job_title": "Employee Engagement Lead - MNC", "description": "Our client is a well-established conglomerate, with group office in Hong Kong and a strong international presence. They have offices across the globe, multiple locations in America, Asia, and Europe. They provide quality products with a strong reputation and have excellent business performance in recent years. They are currently looking for an Employee Engagement Lead for the Hong Kong Group office.\n\nClient Details\n\nOur client is a well-established conglomerate, with group office in Hong Kong and a strong international presence. They have offices across the globe, multiple locations in America, Asia, and Europe. They provide quality products with a strong reputation and have excellent business performance in recent years. They are currently looking for an Employee Engagement Lead for the Hong Kong Group office.\n\nCompany Culture:\n\nFlexible work arrangement\nInternational team, lean structure\nYoung and energetic\nNice and friendly working environment\nEncourage internal mobility\n\nDescription\n\nEstablish and deliver best in class employee experiences and engagement strategy\nDevelop creative campaigns and initiatives, improve employee lifecycle and experience, and share best practice across the organization\nDrive Change Management, integrate technology to improve internal communication and connection\nWork closely with senior management to organise and support employee engagement events and activities aligning with group vision and goals\nPartner with HR colleagues to connect employee value proposition and employer brand to all parts of the employee lifecycle\nMeasure employee engagement program and strategies outcome through dashboard and reporting\n\nProfile\n\nBachelor's degree in relevant disciplines\nAt least 8 years' experience in Employee Engagement in sizable and international organizations\nCapable in executing Employee Engagement survey, projects and vendor management\nFlexible, Detail-minded, good team player, well-organized with good interpersonal skills\nFluent English and Chinese, both written and spoken\nStrong computer skills, using MS Office\n\nJob Offer\n\n5 days' work\nWork from home policy in place\nGreat Discretionary Bonus\nComprehensive medical coverage for staff and dependant\nDental insurance\nAnnual Body Check Up\nExciting Project Exposure\nWork life balance\nMNC Working environment", "employment_types": ["Full Time", "Contract"], "selling_points": ["Friendly and team-based culture", "Flexi Work Arrangement", "Attractive benefit and remuneration package"], "locations": ["Not Specified"], "categories": ["Admin & HR", "Others", "HR Director / Manager", "Training & Development"], "post_time": "2022-01-12T11:33:42Z", "salary": {"currency": "HKD", "max": 119999, "min": 70000, "period": "monthly", "term": null}, "salary_visible": true, "title_keywords": ["lead"], "responsibilities": ["reporting", "management", "change management", "hr", "quality", "develop", "communication", "executing", "senior management", "insurance"], "requirements": {"degrees": ["degree", "bachelor"], "majors": [], "languages": ["english", "chinese"], "language_level": ["fluent"], "hard_skills": ["lean", "nice", "vendor", "computer skills", "ms office"], "soft_skills": ["flexible", "detail-minded", "good team player", "capable", "well-organized", "communication", "energetic", "comprehensive", "friendly", "interpersonal skills", "creative", "mobility"], "languages_combined": [{"language": "english", "language_level": ["fluent"]}, {"language": "chinese", "language_level": ["fluent"]}]}, "experience_required": {"duration": ["at least 8 years"], "field": []}}, {"job_id": "100003009045317", "location_code": "hk", "company": "AXA Region Insurance Company Limited", "job_title": "\u6bcf\u54684\u5929\u5de5\u4f5c\u4e0d\u8a2d\u696d\u7e3e\u58d3\u529b / \u8ca1\u5bcc\u7406\u8ca1\u7d93\u7406 Wealth Management Manager/ \u5f37\u7a4d\u91d1\u6574\u5408\u5c08\u54e1 MPF Consultant", "description": "\u6211\u5011\u63d0\u4f9b\u5168\u9762\u4e00\u7ad9\u5f0f\u7406\u8ca1\u670d\u52d9\uff1a\u5305\u62ec: \u8ca1\u5bcc\u7ba1\u7406\uff0c\u8cc7\u7522\u50b3\u627f\uff0c\u9000\u7a05\u81ea\u9858\u91ab\u4fdd\uff0c\u5371\u75be\u4fdd\u969c\u3001\u77ed\u671f\u9ad8\u5132\u755c\u7522\u54c1\u3001\u5f37\u7a4d\u91d1\u6574\u5408\uff0c\u9000\u7a05\u5e74\u91d1\u9000\u4f11\u7b56\u5283\u3001\u4e00\u822c\u4fdd\u96aa\u3001\u516c\u53f8\u5718\u9ad4\u91ab\u7642\uff0c\u4f01\u696d\u4fdd\u96aa\n\n\u6211\u5011\u62db\u52df\u6709\u610f\u5275\u696d\u6216\u767c\u5c55\u500b\u4eba\u4e8b\u696d\u7684\u60a8\uff0c\u4ee5\u96f6\u6210\u672c\u6253\u9020\u4e00\u500b\u7531\u60a8\u81ea\u5df1\u8a71\u4e8b\u7684\u8ca1\u7b56\u672a\u4f86\uff01\n\n\u5982\u679c\u4f60\u662f\n\n\u5177\u4f01\u696d\u5bb6\u614b\u5ea6\uff0c\u6709\u5fd7\u5c0b\u627e\u9ad8\u6536\u5165\n\u4e8b\u696d\u505c\u6eef\u4e0d\u524d\uff0c\u6c92\u6709\u767c\u5c55\u7a7a\u9593\n\u5617\u8a66\u4e00\u500b\u65b0\u7684\u884c\u696d\u6311\u6230\uff0c\u6539\u8b8a\u73fe\u72c0\n\u5de5\u4f5c\u91cd\u8986\u6c89\u60b6\n\u559c\u6b61\u5f48\u6027\u81ea\u4e3b\u5de5\u4f5c\u6a21\u5f0f\n\u597d\u62fc\u640f\u4f46\u662f\u6536\u5165\u8207\u52aa\u529b\u4e0d\u6210\u6b63\u6bd4\n\n\u5982\u679c\u4f60\u52e4\u596e\u9032\u53d6\uff0c\u4fdd\u96aa\u7406\u8ca1\u4e8b\u696d\u7d55\u5c0d\u662f\u4e00\u4efd\u975e\u5e38\u6709\u6311\u6230\u6027\u7684\u5de5\u4f5c\uff0c\u7d55\u5c0d\u591a\u52de\u591a\u5f97\n\n\u52a0\u5165\u6211\u5011AXA\u5b89\u76db !!\u00a0\n\n\u5de5\u4f5c\u7bc4\u570d\u00a0\n\n\u70ba\u5ba2\u6236\u5ea6\u8eab\u5b9a\u505a\u9069\u5207\u7406\u8ca1\u65b9\u6848\uff0c\u5305\u62ec\u4fdd\u96aa, \u6559\u80b2\u57fa\u91d1, \u9000\u4f11\uff0c\u50b3\u627f\uff0c\u6295\u8cc7\u7b49\u65b9\u6848\n\u4e00\u822c\u4fdd\u96aa\u7522\u54c1\u54a8\u8a62\u53ca\u5831\u50f9\u670d\u52d9\u00a0\u00a0\n\u5f37\u7a4d\u91d1\u670d\u52d9\n\u4f01\u696d\u4fdd\u96aa\uff0c\u5718\u9ad4\u91ab\u7642\n\n\u5165\u8077\u8981\u6c42\n\n\u5927\u5c08\u6216\u5927\u5b78\u4ee5\u4e0a\uff0c\u85aa\u91d1\u7279\u512a\u00a0\n\u9999\u6e2f\u4e2d\u4e94\u6216\u4ee5\u4e0a\u7a0b\u5ea6 \uff0c\u570b\u5167\u9ad8\u8003\u5b78\u6b77\u6216\u4ee5\u4e0a\u00a0\n\u7121\u9700\u5de5\u4f5c\u7d93\u9a57\uff0c\u6b61\u8fce\u570b\u5167\u50d1\u80de\uff0c\u65b0\u79fb\u6c11\uff0c\u6301 IANG \u7c3d\u8b49\u5c08\u624d\u52a0\u76df\n\u6b61\u8fce\u4fdd\u96aa\u540c\u696d, \u9280\u884c\u8077\u54e1\u8f49\u8077, \u53ef\u76f4\u63a5\u5b89\u6392\u7ba1\u7406\u8077\u4f4d\u53ca\u7279\u512a\u5f85\u9047 (\u8f49\u8077\u88dc\u511f\u91d1)\n\u826f\u597d\u4eba\u969b\u95dc\u4fc2\uff0c\u6e9d\u901a\u6280\u5de7\u00a0\n\u826f\u597d\u7684\u5718\u968a\u5408\u4f5c\u7cbe\u795e\uff0c\u80fd\u5920\u5728\u58d3\u529b\u4e0b\u7368\u7acb\u5de5\u4f5c\u00a0\n\u52e4\u596e\u5916\u5411\uff0c\u71b1\u8aa0\uff0c\u8cac\u4efb\u611f\u00a0\n\n\u6211\u5011\u63d0\u4f9b\uff1a\u00a0\n\n\u514d\u8cbb\u8003\u8a66\u5377\u4e00\u5377\u4e09\u00a0\n24\u500b\u6708\u8ca1\u52d9\u652f\u63f4\uff08\u6bcf\u6708\u6d25\u8cbc $10,000- $40,000\uff09+ \u7121\u4e0a\u9650\u4f63\u91d1 \uff0b9\u500b\u82b1\u7d05 \uff0b\u767e\u842c\u5713\u684c\u6703\u82b1\u7d05\n\u89c0\u5858\u7532\u7d1a\u5beb\u5b57\u6a13\n\u5b8c\u5584\u5728\u8077\u57f9\u8a13\n\u63d0\u4f9b\u6a5f\u6703\u8003\u53d6\u300a\u6838\u51c6\u9000\u4f11\u9867\u554fQRA\u300b\u300a\u4eba\u58fd\u4fdd\u96aa\u6838\u4fdd\u8b49\u66f8\u300b\u7b49\u5c08\u696d\u8cc7\u683c\u00a0\n\nMDRT\u5718\u968a\u57f9\u8a13\u5e2b\uff0c\u884c\u696d\u5091\u51fa\u63a8\u92b7\u54e1\u734e(DSA)\u51a0\u8ecd\u57f9\u8a13\u5e2b\u5718\u968a\n\u52a9\u4f60\u6210\u70ba\u884c\u696d\u7cbe\u82f1\uff0c\u6210\u70baMDRT\uff0c\u7279\u5feb\u767c\u5c55\u5c6c\u65bc\u81ea\u5df1\u7684\u7406\u8ca1\u7b56\u5283\u4e8b\u696d!", "employment_types": ["Full Time"], "selling_points": ["\u6bcf\u6708\u6d25\u8cbc $10,000- $40,000 + \u7121\u4e0a\u9650\u4f63\u91d1 \uff0b9\u500b\u82b1\u7d05", "\u6bcf\u5e74\u696d\u7e3e\u734e\u8cde\u74b0\u7403\u65c5\u904a \uff0c\u5718\u9ad4\u91ab\u7642\u798f\u5229", "\u7279\u5feb\u5347\u8077\u6a5f\u6703"], "locations": ["Kwun Tong"], "categories": ["Banking / Finance", "Credit Analysis / Approval", "Admin & HR", "Training & Development", "Others", "Student / Fresh Graduate / No Experience"], "post_time": "2022-01-13T07:36:33Z", "salary": {"currency": null, "max": null, "min": null, "period": "monthly", "term": null}, "salary_visible": false, "title_keywords": ["wealth management manager", "mpf consultant"], "responsibilities": [], "requirements": {"degrees": [], "majors": [], "languages": [], "language_level": [], "hard_skills": [], "soft_skills": [], "languages_combined": []}, "experience_required": {"duration": [], "field": []}}, {"job_id": "100003009031932", "location_code": "hk", "company": "Dah Chong Hong Holdings Limited", "job_title": "Group Learning & Development Officer (Ref: L&DO \u2013 GHR)", "description": "The incumbent is responsible for designing, delivering, organizing and following-up various corporate training programmes, organization development initiatives and campaigns in the Group.\n\nResponsibilities:\n\nFormulate, organise and execute learning initiatives and activities in the group level with clear planning and training objectives\nDesign and develop digital self-learning materials, campaign and assessment for generic training programmes\nResponsible for orientation programme to create fun and professional employee experience\nEvaluate the effectiveness of training programmes and take follow-up actions.\nAssist in controlling overall expenses, preparing reports and maintaining employee database\nProvide support for Group-wide organization development initiatives and programmes\nProvide administration support for programmes and campaigns\nHandle other ad hoc projects when necessary.\n\nRequirements:\n\nUniversity graduate with minimum of 3 years of relevant working experience\nExperience in self-learning materials design and implementation is required\nProactive learner with positive and can-do attitude\nExcellent presentation, communication, and project management skills\nDetail-minded, well-organized, creative in idea generation and application in daily work\nResponsible, flexible, and able to work in face-paced environment\nExcellent command of spoken and written English, Chinese and Putonghua is required\nProficient in video editing, MS Office application and Chinese Word Processing\n\n*Candidates with more experience will be considered for Senior Learning & Development Officer\n\n*Candidates with less experience will be considered for Assistant Learning & Development Officer\n\nWe offer competitive salary, discretionary bonus, medical insurance, life and personal accident insurance, annual leave and staff purchase discount. Interested candidates please send your resume with salary expectation by email or clicking \"Apply Now\".\n\nWe are equal opportunities employer. Applicants who are not invited within 2 months may consider their application unsuccessful. All applicants may be considered for other suitable positions with DCH Group / CITIC Pacific Group and will be deleted from our files after 6 months from the date of application.", "employment_types": ["Full Time", "Permanent"], "selling_points": [], "locations": ["Kowloon Bay"], "categories": ["Admin & HR", "Others", "HR Supporting Staff", "Training & Development"], "post_time": "2022-01-07T09:59:19Z", "salary": {"currency": null, "max": null, "min": null, "period": "monthly", "term": null}, "salary_visible": false, "title_keywords": ["officer"], "responsibilities": ["administration", "provide support", "maintaining", "expenses", "design and develop", "evaluate", "ad hoc projects", "preparing reports", "database", "planning"], "requirements": {"degrees": ["university graduate"], "majors": [], "languages": ["putonghua", "english", "chinese"], "language_level": ["excellent", "proficient"], "hard_skills": ["video editing", "project management", "chinese word processing", "ms office"], "soft_skills": ["detail-minded", "flexible", "creative", "responsible", "can-do attitude", "project management skills", "well-organized", "communication", "learning", "proactive", "presentation", "positive"], "languages_combined": [{"language": "putonghua", "language_level": ["excellent"]}, {"language": "english", "language_level": ["excellent"]}, {"language": "chinese", "language_level": ["excellent", "proficient"]}]}, "experience_required": {"duration": ["minimum of 3 years"], "field": ["learning & development", "relevant working experience", "design"]}}, {"job_id": "100003009037912", "location_code": "hk", "company": "Hsin Chong Aster Building Services Limited", "job_title": "Assistant Human Resources Officer / Human Resources Assistant (Ref: HR)", "description": "We are a well-established Building Services Contractor.\u00a0 To cope with our rapid business development, we are now looking for high caliber talents to join our company.\n\n\n\n\u00a0Job Responsibilities:\n\nAssist in all-rounded human resources functions, including staff recruitment, compensation & benefits administration, staff relations, performance management, training and development;\nParticipate\u00a0in\u00a0 annual HR exercises and ad-hoc tasks as assigned.\nJob Requirements:\n\nDiploma or above in Human Resources Management or equivalent;\n1-2 years of relevant HR experience;\nWell versed in Hong Kong Employment Ordinance and other HR related ordinances;\nSelf-driven, well-organized and detail-minded;\nGood interpersonal and communication skills;\nStrong computer literacy in MS Office, with HRIS experience is preferred;\nCandidate with less experience will be considered as Human Resources Assistant.\nFresh graduates are welcomed.\n\nInterested parties, please apply with full resume, date availability, current and expected salary to the Human Resources Manager by clicking \"Apply Now\".\n\nTo learn more about us, please visit our website: aster.hk.com\u00a0\n\nWe are an equal-opportunity employer and welcome applications from all qualified candidates. Personal data collected will be treated in strict confidence and will be used for recruitment purpose only.\u00a0 Applicants who are not invited for an interview within 8 weeks may consider their applications unsuccessful.\n", "employment_types": ["Full Time", "Permanent"], "selling_points": ["HR / C&B / Recruitment / Training", "HR Generalist / All rounded HR functions", "Human Resources Assistant / Assistant HR Officer"], "locations": ["Ngau Tau Kok"], "categories": ["Admin & HR", "Compensation & Benefits", "HR Supporting Staff", "Training & Development"], "post_time": "2022-01-11T04:13:23Z", "salary": {"currency": null, "max": null, "min": null, "period": "monthly", "term": null}, "salary_visible": false, "title_keywords": ["assistant human resources officer", "hr", "human resources assistant"], "responsibilities": ["management", "hr", "ad-hoc tasks", "recruitment", "human resources functions", "administration"], "requirements": {"degrees": ["diploma or above"], "majors": [], "languages": [], "language_level": [], "hard_skills": ["hong kong employment ordinance", "ms office"], "soft_skills": ["detail-minded", "communication skills", "well-organized", "driven", "computer literacy", "interpersonal"], "languages_combined": []}, "experience_required": {"duration": ["1-2 years"], "field": ["hr", "human resources"]}}, {"job_id": "100003009034951", "location_code": "hk", "company": "Citybase Property Management Limited", "job_title": "Human Resources Officer", "description": "Responsibilities\n\nResponsible for Human Resources functions including recruitment, employee services, staff training and staff relations\nProvide HR services and professional advice to internal\u00a0and external customers\nParticipate in ad hoc HR projects as assigned\n\nRequirements\n\nDiploma or above in Human Resources Management, Business Administration or related disciplines\nMinimum\u00a03 years' relevant experience gained from\u00a0sizable organization or property management companies preferred\nWell versed in Hong Kong Employment Ordinance and related legislations\nGood\u00a0computer literacy in MS office and Human Resources Information System, e.g. IPL\nGood command of both written and spoken in English and Chinese (Cantonese)\nMeticulous, mature, independent with strong sense of responsibility\nImmediate availability is preferred\nThe working location is Tai Kok Tsui\n\nWe will offer attractive compensation package to the right candidate. Please send application enclosing resume stating career and salary history, expected salary and date of availability to The Human Resources Manager, Citybase Property Management Limited, Unit No.1, 6/F, Hampton Loft, 11 Hoi Fan Road, Tai Kok Tsui, Kowloon by fax at 2717 4717 or by clicking ''Apply Now'' (in word format). Please quote the reference of the position you apply for in all correspondences.\n\nWe are an equal opportunity employer and welcome applications from all qualified candidates. Personal data collected will be treated in strictest confidence and handled confidentially by authorized personnel for recruitment-related purposes within the Group. Applicants not hearing from us within six weeks from the date of advertisement may consider their applications unsuccessful.", "employment_types": ["Full Time", "Permanent"], "selling_points": ["Diploma holder", "Minimum 3 year relevant experience", "Well versed in Hong Kong Employment Ordinance"], "locations": ["Mong Kok"], "categories": ["Admin & HR", "HR Supporting Staff", "Training & Development", "Property / Real Estate", "Property Management"], "post_time": "2022-01-10T04:49:31Z", "salary": {"currency": null, "max": null, "min": null, "period": "monthly", "term": null}, "salary_visible": false, "title_keywords": ["human resources officer"], "responsibilities": ["internal and external customers", "ad hoc", "hr", "recruitment", "human resources functions"], "requirements": {"degrees": ["diploma or above"], "majors": ["related disciplines", "business administration"], "languages": ["cantonese", "english", "chinese"], "language_level": ["good command"], "hard_skills": ["no", "hong kong employment ordinance", "ipl", "information system", "word", "ms office"], "soft_skills": ["meticulous", "confidence", "independent", "sense of responsibility", "mature", "computer literacy"], "languages_combined": [{"language": "cantonese", "language_level": ["good command"]}, {"language": "english", "language_level": ["good command"]}, {"language": "chinese", "language_level": ["good command"]}]}, "experience_required": {"duration": ["minimum 3 years"], "field": ["sizable organization", "management", "relevant experience"]}}, {"job_id": "100003009034426", "location_code": "hk", "company": "Hong Kong Aircraft Engineering Co Ltd", "job_title": "Group Talent Management Specialist", "description": "Scope of Duties:\u00a0\n\nWork closely with Assistant Manager, Group Talent Management;\u00a0\u00a0\nEngage in talent review, succession planning and performance management exercises across all HAECO Group entities;\u00a0\nManage the talent management programmes for the Group;\u00a0\u00a0\nAdminister and maintain the Performance Management and Succession Planning systems;\u00a0\nProvide regular tracking reports and relevant analysis.\u00a0\nLiaise and negotiate with internal and external parties on talent development related activities;\u00a0\u00a0\nPerform other relevant duties as assigned\u00a0\n\nRequirements:\u00a0\n\nHolder of recognised degree in Human Resources or related disciplines;\u00a0\u00a0\n3 years of solid experience in talent management or human resources functions at sizable organisations;\u00a0\u00a0\nAttention to details, action-oriented and a good team player;\u00a0\u00a0\nExcellent communication and interpersonal skills;\u00a0\u00a0\nHands-on experience in SAP/ HR systems is preferred;\u00a0\nProficiency in MS Office applications e.g. Word, PowerPoint and Excel\u00a0\nExcellent command of English and Chinese, both spoken and written, fluency in Putonghua will be an advantage\u00a0\n\nHow to Apply:\n\nPlease send your resume with expected salary, quoting the employer's reference no., to: Human Resources Department - Talent & Partnership Team, Hong Kong Aircraft Engineering Company Limited, 80 South Perimeter Road, Hong Kong International Airport, Lantau, Hong Kong OR submit your application via\u00a0https://careers.haeco.com/hkg/job-openings/\n\nCandidates not contacted 4-6 weeks after submission of applications and/or interviews may consider their application unsuccessful.\n\nAll information provided by candidates will be treated in strict confidence and will be used for employment purpose only.", "employment_types": ["Full Time", "Permanent"], "selling_points": ["3 years of solid experience in talent management", "Holder of recognised degree in Human Resources", "Hands-on experience in SAP/ HR systems"], "locations": ["Airport Area"], "categories": ["Admin & HR", "Others", "Recruitment / Executive Search", "Training & Development"], "post_time": "2022-01-10T03:24:21Z", "salary": {"currency": null, "max": null, "min": null, "period": "monthly", "term": null}, "salary_visible": false, "title_keywords": ["specialist"], "responsibilities": ["liaise", "management", "tracking", "analysis", "review", "systems", "internal and external parties", "maintain", "reports", "planning"], "requirements": {"degrees": ["degree"], "majors": ["related disciplines"], "languages": ["putonghua", "english", "chinese"], "language_level": ["fluency", "advantage", "excellent"], "hard_skills": ["excel", "no", "sap", "aircraft", "word", "powerpoint", "ms office"], "soft_skills": ["good team player", "confidence", "hands-on", "communication and interpersonal skills", "attention to details"], "languages_combined": [{"language": "putonghua", "language_level": ["fluency", "advantage", "excellent"]}, {"language": "english", "language_level": ["advantage", "excellent"]}, {"language": "chinese", "language_level": ["advantage", "excellent"]}]}, "experience_required": {"duration": ["3 years"], "field": ["hr", "management", "human resources"]}}, {"job_id": "100003009030218", "location_code": "hk", "company": "Walters People (HK)", "job_title": "Senior eLearning Officer - Technology Manufacturer (28-32K)", "description": "Our client is one of the leading technology manufacturers in Hong Kong. With their expanding business, they are now seeking for a Senior eLearning Officer to join their team.\n\nMain Responsibilities\n\nMaintain data integrity for the Workday LMS (Learning Management System), such as course descriptions, course or class changes, training content, materials, user groups etc.\nAssist in establishing TTM global eLearning ecosystem and creates course design templates\nCreate user groups and permissions, manual course assignments/adjustments, train users on LMS\nProvide governance, oversight, and general management of the LMS by communicating policies and standards\nCoordinate and facilitate webinar activities\nCarry out ad hoc projects and tasks assigned by department head\n\nMain Requirements\n\nBachelor Degree in HR Management or equivalent\nMinimum of 5 years experience in eLearning/ Training & Development\nExperienced in eLearning authoring tools is preferred\nStrong in project management skills, detail-minded and able to work under pressure\nGood command of both English, Cantonese and Mandarin", "employment_types": ["Full Time", "Permanent"], "selling_points": ["Leading Technologies Manufacturer", "Career Development", "Attractive Package"], "locations": ["Not Specified"], "categories": ["Admin & HR", "Others", "HR Supporting Staff", "Training & Development"], "post_time": "2022-01-07T06:59:49Z", "salary": {"currency": "HKD", "max": 29999, "min": 25000, "period": "monthly", "term": null}, "salary_visible": true, "title_keywords": ["officer"], "responsibilities": ["management", "policies", "design", "coordinate", "ad hoc projects", "maintain data"], "requirements": {"degrees": ["degree", "bachelor"], "majors": [], "languages": ["cantonese", "english", "mandarin"], "language_level": ["good command"], "hard_skills": ["project management"], "soft_skills": ["detail-minded", "project management skills", "work under pressure"], "languages_combined": [{"language": "cantonese", "language_level": ["good command"]}, {"language": "english", "language_level": ["good command"]}, {"language": "mandarin", "language_level": ["good command"]}]}, "experience_required": {"duration": ["minimum of 5 years"], "field": ["development", "training"]}}, {"job_id": "100003009038988", "location_code": "hk", "company": "Talentus Group HK Limited", "job_title": "Senior / Regional HR Business Partner, Greater China", "description": "About the Company\u00a0\n\nOur client is\u00a0a retailer expanding its brand presence in Greater China.\u00a0To cope with\u00a0business needs,\u00a0management is looking for a Senior / Regional HR Business Partner\u00a0to\u00a0be based in Hong Kong and act as a key stakeholders within the Asia region business unit.\n\n\nAbout the Role\n\nReporting to the Managing Director of Asia, you will provide HR Advisory services related to Talent Acquisition, policies reviews, Employee Relations and general HR Administrative duties. You will build a strong relationship with business stakeholders and partner with other HR specialist around the globe to support the delivery of projects and initiatives that aligns with the business expansion strategies. Ad-hoc projects will be assigned as needed.\n\nYou will serve as a Brand Ambassador and your\u00a0mission\u00a0will be to drive the company growth for Asia through rolling out HR initiatives and acting as the HR first in-charge for Asia. Daily job duties will include budget planning, annual review, talent review exercise, and on/off-boarding.\n\nRequirements:\u00a0\n\nDegree holder with a proven track record with any sizeable retail\u00a0MNCs\n6\u00a0years relevant HR experience, ideally from a fast growing company\nExposure in multinational companies will be an advantage.\nGood business acumen and understanding towards\u00a0talents in Greater China region\nAbility to communicate and collaborate\u00a0with\u00a0multiple stakeholders\nExcellent verbal and written English, Mandarin and Cantonese (any other spoken language will be an advantage)\n\nInterested parties, please apply directly with your most updated resume, latest and expected salary package.\u00a0Referral programs are available.\u00a0\n\nNote: All information collected will be kept in strict confidence and will be used for recruitment purpose only.", "employment_types": ["Full Time"], "selling_points": ["Fast growing MNC", "Represent Asia HR function as 1st in-charge", "Fast track career development"], "locations": ["Not Specified"], "categories": ["Admin & HR", "Administration / Operation Manager", "Recruitment / Executive Search", "Training & Development"], "post_time": "2022-01-11T08:24:45Z", "salary": {"currency": null, "max": null, "min": null, "period": "monthly", "term": null}, "salary_visible": false, "title_keywords": ["hr"], "responsibilities": ["collaborate with", "reporting", "management", "budget planning", "policies", "hr", "review", "administrative duties", "ad-hoc projects"], "requirements": {"degrees": ["degree holder"], "majors": [], "languages": ["cantonese", "english", "mandarin"], "language_level": ["advantage", "excellent"], "hard_skills": ["acumen"], "soft_skills": ["business acumen"], "languages_combined": [{"language": "cantonese", "language_level": ["excellent"]}, {"language": "english", "language_level": ["advantage", "excellent"]}, {"language": "mandarin", "language_level": ["advantage", "excellent"]}]}, "experience_required": {"duration": ["6 years"], "field": ["hr"]}}, {"job_id": "100003009036065", "location_code": "hk", "company": "Aurabeat Technology Limited", "job_title": "Talent Acquisition & Development Specialist", "description": "To cope with our fast expansion, we are looking for suitable candidates to join our HR & Admin team.\u00a0\n\nResponsibilities\n\nTalent Acquisition & Development\n\nFormulate and implement recruitment strategies & initiatives to attract talents and to cope with rapid hiring demand for business global & regional expansion.\nResponsible for the whole recruitment process including job advertisement posting, sourcing, screening, arranging & conducting interviews, preparing hiring proposals and making offers\nWork proactively to develop close working relationships with different departments to identify the manpower and business needs & requirements\nExplore potential and evaluate the effectiveness of recruitment channels on oversea market\u00a0\nHR Business Partnering\n\nPerformance management and implement talent development programs\nSuggest measures for improving employee relations and retention\nAssist to draft, develop and implement HR policies and procedures in compliance\u00a0with Hong Kong Labor Ordinance\nPerform other ad-hoc projects and tasks as assigned\nRequirements\n\nUniversity degree in Human Resources Management or related discipline\u00a0\nMinimum 5 years\u2019 experience in HR Services & office management.\nPrior experience as a Talent Acquisition, or similar experience in an HR role.\nKnowledge of job posting sites and various interviewing methods\nKnowledge and experience of employment-related laws and regulations in overseas countries is an advantage\nIndependent, detail-minded, self-motivated, able to work in a fast-paced environment and a good team player\nAble to work under tight deadlines, dynamic/start up working environment and culture\nGood command of written and spoken English and Chinese\nProficient in Microsoft Office (Word, Excel and PowerPoint)\u00a0\nA candidate with more experience will be considered as Senior HR Officer.\nImmediate available is highly preferred\n\nWe offer 5-day work, attractive remuneration package to the successful candidate. Salary will be commensurate with qualifications and experience. Interested parties please send a detailed resume to our\u00a0Human Resources Department\u00a0by clicking the\u00a0Apply Now\u00a0button.\n\nWe are an equal opportunity employer. All information collected will be considered strictly confidential and will be used for recruitment purposes only.", "employment_types": ["Full Time", "Permanent"], "selling_points": ["Handle daily recruitment duties", "Mature, Responsible, Detailed Mind", "Proactive, Well-organized and Muti task"], "locations": ["Tsuen Wan Area"], "categories": ["Admin & HR", "Others", "Recruitment / Executive Search", "Training & Development"], "post_time": "2022-01-10T09:13:44Z", "salary": {"currency": null, "max": null, "min": null, "period": "monthly", "term": null}, "salary_visible": false, "title_keywords": ["specialist"], "responsibilities": ["management", "development programs", "job advertisement", "policies", "hr", "compliance", "procedures", "develop", "evaluate", "conducting interviews", "recruitment", "working relationships", "recruitment process", "ad-hoc projects"], "requirements": {"degrees": ["university degree"], "majors": [], "languages": ["english", "chinese"], "language_level": ["good command"], "hard_skills": ["excel", "microsoft office", "word", "powerpoint", "dynamic"], "soft_skills": ["detail-minded", "good team player", "self-motivated", "independent", "fast-paced environment", "dynamic"], "languages_combined": [{"language": "english", "language_level": ["good command"]}, {"language": "chinese", "language_level": ["good command"]}]}, "experience_required": {"duration": ["minimum 5 years"], "field": ["related", "hr", "management"]}}, {"job_id": "100003009035016", "location_code": "hk", "company": "Health Care & Co.", "job_title": "Head of HR and administration Department - URGENT Five Days work", "description": "Job Duties:-\n\n*Responsible for performing full spectrum of HR duties including staff planning, recruitment and selection, orientation, training and development program and coordinate with managers of other departments on their needs and requirements\n\n*Responsible for planning on compensation and benefits, performance appraisal arrangement, policies set up and implementation\n\n*Daily routine personnel matters such as maintaining appropriate and accurate personnel files, attendance record, leave record, payroll and MPF calculation etc.\n\n*Lead the team and improve the\u00a0office management and administrative work.\n\n*Applicant with less experiences will be considered as assistant supervisor of the HR and administration Department.\n\nJob Requirement:-\n\nUniversity graduate in Human Resources Management, Business Management or related disciplines\n5 years or more relevant HR and Administration experience, applicant with higher qualification will be considered as Assistant Manager.\nSound knowledge of Hong Kong and\u00a0PRC\u00a0Employment Ordinance.\nStrong communication, analytical and interpersonal skills\nGood command of both spoken and written English and Mandarin is a must\nProficiency in PC applications such as MS Word, Excel, PowerPoint and Chinese Word Processing is essential\n\n** 5 days OFF and bank holidays. **\n\nStaff benefit: Year end bonus, medical scheme and study sponsorship.\n\n\u00a0Interested parties, please send full resume and expected salary to us. (Attn: Ms.Queenie Hwang)", "employment_types": ["Full Time", "Permanent"], "selling_points": ["Support HR Team to ensure smooth operation", "Five-day work week", "Discretionary Bonus"], "locations": ["Kwai Hing"], "categories": ["Admin & HR", "HR Director / Manager", "Recruitment / Executive Search", "Training & Development"], "post_time": "2022-01-10T05:15:43Z", "salary": {"currency": null, "max": null, "min": null, "period": "monthly", "term": null}, "salary_visible": false, "title_keywords": ["hr"], "responsibilities": ["coordinate with", "recruitment", "hr duties", "planning"], "requirements": {"degrees": [], "majors": [], "languages": [], "language_level": [], "hard_skills": [], "soft_skills": [], "languages_combined": []}, "experience_required": {"duration": [], "field": []}}, {"job_id": "100003009028277", "location_code": "hk", "company": "Morgan McKinley", "job_title": "Assistant Training & Development Manager - Engineering Leader", "description": "Responsibilities\nact as the key contact and subject matter expert at group level on all training & development matters\ndesign and implement group training and development initiatives & projects\nidentify the training needs and develop relevant programmes accordingly\nlaunch e-training programmes to improve the digital capability of internal staff of all levels\nintroduce relevant training programme to reskill and upskill internal staff\nwork closely with other departments and business leaders to drive a learning culture\nprovide guidance and support to HR for launching training & development programs\nother ad-hoc projects as assigned\nRequirements\ndegree or above in Human Resource Management or related discipline\nminimum 5 years of relevant T&D experience\nexperience in identifying training needs & designing new training programmes\nexcellent facilitation, training, stakeholder management and project managing skills\nexperience of launching and implement Learning Management System (LMS) is preferrable\ncertified trainer on leadership programme or assessment tools has an advantage\nBenefits\n5 day work week\ncompetitive salary package\nend of year bonus\non the job training\ndynamic working culture\nmedical coverage\ndental insurance", "employment_types": ["Full Time", "Permanent"], "selling_points": ["Excellent salary package", "Dynamic working culture", "Stable working hours"], "locations": ["Not Specified"], "categories": ["Admin & HR", "Training & Development"], "post_time": "2022-01-07T01:56:42Z", "salary": {"currency": null, "max": null, "min": null, "period": "monthly", "term": null}, "salary_visible": false, "title_keywords": ["manager", "assistant"], "responsibilities": ["development programs", "hr", "subject matter expert", "design", "work closely with other departments", "develop", "contact", "ad-hoc projects", "provide guidance"], "requirements": {"degrees": ["degree or above"], "majors": [], "languages": [], "language_level": [], "hard_skills": [], "soft_skills": ["learning", "leadership"], "languages_combined": []}, "experience_required": {"duration": ["minimum 5 years"], "field": ["management", "training"]}}, {"job_id": "100003009032986", "location_code": "hk", "company": "Guardforce Ltd", "job_title": "Quality Assurance Manager", "description": "Responsibilities:\n\nFormulate and execute training strategies and plans that are aligned with business strategies and organizational objectives\nIdentify training and development needs and develop, design and deliver various training programs\nReview staff development plan for frontline operations to maintain or upgrade service quality\nMonitor and implement a set of quality and effective training program to frontline staff and different levels of staff\nReview training effectiveness by assessing employee performance and trainee's feedback\nEvaluate the training performance and conduct action plan for enhancement / improvement\nPerform risk assessment and inspection as needed\u00a0\u00a0\nHandle ad hoc assignments and projects as assigned by Management\n\nRequirements:\n\nDegree holder in related disciplines\nMinimum 5 years solid training and development experiences, preferably in security industries\nExperience in good training sense in term of course development, design and evaluation\nStrong organizational, communication (English & Chinese) and interpersonal skills\nProficient in MS office\nAbility to work in fast paced environment and able to multi-task and think creatively\nImmediately available is highly preferred\n\nJoin Us! We offer attractive remuneration packages to the right candidate.\n\nInterested parties please send your full resume stating your\u00a0present and expected salary & date of availability by clicking \"Apply Now\"or\u00a0\n\nFax: 2333-3481; or\nMail: HR Department, 2/F., Guardforce Centre, 3 Hok Yuen Street East, Hung Hom, Kowloon.\n\nPersonal data provided in your application will be kept in the strictest confidence. It will only be used for employment-related purposes by any entity within our Group. Applicants not notified within 1 month will be considered as unsuccessful. Unsuccessful application may be kept for another 3 months for new openings or consideration by another entity within our Group before properly shredded.\n\nSecurity Licence No. : 0092", "employment_types": ["Full Time", "Permanent"], "selling_points": [], "locations": ["Hung Hom"], "categories": ["Sales, CS & Business Devpt", "Business Development", "Admin & HR", "Training & Development"], "post_time": "2022-01-08T05:12:44Z", "salary": {"currency": null, "max": null, "min": null, "period": "monthly", "term": null}, "salary_visible": false, "title_keywords": ["manager"], "responsibilities": ["management", "operations", "review", "quality", "monitor", "design", "develop", "evaluate", "inspection", "maintain", "ad hoc assignments", "plan", "plans"], "requirements": {"degrees": ["degree holder"], "majors": ["related disciplines"], "languages": ["english", "chinese"], "language_level": [], "hard_skills": ["ms office"], "soft_skills": ["communication", "organizational", "interpersonal skills", "multi-task"], "languages_combined": [{"language": "english", "language_level": []}, {"language": "chinese", "language_level": []}]}, "experience_required": {"duration": ["minimum 5 years"], "field": ["development", "security", "training", "design"]}}, {"job_id": "100003009043973", "location_code": "hk", "company": "AIA International Limited", "job_title": "Relationship Manager \u5ba2\u6236\u7d93\u7406", "description": "\u4e3b\u8981\u5de5\u4f5c\uff1a\n\n\u8207\u5ba2\u6236\u5efa\u7acb\u826f\u597d\u9577\u9060\u95dc\u4fc2\n\u5efa\u8b70\u5408\u9069\u8ca1\u5bcc\u589e\u503c\u53ca\u4fdd\u969c\u65b9\u6848\n\u63d0\u4f9b\u512a\u8cea\u6eff\u610f\u7684\u5ba2\u6236\u670d\u52d9\n\u4e3b\u52d5\u7a4d\u6975, \u6b63\u9762\u4e0a\u9032:\n\n\u5165\u8077\u8981\u6c42:\n\u826f\u597d\u6e9d\u901a\u6280\u5de7\n\u6709\u8cac\u4efb\u5fc3\n\u6b61\u8fce\u975e\u91d1\u878d\u670d\u52d9\u884c\u696d\u76f8\u95dc\u4eba\u58eb\n\u798f\u5229\u5f85\u9047\uff1a\n\u8c50\u539a\u4f63\u91d1\u3001\u6bcf\u6708\u6d25\u8cbc\u3001\u5e74\u7d42\u734e\u91d1\u53ca\u82b1\u7d05\n\u6301\u4e45\u907f\u52d5\u6536\u5165\n\u6d77\u5916\u6703\u8b70\u3001\u65c5\u904a\u734e\u8cde\n\u5b8c\u5584\u57f9\u8a13\n\u5feb\u901f\u664b\u5347\u6a5f\u6703\uff08Fast Track Program)\n\u6210\u70ba\u884c\u5167\u9802\u5c16\u7684\u767e\u842c\u5713\u684c\uff08MDRT\uff09\u6703\u54e1\n\u5efa\u7acb\u5718\u968a\u3001\u767c\u5c55\u7a69\u5065\u4e8b\u696d\n\u00a0\u696d\u52d9\u7279\u6027:\n\u96c6\u5275\u696d\uff08\u81ea\u4e3b\u6536\u5165\u7121\u4e0a\u9650\uff09\uff0b\u53d7\u85aa\uff08\u57f9\u8a13\u652f\u63f4\u4f4e\u6210\u672c\uff09\u7684\u512a\u9ede\n\u00a0\u4e00\u4efd\u53ef\u8b93\u4f60\u627e\u5230\u5922\u60f3\uff0c\u5be6\u73fe\u7406\u60f3\u7684\u4e8b\u696d\n\u7531\u903e\u5341\u5e74\u7d93\u9a57\u5e2b\u5085\u4e00\u5c0d\u4e00\u57f9\u8a13\u7763\u5c0e\n\u5b8c\u5584\u65b0\u4eba\u7cfb\u7d71\u57f9\u8a13\uff0c\u7ba1\u7406\uff0c\u652f\u63f4\u914d\u5957\n\u771f\u6b63\u7531\u96f6\u958b\u59cb\uff0c\u6559\u4f60\u7cbe\u901a\u672c\u5730\u5dff\u5834\uff0c\u958b\u767c\u5167\u5730\u5dff\u5834\n\u00a0\n\n\n\n\u770b\u770b\u4ed6\u5011\u7684\u6545\u4e8b (Copy Link)\n\n\u9ad8\u6d88\u8cbb\u54c1\u724c\u96f6\u552e\u696dSales. \u70ba\u904e\u7bc0\u53ef\u4ee5\u591a\u966a\u4f34\u5bb6\u4eba, \u6191\u92b7\u552e\u7d93\u9a57\u6210\u529f\u8f49\u63db\u8dd1\u9053\nhttps://www.youtube.com/watch?v=-VBap7uHbqE\n\u7a7a\u59d0\u62d2\u7d55\u5929\u5929\u91cd\u8986\u505a\u6a5f\u68b0\u4eba, \u83ef\u9e97\u8f49\u8eab\u5f8c\u627e\u5230\u524d\u6240\u672a\u6709\u7684\u6eff\u8db3\u611f\u00a0\nhttps://youtu.be/pK4b0KryyG0\n\u9280\u9280\u884c\u5e2b\u5f92\u6253\u5de5\u8b8a\u5275\u696d\uff0c\u7a81\u7834\u6536\u5165\u4e0a\u9650\nhttps://www.youtube.com/watch?v=k5tlLWmXa4g\n\u9280\u884c\u7cbe\u82f1\u5c07\u7d93\u9a57\u8f49\u5316\u6210\u512a\u52e2\uff0c\u628a\u63e1\u6642\u6a5f,\u501f\u53cb\u90a6\u5e73\u53f0\u5feb\u901f\u767c\u5c55\u9f90\u5927\u5718\u968ahttps://www.youtube.com/watch?v=n_l9lzrHq0Y\n\n\n\n\u7533\u8acb\u6216\u806f\u7d61\u65b9\u6cd5\uff1a\n\u6309\u300cApply Now\u300d\u4e26\u9644\u4e0aCV\uff0c\u4ea6\u53ef\u81f4\u96fb 37276302 \u8207\u4e3b\u7ba1\u7d04\u898b\u8a73\u8ac7\uff0c\u5f35\u5c0f\u59d0\u6d3d", "employment_types": ["Full Time", "Part Time", "Permanent", "Contract"], "selling_points": ["\u96c6 \u5275\u696d\uff08\u81ea\u4e3b\u6536\u5165\u7121\u4e0a\u9650\uff09\uff0b \u53d7\u85aa\uff08\u57f9\u8a13\u652f\u63f4\u4f4e\u6210\u672c\uff09\u7684\u512a\u9ede", "\u5275\u9020\u6301\u4e45\u907f\u52d5\u6536\u5165\uff0b \u5feb\u901f\u664b\u5347\u6a5f\u6703\uff08Fast Track Program)", "\u903e\u5341\u5e74\u7d93\u9a57MDRT Life Member \u5e2b\u5085\u4e00\u5c0d\u4e00\u7763\u5c0e \uff0b \u884c\u696d\u9802\u5c16\u5718\u968a\u7cfb\u7d71\u5316\u57f9\u8a13"], "locations": ["Eastern Area"], "categories": ["Education", "Teacher", "Admin & HR", "Training & Development", "Marketing / Public Relations", "Marketing - Marketing Communication"], "post_time": "2022-01-13T02:39:06Z", "salary": {"currency": null, "max": null, "min": null, "period": "monthly", "term": null}, "salary_visible": false, "title_keywords": ["relationship manager"], "responsibilities": [], "requirements": {"degrees": [], "majors": [], "languages": [], "language_level": [], "hard_skills": [], "soft_skills": [], "languages_combined": []}, "experience_required": {"duration": [], "field": []}}, {"job_id": "100003009035279", "location_code": "hk", "company": "Cornerstone Robotics Limited", "job_title": "HR Business Partner", "description": "Responsibilities\n\nThis position is responsible for executing the talent strategy, providing a consistent experience to managers and employees and supporting and executing the engagement strategy for the market. The HR Business Partner provides HR partnership to managers focusing on the work environment, employee relations, employee retention and business processes by executing the business unit HR strategy.\n\nHR Services\n\nContribute to the creation and maintenance of consistent policies used within HR, communicate changes and ensure policies are consistently applied by organization\nBe a champion of change, share best practices and support Business Leaders and Managers in adopting new practices and initiatives, including new HR systems/processes.\nEnsures legal compliance by monitoring and implementing applicable statutory requirements, conducting investigations, maintaining records.\n\nBusiness Partnering\n\nBe the contact point for Business Unit Leaders regarding the implementation of people strategy.\nFacilitate business leaders to identify, advocate and enable decisions & actions to drive effectiveness and business performance, including but not limited to people-related actions, e.g. people engagement & retention, performance management, change management, talent development.\nUnderstand the purpose and value of the program, bring ideas and initiatives to drive alignment and maximise the benefit for people and the business.\n\nQualifications\n\n4+ years experience in Human Resources with solid understanding in in various HR fields.\nStrong business acumen, presentation & facilitation, consulting, relationship-building, influence and project management skills.\nDemonstrated ability to build relationships and influence different groups.\nStrong situational assessment and objective evaluation skills.", "employment_types": ["Full Time", "Permanent"], "selling_points": ["Business Partnering role, fast-growing startup", "4+ years with solid understanding in HR modules", "HR projects & strategic planning"], "locations": ["Shatin Area"], "categories": ["Admin & HR", "Compensation & Benefits", "Recruitment / Executive Search", "Training & Development"], "post_time": "2022-01-10T06:38:24Z", "salary": {"currency": null, "max": null, "min": null, "period": "monthly", "term": null}, "salary_visible": false, "title_keywords": ["hr"], "responsibilities": ["management", "change management", "ideas", "maintenance", "maintaining", "consulting", "policies", "hr", "systems", "compliance", "monitoring", "implementation", "statutory requirements", "project management", "executing", "contact", "evaluation"], "requirements": {"degrees": [], "majors": [], "languages": [], "language_level": [], "hard_skills": ["project management", "maintenance", "acumen"], "soft_skills": ["business acumen", "project management skills", "presentation", "responsible"], "languages_combined": []}, "experience_required": {"duration": ["4+ years"], "field": ["hr", "human resources"]}}, {"job_id": "100003009028740", "location_code": "hk", "company": "Securitas Security Services (Hong Kong) Limited", "job_title": "Training Specialist", "description": "To deliver professional training to the whole of the Physical Security and Reception Team, including all levels of seniority\nConduct training programmes by classroom, on-site, systems-related or e-learning operational training\nEnsure trainees obtain adequate skills and knowledge to provide quality services with no training lapse\nEnsure that appropriate coaching is provided to all new hires to complete all the mandatory trainings\nTo train the trainers appointed by operations parties\nTo evaluate and review the training programmes to ensure training requirements and effectiveness are met\nPro-actively work with the Management and the Operational Excellence Group (OEG) to design and develop training programme according to compliance with the enterprise policies, processes and procedure\nBuild highly trusted relationships with staff ensuring that the company is proactively engaging, listening and acting on their feedback\nTo complete special projects and other requirements assigned by supervisor\n\nJob Requirement\n\nBachelor of human resources, Security Management, Training and Development or related discipline\nMinimum 5 years of solid working experience in staff training\nProven ability to influence key business partners\nKnowledge in the security operations would be an advantage\nGood command of written and spoken English and Chinese (including Mandarin)\nAdvanced computer skills and proficiency\nGood presentation& communication skills\nStrong planning, organizing and analytical skills\nAbility to work with minimal supervision\nOccasional travel is required after COVID-19 issues", "employment_types": ["Full Time"], "selling_points": ["Design, develop and conduct training programmes", "Maintain and update all training materials", "Conduct assessment on the proficiency of trainees"], "locations": ["Tai Koo"], "categories": ["Admin & HR", "Training & Development", "Others", "Security / Safety Control"], "post_time": "2022-01-07T03:03:22Z", "salary": {"currency": null, "max": null, "min": null, "period": "monthly", "term": null}, "salary_visible": false, "title_keywords": ["specialist"], "responsibilities": ["management", "operations", "policies", "review", "systems", "quality", "design and develop", "compliance", "evaluate", "communication", "planning"], "requirements": {"degrees": ["bachelor"], "majors": [], "languages": ["english", "chinese", "mandarin"], "language_level": ["good command"], "hard_skills": ["computer skills", "no", "security management", "analytical skills"], "soft_skills": ["communication skills", "advanced", "analytical skills", "learning", "presentation"], "languages_combined": [{"language": "english", "language_level": ["good command"]}, {"language": "chinese", "language_level": ["good command"]}, {"language": "mandarin", "language_level": ["good command"]}]}, "experience_required": {"duration": ["minimum 5 years"], "field": ["training"]}}, {"job_id": "100003009028465", "location_code": "hk", "company": "Sa Sa Cosmetic Company Limited", "job_title": "Senior Training Officer / Training Officer", "description": "Responsibilities:\n\nResponsible for handling full spectrum of Training & Development functions.\nIdentify\u00a0training needs and develop training for frontline staff to enhance the service standard\nMonitor and evaluate training effectiveness through effective field coaching and regular shop visits\nTo enhance staffs\u2019 technical competences, work knowledge and soft skills development\nAssist in talent review and staff development plan\nTrain the trainers to increase the operations productivity\nManage training budgets and monitor the expenses throughout budget reviews and forecasts in a regular basis\nTraining coordination with all Brands and HQ training team\nSupport any ad hoc projects as assigned not limited to organize mystery shopper program, develop, and organize staff relations / team building activities\n\nRequirements:\n\nDegree holder in related discipline\nMinimum 6 years' experiences in beauty retail training are highly preferred\nWith solid operations experience is an advantage\nProven track record in developing and conducting training programs for frontline staff\nExcellent presentation and interpersonal skills, able to communicate well with different levels of employees\nGood project management skills with high level of accuracy, reliable and able to manage multi-tasks in a timely manner\nStrong execution & problem-solving skills, pleasant, mature, and positive with a \"can-do\" mindset\nGood command in English / Cantonese/ Mandarin\nProficient in MS Office and Chinese Word Processing\nCandidates with less experiences will be considered as Senior Training Officer\n\nTo learn more about our company, please visit our website\u00a0and\u00a0http://www.cdfg.com.cn/\n\nWe offer 5-day work week, competitive salary and fringe benefits to the right candidate. Interested parties please apply with full resume with current and expected salary\u00a0by clicking \"Apply Now\".\n\nAll information provided by applicants will be treated in strict confidence and used for recruitment purpose only. All personal data of unsuccessful applicants will be retained for 6 months for future recruitment purpose and will then be destroyed.", "employment_types": ["Full Time", "Permanent"], "selling_points": ["Product training (skincare, fragrance etc.)", "Conduct classroom training and field coaching", "Develop product related education materials"], "locations": ["Siu Sai Wan"], "categories": ["Beauty Care / Health", "Others", "Admin & HR", "Training & Development"], "post_time": "2022-01-07T02:22:14Z", "salary": {"currency": null, "max": null, "min": null, "period": null, "term": null}, "salary_visible": false, "title_keywords": ["officer"], "responsibilities": ["budgets", "service standard", "operations", "review", "monitor", "expenses", "budget", "develop", "evaluate", "coordination with", "ad hoc projects", "plan"], "requirements": {"degrees": ["degree holder"], "majors": [], "languages": ["cantonese", "english", "chinese", "mandarin"], "language_level": ["good command", "proficient"], "hard_skills": ["problem-solving skills", "project management", "chinese word processing", "ms office"], "soft_skills": ["multi-tasks", "project management skills", "timely", "mature", "pleasant", "interpersonal skills", "can-do", "problem-solving skills", "reliable", "presentation", "positive"], "languages_combined": [{"language": "cantonese", "language_level": ["good command"]}, {"language": "english", "language_level": ["good command"]}, {"language": "chinese", "language_level": ["proficient"]}, {"language": "mandarin", "language_level": ["good command"]}]}, "experience_required": {"duration": ["minimum 6 years"], "field": ["training", "retail", "beauty"]}}, {"job_id": "100003009030778", "location_code": "hk", "company": "Michael Page", "job_title": "Senior Learning and Development Manager", "description": "This is a newly created position due to the increasing need for further training and development opportunities for our client's senior level staff.\n\nClient Details\n\nOur client is a listed company with over 4000 staff in Hong Kong and China.\n\nDescription\n\nReporting to the Head of L&D, you will take an active role in the talent review process and partner with the HRBP team and business leaders to identify the talent and skill gaps in the organisation. Once the key areas of development are identified, you will lead the team in the design and development of the L&D and talent development programs with specific focus in management capability. Our client is looking for someone with strength in the design and development of e-learning programs. Those who have knowledge and experience using digital platforms and have connections with suppliers who can provide such service would be highly sought after. Aside from management capabilities, the company has their regular L&D calendar , and would invite their key leaders and subject matter expert to share their experience, business development plans, business updates and any other subjects the management team feels crucial to strengthen within the company. Experience using SAP Success Factors would be a plus.\n\nProfile\n\nYou will be degree qualified with a minimum of 12-15 years of L&D experience gained from sizable corporations, preferably headquartered in Hong Kong with regional coverage, or multinational companies where you actively took part in the design and development of the programs. You will have experience in the design, development and delivery of the management capability programs, those with in-depth experience using digital/multimedia will have an advantage. A good level of command in English and Chinese is required.\n\nJob Offer\n\nThis is a newly created position with a listed company in Hong Kong and multiple locations in China.\n\nTo apply online please click the 'Apply' button below. For a confidential discussion about this role please contact Grace Lee on +852 2848 4721", "employment_types": ["Full Time", "Permanent"], "selling_points": ["Newly created role", "E-Learning , Digital platforms", "Management capabilities & talent development"], "locations": ["Not Specified"], "categories": ["Admin & HR", "Training & Development"], "post_time": "2022-01-07T08:18:50Z", "salary": {"currency": null, "max": null, "min": null, "period": "monthly", "term": null}, "salary_visible": false, "title_keywords": ["manager"], "responsibilities": ["reporting", "management", "management team", "development programs", "review", "subject matter expert", "design", "contact", "plans"], "requirements": {"degrees": ["degree"], "majors": ["design"], "languages": ["english", "chinese"], "language_level": ["good"], "hard_skills": ["focus", "multimedia", "sap", "plus"], "soft_skills": ["focus", "active", "organisation", "learning"], "languages_combined": [{"language": "english", "language_level": ["good"]}, {"language": "chinese", "language_level": ["good"]}]}, "experience_required": {"duration": ["minimum of 12-15 years"], "field": ["management", "development", "business development", "design", "business", "digital", "team"]}}, {"job_id": "100003009028921", "location_code": "hk", "company": "Tao Heung Group Limited", "job_title": "Training Officer", "description": "Working in Tao Heung Group, besides remuneration and benefits, you can also\n1) Get a chance to work in one of the largest F&B groups,\n2) Get cross-border exposure, and\n3) Get some challenging yet fulfilling and rewarding experience.\n\nPlease join us as:\n\nTraining Officer\n\nJob Description:\n\nAssist in training programs for all front-line staff levels to enhance and polish customer services skill, product knowledge, and drive the Company culture;\nCoordinate with different parties for training implementation;\nMaintain and update training materials and record, prepare training statistics in regular basis;\nProvide logistic support and participate in other projects as required.\n\nRequirement:\n\nDegree in Human Resources Management, Training or related discipline;\n2 years solid experience in training and development, preferably in F&B industry;\nExperience in Mystery Shopper and QF programs would be an advantage;\nHigh attention to details, good communication and interpersonal skills;\nIndependent, fast-paced, multi-tasking, result-oriented and self-motivated.\n\nInterested parties please apply with detailed resume, current salary, expected salary and contact numbers to the Human Resources Manager, Tao Heung Group Ltd. by clicking \"APPLY NOW\"\n\nApplication letters collected will be used for recruitment purpose only.", "employment_types": ["Full Time"], "selling_points": ["Food & Beverage", "Training & Development", "2 years solid experience"], "locations": ["Tai Po Area"], "categories": ["Hospitality / F & B", "Food & Beverage", "Admin & HR", "HR Supporting Staff", "Training & Development"], "post_time": "2022-01-07T03:35:44Z", "salary": {"currency": null, "max": null, "min": null, "period": "monthly", "term": null}, "salary_visible": false, "title_keywords": ["officer"], "responsibilities": [], "requirements": {"degrees": [], "majors": [], "languages": [], "language_level": [], "hard_skills": [], "soft_skills": [], "languages_combined": []}, "experience_required": {"duration": [], "field": []}}]