[{"job_id": "100003009053067", "location_code": "hk", "company": "Orient Overseas Container Line Ltd (OOCL)", "job_title": "Senior Technical Analyst / Technical Analyst - Networking", "description": "Job Duties:\n\nTo provide technical support on WAN/LAN environment with specific focus on Metro-Ethernet network,\u00a0core routers, network switches, firewall appliances and load balancers;\nTo liaise with users and vendors for requirement study, implementation and on-going support activities;\nTo participate in technical specification development and proposal evaluation for new projects / enhancements;\nTo prepare test plan and conduct acceptance test;\nTo install security patches and upgrade on various hardware platforms and software applications;\nTo perform administration tasks and backup job related to various network and server platforms;\nTo update technical documents and prepare operation manual\n\nJob Requirements:\n\nHigher Diploma or above in IT related discipline\nAt least have 4 years\u2019 experience in IT field\nAt least 2 years of experience in network infrastructure support/ administration and configuration in the WAN/LAN environment\nSound knowledge in dynamic routing adopted in WAN/LAN environment\nHands on experience in firewall products\nKnowledge in Network monitoring and management tools is preferred\nPossession of certifications of CCNA or similar qualification is preferred\nIndependent, proactive and able to work under pressure\nGood communication skills\nProficient in both spoken and written English and Cantonese.\n\n\nFor more job opportunity, please visit our website: www.clts.com\n\nThe personal information collected is strictly for recruitment purpose only.", "employment_types": ["Full Time", "Permanent"], "selling_points": ["Software-Defined Network, Network Security", "Global Network Infrastructure projects", "5-day work, Double Pay, Discretionary Bonus"], "locations": ["Shatin Area"], "categories": ["Information Technology (IT)", "Application Specialist - Network", "Security", "Network & System"], "post_time": "2022-01-17T05:33:52Z", "salary": {"currency": null, "max": null, "min": null, "period": "monthly", "term": null}, "salary_visible": false, "title_keywords": ["analyst"], "responsibilities": ["software", "technical support", "implementation", "hardware", "plan", "evaluation", "liaise with", "administration"], "requirements": {"degrees": ["higher diploma or above"], "majors": ["it"], "languages": ["cantonese", "english"], "language_level": ["proficient"], "hard_skills": ["infrastructure support", "ccna", "dynamic", "firewall", "wan"], "soft_skills": ["communication skills", "independent", "hands on", "dynamic", "proactive", "work under pressure"], "languages_combined": [{"language": "cantonese", "language_level": ["proficient"]}, {"language": "english", "language_level": ["proficient"]}]}, "experience_required": {"duration": ["4 years", "at least 2 years"], "field": ["infrastructure", "it", "administration"]}}, {"job_id": "100003009053049", "location_code": "hk", "company": "JFE Consulting Limited", "job_title": "Network System Analyst", "description": "\u00a0Accelerate your career\n\nExperience the latest technologies in global network infrastructure, software-defined network, hybrid cloud and cyber security\nGain exposure in running a global data, voice network and hybrid multi-cloud network infrastructure\u00a0\n\nYour role\n\nTechnology driver on Software-Defined Network, Hybrid Cloud, Network Security and Unified Communications\nArchitectural design and Implementation on Global Network Infrastructure projects\nProvide second tier support on global network, IP telephony and Contact Centre for global offices\nResearch and evaluate new technologies on networking, cloud and cyber security\u00a0\n\nWho we are looking for\n\nUniversity graduate in Computer Science, Computer Engineering or related discipline\nMinimum 3 years\u2019 working experience in Software-Defined Network, Next-Generation firewall, Hybrid Cloud, Unified Communication or Cyber Security\nSelf-motivated, analytical, with curious mindset\nEager to learn in a fast-paced and dynamic environment\nHolder of CCNA / CCNP is preferable\nDemonstrate a good learning track record with excellent interpersonal and communication skills\nGood command of spoken and written English, Mandarin is an advantage\nHigh quality candidate with less experience will also be considered for a junior position\nInterested parties please send your application letter with detailed resume and expected salary by clicking \"Apply Now\" .\n\n(Data collected will be used for recruitment purpose only.)", "employment_types": ["Full Time", "Permanent"], "selling_points": ["Network System Analyst", "Experienced in supporting network devices", "Attractive salary"], "locations": ["Quarry Bay"], "categories": ["Information Technology (IT)", "Application Specialist - Network", "Network & System", "Others"], "post_time": "2022-01-17T05:24:24Z", "salary": {"currency": null, "max": null, "min": null, "period": "monthly", "term": null}, "salary_visible": false, "title_keywords": ["system analyst"], "responsibilities": ["network infrastructure", "software", "data", "cyber security", "quality", "implementation", "design", "evaluate", "communication", "contact"], "requirements": {"degrees": ["university graduate"], "majors": ["computer engineering", "computer science"], "languages": ["english", "mandarin"], "language_level": ["advantage", "good command"], "hard_skills": ["cyber security", "ccnp", "ccna", "ip", "unified communication", "dynamic", "firewall"], "soft_skills": ["communication skills", "self-motivated", "dynamic environment", "communication", "eager to learn", "learning", "interpersonal"], "languages_combined": [{"language": "english", "language_level": ["advantage", "good command"]}, {"language": "mandarin", "language_level": ["advantage", "good command"]}]}, "experience_required": {"duration": ["minimum 3 years"], "field": ["infrastructure", "security"]}}, {"job_id": "100003009053377", "location_code": "hk", "company": "ELM Computer Technologies Ltd", "job_title": "Senior System Engineer", "description": "Our client, one of the leading IT companies, is looking for high calibres to join their winning team:-\n\nResponsiblities:\n\n\n\u00a0\u00a0Provide network support and perform troubleshoot to resolve various WAN/LAN connectivity issues.\nAssist various departments to maintain network security and configure remote routers and firewalls and provide engineering support.\nAnalyze and recommend solutions, upgrades services to streamline process and recommend improvements.\nMaintain hardware and software for network perform troubleshoot and assist in installation and upgrade workstations and Servers.\nInstall and maintain data and voice circuits through routers, switches, and Wide Area Network devices.\n\nRequirements:\n\n\nA degree or above in computer science or equivalent;\nAt least 6 years of post-qualification IT experience\n\u00a0At least 4 years of functional/specialty experience in design and/or implementation of network infrastructure(s);\nExperience in supporting network devices from different vendors: Routers, Switches, Multi-layer Switches, Firewalls, Local Server Load Balancers, IPSec VPN, SSL VPN, IPS/IDS, Web Application Firewall etc.;\nFamiliar with network configurations and changes, spanning-tree, dynamic routing protocols, VLANs, DHCP, NAT, ACL, QoS, Metro Network etc.", "employment_types": ["Contract"], "selling_points": ["With 5 years of working experience", "Solid experience in Unix/Linux and VM environment", "Knowledge/experience in cloud products"], "locations": ["Shatin Area"], "categories": ["Information Technology (IT)", "IT Project Management / Team Lead", "Application Specialist - Network", "Network & System"], "post_time": "2022-01-17T06:53:24Z", "salary": {"currency": null, "max": null, "min": null, "period": "monthly", "term": null}, "salary_visible": false, "title_keywords": ["senior system engineer"], "responsibilities": ["maintain network", "installation", "software", "upgrades", "hardware", "maintain", "troubleshoot", "maintain data"], "requirements": {"degrees": ["degree or above"], "majors": ["computer science"], "languages": [], "language_level": [], "hard_skills": ["server", "dynamic", "vpn", "web application firewall"], "soft_skills": ["dynamic"], "languages_combined": []}, "experience_required": {"duration": ["at least 6 years", "at least 4 years"], "field": ["post-qualification", "design", "it experience"]}}, {"job_id": "100003009051043", "location_code": "hk", "company": "The Wharf Group", "job_title": "Network Engineer", "description": "Founded in 1990, ELM Computer Technologies Limited (ELM) has been providing state-of-the-art IT solutions and professional services to our clients for thirty (30) years. The wide area of expertise in IT that ELM possesses under its belt has enabled the company to offer services on the lines of Multi-cloud Management, DevOps and Microservices Management, Business Analytics, Application Performance Management, Access and Identity Management, Enterprise Facilities and Asset Management, IT Services Management, Data Protection, and Enterprise Mobility Management.\n\nWith modern technologies such as cloud computing, business analytics, IoT, mobility, blockchain coming to mainstream prominence, constant adaption and innovation to cope with the evolving market has become a mandate that will continue to shape markets worldwide for the near foreseeable future. ELM under its strong technical capability will continue growing with its team members and clients together in the new digital world.\n\nResponsibilities:\u00a0\n\nPerform evaluation, installation, configuration, administration and troubleshooting of resources including OS, hardware & software\nInvolve in infrastructure planning and establishing security best practices\nConducting system/user acceptance test\nPrepare technical documentation & User Manual\nProvide 2nd or 3rd Tier support\nCapable to work during non office hour\u00a0\n\nRequirements:\n\nUniversity holder in Computer Science, Information Systems or related disciples\nWith 5 years of working experience\nSolid experience in Unix/Linux and VM environment\nKnowledge in shell script programming\nKnowledge/experience in cloud products (VMware products/Openshift) & IBM software products\nUnderstanding of networking concepts: TCP/IP, LAN/WAN, DHCP, DNS, Routing, Switching/Firewall\nExperience in infrastructure design is an advantage\nExcellent command in spoken and written English and Chinese\u00a0\n\nWe offer a comprehensive package to the right candidates. Please send your resume (IN MS WORDFORMAT) with contact phone number and EXPECTED SALARY (MUST) to Human Resources Department, 16/F, Topsail Plaza, 11 On Sum Street, Shatin, Hong Kong or email us. For more information, please visit our web site www.elm.com.hk\n\nAll information provided by applicants will be treated in strict confidence and will only be used for recruitment related purposes. All personal data supplied will be destroyed within six months after the selection process.", "employment_types": ["Full Time", "Permanent"], "selling_points": [], "locations": ["Tsim Sha Tsui"], "categories": ["Information Technology (IT)", "Application Specialist - Network", "Network & System", "Technical Writing"], "post_time": "2022-01-15T01:26:08Z", "salary": {"currency": null, "max": null, "min": null, "period": null, "term": null}, "salary_visible": false, "title_keywords": ["engineer"], "responsibilities": ["installation", "software", "configuration", "infrastructure", "troubleshooting", "hardware", "planning", "evaluation", "documentation", "administration"], "requirements": {"degrees": [], "majors": [], "languages": ["english", "chinese"], "language_level": ["excellent"], "hard_skills": ["linux", "vmware", "dns", "tcp", "ip", "programming", "firewall", "wan"], "soft_skills": [], "languages_combined": [{"language": "english", "language_level": ["excellent"]}, {"language": "chinese", "language_level": ["excellent"]}]}, "experience_required": {"duration": ["5 years"], "field": ["infrastructure", "design"]}}, {"job_id": "100003009054500", "location_code": "hk", "company": "Linkers International Limited", "job_title": "Network Engineer (inhouse, perm role, 5 days work) 25k-32k", "description": "THE JOB\n\nManage and configure WAN, LAN, Firewall, IPS, Application Firewall, and Load Balancer\nWork with development teams on systems design and implementation\nPerform daily operation, network health check and monitoring\u2002\u2002\u2002\u2002\u2002\nTo assist in troubleshooting networking issues and incidents\nMaintain up to date systems documentation\n\nTHE PERSON\n\nDiploma / Degree\u00a0 holder in Information Technology, Information System, Computer\u00a0 \u00a0\n2 years relevant experience in networking implementation and maintenance supports\nCisco CCNA/ CCNP certified is preferred\u00a0\nSolid experience in handling networking or security products\nGood troubleshooting skills\nGood communication & problem-solving skills\nSelf-motivated, well organized and able to work independently\n\nIf you're interested in this role, please click the Apply button above or via Linkers website at https://jobs.linkerscareers.com/ with your CV.\n\nIf you would like to have a further discussion about this role, please contact us at +852 2391 2813.\n\nPersonal data collected will be used for recruitment purposes only.", "employment_types": ["Full Time", "Permanent"], "selling_points": ["Perm role at sizeble IT company, 25k-32k + bonus", "No shift / on call duty required, Mon-Fri 9am-6pm", "Up to 1 year exp in networking support"], "locations": ["Hung Hom"], "categories": ["Information Technology (IT)", "Application Specialist - Network", "Network & System"], "post_time": "2022-01-17T09:48:22Z", "salary": {"currency": "HKD", "max": 34999, "min": 25000, "period": "monthly", "term": null}, "salary_visible": true, "title_keywords": ["engineer"], "responsibilities": ["systems", "daily operation", "teams", "implementation", "design", "monitoring", "troubleshooting", "maintain", "documentation"], "requirements": {"degrees": ["diploma", "degree"], "majors": ["information technology"], "languages": [], "language_level": [], "hard_skills": ["maintenance", "ccnp", "ccna", "information system", "problem-solving skills"], "soft_skills": ["self-motivated", "work independently", "interested in", "well organized", "troubleshooting", "communication", "problem-solving skills"], "languages_combined": []}, "experience_required": {"duration": ["2 years"], "field": ["relevant experience", "security", "maintenance"]}}, {"job_id": "100003009054241", "location_code": "hk", "company": "", "job_title": "IT Infrastructure Analyst", "description": "IT Infrastructure Analyst is responsible for national wide IT infrastructure support, including management of WAN, LAN & telecom in existing site; infrastructure plan, design and implementation for new site.\n\nBe the key role to lead the IT related tasks in local infra focus projects\n\nThe Job\n\nProvide the first level support on Greater China IT infrastructure including network and telecom\nCoordinate with Regional IT, management and service provider to roll out various infrastructure projects\nConfigure network and telecom equipment as need, apply necessary IT securities policy in the equipments\nHandle break/fix issues as required on network and telecom equipment.\nPerformance monitor for\u00a0 network and telecom system\nMaintain and report on current network and telecom system.\nSubmit Request for change requests to the Change Management Board as required for additions or changes made to the network\nCreate and maintain network and process documentation covering backups, patching, hardware, software or other items as deemed necessary by their supervisor.\nPlan, organize, oversee, and perform optimizations of the network and telecom environment.\nPerform after hour maintenance and emergency on call work as needed\nAct as the backup person for other infra support functions, such as Email, Storage, Backup, AD management\nPerform and monitor the backup processes for server and data storage devices at the various Data Centers and Server rooms.\nManage and control the service of external IT service vendor\u00a0\u00a0\n\nThe requirement\n\nMinimum of 5 years working in a large global organisation using in-sourced and out-sourced IT services\nHands-on experience of developing and implementing best practice service management processes in a fast-moving organisation\nPerformance-focused and able to motivate teams that demand and achieve service excellence\nCommercial focus, pragmatism and sound negotiating skills\nClear communicator with excellent interpersonal skills, able to build effective relationships with internal and external partners / service providers\nAble to calmly take ownership of the identification and resolution of team, technical or commercial service management issues and to resolve problems quickly and effectively\nA specialist knowledge of IT Service Management Best Practice (ITIL)\nExperience of working in a Logistics Organisation in an IT Management Capacity\nCan demonstrate having championed and promoted service improvements\nCan illustrate how they have improved quality and customer satisfaction with IT services\nExperience of the process to coordinate, monitor and control system transitions from development to live operation maintaining service delivery quality and minimise disruption\n\nWe offer attractive remuneration packages to the right candidates. Interested parties, please send us an email to obtain an application form or please contact us at (852) 2942 9401 for company details.", "employment_types": ["Full Time", "Permanent"], "selling_points": ["5 years or above in-house IT support", "Software/Hardware/Networking", "Good communication"], "locations": ["Kowloon Bay"], "categories": ["Information Technology (IT)", "Hardware", "Support", "Application Specialist - Network"], "post_time": "2022-01-17T08:54:57Z", "salary": {"currency": null, "max": null, "min": null, "period": null, "term": null}, "salary_visible": false, "title_keywords": ["analyst"], "responsibilities": ["maintain network", "management", "control", "change management", "it infrastructure", "software", "maintenance", "data", "it service", "infrastructure", "monitor", "coordinate with", "hardware", "maintain", "plan", "backups", "documentation", "report"], "requirements": {"degrees": [], "majors": [], "languages": [], "language_level": [], "hard_skills": ["itil", "focus"], "soft_skills": ["focused", "clear", "hands-on", "interpersonal skills", "organisation", "focus", "communicator"], "languages_combined": []}, "experience_required": {"duration": [], "field": ["management", "development", "developing", "it", "logistics", "operation"]}}, {"job_id": "100003009052633", "location_code": "hk", "company": "\u4fe1\u9280(\u9999\u6e2f)\u6295\u8cc7\u6709\u9650\u516c\u53f8", "job_title": "I.T Network Manager", "description": "Report directly to the Regional Director of IT, APAC, the job holder will be responsible to provide technical support and maintain IT Infrastructure in good condition.\n\n\u00a0Responsibilities:\n\nNetwork support & trouble shooting includes structure cabling, network device and servers.\u00a0\nDesktop support & trouble shooting includes software installation, configuration and setup.\nProvide support & advices in daily system administration and maintain the good condition of IT infrastructure includes WAN, LAN, Server, and Desktop.\nSystem administration on operating system level such as maintenance of user authorization, system configuration, version upgrade, system patching, server / client security and regular system backup and maintenance.\nPerform periodic system performance monitoring includes capacity utilization, system log, software update and preventive maintenance to maintain at 99.99% system availability.\nFollow the standard procedure and to ensure the compliance of corporate standard are maintained at all time.\nMaintain system documentation, testing plan and job scheduling.\nPlan and implement future network/system enhancements and upgrade/migration.\nAssist and support project deployment in the region\n\nRequirements:\n\nDegree holder in Computer Science\nHolding of MCSE and/or MCSA and CCNA certificates\nMinimum 5 years of solid experience in in both IT on-going support, and IT project management\nSolid experience in managing sizable IT infrastructures, helpdesk and end-user support\nPractical experience in Windows, Linux, TCP/IP, VPN, VLAN, WAN, Active Directory, IPT, Switch configuration, VM, Firewall, Proxy, and ITIL best practices, etc.\nExcellent analytical, problem-solving, strong communication and interpersonal skills\nProactive and service oriented, self-motivated, able to work independently and under pressure, open-minded to work in multi-cultural environment\nEffective vendor management and contract negotiation skills\nExcellent in written and spoken English and Chinese\nCandidate with less experience will be considered as Senior Network Administrator\n\nWe offer an attractive remuneration package in commensurate with the qualifications and experience to the right candidate. Interested parties please apply with full resume, present and expected salaries and availability by clicking \"Apply Now\".\n\nAll applications received will be used exclusively for employment purpose only. Applications not invited for interview within 6 weeks may consider their applications unsuccessful.\n\nFor more details, please visit our Website\u00a0https://www.lsgskychefs.com\n", "employment_types": ["Full Time"], "selling_points": ["\u6301CISP\u3001CISA\u3001CCNA\u3001CCNP\u8005\u512a\u5148\u8003\u616e", "\u9632\u706b\u7246\u3001\u8def\u7531\u5668\u3001\u4ea4\u63db\u6a5f\u3001\u6a5f\u623f\u7ba1\u7406\u7d93\u9a57", "\u7db2\u8def\u5b89\u5168\u3001\u8cc7\u8a0a\u5b89\u5168\u7ba1\u7406\u548c\u8cc7\u8a0a\u79d1\u6280\u98a8\u96aa\u7ba1\u7406"], "locations": ["Admiralty"], "categories": ["Information Technology (IT)", "Application Specialist - Network"], "post_time": "2022-01-17T03:36:22Z", "salary": {"currency": null, "max": null, "min": null, "period": "monthly", "term": null}, "salary_visible": false, "title_keywords": ["manager"], "responsibilities": ["installation", "provide support", "software", "it infrastructure", "maintenance", "configuration", "system documentation", "monitoring", "compliance", "testing", "scheduling", "maintain", "plan", "migration", "setup", "administration"], "requirements": {"degrees": ["degree holder"], "majors": ["computer science"], "languages": ["english", "chinese"], "language_level": ["excellent"], "hard_skills": ["itil", "mcse", "linux", "firewall", "active directory", "tcp", "switch", "problem-solving", "ccna", "vendor", "project management", "ip", "vpn", "mcsa", "wan"], "soft_skills": ["self-motivated", "proactive", "work independently", "under pressure", "open-minded", "problem-solving", "project management", "negotiation skills", "communication and interpersonal skills", "active"], "languages_combined": [{"language": "english", "language_level": ["excellent"]}, {"language": "chinese", "language_level": ["excellent"]}]}, "experience_required": {"duration": ["minimum 5 years"], "field": ["project management", "it"]}}, {"job_id": "100003009052960", "location_code": "hk", "company": "NexLen Internationl Limited", "job_title": "Technical Engineer (Network and Cybersecurity)", "description": "Responsibilities:\n\nProvide support on the routine monitoring, configuration and maintenance of network devices\u00a0\nPerform first-tier end-user support on network connectivity problem\nPrepare and maintain documentation on network infrastructure, network setup, drawings, inventory and guidelines\nAssist to evaluate new technologies, plan and implement solutions to cope with\u00a0the business requirements\nHandle urgent business requests and network deployment duties timely during normal and non-office hours with company-assigned facilities including phone and laptop\n\nRequirements:\n\nDegree holder in Information Technology, Computer Science or related disciplines\nMinimum 2 years\u2019 experience in network implementations and operation, with strong technical exposure in LAN, WAN, switches, routers and firewall\nSolid experience in network infrastructure implementation projects with internal technical teams and external support partners\nHands-on experience in router & switch management for H3C/ Cisco/ Juniper; and firewall management on SonicWALL/ Palo Alto/ Checkpoint\nSelf-motivated, well-organized, good interpersonal skills, able to work independently or in a team\nGood command of both written and spoken English and Chinese\n\nWe work 5 days per week.\n\nInterested parties, please click \"APPLY NOW\" below and attach with your application letter and full resume.\u00a0\n\nFor further information of the Wharf Group, please visit our website: www.wharfholdings.com\n", "employment_types": ["Full Time", "Permanent"], "selling_points": ["Attractive salary package", "Customer orientated, problem solving", "2 years solid hands on experience in IT/Security"], "locations": ["Kwun Tong"], "categories": ["Information Technology (IT)", "Support", "Application Specialist - Network", "Network & System"], "post_time": "2022-01-17T04:42:30Z", "salary": {"currency": null, "max": null, "min": null, "period": "monthly", "term": null}, "salary_visible": false, "title_keywords": ["technical engineer"], "responsibilities": ["network infrastructure", "provide support", "maintenance", "configuration", "guidelines", "inventory", "monitoring", "drawings", "evaluate", "plan", "maintain documentation", "setup"], "requirements": {"degrees": ["degree holder"], "majors": ["related disciplines", "computer science", "information technology"], "languages": ["english", "chinese"], "language_level": ["good command"], "hard_skills": ["router", "wan", "switch", "firewall"], "soft_skills": ["work independently", "self-motivated", "well-organized", "hands-on", "interpersonal skills"], "languages_combined": [{"language": "english", "language_level": ["good command"]}, {"language": "chinese", "language_level": ["good command"]}]}, "experience_required": {"duration": ["minimum 2 years"], "field": ["infrastructure", "management", "operation"]}}, {"job_id": "100003009051179", "location_code": "hk", "company": "Job Gallery Consultancy Limited", "job_title": "Network Support Engineer", "description": "Job Responsibilities\n\nPreform post-sales activities\nResponsible for network and cybersecurity area, support sales team and provide excellent service to customers\n\nRequirements\n\n3 years' solid working experience in network and cybersecurity\nDegree / High Diploma in information engineering or equivalent\nLogical, positive thinking, hard working and enjoy teamwork\nGood interpersonal and communication skills\nGood team player, target-oriented with strong analytical and problem solving skills\nCISSP, CCNA is a plus\n\nWe offer attractive salary and fringe benefit package to the right candidate. Interested parties please send full resume with expected salary.\n\nPersonal data provided in your application will be kept in the strictest confidence. It will be used for employment-related purposes. Applications not notified within 1 month will be considered as unsuccessful. Unsuccessful application may be kept for another 3 months for new openings before properly shredded.", "employment_types": ["Full Time"], "selling_points": ["Handle advance customer technical enquiries", "Degree in Computer Science,Information Technology", "At least 3 year on computer and Network"], "locations": ["Shatin Area"], "categories": ["Information Technology (IT)", "Application Specialist - Network"], "post_time": "2022-01-15T04:12:40Z", "salary": {"currency": null, "max": null, "min": null, "period": "monthly", "term": null}, "salary_visible": false, "title_keywords": ["support engineer"], "responsibilities": ["sales activities", "sales team"], "requirements": {"degrees": ["high diploma", "degree"], "majors": ["engineering"], "languages": [], "language_level": [], "hard_skills": ["problem solving skills", "ccna", "plus"], "soft_skills": ["communication skills", "good team player", "hard working", "teamwork", "positive thinking", "analytical and problem solving skills", "interpersonal"], "languages_combined": []}, "experience_required": {"duration": ["3 years"], "field": []}}, {"job_id": "100003009054539", "location_code": "hk", "company": "PERSOLKELLY Hong Kong Limited", "job_title": "Helpdesk Support Specialist (VIP Support)", "description": "Our client from a E-Commerce sector is looking for a Helpdesk Support Specialist to support their internal system including\u00a0personnel EHR, administration, finance, procurement, IT services, assets, workflow, collaboration system and office networks. The successful candidate\u00a0will work cross-functionally to support our international business and users across different locations across Europe; support basic office IT infrastructure, provide IT services and IT assets management; manage regional and group-wide projects such as new office build project, company-wide project support e.g. Double 11, business-specific project e.g. global user experience improvement; involve in global Merge & Acquisition integration projects working on cross-function collaboration from different business units in different continents, etc.\n\nRequirement\n\nProvide 1st and 2nd level IT support including desktop related technical assistance via telephone, ticket system, emails and instant chat messaging tool, etc.\nSupport event, video conference with understanding knowhow and break fix\nSupport and troubleshoot desktop Technology and application like Microsoft Office\nWith proactive communication with senior executive with quick resolution and follow up plan\nYoung, initiative and willing to learn\nFast learner on new technology with data driven\nEnsuring proper documentation, notification, tracking, and follow up of all incidents.\u00a0\n\nJob requirements:\n\n5+ years of work experience in large enterprise companies\nUniversity degree in computer science or equivalent experience in IT\nStrong knowledge in User & VIP Support and ITIL methodology\nProven ability of project management\nStrong Communication with different department and stakeholders\n\nPreferred Requirements:\n\nExcellent Mandarin (Speaking and writing)\nFamiliar with Mac OS\n\nTo apply for this position, please send your full r\u00e9sum\u00e9 to\u00a0Contract_hk @persolkelly.com\u00a0in word format indicating the reference number and title.\n\nIf you are not contacted by our consultants within 2 weeks, please consider your application unsuccessful. All applications will be treated in strict confidence, and used for recruitment purposes only in accordance with\u00a0PERSOLKELLY Hong Kong Limited\u2019s Privacy Notice.", "employment_types": ["Full Time"], "selling_points": ["VIP Helpdesk Support", "E-Commerce", "Competitive Package"], "locations": ["Central & Western Area"], "categories": ["Information Technology (IT)", "Support", "Application Specialist - Network", "Network & System"], "post_time": "2022-01-17T09:55:02Z", "salary": {"currency": null, "max": null, "min": null, "period": "monthly", "term": null}, "salary_visible": false, "title_keywords": ["specialist"], "responsibilities": ["management", "tracking", "it infrastructure", "data", "user experience", "communication", "resolution", "project management", "recruitment", "troubleshoot", "plan", "documentation", "technical assistance", "administration"], "requirements": {"degrees": ["university degree"], "majors": ["it", "computer science"], "languages": ["mandarin"], "language_level": ["excellent"], "hard_skills": ["itil", "mac os", "documentation", "basic", "microsoft office", "e-commerce", "word", "project management", "integration"], "soft_skills": ["confidence", "willing to learn", "driven", "communication", "project management", "troubleshoot", "proactive", "fast learner", "initiative"], "languages_combined": [{"language": "mandarin", "language_level": ["excellent"]}]}, "experience_required": {"duration": ["5+ years"], "field": ["it"]}}, {"job_id": "100003009053065", "location_code": "hk", "company": "OCBC Wing Hang Bank Limited", "job_title": "Fintech Intern, System Development (12 months contract from Jul 2022 to Jun 2023)", "description": "WeLab is a leading fintech company in Asia, \u00a0which operates one of first licensed digital banks in Asia \u2013 WeLab Bank, as well as multiple leading online financial services businesses including WeLend and WeLab Bank in Hong Kong, WeLab Digital (\u6211\u6765\u6570\u79d1), Taoxinji (\u6dd8\u65b0\u673a), Wallet Gugu (\u94b1\u5939\u8c37\u8c37) and Tianmian Tech (\u5929\u5195\u79d1\u6280)\u00a0in Mainland China and Maucash in Indonesia. WeLab aims to bring joy to everyone\u2019s financial journey. We strive to improve people\u2019s lives by reinventing financial services through game-changing technology. We put our people first, whether it\u2019s our customers or our employees.\nWe are an energetic and passionate team that can deliver and execute. We are looking for other intellectually curious, open-minded and smart-working individuals who are just as passionate as we are about making financial services enjoyable. Now you have the opportunity to join us on our journey to achieve our vision and be part of building a better financial future for everyone.\nAbout you:\nYou're a go-getter with mad juggling skills (or multiple hats) who can thrive in a fast-paced, agile environment\nYou have a strong thirst for knowledge and are driven to find solutions that don't exist yet\nYou are comfortable with ambiguity and extremely resourceful (in your past life you could've been a detective)\nYou always find a way to get things done without sacrificing the quality of your work, integrity and values. No task is off limits for you.\nYou are humble and prioritize the success of the team over your own with an eagerness to help those around you\nYou don't shy away from challenges and have the ability to bounce back from setbacks\nWhat you\u2019ll do and what success looks like in this role\nResponsible for evaluation, moderation, design, execution, implementation, monitoring, health check for IT infrastructure projects\nParticipate and help in internal and external auditors, business continuity planning, disaster recovery and other security related activities.\nMonitoring, Capacity Planning, Keeping Inventory of infrastructure, network and security hardware, software and services contracts.\nExecute and reporting on network and security procedures and standards.\nMonitoring, reporting and applying system / security patches and upgrades to systems.\nWork on execution, monitoring and reporting on IT Infrastructure and security projects\nWork under company defined quality and security standards.\u00a0 Adhere to all established risk control guidelines, procedures and measures to identify, assess, report, mitigate and monitor the risks involved in the day-to-day work\nMaintain daily operation and support to users\nExplore new technology and perform proof of concept\nPerform user support and security awareness training\nWork alongside with other team members and report to team lead\nWhat is required and what we\u2019re looking for\nHigher Diploma or above in Computer Science, IT or related discipline\nMinimum 2 years of IT experience preferably in the financial sector with proven experience in IT Infrastructure, Network and Security operations\nGood technical knowledge in IT Infrastructure, including cloud, network and security areas\nGood knowledge in IT security, performance tuning, capacity planning, storage, and networking\nGood analytical, communication and problem solving skills\nGood team player\nHolder of CISSP/CISA certification is preferred\nGood command of both spoken and written Chinese and English\nWeLab perks:\nCompetitive salary\nLearning and development stipend, because we value lifelong learning and believe the best way to invest in our employees is to encourage them to continue to learn\nWork hard and laugh lots (chicken wings and french toast, etc.) with a high-performing, fun and diverse team\nHappiness Dollars for spending on anything that makes you happy\nCoffee stipend\nConveniently located office surrounded by diverse and delicious lunch options\nLively office with gaming consoles and a ping pong table\nFun extracurricular activities with your colleagues like hiking, yoga, badminton, wine tasting, dragon boat racing, rock climbing, etc.\nEmployee referral bonuses\nAwards & recognition:\nFinancial Times (FT) 2020 Asia-Pacific High-Growth Companies \u2013 #2 ranked company\n2020 CNBC Disruptor 50 List - #11, only company included from Hong Kong and just one of five from Asia\nWe offer competitive salary package to the successful candidate.\u00a0If you are interested in joining this exciting team, please apply with resume via the \"Apply\" button below.\nAll information provided by applicants will be used for recruitment purposes only. Information of unsuccessful applicants will be destroyed within 24 months of receipt.\u00a0", "employment_types": ["Temporary", "Contract"], "selling_points": ["CRM", "Customer Risk Assessment Engine", "Investment Product system for E-Banking and Mobile"], "locations": ["Shau Kei Wan"], "categories": ["Information Technology (IT)", "Application Specialist - Software", "Application Specialist - Network", "Others"], "post_time": "2022-01-17T05:33:19Z", "salary": {"currency": null, "max": null, "min": null, "period": "monthly", "term": null}, "salary_visible": false, "title_keywords": ["intern"], "responsibilities": ["business continuity", "software", "operations", "inventory", "quality", "design", "communication", "maintain", "evaluation", "control", "it infrastructure", "contracts", "infrastructure", "monitor", "implementation", "report", "reporting", "upgrades", "monitoring", "procedures", "guidelines", "systems", "daily operation", "external auditors", "hardware", "planning"], "requirements": {"degrees": ["higher diploma or above"], "majors": ["it", "computer science"], "languages": ["english", "french", "chinese"], "language_level": ["good command"], "hard_skills": ["no", "joy", "agile", "fun", "hardware", "problem solving skills", "go", "mad"], "soft_skills": ["passionate", "good team player", "agile", "resourceful", "responsible", "open-minded", "integrity", "prioritize", "communication", "diverse", "learning", "problem solving skills", "energetic", "driven"], "languages_combined": [{"language": "english", "language_level": ["good command"]}, {"language": "french", "language_level": []}, {"language": "chinese", "language_level": ["good command"]}]}, "experience_required": {"duration": ["minimum 2 years"], "field": ["infrastructure", "it experience", "it", "security", "financial"]}}, {"job_id": "100003009053060", "location_code": "hk", "company": "OCBC Wing Hang Bank Limited", "job_title": "Fintech Intern, Digital Projects (12 months contract from Jul 2022 to Jun 2023)", "description": "\u5de5\u4f5c\u8077\u8cac\uff1a\n\n\u7ba1\u7406\u53ca\u5efa\u8a2d\u516c\u53f8\u7db2\u8def\u57fa\u790e\u67b6\u69cb\uff0c\u843d\u5be6\u53ca\u76e3\u63a7\u5404\u9805\u8cc7\u8a0a\u5b89\u5168\u8981\u6c42\uff1b\n\u843d\u5be6\u76e3\u7ba1\u6a5f\u69cb\u53ca\u7e3d\u884c\u4e26\u8868\u8cc7\u8a0a\u79d1\u6280\u98a8\u96aa\u7ba1\u7406\u7684\u8981\u6c42\uff1b\n\u57f7\u884c\u65e5\u5e38\u7db2\u8def\u6aa2\u67e5\u3001\u5347\u7d1a\u3001\u5efa\u8a2d\u65b0\u5c08\u6848\u53ca\u914d\u5408\u696d\u52d9\u9700\u8981\u6539\u9020\u7db2\u8def\u67b6\u69cb\uff1b\n\u6a5f\u623f\u7684\u65e5\u5e38\u7dad\u8b77\u53ca\u7ba1\u7406\uff1b\u4e26\u63d0\u4f9b\u5176\u5b83\u5468\u908a\u7cfb\u7d71\u7684\u652f\u63f4\u3002\u4f8b\u5982\uff0c\u8996\u983b\u7cfb\u7d71\u3001\u8cc7\u6599\u5eab\u5099\u4efd\u53ca\u516c\u6587\u7cfb\u7d71\u7684\u652f\u63f4\u7b49\uff1b\n\u8ca0\u8cac\u516c\u53f8\u65e5\u5e38\u8fa6\u516c\u8a2d\u5099\u3001\u7db2\u8def\u8a2d\u5099\u7684\u63a1\u8cfc\u5de5\u4f5c\uff1b\n\u5b8c\u6210\u90e8\u9580\u5206\u914d\u7684\u5176\u4ed6\u5de5\u4f5c\u3002\n\n\u4efb\u8077\u8981\u6c42\uff1a\n\n\u77e5\u540d\u9662\u6821\u7d93\u7ba1\u985e\u7d71\u62db\u672c\u79d1\u53ca\u4ee5\u4e0a\u5b78\u6b77\uff1b\n3\u5e74\u4ee5\u4e0a\u91d1\u878d\u884c\u696d\u76f8\u95dc\u7d93\u9a57, \u6301CISP\u3001CISA\u3001CCNA\u3001CCNP\u8005\u512a\u5148\u8003\u616e;\n\u5177\u6709\u9632\u706b\u7246\u3001\u8def\u7531\u5668\u3001\u4ea4\u63db\u6a5f\u53ca\u5176\u5b83\u5b89\u5168\u8a2d\u5099\u7684\u8a2d\u5b9a\u53ca\u6a5f\u623f\u7ba1\u7406\u7d93\u9a57\uff1b\n\u5177\u6709AD\u670d\u52d9\u3001\u4f3a\u670d\u5668\u53ca\u90f5\u4ef6\u4f3a\u670d\u5668\u7684\u7ba1\u7406\u7d93\u9a57\uff1b\n\u5177\u5099\u8f03\u597d\u5c08\u696d\u80fd\u529b\uff0c\u5305\u62ec\u7db2\u8def\u5b89\u5168\u3001\u8cc7\u8a0a\u5b89\u5168\u7ba1\u7406\u548c\u8cc7\u8a0a\u79d1\u6280\u98a8\u96aa\u7ba1\u7406\u76f8\u95dc\u9818\u57df;\n\u56b4\u8b39\u7d30\u7dfb, \u5177\u5718\u968a\u7cbe\u795e\u3001\u7d44\u7e54\u5354\u8abf\u80fd\u529b\u8207\u6297\u58d3\u80fd\u529b\uff1b\n\u826f\u597d\u6e9d\u901a\u80fd\u529b\uff0c \u64cd\u6d41\u5229\u5ee3\u6771\u8a71\u3001\u666e\u901a\u8a71\u548c\u826f\u597d\u82f1\u8a9e\u3002", "employment_types": ["Temporary", "Contract"], "selling_points": ["\u200bAssist business and IT teams", "Digital / e-Banking initiatives", "Knowledge in online collaboration tools"], "locations": ["Shau Kei Wan"], "categories": ["Information Technology (IT)", "Application Specialist - Software", "Application Specialist - Network", "Others"], "post_time": "2022-01-17T05:30:40Z", "salary": {"currency": null, "max": null, "min": null, "period": "monthly", "term": null}, "salary_visible": false, "title_keywords": ["intern"], "responsibilities": [], "requirements": {"degrees": [], "majors": [], "languages": [], "language_level": [], "hard_skills": [], "soft_skills": [], "languages_combined": []}, "experience_required": {"duration": [], "field": []}}, {"job_id": "100003009054525", "location_code": "hk", "company": "Linkers International Limited", "job_title": "[Senior] Cloud Engineer (AWS / Azure) Perm role, on job training provided (25k-40k)", "description": "Accelerate your career\n\nExperience the latest technology on cloud and infrastructure services\nLearn and apply the latest technologies in building enterprise office intelligence solution and infrastructure services\nGain global exposure on office intelligence solution management\u00a0\n\nYour role\n\nParticipate in enterprise office intelligence solution design, solution and software development\nResearch and evaluate new technologies on different office intelligence solutions\nInteract directly with users through user centered design techniques including observational research, interviews, and concept testing to uncover needs, learn about user behavior and explore design concepts.\nTranslate visionary ideas or requirements into thoughtful and compelling design concepts and work with team members to muck up both low and high-fidelity prototypes and implement solution for different business users globally\nParticipate in server and desktop solution research and development\nParticipate in architectural design and implementation of infrastructure services\n2nd tier technical support of infrastructure servers platform\u00a0\n\nWho we are looking for\n\nBachelor\u2019s degree in Computer Engineering, Computer Science or IT related disciplines\nEager to learn in a fast-paced and dynamic environment\nPassionate in pursuing IT professionalism\nAt least 2 years of IT infrastructure support and administration in an enterprise environment\nProficient in Microsoft Windows Server and desktop operating environment and network (Windows 2016 Server, Active Directory, DNS, Windows 10 Desktop)\nKnowledge on cloud product like Azure, AWS and O365\nGood command of spoken and written English, Mandarin is an advantage\u00a0\n\nPlease send your application letter with detailed resume and expected salary by clicking \"Apply Now\" and quote the reference number on the subject\u00a0\n\n(Data collected will be used for recruitment purpose only.)", "employment_types": ["Full Time", "Permanent"], "selling_points": ["5 days work, perm role at sizeable company", "Hands on AWS / Azure / any cloud techonology", "Welcome junior / senior, on job training provided"], "locations": ["Hung Hom"], "categories": ["Information Technology (IT)", "Application Specialist - Software", "Support", "Application Specialist - Network"], "post_time": "2022-01-17T09:53:02Z", "salary": {"currency": "HKD", "max": 44999, "min": 25000, "period": "monthly", "term": null}, "salary_visible": true, "title_keywords": ["engineer"], "responsibilities": ["design concepts", "management", "ideas", "software", "it infrastructure", "active directory", "technical support", "dns", "data", "infrastructure", "implementation", "design", "testing", "evaluate", "recruitment", "administration"], "requirements": {"degrees": ["degree", "bachelor"], "majors": ["related disciplines", "it", "computer engineering", "computer science"], "languages": ["english", "mandarin"], "language_level": ["advantage", "good command"], "hard_skills": ["o365", "infrastructure support", "azure", "servers", "active directory", "dns", "aws", "windows 10", "dynamic", "server", "windows server"], "soft_skills": ["passionate", "dynamic environment", "eager to learn", "visionary", "active", "detailed"], "languages_combined": [{"language": "english", "language_level": ["advantage", "good command"]}, {"language": "mandarin", "language_level": ["advantage", "good command"]}]}, "experience_required": {"duration": [], "field": ["infrastructure"]}}, {"job_id": "100003009053069", "location_code": "hk", "company": "Orient Overseas Container Line Ltd (OOCL)", "job_title": "Technical Analyst - Office Intelligence Solution / Infrastructure", "description": "Background:\u00a0My client is one of the top-tier financial services firms in Hong Kong who is now looking for an experienced Senior Network Manager to join their team.\n\nDuties\n\n\nHave overall responsibility for the development and on-going management and support of Group IT Network Infrastructure\nTo build a deep understanding of key business areas around the region to plan, develop and implement Network infrastructure solutions that will deliver corporate and service specific objectives and meet the strategic priorities of the BU\nSupervise the Network Operation Support Team for Cloud infrastructure Integration, Migration and BAU Support.\nManage, design, and architect On-Premise and Cloud Network and Data Centre infrastructure\nEvaluates New IT Network products or services and suggests changes to existing products or services to better aide the end user\nSupport IT Network Infrastructure Setup & Network Integration/Separation of New business entity\nLiaise with IT application, infra and security architect on the technical development of converged solutions and process to enhance the operations of services\nLead a team with managers and Technical engineers to negotiate with vendors, auditors, consultants.\u00a0\nLead the Network Infrastructure team for management and support of Group IT Network and services availability, capacity and critical support for business system and ensure the service is meet SLA Standard\nLead the Network team to manage and support IT infrastructure projects\nLead the Network Operation Team to support the migration and operation support.\nEnsure the IT Network infrastructure are fulfil compliance/security requirement\nTechnical Evaluation of Network solution, latest technology and management tools on Cloud environment\nAssists in conducting DR Drill and BCP process\nAssist in Vendor and Contract Management to support IT Network infrastructure\n\nRequirements:\n\n\nDegree holder in Computer Science / Information Technology or equivalent with more than 15 years of relevant experience which 6-8 years in managerial level\nITIL foundation certification with relevant experience in this area\nHolder of professional qualification(s) preferred, e.g. Cisco, Checkpoint, Azure, AWS Certification, but not a must\u00a0\nSolid experience in network administration with Strong Knowledge in LAN/MAN/WAN/SD-WAN/Cloud Network Architecture (AWS & AWS), Micro-Segmentation Firewall, Router/Switch, Wireless LAN, VPN, IPS, WAF, SLB, Network Management, Performance Monitoring and Automation Tools\nStrong problem solving, management and analytical skills with in-depth knowledge of Regional Datacentre and Cloud Network Infrastructure, DR Management and Security.\nStrong knowledge on various vendor products such as Cisco, Checkpoint, Palo alto, Imperva, F5, Riverbed, Megaport, MPLS and SDWAN solution. (Either 2 of the following)\u00a0\nGood command of written English and Chinese; fluent in spoken English\n\nIf you are interested in this position, please apply online by submitting your latest CV in Word format including current & expected salary. Kindly note that only shortlisted candidates will be notified.", "employment_types": ["Full Time", "Permanent"], "selling_points": ["5 day work week + Benefits", "Opportunities to explore to new technologies", "Good team player; Strong communication skills"], "locations": ["Shatin Area"], "categories": ["Information Technology (IT)", "Hardware", "Application Specialist - Network", "Security"], "post_time": "2022-01-17T05:33:53Z", "salary": {"currency": null, "max": null, "min": null, "period": "monthly", "term": null}, "salary_visible": false, "title_keywords": ["analyst"], "responsibilities": ["network infrastructure", "management", "it infrastructure", "data", "operations", "infrastructure", "compliance", "contract management", "design", "develop", "lead a team", "network integration", "security requirement", "plan", "evaluation", "liaise with", "migration", "setup"], "requirements": {"degrees": ["degree holder"], "majors": ["computer science", "information technology"], "languages": ["english", "chinese"], "language_level": ["good command", "fluent"], "hard_skills": ["itil", "network administration", "network management", "azure", "switch", "vendor", "word", "aws", "router", "problem solving", "analytical skills", "sd-wan", "vpn", "firewall", "wan"], "soft_skills": ["problem solving", "interested in", "analytical skills"], "languages_combined": [{"language": "english", "language_level": ["fluent", "good command"]}, {"language": "chinese", "language_level": ["fluent", "good command"]}]}, "experience_required": {"duration": ["6-8 years", "15 years"], "field": ["network administration", "managerial", "management", "information technology", "relevant experience"]}}, {"job_id": "100003009048514", "location_code": "hk", "company": "Dataplugs Limited", "job_title": "System Engineer (Near Ngau Tau Kok MTR station)", "description": "Job Duties:\n\nProvides end-user support and problem-solving support on hardware, software & package installation and maintenance for servers & PCs\nPerforms IT audit & complete group IT checklists & surveys\nLiaisons with internal & external vendors on network, email, application system (SBO), IT contracts and other related issues\nSet up presentation and conference equipment\nStudies and supports on IT security control software\nMaintains company Intranet website\nConducts fixed asset stock take with A/C Dept.\nAd Hoc projects\n\nJob Requirements:\n\nHigher Diploma or above in information technology, computer technology, or a similar field.\nAt least two years' experience as an IT support or related role.\nExperience working with Microsoft Office 2016, 2019, or Office 365.\nStrong troubleshooting, analytical, and problem-solving skills.\nGood interpersonal skills and the ability to work with technical and non-technical personnel.", "employment_types": ["Full Time", "Permanent"], "selling_points": ["Develop & maintain cloud infrastructure", "Linux, Windows Administration and VMware support", "Performance Bonus, Medical & Dental Insurance"], "locations": ["Ngau Tau Kok"], "categories": ["Information Technology (IT)", "Application Specialist - Network", "Network & System", "Others"], "post_time": "2022-01-15T19:11:34Z", "salary": {"currency": null, "max": null, "min": null, "period": "monthly", "term": null}, "salary_visible": false, "title_keywords": ["system engineer"], "responsibilities": ["installation", "control", "software", "maintenance", "contracts", "pcs", "audit", "application system", "website", "stock take", "hardware", "ad hoc projects"], "requirements": {"degrees": ["higher diploma or above"], "majors": ["information technology"], "languages": [], "language_level": [], "hard_skills": ["problem-solving skills", "office 365", "microsoft office"], "soft_skills": ["problem-solving skills", "interpersonal skills", "troubleshooting"], "languages_combined": []}, "experience_required": {"duration": ["at least two years"], "field": ["related", "it support"]}}, {"job_id": "100003009052809", "location_code": "hk", "company": "HomePlus (Hong Kong) Limited (HOME+)", "job_title": "(Senior) IT Manager", "description": "Our partner who specializes in AI, Blockchain, and IoT solutions, is urgently seeking for mobile developers to join their growing team. This role will primarily focus on mobile applications development and their integration with backend services. You will also be working along-side other global engineers and developers on different layers of the infrastructure. Thus, communication and commitment to collaborative problem-solving, sophisticated design, and adopted key technology is essential.\n\nResponsibilities\n\nDevelop mobile applications and their integration with backend services\nTranslate designs and wireframes into high quality code\nDesign, build, and maintain high performance, reusable, and reliable code along with requirement specification\nEnsure the best possible performance, quality, and responsiveness of the application\nDevelopment and maintenance of applications aimed at a vast number of diverse mobile devices\nWork along-side other IT teams on different layers of infrastructure\nResolve tough technical issues of mobile OS system\nAct as an independent problem solver, identify and correct bottlenecks and fix bugs, help maintain code quality, organization, and automation\nAssist to maintain business as usual operations of customers, perform desktop support duties (e.g. computer installation, hardware/software configurations on desktop, laptop, mobile devices)\nPerform systems and network monitoring, and routine hardware/software maintenance\nParticipate in design, develop, preparation of projects (e.g. cloud migration)\n\nRequirements\n\nDegree graduate or above in Computer Science, Information Technology or relevant discipline\nMinimum 2 years object-oriented software development experience, especially in mobile/web application\nKnowledge of Android SDK and iOS development platform including different mobile devices versions and how to deal with various screen sizes\nFamiliar with RESTful APIs and strong knowledge of mobile UI design principles, patterns, and best practices\nExperience with offline storage, threading, and performance tuning\nKnowledge of open-source Android ecosystem, iOS ecosystem, and the libraries available for common tasks\nKnowledgeable with O2O application development, familiar with cloud message APIs and push notifications\nGood understanding of Linux OS, Windows OS, Office 365 Microsoft Application Active Directory, Exchange, MS Teams, etc.\nKnowledge in server, VMWare, OC, TCP/IP, HTTPS and LAN/WAN networking equipment\nKnowledge in SQL (MS SQL, Oracle DB), Oracle Forms and Report\nPatching, Hardware, Software, and OS troubleshooting\nQuick learner, willing to learn new technologies especially new mobile OS platform\nCan work under pressure and independently\nFluency in spoken and written English and Chinese (Mandarin & Cantonese)\nCandidates with lesser experience will be considered for Jr. role\nFresh graduates are welcome", "employment_types": ["Full Time"], "selling_points": ["Handson exp. in Cloud Architect (AWS) & Magento 2", "Agile & Flexible working culture with great team", "Join Us if You're Passionate about E-commerce"], "locations": ["Kwai Hing"], "categories": ["Information Technology (IT)", "IT Management", "Application Specialist - Network", "E-commerce", "Product Management / Business Analyst"], "post_time": "2022-01-17T04:23:54Z", "salary": {"currency": null, "max": null, "min": null, "period": "monthly", "term": null}, "salary_visible": false, "title_keywords": ["it manager"], "responsibilities": ["installation", "software", "maintenance", "operations", "infrastructure", "quality", "teams", "design", "develop", "systems", "hardware", "monitoring", "maintain", "mobile devices", "migration"], "requirements": {"degrees": ["degree"], "majors": ["computer science", "information technology"], "languages": ["cantonese", "english", "chinese", "mandarin"], "language_level": ["fluency"], "hard_skills": ["linux", "office 365", "oracle", "vmware", "android sdk", "web", "active directory", "tcp", "sql", "mobile", "ip", "os", "hardware", "server", "wan", "ms sql", "android", "exchange"], "soft_skills": ["independently", "willing to learn", "troubleshooting", "quick learner", "active", "work under pressure"], "languages_combined": [{"language": "cantonese", "language_level": ["fluency"]}, {"language": "english", "language_level": ["fluency"]}, {"language": "chinese", "language_level": ["fluency"]}, {"language": "mandarin", "language_level": ["fluency"]}]}, "experience_required": {"duration": ["minimum 2 years"], "field": ["software development"]}}, {"job_id": "100003009050397", "location_code": "hk", "company": "Gold Partners (Asia) Asset Management Company Limited", "job_title": "Infrastructure Manager - HQIT", "description": "Responsibilities\n\u200bParticipant in key projects for business development with good quality delivery\nInvolve in system development life cycle activities of project, including user requirement collection, solution design, coding and testing, documentation and post-implementation support\nRequirements\n\u200bPostgraduate or 3rd year in Computing Science or Data Analytics or related subject\nExperience in latest Internet/Mobile Application development is a plus\nKnowledge in Java, J2EE, HTML5, Oracle SQL, Shell scripts\nGood command of written and spoken English\nSpeaking in Cantonese is preferred\nIndependent and self-initiative\nAttractive remuneration package will be offered to the right candidate.\u00a0 Please apply with full resume stating present & expected salary and contact phone number\u00a0to\u00a0The Human Resources Manager, 10/F, 161 Queen\u2019s Road Central, Hong Kong.\u00a0Please quote the reference.\n\n\nPersonal data collected will be used for recruitment purpose only.\u00a0 For more information, please visit our website:\u00a0http://www.ocbcwhhk.com.", "employment_types": ["Full Time", "Permanent"], "selling_points": [], "locations": ["Kowloon Bay"], "categories": ["Information Technology (IT)", "IT Management", "Application Specialist - Network", "Network & System"], "post_time": "2022-01-15T03:51:06Z", "salary": {"currency": null, "max": null, "min": null, "period": "monthly", "term": null}, "salary_visible": false, "title_keywords": ["manager"], "responsibilities": ["user requirement", "quality", "implementation", "coding", "design", "testing", "documentation"], "requirements": {"degrees": [], "majors": [], "languages": ["cantonese", "english"], "language_level": ["good command"], "hard_skills": ["plus", "java", "data analytics", "sql", "mobile", "oracle"], "soft_skills": ["independent", "self-initiative"], "languages_combined": [{"language": "cantonese", "language_level": []}, {"language": "english", "language_level": ["good command"]}]}, "experience_required": {"duration": [], "field": ["application development"]}}, {"job_id": "100003009054646", "location_code": "hk", "company": "Hitech Personnel Agency Co Ltd", "job_title": "Sales & Marketing Representative/Manager - Gi Group", "description": "Responsibilities\n\u200bAssist business and IT teams to gather requirements and define project scope\nAssist to identify functional impacts to front-to-back systems due to the gathered business and regulatory requirements\nAssist to analyse the business requirements to determine technology needs\nAssist to document fact-findings and results, design new process for delighted customer experience (CX) and specify system changes\nRequirements\n\u200bPostgraduate or 3rd year in Computing Science or e-commerce or related subject\nExperience in digital solution is a plus\nKnowledge in online collaboration tools (e.g. Jira, confluence, inVision), UML, HTML5, Xcode, Android and Business Process Model and Notation (BPMN) would be an advantage\nGood command of written and spoken English\nSpeaking in Cantonese is preferred\nDigital initiatives solutioning (mobile, internet or other banking products)\nIndependent and self-initiative\nAttractive remuneration package will be offered to the right candidate.\u00a0 Please apply with full resume stating present & expected salary and contact phone number\u00a0to\u00a0The Human Resources Manager, 10/F, 161 Queen\u2019s Road Central, Hong Kong.\u00a0Please quote the reference.\n\n\nPersonal data collected will be used for recruitment purpose only.\u00a0 For more information, please visit our website:\u00a0http://www.ocbcwhhk.com.", "employment_types": ["Full Time", "Permanent"], "selling_points": ["US Multinational Corporation", "Corporate Client in Finance, Retail & Hospitality", "IT Infrastructure/Software and Service Provider"], "locations": ["Quarry Bay"], "categories": ["Sales, CS & Business Devpt", "Business Development", "Information Technology (IT)", "Application Specialist - Software", "Application Specialist - Network"], "post_time": "2022-01-17T10:24:01Z", "salary": {"currency": null, "max": null, "min": null, "period": "monthly", "term": null}, "salary_visible": false, "title_keywords": ["representative", "manager", "sales"], "responsibilities": ["regulatory requirements", "systems", "teams", "design", "system changes", "analyse"], "requirements": {"degrees": [], "majors": [], "languages": ["cantonese", "english"], "language_level": ["good command"], "hard_skills": ["mobile", "plus", "android", "e-commerce"], "soft_skills": ["independent", "self-initiative"], "languages_combined": [{"language": "cantonese", "language_level": []}, {"language": "english", "language_level": ["good command"]}]}, "experience_required": {"duration": [], "field": ["digital"]}}, {"job_id": "100003009050506", "location_code": "hk", "company": "CL Technical Services Ltd.", "job_title": "IT Support Engineer (Perm, up to $19K, Shatin)", "description": "Responsibilities:\n\nOversee and administrate company group wide Server infrastructure (Physical/VM/Cloud) & Data Storage Management with security.\nPerform implementation including planning, designing, installing, configuring, migrating, testing on server infrastructure (Physical/VM/Cloud) & Data Storage with security.\nPerform server enhancement, performance and health status monitoring, troubleshooting network related issues and problem.\n2nd Support for network administration, LAN/WAN infrastructure operation and network monitoring\nWork closely within IT teams and external vendors to complete various IT projects and technologies advancement.\nPropose of new technologies/ideas to improve overall efficiency, effectiveness, reliability and availability of Server infrastructure.\n\nRequirements:\n\nGraduate of higher diploma or above in Information Technology, Computer Science or related disciplines\nProficient in Windows Server, VMWare, DBMS, SAN Storage, Backup solutions, Data Security, Office 365 Environments, Active Directory & Hybrid Exchange configuration and setup\nFamiliar of network infrastructure, Firewall, Router, VPN, Endpoint Security.\nAt least 5 years of working experience in network/server administration.\nStrong analytical, self-motivated, independent, problem solving and project management skills.\nGood time management and can work under pressure.\nGood spoken and written in English, Cantonese and Mandarin\nHolder of VMWare certificate is an advantage.\nWe offer competitive remuneration package and good prospects to the right candidates.\u00a0 Interested parties please send your full resume with expected salary to apply.\n\n\n*Data collected will be kept confidential and used for recruitment purposes only.", "employment_types": ["Full Time"], "selling_points": ["Discretionary bonus", "5 days work", "Shatin"], "locations": ["Shatin Area"], "categories": ["Information Technology (IT)", "Support", "Application Specialist - Network", "Network & System"], "post_time": "2022-01-14T10:34:29Z", "salary": {"currency": null, "max": null, "min": null, "period": "monthly", "term": null}, "salary_visible": false, "title_keywords": ["it support engineer"], "responsibilities": ["network administration", "management", "ideas", "data", "infrastructure", "monitoring", "implementation", "troubleshooting", "testing", "teams", "configuring", "installing", "designing", "planning"], "requirements": {"degrees": ["certificate", "higher diploma or above"], "majors": ["related disciplines", "computer science", "information technology"], "languages": ["cantonese", "english", "mandarin"], "language_level": ["good"], "hard_skills": ["office 365", "vmware", "active directory", "server administration", "router", "problem solving", "dbms", "project management", "vpn", "firewall", "windows server", "exchange"], "soft_skills": ["self-motivated", "independent", "project management skills", "problem solving", "time management", "active", "work under pressure"], "languages_combined": [{"language": "cantonese", "language_level": ["good"]}, {"language": "english", "language_level": ["good"]}, {"language": "mandarin", "language_level": ["good"]}]}, "experience_required": {"duration": ["at least 5 years"], "field": ["server administration"]}}, {"job_id": "100003009053832", "location_code": "hk", "company": "Reveal Media Hong Kong Limited", "job_title": "First Line Support Engineer", "description": "Job Responsibilities:\n\nResponsible for system analysis and application development\nMonitor the system and provide maintenance support for current systems\nResponsible for system rollout, deployment and operation support\u00a0\nConduct SIT, UAT, system and software testing\n\nJob Requirements:\n\nDegree holder in Computer Science, Engineering or equivalent\nProficient in C#.NET is preferred\nExperience with using enterprise DMS/EDMS package is preferred;\nImmediate available is an advantage.\n\n\n\nInterested parties, please send your full resume in word format together with salary expectation to katherineli @grammytech.com\n\n(All data collected would be used for recruitment purposes only)", "employment_types": ["Full Time"], "selling_points": [], "locations": ["Wan Chai"], "categories": ["Information Technology (IT)", "Application Specialist - Network"], "post_time": "2022-01-17T09:06:14Z", "salary": {"currency": null, "max": null, "min": null, "period": "monthly", "term": null}, "salary_visible": false, "title_keywords": ["support engineer"], "responsibilities": ["uat", "software", "maintenance support", "analysis", "systems", "monitor", "testing", "application development"], "requirements": {"degrees": ["degree holder"], "majors": ["engineering", "computer science"], "languages": [], "language_level": [], "hard_skills": ["c#"], "soft_skills": [], "languages_combined": []}, "experience_required": {"duration": [], "field": []}}, {"job_id": "100003009054427", "location_code": "hk", "company": "TalentQuest HR Limited", "job_title": "Back End Architect", "description": "Job Description\nWith ever increasing growth and expansion, we looking for a new IT Security Assistant Manager to join our InfoSec team. Ideally, this technical hand-on security person has worked an enterprise environment, where they would be responsible for on-going security management, threat assessment, testing, deployment and vendor management.\n\nKey Responsibilities:\nSecurity operation and BAU support as below:\n\nRespond for Internal / 3rd party security risk assessments\nPerform Vulnerability assessments (Qualys or Nessus) and handle the daily news feeds,\nCoordinate 3rd party Vendor to do penetration tests (Knowledge of kaliLinux or Metasploit or OWASP is a plus),\nIn charge of the Identity and password access management tools and control (CyberArk),\nPromote security awareness training and practices for the organization,\nongoing improvement on FortiSIEM rules\nHandle security alerts generated from Crowdstrike, Mcafee and SOC\nCollect KPI/KRI data and report monthly to Group\n\nMinimum Requirements:\n\n5 years of technical information security experience\nProfessional certification in of CISSP, CEH, CISA, CRISC or CISM equivalent\nUniversity degree in Computer Science, Information Systems or other technology-related disciplines\nFluent in both spoken and written English and Chinese\n\nKnowledge with the below Security tools is highly preferred:\n\nSecurity technology expertise in vulnerability assessments (Qualys or Nessus), penetration tests (KaliLinux or Metasploit), identity and password access management control (CyberArk), SIEM (FortiSIEM/Splunk,) CIS (hardening) Firewall (PaloAlto, Fortinet), AntiDDoS & WAF (Cloudflare), Endpoint (Crowdstrike, Mcafee, ManageEngine Central Desktop Manage).\nKnowledge in COBIT 5, NIST or ISO27001 framework\nEnterprise financial institution exposure (insurance or banking)\nExposure to similar security tools would also be considered\n\nFor strong candidates with less experience, they will be considered for an IT Security Specialist position.", "employment_types": ["Full Time", "Permanent"], "selling_points": ["Team Management", "Back End Architecture", "Code Reviews"], "locations": ["Not Specified"], "categories": ["Information Technology (IT)", "IT Project Management / Team Lead", "Application Specialist - Network", "Network & System"], "post_time": "2022-01-17T09:30:21Z", "salary": {"currency": null, "max": null, "min": null, "period": "monthly", "term": null}, "salary_visible": false, "title_keywords": [], "responsibilities": ["management", "control", "data", "testing", "coordinate", "security operation", "report"], "requirements": {"degrees": ["university degree"], "majors": ["related disciplines", "computer science"], "languages": ["english", "chinese"], "language_level": ["fluent"], "hard_skills": ["firewall"], "soft_skills": [], "languages_combined": [{"language": "english", "language_level": ["fluent"]}, {"language": "chinese", "language_level": ["fluent"]}]}, "experience_required": {"duration": ["5 years"], "field": ["it", "security"]}}, {"job_id": "100003009048646", "location_code": "hk", "company": "Kerry Properties Limited", "job_title": "Lead Network Specialist, Technology & Innovation", "description": "Our client is a top tier ICT company and they are now looking for an Assistant Manager/Manager to lead one of their consultant team.\n\nResponsibilities\n\nDesign & architect the implementation of cloud solution using AWS, Alibaba Cloud, Microsoft Azure, advise customers on various cloud solution options & recommend a solution that aligns with business customer needs\nEngage in the AWS Services Configuration Management, Cloud Automation and Design for the AWS platform and applications\nResponsible to build Cloud infrastructure as a code (CDK, Terraform, Ansible) capability by planning and implementation of the cloud platform\nArchitect level of AWS cloud, Alibaba Cloud, Azure is a plus\nPerform system and network, design, implementation, monitoring, capacity management, security operations, and support in AWS, Alibaba Cloud, Microsoft Azure environment\nWork with the business and technical stakeholders on explaining the technical solutions\n\nRequirements\n\nBachelor\u2019s degree in IT-related, Computer Science discipline\u00a0\n2+ years of experience in Cloud computing technologies, concepts, and Cloud consulting, in the areas of Public Cloud , Private Cloud, Hybrid Cloud, Global Cloud technologies in AWS, Alibaba Cloud and Azure Cloud\nAcquired AWS Solution Architect Professional Certificate, specialty certificate in security and network is a plus\nCertificate in Alibaba Cloud, Azure and Google Cloud is a plus\nExperience with Cloud Automation & configuration management\nExperience with Cloud platform operations including system, network, and security monitoring\u00a0\nGood Communications skills in English\u00a0\nTalents with more experience will be considered Senior Cloud Engineer", "employment_types": ["Permanent"], "selling_points": ["Top-tier Properties Developer", "Promising Career Path", "Competitive Compensation Package"], "locations": ["Quarry Bay"], "categories": ["Information Technology (IT)", "Application Specialist - Network", "Network & System"], "post_time": "2022-01-14T06:57:12Z", "salary": {"currency": null, "max": null, "min": null, "period": "monthly", "term": null}, "salary_visible": false, "title_keywords": ["specialist", "lead"], "responsibilities": ["management", "configuration", "operations", "infrastructure", "monitoring", "implementation", "design", "planning"], "requirements": {"degrees": ["certificate", "degree", "bachelor"], "majors": ["it", "computer science"], "languages": ["english"], "language_level": ["good"], "hard_skills": ["computing technologies", "plus", "azure", "aws"], "soft_skills": [], "languages_combined": [{"language": "english", "language_level": ["good"]}]}, "experience_required": {"duration": ["2+ years"], "field": ["management", "security", "consulting"]}}, {"job_id": "100003009044844", "location_code": "hk", "company": "FWD Life Insurance Company (Bermuda) Limited", "job_title": "Manager, Infrastructure Service Delivery (Network)", "description": "THE JOB\n\nCapability to deploy and configue proposed architecture\nManage Cloud resources and services\nTroubleshoot operation issues and incidents\nCooperate with development team on Cloud integration and optimization\nFulfill DevOps flow of the team\nDocumentation / R&D / POC of services on Clouds\n\nTHE PERSON\n\nBachelor's degree or above in Computer Science or related disciplines\u2002\u2002\u2002\u2002\u2002\n2+ years of public / private / hybrid Cloud experience\nExperience with container (i.e. ECS, AKS, OpenShift, K8S), auto-scaling, HA would be an advantage\nExperience with Cloud CI / CD automations (i.e. Terraform, GitFlow, pipeline) would be an advantage\nExperience in handling networking or security product is a plus\nSelf-motived and able to work under pressure\nWilling to learn\n\nIf you're interested in this role, please click the Apply button above or via Linkers website at https://jobs.linkerscareers.com/ with your CV.\n\nIf you would like to have a further discussion about this role, please contact us at +852 2391 2813.\n\nPersonal data collected will be used for recruitment purposes only.", "employment_types": ["Full Time"], "selling_points": ["Design & implement network infrastructure solution", "Recommend infrastructure solutions", "Assist to maintain IT security standard"], "locations": ["Kwun Tong"], "categories": ["Information Technology (IT)", "Application Specialist - Software", "Application Specialist - Network"], "post_time": "2022-01-13T06:27:03Z", "salary": {"currency": null, "max": null, "min": null, "period": "monthly", "term": null}, "salary_visible": false, "title_keywords": ["manager"], "responsibilities": ["troubleshoot", "deploy", "documentation", "architecture", "cooperate with"], "requirements": {"degrees": ["degree or above", "bachelor"], "majors": ["related disciplines", "computer science"], "languages": [], "language_level": [], "hard_skills": ["plus", "container"], "soft_skills": ["interested in", "willing to learn", "work under pressure"], "languages_combined": []}, "experience_required": {"duration": ["2+ years"], "field": ["security"]}}, {"job_id": "100003009050794", "location_code": "hk", "company": "City Super Ltd", "job_title": "Server Administration Officer", "description": "Responsibilities:\n\n\nParticipate in develop and maintain private and public cloud infrastructure\nProactively monitoring system performance, backup, migration and capacity planning\nAutomate systems build and code promotion processes\nImplement and Manage software upgrades, patches on system\n\nRequirements:\n\n\n\nHigher Diploma in a technical discipline or equivalent work experience\n3+ years experience in system engineer or administration in sizeable production environment\nProficient in Linux, Windows Administration and VMware support\nProven knowledge in infrastructure, storage and network of on-premises is highly recommended\nExperience with public or private cloud technologies include AWS/Azure/GCP/AliCloud/OpenStack/VMware etc. (a few is beneficial)\nTechnical proficiency with mainstream automation and configuration management solutions include Ansible, Terraform, CI/CD, Git etc.\nHands on experience on system monitoring, preformance analysis and enhancement\nHands on experience on backup, failover and DR site solution\nPreparing technical documentation\nKnowledge of Kubernetes, docker as well as infrastructure design and development\nKnowledge of scripting with Bash or Python\nKnowledge of software-defined storage (Ceph) and SDN is an advantage\nFamiliar with Micro-services Architecture would be a definite advantage\nKnowledge of OpenStack is a plus\nStrong team player and self-motivation. Enjoy deliver solutions to the business\nProactive, innovative and passionate about technology\nCandidate with more experience will be considered as senior position\n\n\u00a0Benefits:\n\n\u00a05-day work week\n\u00a0Medical insurance\n\u00a0Dental Insurance\n\u00a0Year-end performance Bonus\n\u00a0Attractive remuneration\n\nSalary Negotiable, depends on experience & qualifications.\n\n\n\nInterested candidate please send your updated CV with expected salary by clicking \"Apply Now\".\n\n\n\nAll applications will be treated in strict confidence and used solely for recruitment purpose.", "employment_types": ["Full Time", "Permanent"], "selling_points": ["Oversee & admin server infrastructure & Data Mgt", "Network infrastructure, Firewall, Router, VPN, Sec", "5 years of working exp in network/server admin"], "locations": ["Tsim Sha Tsui"], "categories": ["Information Technology (IT)", "Application Specialist - Network", "Security", "Network & System"], "post_time": "2022-01-14T11:24:05Z", "salary": {"currency": null, "max": null, "min": null, "period": "monthly", "term": null}, "salary_visible": false, "title_keywords": ["server", "administration officer"], "responsibilities": ["software", "upgrades", "infrastructure", "monitoring", "systems", "develop", "maintain", "migration", "planning"], "requirements": {"degrees": ["diploma"], "majors": [], "languages": [], "language_level": [], "hard_skills": ["linux", "plus", "git", "azure", "vmware", "analysis", "bash", "aws", "ansible", "python", "documentation"], "soft_skills": ["innovative", "hands on", "self-motivation", "team player", "proactive", "passionate about"], "languages_combined": []}, "experience_required": {"duration": ["3+ years"], "field": ["administration"]}}, {"job_id": "100003009053050", "location_code": "hk", "company": "OCBC Wing Hang Bank Limited", "job_title": "System Analyst (Mainframe)", "description": "The purpose to you with this career opportunity will be...\n\nDrive project management and implementation of E-Commerce platform to support E-Commerce Business\nLeading a highly dynamic and innovative team in Agile/Scrum approach, to implement new projects, maintain and support change request\n\nWhat efforts you need to make for this role?\n\nAccountable for managing the design, implementation and delivery of E-Commerce Website to meet the E-Commerce business requirements and needs\nHave a deep understanding and hands-on experience in cloud architecture design, web application development, API development and troubleshooting\nPlan and procure external/internal resources according to the scope and budget of the project; manage and maintain that resource plan\nLiaise with software vendors and the business team to coordinate new website modules implementation, integrating functionalities across applications or modules, and maintenance activities\nProduce and communicate internal and external project status reports and maintain all necessary project documentation\nManage business requirements and lead the analysis, design, development, testing, release and maintenance\nWorks independently with minimal supervision; act as subject matter expert\nFollows applicable standards, policies, procedures, and best practices in the implementation and/or maintenance of applications or application modules\nPerforms other duties as requested\n\nLet's check if you are/ have\u2026\n\nDegree holder in Computer Science, Engineering or equivalent\nMinimum of 10-15 years related professional experience in IT, including\u00a05 years\u00a0at\u00a0management position\nMinimum of 6 years E-Commerce Website Implementation experience\nHas experience for payment gateway implementation e.g. AliPay, Global Payment, PayMe, WeChat Pay, etc.\nDemonstrated ability to understand business processes from a customer perspective, identify technical enablers, procedural re-engineering solutions and process improvements that meet business needs across the organization\nExcellent skills to work in cross-team environment, effectively interacting with internal & external parties, both written & verbal\nProven working experience in Project Management, with solid organizational skills including attention to detail and multitasking skills\nHands on experience on\u00a0Magento 2\u00a0is a plus\nProject Management Professional / Scrum / Agile certification is a plus\nExperience on AWS / Azure / DevOps is an advantage\nExperience on architecture design, Kubernetes, containers, micro-services, message queue is an advantage\n\nWhat you get in return\u2026\n\nApart from competitive salary package and benefits, in HKBN, you will work flexibly under our Talent-first culture\u00a0and we uphold Life-Work Priority. Examples of our flexible initiatives:\n\nFive-day work week and shorten working hours (8 hours including 1 hour 15 mins meal break)\nHalf Day Off Friday once a month (compensation leave for Talents who work on shift)\nHalf Day Off on Festival Eve (compensation leave for Talents who work on shift)\nUnique leaves arrangement: Family-care leave, Anniversary leave, Bonus leave, Volunteer leave, Sabbatical leave, etc.\nComprehensive medical and life insurance coverage\nUpgraded maternity leave and paternity leave\nDiscounted Talent plan offers including broadband and mobile plans and other promoted products\nEducation subsidies and Examination leave\nYear-end discretionary bonus", "employment_types": ["Full Time", "Permanent"], "selling_points": ["Design and integrate system components", "Design programming work units", "Supervise Developers and perform code review"], "locations": ["Shau Kei Wan"], "categories": ["Information Technology (IT)", "Software Development", "Application Specialist - Network", "Network & System"], "post_time": "2022-01-17T05:24:26Z", "salary": {"currency": null, "max": null, "min": null, "period": "monthly", "term": null}, "salary_visible": false, "title_keywords": ["system analyst"], "responsibilities": ["software", "budget", "external parties", "website", "design", "troubleshooting", "payment", "maintain", "plan", "liaise with", "application development", "project documentation", "other duties", "implementation", "testing", "reports", "architecture", "re-engineering", "management", "procedures", "maintenance", "policies", "analysis", "subject matter expert", "coordinate", "project management", "e-commerce platform"], "requirements": {"degrees": ["degree holder"], "majors": ["engineering", "computer science"], "languages": [], "language_level": [], "hard_skills": ["plus", "web application development", "agile", "maintenance", "e-commerce", "project management professional", "azure", "analysis", "devops", "wechat", "aws", "project management", "make", "dynamic", "documentation"], "soft_skills": ["organizational skills", "independently", "agile", "deep", "accountable", "troubleshooting", "project management", "hands-on", "dynamic", "hands on", "attention to detail", "innovative"], "languages_combined": []}, "experience_required": {"duration": ["5 years", "minimum of 6 years", "minimum of 10-15 years"], "field": ["e-commerce", "related", "development", "devops", "troubleshooting", "design", "management position", "project management", "it", "application development"]}}, {"job_id": "100003009046777", "location_code": "hk", "company": "AsiaWorld-Expo Management Limited", "job_title": "Assistant Information Technology (IT) Manager", "description": "Responsibilities\n\n\u00a0\u00a0\u00a0\u00a0\u00a0\u00a0\u00a0 Present and demonstrate IT solutions of leading brands to partners and users\n\u00a0\u00a0\u00a0\u00a0\u00a0\u00a0\u00a0 Partner with Sales team to develop business opportunities majority in enterprise network infrastructure solutions and manage presales cases closely\n\u00a0\u00a0\u00a0\u00a0\u00a0\u00a0\u00a0 Understand, analyze customer requirements by solution base selling approach to achieve business outcome\n\u00a0\u00a0\u00a0\u00a0\u00a0\u00a0\u00a0 Responsible for quality deliverables including technical proposal, solutions presentation and demonstration, proof of concept test (POC) and test report\n\u00a0\u00a0\u00a0\u00a0\u00a0\u00a0\u00a0 Good customer, vendor handling skills\n\u00a0\u00a0\u00a0\u00a0\u00a0\u00a0\u00a0 Provide deliverables for win-case with task list and high-level design as solution assurance for project implementation\n\n\u00a0Requirements\n\n\u00a0\u00a0\u00a0\u00a0\u00a0\u00a0\u00a0 Degree holder in Computer Science, Electronics, Information Engineering or related disciplines\n\u00a0\u00a0\u00a0\u00a0\u00a0\u00a0\u00a0 Cisco CCIE / CCNP / CCNA certified or equivalent.\n\u00a0\u00a0\u00a0\u00a0\u00a0\u00a0\u00a0 Have 2-3 years of experience in solution deploying and support in\u00a0Infrastructure and Networking\n\u00a0\u00a0\u00a0\u00a0\u00a0\u00a0\u00a0 Passionate in ICT technology and enthusiastic to serve as pioneer in learning advanced technology\n\u00a0\u00a0\u00a0\u00a0\u00a0\u00a0\u00a0 Good communication, interpersonal skills & team player.\n\u00a0\u00a0\u00a0\u00a0\u00a0\u00a0\u00a0 Good command of written and spoken English & Chinese.\n\u00a0\u00a0\u00a0\u00a0\u00a0\u00a0\u00a0 Self-motivated and interested to explore new technologies and solutions.", "employment_types": ["Full Time", "Permanent"], "selling_points": ["Information Technology (IT)", "IT Infrastructure", "Network, System"], "locations": ["Airport Area"], "categories": ["Information Technology (IT)", "IT Project Management / Team Lead", "Application Specialist - Network", "Network & System"], "post_time": "2022-01-14T01:01:34Z", "salary": {"currency": null, "max": null, "min": null, "period": "monthly", "term": null}, "salary_visible": false, "title_keywords": ["manager", "assistant"], "responsibilities": ["network infrastructure", "business opportunities", "quality", "implementation", "design", "develop", "sales team", "report"], "requirements": {"degrees": ["degree holder"], "majors": ["related disciplines", "engineering", "computer science"], "languages": ["english", "chinese"], "language_level": ["good command"], "hard_skills": ["ccnp", "ccna"], "soft_skills": ["passionate", "self-motivated", "advanced", "communication", "learning", "interpersonal skills", "enthusiastic", "team player"], "languages_combined": [{"language": "english", "language_level": ["good command"]}, {"language": "chinese", "language_level": ["good command"]}]}, "experience_required": {"duration": ["2-3 years"], "field": ["infrastructure"]}}, {"job_id": "100003009055968", "location_code": "hk", "company": "CL Technical Services Ltd.", "job_title": "Network Engineer (over $40K, Shatin)", "description": "Job Duties:\n\nTo provide technical support on WAN/LAN environment with specific focus on Metro-Ethernet network,\u00a0core routers, network switches, firewall appliances and load balancers;\nTo liaise with users and vendors for requirement study, implementation and on-going support activities;\nTo participate in technical specification development and proposal evaluation for new projects / enhancements;\nTo prepare test plan and conduct acceptance test;\nTo install security patches and upgrade on various hardware platforms and software applications;\nTo perform administration tasks and backup job related to various network and server platforms;\nTo update technical documents and prepare operation manual\n\nJob Requirements:\n\nHigher Diploma or above in IT related discipline\nAt least have 4 years\u2019 experience in IT field\nAt least 2 years of experience in network infrastructure support/ administration and configuration in the WAN/LAN environment\nSound knowledge in dynamic routing adopted in WAN/LAN environment\nHands on experience in firewall products\nKnowledge in Network monitoring and management tools is preferred\nPossession of certifications of CCNA or similar qualification is preferred\nIndependent, proactive and able to work under pressure\nGood communication skills\nProficient in both spoken and written English and Cantonese.\n\n\nFor more job opportunity, please visit our website: www.clts.com\n\nThe personal information collected is strictly for recruitment purpose only.", "employment_types": ["Full Time"], "selling_points": ["5 days work", "medical", "Stable working environment"], "locations": ["Shatin Area"], "categories": ["Information Technology (IT)", "Application Specialist - Network", "Network & System", "Technical / Functional Consulting"], "post_time": "2022-01-18T03:10:20Z", "salary": {"currency": null, "max": null, "min": null, "period": "monthly", "term": null}, "salary_visible": false, "title_keywords": ["engineer"], "responsibilities": ["software", "technical support", "implementation", "hardware", "plan", "evaluation", "liaise with", "administration"], "requirements": {"degrees": ["higher diploma or above"], "majors": ["it"], "languages": ["cantonese", "english"], "language_level": ["proficient"], "hard_skills": ["infrastructure support", "ccna", "dynamic", "firewall", "wan"], "soft_skills": ["communication skills", "independent", "hands on", "dynamic", "proactive", "work under pressure"], "languages_combined": [{"language": "cantonese", "language_level": ["proficient"]}, {"language": "english", "language_level": ["proficient"]}]}, "experience_required": {"duration": ["4 years", "at least 2 years"], "field": ["infrastructure", "it", "administration"]}}, {"job_id": "100003009055131", "location_code": "hk", "company": "Meyer Aluminium Ltd", "job_title": "TECHNICAL ANALYST", "description": "The appointee will report to the\u00a0System Engineering Services Manager\u00a0and is responsible for network infrastructure\u00a0planning, implementation, administration\u00a0monitoring and trouble shooting. \u00a0Your prerequisite attributes are:\n\nUniversity/Tertiary\u00a0graduate in related disciplines;\nAt least 3\u00a0years\u2019\u00a0experience in Windows Server and network configuration and administration;\nIn-depth network knowledge and solid hands-on experience in firewall, routers and switches;\nExperience in VCP is an advantage.\n\nWe offer competitive remuneration plus comprehensive fringe benefits. \u00a0Interested parties, please send full resume and salary expected to Senior Human Resources Officer, Meyer Aluminium Ltd, 5 Dai Li Street, Tai Po Industrial Estate, Tai Po, New Territories. \u00a0or clicking \"Apply Now'. \u00a0All applications will be treated in strictly confidential.", "employment_types": ["Full Time"], "selling_points": [], "locations": ["Tai Po Area"], "categories": ["Information Technology (IT)", "Application Specialist - Network", "Security", "Network & System"], "post_time": "2022-01-18T01:20:25Z", "salary": {"currency": null, "max": null, "min": null, "period": "monthly", "term": null}, "salary_visible": false, "title_keywords": ["analyst"], "responsibilities": ["network infrastructure", "configuration", "monitoring", "implementation", "planning", "report", "administration"], "requirements": {"degrees": [], "majors": [], "languages": [], "language_level": [], "hard_skills": ["windows server", "firewall"], "soft_skills": ["hands-on", "responsible"], "languages_combined": []}, "experience_required": {"duration": ["at least 3 years"], "field": ["administration"]}}, {"job_id": "100003009053843", "location_code": "hk", "company": "LSG Catering Hong Kong Ltd", "job_title": "Assistant Manager IT Network \u2013 Asia Pacific", "description": "Report directly to the Regional Director of IT, APAC, the job holder will be responsible to provide technical support and maintain IT Infrastructure in good condition.\n\n\u00a0Responsibilities:\n\nNetwork support & trouble shooting includes structure cabling, network device and servers.\u00a0\nDesktop support & trouble shooting includes software installation, configuration and setup.\nProvide support & advices in daily system administration and maintain the good condition of IT infrastructure includes WAN, LAN, Server, and Desktop.\nSystem administration on operating system level such as maintenance of user authorization, system configuration, version upgrade, system patching, server / client security and regular system backup and maintenance.\nPerform periodic system performance monitoring includes capacity utilization, system log, software update and preventive maintenance to maintain at 99.99% system availability.\nFollow the standard procedure and to ensure the compliance of corporate standard are maintained at all time.\nMaintain system documentation, testing plan and job scheduling.\nPlan and implement future network/system enhancements and upgrade/migration.\nAssist and support project deployment in the region\n\nRequirements:\n\nDegree holder in Computer Science\nHolding of MCSE and/or MCSA and CCNA certificates\nMinimum 5 years of solid experience in in both IT on-going support, and IT project management\nSolid experience in managing sizable IT infrastructures, helpdesk and end-user support\nPractical experience in Windows, Linux, TCP/IP, VPN, VLAN, WAN, Active Directory, IPT, Switch configuration, VM, Firewall, Proxy, and ITIL best practices, etc.\nExcellent analytical, problem-solving, strong communication and interpersonal skills\nProactive and service oriented, self-motivated, able to work independently and under pressure, open-minded to work in multi-cultural environment\nEffective vendor management and contract negotiation skills\nExcellent in written and spoken English and Chinese\nCandidate with less experience will be considered as Senior Network Administrator\n\nWe offer an attractive remuneration package in commensurate with the qualifications and experience to the right candidate. Interested parties please apply with full resume, present and expected salaries and availability by clicking \"Apply Now\".\n\nAll applications received will be used exclusively for employment purpose only. Applications not invited for interview within 6 weeks may consider their applications unsuccessful.\n\nFor more details, please visit our Website\u00a0https://www.lsgskychefs.com\n", "employment_types": ["Full Time", "Permanent"], "selling_points": [], "locations": ["Airport Area"], "categories": ["Information Technology (IT)", "IT Project Management / Team Lead", "Application Specialist - Network", "Network & System"], "post_time": "2022-01-17T07:36:34Z", "salary": {"currency": null, "max": null, "min": null, "period": "monthly", "term": null}, "salary_visible": false, "title_keywords": ["assistant manager"], "responsibilities": ["installation", "provide support", "software", "it infrastructure", "maintenance", "configuration", "system documentation", "monitoring", "compliance", "testing", "scheduling", "maintain", "plan", "migration", "setup", "administration"], "requirements": {"degrees": ["degree holder"], "majors": ["computer science"], "languages": ["english", "chinese"], "language_level": ["excellent"], "hard_skills": ["itil", "mcse", "linux", "firewall", "active directory", "tcp", "switch", "problem-solving", "ccna", "vendor", "project management", "ip", "vpn", "mcsa", "wan"], "soft_skills": ["self-motivated", "proactive", "work independently", "under pressure", "open-minded", "problem-solving", "project management", "negotiation skills", "communication and interpersonal skills", "active"], "languages_combined": [{"language": "english", "language_level": ["excellent"]}, {"language": "chinese", "language_level": ["excellent"]}]}, "experience_required": {"duration": ["minimum 5 years"], "field": ["project management", "it"]}}, {"job_id": "100003009052963", "location_code": "hk", "company": "NexLen International Limited", "job_title": "Technical Consultant / Pre-Sales Consultant (Network and Cybersecurity)", "description": "Job Description\n\nConduct pre-sales and consultative activities\nUnderstand and translate business and functional requirements into solution proposals, presentations, and scope of work\nResponsible for network and cybersecurity area, provide consultancy and solution to sales team and customers\nJob Requirement\n3 years' solid working experience in network and cybersecurity Pre-sales Consultancy\nLogical, positive thinking, hard working and enjoy teamwork\nGood interpersonal and communication skills\nGood team player, target-oriented with strong analytical and problem solving skills\nCISSP, CCNA/ CCNP is\u00a0preferable\n\n\nWe offer attractive salary and fringe benefit package to the right candidate. Interested parties please send full resume with expected salary.\n\nPersonal data provided in your application will be kept in the strictest confidence. It will be used for employment-related purposes. Applications not notified within 1 month will be considered as unsuccessful. Unsuccessful application may be kept for another 3 months for new openings before properly shredded.", "employment_types": ["Full Time"], "selling_points": ["Attractive salary package", "Customer orientated, provide network and cybersecu", "Provide network and cybersecurity consultancy"], "locations": ["Kwun Tong"], "categories": ["Information Technology (IT)", "Product Management / Business Analyst", "Application Specialist - Network", "Security"], "post_time": "2022-01-17T04:42:32Z", "salary": {"currency": null, "max": null, "min": null, "period": "monthly", "term": null}, "salary_visible": false, "title_keywords": ["sales consultant", "consultant"], "responsibilities": ["sales team", "presentations"], "requirements": {"degrees": [], "majors": [], "languages": [], "language_level": [], "hard_skills": ["problem solving skills", "ccna", "ccnp"], "soft_skills": ["communication skills", "good team player", "hard working", "teamwork", "positive thinking", "analytical and problem solving skills", "interpersonal"], "languages_combined": []}, "experience_required": {"duration": ["3 years"], "field": []}}, {"job_id": "100003009055313", "location_code": "hk", "company": "Wellesley Associates Limited", "job_title": "Senior Manager, Network Infrastructure - Financial Services/Inhouse \u2013 65-75+K + 2-3 months Bonus", "description": "Background:\u00a0My client is one of the top-tier financial services firms in Hong Kong who is now looking for an experienced Senior Network Manager to join their team.\n\nDuties\n\n\nHave overall responsibility for the development and on-going management and support of Group IT Network Infrastructure\nTo build a deep understanding of key business areas around the region to plan, develop and implement Network infrastructure solutions that will deliver corporate and service specific objectives and meet the strategic priorities of the BU\nSupervise the Network Operation Support Team for Cloud infrastructure Integration, Migration and BAU Support.\nManage, design, and architect On-Premise and Cloud Network and Data Centre infrastructure\nEvaluates New IT Network products or services and suggests changes to existing products or services to better aide the end user\nSupport IT Network Infrastructure Setup & Network Integration/Separation of New business entity\nLiaise with IT application, infra and security architect on the technical development of converged solutions and process to enhance the operations of services\nLead a team with managers and Technical engineers to negotiate with vendors, auditors, consultants.\u00a0\nLead the Network Infrastructure team for management and support of Group IT Network and services availability, capacity and critical support for business system and ensure the service is meet SLA Standard\nLead the Network team to manage and support IT infrastructure projects\nLead the Network Operation Team to support the migration and operation support.\nEnsure the IT Network infrastructure are fulfil compliance/security requirement\nTechnical Evaluation of Network solution, latest technology and management tools on Cloud environment\nAssists in conducting DR Drill and BCP process\nAssist in Vendor and Contract Management to support IT Network infrastructure\n\nRequirements:\n\n\nDegree holder in Computer Science / Information Technology or equivalent with more than 15 years of relevant experience which 6-8 years in managerial level\nITIL foundation certification with relevant experience in this area\nHolder of professional qualification(s) preferred, e.g. Cisco, Checkpoint, Azure, AWS Certification, but not a must\u00a0\nSolid experience in network administration with Strong Knowledge in LAN/MAN/WAN/SD-WAN/Cloud Network Architecture (AWS & AWS), Micro-Segmentation Firewall, Router/Switch, Wireless LAN, VPN, IPS, WAF, SLB, Network Management, Performance Monitoring and Automation Tools\nStrong problem solving, management and analytical skills with in-depth knowledge of Regional Datacentre and Cloud Network Infrastructure, DR Management and Security.\nStrong knowledge on various vendor products such as Cisco, Checkpoint, Palo alto, Imperva, F5, Riverbed, Megaport, MPLS and SDWAN solution. (Either 2 of the following)\u00a0\nGood command of written English and Chinese; fluent in spoken English\n\nIf you are interested in this position, please apply online by submitting your latest CV in Word format including current & expected salary. Kindly note that only shortlisted candidates will be notified.", "employment_types": ["Full Time"], "selling_points": ["FS Group Level In-House", "Senior Manager, Network Infrastructure", "65-75K + 2-3 months Bonus"], "locations": ["Not Specified"], "categories": ["Information Technology (IT)", "Hardware", "Application Specialist - Network", "Network & System"], "post_time": "2022-01-18T02:08:56Z", "salary": {"currency": null, "max": null, "min": null, "period": "monthly", "term": null}, "salary_visible": false, "title_keywords": ["senior manager"], "responsibilities": ["network infrastructure", "management", "it infrastructure", "data", "operations", "infrastructure", "compliance", "contract management", "design", "develop", "lead a team", "network integration", "security requirement", "plan", "evaluation", "liaise with", "migration", "setup"], "requirements": {"degrees": ["degree holder"], "majors": ["computer science", "information technology"], "languages": ["english", "chinese"], "language_level": ["good command", "fluent"], "hard_skills": ["itil", "network administration", "network management", "azure", "switch", "vendor", "word", "aws", "router", "problem solving", "analytical skills", "sd-wan", "vpn", "firewall", "wan"], "soft_skills": ["problem solving", "interested in", "analytical skills"], "languages_combined": [{"language": "english", "language_level": ["fluent", "good command"]}, {"language": "chinese", "language_level": ["fluent", "good command"]}]}, "experience_required": {"duration": ["6-8 years", "15 years"], "field": ["network administration", "managerial", "management", "information technology", "relevant experience"]}}, {"job_id": "100003009055784", "location_code": "hk", "company": "Links International", "job_title": "Mobile Developer", "description": "Our partner who specializes in AI, Blockchain, and IoT solutions, is urgently seeking for mobile developers to join their growing team. This role will primarily focus on mobile applications development and their integration with backend services. You will also be working along-side other global engineers and developers on different layers of the infrastructure. Thus, communication and commitment to collaborative problem-solving, sophisticated design, and adopted key technology is essential.\n\nResponsibilities\n\nDevelop mobile applications and their integration with backend services\nTranslate designs and wireframes into high quality code\nDesign, build, and maintain high performance, reusable, and reliable code along with requirement specification\nEnsure the best possible performance, quality, and responsiveness of the application\nDevelopment and maintenance of applications aimed at a vast number of diverse mobile devices\nWork along-side other IT teams on different layers of infrastructure\nResolve tough technical issues of mobile OS system\nAct as an independent problem solver, identify and correct bottlenecks and fix bugs, help maintain code quality, organization, and automation\nAssist to maintain business as usual operations of customers, perform desktop support duties (e.g. computer installation, hardware/software configurations on desktop, laptop, mobile devices)\nPerform systems and network monitoring, and routine hardware/software maintenance\nParticipate in design, develop, preparation of projects (e.g. cloud migration)\n\nRequirements\n\nDegree graduate or above in Computer Science, Information Technology or relevant discipline\nMinimum 2 years object-oriented software development experience, especially in mobile/web application\nKnowledge of Android SDK and iOS development platform including different mobile devices versions and how to deal with various screen sizes\nFamiliar with RESTful APIs and strong knowledge of mobile UI design principles, patterns, and best practices\nExperience with offline storage, threading, and performance tuning\nKnowledge of open-source Android ecosystem, iOS ecosystem, and the libraries available for common tasks\nKnowledgeable with O2O application development, familiar with cloud message APIs and push notifications\nGood understanding of Linux OS, Windows OS, Office 365 Microsoft Application Active Directory, Exchange, MS Teams, etc.\nKnowledge in server, VMWare, OC, TCP/IP, HTTPS and LAN/WAN networking equipment\nKnowledge in SQL (MS SQL, Oracle DB), Oracle Forms and Report\nPatching, Hardware, Software, and OS troubleshooting\nQuick learner, willing to learn new technologies especially new mobile OS platform\nCan work under pressure and independently\nFluency in spoken and written English and Chinese (Mandarin & Cantonese)\nCandidates with lesser experience will be considered for Jr. role\nFresh graduates are welcome", "employment_types": ["Full Time", "Permanent"], "selling_points": ["2 days work from home", "Hands-on mobile applications development", "Participate in projects using latest technologies"], "locations": ["Not Specified"], "categories": ["Information Technology (IT)", "Application Specialist - Software", "Software Development", "Application Specialist - Network"], "post_time": "2022-01-18T02:56:52Z", "salary": {"currency": "HKD", "max": 44999, "min": 35000, "period": "monthly", "term": null}, "salary_visible": true, "title_keywords": ["developer"], "responsibilities": ["installation", "software", "maintenance", "operations", "infrastructure", "quality", "teams", "design", "develop", "systems", "hardware", "monitoring", "maintain", "mobile devices", "migration"], "requirements": {"degrees": ["degree"], "majors": ["computer science", "information technology"], "languages": ["cantonese", "english", "chinese", "mandarin"], "language_level": ["fluency"], "hard_skills": ["linux", "office 365", "oracle", "vmware", "android sdk", "web", "active directory", "tcp", "sql", "mobile", "ip", "os", "hardware", "server", "wan", "ms sql", "android", "exchange"], "soft_skills": ["independently", "willing to learn", "troubleshooting", "quick learner", "active", "work under pressure"], "languages_combined": [{"language": "cantonese", "language_level": ["fluency"]}, {"language": "english", "language_level": ["fluency"]}, {"language": "chinese", "language_level": ["fluency"]}, {"language": "mandarin", "language_level": ["fluency"]}]}, "experience_required": {"duration": ["minimum 2 years"], "field": ["software development"]}}, {"job_id": "100003009055435", "location_code": "hk", "company": "Welend Limited", "job_title": "Network and Security Team Lead", "description": "WeLab is a leading fintech company in Asia, \u00a0which operates one of first licensed digital banks in Asia \u2013 WeLab Bank, as well as multiple leading online financial services businesses including WeLend and WeLab Bank in Hong Kong, WeLab Digital (\u6211\u6765\u6570\u79d1), Taoxinji (\u6dd8\u65b0\u673a), Wallet Gugu (\u94b1\u5939\u8c37\u8c37) and Tianmian Tech (\u5929\u5195\u79d1\u6280)\u00a0in Mainland China and Maucash in Indonesia. WeLab aims to bring joy to everyone\u2019s financial journey. We strive to improve people\u2019s lives by reinventing financial services through game-changing technology. We put our people first, whether it\u2019s our customers or our employees.\nWe are an energetic and passionate team that can deliver and execute. We are looking for other intellectually curious, open-minded and smart-working individuals who are just as passionate as we are about making financial services enjoyable. Now you have the opportunity to join us on our journey to achieve our vision and be part of building a better financial future for everyone.\nAbout you:\nYou're a go-getter with mad juggling skills (or multiple hats) who can thrive in a fast-paced, agile environment\nYou have a strong thirst for knowledge and are driven to find solutions that don't exist yet\nYou are comfortable with ambiguity and extremely resourceful (in your past life you could've been a detective)\nYou always find a way to get things done without sacrificing the quality of your work, integrity and values. No task is off limits for you.\nYou are humble and prioritize the success of the team over your own with an eagerness to help those around you\nYou don't shy away from challenges and have the ability to bounce back from setbacks\nWhat you\u2019ll do and what success looks like in this role\nResponsible for evaluation, moderation, formation, planning, design, implementation, monitoring for IT infrastructure projects.\nParticipate and help in internal and external auditors, business continuity planning, disaster recovery and other security related activities.\nDefine, execute and report on IT infrastructure, network and security procedures and standards.\nMonitoring, reporting and applying system/security patches and system upgrades.\nHelp to define and implement IT Infrastructure roadmap and strategy formulation.\nCollaborate with key business and IT stakeholders to define IT Infrastructure solutions and security standards according to business requirements and align with the company\u2019s long term strategies\nDefine infrastructure and network architecture standards, maintain design guidelines, technology roadmap and strategies, principles\nWork under company defined quality and security standards. Adhere to all established risk control guidelines, procedures and measures to identify, assess, report, mitigate and monitor the risks involved in the day-to-day work\nMaintain daily operation and support to users\nExplore new technology and perform proof of concept\nPerform user support and security awareness training\nProvide supervision and guidance to team members\nWhat is required and what we\u2019re looking for\nDegree or above in Computer Science, IT or related discipline\nMinimum 5 years of IT experience preferably in the financial sector with proven experience in IT architecture design, Network and Security operations\nExtensive technical knowledge in IT Infrastructure, including cloud, network and security areas\nSound knowledge in IT security, performance tuning, capacity planning, storage, and networking\nGood analytical, communication and problem solving skills\nExperience with managing and leading small team\nHolder of CISSP/CISA certification is preferred\nGood command of both spoken and written Chinese and English\nWeLab perks:\nCompetitive salary\nLearning and development stipend, because we value lifelong learning and believe the best way to invest in our employees is to encourage them to continue to learn\nWork hard and laugh lots (chicken wings and french toast, etc.) with a high-performing, fun and diverse team\nHappiness Dollars for spending on anything that makes you happy\nCoffee stipend\nConveniently located office surrounded by diverse and delicious lunch options\nLively office with gaming consoles and a ping pong table\nFun extracurricular activities with your colleagues like hiking, yoga, badminton, wine tasting, dragon boat racing, rock climbing, etc.\nEmployee referral bonuses\nAwards & recognition:\nFinancial Times (FT) 2020 Asia-Pacific High-Growth Companies \u2013 #2 ranked company\n2020 CNBC Disruptor 50 List - #11, only company included from Hong Kong and just one of five from Asia\nWe offer competitive salary package to the successful candidate.\u00a0If you are interested in joining this exciting team, please apply with resume via the \"Apply\" button below.\nAll information provided by applicants will be used for recruitment purposes only. Information of unsuccessful applicants will be destroyed within 24 months of receipt.\u00a0", "employment_types": ["Full Time", "Permanent"], "selling_points": ["Responsible for IT infrastructure projects", "Help internal and external security related events", "Define, execute and report on IT infrastructure"], "locations": ["Quarry Bay"], "categories": ["Information Technology (IT)", "IT Project Management / Team Lead", "Application Specialist - Network", "Security"], "post_time": "2022-01-18T02:34:51Z", "salary": {"currency": null, "max": null, "min": null, "period": "monthly", "term": null}, "salary_visible": false, "title_keywords": ["lead"], "responsibilities": ["collaborate with", "business continuity", "operations", "quality", "design", "communication", "maintain", "planning", "evaluation", "control", "it infrastructure", "infrastructure", "monitor", "implementation", "architecture", "report", "reporting", "guidance", "upgrades", "monitoring", "procedures", "guidelines", "daily operation", "provide supervision", "external auditors"], "requirements": {"degrees": ["degree or above"], "majors": ["it", "computer science"], "languages": ["english", "french", "chinese"], "language_level": ["good command"], "hard_skills": ["small", "no", "joy", "agile", "fun", "system upgrades", "problem solving skills", "go", "mad"], "soft_skills": ["passionate", "agile", "resourceful", "responsible", "open-minded", "integrity", "prioritize", "communication", "diverse", "learning", "problem solving skills", "energetic", "extensive", "driven"], "languages_combined": [{"language": "english", "language_level": ["good command"]}, {"language": "french", "language_level": []}, {"language": "chinese", "language_level": ["good command"]}]}, "experience_required": {"duration": ["minimum 5 years"], "field": ["design", "it experience", "it", "security", "team", "financial"]}}, {"job_id": "100003009052488", "location_code": "hk", "company": "GrammyTech Ltd", "job_title": "System Analyst", "description": "Job Responsibilities:\n\nResponsible for system analysis and application development\nMonitor the system and provide maintenance support for current systems\nResponsible for system rollout, deployment and operation support\u00a0\nConduct SIT, UAT, system and software testing\n\nJob Requirements:\n\nDegree holder in Computer Science, Engineering or equivalent\nProficient in C#.NET is preferred\nExperience with using enterprise DMS/EDMS package is preferred;\nImmediate available is an advantage.\n\n\n\nInterested parties, please send your full resume in word format together with salary expectation to katherineli @grammytech.com\n\n(All data collected would be used for recruitment purposes only)", "employment_types": ["Full Time"], "selling_points": ["IT Project", "System Analysis", "Good Career Progression"], "locations": ["Kwun Tong Area"], "categories": ["Information Technology (IT)", "Application Specialist - Network", "Security", "Network & System"], "post_time": "2022-01-17T03:10:29Z", "salary": {"currency": null, "max": null, "min": null, "period": "monthly", "term": null}, "salary_visible": false, "title_keywords": ["system analyst"], "responsibilities": ["uat", "software", "maintenance support", "analysis", "systems", "monitor", "testing", "application development"], "requirements": {"degrees": ["degree holder"], "majors": ["engineering", "computer science"], "languages": [], "language_level": [], "hard_skills": ["c#"], "soft_skills": [], "languages_combined": []}, "experience_required": {"duration": [], "field": []}}, {"job_id": "100003009055043", "location_code": "hk", "company": "Generali Life (Hong Kong) Limited", "job_title": "IT Security Assistant Manager", "description": "Job Description\nWith ever increasing growth and expansion, we looking for a new IT Security Assistant Manager to join our InfoSec team. Ideally, this technical hand-on security person has worked an enterprise environment, where they would be responsible for on-going security management, threat assessment, testing, deployment and vendor management.\n\nKey Responsibilities:\nSecurity operation and BAU support as below:\n\nRespond for Internal / 3rd party security risk assessments\nPerform Vulnerability assessments (Qualys or Nessus) and handle the daily news feeds,\nCoordinate 3rd party Vendor to do penetration tests (Knowledge of kaliLinux or Metasploit or OWASP is a plus),\nIn charge of the Identity and password access management tools and control (CyberArk),\nPromote security awareness training and practices for the organization,\nongoing improvement on FortiSIEM rules\nHandle security alerts generated from Crowdstrike, Mcafee and SOC\nCollect KPI/KRI data and report monthly to Group\n\nMinimum Requirements:\n\n5 years of technical information security experience\nProfessional certification in of CISSP, CEH, CISA, CRISC or CISM equivalent\nUniversity degree in Computer Science, Information Systems or other technology-related disciplines\nFluent in both spoken and written English and Chinese\n\nKnowledge with the below Security tools is highly preferred:\n\nSecurity technology expertise in vulnerability assessments (Qualys or Nessus), penetration tests (KaliLinux or Metasploit), identity and password access management control (CyberArk), SIEM (FortiSIEM/Splunk,) CIS (hardening) Firewall (PaloAlto, Fortinet), AntiDDoS & WAF (Cloudflare), Endpoint (Crowdstrike, Mcafee, ManageEngine Central Desktop Manage).\nKnowledge in COBIT 5, NIST or ISO27001 framework\nEnterprise financial institution exposure (insurance or banking)\nExposure to similar security tools would also be considered\n\nFor strong candidates with less experience, they will be considered for an IT Security Specialist position.", "employment_types": ["Full Time", "Permanent"], "selling_points": [], "locations": ["Tai Koo"], "categories": ["Information Technology (IT)", "Application Specialist - Network", "Security", "Network & System"], "post_time": "2022-01-18T00:49:18Z", "salary": {"currency": null, "max": null, "min": null, "period": "monthly", "term": null}, "salary_visible": false, "title_keywords": ["assistant manager"], "responsibilities": ["management", "control", "data", "testing", "coordinate", "security operation", "report"], "requirements": {"degrees": ["university degree"], "majors": ["related disciplines", "computer science"], "languages": ["english", "chinese"], "language_level": ["fluent"], "hard_skills": ["firewall"], "soft_skills": [], "languages_combined": [{"language": "english", "language_level": ["fluent"]}, {"language": "chinese", "language_level": ["fluent"]}]}, "experience_required": {"duration": ["5 years"], "field": ["it", "security"]}}, {"job_id": "100003009056023", "location_code": "hk", "company": "Gemini Executive Search & Selection", "job_title": "Senior / Cloud Engineer", "description": "Our client is a top tier ICT company and they are now looking for an Assistant Manager/Manager to lead one of their consultant team.\n\nResponsibilities\n\nDesign & architect the implementation of cloud solution using AWS, Alibaba Cloud, Microsoft Azure, advise customers on various cloud solution options & recommend a solution that aligns with business customer needs\nEngage in the AWS Services Configuration Management, Cloud Automation and Design for the AWS platform and applications\nResponsible to build Cloud infrastructure as a code (CDK, Terraform, Ansible) capability by planning and implementation of the cloud platform\nArchitect level of AWS cloud, Alibaba Cloud, Azure is a plus\nPerform system and network, design, implementation, monitoring, capacity management, security operations, and support in AWS, Alibaba Cloud, Microsoft Azure environment\nWork with the business and technical stakeholders on explaining the technical solutions\n\nRequirements\n\nBachelor\u2019s degree in IT-related, Computer Science discipline\u00a0\n2+ years of experience in Cloud computing technologies, concepts, and Cloud consulting, in the areas of Public Cloud , Private Cloud, Hybrid Cloud, Global Cloud technologies in AWS, Alibaba Cloud and Azure Cloud\nAcquired AWS Solution Architect Professional Certificate, specialty certificate in security and network is a plus\nCertificate in Alibaba Cloud, Azure and Google Cloud is a plus\nExperience with Cloud Automation & configuration management\nExperience with Cloud platform operations including system, network, and security monitoring\u00a0\nGood Communications skills in English\u00a0\nTalents with more experience will be considered Senior Cloud Engineer", "employment_types": ["Full Time", "Permanent"], "selling_points": ["AWS/Azure/AliCloud Service Configure Management", "2+ year on the cloud computing platform", "Certificate in Alibaba Cloud, Azure & Google Cloud"], "locations": ["Central & Western Area"], "categories": ["Information Technology (IT)", "Application Specialist - Network", "Network & System"], "post_time": "2022-01-18T03:11:57Z", "salary": {"currency": null, "max": null, "min": null, "period": "monthly", "term": null}, "salary_visible": false, "title_keywords": ["engineer"], "responsibilities": ["management", "configuration", "operations", "infrastructure", "monitoring", "implementation", "design", "planning"], "requirements": {"degrees": ["certificate", "degree", "bachelor"], "majors": ["it", "computer science"], "languages": ["english"], "language_level": ["good"], "hard_skills": ["computing technologies", "plus", "azure", "aws"], "soft_skills": [], "languages_combined": [{"language": "english", "language_level": ["good"]}]}, "experience_required": {"duration": ["2+ years"], "field": ["management", "security", "consulting"]}}, {"job_id": "100003009051194", "location_code": "hk", "company": "Kingvisions Consultants Limited", "job_title": "Pre-sales Engineer/ Solution Consultant (Networking & Security)", "description": "Responsibilities\n\n\u00a0\u00a0\u00a0\u00a0\u00a0\u00a0\u00a0 Present and demonstrate IT solutions of leading brands to partners and users\n\u00a0\u00a0\u00a0\u00a0\u00a0\u00a0\u00a0 Partner with Sales team to develop business opportunities majority in enterprise network infrastructure solutions and manage presales cases closely\n\u00a0\u00a0\u00a0\u00a0\u00a0\u00a0\u00a0 Understand, analyze customer requirements by solution base selling approach to achieve business outcome\n\u00a0\u00a0\u00a0\u00a0\u00a0\u00a0\u00a0 Responsible for quality deliverables including technical proposal, solutions presentation and demonstration, proof of concept test (POC) and test report\n\u00a0\u00a0\u00a0\u00a0\u00a0\u00a0\u00a0 Good customer, vendor handling skills\n\u00a0\u00a0\u00a0\u00a0\u00a0\u00a0\u00a0 Provide deliverables for win-case with task list and high-level design as solution assurance for project implementation\n\n\u00a0Requirements\n\n\u00a0\u00a0\u00a0\u00a0\u00a0\u00a0\u00a0 Degree holder in Computer Science, Electronics, Information Engineering or related disciplines\n\u00a0\u00a0\u00a0\u00a0\u00a0\u00a0\u00a0 Cisco CCIE / CCNP / CCNA certified or equivalent.\n\u00a0\u00a0\u00a0\u00a0\u00a0\u00a0\u00a0 Have 2-3 years of experience in solution deploying and support in\u00a0Infrastructure and Networking\n\u00a0\u00a0\u00a0\u00a0\u00a0\u00a0\u00a0 Passionate in ICT technology and enthusiastic to serve as pioneer in learning advanced technology\n\u00a0\u00a0\u00a0\u00a0\u00a0\u00a0\u00a0 Good communication, interpersonal skills & team player.\n\u00a0\u00a0\u00a0\u00a0\u00a0\u00a0\u00a0 Good command of written and spoken English & Chinese.\n\u00a0\u00a0\u00a0\u00a0\u00a0\u00a0\u00a0 Self-motivated and interested to explore new technologies and solutions.", "employment_types": ["Full Time", "Permanent"], "selling_points": ["Join-in bonus provided!! Same as yr end bonus!!", "1-3 yrs in solution briefing, deploying & support", "Engineer experience also welcome!"], "locations": ["Wan Chai Area"], "categories": ["Information Technology (IT)", "Application Specialist - Network", "Network & System", "Technical / Functional Consulting"], "post_time": "2022-01-15T04:34:40Z", "salary": {"currency": "HKD", "max": 54999, "min": 25000, "period": "monthly", "term": null}, "salary_visible": true, "title_keywords": ["consultant", "sales engineer"], "responsibilities": ["network infrastructure", "business opportunities", "quality", "implementation", "design", "develop", "sales team", "report"], "requirements": {"degrees": ["degree holder"], "majors": ["related disciplines", "engineering", "computer science"], "languages": ["english", "chinese"], "language_level": ["good command"], "hard_skills": ["ccnp", "ccna"], "soft_skills": ["passionate", "self-motivated", "advanced", "communication", "learning", "interpersonal skills", "enthusiastic", "team player"], "languages_combined": [{"language": "english", "language_level": ["good command"]}, {"language": "chinese", "language_level": ["good command"]}]}, "experience_required": {"duration": ["2-3 years"], "field": ["infrastructure"]}}, {"job_id": "100003009051485", "location_code": "hk", "company": "Tech Advance Consultancy Limited", "job_title": "Junior Data Center Operator (7x24 Shift)", "description": "\nJobs Duties:\n\nProvide Technical Support services including: Data Centre operations, equipment maintenance and service provisioning\nProvide technical support services including fault reporting, troubleshooting, cable testing, equipment installation for external customers\nInstall and uninstall customer connectivity service, including circuit testing and labeling\nProvide training workshops to new or junior team member\nPerform cross connect related audit duties, record validation and housekeeping work\nManage MMR expansion projects such as frame installation, fiber runner / cable ladder installation and pre-wire cabling work\nSupport for local networking devices (Cisco / Juniper / Brocade / H3C)\nIncident handling, problem troubleshooting and escalation to upper tier\nMaintain accurate records, document all problems, and prepare reports\nExhibit quality workmanship on all work\nManage multiple concurrent interdisciplinary projects and ability to work in a team\nDelivery of operation reports, management report and customer report\nEnsure compliance with operation rules in managing customers' equipment\n\nRequirements:\n\nWilling to perform 7 x 24 shift duty\nCustomer focus with good communications and interpersonal skills\nGood presentation skills and problem solving skills\nDiscipline, self-initiative, self-motivate\nHands-on experience in hotline support and data center operations is preferred.\nWorking experience in data center operation / technical support / hotline support is preferred\nImmediately available will be advantage\nFresh Graduates are Welcome", "employment_types": ["Full Time", "Contract"], "selling_points": ["Fresh Graduates are Welcome", "Good job opportunities", "Career developments"], "locations": ["Southern Area"], "categories": ["Information Technology (IT)", "Support", "Application Specialist - Network", "Network & System"], "post_time": "2022-01-16T04:12:37Z", "salary": {"currency": null, "max": null, "min": null, "period": "monthly", "term": null}, "salary_visible": false, "title_keywords": ["operator", "junior"], "responsibilities": ["provide training", "reporting", "installation", "maintenance", "data", "technical support", "operations", "housekeeping", "quality", "troubleshooting", "audit", "testing", "ensure compliance", "maintain", "reports", "prepare reports", "management report", "report"], "requirements": {"degrees": [], "majors": [], "languages": [], "language_level": [], "hard_skills": ["focus", "problem solving skills"], "soft_skills": ["presentation skills", "hands-on", "interpersonal skills", "self-initiative", "customer focus", "problem solving skills"], "languages_combined": []}, "experience_required": {"duration": [], "field": ["operation"]}}, {"job_id": "100003009055308", "location_code": "hk", "company": "Wellesley Associates Limited", "job_title": "Infrastructure Assistant Manager - O365 Cloud - Financial Services/MNC - 45-55K + Bonus", "description": "Background:\u00a0My client is one of the top-tier Financial Services firms in Hong Kong who is now looking for an experienced candidate with solid O365 experience to join their team.\n\n\nDuties\n\n\nHave overall responsibility for the development and on-going management of MS O365 and Messaging Infrastructure and support Group IT platform and shared services\nAssist in Managing and Design the Microsoft O365, Corporate Directory Services and Integration of 3rd party\u2019s technology solution.\nSupport cloud adoption with the cloud operation and delivery team aligning to the Technology Strategy\nSupport IT Infrastructure/System setup & migration for new business entity\nLiaise with IT application, application architect and security team on the technical development of converged solutions and process to enhance the operations of services\nTechnical Evaluation of latest IT technology and management tools on Microsoft O365 environment\nLead Technical engineers to negotiate with vendors, auditors, consultants.\nEnsure the managed IT infrastructure are fulfil compliance/security requirement\nAssists in conducting DR Drill and BCP process\n\nRequirements:\n\n\nDegree holder in Computer Science / Information Technology or equivalent with\n5-10 years of relevant experience which 2 years in managerial level (Team/People management experience)\nSolid experience in MS O365, Active Directory Services, MS Exchange, MDM, SCCM, Cloud infrastructure (Azure & AWS), HCI, VMware, SAN Storage Management, SSL Cert Management & Encryption technology, Backup & Disaster Recovery Solution\nStrong problem solving, management and analytical skills with in-depth knowledge of O365, Messaging, Server, Network, DR Management, etc\n\nStrong knowledge in Infrastructure Architecture.\nGood command of written and spoken English and Chinese\n\nIf you are interested in this position, please apply online by submitting your latest CV in Word format including current & expected salary. Kindly note that only shortlisted candidates will be notified.", "employment_types": ["Full Time"], "selling_points": ["O365/ Cloud (AWS/Azure)", "Inhouse Financial Services", "45-55K + 2-3 months Bonus"], "locations": ["Not Specified"], "categories": ["Information Technology (IT)", "IT Management", "Application Specialist - Network", "Network & System"], "post_time": "2022-01-18T02:08:01Z", "salary": {"currency": null, "max": null, "min": null, "period": "monthly", "term": null}, "salary_visible": false, "title_keywords": ["assistant manager"], "responsibilities": ["management", "it infrastructure", "operations", "infrastructure", "compliance", "design", "security requirement", "evaluation", "liaise with", "migration", "setup"], "requirements": {"degrees": ["degree holder"], "majors": ["computer science", "information technology"], "languages": ["english", "chinese"], "language_level": ["good command"], "hard_skills": ["o365", "azure", "vmware", "active directory", "sccm", "word", "aws", "problem solving", "analytical skills", "server", "exchange"], "soft_skills": ["problem solving", "active", "interested in", "analytical skills"], "languages_combined": [{"language": "english", "language_level": ["good command"]}, {"language": "chinese", "language_level": ["good command"]}]}, "experience_required": {"duration": ["2 years", "5-10 years"], "field": ["managerial", "management", "disaster recovery", "people management", "cloud infrastructure", "relevant experience", "team"]}}, {"job_id": "100003009049468", "location_code": "hk", "company": "ISS Facility Services Limited", "job_title": "IT Helpdesk Support (Job Ref: ADV/22/013)", "description": "Responsibilities\n\nProvide day-to-day support on troubleshooting, maintenance, network infrastructure, mobile applications, web services, end-user, Microsoft 365, and helpdesk support\nAssist to monitor all network, security, and computer systems to meet the organization's business needs and future development\nAssist to maintain the organization's LAN / WAN / WiFi environment and server systems\nIdentify, analyze, resolve network problems, performance issues and computer resources allocation\nHandle installation of hardware and software as well as maintain software / hardware inventory, process renewal, maintenance, and subscription\nPerform ad hoc duties as assigned\n\nRequirements\n\nDiploma holder in Computer Science, Information Technology, or related disciplines\nMinimum 1-2 years\u2019 experience in networking administration / Microsoft 365, Systems support and LAN / WAN / WiFi management\nExperience of monitoring datacenter / Windows domain server / VMWare perform / IT security or site management is preferred\nSound knowledge in TCP/IP, DNS, DHCP, Cloud service and VPN networks\nCertification in ITIL is preferred but not a must\nProactive, detail-minded, problem solving skills and sensitive to business priorities\nGood command of both spoken & written English & Chinese\nExcellent interpersonal and communication skills to work with both internal stakeholders & external vendors\nImmediately available is an advantage\nFresh graduates are welcomed\n\nWe offer professional development opportunities, attractive remuneration and fringe benefits to the right candidate.\u00a0 Interested parties please send a detailed resume, current/expected salary, contact number and the job reference no \u201cADV/22/013\u201d via \"Apply Now\".\n\nInformation provided by applicants will only be used for recruitment related purposes and will be handled confidentially by authorized personnel.\u00a0 All personal data of unsuccessful candidates will be destroyed after three months from the date of applications.", "employment_types": ["Full Time"], "selling_points": ["Provide day-to-day helpdesk support", "Identify, analyze, resolve network problems", "Fresh graduates are welcomed"], "locations": ["Not Specified"], "categories": ["Information Technology (IT)", "Support", "Application Specialist - Network", "Network & System"], "post_time": "2022-01-14T08:44:33Z", "salary": {"currency": null, "max": null, "min": null, "period": "monthly", "term": null}, "salary_visible": false, "title_keywords": [], "responsibilities": ["network infrastructure", "installation", "ad hoc duties", "software", "maintenance", "inventory", "systems", "monitor", "computer systems", "troubleshooting", "hardware", "maintain"], "requirements": {"degrees": ["diploma holder"], "majors": ["related disciplines", "computer science", "information technology"], "languages": ["english", "chinese"], "language_level": ["good command"], "hard_skills": ["itil", "vmware", "dns", "tcp", "ip", "vpn", "server", "problem solving skills", "wan"], "soft_skills": ["detail-minded", "communication skills", "sensitive to", "problem solving skills", "proactive", "interpersonal"], "languages_combined": [{"language": "english", "language_level": ["good command"]}, {"language": "chinese", "language_level": ["good command"]}]}, "experience_required": {"duration": ["minimum 1-2 years"], "field": ["management", "it", "security", "administration"]}}, {"job_id": "100003009049724", "location_code": "hk", "company": "Pathos Consultancy Limited", "job_title": "Senior Network Engineer Perm - $48k", "description": "The Company\nOur client is one of the largest Chinese Investment Banks in Hong Kong. Currently expanding their infrastructure team and looking for Server and Network support.\u00a0\n\nThe Role\u00a0\n\nHandle daily operations on network and security;\nHandle network and security equipment installation and configuration;\nHandle troubleshooting, incident support, and coordination with service partner and carriers;\nProvide onsite support for among HK office and remote support for CN offices;\nWork closely with application and Helpdesk team to prepare applications and service roll-out;\nResearch on new information technology and perform product evaluation with vendors;\nHandle and support user side scheduled and ad hoc requests;\nAssist in suggesting and implementing improvement solution on daily internal and user operations;\nOther IT related ad-hoc tasks when needed.\u00a0\n\nYour Profile\n\n\nBachelor degree in Information Technology, Computer Science or related disciplines;\nIT certification holder such as CCNA, CCNP or equivalent is preferable;\nMinimum 5 years practical experience in IT infrastructure. Candidate with less experience will also be considered as junior role;\nSolid Hands-on experience in Cisco router and switch; reputable firewall (e.g. CheckPoint, Fortigate, Palo Alto etc.), WIFI etc.;\nKnowledge of VLANs, routing, switching, IPSec VPN, and IPv4/IPv6 addressing;\nExperience of administrate security related systems and related products such as IDS, IPS, WAF, EDR, UEBA, SIEM and NAC etc is added advantage;\nExperience of build and maintain data center for Financial Services with Cloud Services like AliCloud, Huawei Cloud, AWS etc is added advantage;\nExperience in using issue tracking systems, network monitoring system is added advantage;\nExposure to different IT infrastructure and vendor products;\nGood analytical mind, problem solving and communication skills;\nTeam player, responsible, independent, self-starter, motivated, multitasking and able to take initiative to get projects completed;\nGood spoken and writing in Mandarin; knowledge of Cantonese/English is a plus.\u00a0\n\nApply Today\nTo apply online (Word attachment only), please click the 'Apply' button. Interested parties please apply with the most updated CV with expected salary and available date via JobsDB. Applicants who do not hear from us within 2 weeks may consider their applications unsuccessful.\u00a0\n\nAbout Pathos\nWe are Pathos Consultancy Limited, a boutique recruitment firm based in Hong Kong strategically placing our candidates across all levels in permanent, temporary and contract roles.\u00a0 We specialize in IT and finance roles for banking, financial services and listed MNC sectors.", "employment_types": ["Full Time", "Permanent"], "selling_points": ["Welcome Senior to Junior Network Engineer", "Great Job Exposure", "At least 3 Months Salary Bonuses"], "locations": ["Central"], "categories": ["Information Technology (IT)", "Support", "Application Specialist - Network", "Network & System"], "post_time": "2022-01-14T09:09:56Z", "salary": {"currency": null, "max": null, "min": null, "period": "monthly", "term": null}, "salary_visible": false, "title_keywords": ["engineer"], "responsibilities": ["installation", "it infrastructure", "configuration", "ad hoc requests", "operations", "infrastructure", "coordination with", "troubleshooting", "ad-hoc tasks", "systems", "monitoring", "communication", "daily operations", "maintain data", "evaluation", "tracking"], "requirements": {"degrees": ["degree", "bachelor"], "majors": ["related disciplines", "computer science", "information technology"], "languages": ["cantonese", "english", "chinese", "mandarin"], "language_level": ["good"], "hard_skills": ["remote support", "plus", "ccnp", "switch", "ccna", "vendor", "word", "router", "aws", "problem solving", "vpn", "firewall", "server", "huawei cloud"], "soft_skills": ["communication skills", "independent", "responsible", "troubleshooting", "problem solving", "hands-on", "analytical mind", "motivated", "coordination", "team player", "initiative"], "languages_combined": [{"language": "cantonese", "language_level": []}, {"language": "english", "language_level": []}, {"language": "chinese", "language_level": []}, {"language": "mandarin", "language_level": ["good"]}]}, "experience_required": {"duration": ["minimum 5 years"], "field": ["related", "infrastructure", "it", "financial services", "security"]}}, {"job_id": "100003009051663", "location_code": "hk", "company": "Nikoyo (HK) Ltd", "job_title": "Systems Engineer", "description": "The Job\n\nResponsible for Presales consultancy,\nDesign infrastructure and create technical specifications to fulfil client requirements, specializing in Cloud Service, Server & Storage (Nutanix, Inspur, Netapp) , HCI and Backup solution (NetApp),\nConduct system operation training for system administrator and users,\nWork closely with sales team at presenting solutions to customer,\n\u00a0Analyze users\u2019 requirements and develop detailed solutions,\nPresent new products and services to enhance current customer relationship,\nCollaborate with end users, vendors and internal management team to process new solutions.\n\nThe Person\n\nDegree holder of Computer Science, Computer Engineering or related disciplines,\nAt least 2 years\u2019 working experience in infrastructure or system design,\nHolder of Professional Certificates such as NetApp, Commvault, AWS, Nutanix or VMware is an advantage,\n\u00a0Project experience on public cloud, SaaS or Backup solution is preferable,\n\u00a0Excellent communication and negotiation skills,\n\u00a0Proficient in both spoken and written English and Chinese,\n\u00a0Self-motivated and strong analytical skills.\n\nApplicant please send us your full resume, stating the date of availability, present and expected salary.\n\nYour application and personal information will be treated as strictly confidential and used only for purposes of recruitment and selection.\n\nApplicants who are not invited to interview within 8 weeks may consider their applications unsuccessful. All personal data of unsuccessful candidates will be destroyed after 6 months.", "employment_types": ["Full Time"], "selling_points": [], "locations": ["Quarry Bay"], "categories": ["Information Technology (IT)", "Product Management / Business Analyst", "Application Specialist - Network", "Technical / Functional Consulting"], "post_time": "2022-01-16T21:50:35Z", "salary": {"currency": null, "max": null, "min": null, "period": "monthly", "term": null}, "salary_visible": false, "title_keywords": ["systems engineer"], "responsibilities": ["collaborate with", "management team", "infrastructure", "design", "develop", "specifications", "sales team"], "requirements": {"degrees": ["degree holder"], "majors": ["related disciplines", "computer engineering", "computer science"], "languages": ["english", "chinese"], "language_level": ["proficient"], "hard_skills": ["system design", "vmware", "analytical skills", "aws"], "soft_skills": ["communication", "negotiation skills", "self-motivated", "analytical skills"], "languages_combined": [{"language": "english", "language_level": ["proficient"]}, {"language": "chinese", "language_level": ["proficient"]}]}, "experience_required": {"duration": ["at least 2 years"], "field": ["infrastructure", "system design"]}}, {"job_id": "100003009047610", "location_code": "hk", "company": "BGC Group (HK) Limited", "job_title": "Deskside Support / Helpdesk Support / IT Support / System Engineer - Tier 1", "description": "Our Client is a leading healthcare technology MNC that provides professional genome sequencing service. Company is focusing on talents through providing employee training and development opportunities. We are looking for professionals who are interested in and passionate about developing further their career with us.\u00a0\u00a0\n\nPLEASANT company culture with RENOWNED company background\nFAST-GROWING enterprise and RAPID career advancement\nGUARANTEED career prospects with EXCELLENT remuneration package\n\nResponsibilities:\n\nProvide day-to-day technical support including network connectivity, system maintenance\nPrioritize and schedule problems. Execute problem diagnostic by using advance troubleshooting skills\nContribute IT infrastructure support - Perform installation, configuration, and upgrade of hardware & computer applications\nAnalyze, trouble shoot and provide solution for OS system and network problems;\nPerform post-resolution follow-ups to help users\n\nRequirements:\n\nBachelor Degree in IT or Computer Science or related discipline\n1 year of experience in all-rounded technical skills on desktop support\nExperience in server room administration is a great advantage\u00a0\nGood verbal and written communications skills in English, Cantonese and Mandarin\nProactive, energetic, and positive attitude\n\n**Candidate with less experience will be also considered**\n\nInterested parties can click 'APPLY NOW' or send email with updated CV to\u00a0 Eden @bgc-group.com.\n\n* Personal data collected will be used for recruitment purposes only.", "employment_types": ["Full Time", "Contract"], "selling_points": ["Degree Holder with 1+ Year of Related Experience", "5-Days Working; 9-6; NO Shift; Work-life Balance", "Renowned and Strong Company Background"], "locations": ["Tai Po Area"], "categories": ["Information Technology (IT)", "Support", "Application Specialist - Network", "Network & System"], "post_time": "2022-01-14T03:34:12Z", "salary": {"currency": null, "max": null, "min": null, "period": "monthly", "term": null}, "salary_visible": false, "title_keywords": ["system engineer", "it support"], "responsibilities": ["installation", "it infrastructure", "maintenance", "technical support", "configuration", "troubleshooting", "resolution", "hardware", "schedule", "computer applications"], "requirements": {"degrees": ["degree", "bachelor"], "majors": ["it", "computer science"], "languages": ["cantonese", "english", "mandarin"], "language_level": ["good"], "hard_skills": ["server"], "soft_skills": ["technical skills", "positive attitude", "energetic", "proactive"], "languages_combined": [{"language": "cantonese", "language_level": ["good"]}, {"language": "english", "language_level": ["good"]}, {"language": "mandarin", "language_level": ["good"]}]}, "experience_required": {"duration": ["1 year"], "field": ["administration"]}}, {"job_id": "100003009052506", "location_code": "hk", "company": "Cathay Pacific Airways Ltd", "job_title": "Solution Lead - Customers", "description": "Reports to:\u00a0Senior Solution Lead\nDepartment: Information Technology (IMT)\n\nRole Introduction\nThis role is responsible for understanding business needs and driving technology direction and solution delivery within a business domain.\n\nKey Responsibilities\n\nLead the solution delivery and assigned projects in technical aspect\nWork with key resources including business units. IM and vendors to conceptualise\u00a0and derive solution approaches\nDrive and challenge the business units on their assumptions and justifications of how they will realistically execute the business plans and realize the benefits\nElicit business requirements or product backlog user stories using essential techniques such as interviews, workshops, use cases and workflow analysis\nAnalyse workflow and tasks to generate business process documentation which describes the business framework, business rules and role category\nPrepare and support business case\u00a0\nMaintain regular and timely communications with project stakeholders throughout the\u00a0project life cycle to ensure risks/issues are addressed and impacts are escalated\nKeep abreast of the corporate technology and tools, business strategy and plans\nAs one of the key team members in product vertical team to\nAnalyse requirements and assess detailed solutions options from a system\u00a0perspective\nSupport solution design and contribute expertise and detailed knowledge to ensure high level design decisions be able to deliver\nEnsure requirements, technical details and solutions are documented into\u00a0the knowledge portal for software development projects and support\nCarry out application development and coach the team members and\u00a0vendors on development and implementation work\nOversee and QA the development of all solution components ensuring this\nMeets requirements and complies with all relevant Cathay Pacific standards\nCarry out level 2 and level 3 incident supports for in-production systems and manage end user expectations\nContribute and follow standards and frameworks for development\nCollaborate with other IM domains to drive innovation\nKeep abreast of the business strategy, business plan and latest industrial trends\n\nRequirements\n\nA minimum of 8 years of IT experience with at least 4 years in Application Development\nTertiary qualifications are essential\nStrong interpersonal skills; promoting healthy relationships and team dynamics with various stakeholders\nProven experience in working with both waterfall and agile development process\nWell-developed analytical, problem-solving, and decision-making skills, leveraging both logic and creativity; strong troubleshooting skills; ability to identify patterns and generate ideas\nProven experience in applying Software Engineering best practices and techniques such as structured analysis, use cases and formal estimation. Ability to listen and articulate ideas verbally and in written formats to a broad range of audiences; ability to ask probing questions and deliver presentations\nFocus on the end user\u2019s or customer\u2019s needs; ability to set expectations and\u00a0understand end user behaviour\nAbility to take raw product requirements and develop software architectures and designs to bring them to life\nAbility and willingness to proactively accept and drive change to accomplish positive collective outcomes\nSolid experience in implementing the secure e-commerce high transaction volume application at enterprise scale and traffic. A strong track record of project delivery for large, cross-functional projects\nSolid experience in systems analysis and software development, with sound knowledge and experience in some of the below areas:\nFront-end framework, responsive web design and scripts such as HTML5, CSS3, jQuery, AngularJS and ReactJS, Websockets and JSON\nSecure, robust and high transaction volume web development with Spring\u00a0boot, J2EE, Node.JS, Adobe Experience Manager, web accessibility and Search Engine Optimization\nAPI and micro-services development\nOpen Source Technology and its managed cloud services such as Java,\u00a0MySQL, Redis and MongoDB\nImplementation and operation of reference architecture, resources and services on Public Clouds\nDocker configuration of Tomcat Application Server, Adobe Experience\u00a0Manager\nCI/CD and monitoring tools (e.g Jenkins, Ansible, Terraform and\u00a0AppDynamics)\nKnowledge on database design and ETL tools\nKnowledge and experience of professional software engineering practices & best practices for the full software development life cycle, including coding standards,\u00a0code reviews, source control management, build processes, testing, and operations\nExperience developing software foundations and environments for application\u00a0development. Good understanding of technology concepts, trends and capabilities\nPassion with new technologies\nRelevant business domain experience in Airlines and B2C\nOccasional non-office hour work will be required for application support and release\nApplication Deadline: 31 January 2022\n\nPersonal & Application Information\n\nCathay Pacific is an Equal Opportunities Employer. Personal data provided by job applicants will be used strictly in accordance with our personal data policy and for recruitment purposes only. Candidates not notified within eight weeks may consider their application unsuccessful. All related information will be kept in our file for up to 24 months. A copy of our Personal Information Collection Statement will be provided upon request by contacting our Data Protection Officer.\n\nPlease note that with effect from 1 December 2021, all employees must be vaccinated in order to access Cathay City and all other Cathay Group Company premises in Hong Kong. Consideration will be given to those who are unable to get vaccinated for valid medical reasons.\n\n\n\n\n", "employment_types": ["Full Time", "Permanent"], "selling_points": ["8 years in IT & 4 years in Application Development", "Driving technology direction and solution delivery", "Travel Benefits, 5-day work, Medical Benefits"], "locations": ["Lantau Island"], "categories": ["Transportation & Logistics", "Aviation Services", "Information Technology (IT)", "Application Specialist - Software", "Application Specialist - Network"], "post_time": "2022-01-17T03:17:14Z", "salary": {"currency": null, "max": null, "min": null, "period": "monthly", "term": null}, "salary_visible": false, "title_keywords": ["lead"], "responsibilities": ["collaborate with", "communications with", "software", "analysis", "systems", "implementation", "business plans", "design", "business process", "maintain", "business plan", "documentation", "plans", "application development", "analyse"], "requirements": {"degrees": [], "majors": [], "languages": [], "language_level": [], "hard_skills": ["web design", "web development", "java", "agile", "web", "e-commerce", "jenkins", "problem-solving", "analysis", "jquery", "code", "presentations", "ansible", "adobe", "airlines", "spring", "application server", "focus"], "soft_skills": ["agile", "problem-solving", "troubleshooting", "robust", "interpersonal skills", "articulate", "focus", "structured", "responsive", "positive"], "languages_combined": []}, "experience_required": {"duration": ["at least 4 years", "minimum of 8 years"], "field": ["management", "engineering", "e-commerce", "development", "developing", "it experience", "testing", "business", "software development", "application development"]}}, {"job_id": "100003009051195", "location_code": "hk", "company": "Kingvisions Consultants Limited", "job_title": "System Engineer/ System Administrator (Windows)", "description": "Responsibility:\n\nResponsible for setting up, administering and upgrading IT infrastructure in Windows platform\nPerform system analysis, planning, design, implementation, monitoring, capacity management, security operations, trouble-shooting and documentation\nPropose and execute continuous improvements on infrastructure solutions\nManagement of documentation of all system, application and security changes, upgrades and new implementations as appropriate\nManage Internal IT systems (i.e. web, email, applications and server, etc.) and Infrastructure (i.e. data center, servers and network, etc.)\n\nRequirements:\n\nDiploma or Degree holders in Computer Science, Information Technology, or related discipline\n1-3 years relevant working experience.\nSolid experience in Microsoft 365 and Azure administration and user support is preferred\nSolid knowledge in Microsoft Windows 10, server 2012+, WAF, DNS, firewall and router\nFamiliar with ITIL process and tools is an advantage\nExperience in VMware, Storage, MDM, Backup, Rapid 7 is an advantage\nStrong organizational communication and interpersonal skills\nGood command of written and spoken English\nCandidates with less experience will also be considered", "employment_types": ["Full Time", "Permanent", "Contract"], "selling_points": ["1-3 years relevant working experience.", "Great career prospect with latest technical skills", "MS Windows 10, server 2012+, WAF, DNS, firewall"], "locations": ["Not Specified"], "categories": ["Information Technology (IT)", "Support", "Application Specialist - Network", "Network & System"], "post_time": "2022-01-15T04:34:40Z", "salary": {"currency": "HKD", "max": 44999, "min": 25000, "period": "monthly", "term": null}, "salary_visible": true, "title_keywords": ["system engineer", "system administrator"], "responsibilities": ["continuous improvements", "management", "it infrastructure", "data", "upgrades", "operations", "analysis", "monitoring", "infrastructure", "implementation", "design", "systems", "documentation", "planning"], "requirements": {"degrees": ["diploma", "degree"], "majors": ["computer science", "information technology"], "languages": ["english"], "language_level": ["good command"], "hard_skills": ["itil", "azure", "dns", "vmware", "router", "windows 10", "rapid", "firewall", "server"], "soft_skills": ["organizational", "communication and interpersonal skills"], "languages_combined": [{"language": "english", "language_level": ["good command"]}]}, "experience_required": {"duration": ["1-3 years"], "field": ["relevant working experience", "administration"]}}, {"job_id": "100003009055750", "location_code": "hk", "company": "PCCW Solutions", "job_title": "Tech Talent - ICT Associate", "description": "The Job\n\nAcquire IT solutions knowledge and soft skills through on-the-job training in different high value and large scale IT projects\nBe exposed to the areas of cloud computing, digital solutions, loT, big data, enterprise applications (SAP / Oracle), software systems application, IT infrastructure operations and applications support\nExciting opportunity to gain exposure in the trending area of Data Analytics, Business Analyst, IoT, Customer Experience Journey and Block Chain\nDevelop a rewarding career in an advanced, fast-paced and multicultural environment.\n\nThe Person\n\nBachelor / Master degree in Computer Science, IT, Electronic Electrical Engineering or related disciplines with less than 2 years of full-time working experience\nGood presentation, interpersonal and communication skills\nA team player with good analytical and problem-solving skills and who relishes challenges\nGood command of spoken and written English and Chinese", "employment_types": ["Full Time"], "selling_points": [], "locations": ["Mong Kok"], "categories": ["Information Technology (IT)", "Application Specialist - Software", "Software Development", "Application Specialist - Network"], "post_time": "2022-01-18T02:55:12Z", "salary": {"currency": null, "max": null, "min": null, "period": "monthly", "term": null}, "salary_visible": false, "title_keywords": ["associate"], "responsibilities": ["software", "it infrastructure", "data", "operations", "systems", "big data", "develop"], "requirements": {"degrees": ["bachelor", "master degree"], "majors": ["related disciplines", "it", "electrical engineering", "computer science"], "languages": ["english", "chinese"], "language_level": ["good command"], "hard_skills": ["problem-solving skills"], "soft_skills": ["communication skills", "presentation", "problem-solving skills", "team player", "interpersonal"], "languages_combined": [{"language": "english", "language_level": ["good command"]}, {"language": "chinese", "language_level": ["good command"]}]}, "experience_required": {"duration": ["2 years"], "field": ["related", "it", "engineering"]}}, {"job_id": "100003009046196", "location_code": "hk", "company": "CL Technical Services Ltd.", "job_title": "Senior Network Engineer (Around $60K)", "description": "Job Duties:\n\nDesign network infrastructure for new server room and offices\nMaintain network infrastructure including network equipment, data lines, servers and PCs\nEnhancement of the network infrastructure.\nMonitor & review the network environment closely and pro-actively to propose improvement plan * Provide technical expertise in supporting the cooperate network and managing network security\n\nJob Requirements:\n\nHigher Diploma or Degree holder in Computer science, information technology or related discipline.\nAt least 4 years\u2019 experience in IT filed with 2 years\u2019 experience in similar capacity\nMinimum of 3 years of working experience in Network & System Management\nStrong technical knowledge and support experience in network infrastructure including network and system management and the support of Local Area Network (LAN), Wide Area Network (WAN), wireless LAN and SSL VPN. 2.\nStrong technical knowledge and support experience in enterprise grade high availability network services including the related network health monitoring and reporting systems.\nGood analytical, interpersonal and problem-solving skills", "employment_types": ["Full Time"], "selling_points": ["Medical", "5 days work", "over $60K"], "locations": ["Central & Western Area"], "categories": ["Information Technology (IT)", "Application Specialist - Network", "Network & System", "Technical / Functional Consulting"], "post_time": "2022-01-13T09:54:30Z", "salary": {"currency": null, "max": null, "min": null, "period": "monthly", "term": null}, "salary_visible": false, "title_keywords": ["engineer"], "responsibilities": ["network infrastructure", "maintain network", "data", "infrastructure", "pcs", "monitor", "design", "review", "plan"], "requirements": {"degrees": ["diploma", "degree holder"], "majors": ["computer science", "information technology"], "languages": [], "language_level": [], "hard_skills": ["problem-solving skills", "wan", "reporting systems", "vpn"], "soft_skills": ["problem-solving skills", "interpersonal"], "languages_combined": []}, "experience_required": {"duration": ["at least 4 years", "2 years", "minimum of 3 years"], "field": ["related", "infrastructure", "management", "it"]}}, {"job_id": "100003009045759", "location_code": "hk", "company": "Kepro Solutions Limited", "job_title": "Consultant (IT Infrastructure)", "description": "The job:\nThe successful candidate will be taking\u00a0a pre-sales role in proposing high-value IT services and solutions consultancy for our clients with various IT needs.\n\n\u00a0Responsibilities:\n\nReviewing the customer IT environment, customer strategic goals, existing capabilities, and other factors that influence project direction\nCollecting customer requirements and designing technical solutions\nArticulating in a clear manner, alternatives in terms of cost, benefit, and risk where multiple solutions exist\nWorking with the Delivery team in the creation of technical project plans and scope of work\nEngage and support sales team with the delivery of the assigned solutions\nDevelop infrastructure solution offerings for sales team to sell to customers\n\n\u00a0Requirements:\n\nHigher Diploma or Degree holder in Computer Science or related disciplines\nMinimum 2+ years\u2019 pre-sales solution experience in IT industry\nIn-depth knowledge in server, storage, networking, virtualization and cloud solutions\nSolid experience in infrastructure solution design\nExperience participating in solution configuration, proof of concept, proposal development and competitive analysis\nDynamic, self-motivated and able to work under pressure\nGood communication and presentation skills in both spoken and written English and Chinese\nWith advantage having experience in storage networking solution\n\nWe offer a competitive remuneration package to the right candidate. Interested parties\u00a0please send your full resume with\u00a0present and expected salary\u00a0to us by\u00a0clicking 'Apply Now'.\u00a0\n\nOnline Job Application:\u00a0https://karingroup.com/careers/.\n\nCorporate Website:\u00a0https://karingroup.com/kepro-solutions/\n\n\n(We are an Equal Opportunity Employer and personal data collected would be used for\u00a0 recruitment purpose only.)", "employment_types": ["Full Time", "Permanent"], "selling_points": ["Pre-sales role in proposing high-value IT services", "Solid experience in infrastructure solution design", "Competitive remuneration package"], "locations": ["Kwun Tong"], "categories": ["Information Technology (IT)", "Hardware", "Application Specialist - Network", "Technical / Functional Consulting"], "post_time": "2022-01-15T03:49:31Z", "salary": {"currency": null, "max": null, "min": null, "period": "monthly", "term": null}, "salary_visible": false, "title_keywords": ["consultant"], "responsibilities": ["cost", "infrastructure", "develop", "sales team", "designing", "plans"], "requirements": {"degrees": ["diploma", "degree holder"], "majors": ["related disciplines", "computer science"], "languages": ["english", "chinese"], "language_level": ["good"], "hard_skills": ["server", "analysis", "dynamic"], "soft_skills": ["self-motivated", "communication", "presentation skills", "dynamic", "work under pressure"], "languages_combined": [{"language": "english", "language_level": ["good"]}, {"language": "chinese", "language_level": ["good"]}]}, "experience_required": {"duration": ["minimum 2+ years"], "field": ["infrastructure", "development", "it", "design"]}}, {"job_id": "100003009044402", "location_code": "hk", "company": "PCCW Solutions", "job_title": "Assistant Systems Specialist", "description": "The Job\n\nTeam member to system support team serving large scale enterprise customer\nCore duty to include providing 7x24 system support service for Windows , VMware , storage and monitoring systems\nNon shift duty based role , out of office hour support duties to be shared amongst support team\n\nThe Person\n\n- Minimum of 2 years solid hands on system support experience for Windows and VMWare platforms.\n\n- Hands on experience in the following areas\n\nMicrosoft Active Directory troubleshooting\nWindows Server deployment and support\nActive Directory Group policies administration\nESXi Server deployment and support", "employment_types": ["Full Time"], "selling_points": [], "locations": ["Mong Kok"], "categories": ["Information Technology (IT)", "Application Specialist - Network", "Network & System"], "post_time": "2022-01-13T03:57:44Z", "salary": {"currency": null, "max": null, "min": null, "period": "monthly", "term": null}, "salary_visible": false, "title_keywords": ["specialist", "assistant"], "responsibilities": ["monitoring", "systems"], "requirements": {"degrees": [], "majors": [], "languages": [], "language_level": [], "hard_skills": ["vmware", "active directory", "deployment", "server", "windows server"], "soft_skills": ["active", "hands on", "troubleshooting"], "languages_combined": []}, "experience_required": {"duration": ["minimum of 2 years"], "field": ["system support"]}}, {"job_id": "100003009043255", "location_code": "hk", "company": "Fung (1937) Management Limited", "job_title": "Senior Network Engineer / Assistant Manager", "description": "Key Responsibilities\nResponsible for entire global network operations, monitoring, support, and implementation for multi-cloud networking, data center network, campus network, WiFi network, regional MPLS network and voice network\nAssist to formulate the network architecture, design, roadmap, standard and policy\nResponsible for all network change management, related audit activities associated with the network environment including documentation requirements, scheduled outages, operational procedures, etc.\nDrive the infrastructure subject matter experts and managed service vendors to implement the global infrastructure projects\nManage a team of engineers and managed services vendors to provide high quality implementation services of network related projects\nProvide a Level 2-3 global network support by 7x24 to the production environment\nResearch and provide technical solution on the use of new products/technology for various infrastructure perspectives\nWork with the business stakeholders to gather the business requirement and come up network solutions to support the business needs\nEnsure the infrastructure services to meet with the corporate standard/policy with proper governance setup\nResponsible for capacity planning and proactive monitoring of all infrastructure related components\nManage different service providers/vendors and its service delivery against KPI and SLA\nThe ideal candidate will have the following qualities:\nDegree in Computer Science, Information Technology, Information Systems or equivalent experience\nAt least 5 years of related experience in enterprise infrastructure network environments on cloud or data center networks including architecture design, project planning, implementation, documentation, and administration\nExtensive experience in WAN, LAN, multi-cloud networking, Wi-Fi, VOIP\nExperience with hybrid cloud connectivity solutions and technologies - AWS Direct Connect, Azure ExpressRoute, Equinix Fabric\nExperience with SD-WAN technologies (Fortinet etc)\nFamiliar with products of Cisco, Fortinet, Azure, AWS, Alibaba Cloud, Equinix, Solarwinds etc.\nProfessional credentials in CCNP, CISSP, cloud certificate or relevant disciplines will be an advantage\nStrong planning and organizing skills including the ability to manage several work streams simultaneously\nGood communication and presentation skills as well as the ability to interact with internal customers independently\nGood team player, vendor management, project management, change management and stakeholder management\nWilling to working overtime and provide non-office hours support\nProactive and committed to work in a quality environment\nProficient command of spoken and written English and Chinese\nCandidate with less experiences will be considered as a Senior Network Engineer", "employment_types": ["Full Time", "Permanent"], "selling_points": ["Manage different service providers/vendors", "Degree in Computer Science", "At least 5 years of related experience"], "locations": ["Lai Chi Kok"], "categories": ["Information Technology (IT)", "Application Specialist - Network", "Network & System", "Others"], "post_time": "2022-01-12T10:23:40Z", "salary": {"currency": null, "max": null, "min": null, "period": "monthly", "term": null}, "salary_visible": false, "title_keywords": ["assistant manager", "engineer"], "responsibilities": ["data", "operations", "quality", "audit", "design", "communication", "administration", "service delivery", "infrastructure", "implementation", "operational procedures", "architecture", "setup", "management", "change management", "monitoring", "documentation", "project planning", "outages", "systems", "project management", "planning"], "requirements": {"degrees": ["certificate", "degree"], "majors": ["computer science", "information technology"], "languages": ["english", "chinese"], "language_level": ["proficient"], "hard_skills": ["azure", "wi-fi", "ccnp", "vendor", "aws", "sla", "project management", "sd-wan", "documentation", "wan"], "soft_skills": ["good team player", "independently", "responsible", "communication", "project management", "presentation skills", "committed", "proactive", "extensive", "ideal"], "languages_combined": [{"language": "english", "language_level": ["proficient"]}, {"language": "chinese", "language_level": ["proficient"]}]}, "experience_required": {"duration": ["at least 5 years"], "field": ["administration", "related", "infrastructure", "design", "information technology", "planning"]}}, {"job_id": "100003009049259", "location_code": "hk", "company": "SmarTone Telecommunications Limited", "job_title": "Engineer, Core Network Engineering", "description": "Responsibilities:\n\nAssist supervisor to conduct system development, support of intelligent bandwidth management and AAA/\u00a0Radius\u00a0platforms\nAssure high system availability with proactive performance monitoring\nConduct system evaluation and testing for new applications or new features\nProvide 7x24 emergency support for fast system fault resolutions\nHandle fault or compliant analysis in related to service enabling systems\nProvide technical support to business marketing on corporate solution\n\n\u00a0Requirements:\n\nDegree, Higher Diploma or equivalent in Electronic Engineering, Computer Science or Telecommunications\nKnowledge in Router, Ethernet Switch, Load Balancer, Firewall, Security, Internet Protocols, Network Management tools\nHands-on experience in Unix/Linux environment and shell script programming will be an advantage\nGood problem solving skill, self-motivated, proactive to learn and able to work independently\nGood communications skill in both English and Cantonese\nWilling to perform work or support outside office hour\nFresh graduates will also be considered", "employment_types": ["Full Time"], "selling_points": ["System evaluation and testing", "Intelligent bandwidth management & Radius platform", "System fault resolutions"], "locations": ["Kowloon Bay"], "categories": ["Engineering", "Telecommunication / Wireless / Radio", "Information Technology (IT)", "Application Specialist - Network", "Network & System"], "post_time": "2022-01-14T08:19:54Z", "salary": {"currency": null, "max": null, "min": null, "period": "monthly", "term": null}, "salary_visible": false, "title_keywords": ["engineer"], "responsibilities": ["management", "technical support", "analysis", "monitoring", "systems", "testing", "evaluation"], "requirements": {"degrees": ["diploma", "degree"], "majors": ["engineering", "computer science"], "languages": ["cantonese", "english"], "language_level": ["good"], "hard_skills": ["network management", "linux", "switch", "router", "problem solving", "programming", "firewall"], "soft_skills": ["work independently", "self-motivated", "hands-on", "problem solving skill", "proactive"], "languages_combined": [{"language": "cantonese", "language_level": ["good"]}, {"language": "english", "language_level": ["good"]}]}, "experience_required": {"duration": [], "field": ["programming"]}}, {"job_id": "100003009044403", "location_code": "hk", "company": "PCCW Solutions", "job_title": "Manager", "description": "General Requirement\n\nA degree or above in information engineering or computer science or electrical and electronic engineering, or equivalent;\nAt least 11 years of post-qualification IT experience;\nAt least 6 years of project management experience;\nAt least 6 years of functional/specialty experience in the management of IT project(s) for the design and implementation of enterprise IT infrastructure(s) connecting more than 5 sites and over 1,000 users\n\nTechnical Requirement\n\nExperience in supporting network devices: Routers, Switches, Multi-layer Switches, Firewalls, Local and Global Server Load Balancers, IPSec VPN, SSL VPN, IPS/IDS, Web Application Firewall, WiFi, 2FA etc.\nExperience in project management for large scale network infrastructure projects with aspects abovementioned\nFamiliar with network protocols configurations and changes, including IPv4 & IPv6, spanning-tree, dynamic routing protocols, VLANs, DHCP, NAT, ACL, QoS, Metro Network, SLB, GSLB, WiFi roaming, 2FA etc.\nCandidate with experience in Cisco voice / IP Telephony setup project is preferable.\nGood problem solving, troubleshooting and analytical skills and can manage customer expectations\n\nJob description\n\nEngaged in projects for network related setup and day-to-day network support and fixup tasks during nursing period, perform task at other customer sites if needed\nHandle network issues escalated from team members and from customer\u2019s network support team\nHandling requests from and discuss with customer including but not limited to: Network changes for abovementioned devices, documentation verification, escalation to vendors, perform eligible image upgrade for network devices bug fixing\nFaulty hardware replacement work\nImage and firmware upgrade for in scope network equipment\nChange management, Incident management and Problem management", "employment_types": ["Full Time"], "selling_points": [], "locations": ["Yau Ma Tei"], "categories": ["Information Technology (IT)", "Application Specialist - Network", "Network & System", "Others"], "post_time": "2022-01-13T03:57:50Z", "salary": {"currency": null, "max": null, "min": null, "period": "monthly", "term": null}, "salary_visible": false, "title_keywords": ["manager"], "responsibilities": ["management", "change management", "network issues", "hardware", "documentation", "setup"], "requirements": {"degrees": ["degree or above"], "majors": ["engineering", "computer science"], "languages": [], "language_level": [], "hard_skills": ["analytical skills", "problem solving", "project management", "ip", "dynamic", "vpn", "web application firewall", "server"], "soft_skills": ["troubleshooting", "analytical skills", "problem solving", "project management", "dynamic"], "languages_combined": []}, "experience_required": {"duration": ["at least 6 years", "at least 11 years"], "field": ["management", "post-qualification", "infrastructure", "design", "it experience", "project management", "it"]}}, {"job_id": "100003009046543", "location_code": "hk", "company": "BOCOM International Holdings Company Limited", "job_title": "(Senior) Network Engineer", "description": "Responsibilities:\n\u00a0\n\nWork in the IT Infrastructure team;\n\nHandle the daily operation on network and security;\n\nHandle network and security equipment installation and configuration;\n\nHandle troubleshooting, incident support, and coordination with service partner and carriers;\n\nHand on experience of maintains connectivity among HK and CN offices.\n\nWork closely with application and Helpdesk team to prepare applications and service roll-out;\n\nResearch on new information technology and perform product evaluation with vendors;\n\nHandle and support user side scheduled and ad hoc requests;\n\nAssist in suggesting and implementing improvement solution on daily internal and user operations;\n\nOther IT related ad-hoc tasks when needed.\n\u00a0\u00a0\u00a0\n\nRequirements:\n\u00a0\u00a0\n\u00a0\n\nBachelor degree in Information Technology, Computer Science or related disciplines;\n\nMinimum 3 years practical experience in IT infrastructure. Candidate with less experience will also be considered as junior role;\n\nSolid Hands-on experience in Cisco router and switch; reputable firewall (e.g. CheckPoint, Fortigate, Palo Alto etc.), WIFI etc.;\n\nExperience of administrate security related systems and related products such as IDS, IPS, WAF, EDR, UEBA, SIEM, NAC, PAM, anti-virus and APT solution, and Sandbox solution, etc.;\n\nExperience of build and maintain data center for Financial Services with Cloud Services like AliCloud, Huawei Cloud, AWS etc.;\n\nKnowledge of VLANs, routing, switching, IPSec VPN, and IPv4/IPv6 addressing;\n\nIT certification holder such as CCNA, CCNP or equivalent is preferable;\n\nExperience in using issue tracking systems, network monitoring system is added advantage;\n\nWorking experience in FSI sector is an added advantage;\n\nExposure to different IT infrastructure and vendor products;\n\nRequired to work overtime for non-office hour deployment or support;\n\nGood analytical mind, problem solving and communication skills;\n\nTeam player, responsible, independent, self-starter, motivated, multitasking and able to take initiative to get projects completed;\n\n\u00a0\u00a0\u00a0\u00a0\u00a0\u00a0\u00a0\u00a0\u00a0\u00a0\u00a0\u00a0\u00a0\u00a0\u00a0\u00a0\u00a0\u00a0\u00a0\u00a0 Good spoken and writing in Mandarin; knowledge of Cantonese/English is a plus.\n\n\u00a0Application:\n\nWe offer an attractive remuneration package including a performance bonus, medical insurance covering dependents, MPF, Life and AD&D insurance, annual leave, birthday leave, marriage leave and training subsidy, etc. to the right candidate.\u00a0\n\nIf you are interested in this opportunity, please send your application with a detailed resume including current and expected salary, latest bonus and availability by clicking \"Apply Now\". Applications without required information will NOT be considered.\n\n*Information provided by applicants will be treated in the strictest confidence and will be solely used for recruitment purpose", "employment_types": ["Full Time", "Permanent"], "selling_points": ["Network Engineer", "Financial Institution", "-"], "locations": ["Central"], "categories": ["Information Technology (IT)", "Support", "Application Specialist - Network", "Network & System"], "post_time": "2022-01-13T13:40:04Z", "salary": {"currency": null, "max": null, "min": null, "period": "monthly", "term": null}, "salary_visible": false, "title_keywords": ["engineer"], "responsibilities": ["installation", "it infrastructure", "configuration", "ad hoc requests", "operations", "coordination with", "daily operation", "troubleshooting", "ad-hoc tasks", "evaluation"], "requirements": {"degrees": ["degree", "bachelor"], "majors": ["related disciplines", "computer science", "information technology"], "languages": ["cantonese", "english", "mandarin"], "language_level": ["good"], "hard_skills": ["plus", "switch", "apt", "ccna", "ccnp", "vendor", "router", "aws", "problem solving", "deployment", "huawei cloud", "firewall", "vpn"], "soft_skills": ["communication skills", "work overtime", "confidence", "independent", "responsible", "interested in", "problem solving", "hands-on", "analytical mind", "motivated", "team player", "initiative", "detailed"], "languages_combined": [{"language": "cantonese", "language_level": []}, {"language": "english", "language_level": []}, {"language": "mandarin", "language_level": ["good"]}]}, "experience_required": {"duration": ["minimum 3 years"], "field": ["related", "infrastructure", "it", "financial services", "security"]}}, {"job_id": "100003009048483", "location_code": "hk", "company": "ST Engineering Infa Systems Limited", "job_title": "Security Engineer", "description": "Duties and Responsibilities:\n\nTo install / configure / test / deploy security software.\nTo work as a team and to collaborate with other engineers, application developers towards delivering the System.\nTo understand the project requirements and adjust the design to meet the customer\u2019s demand as necessary.\nTo produce the necessary documentation on the installation / configuration / deployment of the security software.\nTo produce the User Acceptance Tests (UAT) test cases.\nTo assist testers in conducting User Acceptance Tests (UAT).\nTo analyze and troubleshoot security issues that may arise.\n\nSkill and experience:\n\nDegree/Diploma in IT or equivalent\nCertificate in IT security related courses.\nAdministrator experience with Microsoft Active Directory\nAdministrator experience with Linux based systems\nExperience administering network related products\nExperience with HSM (Hardware Security Module) products\nExperience with Active Directory Certificate Services (ADCS)\nExperience with PAM (Privileged Access Management) products\n\nWe offer excellent career opportunities and remuneration package. Interested parties, please send Full C.V. provided Date Available, Current and Expected Salary with Reference No. on the letter to the following address: 17/F, 169 Electric Road, North Point, Hong Kong OR you may reach us by fax/ email: 852-2231 0718/ Click \"Apply Now\". Attn to Ms Jacqueline Sy.", "employment_types": ["Full Time", "Permanent"], "selling_points": [], "locations": ["Tsim Sha Tsui"], "categories": ["Information Technology (IT)", "Application Specialist - Network", "Security", "Network & System"], "post_time": "2022-01-14T06:39:24Z", "salary": {"currency": null, "max": null, "min": null, "period": "monthly", "term": null}, "salary_visible": false, "title_keywords": ["engineer"], "responsibilities": ["collaborate with", "project requirements", "installation", "management", "software", "uat", "active directory", "configuration", "systems", "design", "hardware", "troubleshoot", "deploy", "documentation"], "requirements": {"degrees": ["certificate", "diploma", "degree"], "majors": ["it"], "languages": [], "language_level": [], "hard_skills": ["linux", "active directory", "hardware", "deployment", "documentation"], "soft_skills": ["active", "troubleshoot", "work as a team"], "languages_combined": []}, "experience_required": {"duration": [], "field": ["related", "management", "security"]}}, {"job_id": "100003009050928", "location_code": "hk", "company": "The Hang Seng University of Hong Kong", "job_title": "Assistant Information Security Manager / Senior Information Security Officer", "description": "Assistant Information Security Manager / Senior Information Security Officer\u00a0\u2013 Information Technology Services Centre (Ref: AISM / SISO (ITSC) 2022-01-14)\n\n(Ref: AISM / SISO (ITSC) 2022-01-14)\n\n\n\nResponsibilities:\n\nreview and update security documents such as policies and guidelines;\nassess risks on applications, systems, networks and adopt security measures in a balance manner for risk mitigation;\naudit and run tests on systems and infrastructure to identity possible issues;\nensure digital assets adequately protected, effectively monitored and managed;\nprovide latest updates on information security to general users to increase their awareness; and\nexplore suitable information security technologies that can better safeguard the information in the university.\n\nApplicants should:\n\npossess a recognised bachelor\u2019s degree or above in Computer Science or related discipline;\npossess updated and relevant qualifications such as CISM, CISSP, CEH, ISO27001;\npreferably have at least 10 years of relevant work experience;\nhave proven records in information security and system auditing in application, networks and system level;\nhave good interpersonal, communication, analytical and problem-solving skills;\nhave good command of written and spoken English and Chinese; and\nbe pleasant with positive mindset, good customer sense and willing to learn new technologies.\n\nThe appointee will be required to work during non-office hours.\u00a0 Work experience in the higher education sector will be an advantage.\u00a0 Applicants with fewer years of experience could be considered as Senior Information Security Officer.\u00a0\n\n\nSalary will be commensurate with qualifications and experience.\u00a0 Interested applicant should visit this link https://recruit.hsu.edu.hk/ and apply on or before 30 January 2022.\u00a0 The University reserves the right not to fill the position in this exercise.\n\nApplicants who are not invited to an interview within three months may consider their applications unsuccessful.\u00a0 All information received will be treated in strict confidence, and the data collected will be used for recruitment purposes only.\u00a0 The Personal Information Collection Statement will be provided upon request.\n\nthe Hang Seng University of Hong Kong, incorporated in Hong Kong with limited liability by guarantee, is an equal opportunity employer.", "employment_types": ["Full Time"], "selling_points": [], "locations": ["Shatin Area"], "categories": ["Information Technology (IT)", "IT Auditing", "IT Management", "Application Specialist - Network"], "post_time": "2022-01-14T11:49:37Z", "salary": {"currency": null, "max": null, "min": null, "period": "monthly", "term": null}, "salary_visible": false, "title_keywords": ["information security manager", "senior information security officer", "assistant"], "responsibilities": ["information security", "data", "guidelines", "policies", "review", "systems", "audit", "infrastructure", "communication", "recruitment", "assess risks", "auditing"], "requirements": {"degrees": ["degree or above", "bachelor"], "majors": ["computer science"], "languages": ["english", "chinese"], "language_level": ["good command"], "hard_skills": ["problem-solving skills"], "soft_skills": ["confidence", "positive mindset", "willing to learn", "pleasant", "communication", "problem-solving skills", "interpersonal"], "languages_combined": [{"language": "english", "language_level": ["good command"]}, {"language": "chinese", "language_level": ["good command"]}]}, "experience_required": {"duration": ["at least 10 years"], "field": ["security", "education"]}}, {"job_id": "100003009039491", "location_code": "hk", "company": "CL Technical Services Ltd.", "job_title": "IT Support Engineer (Perm, up to $19K, Science Park)", "description": "Job Duties:\n\nProvides end-user support and problem-solving support on hardware, software & package installation and maintenance for servers & PCs\nPerforms IT audit & complete group IT checklists & surveys\nLiaisons with internal & external vendors on network, email, application system (SBO), IT contracts and other related issues\nSet up presentation and conference equipment\nStudies and supports on IT security control software\nMaintains company Intranet website\nConducts fixed asset stock take with A/C Dept.\nAd Hoc projects\n\nJob Requirements:\n\nHigher Diploma or above in information technology, computer technology, or a similar field.\nAt least two years' experience as an IT support or related role.\nExperience working with Microsoft Office 2016, 2019, or Office 365.\nStrong troubleshooting, analytical, and problem-solving skills.\nGood interpersonal skills and the ability to work with technical and non-technical personnel.", "employment_types": ["Full Time"], "selling_points": ["Discretionary bonus", "5 days work", "Shatin"], "locations": ["Shatin Area"], "categories": ["Information Technology (IT)", "Support", "Application Specialist - Network", "Network & System"], "post_time": "2022-01-11T09:55:10Z", "salary": {"currency": null, "max": null, "min": null, "period": "monthly", "term": null}, "salary_visible": false, "title_keywords": ["it support engineer"], "responsibilities": ["installation", "control", "software", "maintenance", "contracts", "pcs", "audit", "application system", "website", "stock take", "hardware", "ad hoc projects"], "requirements": {"degrees": ["higher diploma or above"], "majors": ["information technology"], "languages": [], "language_level": [], "hard_skills": ["problem-solving skills", "office 365", "microsoft office"], "soft_skills": ["problem-solving skills", "interpersonal skills", "troubleshooting"], "languages_combined": []}, "experience_required": {"duration": ["at least two years"], "field": ["related", "it support"]}}, {"job_id": "100003009046209", "location_code": "hk", "company": "Fountain Set (Holdings) Limited", "job_title": "System Administrator", "description": "Job Description\n\n\u00a0\u00a0\u00a0\u00a0\u00a0\u00a0\u00a0\u00a0 Provide support, maintenance and troubleshooting service for user computers & company network\n\u00a0\u00a0\u00a0\u00a0\u00a0\u00a0\u00a0\u00a0 Provide support to daily operations\n\u00a0\u00a0\u00a0\u00a0\u00a0\u00a0\u00a0\u00a0 Monitor, administer and backup of File Servers, Web Servers, Mail Servers, SharePoint, Lync, Firewalls and other network appliances\n\u00a0\u00a0\u00a0\u00a0\u00a0\u00a0\u00a0\u00a0 Inventory control of computer hardware and software\n\u00a0\u00a0\u00a0\u00a0\u00a0\u00a0\u00a0\u00a0 Handle System Documentation\n\u00a0\u00a0\u00a0\u00a0\u00a0\u00a0\u00a0\u00a0 Responsible for project proposal and implementation\n\u00a0\u00a0\u00a0\u00a0\u00a0\u00a0\u00a0\u00a0 Provide support Regional Offices & Branches\n\nRequirement\n\n\u00a0\u00a0\u00a0\u00a0\u00a0\u00a0\u00a0\u00a0 University graduate in Computer Science / Information System\n\u00a0\u00a0\u00a0\u00a0\u00a0\u00a0\u00a0\u00a0 Minimum 4-year experience in system support, computer system evaluation, installation,\u00a0 operation administration and support is a must\n\u00a0\u00a0\u00a0\u00a0\u00a0\u00a0\u00a0\u00a0 Familiar in MS Window servers, MS Exchange, MS SharePoint, MS Lync, SCCM, Active Directory integrated DNS, TCP/IP, DHCP and WINS operation\n\u00a0\u00a0\u00a0\u00a0\u00a0\u00a0\u00a0\u00a0 In-depth knowledge of disk management with SAN, NAS and local storage with an emphasis on disk layout and performance\n\u00a0\u00a0\u00a0\u00a0\u00a0\u00a0\u00a0\u00a0 Technical experiences in administration SMTP, Proxy, Backup/Restore\n\u00a0\u00a0\u00a0\u00a0\u00a0\u00a0\u00a0\u00a0 Familiar with TCP/IP, networking and cabling\n\u00a0\u00a0\u00a0\u00a0\u00a0\u00a0\u00a0\u00a0 Hands on helpdesk and end-user support\n\u00a0\u00a0\u00a0\u00a0\u00a0\u00a0\u00a0\u00a0 Good troubleshooting skills of hardware & software\n\u00a0\u00a0\u00a0\u00a0\u00a0\u00a0\u00a0\u00a0 Self-motivated, positive, able to work under pressure & independently\n\u00a0\u00a0\u00a0\u00a0\u00a0\u00a0\u00a0\u00a0 Willing to work overtime\n\u00a0\u00a0\u00a0\u00a0\u00a0\u00a0\u00a0\u00a0 Occasional travel to PRC/overseas is required\n\u00a0\u00a0\u00a0\u00a0\u00a0\u00a0\u00a0\u00a0 Related disciplines and holder of CCNP and MCSE is an advantage\n\nApplication:\n\nWe offer 5-day work week and remuneration package to the right candidate. Interested parties please submit your full resume with expected salary and date of availability to Group Administrative Services Department by clicking the \"Apply Now\" button.\n\nAll personal data collected will be used for recruitment purpose only and kept confidential.\u00a0\n\nwww.fshl.com", "employment_types": ["Full Time", "Permanent"], "selling_points": [], "locations": ["Kwai Hing"], "categories": ["Information Technology (IT)", "Application Specialist - Software", "IT Project Management / Team Lead", "Application Specialist - Network"], "post_time": "2022-01-13T09:57:49Z", "salary": {"currency": null, "max": null, "min": null, "period": "monthly", "term": null}, "salary_visible": false, "title_keywords": ["system administrator"], "responsibilities": ["provide support", "software", "maintenance", "system documentation", "monitor", "troubleshooting", "implementation", "hardware", "daily operations", "inventory control"], "requirements": {"degrees": ["university graduate"], "majors": ["computer science"], "languages": [], "language_level": [], "hard_skills": ["lync", "mcse", "servers", "active directory", "dns", "sccm", "tcp", "ccnp", "information system", "ip", "hardware", "nas", "exchange"], "soft_skills": ["self-motivated", "independently", "work overtime", "troubleshooting", "hands on", "active", "positive", "work under pressure"], "languages_combined": []}, "experience_required": {"duration": ["minimum 4-year"], "field": ["installation", "system support", "operation", "administration"]}}, {"job_id": "100003009045357", "location_code": "hk", "company": "Foodgears Industrial International Limited", "job_title": "Senior IT Application Support Analyst", "description": "Responsibilities\nResponsible for designing and implementing organizational technology for businesses. Create solutions for collecting and analyzing market data, customer input, and client information.\nInvolve to implement ERP system, software and hardware for APAC Offices\nProvide all kinds of technical support, troubleshooting & solutions to the problems on IT systems, networks, software & hardware\nAssist projects with Ad Hoc tasks\n\n\nRequirement\nHigher Diploma Holder in Information System / Computer Science or related discipline\n3 years or above of relevant I.T. experience in commercial or industrial organization\nHands on experience in ERP System, Windows Server, MS SQL Server/Office products and network is a must\nSound knowledge in any BI Report tools\nGood written and spoken English, Cantonese and Mandarin are required for supporting local and APAC users\nGood inter-personal and communication skills\n\n\nRemuneration\n5 Working Days\nBank Holidays\nDental & Medical Coverage\n\n\nWe offer attractive remuneration package to the right candidate.\u00a0 Interested parties please send full resume with present & expected salary and available date by clicking \"Apply Now\".\nAll personal data collected will be used for recruitment purpose only.", "employment_types": ["Full Time", "Permanent"], "selling_points": [], "locations": ["Wong Tai Sin Area"], "categories": ["Information Technology (IT)", "IT Management", "Application Specialist - Network", "Network & System"], "post_time": "2022-01-13T07:40:52Z", "salary": {"currency": null, "max": null, "min": null, "period": "monthly", "term": null}, "salary_visible": false, "title_keywords": ["analyst", "application support"], "responsibilities": ["software", "technical support", "client information", "systems", "troubleshooting", "ad hoc tasks", "hardware", "designing", "market data"], "requirements": {"degrees": ["higher diploma holder"], "majors": ["computer science"], "languages": ["cantonese", "english", "mandarin"], "language_level": ["good"], "hard_skills": ["bi", "ms sql server", "information system", "erp system", "windows server"], "soft_skills": ["communication skills", "hands on", "inter-personal"], "languages_combined": [{"language": "cantonese", "language_level": ["good"]}, {"language": "english", "language_level": ["good"]}, {"language": "mandarin", "language_level": ["good"]}]}, "experience_required": {"duration": [], "field": ["sql", "commercial", "erp system"]}}, {"job_id": "100003009046908", "location_code": "hk", "company": "Thales Transport & Security (Hong Kong) Limited", "job_title": "Professional Services Consultant (Cybersecurity)", "description": "Responsibilities\n\nHand-over customer and pre-sales information from Pre-Sales teams (scope & offer, customer context & constraints)\nContact customer to review the scope, plan the activities and review pre-requisites for the mission\nDefine and agree with customer the design of the solution and technical choices\nTravel to customer premises (usually data centre) to install and deploy our solutions\nWrite technical documentations related with installation and configuration of the solution\nGet customer acceptance to proceed with invoicing\n\nRequirements\n\nDegree in Computer Science, Cybersecurity, Information Services or a related field\nSolid delivery experience with technical skills of cryptography, IT Network and Security, and some exposure to software developments\nMinimum of 5 years of customer facing experience, in IT Network & security domain\nTechnically hands-on with skills in problems solving, development and architecture design\nFluent English (Cantonese is a plus)\nExperience on key management, encryption and hardware security modules (HSM) is a plus\n\nRequired Technical skills\n\nFamiliar with Unix/Linux and Windows systems administration\nExperience in database administration (mainly Oracle, MySQL and MS SQL)\nKnowledge of Authentication and Identity management solutions\nExperience in Key Management Interoperability Protocol (KMIP)\nProgramming background and experience (Java, C++, .NET, SQL, XML)", "employment_types": ["Full Time", "Permanent"], "selling_points": ["Programming experience is required", "5+ years of IT Network/Cybersecurity domain", "Flexible working hours"], "locations": ["Mong Kok"], "categories": ["Information Technology (IT)", "Application Specialist - Network", "Security", "Network & System"], "post_time": "2022-01-14T01:41:30Z", "salary": {"currency": null, "max": null, "min": null, "period": "monthly", "term": null}, "salary_visible": false, "title_keywords": ["consultant"], "responsibilities": ["installation", "data", "configuration", "review", "teams", "design", "invoicing", "contact", "plan", "deploy"], "requirements": {"degrees": ["degree"], "majors": ["computer science"], "languages": ["cantonese", "english"], "language_level": ["fluent"], "hard_skills": ["linux", "plus", "java", "c++", "sql", "hardware", "programming", "ms sql", "oracle"], "soft_skills": ["technical skills", "hands-on"], "languages_combined": [{"language": "cantonese", "language_level": []}, {"language": "english", "language_level": ["fluent"]}]}, "experience_required": {"duration": ["minimum of 5 years"], "field": ["management", "sql", "it", "security", "database", "programming", "administration"]}}, {"job_id": "100003009042118", "location_code": "hk", "company": "Phase Scientific International Limited", "job_title": "Senior IT Coordinator/ Executive", "description": "Job Description\n\nResponsibilities:\n\n\n-\u00a0 \u00a0 \u00a0Responsible for internal department & external vendors to manage and deliver successful technical solutions.\n\n-\u00a0\u00a0\u00a0\u00a0 Prepare proposal documents and submissions.\n\n-\u00a0\u00a0\u00a0\u00a0 Enhance the performance with business users.\n\n-\u00a0\u00a0\u00a0\u00a0 Ensure the to meet quality and schedule for different IT projects.\n\nRequirements:\n\n\n-\u00a0\u00a0\u00a0\u00a0 At least 2 years in IT experience.\n\n-\u00a0\u00a0\u00a0\u00a0 Working knowledge in software applications integration and planning.\n\n-\u00a0\u00a0\u00a0\u00a0 Able to translate complex concepts into clear and precise written document.\n\n-\u00a0\u00a0\u00a0\u00a0 Experience in quality testing and UAT on software application development.\n\nWe offer an attractive basic salary, 5-day work, on-the-job training and career advancement opportunity to the right candidates.\u00a0 Please send full resume with availability, current and expected salary by clicking \"Apply Now\"\u00a0\n\n\u00a0Benefits\n\n\u00a0\u00a0\u00a0\u00a0\u00a0\u00a0\u00a0\u00a0 Five-day work\n\u00a0\u00a0\u00a0\u00a0\u00a0\u00a0\u00a0\u00a0 Bank Holidays\n\u00a0\u00a0\u00a0\u00a0\u00a0\u00a0\u00a0\u00a0 Medical Insurance\n\u00a0\u00a0\u00a0\u00a0\u00a0\u00a0\u00a0\u00a0 12+ Days Annual leave\n\u00a0\u00a0\u00a0\u00a0\u00a0\u00a0\u00a0\u00a0 Paid Marriage Leave\n\u00a0\u00a0\u00a0\u00a0\u00a0\u00a0\u00a0\u00a0 Birthday Leave\n\n(Personal data collected will be used for recruitment purpose only.)", "employment_types": ["Full Time", "Permanent"], "selling_points": ["Internal customers and vendors management", "really to deal with customers tactfully", "always think out of the box"], "locations": ["Kwun Tong"], "categories": ["Information Technology (IT)", "Support", "Application Specialist - Network", "Technical / Functional Consulting"], "post_time": "2022-01-12T06:17:10Z", "salary": {"currency": null, "max": null, "min": null, "period": "monthly", "term": null}, "salary_visible": false, "title_keywords": ["coordinator", "executive"], "responsibilities": ["quality", "schedule"], "requirements": {"degrees": [], "majors": [], "languages": [], "language_level": [], "hard_skills": ["integration"], "soft_skills": ["clear", "precise"], "languages_combined": []}, "experience_required": {"duration": ["at least 2 years"], "field": ["testing", "application development", "it experience"]}}, {"job_id": "100003009043914", "location_code": "hk", "company": "Be Myjob Company Limited", "job_title": "Network and Voice Engineer (iBank / Securities Firm)", "description": "Responsibilities:\nManaging day to day operations for telephony systems, voice recording preservations\nProvides systems support and problem resolution for Voice Services, and Voice Recording. This includes voice recorder and telephone system management, daily health checks, patching and troubleshooting\nProvide end-user support on voice services/desktop\nCollaborates with the business, along with the technical and operational groups across the firm to ensure alignment of technical solutions to the business strategy, use and deployment of best practices in business support solutions, and the alignment and application of firm operational and security standards.\nResponsible for router, firewall and IP networking equipment installation, administration and maintenance\nVendor and Project management\nManage IT asset and server hardware inventory\nHardware/software setup, maintenance and trouble-shooting\nFollow up ad-hoc task\n\nRequirements:\n\nDegree holder in Computer Science, Information Engineering or related discipline(s)\nMinimum 3 years of experience in switching, routing, and firewall technologies and network security principles. Cisco(R&S), Huawei, wireless, Firewalls (cisco/Palo Alto/Fortinet)\nHands-on experience in managing enterprise voice systems (e.g. Cisco CUCM, Avaya, Siemens\u2026other), Voice Recording platforms (e.g. NICE, Red Box)\nHands-on experience in supporting front office Trade Floor voice systems, working with traders, infrastructure (e.g. IPC, BT, etc.)\nProven strong record of meeting strategic technology targets and deliverables operational demands while under stressful time constraints and demands\nKnowledge in Windows, LINUX and UNIX platform administration would be an advantage Holder of CCNP is definitely an advantage\nOccasionally work in a non-office hours as project needs\nGood command of written and spoken English and Chinese (including Putonghua)", "employment_types": ["Full Time", "Permanent"], "selling_points": ["Listed financial institution", "Network and Voice systems and configuration", "Routers & switches, firewalls"], "locations": ["Central"], "categories": ["Information Technology (IT)", "Hardware", "Application Specialist - Network", "Network & System"], "post_time": "2022-01-13T02:26:37Z", "salary": {"currency": null, "max": null, "min": null, "period": "monthly", "term": null}, "salary_visible": false, "title_keywords": ["engineer"], "responsibilities": ["ad-hoc", "installation", "management", "day to day operations", "maintenance", "server hardware", "software", "inventory", "telephone system", "systems", "troubleshooting", "resolution", "project management", "hardware", "setup", "administration"], "requirements": {"degrees": ["degree holder"], "majors": ["engineering", "computer science"], "languages": ["putonghua", "english", "chinese"], "language_level": ["good command"], "hard_skills": ["linux", "nice", "ccnp", "firewall", "red"], "soft_skills": ["hands-on"], "languages_combined": [{"language": "putonghua", "language_level": ["good command"]}, {"language": "english", "language_level": ["good command"]}, {"language": "chinese", "language_level": ["good command"]}]}, "experience_required": {"duration": ["minimum 3 years"], "field": ["infrastructure", "security"]}}, {"job_id": "100003009044669", "location_code": "hk", "company": "Same Page Recruitment Co", "job_title": "Technician (\u5bb6\u96fb\u5b89\u88dd\u53ca\u7ef4\u4fee)", "description": "Our client is a local enterprise solution firm,\u00a0seeking for high caliber candidates to join the hardware installation team.\n\n\nInstallation of CCTV camera, IT hardware\u00a0\n\u5bb6\u96fb\u5b89\u88dd\u53ca\u7ef4\u4fee\nRepair and maintenance of electronic appliances\nMaintain software and hardware\u00a0\nDiploma in Computer Science/ Electronic Engineer or\u00a0related disciplines\nOnsite installation experience will be a plus\n\u96fb\u5de5A\u724c\nExperienced in PC support or CCTV, etc.\u00a0\u00a0\u00a0 \u00a0 \u00a0 \u00a0 \u00a0 \u00a0 \u00a0 \u00a0 \u00a0", "employment_types": ["Full Time", "Permanent"], "selling_points": ["CCTV installation", "\u96fb\u5de5A\u724c", "Bank holiday, year end bonus"], "locations": ["Central & Western Area"], "categories": ["Engineering", "Electrical / Electronics", "Information Technology (IT)", "Support", "Application Specialist - Network"], "post_time": "2022-01-13T05:14:37Z", "salary": {"currency": null, "max": null, "min": null, "period": "monthly", "term": null}, "salary_visible": false, "title_keywords": ["technician"], "responsibilities": ["installation", "software", "maintenance", "hardware", "repair", "maintain"], "requirements": {"degrees": ["diploma"], "majors": ["related disciplines", "computer science"], "languages": [], "language_level": [], "hard_skills": ["plus", "maintenance", "cctv", "hardware", "pc"], "soft_skills": [], "languages_combined": []}, "experience_required": {"duration": [], "field": ["installation"]}}, {"job_id": "100003009044285", "location_code": "hk", "company": "OCBC Wing Hang Bank Limited", "job_title": "Infrastructure Architect", "description": "Responsibilities\n\n\u200bAct as technical architect for infrastructure design based on application, system, regulatory requirements\nDefine the long-term technology strategies which allows the application developers to adopt the appropriate technical solutions for solving the business problems\nReview the technology strategies periodically to keep pace with the current demands\nAlign the Cloud infrastructure strategy for the bank\u2019s usage\nDocument the technical solutions and the standards for application developers to follow\nAct as infrastructure representative with development teams\nRequirements\n\n\u200bUniversity degree in Computer Science or related disciplines\nMinimum 10 years\u2019 experience in IT Infrastructure and Security\nSubject matter expert on one or multiple domains including network, security, servers (IBM AIX, Linux, Windows), middleware, web server, database, storage, ESB and API.\nFamiliar with policy and procedure for Financial Institute\nGood communication skills and independent\n\nAttractive remuneration package will be offered to the right candidate. Please apply with full resume stating present & expected salary and contact phone number\u00a0to\u00a0The Human Resources Manager, 10/F, 161 Queen\u2019s Road Central, Hong Kong.\u00a0Please quote the reference.\n\nPersonal data collected will be used for recruitment purpose only. For more information, please visit our website:\u00a0http://www.ocbcwhhk.com.\n\n\n\n", "employment_types": ["Full Time", "Permanent"], "selling_points": ["Technical architect", "Review the technology strategies", "Document the technical solutions"], "locations": ["Shau Kei Wan"], "categories": ["Information Technology (IT)", "Software Development", "Application Specialist - Network", "Network & System"], "post_time": "2022-01-13T03:40:27Z", "salary": {"currency": null, "max": null, "min": null, "period": "monthly", "term": null}, "salary_visible": false, "title_keywords": [], "responsibilities": ["regulatory requirements", "review", "infrastructure", "technology strategies", "design", "teams"], "requirements": {"degrees": ["degree"], "majors": ["related disciplines", "computer science"], "languages": [], "language_level": [], "hard_skills": ["web server", "linux", "servers"], "soft_skills": ["communication skills", "independent"], "languages_combined": []}, "experience_required": {"duration": ["minimum 10 years"], "field": ["infrastructure", "it", "security"]}}, {"job_id": "100003009036813", "location_code": "hk", "company": "Alchemy Recruitment Limited", "job_title": "Local Area Network Administrator", "description": "Alchemy is partnering exclusively with our global services firm in their search for a Network Administrator to join their team in Hongkong.\n\nKey duties and responsibilities of the Network Administrator include:\n\nResponsible for the implementation, support all network services and network infrastructure.\n\nProvide support on all IT hardware and LAN server software.\n\nOperate networking devices including Firewall, VLAN/LAN, WAN links, web proxies, wireless controllers & access points, server and remote access for the network services\n\nEvaluates technology options and new products.\n\nParticipates in global & regional IT projects in network perspective.\n\nHandle deployment or maintenance on network related hardware and software.\n\nSkills and experience required:\n\nProficient in spoken and written Chinese and English.\n\nBachelor\u2019s degree or above in Computer Science or related discipline.\n\nAt least 2 years\u2019 experience in IT operation and management support.\n\nExperience in information security audit is preferable.\n\nExperienced in both on-premises and cloud environment preferred.", "employment_types": ["Full Time"], "selling_points": ["multinational company", "Competitive salary", "Nice working environment"], "locations": ["Wan Chai"], "categories": ["Information Technology (IT)", "Application Specialist - Network"], "post_time": "2022-01-10T14:59:36Z", "salary": {"currency": null, "max": null, "min": null, "period": "monthly", "term": null}, "salary_visible": false, "title_keywords": ["administrator"], "responsibilities": ["network infrastructure", "provide support", "management", "software", "maintenance", "information security", "implementation", "audit", "hardware"], "requirements": {"degrees": ["degree or above", "bachelor"], "majors": ["computer science"], "languages": ["english", "chinese"], "language_level": ["proficient"], "hard_skills": ["web", "maintenance", "access points", "hardware", "deployment", "firewall", "server", "cloud environment", "wan"], "soft_skills": ["responsible"], "languages_combined": [{"language": "english", "language_level": ["proficient"]}, {"language": "chinese", "language_level": ["proficient"]}]}, "experience_required": {"duration": ["at least 2 years"], "field": ["management", "audit", "operation", "it", "security"]}}, {"job_id": "100003009050364", "location_code": "hk", "company": "Bond West Consultants", "job_title": "IT Project Team Leader (Finance Client) (45 - 60K)", "description": "(Ref Number: jobs@0114ew)\n\nOur client, an IT solution provider is now looking for high caliber candidates as follows:\n\nIT Project Team Leader\n\nResponsibilities:\n\nImplementation and support of Client's IT Infrastructure\nHandle the project of servers/ firewalls/ switches setting up\nProvide Level 3 support\nResponsible for systems/ technical support and administration on network, desktop/server hardware and software, and application systems\n\n\nRequirements:\n\nDiploma\u00a0holder of IT or others related\nAt least 4 years experience for Windows platforms support, such Microsoft Windows 8/10, Microsoft Office 2016/ 2013, Windows Server 2016/ 2012 and Microsoft Exchange Server\nKnowledge of TCP/ IP, LAN/ WAN, DHCP, DNS, Routing and Switching/ Firewall\nCisco Firewall/switches, VMWare exp. is a must\nCertificate Holders of CCNP, CCIE or MCSE is a plus\nGood command of written & spoken English and Mandarin\nImmediate availability is highly preferred\n\nPlease send in your full resume with last drawn, expected salary and availability\u00a0to Bond West Application Email Address\u00a0\"Click Here\"\u00a0or via\u00a0\"APPLY\" button.\n\nFor any query, please feel free to contact\u00a0Mr. Wongat 2957 8079.\n\nFor more job opportunity, please visit our website:\u00a0www.bondwest.com.hk\n\n(Data collected is only for recruitment purpose)", "employment_types": ["Full Time"], "selling_points": ["Exp. of handle finance clients", "Leading a small size team", "Focus on Infrastructure/ Network project"], "locations": ["Central"], "categories": ["Information Technology (IT)", "IT Project Management / Team Lead", "IT Management", "Application Specialist - Network"], "post_time": "2022-01-14T10:12:18Z", "salary": {"currency": null, "max": null, "min": null, "period": "monthly", "term": null}, "salary_visible": false, "title_keywords": ["team leader"], "responsibilities": ["it infrastructure", "server hardware", "software", "technical support", "systems", "implementation", "application systems", "administration"], "requirements": {"degrees": ["diploma holder", "certificate"], "majors": ["it"], "languages": ["english", "mandarin"], "language_level": ["good command"], "hard_skills": ["mcse", "plus", "dns", "vmware", "tcp", "microsoft office", "ccnp", "ip", "firewall", "server", "wan", "windows server", "microsoft exchange"], "soft_skills": [], "languages_combined": [{"language": "english", "language_level": ["good command"]}, {"language": "mandarin", "language_level": ["good command"]}]}, "experience_required": {"duration": ["at least 4 years"], "field": []}}, {"job_id": "100003009050833", "location_code": "hk", "company": "Bank of Communications Trustee Limited", "job_title": "System Support Engineer", "description": "Responsibilities\nPerform system support and maintain application servers\nAssist in project management, software installation and ad-hoc technical problems solving\nImplement Windows patches and upgrade server operating system\nPerform other administrative and emergency support\nPerform ad-hoc assignments as required\nRequirements\nDegree in computer science, information technology or equivalent\nAt least 3 years working experience in system server support and management experience\nExperience in Windows / Linux server / network / firewall configuration and software installation\nSolid experience on Windows/ Linux scripting, Citrix, Microsoft Exchange, VMWare and Veem backup solution\nIndependent, patient with good problem diagnosis and solving skills\nProficient in both spoken and written English and Chinese, Putonghua a plus\nCandidate with more experience will be considered with senior position\nImmediately available is highly preferred\nPlease click \"Apply Now\" to submit your application.\nPersonal data collected will be used for recruitment purpose only.", "employment_types": ["Full Time", "Permanent"], "selling_points": ["Perform system support", "Maintain application servers", "At least 3 years working experience"], "locations": ["Not Specified"], "categories": ["Information Technology (IT)", "Support", "Application Specialist - Network", "Network & System"], "post_time": "2022-01-14T11:31:03Z", "salary": {"currency": null, "max": null, "min": null, "period": "monthly", "term": null}, "salary_visible": false, "title_keywords": ["system support", "engineer"], "responsibilities": ["ad-hoc", "installation", "problems solving", "software", "ad-hoc assignments", "project management", "maintain"], "requirements": {"degrees": ["degree"], "majors": ["computer science", "information technology"], "languages": ["putonghua", "english", "chinese"], "language_level": ["proficient"], "hard_skills": ["linux", "plus", "vmware", "citrix", "firewall", "server", "microsoft exchange"], "soft_skills": ["patient", "independent"], "languages_combined": [{"language": "putonghua", "language_level": ["proficient"]}, {"language": "english", "language_level": ["proficient"]}, {"language": "chinese", "language_level": ["proficient"]}]}, "experience_required": {"duration": ["at least 3 years"], "field": ["installation", "management"]}}, {"job_id": "100003009044400", "location_code": "hk", "company": "PCCW Solutions", "job_title": "Senior Systems Administrator", "description": "The Job\n\nTeam member to system support team serving large scale enterprise customer\nCore duty to include providing patch management services to large scale server and desktop environment\nNon shift duty based role , out of office hour support duties to be shared amongst support team\n\nThe Person\n\n- Minimum of 1 year solid hands on patch management experience using centralized patch management tools\n\n- Hands on experience in the following areas\n\nProvide patch management services to Windows Server and Windows Desktops using centralized patch management tools , preferably IBM BigFix\nTroubleshoot patch installation errors on Windows Servers and Windows Desktops", "employment_types": ["Full Time"], "selling_points": [], "locations": ["Mong Kok"], "categories": ["Information Technology (IT)", "Support", "Application Specialist - Network", "Network & System"], "post_time": "2022-01-13T03:57:39Z", "salary": {"currency": null, "max": null, "min": null, "period": "monthly", "term": null}, "salary_visible": false, "title_keywords": ["administrator"], "responsibilities": ["patch management"], "requirements": {"degrees": [], "majors": [], "languages": [], "language_level": [], "hard_skills": ["windows server", "servers"], "soft_skills": ["hands on", "troubleshoot"], "languages_combined": []}, "experience_required": {"duration": ["minimum of 1 year"], "field": ["management"]}}, {"job_id": "100003009048633", "location_code": "hk", "company": "United Overseas Bank Limited", "job_title": "Contract Senior Officer, Business Technology and Operation Management (1-year renewable contract)", "description": "Take ownership and work on I.T. application systems project, including requirement solicitation, system design, programming, testing, implementation, documentation and support, for new and maintenance project (such as API, Data Science / Management, ETL and data visualization)\nCarry out systems application activities including coordination with overseas Head Office, trouble-shooting, testing, UAT support, implementation and production support\nWork on local business solutions, coordinate on system change request and work on ad-hoc project\nCoordinate with vendor for vendor supplied application systems\nCreate and maintain system documentation and operation procedure manuals\nEnsure deliverables comply with policies, standards and methodologies\nHandle ad-hoc projects when needed\u00a0\n\nRequirements\n\nMinimum Diploma/Degree in Computer Science, IT or related field\nKnowledge in IT system deployment/development / maintenance with at least 2-3 years in business analysis, project activities, system design and development\nGood knowledge in banking products in relation to IT systems. Good knowledge in application system design and development, databases, data flow and testing\nHands-on system technical design and development (Microsoft Macro and Access Database programming is a must; Microsoft SQL Server, API, Python and MS Power BI experience is a plus.)\nPrior experience in banking/financial sector preferable, especially on wholesale banking and deposit protection scheme\nHands-on project activities planning and handling\nSound knowledge of project life cycle and application development process\nStrong analytical and presentation skills\nProficient in English and Cantonese with good communication skills\nProactive, able to work independently and meet project deadlines", "employment_types": ["Full Time", "Contract"], "selling_points": ["Renewable Contract with Attractive Remuneration", "Banking Exposure", "Senior Officer + Excellent Learning Opportunities"], "locations": ["Causeway Bay"], "categories": ["Information Technology (IT)", "Application Specialist - Network", "Network & System"], "post_time": "2022-01-14T06:56:18Z", "salary": {"currency": null, "max": null, "min": null, "period": "monthly", "term": null}, "salary_visible": false, "title_keywords": ["senior officer"], "responsibilities": ["ad-hoc", "visualization", "data", "coordination with", "design", "communication", "maintain", "database", "ad-hoc projects", "application systems", "application development", "uat", "system documentation", "implementation", "application system", "testing", "banking", "management", "coordinate with", "documentation", "power bi", "maintenance", "it system deployment", "policies", "systems", "coordinate", "system design", "databases", "business analysis", "planning"], "requirements": {"degrees": ["diploma", "degree"], "majors": ["it", "computer science"], "languages": ["cantonese", "english"], "language_level": ["good", "proficient"], "hard_skills": ["macro", "bi", "plus", "maintenance", "analysis", "vendor", "application system", "python", "scheme", "system design", "database programming", "deployment", "programming", "data visualization", "documentation", "databases", "microsoft sql server"], "soft_skills": ["communication skills", "work independently", "hands-on", "presentation skills", "coordination", "proactive"], "languages_combined": [{"language": "cantonese", "language_level": ["good", "proficient"]}, {"language": "english", "language_level": ["good", "proficient"]}]}, "experience_required": {"duration": [], "field": ["sql", "financial", "banking"]}}, {"job_id": "100003009044398", "location_code": "hk", "company": "PCCW Solutions", "job_title": "Senior Systems Specialist", "description": "The Job\n\nImplement multi-site VMware based Private Cloud solution for FinTech Customer.\n\nThe Person\n\n- University graduate\n\n- Minimum of 10 years solid experience in IT system infrastructure implementation\n\n- Mandatory hands on technical implementation experience in the following areas\n\nHigh availability Virtualization server farm based on VMware vSphere Metro Storage Cluster (vMSC)\nMulti-Site and Multi-Pathed Fiber Channel SAN Storage and SAN Fabric, using HDS Storage with Global Active Device Implementation and Brocade SAN switches and perform data-at-rest encryption with Thales based KMS\nBackup Solution based on Veritas NetBackup with Automatic Image Replication functionality as well as Policy Lifecycle Manager\nAvailability monitoring \u00a0Solution, preferably based on MicroFocus Operation Bridge , SiteScope and Network Node Manager\nApplying CIS Level 2 Hardening for Windows Server & Red Hat Linux 8\nPatch Management experience using MicroFocus Server Automation\n\n- Mandatory Professional Certificates\n\nVMware Certified Advanced Professional - Data Center Virtualization\nITIL Intermediate Services Operation\n\n- Proficient in both written and spoken English and Chinese.", "employment_types": ["Full Time"], "selling_points": [], "locations": ["Mong Kok"], "categories": ["Information Technology (IT)", "Application Specialist - Software", "Application Specialist - Network"], "post_time": "2022-01-13T03:57:29Z", "salary": {"currency": null, "max": null, "min": null, "period": "monthly", "term": null}, "salary_visible": false, "title_keywords": ["specialist"], "responsibilities": [], "requirements": {"degrees": ["university graduate"], "majors": [], "languages": ["english", "chinese"], "language_level": ["proficient"], "hard_skills": ["itil", "red hat", "linux", "vmware", "server", "windows server"], "soft_skills": ["active", "hands on", "advanced"], "languages_combined": [{"language": "english", "language_level": ["proficient"]}, {"language": "chinese", "language_level": ["proficient"]}]}, "experience_required": {"duration": ["minimum of 10 years"], "field": ["infrastructure", "management", "it"]}}, {"job_id": "100003009045573", "location_code": "hk", "company": "HGC Global Communications Limited", "job_title": "Senior Solution Business Development Manager- Networking Solutions & Emerging Technologies", "description": "Formulate and execute the strategic business plan to maximise the business opportunities on assigned ranges of products (Networking Solution and emerging technologies) and implement product marketing programs to capture incremental revenues\nDevelop new solutions and business models based on technology trend and customer needs\nNurture and manage the relationship with vendors of assigned products, develop partnerships, drive and execute joint promotion events\nDefine product positioning and develop value propositions\nLead a team to achieve the Individual & Team business target in term of volume, sales and net revenue\n\nRequirements\n\nDegree holder in IT related, with at least 10 years\u2019 experience in sales and/or product marketing in the ICT / Telecom / IT industry\nStrong Business acumen with ability to grasp the business opportunities and drive the team to meet the assigned KPIs\nExperience in Network Solutions, Network Security, Cloud and Virtualization product development\nVendor knowledge in CISCO Network will be an advantage\nExcellent in both spoken and written Chinese and English, ability to speak in Putonghua will be an advantage\nPrior product / presales experience in networking solutions is a plus\nPassionate in new technologies\nProficiency with power-point and Excel\nCreative brainstorming, ambitious; self-starter; proactive and aggressive\nStrong people management, inter-personal and communication skills", "employment_types": ["Full Time"], "selling_points": [], "locations": ["Not Specified"], "categories": ["Management", "General Management", "Information Technology (IT)", "IT Project Management / Team Lead", "Application Specialist - Network"], "post_time": "2022-01-13T08:06:33Z", "salary": {"currency": null, "max": null, "min": null, "period": "monthly", "term": null}, "salary_visible": false, "title_keywords": ["business development manager"], "responsibilities": ["management", "business opportunities", "develop", "communication", "lead a team", "business plan", "kpis"], "requirements": {"degrees": ["degree holder"], "majors": ["it", "marketing"], "languages": ["putonghua", "english", "chinese"], "language_level": ["advantage", "excellent"], "hard_skills": ["excel", "plus", "vendor", "acumen"], "soft_skills": ["passionate", "communication skills", "creative", "inter-personal", "business acumen", "proactive"], "languages_combined": [{"language": "putonghua", "language_level": ["advantage", "excellent"]}, {"language": "english", "language_level": ["advantage", "excellent"]}, {"language": "chinese", "language_level": ["advantage", "excellent"]}]}, "experience_required": {"duration": ["at least 10 years"], "field": ["related", "it", "marketing", "security", "product development"]}}, {"job_id": "100003009042620", "location_code": "hk", "company": "ARINC Incorporated", "job_title": "Senior System Implementation Engineer", "description": "Collins Aerospace, a Raytheon Technologies company, is a leader in technologically advanced and intelligent solutions for the global aerospace and defense industry. Collins Aerospace has the capabilities, comprehensive portfolio, and expertise to solve customers\u2019 toughest challenges and to meet the demands of a rapidly evolving global market.\n\nInformation Management Services (ARINC Incorporated) business, which is part of the Connected Aviation Solutions SBU, provides critical services to airlines and aircraft operators over our secure network and hardware components.\n\nWe are seeking a Senior System Implementation Engineer to join our Airports Team, based in Hong Kong.\u00a0 We are seeking an enthusiastic team player with excellent communication skills and a strong focus on customer service who will have the following primary responsibilities, but not limited to:\n\nResponsibilities\n\nDeploy full spectrum of Airports common use systems and products \u2014 at some of the worlds\u2019 most prestigious airports within Asia Pacific.\nInstall, update, and test new and existing airline and airport applications, configure common use workstations and peripherals. Install third party software products and integrate them into Airports common use and system integration products.\nParticipate in deployment activities required for airports in APAC \u2013 Travel to customer sites, perform site surveys, interface with local technical personnel, and perform installation activities. Also assist in other critical projects at other airports within North America region and travel to other sites if and when necessary.\nConducts technical analysis of product implementations, modifications and enhancements to product in accordance with specific customer specifications and implementations.\nProvide best practices for day to day operations, performance analysis, tuning and capacity planning for products deployed and suggest and implement performance improvements when necessary.\nProactively detect problems, report and escalate the problems to next level of support when they can\u2019t be resolved in timely manner. Interface with on-site maintenance personnel, provide 3nd level supports where needed in order to meet the Service Level Agreements (SLA).\nFrequently interact with customers and coordinate with Airlines and Airport Authorities at airports regarding technical requirements, configurations and testing of airline and airport applications. Commission and hand over systems components and enhancements to customer representatives.\nInvolves in all aspects of intra-Airports technical discussions involving technical problems at sites.\nClosely liaisons with the project management organization, account management, customer support and sales team for technical exchange of information and planning of operations.\nWork with 1st and 2nd level technical support and development teams and other cross departments to assist resolving engineering issues/problems. Actively addresses performance issues and risks.\nRequirements\n\nBachelor's degree in Computer Science, Mathematics, Engineering or related technical degree.\nAt least 5 years as a system engineer at an Enterprise IT company or managed services organization\nMinimum 5 years of hands on experience in implementation and troubleshooting of enterprise networks\nIn-depth understanding of communication protocols (mainly TCP/IP) and routing protocols (e.g. BGP, OSPF)\nExperience in the installation, configuration of Cisco routers, switches, ASA routers.\nProfessional certification (e.g. CCNP, CCDP)\nHave knowledge in cloud types and cloud service models.\nHave knowledge and experience in virtualization, containerization technologies such as Dockers, Red Hat OpenShift and Kubernetes, etc.\nExperience in dealing with cloud service providers especially in AWS (amazon web services)\nExperience on implementation, administration and troubleshooting virtualization technologies (VMware, Hyper-V, Oracle VirtualBox)\nExperience on implementation, administration and troubleshooting Microsoft Window Servers.\nTravel required (30-50%)\nLocation of work is at Hong Kong International Airport\nDesired Knowledge, Skills and Experience\nExperience in airline and airports industry, airport IT systems and environment, Airport Operations and Systems Integration and/or with any of the following: common use check-in/boarding systems and peripherals, FIDS, Overhead Signage, Self-service check-in, Self-Bag Drop and Automated Self Boarding\nMonitoring application such as Whatsup Gold, Zabbix, HP Open View, etc.\nExperience with network diagnostic, monitoring and analysis tools.\nFamiliarity with access control models and network security\nFamiliarity with Self Service Bag Drop, Self-Boarding Gate and Biometrics.\nFamiliarity with IATA CUPPS CUSS\nKnowledge of coding languages for scripting (e.g Visual Basic, Html Markup, Python, Perl)", "employment_types": ["Full Time", "Permanent"], "selling_points": [], "locations": ["Airport Area"], "categories": ["Information Technology (IT)", "Application Specialist - Network"], "post_time": "2022-01-12T08:12:24Z", "salary": {"currency": null, "max": null, "min": null, "period": "monthly", "term": null}, "salary_visible": false, "title_keywords": ["engineer"], "responsibilities": ["software", "operations", "deploy", "day to day operations", "teams", "testing", "report", "installation", "management", "coordinate with", "specifications", "third party", "maintenance", "technical support", "analysis", "systems", "project management", "sales team", "planning"], "requirements": {"degrees": ["degree", "bachelor"], "majors": ["mathematics", "engineering", "computer science"], "languages": [], "language_level": [], "hard_skills": ["red hat", "hyper-v", "oracle", "airports", "vmware", "servers", "tcp", "perl", "ccnp", "analysis", "airline", "html", "aws", "python", "ip", "visual basic", "integration", "amazon web services"], "soft_skills": ["communication", "hands on", "troubleshooting"], "languages_combined": []}, "experience_required": {"duration": ["minimum 5 years"], "field": ["installation", "it", "troubleshooting", "administration"]}}, {"job_id": "100003009047073", "location_code": "hk", "company": "UCR Technology Limited", "job_title": "Infrastructure Engineer", "description": "Job Highlights\n\nProvide technical advices on Cloud and Virtualization projects\nWindows Server Administration\nStrong knowledge on vendor products\n\nResponsibilities\n\nImplement company cloud platform with on-going expansion, software\u00a0updates and scheduled\u00a0maintenance\nDesign and document cloud platform infrastructure planning and operational workflow\nResponsible for providing technical advices on cloud related projects, including new deployment, migration, system expansion and integrations with new and existing systems\nDevelop scripts for monitoring company cloud platforms\nWork with application team to enable cloud application development\nAdminister, Manage and Configure Windows Server and VM admin\nPerform system activities check, health monitoring and troubleshooting of network and security infrastructure\nInstallation and administration of network and security infrastructure\nProvide day-to-day management for infrastructure services and support, performance and service monitoring and backup operation\nPerform configuration and troubleshooting\nIT hardware and software inventory update and review\nPropose and execute continuous improvements on network operations\n\nRequirements\n\nBachelor Degree in Computer Science / Information Technology or equivalent\nMinimum 3 years of experience in windows server administration\nMinimum 3 years of experience working on Microsoft infrastructure related solution design, deployment and support\nCertified and experienced in cloud infrastructure (AWS or Microsoft Azure) is an advantage\nCredentials in the following areas are preferred: Active Directory, SCCM, SCOM, Lync, SQL, desktop deployment\nIn-depth capability and understanding of VMWare and Hyper-V\nAbility to formulae, deploy and support a VDI solution using VMWare View\u00a0\nAbility to articulate and develop solution architectures and roadmaps for clients\nExperience in designing and managing system level WAN and LANS\nStrong knowledge and experience on various vendor products, such as firewall/switch, Cisco router/firewall/switch, Fortinet firewall, etc.\nCitrix certifications & credentials (CCNA / CCNP / CCSP / CCEE / CCIA) is preferred\nMicrosoft certifications & credentials, MCSE, MCITP and/or equivalent\nExcellent communication skills with good command of written and spoken English and Cantonese\nAble to work independently & under pressure\n\nUCR Technology\u00a0is an equal opportunity employer and welcomes applications from all qualified candidates. Information provided will be treated in strict confidence and will only be used for recruitment-related purposes.", "employment_types": ["Full Time", "Permanent"], "selling_points": ["5-day work week", "Work-life balance & teamwork", "Cloud projects & operations"], "locations": ["Hung Hom"], "categories": ["Information Technology (IT)", "Support", "Application Specialist - Network", "Network & System"], "post_time": "2022-01-14T02:15:24Z", "salary": {"currency": null, "max": null, "min": null, "period": "monthly", "term": null}, "salary_visible": false, "title_keywords": ["engineer"], "responsibilities": ["software", "operations", "inventory", "troubleshooting", "design", "application development", "administration", "configuration", "infrastructure", "develop", "day-to-day management", "migration", "continuous improvements", "installation", "monitoring", "review", "maintenance", "systems", "hardware", "planning"], "requirements": {"degrees": ["degree", "bachelor"], "majors": ["computer science", "information technology"], "languages": ["cantonese", "english"], "language_level": ["excellent", "good command"], "hard_skills": ["azure", "active directory", "ccnp", "vendor", "wan", "hyper-v", "vmware", "ccna", "firewall", "sccm", "aws", "sql", "router", "citrix", "lync", "mcse", "lans", "switch", "deployment", "windows server"], "soft_skills": ["communication skills", "work independently", "confidence", "under pressure", "articulate", "active"], "languages_combined": [{"language": "cantonese", "language_level": ["excellent", "good command"]}, {"language": "english", "language_level": ["excellent", "good command"]}]}, "experience_required": {"duration": ["minimum 3 years"], "field": ["related", "infrastructure", "design", "server administration"]}}, {"job_id": "100003009042204", "location_code": "hk", "company": "Randstad Hong Kong Limited", "job_title": "Sr. System Implementation Engineer (interactive solutions,$40K)", "description": "about the company\n\nMy client is a US-based company in the aviation industry. Apart from heavy industry, they also have digital solutions providing to the commercial aviation sector. Their products are a series of interactive technologies that aim to minimize the face-to-face interactions for commercial passengers.\n\nabout the role\n\nLiaise with sales team to understand client's requirements and design a feasible plan to implement company's digital solutions to client's end\nInstall, configure, update and test new and existing applications and workstations both on-site and remotely\nSetup, configure and manage the network systems, cloud migration, cloud platform operations\nAct as L3 support to digital applications when needed and meet Service Level Agreement. Worked with regional team across APAC to deliver implementations.\nPrepare technical analysis for product implementation and enhancement with particular specifications\n\nabout the requirement\n\n5 years of experience in systems implementations, enterprise systems, or managed services. Ideally from the aviation, airport, or airline sector\nHands-on experience on L2 or L3 product support and troubleshooting\nStrong understanding in network systems and protocols (TCP/IP), and routing protocols. Holder of CCNP, CCDP will be a big plus.\nExperienced in deployment of Cisco ASA routers and switches.\nKnowledge in cloud platforms and services, ideally AWS\nUnderstanding on experience in DevOps will be an advantage, e.g., Docers, OpenShift, Kubernetes, etc.\nUnderstanding on VDI will be an advantage, e.g., VMWare, Hyper-V, VirtualBox, etc.\n\nIf you come from a background of IoT, Smart Lving, Smart Bulding, System Implementaion, or you have worked on aviation or airport projects, please do not hesitate to proceed with this opening.\n\nInterested parties, please submit your application by clicking \"apply\". Alternatively, please contact Brian Law through email at brian.law@randstad.com.hk, or through WhatsApp at +852 6275 7519.", "employment_types": ["Full Time", "Permanent"], "selling_points": ["Interactive sol. to reduce face-to-face contact", "Network, Cloud (AWS) and Virtualization", "US-based company with a stable business"], "locations": ["Not Specified"], "categories": ["Information Technology (IT)", "IT Management", "Application Specialist - Network", "Network & System"], "post_time": "2022-01-12T06:35:46Z", "salary": {"currency": "HKD", "max": 44999, "min": 35000, "period": "monthly", "term": null}, "salary_visible": true, "title_keywords": ["engineer"], "responsibilities": ["operations", "analysis", "systems", "implementation", "design", "troubleshooting", "team across", "specifications", "sales team", "plan", "liaise with", "migration", "setup"], "requirements": {"degrees": [], "majors": [], "languages": [], "language_level": [], "hard_skills": ["hyper-v", "plus", "vmware", "tcp", "ccnp", "devops", "airline", "technical analysis", "aws", "ip", "deployment", "service level agreement"], "soft_skills": ["hands-on", "troubleshooting"], "languages_combined": []}, "experience_required": {"duration": ["5 years"], "field": ["devops", "troubleshooting"]}}, {"job_id": "100003009043694", "location_code": "hk", "company": "Peoplebank Hong Kong Ltd", "job_title": "Data Centre Engineer (Freelancer & 10 months contract)", "description": "Responsibilities:\n\nWork closely with Project Manager to carry out Data Centre relocation project.\nSupport cabling planning, set-up and troubleshooting including physical installation and removal of structured cabling, and cabling components, pathway systems, and related material\nChecking and maintaining the IT facilities including:\no Test all types of cables - Copper, fibre (MM/SM), dark fibre, DWDM, MPO, etc.\no Replace cables\no Check network connections\no Trace cables\no Clean and polish fibre ends\nAccurately track, record, and maintain documentation related to cabling in designated tools and any internal tools.\nOther ad hoc duties as assigned.\n\nRequirements:\n\nWith solid experience in handling data centre relocation project.\nExperience in MNC / banking industry will be an advantage.\nGood communication skills in English and Cantonese.\nWilling to work flexibly and cope with tight project schedule.\n\nInterested parties please share the resume by Apply Now.\n\n", "employment_types": ["Full Time", "Contract"], "selling_points": ["Data Centre relocation projects for bank", "Good communication skills", "10 month contract"], "locations": ["Not Specified"], "categories": ["Information Technology (IT)", "Support", "Application Specialist - Network", "Network & System"], "post_time": "2022-01-13T01:30:56Z", "salary": {"currency": null, "max": null, "min": null, "period": "monthly", "term": null}, "salary_visible": false, "title_keywords": ["engineer"], "responsibilities": ["ad hoc duties", "installation", "maintaining", "data", "systems", "troubleshooting", "checking", "maintain documentation", "planning"], "requirements": {"degrees": [], "majors": [], "languages": ["cantonese", "english"], "language_level": ["good"], "hard_skills": [], "soft_skills": ["communication skills"], "languages_combined": [{"language": "cantonese", "language_level": ["good"]}, {"language": "english", "language_level": ["good"]}]}, "experience_required": {"duration": [], "field": ["banking industry"]}}, {"job_id": "100003009049988", "location_code": "hk", "company": "GrammyTech Ltd", "job_title": "Cyber Security Engineer", "description": "MNC retail chain is looking for a Cyber Security Engineer in Hong Kong\n\nJob Duties:\n\n\nHigher Diploma or Degree holder\u00a0\nFundamental security concepts\u00a0\u00a0\nDetect, analyze and respond to cyber-attacks\nResponse to incidents and reduce risk to different parties\nObtained Cyber security certificate a plus\nInterested parties, please send your full resume in word format together with salary expectation to danielmo @grammytech.com", "employment_types": ["Full Time"], "selling_points": ["Threat analysis", "Cyber defence", "Security solution"], "locations": ["Tsim Sha Tsui"], "categories": ["Information Technology (IT)", "Application Specialist - Network", "Security", "Network & System"], "post_time": "2022-01-14T09:36:06Z", "salary": {"currency": null, "max": null, "min": null, "period": "monthly", "term": null}, "salary_visible": false, "title_keywords": ["engineer"], "responsibilities": ["cyber security"], "requirements": {"degrees": ["certificate", "diploma", "degree holder"], "majors": [], "languages": [], "language_level": [], "hard_skills": ["plus", "cyber security"], "soft_skills": [], "languages_combined": []}, "experience_required": {"duration": [], "field": []}}, {"job_id": "100003009040326", "location_code": "hk", "company": "Orient Overseas Container Line Ltd (OOCL)", "job_title": "Technical Analyst - Enterprise Systems", "description": "Accelerate your career\n\nYou will be a core member of our System Support Team to implement & support the mission critical Enterprise System and Infrastructures including VMware.\nThis is an excellent opportunity to participate in our most challenging project of Enterprise system implementation, supporting and new technologies evaluations.\u00a0\n\nYour role\n\nEvaluate and implement efficient and scalable system management and automation tools to support our Enterprise Applications on Linux & Windows platforms. This\u00a0is an excellent opportunity to participate in our most challenging project of Enterprise system implementation, supporting and new technologies evaluations.\nProvide timely support, trouble shooting and implement the fixing in related platforms\nProvide the Disaster Recovery environment implementation and support\u00a0\n\nWho we are looking for\n\n2 years or above experience in\u00a0Virtualization, Enterprise LINUX and Windows\nExperience in Docker platform and Disaster Recovery environment design and operation\u00a0is advantageous\nExperience in developing automation scripts such as Linux Shell, PowerShell scripts, Python and Perl are also advantageous\u00a0\n\nInterested parties please send your application letter with detailed resume and expected salary by clicking \"Apply Now\" .\n\n(Data collected will be used for recruitment purpose only.)", "employment_types": ["Full Time", "Permanent"], "selling_points": ["Virtualization,Enterprise LINUX, Docker, DR Design", "Good fringe benefits", "Automation & Trouble Shooting & Maintenance"], "locations": ["Shatin Area"], "categories": ["Information Technology (IT)", "Support", "Application Specialist - Network", "Network & System"], "post_time": "2022-01-12T02:18:14Z", "salary": {"currency": null, "max": null, "min": null, "period": "monthly", "term": null}, "salary_visible": false, "title_keywords": ["analyst"], "responsibilities": ["management", "implementation", "design", "developing", "evaluate"], "requirements": {"degrees": [], "majors": [], "languages": [], "language_level": [], "hard_skills": ["linux", "vmware", "python", "powershell", "system implementation", "perl"], "soft_skills": ["efficient", "timely"], "languages_combined": []}, "experience_required": {"duration": ["2 years"], "field": ["operation", "disaster recovery", "developing", "design"]}}, {"job_id": "100003009048676", "location_code": "hk", "company": "Lloyd Karson International Limited", "job_title": "Senior Windows Engineer / Senior System Engineer - Windows(AD, O365, VM, Cloud) \u2013 FSI (HKD40 \u2013 60k)", "description": "The client is a global prestigious MNC financial Group, is now seeking a new headcount for Senior Windows Engineer / Senior System Engineer - Windows (AD, O365, VM, Cloud) \u2013 FSI (HKD40 \u2013 50k) to join their team\n\nResponsibilities:\n\nSupport on-premise and cloud infrastructure environment across the APAC region\nPerform evaluation, installation, configuration, administration, incident resolution and troubleshooting of resources including OS, hardware and software\nResponsible for the configuration, deployment and implementation of Window, AD,Office 365, VM and cloud platform\nDesign and implement new infrastructure and systems, enhance and integrate the existing operation\nPerform Disaster Recovery Drill and ensure security patches are updated and compliance with security auditing\nManage the documentation of all systems, applications and security changes, upgrades and new implementation\nAssess systems to identify potential weaknesses or problems and to ensure High Availability & Business Continuity of the internal systems and execution\nClosely collaborate with other teams for new technology solution setup and POC deployment\n\nRequirements:\n\nBachelor Degree of Computer Science, Information Technology or related disciplines\nMinimum 7 years of relevant experience in IT solutions implementation and system integration\nFamiliar with IT infrastructure or system monitoring administration/operation\nHands-on experience in Microsoft platform (Window 2012/2016/2019), Windows Active Directory, Office 365 and other related technologies, solid working knowledge of UCS/HCI/VxRail server hardware\nScripting experience is required, such as shell, bash, perl, python\nExperience of database server (MS SQL) is preferable\nStrong problem solving, communication and interpersonal skills\nGood command of both written and spoken English and Chinese\n\nIf you would like to apply for Senior Windows Engineer / Senior System Engineer - Windows (AD, O365, VM, Cloud) \u2013 FSI (HKD40 \u2013 50k) role or find out more, please click \"Apply Now\" or send your resume to arthurwong(at)lloydkarson.com quoting the reference: 134312", "employment_types": ["Full Time", "Permanent"], "selling_points": ["Support on-prem & cloud infrastructure across APAC", "Strong in Window, AD, Office 365, VM, Cloud", "Immediately available is highly preferable"], "locations": ["Quarry Bay"], "categories": ["Banking / Finance", "Others", "Information Technology (IT)", "Application Specialist - Network", "Network & System"], "post_time": "2022-01-14T07:01:20Z", "salary": {"currency": "HKD", "max": 69999, "min": 45000, "period": "monthly", "term": null}, "salary_visible": true, "title_keywords": ["engineer", "senior system engineer"], "responsibilities": ["collaborate with", "business continuity", "software", "troubleshooting", "design", "evaluation", "administration", "configuration", "infrastructure", "compliance", "implementation", "teams", "resolution", "internal systems", "setup", "installation", "upgrades", "documentation", "systems", "hardware", "auditing"], "requirements": {"degrees": ["degree", "bachelor"], "majors": ["related disciplines", "computer science", "information technology"], "languages": ["english", "chinese"], "language_level": ["good command"], "hard_skills": ["server", "office 365", "o365", "active directory", "bash", "python", "problem solving", "hardware", "integration", "ms sql", "perl"], "soft_skills": ["problem solving", "hands-on", "active", "communication and interpersonal skills"], "languages_combined": [{"language": "english", "language_level": ["good command"]}, {"language": "chinese", "language_level": ["good command"]}]}, "experience_required": {"duration": ["minimum 7 years"], "field": ["related", "sql", "it", "relevant experience", "database"]}}, {"job_id": "100003009046251", "location_code": "hk", "company": "Eternity Consultants (HK) Ltd", "job_title": "Data center Operator (permanent, bonus, 15 Anuual leave)", "description": "The datacenter of an international bank is looking for a post below:\n\n(permanent, bonus, 15 Anuual leave)\u00a0\n\nResponsibilities\n\nPerform operator\u2019s job duties from the front end to the back end\nCoordinate & liaise with different parties about operational matters\nIncident management and escalation\n\nRequirements\n\nDiploma / certificate or above in IT related discipline\nMinimum 1 years\u2019 relevant experience\n7x24 roster duty is required\n\nFor more jobs, please visit our website:\u00a0www.hketernity.com\n\n\u00a0(Personal data submitted are for recruitment purpose only.)", "employment_types": ["Full Time"], "selling_points": ["an international bank", "-", "-"], "locations": ["Not Specified"], "categories": ["Information Technology (IT)", "Support", "Application Specialist - Network", "Network & System"], "post_time": "2022-01-13T10:06:07Z", "salary": {"currency": null, "max": null, "min": null, "period": "monthly", "term": null}, "salary_visible": false, "title_keywords": ["operator"], "responsibilities": ["coordinate", "liaise with", "management", "operational matters"], "requirements": {"degrees": ["certificate", "diploma"], "majors": ["it"], "languages": [], "language_level": [], "hard_skills": [], "soft_skills": [], "languages_combined": []}, "experience_required": {"duration": ["minimum 1 years"], "field": ["relevant experience"]}}, {"job_id": "100003009044292", "location_code": "hk", "company": "OCBC Wing Hang Bank Limited", "job_title": "Technology Architect", "description": "Roles & Responsibilities\n\nWork with IDC partners to explore IDC collaboration opportunities in terms of IDC capacity expansion and service/product development\n\nSupport respective BUs in IDC bid proposal, solution preparation, quotation, technical clarification, negotiation, delivery planning etc.\n\nMaintain market intelligence database for both HKG and regional IDC markets\n\nGuide and control SLA definition with partners as well as ongoing governance\n\nSupport and provide insight in evaluating potential IDC solution and built-out projects\n\nRequirements:\n\n10-15 years in solution marketing or pre-sales experience among ICT, preferably IDC market with thorough knowledge in handling business requirements of different market segments\u00a0\n\nExperience in complex tender bid process and insight to advise business tactics\n\nKnowledgeable of IDC operational best practices including TIA-942, ISO 27001, 20000, PCI-BSS etc.\n\nGood presentation skills with technical know-how of IDC solution and latest market trend.\n\nWe offer competitive salary package and career development opportunity.\u00a0 Interested parties, please quote our reference number and apply with full resume,\u00a0present and expected salary, by clicking \"APPLY NOW\".\u00a0\n\nWe are an equal opportunity employer and welcome applications from all qualified candidates. Information provided will be treated in strict confidence and only be used for consideration of your application for the relevant post within the HGC Global Communications Limited. Personal data provided by job applicants will be used strictly according to our Personal Information Collection Statement, a copy of which will be available upon written request. Information of unsuccessful candidates will be destroyed within six months.", "employment_types": ["Full Time", "Permanent"], "selling_points": ["\u200bConsult and influence digital application teams", "Collaborate with other staff", "Develop digital architecture standards/guidelines"], "locations": ["Shau Kei Wan"], "categories": ["Information Technology (IT)", "Application Specialist - Software", "Software Development", "Application Specialist - Network"], "post_time": "2022-01-13T03:40:29Z", "salary": {"currency": null, "max": null, "min": null, "period": "monthly", "term": null}, "salary_visible": false, "title_keywords": [], "responsibilities": ["control", "clarification", "quotation", "maintain", "database", "planning"], "requirements": {"degrees": [], "majors": [], "languages": [], "language_level": [], "hard_skills": [], "soft_skills": ["presentation skills", "thorough"], "languages_combined": []}, "experience_required": {"duration": ["10-15 years"], "field": ["business", "marketing"]}}, {"job_id": "100003009045853", "location_code": "hk", "company": "Seamatch Asia Limited", "job_title": "IT Trainee - Network Engineer/ Programmer/ Business Analyst (Fresh graduates are welcome)", "description": "What are you going to do as a Native Mobile Developer?\n\nAs a Native Mobile Developer, you will be joining a leading fintech company in Asia, which operates one of the first licensed digital banks in Asia.\n\nYou will be responsible for\n\nFull-stack development with the latest technologies.\nEnhance the current applications, technical architecture enhancements, code refactoring, incorporating updated libraries.\nEnsure smooth and performant operation of applications in production.\nMaintain continuous integration and delivery by enhancing the CI/CD pipeline.\nCreate technical documentation and provide written knowledge transfer material\nMaintaining and improving existing codebases and peer review code changes\nLiaising with colleagues to implement the technical design\n\nWhat is offered to you?\n\nMonthly salary up to HKD40,000 per month\nHigh-performing, fun and diverse team\nLearning and development provided\nLively and open space office\nTeam building activities\n\nWhat is expected of you?\n\nDegree or above in Computer Science / Engineering or related field\n3+ years of professional experience in software development\nSkilled in Java, Kotlin (Android)/ Swift (iOS)\nExperience and good understanding of Test-Driven-Development (TDD), implement instrumented unit tests\nProficiency in troubleshooting software issues and debugging a large codebase\nGood logical and analytical reasoning capabilities\nFluent in English, good written and verbal communication skills\n\nWhere are you going to work?\n\nAs a talented Mobile Developer, you will join a leading fintech company in Asia, which operates one of the first licensed digital banks in Asia, as well as multiple leading online financial services businesses in Hong Kong, Mainland China and Indonesia. They strive to improve people's lives by reinventing financial services through game-changing technology.\n\nAs the only homegrown Hong Kong fintech to receive a virtual banking license, they aim to reinvent and redefine the banking experience by building a people-caring service.\n\nThey are an energetic and passionate team that can deliver and execute. They are looking for other intellectually curious, open-minded and smart-working individuals who are just as passionate as they are about making financial services enjoyable.\n\nLearn more or apply directly?\n\nHow do you feel about this Job? Are you ready for the challenges in this Dynamic Company? You can apply directly, click on the 'Apply' button. For more information about this vacancy or other opportunities, you can contact me at Larissa.li@ambitiouspeople.com or call me on 3511 6261.", "employment_types": ["Full Time", "Permanent"], "selling_points": ["ccna", "network", "engineer"], "locations": ["Central & Western Area"], "categories": ["Information Technology (IT)", "Application Specialist - Network"], "post_time": "2022-01-13T08:55:16Z", "salary": {"currency": "HKD", "max": 24999, "min": 20000, "period": "monthly", "term": null}, "salary_visible": true, "title_keywords": ["programmer", "engineer", "trainee", "business analyst"], "responsibilities": ["software issues", "software", "maintaining", "review", "liaising with", "design", "troubleshooting", "communication", "maintain", "contact", "banking", "documentation", "architecture"], "requirements": {"degrees": ["degree or above"], "majors": ["engineering", "computer science"], "languages": ["english"], "language_level": ["good", "fluent"], "hard_skills": ["java", "documentation", "fun", "swift", "mobile", "dynamic", "integration", "code", "kotlin", "android"], "soft_skills": ["passionate", "communication skills", "responsible", "open-minded", "troubleshooting", "diverse", "learning", "dynamic", "smooth", "energetic", "driven"], "languages_combined": [{"language": "english", "language_level": ["fluent", "good"]}]}, "experience_required": {"duration": ["3+ years"], "field": ["development", "banking", "banking experience", "software development"]}}, {"job_id": "100003009044393", "location_code": "hk", "company": "PCCW Solutions", "job_title": "Senior Systems Specialist", "description": "Job Highlights\n\nGood exposure in IT solutions of hospitals\nOpportunities for career development\n5-day work week, flexi\u00a0working hours\n\nJob Duties\n\nSupport day to day systems operations or infrastructure\nMonitor day to day systems log files\nProvide\u00a0technical assistance and support for incoming queries and issues related to computer systems, software, and hardware\nPrioritize tasks and complete works in accordance with the planned schedule and quality\n\nRequirements\n\nUniversity graduate or above in Computer Science, Information Technology or related disciplines\nMinimum 2 years of relevant working experience\nExperienced in hospital\u2019s IT solution is an absolute advantage\nPreferably with experience in Linux\nKnowledge of Docker and Oracle DB is a definite advantage\nGood command of written and spoken English & Chinese\nCandidates with less experience will be considered as Junior Application Specialist\n\nWorking location: Science Park (Shatin)\n\nWorking environment: http://www.ewell.hk/\u00a0\n\nInterested parties please email\u00a0full resume with current and\u00a0expected\u00a0salary and date of availability.\u00a0Candidates who cannot provide such information will not be considered for an interview.\n\n(Personal information collected will be treated in strict confidence and be used for recruitment purpose only)", "employment_types": ["Full Time"], "selling_points": [], "locations": ["Yau Ma Tei"], "categories": ["Information Technology (IT)", "Application Specialist - Network", "Network & System", "Others"], "post_time": "2022-01-13T03:57:04Z", "salary": {"currency": null, "max": null, "min": null, "period": "monthly", "term": null}, "salary_visible": false, "title_keywords": ["specialist"], "responsibilities": ["software", "operations", "systems", "monitor", "infrastructure", "computer systems", "quality", "hardware", "schedule", "technical assistance"], "requirements": {"degrees": ["university graduate or above"], "majors": ["related disciplines", "computer science", "information technology"], "languages": ["english", "chinese"], "language_level": ["good command"], "hard_skills": ["linux", "oracle"], "soft_skills": [], "languages_combined": [{"language": "english", "language_level": ["good command"]}, {"language": "chinese", "language_level": ["good command"]}]}, "experience_required": {"duration": ["minimum 2 years"], "field": ["relevant working experience"]}}, {"job_id": "100003009037629", "location_code": "hk", "company": "Senko Advanced Components (HK) Ltd", "job_title": "IT Support Specialist", "description": "Responsibilities\n\u200bConsult and influence digital application teams regarding solutions.\nCollaborate with other staff to design and implement effective technology solutions, while using innovative business and technology processes to identify and implement improvement initiatives, eliminate redundancies and maximize the reuse of applications.\nDevelop digital architecture standards/guidelines/policies based on the bank\u2019s needs, regulatory requirements and anticipated technology advances to guide\nSolutioning and project\nRecommend future technology capabilities and the overall digital enterprise architect business strategy and processes and translating business strategy and processes into actionable digital IT Systems strategy supported by well-defined future state capabilities and transition plans\nRequirements\n\u200bBachelor\u2019s Degree in Computer Science or related discipline\nKnowledge of latest Fintech technology and enterprise grade IT infrastructure especially focus on E-Channel architecture such as mobile technologies, cyber security, micro-service, SOA, Open API, cloud.\nKnowledge of regulation and compliance requirement in E-Channels\nExcellent team management and coordination skill.\n7 years\u2019 experience in an IT environment, focusing on solutions delivery\n4 years of Architecture experience including advanced knowledge of development methodologies and designing solutions\nAPI Management, REST/JSON APIs, and modern SOA expertise\nStrong decision making skills, with the ability to effectively solve business problems\nEffective organizational and communication skills including the ability to express complex concepts clearly and concisely\nRequire travel but not often\n\nAttractive remuneration package will be offered to the right candidate.\u00a0 Please apply with full resume stating present & expected salary and contact phone number\u00a0to\u00a0The Human Resources Manager, 10/F, 161 Queen\u2019s Road Central, Hong Kong.\u00a0Please quote the reference.\n\nPersonal data collected will be used for recruitment purpose only.\u00a0 For more information, please visit our website:\u00a0http://www.ocbcwhhk.com.", "employment_types": ["Full Time", "Permanent"], "selling_points": ["Oversee IT infrastructure, servers, application", "Perform server maintenance, administration, backup", "Manage external suppliers and local vendors"], "locations": ["Ngau Tau Kok"], "categories": ["Information Technology (IT)", "Application Specialist - Network", "Network & System", "Others"], "post_time": "2022-01-11T03:19:47Z", "salary": {"currency": null, "max": null, "min": null, "period": "monthly", "term": null}, "salary_visible": false, "title_keywords": ["specialist", "it support"], "responsibilities": ["collaborate with", "guidelines", "policies", "regulatory requirements", "systems", "teams", "design", "develop", "plans", "architecture"], "requirements": {"degrees": ["degree"], "majors": ["computer science"], "languages": [], "language_level": [], "hard_skills": ["mobile", "focus", "cyber security"], "soft_skills": ["communication skills", "decision making skills", "advanced", "coordination skill", "organizational", "focus"], "languages_combined": []}, "experience_required": {"duration": ["7 years", "4 years"], "field": ["development", "it"]}}, {"job_id": "100003009037870", "location_code": "hk", "company": "Seamatch Asia Limited", "job_title": "Assistant IT Manager / System Administrator / Assistant Project Manager (inhouse, 5 days work)", "description": "Our client is looking for the talent to join their team.\u00a0\n\nProgramming/ Mobile Developer:\n\nResponsibilities:\n\nResponsible for on-going in-house Web applications\u00a0and Mobile Apps developments and enhancements\nEither experience\u00a0 Java or C#, .NET programming are welcome\nInvolve in coding, testing, UAT\nProvide business applications support for the programming system\n\n\u00a0Requirements:\n\nDegree in Electronics, Computer, Information Engineering or equivalent\nInterest on programming\nCoding is requirement\nInternship or school project on coding is advantage\nFresh graduates are welcome\n\nBusiness Analyst\n\nResponsibilities\n\nParticipate in business and systems projects and ensure quality delivery of the systems\nLead requirements gathering, analysis and prepare user requirement specifications in accordance with business needs\nManage requirements throughout project life cycles\nPrepare test plan and participate in quality assurance testing cycles\nConduct SIT to ensure the enhanced systems meet the requirement specifications\nSupport UAT, prepare user manual and conduct training\nAssist project team members with the development of project documentation\nAnalyze business processes, identify problem areas of systems and recommend solutions\nCo-ordinate with users of different areas , investigate & resolve issues and concerns raised by users\nPrioritizing initiatives based on business needs and requirements\nMonitoring deliverables and ensuring timely completion of projects\n\nRequirements:\n\nDegree holder with major in Computing\nExcellent interpersonal, verbal and written communication skills\n\nFor a confidential discussion, please contact Sarah Chan on 2111 3539\n\nTo apply online please click the Apply button below.", "employment_types": ["Full Time"], "selling_points": ["Assistant IT Manager", "System Administrator", "Project Manager"], "locations": ["Not Specified"], "categories": ["Information Technology (IT)", "IT Management", "Application Specialist - Network", "Security"], "post_time": "2022-01-11T04:06:30Z", "salary": {"currency": null, "max": null, "min": null, "period": "monthly", "term": null}, "salary_visible": false, "title_keywords": ["assistant project manager", "system administrator", "it manager", "assistant"], "responsibilities": ["uat", "coding", "testing"], "requirements": {"degrees": ["degree", "degree holder"], "majors": ["engineering"], "languages": [], "language_level": [], "hard_skills": ["documentation", "analysis", "programming"], "soft_skills": ["communication skills", "timely", "interpersonal", "prioritizing"], "languages_combined": []}, "experience_required": {"duration": [], "field": []}}, {"job_id": "100003009044643", "location_code": "hk", "company": "HKT Consumer Group", "job_title": "Assistant Project Manager (IT), Smart Living B2B", "description": "Job Highlights\n\nSystem Analyst experience\nWith at least 5 years of experience in system development and implementation\nOver 18 years IT experience is preferable\nWith hands on coding experience in Java, Spring, JNI, API, JavaScript, VB/VB .Net, AngularJS and DB2.\nProactive on problem solving and provide solutions to customer.\n\nJob Description\n\nThe Job:\n\nThe successful candidates will be responsible for application implementation and ongoing maintenance support with the following scope of duties:\u00a0\n\nManage vendor for delivering project\nReview and recommend infrastructure and system architecture\nStudy requirement, analysis, design, documentation and co-ordination with users, technical and operations teams\nDevelop enhancement functions for existing system and integration with other systems\nMaintain system design, procedures, user and system manual documentation\nPrepare/Review test plan, test cases/scripts, test environments, data and perform testing\nSupport user acceptance testing and system implementation\nProvide ongoing user and application support\nWorking location :\u00a0 WanChai\u00a0\n\nThe Person:\n\nDegree or Higher Diploma holder in Computer Science, Information Technology or related disciplines\nAt least 5 years of IT experience, which includes at least 3 years of functional/specialty experience in design and/or implementation of enterprise application system(s) with over 1000 users per enterprise application system\nSolid experience in Java, SQL, JavaScript, HTML, CSS, Eclipse, J2EE, XML, Struts, Jasper report, JNI, API, VB/VB .Net, AngularJS and DB2\nProven record in developing enterprise systems\nKnowledgeable and experienced in systems analysis and design\nEffective verbal and written communication in English and Chinese\nGood analytical, inter-personal and problem solving skills\nGood team player, positive attitude, innovative, self-initiating, eager to learn and share with other team members, hardworking, able to work under pressure and work independently", "employment_types": ["Full Time"], "selling_points": [], "locations": ["Quarry Bay"], "categories": ["Information Technology (IT)", "IT Project Management / Team Lead", "Product Management / Business Analyst", "Application Specialist - Network"], "post_time": "2022-01-13T04:58:20Z", "salary": {"currency": null, "max": null, "min": null, "period": "monthly", "term": null}, "salary_visible": false, "title_keywords": ["assistant project manager"], "responsibilities": ["data", "operations", "maintenance support", "infrastructure", "review", "implementation", "analysis", "design", "teams", "develop", "systems", "maintain", "system design", "procedures", "plan", "testing", "documentation", "architecture"], "requirements": {"degrees": ["degree", "higher diploma holder"], "majors": ["related disciplines", "computer science", "information technology"], "languages": ["english", "chinese"], "language_level": [], "hard_skills": ["java", "struts", "analysis", "html", "application system", "sql", "javascript", "css", "problem solving skills"], "soft_skills": ["good team player", "work independently", "inter-personal", "communication", "positive attitude", "eager to learn", "problem solving skills", "innovative", "hardworking", "work under pressure"], "languages_combined": [{"language": "english", "language_level": []}, {"language": "chinese", "language_level": []}]}, "experience_required": {"duration": ["at least 3 years", "at least 5 years"], "field": ["sql", "design", "it experience"]}}, {"job_id": "100003009039440", "location_code": "hk", "company": "The Hong Kong University of Science and Technology", "job_title": "Associate IT Specialist (Job ID: 7039)", "description": "Responsibilities:\n\nResponsible for IT Infrastructure support, system performance and service monitoring, proactive system tuning, backup operation, Intranet / website maintenance\nUnderstand and apply system wide workflow and processes as well as relationships with other internal and external parties\nAssist company to achieve Digital Transformation through internal process automation.\nAssist and enhance IT security in Corporate standard\nBe an Administrator of Office 365 infrastructure and daily operations on system support\nWork with Development Team for in-house application enhancement\nOversee and assist IT department on IT system, cost control, analyses company needs and implement improvement solution\n\n\u00a0Requirements:\n\nMinimum 5-8 years of working experience in IT infrastructure, application system support, and or end user support, with experience in ERP, PLM, SAP\nExperience on setup, maintain oversea offices enterprise infrastructure, Active Directory, Group Policy, O365, Identify and Access Management, Windows, Linux, and cloud services (Azure)\nKnowledge in Programming language (Java / Python / C++)\nKnowledge in IT security\nWith detail minded, high accuracy and be sensitive in numbers\nWith leadership of responsibility and willing to corporate with teammates\nProficient in both spoken and written English", "employment_types": ["Full Time"], "selling_points": ["public and private cloud infrastructure", "public cloud messaging and collaboration platform", "identity and access management systems"], "locations": ["Sai Kung"], "categories": ["Information Technology (IT)", "Application Specialist - Network", "Network & System", "Others"], "post_time": "2022-01-11T09:46:53Z", "salary": {"currency": null, "max": null, "min": null, "period": "monthly", "term": null}, "salary_visible": false, "title_keywords": ["associate", "it specialist"], "responsibilities": ["it infrastructure", "monitoring", "internal and external parties", "website maintenance", "infrastructure", "daily operations", "cost control"], "requirements": {"degrees": [], "majors": [], "languages": ["english"], "language_level": ["proficient"], "hard_skills": ["o365", "linux", "java", "azure", "active directory", "sap", "c++", "application system", "erp", "programming", "python"], "soft_skills": ["active", "leadership", "sensitive"], "languages_combined": [{"language": "english", "language_level": ["proficient"]}]}, "experience_required": {"duration": ["minimum 5-8 years"], "field": ["infrastructure", "system support", "it", "management"]}}, {"job_id": "100003009044284", "location_code": "hk", "company": "OCBC Wing Hang Bank Limited", "job_title": "Developer Analyst / Application Specialist", "description": "The successful candidate will be part of the Product Development & Management Team responsible for managing the portfolio of existing/ new products, implementing product plans and actions. He/she also needs to have excellent business and marketing sense in applying available technologies, development & support resources to meet customer requirements.\n\nThe team has been successful in capturing new business opportunities with advanced solutions and services, targeting for residential property developers. On this particular position, the candidate will be responsible to manage IT projects, resources planning, coordination & support on Application Server, Network Infrastructure, Database for the IT systems at clients\u2019 projects. Liaison with clients, internal/ external application development teams, equipment vendors, production of project proposals & managing contractor relationship are part of his / her routine. Capability to provide timely responses to support tenders and strong project management skill is a prerequisite.\n\nTo Succeed in this Role\n\nDegree holder in Information Technology, Computer Science or other equivalent engineering disciplines\nAt least 5 years solid IT experience, such as server deployment, upgrade & data backup/migration projects, IT system design & implementation, security protection, etc.\nStrong project management skills\nSelf-initiated, highly motivated, meticulous and result-oriented\nHighly organized and able to perform under pressure\nGood command of both spoken and written Chinese and English", "employment_types": ["Full Time", "Permanent"], "selling_points": ["Design and integrate system components", "Design programming work units", "Supervise Developers and perform code review"], "locations": ["Shau Kei Wan"], "categories": ["Information Technology (IT)", "Software Development", "Application Specialist - Network", "Network & System"], "post_time": "2022-01-13T03:40:27Z", "salary": {"currency": null, "max": null, "min": null, "period": "monthly", "term": null}, "salary_visible": false, "title_keywords": ["analyst", "developer", "application specialist"], "responsibilities": ["network infrastructure", "management team", "data", "business opportunities", "systems", "teams", "implementation", "project management", "system design", "coordination", "database", "plans", "application development", "migration", "planning"], "requirements": {"degrees": ["degree holder"], "majors": ["engineering", "computer science", "information technology"], "languages": ["english", "chinese"], "language_level": ["good command"], "hard_skills": ["project management", "system design", "deployment", "server", "application server"], "soft_skills": ["meticulous", "organized", "marketing sense", "advanced", "responsible", "under pressure", "project management skills", "timely", "motivated", "coordination", "project management skill", "result-oriented"], "languages_combined": [{"language": "english", "language_level": ["good command"]}, {"language": "chinese", "language_level": ["good command"]}]}, "experience_required": {"duration": ["at least 5 years"], "field": ["it system design", "security", "it experience"]}}, {"job_id": "100003009037692", "location_code": "hk", "company": "Randstad Hong Kong Limited", "job_title": "Network Engineer (Securities Firm, $50K basic plus bonus)", "description": "Our client is a well-known global consumer product company with long history. They are in search for a VIP Support Engineer to join their growing business\n\nJob Responsibility\n\n\nProviding first line technical support to internal users - taking enquiries by phone and email\nDealing with problems for hardware, such as servers, computers and printers, and software programs\nHandling hardware service requests such as video conference setup, new hardware etc...\nTroubleshoot and identify technical issues and reporting to technical teams\nManaging junior support staff\n\nJob Requirements\n\n\nDegree in technology related studies\nMinimum 5 years of experience in Helpdesk/Service desk role with VIP support\nExcellent communication in spoken and written English is required\nStrong customer service mindset\nQuick reaction to problems and able to offer workaround solutions in short amount of time", "employment_types": ["Full Time", "Permanent"], "selling_points": [], "locations": ["Not Specified"], "categories": ["Information Technology (IT)", "Support", "Application Specialist - Network", "Network & System"], "post_time": "2022-01-11T03:31:25Z", "salary": {"currency": "HKD", "max": 54999, "min": 30000, "period": "monthly", "term": null}, "salary_visible": true, "title_keywords": ["engineer"], "responsibilities": ["reporting", "software", "technical support", "teams", "hardware", "troubleshoot", "setup"], "requirements": {"degrees": ["degree"], "majors": [], "languages": ["english"], "language_level": ["excellent"], "hard_skills": [], "soft_skills": ["communication", "customer service"], "languages_combined": [{"language": "english", "language_level": ["excellent"]}]}, "experience_required": {"duration": ["minimum 5 years"], "field": []}}, {"job_id": "100003009038702", "location_code": "hk", "company": "AAStocks.com Limited", "job_title": "System Specialist", "description": "Job Title:\u00a0\u00a0\u00a0\u00a0\u00a0\u00a0\u00a0\u00a0\u00a0\u00a0\u00a0Associate IT Specialist\nDepartment:\u00a0 \u00a0 \u00a0Information Technology Services Center\nJob ID:\u00a0 \u00a0 \u00a0 \u00a0 \u00a0 \u00a0 \u00a0\u00a07039\n\nJob Posting Details\n\nInformation Technology Services Center (ITSC) is responsible for developing and managing the IT infrastructure of the University, and championing the wise use of IT for learning, research, and administration activities.\u00a0 The ITSC Infrastructure Systems team develops and supports various IT infrastructures and systems including but not limited to the following areas: (1) public and private cloud infrastructure; (2) public cloud messaging and collaboration platform; (3) identity and access management systems; (4) Windows desktop environment; and (5) web server clusters.\n\nOur team is looking for a high-caliber individual to fill the position of Associate IT Specialist.\u00a0 The appointee will undertake new IT projects and provide operational support of existing systems such as incident follow-up, change management, system update and enhancement.\n\nApplicants should have:\n\nBachelor\u2019s degree in Computer Science, Computer Engineering, Information systems or related disciplines;\nA minimum of 3 years\u2019 experience in enterprise scale and mission-critical IT infrastructure support or implementation;\nExperience in the following disciplines:\n-\u00a0 \u00a0 \u00a0Server Administration: Windows Server, CentOS, Ubuntu\n-\u00a0 \u00a0 \u00a0Virtualization Platform: VMware vCenter and NSX\n-\u00a0 \u00a0\u00a0Collaboration Platform: Microsoft 365, Azure AD, Exchange Online, OneDrive for Business, SharePoint Online\n-\u00a0 \u00a0 \u00a0Cloud Platform: Azure identity, computing, and storage services\nHolder of following certificates or related is an advantage:\n-\u00a0 \u00a0 \u00a0Microsoft Certified: Azure Fundamentals\n-\u00a0 \u00a0 \u00a0Microsoft 365 Certified: Fundamentals\n-\u00a0 \u00a0 \u00a0VMware Certified Professional \u2013 Data Center Virtualization\n-\u00a0 \u00a0 \u00a0ITIL Foundation;\nGood command of written and spoken English and Chinese languages, and good analytical, problem-solving and communication skill; and\nAble to work under pressure and a good team player with self-initiative attitude\n(Duration: 2 years, renewable)\n\n\nStarting salary will be commensurate with qualifications and experience.\u00a0 Fringe benefits including annual leave, medical and dental benefits will be provided.\u00a0 A gratuity will be payable upon successful completion of contract.\n\nApplication Procedure\nIn support of a green work environment, we accept applications submitted online only. \u00a0To apply, please complete an online application form through the HKUST Careers website (https://hkustcareers.ust.hk) and return it online to the Human Resources Office on or before\u00a0Monday, 31 January 2022.\u00a0 Applicants will receive an acknowledgement by email upon successful submission.\u00a0 We thank applicants for their interest, but advise that only shortlisted candidates will be notified of the result of the application.\n\n(Information provided by applicants will be used for recruitment and other employment-related purposes only.)\n\nHKUST is an equal opportunities employer and is committed to our core values of\ninclusiveness, diversity, and respect.", "employment_types": ["Full Time", "Permanent"], "selling_points": ["Maintain and support systems", "Diploma or above in Computer Science", "3 years relevant working experience"], "locations": ["Not Specified"], "categories": ["Information Technology (IT)", "Application Specialist - Network", "Network & System", "Others"], "post_time": "2022-01-11T07:39:32Z", "salary": {"currency": null, "max": null, "min": null, "period": "monthly", "term": null}, "salary_visible": false, "title_keywords": ["specialist"], "responsibilities": ["management", "operational support", "change management", "it infrastructure", "data", "work under pressure", "system update", "systems", "infrastructure", "developing", "implementation", "communication", "administration"], "requirements": {"degrees": ["degree", "bachelor"], "majors": ["related disciplines", "computer engineering", "computer science"], "languages": ["english", "chinese"], "language_level": ["good command", "good"], "hard_skills": ["web server", "itil", "infrastructure support", "azure", "vmware", "server administration", "id", "centos", "problem-solving", "exchange", "windows server", "windows desktop", "public and private cloud"], "soft_skills": ["good team player", "responsible", "problem-solving", "communication skill", "learning", "self-initiative", "work under pressure"], "languages_combined": [{"language": "english", "language_level": ["good command", "good"]}, {"language": "chinese", "language_level": ["good command", "good"]}]}, "experience_required": {"duration": ["minimum of 3 years"], "field": ["infrastructure", "it"]}}, {"job_id": "100003009041468", "location_code": "hk", "company": "MediaPlace Limited", "job_title": "Web Developer (Social Media Analytics)", "description": "Responsibilities\n\u200bUnderstand functional, migration, security and quality requirements, business process design, workflow design and user interface design\nDesign and integrate system components: screens, reports, interfaces, automated processes\nDesign programming work units and supervise programming activities\nDesign logical and physical databases\nSupervise Developers and perform code review\nProvide technical support to Developers, and interact with various IT supports\nPrepare or/and perform system test planning and execution tasks\nDevelop procedures, training and documentation for Technical & Business users\nRequirements\n\u200bUniversity degree / Diploma holder in Information Technology or related disciplines\n5+ years in IT experience especially in Java, Oracle/MSSQL\u00a0 and SQL development\nFamiliar with Windows script, Unix/Linux script, Excel VBA added advantage\nFamiliar with SAS, SDLC and Agile development is added advantage\nExperience in implementing Microservices application and microservice design is added advantage\nExperience in API and ESB integration is preferred\nGood problem solving, communication and interpersonal skills\nGood command of spoken and written English and Chinese\nCandidate with less experience will also be considered\n\nAttractive remuneration package will be offered to the right candidate.\u00a0 Please apply with full resume stating present & expected salary and contact phone number\u00a0to\u00a0The Human Resources Manager, 10/F, 161 Queen\u2019s Road Central, Hong Kong.\u00a0Please quote the reference.\n\nPersonal data collected will be used for recruitment purpose only.\u00a0 For more information, please visit our website:\u00a0http://www.ocbcwhhk.com.", "employment_types": ["Full Time", "Permanent"], "selling_points": ["Fun, young and joyful office environment", "Birthday Leave & Anniversary Leave", "Specializing in developing BrandTech products"], "locations": ["Lai Chi Kok"], "categories": ["Information Technology (IT)", "IT - Webmaster / SEO", "Application Specialist - Network", "Network & System"], "post_time": "2022-01-12T03:55:11Z", "salary": {"currency": null, "max": null, "min": null, "period": "monthly", "term": null}, "salary_visible": false, "title_keywords": ["developer"], "responsibilities": ["technical support", "review", "quality", "procedures", "design", "develop", "user interface", "business process", "reports", "databases", "documentation", "migration", "planning"], "requirements": {"degrees": ["diploma holder", "degree"], "majors": ["related disciplines", "information technology"], "languages": ["english", "chinese"], "language_level": ["good command"], "hard_skills": ["linux", "java", "excel", "vba", "agile", "integration", "sas", "microservices", "sql", "problem solving", "sdlc", "mssql", "oracle"], "soft_skills": ["problem solving", "communication and interpersonal skills", "agile"], "languages_combined": [{"language": "english", "language_level": ["good command"]}, {"language": "chinese", "language_level": ["good command"]}]}, "experience_required": {"duration": ["5+ years"], "field": ["sql", "development", "design", "it experience"]}}, {"job_id": "100003009043070", "location_code": "hk", "company": "Synnex Technology International (HK) Ltd", "job_title": "System Engineer / Project Manager", "description": "Job Responsibilities:\nReport to the Senior Manager performing various system administrative processing:\nMaintain and support systems (with 24X7 Service Level) with duty phone\nDevelop, deploy and maintain the operation procedures with communicating to IT Operation Team\nMaintain monitor the large scale system health and routine system operations\nMaintain the installation and configuration procedures for IT infrastructure.\nActively review, monitor and improve the IT infrastructure\nCollect and present performance information related to IT infrastructure\nCoordinate and update the architecture, design and documentation of networks and systems to meet company requirements.\nEnsure to capture, prioritize and solve problems in organized manner.\nEnsure IT infrastructure security, reliability and availability\nProvide technical support to company\u2019s projects\nPrepare system documentations\nJob Requirements:\nDiploma or above in Computer Science or related subjects\n3 years relevant working experience in system and database administration, preferably in Internet industry\nHands-on experience in designing/implementing large scale infrastructure projects (including firewall, Cisco switch, load balancing, WAN, etc.)\nExperience in MS SQL Server, MySQL, Windows Server, VMware, AD and LINUX\nBasic knowledge in system scripting\nResponsible, self-motivated & independent\nPlease click \"Apply Now\" to submit your application.\nPersonal data collected will be used for recruitment purpose only.", "employment_types": ["Full Time", "Permanent"], "selling_points": [], "locations": ["Kowloon Bay"], "categories": ["Information Technology (IT)", "IT Project Management / Team Lead", "Application Specialist - Network", "Technical / Functional Consulting"], "post_time": "2022-01-12T09:42:16Z", "salary": {"currency": null, "max": null, "min": null, "period": "monthly", "term": null}, "salary_visible": false, "title_keywords": ["project manager", "system engineer"], "responsibilities": ["installation", "it infrastructure", "configuration", "operations", "technical support", "systems", "procedures", "monitor", "review", "develop", "coordinate", "design", "maintain", "deploy", "documentation", "architecture", "report"], "requirements": {"degrees": ["diploma or above"], "majors": ["computer science"], "languages": [], "language_level": [], "hard_skills": ["linux", "basic", "vmware", "ms sql server", "system scripting", "firewall", "wan", "windows server", "cisco switch"], "soft_skills": ["hands-on", "independent", "self-motivated", "responsible"], "languages_combined": []}, "experience_required": {"duration": ["3 years"], "field": ["sql", "system and database administration", "infrastructure", "relevant working experience"]}}, {"job_id": "100003009035792", "location_code": "hk", "company": "Macroview Telecom Limited", "job_title": "Senior Solution Consultant - Network Infrastructure Solutions (Pre-Sales)", "description": "The Challenge to You:\n\n\nIntroduce Cloud beauty and assist client toward Hybrid/Multi-Cloud transformation;\nStudy of major Cloud providers (Azure, AWS, Google Cloud, Alibaba Cloud\u2026 ) and present the latest cloud solutions from IaaS to SaaS to client and identify sales leads;\u00a0\nEnable Sales team and other parties for Cloud offerings to drive Cloud development;\u00a0\nSolution design, planning, and implement together with service engineer and project manager in different industries and scales;\u00a0\nProvide consultation services, POC, and professional services for Cloud business.\n\nRequirements:\n\n\nBachelor degree in Information Technology, Computer Science or related disciplines;\u00a0\n\nKnowledge of any Cloud platform with experience in major areas like compute, storage, backup & recovery, etc.;\u00a0\nStrong learner for exam and possession of existing Cloud certificate is an advantage;\u00a0\nGood presentation and interpersonal skills;\u00a0\nSelf-motivated, strong analytical reasoning and problem solving skills;\u00a0\nProficient in both spoken and written English and Chinese;\u00a0\nFresh graduates will also be considered\n\nWe offer attractive remuneration package to the right candidate.\u00a0\u00a0Including on-job training, 5 days work week, medical insurance, performance incentive, etc.\n\nFor more information about Synnex, please visit\u00a0http://www.synnex.com.hk\n\nAll information will be treated in strict confidence and will be used exclusively for recruitment related purpose only.\u00a0", "employment_types": ["Full Time", "Permanent"], "selling_points": ["Cisco CCIE / CCNP certified or equivalent", "Exp. in Cisco network infrastructure solution", "At least 5 years experience in IT networking field"], "locations": ["Quarry Bay"], "categories": ["Information Technology (IT)", "Application Specialist - Network", "Network & System", "Technical / Functional Consulting"], "post_time": "2022-01-10T08:27:02Z", "salary": {"currency": null, "max": null, "min": null, "period": "monthly", "term": null}, "salary_visible": false, "title_keywords": ["consultant", "sales"], "responsibilities": ["sales team", "design", "planning"], "requirements": {"degrees": ["certificate", "degree", "bachelor"], "majors": ["related disciplines", "computer science", "information technology"], "languages": ["english", "chinese"], "language_level": ["proficient"], "hard_skills": ["problem solving skills", "azure", "aws"], "soft_skills": ["self-motivated", "interpersonal skills", "presentation", "problem solving skills"], "languages_combined": [{"language": "english", "language_level": ["proficient"]}, {"language": "chinese", "language_level": ["proficient"]}]}, "experience_required": {"duration": [], "field": []}}, {"job_id": "100003009045494", "location_code": "hk", "company": "Michael Page", "job_title": "Senior Manager, Cloud Architect", "description": "Responsibilities:\n\nPartner with Sales team to develop business opportunities majority in enterprise network infrastructure solutions and manage presales cases closely\nUnderstand, analyze customer requirements by solution base selling approach to achieve business outcome\nResponsible for quality deliverables including technical proposal, solutions presentation and demonstration, proof of concept test (POC) and test report\nGood customer, vendor handling skills\nProvide deliverables for win-case with task list and high-level design as solution assurance for project implementation\n\n\u00a0Requirements:\n\nDegree holders in related disciplines with at least 5 years\u2019 experience in IT networking field\nCisco CCIE / CCNP certified or equivalent.\nHands-on experience in Cisco network infrastructure solution\nPassionate in ICT technology and enthusiastic to serve as pioneer in learning advanced technology\nMature, highly initiative and willing to work under pressure\nGood interpersonal communication, team player and presentation skill\nGood command of both written and spoken English and Chinese\nCandidate with following capabilities will be considered as an advantage:\nExperience in mentoring junior teammate\nKnowledge in Business Intelligence\nStrong analytical mind in analyzing statistics data\nKnowledge in SDN, SDWAN and computing scripting (e.g. Python, PowerShell etc)\u00a0\n\nWe offer attractive remuneration package, medical benefits and marriage leave to the right candidate. Interested parties please send full resume with expected salary by clicking 'Apply Now '.\n\nAll information collected will be used for recruitment purpose only.\n\nTo know more about Macroview, please visit:\u00a0http://www.macroview.com", "employment_types": ["Full Time", "Permanent"], "selling_points": ["10 - 15 years exp. with Cloud Computing & Archi.", "Cloud Program and Infrastructure Transformation", "Good facilitation and project management skills"], "locations": ["Not Specified"], "categories": ["Information Technology (IT)", "IT Project Management / Team Lead", "IT Management", "Application Specialist - Network"], "post_time": "2022-01-13T07:57:01Z", "salary": {"currency": null, "max": null, "min": null, "period": "monthly", "term": null}, "salary_visible": false, "title_keywords": ["senior manager"], "responsibilities": ["network infrastructure", "business opportunities", "quality", "implementation", "design", "develop", "sales team", "report"], "requirements": {"degrees": ["degree"], "majors": ["related disciplines", "it"], "languages": ["english", "chinese"], "language_level": ["good command"], "hard_skills": ["presentation skill", "ccnp", "powershell", "python", "business intelligence"], "soft_skills": ["passionate", "presentation skill", "advanced", "mature", "communication", "hands-on", "learning", "analytical mind", "enthusiastic", "team player", "interpersonal", "initiative", "work under pressure"], "languages_combined": [{"language": "english", "language_level": ["good command"]}, {"language": "chinese", "language_level": ["good command"]}]}, "experience_required": {"duration": ["at least 5 years"], "field": ["related", "it networking", "infrastructure"]}}, {"job_id": "100003009028170", "location_code": "hk", "company": "Nippon Express (HK) Co Ltd", "job_title": "Network Engineer", "description": "Facilitate the cloud program and infrastructure transformation within the IT Group of the company.\n\nClient Details\n\nOur client is launching strategic transformation initiatives across the business.\n\nDescription\n\nProvide architectural design and guidance for cloud adoption in multi-cloud environment.\nManage architectural standards and compliance for cloud projects, adopt cloud native technology from various cloud service providers.\nWork closely with IT Business Partnering to understand the use cases and explore the optimal options to maximise benefits to the business\nWork closely with Enterprise Architect and IT Business Enablement to establish overall technology and architecture framework. Provide expertise support to customer experience transformation, data analytic and digital workplace on architectural matters and cloud adoption.\n\nProfile\n\nBachelor's degree in IT, Computing Science, or related disciplines.\n8-10 years of experience in large-scale cloud application development plus leading a team for cloud projects.\nExtensive experience in cloud computing, such as product sourcing cost and risk management, cyber security, etc.\nGood at facilitation, project management, change management and relationship management\nProactive, performance driven and results oriented\n\nJob Offer\n\nAttractive remuneration package + Benefits\n\nTo apply online please click the 'Apply' button below. For a confidential discussion about this role please contact Connie Mo on +852 2848 9540.", "employment_types": ["Full Time", "Permanent"], "selling_points": [], "locations": ["Tsim Sha Tsui"], "categories": ["Information Technology (IT)", "Application Specialist - Network", "Network & System"], "post_time": "2022-01-07T02:55:45Z", "salary": {"currency": null, "max": null, "min": null, "period": "monthly", "term": null}, "salary_visible": false, "title_keywords": ["engineer"], "responsibilities": ["guidance", "infrastructure", "design", "compliance"], "requirements": {"degrees": [], "majors": [], "languages": [], "language_level": [], "hard_skills": ["cloud environment"], "soft_skills": [], "languages_combined": []}, "experience_required": {"duration": [], "field": []}}, {"job_id": "100003009037451", "location_code": "hk", "company": "NewPages Recruitment Company Limited", "job_title": "Mobile App Developer ( iOS / Android / Flutter) - $28K-$38K", "description": "Job Description\n\n\nResponsible for full spectrum of cyber security function in accordance with the established policies, guidelines and process\nWill be involved in new system and projects as an advisor to IT teams and business operations throughout the project life cycle to safeguard the business, systems and data\nWill be conducted security incident handling, investigation and reporting\nProvide IT compliance advice and coordinate with internal and external auditors to perform information system audit\nDevelop and enhance the security operation and monitoring\n\nRequirements\u00a0\n\nDegree in Computer Science or IT related fields\u00a0\n4-5 years of IT security and risk management experience\u00a0\nHolder of CISA / CISSP / CISM/ CEHis preferred\nFamiliar with industry frameworks, ISO27001, NIST, ITIL, PCI\nExperience in running SOC is a plus\nExcellent interpersonal and communication skills in English and Chinese (including Putonghua)\u00a0\n\nThis is a great opportunity to\u00a0be part of the team and get more new exposure. If you are interested in this role please send us your CV or call us on +852 2885 8318 for a further discussion.", "employment_types": ["Full Time"], "selling_points": ["Start-up, digital media", "Mobile App,  Android or iOS", "Young Culture: work smart, play hard"], "locations": ["Wong Tai Sin Area"], "categories": ["Information Technology (IT)", "Application Specialist - Software", "Application Specialist - Network"], "post_time": "2022-01-11T02:51:57Z", "salary": {"currency": "HKD", "max": 44999, "min": 30000, "period": "monthly", "term": null}, "salary_visible": true, "title_keywords": ["developer"], "responsibilities": ["reporting", "cyber security", "guidelines", "policies", "operations", "systems", "teams", "data", "investigation", "compliance", "coordinate with", "audit", "develop", "security operation", "monitoring", "external auditors"], "requirements": {"degrees": ["degree"], "majors": ["it", "computer science"], "languages": ["putonghua", "english", "chinese"], "language_level": ["excellent"], "hard_skills": ["itil", "plus"], "soft_skills": ["communication skills", "interested in", "interpersonal"], "languages_combined": [{"language": "putonghua", "language_level": ["excellent"]}, {"language": "english", "language_level": ["excellent"]}, {"language": "chinese", "language_level": ["excellent"]}]}, "experience_required": {"duration": ["4-5 years"], "field": ["risk management", "it", "security"]}}, {"job_id": "100003009042734", "location_code": "hk", "company": "Cornerstone Global Partners", "job_title": "Cloud Architect (Leading Bank/Insurance company)", "description": "CGP Enterprise Solution is currently working with Leading International Bank in Hong Kong for\u00a0Cloud Architect,\u00a0please feel free to reach out if interested.\n\nResponsibilities\n\nThe role of Cloud Architect requires the following high-level responsibilities related to cloud assessments, planning, and cloud migrations\nYou are expected have depth of knowledge of specified technological area, which includes knowledge of applicable processes, methodologies, standards, products and frameworks\nYou would be responsible for defining and documenting architecture, capturing and documenting non-functional (architectural) requirements, preparing estimates and defining technical solutions to proposals (RFPs)\nYou will provide technical leadership to project team to perform design to deployment related activities, provide guidance, perform reviews, prevent and resolve technical issues\n\u00a0\n\u00a0\nRequirements\n\nThe Cloud Architect role has significant experience with software development techniques and technologies and more recent experience assessing, designing and implementing complex enterprise solutions in a cloud environment\nThe Cloud Architect candidate has identified technical blockers, planned, and executed cloud migration projects\nThe candidate should possess a proven ability as a developer and architect for enterprise systems and be well-versed in a myriad of technologies to include a thorough understanding of cloud platforms, data, networking, and security\nThe candidate should have strong communication skills and be capable of interfacing with high-level system stakeholders and clients as well as developers, operators, and other technical SMEs\nThe candidate shall be capable of assessing existing applications, analyzing alternative cloud solutions, providing recommendations, and creating realistic migration roadmaps and plans\nThe candidate shall be an agent of change in application teams migrating into the cloud. They should be very familiar with the service offerings from multiple cloud service providers and the technical and business impacts of integrating with those services. Ideally the Cloud Architect will have a certification from a major cloud service provider", "employment_types": ["Permanent"], "selling_points": ["AWS", "Cloud Architect", "Insurance/Virtual Bank"], "locations": ["Central & Western Area"], "categories": ["Information Technology (IT)", "Application Specialist - Network"], "post_time": "2022-01-12T08:34:39Z", "salary": {"currency": "HKD", "max": 7999, "min": 0, "period": "monthly", "term": null}, "salary_visible": true, "title_keywords": [], "responsibilities": ["migrations", "design", "provide guidance", "architecture", "planning"], "requirements": {"degrees": [], "majors": [], "languages": [], "language_level": [], "hard_skills": ["cloud environment"], "soft_skills": ["communication skills", "capable", "thorough"], "languages_combined": []}, "experience_required": {"duration": [], "field": ["software development"]}}, {"job_id": "100003009042950", "location_code": "hk", "company": "Conwel Technology Limited", "job_title": "Programmer / Software Developer", "description": "Responsibilities:\n\n\n\nTo develop and maintain system and applications\nTo perform coding, testing and debug in different stages\nTo conduct system implementation, configuration and deployment\nTo participate in research, project analysis and system development\nTo adhere to project schedules and timelines\nTo report projects / tasks progress and status to supervisor\n\n\n\nRequirements:\n\n\n\nHigher Diploma or above in Computer Science or related disciplines\nHands on experience in .Net or .Net Core (C#)\nExcellent Programming skills in ASP.NET, Node.js\nStrong knowledge of Database, e.g. MySQL, MSSQL\nFamiliar with web servers or development tools, e.g. IIS, Nginx, Git\nExperience in web front-end development is an advantage. such as HTML, Javascript, Angular, CSS, etc.\nExperience in DevOps, Jenkins, CI/CD is an advantage\nKnowledge about MongoDB, Redis is an advantage\nKnowledge about Ai, NLP, Machine Learning is an advantage\nDemonstrate positive and can-do attitude to provide alternatives and solutions\nAct as a strong team player and proactive to resolve problem\nStrong sense of responsibility and self-motivated to embrace challenges\nGood analytical and problem-solving skills\nFresh graduates are welcome, training will be provided to the right candidate, candidates with less experience will be considered as Junior Programmer / Developer\nInterested parties please state your employment history, present and expected salary on your resume.\n\nWe are an equal opportunity employer and welcome applications from all qualified candidates. All personal information provided will be treated in strict confidence and used solely for recruitment purpose. It is possible that information about the applicant or the applicant\u2019s application will be shared within the Conpak Group.\n\nApplicants not hearing from us within 6 weeks from the date of advertisement may consider applications unsuccessful. Personal data of an unsuccessful applicant will normally be kept for a period of 2 years.", "employment_types": ["Full Time"], "selling_points": [], "locations": ["Tsim Sha Tsui"], "categories": ["Information Technology (IT)", "Software Development", "Application Specialist - Network", "Network & System"], "post_time": "2022-01-12T09:17:39Z", "salary": {"currency": null, "max": null, "min": null, "period": "monthly", "term": null}, "salary_visible": false, "title_keywords": ["developer", "programmer"], "responsibilities": ["configuration", "schedules", "analysis", "implementation", "coding", "testing", "develop", "maintain", "report"], "requirements": {"degrees": ["higher diploma or above"], "majors": ["related disciplines", "computer science"], "languages": [], "language_level": [], "hard_skills": ["git", "jenkins", "web", "ai", "problem-solving skills", "devops", "iis", "html", "javascript", "programming", "angular", "mssql", "css", "web servers", "c#"], "soft_skills": ["self-motivated", "can-do attitude", "sense of responsibility", "hands on", "learning", "problem-solving skills", "team player", "proactive", "positive"], "languages_combined": []}, "experience_required": {"duration": [], "field": ["developer", "development", "devops", "training"]}}, {"job_id": "100003009043494", "location_code": "hk", "company": "Hong Kong Exchanges and Clearing Limited", "job_title": "Senior Infrastructure Automation Engineer - Technology Infrastructure - IT - Associate - 12 months contract", "description": "Senior Infrastructure Automation Engineer is a member of the Infrastructure Automation team within HKEX Technology Infrastructure Team. This role will be responsible for supporting Infrastructure related Automation initiatives. Participate in brainstorming, writing automation code, testing & piloting code created solutions.\n\u00a0\nResponsibilities:\nWork on ongoing Automation projects to automate complex infrastructure deployment/management, repeatable tasks and to gather data for analytics and reporting\nDevelop solutions using various code using common languages such as python, powershell, ansible, Terraform etc. with Mainland Technology Centre developers\nWork closely with Infrastructure Architecture and Engineering teams to design and build advanced automated build, test, and release infrastructure.\nDesign, build, test, deploy automation code that implements an \u201cAs a service\u201d product\nGather requirements for high-level initiatives, translate and break down into actionable steps\nPrioritizes features and user stories, managing functional and technical dependencies\nFollow up and work with Mainland Technology Centre to fix defects that are encountered\nEffectively communicate engineering solutions through detailed high and low-level diagrams.\nProduce detailed design specification and other technical documentation.\nCollaborate and participate in conversations with various teams to brainstorm new insights and ways to improve infrastructure automation.\n\u00a0\nJob Requirement:\nWith at least 5 years of working experience on Infrastructure or Application Development.\nWith at least 2 years experience in developing Infrastructure as Code\nDegree in technology-related field preferred, or equivalent work or education-related experience.\nExperience on automate and execute using standard automation tools and programming languages.\nCompetent with Shell Script, PowerShell, Python\nDemonstrated experience with Infrastructure as Code (IaC) concepts and tools such as Terraform, Ansible, AWS CloudFormation, GitLab, AWS CLI, Jenkins, Artifactory, Gitlab, Dockerfile, Tanzu Build Service (TBS)\nGood understanding of Networking & Infrastructure Fundamentals\nGood understanding of large-scale infrastructure deployments in enterprise-wide environments.\nGood understanding of infrastructure security principles.\nStrong communication skills and ability to support and work in a team environment\n\nApplicants who do not hear from us within 6 weeks may consider their applications unsuccessful. Personal data provided will only be used for the purpose of employment application to HKEX.", "employment_types": ["Full Time"], "selling_points": ["Infrastructure or Application Development", "Infrastructure as Code: Terraform/ Ansible/ AWS", "Infrastructure Automation Projects"], "locations": ["Tseung Kwan O"], "categories": ["Information Technology (IT)", "Application Specialist - Network", "Network & System"], "post_time": "2022-01-12T14:25:53Z", "salary": {"currency": null, "max": null, "min": null, "period": "monthly", "term": null}, "salary_visible": false, "title_keywords": ["associate", "engineer"], "responsibilities": ["collaborate", "reporting", "management", "data", "infrastructure", "teams", "design", "develop", "deploy", "documentation", "architecture"], "requirements": {"degrees": ["degree"], "majors": [], "languages": [], "language_level": [], "hard_skills": ["jenkins", "aws", "ansible", "powershell", "programming", "python", "code"], "soft_skills": ["communication skills", "competent"], "languages_combined": []}, "experience_required": {"duration": ["at least 2 years", "at least 5 years"], "field": ["education-related", "related", "infrastructure", "developing", "programming", "application development"]}}, {"job_id": "100003009035275", "location_code": "hk", "company": "Bank of China (Hong Kong) Limited", "job_title": "Technology Risk Management \u2013 Manager (Cyber Security)", "description": "Responsibilities:\nProvide support in maintenance and administration of IT server/storage infrastructure\nProvide hardware and software installation, patch update and upgrade\nMonitor the performance of the infrastructure and performance\nManage server security\nConduct problem analysis and liaise with other team to resolve issue\nMaintain system documentation and asset inventory management\nProvides advice relating to servers and infrastructure areas\nQualifications:\nPossess a bachelor degree in Information System, Computer Studies or related disciplines is preferred\n5 year or above working experience in related field is preferred\nTechnical knowledge and experience with the following:\nAdministration of Microsoft Server, Active Directory, Group Policy, DNS and File Service\nAdministration of AIX/Linux servers and applications including Bind, Apache, SSH\nNutanix HCI and VMware ESXi\nVeeam Backup Solutions\nScripting such as shell scripts or PowerShell\nProject management skill is a plus\nBanking industry experience is at an advantage\nStrong demonstrated problem solving and documentation skills\nSelf-motivated, Good communication and interpersonal skills\nGood command of written and spoken English and Chinese\nWe offer competitive remuneration package and career prospects to the right candidate. Salary will be commensurate with qualifications and experience. Our attractive remuneration package includes 5-day work week, year-end bonus, performance bonus, dental and medical benefits, employer voluntary contributions to MPF, education allowance, staff well-being sponsorship, birthday leave, marriage leave, family care leave, etc.\n\nInterested candidates please send your full resume stating contact details, current and expected salary by clicking \u201cApply Now\u201d.\n\nPersonal data collected will be used for recruitment purpose only. We are an equal opportunity employer.", "employment_types": ["Full Time"], "selling_points": ["-", "-", "-"], "locations": ["Shatin Area"], "categories": ["Information Technology (IT)", "Application Specialist - Network"], "post_time": "2022-01-10T06:36:16Z", "salary": {"currency": null, "max": null, "min": null, "period": "monthly", "term": null}, "salary_visible": false, "title_keywords": ["manager"], "responsibilities": ["software", "active directory", "communication", "maintain", "asset inventory", "liaise with", "administration", "system documentation", "infrastructure", "banking", "installation", "provide support", "management", "documentation", "dns", "maintenance", "analysis", "hardware", "project management", "monitor the performance"], "requirements": {"degrees": ["degree", "bachelor"], "majors": ["related disciplines", "computer studies"], "languages": ["english", "chinese"], "language_level": ["good command"], "hard_skills": ["linux", "apache", "documentation", "plus", "servers", "maintenance", "active directory", "dns", "vmware", "analysis", "information system", "problem solving", "hardware", "project management", "powershell", "server"], "soft_skills": ["self-motivated", "problem solving", "communication and interpersonal skills", "project management skill", "active"], "languages_combined": [{"language": "english", "language_level": ["good command"]}, {"language": "chinese", "language_level": ["good command"]}]}, "experience_required": {"duration": ["5 year"], "field": ["related", "banking industry"]}}, {"job_id": "100003008640498", "location_code": "hk", "company": "PERSOLKELLY Hong Kong Limited", "job_title": "IT Infrastructure Engineer (30K x 13Months + Bonus / MNC Company)", "description": "Roles and Responsibilities:\n\nProvide advisory and recommendation from risk perspective.\n\nProvide Cyber Security incident response operation and support.\n\nResearch and evaluate on latest security threats and Cyber Security Intelligence.\n\nAssist to establish infrastructure review processes on network and infrastructure operation.\n\nParticipate in Cyber Security projects for the Design, development and implementation.\n\nParticipate in Red Team testing.\n\nAssist in planning of technology related risk management strategies, processes and work plans.\n\nManage independent penetration test for the corporate infrastructure.\n\nFamiliar with security testing tools e.g. Fortify, AppScan and Nessus is preferable.\n\nFamiliar with technologies on Firewall, IDS, IPS, SIEM , DevSecOps and Network/Cloud Infrastructure is preferable.\n\nFamiliar with industry good practice OWASP is preferable.\n\nJob Requirements:\n\nDegree holder in Computer Science or other degree majoring in Information Systems, or related discipline.\n\nOver 2 years of experience in IT security, technology risk, risk management, compliance or IT audit function, gained from other sizable financial institutions\n\nHolding at least one recognized professional qualification under HKMA enhanced competency framework such as CISA, CISSP, CRISC is preferable.\n\nSound knowledge of application security, \u00a0network security or platform security.\n\nGood command of written and spoken English with Mandarin is preferable.\n\nGood communication and interpersonal skills; and\n\nIndependent and strong self-initiative.\n\nCandidate with less experience will be considered", "employment_types": ["Full Time", "Permanent"], "selling_points": ["MNC Exposure", "Min 3 years of exp in infra support (L1-L2)", "Double Pay + Bonus, Perm"], "locations": ["Airport Area"], "categories": ["Information Technology (IT)", "Support", "Application Specialist - Network", "Security"], "post_time": "2022-01-11T06:27:34Z", "salary": {"currency": null, "max": null, "min": null, "period": "monthly", "term": null}, "salary_visible": false, "title_keywords": ["engineer"], "responsibilities": ["management", "cyber security", "review", "infrastructure", "implementation", "design", "testing", "evaluate", "plans", "planning"], "requirements": {"degrees": ["degree", "degree holder"], "majors": ["computer science"], "languages": ["english", "mandarin"], "language_level": ["good command"], "hard_skills": ["hkma"], "soft_skills": ["communication and interpersonal skills", "independent", "self-initiative"], "languages_combined": [{"language": "english", "language_level": ["good command"]}, {"language": "mandarin", "language_level": ["good command"]}]}, "experience_required": {"duration": ["2 years"], "field": ["risk management", "compliance", "audit", "it", "security", "financial institutions"]}}, {"job_id": "100003009038180", "location_code": "hk", "company": "Chandler Macleod Group (HK) Limited", "job_title": "Infrastructure Manager", "description": "Hip Shing Hong strives to fill work and life with positive energy, and crafts spaces that promote wellness.\n\nCome and join us to take on new challenges where your creativity is cherished.\n\nWe are looking for a talent to:\n\nResponsible for Group IT infrastructure and helpdesk support\nDeploy, support and maintain server and network infrastructures\nProvide helpdesk support to internal users\nOrganize and administer maintenance and renewal\nMaintain and update/upgrade hardware and software\nPerform change and configuration, backup, risk mitigation and disaster recovery routines\nMonitor and improve capacity, security, compatibility and performance of server, system and network operations\n\nBasic requirements:\n\nDegree holder or above in Information Technology, Computer Science or related disciplines\n3-5 years work experience in IT administration and operations of server, system, and network infrastructure\nStrong knowledge in Windows Server, IIS, Apache, VMWare (vSphere), Linux (CentOS), Unix, SQL Server, and MySQL, Firewall, TCP/IP, VOIP, VPN, LAN, VLAN, WLAN, WAN, SAN & NAS\nProficient in Windows Domain, Active Directory (Manager Account Users, OUs, Domain, Site), Group Policy Object, Backup & Recovery (Veeam & NetBackup), SAN storage and server management and virtualization\nExperience in Cloud (IaaS), Cybersecurity, Windows PowerShell or Unix Shell automation and diagnosis scripts is an advantage\nResponsible, independent and self-motivated\nGood command of both spoken and written English and Chinese\n\nBenefits:\u00a0\u00a0\n\nMedical insurance\nDental insurance\nDiscretionary year-end bonus\nEducation and training allowance\nPaid marriage leave & gift\nPaid emergency leave\nPaid children's birthday leave\nPaid compassionate leave\nAcademic scholarship\n\nWe are constantly looking for talents who are proactive and responsible to be part of our Hip Shing Hong\u2019s family. If you are a\u00a0good team player and ready for the next challenge, please apply now!\n\nTo know more about us, you are welcome to visit\u00a0www.hshd.com.hk.\n\nAll information provided by applicants will be treated in strict confidence and be used for recruitment purpose only.\u00a0", "employment_types": ["Full Time", "Permanent"], "selling_points": ["Retail industry", "Expanding Team", "Well established organisation"], "locations": ["Not Specified"], "categories": ["Information Technology (IT)", "IT Management", "Application Specialist - Network", "Technical / Functional Consulting"], "post_time": "2022-01-11T05:54:27Z", "salary": {"currency": null, "max": null, "min": null, "period": "monthly", "term": null}, "salary_visible": false, "title_keywords": ["manager"], "responsibilities": [], "requirements": {"degrees": [], "majors": [], "languages": [], "language_level": [], "hard_skills": [], "soft_skills": ["positive"], "languages_combined": []}, "experience_required": {"duration": [], "field": []}}]