[{"job_id": "100003009053018", "location_code": "hk", "company": "Viu", "job_title": "Senior Data Strategy Manager, Hong Kong", "description": "Responsibilities :\n\n\nResponsible for Java-based application services\nPerform system design, development, testing, implementation, support, maintenance and enhancement\nProvide system maintenance and support of production systems\nExplore and recommend new technology to improve existing products and services\nRequirements :\nDegree in Computer Science, Information Technology or related disciplines\nExperience in Java Development\nKnowledge of algorithm, data structure and design patterns.\nUnderstanding of distributed web application and system design.\nOOP and basic knowledge of software\u00a0\nKnowledge in Spring Frameworks, Hibernate Frameworks, applications will be an advantage\nPro-active, initiative and able to complete job assignments independently with minimum supervision\nWilling to work in competent, challenging and team-working environment", "employment_types": ["Full Time"], "selling_points": [], "locations": ["Kowloon Bay"], "categories": ["Information Technology (IT)", "Application Specialist - Software", "Technical / Functional Consulting", "Data Scientist"], "post_time": "2022-01-17T05:07:37Z", "salary": {"currency": null, "max": null, "min": null, "period": null, "term": null}, "salary_visible": false, "title_keywords": ["manager"], "responsibilities": ["maintenance", "systems", "implementation", "testing", "system design"], "requirements": {"degrees": ["degree"], "majors": ["related disciplines", "computer science", "information technology"], "languages": [], "language_level": [], "hard_skills": ["java", "hibernate", "basic", "web", "system design", "spring"], "soft_skills": ["independently", "initiative", "competent", "pro-active"], "languages_combined": []}, "experience_required": {"duration": [], "field": ["development"]}}, {"job_id": "100003009052580", "location_code": "hk", "company": "Sun Life Hong Kong Ltd", "job_title": "Senior Manager, Data Management", "description": "Responsibilities :\nGather and evaluate user requirements in collaboration with product managers and engineers\nIllustrate design ideas using storyboards, process flows and sitemaps\nDevelop UI mockups and prototypes that clearly illustrate how sites function and look like\nPrepare and present rough drafts to internal teams and key stakeholders\nIdentify and troubleshoot UX problems\u00a0\nConduct layout adjustments based on user feedback\nRequirements :\nMinimum 3 years\u2019 solid experience on UI/UX design of web application and mobile app\nExperience with large customer facing platform preferred\u00a0\nExtensive knowledge of wireframing and prototyping tools such as Sketch, Figma, and Adobe Xd\nExperience in user testing and usability analysis\nExcellent verbal and written communication skills\nImmediate availability is highly preferred\u00a0", "employment_types": ["Full Time", "Permanent"], "selling_points": ["Data Governance experiences", "Experience in designing data structure", "Machine Learning and AI"], "locations": ["Hung Hom"], "categories": ["Information Technology (IT)", "Software Development", "Others", "Data Scientist"], "post_time": "2022-01-17T03:28:11Z", "salary": {"currency": null, "max": null, "min": null, "period": "monthly", "term": null}, "salary_visible": false, "title_keywords": ["senior manager"], "responsibilities": ["ideas", "teams", "design", "develop", "evaluate", "troubleshoot", "ui", "storyboards"], "requirements": {"degrees": [], "majors": [], "languages": [], "language_level": [], "hard_skills": ["adobe xd", "mobile", "analysis", "web"], "soft_skills": ["communication skills", "extensive"], "languages_combined": []}, "experience_required": {"duration": ["minimum 3 years"], "field": ["design", "testing"]}}, {"job_id": "100003009052990", "location_code": "hk", "company": "Edvance Technology (Hong Kong) Limited", "job_title": "Technical Consultant (Cybersecurity Data Analytics)", "description": "Responsibilities:\n\n\nWorking in the Digital Products Group Department\nTesting AI, Cloud, IoT products\u00a0\nDesigning test plans, scenarios, scripts, and procedures.\nPerform UAT and SIT\nWorking with the development team to correct bugs and errors\nAgile working environment\nRequirements:\n\nMinimum of 3 years experience in QA with at least 2 years experience in Automation Testing\nA Bachelor's degree in Computer Science, Engineering, or related field\nSolid knowledge of SQL and scripting\nKnowledge of Java / Python / Node.js\u00a0\nKnowledge of Selenium\u00a0\u00a0\nGood team working and critical thinking skills.", "employment_types": ["Full Time", "Permanent"], "selling_points": ["3-5 Years Experience", "Apply Data Science in Cybersecurity", "SIEM knowledge an advantage"], "locations": ["Ngau Tau Kok"], "categories": ["Information Technology (IT)", "Data Scientist"], "post_time": "2022-01-17T04:52:43Z", "salary": {"currency": null, "max": null, "min": null, "period": "monthly", "term": null}, "salary_visible": false, "title_keywords": ["consultant"], "responsibilities": ["uat", "procedures", "testing", "designing", "plans"], "requirements": {"degrees": ["degree", "bachelor"], "majors": ["engineering", "computer science"], "languages": [], "language_level": [], "hard_skills": ["sql", "java", "python"], "soft_skills": ["team working"], "languages_combined": []}, "experience_required": {"duration": ["at least 2 years", "minimum of 3 years"], "field": ["qa", "testing"]}}, {"job_id": "100003009054155", "location_code": "hk", "company": "Hong Kong Baptist University", "job_title": "Systems Analyst (Data Analytics) (PR0465/21-22)", "description": "Responsibilities\n\nCoordinate and communicate with business users for production products\nAssist Business Analysts to ensure IT deliverables that would satisfy business requirements and would achieve anticipated business benefits\nWork with key project members e.g. project manager, developers, QA to help them understand business requirements and the processes, to ensure finished product complies with users and business specifications\n\nRequirements\n\nExcellent communication skills with possession of good problem-solving ability\nWilling to learn and work under pressure\nProactive, confident, can-do attitude\nAble to work effectively with business users and technical team\nExperience in Finance products / projects is a big plus!\nNative Cantonese Speaker\u00a0\nBenefits\n\nPassionate and Young Team\nMedical, Dental Insurance\n18 days AL\nOn-site Training\n5 days Work Week", "employment_types": ["Full Time"], "selling_points": ["Design and analyse data", "Implement data warehouse system", "Perform analysis on large/diverse datasets"], "locations": ["Kowloon City"], "categories": ["Professional Services", "Business Analysis / Data Analysis", "Information Technology (IT)", "Data Scientist"], "post_time": "2022-01-17T08:35:49Z", "salary": {"currency": null, "max": null, "min": null, "period": "monthly", "term": null}, "salary_visible": false, "title_keywords": ["analyst"], "responsibilities": ["coordinate", "communicate with"], "requirements": {"degrees": [], "majors": [], "languages": [], "language_level": [], "hard_skills": [], "soft_skills": [], "languages_combined": []}, "experience_required": {"duration": [], "field": []}}, {"job_id": "100003009054886", "location_code": "hk", "company": "Vpon HK Limited", "job_title": "Senior Operations Executive (Digital Campaign)", "description": "Responsibilities :\n\nWork closely with Project Lead to develop application for users\nMaintain and support the application for production and usage\nWeb development\u00a0\n\nRequirements :\n\nDegree holder in Computer Science or related disciplines\nExperience in PHP\u00a0\nWelcome Fresh graduates", "employment_types": ["Full Time", "Permanent"], "selling_points": ["Data Interpretation", "Data Optimizations", "Maintain & manage advertising platforms"], "locations": ["Quarry Bay"], "categories": ["Information Technology (IT)", "Product Management / Business Analyst", "Marketing / Public Relations", "Digital Marketing", "Data Scientist"], "post_time": "2022-01-17T12:37:33Z", "salary": {"currency": null, "max": null, "min": null, "period": "monthly", "term": null}, "salary_visible": false, "title_keywords": ["senior operations", "executive"], "responsibilities": ["maintain", "develop"], "requirements": {"degrees": ["degree holder"], "majors": ["related disciplines", "computer science"], "languages": [], "language_level": [], "hard_skills": ["php"], "soft_skills": [], "languages_combined": []}, "experience_required": {"duration": [], "field": []}}, {"job_id": "100003009051528", "location_code": "hk", "company": "Ma Belle Jewellery Co Ltd", "job_title": "Senior Programmer / Programmer", "description": "Responsibilities:\n\nParticipate in In-house application development including\u00a0design, development, and testing.\nDevelop frontend interfaces or backend systems, and APIs for mobile and web applications\nGathering user requirements and ensuring the platforms are able to meet the business needs.\nPerform cloud-native application development\nPrepare related technical documents.\u00a0\nRequirements:\n\nDegree / Higher Diploma in Computer Science, Information Technology or related disciplines.\n1+ years' relevant experience or above will be considered as\u00a0Software Engineer.\nFresh graduation with relevant project/ internship experience will also be considered.\nGood to have either programming of Node JS/ React JS/ Angular/ Vue.JS/ NoSQL\nHands-on development experience\u00a0\nFintech project experience is preferable\u00a0\nGood communication, presentation, and interpersonal skills\nCandidate with more experience\u00a0will be considered\u00a0as a\u00a0 Project Lead", "employment_types": ["Full Time", "Permanent"], "selling_points": ["Perform system design, development & testing", "Various Project Exposure", "Fresh Graduates are welcome"], "locations": ["Tin Hau"], "categories": ["Information Technology (IT)", "Application Specialist - Software", "Software Development", "Data Scientist"], "post_time": "2022-01-16T08:05:52Z", "salary": {"currency": null, "max": null, "min": null, "period": "monthly", "term": null}, "salary_visible": false, "title_keywords": ["programmer", "senior programmer"], "responsibilities": ["systems", "design", "develop", "testing", "application development"], "requirements": {"degrees": ["diploma", "degree"], "majors": ["related disciplines", "computer science", "information technology"], "languages": [], "language_level": [], "hard_skills": ["angular", "programming", "react"], "soft_skills": ["communication", "hands-on", "interpersonal skills", "presentation"], "languages_combined": []}, "experience_required": {"duration": ["1+ years"], "field": ["development", "relevant experience"]}}, {"job_id": "100003009051571", "location_code": "hk", "company": "GoAnimate Hong Kong Limited", "job_title": "Senior Data Analyst", "description": "Responsibilities\nTo be a team member of Business Innovation & FinTech Department\nAssist Test Manager to complete all UAT related activities\nPrepare test cases and provide appropriate planning and execution in feature testing, regression testing, integration testing, performance testing, and another non-functional testing to ensure successful application/product deployment.\nPrepare and update training materials, user manuals.\nUpdate and maintain best QA procedures and standards, including test planning, test data preparation, and test automation.\nDesign and prepare Test plans, Test Scenarios, and Test Cases according to user requirements.\nReport any findings and prepare a testing report\nRequirements\nUniversity graduate with 1-2 years\u2019 working experience in IT industry is preferable\u00a0\nPrepare UAT test cases according to the user requirement and UI design\nExecute UAT test cases in regular or ad-hoc release cycles\nReport defect/issue clearly with detail steps using the provided bug tracking tools\nGenerate daily test report for management\nSolid experience in performing UAT\nExperience with performance and/or security testing is a plus\nStrong communication and presentation skill is an advantage\nFamiliar with Excel, HPQC, JIRA\nProficient in of both spoken and written English and Chinese", "employment_types": ["Full Time", "Permanent"], "selling_points": ["Working knowledge (SQL Server, Oracle or MySQL)", "PL/SQL, Python, Ruby", "Bachelor degree or above in Computer Science"], "locations": ["Sheung Wan"], "categories": ["Information Technology (IT)", "DBA", "Others", "Data Scientist"], "post_time": "2022-01-16T11:06:20Z", "salary": {"currency": null, "max": null, "min": null, "period": "monthly", "term": null}, "salary_visible": false, "title_keywords": ["data analyst"], "responsibilities": ["uat", "performance testing", "data", "procedures", "design", "testing", "maintain", "plans", "report", "planning"], "requirements": {"degrees": ["university graduate"], "majors": ["it"], "languages": ["english", "chinese"], "language_level": ["proficient"], "hard_skills": ["presentation skill", "excel", "plus"], "soft_skills": ["communication", "presentation skill"], "languages_combined": [{"language": "english", "language_level": ["proficient"]}, {"language": "chinese", "language_level": ["proficient"]}]}, "experience_required": {"duration": ["1-2 years"], "field": ["it", "security", "testing"]}}, {"job_id": "100003009051587", "location_code": "hk", "company": "Trinity Search Limited", "job_title": "Business Analyst - Property Developer", "description": "Responsibilities:\n\nPerform data mining, analyse\u00a0large amount of data using statistical techniques and create analytics solutions.\nGather and consolidate data analytics requirements for B2B project and align with\nCouncil\u2019s data architecture.\nDesign and develop solutions for data analytics projects according to business\u00a0requirements.\nUse visualization tools to design and build dynamic dashboards and reports.\nManage and participate in data analytic project initiatives, including but not limited to data schema design, ETL design and development, data presentation and visualization.\nKeep abreast of data analytics trends and propose the use of latest data tools / cloud\u00a0services.\nRequirements:\n\nDegree or equivalent qualification in Computer Science, Statistics, Information Management or related disciplines.\n5 years of working experience as a Data Analyst.\nGood command of querying databases and using statistical computer languages: Python, R and SQL, etc.\nFamiliar with visualization tool, e.g. Tableau, Google Data Studio, Adobe Analytics.\nExperience in machine learning models would be an added advantage.\nExperience in data analytics technologies would be an added advantage, e.g. AWS,\u00a0Redshift, Athena, S3, Glue, Lambda, Kinesis.\nSolid experience in large scale data analytics and visualization.\nSelf-motivated and able to work independently.\nExcellent interpersonal, written and verbal communications skills in both English and\u00a0Chinese.\nBenefits\n\n20 Days AL\n5 days Work Week\nMedical and Dental Insurance\nEducation Allowance\nOn-site Training", "employment_types": ["Full Time"], "selling_points": ["Business Analyst", "Group Corporate Strategies", "Internal Management Consulting"], "locations": ["Central & Western Area"], "categories": ["Professional Services", "Business Analysis / Data Analysis", "Business Consultancy", "Information Technology (IT)", "Data Scientist"], "post_time": "2022-01-16T13:01:34Z", "salary": {"currency": null, "max": null, "min": null, "period": "monthly", "term": null}, "salary_visible": false, "title_keywords": ["developer", "business analyst"], "responsibilities": ["visualization", "data", "design and develop", "design", "reports", "data mining", "architecture", "analyse"], "requirements": {"degrees": ["degree"], "majors": ["related disciplines", "statistics", "computer science"], "languages": ["english", "chinese"], "language_level": ["excellent"], "hard_skills": ["data analytics", "tableau", "aws", "sql", "adobe", "databases", "python", "r", "s3"], "soft_skills": ["self-motivated", "learning", "work independently", "interpersonal"], "languages_combined": [{"language": "english", "language_level": ["excellent"]}, {"language": "chinese", "language_level": ["excellent"]}]}, "experience_required": {"duration": ["5 years"], "field": []}}, {"job_id": "100003009051750", "location_code": "hk", "company": "Pinpoint Asia Limited", "job_title": "ETL Data Senior System Analyst - Leading Bank", "description": "Responsibilities\n\nDevelop tools for application and performance monitoring\nAutomate and streamline operations and processes\nCommunicate, escalate and follow up as appropriate to ensure that problems are solved\nDevelop in cloud environments such as AWS and Azure;\nContribute to system architecture design.\nRequirements\n\nInterested in building first-class product to solve real world problems\nProficiency in one or more of the following programming languages: Python, Golang, Java or Node.js\nExperience with any of the Cloud Service Providers (CSP), including AWS or Azure or GCP or Aliyun\nDocker, Kubernetes, Cloudformation, Newrelic\nProficiency in DevOps and CI/CD would be an advantage\nCandidate with less experience but interested in DevOps are also Welcome!\n( We have 6 people in the DevOps Team and Wish YOU Join Us! )", "employment_types": ["Full Time", "Permanent"], "selling_points": ["Datawarehouse / ETL Design and Build", "Banking Perm Role", "Large Scale Project"], "locations": ["Not Specified"], "categories": ["Information Technology (IT)", "DBA", "Software Development", "Data Scientist"], "post_time": "2022-01-17T00:13:52Z", "salary": {"currency": "HKD", "max": 54999, "min": 45000, "period": "monthly", "term": null}, "salary_visible": true, "title_keywords": ["system analyst"], "responsibilities": ["operations", "monitoring", "design", "develop", "architecture"], "requirements": {"degrees": [], "majors": [], "languages": [], "language_level": [], "hard_skills": ["java", "azure", "devops", "aws", "csp", "programming", "python"], "soft_skills": ["first-class", "interested in"], "languages_combined": []}, "experience_required": {"duration": [], "field": ["devops"]}}, {"job_id": "100003009053009", "location_code": "hk", "company": "JFE Consulting Limited", "job_title": "Database Administrator", "description": "Job Description\nBe part of the delivery team to implement modules and applications\nWork closely with the creative design team on delivery\u00a0high-quality web application projects\nResponsible for hands-on development with Java web and server-side programming\nMaintain and provide system support of the existing in-house systems\nWork as a coordinator with teams and users\n\n\u00a0Requirement\n\nproficiency in\u00a0Java 8+\u00a0and Declarative/Functional Programming\nExperienced in\u00a0Spring Framework, Hibernate or OGM Tools\nExperience in Web, JS, Node.js,\u00a0Kotlin, Golang would be advantage\nExperience in MQ, Document / Graph DB would be advantage\nExperience in Public/Private Cloud, Containerization and Scalable Architecture would be advantage\nExcellent communication and interpersonal skills\nDemonstrate a positive and can-do attitude, also a strong team player\nPassionate to new technologies\nCandidate with more experience will be considered as\u00a0Senior Software Engineer\nFresh Graduate\u00a0are also Welcome!", "employment_types": ["Full Time", "Permanent"], "selling_points": ["Database Administrator", "Experienced in DB2/MS SQL", "attractive salary"], "locations": ["Quarry Bay"], "categories": ["Information Technology (IT)", "DBA", "IT Management", "Data Scientist"], "post_time": "2022-01-17T05:00:33Z", "salary": {"currency": null, "max": null, "min": null, "period": "monthly", "term": null}, "salary_visible": false, "title_keywords": ["administrator"], "responsibilities": ["systems", "teams", "quality", "design", "maintain"], "requirements": {"degrees": ["fresh graduate"], "majors": [], "languages": [], "language_level": [], "hard_skills": ["java", "hibernate", "web", "spring", "programming", "kotlin"], "soft_skills": ["passionate", "can-do attitude", "communication and interpersonal skills", "team player", "positive"], "languages_combined": []}, "experience_required": {"duration": [], "field": []}}, {"job_id": "100003009053669", "location_code": "hk", "company": "JFE Consulting Limited", "job_title": "Senior Technical Analyst - Oracle, MongoDB Database Administrator", "description": "Responsibilities\n\nTransactions bookkeeping and reconciliation of accounts\nVerify data from different reporting tools by daily/ weekly/ monthly basis\nOngoing monitoring of digital asset balances at specific cut-off times and checking digital asset movement\nInvolvement in preparing daily, weekly ,monthly treasury reports\nSupport in the development and streamline of workflows\nCoordinate with internal and external parties to handle day-to-day duties\nAssist in ad hoc tasks as assigned\n\nRequirements\n\nDegree or above in finance, accounting or economics\nExperience in Bank, FinTech, cryptocurrency and blockchain will also be considered\nAble to demonstrate basic data analytical skill and programming experiences\nThe habit of paying painstaking attention to details, correct data and following procedures meticulously\nCapable to work in a challenging, fast-paced team-oriented environment\nProficient in excel formula is a plus\nWork shift : Thursday to Monday , public holidays (Five-Day Work Week) 9am-6pm", "employment_types": ["Full Time", "Permanent"], "selling_points": ["Knowledge in ORacle DB, MongoDB, MYSQL", "Exposure to Oracle technology, e.g. Oracle DB&OEM", "Attractive salary"], "locations": ["Shatin Area"], "categories": ["Information Technology (IT)", "DBA", "IT Management", "Data Scientist"], "post_time": "2022-01-17T07:19:09Z", "salary": {"currency": null, "max": null, "min": null, "period": "monthly", "term": null}, "salary_visible": false, "title_keywords": ["analyst", "administrator"], "responsibilities": ["reporting", "data", "monitoring", "coordinate with", "checking", "transactions", "internal and external parties", "ad hoc tasks", "reports"], "requirements": {"degrees": ["degree or above"], "majors": ["finance", "accounting", "economics"], "languages": [], "language_level": [], "hard_skills": ["blockchain", "excel", "analytical skill", "plus", "basic", "programming", "cryptocurrency"], "soft_skills": ["analytical skill", "capable", "painstaking", "attention to details"], "languages_combined": []}, "experience_required": {"duration": [], "field": ["programming", "analytical"]}}, {"job_id": "100003009054043", "location_code": "hk", "company": "Konica Minolta Business Solutions (HK) Limited", "job_title": "System Analyst", "description": "Responsibilities\n\nDevelopment of iOS/ Android mobile application\nTechnical system design, development and UAT\nRequirement analysis and documentation\nCoordinate with offshore team on system development and implementation\nWork closely with internal & external parties to collect and analyze their requirements\n\nRequirements\n\nHigher Diploma or above in Technology, Computer Science, Engineering or related disciplines\nSolid experience in mobile software development on iOS or Android platform\nExperience in Kotlin, Java - Android / Swift - iOS platform / Flutter, React Native - Hybrid\nFresh graduates with programming background and strong motivation to learn will be considered\nExperienced candidates will be considered for a senior position\nFamiliar with Agile development methodology is a definite advantage\n\nWhat we can provide\n\nDouble Pay\nDiscretionary Performance Bonus\nLife Insurance\nMedical insurance\nFree Snacks and Drinks", "employment_types": ["Full Time", "Permanent"], "selling_points": ["Use State-of-the-Art development platform and tech", "Wide exposure for various customers and business", "Development and new technology"], "locations": ["Tai Koo"], "categories": ["Information Technology (IT)", "Application Specialist - Software", "Software Development", "Data Scientist"], "post_time": "2022-01-17T08:11:15Z", "salary": {"currency": null, "max": null, "min": null, "period": "monthly", "term": null}, "salary_visible": false, "title_keywords": ["system analyst"], "responsibilities": ["system design", "uat"], "requirements": {"degrees": ["higher diploma or above"], "majors": ["related disciplines", "engineering", "computer science"], "languages": [], "language_level": [], "hard_skills": ["java", "agile", "analysis", "swift", "mobile", "react native", "programming", "documentation", "kotlin", "android"], "soft_skills": ["agile"], "languages_combined": []}, "experience_required": {"duration": [], "field": ["software development"]}}, {"job_id": "100003009053597", "location_code": "hk", "company": "Toray Industries (H.K.) Limited", "job_title": "System & Software Engineer", "description": "As our business is growing, our Banking & Financial Services Division is going to hire Recruitment Consultants in order to further boost our performance. You may find the details below :\n\n\nResponsibilities :\n\nUnderstand clearly the requirements of the clients regarding different job openings\nSource candidates' profiles and contacts via various channels\nMake calls and communicate with candidates for explaining the job opportunities\nTry your best to facilitate the whole recruitment process\nFollow-up on numbers of candidates\u00a0\nModify candidates' CVs in accordance with our company standard format\nOther ad hoc duties as assigned\nRequirements :\n\nDegree or above\u00a0( Business Related would be an advantage )\nRelevant experience in Recruitment or Sales will be an advantage\nFresh Graduates are also welcome\nMotivated and target driven personality\nGood command of English, Cantonese and Mandarin", "employment_types": ["Full Time", "Permanent"], "selling_points": [], "locations": ["Tsim Sha Tsui"], "categories": ["Information Technology (IT)", "Product Management / Business Analyst", "Software Development", "Data Scientist"], "post_time": "2022-01-17T07:12:55Z", "salary": {"currency": null, "max": null, "min": null, "period": "monthly", "term": null}, "salary_visible": false, "title_keywords": ["software engineer"], "responsibilities": ["communicate with", "recruitment process", "ad hoc duties"], "requirements": {"degrees": ["degree or above"], "majors": ["business"], "languages": ["cantonese", "english", "mandarin"], "language_level": ["good command"], "hard_skills": [], "soft_skills": ["motivated", "driven"], "languages_combined": [{"language": "cantonese", "language_level": ["good command"]}, {"language": "english", "language_level": ["good command"]}, {"language": "mandarin", "language_level": ["good command"]}]}, "experience_required": {"duration": [], "field": ["recruitment", "relevant experience"]}}, {"job_id": "100003009052970", "location_code": "hk", "company": "Air Logistics Limited", "job_title": "Data Analyst", "description": "Job description:\n\nAs part of the Global Business Intelligence team you will be responsible for management of our Microsoft Analysis Services (Microsoft Tabular Model) and related processes in the Microsoft Azure Datalake. Using your skillset to realize analyse and integrate the dataflows according to the end user requirements, assemble data from various sources and produce outputs in Power BI.\n\n\nKey Responsibilities:\n\n\nManaging the developments in the Microsoft Analysis Services (Tabular model)\nCommunicating with technical and operational teams to ensure data integrity, security and optimized performance at the report and database level\nIdentifying and resolving data quality issues, validating datasets to ensure data integrity\nDetermining business requirements for reports and business intelligence solutions\nAnalyse the different Data sources and give new insights to the Business Stakeholders\nBuilding and updating dynamic Power Bi reports and dashboards, performing data quality checks\nAssisting with other data related duties\n\n\u00a0Required Experience/Education:\n\nBachelor\u2019s Degree in Analytics, Information Technology, Computer Science, Statistics, Engineering, Logistics, Supply Chain or another analytical discipline from an accredited college or university or equivalent experience\n3+ years of Data Analysis experience would be preferred\n\nRequired Skill:\n\n\nMicrosoft Analysis Services (Tabular model) experience has the preference\nExperience in Power BI or Tableau is preferred\nExperience in Python, SQL or Databricks is an advantage\nGood knowledge of DAX language is an advantage\nGood understanding to analyse & visualize data\nStrong speaking and writing English skills\n\nWe offer 5 days work with medical plan. Interested parties please send resume with current & salary expected\u00a0 and available date.\u00a0 All information provided will be treated in strict confidential and used solely for recruitment purposes.", "employment_types": ["Full Time", "Permanent"], "selling_points": ["5-day work", "Mulit-national environment", "Ensure the accuracy and integrity of data"], "locations": ["Lai Chi Kok"], "categories": ["Information Technology (IT)", "Product Management / Business Analyst", "Data Scientist"], "post_time": "2022-01-17T04:45:15Z", "salary": {"currency": null, "max": null, "min": null, "period": "monthly", "term": null}, "salary_visible": false, "title_keywords": ["data analyst"], "responsibilities": ["management", "power bi", "data", "analysis", "teams", "quality", "data analysis", "communicating with", "reports", "logistics", "database", "report", "analyse"], "requirements": {"degrees": [], "majors": [], "languages": ["english"], "language_level": [], "hard_skills": ["bi", "analysis", "tableau", "sql", "python"], "soft_skills": [], "languages_combined": [{"language": "english", "language_level": []}]}, "experience_required": {"duration": [], "field": ["sql"]}}, {"job_id": "100003009056204", "location_code": "hk", "company": "DFI Retail Group DFI\u96f6\u552e\u96c6\u5718", "job_title": "Senior/ Customer Insights Senior Analyst - yuu", "description": "Responsibilities\n\nDevelopment of iOS/ Android mobile application\nTechnical system design, development and UAT\nRequirement analysis and documentation\nCoordinate with offshore team on system development and implementation\nWork closely with internal & external parties to collect and analyze their requirements\n\nRequirements\n\nHigher Diploma or above in Technology, Computer Science, Engineering or related disciplines\nSolid experience in mobile software development on iOS or Android platform\nExperience in Kotlin, Java - Android / Swift - iOS platform / Flutter, React Native - Hybrid\nFresh graduates with programming background and strong motivation to learn will be considered\nExperienced candidates will be considered for a senior position\nFamiliar with Agile development methodology is a definite advantage\n\nWhat we can provide\n\nDouble Pay\nDiscretionary Performance Bonus\nLife Insurance\nMedical insurance\nFree Snacks and Drinks", "employment_types": ["Permanent"], "selling_points": ["Sales and yuu customer data analysis", "From business issues into analytical project", "Spark, SQL, Python"], "locations": ["Quarry Bay"], "categories": ["Information Technology (IT)", "Data Scientist"], "post_time": "2022-01-18T03:32:25Z", "salary": {"currency": null, "max": null, "min": null, "period": "monthly", "term": null}, "salary_visible": false, "title_keywords": ["senior analyst"], "responsibilities": ["system design", "uat"], "requirements": {"degrees": ["higher diploma or above"], "majors": ["related disciplines", "engineering", "computer science"], "languages": [], "language_level": [], "hard_skills": ["java", "agile", "analysis", "swift", "mobile", "react native", "programming", "documentation", "kotlin", "android"], "soft_skills": ["agile"], "languages_combined": []}, "experience_required": {"duration": [], "field": ["software development"]}}, {"job_id": "100003009053762", "location_code": "hk", "company": "ST Partnership Limited", "job_title": "Data Analyst (Power BI/ Alteryx) - Reputable MNC Supply Chain", "description": "Responsibilities:\n\nUnderstand the business of CRM and platform product ecosystem, design and develop KPI dashboards and reports ( Tableau, etc ), establish the foundation for all key metrics tracking to evaluate overall effectiveness\nCreate actionable insights and provide campaign optimization recommendations for the CRM team through data extraction and transformation processes using data analytics tools ( SQL, R, Python, etc )\nHypothesize and perform exploratory customer analysis ( customer life cycle analysis, customer segmentation, campaign attribution, A / B testing, RFM analysis, customer behavioral modeling, funnel analysis, CLV, etc. ), ability to transform unstructured data into clear business opportunities\nDevelop best practices of customer targeting strategy for customer lifecycle campaigns ( activation, retention, upsell, cross-sell, churn management, etc ) through data-driven methods\nPartner with data engineering / tech team, ability to plan data requirements and priority pipelines to maintain CRM data landscapes with accuracy and efficiency\nPerform deep-dive statistical analysis and develop data models that can be used for long-term optimization\nAd-hoc support on campaign audience targeting list and key campaign analysis\nStreamline data workflow to improve efficiency in operational processes\nActively Monitor metrics trends or patterns and troubleshoot operation gaps in a timely manners\nShare learnings and results with stakeholders of all seniority and create a data-driven environment within the team\nRequirements\n1+ years of experience as data analyst\nExperience in e-commerce, retail, consulting, tech company, financial services is desirable\nBachelor\u2019s degree in business administration, marketing, business analytics, statistics, economics, mathematics, or quant related fields\nFamiliar with Python / R\nProficient in visualization tools like Tableau, Power BI, Mixpanel or similar tools\nExperience with CRM Tools such as Braze / Hubspot / Salesforce\nStrong business acumen and good at problem-solving, have a good understanding of customer analytics techniques ( customer lifecycle, RFM modeling, clustering segmentation, conversion prediction, etc ), basic statistical concepts such as hypothesis testing, regression is required.\nGood communication skills, effectively communicate ideas and requirements to technical and non-technical audiences\nHighly motivated with a can-do attitude, ability to think creatively and strategically for evolving data-driven solutions\nA team player and able to work independently with minimal supervision\nAttention to details and precision\nPassionate about the crypto / blockchain industry is a strong plus\n\n\n\n", "employment_types": ["Full Time", "Permanent"], "selling_points": ["Data Analyst (Power BI/ Alteryx)", "TB - PB Scale platform", "Perm opportunity"], "locations": ["Tsuen Wan Area"], "categories": ["Information Technology (IT)", "Application Specialist - Software", "Software Development", "Data Scientist"], "post_time": "2022-01-17T07:28:30Z", "salary": {"currency": "HKD", "max": 44999, "min": 30000, "period": "monthly", "term": null}, "salary_visible": true, "title_keywords": ["data analyst"], "responsibilities": ["ad-hoc", "analytics tools", "management", "data", "analysis", "business opportunities", "design and develop", "monitor", "testing", "evaluate", "develop", "maintain", "reports", "troubleshoot", "plan", "tracking"], "requirements": {"degrees": ["degree", "bachelor"], "majors": ["mathematics", "business administration", "economics", "statistics", "marketing", "business analytics"], "languages": [], "language_level": [], "hard_skills": ["blockchain", "plus", "bi", "salesforce", "basic", "crypto", "e-commerce", "problem-solving", "tableau", "python", "r", "acumen"], "soft_skills": ["communication skills", "work independently", "can-do attitude", "problem-solving", "motivated", "attention to details", "business acumen", "team player", "driven", "passionate about"], "languages_combined": []}, "experience_required": {"duration": ["1+ years"], "field": ["consulting", "e-commerce", "tech", "financial services", "retail"]}}, {"job_id": "100003009054895", "location_code": "hk", "company": "David James Recruitment  China Limited", "job_title": "Software AI Engineer - Global learning platform - HKD$30k - 48k (Generous Bonus)", "description": "Responsibilities:\nSupporting teams with recruitment projects as required, such as preparing candidate packs and associated materials for a recruitment event\nRunning standard reports from the recruitment system to ensure an effective flow of management information to internal stakeholder\nArranging meetings/calls between the recruitment team and internal and external stakeholders\nPro-actively contributing to initiatives and/or projects across all teams as required\n\nRequirements:\n\nGood in Engish and Mandarin and Cantonese\nHold a Bachelor Degree\nExcellent communication skills (verbal and written), with an eye for detail\nPossess outstanding organizational and time management skills, with an ability to prioritize and manage multiple projects and tasks simultaneously", "employment_types": ["Full Time", "Permanent"], "selling_points": ["Machine Learning exposure in Global context", "Generous package and bonus", "Work From Home Scheme"], "locations": ["Others"], "categories": ["Information Technology (IT)", "IT Project Management / Team Lead", "Software Development", "Data Scientist"], "post_time": "2022-01-17T12:56:38Z", "salary": {"currency": null, "max": null, "min": null, "period": "monthly", "term": null}, "salary_visible": false, "title_keywords": ["engineer"], "responsibilities": ["recruitment", "management", "teams", "reports"], "requirements": {"degrees": ["degree", "bachelor"], "majors": [], "languages": ["cantonese", "mandarin"], "language_level": ["good"], "hard_skills": [], "soft_skills": ["communication skills", "time management skills", "organizational", "prioritize", "eye for detail"], "languages_combined": [{"language": "cantonese", "language_level": ["good"]}, {"language": "mandarin", "language_level": ["good"]}]}, "experience_required": {"duration": [], "field": []}}, {"job_id": "100003009052856", "location_code": "hk", "company": "SIRIUS Partners Limited", "job_title": "Senior Data Manager", "description": "Reporting to the Fund Manager, you will:\n\nBe responsible for fixed income and equity trading for funds and client accounts\nWork as part of the investment team to provide real-time market colour, identify investment opportunities, and implement effective trades to derive profits\nAssist in the portfolio management of funds and client accounts\nAssist in client marketing and day to day client communication\nMaintain and develop new trading instruments and other relevant products to enhance investment returns\n\nRequirements:\n\n3 - 5 years of relevant trading experience in fixed income or equity\nPrefer degree in business, finance or any similar field;\nFamiliar with the fixed income and equity markets ecosystem\nSolid understanding of investment products, trading strategies and risk management\nAbility to work accurately under stress;\nFast learner, proactive and quick reaction to market changes\nFluent in English and Mandarin", "employment_types": ["Full Time", "Permanent"], "selling_points": ["Data Governance; equity market operations", "data operating model; data quality solutions", "Cloud; data cleansing"], "locations": ["Central & Western Area"], "categories": ["Information Technology (IT)", "Data Scientist"], "post_time": "2022-01-17T04:17:38Z", "salary": {"currency": null, "max": null, "min": null, "period": "monthly", "term": null}, "salary_visible": false, "title_keywords": ["manager"], "responsibilities": ["reporting", "management", "develop", "communication", "maintain", "investment returns"], "requirements": {"degrees": ["degree"], "majors": ["finance", "business"], "languages": ["english", "mandarin"], "language_level": ["fluent"], "hard_skills": ["investment products"], "soft_skills": ["communication", "proactive", "fast learner", "responsible"], "languages_combined": [{"language": "english", "language_level": ["fluent"]}, {"language": "mandarin", "language_level": ["fluent"]}]}, "experience_required": {"duration": ["3 - 5 years"], "field": ["trading"]}}, {"job_id": "100003009055059", "location_code": "hk", "company": "Bank of China Group Insurance Company Limited", "job_title": "IT Senior Data Analyst / Data Analysis Manager", "description": "Highlights :\nRemote Working\nCrypto\u00a0\nGreat Benefits\u00a0\n\nResponsibilities :\n\nPropose, design, and launch CRM campaigns and workflows in collaboration with Product, User Acquisition, Marketing, and Tech teams\nMap user journeys and optimize campaigns for funnel conversion\nDrive platform retention, loyalty, engagement, and usage metrics for the Crypto.com products and services (e.g. DAU/MAU, purchases )\nSupport analysis and enhancement of CRM campaigns\nExecute A/B tests and own analysis of results to ensure maximum impact and effectiveness\nDevise ways to improve usage of the CRM platform by automatic basic, everyday tasks\nPulling reports from the CRM platform into data visualization tools\nMeeting with other stakeholders and teams to analyse industry trends and tailor CRM campaigns to meet business objectives\nAssess and plan data points to integrate with CRM platform\n\nRequirements :\nBA/BS degree in Business Administration, Mathematics, Statistics, Information System, Computer Science, Business Analytics, Data Science or relevant field\nMinimum of 3 years experience in e-commerce business\nExpertise and proven experience in CRM software ( e.g. Braze, Hubspot, Salesforce, Marketo )\nAbility to integrate CRM platform with internal data visualization platforms and customer data platforms ( CDPs )\nStrong experience with Google Analytics and Google Tag Manager, including analytics, tag implementation, conversion tracking\nExcellent skills in MS Office suite of programs\nExcellent command of English, both written and verbally\nProficiency in building email templates via HTML\nProficiency in SQL or Python and other programming languages\nExperience in copywriting and / or design a plus\nStrong understanding of cryptocurrency / blockchain industries including non-fungible tokens\nA strong eye for detail and precision\nSelf-directed learning attitude and strong sense of ownership\nQuick-thinking to respond to ever-changing and volatile market conditions", "employment_types": ["Full Time", "Permanent"], "selling_points": [], "locations": ["Central"], "categories": ["Information Technology (IT)", "Data Scientist"], "post_time": "2022-01-18T01:03:34Z", "salary": {"currency": "HKD", "max": 54999, "min": 35000, "period": "monthly", "term": null}, "salary_visible": true, "title_keywords": ["manager", "data analyst"], "responsibilities": [], "requirements": {"degrees": [], "majors": [], "languages": [], "language_level": [], "hard_skills": [], "soft_skills": [], "languages_combined": []}, "experience_required": {"duration": [], "field": []}}, {"job_id": "100003009052002", "location_code": "hk", "company": "Johnson Electric Industrial Manufactory Limited", "job_title": "Data Analyst (Intern / Permanent role)", "description": "\u00a0Responsibilities :\nDesign product flows and journeys that optimize user experience based on the acquired insights as well as business and technical requirements.\u00a0\nFollow through product from concept development, artwork design\u00a0and production\nExecute creative solutions to meet the client needs\nDevelop pixel-perfect UI components that are ready for production and ensure design consistency across different app and web platforms.\nDevelop pixel-perfect UI components that are ready for production and ensure design consistency across different app and web platforms.\nCreate compelling user interface designs for Mobile apps and\nwebsites\n\n\u00a0Requirements :\n\nDiploma or above in Graphic / Multimedia Design or related\u00a0disciplines\n3+ years of UX and UI design experience and have experience designing for large customer-facing platforms.\nUnderstanding of UI/UX design methodologies on mobile and desktop platform\nStrong skilled in Figma, Adobe, Sketch, etc.\n\nStrong self-motivation to start and run the work individually and with the teams.\n\nGood understanding of interaction, journeys and prototyping is an advantage\nSelf-motivated, willing to learn, and a strong sense of responsibility and commitment\nExperienced in the Website interface will be an advantag\nMore experience shall be considered as a Senior\u00a0UI / UX Designer", "employment_types": ["Full Time"], "selling_points": ["Business data management", "Power BI software", "Competitive Remuneration"], "locations": ["Tai Po Area"], "categories": ["Engineering", "Manufacturing & Production", "Information Technology (IT)", "Product Management / Business Analyst", "Data Scientist"], "post_time": "2022-01-17T01:48:24Z", "salary": {"currency": null, "max": null, "min": null, "period": "monthly", "term": null}, "salary_visible": false, "title_keywords": ["data analyst", "intern"], "responsibilities": ["user experience", "design", "develop", "user interface", "ui"], "requirements": {"degrees": ["diploma or above"], "majors": ["multimedia design", "related disciplines"], "languages": [], "language_level": [], "hard_skills": ["mobile", "adobe", "multimedia"], "soft_skills": ["self-motivated", "self-motivation", "willing to learn", "sense of responsibility"], "languages_combined": []}, "experience_required": {"duration": ["3+ years"], "field": ["designer", "design"]}}, {"job_id": "100003009052177", "location_code": "hk", "company": "PERSOLKELLY Hong Kong Limited", "job_title": "Data Engineer / Lead Data Engineer (Big Data, ETL, Python, AWS)", "description": "Our client, a cognitive solutions and cloud platform company headquartered in New York with operations in over 175 countries and has played a pivotal role in Hong Kong\u2019s development and transformation.\n\nResponsibilities:\n\nWorking with business stakeholders to understand business needs and ideas and translate them into meaningful data/analytics solutions.\nWork on the end to end flow of a broad range of analytics use cases to deliver real business value\nWriting software to clean and investigate large, messy data sets of numerical and textual data\nAnalysis of complex datasets to make decisions, and creates visualization to drive data insight, and develops scalable algorithms and models\nMake strategy recommendation on data pull, integration, aggregation and retention incorporating business requirements and knowledge of best practices\nRequirement\n\nUniversity degree in computer science, data science, Statistics, or any other equivalent degree\nHands-on experience in SQL, Python, ETL\nHands-on experience in building dashboards, data modelling and Data Analytic\nExperience in AWS microservice. AWS cloud development with AWS certificate is in advanced.\nExperience in end-to-end solution (Informatica ETL/Alteryx) would be a big plus\nDemonstrated ability to think strategically about business, product and technical challenges in an enterprise environment\nNative Cantonese, Good Mandarin, Good English\nPrevious IT experience in consulting firm or services vendors is preferred\nCandidates with more experience would be considered as Senior data engineer / lead data engineer\n\nTo apply for this position, please send your full resume to contract_hk @persolkelly.com in word format indicating the job title.\u00a0\n\nIf you are not contacted by our consultants within 2 weeks, please consider your application unsuccessful. All applications will be treated in strict confidence and used for recruitment purposes only in accordance with PERSOLKELLY Hong Kong Limited's Privacy Notice", "employment_types": ["Full Time"], "selling_points": ["Python, ETL", "AWS Cloud", "Big Data"], "locations": ["Not Specified"], "categories": ["Information Technology (IT)", "Application Specialist - Software", "Software Development", "Data Scientist"], "post_time": "2022-01-17T02:21:28Z", "salary": {"currency": null, "max": null, "min": null, "period": "monthly", "term": null}, "salary_visible": false, "title_keywords": ["lead", "data engineer"], "responsibilities": ["ideas", "software", "visualization", "data", "analysis"], "requirements": {"degrees": ["certificate", "university degree", "degree"], "majors": ["data science", "statistics", "computer science"], "languages": ["cantonese", "english", "mandarin"], "language_level": ["native", "good"], "hard_skills": ["plus", "word", "aws", "sql", "alteryx", "python"], "soft_skills": ["hands-on", "confidence", "advanced", "think strategically"], "languages_combined": [{"language": "cantonese", "language_level": ["native"]}, {"language": "english", "language_level": ["good"]}, {"language": "mandarin", "language_level": ["native"]}]}, "experience_required": {"duration": [], "field": ["sql", "consulting", "it experience"]}}, {"job_id": "100003009047980", "location_code": "hk", "company": "Convoy Global Holdings Limited", "job_title": "Senior Data Analyst", "description": "As being a technology-enabled financial B2B platform, provides all-around services and integrates a full range of financial products. Our mission is to accelerate the business growth of our B2B partners and unleash their potentials at ease.\n\nWe\u2019re growing fast and are building a business that is focused and fit for the future. We\u2019re looking for a SeniorData Analyst in our Data team to join the team and share our vision and venture our success.\n\nWhat you will be working on:\n\nInterpret data, analyze results using statistical techniques and provide ongoing BI and business reports\nAcquire data from primary or secondary data sources and maintain databases/data systems\nIdentify, analyze, and interpret trends or patterns in complex data sets\nFilter and clean data by reviewing computer reports, documents, and performance indicators to locate and correct code problems\nWork with management and business users to prioritize business and information needs\nLocate and define new business decisions, process improvement opportunities\nWork with data architect and developer to develop and implement databases, data collection systems, data analytics, and other strategies that optimize statistical efficiency and quality\nManage and participate in end-to-end BI journey includes but not limited to data modeling, ETL design and development, data governance, database management, data presentation, and visualization\nPerform any ad-hoc projects as assigned\n\nWhat we are looking for:\n\nDegree holder in Mathematics, Computer Science, Information Management, Statistics or related disciplines. Master degree an advantage\n2 - 7 years working experience in\u00a0Dimensional Data Modeling\u00a0(e.g.\u00a0star-schema),\u00a0PowerBI,\u00a0Data Factory/SSIS\u00a0and\u00a0MSSQL\nTechnical expertise regarding Enterprise Data Warehouse Design which consists of\u00a0ODS,\u00a0STG\u00a0and\u00a0DW,\u00a0SSIS\u00a0ETL\u00a0Design and\u00a0Stored-Procedure\u00a0Development\nStrong knowledge of and experience with\u00a0PowerBI,\u00a0MDX,\u00a0DAX,\u00a0T-SQL\u00a0and\u00a0Python\nAble to use\u00a0PowerBI\u00a0and Python\u2019s\u00a0Matplotlib,\u00a0NumPy\u00a0and\u00a0Pandas\u00a0for Statistical Data Analysis and Data Visualization\nExperience in administering Azure\u2019s products (Azure SQL Database,\u00a0Data Warehouse,\u00a0Data Factory)\nExcellent at Data Presentation and have a good sense of numbers\nExcellent verbal and written communication skills\nGood command of both spoken and written English and Chinese\nKnowledge of insurance and financial products is an advantage\nWe offer competitive remuneration including career prospects to the right candidate. Interested parties please send detailed resume with availability, current and expected salaries to\u00a0Human Resources Department\u00a0by clicking the\u00a0Apply Now\u00a0button and upload your CV and cover letter.\u00a0\n(All applications will be treated in strict confidence and used for recruitment purpose within Convoy Global Holdings Limited only. All applicants are kept on file six months from the date of the application.)", "employment_types": ["Full Time", "Permanent"], "selling_points": ["Interpret data, analyze results", "Excellent at Data Presentation", "Knowledge of statistics, database design"], "locations": ["Wan Chai"], "categories": ["Information Technology (IT)", "DBA", "Product Management / Business Analyst", "Data Scientist"], "post_time": "2022-01-14T04:24:26Z", "salary": {"currency": null, "max": null, "min": null, "period": "monthly", "term": null}, "salary_visible": false, "title_keywords": ["data analyst"], "responsibilities": ["management", "work with management", "visualization", "data", "systems", "quality", "design", "develop", "data analysis", "communication", "maintain", "reports", "databases", "data collection", "database", "ad-hoc projects", "insurance"], "requirements": {"degrees": ["master degree", "degree holder"], "majors": ["related disciplines", "mathematics", "statistics", "computer science"], "languages": ["english", "chinese"], "language_level": ["good command"], "hard_skills": ["clean", "ease", "bi", "azure", "data warehouse", "data analytics", "analysis", "t-sql", "python", "sql", "databases", "data visualization", "mssql", "code"], "soft_skills": ["communication skills", "presentation", "prioritize", "focused"], "languages_combined": [{"language": "english", "language_level": ["good command"]}, {"language": "chinese", "language_level": ["good command"]}]}, "experience_required": {"duration": ["2 - 7 years"], "field": ["sql", "database"]}}, {"job_id": "100003009046554", "location_code": "hk", "company": "Sun Hung Kai Properties Ltd", "job_title": "ASSISTANT MANAGER \u2013 DATA ANALYTICS", "description": "Requirements:\n\n\nBachelor\u2019s degree in Computer Science, Statistics or Information Management or related discipline\nMinimum 7 years\u2019 experience in data analytics, managing data warehouse, business intelligence of mobile app loyalty program, preferably with retail market exposure\nHands-on experience in ETL process, database management, data analysis with data visualization tools and Google Analytics\nProficiency in SQL programming (e.g. MySQL, MSSQL, etc) and Tableau is a must\nStrong business acumen, analytical skills and numerical sense, able to work independently\nWell-organized, self-motivated and a good team player\nEffective communication skills, both in oral presentation and report writing\nProven English proficiency\n\nResponsibilities:\n\n\nManage data warehouse, consolidate and integrate data from diversified data source including MySQL Database, Google Analytics, etc\nAnalyze consumer data of customer loyalty programs and identify insights for management on business development opportunities\nDevelop and built segmentation platform for performing the evaluation of segmentation used in different channels\nOrganize and prepare regular business analysis reports\nCommunicate and coordinate with internal and external parties to refine data management and analytics procedures, workflows and other best practices\nDevelop Business Intelligence tools / Dashboards to facilitate efficient cross-platform data analysis\nMaintain data integrity and conduct periodic quality assurance tracking of the Company\u2019s customer loyalty program\u2019s databases\n\n(Candidates with more experience will be considered for Manager \u2013 Data Analytics.)\n\nGood remuneration and attractive fringe benefits will be offered to the successful applicant. Interested parties please apply with full resume, present and expected salary, available date by clicking \u201cApply Now\u201d.\n\nFor further information, please visit our company website:\u00a0http://www.shkp.com/.\n\n\nWe are an equal opportunity employer and welcome applications from all qualified candidates. All personal data collected will be used for recruitment purpose only.\u00a0 Applicants not hearing from us within 3 months may consider their applications unsuccessful.\u00a0 All personal data collected will be destroyed within 24 months.", "employment_types": ["Full Time", "Permanent"], "selling_points": ["Manage data warehouse & integrate data", "Organize and prepare business analysis reports", "Develop Business Intelligence tools"], "locations": ["Wan Chai"], "categories": ["Professional Services", "Business Analysis / Data Analysis", "Information Technology (IT)", "Product Management / Business Analyst", "Data Scientist"], "post_time": "2022-01-13T13:52:27Z", "salary": {"currency": null, "max": null, "min": null, "period": null, "term": null}, "salary_visible": false, "title_keywords": ["assistant manager"], "responsibilities": ["management", "data", "internal and external parties", "coordinate with", "procedures", "quality", "develop", "business analysis reports", "data analysis", "database", "evaluation", "maintain data", "databases", "tracking"], "requirements": {"degrees": ["degree", "bachelor"], "majors": ["statistics", "computer science"], "languages": ["english"], "language_level": ["proficiency"], "hard_skills": ["google analytics", "data warehouse", "data analytics", "analysis", "tableau", "analytical skills", "sql", "mobile", "programming", "data visualization", "mssql", "business intelligence", "acumen"], "soft_skills": ["communication skills", "work independently", "self-motivated", "good team player", "oral", "well-organized", "analytical skills", "hands-on", "business acumen", "presentation"], "languages_combined": [{"language": "english", "language_level": ["proficiency"]}]}, "experience_required": {"duration": ["minimum 7 years"], "field": ["data analysis", "business", "database management", "retail"]}}, {"job_id": "100003009053268", "location_code": "hk", "company": "Centaline Data Technology Limited", "job_title": "Programmer / Senior Programmer  (5-day Work)", "description": "Responsibilities\n\n* Participate in system development, testing and implementation\n\n* Responsible for API development, implementation, maintenance and training\n\n* Cooperate with Web and App teams to develop websites and Apps\n\n* Assist in SQL optimization and other database performance\n\n* Keen interest in exploring new technology\n\nRequirements\n\n* Bachelor Degree or Diploma in Computer Science, Information Technology or related disciplines\n\n* Experience in one of the programming languages such as\n\n.NET programming(C#), Node.js, SQL, mongoDB, elasticsearch\n\n,HTML5, VueJs, Docker, Nginx is a plus\n\n* Experience in software development using OOP, design patterns would be an advantage\n\n* Can work independently and be self-motivated\n\n* Fresh Graduates will also be considered\n\n* Candidate with more experience will be considered as Senior Programmer\n\n* Immediate available is preferred", "employment_types": ["Full Time", "Permanent"], "selling_points": ["API development and application system developme", "SQL optimization / On-job training", "Quarterly Bonus / Medical / Education Allowance"], "locations": ["Tsim Sha Tsui"], "categories": ["Information Technology (IT)", "IT - Webmaster / SEO", "Mobile / Wireless Communications", "Data Scientist"], "post_time": "2022-01-17T06:37:11Z", "salary": {"currency": null, "max": null, "min": null, "period": "monthly", "term": null}, "salary_visible": false, "title_keywords": ["programmer", "senior programmer"], "responsibilities": ["maintenance", "teams", "implementation", "testing", "develop", "database", "cooperate with"], "requirements": {"degrees": ["diploma", "degree", "bachelor"], "majors": ["related disciplines", "computer science", "information technology"], "languages": [], "language_level": [], "hard_skills": ["sql", "plus", "programming"], "soft_skills": ["work independently", "self-motivated"], "languages_combined": []}, "experience_required": {"duration": [], "field": ["design", "programming", "software development"]}}, {"job_id": "100003009045758", "location_code": "hk", "company": "Kepro Solutions Limited", "job_title": "Consultant/Associate Consultant - Data Services", "description": "Responsibilities:\u00a0\n\nBI, Data management project implementation (Data integration, Data Governance, Data security etc.).\nPrepare and conduct demonstration/presentation to clients and partners\nPrepare proposal and tender documents in response to clients\u2019 requirements (Construct, design, architect and describe a cost effective solution for potential customers; and\n\u00a0Involve in initial planning and design of projects and transform all business requirements into technical specifications.\n\n\u00a0Requirements:\n\nDegree in Computer Sciences / Information Technology / Data management or related discipline.\nMore than 3 year of experience on designing (scripting) and implementing schedule based ETL processes with ETL tools such as SSIS, Alteryx, Pentaho PDI, Informatica, DataStage, or other open source ETL tools such as Talend\nData Warehouse design and data mining knowledge\nExcellent presentation, communication, and interpersonal skills\nPrepare related documentations during the project life cycle\nAbility to provide efficient, timely, and reliable service to customers\u00a0\nSolid experience in BI, database management, data analyst and modeling.\nGood command of both written and spoken English and Chinese\nImmediate available in highly preferred\nWe offer a competitive remuneration package to the right candidate. Interested parties please send your full resume with\u00a0present and expected salary to us by\u00a0clicking 'Apply Now'.\n\n\nCompany Address: 9/F, The Whitney, 183 Wai Yip Street, Kwun Tong, Hong Kong\n\nKepro Solutions Website:\u00a0https://intranet.karingroup.com/IntranetApp/Default.aspx\n\n(We are an Equal Opportunity Employer and personal data collected would be used for recruitment purpose only.)", "employment_types": ["Full Time", "Permanent"], "selling_points": ["3+ years relating to data management solutions", "Provide efficient solutions in handling data", "5-day week, steady career path"], "locations": ["Kwun Tong"], "categories": ["Information Technology (IT)", "Product Management / Business Analyst", "Technical / Functional Consulting", "Data Scientist"], "post_time": "2022-01-15T03:49:31Z", "salary": {"currency": null, "max": null, "min": null, "period": "monthly", "term": null}, "salary_visible": false, "title_keywords": ["associate", "consultant"], "responsibilities": ["management", "cost", "tender documents", "data", "implementation", "design", "specifications", "planning"], "requirements": {"degrees": ["degree"], "majors": ["information technology"], "languages": ["english", "chinese"], "language_level": ["good command"], "hard_skills": ["bi", "data management", "data warehouse", "alteryx", "data mining", "documentations"], "soft_skills": ["efficient", "timely", "communication", "interpersonal skills", "reliable", "presentation"], "languages_combined": [{"language": "english", "language_level": ["good command"]}, {"language": "chinese", "language_level": ["good command"]}]}, "experience_required": {"duration": ["3 year"], "field": ["database management"]}}, {"job_id": "100003009053603", "location_code": "hk", "company": "JFE Consulting Limited", "job_title": "Senior Database Administrator (DBA)", "description": "Our client, one of the leading IT companies, is looking for high calibres to join their winning team:-\n\nResponsibilities:\n\nInstall, design and maintain database system software and implement database security.\nMonitor and analyze database performance and ensure effective and efficient utilization of database systems/processes.\nMaintain database dictionaries and support tools; develop and maintain accurate system documentation.\nParticipate in the development and maintenance of strategic, architectural and tactical plans for the database and data warehouse environments; be conversant with, and cognizant of, the future direction of systems, how that direction impacts the company and how future and current database systems can be exploited for the company\u2019s benefit. \u00a0\nYou will design, execute and supervise DML/DDL according to business requirements.\n\nRequirements:\n\nBS degree in Information Technology/Computer Science or equivalent combination of education and experience.\nFive or more years of SQL server database experience as Database Administrator (DBA), including experience installing, configuring, designing, patching, archiving, and monitoring to include performance tuning databases with indexing.\nYou have strong experience with database software (especially MySQL),\u00a0\nYou are proficient in SQL programming and Shell;", "employment_types": ["Full Time", "Permanent"], "selling_points": ["MySQL DBA", "Redis, HBase, Shell", "5-day work; attractive salary"], "locations": ["Not Specified"], "categories": ["Information Technology (IT)", "DBA", "IT Management", "Data Scientist"], "post_time": "2022-01-17T07:13:37Z", "salary": {"currency": null, "max": null, "min": null, "period": "monthly", "term": null}, "salary_visible": false, "title_keywords": ["administrator"], "responsibilities": ["software", "system documentation", "maintenance", "data", "systems", "monitor", "design", "develop", "maintain", "database", "plans"], "requirements": {"degrees": ["degree"], "majors": ["computer science", "information technology"], "languages": [], "language_level": [], "hard_skills": ["sql", "server", "programming", "databases"], "soft_skills": [], "languages_combined": []}, "experience_required": {"duration": [], "field": ["sql", "education", "database", "information technology"]}}, {"job_id": "100003009046526", "location_code": "hk", "company": "Sun Hung Kai Properties Ltd", "job_title": "ASSOCIATE DATA SCIENTIST / DATA SCIENTIST", "description": "Requirements:\n\n\nBachelor\u2019s degree in Computer Science, Econometrics, Mathematics, Operation Research, Statistics or related disciplines\nMinimum 2 years\u2019 work experience in data science with proven track record of leveraging large amount of data to drive significant business impact\nAdvanced analytical skills, experience in recommending appropriate algorithm and methodology for problem-solving and decision making, leveraging both logic and creativity\nExposure to Amazon AWS core services such as S3, EC2, API Gateway, and Lambda is advantageous\nExperience in prototyping and productionalizing advance analytics solutions in business\nMust be proficient in Python. Knowledge of Java, Scala and C++ is a plus\nExperience in IT big data tools (e.g Hadoop, Spark), as well as query languages for SQL and NoSQL\nFamiliar with machine learning algorithm and libraries (e.g. scikit-learn, XGBoost, LGBM, TensorFlow etc.)\nProficiency in data visualization tools, ideally Tableau\nExperience with MLOps and DevOps solution architecture design is a plus\nUnderstands common software engineering best practices such as is a code versioning, test-driven development, and code modularization\n\nResponsibilities:\n\n\nTranslate unstructured business questions into quantitative problems\nPrototyping advance analytics and machine learning solutions for business partners\nProvide advanced analytics support and advise on appropriate analytical models based on available data, technology and platform\nMake intelligent approximations to the model if required to make it scalable and operatable\nAnticipate needs and lead implementation of capabilities such as data modelling, algorithms, new technology & partners\nRecommend and implement the development path of capabilities and skillsets to foster a culture of applying data & insight driven culture in decision making\n\n(Candidates with more experience will be considered as Data Scientist.)\n\nGood remuneration and attractive fringe benefits will be offered to the successful applicant. Interested parties please apply with full resume, present and expected salary, available date by clicking \u201cApply Now\u201d.\n\nFor further information, please visit our company website:\u00a0http://www.shkp.com/.\n\nWe are an equal opportunity employer and welcome applications from all qualified candidates. All personal data collected will be used for recruitment purpose only.\u00a0 Applicants not hearing from us within 3 months may consider their applications unsuccessful.\u00a0 All personal data collected will be destroyed within 24 months.", "employment_types": ["Full Time", "Permanent"], "selling_points": ["Leveraging large amount of data", "Must be proficient in Python", "Amazon AWS, Big data tools, query lang for SQL"], "locations": ["Wan Chai"], "categories": ["Professional Services", "Business Analysis / Data Analysis", "Information Technology (IT)", "Product Management / Business Analyst", "Data Scientist"], "post_time": "2022-01-13T13:10:50Z", "salary": {"currency": null, "max": null, "min": null, "period": null, "term": null}, "salary_visible": false, "title_keywords": ["associate", "data scientist"], "responsibilities": ["implementation", "data"], "requirements": {"degrees": ["degree", "bachelor"], "majors": ["related disciplines", "mathematics", "statistics", "computer science"], "languages": [], "language_level": [], "hard_skills": ["java", "amazon", "plus", "c++", "problem-solving", "devops", "code", "tableau", "aws", "analytical skills", "scala", "sql", "data visualization", "python", "spark", "s3"], "soft_skills": ["advanced", "problem-solving", "analytical skills", "learning", "driven", "decision making"], "languages_combined": []}, "experience_required": {"duration": ["minimum 2 years"], "field": ["analytical", "devops", "design", "business", "it"]}}, {"job_id": "100003009047575", "location_code": "hk", "company": "China CITIC Bank International Limited", "job_title": "Officer, Data Office", "description": "Job Purpose:\n\n\nAssist in research/ design/ develop advanced analytic models/approach for innovative analytic requirement from BUs/SUs in AI/ Big Data/ Machine Learning, as well as the development of data governance policies and guidelines, and support the data management implementation.\u00a0\u00a0\n\nResponsibilities:\n\nAssist line manager to analyze data for trends and patterns, and interpret data with a clear objective in mind\nDevelop procedures related to program development and version control using data analytic tool\nSupport line manager to establish and revamp bank wide data governance framework\nContribute in data management initiatives of data standardization, data quality, data lineages etc. with collaboration with data owners\nSupport projects / initiatives assigned by line manager\n\nRequirements:\n\n\nDegree holder in Quantitative disciplines (Computer Sciences/ Engineering/ Statistics/ Economics/ Business Analysis)\nBasic understanding in developing analytic solutions/models including the use of both structured and unstructured data sources\nAwareness of both quality and risk, especially compliance-related risk issues\nFundamental knowledge in data related regulations, e.g. BCBS239, GDPR etc.\nGood command of both written and spoken English and Chinese\n\n\n\nFor more details about career opportunities with the Bank, please visit our website\u00a0http://www.cncbinternational.com/careers/en/index.jsp. Please apply with full resume stating current and expected salaries.\n\n\u00a0Personal data collected will be used for recruitment related purposes only. Applicants not invited for interview within 6 weeks may consider their applications unsuccessful. However, applicants may be considered for other suitable positions within the Group for a period of not more than 2 years. Personal data will be destroyed at any time after 3 months.\n\n\u00a0China CITIC Bank International is committed to being an equal opportunities employer and intends to provide a work environment free of unlawful discrimination or harassment. All employment decisions will be made in a non-discriminatory manner.", "employment_types": ["Full Time", "Permanent"], "selling_points": ["Analyze data for trends and patterns", "Develop data governance policies & guideline", "Data management implementation"], "locations": ["Quarry Bay"], "categories": ["Information Technology (IT)", "DBA", "Others", "Data Scientist"], "post_time": "2022-01-14T03:45:08Z", "salary": {"currency": null, "max": null, "min": null, "period": "monthly", "term": null}, "salary_visible": false, "title_keywords": ["officer"], "responsibilities": ["support projects", "control", "revamp", "management", "data", "procedures", "quality", "develop", "analyze data"], "requirements": {"degrees": ["degree holder"], "majors": ["business", "economics", "statistics", "engineering"], "languages": ["english", "chinese"], "language_level": ["good command"], "hard_skills": ["analysis", "basic"], "soft_skills": ["committed", "structured"], "languages_combined": [{"language": "english", "language_level": ["good command"]}, {"language": "chinese", "language_level": ["good command"]}]}, "experience_required": {"duration": [], "field": []}}, {"job_id": "100003009050378", "location_code": "hk", "company": "Conners Consulting Limited", "job_title": "Data Science / Data Analytics Manager (Leading bank with excellent package )", "description": "Our client is a fast expanding and reputable bank in Hong Kong, is looking for a high caliber to join the group.\u00a0\nResponsibilities:\nTo support the Data Science team in creating road map for implementation of data analytics strategy\nTo assist to build data model. Review and validate model effectiveness and performance\nTo address statistical, machine learning and data understanding problems\nTo collaborate with internal stakeholders and external vendors on project planning and execution\nRequirements:\nSound knowledge of data modelling, machine learning, data warehousing/migration\u00a0\nMinimum 7 years relevant experience in banking or FI\u00a0\nGood communication / negotiation and project management skills with strong sense of innovation\nProficient in MongoDB, MySQL, Java and Python\n\u200b\nTo apply, please send your detailed resume to winnie[at]connersconsulting[dot]com or contact Winnie Lai at 3618 8348 for a confidential discussion.\nOnly shortlisted candidates will be notified.\u00a0 Applicants who are not contacted within two weeks may consider their applications unsuccessful.\u00a0 All data collected will be used for recruitment purpose only & will be used strictly confidential.\nConners Consulting Limited\n2005 Kai Tak Commercial Building, 317 Des Voeux Road Central Hong Kong\n(website:\u00a0www.connersconsulting.com)\u00a0 Tel: (852) 3996 8090", "employment_types": ["Full Time", "Permanent"], "selling_points": ["Permeant role", "Renewable contract with attractive package", "Fast expanding and leading commercial bank"], "locations": ["Kwun Tong Area"], "categories": ["Information Technology (IT)", "DBA", "Technical / Functional Consulting", "Data Scientist"], "post_time": "2022-01-15T03:51:03Z", "salary": {"currency": null, "max": null, "min": null, "period": "monthly", "term": null}, "salary_visible": false, "title_keywords": ["manager"], "responsibilities": ["collaborate with", "project planning", "data", "review", "implementation"], "requirements": {"degrees": [], "majors": [], "languages": [], "language_level": [], "hard_skills": ["python", "project management", "java"], "soft_skills": ["negotiation", "project management skills", "communication", "learning", "detailed"], "languages_combined": []}, "experience_required": {"duration": ["minimum 7 years"], "field": ["relevant experience", "banking"]}}, {"job_id": "100003009045955", "location_code": "hk", "company": "Brand Loyalty Ltd", "job_title": "Data Analyst", "description": "As a Consumer and Business Intelligence Specialist you will deliver impactful data results for our business and clients while working closely with a cross-functional global team. You will be working with large-scale retail transactional\u00a0and other behavioral data gathered from local markets. The data you analyze\u00a0will play a crucial role in helping our business and our clients understand the\u00a0power of BrandLoyalty programs. You will also be part of the largest loyalty\u00a0Campaign provider globally, with experience in over 60 countries.\u00a0You\u2019ll be in charge of maintaining and improving our Data & Insight solutions\n\nwhich run in the Azure cloud. BrandLoyalty lead the way in placing the consumer at the heart of decision-making, and you will play a key part in helping us to maintain this lead in a highly competitive environment. You\u2019ll also be part of a talented, multi-disciplinary business. This means working with a diverse range of stakeholders and constantly working through the best technical solutions to meet their needs.\n\nYour team and responsibilities\n\nBusiness Requirements Identification;\u00a0support collection of business requirements using a variety of methods such as\ninterviews, document analysis, and workflow analysis to express requirements\nclearly and succinctly.\nData Collection and Analysis; collate and analyze data using pre-set tools, methods and formats. Involves\nworking independently.\nInsights and Reporting; contribute to the design and creation of reporting strategies and templates. Lead\u00a0execution of complex reports, identifying and interpreting complex patterns and\u00a0trends, and translating those insights into actionable recommendations.\nRecommendations; advise managers how to apply a wide variety of existing procedures and\u00a0precedents.\nStakeholder Engagement; contribute to stakeholder engagement through identifying stakeholders, finding\u00a0out their needs/issues/concern and reacting to these by arranging meetings and\u00a0events and drafting supporting materials to promote understanding and\u00a0commitment.\nWorkshop Facilitation; support process development workshops with subject matter experts, drive\u00a0agreement on process\u00a0flows across functional areas, and document processes\u00a0and activity workflows to develop clear and detailed process maps.\nAdvanced and Predictive Analytics; support interpretation of advanced and predictive analytics data, using\u00a0specialized software tools and functionalities.\nImprovement through Business Intelligence;\u00a0create basic machine learning algorithms and support creation of more complex\u00a0algorithms that identify patterns in structured data. Partner with different\u00a0business stakeholders and internal clients to ensure the collection of data in\u00a0accordance with model standards.\n\nRequirements\n\nWhat qualities do you bring?\n\nMinimum of 3 to 6 years\u2019 experience within a commercial organization working hands on with data and analytical tools. Preferably with membership card/ retailer (food or non-food) experience\nManagerial basic experience of coordinating the work of others; minimum of 3 to 6 months.\u00a0\nExperience in a relevant field: Computer Science, Mathematics, Physics\nHands-on experience with SQL Server, Azure SQL server, Azure Data warehouse and Data Factory, and experience with data ingestion (cleaning, ETL, validation), and (T)SQL scripting. Certified MSSQL 2014 is a plus\nStrong Experience in Microsoft PowerBI & PowerBI-related data architecture\nUnderstanding complex data warehousing and relational databases\nAble to set up databases and data modeling\nKnowledge of big data technologies (preferable)\nScripting in Python or R (preferable)\nSelf-service Business Intelligence tool (Tableau preferred)\nExperience with an agile way of working.\nStrong analytical and numerical skills\nRisk management. Ability to identify potential risks and to resolve with impacted parties\nHigh level of commercial acumen\nAble to communicate clearly with senior management across disciplines\nFluent written and spoken English\nExcellent attention to detail and out of the box mentality.\nAble and willing\u00a0to travel 5-15%\u00a0\n\nWhat do we offer?\n\nAre you up for the challenge? BrandLoyalty wants you to have fun in your work, contribute to our growth and share the successes with your team/company. This is just a short list of what BrandLoyalty can offer you:\n\nPurpose-driven company: happy people, better business;\nPersonal & professional development opportunities within a multinational growth business;\nWork with a team of 50+ nationalities in over 55 countries around the world;\nBrandLoyalty is part of Loyalty Ventures Inc. - a leading provider of tech-enabled data-driven consumer loyalty solutions.\nExceptional terms of employment \u2013 compensation, on-site gym with personal trainers, healthy daily lunches cooked by an in-house team, and spectacular team gatherings.\n\nBrandLoyalty is known for being a diverse & inclusive workplace because we believe that this drives our purpose \u201cNext Generation Happiness\u201d and creates a better future every day for our people, clients and partners. All qualified applicants will receive consideration without regard to race, color, religion, sex, national origin, age, sexual orientation, gender identity, gender expression or disability.", "employment_types": ["Full Time"], "selling_points": [], "locations": ["Not Specified"], "categories": ["Information Technology (IT)", "Data Scientist"], "post_time": "2022-01-13T09:14:00Z", "salary": {"currency": null, "max": null, "min": null, "period": "monthly", "term": null}, "salary_visible": false, "title_keywords": ["data analyst"], "responsibilities": [], "requirements": {"degrees": [], "majors": [], "languages": ["english"], "language_level": ["fluent"], "hard_skills": ["server", "plus", "basic", "azure", "agile", "data warehouse", "analysis", "mssql", "python", "sql", "tableau", "numerical skills", "databases", "workshops", "r", "business intelligence", "acumen"], "soft_skills": ["independently", "advanced", "agile", "clear", "hands-on", "learning", "hands on", "attention to detail", "structured", "detailed"], "languages_combined": [{"language": "english", "language_level": ["fluent"]}]}, "experience_required": {"duration": ["minimum of 3 to 6 years"], "field": ["managerial", "analytical", "related", "sql", "commercial", "food"]}}, {"job_id": "100003009048923", "location_code": "hk", "company": "Heep Hong Society", "job_title": "Business Intelligence Data Analyst", "description": "Responsibilities:\n\nDesign, implementation, deployment and problem diagnosis of the data analytics solutions\nEnsure the implementation process are followed for each project and task\nWork closely with users and project team to understand requirements are met\nPrepare documentation on user requirements, solution design, and user guide\nProject are deliver on-time to the standard required and within the constraints of the delivery process\nCommunicate and manage proactively on issues affecting delivery\n\nRequirements:\n\nUniversity graduate in Computer Science, Information Technology / Information System or a related discipline\nAt least 3-5 years' experience as data analyst, data scientist or data engineer\nHands-on and solid experiences in the following areas: (i)Reporting: Management Reporting using BI dashboard & Excel;(ii) BI tools (at least one): QlikView, Power BI; (iii)Database: SQL Server, MySQL, any NoSQL DB\nUnderstanding Azure Data Factory, Azure Synapse would be an advantage\nProven experience in process and analysis of data using SQL or python\nExperience in cross-functional team or Agile/Scrum/Kanban would be an advantage\nStrong communication skills in both written and presentation\nGood command of both spoken and written in English & Chinese\n\nWe provide equal employment opportunities to all employees and applicants. For interested parties, please click\u00a0\u201cApply Now\u201d.\n\n(Personal data collected will be used for recruitment purpose only)", "employment_types": ["Full Time"], "selling_points": ["Design, implement, deploy, problem diagnosis", "Data analytics, user req., solution design", "Comp. Sci, IT/Info System Degree; min. 3-5yrs' exp"], "locations": ["Ngau Tau Kok"], "categories": ["Information Technology (IT)", "DBA", "Product Management / Business Analyst", "Data Scientist"], "post_time": "2022-01-14T11:32:05Z", "salary": {"currency": null, "max": null, "min": null, "period": "monthly", "term": null}, "salary_visible": false, "title_keywords": ["data analyst"], "responsibilities": ["documentation", "implementation", "design", "data"], "requirements": {"degrees": ["university graduate"], "majors": ["computer science", "information technology"], "languages": ["english", "chinese"], "language_level": ["good command"], "hard_skills": ["excel", "qlikview", "bi", "azure", "agile", "analysis", "information system", "python", "sql", "server"], "soft_skills": ["communication skills", "hands-on", "presentation", "agile"], "languages_combined": [{"language": "english", "language_level": ["good command"]}, {"language": "chinese", "language_level": ["good command"]}]}, "experience_required": {"duration": ["at least 3-5 years"], "field": ["sql", "management", "team"]}}, {"job_id": "100003009049364", "location_code": "hk", "company": "HGC Global Communications Limited", "job_title": "System Analyst (Data)", "description": "Responsibilities:\n\nFormulate and implement various business strategies and plans for Business Intelligent and data analytics, includes marketing campaigns, data extract, customer list preparation, and promoting throughout the company to achieve the company's business and management. Conduct data design based on user business and technical requirements;\nAnalyze IB / local business operation, organize the company's annual, quarterly, and monthly production and operation analysis and work plan, supervise and coordinate the implementation among various functional departments accordingly. Prepare business and technical documentations and conduct user training;\nWork closely with various business unit to implement the action plans and react responsively to any constraints and barriers;\nParticipate in ad-hoc data / analytic exercise to prepare and analyze customer data.\n\nRequirements:\u00a0 \u00a0 \u00a0 \u00a0 \u00a0 \u00a0 \u00a0 \u00a0 \u00a0 \u00a0 \u00a0 \u00a0 \u00a0 \u00a0 \u00a0\u00a0\u00a0\n\nDegree holder in Computer Engineering, Information Technology, Statistics or related disciplines.\n5 years of experience in customer analytic, data warehouse and BI platform, preferably in telecommunication industry.\nProficient in data analytics design and segmentation with PL/SQL, MS SQL and Python coding or correlation platform.\nKnowledge, skills and experience in system design and development with all / some of the following technologies:Exposure in Design pattern, Java applications Framework would be an advantage.\nOperating System: Windows, Linux, IBM AIX;\nDatabase / Network: Oracle, MySQL, MS SQL;\nProgramming Language: Java, JavaEE - Web, Website building (e.g. PHP, JavaScript & AngularJS - Jquery, Ajax), APEX, Python, Ruby;\nOthers: BI tools: OBIEE / Discoverer, ETL: ODI, Oracle Weblogic, Web Security, Big-Data tool, like Hadoop / Splunk;\nStrong communication and coordination skills, Self-motivated with analytical and problem solving capability.\nGood command of written and spoken Chinese and English and proficient in Mandarin.\n\nWe offer competitive salary package and career development opportunity. \u00a0Interested parties, please apply with full resume, present and expected salary, by clicking \u201cAPPLY NOW\u201d.\u00a0\u00a0Please quote the reference number on the e-mail subject.\n\nWe are an equal opportunity employer and welcome applications from all qualified candidates. Information provided will be treated in strict confidence and only be used for consideration of your application for the relevant post within HGC Global Communications Limited. Personal data provided by job applicants will be used strictly according to our Personal Information Collection Statement, a copy of which will be available upon written request. Information of unsuccessful candidates will be destroyed within six months.", "employment_types": ["Full Time", "Permanent"], "selling_points": ["Customer Analytic", "Data Warehouse", "BI Platform"], "locations": ["Tsing Yi"], "categories": ["Information Technology (IT)", "Product Management / Business Analyst", "Software Development", "Data Scientist"], "post_time": "2022-01-14T08:31:43Z", "salary": {"currency": null, "max": null, "min": null, "period": "monthly", "term": null}, "salary_visible": false, "title_keywords": ["system analyst"], "responsibilities": ["ad-hoc", "business operation", "management", "data", "analysis", "implementation", "design", "customer data", "coordinate", "marketing campaigns", "plan", "plans"], "requirements": {"degrees": ["degree holder"], "majors": ["related disciplines", "statistics", "computer engineering", "information technology"], "languages": ["english", "chinese", "mandarin"], "language_level": ["good command", "proficient"], "hard_skills": ["bi", "web", "jquery", "java", "problem solving", "ajax", "ms sql", "apex", "data warehouse", "data analytics", "ruby", "sql", "javascript", "python", "oracle", "linux", "php", "system design", "programming", "pl"], "soft_skills": ["communication", "self-motivated", "coordination skills", "problem solving"], "languages_combined": [{"language": "english", "language_level": ["good command"]}, {"language": "chinese", "language_level": ["proficient", "good command"]}, {"language": "mandarin", "language_level": ["good command"]}]}, "experience_required": {"duration": ["5 years"], "field": ["development", "system design", "design"]}}, {"job_id": "100003009045780", "location_code": "hk", "company": "Kepro Solutions Limited", "job_title": "Consultant/Associate Consultant \u2013 Business Intelligence", "description": "Dashboard implementation project\nBI systems support and maintenance\n\nRequirements\n\nDegree in Computer Sciences / Information Technology / Data management but not a must or related discipline.\nExperience in using Business Intelligence (BI) / Data Visualization tools such as Tableau, PowerBI, Qlikview etc.\nExperience in SQL, Python programming is an advantage.\nETL project experience is an advantage.\nAbility to provide efficient, timely, and reliable service to customers.\nGood command of both written and spoken English and Chinese.\nFresh graduates would also be considered.\n\nWe offer a competitive remuneration package to the right candidate. Interested parties please send your full resume with\u00a0present and expected salary to us by\u00a0clicking 'Apply Now'.\n\nCompany Address: 9/F, The Whitney, 183 Wai Yip Street, Kwun Tong, Hong Kong\n\nKepro Solutions Website:\u00a0https://intranet.karingroup.com/IntranetApp/Default.aspx\n\n\n(We are an Equal Opportunity Employer and personal data collected would be used for recruitment purpose only.)", "employment_types": ["Full Time", "Permanent"], "selling_points": ["Fresh graduates are welcome; 5-day work", "BI and Data Analytics", "Big data projects exposure and Steady career path"], "locations": ["Kwun Tong"], "categories": ["Professional Services", "Business Analysis / Data Analysis", "Information Technology (IT)", "Product Management / Business Analyst", "Data Scientist"], "post_time": "2022-01-15T03:49:32Z", "salary": {"currency": null, "max": null, "min": null, "period": "monthly", "term": null}, "salary_visible": false, "title_keywords": ["associate", "consultant"], "responsibilities": ["management", "visualization", "maintenance", "data", "systems", "implementation"], "requirements": {"degrees": ["degree"], "majors": ["information technology"], "languages": ["english", "chinese"], "language_level": ["good command"], "hard_skills": ["qlikview", "bi", "data management", "maintenance", "tableau", "sql", "programming", "data visualization", "python", "business intelligence"], "soft_skills": ["efficient", "timely", "reliable"], "languages_combined": [{"language": "english", "language_level": ["good command"]}, {"language": "chinese", "language_level": ["good command"]}]}, "experience_required": {"duration": [], "field": ["sql", "business", "programming"]}}, {"job_id": "100003009048448", "location_code": "hk", "company": "S.F. Express (Hong Kong) Limited", "job_title": "Senior Data Scientist", "description": "Responsibilities:\n\nEngage with different business units to understand the challenges and identify possible solutions.\nBuilding, training, evaluation models such as retention, risk, fraud, etc.\nKnowledge & statistics sharing and mentoring direct reports\nCollect data from different sources to enhance understanding of data trends.\nInvestigate tools for real-time analysis, time series trends, etc.\nProduction environment machine learning and AI is a plus\n\n\u00a0Technical Skills:\n\nExperience in interactive data exploration and data-driven storytelling\nUnderstanding and application of Big Data and distributed computing principles (Hadoop and MapReduce).\nStrong analytical and statistical knowledge with an understanding of the latest machine learning algorithms for both unstructured and structured data\n\nRequirement:\n\nDegree holder in Computer Science, Business Analytics, Information Technology, or other related disciplines.\nExperience using other statistical programming languages such as Python, SQL, and Hive.\nAt least 3 years of professional experience with analytic projects.\nStrong analytical, critical thinking, and creative problem-solving skills.\nOperates with little supervision in a complex, dynamic, matrixed environment. Able to handle multiple tasks at one time.\nUnderstanding current industry challenges and trends at the level needed to identify business needs and opportunities proactively.\nProven track record and ability to mentor and supervise junior resources on a project assignment basis\n\n\n\nWe offer attractive remuneration package and fringe benefits to the suitable candidates. Interested parties, please submit your application to us. If you do not want to apply as a JobsDB member, you may send your full resume with your availability, current and expected salaries to recruit01 at sf-express.com.\n\nYou are welcome to visit our website at\u00a0https://htm.sf-express.com/hk/tc/\u00a0for more information about us.\n\nCandidates who are not invited for an interview within 1-month may consider their applications unsuccessful.\n\nAll personal data provided by job applicants will be used only for recruitment purposes and will be treated strictly confidential. Unsuccessful applications will be retained for a maximum period of 24-month.", "employment_types": ["Full Time", "Permanent"], "selling_points": ["Free shuttle bus coverage", "2 months or above performance bonus", "Attractive basic salary"], "locations": ["Tsing Yi"], "categories": ["Information Technology (IT)", "IT Project Management / Team Lead", "Product Management / Business Analyst", "Data Scientist"], "post_time": "2022-01-14T06:36:17Z", "salary": {"currency": null, "max": null, "min": null, "period": "monthly", "term": null}, "salary_visible": false, "title_keywords": ["data scientist"], "responsibilities": ["data", "analysis", "big data", "reports", "evaluation"], "requirements": {"degrees": ["degree holder"], "majors": ["related disciplines", "business analytics", "computer science", "information technology"], "languages": [], "language_level": [], "hard_skills": ["sql", "dynamic", "programming", "python", "problem-solving skills"], "soft_skills": ["handle multiple tasks", "problem-solving skills", "dynamic", "creative"], "languages_combined": []}, "experience_required": {"duration": ["at least 3 years"], "field": ["sql", "programming"]}}, {"job_id": "100003009048428", "location_code": "hk", "company": "BOC Credit Card (International) Limited", "job_title": "(Senior) Data Analytic Manager", "description": "Responsibilities:\nStrategize and work with tech team on data collection to enable business decisions, such as operations optimization and product mix strategies\nAnalyze business data regularly to identify business opportunities and operational improvement opportunities\nConduct in-depth analytical studies combining external research data and internal business analytics to facilitate senior management decisions\nCollaborate with tech and business lines to automate operational processes based on business analysis insights such as merchant category, instalment life-cycle etc.\nDesign comprehensive and user-friendl y dashboard for business line teams\nLead, coach and supervise assigned team to deliver tangible results in each of the above area\nRequirement:\nAt least 4 years of experience in business\u00a0analysis with a Bachelor's degree in Mathematics, Statistics, Computer Science, Business or Economics\nExperience in programming or analytic tools such as SQL, VBA, Python, SAS\nExcellent skills with data visualization for storytelling even with non-technical business partners\nStrong communication, time management and work organization skills\nGood command of both spoken and written Chinese (including Putonghua) and English\nProficient in MS Office application", "employment_types": ["Full Time"], "selling_points": ["Analyze business data regularly", "At least 4 years of experience", "Experience in programming or analytic tools"], "locations": ["Sheung Wan"], "categories": ["Information Technology (IT)", "Product Management / Business Analyst", "Others", "Data Scientist"], "post_time": "2022-01-14T06:32:43Z", "salary": {"currency": null, "max": null, "min": null, "period": "monthly", "term": null}, "salary_visible": false, "title_keywords": ["manager"], "responsibilities": ["collaborate with", "identify business opportunities", "data", "operations", "teams", "design", "data collection", "business analysis", "senior management"], "requirements": {"degrees": ["degree", "bachelor"], "majors": ["mathematics", "economics", "statistics", "business", "computer science"], "languages": ["putonghua", "english", "chinese"], "language_level": ["good command"], "hard_skills": ["vba", "sas", "analysis", "sql", "programming", "data visualization", "python", "ms office"], "soft_skills": ["communication", "time management", "organization skills"], "languages_combined": [{"language": "putonghua", "language_level": ["good command"]}, {"language": "english", "language_level": ["good command"]}, {"language": "chinese", "language_level": ["good command"]}]}, "experience_required": {"duration": ["at least 4 years"], "field": ["statistics", "sql", "business", "programming", "business analysis"]}}, {"job_id": "100003009047688", "location_code": "hk", "company": "iTalent Company", "job_title": "Assistant Data Analytics Manager - HK Listed Company", "description": "Our client\n\nA HK listed company. They are looking for Assistant Data Analytics Manager to join their team.\n\nYour role\n\nDefine best practice in data architecture, structure and processing\nDesign and create end-to-end ETL processes utilizing tools such as Python and SQL\nData integration from third-party data source\nResearch and explore on new analytic methodology for structured and unstructured data\nPrepare reports and analysis, provide business insights to support the strategic decisions\nVendor management for AI / BI related projects\n\nRequirement\n\nBachelor degree with minimum 5 years of relevant experience in Data Management\nExperience in building & deploying large scale machine learning models\nHands on experience in evaluate and deploy AI models, like NLP classification model and image recognition model, etc\nFamiliar with Tableau, Google Data Studio and Google Cloud Platform (GCP) related tools including Cloud Function, Cloud logging, BigQuery, Google sheet API, PubSub, etc\nProficient in programming using SQL and python\nQuick learner and Able to work independently as well as a good team player, efficient & minimal mistake tolerance\n\nClick \"Apply Now\" to apply for this position or\u00a0call\u00a0us\u00a0at\u00a0+852 2762 4829\u00a0for a confidential discussion. All information collected will be kept in strict confidence and will be used for recruitment purpose only.", "employment_types": ["Full Time", "Permanent"], "selling_points": ["Data artchitecture, processing and integration", "5 yrs+ exp in data management and deploy AI models", "Proficient in SQL, Python and GCP tools"], "locations": ["Not Specified"], "categories": ["Professional Services", "Business Analysis / Data Analysis", "Information Technology (IT)", "DBA", "Data Scientist"], "post_time": "2022-01-14T03:48:17Z", "salary": {"currency": null, "max": null, "min": null, "period": "monthly", "term": null}, "salary_visible": false, "title_keywords": ["manager", "assistant"], "responsibilities": ["management", "data", "analysis", "design", "evaluate", "recruitment", "deploy", "prepare reports", "architecture"], "requirements": {"degrees": ["degree", "bachelor"], "majors": [], "languages": [], "language_level": [], "hard_skills": ["bi", "data management", "integration", "ai", "data analytics", "analysis", "vendor", "tableau", "sql", "programming", "python", "processing"], "soft_skills": ["efficient", "work independently", "good team player", "confidence", "quick learner", "hands on", "learning", "structured"], "languages_combined": []}, "experience_required": {"duration": ["minimum 5 years"], "field": ["management", "relevant experience"]}}, {"job_id": "100003009050889", "location_code": "hk", "company": "KOS International Limited", "job_title": "Senior Manager, Business Analytics & Data Warehouse (Bank)", "description": "Senior Manager, Business Analytics and Data Warehouse (Bank)\n\nBusiness and campaign analysis\nData warehouse and platform enhancement\nData modeling projects\n\nAbout the company\n\nOur client is a fast growing and well-established banking group with extensive branch network in Hong Kong. Due to the recent expansion, they are now looking for a Senior Manager for their Business Analytics and Data Warehouse team.\n\nAbout the role\n\nReporting to Team Head, you will be responsible for preparing various business analysis based on statistical modeling and data mining to provide business insight to management. You have to propose, build and execute predictive modeling and data projects independently. You are required to manage overall performance and security control of data platform. In addition, you will participate in policy and regulatory updates as well as maintenance of data framework to ensure effective operations of data team.\n\nThe Successful Applicant\n\nTo qualify, the successful individual must possess:\n\nUniversity Graduate, preferably in Statistics, Quantitative Analysis, Data Science or related disciplines.\nMinimum 5-7 years of relevant experience in managing data analytics, statistical modeling and data warehouse projects independently.\nStrong business sense, good analytical mind and presentation skills.\nSolid knowledge in SAS, Python, Tableau and other data analytics tools is a must.\nGood command of spoken and written English, Chinese and Mandarin.\nCandidate with less experience will be considered as Manager position.\n\nClick \"Apply Now\" to apply for this position or call Emily Leung at +852 3180 4913 for a confidential discussion. All information collected will be kept in strict confidence and will be used for recruitment purpose only.", "employment_types": ["Full Time", "Permanent"], "selling_points": ["Strong business analytics skills", "Data warehouse and modeling projects", "SAS / SQL required"], "locations": ["Not Specified"], "categories": ["Banking / Finance", "Retail Banking", "Professional Services", "Business Analysis / Data Analysis", "Information Technology (IT)", "Data Scientist"], "post_time": "2022-01-14T11:40:02Z", "salary": {"currency": null, "max": null, "min": null, "period": "monthly", "term": null}, "salary_visible": false, "title_keywords": ["senior manager"], "responsibilities": ["reporting", "data mining", "management", "control", "analytics tools", "maintenance", "data", "operations", "analysis", "recruitment", "banking", "business analysis"], "requirements": {"degrees": ["university graduate"], "majors": ["related disciplines", "data science", "statistics"], "languages": ["english", "chinese", "mandarin"], "language_level": ["good command"], "hard_skills": ["maintenance", "sas", "data warehouse", "data analytics", "analysis", "tableau", "python", "data mining"], "soft_skills": ["independently", "confidence", "responsible", "business sense", "presentation skills", "analytical mind", "extensive"], "languages_combined": [{"language": "english", "language_level": ["good command"]}, {"language": "chinese", "language_level": ["good command"]}, {"language": "mandarin", "language_level": ["good command"]}]}, "experience_required": {"duration": ["minimum 5-7 years"], "field": ["relevant experience"]}}, {"job_id": "100003009045107", "location_code": "hk", "company": "iPYGG Fintech Group Limited", "job_title": "Quantitative Developer", "description": "\u00a0\u25cf Explore machine learning methods for portfolio construction and risk management\n\n\u25cf Demonstrate interest in learning about the fintech ecosystem and various stakeholders involved\n\n\u00a0\n\nExplore different approaches in Machine Learning and Deep Learning for creating trading strategies\nDevelop a trading bot for short term investments on futures and options\n\nJob Requirements:\n\n\u25cf Graduated from Computer Science, Computer Engineering, Financial Engineering, Information Technology, Electrical Engineering or Finance majors\n\n\u25cf Strong understanding of different machine learning techniques (clustering, decision tree learning, artificial neural networks)\n\n\u25cf Knowledge of statistical techniques and concepts (regression, time series analysis, statistical tests.)\n\n\u25cf Experience with Python libraries (pandas, numpy, scikit-learn, selenium etc.) for data processing and process automation\n\n\u25cf Proficiency with a deep learning framework such as TensorFlow or Keras\n\n\u25cf Experience with database management systems like MySQL\n\n\u25cf Solid knowledge of computer science fundamentals including algorithms, data structures, databases\n\n\u25cf Ability to document and present research in a methodological manner\n\n\u25cf Self-driven candidate that can take responsibility and work independently whilst collaborating with others\n\n\u25cf Strong problem-solving skills with an emphasis on product development and research\n\n\u25cf 5-day work week\n\n\u25cf Write defensive production-grade code with emphasis on readability, modularity, and reusability\n\nHave knowledge about trading strategies and experience with Interactive brokers API\nHave an in depth understanding of Financial Models, indicators, and futures and options\n\n\n\nGood to have:\n\n\u25cf Familiarity with fundamental portfolio management concepts like MPT, CAPM and basic risk metrics", "employment_types": ["Full Time", "Permanent"], "selling_points": ["Young energetic working environment", "Building disruptive solution in the market", "Promotion opportunities"], "locations": ["Tsuen Wan Area"], "categories": ["Banking / Finance", "Investment", "Information Technology (IT)", "Software Development", "Data Scientist"], "post_time": "2022-01-13T07:13:24Z", "salary": {"currency": "HKD", "max": 24999, "min": 17000, "period": "monthly", "term": null}, "salary_visible": true, "title_keywords": ["developer"], "responsibilities": ["management", "clustering", "data", "financial models", "analysis", "systems", "data processing", "develop", "database", "databases"], "requirements": {"degrees": [], "majors": [], "languages": [], "language_level": [], "hard_skills": ["basic", "analysis", "code", "databases", "python", "problem-solving skills", "processing"], "soft_skills": ["work independently", "deep", "learning", "problem-solving skills", "driven"], "languages_combined": []}, "experience_required": {"duration": [], "field": ["database management", "trading"]}}, {"job_id": "100003009049675", "location_code": "hk", "company": "P & A Consultant Limited", "job_title": "Sr. Data Analyst / Data Analyst/ Data Engineer  X2 - (Top Urgent )", "description": "Sr. Data Analyst/ Data Analyst/ Data Engineer X2\u00a0\nLocation : Tsuen Wan ( 5 Days ) Salary : 23-38K ( Negotiable)\u00a0\n\nResponsibilities :\u00a0\n\n\nResponsible for the structuring & execution of the company\u2019s in-house data management & business intelligence planning\nGathering & understanding of business & user requirement, then plan out the execution of the business intelligence projects\nStructure & execute company\u2019s data-collection tasks, ETL process, and manage data warehouse\nBuild up front-end Business Intelligence dashboards / platforms for varies in-house units\nProvide maintenance and support for existing applications\u00a0\n\nRequirements:\n\n\n2-8 years of experience in Data Analyst position\n\nRequired knowledge in: SQL, Tableau, database structure\nAdditional knowledge in: Python, MS Dynamic (ERP), ETL tools, preferred\nStrong sense of responsibility and a good team player;\nGood communication skills including spoken, written English and Chinese\nCandidates have less exp also will be consider\n*** Personal data will be treated with strict confidential and used for recruitment purpose only\n*** P & A consultant Ltd will not charge any fees from the above-stated job-seeker, your job apply to our company means your acceptance of our terms and conditions.", "employment_types": ["Full Time"], "selling_points": [], "locations": ["Tsuen Wan Area"], "categories": ["Professional Services", "Business Analysis / Data Analysis", "Information Technology (IT)", "Product Management / Business Analyst", "Data Scientist"], "post_time": "2022-01-15T03:50:34Z", "salary": {"currency": null, "max": null, "min": null, "period": "monthly", "term": null}, "salary_visible": false, "title_keywords": ["data analyst", "data engineer"], "responsibilities": ["user requirement", "management", "maintenance", "data", "plan", "planning"], "requirements": {"degrees": [], "majors": [], "languages": ["english", "chinese"], "language_level": ["good"], "hard_skills": ["erp", "tableau", "sql", "dynamic", "python"], "soft_skills": ["communication skills", "good team player", "dynamic", "sense of responsibility"], "languages_combined": [{"language": "english", "language_level": ["good"]}, {"language": "chinese", "language_level": ["good"]}]}, "experience_required": {"duration": ["2-8 years"], "field": []}}, {"job_id": "100003009048677", "location_code": "hk", "company": "Lloyd Karson International Limited", "job_title": "Sr Data Analyst / Senior System Analyst \u2013 Data warehouse - Insurance (ETL/ SSIS /PowerBI)(40k \u2013 50k)", "description": "The client is a global prestigious MNC Insurance Group, is now seeking a new headcount for Senior Data Analyst / Senior System Analyst \u2013 Data warehouse - Insurance (ETL / SSIS / PowerBI) (HKD40k \u2013 50k) to join their team\n\nResponsibilities:\n\nDesign, build and maintain datawarehouse / datamart models - a centralized repository of integrated data from various data sources, and required components such as ETL processes, reports and dashboards\nDesign and create end-to-end ETL processes utilizing tools such as MS SQL Server Integration Services (SSIS), SSAS or others\u00a0\nUtilize Microsoft Power BI and SQL Server Reporting Services in designing and building reports and dashboards\nDefine and create business datamarts / datasets, measures, KPIs and dashboards to empower data analytic\u00a0capability across functional teams for Life Business\nStudy and understand\u00a0the Company\u2019s business processes and applications, including their effect on data and reporting, and applies the knowledge gained in designing datasets, reports and dashboards\nIdentify and document requirements for DWH components, dashboards and reports by working with IT and SMEs\nPrepare test plan, test cases / scripts, perform testing and user training\u00a0\nAssemble performance statistics, analyzes them and makes recommendations for improvements\nEstablish data dictionary and other related documentation\n\nRequirements:\n\nBachelor degree with minimum 5 years of relevant experience in Business / Requirement Analysis, Data Transformation & Visualization, preferably in insurance industry\nProven experience in data-mapping, ETL process, data-modeling and reporting / dashboard functions is required\nSound experience using Microsoft Azure, Microsoft SQL Server, SSIS, SSRS, SSAS, PowerBI\u00a0\nGood knowledge of insurance products, operations, policy admin system would be an advantage\nGood analytical, problem solving and communication skills \u00a0\nAble to articulate business processes / requirements to all levels\nProficient working independently and in a team setting\nHave can-do attitude and willing to go the extra mile\nPossess excellent skill in writing and communicating in both English and Cantonese\n\nIf you would like to apply for this Senior Data Analyst / Senior System Analyst \u2013 Data warehouse \u2013 Insurance (ETL / SSIS / PowerBI)(HKD40k \u2013 50k) role or find out more, please click \"Apply Now\" or send your resume to arthurwong(at)lloydkarson.com quoting the reference: 137212", "employment_types": ["Full Time", "Permanent"], "selling_points": ["Design, build & maintain datawarehouse for Life", "Data-mapping / modeling, ETL process, Dashboard", "MS Azure, MS SQL Server, SSIS, SSRS, SSAS, PowerBI"], "locations": ["Quarry Bay"], "categories": ["Banking / Finance", "Others", "Information Technology (IT)", "DBA", "Data Scientist"], "post_time": "2022-01-14T07:01:20Z", "salary": {"currency": "HKD", "max": 54999, "min": 35000, "period": "monthly", "term": null}, "salary_visible": true, "title_keywords": ["system analyst", "data analyst"], "responsibilities": ["reporting", "power bi", "related documentation", "data", "teams", "design", "testing", "maintain", "reports", "plan", "designing", "kpis"], "requirements": {"degrees": ["degree", "bachelor"], "majors": ["business", "insurance"], "languages": ["cantonese", "english"], "language_level": ["excellent"], "hard_skills": ["azure", "data warehouse", "analysis", "problem solving", "microsoft sql server", "go"], "soft_skills": ["communication skills", "independently", "can-do attitude", "problem solving", "articulate"], "languages_combined": [{"language": "cantonese", "language_level": ["excellent"]}, {"language": "english", "language_level": ["excellent"]}]}, "experience_required": {"duration": ["minimum 5 years"], "field": ["sql", "business", "relevant experience", "insurance industry"]}}, {"job_id": "100003009038812", "location_code": "hk", "company": "Pong Yuen Holdings Ltd", "job_title": "Data Scientist / Researcher / Software Engineer", "description": "Responsibilities\n\nResearch and develop machine learning models for a wide range of applications including data science, computer vision, computer graphics and natural language processing\nConduct systematic proof-of-principle and proof-of-concept development for proposed algorithms/solutions\nResearch and investigate algorithms to classify and analyse the collected data\nPerform data visualization to show the analytic result and prediction\nDevelop reusable modules/libraries to support different applications/tasks\nRun and analyze experiments to diagnose problems\nConduct prior art search and draft patent for filing preparation\nRequirements\n\nBachelor or above in Computer Science, Mathematics, Physics, Engineering, Statistics or other related technical major fields\nRelevant experience in machine learning, natural language processing and/or knowledge graph with proven track record\nExperience in Data analysis and Visualizations to show predicted data\nExperience in Python, C and common data processing and machine learning libraries\nExperience in developing machine learning and deep learning models\nEffective communication skills and ability to work in a collaborative environment\nCandidate with less experience may also be considered as junior position", "employment_types": ["Full Time"], "selling_points": [], "locations": ["Shatin Area"], "categories": ["Professional Services", "Business Analysis / Data Analysis", "Sciences, Lab, R&D", "Research & Development (R&D)", "Information Technology (IT)", "Data Scientist"], "post_time": "2022-01-11T07:52:24Z", "salary": {"currency": null, "max": null, "min": null, "period": "monthly", "term": null}, "salary_visible": false, "title_keywords": ["software engineer", "researcher", "data scientist"], "responsibilities": ["graphics", "visualization", "data", "diagnose", "develop", "analyse"], "requirements": {"degrees": ["bachelor"], "majors": ["mathematics", "engineering", "statistics", "physics", "computer science"], "languages": [], "language_level": [], "hard_skills": ["python", "c", "analysis", "processing"], "soft_skills": ["communication skills", "learning", "deep", "collaborative"], "languages_combined": []}, "experience_required": {"duration": [], "field": ["data analysis", "relevant experience", "developing"]}}, {"job_id": "100003009046450", "location_code": "hk", "company": "Ambition", "job_title": "Data Engineer / Data Analyst - Buy Side", "description": "Data Engineer / Data Analyst - Buy Side\n\nResponsibilities:\n\n\nCollect and clean structured and unstructured data, develop and maintain data pipeline, analyze and visualize financial/fund data\nDevelop and maintain front and back-end database architecture\nTransform data into meaningful conclusions and recommendations\nPropose and implement automation pipeline that supports daily operation processes\nCollaborate with other teams to promote a data-driven approach within the firm\nAd-hoc tasks related to data processing and analysis\nAssist in IT-related initiatives\nLiaise with external data and IT vendors\n\nRequirements:\n\n\nDegree in Computer Science, Engineering, Data Analytics, Financial Engineering or related disciplines\n1 year+ of work experience in related areas (preferably in the financial industry)\nProficiency in Python is a must\nKnowledge in ML/NLP and HTML/CSS/JavaScript is preferable\nSolid knowledge of computer science fundamentals including algorithms, data structures, and databases\nFamiliarity with web frameworks such as Flask or database systems such as MySQL\nAbility to work independently\nA team player and a self-starter, with a strong sense of responsibility and the ability to work well under pressure\nDetail-oriented, solid numerical reasoning ability, excellent problem-solving skills\nStrong communication and interpersonal skills\nProficient in both English and Chinese\n\nIf this job isn't quite right for you, but you know someone who would be great at this role, why not take advantage of our referral scheme? We offer HKD1000 in Apple gift cards for every referred candidate who we place in a role. Terms & Conditions Apply. https://www.ambition.com.hk/refer-a-friend", "employment_types": ["Full Time", "Permanent"], "selling_points": ["Python, Machine Learning, NLP, JavaScript, CSS", "Buy Side opportunity - Asset Management", "Work closely with Strategists / Traders"], "locations": ["Not Specified"], "categories": ["Information Technology (IT)", "Software Development", "Banking / Finance", "Asset Management", "Data Scientist"], "post_time": "2022-01-13T11:16:53Z", "salary": {"currency": "HKD", "max": 54999, "min": 45000, "period": "monthly", "term": null}, "salary_visible": true, "title_keywords": ["data analyst", "data engineer"], "responsibilities": ["collaborate with", "data", "ad-hoc tasks", "analysis", "daily operation", "teams", "develop", "data processing", "maintain", "database", "maintain data", "liaise with", "architecture"], "requirements": {"degrees": ["degree"], "majors": ["related disciplines", "engineering", "computer science"], "languages": ["english", "chinese"], "language_level": ["proficient"], "hard_skills": ["web", "problem-solving skills", "data analytics", "scheme", "html", "ml", "javascript", "databases", "python", "css"], "soft_skills": ["work independently", "under pressure", "sense of responsibility", "detail-oriented", "communication and interpersonal skills", "problem-solving skills", "team player"], "languages_combined": [{"language": "english", "language_level": ["proficient"]}, {"language": "chinese", "language_level": ["proficient"]}]}, "experience_required": {"duration": [], "field": ["related", "financial industry"]}}, {"job_id": "100003009052243", "location_code": "hk", "company": "Cathay Pacific Airways Ltd", "job_title": "Assistant Manager - Cargo Digital Analytics", "description": "Reports to: Cargo Digital Manager- Transformation and Analytics\u00a0\nDepartment:\u00a0Cargo Commercial\n\nRole Introduction\n\n\nTo support the Cargo Digital Manager \u2013 Transformation and Analytics to generate actionable insights to support the data driven culture within Cargo in decision making processes, and to proactively support both cargo commercial and service delivery teams in applying and integrating the right set of metrics, analytics model and visualization into day-to-day operations\nThis role is one of the key capabilities to enhance the analytics power for Cargo with new data, derived insight, tools and training with proper testing and requirement sets. This candidate will work to support Cargo Digital team to cover the\u00a0 whole Cargo function in ensure the compliance of quality & data governance policies and processes so to uphold security, quality and value of the analytics assets.\nKey Responsibility\u00a0\nWork closely with different Cargo business units to ensure a holistic view on analytics, identify potential synergy and ensure data requirements and impact of other databases are well thought through accommodated in any new Cargo digital transformation initiative\nDesign with different cargo business units to frame business questions and analytics / report use cases, identify quantitative / qualitative benefits, and iron out any development and BU action dependencies, such as process change, system integration, etc\nSupport the development of the long term analytics roadmap for cargo department aligning with CX digital strategy\nConsolidate data requirements per use case needs, and seek approval from data owner on data application\nPerform analysis and build dashboard visualizations per BU use case requirement. Conduct dashboard enhancements when needed\nAct as a bridge between Cargo and IT to facilitate analytics related technical development\u00a0\nBring in new data & insight, support data model design and data definitions to ensure proper and aligned application of data across different use cases\nFacilitate new data classification process with respective Cargo BU\nTrain and facilitate cargo business units in order to build up cargo analytics community to strengthen our data-driven decision making power across cargo business units \u00a0\nManage data quality by implementing quality metrics & regular monitoring, working on incidents to maintain accessibility and consistency of data as well as readiness of related analytics capabilities\nEnforce data governance practices to uphold the value of the data access, within the company and external parties\nSupport new digital analysis and data mining solutions to enable operational excellence improvement\n\n\nRequirements\n\n\nMinimum 4 years of working experience relating to data & analytics\nGood understanding of Cargo business is a plus\nStrong analytics abilities, numerate and familiar with statistical algorithms with good business acumen\nExpert in using analytics & query tools e.g. Alteryx and data modelling technique\nProficiency in data visualization tools, ideally QlikSense\nProficiency in scripting languages (Python / SQL)\nTeam player with strong communication & interpersonal skills, able to share effectively across different business streams\nCurious, meticulous, self-motivated and strong continuous improvement mindset\nWorking knowledge in project management / JIRA a plus\nApplication Deadline:\u00a031 Jan 2022\n\n\nPersonal & Application Information\n\nCathay Pacific is an Equal Opportunities Employer. Personal data provided by job applicants will be used strictly in accordance with our personal data policy and for recruitment purposes only. Candidates not notified within eight weeks may consider their application unsuccessful. All related information will be kept in our file for up to 24 months. A copy of our Personal Information Collection Statement will be provided upon request by contacting our Data\u00a0Protection Officer.\n\nPlease note that with effect from 1 December 2021, all employees must be vaccinated in order to access Cathay City and all other Cathay Group Company premises in Hong Kong. Consideration will be given to those who are unable to get vaccinated for valid medical reasons.\n\n\n\n", "employment_types": ["Full Time"], "selling_points": ["Minimum 4 years of working experience", "Data & analytics", "Travel Benefits, 5-days work, Medical Benefits"], "locations": ["Lantau Island"], "categories": ["Transportation & Logistics", "Freight Forwarding", "Supply Chain", "Information Technology (IT)", "Data Scientist"], "post_time": "2022-01-17T02:33:33Z", "salary": {"currency": null, "max": null, "min": null, "period": "monthly", "term": null}, "salary_visible": false, "title_keywords": ["assistant manager"], "responsibilities": ["data", "analysis", "monitoring", "quality", "external parties", "design", "maintain", "databases", "data mining", "report"], "requirements": {"degrees": [], "majors": [], "languages": [], "language_level": [], "hard_skills": ["plus", "data visualization", "sql", "project management", "alteryx", "python", "acumen"], "soft_skills": ["meticulous", "self-motivated", "communication", "project management", "interpersonal skills", "business acumen", "team player"], "languages_combined": []}, "experience_required": {"duration": ["minimum 4 years"], "field": []}}, {"job_id": "100003009049744", "location_code": "hk", "company": "China Mobile Hong Kong \u4e2d\u570b\u79fb\u52d5\u9999\u6e2f", "job_title": "Assistant Customer Data Analytics Manager", "description": "CHINA MOBILE HONG KONG COMPANY LIMITED (\"CMHK\") is the wholly-owned subsidiary of China Mobile Limited (HKEx: 941) (NYSE: CHL), which ranks 65th on the Fortune Global 500.\n\nOur company strives to offer superior service experience and to become the preferable digital partner for customers. We are preserving an environment with trust, responsibility and caring. At CMHK, we commit to maximizing people\u2019s potential and paving the way toward success for every striver. We are now inviting high caliber professional to join us.\n\n\nIn this position, you will:\n\n\nParticipate in the development if CS System Projects, future state products and offerings and collaborate the business analysis result with the stakeholders\nSupport business development by providing customer analytics knowledge and work with business lead to advice internal customers on the best solution\nDevelop and maintain strong relationships with key business stakeholders to ensure a good understanding of business drivers and priorities\nManage the business analysis information to ensure the accuracy of CS system information provided\nProvide incident report and review with team leader for improvement and development\nPerform user acceptance tests, production tests, data validation and integrated tests\nDevelop training documentation and delivers end user training to enable the effective use of CS system/application\n\nTo be successful in this position, you should meet the following requirements:\n\n\nDegree holder in Statistics, Information Technology, Business Analysis related disciplines or equivalent\n\nAt least 5 years relevant experience in\u00a0Business Analyst (System related) or mobile telecom industry with few in supervisory level\nPassion on building new system/application and continuously optimize it based on observation, study system usage and user's need. \u00a0Well organized, with analytical mind and work independently. \u00a0Detail-oriented and eager to work with complex business workflows\nKnowledge and use of Excel, PowerPoint, Cognos, BI tools\n\n\u00a0When you work:\n\n5 days work\u00a0\n\nWhat you enjoy:\n\nDouble pay\nDiscretionary bonus\nLife insurance\nMedical insurance\nAnnual leave\nBirthday leave\nBirthday gift\nMarriage leave\nCompassionate leave\nStaff discount\n\n\n\nCMHK is committed to be an equal opportunity employer. We offer exceptional benefits package and the opportunity to work in a challenging environment. Personal data provided by applicants will be treated strictly in accordance with our personal data policy and for recruitment purposes only.\n\nPlease submit your application to us by clicking the APPLY NOW button and send your full resume with your availability, current and expected salary to us.", "employment_types": ["Full Time", "Permanent"], "selling_points": ["CS System Development", "Customer analytics", "Supervisory experience"], "locations": ["Kwai Hing"], "categories": ["Professional Services", "Business Analysis / Data Analysis", "Information Technology (IT)", "Product Management / Business Analyst", "Data Scientist"], "post_time": "2022-01-14T09:11:24Z", "salary": {"currency": null, "max": null, "min": null, "period": null, "term": null}, "salary_visible": false, "title_keywords": ["manager", "assistant"], "responsibilities": ["collaborate", "documentation", "data", "review", "develop", "maintain", "business analysis", "insurance", "report"], "requirements": {"degrees": ["degree holder"], "majors": ["related disciplines", "business", "statistics", "information technology"], "languages": [], "language_level": [], "hard_skills": ["excel", "bi", "analysis", "powerpoint", "mobile", "documentation"], "soft_skills": ["work independently", "well organized", "detail-oriented", "committed", "analytical mind", "superior"], "languages_combined": []}, "experience_required": {"duration": ["at least 5 years"], "field": ["related", "business", "relevant experience", "digital", "supervisory level"]}}, {"job_id": "100003009048913", "location_code": "hk", "company": "GTS Platform Services Limited", "job_title": "Business Analyst (new headcount)", "description": "Job Responsibilities:\n\nResponsible for data collection, set data indicators and establish data model;\nUnderstand business nature, manage all aspects of a project including planning, execution, timing, quality, cost and risk, etc.;\nLiaise with R&D team to output database and dashboards for trading platform purpose;\nSupport end-users feedback channels and provide solutions to optimize the product strategies;\nCooperate with Operations team and Product team to perform data analysis and reports.\nRequirements:\n\nDegree holder in Computer Science / Statistics / Information Technology or related discipline;\n3+ years of experience in data analysis, preferably in Finance or IT industry;\nHands-on experience in data analytical tools including Tableau, Microsoft Power BI, Cognos, etc.;\nStrong business sense, able to discover problems from data and capture opportunities;\nGood logical and analytical skills, able to work under pressure;\nCandidate with solid management experience can apply Business Intelligence Manager role;\nFluent in speaking Cantonese, English and Mandarin.\nWe offer supportive environment and attractive remunerations to the right candidate:\n\n5 days work\n13 - 21 days annual leave\nDiscretionary bonus\nFestival cash incentives\nMarriage leave\nCompassionate leave\nMedical insurance\nDental scheme\nWFH policy\nUnlimited snacks and drinks provided\nPeriodic tea time gathering", "employment_types": ["Full Time", "Permanent"], "selling_points": ["New headcount", "Tableau, Microsoft Power BI, Cognos", "Excellent business analysis skills"], "locations": ["Tsim Sha Tsui"], "categories": ["Information Technology (IT)", "Product Management / Business Analyst", "E-commerce", "Product Management / Business Analyst", "Data Scientist"], "post_time": "2022-01-14T07:41:06Z", "salary": {"currency": null, "max": null, "min": null, "period": "monthly", "term": null}, "salary_visible": false, "title_keywords": ["business analyst"], "responsibilities": ["cost", "data", "operations", "quality", "provide solutions", "data analysis", "reports", "data collection", "database", "liaise with", "cooperate with", "planning"], "requirements": {"degrees": ["degree holder"], "majors": ["statistics", "computer science", "information technology"], "languages": ["cantonese", "english", "mandarin"], "language_level": ["fluent"], "hard_skills": ["bi", "analysis", "tableau", "analytical skills", "business intelligence"], "soft_skills": ["work under pressure", "hands-on", "analytical skills", "business sense"], "languages_combined": [{"language": "cantonese", "language_level": ["fluent"]}, {"language": "english", "language_level": ["fluent"]}, {"language": "mandarin", "language_level": ["fluent"]}]}, "experience_required": {"duration": ["3+ years"], "field": ["management", "analytical", "finance", "data analysis", "it", "business"]}}, {"job_id": "100003009043195", "location_code": "hk", "company": "Arup", "job_title": "Data Analyst", "description": "Responsibilities:\n\nCreate, develop and maintain architecture of data and business intelligence system\nGet involved in data mining, management and develop analytics models\nDevelop analytics algorithm and data roadmap\nIdentify and solve business-related problems by using data-driven techniques\nResearch latest technologies and techniques of big data sources / deep learning and Machine Learning techniques\nCommunicate findings with internal users and prepare reports to present workable solutions to both technical and non-technical stakeholders\nWork with developers and application analysts within the team to deliver results to the clients in easy-to-understand format\n\nQualifications & Experience required:\n\nFresh PhD with research experience or Master Degree in Mathematics, Data Science or related discipline with around 3 years of relevant experience\nExperience in applying data analytics, data mining and machine learning within business environment\nExperience in a consulting firm environment will be an advantage\nHave an interest in engineering and building industry\nHands-on experience in TensorFlow, Keras and Python\nStrong analytical and organization skills\nAble to work independently coupled with strong interpersonal skills\nProficiency in both written and spoken English and Chinese\n\n\nWe offer a competitive remuneration package commensurate with qualifications and experience to the right candidate including Global Profit Share scheme, additional fringe benefits of maternity/paternity leave and long-term career development opportunities.\u00a0\nFor interested applicants, please click \u201cApply Now\" to submit your online application.\n\nTo explore more job opportunities in Arup, please visit our website at http://www.arup.com/Careers/Experienced_Hires/ApplyForAJob\n\nPersonal data collected will be used for recruitment purpose only. Applicants not contacted within 8 weeks may consider their applications unsuccessful.\n\u00a0", "employment_types": ["Full Time", "Permanent"], "selling_points": [], "locations": ["Kowloon City Area"], "categories": ["Professional Services", "Business Analysis / Data Analysis", "Information Technology (IT)", "Data Scientist"], "post_time": "2022-01-12T10:11:27Z", "salary": {"currency": null, "max": null, "min": null, "period": null, "term": null}, "salary_visible": false, "title_keywords": ["data analyst"], "responsibilities": ["management", "prepare reports", "consulting", "data", "big data", "website", "develop", "maintain", "recruitment", "career development", "data mining", "personal data", "architecture"], "requirements": {"degrees": ["master degree"], "majors": ["mathematics", "data science"], "languages": ["english", "chinese"], "language_level": ["proficiency"], "hard_skills": ["data analytics", "scheme", "python", "data mining", "business intelligence"], "soft_skills": ["work independently", "deep", "organization skills", "hands-on", "learning", "interpersonal skills", "business environment", "driven"], "languages_combined": [{"language": "english", "language_level": ["proficiency"]}, {"language": "chinese", "language_level": ["proficiency"]}]}, "experience_required": {"duration": ["3 years"], "field": ["research", "consulting", "related", "development", "business", "relevant experience"]}}, {"job_id": "100003009049857", "location_code": "hk", "company": "Orient Overseas Container Line Ltd (OOCL)", "job_title": "Senior Officer / Assistant Manager, Corporate Process Data Analytics, Traffic Control Center", "description": "Responsibilities:\nTo transform TCC end-to-end process workflow to next era of digitalization\nTo steer TCC system initiatives and requirements, prioritize development items with ISD\nTo provide first line support on applications usage problem and follow up production issues with ISD\nTo provide trainings for TCC new joins and assist the teams in live application of system in day-to-day operations\nTo gain insight and address business issues through data exploration\nTo handle day-to-day shipment disruptions\nTo work in Traffic for short-term on-the-job training\nRequirements:\nUniversity graduate in Business and Information System related disciplines\nAt least 3 years relevant work experience, preferably in shipping industry\nGood communication, analytical, decision making and problem solving skills\nSelf-initiative and sensitive to figures and details\nAble to work independently and under pressure; possess business sense\nProficient in spoken and written English and Chinese, spoken Mandarin preferred\nCompetent in Windows applications and hands-on experience in Spotfire / Tableau will be an advantage\nPlease click \"Apply Now\" to submit your application.\nPersonal data collected will be used for recruitment purpose only.", "employment_types": ["Full Time", "Permanent"], "selling_points": ["Handle day-to-day shipment disruptions", "University graduate in Business&Information System", "At least 3 years relevant work experience"], "locations": ["Wan Chai"], "categories": ["Sales, CS & Business Devpt", "Business Development", "Transportation & Logistics", "Shipping", "Information Technology (IT)", "Data Scientist"], "post_time": "2022-01-14T09:19:28Z", "salary": {"currency": null, "max": null, "min": null, "period": "monthly", "term": null}, "salary_visible": false, "title_keywords": ["senior officer", "assistant manager,"], "responsibilities": ["day-to-day operations", "teams", "data"], "requirements": {"degrees": ["university graduate"], "majors": ["related disciplines", "business"], "languages": ["english", "chinese", "mandarin"], "language_level": ["proficient"], "hard_skills": ["problem solving skills", "information system", "tableau"], "soft_skills": ["work independently", "under pressure", "business sense", "competent", "sensitive to figures", "communication", "hands-on", "self-initiative", "problem solving skills", "decision making"], "languages_combined": [{"language": "english", "language_level": ["proficient"]}, {"language": "chinese", "language_level": ["proficient"]}, {"language": "mandarin", "language_level": ["proficient"]}]}, "experience_required": {"duration": ["at least 3 years"], "field": ["shipping industry"]}}, {"job_id": "100003009043937", "location_code": "hk", "company": "CLPS Technology (Hong Kong) Co., Limited", "job_title": "Data Analyst (Fintech)", "description": "Responsibilities:\n\nManage data requests from other business units, understand their business goals and translate unstructured business questions into quantitative metrics.\nTo be proactively in analytic area e.g. analyze user behavioral data to identify patterns, uncover opportunities, facilitate the formulation of business goals, and to improve sales business and reduce churn.\nResponsible for data pipeline, data modeling, validation, cleansing and governance work\nDevelop Dashboards to facilitate efficient data analysis for product performance, customer profiles and campaign effectiveness;\nConduct quantitative analysis and data mining to support management decisions and provide data-driven recommendation\nEngage with Offshore Data Engineer team on ETL works, data modeling and continuously refine data platform offerings\nDrive automation in related processes and improving efficiency\n\nRequirements:\n\nDegree holder in Computer Science, Math & Statistic, Data Science, IT/IS, Engineering or related data disciplines\nAt least 3-5 years of experiences as data analyst, data scientist or data engineer\nHands-on and Solid experiences in the following areas\nReporting: Management Reporting using BI dashboard & Excel\nBI tools (at least one): QlikView, Power BI and Tableau etc\nDatabase: SQL Server, MySQL, any NoSQL DB\nUnderstanding Azure Data Factory, Azure Synapse would be an advantage\nProven experience in process and analysis of data using SQL or python;\nExperience in cross-functional team or Agile/Scrum/Kanban would be an advantage\nStrong communication skills in both written and presentation\nGood command of both spoken and written in English & Chinese\n\nWe Offer\n\nGood Learning Environment\nCompetitive Package + Benefits\nYoung and Energetic Working Environment\nYear-end Bonus\nRegional Exposure\u00a0\nTo apply for this position, please send\u00a0detailed resume with\u00a0expected salary and date available\u00a0by simply clicking on the \u201cAPPLY NOW\u201d bottom.\u00a0\u00a0", "employment_types": ["Full Time", "Permanent"], "selling_points": ["SQL Server, ETL tools \u2013 Data clearing", "QlikView, Power BI and Tableau etc", "Competitive compensation"], "locations": ["Central & Western Area"], "categories": ["Information Technology (IT)", "DBA", "Technical / Functional Consulting", "Data Scientist"], "post_time": "2022-01-13T02:31:06Z", "salary": {"currency": null, "max": null, "min": null, "period": "monthly", "term": null}, "salary_visible": false, "title_keywords": ["data analyst"], "responsibilities": ["business goals", "management", "data", "cleansing", "analysis", "develop", "data analysis", "data mining"], "requirements": {"degrees": ["degree holder"], "majors": ["data science", "engineering", "it", "computer science", "math"], "languages": ["english", "chinese"], "language_level": ["good command"], "hard_skills": ["excel", "qlikview", "bi", "azure", "agile", "analysis", "tableau", "python", "sql", "server", "math"], "soft_skills": ["communication skills", "hands-on", "presentation", "agile"], "languages_combined": [{"language": "english", "language_level": ["good command"]}, {"language": "chinese", "language_level": ["good command"]}]}, "experience_required": {"duration": ["at least 3-5 years"], "field": ["sql", "team"]}}, {"job_id": "100003009042804", "location_code": "hk", "company": "Clustertech Limited", "job_title": "Data Scientist / Computational Scientist", "description": "Responsibilities:\n\nSolve practical problems by using computational skills and cross-category approaches of data mining/statistics/artificial intelligence/mathematical optimization;\nUtilize user characteristics and behavior data, financial data to do data mining and model building analysis;\nParticipate in client research to collect users\u2019 need, prepare reports of clients\u2019 behavior analysis;\nNeed to travel to the mainland on a need basis.\n\nRequirements:\n\nMajor in Computer Science, Engineering, Statistics or related disciplines;\n1-2 years hands on relevant working experience;\nGood at analytical thinking with solid mathematics knowledge;\nGood master of foundation theories and approaches of data mining or statistics field;\nProficiency in Java, Python, R or at least one programming language;\nKnowledge of data structure and algorithm;\nExperience in processing mass data, model building, and product improvement by mathematical approach is preferable;\nKnowledge of MYSQL,ORACLE database operation with excellent tuning skills is an advantage;\nKnowledge of machine learning or statistics field with experience in data mining projects is preferred;\nTeam spirit, proactive in idea sharing with good communication skills (Chinese and English);\nPreference will be given to candidates with high integrity, team spirit, strong sense of responsibility, and passion for the application of modern computing technology in China.\n\nWe offer competitive remuneration package including 5-day work and 15-day annual leave to the right candidate with excellent career advancement.\n\nAll applications will be treated in strict confidence. Personal information collected will be used solely for the purpose of recruitment. If you are not invited for an interview within 4 weeks, your application will be filed for a further 2 years and be considered for any other appropriate positions within the company or related companies.\n\nFor more information about\u00a0ClusterTech, please visit our web site at\u00a0http://www.clustertech.com.", "employment_types": ["Full Time", "Permanent"], "selling_points": [], "locations": ["Shatin Area"], "categories": ["Information Technology (IT)", "Data Scientist"], "post_time": "2022-01-12T08:52:31Z", "salary": {"currency": null, "max": null, "min": null, "period": "monthly", "term": null}, "salary_visible": false, "title_keywords": ["data scientist", "scientist"], "responsibilities": ["data mining", "analysis", "prepare reports", "data"], "requirements": {"degrees": ["master"], "majors": ["statistics"], "languages": ["english", "chinese"], "language_level": ["good"], "hard_skills": ["java", "python", "programming", "data mining", "r", "processing", "oracle"], "soft_skills": ["communication skills", "team spirit", "sense of responsibility", "passion for", "integrity", "hands on", "learning", "proactive"], "languages_combined": [{"language": "english", "language_level": ["good"]}, {"language": "chinese", "language_level": ["good"]}]}, "experience_required": {"duration": ["1-2 years"], "field": ["statistics", "relevant working experience"]}}, {"job_id": "100003009044031", "location_code": "hk", "company": "CLPS Technology (Hong Kong) Co., Limited", "job_title": "Data Engineer / Analyst", "description": "Responsibilities\n\nResponsible for developing business intelligence, management reports and visualizations on business performance & key metrics using BI tools and excel\nManage data requests from other business units, understand their business goals and translate unstructured business questions into quantitative metrics.\nTo own existing operational reports and manage data related applications (BI applications and data platform)\nTo be proactively in analytic area e.g. analyze user behavioral data to identify patterns, uncover opportunities, facilitate the formulation of business goals, and to improve sales business and reduce churn.\nResponsible for data pipeline, data modeling, validation, cleansing and governance work\nEngage with Offshore Data Engineer team on ETL works, data modeling and continuously refine data platform offerings\nDrive automation in related processes and improving efficiency\nPromote a data-driven culture throughout the organization\n\nRequirements\n\nDegree holder in Computer Science, Math & Statistic, Data Science, IT/IS, Engineering or related data disciplines\nAt least 3-5 years of experiences as data analyst, data scientist or data engineer\nHands on experiences in the following areas:\nReporting: Management Reporting using BI dashboard & Excel\nBI tools (at least one): QlikView, Power BI and Tableau etc\nDatabase: SQL Server, MySQL, any NoSQL DB\nUnderstanding Azure Data Factory, Azure Synapse would be an advantage\nProven experience in process and analysis of data using SQL or python;\nExperience in cross-functional team or Agile/Scrum/Kanban would be an advantage\nStrong communication skills in both written and presentation\nGood command of both spoken and written in English & Chinese", "employment_types": ["Full Time"], "selling_points": ["3-5 years of experiences as data analyst, engineer", "QlikView, Power BI or Tableau", "Process and analysis of data using SQL or python"], "locations": ["Not Specified"], "categories": ["Information Technology (IT)", "Data Scientist"], "post_time": "2022-01-13T02:51:36Z", "salary": {"currency": null, "max": null, "min": null, "period": "monthly", "term": null}, "salary_visible": false, "title_keywords": ["analyst", "data engineer"], "responsibilities": ["business goals", "data", "cleansing", "developing", "management reports", "reports"], "requirements": {"degrees": ["degree holder"], "majors": ["data science", "engineering", "it", "computer science", "math"], "languages": ["english", "chinese"], "language_level": ["good command"], "hard_skills": ["excel", "qlikview", "bi", "azure", "agile", "analysis", "tableau", "python", "sql", "server", "math"], "soft_skills": ["communication skills", "hands on", "presentation", "agile"], "languages_combined": [{"language": "english", "language_level": ["good command"]}, {"language": "chinese", "language_level": ["good command"]}]}, "experience_required": {"duration": ["at least 3-5 years"], "field": ["sql", "team"]}}, {"job_id": "100003009046232", "location_code": "hk", "company": "HK Maxim Recruitment Limited", "job_title": "Data Analyst", "description": "Just one of our excellent client side project management jobs!\nOur client is seeking to appoint a dynamic and forward thinking Data Analyst to manage the internal billing operation\u00a0across the APAC region\u00a0\n\nProject Details\n\nOur client\u00a0is looking for a Data Analyst for a secondment assignment with their client, a reputable global banking and financial services organisation. The successful candidate will manage the internal billing operation for the Asia-Pacific region, which involves coordination with multiple stakeholders across functional groups.\n\nResponsibilities and Duties\nManaging the Asia-Pacific monthly billing process, bringing together price and quantity data using corporate services space data management system and the CS management information tool\u2019s automated rate setting functionality to generate building and management recharges for country teams to use for monthly billing purposes\nPreparing commentaries on variance by business for APAC\u00a0countries and entities, logging issues and errors, preparing and submitting monthly adjustments and all related activities\nActing as quality assurance and reviewing and validating the dataset for monthly financial review meetings from the group operational intelligence dashboard\nAssisting in providing data to support all business partnering activities\nDeveloping and maintaining a comprehensive knowledge of various CS, finance key data sources, formats/outputs and data recipients to ensure the accuracy and integrity of recharges data both in terms of price, quantity\u00a0and recipient entities and cost centres\nEnsuring appropriate data governance across these systems where CS has overall accountability\nWorking closely with stakeholders both within and outside CS, gaining an in-depth appreciation of the data, procedures and systems that are required to produce and process billing files in order to respond to queries and drive improvements\nWorking under pressure and within an environment with a high-volume and diverse activity across the regional real estate portfolio, all of which must be adequately controlled and operated within group financial, planning and quality parameters\nUndertaking responsibility as a coordinator for the regional recharge service desk to track and monitor incoming enquires\nAssisting with quarterly financial resource plan\u00a0exercise and other ad hoc activities\nDesired Skills and Experience\n\nCandidates should demonstrate:\n\nAnalytical background and proven ability in data particularly financial\u00a0analysis, process implementation and production of MI, including the ability to present data within the context of business activities\nData Analysis experience\nHighly numerate and technology literate\nKnowledge of enterprise level financial and billing systems and reporting\nStrong attention to detail and accuracy in all work outputs\nAbility to link functional strategic objectives to day-to-day operational processes and management\nAbility to analyse multiple extensive datasets from golden sources to resolve enquiries\nHighly organised with ability to prioritise a varied and demanding workload\nProven project management skills\nStrong interpersonal skills\nStrong team player\nQualifications/Educational Requirements\nBachelor\u2019s degree in Computer Science or related discipline\nMicrosoft certification\nEmploying Company Overview and Profile\n\nOur client is one of the world\u2019s leading physical assets management and construction consultancies, dedicated to advising clients in respect of the management and utilisation of their physical assets, and is differentiated by innovation, expertise and experience.\u00a0With principal offices in Dubai, Hong Kong, London, Mumbai, New York and Shanghai, they operate throughout the Americas, Asia Pacific, Europe, India and the Middle East.\n\nMaxim continues to support construction careers in Hong Kong by seeking to identify for our client a suitably accomplished IT Support Analyst to expand their team.\n\nAdditional Benefits Package and Incentives\n\nAttractive salary package available.", "employment_types": ["Full Time"], "selling_points": ["Managing Internal Monthly Billing Process", "Managing large Data", "Excellent Career Prospects"], "locations": ["Central"], "categories": ["Information Technology (IT)", "Data Scientist"], "post_time": "2022-01-13T10:02:36Z", "salary": {"currency": "HKD", "max": 34999, "min": 25000, "period": "monthly", "term": null}, "salary_visible": true, "title_keywords": ["data analyst"], "responsibilities": ["data", "quality", "plan", "ad hoc", "maintaining", "teams", "developing", "monitor", "implementation", "analyse", "business activities", "reporting", "management", "cost", "billing process", "review", "procedures", "data analysis", "systems", "financial analysis", "project management", "planning"], "requirements": {"degrees": ["degree", "bachelor"], "majors": ["computer science"], "languages": [], "language_level": [], "hard_skills": [], "soft_skills": [], "languages_combined": []}, "experience_required": {"duration": [], "field": ["management", "construction"]}}, {"job_id": "100003009042510", "location_code": "hk", "company": "Viu", "job_title": "Data Scientist", "description": "We are now looking for a Data Scientist to join our data team in Hong Kong. You\u2019ll be responsible for building up the best-in-class data science solutions to our production environments. You\u2019ll work closely with our engineering, product and business teams to formulate, communicate and execute a holistic data science strategy that leverages industry best practices.\n\nYour New Role:\u00a0\n\nLead the design, implementation and on-going testing for algorithms for recommendation, propensity modelling and machine learning initiatives.\nWork closely with engineering and product teams to deploy data services to production environments.\nEnhance data collection procedures to optimise analytical and modelling systems.\nEngage with business stakeholders, understand their pain points to identify opportunities and contribute to delivering incremental value to the business.\nChampion a culture of innovation and analytical thinking across the business.\u00a0\n\nWhat makes you succeed\n\nTo be successful in your new position, it is essential to have the following skills:\n\nDegree in Mathematics, Statistics, Actuarial or Computer Science.\nAt least 6 years of demonstrated industry experience in data analytics, performance marketing, or big data related fields.\nExperience with large, complex and multiple data sets from various sources.\nHands-on experience in using big data components such as Hive, Pig, Spark, Kafka, Presto and MapReduce.\nStrong in SQL and Python/R.\nExperience in AWS (Sagemaker, EMR, Glue, EKS), Google Cloud or other Public cloud environments is a must.\nPreferably experience in deploying and running ML algorithms in production; knowledge on ML model and algorithms is highly desirable.\nWorking experience in digital, e-commerce industry, mobile app and web environment is highly desirable.\nGood presentation and communication skills; strong analytical, problem-solving and interpersonal skills.\nFlexible and able to work in a dynamic environment and manage your own time and in a high paced work environment and tight timeline.\nGood command of both written and spoken English and Chinese.", "employment_types": ["Full Time"], "selling_points": [], "locations": ["Kowloon Bay"], "categories": ["Information Technology (IT)", "Application Specialist - Software", "Software Development", "Data Scientist"], "post_time": "2022-01-12T07:49:54Z", "salary": {"currency": null, "max": null, "min": null, "period": null, "term": null}, "salary_visible": false, "title_keywords": ["data scientist"], "responsibilities": ["mobile app", "data", "systems", "teams", "implementation", "design", "testing", "procedures", "big data", "communication", "data collection", "deploy"], "requirements": {"degrees": ["degree"], "majors": ["mathematics", "statistics", "computer science"], "languages": ["english", "chinese"], "language_level": ["good command"], "hard_skills": ["web", "e-commerce", "data analytics", "problem-solving", "aws", "sql", "ml", "mobile", "dynamic", "python", "r", "spark"], "soft_skills": ["flexible", "communication skills", "dynamic environment", "responsible", "problem-solving", "hands-on", "learning", "interpersonal skills", "presentation"], "languages_combined": [{"language": "english", "language_level": ["good command"]}, {"language": "chinese", "language_level": ["good command"]}]}, "experience_required": {"duration": ["at least 6 years"], "field": ["related", "digital", "marketing", "e-commerce"]}}, {"job_id": "100003009048827", "location_code": "hk", "company": "Hong Kong Air Cargo Terminals Ltd", "job_title": "Senior Business Analyst", "description": "Duties\n\nIdentify opportunities to deliver IT Solutions in accordance with the company IT roadmap\nCollect business initiatives, business cases and requirements from user departments and external users, to deliver digitalize and innovative solutions\nPlan and manage the project delivery of end-to-end project life cycle in both agile and waterfall methodology, including solution evaluation, project charter, manage resource plan, backlog and issue management and post-implementation review\nCollaborate with different stakeholders and team members to achieve project objectives in an effective and efficient manner\nKeep abreast with latest trend of technology and products, and cultivate innovation mindset with stakeholders\nProvide technical leadership for production incidents management, impact analysis, solution resolution, stakeholder communication and root cause analysis\nProvide on-going support and maintenance of IT applications to ensure service stability and availability\nEstablish and drive\u00a0continuous improvement of standard IT Practices and Governance\nProvide guidance, train and develop subordinates within the application development team and ensure good team work, morale and discipline are maintained\n\nQualifications\u00a0\n\n\nDegree holder\u00a0in IT, Computer Engineering, Computer Science or related disciplines\nAt least 8 years' working experience in IT application development with at least 4 years' in project management, project delivery, digital solutions design and development, and maintenance aspect\nProven track record of managing multiple application development projects\nPossession of the following experience preferred:\nSolid experience in managing full DevOps software development life cycle (SDLC) for mission critical systems\nManagement of lT team to conduct research and development projects\nManagement of projects performed by internal resources and external vendors\nProven ability to lead, motivate and develop a team\nHands-on experience in working with System Integrators or Consulting companies will be an advantage\nStrong technical knowledge in software architecture and integration design and project delivery in Java development, web design framework, data analytics, cloud computing technology\nGood people management, communication and presentation skills\nPrior experience of application development in airfreight, logistics or aviation industry is definitely an advantage\n\n\nWe offer 5-Day work week with a competitive and comprehensive remuneration package including Chinese New Year bonus, discretionary bonus, transport subsidy, employer topped-up MPF contributions, medical benefits (including family members), voluntary dental coverage (including family members), life insurance, birthday leave, extra annual leave, marriage leave, maternity leave, paternity leave, newborn baby gift, sports centre and free shuttle bus.\n\nInterested parties please apply with full resume detailing experience, qualifications and expected salary by post, by e-mail or click \"Apply Now\".\n\nBy post: Human Resources, 6/F, North Office Block, SuperTerminal 1, Hong Kong International Airport, HK\n\nPlease quote the above reference in your application. To know more about our company, please visit our website https://careers.hactl.com/.\n\nApplicants not invited for interview within four weeks should consider their applications unsuccessful. Applicants\u2019 personal data collected will only be used for the sole purpose of recruitment. The data of unsuccessful applicants will be destroyed within six months.", "employment_types": ["Full Time", "Permanent"], "selling_points": ["Experienced in IT application development", "Guarantee 13th month pay & discretionary bonus", "Free shuttle bus and traffic allowance"], "locations": ["Airport Area"], "categories": ["Information Technology (IT)", "Network & System", "Technical / Functional Consulting", "Data Scientist"], "post_time": "2022-01-14T07:21:55Z", "salary": {"currency": null, "max": null, "min": null, "period": "monthly", "term": null}, "salary_visible": false, "title_keywords": ["senior business analyst"], "responsibilities": ["collaborate with", "business initiatives", "software", "consulting", "data", "design", "communication", "plan", "evaluation", "application development", "conduct research", "implementation", "develop", "resolution", "it roadmap", "logistics", "architecture", "management", "mpf", "review", "provide guidance", "maintenance", "analysis", "systems", "project management", "insurance"], "requirements": {"degrees": ["degree holder"], "majors": ["related disciplines", "it", "computer engineering", "computer science"], "languages": ["chinese"], "language_level": [], "hard_skills": ["web design", "java", "agile", "maintenance", "data analytics", "analysis", "devops", "project management", "sdlc", "integration"], "soft_skills": ["efficient", "good team work", "agile", "communication", "project management", "hands-on", "presentation skills", "comprehensive", "innovative", "leadership"], "languages_combined": [{"language": "chinese", "language_level": []}]}, "experience_required": {"duration": ["at least 8 years", "at least 4 years"], "field": ["maintenance", "consulting", "development", "devops", "design", "project management", "it", "logistics", "software development", "digital", "application development"]}}, {"job_id": "100003009041546", "location_code": "hk", "company": "Seamatch Asia Limited", "job_title": "Data Analysts / Senior Data Analysts / Trainee Analysts x 20 (updated job description)", "description": "\nOur client is one of the largest online shopping ecommerce platforms in Hong Kong. They are looking for new team members to join their data science teams.\n\nData Analysts / Senior Data Analysts / Trainee Analysts\u00a0\n\n20K (entry levels) to around 60K (senior levels)\n\n\nResponsibilities:\n\nAgile team collaboration in continual development of Company's Azure Cloud data analytics platform, data flow and\u00a0data pipelines\nAI analytics and machine learning tools development\nData mining, data discovery and metadata management for business intelligence (BI), quantitative modeling, machine learning and predictive analytics projects\nData visualization, BI reporting, data dashboard design & development\nRequirements:\n\nDegree holder in IT and data sciences related subjects\nOver or around 3 years of technical experience in data engineering, data warehousing, data analytics or related functional areas\nJunior candidates with good knowledge of current AI and machine learning technology trends are welcome\nFamiliar with data visualization tools such as\u00a0Tableau or\u00a0Power BI\nGood knowledge of Python / R / SQL programming, machine learning algorithms, analytic tools such as Microsoft Power BI, TensorFlow, Tableau, Google\u00a0Analytics, AWS Cloud, etc.\nFluent Chinese and English communication with local team members\n\u00a0\n*** Junior candidates with good knowledge of current AI and machine learning technology trends are welcome", "employment_types": ["Full Time", "Permanent"], "selling_points": ["Data Analyst, Senior Data Analyst, Trainee Analyst", "Data warehousing, data integration, data analytics", "Good sense of SQL logic and data flow required"], "locations": ["Tsim Sha Tsui"], "categories": ["Information Technology (IT)", "Application Specialist - Software", "DBA", "Data Scientist"], "post_time": "2022-01-12T04:01:12Z", "salary": {"currency": null, "max": null, "min": null, "period": "monthly", "term": null}, "salary_visible": false, "title_keywords": ["trainee"], "responsibilities": ["reporting", "management", "visualization", "data", "design", "data mining"], "requirements": {"degrees": ["degree holder"], "majors": ["it"], "languages": ["english", "chinese"], "language_level": ["fluent"], "hard_skills": ["google analytics", "bi", "ai", "data analytics", "tableau", "aws", "sql", "programming", "data visualization", "python", "r"], "soft_skills": ["communication", "learning"], "languages_combined": [{"language": "english", "language_level": ["fluent"]}, {"language": "chinese", "language_level": ["fluent"]}]}, "experience_required": {"duration": ["3 years"], "field": ["related", "engineering"]}}, {"job_id": "100003008807572", "location_code": "hk", "company": "Osmium Consulting Group Limited", "job_title": "CRM Data Analyst", "description": "Responsibilities:\n\nUnderstand the business of CRM and platform product ecosystem, design and develop KPI dashboards and reports ( Tableau, etc ), establish the foundation for all key metrics tracking to evaluate overall effectiveness\nCreate actionable insights and provide campaign optimization recommendations for the CRM team through data extraction and transformation processes using data analytics tools ( SQL, R, Python, etc )\nHypothesize and perform exploratory customer analysis ( customer life cycle analysis, customer segmentation, campaign attribution, A / B testing, RFM analysis, customer behavioral modeling, funnel analysis, CLV, etc. ), ability to transform unstructured data into clear business opportunities\nDevelop best practices of customer targeting strategy for customer lifecycle campaigns ( activation, retention, upsell, cross-sell, churn management, etc ) through data-driven methods\nPartner with data engineering / tech team, ability to plan data requirements and priority pipelines to maintain CRM data landscapes with accuracy and efficiency\nPerform deep-dive statistical analysis and develop data models that can be used for long-term optimization\nAd-hoc support on campaign audience targeting list and key campaign analysis\nStreamline data workflow to improve efficiency in operational processes\nActively Monitor metrics trends or patterns and troubleshoot operation gaps in a timely manners\nShare learnings and results with stakeholders of all seniority and create a data-driven environment within the team\nRequirements\n1+ years of experience as data analyst\nExperience in e-commerce, retail, consulting, tech company, financial services is desirable\nBachelor\u2019s degree in business administration, marketing, business analytics, statistics, economics, mathematics, or quant related fields\nFamiliar with Python / R\nProficient in visualization tools like Tableau, Power BI, Mixpanel or similar tools\nExperience with CRM Tools such as Braze / Hubspot / Salesforce\nStrong business acumen and good at problem-solving, have a good understanding of customer analytics techniques ( customer lifecycle, RFM modeling, clustering segmentation, conversion prediction, etc ), basic statistical concepts such as hypothesis testing, regression is required.\nGood communication skills, effectively communicate ideas and requirements to technical and non-technical audiences\nHighly motivated with a can-do attitude, ability to think creatively and strategically for evolving data-driven solutions\nA team player and able to work independently with minimal supervision\nAttention to details and precision\nPassionate about the crypto / blockchain industry is a strong plus\n\n\n\n", "employment_types": ["Full Time", "Permanent"], "selling_points": ["Crypto", "Work From Home", "Great Benefits"], "locations": ["Others"], "categories": ["Marketing / Public Relations", "Marketing - Market Research", "Digital Marketing", "Information Technology (IT)", "Data Scientist"], "post_time": "2022-01-13T07:47:09Z", "salary": {"currency": "HKD", "max": 29999, "min": 20000, "period": "monthly", "term": null}, "salary_visible": true, "title_keywords": ["data analyst"], "responsibilities": ["ad-hoc", "analytics tools", "management", "data", "analysis", "business opportunities", "design and develop", "monitor", "testing", "evaluate", "develop", "maintain", "reports", "troubleshoot", "plan", "tracking"], "requirements": {"degrees": ["degree", "bachelor"], "majors": ["mathematics", "business administration", "economics", "statistics", "marketing", "business analytics"], "languages": [], "language_level": [], "hard_skills": ["blockchain", "plus", "bi", "salesforce", "basic", "crypto", "e-commerce", "problem-solving", "tableau", "python", "r", "acumen"], "soft_skills": ["communication skills", "work independently", "can-do attitude", "problem-solving", "motivated", "attention to details", "business acumen", "team player", "driven", "passionate about"], "languages_combined": []}, "experience_required": {"duration": ["1+ years"], "field": ["consulting", "e-commerce", "tech", "financial services", "retail"]}}, {"job_id": "100003009047304", "location_code": "hk", "company": "Mattex Asia Development Limited", "job_title": "Business Analyst", "description": "Responsibilities\u00a0\n\n\nConverts business requirements into technical solutions, communicates them to engineering teams, breaks down user stories into measurable tasks;\nLiaise among users and the technical developers to ensure business requirements are well defined and properly implemented;\nAssist project implementation with proactively manage all the potential risks on projects and recommend mitigating measures if required;\nFormulate test plans, conduct UAT;\nPrepare training materials and conduct user training;\nHandle end user enquiries, provide solution on a timely manner;\nIdentify new product features through handling of user enquiries;\nAssist with ad-hoc tasks as assigned.\u00a0\n\nRequirements\n\n\nBachelor Degree or above in Computer Science or related field with minimum 3 years relevant experience, candidates with lesser experience can be considered for a more junior level position;\nFamiliar with agile development cycle and UAT process;\nAmbitious to develop both web and mobile app with excellent end-user experience;\nSound understanding of business processes and logistic workflow;\nGood command of spoken and written English and Chinese (Cantonese & Mandarin);\nCommitted, responsible, highly motivated and able to work independently.\n\nWe offer competitive remuneration package with comprehensive fringe benefits to the right candidates:\n\n- Birthday Leave / Marriage Leave / Paternity Leave / Examination Leave\n- Staff Care Programme\n- Career Development Programme\u00a0\n\nContact us\n\nQualified candidate, please email your full resume with academic credentials, working experience, expected salary and availability by clicking the \"apply now\" button as below.", "employment_types": ["Full Time", "Permanent"], "selling_points": ["Converts bus. requirements into technical solution", "Assist project implementation with proactively mgt", "Formulate test plans & conduct UAT"], "locations": ["Lai Chi Kok"], "categories": ["Building & Construction", "Building / Construction / QS", "Sciences, Lab, R&D", "Others", "Information Technology (IT)", "Data Scientist"], "post_time": "2022-01-14T02:48:08Z", "salary": {"currency": null, "max": null, "min": null, "period": "monthly", "term": null}, "salary_visible": false, "title_keywords": ["business analyst"], "responsibilities": ["liaise", "uat", "ad-hoc tasks", "teams", "implementation", "a timely manner", "plans"], "requirements": {"degrees": ["degree or above", "bachelor"], "majors": ["computer science"], "languages": ["cantonese", "english", "chinese", "mandarin"], "language_level": ["good command"], "hard_skills": ["mobile", "agile", "web"], "soft_skills": ["work independently", "agile", "responsible", "committed", "motivated"], "languages_combined": [{"language": "cantonese", "language_level": ["good command"]}, {"language": "english", "language_level": ["good command"]}, {"language": "chinese", "language_level": ["good command"]}, {"language": "mandarin", "language_level": ["good command"]}]}, "experience_required": {"duration": ["minimum 3 years"], "field": ["related", "relevant experience"]}}, {"job_id": "100003009037949", "location_code": "hk", "company": "JFE Consulting Limited", "job_title": "Data Analyst", "description": "\nJob Description\n\n\nIdentify data opportunities and transfer data to meaningful business insights\nCollect data, build and maintain data warehouse,\u00a0data analysis with SQL, OracleDB, Python, Tableau and maintain the dashboard to interpret the analysis results\nIdentify and support improvements in daily reporting and data consolidation through automated and streamlined processes\nWork with other business units on some ad-hoc analytical projects/tasks and handle some regular reports\nCollect data, build and maintain data pipelines, conduct data exploration and visualization, develop and maintain the dashboard to interpret the analysis results\nSupport and align efforts to drive business process analysis meeting to support the Business Unit\nEnsure a valid data analyzing process\u00a0including data extraction, manipulation, processing, storage, archival and more\nRequirements\n\u00a0\nUniversity graduate in Statistics, Data Science, Computer Science/Information System & Mathematics or relevant discipline\n2 years of analytical\u00a0experience including proficiency in SAS (including EM/EG/VIYA) & SQL and superior knowledge of Excel..\nSelf-motivated and able to accomplish multiple tasks\nIntermediate python skills - you are able to write modular, well documented, and scalable code\u00a0\nIntermediate knowledge of standard Data Science and Machine Learning techniques\nStrong communication and conceptual problem-solving skills\nRelentless business focus and drive for impact\n\n\n", "employment_types": ["Full Time"], "selling_points": ["2 years related experience", "SQL, Python, Tableau", "Passionate about data"], "locations": ["Central & Western Area"], "categories": ["Professional Services", "Business Analysis / Data Analysis", "Information Technology (IT)", "Product Management / Business Analyst", "Data Scientist"], "post_time": "2022-01-11T04:24:04Z", "salary": {"currency": null, "max": null, "min": null, "period": "monthly", "term": null}, "salary_visible": false, "title_keywords": ["data analyst"], "responsibilities": ["ad-hoc", "reporting", "manipulation", "visualization", "data", "analysis", "develop", "data analysis", "maintain", "reports", "business process", "maintain data"], "requirements": {"degrees": ["university graduate"], "majors": ["data science", "statistics", "computer science", "mathematics"], "languages": [], "language_level": [], "hard_skills": ["excel", "sas", "problem-solving skills", "information system", "sql", "python", "code", "focus"], "soft_skills": ["self-motivated", "multiple tasks", "communication", "relentless", "learning", "problem-solving skills", "focus", "superior"], "languages_combined": []}, "experience_required": {"duration": ["2 years"], "field": ["sql", "analytical"]}}, {"job_id": "100003009048572", "location_code": "hk", "company": "S.F. Express (Hong Kong) Limited", "job_title": "Senior Business Analyst (IT)", "description": "Responsibilities:\n\nUnderstand the business needs, balance the requirements amongst business stakeholders and recommend solutions\nAnalyze users \u2018 requirements and translate users\u2019 ideas and cases into functional specification\nWork closely with onshore/offshore development team and external vendors to ensure the system can be completed timely\nManage the project schedule from the high-level system design and analysis, system implementation/enhancement, UAT to system deployment\nPrepare and maintain function specification and training documentation\n\nRequirement:\n\nDegree holder of Computer Science, Business Analytics, Information Technology, Logistics or other related disciplines\n3 - 5 year plus working experience in software development, system solution consultancy, or developing programmable documents, preferably in Logistics/Courier Industries or consultant companies\nPractical experience in understanding, analyzing, and verifying user requirements versus business processes to develop programmable documents\nGood command of written and spoken English and Chinese (including Putonghua)\nSelf-motivated, positive, able to work under pressure with emphasis on deliverables\n\nWe offer attractive remuneration package and fringe benefits to suitable candidates. Interested parties, please submit your application to us. If you do not want to apply as JobsDB member, you may send your full resume with your availability, current and expected salaries to recruit01 at sf-express.com.\n\nYou are welcome to visit our website at\u00a0https://htm.sf-express.com/hk/tc/\u00a0for more information about us.\n\nCandidates who are not invited for an interview within 1-month may consider their applications unsuccessful.\n\nAll personal data provided by job applicants will be used only for recruitment purposes and will be treated strictly confidential. Unsuccessful applications will be retained for a maximum period of 24-month.", "employment_types": ["Full Time"], "selling_points": ["Free shuttle bus coverage", "2 months or above performance bonus", "Attractive basic salary"], "locations": ["Tsing Yi"], "categories": ["Information Technology (IT)", "IT Management", "Product Management / Business Analyst", "Data Scientist"], "post_time": "2022-01-14T06:49:42Z", "salary": {"currency": null, "max": null, "min": null, "period": "monthly", "term": null}, "salary_visible": false, "title_keywords": ["senior business analyst"], "responsibilities": ["ideas", "uat", "analysis", "implementation", "system design", "maintain", "schedule", "documentation"], "requirements": {"degrees": ["degree holder"], "majors": ["related disciplines", "business analytics", "computer science", "information technology"], "languages": ["putonghua", "english", "chinese"], "language_level": ["good command"], "hard_skills": ["plus"], "soft_skills": ["self-motivated", "positive", "work under pressure"], "languages_combined": [{"language": "putonghua", "language_level": ["good command"]}, {"language": "english", "language_level": ["good command"]}, {"language": "chinese", "language_level": ["good command"]}]}, "experience_required": {"duration": ["3 - 5 year"], "field": ["business", "logistics", "developing", "software development"]}}, {"job_id": "100003009039727", "location_code": "hk", "company": "Wunderman Thompson Limited", "job_title": "Wunderman Thompson | Data Analyst (Fresh Graduates are Welcome)", "description": "At Wunderman Thompson we exist to inspire growth for ambitious brands. Part creative agency, part consultancy and part technology company, our experts provide end-to-end capabilities at a global scale to deliver inspiration across the entire brand and customer experience.\n\nWhat you'll do\n\nSupport client\u2019s data-driven marketing activities based on various data requirements\nChampion quality data within client\u2019s customer database\nPrepare regular reports and presentations with key findings, observations, business insights and recommendation to clients\nSupport account servicing teams to deliver quality and creative data services to clients via pre-campaign analysis & post-campaign tracking and evaluation\nPerform ad hoc analysis / data extraction\n\nWhat you'll need\n\nDegree holder in Statistics, Economics, Operational Research, Marketing, Social Science, or related disciplines\nProficient in SQL and MS Excel\nUnderstanding of Google Analytics, Google Search Console, Google Ads or Adobe Analytics is preferred\nKnowledge in CRM, database marketing and digital analytics is an advantage\nGood analytical and problem-solving skills, attention to detail and sensitive to numbers\nGood command of written and spoken English & Chinese\nStrong presentation & communication skills and able to translate data into meaningful business insights with recommendation\nProactive, willing to learn, able to work under minimal supervising\nComfortable in a fast-paced and result oriented environment\nFresh Graduates are welcome\n\nWT are committed to growing and sustaining an agency that is both representative and inclusive of the communities we live and work within. At WT, we believe that a diverse and inclusive workforce enables our agency to thrive and deliver brilliant work. We actively welcome applications from individuals and groups who are under-represented and celebrate difference be it ethnicity, religion, age, gender, gender identity or expression, sexual orientation, marital status or disability.\n\nWe are 20,000 strong in 90 markets around the world, where our people bring together creative storytelling, diverse perspectives, inclusive thinking, and highly specialized vertical capabilities, to drive growth for our clients. We offer deep expertise across the entire customer journey, including communications, commerce, consultancy, CRM, CX, data, production and technology.\n\nWunderman Thompson is a WPP agency (NYSE: WPP).\n\nFor more information, please visit us at www.wundermanthompson.com and follow Wunderman Thompson on our social channels via Twitter, Facebook, LinkedIn, and Instagram.\n\nInterested candidates should send your CV, current, expected salary and contact number details to us.\n\nAll information will be treated in the strictest confidence and used for recruitment purposes. Only short-listed candidates will be contacted for interview.", "employment_types": ["Full Time"], "selling_points": ["Fresh Graduates are welcome", "SQL, MS Excel", "Passionate about data"], "locations": ["Quarry Bay"], "categories": ["Information Technology (IT)", "Product Management / Business Analyst", "Data Scientist"], "post_time": "2022-01-11T10:42:25Z", "salary": {"currency": null, "max": null, "min": null, "period": "monthly", "term": null}, "salary_visible": false, "title_keywords": ["data analyst"], "responsibilities": ["supervising", "ad hoc", "data", "analysis", "quality", "teams", "presentations", "communication", "reports", "database", "evaluation", "tracking"], "requirements": {"degrees": ["degree holder"], "majors": ["science", "economics", "statistics", "related disciplines", "marketing"], "languages": ["english", "chinese"], "language_level": ["good command"], "hard_skills": ["google analytics", "analysis", "presentations", "sql", "ms excel", "adobe", "problem-solving skills"], "soft_skills": ["communication skills", "proactive", "presentation", "willing to learn", "committed", "result oriented", "diverse", "attention to detail", "problem-solving skills", "sensitive to numbers", "creative", "driven"], "languages_combined": [{"language": "english", "language_level": ["good command"]}, {"language": "chinese", "language_level": ["good command"]}]}, "experience_required": {"duration": [], "field": ["agency", "brand"]}}, {"job_id": "100003009045871", "location_code": "hk", "company": "DKSH Hong Kong Limited", "job_title": "System Analyst (Business Intelligence)", "description": "Job Responsibilities:\n\nIdentify opportunities to optimize enterprise database architectures as a part of Business Intelligence initiatives\nProvide solutions, perform implementation and monitor validation processes to ensure data integrity and optimal performance\nDesign, implement and monitor source-to-target systems to ensure availability, as well as providing support, problem determination and resolution of business intelligence reporting / technical issues within service level expectations\nParticipate in infrastructure design and installations that suit different business operations\nPerform all phases of the ETL process to ensure compliance with standard operating procedures and global templates\nMaintain internal processes and quality standards documentation to ensure process controls and audits are up to date and aligned to DKSH IT standards\nAssist and support Business Objects application / SQL databases within various project / implementations, including global / country support processes\nConduct knowledge transfer, training and best practice sharing to local Country IT or other internal stakeholders to ensure knowledge availability / continuity\nNegotiate solutions with business stakeholders and users\nEnsure adherence to agreed service/operational level agreements as well as user satisfaction\n\nJob Requirements:\n\nDiploma or above in Computing / Information Technology or equivalent\nAt least 1 year of relevant experience, solid experience in the implementation of business intelligence tools (e.g. SAP Business Warehouse, Business Warehouse on HANA, QlikView, Lumira, Business Objects and SQL) and performance-tuning of business intelligence systems\nProven visual design skills used to create information-dense and easy-to-understand reports/dashboards\nAbility to demonstrate relational database and star schema design and implementation skills\nProficiencies in office productivity tools (e.g. Excel, Word and PowerPoint\nGood command in both written and spoken English and Chinese\nCandidate with more experience will be considered as Senior role\nWorking Location: Wong Chuk Hang\n\n\n\nWe offer 5-day work week, performance bonus and attractive benefits including medical insurance.\u00a0Please apply with full particulars, contact number and current/ expected salary to Human Resources Department, DKSH Hong Kong Limited, 23rd Floor, Tower A, Southmark, 11 Yip Hing Street, Wong Chuk Hang, Hong Kong or fax:2895 9711.\n\nAll personal data collected will be used for recruitment purpose only.\u00a0Candidates will be contacted within 2 weeks if the background and experience are closely relevant to the job requirement.\n\nDrive Growth. Be the Difference. Join DKSH.\n\nDKSH\u2019s strength lies in our great diversity of services, industries, clients, products, regions, and employees from various cultures. We are proud of our people: they are the best in the industry and the reason for our business success. They are passionate, energetic, and purposeful, positively touching millions of lives through the products and services we provide. Join us today if you are ready to \u201cDrive Growth. Be the Difference.\u201d With DKSH, you will experience a world of learning and development, own your career and take business responsibility, and have a positive impact that touches people\u2019s lives.", "employment_types": ["Full Time", "Permanent"], "selling_points": ["Diploma or above in Computing / Information Tech", "Implementation of business intelligence tools", "Optimize enterprise database architectures"], "locations": ["Aberdeen"], "categories": ["Information Technology (IT)", "Support", "Product Management / Business Analyst", "Data Scientist"], "post_time": "2022-01-13T08:59:31Z", "salary": {"currency": null, "max": null, "min": null, "period": "monthly", "term": null}, "salary_visible": false, "title_keywords": ["system analyst"], "responsibilities": ["data", "operations", "ensure adherence", "quality", "design", "maintain", "database", "infrastructure", "monitor", "implementation", "resolution", "reporting", "procedures", "provide solutions", "providing support", "audits", "documentation", "systems", "ensure compliance", "databases"], "requirements": {"degrees": ["diploma or above"], "majors": ["information technology"], "languages": ["english", "chinese"], "language_level": ["good command"], "hard_skills": ["qlikview", "excel", "sap", "word", "powerpoint", "sql", "visual design", "business intelligence"], "soft_skills": [], "languages_combined": [{"language": "english", "language_level": ["good command"]}, {"language": "chinese", "language_level": ["good command"]}]}, "experience_required": {"duration": ["at least 1 year"], "field": ["business", "relevant experience"]}}, {"job_id": "100003009048559", "location_code": "hk", "company": "S.F. Express (Hong Kong) Limited", "job_title": "Business Analyst (IT)", "description": "Responsibilities:\n\nUnderstand the business needs, balance the requirements amongst business stakeholders and recommend solutions\nAnalyze users \u2018 requirements and translate users\u2019 ideas and cases into functional specification\nWork closely with onshore/offshore development team and external vendors to ensure the system can be completed timely\nManage the project schedule from the high-level system design and analysis, system implementation/enhancement, UAT to system deployment\nPrepare and maintain function specification and training documentation\n\nRequirement:\n\nHigher Diploma or above in Computer Science, Business Analytics, Information Technology, Logistics or other related disciplines\n1 year plus the working experience in software development, system solution consultancy, or developing programmable documents, preferably in Logistics/Courier Industries or consultant companies\nPractical experience in understanding, analyzing, and verifying user requirements versus business processes to develop programmable documents\nGood command of written and spoken English and Chinese (including Putonghua)\nSelf-motivated, positive, able to work under pressure with emphasis on deliverables\n\nWe offer attractive remuneration package and fringe benefits to suitable candidates. Interested parties, please submit your application to us. If you do not want to apply as JobsDB member, you may send your full resume with your availability, current and expected salaries to recruit01 at sf-express.com.\n\nYou are welcome to visit our website at\u00a0https://htm.sf-express.com/hk/tc/\u00a0for more information about us.\n\nCandidates who are not invited for an interview within 1-month may consider their applications unsuccessful.\n\nAll personal data provided by job applicants will be used only for recruitment purposes and will be treated strictly confidential. Unsuccessful applications will be retained for a maximum period of 24-month.", "employment_types": ["Full Time", "Permanent"], "selling_points": ["Free shuttle bus coverage", "2 months or above performance bonus", "Attractive basic salary"], "locations": ["Tsing Yi"], "categories": ["Information Technology (IT)", "IT Management", "Product Management / Business Analyst", "Data Scientist"], "post_time": "2022-01-14T06:47:44Z", "salary": {"currency": null, "max": null, "min": null, "period": "monthly", "term": null}, "salary_visible": false, "title_keywords": ["business analyst"], "responsibilities": ["ideas", "uat", "analysis", "implementation", "system design", "maintain", "schedule", "documentation"], "requirements": {"degrees": ["higher diploma or above"], "majors": ["related disciplines", "business analytics", "computer science", "information technology"], "languages": ["putonghua", "english", "chinese"], "language_level": ["good command"], "hard_skills": ["plus"], "soft_skills": ["self-motivated", "positive", "work under pressure"], "languages_combined": [{"language": "putonghua", "language_level": ["good command"]}, {"language": "english", "language_level": ["good command"]}, {"language": "chinese", "language_level": ["good command"]}]}, "experience_required": {"duration": ["1 year"], "field": ["business", "logistics", "developing", "software development"]}}, {"job_id": "100003009043330", "location_code": "hk", "company": "Cornerstone Global Partners", "job_title": "Research Engineer \u2013 AI and Privacy-enhancing Technologies", "description": "Qualifications\n\nApplicants should possess a Bachelor or Master\u2019s degree in Engineering, Computer Science, Computer Engineering, Information Engineering or related disciplines, preferably in artificial intelligence and deep learning. Other qualifications may include:-\n\n\u00a0\u00a0\u00a0\u00a0\u00a0\u00a0\u00a0 3 years or more hands-on working experience on mathematical modelling, statistics learning, data mining, time series, optimization with demonstrated knowledge of machine learning and data mining techniques (regression, decision trees, clustering, neural networks, etc.)\n\u00a0\u00a0\u00a0\u00a0\u00a0\u00a0\u00a0 Familiar with at least one deep learning framework such as TensorFlow /PyTorch\n\u00a0\u00a0\u00a0\u00a0\u00a0\u00a0\u00a0 Technical proficiency in programming languages: Python or C/C++\n\u00a0\u00a0\u00a0\u00a0\u00a0\u00a0\u00a0 Proven experience in working with large databases and relational databases (e.g., SQL/ MongoDB/MariaDB )\n\u00a0\u00a0\u00a0\u00a0\u00a0\u00a0\u00a0 Experience with NLP, cryptography or Federated Learning is a plus\n\u00a0\u00a0\u00a0\u00a0\u00a0\u00a0\u00a0 Experience with Docker, RESTful API and gRPC is a plus\n\u00a0\u00a0\u00a0\u00a0\u00a0\u00a0\u00a0 Passionate, mature, self-motivated, and able to work independently and meet tight deadlines\n\u00a0\u00a0\u00a0\u00a0\u00a0\u00a0\u00a0 Good command of both spoken and written English, Chinese (including Putonghua) preferred\n\nJob Description\n\n\u00a0\u00a0\u00a0\u00a0\u00a0\u00a0\u00a0 Explore on new technologies to develop and support on software projects\n\u00a0\u00a0\u00a0\u00a0\u00a0\u00a0\u00a0 Apply the new modelling framework on privacy computing data platform\n\u00a0\u00a0\u00a0\u00a0\u00a0\u00a0\u00a0 Identify specific areas to improve on, and optimize the framework for further research\n\u00a0\u00a0\u00a0\u00a0\u00a0\u00a0\u00a0 Implement AI algorithms and prototypes to test new ideas\n\u00a0\u00a0\u00a0\u00a0\u00a0\u00a0\u00a0 Deploy machine learning models and APIs to the production environment\n\u00a0\u00a0\u00a0\u00a0\u00a0\u00a0\u00a0 Support full software lifecycle including design, development, debugging, and testing\n\u00a0\u00a0\u00a0\u00a0\u00a0\u00a0\u00a0 Coordinate resources to carry out R&D tasks against the plans and complete the projects (including R&D work, technical report and paper, patents, etc.) as scheduled with high standard\n\u00a0\u00a0\u00a0\u00a0\u00a0\u00a0\u00a0 Build up and maintain a good network with other professional organizations so as to acquire new technologies and create synergy\n\n\u00a0Strongly Preferred\n\n\u00a0\u00a0\u00a0\u00a0\u00a0\u00a0\u00a0 Familiar with containerization and virtualization technologies and platforms such as Docker, Kubernetes and KVM.\n\u00a0\u00a0\u00a0\u00a0\u00a0\u00a0\u00a0 Knowledge/experience with modern operating systems.\n\u00a0\u00a0\u00a0\u00a0\u00a0\u00a0\u00a0 Familiar with Cloud computation and programming, hands-on experience with AWS, Azure, and GCP.", "employment_types": ["Full Time"], "selling_points": ["R&D in leveraging privacy-enhancing technologies", "Knowledge of AI and Deep Learning", "Knowledge of cryptography (plus)"], "locations": ["Causeway Bay"], "categories": ["Information Technology (IT)", "Data Scientist"], "post_time": "2022-01-12T10:52:52Z", "salary": {"currency": null, "max": null, "min": null, "period": "monthly", "term": null}, "salary_visible": false, "title_keywords": ["engineer"], "responsibilities": ["clustering", "ideas", "software", "data", "design", "develop", "testing", "coordinate", "maintain", "databases", "deploy", "data mining", "plans", "operating systems", "report"], "requirements": {"degrees": ["degree", "bachelor", "master"], "majors": ["related disciplines", "computer engineering", "engineering", "computer science"], "languages": ["putonghua", "english", "chinese"], "language_level": ["good command"], "hard_skills": ["r&d", "plus", "restful api", "azure", "c++", "ai", "python", "sql", "aws", "c", "programming", "databases", "data mining"], "soft_skills": ["passionate", "self-motivated", "work independently", "meet tight deadlines", "deep", "mature", "hands-on", "learning"], "languages_combined": [{"language": "putonghua", "language_level": ["good command"]}, {"language": "english", "language_level": ["good command"]}, {"language": "chinese", "language_level": ["good command"]}]}, "experience_required": {"duration": ["3 years"], "field": ["statistics", "programming"]}}, {"job_id": "100003009050099", "location_code": "hk", "company": "ADECCO", "job_title": "RPA Developer (AI Engineer) - HK$40k-50k", "description": "My client is a Leading Financial Institute is looking for high-caliber person to fill the position\n\n\n\nResponsibilities:\n\nBuilding RPA solutions and BPM automation\n\nEnrich and transform corporate data to enable searching, data visualization, and advanced analytics under Continuous delivery model\nWorking with data scientists to industrialise prototype models in data engineering context\nPartner with process re-engineering specialists, working closely business stakeholders to review business operating models and drive streamlining\nWork with Architects, Platform Engineers and Product Management to evaluate and onboard new technology solutions to enrich our platform offering\nRequirements:\n4 years experience in Data Engineering or related working experiences\nData driven thinking capabilities\nExcellent communication skills and experience of working in an international team\nSolid grounding in Financial Service\nExperience with Data processing in large scale enterprise environment is highly desired.\nExperience of implementing complex RPA solution is a big plus\nInterested parties, please\u00a0apply the position via\u00a0Click HERE\u00a0with your CV, or if you would like to have a further discussion on Joey +852 9844 6309 for a confidential discussion about the post.\n\nPlease note that only shortlisted candidates will be notified. All information gathered will be treated in strict confidence and solely used for recruitment purposes.", "employment_types": ["Full Time", "Permanent"], "selling_points": ["AI / Machine Learning technology", "software platforms & automation platform", "Building RPA solutions"], "locations": ["Central"], "categories": ["Information Technology (IT)", "DBA", "Software Development", "Data Scientist"], "post_time": "2022-01-14T09:46:45Z", "salary": {"currency": null, "max": null, "min": null, "period": "monthly", "term": null}, "salary_visible": false, "title_keywords": ["developer", "engineer"], "responsibilities": ["management", "visualization", "data", "review", "evaluate", "re-engineering"], "requirements": {"degrees": [], "majors": [], "languages": [], "language_level": [], "hard_skills": ["rpa", "plus", "processing"], "soft_skills": ["communication skills", "driven"], "languages_combined": []}, "experience_required": {"duration": ["4 years"], "field": ["related", "engineering", "team"]}}, {"job_id": "100003009044042", "location_code": "hk", "company": "Swire Resources Ltd", "job_title": "Data Management Specialist", "description": "Job Duties and Responsibilities\n\nDevelop customer analytics data foundation and deliver behavioral analytics deliverables to business units with business insights and recommendation\nEnable the dialogue about the value and meaning of the analytic insights, and make it easy for business stakeholders to apply data-driving decisions across the business\nExplore the availability, access and transformation/use of sales performance and browsing data for analytics purpose\nDevelop advanced analytics/machine Learning-based solutions to uplift effectiveness of analytics and modelling riding on (i) supervised/ unsupervised Machine Learning techniques (ii) unstructured data e.g. digital footprint\nWork with business users in setting the data strategy and vision\nWork with the business users in collaboration around value-driven data analytics and focus effort on what is best to deliver to business\n\n\u00a0Requirements\n\n\n\nBachelor\u2019s / Master's degree in Mathematics, Computer Science, Data and Information Management or a related discipline\nMinimum 3 years of hands-on experience in developing and executing large scale analytics deliverables/ projects in Retail Industry\nProficiency with one or more programming/scripting languages (e.g. Python, R) as well as SQL\nHands on experience in Google Cloud and Google BigQuery platforms.\nExperience in applying artificial intelligence and machine learning techniques/algorithms infused with industry knowledge to enhance business strategies\nStrong in transforming analytical concepts and developments into business strategies and applications for the uplift of business value\nAbility to build strong stakeholders\u2019 relationships through thorough understanding of business requirements and the ability to analyse issues to find effective solutions\nEffective presentation, communication and interpersonal skills\n\nWe offer competitive remuneration package with\u00a0a wide range of fringe benefits including\n\n5-day work week\nDiscretionary Bonus\nComprehensive Medical Coverage\nStaff Shopping Discount\nNon-contributory Retirement Benefits Scheme\nBirthday Leave\nPlease send resume with present and expected salary to Human Resources Department, Swire Resources Limited, 12/F Kingston International Centre 19 Wang Chiu Road Kowloon Bay Hong Kong or by clicking the \"Apply Now\" button below.\n\nSwire Resources Limited is Equal Opportunity Employer", "employment_types": ["Full Time", "Permanent"], "selling_points": ["Data Analyst, Knowledge in Python, R", "Experience in Google Cloud, Googloe BigQuery", "AI, machine learning techniques/algorithms"], "locations": ["Kowloon Bay"], "categories": ["Professional Services", "Business Analysis / Data Analysis", "Information Technology (IT)", "Data Scientist"], "post_time": "2022-01-13T02:54:02Z", "salary": {"currency": null, "max": null, "min": null, "period": "monthly", "term": null}, "salary_visible": false, "title_keywords": ["specialist"], "responsibilities": ["sales performance", "data", "develop"], "requirements": {"degrees": ["degree", "bachelor", "master"], "majors": ["mathematics", "computer science"], "languages": [], "language_level": [], "hard_skills": ["python", "r", "sql", "programming"], "soft_skills": ["ability to analyse", "hands-on", "hands on", "learning", "thorough", "communication and interpersonal skills", "presentation"], "languages_combined": []}, "experience_required": {"duration": ["minimum 3 years"], "field": ["retail industry", "business", "developing"]}}, {"job_id": "100003009044649", "location_code": "hk", "company": "Ambition", "job_title": "Assistant Manager/ Senior Business Analyst, Data Analytics", "description": "Company\n\nOur client is a well-established online digital company in Hong Kong. They are now expanding their data analytic capacity and looking for a dynamic individual to join their team in Hong Kong.\n\nKey Responsibilities\n\nYou will lead a small team and work closely with Sales and Marketing team, Product Development team and E-commerce team to perform quantitative data analysis on business performance. Being a key member in the team, you will build and monitor performance dashboard to provide timely update to senior management team on the latest business trends, KPI tracking and product usage. You will optimize data mining, data collection and reporting process and ensure relevant insights and business recommendations are delivered effectively and efficiently. You will work closely with senior business stakeholders and participate in business planning and drive innovation.\n\nKey Requiremet\n\nDegree holder in Information Technology, Statistics, Data Analytics or related disciplines.\n3-6 years of relevant work experience in data analytics/ business analysis preferably with exposure to online digital/ e-commerce business.\nGood knowledge in using data visualization tools such as Power BI and Tableau is a must.\nExperienced in database management and ETL tools would be a plus.\nStrong business acumen and experienced in presenting insights and recommendations to senior stakeholders.\nGood problem solving and interpersonal skills are essential.\nExcellent command in English (spoken and written) is required.\n\nIf this job isn't quite right for you, but you know someone who would be great at this role, why not take advantage of our referral scheme? We offer HKD1000 in Apple gift cards for every referred candidate who we place in a role. Terms & Conditions Apply. https://www.ambition.com.hk/refer-a-friend", "employment_types": ["Full Time", "Permanent"], "selling_points": ["Well-established brand name in Hong Kong", "Stable work environment", "Good commercial exposure"], "locations": ["Not Specified"], "categories": ["Information Technology (IT)", "Product Management / Business Analyst", "Others", "Data Scientist"], "post_time": "2022-01-13T04:58:50Z", "salary": {"currency": null, "max": null, "min": null, "period": "monthly", "term": null}, "salary_visible": false, "title_keywords": ["assistant manager", "senior business analyst"], "responsibilities": ["reporting", "monitor performance", "lead a small team", "data analysis", "planning", "data collection", "data mining", "senior management", "tracking"], "requirements": {"degrees": ["degree holder"], "majors": ["related disciplines", "statistics", "information technology"], "languages": ["english"], "language_level": ["excellent"], "hard_skills": ["plus", "bi", "e-commerce", "data analytics", "analysis", "scheme", "tableau", "problem solving", "data visualization", "acumen"], "soft_skills": ["business acumen", "interpersonal skills", "problem solving"], "languages_combined": [{"language": "english", "language_level": ["excellent"]}]}, "experience_required": {"duration": ["3-6 years"], "field": ["business analysis", "digital", "business", "e-commerce"]}}, {"job_id": "100003009050300", "location_code": "hk", "company": "CL Technical Services Ltd.", "job_title": "Senior Business Analyst (ETL, BI, Qliksense / Tableau, over $40K)", "description": "Job details:\n\nCollect requirement from external & internal business users to prepare technical user requirement specifications\nPerform data analyses and extraction, and generate reports by using different data visualization, reporting and analytical tools\nParticipate in the new project initiatives such as new data management projects, business intelligence (BI) and data analytics projects, robotic processing automation projects etc.\nProvide application support and perform testing in various IT systems\nReview coding and testing results produced by vendors\nPrepare tender for IT projects and perform IT procurement\nPerform tasks as assigned by the supervisors\n\nRequirements:\n\nBachelor\u2019s Degree in Information System / Computer Science / Data Science or related disciplines\n5 years' relevant work experience with 1 years of solid experience in project development and implementation\nExperience in at least one of the data visualizations tools such as Qliksense / Tableau / Power BI / IBM Cognos Analytics / SAS etc.\u00a0\u00a0\nExperience in using other databases/tools will also be considered\nWell versed in SQL\nGood understanding of data architectures, infrastructures, software, application and analytics is preferred\nExperience in IT vendor management, procurement and tender preparation is a plus\nGood communication and interpersonal skills\nGood command in both written and spoken English and Chinese\n\nFor more job opportunity, please visit our website: www.clts.com\n\nThe personal information is collected strictly for recruitment purpose only.", "employment_types": ["Full Time"], "selling_points": ["Several Vacancies", "BI & Data warehouse", "Work Life Balance"], "locations": ["Aberdeen"], "categories": ["Information Technology (IT)", "Application Specialist - Software", "IT Management", "Data Scientist"], "post_time": "2022-01-14T10:04:50Z", "salary": {"currency": null, "max": null, "min": null, "period": "monthly", "term": null}, "salary_visible": false, "title_keywords": ["senior business analyst"], "responsibilities": ["user requirement", "reporting", "management", "visualization", "data", "systems", "review", "coding", "testing", "specifications", "reports", "tender", "it procurement"], "requirements": {"degrees": ["degree", "bachelor"], "majors": ["related disciplines", "data science", "computer science"], "languages": ["english", "chinese"], "language_level": ["good command"], "hard_skills": ["plus", "bi", "sas", "information system", "tableau", "vendor", "sql", "databases"], "soft_skills": ["communication and interpersonal skills"], "languages_combined": [{"language": "english", "language_level": ["good command"]}, {"language": "chinese", "language_level": ["good command"]}]}, "experience_required": {"duration": ["5 years", "1 years"], "field": ["development", "management", "it", "procurement"]}}, {"job_id": "100003009048993", "location_code": "hk", "company": "SAE Magnetics (Hong Kong) Ltd", "job_title": "Database Administrator / Database Specialist / DBA", "description": "Responsibilities\n- Perform Server and Oracle database administration (DBA) including performance monitoring & tuning, implementation of changes and application of new patches & versions when required;\n- Carry out system maintenance including installation, troubleshooting, disaster recovery planning & execution, providing end-to-end technical support;\n- Responsible for installing and configuring database server software;\n- Schedule and perform regular server maintenance;\n- Manage the RMAN backup and restoration;\n- Create database management procedures;\n\nRequirement\nAcademic Qualification: Bachelor Degree holder or above\nField of Study: Computer Engineering, Computer Science or IT related disciplines\nYear of Experience: More than 5 years relevant working experience in Oracle database\n- Oracle Certification holder is preferred;\n- Knowledge of data backup, recovery, security, integrity and SQL;\n- Sound knowledge in Windows, Linux platform, Shell Script compiling and ODA;\n- Hands-on experience in disaster recovery and database backup procedures;\n- Hands-on experience in Oracle Database / MS SQL Database / MSSQL Server;\n- Ability to work independently with minimal supervision;\n- Good command of both written and spoken Chinese & English.\n*Candidates with more experience will be considered as Senior Database Administrator.\n\nWorking Location: HK Science Park, Shatin (Frequently travel to Dongguan)\n\nFringe Benefit\n- Five Day Work;\n- Double Pay;\n- Incentive Bonus;\n- 12-19 days Annual Leave;\n- PRC Company Dormitory will be provided;\n- Company Shuttle Bus Services between HK & PRC Plant;\n- Medical, Dental & Life Insurance Scheme;\n\nApplication Method\nInterested parties please click \"APPLY NOW\" or send your application with the title & expected salary to HK Human Resources via Application E-mail.\n\nAll personal data collected will be used for recruitment purpose only. Only short-listed candidates will be contacted for interview.", "employment_types": ["Full Time", "Permanent"], "selling_points": ["Perform Server and Oracle database administration", "5 day work; Double Pay; Incentive Bonus; 12-19 AL", "HK Science Park; Frequently travel to Dongguan"], "locations": ["Shatin Area"], "categories": ["Information Technology (IT)", "DBA", "Data Scientist"], "post_time": "2022-01-15T19:11:36Z", "salary": {"currency": null, "max": null, "min": null, "period": "monthly", "term": null}, "salary_visible": false, "title_keywords": ["specialist", "administrator"], "responsibilities": ["installation", "management", "software", "maintenance", "recovery planning", "technical support", "monitoring", "procedures", "implementation", "troubleshooting", "configuring", "installing", "schedule", "database", "administration"], "requirements": {"degrees": ["bachelor degree holder"], "majors": [], "languages": ["english", "chinese"], "language_level": ["good command"], "hard_skills": ["linux", "server", "scheme", "sql", "mssql", "ms sql", "oracle"], "soft_skills": ["hands-on", "integrity", "work independently"], "languages_combined": [{"language": "english", "language_level": ["good command"]}, {"language": "chinese", "language_level": ["good command"]}]}, "experience_required": {"duration": ["5 years"], "field": ["sql", "disaster recovery", "relevant working experience", "database"]}}, {"job_id": "100003009043813", "location_code": "hk", "company": "Arup", "job_title": "Graduate Data Scientist", "description": "Responsibilities:\nAnalyze engineering discipline business requirements\nAdvise appropriate emerging technologies that would make a step change to our design / advisory services to clients\nAdvise data driven services to our traditional advisory services in built environment and where applicable for creating technology system architecture to support the projects\nManage the digital services programme intended to uplift the regional digital competency and create new services\nKeep abreast of global digital services initiatives to map regional relevance\nCollaborate with domain / business leaders and various regional teams to explore additional digital revenue opportunities and engage them with best practices\nDevelop web applications and backend Application Programming Interface (API)\nAssure application quality through proper design, testing and documentation\nCollaborate closely with in-house engineers and consultants on business support\nQualifications & Experience required:\nDegree in Computer Science or other IT related field\nDemonstrable proficiency\u00a0in:Strong interest in IoT & AI / MLStrong interest in IoT & AI / MLStrong interest in IoT & AI / MLStrong interest in IoT & AI / MLStrong interest in\u00a0IoT & AI / ML\u00a0Strong interest in\u00a0IoT & AI / MLStrong interest in IoT & AI / MLStrong interest in IoT & AI / ML\nLanguages of Javascript, Typescript, C#, Python, Go, Java, C\nKnowledge in ReactJS, VueJS, NodeJS, RESTful API, MongoDB\nExperience in GIS application development is an advantage\nExperience in using cloud platform like AWS, Azure, GCP\nStrong interest in IoT & AI / ML\nDemonstrate passion and quick learning ability for staying ahead of the tech curve: constantly experimenting with new frameworks and technology\nExperience working in an agile team environment\nProficiency in both written and spoken English and\u00a0at least one of the Asian languages will be an advantage\nWe offer a competitive remuneration package commensurate with qualifications and experience to the right candidate including Global Profit Share scheme, additional fringe benefits of maternity/paternity leave and long-term career development opportunities.\n\nFor interested applicants, please click\u00a0\u201cApply Now\u201d\u00a0to submit your online application.\n\nTo explore more job opportunities in Arup, please visit our website at\u00a0http://www.arup.com/Careers/Experienced_Hires/ApplyForAJob\n\nPersonal\u00a0data collected will\u00a0be used for recruitment purpose only. Applicants not contacted within 8 weeks may consider their applications unsuccessful.\u00a0", "employment_types": ["Full Time", "Permanent"], "selling_points": [], "locations": ["Kowloon City"], "categories": ["Information Technology (IT)", "Others", "Data Scientist"], "post_time": "2022-01-13T02:04:25Z", "salary": {"currency": null, "max": null, "min": null, "period": null, "term": null}, "salary_visible": false, "title_keywords": ["data scientist"], "responsibilities": ["collaborate with", "collaborate", "data", "teams", "quality", "design", "develop", "testing", "website", "personal data", "recruitment", "career development", "documentation", "application development", "architecture"], "requirements": {"degrees": ["degree"], "majors": ["it", "computer science"], "languages": ["english"], "language_level": ["advantage", "proficiency"], "hard_skills": ["java", "restful api", "web applications", "azure", "agile", "ai", "scheme", "python", "ml", "make", "aws", "javascript", "typescript", "c", "programming", "documentation", "go", "c#"], "soft_skills": ["learning ability", "driven", "agile"], "languages_combined": [{"language": "english", "language_level": ["proficiency", "advantage"]}]}, "experience_required": {"duration": [], "field": ["development", "application development", "team"]}}, {"job_id": "100003009041904", "location_code": "hk", "company": "GOGO TECH LTD", "job_title": "Specialist, Data Analytics", "description": "For direct application please click here\u00a0\u00a0\u00a0\n\nThis role will be based in Hong Kong and will report to the Data Manager and work closely with the management team. As a key member of our Data team, you will be responsible for several data segments where you will work in partnership with local teams to help them leverage data to accelerate their various projects and initiatives.\n\nYou will develop an in-depth understanding of business operations in order to provide the best analysis and tools (reports, dashboards etc) to support decision-making and performance management.\n\n\nWhat you will be\u00a0delivering\n\n\nUse statistical analysis to find patterns and draw insights from large data sets\nDesign, build and maintain reports and dashboards to enable local teams to make optimal business decisions;\nPerform data extraction and SQL querying upon request;\nConduct in-depth, insightful, and skillfully presented analysis on business topics and trends;\nUncover actionable insights to recommend a feasible solution, for different markets;\nWho you are\n\nProficiency in data science oriented Python libraries such as Pandas, Numpy, Matplotlib and Seaborn\u00a0\nFundamental understanding of statistical methods and tests;\nStrong analytical skills and ability to tell a story from data and present it in a clear and compelling way;\nProficient communication in English is a must;\nAt least a bachelor\u2019s degree in Computer Science, Applied Mathematics, Economics, or an other relevant field;\nNice to have\n\nExperience using big data analytics tools such as Spark, Pyspark\nUnderstanding of machine learning concepts\nPrior usage of cloud computing platforms such as AWS, GCP or Azure\nPrevious experience using statistics or machine learning to solve problems or increase revenue\nInterested?\n\n\nIf you are passionate about coding and problem solving, we would love to hear from you. Feel free to send your CV and Github profile or any projects though here\u00a0to\u00a0you feel like showing off.\n\nPerks and Benefits\n\n\nBirthday Leave \u00a0\nMedical and Dental\u00a0\nStart-up Work Environment\u00a0\u00a0\nFlexible Work Arrangement\u00a0\nGOGOX New Joiner Kit", "employment_types": ["Full Time", "Permanent"], "selling_points": ["Start up culture", "Flexible work arrangements", "Excellent learning opportunity"], "locations": ["Kwun Tong"], "categories": ["Information Technology (IT)", "DBA", "Data Scientist"], "post_time": "2022-01-12T04:37:45Z", "salary": {"currency": null, "max": null, "min": null, "period": "monthly", "term": null}, "salary_visible": false, "title_keywords": ["specialist"], "responsibilities": ["data", "analysis", "teams", "design", "maintain", "reports"], "requirements": {"degrees": ["degree", "bachelor"], "majors": ["economics", "computer science", "applied mathematics"], "languages": ["english"], "language_level": ["proficient"], "hard_skills": ["computing platforms", "azure", "data analytics", "nice", "analytical skills", "aws", "problem solving", "python", "spark"], "soft_skills": ["analytical skills", "clear", "solve problems", "communication", "learning", "problem solving", "passionate about"], "languages_combined": [{"language": "english", "language_level": ["proficient"]}]}, "experience_required": {"duration": [], "field": ["statistics"]}}, {"job_id": "100003009049386", "location_code": "hk", "company": "Viu", "job_title": "Business Insight & Analytics Manager, Hong Kong", "description": "Your New Role\n\nAs a Business Insights & Analytics Manager on the Growth team, you will take a leading role in generating business insights and improving operational efficiency. You will manage data analysts based in local markets and collaborate with regional domain experts across Product, Marketing, Content, Engineering, and Subscription teams to gain insights, drive tangible business impact, and promote a data-driven culture. You will also play a significant role in formulating our team\u2019s overall data strategy and be a part of Viu\u2019s data transformation journey.\u00a0\n\n\n\n\nYour impact\n\nWork closely with different business units to understand their business goals and translate unstructured business questions into quantitative problems.\n\nLead local data analysts to analyze user behavioral data to identify patterns, uncover opportunities, facilitate the formulation of business plans, and to improve conversion and reduce churn.\n\nDesign and build reports and visualizations on business performance.\n\nDesign A/B tests and propose actionable recommendations.\n\nCollaborate with Marketing, Product, Content, and Engineering to further optimize operations.\n\nPromote a data-driven culture throughout the organization.\n\nWhat makes your succeed\n\nDegree in Engineering, Business, Statistics, Computer Science, Data Science, or any related analytical field.\n\n5 \u2013 8 years\u2019 of work experience in prescriptive analytics and implementing statistical models.\n\n3+ years of work experience using SQL.\n\nProficiency in Python/R or other statistical programming languages.\n\nFamiliarity with data exploration and data visualization tools like Tableau.\n\nUnderstanding of statistics concepts (e.g. hypothesis testing, regression analysis).\n\nUnderstanding of A/B test design and implementation.\n\nKnowledge of Marketing Attribution, Marketing Automation and ROAS preferred\n\nExcellent communication skills, able to convey complex concepts to technical and non-technical audiences alike. Proficiency in spoken and written English.\n\nExperience with OTT, startups, tech, or subscription businesses would be a plus.", "employment_types": ["Full Time"], "selling_points": [], "locations": ["Kowloon Bay"], "categories": ["Information Technology (IT)", "Application Specialist - Software", "Technical / Functional Consulting", "Data Scientist"], "post_time": "2022-01-14T08:43:37Z", "salary": {"currency": null, "max": null, "min": null, "period": null, "term": null}, "salary_visible": false, "title_keywords": ["manager"], "responsibilities": ["collaborate with", "business goals", "visualization", "data", "operations", "analysis", "teams", "implementation", "business plans", "design", "testing", "communication", "reports"], "requirements": {"degrees": ["degree"], "majors": ["data science", "engineering", "statistics", "business", "computer science"], "languages": ["english"], "language_level": ["proficiency"], "hard_skills": ["plus", "analysis", "tableau", "sql", "programming", "data visualization", "python", "r"], "soft_skills": ["communication skills", "driven"], "languages_combined": [{"language": "english", "language_level": ["proficiency"]}]}, "experience_required": {"duration": ["8 years", "3+ years"], "field": ["sql", "tech"]}}, {"job_id": "100003009043830", "location_code": "hk", "company": "Attivo Consulting Limited", "job_title": "Senior Data Analyst (40-45K)", "description": "Being the Market Leader in the Engineering Service Field, our client is inviting professionals like you to join their fast-growing System and Support Team for Asia Pacific Region.\n\nResponsibilities:\n\nTo perform complex data compilation and analysis to support business operation for Asia Pacific Region.\nTo ensure proper behavior and data captured into system; Develop KPI\u2019s monitoring\nTo provide various tasks and activities in systems and overall operational support including regular status update, system roll outs / system project implementation\nTo support business master data maintenance in system\nTo coordinate applicable safety work method statements documents, manuals, checklist for analyze and contribute to budgetary process based on projected product offering and manufacturing cost structures.\nHighly interact with I.T. department, as data user perspective to give suggestion and support the development of new modules by providing mock-up as well as hands-on user acceptance test\n\nRequirements:\n\nBachelor\u2019s Degree in Engineering, BBA, Quantitative Analyst or related disciplines;\n6 years or above experience in Data, Business, Operations, System analyst;\nHighly prefer candidate from Technical Industry / Engineering Services Industry / Large-scale Manufacture; such as Elevator, Building Services, Constructions, Automation Systems, Infrastructure Engineering Services Industry\nStrong experience in utilizing ERP systems and KPI\u2019s to drive operational excellence\nExcellent communications skills with ability to develop constructive and cooperative internal and external working relationships\nHighly proficiency in Excel, PowerPoint, Power BI; SAP knowledge is highly preferred; others ERP system will also consider\nExcellent written and communication skills in English is a MUST; Mandarin is important\nCandidate with less experience will be consider as Data Specialist\u00a0\n\nInterested parties please\u00a0click on \"Apply Now\" to attach your full resume (with expected salary & date available) or email to resume(at)attivoasia.com", "employment_types": ["Permanent"], "selling_points": ["Power BI, SAP, ERP system operational excellence", "Regional role, MNC, Prefer Engineer background", "Fluent in English & Mandarin, Logical Thinker"], "locations": ["Not Specified"], "categories": ["Engineering", "Engineering Project Management", "Mechanical", "Information Technology (IT)", "Data Scientist"], "post_time": "2022-01-13T02:06:34Z", "salary": {"currency": null, "max": null, "min": null, "period": "monthly", "term": null}, "salary_visible": false, "title_keywords": ["data analyst"], "responsibilities": ["business operation", "cost", "operational support", "maintenance", "data", "analysis", "monitoring", "systems", "implementation", "develop", "coordinate"], "requirements": {"degrees": ["degree", "bachelor"], "majors": ["related disciplines", "bba", "engineering"], "languages": ["english", "mandarin"], "language_level": ["excellent"], "hard_skills": ["erp systems", "excel", "bi", "sap", "powerpoint", "erp system"], "soft_skills": ["communication skills", "cooperative", "constructive"], "languages_combined": [{"language": "english", "language_level": ["excellent"]}, {"language": "mandarin", "language_level": []}]}, "experience_required": {"duration": ["6 years"], "field": ["system analyst", "business"]}}, {"job_id": "100003009037181", "location_code": "hk", "company": "Centaline Data Technology Limited", "job_title": "Data Analyst / Data Programmer (5-day Work)", "description": "Responsibilities:\n\n* Analyse data from property management system;\n\n* Generate and disseminate reports;\n\n* Implement data flow;\n\n\n\nRequirements:\n\n* University degree or above, major in IT or statistics related discipline;\n\n* 1-4 years working experience in handling data;\n\n* Good knowledge in Python;\n\n* Knowledge on Software development Life Cycle, MSSQL (SSMS, SSIS), ETL, data cleansing;\n\n* Knowledge in Tableau is an advantage;\n\n* With strong sense of responsibility, self-motivated, committed, strong analytical and problem solving skills, good interpersonal & communication skills, team player;\n\n* Detail oriented and well organized;", "employment_types": ["Full Time", "Permanent"], "selling_points": ["Quarterly Bonus / Medical / Education Allowance", "Databank Management", "Data Migration and Analysis"], "locations": ["Tsim Sha Tsui"], "categories": ["Information Technology (IT)", "DBA", "Software Development", "Data Scientist"], "post_time": "2022-01-11T01:59:41Z", "salary": {"currency": null, "max": null, "min": null, "period": "monthly", "term": null}, "salary_visible": false, "title_keywords": ["programmer", "data analyst"], "responsibilities": ["management", "data", "reports", "analyse"], "requirements": {"degrees": ["degree or above"], "majors": ["it", "statistics"], "languages": [], "language_level": [], "hard_skills": ["python", "problem solving skills", "tableau", "mssql"], "soft_skills": ["communication skills", "self-motivated", "sense of responsibility", "detail oriented", "well organized", "committed", "analytical and problem solving skills", "team player", "interpersonal"], "languages_combined": []}, "experience_required": {"duration": ["1-4 years"], "field": []}}, {"job_id": "100003009040466", "location_code": "hk", "company": "Yusen Logistics Global Management Limited", "job_title": "Process Analyst- Master Data Team", "description": "Job Descriptions\n\n\nThis position is to support ensuring master data integrity in core operational system for freight forwarding business as well as managing the process to keep and improve data integrity and quality both from viewpoint of operational efficiency and Data Analytic.\u00a0 Expected to work under the supervision of Manager in charge of master data.\n\n\n\n\u00fcPerform daily master data maintenance tasks in global operational system;\n\u00fcSupport preparing rule or guideline related to master data;\n\n\u00fcMonitor and verify master data quality and take a necessary counter action;\n\n\u00fcSupport planning and executing improvement on master data maintenance process and model fitting to data analytic or operational purpose;\n\n\u00fc\u00a0Communicate with regions and countries about master data maintenance issue.\nQualification & experience Requirements:-\n\nExperience and knowledge of operation in air or ocean freight forwarding is great advantage;\nPreferable to have some working experiences as an office worker, but fresh graduate without experience can be considered as well;\nAbility to work on own initiative within agreed boundaries;\nDegree holder or above in related discipline;\nGood communication and writing skill in English, particularly for preparing a manual, SOP and/or any other documentation;\nExperience and knowledge of freight forwarding operating system (particularly CargoWise One) is great advantage;\nExperience and knowledge to manage master data in any type of system is great advantage;\nImmediately available preferred.\u00a0\n\nInterested parties please send full resume with employment history and\u00a0expected salary\u00a0to HRA Division,\u00a0Yusen Logistics Global Management Limited at Level 31, Tower 1, Kowloon Commerce Centre, 51 Kwai Cheong Road, Kwai Chung or by email to hr.ylhk @ hk.yusen-logistics.com.\n\nYusen Logistics Global Management Limited is an equal opportunity employer. All information collected will be used for recruitment purpose only.", "employment_types": ["Full Time", "Permanent"], "selling_points": ["5 days work 14-20 AL, CargoWise One user", "master data quality & analytic, guideline prepare", "w/ logistics/related biz diploma or up, good Eng."], "locations": ["Kwai Hing"], "categories": ["Transportation & Logistics", "Freight Forwarding", "Supply Chain", "Information Technology (IT)", "Data Scientist"], "post_time": "2022-01-12T23:26:10Z", "salary": {"currency": null, "max": null, "min": null, "period": "monthly", "term": null}, "salary_visible": false, "title_keywords": ["analyst"], "responsibilities": ["communicate with", "maintenance", "data", "quality", "maintenance tasks", "executing", "planning"], "requirements": {"degrees": ["master", "fresh graduate", "degree holder"], "majors": [], "languages": ["english"], "language_level": ["good"], "hard_skills": ["documentation", "writing skill"], "soft_skills": ["communication", "initiative", "writing skill"], "languages_combined": [{"language": "english", "language_level": ["good"]}]}, "experience_required": {"duration": [], "field": ["operation"]}}, {"job_id": "100003009046175", "location_code": "hk", "company": "Target Sourcing Services Hong Kong Limited", "job_title": "Business Analyst (Raw Materials team)", "description": "As a Analyst of Raw Materials, you will be responsible for executing and improving critical functions through developing, building and maintaining data management model. You will also be responsible for enhancing current workflow by process automation and providing details on business metrics by creating reports and dashboards for the raw materials team.\n\nPrinciple Duties and Responsibilities\n\n\nCollect structured and unstructured data, build and maintain data pipelines, conduct data exploration and visualization, develop and maintain the dashboard to interpret the analysis results\nLeverage data science tools/techniques to analysis large data sets through custom models and algorithms to uncover insights, pattern and trends in the data\nIdentify and support improvements in daily work efficiency through automated and streamlined processes\nManage routine data processes e.g. inventory data collection, reconciliation, etc.\nCore responsibilities of this job are described within this job description. Job duties may change at any time due to business needs.\n\nRequirements\n\nCollege degree or equivalent work experience in data analysis\n\n1-2 years of experience in workflow enhancement, workflow digitalization, data analysis and data visualization via dashboards\nExpertise in Microsoft Excel - \u00a0VBA, Power Query\nExperience in MS forms, MS flow, One drive, SharePoint\nDemonstrated ability to work across multiple teams as well as independently\nStrong verbal and written communication skills addressing a variety of levels, internal and external\nHigh attention to detail and accuracy\nFlexible, resilient and nimble, comfortable working in grey areas with constant change\nAccountable with a high degree of initiative\nStrong organization and collaboration skills\nDesired Requirements\n\nExperience in Vendor Management and Product Lifecycle Management systems, Smartsheet, DOMO, and other analytics software\nBenefits\n\n\nEligible team members will receive one of the best earnings packages anywhere, including competitive pay, all-around insurance coverage, training and development and many other perks and benefits. Target is an Equal Employment Opportunity Employer.\u00a0\n\nInterested parties please apply in writing with detailed resume, last salary and\u00a0expected salary.\n\nFor more company information, please feel free to visit:\u00a0www.target.com\n\n(Data collected will be used for recruitment purpose only)", "employment_types": ["Full Time"], "selling_points": [], "locations": ["Hung Hom"], "categories": ["Professional Services", "Business Analysis / Data Analysis", "Information Technology (IT)", "Data Scientist"], "post_time": "2022-01-13T09:50:31Z", "salary": {"currency": null, "max": null, "min": null, "period": "monthly", "term": null}, "salary_visible": false, "title_keywords": ["business analyst"], "responsibilities": ["visualization", "data", "analysis", "inventory", "develop", "maintain", "maintain data", "data collection"], "requirements": {"degrees": ["degree"], "majors": [], "languages": [], "language_level": [], "hard_skills": ["vba", "analysis", "vendor", "microsoft excel", "data visualization"], "soft_skills": ["flexible", "communication skills", "independently", "accountable", "attention to detail", "initiative"], "languages_combined": []}, "experience_required": {"duration": ["1-2 years"], "field": ["data analysis", "management"]}}, {"job_id": "100003009042756", "location_code": "hk", "company": "Avnet Technology Hong Kong Limited", "job_title": "Business Analyst/ Solutions Analyst (RPA Robotic Process Automation)", "description": "Job Duties:\n\n\nResponsible for automation solutions with programming throughout development, testing and implementation stages\nResponsible for analytical solutions with various systems, including projects with new systems\nWorking with business users to provide on-going support and enhancement of automation solutions\nConduct business analysis based on managements\u2019 requirements\nHandle new projects and other ad-hoc reports as assigned\n\nQualification & Experience:\n\n\nDegree holder in Computer Science or related discipline\n2 year of Development & Programming experience\nProficient in VBA, SQL, Java, Python and .NET\nKnowledge of RPA Robotic Process Automation is a definite advantage\nGood command of spoken and written in English, Cantonese and Mandarin\nFresh Graduate will also be considered\nInterested parties please send your application to our career website - Here.\n\n\nAll applications will be treated in strict confidence and personal data provided with be used solely for recruitment purpose. Unsuccessful candidates may be considered for other vacancies. Applicants who are not contacted within one month should consider their applications filed for future reference. All unsuccessful applications will be destroyed within six months.", "employment_types": ["Full Time", "Permanent"], "selling_points": ["5 days work", "Double Pay, Discretionary incentive", "Fresh Graduate will also be considered"], "locations": ["Kowloon Bay"], "categories": ["Professional Services", "Business Analysis / Data Analysis", "Information Technology (IT)", "DBA", "Data Scientist"], "post_time": "2022-01-12T08:42:26Z", "salary": {"currency": null, "max": null, "min": null, "period": "monthly", "term": null}, "salary_visible": false, "title_keywords": ["analyst", "business analyst"], "responsibilities": ["ad-hoc", "systems", "implementation", "testing", "reports", "business analysis"], "requirements": {"degrees": ["fresh graduate", "degree holder"], "majors": ["computer science"], "languages": ["cantonese", "english", "mandarin"], "language_level": ["good command"], "hard_skills": ["vba", "java", "analysis", "sql", "rpa", "programming", "python"], "soft_skills": ["responsible"], "languages_combined": [{"language": "cantonese", "language_level": ["good command"]}, {"language": "english", "language_level": ["good command"]}, {"language": "mandarin", "language_level": ["good command"]}]}, "experience_required": {"duration": ["2 year"], "field": ["development", "programming"]}}, {"job_id": "100003009042503", "location_code": "hk", "company": "Viu", "job_title": "Senior Data Engineer, Hong Kong", "description": "Your New Role\n\nYou will have the opportunities to manage various projects and work closely with the team to facilitate new initiatives.\n\n\n\nWe are looking for a professional to join our data team in Hong Kong. The role will be responsible for building up best in class data infrastructure, data engineering solutions. This involves formulating, communicating, and executing a holistic and forward-looking data strategy that leverages industry best practices around data and technology. The incumbent will also work with cross-functional teams within the organization of different countries.\n\nKey Responsibilities\n\nLeveraging industry best practices to build highly flexible, scalable and cost effective data pipelines and platforms.\nBuild end to end data pipelines, from requirement gathering, ingestion, QA & unit testing to visualization.\nManage the data lakehouse architecture and self-service tools, ensuring that data is highly available and reusable for enabling data science initiatives, analytics and end users to drive business growth.\nDevelop efficient clean code, improve existing code for better performance, code review, execute code builds to test and production environments.\nProductionize machine learning algorithms, build APIs to serve on the Viu platform.\nManage and lead several data projects.\n\nWhat makes you succeed\u00a0\n\nTo be successful in your new position it is important that you are someone who is forward thinking and who takes initiative. Also, it is essential to have the following skills:\n\nDegree in Computer Science, Information System, Actuarial or related discipline.\nAt least 5 years of demonstrated industry experience in data warehouse, ETL, BI, Big data areas and broad exposure to all its sub-disciplines.\nExperience on working with large, complex and multiple data sets from various sources.\nExpert in data architecture, data modelling and design, data pipeline and data integration.\nHands-on experience on using big data components such as Hive, Spark, Presto, Python and Airflow.\nStrong in SQL, Python/Scala.\nExperience in AWS (EC2, S3, Kinesis/Kafka, Athena, Redshift), Google Cloud or other Public cloud environments is a must.\nExperience in leading a small team of data engineers.\nPreferably experience of deploying and running ML algorithms in production; knowledge on ML model and algorithms is highly desirable.\nExperience with Kubernetes, Service Mesh, or Microservices is a plus.\nWorking experience in the digital, e-commerce industry, mobile app and web environment is highly desirable.\nGood presentation and communication skills; strong analytical, problem-solving and interpersonal skills.\nFlexible and able to work in a dynamic environment and manage your own time and in a high paced work environment and tight timeline.\nGood command of both written and spoken English and Chinese.\nCandidates with less experience will be considered as Data Engineer.", "employment_types": ["Full Time"], "selling_points": [], "locations": ["Kowloon Bay"], "categories": ["Information Technology (IT)", "Application Specialist - Software", "Technical / Functional Consulting", "Data Scientist"], "post_time": "2022-01-12T07:48:49Z", "salary": {"currency": null, "max": null, "min": null, "period": null, "term": null}, "salary_visible": false, "title_keywords": ["data engineer"], "responsibilities": ["cost", "mobile app", "visualization", "data", "infrastructure", "review", "big data", "design", "testing", "develop", "communication", "executing", "architecture", "cross-functional teams"], "requirements": {"degrees": ["degree"], "majors": ["computer science"], "languages": ["english", "chinese"], "language_level": ["good command"], "hard_skills": ["clean", "plus", "bi", "web", "e-commerce", "information system", "scala", "ml", "s3", "problem-solving", "microservices", "integration", "spark", "small", "pipelines", "data warehouse", "airflow", "sql", "aws", "dynamic", "python", "mobile", "code"], "soft_skills": ["flexible", "efficient", "communication skills", "dynamic environment", "responsible", "problem-solving", "presentation", "hands-on", "learning", "interpersonal skills", "initiative"], "languages_combined": [{"language": "english", "language_level": ["good command"]}, {"language": "chinese", "language_level": ["good command"]}]}, "experience_required": {"duration": ["at least 5 years"], "field": ["digital", "e-commerce", "team"]}}, {"job_id": "100003009039859", "location_code": "hk", "company": "David James Recruitment Limited", "job_title": "Senior Data Engineer / Data Engineer - Renowned eCommerce platform - HKD$30k - 40k", "description": "My client is a well-known eCommerce\u00a0conglomerate. Recently undergoing a great transformation, they are now looking for energetic data engineers to aid with their rapid growth. You will be working very closely with the product team and potentially owning the data products.\n\nIf you have been working in a traditional firm with standard working yet boring procedure, come join the team and expose in exciting projects.\n\n\nDuties:\u00a0\n\nBuild and optimise batch and streaming data pipelines to provide reliable and organised data products for downstream consumptions (e.g. analytics and machine learning applications)\n\nImprove the deployment of analytical applications utilizing cloud-native architectures and CI/CD tools\n\nRequirements:\u00a0\n\nBachelor\u2019s Degree in Computer Science or\u00a0related disciplines\n1-2 years of experience in data related development\nSolid experience in SQL\nProficiency in Python and at least one static-type programming language (e.g. Java, Scala, C++), especially on concurrency and OOP\n\nIf you are interested in please send us your CV or call us on +852 3619 9859 for a further discussion", "employment_types": ["Full Time", "Permanent"], "selling_points": ["Generous Salary Package and Young Workplace", "Good Exposure to new team expansion", "Project experience in Kafka, MongoDB, K8s and CICD"], "locations": ["Others"], "categories": ["Information Technology (IT)", "Product Management / Business Analyst", "Others", "Data Scientist"], "post_time": "2022-01-11T12:44:50Z", "salary": {"currency": null, "max": null, "min": null, "period": "monthly", "term": null}, "salary_visible": false, "title_keywords": ["data engineer"], "responsibilities": ["data"], "requirements": {"degrees": ["degree", "bachelor"], "majors": ["related disciplines", "computer science"], "languages": [], "language_level": [], "hard_skills": ["java", "c++", "sql", "scala", "programming", "python"], "soft_skills": ["interested in"], "languages_combined": []}, "experience_required": {"duration": ["1-2 years"], "field": ["related", "development", "sql"]}}, {"job_id": "100003009035713", "location_code": "hk", "company": "Konica Minolta Business Solutions (HK) Limited", "job_title": "Data Analyst", "description": "Job Duties:\n\nGather business and operational requirements from stakeholders to build BI reports and analysis with query tools\nProvide maintenance and modification to existing BI reports\nPerform regular reports, business analysis and statistical work on a timely basis and ensure operation data correctness for business units and management\nProvide input on the design and maintenance of BI reports, standard data dashboards, graphics and visuals that provide meaningful business insight\nSupport ad-hoc management insight to facilitate the business decision making process\n\nRequirements:\n\n\nHigher Diploma in Statistics, Data Science, Information Systems or related disciplines\nMinimum 1-2 years' hands-on experience in data analytics\nFamiliarity with data visualization tool (e.g. PowerBI, Tableau)\nProven experience in process and analysis of data using SQL or Python\nProficient in Microsoft Excel, Word & PowerPoint\nGood analytical and problem-solving skills, attention to detail and sensitive to numbers\nPositive, Proactive and open in mindset to learn and adapt new things\nGood command of written and spoken English & Chinese\n\nBenefits:\n\n\n5-Day Work Week\nDouble Pay and Discretionary Bonus\nPublic Holiday\nMedical Insurance\nBirthday Leave\nStaff Recreational Activity", "employment_types": ["Full Time", "Permanent"], "selling_points": ["1-2 years experience in data analytics", "PowerBI, Tableau", "Sensitive to numbers"], "locations": ["Quarry Bay"], "categories": ["Professional Services", "Business Analysis / Data Analysis", "Sciences, Lab, R&D", "Research & Development (R&D)", "Information Technology (IT)", "Data Scientist"], "post_time": "2022-01-10T08:14:44Z", "salary": {"currency": null, "max": null, "min": null, "period": "monthly", "term": null}, "salary_visible": false, "title_keywords": ["data analyst"], "responsibilities": ["graphics", "ad-hoc", "management", "maintenance", "data", "analysis", "design", "reports", "business analysis"], "requirements": {"degrees": ["diploma"], "majors": ["related disciplines", "data science", "statistics"], "languages": ["english", "chinese"], "language_level": ["good command"], "hard_skills": ["data analytics", "analysis", "word", "tableau", "microsoft excel", "sql", "powerpoint", "data visualization", "python", "problem-solving skills"], "soft_skills": ["hands-on", "attention to detail", "problem-solving skills", "sensitive to numbers", "proactive", "positive"], "languages_combined": [{"language": "english", "language_level": ["good command"]}, {"language": "chinese", "language_level": ["good command"]}]}, "experience_required": {"duration": ["minimum 1-2 years"], "field": ["sql"]}}, {"job_id": "100003009043514", "location_code": "hk", "company": "Nigel Frank International", "job_title": "Data Engineer (new headcount)", "description": "About Our Client\n\nMy client is a listed and well-known organisation founded for decades. It is looking for a data specialist to join their growing team in Hong Kong HQ. The role will building up the best-in-class data science solutions to their production environments. It\u2019s an unique opportunity to join the renowned company.\n\nJob Responsibility\n\nResponsible data platform architecture including big data, NoSQL and AI, and applications for providing data services to business users\nDesign and develop architecture, data pipeline, data optimisation\nImplement enterprise-level data warehouse platform, complete data warehouse architecture design, data modeling and ETL development\nBuild analytics tools that utilize the data pipeline to provide actionable insights for end users\n\nJob Requirement\n\n10 years of experience in system development experience on enterprise grade product\nStrong understanding of data architecture, data modeling, data governance, metadata management, data asset management and enterprise architectures\nExperience in Scala, Java, Python, SQL and NoSQL\nExperience in ETL development or Big Data Technologies, or Data Transformation, and modelling\nExcellent command of written and spoken English and Chinese\nDegree or equivalent qualification in Computer Science, Statistics, Information Management or related disciplines\n\nCompensation/Benefits\n\nPerformance bonus\nPermanent, HK-based role\nMedical insurance\nThis is a new role to market and the salary is negotiable. If this outstanding opportunity sounds like your next career move, please click \"Apply Now\". Any enquirers please reach me by +852 3018 0386.\u00a0\n\n", "employment_types": ["Full Time", "Permanent"], "selling_points": ["Data Analytics, Data Engineer", "Exp in ETL, data management, data pipeline, SQL", "5 days work, listed company"], "locations": ["Not Specified"], "categories": ["Information Technology (IT)", "Application Specialist - Software", "Software Development", "Data Scientist"], "post_time": "2022-01-12T15:12:42Z", "salary": {"currency": "HKD", "max": 54999, "min": 30000, "period": "monthly", "term": null}, "salary_visible": true, "title_keywords": ["data engineer"], "responsibilities": ["analytics tools", "data", "design and develop", "big data", "design", "architecture"], "requirements": {"degrees": ["degree"], "majors": ["related disciplines", "statistics", "computer science"], "languages": ["english", "chinese"], "language_level": ["excellent"], "hard_skills": ["scala", "java", "sql", "python"], "soft_skills": [], "languages_combined": [{"language": "english", "language_level": ["excellent"]}, {"language": "chinese", "language_level": ["excellent"]}]}, "experience_required": {"duration": ["10 years"], "field": ["sql", "development", "system development"]}}, {"job_id": "100003009036036", "location_code": "hk", "company": "Orient Overseas Container Line Ltd (OOCL)", "job_title": "Technical Analyst - Application Development", "description": "Responsibilities:\n\nAnalyze user requirements, perform feasibility studies and impact analysis\nPerform technical design, development, unit testing and development integration testing to deliver high performance, scalable, flexible and reliable software systems\nWork with project teams from oversea to perform system integration, testing and production environment setup, deployment and release\nWork with Data Scientist team to perform data research, model design, development and testing\nProduce high quality deliverables based on thorough understanding of business requirements\nProvide technical supports during system development and production roll-out\n\nRequirements:\n\nUniversity graduate in Computer Science, or related disciplines\nAt least 2 year of Python/Oracle/PLSQL/MEAN Stack application development project experience\nSolid understanding of object-oriented programming principles and design\nSolid experience in programming Rich Internet Application (JavaScript, JSON, CSS, SOAP/RESTful web services)\nSolid experience in Machine Learning (e.g. Optimization) projects and Data Visualization Tools is an advantage\nKnowledge of Software Development Life Cycles, requirement study, design walk-through and release control process\nGood command of spoken and written English,\u00a0Putonghua is an advantage\nCandidate with\u00a0more experience will be considered as Senior Technical Analyst\n\n\nInterested parties please send your application letter with detailed resume and expected salary by clicking\u00a0\"Apply Now\"\u00a0.\n\n(Data collected will be used for recruitment purpose only.)\u00a0", "employment_types": ["Full Time", "Permanent"], "selling_points": ["Python/Oracle/PLSQL/MEAN Stack", "Rich Programming Skill", "Machine Learning"], "locations": ["Shatin Area"], "categories": ["Information Technology (IT)", "Application Specialist - Software", "Software Development", "Data Scientist"], "post_time": "2022-01-10T09:10:04Z", "salary": {"currency": null, "max": null, "min": null, "period": "monthly", "term": null}, "salary_visible": false, "title_keywords": ["analyst"], "responsibilities": ["technical supports", "software", "data", "analysis", "systems", "teams", "quality", "design", "testing", "setup"], "requirements": {"degrees": ["university graduate"], "majors": ["related disciplines", "computer science"], "languages": ["putonghua", "english"], "language_level": ["advantage", "good command"], "hard_skills": ["javascript", "programming", "data visualization", "python", "css", "web services", "oracle"], "soft_skills": ["learning"], "languages_combined": [{"language": "putonghua", "language_level": ["advantage", "good command"]}, {"language": "english", "language_level": ["good command"]}]}, "experience_required": {"duration": ["at least 2 year"], "field": ["application development", "programming"]}}, {"job_id": "100003009050716", "location_code": "hk", "company": "Hutchison Telecommunications (Hong Kong) Limited", "job_title": "BI Developer", "description": "Job Responsibilities:\n\nIdentify data sources, transform, correlate and aggregate information, load useful records to Data Warehouses, and formulate Data Marts for users to access\nData integrity assurance, monitor job alerts, rescue/ restore problem data records/ jobs\nAnalyze the information and produce useful summarized figures/ reports to management\nJobs/ scripting/ SQL statements tuning\nAutomation of users reports\nSystem maintenance support\n\nJob Requirements:\n\nDegree or Higher Diploma holder in Computer Science or related disciplines\nFamiliar with Database applications\nExperience in statistics analysis and presentation\nUnderstanding of structural and unstructured data manipulation\nGood command of written and spoken English and Cantonese included Mandarin\n\nComputer Skills:\n\nComputer Software (e.g. MS Office): Talend ETL, Tableau, Oracle OBIEE, Adobe AEM, Google Cloud\nOperating System: Unix/ Linux, Windows Server\nDatabase/ Network: Oracle, MongoDB, MYSQL, MS-SQL\nProgramming Language: PL-SQL, Python, C++, Java, Unix shell scripting, Google Big Query\nOther skills: REST API, JSON, XML, NoSQL, K-SQL\n\nApart from competitive remuneration package and exciting opportunity for career development within the Group, we provide attractive employee benefits such as free company shuttle, free company SIM card and preferential SIM plan offers, comprehensive medical & insurance schemes, as well as full range of other employee well-being provisions.\n\nInterested parties, please apply with full resume, present and expected salary, by clicking \u201cAPPLY NOW\u201d. Please quote the reference number on the e-mail subject.\n\nWe are an equal opportunity employer and welcome applications from all qualified candidates. Personal data collected will be treated in the strictest confidence and handled confidentially by authorised personnel for recruitment-related purposes only within the CK Hutchison Group of companies. The personal data of unsuccessful applicants will be destroyed after the recruitment exercise pursuant to the requirements of the Personal Data (Privacy) Ordinance in Hong Kong.", "employment_types": ["Full Time", "Permanent"], "selling_points": [], "locations": ["Tsing Yi"], "categories": ["Professional Services", "Business Analysis / Data Analysis", "Information Technology (IT)", "Others", "Data Scientist"], "post_time": "2022-01-14T11:13:31Z", "salary": {"currency": null, "max": null, "min": null, "period": "monthly", "term": null}, "salary_visible": false, "title_keywords": ["developer"], "responsibilities": ["management", "data", "maintenance support", "monitor", "reports"], "requirements": {"degrees": ["degree", "higher diploma holder"], "majors": ["related disciplines", "computer science"], "languages": ["cantonese", "english", "mandarin"], "language_level": ["good command"], "hard_skills": ["linux", "oracle", "java", "c++", "analysis", "unix shell", "tableau", "pl", "sql", "adobe", "computer skills", "ms-sql", "programming", "python", "data manipulation", "windows server", "ms office"], "soft_skills": ["comprehensive", "presentation"], "languages_combined": [{"language": "cantonese", "language_level": ["good command"]}, {"language": "english", "language_level": ["good command"]}, {"language": "mandarin", "language_level": ["good command"]}]}, "experience_required": {"duration": [], "field": ["statistics"]}}, {"job_id": "100003009039627", "location_code": "hk", "company": "BDO Financial Services Limited", "job_title": "Data Analyst  \u2013 Banking", "description": "Our client is a multinational bank with an all-rounded financial operations at its prime within the APAC region.\u00a0 They are looking for a young and energetic individual to support their Group Finance Project initiatives\n\n\u00a0Responsibilities:\u00a0\n\n\nDevelop Dashboards to monitor operations performance\nManaging data quality issues and data design/solutions\nSupport on UAT and users' transition experience\nConsolidate a large amount of market data and apply analytical methods to generate business insights and improve operational efficiency\nDevelop Qlik Sense solutions (or equivalent) as a BI tool to visualize and automate reporting\nFacilitate and coordinate with different functional units to including front office, middle office and supporting departments to ensure the progress of the projects /initiatives\nCultivate the mindset of internal customers on continuous improvement through various improvement initiatives\nKeep abreast of the market, suggest and propose new improvement initiatives\nLiaise with business users and IT on defining project initiatives, requirement documentation and analysis\nDevelop testing schedules and test plans for UAT with close monitoring on implementation progress\nDocument on workflow procedures for business users\nProvide recommendations on operational process workflows reviews and solutions\n\n\u00a0Requirements:\u00a0\n\nTertiary qualification or above preferred\nAt least 3-5 years\u2019 experience in performing data analysis & extraction with the use of SQL\nExperience in data science and modelling is an added advantage (but not a must)\nGood Knowledge with project mechanics and process design techniques preferred\nWell versed in digital business insight\u00a0\nGood business analysis, problem solving and facilitation skills\nAble to manage personal workload with good communication skills\nGood command of both written and spoken English, Cantonese & Mandarin", "employment_types": ["Full Time", "Permanent"], "selling_points": ["Attractive Remuneration", "Banking Experience preferred", "Data Analysis"], "locations": ["Not Specified"], "categories": ["Banking / Finance", "Financial Services", "Professional Services", "Business Analysis / Data Analysis", "Information Technology (IT)", "Data Scientist"], "post_time": "2022-01-11T10:15:39Z", "salary": {"currency": null, "max": null, "min": null, "period": "monthly", "term": null}, "salary_visible": false, "title_keywords": ["data analyst"], "responsibilities": ["data", "schedules", "operations", "quality", "design", "liaise with", "plans", "market data", "uat", "monitor", "implementation", "develop", "testing", "reporting", "monitoring", "coordinate with", "procedures", "provide recommendations", "documentation", "analysis"], "requirements": {"degrees": [], "majors": [], "languages": ["cantonese", "english", "mandarin"], "language_level": ["good command"], "hard_skills": ["sql", "analysis", "problem solving"], "soft_skills": ["problem solving", "communication skills"], "languages_combined": [{"language": "cantonese", "language_level": ["good command"]}, {"language": "english", "language_level": ["good command"]}, {"language": "mandarin", "language_level": ["good command"]}]}, "experience_required": {"duration": ["at least 3-5 years"], "field": ["data analysis", "sql"]}}, {"job_id": "100003009034843", "location_code": "hk", "company": "Osmium Consulting Group Limited", "job_title": "Data Analyst / Data Engineer ( Up to $40K )", "description": "Responsibilities:\n\nData warehousing and data extract/transform/load (ETL) integration in cloud and on-premise environments\nPerform Data Analytic, Data Visualization, Data Modeling, and Dashboard Building\nTroubleshoot issues on BI reports and dashboards\nWorking with stakeholders across all functions, to understand their needs and how to factor them into the automation and analytics models\nInterpret information requirements from business users and translating them into reporting solutions\n\nRequirements:\n\nDegree in Computer Science/ Engineering/ Information Systems/ Statistics or a related discipline\n1+ years of experience in business intelligence and data analytics\nProficient in converting business requirements into data model solutions and visualization\nStrong commercial and practical experience with data visualization, dashboard, and report development\nExperience in SQL, Power BI, Python is a must; knowledge in tools like AWS would also be an advantage\nHigh energy, self-motivation, and ability to thrive in a fast-paced working environment with a customer-focused attitude\nProficient in spoken and written English is necessary\nCandidates with more experience will be considered for other position", "employment_types": ["Full Time", "Permanent"], "selling_points": ["Data Analytics | Data Engineer | MNC | FinTech", "Python | Power BI | Dynamic and Friendly Culture", "5 Day Work | Attractive Package | Large Scale Firm"], "locations": ["Central"], "categories": ["Professional Services", "Business Analysis / Data Analysis", "Information Technology (IT)", "DBA", "Data Scientist"], "post_time": "2022-01-10T04:24:55Z", "salary": {"currency": "HKD", "max": 44999, "min": 25000, "period": "monthly", "term": null}, "salary_visible": true, "title_keywords": ["data analyst", "data engineer"], "responsibilities": ["warehousing", "reporting", "visualization", "data", "reports", "troubleshoot"], "requirements": {"degrees": ["degree"], "majors": ["statistics", "engineering", "computer science"], "languages": ["english"], "language_level": ["proficient"], "hard_skills": ["bi", "data analytics", "aws", "sql", "data visualization", "python", "business intelligence"], "soft_skills": ["self-motivation", "customer-focused"], "languages_combined": [{"language": "english", "language_level": ["proficient"]}]}, "experience_required": {"duration": ["1+ years"], "field": ["sql", "commercial", "development", "business"]}}, {"job_id": "100003009042340", "location_code": "hk", "company": "CMB International Capital Corporation Limited", "job_title": "Data Engineer(One-year contract) - IT Department", "description": "Responsibilities\n\nParticipate in the implementation of an enterprise-level data warehouse platform, complete data warehouse architecture design ,data modeling and ETL development based on big data technology.\nGather business data requirements to define data strategy and data models , translate business questions into data solutions.\nEstablish organization data governance model, responsible for data quality management.\n\nRequirements\n\n\nAt least\u00a03 years practical experience on Data Warehouse development, with experience in large scale Data Warehouse project.\nExperience in using ETL tool to develop data transformation and handling.\nFamiliar with Kimball dimensional modeling method, with massive data processing experience.\nSolid experience on Spark,\u00a0Flink and data visualization tools (Tableau)\u00a0\u00a0 is preferred.\nSolid experience on cloud like Azure, AWS or Ali cloud is preferred.\nSolid\u00a0knowledge\u00a0on\u00a0accounting/\u00a0financial\u00a0products is\u00a0preferred.\nExperience in metadata management, data quality management, and data governance is preferred.\nProficient in demand analysis and design, familiar with banking and securities related business is preferred.\nA team player, fast learner, mature and able to work under pressure.\n\nWe offer competitive remuneration package and comprehensive fringe benefit to the right candidate. Interested parties please forward your full resume with availability, expected salary by pressing \"Apply now\".\n\nPersonal data collected will be used for recruitment related purposes only. Applicants not invited for an interview within 2 months from the date of this posting may consider their applications unsuccessful. Personal data will be destroyed after 3 months.\n\nFor further information about our Company, please visit our website: https://www.cmbi.com.hk/en-US/\n\n\n", "employment_types": ["Full Time", "Contract"], "selling_points": ["Kimball dimensional modeling method", "Database development", "Financial data analysis"], "locations": ["Central"], "categories": ["Information Technology (IT)", "Application Specialist - Software", "DBA", "Data Scientist"], "post_time": "2022-01-12T07:07:33Z", "salary": {"currency": null, "max": null, "min": null, "period": "monthly", "term": null}, "salary_visible": false, "title_keywords": [], "responsibilities": ["management", "data", "big data", "implementation", "design", "quality", "architecture"], "requirements": {"degrees": [], "majors": [], "languages": [], "language_level": [], "hard_skills": ["azure", "data warehouse", "analysis", "tableau", "aws", "data visualization", "spark", "processing"], "soft_skills": ["team player", "fast learner", "mature", "work under pressure"], "languages_combined": []}, "experience_required": {"duration": ["at least 3 years"], "field": ["development", "management", "quality management"]}}, {"job_id": "100003009046312", "location_code": "hk", "company": "China Taiping Life Insurance (Hong Kong) Company Limited", "job_title": "Investment Reporting-Head / Senior Manager", "description": "Job Responsibility\n\nManage the investment system maintenance and development process, which are consist of\nInvestment report system: generate regular report to fulfill various internal and external reporting requirements.\nInvestment performance system: able to store and extract all historical performance related data for all portfolio and also the benchmark.\nInvestment risk management system: able to store and extract quantitative financial risk data and parameters.\nFundamental analysis database: able to store and extract fundamental data for various market and securities.\nMacau Investment Operation: Assisting external asset management companies and the company's internal financial department to prepare regular reports, formulate investment agreements in accordance with Macau regulatory requirements and supervise the implementation of entrusted investment guidelines\nRequirement\n\nDegree in Data Science, Computer Science, Financial Engineering, Math, Physics or other quantitative fields.\nMinimum 5 years of solid working experiences from asset management system development, IT consulting, banking or financial advisory firm.\nExcellent capability in data mining and quantitative modeling.\nIn depth knowledge of at least one mainstream programming languages such as C++/Java/Python and basic database design and SQL knowledge are desired.\nGood time management skills, independent problem-solving skills and ability to multitask and work under pressure to meet tight deadlines,.\n\n", "employment_types": ["Full Time"], "selling_points": ["Investment system reporting", "Data mining and quantitative modeling", "Attractive remuneration package"], "locations": ["North Point"], "categories": ["Banking / Finance", "Asset Management", "Information Technology (IT)", "Data Scientist"], "post_time": "2022-01-13T10:25:05Z", "salary": {"currency": null, "max": null, "min": null, "period": "monthly", "term": null}, "salary_visible": false, "title_keywords": ["senior manager"], "responsibilities": ["reporting", "management", "maintenance", "data", "guidelines", "regulatory requirements", "analysis", "implementation", "asset management", "reports", "database", "report"], "requirements": {"degrees": ["degree"], "majors": ["data science", "engineering", "physics", "computer science", "math"], "languages": [], "language_level": [], "hard_skills": ["java", "basic", "c++", "python", "sql", "programming", "data mining", "problem-solving skills", "math"], "soft_skills": ["meet tight deadlines", "independent", "time management skills", "problem-solving skills", "ability to multitask", "work under pressure"], "languages_combined": []}, "experience_required": {"duration": ["minimum 5 years"], "field": ["consulting", "financial", "system development", "it", "banking", "asset management"]}}, {"job_id": "100003009045429", "location_code": "hk", "company": "Michael Page", "job_title": "Group Analytics Architect", "description": "Large conglomerate\nGroup level role - strategic mindset and able to provide big picture to retail and property businesses\nData re-map across brand's website & build data set'\nDevelop data lake\nData management & governance\nData solution design, development and testing\nExposure to large public cloud\nExposure across APAC\n\n\u5ba2\u6237\u7b80\u4ecb\n\nOur client is a large conglomerate with business across APAC. To cope with the business growth, they are currently hiring a Group Analytics Architect who has a strategic mindset to provide big picture to its retail and property businesses in facilitating innovation & transformation across APAC.\n\nThis candidate will work closely with Cloud Architect, facilitate data integration and line up across customer, tenants and facilities. Hands on in developing data lakes on cloud, data re-mapping across brand's website and building data set. Also required to design and advise on data modelling for projects across APAC.\n\n\u5de5\u4f5c\u5185\u5bb9\n\nSits in Group level to provide big picture to its retail & property businesses in facilitating innovation and transformation\nWork closely with Cloud Architect to facilitate data integration, analytics and links up the data across customer, tenants and facilitates in providing meaningful insights\nTake lead in data management through defining practices and knowledge transfer to the BU's data engineers, scientist and analysts\nHands on in developing data lakes on large public cloud\nData re-map across multiple brands' website and build data set\nDesign and advise on data modelling for regional projects\n\n\u7406\u60f3\u7684\u6c42\u804c\u8005\n\nBachelor in Computer Science, Statistics, Information Management or relevant disciplines\nMinimum 4 years in Data Architecture/ Engineering\nHands on with SQL. Experience in MS SQL Server\nStrong in analytics services in large public cloud (e.g. Azure, AWS, GCP etc.)\nExtensive knowledge in data modelling methodologies e.g. Kimball, Data Vault etc.\nExpereince in managing massive data set, hands on with reporting and machine learning environment\nExperience with data warehousing & governance\nRetail/ FMCG/ Property industry background is a plus\nGood command in English and Chinese\n\n\u798f\u5229\u5f85\u9047\n\nOur client offer attractive compensation package with sustainable career path to the candidates.\n\nTo apply online please click the 'Apply' button below. For a confidential discussion about this role please contact Eliza Lai on +852 2848 9544.", "employment_types": ["Full Time", "Permanent"], "selling_points": ["Large conglomerate", "Data re-map & build data set", "Exposure to large public cloud"], "locations": ["Not Specified"], "categories": ["Information Technology (IT)", "Application Specialist - Software", "IT Project Management / Team Lead", "Data Scientist"], "post_time": "2022-01-13T07:49:50Z", "salary": {"currency": null, "max": null, "min": null, "period": "monthly", "term": null}, "salary_visible": false, "title_keywords": [], "responsibilities": ["reporting", "management", "warehousing", "data", "website", "design", "develop", "testing", "developing", "contact", "architecture"], "requirements": {"degrees": ["bachelor"], "majors": ["statistics", "computer science"], "languages": ["english", "chinese"], "language_level": ["good command"], "hard_skills": ["plus", "azure", "data management", "ms sql server", "aws", "sql", "integration"], "soft_skills": ["hands on", "extensive", "learning"], "languages_combined": [{"language": "english", "language_level": ["good command"]}, {"language": "chinese", "language_level": ["good command"]}]}, "experience_required": {"duration": [], "field": ["sql"]}}, {"job_id": "100003009043962", "location_code": "hk", "company": "ADECCO", "job_title": "SAP Data Analyst (30K or above)", "description": "Our client is a leading company and currently they are looking for a SAP System Data Analyst\u00a0to join their team.\n\nResponsibilities\n\nProvide analytical support on procurement data and resolve procurement system issues\nCollect data, build and maintain data warehouse,\u00a0data analysis with SAP and maintain the dashboard to interpret the analysis results\nIdentify and support improvements in daily reporting and data consolidation through automated and streamlined processes\nCommunicate with IT Desk if system error\u00a0\n\nRequirement\n\nDegree or relevant professional qualifications in purchasing/supply management, and/or a university graduate with major in business management.\nProficiency on Data Analysis using Microsoft Office Tools\nExperience on operations of SAP ERP systems\nAt least 2 years of experience on administration and supporting IT System\nGood written and spoken English\nEffective interpersonal and communication skilll\n\nIf you're interested in this role, please please\u00a0CLICK HERE\u00a0or\u00a0click 'Apply Now' to apply the position via Adecco website with your CV.\n\nPlease note that only short listed candidates will be notified. All information gathered will be treated in strict confidence and solely used for recruitment purposes.", "employment_types": ["Full Time", "Temporary", "Contract"], "selling_points": [], "locations": ["Sham Shui Po"], "categories": ["Information Technology (IT)", "Product Management / Business Analyst", "Merchandising & Purchasing", "Procurement / Purchasing / Sourcing", "Data Scientist"], "post_time": "2022-01-13T02:36:45Z", "salary": {"currency": null, "max": null, "min": null, "period": "monthly", "term": null}, "salary_visible": false, "title_keywords": ["data analyst"], "responsibilities": ["communicate with", "reporting", "data", "analysis", "data analysis", "maintain", "maintain data"], "requirements": {"degrees": ["university graduate", "degree"], "majors": ["business"], "languages": ["english"], "language_level": ["good"], "hard_skills": ["business management", "erp systems", "sap", "microsoft office", "professional qualifications", "analysis"], "soft_skills": ["communication", "confidence", "interested in", "interpersonal"], "languages_combined": [{"language": "english", "language_level": ["good"]}]}, "experience_required": {"duration": ["at least 2 years"], "field": ["it", "administration"]}}, {"job_id": "100003009043954", "location_code": "hk", "company": "Pinpoint Asia Limited", "job_title": "Data Strategy and Architecture Leader", "description": "Our client, a large well-known enterprise, with a state-of-the-art technology setup, is looking for a Data Strategy and Architecture Leader to lead their enterprise-wide Data Strategy, Governance, and Architecture. The selected candidate will be leading the Enterprise Architect in building Data Architecture for the whole firm. This role is a senior leadership position working closely with the firm senior management.\n\nResponsibilities:\n\nDefine and manage the Data Governance Framework which creates a data-centric strategy for the whole organization.\nLead the definition of the enterprise data models, policies, and standards that support and align with the defined EA roadmap.\nDefine key metrics to measure performance, quality, clarity, accessibility, and compliance.\nWork with the senior leaders in defining the technology strategy, standard, and policy in data.\nEstablish and maintain core data models, information standards, and data management lifecycle controls.\nProvide End-to-end data design and management for data acquisition and processing, data quality, and governance for the Enterprise Data platform.\nDevelop and improve data governance standards including records management, data quality, metadata, modeling, and data provisioning.\n\nRequirements:\n\nAt least 12 years of working experience in the IT Data Management, Data Governance, and Data Architecture area.\nProven experience in establishing a data governance model and framework.\nUnderstanding of Enterprise Architecture concepts.\nAbility to lead in architecture analysis, modeling, and design ensuring alignment with business and Architecture strategy. This includes the ownership of the architecture artifacts, controlling the architectural integrity, and managing critical architectural trade-offs\nStrategic thinking and communication, which able to coach and lead all levels of people.\nStrong leadership and influencing skills. Strong communications and negotiation skills to speak with key stakeholders.\nBachelor or Master's degree from a reputable University.\nExcellent communication skills in English.\n\nIf this outstanding opportunity sounds like your next career move, please send your resume in Word format to Danny Kwan at resume(at)pinpointasia(dot)com and put Data Strategy and Architecture Leader in the subject header.\n\nData provided is for recruitment purposes only.", "employment_types": ["Full Time", "Permanent"], "selling_points": ["Define Firmwise Architecture", "Leadership Position", "Large Enterprise Organization"], "locations": ["Not Specified"], "categories": ["Information Technology (IT)", "DBA", "IT Management", "Data Scientist"], "post_time": "2022-01-13T02:35:15Z", "salary": {"currency": "HKD", "max": 119999, "min": 90000, "period": "monthly", "term": null}, "salary_visible": true, "title_keywords": [], "responsibilities": ["management", "data", "policies", "compliance", "quality", "design", "develop", "maintain"], "requirements": {"degrees": ["degree", "bachelor", "master"], "majors": [], "languages": ["english"], "language_level": ["excellent"], "hard_skills": ["analysis", "data management", "word"], "soft_skills": ["communication skills", "strategic thinking", "integrity", "communication", "negotiation skills", "leadership"], "languages_combined": [{"language": "english", "language_level": ["excellent"]}]}, "experience_required": {"duration": ["at least 12 years"], "field": ["management", "it"]}}, {"job_id": "100003009044163", "location_code": "hk", "company": "Peoplebank Hong Kong Ltd", "job_title": "Data Governance Lead (12-month renewable contract)", "description": "\nKey responsibilities include:\n\nBe the go-to person in the organisation regarding data governance issues\nDefine and manage our firm-wise Data Governance framework in accordance to our internal Data Policy and industry best practice\nWork closely with Data Stewards in various business areas to design and continuously refine and optimise our data governance process\nWork closely with Architect, Platform Engineers to implement data governance software and drive adoption across the organisation\nWork with Engineers to identify process automation and streamlining opportunity where possible and are repeatable and reliable\n\n\n\nThe qualifications you need:\n\nWe expect the ideal candidate to have extensive experience (6+ years) in data management and governance, while having 2+ years in an enterprise environment.\nFurthermore, you have:\nStrong stakeholder management skills, able to provide strategic influence to senior business stakeholders on data governance framework adoption\nExperience of implementing of data governance framework and operating data committee in an enterprise environment is highly desired.\nExperience in data catalogue tools and drive implementation of data governance SOP with it\nExperience of implementing data security capabilities such as encryption, anonymization is a plus.\nData driven thinking capabilities\nSolid grounding in Financial Service\nExcellent communication skills and experience of working in an international team\n\n\n\nInterested parties please share your resume by Apply Now.", "employment_types": ["Full Time", "Contract"], "selling_points": ["Manage data governance", "Exp in working at enterprise environment", "12 months renewable contract"], "locations": ["Central & Western Area"], "categories": ["Information Technology (IT)", "IT Project Management / Team Lead", "IT Management", "Data Scientist"], "post_time": "2022-01-13T03:15:51Z", "salary": {"currency": null, "max": null, "min": null, "period": "monthly", "term": null}, "salary_visible": false, "title_keywords": ["lead"], "responsibilities": ["management", "software", "data", "implementation", "design", "communication", "catalogue"], "requirements": {"degrees": [], "majors": [], "languages": [], "language_level": [], "hard_skills": ["plus", "go", "data management"], "soft_skills": ["communication skills", "organisation", "reliable", "extensive", "driven", "ideal"], "languages_combined": []}, "experience_required": {"duration": ["6+ years", "2+ years"], "field": ["management", "it", "security", "team"]}}, {"job_id": "100003009035798", "location_code": "hk", "company": "Macroview Telecom Limited", "job_title": "Data Engineer", "description": "Job\u00a0Descriptions:\n\nDesign, implement and manage data pipeline workloads of business operational data for scalable analytic purposes\nProvide data retrieval, delivery and analytic services to business stakeholders\nCollaborate with application development team to provide integrated digital solutions to business users\nRequirements:\n\nUniversity graduate in Computer Sciences, Information Systems, Data Science or related disciplines\u00a0\n1 \u2013 2 years of experience in data pipeline design and implementation\nHands-on experience in Java and/or Python for ETL with various databases (e.g. MSSQL, Oracle, MongoDB, Redis)\nPrior knowledge or experience in one or more of the followings areas are preferred: - BI / data visualization tools (e.g. Power BI / Tableau)\nData processing (batch and stream) and analytic components (e.g. Apache Airflow, Nifi, Kafka, Flink)\nData services in public cloud platforms (GCP, AWS or Azure)\nBusiness financial analysis, Principles of financial / managerial accounting,\nGood in both spoken and written Cantonese and English. Mandarin is a plus\nAble to work independent with strong analytical and problem-solving skills\nStrong passion in new and emerging technologies and willing to learn\nGood team player and interpersonal skills, with high level of personal accountability", "employment_types": ["Full Time", "Permanent"], "selling_points": ["1-2 years experience in data pipeline design", "Data services in public cloud platforms", "Power BI / Tableau, Data processing"], "locations": ["Quarry Bay"], "categories": ["Professional Services", "Business Analysis / Data Analysis", "Information Technology (IT)", "Product Management / Business Analyst", "Data Scientist"], "post_time": "2022-01-10T08:27:04Z", "salary": {"currency": null, "max": null, "min": null, "period": "monthly", "term": null}, "salary_visible": false, "title_keywords": ["data engineer"], "responsibilities": ["collaborate with", "application development", "design", "data"], "requirements": {"degrees": ["university graduate"], "majors": ["related disciplines", "data science"], "languages": ["cantonese", "english", "mandarin"], "language_level": ["good"], "hard_skills": ["java", "bi", "apache", "azure", "plus", "mssql", "tableau", "airflow", "public cloud platforms", "batch", "aws", "financial analysis", "databases", "data visualization", "python", "problem-solving skills", "processing", "oracle"], "soft_skills": ["good team player", "independent", "accountability", "passion in", "willing to learn", "hands-on", "interpersonal skills", "problem-solving skills"], "languages_combined": [{"language": "cantonese", "language_level": ["good"]}, {"language": "english", "language_level": ["good"]}, {"language": "mandarin", "language_level": []}]}, "experience_required": {"duration": ["2 years"], "field": ["design"]}}, {"job_id": "100003009042043", "location_code": "hk", "company": "Jardine Restaurant Group", "job_title": "IT Infrastructure Specialist (Cloud & Data Centers)", "description": "Responsibilities:\n\nManaging and optimizing cloud environments in accordance with IT guidelines\nDeveloping solution architecture designs for Digital cloud platforms/services ensuring alignment with company defined patterns/blueprints\nImplement Azure IaaS and PaaS technologies and services: Azure VMs, Azure Storage, VNET\u2019s, Resource Manager, Azure Backup, App Services, Azure Active Directory and Azure Data services.\nImplement systems monitoring tools and policy for systems, devices, and services including cloud solutions based on Microsoft Azure\nImplement and deploy Intune (VMware Workspace), SCCM (ManageEngine) and other tools as necessary\nDeploy and manage virtual machines based on Windows OS\nDeploying and debugging cloud applications and services\nParticipate in the build, deployment, and monitoring of portable data centres for MSF field operations\nCollaborate closely with the enterprise and infrastructure architects, support, and the IT security teams\nParticipate in infrastructure related projects in partner sections and provide advisory services\nProvide escalation for IT support issues that require engineering support\nNetwork configuration of devices from vendors such as Juniper, Cisco, Unifi, and Palo Alto\n\n\n\nRequirements:\n\n\u00a0At least 5+ years of hands-on experience with\u00a0cloud technologies\u00a0and their implementation with experience in\u00a0Azure\nProficiency in Azure IaaS and PaaS technologies and services: Azure VMs, Azure Storage, VNET\u2019s, Resource Manager, Azure SQL, Azure Backup, Traffic Manager, Cloud & App Services, Azure Active Directory\nExpertise translating business requirements / problems into technical architectures utilizing Azure and complementary technologies\nExperience in providing Azure advisory to Company Sections including assessments, presenting recommendations on Azure migration roadmaps, architecture / designs etc.\nCandidate will lead analysis, recommendations, and presentation of approaches to Company sections complex problems based on prior experience and researches\nExperience in deploying Azure IaaS and PaaS solutions based on a range of Azure technologies and services such as Compute, Data Services, App Services and Network Services etc.\nExperience in conducting Azure PoCs, deployment and migration of various workloads to Azure services from traditional infrastructure or other Clouds\nExperience in deployment and migration of various workloads to Azure\nProficiency in Windows operating system and storage technologies\nCollaborate with internal functional and technical teams to ensure Azure based solutions are appropriately architected, engineered, tested, & deployed", "employment_types": ["Full Time"], "selling_points": ["Digital cloud technologies", "Azure IaaS and PaaS technologies", "Intune (VMware Workspace), SCCM (ManageEngine)"], "locations": ["Hung Hom"], "categories": ["Information Technology (IT)", "DBA", "Application Specialist - Network", "Data Scientist"], "post_time": "2022-01-12T05:39:48Z", "salary": {"currency": null, "max": null, "min": null, "period": "monthly", "term": null}, "salary_visible": false, "title_keywords": ["specialist"], "responsibilities": ["collaborate", "active directory", "data", "guidelines", "operations", "configuration", "systems", "monitoring", "developing", "infrastructure", "teams", "deploy", "architecture"], "requirements": {"degrees": [], "majors": [], "languages": [], "language_level": [], "hard_skills": ["azure", "active directory", "analysis", "sql", "deployment"], "soft_skills": ["hands-on", "active", "presentation"], "languages_combined": []}, "experience_required": {"duration": ["at least 5+ years"], "field": ["infrastructure"]}}, {"job_id": "100003009046451", "location_code": "hk", "company": "Ambition", "job_title": "Quant Developer", "description": "Responsibilities\n\nDesign, build and maintain high performance, high availability and high scalability platform and tools for:\n\n\n\nAutomatic execution of proprietary trading orders\nTrading signals generation and notification\nTrading data visualisation\nMarket-making platform enhancement\nDevelop portfolio optimisation models and systematic investment strategies\nDesign, develop, and deploy elegant software solutions across research, alpha & signal generation, systematic and non-systematic trading\nBuild automated ETL pipelines to support rapid but controlled transition from research to live trading\nSupport the team in operations workflow\n\nJob Requirements\n\n\n\nBachelor's, Master's or PhD degree in Computer Science, Mathematics, Statistics, or equivalent field\nPrevious experience in blockchain / cryptos are preferred but not required\nProficiency with one or more programming languages (e.g. C++, Python, or Java)\nHands-on experience analysing complex data and building statistical models\nGood knowledge of data-structures and algorithms\nGood command in spoken and written English and Chinese\n\nReach out to Louis Hui (Louis.Hui@Ambition.com.hk) if you are interested.\n\n\n\nIf this job isn't quite right for you, but you know someone who would be great at this role, why not take advantage of our referral scheme? We offer HKD1000 in Apple gift cards for every referred candidate who we place in a role. Terms & Conditions Apply. https://www.ambition.com.hk/refer-a-friend", "employment_types": ["Full Time", "Permanent"], "selling_points": ["Hedge Fund - Digital Assets", "Algorithm Trading", "Python / C++ / C# / Java"], "locations": ["Not Specified"], "categories": ["Information Technology (IT)", "Software Development", "Banking / Finance", "Asset Management", "Data Scientist"], "post_time": "2022-01-13T11:17:53Z", "salary": {"currency": "HKD", "max": null, "min": 70000, "period": "monthly", "term": null}, "salary_visible": true, "title_keywords": ["developer"], "responsibilities": ["investment strategies", "software", "data", "operations", "design", "develop", "maintain", "deploy", "support the team"], "requirements": {"degrees": ["degree", "bachelor", "master"], "majors": ["mathematics", "statistics", "computer science"], "languages": ["english", "chinese"], "language_level": ["good command"], "hard_skills": ["blockchain", "java", "c++", "scheme", "programming", "python"], "soft_skills": ["hands-on"], "languages_combined": [{"language": "english", "language_level": ["good command"]}, {"language": "chinese", "language_level": ["good command"]}]}, "experience_required": {"duration": [], "field": []}}, {"job_id": "100003009037522", "location_code": "hk", "company": "Venturenix Limited", "job_title": "Business Intelligence: Data Visualization Analyst (Tableau) @MNC | HKD 35k", "description": "Our client, an MNC in retail industry is currently looking for a Data Visualization Specialist who uses Tableau as the main tool.\n\nJob duties:\n\n\nDashboard development by Tableau\nTableau dashboard adaptation and replication\nRequirements:\n\n\nAt least 2 years experience on Tableau\nBasic SQL knowledge\nRelated certifications would be a plus\nInterested parties please directly apply with \"apply now\".", "employment_types": ["Full Time", "Permanent"], "selling_points": ["Global MNC exposure", "Tableau, BI, Data Visualization", "Retail Big Data"], "locations": ["Shatin Area"], "categories": ["Information Technology (IT)", "DBA", "Data Scientist"], "post_time": "2022-01-11T03:01:21Z", "salary": {"currency": null, "max": null, "min": null, "period": "monthly", "term": null}, "salary_visible": false, "title_keywords": ["analyst"], "responsibilities": [], "requirements": {"degrees": [], "majors": [], "languages": [], "language_level": [], "hard_skills": ["sql", "plus", "basic", "tableau"], "soft_skills": [], "languages_combined": []}, "experience_required": {"duration": ["at least 2 years"], "field": []}}, {"job_id": "100003009041130", "location_code": "hk", "company": "CL Technical Services Ltd.", "job_title": "Data Engineer / ETL Developer (BI, 5 Days Work, $25-30K)", "description": "Job details:\n\nWork closely with oversea partners and report to oversea team lead\nCollect user requirement, perform data engineering, system development, set up\nImplement software components from the specification and guidelines\nDevelop unit test cases, perform testing and record the results\nSupport UAT and system implementation\nPrepare system and operations documents\nAssist in developing data warehouse and AI\n\nRequirements:\n\nDegree holder in Computer Science / Data Science or equivalent\n3 years\u2019 experience with data including reporting, managing, and analysing\nHands on experience in Python / SAS and SQL\nGood communication and interpersonal skills\nProficient in both written and spoken English and Chinese\n\nFor more job opportunity, please visit our website: www.clts.com\n\nThe personal information is collected strictly for recruitment purpose only.", "employment_types": ["Full Time"], "selling_points": ["Several job vacancies", "Listed company", "Great learning opportunity"], "locations": ["Mong Kok"], "categories": ["Information Technology (IT)", "IT Management", "Technical Writing", "Data Scientist"], "post_time": "2022-01-12T03:29:12Z", "salary": {"currency": null, "max": null, "min": null, "period": "monthly", "term": null}, "salary_visible": false, "title_keywords": ["developer", "data engineer"], "responsibilities": ["user requirement", "software", "uat", "data", "guidelines", "operations", "implementation", "developing", "develop", "testing", "report"], "requirements": {"degrees": ["degree holder"], "majors": ["data science", "computer science"], "languages": ["english", "chinese"], "language_level": ["proficient"], "hard_skills": ["python", "sql", "sas"], "soft_skills": ["hands on", "communication and interpersonal skills"], "languages_combined": [{"language": "english", "language_level": ["proficient"]}, {"language": "chinese", "language_level": ["proficient"]}]}, "experience_required": {"duration": ["3 years"], "field": ["sql"]}}, {"job_id": "100003009034847", "location_code": "hk", "company": "Osmium Consulting Group Limited", "job_title": "Data Scientist / Engineer / Analyst | 40K - 50K", "description": "Responsibilities:\n\nPerform data mining, analyse\u00a0large amount of data using statistical techniques and create analytics solutions.\nGather and consolidate data analytics requirements for B2B project and align with\nCouncil\u2019s data architecture.\nDesign and develop solutions for data analytics projects according to business\u00a0requirements.\nUse visualization tools to design and build dynamic dashboards and reports.\nManage and participate in data analytic project initiatives, including but not limited to data schema design, ETL design and development, data presentation and visualization.\nKeep abreast of data analytics trends and propose the use of latest data tools / cloud\u00a0services.\nRequirements:\n\nDegree or equivalent qualification in Computer Science, Statistics, Information Management or related disciplines.\n5 years of working experience as a Data Analyst.\nGood command of querying databases and using statistical computer languages: Python, R and SQL, etc.\nFamiliar with visualization tool, e.g. Tableau, Google Data Studio, Adobe Analytics.\nExperience in machine learning models would be an added advantage.\nExperience in data analytics technologies would be an added advantage, e.g. AWS,\u00a0Redshift, Athena, S3, Glue, Lambda, Kinesis.\nSolid experience in large scale data analytics and visualization.\nSelf-motivated and able to work independently.\nExcellent interpersonal, written and verbal communications skills in both English and\u00a0Chinese.\nBenefits\n\n20 Days AL\n5 days Work Week\nMedical and Dental Insurance\nEducation Allowance\nOn-site Training", "employment_types": ["Full Time", "Permanent"], "selling_points": ["20 Days AL | 5-day Work Week | Attractive Package", "Global FinTech Company | E-Commerce | Career Path", "Data Warehouse | Data Scientist | Data Engineer"], "locations": ["Ngau Tau Kok"], "categories": ["Information Technology (IT)", "DBA", "IT Management", "Data Scientist"], "post_time": "2022-01-10T04:25:12Z", "salary": {"currency": "HKD", "max": 54999, "min": 35000, "period": "monthly", "term": null}, "salary_visible": true, "title_keywords": ["analyst", "data scientist", "engineer"], "responsibilities": ["visualization", "data", "design and develop", "design", "reports", "data mining", "architecture", "analyse"], "requirements": {"degrees": ["degree"], "majors": ["related disciplines", "statistics", "computer science"], "languages": ["english", "chinese"], "language_level": ["excellent"], "hard_skills": ["data analytics", "tableau", "aws", "sql", "adobe", "databases", "python", "r", "s3"], "soft_skills": ["self-motivated", "learning", "work independently", "interpersonal"], "languages_combined": [{"language": "english", "language_level": ["excellent"]}, {"language": "chinese", "language_level": ["excellent"]}]}, "experience_required": {"duration": ["5 years"], "field": []}}, {"job_id": "100003009043628", "location_code": "hk", "company": "Hong Kong Applied Science and Technology Research Institute Company Limited (ASTRI)", "job_title": "Machine Learning on Audio and Video Analysis - Principal Engineer/Senior Engineer/Engineer", "description": "Reference #:\u00a0CTO/CCT/13\n\u00a0Openings: 4\nJob Responsibilities\nAssist in R&D project\nAlgorithm research and software development on speech recognition, speech synthesize, speaker verification, and natural language processing\nResearch on video processing, virtual avatar generation, synchronization of video and audio generation\nDeliver innovative technology\n\u00a0\nRequirements\nMaster or Bachelor degree or above in Computer Science, Data Science, Information Engineering, Mathematics or related disciplines with a minimum of 3 years relevant experience\nProfessional background in at least one of the following areas: machine learning, audio processing, computer vision, signal processing is highly preferred\nStrong programming skills of at least one of the following languages: Python, C/C++, java, javascript, php is a plus\nFamiliarity with open source libraries including Tensorflow, PyTorch, Keras, kaldi, wav2vec, SpeechBrain, Wenet, etc, is a plus\nTeam player with good analytical and strong communication skills\nGood command of both written and spoken English and Cantonese\nLive ASTRI values\nApplication\n\nThe appointment will be on renewable contract terms with a competitive salary and performance-linked variable pay. Fringe benefits include paid leave, medical and dental benefits, insurance coverage and contribution to MPF. The incumbent will normally work\u00a0a five-day week.\n\nInterested candidates, please send an application (quoting Ref. No.) with a detailed resume, current and expected salary to\u00a0Talent Acquisition by clicking \"APPLY NOW\".\u00a0The resume should\u00a0not\u00a0include any sensitive personal information such as HKID or passport number, photo, etc.\u00a0\n\nPosition offer is subject to the applicant\u2019s experience and academic qualification. The application will be open until the position is filled. Only short-listed candidates will be notified. ASTRI reserves the right not to fill the position.\n\nASTRI is an Equal Opportunities Employer. Personal data provided by job applicants will be used\u00a0exclusively\u00a0for recruitment\u00a0only. For details, please refer to\u00a0Privacy - ASTRI - Hong Kong Applied Science and Technology Research Institute Company Limited, in particular section 9.", "employment_types": ["Full Time", "Contract"], "selling_points": ["Machine Learning", "Algorithm research and software development", "Speech recognition"], "locations": ["Shatin Area"], "categories": ["Engineering", "Electrical / Electronics", "Information Technology (IT)", "Software Development", "Data Scientist"], "post_time": "2022-01-13T01:07:10Z", "salary": {"currency": null, "max": null, "min": null, "period": "monthly", "term": null}, "salary_visible": false, "title_keywords": ["senior engineer", "engineer"], "responsibilities": ["audio", "software"], "requirements": {"degrees": ["degree or above", "bachelor", "master"], "majors": ["data science", "mathematics", "engineering", "related disciplines", "computer science"], "languages": ["cantonese", "english"], "language_level": ["good command"], "hard_skills": ["java", "plus", "c++", "php", "c", "javascript", "programming", "python", "processing", "signal"], "soft_skills": ["communication skills", "team player", "learning"], "languages_combined": [{"language": "cantonese", "language_level": ["good command"]}, {"language": "english", "language_level": ["good command"]}]}, "experience_required": {"duration": ["minimum of 3 years"], "field": ["related", "relevant experience", "engineering"]}}, {"job_id": "100003009036101", "location_code": "hk", "company": "Chilin (HK) Limited", "job_title": "Tech Manager, Data Scientist, Post-doc / Res Asso/ Res Asst  (Data Sci, Comp Ling, HLT)", "description": "Technical Manager, Data Scientist (salary negotiable)\n\nPost-doc (min. 30K/month + benefits)\n\nResearch Associate (min. 21K/month + benefits) (without PhD)\n\nResearch Assistant (min. 18K/month + benefits)\n\nRequirements\n\nHigh computer literacy.\u00a0\nPHD/MSc/BSc/MA/BA degree in fields related to Computational Linguistics, Translation, Human Language Technology, Information Technology, Linguistics or Translation.\nGood communication skills in English and Chinese is essential.\nFamiliarity with existing Chinese language databases, KWIC and other search protocols.\nPrior experience involving technical materials and/or Natural Language Processing is preferred.\nExperience using one or more commercial Computer Aided Translation (CAT) tools, such as SDL Trados, MemoQ, Memsource will be an advantage.\n\n\u00a0An optimal combination of some responsibilities\n\nMaintenance and expansion of monolingual and bilingual textual databases, and application of search routines.\nMaintenance and expansion of term banks.\nBenchmark performance of CAT tools with enhanced translation memory and term-base files.\nSupport demonstration and documentation of TMX products and other corpus material.\nContent analysis.\nDocumentation and Post-editing", "employment_types": ["Full Time"], "selling_points": [], "locations": ["Yau Ma Tei"], "categories": ["Information Technology (IT)", "IT Management", "Software Development", "Data Scientist"], "post_time": "2022-01-10T09:35:44Z", "salary": {"currency": null, "max": null, "min": null, "period": "monthly", "term": null}, "salary_visible": false, "title_keywords": ["manager", "data scientist"], "responsibilities": [], "requirements": {"degrees": [], "majors": [], "languages": [], "language_level": [], "hard_skills": [], "soft_skills": [], "languages_combined": []}, "experience_required": {"duration": [], "field": []}}, {"job_id": "100003009037062", "location_code": "hk", "company": "Cignal Technology Company Limited", "job_title": "Senior Data Engineer", "description": "About the role:\n\nDevelop data model for the data stored in database\nEnsure consistency in naming conventions, default values, semantics, security while ensuring quality of the data\nEstablish the entities, attributes, and their relationships in RDB according to reporting requirements\nDefine the relational tables, primary and foreign keys. Write stored procedures or views for data processing\nWrite comprehensive documentation including but not limited to data modelling ,data dictionaries , data interface design\n\nAbout you:\n\nMaster\u2019s degree is preferred (Business, Engineering, Statistics, Computer Science, Mathematics or related field)\nMinimum 7 years' relevant work experience in fast paced, matrix and global environment\nProven problem solving skills, attention to detail, and exceptional organizational skills\nWorking experience in risk, KYC or Customer services team would be a plus\nAdvanced knowledge of data retrieving and processing using SQL, ETL, and data warehouse; Proficient with SQL in creating views and stored procedures\nFamiliar with at least one of the programming languages (Python, R, Go, Java)\nExperience using test/control methodology, and using machine learning techniques\nKnowledge of big data tools such as Hive , Spark , maxcompute, elasticsearch\nProficient with one or more major BI tools including PowerBI/Tableau/DOMO and etc", "employment_types": ["Full Time"], "selling_points": ["Global leading Blockchain company", "Global, decentralised, cohesive culture", "Customer, Risk and Product analytics"], "locations": ["Causeway Bay"], "categories": ["Professional Services", "Business Analysis / Data Analysis", "Information Technology (IT)", "Product Management / Business Analyst", "Data Scientist"], "post_time": "2022-01-11T01:35:13Z", "salary": {"currency": null, "max": null, "min": null, "period": "monthly", "term": null}, "salary_visible": false, "title_keywords": ["data engineer"], "responsibilities": ["reporting", "control", "data", "quality", "procedures", "design", "develop", "data processing", "customer services", "big data", "database", "kyc", "documentation"], "requirements": {"degrees": ["degree", "master"], "majors": ["mathematics", "engineering", "statistics", "business", "computer science"], "languages": [], "language_level": [], "hard_skills": ["plus", "java", "bi", "data warehouse", "tableau", "python", "sql", "go", "programming", "kyc", "documentation", "r", "problem solving skills", "processing", "spark"], "soft_skills": ["organizational skills", "advanced", "comprehensive", "learning", "attention to detail", "problem solving skills"], "languages_combined": []}, "experience_required": {"duration": ["minimum 7 years"], "field": ["team", "customer services"]}}, {"job_id": "100003009037128", "location_code": "hk", "company": "Hong Kong Express Airways Limited", "job_title": "Specialist, Data Analytics", "description": "DEAR TALENT, YOUR MOVE!\n\nBeing the new rising airline since 2013, we are the Hong Kong\u2019s only Low Cost Carrier (LCC) offering you safe and flexible service options to Hong Kong and beyond.\n\nWe\u2019re on a mission to inspire you to be different, to shake things up, to inspire the spirit of adventure by bringing you to fascinating destinations that few others serve.\n\nSpread your wings and fly with us!\n\n\nWhat will you do?\u00a0\n\nPerform exploratory data analysis and develop business values from data;\nBuild and deploy the predictive model on cloud;\nUnderstand the data and create insightful visualization to facilitate user understanding;\nExamine data schema and ensure/maintain data quality;\nIdentify opportunities for leveraging corporate data and drive data-driven solutions to meet business goals;\nExplore innovative ways for data integration to enforce good governance on data management and regulatory compliance;\nAssess the potential usefulness and validity of data sources;\nAct as a Data Steward of the organization, conduct a Privacy Impact Assessment, govern the internal data usage and monitor the third party regularly to ensure the handling of personal data (not limited to access, transfer and retention of data) is in line with the data handling manuals and guidelines;\nSupport ad-hoc duties as assigned.\n\nWe are a perfect match, if you are:\n\nBachelor\u2019s degree, preferably in Mathematics, Statistics, Computer Science related discipline;\nMinimum 2 years of experience relating to Data Analytics and Data integration;\nKnowledge in SQL, Python is required;\nExperience in statistical libraries by using python;\nExperience in the solution of ETL, cleaning, desensitization;\nExperience in data visualization tools, such as Data Studio, PowerBI;\nExperience in Linux is preferred;\nKnowledge and\u00a0 hands-on experience on GCP platform and tools including BigQuery, Data Fusion, Compute Engine, Cloud Function, Pub/Sup, Source Repositories;\nGood communication and presentation skills;\nAirline or travel industry knowledge is highly beneficial.\n\nYour Future Work Life?\n\nWork flexibly with staggered working hours and flexible workplace\nDress Casual and Smart everyday\nWork in a newly-designed office with open seating, stylish breakout areas, game room, gym and free coffee\u2026\nWork with a group of energetic and multicultural professionals (up to 50 nationalities!)\nHave great fun in Snack Friday, New Year Market, Fly with your Kids Day, Basketball Team\u2026\nHave your voice heard through Townhalls, Crew forums, CEO live sessions etc.\n\nWhat will you enjoy?\n\nFly anywhere we fly for free plus taxes during leisure with your friends and family\nSpecial privileges to buy duty free products\nCareer Express\n\n\n\nYou will be inspired by our core values.\nYou will be inspired by our vibrant, efficient and entrepreneurial spirit. Join our fun, collaborative and reliable team to ignite your dream!\n\n\n\nInterested? It\u2019s time to have YOUR MOVE!\nIf you're ready to embark your adventure, start by clicking the \u2018Apply now\u2019 and get on the plane to fly with HK Express!\u00a0", "employment_types": ["Full Time"], "selling_points": ["Flexible Working Practices, WFH, Travel Benefits", "Perform exploratory data analysis", "Build and deploy the predictive model on cloud"], "locations": ["Tung Chung"], "categories": ["Professional Services", "Business Analysis / Data Analysis", "Information Technology (IT)", "DBA", "Data Scientist"], "post_time": "2022-01-11T01:49:38Z", "salary": {"currency": null, "max": null, "min": null, "period": "monthly", "term": null}, "salary_visible": false, "title_keywords": ["specialist"], "responsibilities": ["cost", "business goals", "management", "visualization", "ad-hoc duties", "data", "guidelines", "compliance", "quality", "monitor", "develop", "data analysis", "communication", "maintain data", "deploy", "cleaning", "personal data", "third party"], "requirements": {"degrees": ["degree", "bachelor"], "majors": ["mathematics", "statistics", "computer science"], "languages": [], "language_level": [], "hard_skills": ["linux", "plus", "data management", "fun", "data analytics", "analysis", "airline", "python", "sql", "safe", "lcc", "data visualization", "integration"], "soft_skills": ["flexible", "efficient", "collaborative", "communication", "hands-on", "presentation skills", "energetic", "reliable", "ad-hoc duties", "innovative", "driven"], "languages_combined": []}, "experience_required": {"duration": ["minimum 2 years"], "field": []}}, {"job_id": "100003009044463", "location_code": "hk", "company": "Kai Shing Management Services Ltd", "job_title": "IT Officer (Innovation Project Officer)", "description": "What will you do?\n\n\nResponsible for IT/IOT project implementation\nWork closely with the Solution Architect and other Software Engineers for the software development a various project\nConduct the on-site testing and commissioning\nLiaise with site to better understanding their needs and requirements\nStrong sense of responsibility and able to meet project deadlines\nDo you have a right\u00a0profile?\n\n\nHigher Diploma or above in Computer & Information Sciences\n1-3 years of relevant experiences in IT/IOT project\nKnowledge of Windows Servers, workstations and Linux is an advantage\nKnowledge and experience of Chatbot, AI, BI and IOT solution is an advantage\nKnowledge in Electronic Engineering is an advantage.\nHaving a good conception of Cloud, including AWS and Azure, is highly preferred\nGood analytical, inter-personal and problem solving skills\nGood team player, positive attitude, innovative, self-initiating, eager to learn new technology and share with other team members, hardworking, able to work under pressure and work independently\nProficient in both English and Mandarin Chinese\n\nWhat do we offer?\n\nAttractive remuneration package\nGreat promotion ladder\nReferral reward\nMedical benefit\nPaid marriage leave, birthday leave, well-being leave and annual leave\nEducation subsidy\nChildren scholarship\nCompany trip\n\nHow to apply?\n\nInterested parties, please apply once with application quoting job reference number, detailed resume, contact telephone number and expected salary by:\n\nClicking the \u201cApply Now\u201d button\nMail to: Human Resources Department, Unit 301-303, 3/F, Apec Plaza, 49 Hoi Yuen Road, Kwun Tong, Hong Kong\nFax to:\u00a0 (852) 2827 8608\nCall:\u00a0(852)\u00a03703 5460\n\n(Attached resume should be in MS Word for Windows)\n\n(Data collected would be used for recruitment purpose only)", "employment_types": ["Full Time", "Permanent"], "selling_points": ["Responsible for IT/IOT project implementation", "Learn new technology", "Relevant experiences in IT/IOT project"], "locations": ["Kwun Tong"], "categories": ["Information Technology (IT)", "Product Management / Business Analyst", "Software Development", "Data Scientist"], "post_time": "2022-01-13T18:54:57Z", "salary": {"currency": null, "max": null, "min": null, "period": "monthly", "term": null}, "salary_visible": false, "title_keywords": ["it officer", "project officer"], "responsibilities": ["commissioning", "software", "implementation", "testing", "liaise with", "work under pressure"], "requirements": {"degrees": ["higher diploma or above"], "majors": ["information sciences"], "languages": ["mandarin chinese", "english"], "language_level": ["proficient"], "hard_skills": ["linux", "bi", "azure", "servers", "ai", "aws", "problem solving skills"], "soft_skills": ["good team player", "work independently", "responsible", "inter-personal", "sense of responsibility", "positive attitude", "eager to learn", "problem solving skills", "innovative", "hardworking", "work under pressure"], "languages_combined": [{"language": "mandarin chinese", "language_level": ["proficient"]}, {"language": "english", "language_level": ["proficient"]}]}, "experience_required": {"duration": ["1-3 years"], "field": ["it"]}}]