[{"job_id": "100003009053009", "location_code": "hk", "company": "JFE Consulting Limited", "job_title": "Database Administrator", "description": "Our client, one of the leading IT companies, is looking for high calibres to join their winning team:\n\nResponsibilities\n\n\n\nWorking with database software to find ways to store, organise and manage data\nTroubleshooting\nKeeping databases up to date\nHelping with database design and development\nManaging database access\nDesigning maintenance procedures and putting them into operation\nIn-depth knowledge of Oracle database including RAC, ASM, Data Guard, RMAN.\nPerform database performance tuning, patching, change management and upgrade.\n\nQualifications:\n\n5+ years relevant work experience in Oracle database support.\n10 years relevant IT experiences.\nExperience in DB2 / MS SQL is a plus.\nExperience in Government projects is an advantage.\nProblem-solving skills\nGood organisational skills\nCommunication and interpersonal skills", "employment_types": ["Full Time", "Permanent"], "selling_points": ["Database Administrator", "Experienced in DB2/MS SQL", "attractive salary"], "locations": ["Quarry Bay"], "categories": ["Information Technology (IT)", "DBA", "IT Management", "Data Scientist"], "post_time": "2022-01-17T05:00:33Z", "salary": {"currency": null, "max": null, "min": null, "period": "monthly", "term": null}, "salary_visible": false, "title_keywords": ["administrator"], "responsibilities": ["change management", "software", "maintenance", "data", "designing", "troubleshooting", "design", "procedures", "communication", "databases", "database"], "requirements": {"degrees": [], "majors": [], "languages": [], "language_level": [], "hard_skills": ["plus", "maintenance", "databases", "problem-solving skills", "ms sql", "oracle"], "soft_skills": ["problem-solving skills", "organisational skills", "troubleshooting", "communication and interpersonal skills"], "languages_combined": []}, "experience_required": {"duration": ["10 years", "5+ years"], "field": ["sql", "it", "database"]}}, {"job_id": "100003009055529", "location_code": "hk", "company": "HKT", "job_title": "Database Administrator - BTU", "description": "Our client, one of the leading IT companies, is looking for high calibres to join their winning team:-\n\nResponsibilities:\n\nInstall, design and maintain database system software and implement database security.\nMonitor and analyze database performance and ensure effective and efficient utilization of database systems/processes.\nMaintain database dictionaries and support tools; develop and maintain accurate system documentation.\nParticipate in the development and maintenance of strategic, architectural and tactical plans for the database and data warehouse environments; be conversant with, and cognizant of, the future direction of systems, how that direction impacts the company and how future and current database systems can be exploited for the company\u2019s benefit. \u00a0\nYou will design, execute and supervise DML/DDL according to business requirements.\n\nRequirements:\n\nBS degree in Information Technology/Computer Science or equivalent combination of education and experience.\nFive or more years of SQL server database experience as Database Administrator (DBA), including experience installing, configuring, designing, patching, archiving, and monitoring to include performance tuning databases with indexing.\nYou have strong experience with database software (especially MySQL),\u00a0\nYou are proficient in SQL programming and Shell;", "employment_types": ["Full Time", "Permanent"], "selling_points": ["Oracle DBA / MySQL", "DB Maintenance - RMAN, Data Guard, RAC", "Oracle Exadata / ExaCC & Oracle Enterprise Manager"], "locations": ["Wan Chai"], "categories": ["Information Technology (IT)", "DBA"], "post_time": "2022-01-18T02:42:20Z", "salary": {"currency": null, "max": null, "min": null, "period": null, "term": null}, "salary_visible": false, "title_keywords": ["administrator"], "responsibilities": ["software", "system documentation", "maintenance", "data", "systems", "monitor", "design", "develop", "maintain", "database", "plans"], "requirements": {"degrees": ["degree"], "majors": ["computer science", "information technology"], "languages": [], "language_level": [], "hard_skills": ["sql", "server", "programming", "databases"], "soft_skills": [], "languages_combined": []}, "experience_required": {"duration": [], "field": ["sql", "education", "database", "information technology"]}}, {"job_id": "100003009056070", "location_code": "hk", "company": "Tata Consultancy Services Limited", "job_title": "DATABASE ADMINISTRATOR IN GOLDENGATE AND EXADATA", "description": "The Expertise We\u2019re Looking For\n\n6-10 years of relevant experience in the area of Database administration\nOracle 12c,11g, and 19c administration\nExpertise in Exadata\nExpertise in Golden Gate replication\nReal application Testing (Oracle RAT)\n6+ plus years performing Oracle 12c,11g, and 19c administration\nExpertise in Exadata, Rapid Application Testing (RAT), Performance tuning, scripting and automation\nExpertise in Golden Gate replication on Oracle Real Application Clusters (RAC)\nSignificant background in solving complex technology challenges\nA solid background working in large-scale software projects\nKnowledge and expertise in cloud, and hybrid cloud technology would be a real plus.\n\nThe Skills that are Key to this role\n\nWork with Application Development and Performance Teams on Tuning Database part during the Design to Deployment phases in the areas of Oracle SQL and PLSQL, RAC & Golden gate\nDemonstrate in-depth knowledge of Oracle RAC, Oracle Performance & Tuning and SQL Tuning\nExperience working with the Application support functions team on database related activities with in-depth knowledge of database environments\nQualified applicant should have 5+ years of Oracle Database Support, Design, Performance & Tuning experience working in a complex, multi-platform environment and should have done production support\nTraditional Database Technologies \u2013 Oracle, RAC, Exadata, Goldengate.\nExpertise analyzing, troubleshooting and performance tuning in Exadata, RAC databases and sql queries\nExpertise with Oracle Golden Gate, database replication and data movement strategies & tools\nPerforming design evaluations/ recommendations for database migration strategies to the cloud\nAdvanced communication skills both verbal and written\nAbility to operationalize solutions and ideas into standard operating procedures (SOP)\nMigration of databases using various ways like building a COB and import/export.\nImplemented Golden gate to replicate data and keeping databases in sync until the time of cutover.\nImplemented classic Golden gate replication as well as integrated replication.\nTested and Implemented different physical and logical Backup and Recovery methods like point in time, Media recovery, Full/partial export/import.\nPerform User Management, creation, monitoring and management of database users, altering passwords of users and granting and revoking system/object privileges, roles, auditing user actions in the database.\nCreating and Managing stored procedures and triggers, distributed data, server tuning, automation of administrative tasks, database.\nConfigure GoldenGate Downstream Mining and Integrated components for Active-Active replication.\nConfigure GoldenGate High Availability using Oracle DBFS and Active DataGuard.\nConfigure GoldenGate Studio or Integrate with Oracle Enterprise Manager 12/13c.\nConflict Detection and Resolution in Active-Active Replication Environments Using Oracle GoldenGate.\nPerform Schema level and Table level data refreshes from Production to Non-Production environments using Data pump EXPDP/IMPDP.", "employment_types": ["Full Time", "Permanent"], "selling_points": ["Expertise in Golden Gate replication on Oracle RAC", "Oracle 12c,11g, and 19c administration", "Expertise in Golden Gate replication"], "locations": ["Others"], "categories": ["Information Technology (IT)", "DBA"], "post_time": "2022-01-18T03:14:51Z", "salary": {"currency": null, "max": null, "min": null, "period": "monthly", "term": null}, "salary_visible": false, "title_keywords": ["administrator"], "responsibilities": ["ideas", "software", "data", "troubleshooting", "design", "communication", "database", "application development", "administration", "teams", "testing", "resolution", "migration", "management", "monitoring", "procedures", "administrative tasks", "databases", "auditing"], "requirements": {"degrees": [], "majors": [], "languages": [], "language_level": [], "hard_skills": ["server", "plus", "sql", "deployment", "databases", "rapid", "migration strategies", "oracle"], "soft_skills": ["communication skills", "advanced", "active", "troubleshooting"], "languages_combined": []}, "experience_required": {"duration": ["5+ years", "6-10 years"], "field": ["administration", "related", "design", "relevant experience", "database", "team"]}}, {"job_id": "100003009053669", "location_code": "hk", "company": "JFE Consulting Limited", "job_title": "Senior Technical Analyst - Oracle, MongoDB Database Administrator", "description": "Our client, one of the leading Logistics companies, is looking for high calires to join their winning team.\n\nResponsibilities:\n\n\nDevelop technical specification\nEnforce, refine and document database standards\nWork with technical/development leads to design, or review designs for databases\nAssess and identify database server resource requirements\nDevelop and maintain data models\nDemonstrate advanced understanding of multiple database platforms\nCode, test and deploy database changes\nLead efforts to develop and improve procedures for automated monitoring and proactive intervention, preventing customer impact\n\nRequirements:\n\n\n\nBachelor\u2019s Degree (in lieu of degree \u2013 9 years of work experience in Engineering and/or IT environment\n5 years of work experience in Engineering and/or IT environment\n5 years of work experience as a Database Administrator on multiple database platforms\nDemonstrated experience with computer or network systems hardware and software development methodology/process obtained through formal training, education, and/or work experience\nIT experiences and exposures to Oracle technology e.g. Oracle DB 10g or above, MongoDB or MYSQL.", "employment_types": ["Full Time", "Permanent"], "selling_points": ["Knowledge in ORacle DB, MongoDB, MYSQL", "Exposure to Oracle technology, e.g. Oracle DB&OEM", "Attractive salary"], "locations": ["Shatin Area"], "categories": ["Information Technology (IT)", "DBA", "IT Management", "Data Scientist"], "post_time": "2022-01-17T07:19:09Z", "salary": {"currency": null, "max": null, "min": null, "period": "monthly", "term": null}, "salary_visible": false, "title_keywords": ["analyst", "administrator"], "responsibilities": ["server resource", "monitoring", "procedures", "review designs", "design", "develop", "deploy", "databases", "database", "maintain data"], "requirements": {"degrees": ["degree", "bachelor"], "majors": ["it", "engineering"], "languages": [], "language_level": [], "hard_skills": ["hardware", "oracle"], "soft_skills": [], "languages_combined": []}, "experience_required": {"duration": ["5 years", "9 years"], "field": ["training", "engineering", "education", "it", "database", "software development"]}}, {"job_id": "100003009052423", "location_code": "hk", "company": "Linkers International Limited", "job_title": "(DBA) Database Administrator / Senior Database Administrator  (in-house, perm role, 5 days work)", "description": "Responsibilities\n\nProvide strategic guidance and implementation of the corporate data warehouse and the corresponding data feeds.\nMonitor and analyze database performance and ensure effective and efficient utilization of database systems/processes.\nInstall, design and maintain database system software and implement database security.\nWork with IT teams to develop an understanding of data and information needs, identify solutions and improve the quality of service while providing support through the logical and physical design of databases\nMaintain database dictionaries and support tools; develop and maintain accurate system documentation.\nImplement a Business Continuity solution for the database environment, including the installation and configuration of database software and replication processes.\nSet and maintain database standards.\nComplete other duties as assigned.\n\nRequirements\n\n\nBS degree in Information Technology/Computer Science or equivalent combination of education and experience.\n5+ years of MySQL/DB2/ MySQL, PostgreSQL Database Administrator (DBA), including experience installing, configuring, designing, patching, archiving, and monitoring to include performance tuning databases with indexing.\nExperience in Window platform and Linux\nExperience with backup/recovery best practices.\nExtensive experience with query tuning and troubleshooting.\nWorking knowledge of data encryption techniques and database querying and management tools.\nExperience in cloud-based database services will be an advantage\nKnowledge in ELT and integration technologies (preferred).\nStrong interpersonal, communication, and writing skills\u00a0\n\n\nTo apply online, please click the Apply button below. For a confidential discussion about this role please contact us on +852 2391 2813.\n\n*Personal data collected will be used for recruitment purposes only.", "employment_types": ["Full Time", "Permanent"], "selling_points": ["Up to 40K - 70K", "Experience in MySQL/ Oracle /MongoDB", "Experience in Window & Linux Platforms"], "locations": ["Not Specified"], "categories": ["Information Technology (IT)", "DBA", "Support", "Others"], "post_time": "2022-01-17T03:00:03Z", "salary": {"currency": null, "max": null, "min": null, "period": "monthly", "term": null}, "salary_visible": false, "title_keywords": ["administrator"], "responsibilities": ["business continuity", "software", "data", "quality", "design", "maintain", "database", "system documentation", "other duties", "configuration", "monitor", "implementation", "teams", "develop", "guidance", "installation", "providing support", "systems", "databases"], "requirements": {"degrees": ["degree"], "majors": ["computer science", "information technology"], "languages": [], "language_level": [], "hard_skills": ["integration", "linux", "databases", "writing skills"], "soft_skills": ["troubleshooting", "writing skills", "communication", "extensive", "interpersonal"], "languages_combined": []}, "experience_required": {"duration": ["5+ years"], "field": ["education", "troubleshooting", "database", "information technology"]}}, {"job_id": "100003009055882", "location_code": "hk", "company": "HKT", "job_title": "Senior System Specialist", "description": "Job\u00a0details:\n\nResponsible for the analysis, design, documentation, development, unit testing, and support of database ETL and report development for software applications\nDesign, develop, test, tune, and implement ETL processes, SSRS Reports, SQL queries, stored procedures\nRequirements:\n\nDegree holder in Computer science, information technology or related discipline\nMinimum 2 years experience in ETL development & SQL in data transformation project (less exp will consider as analyst programmer)\nProficient in SQL Server Integration Service (SSIS), SQL Server Reporting Services (SSRS)\nExperience in a report development and business intelligence\nSolid analytical and problem-solving skills", "employment_types": ["Full Time"], "selling_points": [], "locations": ["Wan Chai"], "categories": ["Information Technology (IT)", "DBA"], "post_time": "2022-01-18T03:02:58Z", "salary": {"currency": null, "max": null, "min": null, "period": "monthly", "term": null}, "salary_visible": false, "title_keywords": ["specialist"], "responsibilities": ["software", "analysis", "procedures", "design", "testing", "develop", "reports", "database", "documentation", "report"], "requirements": {"degrees": ["degree holder"], "majors": ["computer science", "information technology"], "languages": [], "language_level": [], "hard_skills": ["integration", "sql", "server", "problem-solving skills", "business intelligence"], "soft_skills": ["problem-solving skills"], "languages_combined": []}, "experience_required": {"duration": ["minimum 2 years"], "field": ["sql", "development", "business"]}}, {"job_id": "100003009051541", "location_code": "hk", "company": "Acton Consulting Limited", "job_title": "System Engineer / System Specialist (Oracle Database) x 3", "description": "Job Descriptions :\n\nPerform system development and enhancement of business systems\nParticipate in system design and gathering users requirement\nConduct system integration test and user acceptance test\nProvide system support to end users\nHandle system documentation update\n\nRequirements:\n\nDiploma\u00a0or above in IT or equivalent\nAt least 2 -3 year\u2019s experience in .Net programming\nExperience in C#, .Net, JavaScript, HTML and CSS\nExperience in SQL, VBA and PowerBI is advantage\nGood command in written and spoken Chinese and English\u00a0\nCandidate with less experience will be considered as Programmer\u00a0", "employment_types": ["Full Time", "Permanent", "Contract"], "selling_points": ["Oracle  Support / Daily operation", "Network knowledge", "AIX / Linux / Unix"], "locations": ["Not Specified"], "categories": ["Information Technology (IT)", "DBA", "Support", "Network & System"], "post_time": "2022-01-16T09:17:23Z", "salary": {"currency": null, "max": null, "min": null, "period": "monthly", "term": null}, "salary_visible": false, "title_keywords": ["specialist", "system engineer"], "responsibilities": ["systems", "system documentation", "system design"], "requirements": {"degrees": ["diploma or above"], "majors": ["it"], "languages": ["english", "chinese"], "language_level": ["good command"], "hard_skills": ["vba", "html", "sql", "javascript", "programming", "css", "c#"], "soft_skills": [], "languages_combined": [{"language": "english", "language_level": ["good command"]}, {"language": "chinese", "language_level": ["good command"]}]}, "experience_required": {"duration": ["at least 2 -3 year"], "field": ["sql"]}}, {"job_id": "100003009055884", "location_code": "hk", "company": "HKT", "job_title": "Senior Technical Officer", "description": "A financial institute\u00a0is currently seeking a high caliber to join their team for large scale banking project\n\nResponsibilities:\n\nParticipate in large scale development\u00a0 project, user requirement gathering, system design, system programming and implementation\nPerform in user training & system testing\u00a0\nPrepare technical specification and related system documents\u00a0\nRequirements:\n\nDegree / Higher Diploma in Computer Science, Information Technology or related disciplines\nMinimum 2 years' in web development using Java, Spring/ Springboot, RestfulAPI, SQL, DB2 and Oracle\nExperience in Node JS is an absolutely advantage\nExperience in Agile/ Scrum will be an advantage\nMature, independent, strong communication and interpersonal skills\nCandidates with more experience will also be considered as System Analyst\u00a0", "employment_types": ["Full Time"], "selling_points": [], "locations": ["Wan Chai"], "categories": ["Information Technology (IT)", "DBA", "Support", "Network & System"], "post_time": "2022-01-18T03:03:03Z", "salary": {"currency": null, "max": null, "min": null, "period": "monthly", "term": null}, "salary_visible": false, "title_keywords": ["senior technical officer"], "responsibilities": ["user requirement", "system design", "implementation", "testing"], "requirements": {"degrees": ["diploma", "degree"], "majors": ["related disciplines", "computer science", "information technology"], "languages": [], "language_level": [], "hard_skills": ["web development", "java", "agile", "sql", "spring", "oracle"], "soft_skills": ["communication and interpersonal skills", "independent", "agile", "mature"], "languages_combined": []}, "experience_required": {"duration": [], "field": ["system analyst"]}}, {"job_id": "100003009048993", "location_code": "hk", "company": "SAE Magnetics (Hong Kong) Ltd", "job_title": "Database Administrator / Database Specialist / DBA", "description": "Responsibility\n\nPerform scalable system management & monitoring, network, application, database and hardware\nManage Enterprise system platform included Virtualization, Windows and Linux\nResponsible for setup, maintenance and troubleshooting on VM platform or Physical server, ensure system availability\nPerform Disaster Recovery Environment management\nPerform Vendor Management\nRequirements\n\nDiploma or about in Computer Science, Information Technology or related disciplines\nMinimum 4 years experience in system administration and technical support in Virtualization, Windows or Linux Platform\nSolid experience in server management such as AD, MS Exchange, O365, Storage, Backup Solution, IT Security etc\nExperience in system administration with scripting is advantage (Shell Script, PowerShell etc)\nProfessional certificate holder is advantage i.e. MCSE, CCNA, LPI, ITIL etc\nMore experience candidate will be considered as Senior System Administrator", "employment_types": ["Full Time", "Permanent"], "selling_points": ["Perform Server and Oracle database administration", "5 day work; Double Pay; Incentive Bonus; 12-19 AL", "HK Science Park; Frequently travel to Dongguan"], "locations": ["Shatin Area"], "categories": ["Information Technology (IT)", "DBA", "Data Scientist"], "post_time": "2022-01-15T19:11:36Z", "salary": {"currency": null, "max": null, "min": null, "period": "monthly", "term": null}, "salary_visible": false, "title_keywords": ["specialist", "administrator"], "responsibilities": ["management", "maintenance", "monitoring", "troubleshooting", "hardware", "database", "setup"], "requirements": {"degrees": ["certificate", "diploma"], "majors": ["related disciplines", "computer science", "information technology"], "languages": [], "language_level": [], "hard_skills": ["itil", "linux", "o365", "mcse", "ccna", "powershell", "server", "exchange"], "soft_skills": [], "languages_combined": []}, "experience_required": {"duration": ["minimum 4 years"], "field": ["management", "it", "security", "administration"]}}, {"job_id": "100003009046204", "location_code": "hk", "company": "Pathsight Limited", "job_title": "Database Consultant / Specialist up to 65k", "description": "Job Duties:\nAccountable for allocation of resources and responsibilities to deliver required results around cost, quality and time\nWorking closely with various stakeholders to ensure the IT infrastructure asset is delivered aligning with the strategic IT and business roadmap\nDesign, configure, administrate and troubleshoot company network\u00a0infrastructure\nLeading a team to perform network project design, implementation and provisioning\nPrepare technical and project related documents.\nNew technology evaluation and suggestion.\n\nRequirements:\n\nHigher Diploma or above in Information Technology or related disciplines.\nAt least 6 years' working experience in\u00a0network infrastructure\u00a0design and support for\u00a0sizable company\nProven technical management and specialist experience of working in a complex IT Network infrastructure environment\nLAN/WAN/MAN architecture design, data centre network architecture design, network topology (physical and logical) design, structural cabling design\u00a0\nFamiliar in some if the below devices\nCisco, Nexus and ACI switches, ISR, ASR and SD-WAN routers\nCisco ASA, ISE, FortiGate and Checkpoint firewalls,\u00a0F5, Bluecoat, Riverbed\u00a0\nWireless -\u00a0 Cisco WLC controllers and AP, Meraki wireless AP\nNetwork services \u2013 DNS, DHCP, FTP, NTP, TACACS, RADIUS, IPSEC\nGood command in spoken and written Chinese and English\nLess experience is considered as Senior Network Engineer / Network Engineer", "employment_types": ["Full Time", "Permanent"], "selling_points": ["1.5 - 3 month bonus depending on performance", "ORSO, Medical, 5days, Bank Holiday etc", "Listed company with stable working environment"], "locations": ["Not Specified"], "categories": ["Information Technology (IT)", "DBA", "IT Management", "Technical / Functional Consulting"], "post_time": "2022-01-13T09:56:49Z", "salary": {"currency": null, "max": null, "min": null, "period": "monthly", "term": null}, "salary_visible": false, "title_keywords": ["specialist", "consultant"], "responsibilities": ["network infrastructure", "cost", "it infrastructure", "related documents", "quality", "implementation", "design", "troubleshoot", "evaluation"], "requirements": {"degrees": ["higher diploma or above"], "majors": ["related disciplines", "information technology"], "languages": ["english", "chinese"], "language_level": ["good command"], "hard_skills": ["ap", "dns", "wan", "sd-wan"], "soft_skills": [], "languages_combined": [{"language": "english", "language_level": ["good command"]}, {"language": "chinese", "language_level": ["good command"]}]}, "experience_required": {"duration": ["at least 6 years"], "field": ["management", "infrastructure", "it", "design"]}}, {"job_id": "100003009045747", "location_code": "hk", "company": "Computer Recruitment Consultants Ltd", "job_title": "Database Administrator", "description": "What you\u2019ll be doing?\n\nFacilitate the implementation and support of deployment in Asia Pacific Region\nPerform detailed analysis of complex business process requirements and provide appropriate system solutions; identify, interpret, validate and document user requirements\nMonitor the external vendor, monitor, regular reporting on project progress to your supervisor and other relevant stakeholders\nFacilitate workshops to collect business requirements and mapping global template as well as identify issues and work around solutions\nSupport in functional unit test, system integration testing and end-to-end scenarios testing\nProvide key user training and end user support as required\n\nWho\u00a0are\u00a0we\u00a0looking\u00a0for?\n\nDegree holder or above in Computer Science/ Information Systems/ Software Engineering or others related\nAt least 5 years of work experience in relevant retail business environments, implementing or using retail business processes and applications\nExperience with SAP IS-Retail/FMS (in following areas: Planning, Retail Financial, Pricing, Value Added Service and Promotions or Supply Chain)\nExperience in deployment project in APAC region is desirable\nExperience in working with global and diverse team\nUnderstanding of integration points with the SD, MM, and FI/CO modules\nProficiency in spoken and written English and Mandarin", "employment_types": ["Full Time"], "selling_points": ["2 years hands-on exp. in database administration", "Installation and configuration of DB Server", "Capacity planning, monitoring, tuning DB Servers"], "locations": ["Not Specified"], "categories": ["Information Technology (IT)", "DBA"], "post_time": "2022-01-14T04:32:33Z", "salary": {"currency": null, "max": null, "min": null, "period": "monthly", "term": null}, "salary_visible": false, "title_keywords": ["administrator"], "responsibilities": ["reporting", "software", "analysis", "systems", "monitor", "implementation", "project progress", "testing", "business process", "collect business requirements", "planning"], "requirements": {"degrees": ["degree holder"], "majors": ["software engineering", "computer science"], "languages": ["english", "mandarin"], "language_level": ["proficiency"], "hard_skills": ["integration", "sap", "analysis", "fms", "vendor", "deployment", "workshops"], "soft_skills": ["diverse", "detailed"], "languages_combined": [{"language": "english", "language_level": ["proficiency"]}, {"language": "mandarin", "language_level": ["proficiency"]}]}, "experience_required": {"duration": ["at least 5 years"], "field": ["supply chain", "business", "planning", "team", "retail", "financial"]}}, {"job_id": "100003009050557", "location_code": "hk", "company": "Walters People (HK)", "job_title": "IBM DB2 Database Administrator DBA - Finance", "description": "Duties :\u00a0\n\nExecute project management processes on assigned project to produce deliverables in time, cost and scope throughout the entire project life-cycle.\nWork closely with business stakeholders and solution provider during business requirement analysis (SDLC) or software package deployment life cycle to produce functional requirements and project implementation document\nPerform business analysis processes to ensure best alignment of business, process, people, and technology to business strategy\nHost or participate business process re-engineering / improvement studies to identify improvement plan and align business operations and IT applications.\nParticipate in testing (prepare, review test plans, track progress, and document testing results and report for remediation and acceptance).\nMaintain project management document plans, methods and tools to the assigned project for adoption\n\nRequirements :\u00a0\n\nDegree holder in Computer Science, Information Technology or related disciplines\nMinimum 3 years solid project management experience in IT industry\nStrong project management and people management skills\nSkilled in SQL, API is an advantage\u00a0\nMature, dynamic, work independent and self-motivated\nFluent in spoken and written English, Cantonese and Mandarin\nCandidate with less project experience will be considered as Business Analyst\u00a0", "employment_types": ["Full Time", "Permanent"], "selling_points": ["IBM DB2", "Purescale", "HADR"], "locations": ["Not Specified"], "categories": ["Information Technology (IT)", "DBA", "Hardware"], "post_time": "2022-01-14T10:44:08Z", "salary": {"currency": "HKD", "max": 69999, "min": 55000, "period": "monthly", "term": null}, "salary_visible": true, "title_keywords": ["administrator"], "responsibilities": ["cost", "software", "operations", "analysis", "review", "implementation", "testing", "business process re-engineering", "project management", "maintain", "plan", "business analysis", "plans", "report"], "requirements": {"degrees": ["degree holder"], "majors": ["related disciplines", "computer science", "information technology"], "languages": ["cantonese", "english", "mandarin"], "language_level": ["fluent"], "hard_skills": ["sql", "project management", "dynamic"], "soft_skills": ["self-motivated", "independent", "mature", "project management", "dynamic"], "languages_combined": [{"language": "cantonese", "language_level": ["fluent"]}, {"language": "english", "language_level": ["fluent"]}, {"language": "mandarin", "language_level": ["fluent"]}]}, "experience_required": {"duration": ["minimum 3 years"], "field": ["business", "project management", "it"]}}, {"job_id": "100003009051571", "location_code": "hk", "company": "GoAnimate Hong Kong Limited", "job_title": "Senior Data Analyst", "description": "Your Responsibilities:\n\nWork closely with internal and external stakeholders in providing HR recruitment including but not limited preparing job descriptions, posting job ads, arranging interviews and preparing employment contract and etc..\nResponsible for new employee onboarding and staff movement.\nParticipate in ad-hoc HR projects and new initiatives as assigned.\n\nOur Requirements:\n\nHigher Diploma or Bachelor degree holder in Human Resources Management or any related qualification.\n2 years of relevant experience in Human Resource recruitment will be an advantage\u00a0\nWell-versed in Employment Ordinance and other HR related regulations in Hong Kong.\nFlexible, proactive and detail-minded with strong communication skill.\nPerformance driven with can-do attitude and able to work under pressure.\nProficiency in both written and spoken English and Chinese. Putonghua is an advantage.;\nImmediately available is highly preferred", "employment_types": ["Full Time", "Permanent"], "selling_points": ["Working knowledge (SQL Server, Oracle or MySQL)", "PL/SQL, Python, Ruby", "Bachelor degree or above in Computer Science"], "locations": ["Sheung Wan"], "categories": ["Information Technology (IT)", "DBA", "Others", "Data Scientist"], "post_time": "2022-01-16T11:06:20Z", "salary": {"currency": null, "max": null, "min": null, "period": "monthly", "term": null}, "salary_visible": false, "title_keywords": ["data analyst"], "responsibilities": ["ad-hoc", "hr", "recruitment"], "requirements": {"degrees": ["diploma", "bachelor degree holder"], "majors": [], "languages": ["putonghua", "english", "chinese"], "language_level": ["advantage", "proficiency"], "hard_skills": [], "soft_skills": ["flexible", "detail-minded", "can-do attitude", "communication skill", "proactive", "driven", "work under pressure"], "languages_combined": [{"language": "putonghua", "language_level": ["advantage"]}, {"language": "english", "language_level": ["proficiency"]}, {"language": "chinese", "language_level": ["proficiency"]}]}, "experience_required": {"duration": ["2 years"], "field": ["recruitment", "relevant experience"]}}, {"job_id": "100003009053603", "location_code": "hk", "company": "JFE Consulting Limited", "job_title": "Senior Database Administrator (DBA)", "description": "Our client, one of the leading IT companies, is looking for high calibres to join their winning team:-\n\nResponsibilities:\n\nInstall, design and maintain database system software and implement database security.\nMonitor and analyze database performance and ensure effective and efficient utilization of database systems/processes.\nMaintain database dictionaries and support tools; develop and maintain accurate system documentation.\nParticipate in the development and maintenance of strategic, architectural and tactical plans for the database and data warehouse environments; be conversant with, and cognizant of, the future direction of systems, how that direction impacts the company and how future and current database systems can be exploited for the company\u2019s benefit. \u00a0\nYou will design, execute and supervise DML/DDL according to business requirements.\n\nRequirements:\n\nBS degree in Information Technology/Computer Science or equivalent combination of education and experience.\nFive or more years of SQL server database experience as Database Administrator (DBA), including experience installing, configuring, designing, patching, archiving, and monitoring to include performance tuning databases with indexing.\nYou have strong experience with database software (especially MySQL),\u00a0\nYou are proficient in SQL programming and Shell;", "employment_types": ["Full Time", "Permanent"], "selling_points": ["MySQL DBA", "Redis, HBase, Shell", "5-day work; attractive salary"], "locations": ["Not Specified"], "categories": ["Information Technology (IT)", "DBA", "IT Management", "Data Scientist"], "post_time": "2022-01-17T07:13:37Z", "salary": {"currency": null, "max": null, "min": null, "period": "monthly", "term": null}, "salary_visible": false, "title_keywords": ["administrator"], "responsibilities": ["software", "system documentation", "maintenance", "data", "systems", "monitor", "design", "develop", "maintain", "database", "plans"], "requirements": {"degrees": ["degree"], "majors": ["computer science", "information technology"], "languages": [], "language_level": [], "hard_skills": ["sql", "server", "programming", "databases"], "soft_skills": [], "languages_combined": []}, "experience_required": {"duration": [], "field": ["sql", "education", "database", "information technology"]}}, {"job_id": "100003009054188", "location_code": "hk", "company": "CK Hutchison Holdings Limited", "job_title": "Database and Systems Administrator", "description": "CK Hutchison, head office of a diversified group of companies with over 18,000 employees in Hong Kong and an additional 279,300 employees worldwide, invites high calibre and self-motivated individuals to join our organisation.\n\nThe Group Information Services Department, located in Hunghom, strives to serve the IT needs of Head Office and is responsible for co-ordinating IT related services within the CK Hutchison Group.\n\nResponsibilities:\n\nPerform database installation and patching\nSupport, monitor and maintain Oracle databases and applications\nPerform application configuration, system administration related tasks\nParticipate in projects with related duties\nHandle service requests raised from users\u00a0\nRequirements:\n\nBachelor degree, diploma or equivalent in Computing related disciplines\nMinimum 2 years' solid Oracle database administration experience\nExperience in Oracle products (e.g. E-Business Suite, Hyperion, etc.) administration\nGood knowledge in shell scripting (Linux / Windows), Oracle SQL & PL/SQL will be an advantage\nStrong problem solving and interpersonal skills\nProficiency in both written and spoken English and Chinese\u00a0\n\n*Candidates with less relevant working experience will be considered as Associate Database and Systems Administrator.\n\nSalary and benefits will commensurate with experience and competence. Please click the \u201cAPPLY NOW\u201d button and include a detailed resume with indication of expected salary.\u00a0 \u00a0\n\n\n\nWe are an equal opportunity employer and welcome applications from all qualified candidates. Personal data collected will be treated in\u00a0the strictest confidence and handled confidentially by authorised personnel for recruitment-related purposes\u00a0only within the CK Hutchison Group of companies.\u00a0\n\nApplicants not\u00a0having heard\u00a0from us within six weeks of the date of application may consider their application unsuccessful.\u00a0The personal data of\u00a0unsuccessful applicants will be destroyed after the recruitment exercise\u00a0pursuant to the requirements of the Personal Data (Privacy) Ordinance in Hong Kong.\n\n\n", "employment_types": ["Full Time"], "selling_points": [], "locations": ["Hung Hom"], "categories": ["Information Technology (IT)", "Application Specialist - Software", "DBA", "Support"], "post_time": "2022-01-17T08:44:04Z", "salary": {"currency": null, "max": null, "min": null, "period": "monthly", "term": null}, "salary_visible": false, "title_keywords": ["administrator"], "responsibilities": ["installation", "configuration", "monitor", "maintain", "databases", "database", "administration"], "requirements": {"degrees": ["diploma", "degree", "bachelor"], "majors": ["related disciplines"], "languages": ["english", "chinese"], "language_level": ["proficiency"], "hard_skills": ["linux", "sql", "problem solving", "pl", "oracle"], "soft_skills": ["problem solving", "interpersonal skills"], "languages_combined": [{"language": "english", "language_level": ["proficiency"]}, {"language": "chinese", "language_level": ["proficiency"]}]}, "experience_required": {"duration": ["minimum 2 years"], "field": ["relevant working experience", "database", "administration"]}}, {"job_id": "100003009050099", "location_code": "hk", "company": "ADECCO", "job_title": "RPA Developer (AI Engineer) - HK$40k-50k", "description": "Our client is a fast expanding and reputable bank in Hong Kong, is looking for a high caliber to join the group.\u00a0\nResponsibilities:\nTo support the Data Science team in creating road map for implementation of data analytics strategy\nTo assist to build data model. Review and validate model effectiveness and performance\nTo address statistical, machine learning and data understanding problems\nTo collaborate with internal stakeholders and external vendors on project planning and execution\nRequirements:\nSound knowledge of data modelling, machine learning, data warehousing/migration\u00a0\nMinimum 7 years relevant experience in banking or FI\u00a0\nGood communication / negotiation and project management skills with strong sense of innovation\nProficient in MongoDB, MySQL, Java and Python\n\u200b\nTo apply, please send your detailed resume to winnie[at]connersconsulting[dot]com or contact Winnie Lai at 3618 8348 for a confidential discussion.\nOnly shortlisted candidates will be notified.\u00a0 Applicants who are not contacted within two weeks may consider their applications unsuccessful.\u00a0 All data collected will be used for recruitment purpose only & will be used strictly confidential.\nConners Consulting Limited\n2005 Kai Tak Commercial Building, 317 Des Voeux Road Central Hong Kong\n(website:\u00a0www.connersconsulting.com)\u00a0 Tel: (852) 3996 8090", "employment_types": ["Full Time", "Permanent"], "selling_points": ["AI / Machine Learning technology", "software platforms & automation platform", "Building RPA solutions"], "locations": ["Central"], "categories": ["Information Technology (IT)", "DBA", "Software Development", "Data Scientist"], "post_time": "2022-01-14T09:46:45Z", "salary": {"currency": null, "max": null, "min": null, "period": "monthly", "term": null}, "salary_visible": false, "title_keywords": ["developer", "engineer"], "responsibilities": ["collaborate with", "project planning", "data", "review", "implementation"], "requirements": {"degrees": [], "majors": [], "languages": [], "language_level": [], "hard_skills": ["python", "project management", "java"], "soft_skills": ["negotiation", "project management skills", "communication", "learning", "detailed"], "languages_combined": []}, "experience_required": {"duration": ["minimum 7 years"], "field": ["relevant experience", "banking"]}}, {"job_id": "100003009042624", "location_code": "hk", "company": "Hong Kong Baptist University", "job_title": "Officer (Database Administration & General Administration) (PR0269/21-22)", "description": "Job Responsibilities:\n-\u00a0Perform database administration and support services in Linux, Windows, IBM z/OS and Cloud platform;\n-\u00a0Implement and support infrastructure solutions in sophisticated, high-performance trading environments that demand stability, high throughput and low latency;\n-\u00a0Provide support and implementation work to application teams including database setup and SQL performance analysis;\n-\u00a0Provide advice for operating policies, technical architecture and configuration of database system;\n-\u00a0Administer and manage Oracle / DB2 Databases including monitoring, troubleshooting, installation, patching and upgrade, performance tuning, backup and recovery, stress test, capacity planning;\n-\u00a0Implement compliance standards and perform regular system compliance review and proactively assesses exposure area;\n-\u00a0Maintain high system availability and ensure all database systems work properly;\n-\u00a0Review SQL, stored procedures and application interfaces with databases;\n-\u00a0Manage vendor to ensure the highest quality delivery and implementation\n\nJob Requirement:\n-\u00a0With at least 7 years of working experience in managing and supporting Oracle / DB2 databases;\n-\u00a0Solid experience with SQL, PL/SQL and shell script/programming would be an advantage;\n-\u00a0Advanced knowledge of Oracle database including RAC, ASM, DataGuard, data partitioning, load balancing, JDBC, ODBC and integration with J2EE applications;\n-\u00a0Strong in SQL and stored procedures;\n-\u00a0Advanced knowledge of database security, backup and recovery, and performance monitoring standards;\n-\u00a0Strong hands-on experience in developing script solutions for process improvement and automation;\u00a0\n-\u00a0Experiences in AWS RDS, MS SQL, MongoDB, DB2 PureScale and HADR is an advantage;\n-\u00a0Understanding of relational and dimensional data modelling;\n-\u00a0Experience in system programming and administration on Linux or Windows Platform;\n-\u00a0Project management experience in sizable scale technology infrastructure implementation;\n-\u00a0Proactive, strong troubleshooting, diagnostic and analytical skills;\n-\u00a0Degree holder in Computer science, Computer engineering, information technology or relevant discipline\n\nApplicants who do not hear from us within 6 weeks may consider their applications unsuccessful. Personal data provided will only be used for the purpose of employment application to HKEX.", "employment_types": ["Full Time"], "selling_points": ["a recognised degree in IT", "Proficiency in data management and administration", "expected to assist in functions/events"], "locations": ["Kowloon City"], "categories": ["Admin & HR", "Clerical / Admin Staff", "Education", "Others", "Information Technology (IT)", "DBA"], "post_time": "2022-01-12T08:12:46Z", "salary": {"currency": null, "max": null, "min": null, "period": "monthly", "term": null}, "salary_visible": false, "title_keywords": ["officer"], "responsibilities": ["quality", "troubleshooting", "maintain", "database", "administration", "configuration", "infrastructure", "teams", "implementation", "compliance", "architecture", "setup", "installation", "provide support", "monitoring", "review", "procedures", "policies", "analysis", "support services", "systems", "provide advice", "databases", "planning"], "requirements": {"degrees": ["degree holder"], "majors": ["computer engineering", "computer science", "information technology"], "languages": [], "language_level": [], "hard_skills": ["linux", "aws", "sql", "odbc", "project management", "analytical skills", "programming", "databases", "integration", "pl", "ms sql", "oracle"], "soft_skills": ["advanced", "troubleshooting", "analytical skills", "project management", "hands-on", "proactive"], "languages_combined": []}, "experience_required": {"duration": ["at least 7 years"], "field": ["infrastructure", "developing", "sql", "project management", "programming", "administration"]}}, {"job_id": "100003009043937", "location_code": "hk", "company": "CLPS Technology (Hong Kong) Co., Limited", "job_title": "Data Analyst (Fintech)", "description": "Role & Responsibilities\n\nWork closely with the Team Leaders, software developers and end users to develop, support and roll out application systems\nHigh involvement on understanding customers\u2019 requirement, providing system design and insight on application performance management issues\nDefining and establishing the technology, standards and processes for logging and monitoring\nResolving production problems and providing timely management update\nBuild and maintain client relationship\nWhat We Are Looking For\n\nBachelor\u2019s degree in IT, computer science or other related fields\nWorking experience on large scale software development, in particular online transaction processing system, and fast paced software development life cycle is preferred\nProven proficiency with Application Performance Monitoring and Log Management solutions for large scale Applications written in C/C++, Java and NodeJS\nExperience in container-based application and project management is an advantage\nSolid experience with Continuous Integration (CI), Continuous Delivery (CD), Continuous Monitoring (CM) and Infrastructure Automation\nKnowledge of professional software engineering practices and best practices for full software development life cycle, including coding standards, code reviews, source control management, build processes, testing, application deployment and operations\n\nWhat You Are Good At\n\nStrong analytical and problem-solving capabilities and proven teamwork skills\nEnjoy learning new technologies and want to build a great product\nSense of ownership for work and desire to deliver great products\nGood interpersonal skills and problem-solving skill\nWritten and oral communication skills in English and Chinese\nSelf-starter, with a keen interest in technology and highly motivated towards success\nProven ability to deliver high profile activities to tight timescale", "employment_types": ["Full Time", "Permanent"], "selling_points": ["SQL Server, ETL tools \u2013 Data clearing", "QlikView, Power BI and Tableau etc", "Competitive compensation"], "locations": ["Central & Western Area"], "categories": ["Information Technology (IT)", "DBA", "Technical / Functional Consulting", "Data Scientist"], "post_time": "2022-01-13T02:31:06Z", "salary": {"currency": null, "max": null, "min": null, "period": "monthly", "term": null}, "salary_visible": false, "title_keywords": ["data analyst"], "responsibilities": ["management", "control", "software", "operations", "monitoring", "infrastructure", "coding", "develop", "testing", "project management", "communication", "system design", "maintain", "continuous monitoring", "transaction processing", "application systems"], "requirements": {"degrees": ["degree", "bachelor"], "majors": ["it", "computer science"], "languages": ["english", "chinese"], "language_level": [], "hard_skills": ["java", "c++", "problem-solving", "project management", "c", "system design", "container", "deployment", "integration", "code", "processing"], "soft_skills": ["communication skills", "oral", "keen", "problem-solving", "timely", "teamwork", "project management", "learning", "interpersonal skills", "motivated"], "languages_combined": [{"language": "english", "language_level": []}, {"language": "chinese", "language_level": []}]}, "experience_required": {"duration": [], "field": ["project management", "infrastructure", "software development"]}}, {"job_id": "100003009038847", "location_code": "hk", "company": "Mtel Career Consulting", "job_title": "Manager (Project/SDM) / Business Analyst/ SA - AP / Engineer (Network / Cloud / Unix) / DBA", "description": "RESPONSIBILITIES\n\n\nResponsible to provide technical support to MySQL, MongoDB, and Oracle databases\nMaintaining the normal operation of the MySQL, MongoDB and Oracle databases running including backup and restoration, troubleshooting and SQL performance tuning, monitoring usage and capacity planning etc\nAssist in database design, installation, configuration, performance tuning and on-going maintenance\nREQUIREMENTS\n\n\nDegree holder with major in Computer Science or related disciplines\nExperience in MySQL\nORACLE database or MongoDB administration experience a plus\nProficiency in Linux platform support and shell script programming\nGood team player, responsible and self-motivated\nProficient spoken and written English, Cantonese and Mandarin is advantage\n\n\nTo apply online, \u00a0please click the Apply button below. For a confidential discussion about this role please contact us on +852 2391 2813.\n\n\n\nPersonal data collected will be used for recruitment purposes only.", "employment_types": ["Full Time", "Permanent", "Temporary"], "selling_points": ["Project manager/System Architect", "SA- AP (Java / c#.Net / Node.js / python)", "Business Analyst"], "locations": ["Not Specified"], "categories": ["Information Technology (IT)", "DBA", "Software Development", "Network & System"], "post_time": "2022-01-12T01:19:31Z", "salary": {"currency": null, "max": null, "min": null, "period": "monthly", "term": null}, "salary_visible": false, "title_keywords": ["manager", "business analyst", "engineer"], "responsibilities": ["installation", "maintaining", "maintenance", "technical support", "configuration", "monitoring", "troubleshooting", "design", "databases", "database", "planning"], "requirements": {"degrees": ["degree holder"], "majors": ["related disciplines", "computer science"], "languages": ["cantonese", "english", "mandarin"], "language_level": ["advantage", "proficient"], "hard_skills": ["linux", "plus", "programming", "oracle"], "soft_skills": ["good team player", "self-motivated", "responsible"], "languages_combined": [{"language": "cantonese", "language_level": ["advantage", "proficient"]}, {"language": "english", "language_level": ["advantage", "proficient"]}, {"language": "mandarin", "language_level": ["advantage", "proficient"]}]}, "experience_required": {"duration": [], "field": ["database", "administration"]}}, {"job_id": "100003009048607", "location_code": "hk", "company": "CITIC Telecom International Holdings Limited", "job_title": "System Support Engineer (Business Support Systems)", "description": "Our client\n\nA HK listed company. They are looking for Data Analytics Manager to join their team.\n\nYour role\n\nStrategic Planning in data collection, processing and providing insight to support business growth\nExplore and apply latest Big Data technologies and applications\nWork with the internal and external stakeholders to enhance the awareness of data insight\nAs the Subject Matter Expert, trainer and advocate to uplift the data analytics skillset and culture of the team\n\nRequirement\n\nMinimum of 7 years' experience with proven record in data analysis/statistics and big data projects\nExperience in both in-house and vendor is a plus\nGood understanding of advanced data analysis tools and methodology, in particulars, big data analytics and Al modelling\nPassionate, creative and organized problem solver with a strong market-centric mindset and data driven capabilities\n\nClick \"Apply Now\" to apply for this position or\u00a0call\u00a0us\u00a0at\u00a0+852 2762 4829\u00a0for a confidential discussion. All information collected will be kept in strict confidence and will be used for recruitment purpose only.", "employment_types": ["Full Time", "Permanent"], "selling_points": ["Business Support Systems support and maintenance", "IT position in Telecom Industry", "Double Pay, Bonus, 5-day work, Medical & Dental"], "locations": ["Kwai Fong"], "categories": ["Information Technology (IT)", "DBA", "Support", "IT Management"], "post_time": "2022-01-14T06:54:06Z", "salary": {"currency": null, "max": null, "min": null, "period": "monthly", "term": null}, "salary_visible": false, "title_keywords": ["system support", "engineer"], "responsibilities": ["strategic planning", "data", "big data", "subject matter expert", "data analysis", "recruitment", "data collection"], "requirements": {"degrees": [], "majors": [], "languages": [], "language_level": [], "hard_skills": ["plus", "data analytics", "analysis", "vendor", "processing"], "soft_skills": ["passionate", "organized", "confidence", "problem solver", "advanced", "creative", "driven"], "languages_combined": []}, "experience_required": {"duration": ["minimum of 7 years"], "field": ["data analysis", "statistics"]}}, {"job_id": "100003009048677", "location_code": "hk", "company": "Lloyd Karson International Limited", "job_title": "Sr Data Analyst / Senior System Analyst \u2013 Data warehouse - Insurance (ETL/ SSIS /PowerBI)(40k \u2013 50k)", "description": "Responsibilities:\n\nSystem deployment, maintenance and support for Telecom Business Support Systems (BSS)\nDevOps tools introduction, development and integration\nDefine systems\u2019 O&M requirements, optimize systems\u2019 architecture and deploy innovative O&M technique\n\nRequirements:\n\nBachelor degree or above in Computer Science or related disciplines\nMinimum 3 years\u2019 experience in IT system development, testing or maintenance\nFamiliar with the functions and architectures of business support IT systems: Billing, CRM and Order system etc.\nFamiliar with\u00a0popular IT maintenance techniques\u00a0e.g. Docker, K8s, Prometheus, ELK, Jenkins, etc.\u00a0\nGood coding/database skills\u00a0in at least two of below areas: Java, PL/SQL, Python, Oracle, MySQL, etc.\nExperience in Oracle/MySQL DBA would be an advantage\nExperience in\u00a0Big Data, K8s development and maintenance would be an advantage\nGood command in both spoken and written English and Chinese (Cantonese & Mandarin)\nGood team player with a strong sense of integrity\nWilling to learn and able to work independently with minimum supervision\u00a0 \u00a0\n\nFringe Benefits:\n\nOn-the-job training\nDouble pay\nAttractive performance bonus\nTransportation allowance\nMedical & dental insurance\nFree meals\nFree shuttle bus service\nTraining subsidies\nStaff discount\n\nWe offer competitive salary and benefit package including double pay, medical and dental benefits, 5-day work, 14 days paid annual leave and free shuttle bus service to the capable candidate. If you are interested, please immediately send your application stating\u00a0your current & expected salary and date availability with full resume\u00a0to\u00a0Human Resources Department\u00a0by email by clicking \"Apply Now\". Please clearly indicate the applied position and reference number on your application.\n\nAll personal data received will be treated strictly confidential and will be used for employment related purpose only.", "employment_types": ["Full Time", "Permanent"], "selling_points": ["Design, build & maintain datawarehouse for Life", "Data-mapping / modeling, ETL process, Dashboard", "MS Azure, MS SQL Server, SSIS, SSRS, SSAS, PowerBI"], "locations": ["Quarry Bay"], "categories": ["Banking / Finance", "Others", "Information Technology (IT)", "DBA", "Data Scientist"], "post_time": "2022-01-14T07:01:20Z", "salary": {"currency": "HKD", "max": 54999, "min": 35000, "period": "monthly", "term": null}, "salary_visible": true, "title_keywords": ["system analyst", "data analyst"], "responsibilities": ["systems", "architecture", "maintenance", "deploy"], "requirements": {"degrees": ["degree or above", "bachelor"], "majors": ["related disciplines", "computer science"], "languages": ["cantonese", "english", "chinese", "mandarin"], "language_level": ["good command"], "hard_skills": ["java", "jenkins", "maintenance", "sql", "python", "pl", "oracle"], "soft_skills": ["good team player", "willing to learn", "integrity", "work independently"], "languages_combined": [{"language": "cantonese", "language_level": ["good command"]}, {"language": "english", "language_level": ["good command"]}, {"language": "chinese", "language_level": ["good command"]}, {"language": "mandarin", "language_level": ["good command"]}]}, "experience_required": {"duration": ["minimum 3 years"], "field": ["development", "it system development", "maintenance", "testing"]}}, {"job_id": "100003009047980", "location_code": "hk", "company": "Convoy Global Holdings Limited", "job_title": "Senior Data Analyst", "description": "ROLES AND RESPONSIBILITIES\n\nDatabase design, planning, implementation, performance monitoring and tuning\nEnsure successful deployment of installations/upgrades\nDatabase administration of Oracle/MySQL\nOperation, planning & design of multiple enterprise Servers.\nProvide trend analysis to the management team.\nPrepare operation and maintenance documents\nWork closely with team members to deliver projects and problem solving on time\n\nQUALIFICATIONS AND REQUIREMENTS\n\nDegree holder in information system or engineering, computer science or related discipline\nMinimum 3 years experience in database administration of Oracle/MySQL Database, including SQL/PLSQL tuning and programming; install/update/patch/interpret oracle enterprise manager, AWR report analysis, backup and recovery, data migrations, redundancy and replications, etc.\nCandidates with OCP/OCA certification is an advantage\nKnowledge in system administration (Unix/Linux) is an advantage\n\nBENEFITS\n\n5-day a week and flexible working hours\n14 days+ annual leave, Birthday leave\nGroup medical (including dental and Chinese Medicine)\nTeam building lunch and Friday Tea\nSmall and nimble team in an energetic, collaborative and liberal environment\n\nREMARKS\n\nWe offer attractive remuneration package and excellent opportunities for career advancement to the right candidate.\u00a0Please send your\u00a0resume\u00a0with\u00a0current\u00a0&\u00a0expected salary\u00a0and\u00a0available\u00a0date\u00a0by clicking\u00a0Apply Now.", "employment_types": ["Full Time", "Permanent"], "selling_points": ["Interpret data, analyze results", "Excellent at Data Presentation", "Knowledge of statistics, database design"], "locations": ["Wan Chai"], "categories": ["Information Technology (IT)", "DBA", "Product Management / Business Analyst", "Data Scientist"], "post_time": "2022-01-14T04:24:26Z", "salary": {"currency": null, "max": null, "min": null, "period": "monthly", "term": null}, "salary_visible": false, "title_keywords": ["data analyst"], "responsibilities": ["administration", "management team", "maintenance", "upgrades", "analysis", "monitoring", "implementation", "design", "database", "planning"], "requirements": {"degrees": ["degree holder"], "majors": ["engineering", "computer science"], "languages": [], "language_level": [], "hard_skills": ["linux", "analysis", "information system", "sql", "programming", "oracle"], "soft_skills": [], "languages_combined": []}, "experience_required": {"duration": ["minimum 3 years"], "field": ["sql", "programming", "database", "administration"]}}, {"job_id": "100003009040332", "location_code": "hk", "company": "Orient Overseas Container Line Ltd (OOCL)", "job_title": "Senior Technical Analyst - Oracle, MongoDB Database Administrator", "description": "My client is a Leading Financial Institute is looking for high-caliber person to fill the position\n\n\n\nResponsibilities:\n\nBuilding RPA solutions and BPM automation\n\nEnrich and transform corporate data to enable searching, data visualization, and advanced analytics under Continuous delivery model\nWorking with data scientists to industrialise prototype models in data engineering context\nPartner with process re-engineering specialists, working closely business stakeholders to review business operating models and drive streamlining\nWork with Architects, Platform Engineers and Product Management to evaluate and onboard new technology solutions to enrich our platform offering\nRequirements:\n4 years experience in Data Engineering or related working experiences\nData driven thinking capabilities\nExcellent communication skills and experience of working in an international team\nSolid grounding in Financial Service\nExperience with Data processing in large scale enterprise environment is highly desired.\nExperience of implementing complex RPA solution is a big plus\nInterested parties, please\u00a0apply the position via\u00a0Click HERE\u00a0with your CV, or if you would like to have a further discussion on Joey +852 9844 6309 for a confidential discussion about the post.\n\nPlease note that only shortlisted candidates will be notified. All information gathered will be treated in strict confidence and solely used for recruitment purposes.", "employment_types": ["Full Time", "Permanent"], "selling_points": ["Knowledge in Oracle DB, MongoDB, MYSQL", "Exposure to Oracle technology e.g. Oracle DB 10g", "Welcome open sources tools and new technologies"], "locations": ["Shatin Area"], "categories": ["Information Technology (IT)", "DBA", "Security", "Testing / QA"], "post_time": "2022-01-12T02:18:36Z", "salary": {"currency": null, "max": null, "min": null, "period": "monthly", "term": null}, "salary_visible": false, "title_keywords": ["analyst", "administrator"], "responsibilities": ["management", "visualization", "data", "review", "evaluate", "re-engineering"], "requirements": {"degrees": [], "majors": [], "languages": [], "language_level": [], "hard_skills": ["rpa", "plus", "processing"], "soft_skills": ["communication skills", "driven"], "languages_combined": []}, "experience_required": {"duration": ["4 years"], "field": ["related", "engineering", "team"]}}, {"job_id": "100003009041069", "location_code": "hk", "company": "JustOneGalaxy Recruitment Limited", "job_title": "Financial BI (Senior) System Analyst/ BI Specialist - Multiple new headcounts", "description": "ALUMNI AFFAIRS OFFICE\n\nOfficer (Database Administration & General Administration) (PR0269/21-22)\n\nThe appointee will be responsible for database administration and general administration of Alumni Affairs Office.\n\nApplicants should possess a recognised degree in IT or related discipline with at least three years of solid experience in a related field.\u00a0 They should be good at processing large amounts of data and should have some experience in alumni relationship management.\u00a0 The appointee is expected to assist in functions/events of the Office and to perform any other duties as assigned. Proficiency in data management and administration and knowledge of HTML and SQL would be advantageous.\u00a0 They should also have an excellent command of English and Chinese; strong interpersonal, analytical, organisational, and communication skills; and be attentive to details.\n\nShortlisted candidates will be invited to attend a written assessment. Applicants who have responded to the previous advertisement are under consideration and need not re-apply.\n\nInitial appointment will be offered on a fixed-term contract of two years. Re-appointment thereafter will be subject to mutual agreement.\n\nRank and salary will be commensurate with qualifications and experience.\n\nApplication Procedure:\n\nApplicants are invited to submit their applications at the HKBU e-Recruitment System (jobs.hkbu.edu.hk). Those not invited for interview 8 weeks after the closing date may consider their applications unsuccessful. Details of the University\u2019s Personal Information Collection Statement can be found at http://hro.hkbu.edu.hk/pics.\n\nThe University reserves the right not to make an appointment for the post advertised, and appointment will be made according to the terms and conditions then applicable at the time of offer.\n\nClosing date:\u00a07 February 2022 (or until the position is filled)", "employment_types": ["Full Time", "Permanent"], "selling_points": ["Top-tier Financial opportunity/ E-commerce new HC", "17AL, Data Analysis, ETC, Visualization, New Tech", "Flexible environment & Culture, Management support"], "locations": ["Not Specified"], "categories": ["Information Technology (IT)", "DBA", "Others", "Data Scientist"], "post_time": "2022-01-12T03:24:27Z", "salary": {"currency": null, "max": null, "min": null, "period": "monthly", "term": null}, "salary_visible": false, "title_keywords": ["specialist", "system analyst"], "responsibilities": ["any other duties", "management", "data", "communication", "recruitment", "database", "administration"], "requirements": {"degrees": ["degree"], "majors": ["it"], "languages": ["english", "chinese"], "language_level": ["excellent"], "hard_skills": ["data management", "html", "sql", "make", "processing"], "soft_skills": ["communication skills", "attentive to details", "interpersonal", "responsible"], "languages_combined": [{"language": "english", "language_level": ["excellent"]}, {"language": "chinese", "language_level": ["excellent"]}]}, "experience_required": {"duration": ["at least three years"], "field": ["related", "management", "it"]}}, {"job_id": "100003009047725", "location_code": "hk", "company": "Public Bank (Hong Kong) Ltd", "job_title": "Data Analyst (Ref: JD-DA)", "description": "Major Responsibilities\n\nSupport the components related to cloud management platform, including vPC, security group, support automation template maintenance and other Cloud overlay infrastructure maintenance\nProvide support to network and computer platforms including firewall, load balancer, Linux and Windows OS, and Kubernetes infrastructure, etc.\nResponsible for generating scripts and templates required for the automatic provisioning of resources\nSupport for directory systems such as Active Directory and ADFS, Single Sign On user profile setup and related SSO technology like SAML, OAuth 2.0 and SCIM 2.0\nExplore new cloud services offerings and install/ execute processes/ standards for optimal use of cloud service provider offerings\nProvide support to the CICD tools (e.g. GitHub Enterprise, Jenkins) and automation tools (e.g. Ansible and Terraform) and responsible for maintaining the automation playbook\nStay well-informed of cloud failures and complications related to cloud services and provide level 2 support for cloud infrastructure or related supporting tool's issue\nResponsible for providing support to new project deployment and development of related SysOps matters and collaborate with the application teams to enable their applications to run on Cloud infrastructure\nAssist to manage vendor\u2019s managed services on the implementation and support operation tasks\nProvide on-call support for emergency production incidents and on-site support for firefighting and perform shift duties as required\nPerform other duties as assigned by supervisor(s)\n\nRequirements\n\nUniversity degree in information technology, computer science or related discipline\nMinimum 5 years of relevant experience preferably gained from major financial institutions. Candidates with less experience may be considered for the position of Specialist I (Cloud Platform)\nExperience in system infrastructure (e.g. system, storage, computing and network), preferably with experience in Cloud and DevOps automation tool support and knowledge of tools and script skills related to Ansible Tower, Terraform, Jenkins, GitHub Python, Ruby, Javascript, JSON, etc.\nPreferably with knowledge of cloud computing technologies and prevailing technology trends\nPositive attitude and strong commitment to the delivery of quality work\nEffective communication skills (both written and verbal) to collaborate with application teams, operation teams and vendors for daily support and project implementation support activities\nGood command of written and spoken English and Chinese, with proficiency in Putonghua an advantage\n\nHow to Apply\nInterested parties please send your curriculum vitae stating your current and expected salaries, and the contact phone number to the Human Resources Division, Unit B, 25/F, MG Tower, 133 Hoi Bun Road, Kwun Tong, Kowloon\u00a0\u00a0by clicking the \"Apply Now\" button below.\nAll applications and personal information collected will be treated in strict confidence and only be used for the purpose of recruitment and selection.\u00a0 The information collected will be accessed by our authorized personnel only.\u00a0 Those applicants not contacted by the Human Resources Division within two months from their application date should consider their applications filed for future reference which will be retained for one year for possible future job matching, and will be destroyed after the expiry of one year.", "employment_types": ["Full Time", "Permanent"], "selling_points": [], "locations": ["Not Specified"], "categories": ["Banking / Finance", "Others", "Information Technology (IT)", "DBA", "Product Management / Business Analyst"], "post_time": "2022-01-15T03:49:00Z", "salary": {"currency": null, "max": null, "min": null, "period": null, "term": null}, "salary_visible": false, "title_keywords": ["data analyst"], "responsibilities": ["collaborate with", "management", "provide support", "perform other duties", "maintenance", "active directory", "maintaining", "infrastructure", "systems", "teams", "implementation", "providing support", "setup"], "requirements": {"degrees": ["university degree"], "majors": ["computer science", "information technology"], "languages": ["putonghua", "english", "chinese"], "language_level": ["advantage", "proficiency", "good command"], "hard_skills": ["jenkins", "computing technologies", "devops", "ruby", "ansible", "javascript", "python"], "soft_skills": ["positive attitude", "communication skills"], "languages_combined": [{"language": "putonghua", "language_level": ["proficiency", "advantage", "good command"]}, {"language": "english", "language_level": ["proficiency", "advantage", "good command"]}, {"language": "chinese", "language_level": ["proficiency", "advantage", "good command"]}]}, "experience_required": {"duration": ["minimum 5 years"], "field": ["related", "devops", "infrastructure", "relevant experience", "financial institutions"]}}, {"job_id": "100003009047688", "location_code": "hk", "company": "iTalent Company", "job_title": "Assistant Data Analytics Manager - HK Listed Company", "description": "Responsibilities:\n\nCollect data, build and maintain data pipelines, conduct data exploration and visualization, develop and maintain the dashboard to interpret the analysis results\nTransfer data into valuable business insights and provide actionable recommendations\nSupport and align efforts to drive business process analysis meeting to support the Business Unit\nEnsure a valid data analyzing process\u00a0including data extraction, manipulation, processing, storage, archival and more\n\nRequirements:\n\nDegree in Data Science,\u00a0Business Analysis\u00a0Statistics, Information Technology or related discipline\n2+ years of experience in Data Analytics related areas (experience in CRM/ Retail/ Healthcare sector will be a plus)\nHands-on experience in data visualization with Tableau/Power BI/ Other visualization tools (Tableau is an advantage)\nStrong analytical,\u00a0presentation, interpersonal,\u00a0communication\u00a0and problem-solving skills\nSolid knowledge of computer science fundamentals including algorithms, data structures, and databases\nSelf-motivated, work proactive and willing to learn new technology\nKnowledge in SQL and Python is preferable\nExperienced in managing and developing data integration, ETL with data warehouse, Google Analytics, Google Tag Manager and BI platform is preferred.\nAbility to work independently under pressure\nImmediate available is highly preferred\n\nCandidate with less experence will be considered as Assistant Data Analyst (Fresh graduate welcome)", "employment_types": ["Full Time", "Permanent"], "selling_points": ["Data artchitecture, processing and integration", "5 yrs+ exp in data management and deploy AI models", "Proficient in SQL, Python and GCP tools"], "locations": ["Not Specified"], "categories": ["Professional Services", "Business Analysis / Data Analysis", "Information Technology (IT)", "DBA", "Data Scientist"], "post_time": "2022-01-14T03:48:17Z", "salary": {"currency": null, "max": null, "min": null, "period": "monthly", "term": null}, "salary_visible": false, "title_keywords": ["manager", "assistant"], "responsibilities": ["manipulation", "visualization", "data", "analysis", "develop", "maintain", "business process", "maintain data"], "requirements": {"degrees": ["degree", "fresh graduate"], "majors": ["data science", "business", "statistics", "information technology"], "languages": [], "language_level": [], "hard_skills": ["google analytics", "plus", "bi", "integration", "data warehouse", "data analytics", "analysis", "tableau", "sql", "databases", "data visualization", "python", "problem-solving skills"], "soft_skills": ["self-motivated", "work independently", "under pressure", "presentation", "willing to learn", "communication", "hands-on", "problem-solving skills", "proactive", "interpersonal"], "languages_combined": []}, "experience_required": {"duration": ["2+ years"], "field": ["related", "healthcare", "retail"]}}, {"job_id": "100003009046449", "location_code": "hk", "company": "Page Group Hong Kong", "job_title": "Data Administration Analyst - MNC Insurance Co.", "description": "As being a technology-enabled financial B2B platform, provides all-around services and integrates a full range of financial products. Our mission is to accelerate the business growth of our B2B partners and unleash their potentials at ease.\n\nWe\u2019re growing fast and are building a business that is focused and fit for the future. We\u2019re looking for a SeniorData Analyst in our Data team to join the team and share our vision and venture our success.\n\nWhat you will be working on:\n\nInterpret data, analyze results using statistical techniques and provide ongoing BI and business reports\nAcquire data from primary or secondary data sources and maintain databases/data systems\nIdentify, analyze, and interpret trends or patterns in complex data sets\nFilter and clean data by reviewing computer reports, documents, and performance indicators to locate and correct code problems\nWork with management and business users to prioritize business and information needs\nLocate and define new business decisions, process improvement opportunities\nWork with data architect and developer to develop and implement databases, data collection systems, data analytics, and other strategies that optimize statistical efficiency and quality\nManage and participate in end-to-end BI journey includes but not limited to data modeling, ETL design and development, data governance, database management, data presentation, and visualization\nPerform any ad-hoc projects as assigned\n\nWhat we are looking for:\n\nDegree holder in Mathematics, Computer Science, Information Management, Statistics or related disciplines. Master degree an advantage\n2 - 7 years working experience in\u00a0Dimensional Data Modeling\u00a0(e.g.\u00a0star-schema),\u00a0PowerBI,\u00a0Data Factory/SSIS\u00a0and\u00a0MSSQL\nTechnical expertise regarding Enterprise Data Warehouse Design which consists of\u00a0ODS,\u00a0STG\u00a0and\u00a0DW,\u00a0SSIS\u00a0ETL\u00a0Design and\u00a0Stored-Procedure\u00a0Development\nStrong knowledge of and experience with\u00a0PowerBI,\u00a0MDX,\u00a0DAX,\u00a0T-SQL\u00a0and\u00a0Python\nAble to use\u00a0PowerBI\u00a0and Python\u2019s\u00a0Matplotlib,\u00a0NumPy\u00a0and\u00a0Pandas\u00a0for Statistical Data Analysis and Data Visualization\nExperience in administering Azure\u2019s products (Azure SQL Database,\u00a0Data Warehouse,\u00a0Data Factory)\nExcellent at Data Presentation and have a good sense of numbers\nExcellent verbal and written communication skills\nGood command of both spoken and written English and Chinese\nKnowledge of insurance and financial products is an advantage\nWe offer competitive remuneration including career prospects to the right candidate. Interested parties please send detailed resume with availability, current and expected salaries to\u00a0Human Resources Department\u00a0by clicking the\u00a0Apply Now\u00a0button and upload your CV and cover letter.\u00a0\n(All applications will be treated in strict confidence and used for recruitment purpose within Convoy Global Holdings Limited only. All applicants are kept on file six months from the date of the application.)", "employment_types": ["Full Time", "Permanent"], "selling_points": ["Basic in Python/VBA/SQL is sufficient", "Insurance experience a definite plus", "Open to insurance candidates interested in data"], "locations": ["Not Specified"], "categories": ["Information Technology (IT)", "DBA", "Software Development", "Insurance", "Others"], "post_time": "2022-01-13T11:15:53Z", "salary": {"currency": "HKD", "max": 24999, "min": 17000, "period": "monthly", "term": null}, "salary_visible": true, "title_keywords": ["analyst"], "responsibilities": ["management", "work with management", "visualization", "data", "systems", "quality", "design", "develop", "data analysis", "communication", "maintain", "reports", "databases", "data collection", "database", "ad-hoc projects", "insurance"], "requirements": {"degrees": ["master degree", "degree holder"], "majors": ["related disciplines", "mathematics", "statistics", "computer science"], "languages": ["english", "chinese"], "language_level": ["good command"], "hard_skills": ["clean", "ease", "bi", "azure", "data warehouse", "data analytics", "analysis", "t-sql", "python", "sql", "databases", "data visualization", "mssql", "code"], "soft_skills": ["communication skills", "presentation", "prioritize", "focused"], "languages_combined": [{"language": "english", "language_level": ["good command"]}, {"language": "chinese", "language_level": ["good command"]}]}, "experience_required": {"duration": ["2 - 7 years"], "field": ["sql", "database"]}}, {"job_id": "100003009050635", "location_code": "hk", "company": "China Mobile International Limited", "job_title": "Senior Application Engineer/ Application Engineer (Ref:CMIJD-0104-AEBOSSDI)", "description": "Manage and participate data warehousing and data analytic project initiatives, including but not limited to data schema design, extract/transform/load (ETL) design, data presentation and visualization\nAcquire data from primary or secondary data sources and maintain databases/data systems\nWork with IT, user department and product owner to build and manage a wide variety of data sets\nTranslate business pain-points and solve by formulating action plans with analytical techniques and mathematical modeling\u00a0\nHelp planning and executing the development of analytical/machine learning solutions from initial design to model development, model validation, implementation, prototyping and testing\nPresent key findings and actionable recommendations to supervisors and other stakeholders\nMaintain good knowledge of data analytics trends and propose the use of latest data tools\nDegree holder in Computer Science or Engineering or related discipline\n3-5 years of experience in relevant business intelligence and data analytics, experience in banking industry is preferred\nExperience in analyzing business / data requirements, data gathering, cleansing & preparation.\nStrong SQL skills and experience working with relational databases.\nStrong data analytical skill and data sense.\nFamiliarity with visualization tools, e.g. Tableau, Qlikview\nSelf-directed with high motivation and demonstrated capability to manage time & projects and to innovate and explore new techniques\nStrong communication and interpersonal skills\nExperience in banking industry preferred, but not a strict requirement.\n\n\n\nTo apply, interested parties please follow the application methods available in the Bank\u2019s career website https://www.publicbank.com.hk/en/aboutus/careeropportunities. You can send us your resume quoting our job reference number together with present & expected salary (a must) to the Human Resources Department by email or fax at 2815 3157 or by post to Human Resources Department, 12/F, Public Bank Centre, 120 Des Voeux Road Central, Hong Kong. You may also visit our career website for other career opportunities available within our Group.\n\nPersonal data collected will be used for recruitment purpose only and will be treated in accordance with the Bank\u2019s Personal Information Collection Statement, a copy of which has been available in the Bank\u2019s career website.", "employment_types": ["Full Time", "Permanent"], "selling_points": ["Development of web-based information systems", "Conducting UAT & delivering training", "Project & Vendor management"], "locations": ["Kwai Hing"], "categories": ["Information Technology (IT)", "Application Specialist - Software", "DBA", "Network & System"], "post_time": "2022-01-14T11:02:24Z", "salary": {"currency": null, "max": null, "min": null, "period": "monthly", "term": null}, "salary_visible": false, "title_keywords": ["application engineer"], "responsibilities": ["warehousing", "visualization", "data", "cleansing", "systems", "implementation", "design", "testing", "communication", "maintain", "executing", "databases", "banking", "plans", "planning"], "requirements": {"degrees": ["degree holder"], "majors": ["engineering", "computer science"], "languages": [], "language_level": [], "hard_skills": ["qlikview", "analytical skill", "data analytics", "tableau", "sql", "databases", "business intelligence"], "soft_skills": ["analytical skill", "learning", "presentation", "communication and interpersonal skills"], "languages_combined": []}, "experience_required": {"duration": ["3-5 years"], "field": ["sql", "banking industry", "business"]}}, {"job_id": "100003009044091", "location_code": "hk", "company": "Hongkong International Terminals Limited", "job_title": "System Engineer (Windows)", "description": "Our client\n\nA HK listed company. They are looking for Assistant Data Analytics Manager to join their team.\n\nYour role\n\nDefine best practice in data architecture, structure and processing\nDesign and create end-to-end ETL processes utilizing tools such as Python and SQL\nData integration from third-party data source\nResearch and explore on new analytic methodology for structured and unstructured data\nPrepare reports and analysis, provide business insights to support the strategic decisions\nVendor management for AI / BI related projects\n\nRequirement\n\nBachelor degree with minimum 5 years of relevant experience in Data Management\nExperience in building & deploying large scale machine learning models\nHands on experience in evaluate and deploy AI models, like NLP classification model and image recognition model, etc\nFamiliar with Tableau, Google Data Studio and Google Cloud Platform (GCP) related tools including Cloud Function, Cloud logging, BigQuery, Google sheet API, PubSub, etc\nProficient in programming using SQL and python\nQuick learner and Able to work independently as well as a good team player, efficient & minimal mistake tolerance\n\nClick \"Apply Now\" to apply for this position or\u00a0call\u00a0us\u00a0at\u00a0+852 2762 4829\u00a0for a confidential discussion. All information collected will be kept in strict confidence and will be used for recruitment purpose only.", "employment_types": ["Full Time", "Permanent"], "selling_points": ["5 Day Work Week, Double Pay, Discretionary Bonus", "Medical Insurance, Free Shuttle Bus", "Wintel infrastructure, troubleshooting"], "locations": ["Kwai Fong"], "categories": ["Information Technology (IT)", "DBA", "Network & System", "Technical / Functional Consulting"], "post_time": "2022-01-13T03:02:25Z", "salary": {"currency": null, "max": null, "min": null, "period": null, "term": null}, "salary_visible": false, "title_keywords": ["system engineer"], "responsibilities": ["management", "data", "analysis", "design", "evaluate", "recruitment", "deploy", "prepare reports", "architecture"], "requirements": {"degrees": ["degree", "bachelor"], "majors": [], "languages": [], "language_level": [], "hard_skills": ["bi", "data management", "integration", "ai", "data analytics", "analysis", "vendor", "tableau", "sql", "programming", "python", "processing"], "soft_skills": ["efficient", "work independently", "good team player", "confidence", "quick learner", "hands on", "learning", "structured"], "languages_combined": []}, "experience_required": {"duration": ["minimum 5 years"], "field": ["management", "relevant experience"]}}, {"job_id": "100003009043714", "location_code": "hk", "company": "Swire Resources Ltd", "job_title": "CRM Data Analyst", "description": "Responsibilities\n\nParticipate in the implementation of an enterprise-level data warehouse platform, complete data warehouse architecture design ,data modeling and ETL development based on big data technology.\nGather business data requirements to define data strategy and data models , translate business questions into data solutions.\nEstablish organization data governance model, responsible for data quality management.\n\nRequirements\n\n\nAt least\u00a03 years practical experience on Data Warehouse development, with experience in large scale Data Warehouse project.\nExperience in using ETL tool to develop data transformation and handling.\nFamiliar with Kimball dimensional modeling method, with massive data processing experience.\nSolid experience on Spark,\u00a0Flink and data visualization tools (Tableau)\u00a0\u00a0 is preferred.\nSolid experience on cloud like Azure, AWS or Ali cloud is preferred.\nSolid\u00a0knowledge\u00a0on\u00a0accounting/\u00a0financial\u00a0products is\u00a0preferred.\nExperience in metadata management, data quality management, and data governance is preferred.\nProficient in demand analysis and design, familiar with banking and securities related business is preferred.\nA team player, fast learner, mature and able to work under pressure.\n\nWe offer competitive remuneration package and comprehensive fringe benefit to the right candidate. Interested parties please forward your full resume with availability, expected salary by pressing \"Apply now\".\n\nPersonal data collected will be used for recruitment related purposes only. Applicants not invited for an interview within 2 months from the date of this posting may consider their applications unsuccessful. Personal data will be destroyed after 3 months.\n\nFor further information about our Company, please visit our website: https://www.cmbi.com.hk/en-US/\n\n\n", "employment_types": ["Full Time", "Permanent"], "selling_points": ["CRM Data extraction, dashboard visualization", "Basic knowledge in Tableau, PowerBI", "Experience in F&B/retail environment"], "locations": ["Kowloon Bay"], "categories": ["Professional Services", "Business Analysis / Data Analysis", "Information Technology (IT)", "DBA", "Marketing / Public Relations", "Others"], "post_time": "2022-01-13T01:38:06Z", "salary": {"currency": null, "max": null, "min": null, "period": "monthly", "term": null}, "salary_visible": false, "title_keywords": ["data analyst"], "responsibilities": ["management", "data", "big data", "implementation", "design", "quality", "architecture"], "requirements": {"degrees": [], "majors": [], "languages": [], "language_level": [], "hard_skills": ["azure", "data warehouse", "analysis", "tableau", "aws", "data visualization", "spark", "processing"], "soft_skills": ["team player", "fast learner", "mature", "work under pressure"], "languages_combined": []}, "experience_required": {"duration": ["at least 3 years"], "field": ["development", "management", "quality management"]}}, {"job_id": "100003009035301", "location_code": "hk", "company": "Swarovski Hong Kong Ltd", "job_title": "System Engineer (Database)", "description": "Responsibilities:\n\nManage data requests from other business units, understand their business goals and translate unstructured business questions into quantitative metrics.\nTo be proactively in analytic area e.g. analyze user behavioral data to identify patterns, uncover opportunities, facilitate the formulation of business goals, and to improve sales business and reduce churn.\nResponsible for data pipeline, data modeling, validation, cleansing and governance work\nDevelop Dashboards to facilitate efficient data analysis for product performance, customer profiles and campaign effectiveness;\nConduct quantitative analysis and data mining to support management decisions and provide data-driven recommendation\nEngage with Offshore Data Engineer team on ETL works, data modeling and continuously refine data platform offerings\nDrive automation in related processes and improving efficiency\n\nRequirements:\n\nDegree holder in Computer Science, Math & Statistic, Data Science, IT/IS, Engineering or related data disciplines\nAt least 3-5 years of experiences as data analyst, data scientist or data engineer\nHands-on and Solid experiences in the following areas\nReporting: Management Reporting using BI dashboard & Excel\nBI tools (at least one): QlikView, Power BI and Tableau etc\nDatabase: SQL Server, MySQL, any NoSQL DB\nUnderstanding Azure Data Factory, Azure Synapse would be an advantage\nProven experience in process and analysis of data using SQL or python;\nExperience in cross-functional team or Agile/Scrum/Kanban would be an advantage\nStrong communication skills in both written and presentation\nGood command of both spoken and written in English & Chinese\n\nWe Offer\n\nGood Learning Environment\nCompetitive Package + Benefits\nYoung and Energetic Working Environment\nYear-end Bonus\nRegional Exposure\u00a0\nTo apply for this position, please send\u00a0detailed resume with\u00a0expected salary and date available\u00a0by simply clicking on the \u201cAPPLY NOW\u201d bottom.\u00a0\u00a0", "employment_types": ["Full Time", "Permanent"], "selling_points": ["3 years experience in database administration", "Diploma/Degree in Computer Science", "Profound scripting skills in Powershell"], "locations": ["Kowloon City"], "categories": ["Information Technology (IT)", "DBA"], "post_time": "2022-01-10T06:43:37Z", "salary": {"currency": null, "max": null, "min": null, "period": "monthly", "term": null}, "salary_visible": false, "title_keywords": ["system engineer"], "responsibilities": ["business goals", "management", "data", "cleansing", "analysis", "develop", "data analysis", "data mining"], "requirements": {"degrees": ["degree holder"], "majors": ["data science", "engineering", "it", "computer science", "math"], "languages": ["english", "chinese"], "language_level": ["good command"], "hard_skills": ["excel", "qlikview", "bi", "azure", "agile", "analysis", "tableau", "python", "sql", "server", "math"], "soft_skills": ["communication skills", "hands-on", "presentation", "agile"], "languages_combined": [{"language": "english", "language_level": ["good command"]}, {"language": "chinese", "language_level": ["good command"]}]}, "experience_required": {"duration": ["at least 3-5 years"], "field": ["sql", "team"]}}, {"job_id": "100003009048923", "location_code": "hk", "company": "Heep Hong Society", "job_title": "Business Intelligence Data Analyst", "description": "This is an great opportunity to join a well known US insurance company. With many ongoing internal projects across APAC, they are currently looking for a candidate that ideally has data experience in an insurance / reinsurance company. Candidates who have experience in insurance settlements / claims / operations and some basic skills in SQL / VBA / Python will definitely be considered as well.\n\nClient Details\n\nThis is an great opportunity to join a well known insurance company, headquartered in the United States. Founded over 50 years ago and listed on the stock exchange, their revenue in 2020 exceeded USD 16 billion.\n\nThis is an great opportunity to join a well known US insurance company. The candidate will join the the company's team that handles all of APAC's data. With many ongoing internal projects, they are currently looking for a candidate that ideally has data experience in an insurance / reinsurance company. Candidates who have experience in insurance settlements / claims / operations and some basic skills in SQL / VBA / Python will definitely be considered as well.\n\nCandidates must have strong communication skills in both English and Cantonese.\n\nDescription\n\nResponsibilities:\n\nExtract and cleanse data sets\nManage structured and unstructured data\nAnalyse and validate data to ensure data integrity\nDiscuss and identify process efficiency opportunities with different departments\nPrepare regular regulatory and client reports\nAny ad-hoc duties and projects as assigned\n\nProfile\n\nRequirements:\n\nBachelor's degree in Statistics, Computer Science, Actuarial Science or any related degree\n1 to 3 years of experience in insurance or re-insurance industry (settlements, operations, claims, analysis or data driven roles in insurance)\nFoundational knowledge in Python / VBA and SQL\nFresh graduates with relevant internship experience are welcome to apply\nCandidate should be logical, have strong analytic skills and be willing to learn\nExcellent communication skills in both Cantonese and English\n\nJob Offer\n\n16 days annual leave\nGuaranteed bonus\nMedical insurance\nDental insurance\nVery stable and friendly team\nTraining and internal growth opportunities\nMNC and western working environment\n\nTo apply online please click the 'Apply' button below. For a confidential discussion about this role please contact Jacqueline Lung on +852 3602 2471", "employment_types": ["Full Time"], "selling_points": ["Design, implement, deploy, problem diagnosis", "Data analytics, user req., solution design", "Comp. Sci, IT/Info System Degree; min. 3-5yrs' exp"], "locations": ["Ngau Tau Kok"], "categories": ["Information Technology (IT)", "DBA", "Product Management / Business Analyst", "Data Scientist"], "post_time": "2022-01-14T11:32:05Z", "salary": {"currency": null, "max": null, "min": null, "period": "monthly", "term": null}, "salary_visible": false, "title_keywords": ["data analyst"], "responsibilities": ["client reports", "analyse", "ad-hoc duties", "data"], "requirements": {"degrees": ["degree", "bachelor"], "majors": ["statistics", "actuarial science", "computer science"], "languages": ["cantonese", "english"], "language_level": ["excellent"], "hard_skills": ["vba", "analysis", "sql", "analytic skills", "python"], "soft_skills": ["communication skills", "willing to learn", "friendly", "stable", "driven"], "languages_combined": [{"language": "cantonese", "language_level": ["excellent"]}, {"language": "english", "language_level": ["excellent"]}]}, "experience_required": {"duration": ["1 to 3 years"], "field": ["insurance", "insurance industry"]}}, {"job_id": "100003009043393", "location_code": "hk", "company": "Leading Edge Group Limited", "job_title": "Data Engineer", "description": "Responsibilities:\n\n\nResponsible for BOSS (business operation support system) maintenance and support, mainly on web module\nProvide leadership in the design, development, testing, implementation, and maintenance of web-based information systems\nCollecting, identifying, and analyzing business requirements\nCoordinating projects and operation tasks with vendor\nConducting UAT and providing training to internal or external users\n\nRequirements:\n\nBachelor or above in Computer Science/Engineering or other IT related disciplines\n2+ years of work experiences in IT or telecommunication industry\nExperience in business support systems such as CRM, Order Processing, experience in web-based application and API is an advantage\nExperience in using Google Analytics, Drupal, Vue, React\nGood knowledge on HTML, CSS, JavaScript, SQL, PHP, JSON, Python\nFamiliar with DBMS and software development lifecycle. Experience in development or maintenance of backend service and database procedure is an advantage\nPositive, persistent, \u201ccan do\u201d personality, passionate with continuous improvement\nGood verbal and written English and Chinese. Fluent Putonghua is a plus\nCandidates with less experience will be considered as Application Engineer\n\nInterested parties please send your full resume with current & expected salary by clicking \"Apply Now\".\u00a0\u00a0\n\nAll personal data provided will be used for consideration of your job application only.", "employment_types": ["Full Time", "Permanent"], "selling_points": ["Year of IT Experience: 1 year or above", "Fields of Study : Computer Engineering related", "Knowledge, skill and experiences on Python or SQL"], "locations": ["Tsim Sha Tsui"], "categories": ["Information Technology (IT)", "Application Specialist - Software", "DBA", "Software Development"], "post_time": "2022-01-12T11:27:51Z", "salary": {"currency": null, "max": null, "min": null, "period": "monthly", "term": null}, "salary_visible": false, "title_keywords": ["data engineer"], "responsibilities": ["business operation", "uat", "maintenance", "systems", "implementation", "design", "testing"], "requirements": {"degrees": ["bachelor"], "majors": ["related disciplines", "it", "engineering", "computer science"], "languages": ["putonghua", "english", "chinese"], "language_level": ["fluent", "good"], "hard_skills": ["google analytics", "plus", "web", "react", "php", "maintenance", "html", "sql", "dbms", "javascript", "order processing", "python", "css"], "soft_skills": ["passionate", "persistent", "positive"], "languages_combined": [{"language": "putonghua", "language_level": ["fluent"]}, {"language": "english", "language_level": ["good"]}, {"language": "chinese", "language_level": ["good"]}]}, "experience_required": {"duration": ["2+ years"], "field": ["maintenance", "business support", "development", "it", "order processing", "database"]}}, {"job_id": "100003009047474", "location_code": "hk", "company": "WiZ Connected Lighting Co. Limited", "job_title": "Backend Data Engineer", "description": "At Swarovski, where innovation meets inspiration, our people desire to explore, experience, and create. We are looking for a System Engineer (Database) where you will get a chance to work in a rewarding role within a diverse team that is pushing boundaries. Be part of a truly iconic global brand, learn and grow with us. We\u2019re bold and inventive, revealing astonishing things like no one else can. A world of wonder awaits you.\n\n\u00a0About the job\n\nBased in Hong Kong SAR, work in a global team to provide and represent IT infrastructure services to Asia Pacific and support to worldwide locations as necessary.\nAdministrate and support Microsoft SQL server, SAP Hana and Oracle database solutions.\nDevelop, monitor, troubleshoot, tune and execute database related activities as required.\nProvide day-to-day support and services on database areas according to Corporate standards and policies.\nParticipate in corporate project implementation and support.\n\nBy applying this job, I understand and accept the principles of personal data protection, please visit the following link to find out more about Data Protection Consent Statement. https://www.swarovskigroup.com/S/careers/data_protection_consent_statement.en.html\u00a0\n\n\nAbout you\n\nWe are looking for a unique and amazing talent, who brings along the following:\n\nDiploma/Degree in Computer Science, or related discipline.\nAt least 3 years experience in database administration.\nHands-on experience in installing, patching and performance tuning on Microsoft SQL Server.\nProfound scripting skills in Powershell and optional in Perl, python and bash shell.\nExposure to SAP HANA (with basic understanding on SAP application), and some knowledge on Oracle are added advantages.\nBasic understanding of OS (Linux and/or Windows) and network technology.\nExperience with multinational company is an added advantage.\nStrong service orientation and be a team player to work closely with the Corporate IT infrastructure support team based in HK.\nAble to work independently and possess good analytical and problem-solving skills.\nGood command of written and spoken English, Mandarin is highly preferable.\nSome traveling is required.\n\nAbout Swarovski\n\nSwarovski is a Wonderlab where magic and science meet.\n\nSwarovski unifies all parts of its organization under one spellbinding idea and brings forward a wondrous new world of crystal craftsmanship. Founded in 1895 in Austria, the company designs, manufactures and sells the world\u2019s highest quality crystal, genuine gemstones, Swarovski Created Diamonds and zirconia, jewelry, and accessories, as well as crystal objects and home accessories. Together with its sister companies Swarovski Optik (optical devices) and Tyrolit (abrasives), Swarovski Crystal Business forms the Swarovski Group.\n\nA responsible relationship with people and the planet has always been an integral part of Swarovski\u2019s heritage. This manifests today in the company\u2019s well-established sustainability agenda with youth-focused education programs and foundations to promote human empowerment and conserve natural resources to achieve positive social impact.", "employment_types": ["Full Time"], "selling_points": ["Backend Data", "Cloud Operations", "Cloud IoT Data Analytics"], "locations": ["Kowloon Bay"], "categories": ["Information Technology (IT)", "DBA"], "post_time": "2022-01-14T03:14:19Z", "salary": {"currency": null, "max": null, "min": null, "period": "monthly", "term": null}, "salary_visible": false, "title_keywords": ["data engineer"], "responsibilities": ["it infrastructure", "data", "policies", "monitor", "implementation", "quality", "develop", "installing", "troubleshoot", "database", "personal data", "administration"], "requirements": {"degrees": ["diploma", "degree"], "majors": ["computer science"], "languages": ["english", "mandarin"], "language_level": ["good command"], "hard_skills": ["linux", "no", "infrastructure support", "basic", "sap", "perl", "html", "bash", "os", "powershell", "microsoft sql server", "python", "problem-solving skills", "oracle"], "soft_skills": ["work independently", "responsible", "focused", "bold", "unique", "diverse", "hands-on", "troubleshoot", "problem-solving skills", "team player", "genuine", "positive"], "languages_combined": [{"language": "english", "language_level": ["good command"]}, {"language": "mandarin", "language_level": ["good command"]}]}, "experience_required": {"duration": ["at least 3 years"], "field": ["sql", "multinational company", "database", "administration"]}}, {"job_id": "100003009043336", "location_code": "hk", "company": "Wang On Properties Limited", "job_title": "Data Analyst", "description": "Responsibilities:\n\nDesign, implementation, deployment and problem diagnosis of the data analytics solutions\nEnsure the implementation process are followed for each project and task\nWork closely with users and project team to understand requirements are met\nPrepare documentation on user requirements, solution design, and user guide\nProject are deliver on-time to the standard required and within the constraints of the delivery process\nCommunicate and manage proactively on issues affecting delivery\n\nRequirements:\n\nUniversity graduate in Computer Science, Information Technology / Information System or a related discipline\nAt least 3-5 years' experience as data analyst, data scientist or data engineer\nHands-on and solid experiences in the following areas: (i)Reporting: Management Reporting using BI dashboard & Excel;(ii) BI tools (at least one): QlikView, Power BI; (iii)Database: SQL Server, MySQL, any NoSQL DB\nUnderstanding Azure Data Factory, Azure Synapse would be an advantage\nProven experience in process and analysis of data using SQL or python\nExperience in cross-functional team or Agile/Scrum/Kanban would be an advantage\nStrong communication skills in both written and presentation\nGood command of both spoken and written in English & Chinese\n\nWe provide equal employment opportunities to all employees and applicants. For interested parties, please click\u00a0\u201cApply Now\u201d.\n\n(Personal data collected will be used for recruitment purpose only)", "employment_types": ["Full Time", "Permanent"], "selling_points": [], "locations": ["Kowloon Bay"], "categories": ["Information Technology (IT)", "DBA", "Data Scientist"], "post_time": "2022-01-12T10:54:49Z", "salary": {"currency": null, "max": null, "min": null, "period": "monthly", "term": null}, "salary_visible": false, "title_keywords": ["data analyst"], "responsibilities": ["documentation", "implementation", "design", "data"], "requirements": {"degrees": ["university graduate"], "majors": ["computer science", "information technology"], "languages": ["english", "chinese"], "language_level": ["good command"], "hard_skills": ["excel", "qlikview", "bi", "azure", "agile", "analysis", "information system", "python", "sql", "server"], "soft_skills": ["communication skills", "hands-on", "presentation", "agile"], "languages_combined": [{"language": "english", "language_level": ["good command"]}, {"language": "chinese", "language_level": ["good command"]}]}, "experience_required": {"duration": ["at least 3-5 years"], "field": ["sql", "management", "team"]}}, {"job_id": "100003009041904", "location_code": "hk", "company": "GOGO TECH LTD", "job_title": "Specialist, Data Analytics", "description": "Accelerate your career\n\n\nYou will be a core member of our System Support Team to implement & support the mission critical Enterprise System and Infrastructures\u00a0including Oracle DB, Exadata,\u00a0ZDLRA, Mongo, Hadoop and DBF platforms in both Hong Kong and Shanghai office.\nThis is an excellent opportunity to participate in our most challenging project of Enterprise system implementation, supporting and new technologies evaluations.\nYour role\nEvaluate and implement efficient and scalable system management and automation tools to support our Enterprise Applications on Linux & Windows platforms.\u00a0On Job Training will be provided where applicable.\n\nProvide timely support, trouble shooting and implement the fixing in related platforms.\nProvide the Disaster Recovery environment implementation and support.\n\nWho we are looking for\n\nUniversity graduate in Information Technology or related disciplines.\nAdequate and related IT experiences and exposures to Oracle technology e.g. Oracle DB 10g or above.\nJunior IT graduate with strong willingness to learn and to implement new technologies is also welcome.\nProficient spoken and written English, Cantonese and Mandarin is advantage.\n\nInterested parties please send your application letter with detailed resume and expected salary by clicking \"Apply Now\" and quote the reference number on the subject\n\n(Data collected will be used for recruitment purpose only.)", "employment_types": ["Full Time", "Permanent"], "selling_points": ["Start up culture", "Flexible work arrangements", "Excellent learning opportunity"], "locations": ["Kwun Tong"], "categories": ["Information Technology (IT)", "DBA", "Data Scientist"], "post_time": "2022-01-12T04:37:45Z", "salary": {"currency": null, "max": null, "min": null, "period": "monthly", "term": null}, "salary_visible": false, "title_keywords": ["specialist"], "responsibilities": ["evaluate", "management", "implementation"], "requirements": {"degrees": ["university graduate"], "majors": ["related disciplines", "information technology"], "languages": ["cantonese", "english", "mandarin"], "language_level": ["advantage", "proficient"], "hard_skills": ["system implementation", "linux", "oracle"], "soft_skills": ["efficient", "timely"], "languages_combined": [{"language": "cantonese", "language_level": ["advantage", "proficient"]}, {"language": "english", "language_level": ["advantage", "proficient"]}, {"language": "mandarin", "language_level": ["advantage", "proficient"]}]}, "experience_required": {"duration": [], "field": ["related", "it"]}}, {"job_id": "100003009042589", "location_code": "hk", "company": "ESD Services Limited (ESDlife)", "job_title": "System Engineer", "description": "You will:\n\n\nProvide technical support on systems, database, software and provide different type of report to users\nTo participate in setup and maintain infrastructure, system, migration, logs monitoring, backup process\nTo assist in troubleshooting operation issues and incidents\nPerform daily operation, housekeeping and monitoring for server and workstation\nMaintain support tools, database tables, recovery and back up procedures\n\nYou should have/be:\n\n\nDiploma / Degree\u00a0 holder in Information Technology, Information System, Computer\u00a0 \u00a0\nMinimum 2 years on user support and system maintenance\nKnowledge in configuration and administration for MSSQL, MySQL, VM ESXi, Windows server, Linux server, Nginx, IIS\nExperience in .NET/Python/Shellscript technology\nGood troubleshooting skills\nGood communication & problem-solving skills\nSelf-motivated, well organized and able to work independently\nImmediate available an advantage\n\nIn addition, you will be able to:\u00a0\n\nAn attractive and competitive remuneration package;\nReceive training and development opportunities\n\nSalary and benefit will commensurate with qualifications and experience.\u00a0\u00a0Interested party, please send in your\u00a0full resume and expected salary\u00a0by clicking the button\u00a0\u2018APPLY NOW\u2019.\n\u00a0\nTo know more about us, please visit our website\nhttps://corporate.esdlife.com\nhttps://ds.esdlife.com/\n\n\nWe are an equal opportunity employer and welcome applications from all qualified candidates. The information provided will be treated in strict confidence and used only for consideration of application for relevant/similar post(s) within the Hutchison Group of Companies.\n\nApplicants not having heard from us within four weeks from the date of this advertisement may consider their application unsuccessful. All personal data of unsuccessful applicants will be destroyed after the recruitment exercise when no longer required.", "employment_types": ["Full Time", "Permanent"], "selling_points": [], "locations": ["Hung Hom"], "categories": ["Information Technology (IT)", "DBA", "Support", "Network & System"], "post_time": "2022-01-12T08:06:02Z", "salary": {"currency": null, "max": null, "min": null, "period": "monthly", "term": null}, "salary_visible": false, "title_keywords": ["system engineer"], "responsibilities": ["software", "troubleshooting", "website", "communication", "maintain", "database", "personal data", "administration", "configuration", "infrastructure", "migration", "setup", "report", "monitoring", "procedures", "maintenance", "technical support", "housekeeping", "systems", "daily operation", "recruitment"], "requirements": {"degrees": ["diploma", "degree"], "majors": ["information technology"], "languages": [], "language_level": [], "hard_skills": ["linux", "no", "maintenance", "information system", "mssql", "iis", "python", "server", "problem-solving skills", "windows server"], "soft_skills": ["self-motivated", "work independently", "confidence", "well organized", "troubleshooting", "communication", "problem-solving skills"], "languages_combined": []}, "experience_required": {"duration": [], "field": []}}, {"job_id": "100003009039285", "location_code": "hk", "company": "Livi Bank Limited", "job_title": "Senior (Manager), System Engineering", "description": "As a key member of the core technology and common services team, our team objective is to provide the standards and best engineering practices to support infrastructure. We have the rare opportunity to redefine banking from a new start. We provide world class practices for the following areas\n\nDatabase engineering standard and support\nNetwork engineering standard and support\nDevSecOps practice and tooling support\nOn premise infrastructure (Linux, Windows, MacOS) standard and support\nCloud infrastructure standard and support\nMiddleware infrastructure standard and support\u00a0\nWe provide full job autonomy to you implementing whatever sensible solutions.\n\nResponsibilities:\n\nHands on database administration\nImplement self servicing infrastructure practices \u2013 e.g. IaaS, DBaaS, FirewallaaS, NetworkaaS\nHands on support network infrastructure for both office network, data center network and cloud infrastructure network\nDevelop scripts and programs to automate system-related operations using automation tools \u2013 e.g. DevOps CICD, Infrastructure as code (Terraform, Kubernetes, etc)\nImplement and support on premise and cloud platforms including servers, storage, containers, network, database, middleware and system management tools\nSoftware, system management tools and server infrastructure with standard designs and configurations\nSupport production infrastructure\nManage system configuration and monitoring\nManage Cloud/On-premises hardware and software inventory and corresponding vendor contracts\nRequirements:\n\nDegree or above with major in Networking, Computer Science, Information Systems or related disciplines\n5 years relevant experience or above\nPreferred certificates in Database Administration\nNice to have certificates in Network related areas\nNice to have certificates in DevOps, Linux, Cloud infrastructure or middleware technologies\nScripting languages (e.g. Shell script, Python, etc)\nInfrastructure as code\nCICD Pipeline knowledge\nStrong passion on taking part in shaping the future of virtual banking through best in class infrastructure services\nProven track records of autonomy and discretion with minimal supervision\nLife long learner and quick learner to new technologies\nTo be a team player, bring best practices to work and have a mindset of continuous improvement\nExcellent command of both spoken and written English and Chinese, including Putonghua\n\nWe offer competitive salary package to the successful candidate.\u00a0 If you are interested in joining this exciting team, please send your full resume including your\u00a0CURRENT\u00a0and\u00a0EXPECTED\u00a0salary for our consideration.\u00a0", "employment_types": ["Full Time", "Permanent"], "selling_points": ["Virtual Bank/ Fintech", "Database engineering", "Excellent Career Development Opportunity"], "locations": ["Quarry Bay"], "categories": ["Banking / Finance", "Retail Banking", "Information Technology (IT)", "DBA", "Network & System"], "post_time": "2022-01-11T09:18:00Z", "salary": {"currency": null, "max": null, "min": null, "period": "monthly", "term": null}, "salary_visible": false, "title_keywords": ["manager"], "responsibilities": [], "requirements": {"degrees": [], "majors": [], "languages": [], "language_level": [], "hard_skills": [], "soft_skills": [], "languages_combined": []}, "experience_required": {"duration": [], "field": []}}, {"job_id": "100003009036482", "location_code": "hk", "company": "Michael Page", "job_title": "Data Engineering Lead", "description": "In this role you will have a specific focus on architecture standardisation and simplification, as well as ownership related to development and creating design, documentation and working with offshore technical team to deliver projects.\n\nClient Details\n\nOur client is conglomerate with a fast-expanding tech platforms.\n\nDescription\n\nLead the database design and working with different teams to choose the best database technologies for the use case\nDatabase optimisation and performance tuning\nBuild the standards and framework, plan the road map\nProvide guidance and implementation on the database monitoring and alerting\n\nProfile\n\nBachelor's degree in Computer Science or related discipline\nMinimum 8 years of experience in managing Oracle database administration/ engineering\nStrong experience in SQL, design, coding, troubleshooting and tuning skills in Oracle\nMust have experience in supporting mission critical production databases\nExperience in scripting using SQL, PL/SQL, shell, JAVA, XML etc would be a plus\nExposure to different Oracle architecture in large scale projects would be a plus\nGood knowledge of Linux, Windows, SAN, Enterprise monitoring/ scheduling tools, Clusters, Virtualization and middleware\n\nJob Offer\n\nCompetitive package\n\nTo apply online please click the 'Apply' button below. For a confidential discussion about this role please contact Connie Mo on +852 2848 9540.", "employment_types": ["Full Time", "Permanent"], "selling_points": ["Major conglomerate", "Lead one of the largest data technology programme", "Competitive Package"], "locations": ["Not Specified"], "categories": ["Information Technology (IT)", "DBA", "IT Project Management / Team Lead", "Network & System"], "post_time": "2022-01-10T10:39:17Z", "salary": {"currency": null, "max": null, "min": null, "period": "monthly", "term": null}, "salary_visible": false, "title_keywords": ["lead"], "responsibilities": ["monitoring", "teams", "implementation", "design", "coding", "troubleshooting", "scheduling", "contact", "database", "plan", "documentation", "databases", "provide guidance", "architecture", "administration"], "requirements": {"degrees": ["degree", "bachelor"], "majors": ["computer science"], "languages": [], "language_level": [], "hard_skills": ["linux", "java", "plus", "sql", "database monitoring", "databases", "documentation", "focus", "pl", "oracle"], "soft_skills": ["focus", "troubleshooting"], "languages_combined": []}, "experience_required": {"duration": ["minimum 8 years"], "field": ["engineering", "troubleshooting", "design", "sql", "database", "administration"]}}, {"job_id": "100003009049366", "location_code": "hk", "company": "HGC Global Communications Limited", "job_title": "Senior DevOps Engineer", "description": "Responsibilities:\n\nBuilding Continuous Integration (CI) and Continuous Delivery (CD) pipelines;\nDriving high levels of automation into those pipelines;\nMentoring and coaching other teams on how to continue to maintain and adjust their pipelines;\nAutomating the configuration and delivery of infrastructure and software releases, and production deployment of new software releases;\nDesign and develop tools and automation to minimize delivery time and increase developer productivity;\nWorking with teams to create runbooks and other operational support documentation to improve operationalization of product releases;\nInvestigating and implementing new software platforms that support service lifecycle operations. E.g. monitoring / telemetry, release management, secret management, automated testing, etc;\nAutomation of operation functions in Python, Shell, and various platform- specific environments.\n\nRequirements:\n\nDegree holder in Computer Science, Information Technology or related disciplines;\nCertificate holder in ITIL / AWS Certified Solutions Architect or equivalent\n5 years' working experience in software delivery and system administration, experience as a database developer or DBA would be advantageous;\nSignificant experience in automating software delivery on public clouds would be advantageous;\nGood knowledge in Git, GitLab, Jenkins, Babnoo, Nexus, Selenium, Ansible, Capistrano, Consul, Terraform, Pack, SOAP-UI, Junit, JIRA, Rally, Docker, Kubernetes, Envoy, Istio, Cucumber, DataDog, Honeycomb, ets;\nCan work independently under limited supervision;\nGood communication skills.\nWe offer competitive salary package and career development opportunity. Free company coach is provided.\u00a0 Interested parties, please quote our reference number and apply with full resume, present and expected salary, by clicking \u201cAPPLY NOW\u201d.\u00a0\n\nWe are an equal opportunity employer and welcome applications from all qualified candidates. Information provided will be treated in strict confidence and only be used for consideration of your application for the relevant post within HGC Global Communications Limited. Personal data provided by job applicants will be used strictly according to our Personal Information Collection Statement, a copy of which will be available upon written request. Information of unsuccessful candidates will be destroyed within six months.", "employment_types": ["Full Time", "Permanent"], "selling_points": ["Drive automation across product lifecycle", "Degree in Computer Science / IT", "5 years' experience in software delivery"], "locations": ["Tsing Yi"], "categories": ["Information Technology (IT)", "DBA", "Product Management / Business Analyst", "Software Development"], "post_time": "2022-01-14T08:31:43Z", "salary": {"currency": null, "max": null, "min": null, "period": "monthly", "term": null}, "salary_visible": false, "title_keywords": ["engineer"], "responsibilities": ["management", "operational support", "software", "configuration", "operations", "infrastructure", "teams", "design and develop", "monitoring", "testing", "maintain", "documentation"], "requirements": {"degrees": ["certificate", "degree holder"], "majors": ["related disciplines", "computer science", "information technology"], "languages": [], "language_level": [], "hard_skills": ["itil", "git", "jenkins", "aws", "ansible"], "soft_skills": ["communication skills", "work independently"], "languages_combined": []}, "experience_required": {"duration": ["5 years"], "field": ["developer", "database", "administration"]}}, {"job_id": "100003009041285", "location_code": "hk", "company": "Robert Walters (HK)", "job_title": "Manager - Advanced Analytics", "description": "The hiring company is one of local financial service comany and would like to hire talents to join their team.\n\nResponsibilities:\n\nPerform data collection and data engineering for Regtech and Customer analytics\nAssist in developing predictive models for Regtech and marketing program\nPerform evaluation on the effectiveness of predictive models\nProvide customer insight, campaign design and tracking reports\n\nRequirements:\n\nUniversity graduate in Computer Science, Applied Statistics, Decision Science, Data Science or in relevant disciplines\nMinimum 5 years working experience in Data Science / Business Analytics from recognized establishments in financial services and/or Fintech related industries\nSolid knowledge of statistical techniques, data modeling, data science, machine learning, analytics\nStrong knowledge on data management and analyst, experience with database such as SQL server, MongoDB, Oracle and Teradata\nStrong knowledge on ETL processes and data product development\nStrong knowledge on model development cycle\nExperience in consumer analytics, business intelligence, customer segmentation, marketing campaign management using SAS, Python, R\nExperience with machine learning, supervised, unsupervised and reinforcement, classification, regression, clustering models\nExperience with data science methodology such as network analysis, pattern recognition, collaborative filtering, natural language process, neural network\nExperience with data visualization using R, Python, Qlik, Tableau is an advantage\nExperience in cloud environment such as AWS, GCP, is an advantage\nGood command of both spoken and written English and Chinese", "employment_types": ["Full Time", "Permanent"], "selling_points": ["Min.5 yrs working exp.in Data / Business Analysis", "Exp with database SQL server, MongoDB, Oracle etc", "Exp with data visualization using R, Python, Qlik"], "locations": ["Not Specified"], "categories": ["Professional Services", "Business Analysis / Data Analysis", "Information Technology (IT)", "DBA", "Data Scientist"], "post_time": "2022-01-12T03:41:36Z", "salary": {"currency": null, "max": null, "min": null, "period": "monthly", "term": null}, "salary_visible": false, "title_keywords": ["manager"], "responsibilities": ["predictive models", "data", "developing", "design", "reports", "data collection", "evaluation", "tracking"], "requirements": {"degrees": ["university graduate"], "majors": ["science", "statistics", "data science", "computer science"], "languages": ["english", "chinese"], "language_level": ["good command"], "hard_skills": ["data management", "sas", "cloud environment", "analysis", "tableau", "python", "sql", "aws", "data visualization", "server", "r", "business intelligence", "oracle"], "soft_skills": ["learning", "collaborative"], "languages_combined": [{"language": "english", "language_level": ["good command"]}, {"language": "chinese", "language_level": ["good command"]}]}, "experience_required": {"duration": ["minimum 5 years"], "field": ["management", "related", "sql", "business", "financial services", "marketing", "database"]}}, {"job_id": "100003009025075", "location_code": "hk", "company": "One Arrow Consulting Asia Limited", "job_title": "Senior Database Administrator / DBA", "description": "\n\nProvide database administration, configuration, tuning, and maintenance, troubleshooting of the MS SQL and Oracle database farm.\nMaintain the database operation including backup and restoration, SQL performance tuning and monitoring usage, etc.\nSupport, monitor and maintain Oracle databases\nParticipate in projects with technical related duties\nProvide advice to the application and infrastructure teams on effective Database services.\nRequirements:\nDegree holder or above in Computer Science or related discipline\n2 years of experience in Oracle database and Linux administration and support\nHands-on experiences on Oracle database installation and administration tasks\nKnowledge in performance tuning and systems development with Unix scripts, and PL/SQL\nProficiency and skillful in Oracle 12c to 19c, and familiar in database recovery methods\nFluent in written English, and excellent communication skills in English and Cantonese", "employment_types": ["Full Time"], "selling_points": ["Database Administrator", "Oracle Database", "Database specialist"], "locations": ["Hung Hom"], "categories": ["Information Technology (IT)", "DBA"], "post_time": "2022-01-06T04:05:45Z", "salary": {"currency": null, "max": null, "min": null, "period": "monthly", "term": null}, "salary_visible": false, "title_keywords": ["administrator"], "responsibilities": ["installation", "maintenance", "configuration", "monitoring", "monitor", "troubleshooting", "infrastructure", "teams", "systems", "communication", "maintain", "provide advice", "database", "databases", "administration"], "requirements": {"degrees": ["degree holder"], "majors": ["computer science"], "languages": ["cantonese", "english"], "language_level": ["excellent", "fluent"], "hard_skills": ["linux", "maintenance", "sql", "databases", "pl", "ms sql", "oracle"], "soft_skills": ["communication skills", "hands-on", "troubleshooting"], "languages_combined": [{"language": "cantonese", "language_level": ["excellent"]}, {"language": "english", "language_level": ["fluent", "excellent"]}]}, "experience_required": {"duration": ["2 years"], "field": ["installation", "database", "administration"]}}, {"job_id": "100003009041546", "location_code": "hk", "company": "Seamatch Asia Limited", "job_title": "Data Analysts / Senior Data Analysts / Trainee Analysts x 20 (updated job description)", "description": "\nOur client is one of the largest online shopping ecommerce platforms in Hong Kong. They are looking for new team members to join their data science teams.\n\nData Analysts / Senior Data Analysts / Trainee Analysts\u00a0\n\n20K (entry levels) to around 60K (senior levels)\n\n\nResponsibilities:\n\nAgile team collaboration in continual development of Company's Azure Cloud data analytics platform, data flow and\u00a0data pipelines\nAI analytics and machine learning tools development\nData mining, data discovery and metadata management for business intelligence (BI), quantitative modeling, machine learning and predictive analytics projects\nData visualization, BI reporting, data dashboard design & development\nRequirements:\n\nDegree holder in IT and data sciences related subjects\nOver or around 3 years of technical experience in data engineering, data warehousing, data analytics or related functional areas\nJunior candidates with good knowledge of current AI and machine learning technology trends are welcome\nFamiliar with data visualization tools such as\u00a0Tableau or\u00a0Power BI\nGood knowledge of Python / R / SQL programming, machine learning algorithms, analytic tools such as Microsoft Power BI, TensorFlow, Tableau, Google\u00a0Analytics, AWS Cloud, etc.\nFluent Chinese and English communication with local team members\n\u00a0\n*** Junior candidates with good knowledge of current AI and machine learning technology trends are welcome", "employment_types": ["Full Time", "Permanent"], "selling_points": ["Data Analyst, Senior Data Analyst, Trainee Analyst", "Data warehousing, data integration, data analytics", "Good sense of SQL logic and data flow required"], "locations": ["Tsim Sha Tsui"], "categories": ["Information Technology (IT)", "Application Specialist - Software", "DBA", "Data Scientist"], "post_time": "2022-01-12T04:01:12Z", "salary": {"currency": null, "max": null, "min": null, "period": "monthly", "term": null}, "salary_visible": false, "title_keywords": ["trainee"], "responsibilities": ["reporting", "management", "visualization", "data", "design", "data mining"], "requirements": {"degrees": ["degree holder"], "majors": ["it"], "languages": ["english", "chinese"], "language_level": ["fluent"], "hard_skills": ["google analytics", "bi", "ai", "data analytics", "tableau", "aws", "sql", "programming", "data visualization", "python", "r"], "soft_skills": ["communication", "learning"], "languages_combined": [{"language": "english", "language_level": ["fluent"]}, {"language": "chinese", "language_level": ["fluent"]}]}, "experience_required": {"duration": ["3 years"], "field": ["related", "engineering"]}}, {"job_id": "100003009039494", "location_code": "hk", "company": "Neat Limited", "job_title": "Data Lead", "description": "At Neat, we\u2019re building a solution that\u2019s friendlier, faster, more modern than a bank. We have users in over 100 countries around the globe, relying on our solutions to manage their business finances.\n\nWant to help us achieve this vision? We\u2019ve built a place where you\u2019ll love doing it!\n\nOur culture of transparency and openness means you\u2019ll have lots of impacts, our test-driven development approach means we move quickly while maintaining super high standards for quality of code and design, and our commitment to your professional growth means you\u2019ll always be learning.\n\nWe are currently looking for a Data Lead who manages and mentors all data scientists and data analysts along with overseeing all data activities. You will look for cost efficient ways to organize, store and analyze data with the goal of creating business value.\n\nWhat You\u2019ll Be Doing:\n\n\nManage the data team.\nLead data mining and collection procedures.\nResponsible for the conception, planning, and prioritizing of data projects.\nInterpret and analyze data problems and guarantee data quality and integrity.\nResponsible for building analytic systems and predictive models as well as experimenting with new models and techniques.\nTest performance of data-driven products.\nVisualize data and create reports.\nEnsure that data projects align with organizational goals.\nUtilize data visualization tools to deliver insights to stakeholders.\nExperiment with new models and techniques.\n\nWe\u2019re Looking For:\u00a0\n\n\nBachelor\u2019s degree in Computer Science, Data Science, Mathematics or related field.\nProven data science experience gained in eCommerce, technology, or start-up environments.\nSolid understanding of machine learning.\nKnowledge of data management and visualization techniques.\nA knack for statistical analysis and predictive modeling.\nSolid knowledge of R, Python and MATLAB.\nExperience with SQL and NoSQL databases.\nProject management experience with collaborating with a wide range of stakeholders from many teams and functions in a fast-paced environment.\nStrong organizational and leadership skills.\u00a0\nExcellent communication skills.\nStrong commercial mindset.\n\nWhat Happens Next?\n\nIf your application is successful, you'll be contacted by our Talent & Culture Team to take part in a video screening and psychometric assessment. If you are a good fit, you will be invited to a video / in person interview with the hiring manager, department head and even some of your colleagues. Lastly, ending the interview process with a culture fit chat with our senior management.\n\nCandidates not contacted within 4 weeks may consider their application unsuccessful. Information provided will be treated in strict confidence and will only be used for recruitment-related purposes. Personal data provided by job applicants will be used strictly in accordance with the employer's personal data policies, a copy of which will be provided immediately upon request.\n\nInterested In Joining Us?\n\nClick here\u00a0to apply now.\n", "employment_types": ["Full Time"], "selling_points": ["Fast-Growing Multicultural Fintech Startup", "Proven Data Science Management Experience", "Flat Structure, Empowerment and Work-Life Balance"], "locations": ["Admiralty"], "categories": ["Professional Services", "Business Analysis / Data Analysis", "Information Technology (IT)", "DBA", "Data Scientist"], "post_time": "2022-01-11T09:55:41Z", "salary": {"currency": null, "max": null, "min": null, "period": "monthly", "term": null}, "salary_visible": false, "title_keywords": ["lead"], "responsibilities": ["predictive models", "visualization", "data", "quality", "design", "communication", "data mining", "senior management", "personal data", "maintaining", "teams", "reports", "analyze data", "cost", "management", "procedures", "policies", "analysis", "systems", "project management", "recruitment", "databases", "planning"], "requirements": {"degrees": ["degree", "bachelor"], "majors": ["data science", "computer science", "mathematics"], "languages": [], "language_level": [], "hard_skills": ["data management", "statistical analysis", "r", "python", "sql", "goal", "project management", "matlab", "data visualization", "data mining", "code", "databases"], "soft_skills": ["efficient", "communication skills", "confidence", "responsible", "fast-paced environment", "organizational", "leadership skills", "interested in", "integrity", "project management", "learning", "driven", "prioritizing"], "languages_combined": []}, "experience_required": {"duration": [], "field": ["ecommerce", "project management", "sql"]}}, {"job_id": "100003009049153", "location_code": "hk", "company": "Connexe Search Limited", "job_title": "Digital Business Analyst", "description": "Our client is a well-known financial company. They are urgently looking for a high caliber candidate to join their dynamic team.\n\nResponsibilities:\n\nGather business requirements and delivery expectations from different stakeholders\nWrite up user story and other business documents\nConduct Use Acceptance Testing to be in line with user story\nDevelop and manage relationships with business users to ensure total satisfaction\n\n\u00a0Requirements:\n\nMinimum 2 years of relevant experience as business analyst, preferably from financial industry\nTechnical background with understanding of Agile methodology\nExperience in digital application management\nCandidates with more experiences will be considered for more senior positions\n\nPlease click Apply Now or email your full resume in MS Word format\u00a0quoting the job reference RT20221013 in the subject field. Your interest will be treated in strict confidence. Only shortlisted candidates will be notified.", "employment_types": ["Full Time"], "selling_points": ["Business Analyst", "Digital project delivery", "Digital application management"], "locations": ["Not Specified"], "categories": ["Information Technology (IT)", "DBA"], "post_time": "2022-01-14T08:11:10Z", "salary": {"currency": null, "max": null, "min": null, "period": "monthly", "term": null}, "salary_visible": false, "title_keywords": ["business analyst"], "responsibilities": ["develop", "testing"], "requirements": {"degrees": [], "majors": [], "languages": [], "language_level": [], "hard_skills": ["agile", "ms word"], "soft_skills": ["confidence", "agile"], "languages_combined": []}, "experience_required": {"duration": ["minimum 2 years"], "field": ["management", "financial industry", "business", "relevant experience", "digital"]}}, {"job_id": "100003009038010", "location_code": "hk", "company": "Delken Group Limited", "job_title": "Project Manager (Digitalisation Office)", "description": "Our client is a well-known banking and financial company, they are currently seeking for a Project Manager (Digitalisation Office) to join their team.\nResponsibilities:\n\nReporting to the Data Lead and PMO Lead, you will be responsible for delivery of multiple data projects within digitalisation programme.\nYou will work with teams of technologists with specialities in Data platforms, Data Governance, Data Engineering and Data Analytics. As the project manager, you plan, execute and monitor projects including quality assurance and risk management, manage budget and submit progress reports to business and technology stakeholders.\nEngage stakeholders through clear communication, manage their understanding, expectations and involvement in the data programme.\u00a0\nWork with Digitalisation Programme PMO to support programme level reporting\u00a0\nKeep abreast of relevant technological advancements, and development of regulatory compliance and industry best practices for continuous improvement\u00a0\nRequirements:\n\nUniversity degree in computer science, software engineering or related fields\u00a0\nAt least five years of experience in project / programme management\u00a0\nExperience in managing data projects is a must\u00a0\nExperience in managing cross departmental projects in enterprise environment is preferable\u00a0\nExperience in managing large scale data infrastructure project is preferable\u00a0\nGood knowledge of agile methodology and DevSecOps\u00a0\nExposure in latest technology in Big data, AI, Machine Learning and API, both commercial and open source\u00a0\nTeam management and problem-solving skills; self-motivated, creative and with proven track record in developing and driving firm-wide initiatives\u00a0\nAbility to do researches and analyses thoroughly and resourcefully\u00a0\nStrong interpersonal, communication, writing and presentation skills\u00a0\nInterested candidates, please send your resume (MS Word document) including employment history, present and expected salary to us.\nFor more jobs, please visit our website:\u00a0www.delken.com.hk.\u00a0\n\n(All personal data submitted will be treated in strict confidential and used for recruitment purposes only.)\n", "employment_types": ["Full Time", "Permanent"], "selling_points": ["Project / programme management exp in data project", "Managing large scale data infrastructure project", "Knowledge of agile methodology & DevSecOps"], "locations": ["Central"], "categories": ["Information Technology (IT)", "DBA", "IT Project Management / Team Lead", "Data Scientist"], "post_time": "2022-01-11T04:34:00Z", "salary": {"currency": null, "max": null, "min": null, "period": "monthly", "term": null}, "salary_visible": false, "title_keywords": ["project manager"], "responsibilities": ["reporting", "management", "data", "progress reports", "budget", "monitor", "teams", "quality", "compliance", "communication", "plan"], "requirements": {"degrees": ["university degree"], "majors": ["software engineering", "computer science"], "languages": [], "language_level": [], "hard_skills": ["problem-solving skills", "agile", "ai"], "soft_skills": ["self-motivated", "agile", "communication", "presentation skills", "learning", "problem-solving skills", "creative", "interpersonal"], "languages_combined": []}, "experience_required": {"duration": ["at least five years"], "field": ["management", "infrastructure"]}}, {"job_id": "100003009034130", "location_code": "hk", "company": "ADECCO", "job_title": "Database Administrator (Oracle)", "description": "Our client is a MNC Tech Corporation, they are looking for Database Operations Administrator with Oracle DB experience to join their team.\n\n\nResponsibilities\nPerform daily operation and reporting\nComplete configuration, installation and support of equipment under Microsoft Windows and Linux in virtualized environments\nTroubleshoot and resolve server, storage and network related issues by providing both onsite and remote/standby support\nMaintain software applications, operating systems and database systems\nPerform regular health checking and system resources monitoring\nIT Support Services on highly virtualized Data Centers\nOracle Database operation support and administration\nRequirements\n\nHigher Diploma in Software Engineering, Computer Science or related disciplines\nMinimum 5 years\u2019 relevant experience in IT infrastructure Project and Support\nSolid support experience on Oracle database 12c administration\nWorking knowledge of Windows Servers, VMware, Anti-virus and other various software applications\nWith Oracle Certified Professional and VMware certified is advantageous\nKnowledge on Oracle database features, such as Data Guard, data encryption is a must\nKnowledge on VPN & Network support\nGood team player, self-motivated with good communication skills and working attitude\nGood command in both spoken and written English and Chinese\nImmediately available is preferred\n\nInterested parties, please\u00a0CLICK HERE\u00a0to apply the position via Adecco website with your CV.\u00a0Please note that only shortlisted candidates will be notified. All information gathered will be treated in strict confidence and solely used for recruitment purposes.", "employment_types": ["Full Time", "Permanent", "Contract"], "selling_points": ["Experience in Oracle Database Administration", "Good interpersonal skills, Mature and Stable", "Excellent Work Environment"], "locations": ["Cheung Sha Wan"], "categories": ["Information Technology (IT)", "DBA", "Support", "Network & System"], "post_time": "2022-01-10T02:45:42Z", "salary": {"currency": null, "max": null, "min": null, "period": "monthly", "term": null}, "salary_visible": false, "title_keywords": ["administrator"], "responsibilities": ["administration", "reporting", "installation", "software", "data", "configuration", "systems", "daily operation", "checking", "monitoring", "support services", "maintain", "troubleshoot", "database", "operating systems"], "requirements": {"degrees": ["diploma"], "majors": ["related disciplines", "software engineering", "computer science"], "languages": ["english", "chinese"], "language_level": ["good command"], "hard_skills": ["vmware", "servers", "vpn", "oracle"], "soft_skills": ["communication skills", "good team player", "self-motivated"], "languages_combined": [{"language": "english", "language_level": ["good command"]}, {"language": "chinese", "language_level": ["good command"]}]}, "experience_required": {"duration": ["minimum 5 years"], "field": ["infrastructure", "it", "relevant experience", "database", "administration"]}}, {"job_id": "100003009038120", "location_code": "hk", "company": "Hong Kong International School", "job_title": "PowerSchool Administrator", "description": "The PowerSchool System Specialist (PSSS) at HKIS will be responsible for leading the technical administration of PowerSchool SIS, PowerTeacher Pro, PowerScheduler, and any additional PowerSchool modules. They will also manage the data integration with other HKIS information systems (Schoology, Schoolsbuddy, FinalSite, etc.). The PSSS helps inform school leadership about enrollments, grading, scheduling, and the development of our system. They provide training to all faculty and staff. Additionally, the position works to extend PowerSchool functionality with an eye towards enhancing user experience, fluid communications from HKIS to students/parents, the inclusion of non-academic activities, and improved data analytics.\nRequirements:\nAssociate degree in Computer Science, Database Administration, Data Analytics, Information Systems or relevant field and/or equal experience and/or certifications preferred.\n3+ years of practical in-depth experience with SQL/Oracle\n2+ years of web development\nExperience:\nAt least 5 - 8 years of PowerSchool experience with knowledge of all aspects of PS including but not limited to the creation, maintenance of custom pages, reports, plugins, registration process, scheduling, grading, APIs, PowerTools, PowerTeacher, GradeBook, Parent/Student Portal, storing grades, EOY procedures, report card setup and training and integration with other LMS (preferably Schoology) and 3rd party tools\nMust have strong technical expertise in PowerSchool, SQL, DBA, and Microsoft Office Suite (including Excel formulas) preferred\nExperienced in data collection of raw data files across multiple departments and multiple systems for data requests for data analyses\nHighly detail-oriented with the ability to manage daily activities and short/long term projects under pressure with accuracy and responsiveness\nExperience with school admissions and fundraising software preferred\nSkills:\nSolid English communication skills, verbal and written. Cantonese and Mandarin are also an advantage\nExcellent customer service and communication skills.\nAbility to work with people of various backgrounds with all levels of technical knowledge\nAbility to work well individually and in a team\nWilling to work with and support our students and learning community\nWilling to work outside office hours when required, especially during busy periods\nAbility to handle confidential files and information in a professional manner\n\nWe invite you to learn more about our school and discover for yourself career opportunities in our remarkable HKIS community at www.hkis.edu.hk\n\nInterested candidates please forward your updated resume together with a cover letter and references by clicking \"Apply Now\"\n\nWe look forward to hearing from you!", "employment_types": ["Full Time", "Permanent"], "selling_points": ["Associate degree in Computer Science", "3+ years of practical in-depth experience with SQL", "At least 5 - 8 years of PowerSchool experience"], "locations": ["Not Specified"], "categories": ["Information Technology (IT)", "DBA", "IT - Webmaster / SEO", "Others"], "post_time": "2022-01-11T05:17:20Z", "salary": {"currency": null, "max": null, "min": null, "period": "monthly", "term": null}, "salary_visible": false, "title_keywords": ["administrator"], "responsibilities": ["provide training", "software", "maintenance", "data", "systems", "procedures", "user experience", "professional manner", "communication", "scheduling", "customer service", "reports", "database", "data collection", "report", "setup", "administration"], "requirements": {"degrees": ["associate degree"], "majors": ["computer science"], "languages": ["cantonese", "english", "mandarin"], "language_level": ["advantage"], "hard_skills": ["excel", "inform", "web development", "hkis", "maintenance", "data analytics", "sql", "microsoft office suite", "integration", "oracle"], "soft_skills": ["communication skills", "under pressure", "responsible", "detail-oriented", "customer service", "learning", "leadership"], "languages_combined": [{"language": "cantonese", "language_level": ["advantage"]}, {"language": "english", "language_level": []}, {"language": "mandarin", "language_level": ["advantage"]}]}, "experience_required": {"duration": ["at least 5 - 8 years", "3+ years"], "field": ["training", "maintenance", "sql", "database", "administration"]}}, {"job_id": "100003009037181", "location_code": "hk", "company": "Centaline Data Technology Limited", "job_title": "Data Analyst / Data Programmer (5-day Work)", "description": "Responsibilities:\n\n* Analyse data from property management system;\n\n* Generate and disseminate reports;\n\n* Implement data flow;\n\n\n\nRequirements:\n\n* University degree or above, major in IT or statistics related discipline;\n\n* 1-4 years working experience in handling data;\n\n* Good knowledge in Python;\n\n* Knowledge on Software development Life Cycle, MSSQL (SSMS, SSIS), ETL, data cleansing;\n\n* Knowledge in Tableau is an advantage;\n\n* With strong sense of responsibility, self-motivated, committed, strong analytical and problem solving skills, good interpersonal & communication skills, team player;\n\n* Detail oriented and well organized;", "employment_types": ["Full Time", "Permanent"], "selling_points": ["Quarterly Bonus / Medical / Education Allowance", "Databank Management", "Data Migration and Analysis"], "locations": ["Tsim Sha Tsui"], "categories": ["Information Technology (IT)", "DBA", "Software Development", "Data Scientist"], "post_time": "2022-01-11T01:59:41Z", "salary": {"currency": null, "max": null, "min": null, "period": "monthly", "term": null}, "salary_visible": false, "title_keywords": ["programmer", "data analyst"], "responsibilities": ["management", "data", "reports", "analyse"], "requirements": {"degrees": ["degree or above"], "majors": ["it", "statistics"], "languages": [], "language_level": [], "hard_skills": ["python", "problem solving skills", "tableau", "mssql"], "soft_skills": ["communication skills", "self-motivated", "sense of responsibility", "detail oriented", "well organized", "committed", "analytical and problem solving skills", "team player", "interpersonal"], "languages_combined": []}, "experience_required": {"duration": ["1-4 years"], "field": []}}, {"job_id": "100003009039015", "location_code": "hk", "company": "CITIC Telecom International Holdings Limited", "job_title": "System Support Engineer (Business Support Systems)", "description": "Responsibilities:\n\nSystem deployment, maintenance and support for Telecom Business Support Systems (BSS)\nDevOps tools introduction, development and integration\nDefine systems\u2019 O&M requirements, optimize systems\u2019 architecture and deploy innovative O&M technique\n\nRequirements:\n\nBachelor degree or above in Computer Science or related disciplines\nMinimum 3 years\u2019 experience in IT system development, testing or maintenance\nFamiliar with the functions and architectures of business support IT systems: Billing, CRM and Order system etc.\nFamiliar with\u00a0popular IT maintenance techniques\u00a0e.g. Docker, K8s, Prometheus, ELK, Jenkins, etc.\u00a0\nGood coding/database skills\u00a0in at least two of below areas: Java, PL/SQL, Python, Oracle, MySQL, etc.\nExperience in Oracle/MySQL DBA would be an advantage\nExperience in\u00a0Big Data, K8s development and maintenance would be an advantage\nGood command in both spoken and written English and Chinese (Cantonese & Mandarin)\nGood team player with a strong sense of integrity\nWilling to learn and able to work independently with minimum supervision\u00a0 \u00a0\n\nFringe Benefits:\n\nOn-the-job training\nDouble pay\nAttractive performance bonus\nTransportation allowance\nMedical & dental insurance\nFree meals\nFree shuttle bus service\nTraining subsidies\nStaff discount\n\nWe offer competitive salary and benefit package including double pay, medical and dental benefits, 5-day work, 14 days paid annual leave and free shuttle bus service to the capable candidate. If you are interested, please immediately send your application stating\u00a0your current & expected salary and date availability with full resume\u00a0to\u00a0Human Resources Department\u00a0by email by clicking \"Apply Now\". Please clearly indicate the applied position and reference number on your application.\n\nAll personal data received will be treated strictly confidential and will be used for employment related purpose only.", "employment_types": ["Full Time", "Permanent"], "selling_points": ["Business Support Systems support and maintenance", "IT position in Telecom Industry", "Double Pay, Bonus, 5-day work, Medical & Dental"], "locations": ["Kwai Fong"], "categories": ["Information Technology (IT)", "DBA", "Support", "IT Management"], "post_time": "2022-01-11T08:23:24Z", "salary": {"currency": null, "max": null, "min": null, "period": "monthly", "term": null}, "salary_visible": false, "title_keywords": ["system support", "engineer"], "responsibilities": ["systems", "architecture", "maintenance", "deploy"], "requirements": {"degrees": ["degree or above", "bachelor"], "majors": ["related disciplines", "computer science"], "languages": ["cantonese", "english", "chinese", "mandarin"], "language_level": ["good command"], "hard_skills": ["java", "jenkins", "maintenance", "sql", "python", "pl", "oracle"], "soft_skills": ["good team player", "willing to learn", "integrity", "work independently"], "languages_combined": [{"language": "cantonese", "language_level": ["good command"]}, {"language": "english", "language_level": ["good command"]}, {"language": "chinese", "language_level": ["good command"]}, {"language": "mandarin", "language_level": ["good command"]}]}, "experience_required": {"duration": ["minimum 3 years"], "field": ["development", "it system development", "maintenance", "testing"]}}, {"job_id": "100003009043954", "location_code": "hk", "company": "Pinpoint Asia Limited", "job_title": "Data Strategy and Architecture Leader", "description": "Our client, a large well-known enterprise, with a state-of-the-art technology setup, is looking for a Data Strategy and Architecture Leader to lead their enterprise-wide Data Strategy, Governance, and Architecture. The selected candidate will be leading the Enterprise Architect in building Data Architecture for the whole firm. This role is a senior leadership position working closely with the firm senior management.\n\nResponsibilities:\n\nDefine and manage the Data Governance Framework which creates a data-centric strategy for the whole organization.\nLead the definition of the enterprise data models, policies, and standards that support and align with the defined EA roadmap.\nDefine key metrics to measure performance, quality, clarity, accessibility, and compliance.\nWork with the senior leaders in defining the technology strategy, standard, and policy in data.\nEstablish and maintain core data models, information standards, and data management lifecycle controls.\nProvide End-to-end data design and management for data acquisition and processing, data quality, and governance for the Enterprise Data platform.\nDevelop and improve data governance standards including records management, data quality, metadata, modeling, and data provisioning.\n\nRequirements:\n\nAt least 12 years of working experience in the IT Data Management, Data Governance, and Data Architecture area.\nProven experience in establishing a data governance model and framework.\nUnderstanding of Enterprise Architecture concepts.\nAbility to lead in architecture analysis, modeling, and design ensuring alignment with business and Architecture strategy. This includes the ownership of the architecture artifacts, controlling the architectural integrity, and managing critical architectural trade-offs\nStrategic thinking and communication, which able to coach and lead all levels of people.\nStrong leadership and influencing skills. Strong communications and negotiation skills to speak with key stakeholders.\nBachelor or Master's degree from a reputable University.\nExcellent communication skills in English.\n\nIf this outstanding opportunity sounds like your next career move, please send your resume in Word format to Danny Kwan at resume(at)pinpointasia(dot)com and put Data Strategy and Architecture Leader in the subject header.\n\nData provided is for recruitment purposes only.", "employment_types": ["Full Time", "Permanent"], "selling_points": ["Define Firmwise Architecture", "Leadership Position", "Large Enterprise Organization"], "locations": ["Not Specified"], "categories": ["Information Technology (IT)", "DBA", "IT Management", "Data Scientist"], "post_time": "2022-01-13T02:35:15Z", "salary": {"currency": "HKD", "max": 119999, "min": 90000, "period": "monthly", "term": null}, "salary_visible": true, "title_keywords": [], "responsibilities": ["management", "data", "policies", "compliance", "quality", "design", "develop", "maintain"], "requirements": {"degrees": ["degree", "bachelor", "master"], "majors": [], "languages": ["english"], "language_level": ["excellent"], "hard_skills": ["analysis", "data management", "word"], "soft_skills": ["communication skills", "strategic thinking", "integrity", "communication", "negotiation skills", "leadership"], "languages_combined": [{"language": "english", "language_level": ["excellent"]}]}, "experience_required": {"duration": ["at least 12 years"], "field": ["management", "it"]}}, {"job_id": "100003009035797", "location_code": "hk", "company": "Macroview Telecom Limited", "job_title": "Cloud Manager", "description": "Job Description\n\nLeading technical engineers / or operational teams to plan, design, implement and support the public/private cloud infrastructure and platform services\nUnderstand industry trends and make recommendations related to the use and security of cloud services and technologies.\nWork with cross-functional teams to deliver the best Customer Experience\nCollaborate with Pre-sales to help on solution design and implementation\nIncorporate strong systems engineering principles to ensure the security, reliability, and scalability of infrastructure components to achieve better operational performance.\nLead cloud planning and design of new technologies and enhancement of existing technologies.\nWork with technology partners and vendors to fulfill customer's SLA, and improve processes related to operations and support, as well as the right technical support experience.\n\nRequirements\n\nBachelor's degree or equivalent (minimum 5 years work experience)\nMore than 3 years of experience in Public/Private cloud project design, implementation, and support.\nExtensive experience in cloud automation and scripting with the mindset of automating IT operations, with experience demonstrating this is advantaged.\nAt least 1 Cloud Certification \u2013 Associate or Professional\nGood working attitude with strong problem solving, communication & interpersonal skill\nGood problem solving, good project planning and management skills\nGood communication and presentation skills in both written and verbal English and Cantonese, which will be key in driving customer and internal communications.\n\nWe offer attractive remuneration package, medical benefits and marriage leave to the right candidate. Interested parties please send full resume with expected salary by clicking \"Apply Now\"\n\n\nAll information collected will be used for recruitment purpose only.\nTo know more about Macroview, please visit: http://www.macroview.com", "employment_types": ["Full Time", "Permanent"], "selling_points": ["Bachelor's degree or equivalent", "More than 3 years of experience", "Leading technical engineers / or operational teams"], "locations": ["Not Specified"], "categories": ["Information Technology (IT)", "DBA", "IT Project Management / Team Lead", "Network & System"], "post_time": "2022-01-10T08:27:04Z", "salary": {"currency": null, "max": null, "min": null, "period": "monthly", "term": null}, "salary_visible": false, "title_keywords": ["manager"], "responsibilities": ["make recommendations", "collaborate with", "technical support", "operations", "infrastructure", "teams", "implementation", "design", "systems", "plan", "cross-functional teams", "planning"], "requirements": {"degrees": ["degree", "bachelor"], "majors": [], "languages": ["cantonese", "english"], "language_level": ["good"], "hard_skills": ["problem solving"], "soft_skills": ["good working attitude", "interpersonal skill", "problem solving", "communication", "presentation skills", "extensive"], "languages_combined": [{"language": "cantonese", "language_level": ["good"]}, {"language": "english", "language_level": ["good"]}]}, "experience_required": {"duration": ["3 years", "minimum 5 years"], "field": ["it operations", "design"]}}, {"job_id": "100003009034843", "location_code": "hk", "company": "Osmium Consulting Group Limited", "job_title": "Data Analyst / Data Engineer ( Up to $40K )", "description": "Responsibilities:\n\nData warehousing and data extract/transform/load (ETL) integration in cloud and on-premise environments\nPerform Data Analytic, Data Visualization, Data Modeling, and Dashboard Building\nTroubleshoot issues on BI reports and dashboards\nWorking with stakeholders across all functions, to understand their needs and how to factor them into the automation and analytics models\nInterpret information requirements from business users and translating them into reporting solutions\n\nRequirements:\n\nDegree in Computer Science/ Engineering/ Information Systems/ Statistics or a related discipline\n1+ years of experience in business intelligence and data analytics\nProficient in converting business requirements into data model solutions and visualization\nStrong commercial and practical experience with data visualization, dashboard, and report development\nExperience in SQL, Power BI, Python is a must; knowledge in tools like AWS would also be an advantage\nHigh energy, self-motivation, and ability to thrive in a fast-paced working environment with a customer-focused attitude\nProficient in spoken and written English is necessary\nCandidates with more experience will be considered for other position", "employment_types": ["Full Time", "Permanent"], "selling_points": ["Data Analytics | Data Engineer | MNC | FinTech", "Python | Power BI | Dynamic and Friendly Culture", "5 Day Work | Attractive Package | Large Scale Firm"], "locations": ["Central"], "categories": ["Professional Services", "Business Analysis / Data Analysis", "Information Technology (IT)", "DBA", "Data Scientist"], "post_time": "2022-01-10T04:24:55Z", "salary": {"currency": "HKD", "max": 44999, "min": 25000, "period": "monthly", "term": null}, "salary_visible": true, "title_keywords": ["data analyst", "data engineer"], "responsibilities": ["warehousing", "reporting", "visualization", "data", "reports", "troubleshoot"], "requirements": {"degrees": ["degree"], "majors": ["statistics", "engineering", "computer science"], "languages": ["english"], "language_level": ["proficient"], "hard_skills": ["bi", "data analytics", "aws", "sql", "data visualization", "python", "business intelligence"], "soft_skills": ["self-motivation", "customer-focused"], "languages_combined": [{"language": "english", "language_level": ["proficient"]}]}, "experience_required": {"duration": ["1+ years"], "field": ["sql", "commercial", "development", "business"]}}, {"job_id": "100003009033408", "location_code": "hk", "company": "HKT", "job_title": "Technical Officer", "description": "Your Role\n\nParticipate in Workplace Transformation Project (O365 Management)\nUtilize Linux (Oracle & Redhat), Virtualization technologies (VMware, Oracle & RedHat), Monitoring/Operational intelligence products (SolarWinds) and Backup products (Veeam)\nProvide technical support and conduct troubleshooting on AD, On-premises Exchange server and O365 cloud services.\nManage the IT inventory for hardware & software, and other IT-related services.\n\nTo succeed in this role\n\nHigher Diploma holder in Computer Science or Information Technology or related disciplines.\nFresh graduates welcome.\n1\u00a0year of system administration experience will be an advantage\nKnowledge\u00a0in (Windows & Linux Server), O365, VMWare ESXi, and data recovery solutions will be an advantage\nGood communication skills, hard-working and can work independently.\nGood attitude and team working", "employment_types": ["Full Time"], "selling_points": [], "locations": ["Lai Chi Kok"], "categories": ["Information Technology (IT)", "DBA", "Support", "Network & System"], "post_time": "2022-01-09T14:56:19Z", "salary": {"currency": null, "max": null, "min": null, "period": "monthly", "term": null}, "salary_visible": false, "title_keywords": ["technical officer"], "responsibilities": ["management", "software", "data", "technical support", "monitoring", "troubleshooting", "communication", "hardware", "it inventory", "administration"], "requirements": {"degrees": ["higher diploma holder"], "majors": ["related disciplines", "computer science", "information technology"], "languages": [], "language_level": [], "hard_skills": ["o365", "linux", "oracle", "vmware", "hardware", "server", "exchange"], "soft_skills": ["communication skills", "work independently", "troubleshooting", "hard-working", "team working"], "languages_combined": []}, "experience_required": {"duration": ["1 year"], "field": ["administration"]}}, {"job_id": "100003009038179", "location_code": "hk", "company": "ADECCO", "job_title": "Senior Data Engineer / Data Engineer (ETL, Big Data, up to 40k)", "description": "Our client is a media corporation with a vision to become a leading content and service provider serving global Chinese communities.\n\nResponsibilities\n\nImplement data platform architecture including big data, NoSQL and AI, and applications for providing data services to other systems and business users.\nResponsible for Data Ingestion\nTranslate requirements into data strategies and models\nWork closely with business / Technology teams to understand their needs and develop data-driven solutions\nDevelop different data solutions as required by the business\nData warehouse architecture design\nExperience\n\n2+ years of experience in data warehouse projects and development\nExperience with ETL development or Big Data Technologies, or Data Transformation, and modeling\nExperience in architecting and building scalable data platforms\nExperience in data governance\nExperience in Enterprise grade BI and reporting tools\nExperience with Cloud Technologies (Data Lake, Google, AWS etc.) or experience with open source technologies\nExperience with 2 of 4 - Java, Scala, R, and Python programming languages\nExperience with Big Query, SQL and/or NOSQL databases\nNeed to support the visualization e.g. DataStudio, Tabluea\nExperience in architecting and building scalable data platforms\n\nEducation\n\nBachelor in Computer Science, Engineering or Big Data or relevant disciplines\n\n\n\nInterested parties, please\u00a0CLICK HERE\u00a0to apply online. (Ref:JDB/IT-TT)\n\nPlease note that only short-listed candidates will be notified. All information gathered will be treated in strict confidence and solely used for recruitment purposes", "employment_types": ["Full Time", "Permanent"], "selling_points": ["Well-known media corporation in HK", "Big Data, ETL development", "Stable business"], "locations": ["Tseung Kwan O"], "categories": ["Information Technology (IT)", "DBA", "Others", "Data Scientist"], "post_time": "2022-01-11T05:54:25Z", "salary": {"currency": null, "max": null, "min": null, "period": "monthly", "term": null}, "salary_visible": false, "title_keywords": ["data engineer"], "responsibilities": ["reporting", "visualization", "data", "systems", "teams", "big data", "design", "develop", "databases", "architecture"], "requirements": {"degrees": ["bachelor"], "majors": ["engineering", "computer science"], "languages": ["chinese"], "language_level": [], "hard_skills": ["java", "bi", "ai", "data warehouse", "aws", "scala", "sql", "programming", "databases", "python", "r"], "soft_skills": ["driven", "responsible"], "languages_combined": [{"language": "chinese", "language_level": []}]}, "experience_required": {"duration": ["2+ years"], "field": ["sql", "development", "programming"]}}, {"job_id": "100003009039799", "location_code": "hk", "company": "Recruit Logic Limited", "job_title": "Data Analyst - Financial Service - 30-40k, perm", "description": "Our client is an innovative Hong Kong-based financial services company. The Company specializes in originating, acquiring and structuring asset-backed securities in Asia, including\u00a0providing high loan-to-valuation (LTV) residential property mortgage with major banks in Hong Kong.\u00a0They are now looking for a Data Analyst in the IT Team\n\n\u00a0Responsibilities:\n\n\n\nDevelop and implement end to end data pipeline from collection, ETL, analysis, reporting to visualization\nPerform and implement business reporting, ad hoc customer data analyses, dashboard building & statistical modelling\nProvide support for data issues, maintain best practices for data management and provide support where necessary for the data projects\nProficient in converting user requests to technical requirements, conduct user acceptance test of in-house-developed/external vendor developed applications\nWork on ad-hoc projects when required.\u00a0\n\n\u00a0Requirements:\n\nHigh school diploma or above in Statistics, Data Science, Computer Science, IT and Mathematics or related disciplines\nAt least 2 years of solid experience in the capacity of Data Analyst\nGood understanding of data modelling and data management process\nExperience in SQL, Power BI, Python is a must\nProficiency in ETL scripting, reporting tools (e.g. Jasper Report), data automation and visualization tools (Power Platform)\nWeb development programming skills (eg. Java or PHP) is a plus\nSelf motivated & able to accomplish multiple tasks\nStrong in problem solving skills and work under tight timeline\nEffective interpersonal and communication skills and able to work with people at all levels\nGood command in both spoken and written English", "employment_types": ["Full Time", "Permanent"], "selling_points": ["Data Analyst - Financial Mortgage firm", "End to end data pipeline, ETL and visualization", "SQL, Power BI, Python"], "locations": ["Wan Chai"], "categories": ["Information Technology (IT)", "DBA", "Data Scientist"], "post_time": "2022-01-11T11:27:14Z", "salary": {"currency": null, "max": null, "min": null, "period": "monthly", "term": null}, "salary_visible": false, "title_keywords": ["data analyst"], "responsibilities": ["reporting", "provide support", "management", "ad hoc", "visualization", "data", "analysis", "develop", "maintain", "customer data", "ad-hoc projects"], "requirements": {"degrees": ["high school diploma"], "majors": ["data science", "mathematics", "statistics", "related disciplines", "it", "computer science"], "languages": ["english"], "language_level": ["good command"], "hard_skills": ["web development", "bi", "data management", "java", "plus", "php", "sql", "programming", "python", "problem solving skills"], "soft_skills": ["communication skills", "multiple tasks", "self motivated", "problem solving skills", "interpersonal"], "languages_combined": [{"language": "english", "language_level": ["good command"]}]}, "experience_required": {"duration": ["at least 2 years"], "field": ["sql"]}}, {"job_id": "100003009037128", "location_code": "hk", "company": "Hong Kong Express Airways Limited", "job_title": "Specialist, Data Analytics", "description": "DEAR TALENT, YOUR MOVE!\n\nBeing the new rising airline since 2013, we are the Hong Kong\u2019s only Low Cost Carrier (LCC) offering you safe and flexible service options to Hong Kong and beyond.\n\nWe\u2019re on a mission to inspire you to be different, to shake things up, to inspire the spirit of adventure by bringing you to fascinating destinations that few others serve.\n\nSpread your wings and fly with us!\n\n\nWhat will you do?\u00a0\n\nPerform exploratory data analysis and develop business values from data;\nBuild and deploy the predictive model on cloud;\nUnderstand the data and create insightful visualization to facilitate user understanding;\nExamine data schema and ensure/maintain data quality;\nIdentify opportunities for leveraging corporate data and drive data-driven solutions to meet business goals;\nExplore innovative ways for data integration to enforce good governance on data management and regulatory compliance;\nAssess the potential usefulness and validity of data sources;\nAct as a Data Steward of the organization, conduct a Privacy Impact Assessment, govern the internal data usage and monitor the third party regularly to ensure the handling of personal data (not limited to access, transfer and retention of data) is in line with the data handling manuals and guidelines;\nSupport ad-hoc duties as assigned.\n\nWe are a perfect match, if you are:\n\nBachelor\u2019s degree, preferably in Mathematics, Statistics, Computer Science related discipline;\nMinimum 2 years of experience relating to Data Analytics and Data integration;\nKnowledge in SQL, Python is required;\nExperience in statistical libraries by using python;\nExperience in the solution of ETL, cleaning, desensitization;\nExperience in data visualization tools, such as Data Studio, PowerBI;\nExperience in Linux is preferred;\nKnowledge and\u00a0 hands-on experience on GCP platform and tools including BigQuery, Data Fusion, Compute Engine, Cloud Function, Pub/Sup, Source Repositories;\nGood communication and presentation skills;\nAirline or travel industry knowledge is highly beneficial.\n\nYour Future Work Life?\n\nWork flexibly with staggered working hours and flexible workplace\nDress Casual and Smart everyday\nWork in a newly-designed office with open seating, stylish breakout areas, game room, gym and free coffee\u2026\nWork with a group of energetic and multicultural professionals (up to 50 nationalities!)\nHave great fun in Snack Friday, New Year Market, Fly with your Kids Day, Basketball Team\u2026\nHave your voice heard through Townhalls, Crew forums, CEO live sessions etc.\n\nWhat will you enjoy?\n\nFly anywhere we fly for free plus taxes during leisure with your friends and family\nSpecial privileges to buy duty free products\nCareer Express\n\n\n\nYou will be inspired by our core values.\nYou will be inspired by our vibrant, efficient and entrepreneurial spirit. Join our fun, collaborative and reliable team to ignite your dream!\n\n\n\nInterested? It\u2019s time to have YOUR MOVE!\nIf you're ready to embark your adventure, start by clicking the \u2018Apply now\u2019 and get on the plane to fly with HK Express!\u00a0", "employment_types": ["Full Time"], "selling_points": ["Flexible Working Practices, WFH, Travel Benefits", "Perform exploratory data analysis", "Build and deploy the predictive model on cloud"], "locations": ["Tung Chung"], "categories": ["Professional Services", "Business Analysis / Data Analysis", "Information Technology (IT)", "DBA", "Data Scientist"], "post_time": "2022-01-11T01:49:38Z", "salary": {"currency": null, "max": null, "min": null, "period": "monthly", "term": null}, "salary_visible": false, "title_keywords": ["specialist"], "responsibilities": ["cost", "business goals", "management", "visualization", "ad-hoc duties", "data", "guidelines", "compliance", "quality", "monitor", "develop", "data analysis", "communication", "maintain data", "deploy", "cleaning", "personal data", "third party"], "requirements": {"degrees": ["degree", "bachelor"], "majors": ["mathematics", "statistics", "computer science"], "languages": [], "language_level": [], "hard_skills": ["linux", "plus", "data management", "fun", "data analytics", "analysis", "airline", "python", "sql", "safe", "lcc", "data visualization", "integration"], "soft_skills": ["flexible", "efficient", "collaborative", "communication", "hands-on", "presentation skills", "energetic", "reliable", "ad-hoc duties", "innovative", "driven"], "languages_combined": []}, "experience_required": {"duration": ["minimum 2 years"], "field": []}}, {"job_id": "100003009042756", "location_code": "hk", "company": "Avnet Technology Hong Kong Limited", "job_title": "Business Analyst/ Solutions Analyst (RPA Robotic Process Automation)", "description": "Job Duties:\n\n\nResponsible for automation solutions with programming throughout development, testing and implementation stages\nResponsible for analytical solutions with various systems, including projects with new systems\nWorking with business users to provide on-going support and enhancement of automation solutions\nConduct business analysis based on managements\u2019 requirements\nHandle new projects and other ad-hoc reports as assigned\n\nQualification & Experience:\n\n\nDegree holder in Computer Science or related discipline\n2 year of Development & Programming experience\nProficient in VBA, SQL, Java, Python and .NET\nKnowledge of RPA Robotic Process Automation is a definite advantage\nGood command of spoken and written in English, Cantonese and Mandarin\nFresh Graduate will also be considered\nInterested parties please send your application to our career website - Here.\n\n\nAll applications will be treated in strict confidence and personal data provided with be used solely for recruitment purpose. Unsuccessful candidates may be considered for other vacancies. Applicants who are not contacted within one month should consider their applications filed for future reference. All unsuccessful applications will be destroyed within six months.", "employment_types": ["Full Time", "Permanent"], "selling_points": ["5 days work", "Double Pay, Discretionary incentive", "Fresh Graduate will also be considered"], "locations": ["Kowloon Bay"], "categories": ["Professional Services", "Business Analysis / Data Analysis", "Information Technology (IT)", "DBA", "Data Scientist"], "post_time": "2022-01-12T08:42:26Z", "salary": {"currency": null, "max": null, "min": null, "period": "monthly", "term": null}, "salary_visible": false, "title_keywords": ["analyst", "business analyst"], "responsibilities": ["ad-hoc", "systems", "implementation", "testing", "reports", "business analysis"], "requirements": {"degrees": ["fresh graduate", "degree holder"], "majors": ["computer science"], "languages": ["cantonese", "english", "mandarin"], "language_level": ["good command"], "hard_skills": ["vba", "java", "analysis", "sql", "rpa", "programming", "python"], "soft_skills": ["responsible"], "languages_combined": [{"language": "cantonese", "language_level": ["good command"]}, {"language": "english", "language_level": ["good command"]}, {"language": "mandarin", "language_level": ["good command"]}]}, "experience_required": {"duration": ["2 year"], "field": ["development", "programming"]}}, {"job_id": "100003009033361", "location_code": "hk", "company": "Robert Walters (HK)", "job_title": "Data Governance Specialist - Bank", "description": "A reputable bank is now hiring two Data Gorvanance Specialist to join their Data Gavernance Team and you will work in a collaborative, intellectually curious environment.\n\nKey Responsibility\n\nSupport to develop standards, policies and procedures to support the creation and provide technical assurance for the on-going implementation of the data governance policy\nSupport and supervise information stewardship activities and management of data quality\nSupport project planning and management to ensure best practice and legal frameworks are followed with regards to data governance\nExperienced in establishing and monitoring of data governance framework\nSupport to design, drive, and contribute to initiatives to improve data quality, consistency and integrity\nSupport in defining data strategy to establish and ensure adherence to the Bank's data governance framework for data policies, standards, governance metrics, processes and data architecture\nCommunicate with stakeholders, resolve conflicts and provide solutions in a timely manner\nLead the facilitation of all working group meetings during execution of Data Governance\nImplement data standards, policies and procedures\nConvey facts and information clearly and accurately\nOperational familiarity in the use of meta-data management, data quality, and data stewardship tools and platforms preferred\n\nRequirement\n\nBachelor's Degree or above, preferably in Computer Science or Engineering or related discipline\nMinimum 1-2 years of experience in Data Governance / AI Model Governance / Data Risk / FEAT / related work\nUnderstanding in data quality improvement, data management processes is preferred\nPrevious experience with data governance / AI model Governance or data risk, auditing, information security, data protection, data management or similar relevant area\nUnderstand the concepts of data governance, being an advocate for the implementation and continuous application of governance principles and processes\nExcellent communication and organisational skills\nProblem solver with excellent communication skills\nConfident working in cross-functional, collaborative environments\nHighly motivated self-starter with the ability to work efficiently with minimal supervision\nCan-do attitude and good problem solving skills\nPassion for spreading the value of data throughout the company and communicating insights to a broad audience with varying levels of technical expertise", "employment_types": ["Full Time", "Temporary"], "selling_points": ["Data/Tech policies, standards, governance metrics", "Data quality, consistency and integrity", "Data stewardship tools and platform"], "locations": ["Kwun Tong"], "categories": ["Professional Services", "Business Analysis / Data Analysis", "Information Technology (IT)", "DBA", "Security"], "post_time": "2022-01-09T11:22:05Z", "salary": {"currency": null, "max": null, "min": null, "period": "monthly", "term": null}, "salary_visible": false, "title_keywords": ["specialist"], "responsibilities": ["communicate with", "management", "project planning", "data", "policies", "ensure adherence", "monitoring", "procedures", "implementation", "quality", "develop", "design", "provide solutions", "a timely manner", "architecture"], "requirements": {"degrees": ["degree or above", "bachelor"], "majors": ["engineering", "computer science"], "languages": [], "language_level": [], "hard_skills": ["problem solving skills", "data management", "ai"], "soft_skills": ["confident", "communication skills", "problem solver", "can-do attitude", "passion for", "collaborative", "communication", "organisational skills", "motivated", "problem solving skills"], "languages_combined": []}, "experience_required": {"duration": ["minimum 1-2 years"], "field": ["related", "management", "security"]}}, {"job_id": "100003009033407", "location_code": "hk", "company": "HKT", "job_title": "System Specialist", "description": "Your Role:\n\nPerform Linux system administration tasks including system/software installation and configuration, security setup and hardening, patch upgrade, system monitoring and health checks.\nProvide support of system administration-related services and solution for projects and operational needs.\nPerform system problem troubleshooting and performance tuning.\nDevelop and maintain system documentation and procedure manuals.\n\nTo succeed in this role\n\nDegree holder in Computer Science or equivalent with at least 3 years of system administration experience\nSolid experience in Linux system administration and technical support, preferable on Red Hat Linux environment.\nExperience in supporting container-based environments is an advantage.\nKnowledge of popular Hadoop distributions administration is an advantage.\nStable, responsible, self-motivated and willing to work under pressure.\nAble to work outside of office hours for production problems and scheduled changes.\nStrong analytical, problem solving, interpersonal and communication skills.\nGood command of English, Cantonese and Mandarin.", "employment_types": ["Full Time"], "selling_points": [], "locations": ["Wan Chai"], "categories": ["Information Technology (IT)", "Application Specialist - Software", "DBA", "Application Specialist - Network"], "post_time": "2022-01-09T14:56:14Z", "salary": {"currency": null, "max": null, "min": null, "period": "monthly", "term": null}, "salary_visible": false, "title_keywords": ["specialist"], "responsibilities": ["installation", "provide support", "software", "system documentation", "configuration", "technical support", "work under pressure", "monitoring", "troubleshooting", "develop", "communication", "maintain", "setup", "administration"], "requirements": {"degrees": ["degree holder"], "majors": ["computer science"], "languages": ["cantonese", "english", "mandarin"], "language_level": ["good command"], "hard_skills": ["linux", "red hat", "problem solving", "container", "documentation"], "soft_skills": ["communication skills", "self-motivated", "responsible", "troubleshooting", "problem solving", "stable", "interpersonal", "work under pressure"], "languages_combined": [{"language": "cantonese", "language_level": ["good command"]}, {"language": "english", "language_level": ["good command"]}, {"language": "mandarin", "language_level": ["good command"]}]}, "experience_required": {"duration": ["at least 3 years"], "field": ["administration"]}}, {"job_id": "100003009035368", "location_code": "hk", "company": "HKT Enterprise Solutions", "job_title": "Senior Market Analyst", "description": "Your\u00a0role\n\nYou will work in the Marketing Data Analytic Team.\u00a0 The major responsibility of this role is to provide high quality insight and facilitate decision making process on business side through data mining and analysis. Major responsibilities include but not limited to the following:\n\nHandle large sets of data to analysis the customer behavior and identify new market opportunities and retention strategies\nPrepare regular management report & dashboards on business performance metrics\nAnalyze marketing trend and identify customer needs by building data-driven attribution models\nConduct market research projects to analyze competitors, determine brand perceptions evaluate market penetration; understand customer satisfaction\nProvide ROI analysis of all marketing campaigns and sales activities (maximize effectiveness)\nPerform UAT, data testing and monitor project execution to maintain data integrity of marketing data mart\nSupport ad-hoc projects as assigned\n\nTo succeed this role\n\nDegree holder in Marketing or Statistics related discipline\n3 years\u2019 solid experience in data analytics, data mining and customer segmentation with strong programming skill in SQL and Python\nFamiliar in Datamart, BI Dashboard and visualization tool such as Qliksense and Tableau\nWorking experience in telecommunication / mobile / Banking/ IT industry is preferred\nA marketing expert who possesses a core strength of strategic thinking\nGood analytical skill and detail-oriented\nExcellent interpersonal and communication skills as well as good command of both written and spoken English and Cantonese", "employment_types": ["Full Time"], "selling_points": [], "locations": ["Quarry Bay"], "categories": ["Banking / Finance", "Analyst", "Information Technology (IT)", "DBA", "Marketing / Public Relations", "Marketing - Market Research"], "post_time": "2022-01-10T06:56:23Z", "salary": {"currency": null, "max": null, "min": null, "period": "monthly", "term": null}, "salary_visible": false, "title_keywords": ["analyst"], "responsibilities": ["visualization", "data", "conduct market research", "quality", "communication", "data mining", "ad-hoc projects", "uat", "monitor", "testing", "marketing campaigns", "banking", "management report", "maintain data", "sales activities", "analyze marketing trend", "analysis", "performance metrics", "evaluate"], "requirements": {"degrees": ["degree holder"], "majors": ["marketing", "statistics"], "languages": ["cantonese", "english"], "language_level": ["excellent", "good command"], "hard_skills": ["analytical skill", "bi", "data analytics", "analysis", "tableau", "python", "sql", "mobile", "programming", "data mining"], "soft_skills": ["communication skills", "analytical skill", "strategic thinking", "integrity", "detail-oriented", "interpersonal", "driven", "decision making"], "languages_combined": [{"language": "cantonese", "language_level": ["excellent", "good command"]}, {"language": "english", "language_level": ["excellent", "good command"]}]}, "experience_required": {"duration": ["3 years"], "field": ["sql", "it", "programming", "banking"]}}, {"job_id": "100003009036052", "location_code": "hk", "company": "Seamatch Asia Limited", "job_title": "Data Analysts / Senior Data Analysts / Trainee Analysts", "description": "\nOur client is one of the largest online shopping ecommerce platforms in Hong Kong. They are looking for new team members to join their data science teams.\n\nData Analysts / Senior Data Analysts / Trainee Analysts\u00a0\n\n20K (entry levels) to around 60K (senior levels)\n\n\nResponsibilities:\n\nAgile team collaboration in continual development of Company's Azure Cloud data analytics platform, data flow and\u00a0data pipelines\nData mining, data discovery and metadata management for business intelligence (BI), quantitative modeling, machine learning and predictive analytics projects\nData warehousing and data extract/transform/load (ETL) integration in cloud and on-premise environments\nData visualization, BI reporting, data dashboard design & development\nRequirements:\n\nDegree holder in IT and data sciences related subjects\nOver or around 3 years of technical experience in data engineering, data warehousing, data analytics or related functional areas\nJunior candidates with good sense of SQL logic and data flow are welcome\nGood knowledge of SQL programming, MS SQL\u00a0databases and analytic tools such as Microsoft Power BI, Excel Power Query, Google\u00a0Analytics, etc.\nFamiliar with using Informatica or SSIS tools for data integration an advantage\nFluent Chinese and English communication with local team members\n\u00a0\n** Less experienced candidates but with good sense of SQL logic and data flow are welcome", "employment_types": ["Full Time", "Permanent"], "selling_points": ["Data Analyst, Senior Data Analyst, Trainee Analyst", "Data warehousing, data integration, data analytics", "Good sense of SQL logic and data flow required"], "locations": ["Tsim Sha Tsui"], "categories": ["Information Technology (IT)", "Application Specialist - Software", "DBA", "Data Scientist"], "post_time": "2022-01-10T09:12:32Z", "salary": {"currency": null, "max": null, "min": null, "period": "monthly", "term": null}, "salary_visible": false, "title_keywords": ["trainee"], "responsibilities": ["warehousing", "management", "reporting", "visualization", "data", "design", "data mining"], "requirements": {"degrees": ["degree holder"], "majors": ["it"], "languages": ["english", "chinese"], "language_level": ["fluent"], "hard_skills": ["excel", "google analytics", "bi", "data analytics", "sql", "databases", "programming", "integration", "ms sql"], "soft_skills": ["communication"], "languages_combined": [{"language": "english", "language_level": ["fluent"]}, {"language": "chinese", "language_level": ["fluent"]}]}, "experience_required": {"duration": ["3 years"], "field": ["related", "engineering"]}}, {"job_id": "100003009036284", "location_code": "hk", "company": "Centaline Data Technology Limited", "job_title": "Programmer / Senior Programmer / Analyst Programmer (5-day Work)", "description": "Responsibilities\n*Responsible for internal system development, implementation, maintenance, documentation and training;\n*User requirements gathering and work closely with internal users\n\nRequirements\n*Bachelor Degree in Computer Science or equivalent;\n*2 years or above relevant experience;\n*Hands on C# / VB .NET /.Net Core, APIs, Web Apps, SQL Server / MySQL;\n*Experience in HTML5, CSS, JQUERY, JAVASCRIPT, REACT is an advantage;\n*A self-motivated team player with good interpersonal and communication skills;\n*Able to work independently to meet project deadlines;\n*Immediately available will be an advantage;", "employment_types": ["Full Time", "Permanent"], "selling_points": ["Quarterly Bonus / Medical / Education Allowance", "Databank Management", "Data Migration and Analysis"], "locations": ["Tsim Sha Tsui"], "categories": ["Information Technology (IT)", "DBA", "Software Development", "Data Scientist"], "post_time": "2022-01-10T09:56:49Z", "salary": {"currency": null, "max": null, "min": null, "period": "monthly", "term": null}, "salary_visible": false, "title_keywords": ["analyst programmer", "programmer", "senior programmer"], "responsibilities": ["documentation", "implementation", "maintenance"], "requirements": {"degrees": ["degree", "bachelor"], "majors": ["computer science"], "languages": [], "language_level": [], "hard_skills": ["react", "web apps", "jquery", "sql", "javascript", "server", "css", "c#"], "soft_skills": ["communication skills", "self-motivated", "work independently", "hands on", "team player", "interpersonal"], "languages_combined": []}, "experience_required": {"duration": ["2 years"], "field": ["relevant experience"]}}, {"job_id": "100003009037466", "location_code": "hk", "company": "World Family Ltd", "job_title": "Data Analysis Executive (5-day work)", "description": "Responsibilities:\nAnalyze and interpret data with MS Power BI\nSupport in dashboards development including data modelling and design\nParticipate in\u00a0BI projects and support the development of dashboards for\u00a0Management\nResponsible for eDM promotion\nRequirements:\nDegree in IT, data management or a related discipline\n1-year experience in SQL, MS SQL Server\nAbility to interpret data from multiple sources and evaluate the impact\nExcellent analytical skills, proactive and passionate about data\nPractical experience in working with MS Power BI\nGood interpersonal and communication skills\nFresh graduated candidate will also be considered as Data Analysis Assistant.\nWork location:\u00a0\u00a0\nT.O.P in Mong Kok\nBenefits:\n5-day work week\nExtra leaves\nCompensation leave for OT\nBonus\nEntertainment fund\nMedical Insurance (including dental insurance)\nStaff discounts\nand other\u00a0comprehensive benefits\nFor further details, please visit our website:\u00a0\nhttps://www.worldfamily.com.hk/\u00a0\nWith energetic working environment in T.O.P, we offer entertainment fund, medical and dental insurance and other comprehensive benefits to the right candidate.\nWe are an equal opportunity employer. Qualified candidates please send your detailed resume in MS Word format along with your present & expected salary and available date by CLICKING the \"APPLY NOW\" button, or mail to Suite 1 & 6-10, 15/F, T.O.P, 700 Nathan Road, Mong Kok.\u00a0\u00a0\u00a0\nOnly short-listed candidates will be contacted. All information collected will be used for Recruitment purpose only.", "employment_types": ["Full Time", "Permanent"], "selling_points": ["Extra leaves, medical, dental insurance provided", "Stable & harmonious working environment", "Work location is next to MTR station (T.O.P)"], "locations": ["Mong Kok"], "categories": ["Professional Services", "Business Analysis / Data Analysis", "Information Technology (IT)", "DBA", "Marketing / Public Relations", "Marketing - Market Research"], "post_time": "2022-01-11T02:53:56Z", "salary": {"currency": null, "max": null, "min": null, "period": null, "term": null}, "salary_visible": false, "title_keywords": ["executive"], "responsibilities": ["management", "power bi", "edm", "data", "design"], "requirements": {"degrees": ["degree"], "majors": ["it"], "languages": [], "language_level": [], "hard_skills": ["bi", "data management", "ms sql server", "analysis", "analytical skills", "sql"], "soft_skills": ["communication skills", "analytical skills", "proactive", "interpersonal", "passionate about"], "languages_combined": []}, "experience_required": {"duration": ["1-year"], "field": ["sql"]}}, {"job_id": "100003009037658", "location_code": "hk", "company": "Venturenix Limited", "job_title": "Data Engineer (SQL) @MNC | 28K", "description": "Job Description\nOur client, an MNC in retail industry is currently looking for a Data Engineer who uses SQL as the main language.\n\nJob duties:\n\n\nTableau Server Maintenance\nTableau Server Analysis\nTableau Dashboard Visualization\nTableau Prep Workflow Building\nRequirements:\n\n\nAt least 1 year experience on SQL & Tableau\nBasic Python knowledge\nRelated certifications would be a plus\nInterested parties please directly apply with \"apply now\".", "employment_types": ["Contract"], "selling_points": ["Global MNC exposure", "Tableau, BI, Data Visualization", "Retail Big Data"], "locations": ["Shatin Area"], "categories": ["Information Technology (IT)", "DBA", "Data Scientist"], "post_time": "2022-01-11T03:25:15Z", "salary": {"currency": null, "max": null, "min": null, "period": "monthly", "term": null}, "salary_visible": false, "title_keywords": ["data engineer"], "responsibilities": ["analysis", "visualization", "maintenance", "data"], "requirements": {"degrees": [], "majors": [], "languages": [], "language_level": [], "hard_skills": ["plus", "basic", "tableau", "sql", "python"], "soft_skills": [], "languages_combined": []}, "experience_required": {"duration": ["at least 1 year"], "field": ["sql"]}}, {"job_id": "100003009030775", "location_code": "hk", "company": "GDS (Hong Kong) Limited", "job_title": "Data Center Manager/Assistant Data Center Manager", "description": "Responsible for the overall development and management of the Hong Kong Data Center portfolio.\u00a0\n\nOversight of the entire Electrical & Mechanical infrastructure, all aspects of the data centre operation, routine maintenance schedules and any break/fix activities.\u00a0\n\nImplementing and support he entire is IT asset lifecycle.\u00a0\n\nStrong relationship building skills required with multiple tenants.\n\nRESPONSIBITIES\n\n\n\u00b7 Managing and developing teams of Data Center Operators/Technicians\n\n\u00b7 Help build and bring new Data Centers into Hong Kong.\n\u00b7 Constantly improving all our processes and procedures.\u00a0\n\n\u00b7 Assisting & managing relationships with external vendors & contractors.\n\u00b7 Liaising with internal teams & management groups.\n\u00b7 Ensuring compliance to Operations, Security and Health & Safety standards in al Data Centers.\n\u00b7 Creating and maintaining metrics of all aspects of our Data Centers and utilising them to drive improvements.\n\u00b7 Implementing service methodologies that include incident management, problem management, change management, capacity management.\n\nQUALIFICATIONS\n\n\u00b7 5+ years of people management experience with direct reports in a Data Centre environment.\n\n\u00b7 Candidate with fewer experiences will be considered for the Assistant DC Manager post.\n\u00b7 In-depth knowledge and expertise in change/incident management.\n\u00b7 Prior experience in managing 7x24 teams in a high tier data center.\n\n\u00b7 Understanding of data center E&M infrastructure and its resiliency design (UPS, Generator, CRAC, cabling, containment routes, etc).\n\n\u00b7 Knowledge and / or experience of various IT standards such as ISO20000, ISO27001, ISO-14000, PCI-DSS, etc.\n\n\u00b7 Good verbal communication in Mandarin and English.\n\n*Personal data submitted are for recruitment purpose only.", "employment_types": ["Full Time"], "selling_points": [], "locations": ["Kwai Fong"], "categories": ["Information Technology (IT)", "DBA", "Support"], "post_time": "2022-01-08T21:06:45Z", "salary": {"currency": null, "max": null, "min": null, "period": "monthly", "term": null}, "salary_visible": false, "title_keywords": ["manager", "assistant"], "responsibilities": ["data", "schedules", "operations", "design", "communication", "personal data", "maintaining", "infrastructure", "teams", "developing", "liaising with", "compliance", "reports", "management", "change management", "procedures", "maintenance", "recruitment", "safety standards"], "requirements": {"degrees": [], "majors": [], "languages": ["english", "mandarin"], "language_level": ["good"], "hard_skills": ["dc", "maintenance"], "soft_skills": ["communication", "responsible"], "languages_combined": [{"language": "english", "language_level": ["good"]}, {"language": "mandarin", "language_level": ["good"]}]}, "experience_required": {"duration": ["5+ years"], "field": ["people management", "it"]}}, {"job_id": "100003009030019", "location_code": "hk", "company": "Gientech Technology (Hong Kong) Limited", "job_title": "Data Engineer", "description": "About us\n\nGientech is a global company offering consulting, digital, technology and operations services to the world\u2019s leading enterprises. From our roots in engineering to the latest in digital transformation, we give customers a competitive edge.\n\nOur Culture\n\nWithin our team, we are about passion to win, value our people, and client orientated, ect. We treat our people with respect and trust and give them a ton of freedom and autonomy to make an impact.\u00a0 Join the growing company using technology to tackle enterprises toughest challenges.\n\nAbout this Job\n\nOrganize data assets to enable analytics initiatives and achieve business objectives. Support client\u2019s customer engagement strategy (sales & services) by onboarding data, data modelling and visualizations as well as promoting data-driven culture across the organization.\n\n\n\nKey Responsibilities\n\nMaintain and enhance current customer analytics data marts and data models\nParticipate in Analytical Datahub project by prototyping data models and liaise with IT on implementation\nCollect and organize digital data from a variety of touchpoints, e.g. ecommerce, customer service, customer lifestyle platform, for deriving interesting insights together with conventional insurance data\nWork closely with customer analytics analyst to make sure the data models are easy to use\nSupport cloud migration project, potentially migrating SAS-based process to Python\nOccasionally support adhoc reporting and data visualization tasks\n\nRequirements\n\nUniversity graduate in Computer Science, Information Systems, Data Science, or a related field\n2 - 5 years of experience in data modeling, preferably within the financial services industry\nProficiency in Python, SAS & SQL\nStrong understanding in database concepts & data modelling, business intelligence disciplines & data management tools\nKnowledge in Google Analytics and BigQuery\nUnderstanding in customer and commercial analytics, direct marketing and telemarketing, ideally within the insurance industry\nExperience in Big Data and Machine Learning tools (e.g. Databricks, AzureML, Spark, Hive) is an advantage\nSound communication skills to work with business partners of different levels and background. Be able to articulate ideas verbally and in written forms\nAble to work independently, creative and detail-oriented", "employment_types": ["Full Time", "Permanent"], "selling_points": ["Fin-tech opportunity in Insurance Industry", "Stable working environment", "SAS and/or Python skills is preferred"], "locations": ["Wan Chai"], "categories": ["Information Technology (IT)", "DBA", "Data Scientist"], "post_time": "2022-01-07T06:37:08Z", "salary": {"currency": null, "max": null, "min": null, "period": "monthly", "term": null}, "salary_visible": false, "title_keywords": ["data engineer"], "responsibilities": ["reporting", "visualization", "data", "implementation", "migration", "maintain", "customer service", "liaise with", "insurance"], "requirements": {"degrees": ["university graduate"], "majors": ["data science", "computer science"], "languages": [], "language_level": [], "hard_skills": ["google analytics", "data management", "sas", "sql", "python", "spark", "business intelligence"], "soft_skills": ["communication skills", "work independently", "detail-oriented", "learning", "articulate", "creative"], "languages_combined": []}, "experience_required": {"duration": ["2 - 5 years"], "field": ["financial services industry"]}}, {"job_id": "100003009029445", "location_code": "hk", "company": "\u7368\u89d2\u7378\u74b0\u7403\u79d1\u6280\u516c\u53f8", "job_title": "Associate Data Scientist / Data Scientist", "description": "Unicorn Studio is seeking a talented, experienced, and collaborative Associate Data Scientist / Data Scientist to join our core team developing high quality AAA games and cinematic animations. The ideal candidate will dig deep into our Unity game data. Visualizing database. Implement and improve the game bot. Working with our Game Developer to implementing end-to-end features, and delivering high quality content to our game players and audiences.\u00a0\n\nRequirements:\n\nBachelor\u2019s degree in Computer Science, Econometrics, Mathematics, Operation Research, Statistics or related disciplines\nMinimum 2 years\u2019 work experience in data science with proven track record of leveraging large amount of data to drive significant business impact\nAdvanced analytical skills, experience in recommending appropriate algorithm and methodology for problem-solving and decision making, leveraging both logic and creativity\nExposure to Amazon AWS core services such as S3, EC2, API Gateway, and Lambda is advantageous\nExperience in prototyping and productionalizing advance analytics solutions in business\nMust be proficient in C#. Knowledge of Java, Scala, Python and C++ is a plus\nExperience in IT big data tools (e.g Hadoop, Spark), as well as query languages for SQL and NoSQL\nFamiliar with machine learning algorithm and libraries (e.g. scikit-learn, XGBoost, LGBM, TensorFlow etc.)\nProficiency in data visualization tools, ideally Tableau\nExperience with MLOps and DevOps solution architecture design is a plus\nUnderstands common software engineering best practices such as is a code versioning, test-driven development, and code modularization\n\nResponsibilities:\n\nTranslate unstructured business questions into quantitative problems\nPrototyping advance analytics and machine learning solutions for business partners\nProvide advanced analytics support and advise on appropriate analytical models based on available data, technology and platform\nMake intelligent approximations to the model if required to make it scalable and operatable\nAnticipate needs and lead implementation of capabilities such as data modelling, algorithms, new technology & partners\nRecommend and implement the development path of capabilities and skillsets to foster a culture of applying data & insight driven culture in decision making\n\n(Candidates with more experience will be considered as Data Scientist.)\n\nInterested parties please send curriculum vitae with full career detail, salary history, availability and expected salary in WORD format by email for interview.\u00a0\n\nFor further information, please visit our company website: http://www.unicornstudio.cc\n", "employment_types": ["Full Time"], "selling_points": [], "locations": ["Kwun Tong"], "categories": ["Information Technology (IT)", "Application Specialist - Software", "DBA", "Data Scientist"], "post_time": "2022-01-07T05:16:22Z", "salary": {"currency": null, "max": null, "min": null, "period": "monthly", "term": null}, "salary_visible": false, "title_keywords": ["associate", "data scientist"], "responsibilities": ["implementation", "data"], "requirements": {"degrees": ["degree", "bachelor"], "majors": ["related disciplines", "mathematics", "statistics", "computer science"], "languages": [], "language_level": [], "hard_skills": ["java", "amazon", "plus", "c++", "problem-solving", "devops", "code", "tableau", "aws", "analytical skills", "scala", "sql", "data visualization", "python", "spark", "s3", "c#"], "soft_skills": ["advanced", "problem-solving", "analytical skills", "learning", "driven", "decision making"], "languages_combined": []}, "experience_required": {"duration": ["minimum 2 years"], "field": ["analytical", "devops", "design", "business", "it"]}}, {"job_id": "100003009025256", "location_code": "hk", "company": "HKT", "job_title": "System Specialist", "description": "Your Role\n\nImplement and administrate sizable environments including Oracle and My SQL server\nAssist and coordinate with application teams on database design and deployment\nConfigure and manage database maintenance including backup & Recovery (RMAN),\u00a0 Data Guard and Real Application Cluster (RAC)\nProvide technical guidance to application team\n\nTo succeed in this role\n\nDegree holder / Diploma in Computer, Information System or equivalent\nA minimum of 5 years\u2019 relevant working experience\nExperience in Oracle Exadata /ExaCC and Oracle Enterprise Manager will \u00a0be an advantage\nSelf-motivated, good customer-oriented attitude and ability to work under pressure as well as good command of both written and spoken English and Cantonese.", "employment_types": ["Full Time"], "selling_points": [], "locations": ["Wan Chai"], "categories": ["Information Technology (IT)", "DBA"], "post_time": "2022-01-06T03:56:58Z", "salary": {"currency": null, "max": null, "min": null, "period": "monthly", "term": null}, "salary_visible": false, "title_keywords": ["specialist"], "responsibilities": ["guidance", "maintenance", "data", "teams", "coordinate with", "design", "database", "work under pressure"], "requirements": {"degrees": ["diploma", "degree holder"], "majors": [], "languages": ["cantonese", "english"], "language_level": ["good command", "good"], "hard_skills": ["maintenance", "my sql", "information system", "deployment", "server", "oracle"], "soft_skills": ["self-motivated", "customer-oriented", "work under pressure"], "languages_combined": [{"language": "cantonese", "language_level": ["good command", "good"]}, {"language": "english", "language_level": ["good command", "good"]}]}, "experience_required": {"duration": ["minimum of 5 years"], "field": ["relevant working experience"]}}, {"job_id": "100003009030772", "location_code": "hk", "company": "GDS (Hong Kong) Limited", "job_title": "Data Center Operator", "description": "Responsibilities:\nConduct systems operations in data center (7x24 shifts)\nProvide administrative and accounting support (9x5 shifts)\nPerform simple daily tasks such as system monitoring and backup operation\nPrepare and follow-up purchase orders and delivery schedule\n\nRequirements:\n\nPreferred Diploma or above\nFresh Graduates are welcome\u00a0\nExperienced in data center operations\u00a0\nDisciplined and willing to learn\nGood command of Cantonese, Mandarin & English\nGood working knowledge of MS office and Chinese typing\nGood communication and interpersonal skills\nVacancy: 10x\n\n*Personal data submitted are for recruitment purpose only.", "employment_types": ["Full Time"], "selling_points": [], "locations": ["Kwai Fong"], "categories": ["Information Technology (IT)", "DBA"], "post_time": "2022-01-08T21:06:45Z", "salary": {"currency": null, "max": null, "min": null, "period": "monthly", "term": null}, "salary_visible": false, "title_keywords": ["operator"], "responsibilities": ["data", "operations", "monitoring", "systems", "delivery schedule", "purchase"], "requirements": {"degrees": ["diploma or above"], "majors": [], "languages": ["cantonese", "english", "chinese", "mandarin"], "language_level": ["good command", "good"], "hard_skills": ["typing", "ms office"], "soft_skills": ["communication and interpersonal skills", "willing to learn"], "languages_combined": [{"language": "cantonese", "language_level": ["good command", "good"]}, {"language": "english", "language_level": ["good command", "good"]}, {"language": "chinese", "language_level": ["good"]}, {"language": "mandarin", "language_level": ["good command", "good"]}]}, "experience_required": {"duration": [], "field": []}}, {"job_id": "100003009020793", "location_code": "hk", "company": "Wisers Information Limited", "job_title": "Database Administrator", "description": "RESPONSIBILITIES\n\n\nResponsible to provide technical support to MySQL, MongoDB, and Oracle databases\nMaintaining the normal operation of the MySQL, MongoDB and Oracle databases running including backup and restoration, troubleshooting and SQL performance tuning, monitoring usage and capacity planning etc\nAssist in database design, installation, configuration, performance tuning and on-going maintenance\nPrepare technical documentation related to updated policies and procedures\u00a0\n\nREQUIREMENTS\n\n\nDegree holder with major in Computer Science or related disciplines\nMinimum 3 years' relevant working experience\nExperience in MySQL\nORACLE database or MongoDB administration experience a plus\nProficiency in Linux platform support and shell script programming\nGood team player, responsible and self-motivated\nProficient spoken and written English, Cantonese and Mandarin is advantage\n\n\n\nInterested parties please apply online with an expected salary. \u00a0Due to the high volume of applicants, only shortlisted candidates will be notified.\n\n(Data collected will be treated as strictly confidential and will be used for recruitment purpose only)", "employment_types": ["Full Time", "Permanent"], "selling_points": ["Fast growing AI/ Big data company in APAC", "Excellent career development in a new tech busines", "Young and dynamic team"], "locations": ["Wan Chai"], "categories": ["Information Technology (IT)", "DBA", "Others"], "post_time": "2022-01-05T02:04:53Z", "salary": {"currency": null, "max": null, "min": null, "period": "monthly", "term": null}, "salary_visible": false, "title_keywords": ["administrator"], "responsibilities": ["installation", "maintaining", "maintenance", "technical support", "configuration", "policies", "monitoring", "procedures", "troubleshooting", "design", "databases", "database", "documentation", "planning"], "requirements": {"degrees": ["degree holder"], "majors": ["related disciplines", "computer science"], "languages": ["cantonese", "english", "mandarin"], "language_level": ["advantage", "proficient"], "hard_skills": ["linux", "plus", "programming", "oracle"], "soft_skills": ["good team player", "self-motivated", "responsible"], "languages_combined": [{"language": "cantonese", "language_level": ["advantage", "proficient"]}, {"language": "english", "language_level": ["advantage", "proficient"]}, {"language": "mandarin", "language_level": ["advantage", "proficient"]}]}, "experience_required": {"duration": ["minimum 3 years"], "field": ["relevant working experience", "database", "administration"]}}, {"job_id": "100003009030982", "location_code": "hk", "company": "Gravitas Recruitment Group", "job_title": "Data Analytics Assistant Manager- Insurance", "description": "The Company\n\nThis is a brand new initiative in 1 of the top insurance company that believes in data- driven solutions to enhance all aspects of the business and operations. The Actuarial function is looking for a Data Analytics Assistant Manager to build up solutions such as Data Dashboards, process automations, predictive analysis to generate data- driven insights for relevant business users.\n\nThe Scope\n\n-Develop Data Visualization tools (PowerBI) and provide data insights on In-Force Management and other topics\n\n-Support Actuarial Team on process automation\n\n-Collaborate with Product and Pricing teams on Insurance Product analytics\n\n-Involve in think-tank and data analytics projects to explore initiatives such as machine learning, predictive analysis, etc.\n\nThe Candidate\n\n-Degree holder of data analytics, statistics, actuarial science or related fields\n\n-3 years of working experience in data analytics. Insurance knowledge is a plus\n\n-Technical proficiency in Python, SQL, PowerBI\n\n-Good communication skills\n\n-Curious personality, with passion to explore new technologies\n\n-Less experienced candidate can be considered as Specialist", "employment_types": ["Full Time", "Permanent"], "selling_points": ["Drive Data Solutions to support Actuarial team", "New initiative with career growth opportunities", "Top-tier brand, work life balance, great benefits"], "locations": ["Not Specified"], "categories": ["Information Technology (IT)", "DBA", "Insurance", "Actuarial", "Data Scientist"], "post_time": "2022-01-07T08:45:43Z", "salary": {"currency": "HKD", "max": 44999, "min": 35000, "period": "monthly", "term": null}, "salary_visible": true, "title_keywords": ["assistant manager"], "responsibilities": ["management", "visualization", "data", "operations", "analysis", "teams", "communication", "insurance"], "requirements": {"degrees": [], "majors": [], "languages": [], "language_level": [], "hard_skills": ["plus", "data analytics", "analysis", "sql", "data visualization", "python"], "soft_skills": ["communication skills", "learning", "driven", "initiative"], "languages_combined": []}, "experience_required": {"duration": [], "field": []}}, {"job_id": "100003009030549", "location_code": "hk", "company": "Fubon Bank (Hong Kong) Limited", "job_title": "Senior Programmer / Analyst Programmer, MIS, Information Technology", "description": "Responsibilities:\n\nSupport the Enterprise Data Warehouse Information System\nGathering user requirements and perform in-depth data analysis to deliver meaningful results to business\nDevelop ETL jobs to ensure data accuracy and completeness in the Data Warehouse\nSupport daily MIS operations and user data requests such as marketing fulfillment exercises and regulatory reporting\n\n\nRequirements:\n\nDegree holder of Information Technology or Information Systems or related discipline.\n3 to 5 years work experience in Information Technology preferably in data mining and analysis in banks.\nExperience in database management such as Oracle, MS SQL Server\nExperience in ETL / SQL / SQL Server Integration Service (SSIS) / MS Excel Macro development\nHas knowledge in Tableau would be an advantage\nStrong problem solving, analytical and interpersonal skills\nTeam player and can work independently\nStrong sense of responsibility and self-motivated\nGood command of spoken and written English / Mandarin\n\n\n\nPlease send your application with full resume indicating current and expected salary, and quoting the above reference no.\n\nFor other vacancies, please visit our website:\u00a0http://www.fubonbank.com.hk/\n\n*All personal data provided by job applicants will be used for recruitment purposes only in accordance with the Bank\u2019s Personal Data Information Collection Statement, a copy of which is available on our website:\u00a0http://www.fubonbank.com.hk/web/html/sh_careers_e.html", "employment_types": ["Permanent"], "selling_points": ["13 Month Pay", "Insurance Benefits", "Insurance Benefits"], "locations": ["Central"], "categories": ["Information Technology (IT)", "DBA", "Network & System", "Data Scientist"], "post_time": "2022-01-07T07:43:53Z", "salary": {"currency": null, "max": null, "min": null, "period": "monthly", "term": null}, "salary_visible": false, "title_keywords": ["analyst programmer", "senior programmer"], "responsibilities": ["reporting", "data", "operations", "fulfillment", "ensure data accuracy", "develop", "data analysis"], "requirements": {"degrees": ["degree holder"], "majors": ["information technology"], "languages": ["english", "mandarin"], "language_level": ["good command"], "hard_skills": ["server", "macro", "no", "integration", "web", "ms sql server", "analysis", "tableau", "html", "sql", "problem solving", "ms excel", "data mining", "oracle"], "soft_skills": ["work independently", "self-motivated", "sense of responsibility", "problem solving", "interpersonal skills", "team player"], "languages_combined": [{"language": "english", "language_level": ["good command"]}, {"language": "mandarin", "language_level": ["good command"]}]}, "experience_required": {"duration": ["3 to 5 years"], "field": ["sql", "development", "database management", "information technology"]}}, {"job_id": "100003009026277", "location_code": "hk", "company": "Robert Walters (HK)", "job_title": "Data Manager (Financial Service Industry)", "description": "One of the well-kwown financial service company is looking for Data talents to join their team.\n\nResponsibilities\n\nImplement data strategy and data governance model\nCollaborate with IT, Operation and business team to deliver a robust, stable, and accurate company's Data platform on cloud\nSet up and execute proper data management procedures and quality control metrics; perform the day-to-day functions to maintain the accuracy and integrity of company's data\nAct as a subject matter expert for company's data platform; initiate enhancements and support user acceptance test for data-related projects\nOptimise the data operation flow\nManage the relationships with data vendors\nDesign and prepare regular reports to support company's clients and meet business needs\nSupport ad-hoc data enquiries from internal and external users\n\nQualifications\n\nUniversity degree in Business, Finance, Computer Science, Engineering or a related discipline\n5-12 years of working experience, preferably with financial database and business analyst experience\nKnowledge of Hong Kong and China equity market operations, including real-time price sourcing, corporate actions, as well as company financial reporting\nKnowledge of SQL and programming language is essential\n1-3 years of experience in managing data warehouse on Cloud and performing data cleansing\nExcellent analytical, problem solving and communication skills\nAbility to handle large amounts of data while maintain intense attention to detail\nPreferably, you have experiences on data dictionary, business glossary, data catalog and data quality solutions\nProficiency in Python and Tableau a plus\nProficiency in both English and Chinese\nGreat sense of ownership and servicing mindset to ensure efficient and effective customer service processes\nCandidates with less experience will be considered for the position of Assistant Data Manager.", "employment_types": ["Full Time", "Permanent"], "selling_points": ["5+ years of working exp with financial database", "Knowledge of SQL and programming language", "Proficiency in both English and Chinese"], "locations": ["Not Specified"], "categories": ["Professional Services", "Business Analysis / Data Analysis", "Information Technology (IT)", "DBA", "Data Scientist"], "post_time": "2022-01-06T07:50:28Z", "salary": {"currency": null, "max": null, "min": null, "period": "monthly", "term": null}, "salary_visible": false, "title_keywords": ["manager"], "responsibilities": ["collaborate with", "ad-hoc", "management", "data", "operations", "cleansing", "procedures", "subject matter expert", "design", "quality", "communication", "maintain", "reports", "financial reporting", "quality control", "database", "customer service"], "requirements": {"degrees": ["university degree"], "majors": ["finance", "business", "engineering", "computer science"], "languages": ["english", "chinese"], "language_level": ["proficiency"], "hard_skills": ["plus", "data management", "data warehouse", "tableau", "sql", "problem solving", "programming", "python"], "soft_skills": ["efficient", "communication skills", "integrity", "robust", "problem solving", "customer service", "attention to detail", "stable", "accurate"], "languages_combined": [{"language": "english", "language_level": ["proficiency"]}, {"language": "chinese", "language_level": ["proficiency"]}]}, "experience_required": {"duration": ["5-12 years", "1-3 years"], "field": ["business", "database", "financial"]}}, {"job_id": "100003009019015", "location_code": "hk", "company": "Walters People (HK)", "job_title": "DB2/Oracle Database Administrator DBA - Finance", "description": "My client is looking for a DB2 DBA to support their daily operation, maintenance and automation.\n\nResponsibilities:\n\nAdministration, maintenance, configuration, installation, and support of databases\nMaintaining the normal operation of the database\nPlatforms running including backup and restoration, troubleshooting and SQL performance tuning, monitoring usage, and capacity planning\nParticipating in technical and administration tasks of database upgrade, database security tools implementations, vulnerability checks, server upgrade, and migration\nProvide technical advice to the application team\nGather users' database requirements and design the proposed systems\nProvide database support in normal/off-hours and on-call attendance\n\nRequirements:\n\nHigher Diploma or above in Computer Science, Engineering, Information Technology;\nMinimum 8 years' DBA experience\nProficiency in the MSSQL, IBM DB2 pureScale database administration\nProficient in database architecture design, installation, migration, and upgrade\nSolid experience in Windows platforms and Linux\nGood command of Cantonese and English", "employment_types": ["Full Time", "Permanent"], "selling_points": ["DB2/Oracle DB", "Performance Tuning", "Disaster Recovery"], "locations": ["Not Specified"], "categories": ["Information Technology (IT)", "DBA", "Hardware"], "post_time": "2022-01-04T06:25:07Z", "salary": {"currency": "HKD", "max": 54999, "min": 45000, "period": "monthly", "term": null}, "salary_visible": true, "title_keywords": ["administrator"], "responsibilities": ["installation", "attendance", "maintenance", "maintaining", "configuration", "technical advice", "monitoring", "systems", "troubleshooting", "design", "planning", "databases", "database", "migration", "administration"], "requirements": {"degrees": ["higher diploma or above"], "majors": ["engineering", "computer science", "information technology"], "languages": ["cantonese", "english"], "language_level": ["good command"], "hard_skills": ["mssql", "linux"], "soft_skills": [], "languages_combined": [{"language": "cantonese", "language_level": ["good command"]}, {"language": "english", "language_level": ["good command"]}]}, "experience_required": {"duration": ["minimum 8 years"], "field": []}}, {"job_id": "100003009032250", "location_code": "hk", "company": "Excel Technology International (Hong Kong) Limited", "job_title": "BI Specialist / Data Analyst", "description": "Responsibilities:\n\nCarry out studies on new requirements, system design and enhancement of BI reporting tools for financial/banking applications.\nPerform development, testing, implementation support and maintenance on BI and data warehouse platform.\n\nRequirements:\n\nBachelor\u2019s degree in Computer Science, Information Technology or equivalent.\nExperience in BI implementation and data warehouse related projects.\nKnowledge in RPA or Advanced Analytics tools is a plus.\nStrong analytic skills, self-motivated and able to work under pressure.\nGood interpersonal skills and able to work in a team.\nGood command in written and spoken English and Chinese.\nFresh graduates with technical skills will also be considered.\n\nFor application, please send your resume with current and expected salary\u00a0to Human Resources Manager, Excel Technology International (HK) Limited, 5th Floor, 663 King\u2019s Road, North Point, Hong Kong or click Apply Now.\n\nData collected from applicants will be kept confidential and only be used for recruitment purpose.\n", "employment_types": ["Full Time", "Permanent"], "selling_points": ["Implement BI / data warehouse platform", "Experience in BI reporting and data analytics", "Fresh graduates are welcome"], "locations": ["Not Specified"], "categories": ["Professional Services", "Business Analysis / Data Analysis", "Information Technology (IT)", "DBA", "Data Scientist"], "post_time": "2022-01-07T10:33:11Z", "salary": {"currency": null, "max": null, "min": null, "period": "monthly", "term": null}, "salary_visible": false, "title_keywords": ["specialist", "data analyst"], "responsibilities": ["reporting", "maintenance", "data", "implementation", "testing", "system design", "banking"], "requirements": {"degrees": ["degree", "bachelor"], "majors": ["computer science", "information technology"], "languages": ["english", "chinese"], "language_level": ["good command"], "hard_skills": ["analytics tools", "plus", "bi", "excel", "data warehouse", "rpa", "analytic skills"], "soft_skills": ["self-motivated", "advanced", "interpersonal skills", "technical skills", "work under pressure"], "languages_combined": [{"language": "english", "language_level": ["good command"]}, {"language": "chinese", "language_level": ["good command"]}]}, "experience_required": {"duration": [], "field": ["related"]}}, {"job_id": "100003009032786", "location_code": "hk", "company": "ADECCO", "job_title": "Senior Data Scientist (Hadoop, MapReduce, up to 50k)", "description": "\n\nOur client is a leading integrated express logistics service provider in China, aims to provide customers with one-stop integrated logistics solutions.\n\nResponsibilities\n\nAssist team manager in mentoring junior staff of data science team\nKnowledge & statistics sharing and mentoring direct reports\nCollect data from different sources to enhance understanding of data trends.\nData cleansing\nTake part in upcoming projects with other departments of the company\nExperience\n\nAt least 3 years of professional experience with analytic projects.\nUnderstanding and application of Big Data and distributed computing principles (Hadoop and MapReduce).\nExperience using other statistical programming languages such as Python, SQL, and Hive.\nProven track record and ability to mentor and supervise junior resources on a project assignment basis\nEducation\n\nDegree holder in Computer Science, Business Analytics, Information Technology, or other related disciplines.\n\n\n\nInterested parties, please\u00a0CLICK HERE\u00a0to apply online. (Ref:JDB/IT-TT)\n\nPlease note that only short-listed candidates will be notified. All information gathered will be treated in strict confidence and solely used for recruitment purposes", "employment_types": ["Full Time", "Permanent"], "selling_points": ["Leading delivery and logistic company in HK", "Data analysis and team leading role", "Stable job with attractive salary and bonus"], "locations": ["Tsing Yi"], "categories": ["Information Technology (IT)", "DBA", "IT Project Management / Team Lead", "Data Scientist"], "post_time": "2022-01-07T16:59:54Z", "salary": {"currency": null, "max": null, "min": null, "period": "monthly", "term": null}, "salary_visible": false, "title_keywords": ["data scientist"], "responsibilities": ["data", "cleansing", "big data", "logistics", "reports"], "requirements": {"degrees": ["degree holder"], "majors": ["related disciplines", "business analytics", "computer science", "information technology"], "languages": [], "language_level": [], "hard_skills": ["python", "sql", "programming"], "soft_skills": [], "languages_combined": []}, "experience_required": {"duration": ["at least 3 years"], "field": ["sql", "programming"]}}, {"job_id": "100003009030015", "location_code": "hk", "company": "Hong Kong Baptist University", "job_title": "Senior AI System Engineer / AI System Engineer (PR0444/21-22)", "description": "AUGMENTED CREATIVITY LAB\n\nSenior AI System Engineer / AI System Engineer (in the rank of Research Fellow / Senior Research Assistant / Research Assistant) (PR0444/21-22)\n\nThe Augmented Creativity Lab at Hong Kong Baptist University invites applications for the Senior AI System Engineer/AI System Engineer position. The selected candidates will work with a group of renowned interdisciplinary researchers, focusing on an AI-based Art Tech project addressing human-machine co-creativity research. More information about the project could be found at https://research.hkbu.edu.hk/highlighted-projects/building-platform-technologies-for-symbiotic-creativity-in-hong-kong.\n\nThe appointees are expected to perform the following roles:\nDesign the architecture of demo/system/platform of symbiotic performance incorporating with AI research engineer, AI scientist and artist; and\nDevelop the demo/system/platform of symbiotic performance.\nPotential candidates should have/be:\n\nA master\u2019s degree in Computer Science, Electronic Engineering, Information Engineering, Mathematics or relevant disciplines with substantial years of related experience.\nCandidates with less experience but with strong R&D record may also be considered;\nSolid system development experience in one or more of the following domains: NLP, computer vision, streaming multimedia, animation generation, etc;\nExperience in Unity based animation generation; Hardware (like optical camera, depth camera, motion sensor or wearable devices devices) based programming experience is preferred;\nSolid hands-on coding skills on Python/C/C++/Java;\nFull-stack coding experience in mainstreaming front end and back end framework;\nFamiliar with deep learning frameworks of PyTorch / TensorFlow; GPU programming of CUDA is required and Mindspore is a plus;\nPreferably be a plus if familiar with multimedia programming of streaming encoding and decoding;\nPreferably familiar with the application of Deep Learning/algorithms, especially with foundation model, transformer model, GANs, GNNs, RL, etc.;\u00a0\nStrong self-motivation and be able to work independently;\nStrong communication skills, the ability to communicate effectively and manage relationships with stakeholders coming from both technical and non-technical backgrounds; and\nFluent in English with good written and oral communication skills.\nInitial appointment will be offered on a fixed-term contract of two years. Re-appointment thereafter will be subject to mutual agreement and availability of funding.\n\nRank and salary will be commensurate with qualifications and experience.\n\nApplication Procedure:\n\nApplications are invited to submit their applications at the HKBU e-Recruitment System (jobs.hkbu.edu.hk). Those not invited for interview 4 months after submission of application may consider their applications unsuccessful. Details of the University\u2019s Personal Information Collection Statement can be found at http://hro.hkbu.edu.hk/pics.\n\nThe University reserves the right not to make an appointment for the posts advertised, and the appointment will be made according to terms and conditions then applicable at the time of offer.\n\nReview of applications will be ongoing until the positions are filled.", "employment_types": ["Full Time"], "selling_points": ["A master\u2019s degree", "Experience in Unity based animation generation", "Full-stack coding experience"], "locations": ["Kowloon City"], "categories": ["Information Technology (IT)", "Application Specialist - Software", "DBA", "Network & System"], "post_time": "2022-01-07T06:35:55Z", "salary": {"currency": null, "max": null, "min": null, "period": "monthly", "term": null}, "salary_visible": false, "title_keywords": ["system engineer"], "responsibilities": ["review", "design", "develop", "coding", "hardware", "communication", "recruitment", "architecture", "animation"], "requirements": {"degrees": ["degree", "master"], "majors": ["mathematics", "engineering", "computer science"], "languages": ["english"], "language_level": ["good", "fluent"], "hard_skills": ["r&d", "java", "plus", "c++", "ai", "cuda", "hardware", "make", "c", "multimedia", "programming", "python", "unity"], "soft_skills": ["communication skills", "work independently", "oral", "deep", "hands-on", "self-motivation", "learning"], "languages_combined": [{"language": "english", "language_level": ["fluent", "good"]}]}, "experience_required": {"duration": [], "field": ["related", "engineering", "programming", "system development"]}}, {"job_id": "100003009032905", "location_code": "hk", "company": "Pinpoint Asia Limited", "job_title": "Data Governance Lead - Leading Financial Institution", "description": "Our client, a leading financial institution, is looking for a Data Governance Lead to join their Data Management team. Great exposure and career development opportunity. This role will take the lead of the entire firm-wide data governance practice.\n\nResponsibilities:\n\nLead the Data Governance function and team members to establish information management standards and data management lifecycle controls.\nDevelop and improve data governance standards including records management, data quality, data integrity, metadata, modeling, and data provisioning.\nAssist and Engage with the different Data Owners to steer the Information Architecture standards and frameworks, considering data residency regulations.\u00a0\nInterface with senior management and different data owners in the data committee.\nEvaluate and design data strategy with the team on Data Management and Data structure planning.\nManage the data solution and process delivery, in relation to the data governance function for data control.\n\nRequirements:\n\nAt least 10 years of experience in the IT data space.\nSounds experience in leading data quality and data protection management practices.\nParticipate in establishing Information Architecture standards, policy, design, and delivery.\nKnowledge of data-related regulatory requirements.\nStrong experience in adopting information assets between the business and technology enterprises.\nBachelor's Degree from a reputable University.\nExcellent communication skills in English\n\nIf this outstanding opportunity sounds like your next career move, please send your resume in Word format to Danny Kwan at resume(at)pinpointasia(dot)com and put Data Governance Lead - Leading Financial Institution in the subject header.\n\nData provided is for recruitment purposes only.", "employment_types": ["Full Time", "Permanent"], "selling_points": ["Data Governance", "Leadership role", "Senior Stakeholder Management"], "locations": ["Not Specified"], "categories": ["Information Technology (IT)", "DBA", "IT Management", "Data Scientist"], "post_time": "2022-01-08T02:26:35Z", "salary": {"currency": "HKD", "max": 119999, "min": 70000, "period": "monthly", "term": null}, "salary_visible": true, "title_keywords": ["lead"], "responsibilities": ["regulations", "management", "control", "data", "quality", "design", "develop", "evaluate", "process delivery", "senior management", "architecture", "planning"], "requirements": {"degrees": ["degree", "bachelor"], "majors": [], "languages": ["english"], "language_level": ["excellent"], "hard_skills": ["word"], "soft_skills": ["communication skills"], "languages_combined": [{"language": "english", "language_level": ["excellent"]}]}, "experience_required": {"duration": ["at least 10 years"], "field": ["business", "management", "it"]}}, {"job_id": "100003009030037", "location_code": "hk", "company": "Hong Kong Baptist University", "job_title": "Senior AI Research Engineer / AI Research Engineer (PR0443/21-22)", "description": "AUGMENTED CREATIVITY LAB\n\nSenior AI Research Engineer / AI Research Engineer (in the rank of Research Fellow / Senior Research Assistant / Research Assistant) (PR0443/21-22)\n\nThe Augmented Creativity Lab at Hong Kong Baptist University invites applications for the Senior AI Research Engineer / AI Research Engineer position. The selected candidates will work with a group of renowned interdisciplinary researchers, focusing on an AI-based Art Tech project addressing human-machine co-creativity research. More information about the project could be found at https://research.hkbu.edu.hk/highlighted-projects/building-platform-technologies-for-symbiotic-creativity-in-hong-kong.\n\nThe appointees are expected to perform the following roles:\nDevelop new algorithms for AI art content generation using Deep Learning;\nDevelop demo/system/platform of symbiotic performance incorporating with AI system engineer, AI scientist and artist; and\nWrite paper/patent and release open source code.\nPotential candidates should have/be:\n\nPhD or master\u2019s degree in Computer Science, Electronic Engineering, Information Engineering, Mathematics or relevant disciplines with substantial years of related experience. Candidates with less experience but with strong research record may also be considered;\nSolid R&D experience in one or more of the following domains: content generation, NLP, computer vision, etc.;\nFamiliar with deep learning/algorithms, especially on foundation model, transformer model, GANs, GNNs, RL, etc.;\nFamiliar with deep learning frameworks of PyTorch/TensorFlow, GPU programming of CUDA. Knowledge of Mindspore is a plus;\nSolid coding skills in Python/C/C++/Java;\nStrong self-motivation and be able to work independently;\nStrong communication skills, the ability to communicate effectively and manage relationships with stakeholders coming from both technical and non-technical backgrounds; and\nFluent in English, good written and oral communication skills.\nInitial appointment will be offered on a fixed-term contract of two years. Re-appointment thereafter will be subject to mutual agreement and availability of funding.\n\nRank and salary will be commensurate with qualifications and experience.\n\nApplication Procedure:\n\nApplications are invited to submit their applications at the HKBU e-Recruitment System (jobs.hkbu.edu.hk). Those not invited for interview 4 months after submission of application may consider their applications unsuccessful. Details of the University\u2019s Personal Information Collection Statement can be found at http://hro.hkbu.edu.hk/pics.\n\nThe University reserves the right not to make an appointment for the posts advertised, and the appointment will be made according to terms and conditions then applicable at the time of offer.\n\nReview of applications is ongoing until the positions are filled.", "employment_types": ["Full Time"], "selling_points": ["PhD or master\u2019s degree", "Solid R&D experience", "Develop new algorithms"], "locations": ["Kowloon City"], "categories": ["Information Technology (IT)", "DBA", "Technical Writing", "Data Scientist"], "post_time": "2022-01-07T06:39:58Z", "salary": {"currency": null, "max": null, "min": null, "period": "monthly", "term": null}, "salary_visible": false, "title_keywords": ["engineer"], "responsibilities": ["review", "coding", "develop", "communication", "recruitment"], "requirements": {"degrees": ["degree", "master"], "majors": ["mathematics", "engineering", "computer science"], "languages": ["english"], "language_level": ["good", "fluent"], "hard_skills": ["r&d", "plus", "java", "c++", "ai", "cuda", "make", "c", "programming", "python", "code"], "soft_skills": ["communication skills", "work independently", "oral", "deep", "self-motivation", "learning"], "languages_combined": [{"language": "english", "language_level": ["fluent", "good"]}]}, "experience_required": {"duration": [], "field": ["related", "research", "engineering"]}}, {"job_id": "100003009027405", "location_code": "hk", "company": "GoAnimate Hong Kong Limited", "job_title": "Senior Engineer (Billing)", "description": "About the company\n\n\n\n\nAt\u00a0VYOND, our mission is to put the power of video in the hands of everyone.\u00a0Vyond\u00a0allows people of all skill levels in all industries and job roles to create dynamic and powerful media. With features that go\u00a0beyond\u00a0moving text and images, you can build character-driven stories or compelling data visualizations that engage audiences and deliver results.\n\nFounded as GoAnimate in 2007,\u00a0Vyond\u00a0has helped Global 2000 organizations, small businesses, and individuals produce more than 30 million videos.\n\nWith offices in Silicon Valley, Hong Kong, and Taiwan,\u00a0Vyond\u00a0employs a team of people whose creativity extends well\u00a0beyond\u00a0our office walls. We are passionate about the power of video and how it makes the static dynamic and transforms the mundane into the captivating.\n\n\n\nVYOND\u2122 is a trademark of GoAnimate, Inc.\u00a0\u00a0\n\nDescription\n\nSenior Engineer (Billing) assists in managing the billing and subscription management system. He / She also assists internal staff to make sure quotes and subscription data are set up correctly.\n\n\n\n\nResponsibilities\n\n\n\n\nWork with different internal teams to resolve quotation, billing, and subscription related issues.\n\nGather requirements and design solutions for improving the subscription management systems.\n\nCollaborate with Engineering, Finance, Billing, Product and Data teams to prepare functional / technical documentation, and help implement solutions.\n\nMonitor billing and subscription data to make sure subscriptions are set up correctly inside both the subscription management system and the Vyond platform.\n\n\n\n\nRequirements\n\n\n\n\nDegree in Computer Science or related field.\n\nTechnical proficiency on Node.js.\n\nFamiliar with RESTful API design and implementation.\n\nFamiliar with database design and operation.\n\nExperience in subscription management systems is an advantage.\n\nKnowledge on Financial data processing is an advantage.\n\nKnowledge on Data Protection regulations is an advantage.\n\nKnowledge on the Salesforce ecosystem is an advantage.\n\nKnowledge on Apex Programming is an advantage.", "employment_types": ["Full Time", "Permanent"], "selling_points": ["Degree in Computer Science", "Technical proficiency on Node.js", "English mandatory"], "locations": ["Central & Western Area"], "categories": ["Information Technology (IT)", "DBA", "Software Development", "Others"], "post_time": "2022-01-06T09:54:23Z", "salary": {"currency": null, "max": null, "min": null, "period": "monthly", "term": null}, "salary_visible": false, "title_keywords": ["senior engineer"], "responsibilities": ["collaborate with", "management", "design solutions", "data", "quotation", "teams", "systems", "monitor", "documentation"], "requirements": {"degrees": ["degree"], "majors": ["computer science"], "languages": [], "language_level": [], "hard_skills": ["restful api", "salesforce", "apex", "programming", "processing"], "soft_skills": [], "languages_combined": []}, "experience_required": {"duration": [], "field": ["management"]}}, {"job_id": "100003009024795", "location_code": "hk", "company": "Sun Hung Kai Properties Ltd", "job_title": "ASSISTANT DATA ANALYST", "description": "Requirements:\n\n\nBachelor\u2019s degree in Business Administration, Economics, Statistics, Information Technology, Computer Science or related disciplines\n2-3 years\u2019 experience in research or data analysis\nKnowledge on SQL, Excel, Powerpoint, Access preferred\nProven English proficiency\nDetail-minded with strong analytical skills and good report writing skills\nWilling to work overtime and on weekends & public holidays\n\nResponsibilities:\n\n\nAssist in data management for Hong Kong residential property market and compile timely reports\nMaintain and enrich in-house database, including data collection from different sources and off-site work\nAssist in ad hoc projects as assigned\n\nGood remuneration and attractive fringe benefits will be offered to the successful applicant. Interested parties please apply with full resume, present and expected salary, available date by clicking \"Apply Now\".\n\nFor further information, please visit our company website: www.shkp.com.\n\nWe are an equal opportunity employer and welcome applications from all qualified candidates. All personal data collected will be used for recruitment purpose only.\u00a0 Applicants not hearing from us within 3 months may consider their applications unsuccessful.\u00a0 All personal data collected will be destroyed within 24 months.", "employment_types": ["Full Time", "Permanent"], "selling_points": ["Data management for HK residential property market", "Knowledge on SQL, Excel, PPT, Access preferred", "Willing to work overtime and on weekends"], "locations": ["Wan Chai"], "categories": ["Professional Services", "Business Analysis / Data Analysis", "Information Technology (IT)", "DBA", "Property / Real Estate", "Others"], "post_time": "2022-01-06T02:32:43Z", "salary": {"currency": null, "max": null, "min": null, "period": null, "term": null}, "salary_visible": false, "title_keywords": ["data analyst", "assistant"], "responsibilities": ["management", "data", "timely reports", "maintain", "ad hoc projects", "database", "data collection"], "requirements": {"degrees": ["degree", "bachelor"], "majors": ["business administration", "economics", "statistics", "information technology", "related disciplines", "computer science"], "languages": ["english"], "language_level": ["proficiency"], "hard_skills": ["excel", "analysis", "powerpoint", "analytical skills", "sql", "writing skills"], "soft_skills": ["detail-minded", "work overtime", "writing skills", "analytical skills"], "languages_combined": [{"language": "english", "language_level": ["proficiency"]}]}, "experience_required": {"duration": ["2-3 years"], "field": ["data analysis", "research"]}}, {"job_id": "100003009024019", "location_code": "hk", "company": "Venturenix Limited", "job_title": "Data Governance (Senior) Manager | up to HKD 900k per annum | Listed Company", "description": "Our client, a listed conglomerate, is looking for a (Senior) Manager of Data Governance. He/she will be responsible for a loyalty program and the digital transformation project.\n\nYour duties\n\nDesign and responsible for the data governance framework, focusing on data quality and security\nLiaise with Business and Functional stakeholders / vendors / tech team for data protection, storage and operations\nDefine data metrics and performance indicators\nRequirements\n\n6+ years of experience in large-scale data / data governance / data management\nLeading experience\nAbility to handle complaints\nExperience in project management\nInterested parties please apply directly.", "employment_types": ["Full Time", "Permanent"], "selling_points": ["Data Governance / Data Management", "Listed Conglomerate", "AWS / Loyalty / Digital Transformation"], "locations": ["Quarry Bay"], "categories": ["Information Technology (IT)", "DBA", "Data Scientist"], "post_time": "2022-01-05T10:24:49Z", "salary": {"currency": null, "max": null, "min": null, "period": "monthly", "term": null}, "salary_visible": false, "title_keywords": ["manager"], "responsibilities": ["data", "operations", "quality", "design", "liaise with"], "requirements": {"degrees": [], "majors": [], "languages": [], "language_level": [], "hard_skills": ["project management", "data management"], "soft_skills": ["project management"], "languages_combined": []}, "experience_required": {"duration": ["6+ years"], "field": ["project management", "management"]}}, {"job_id": "100003009025611", "location_code": "hk", "company": "Links International", "job_title": "Sr. Infrastructure Specialist", "description": "Responsibilities\n\nDesign and develop security strategy to protect the company's IT infrastructure\nDesign, develop, and implement IT disaster recovery strategy to protect and minimize downtime and data loss in the event of a disaster\nManage, monitor. and optimize various cloud platform (e.g. AWS, O365)\nProtect the company's data by using various backup strategies\n\nRequirements\n\nDegree or above in Computer Science, Information Technology, or relevant discipline\n5+ years hands-on working experience in IT networking, security, server, and storage\nExperience in IT security products (e.g. EPP, EDR, Endpoint, patching tools, etc.)\nHands-on administering and maintaining Active Directory, O365, etc.\nKnowledge/experience in IT storage products (e.g. HPE 3PAR, NAS, DAS, etc.)\nGood experience in network and system monitoring tools, group policy, Powershell scripting, etc.\nExperience on project management and vendor management\nGood communication and interpersonal skills with good analytic and problem-solving capacity\nFluent in English and Cantonese\nImmediately available is highly preferred", "employment_types": ["Full Time", "Permanent"], "selling_points": ["Min. 5 yrs experience in Infrastructure", "Experience in network, cybersecurity, etc.", "Exp. in Azure platform is an advantage"], "locations": ["Not Specified"], "categories": ["Information Technology (IT)", "DBA", "Security", "Network & System"], "post_time": "2022-01-06T05:44:27Z", "salary": {"currency": "HKD", "max": 44999, "min": 30000, "period": "monthly", "term": null}, "salary_visible": true, "title_keywords": ["specialist"], "responsibilities": ["it infrastructure", "data", "design and develop", "monitor", "design", "develop"], "requirements": {"degrees": ["degree or above"], "majors": ["computer science", "information technology"], "languages": ["cantonese", "english"], "language_level": ["fluent"], "hard_skills": ["o365", "active directory", "nas", "problem-solving", "vendor", "project management", "powershell", "server"], "soft_skills": ["problem-solving", "project management", "hands-on", "communication and interpersonal skills", "active"], "languages_combined": [{"language": "cantonese", "language_level": ["fluent"]}, {"language": "english", "language_level": ["fluent"]}]}, "experience_required": {"duration": ["5+ years"], "field": ["management", "project management", "it", "security", "it networking"]}}, {"job_id": "100003009016375", "location_code": "hk", "company": "The Bank of East Asia, Limited", "job_title": "Senior Data Architect", "description": "Information Technology Department\n\nSenior Data Architect\u00a0 (Job ID: 3276)\n\nResponsibilities\n\nTo be a team member of Information Technology Department\nTo assist the architecture team in creating enterprise conceptual logical and physical data models\nTo produce details of proposal while applying data architecture best practices and keeping data warehouse big picture and direction under consideration with justifications\nTo validate conceptual logical data models with business subject matter experts\nTo assist in developing database design and architecture documentation for development and management\nTo support in building an enterprise data management framework and blueprint\nTo provide technical support to production system to ensure smooth operation within the Bank\n\n\nRequirements\n\nUniversity graduate in Information Technology, Computer Science or in a related discipline\nMinimum 10 years\u2019 working experience in data or infrastructure architecture from recognized establishments in financial services and/or Fintech related industries\nExperience in Cloud data architecture\nExperience in AI/ML architecture and DataOps, e.g., Kubeflow, Airflow.\nExperience in relational database such as SQL server, Oracle and Teradata\nExcellent communication and negotiation skills\nProficient in\u00a0both spoken and written English and Chinese\n\n\u00a0Candidates with less experience will be considered as Data Architect\n\n\n\nPlease apply online via the BEA Careers website at https://careers.hkbea.com/psp/hcmprd/EMPLOYEE/HRMS/c/HRS_HRAM.HRS_APP_SCHJOB.GBL?Page=HRS_APP_JBPST&Action=UFOCUS=Applicant&SiteId=1&JobOpeningId=3276&PostingSeq=1 or by clicking the \"Apply Now\" button below. Kindly note that if you are a new user, you have to first create your User Profile before you can apply.\nPersonal data provided by job applicants will be used for recruitment purposes only and will be treated in accordance with the Bank's Personal Information Collection (Employees) Statement and Privacy Policy Statement. Applicants who are not invited for interviews within six weeks may consider their applications unsuccessful and the personal data collected will be destroyed after six months.", "employment_types": ["Full Time", "Permanent"], "selling_points": ["Create & Validate enterprise logical data model", "Cloud Architecture (in AWS, Azure) & Related DB", "Experienced in data architecture in FI and bank"], "locations": ["Not Specified"], "categories": ["Information Technology (IT)", "DBA", "Others", "Data Scientist"], "post_time": "2022-01-03T08:57:30Z", "salary": {"currency": null, "max": null, "min": null, "period": null, "term": null}, "salary_visible": false, "title_keywords": [], "responsibilities": ["management", "data", "technical support", "developing", "design", "database", "documentation", "architecture"], "requirements": {"degrees": ["university graduate"], "majors": ["computer science", "information technology"], "languages": ["english", "chinese"], "language_level": ["proficient"], "hard_skills": ["ai", "airflow", "ml", "sql", "c", "server", "oracle"], "soft_skills": ["communication", "negotiation skills"], "languages_combined": [{"language": "english", "language_level": ["proficient"]}, {"language": "chinese", "language_level": ["proficient"]}]}, "experience_required": {"duration": ["minimum 10 years"], "field": ["related", "infrastructure", "sql", "financial services", "database"]}}, {"job_id": "100003009021858", "location_code": "hk", "company": "Aedas Limited", "job_title": "System Analyst / Analyst Programmer", "description": "Responsibilities:\n\nCommunicate and analyze user requirements and design system solutions\nProvide hands-on Technical design, leading and development of .NET based system\nMaintenance support and end to end troubleshoot\nAssist in database administration\nCreation of technical documentation to accompany source code, user manual documentation\nCoordinate system testing, deployment and system upgrade\n\n\u00a0Requirements:\n\nDegree in Computer Science or related disciplines\n5 years development experience in Web Application and Database development\nStrong experience in VB .NET, ASP.NET, HTML, JavaScript, JQuery and Crystal Report\nFamiliar with MS-SQL, T-SQL\nKnowledge in SharePoint development is an advantage\nExcellent analytical, problem-solving, teamwork and interpersonal skills\nWilling to take challenge and able to work under pressure\nGood communication skill in Cantonese and English\nCandidate with less experience will be considered as Analyst Programmer\n\nAedas\u00a0provides opportunities for long term career development with an expanding international practice. We offer attractive compensation and benefit package. Interested parties please send detailed CV, current & expected salary and availability by clicking\u00a0Apply now.\n\nAedas is an Equal Opportunity Employer\n(Data collected will be used for recruitment purpose only)", "employment_types": ["Full Time", "Permanent"], "selling_points": ["Degree in Computer Science / IT related discipline", "5 yr exp in Web Application & Database Development", "5-day work week, Medical & Dental Insurance"], "locations": ["Quarry Bay"], "categories": ["Information Technology (IT)", "DBA", "Software Development", "Others"], "post_time": "2022-01-05T04:38:00Z", "salary": {"currency": null, "max": null, "min": null, "period": "monthly", "term": null}, "salary_visible": false, "title_keywords": ["analyst programmer", "system analyst"], "responsibilities": ["maintenance support", "design", "testing", "coordinate", "troubleshoot", "database", "documentation", "administration"], "requirements": {"degrees": ["degree"], "majors": ["related disciplines", "computer science"], "languages": ["cantonese", "english"], "language_level": ["good"], "hard_skills": ["web", "jquery", "t-sql", "problem-solving", "html", "javascript", "ms-sql"], "soft_skills": ["problem-solving", "communication skill", "teamwork", "interpersonal skills", "work under pressure"], "languages_combined": [{"language": "cantonese", "language_level": ["good"]}, {"language": "english", "language_level": ["good"]}]}, "experience_required": {"duration": ["5 years"], "field": ["development", "database"]}}, {"job_id": "100003009019878", "location_code": "hk", "company": "World Wide Fund For Nature Hong Kong", "job_title": "Senior Officer/ Officer, Data Operations and Analysis", "description": "Principal Functions\u00a0and Purpose of the position:\nAssist the organization to perform data analysis of the database of WWF HK to increase efficiency and improve performance of fundraising/donor engagement/event participation by discovering patterns in data, enabling insight analytics with dashboards and reports\u00a0\nMajor Duties and Responsibilities:\nDesign, analyze, develop, and evaluate data mining in the Logical Data Warehouse (LDW) environment in superset and Raiser Edge (RE) database to support the development of WWF HK\nEnsure the payment transaction process, generate accurate financial and analytical reports and ensure that the database effectively captures donor gift information; develop reports to validate gift data\nCreate different queries to extract data from the database to suit the needs of stakeholders.\nRespond to ad-hoc requests for analysis, standardizing and automating procedures such as\u00a0integrating with superset Online Analytical Processing (OLAP) tools for ad-hoc reports or in-depth analysis\u00a0for responding to stakeholders\u2019 requests.\nMaintain documentation and source control for the whole LDW operation including necessary database view, diagram, and SQL\nProvide operation and analytical support to those teams using RE and related tools\nLiaise with external agencies to ensure data is transferred and processed efficiently and in accordance with our data protection obligations working with colleagues.\nAssist in importing process of records from mailing appeals and other fundraising programs\nAssist in the project for changing/upgrading the database system\nRequired Functional Skills:\nDegree holder with experience in Information Technology, or in a related area is preferred.\n3-5 years of relevant experience in data operations and analysis.\nKnowledge and experience of Raiser Edge will be a definite advantage.\nProficient in computer skills, including MS Word, Excel, SQL query is highly preferred.\u00a0\nperform data analysis of the database\n\nHighly motivated, willing to learn, good teamwork and able to work under high pressure\nGood written and spoken English skill\nImmediate available is highly preferred\nWorking Location:\u00a0Kwai Hing\nWe offer a 5-day work week and competitive rewards and benefits package to the right candidate.\u00a0\u00a0Interested party please apply with full resume, stating present and expected salary and available date. Only shortlisted applicants will be notified.\nWWF, the World Wide Fund for Nature, a non-profit organization, headquartered in Switzerland, is one of the world\u2019s most recognizable and respected independent conservation organizations.\u00a0\nTo find out more about us, please visit our website at\u00a0wwf.org.hk\u00a0now.", "employment_types": ["Full Time", "Permanent"], "selling_points": ["Perform data analysis and management", "Generate accurate financial and analytical reports", "IT background with SQL query experience"], "locations": ["Kwai Hing"], "categories": ["Information Technology (IT)", "DBA", "Product Management / Business Analyst", "Data Scientist"], "post_time": "2022-01-04T09:28:17Z", "salary": {"currency": null, "max": null, "min": null, "period": "monthly", "term": null}, "salary_visible": false, "title_keywords": ["senior officer", "officer", "operations"], "responsibilities": ["ad-hoc", "control", "maintain documentation", "data", "operations", "analysis", "procedures", "teams", "design", "develop", "data analysis", "evaluate", "payment", "liaise with", "reports", "database", "ad-hoc requests", "data mining"], "requirements": {"degrees": ["degree holder"], "majors": ["information technology"], "languages": ["english"], "language_level": ["good"], "hard_skills": ["excel", "documentation", "data warehouse", "analysis", "sql", "computer skills", "data mining", "processing", "ms word"], "soft_skills": ["teamwork", "willing to learn", "motivated", "work under high pressure", "accurate"], "languages_combined": [{"language": "english", "language_level": ["good"]}]}, "experience_required": {"duration": ["3-5 years"], "field": ["related", "relevant experience", "information technology"]}}, {"job_id": "100003009024742", "location_code": "hk", "company": "Sun Hung Kai Properties Ltd", "job_title": "SYSTEM ANALYST", "description": "Requirements:\n\n\nBachelor\u2019s degree in Information Technology, Computer Science or related disciplines\nMinimum 8 years\u2019 experience in database programming, ETL process and data analytics\nGood command of SQL, Excel, VBA, ETL. Knowledge in Python, R, Tableau a plus\nExperience in data analytics technologies, e.g. Redshift, AWS an advantage\nProven English proficiency\nDetail-minded, self-motivated with good analytical & problem solving skills\nGood communication & interpersonal skills\n\nResponsibilities:\n\n\nSupport to build, develop and maintain the new centralized property-related data platform\nResponsible for ETL programming development, data warehouse maintenance, date integration projects, etc\nOversee and manage the work-flow of data quality management, data cleansing and data exchanges processes by designing and implementing different rules and best practice\nParticipate in ad-hoc data analytics projects and perform data extraction to facilities analysis\nCompile system documentation such as specifications and manuals\n\n(Candidates with less experience will be considered for Senior Analyst Programmer / Analyst Programmer.)\n\nGood remuneration and attractive fringe benefits will be offered to the successful applicant. Interested parties please apply with full resume, present and expected salary, available date by clicking \u201cApply Now\u201d.\n\nFor further information, please visit our company website:\u00a0http://www.shkp.com/.\n\nWe are an equal opportunity employer and welcome applications from all qualified candidates. All personal data collected will be used for recruitment purpose only.\u00a0 Applicants not hearing from us within 3 months may consider their applications unsuccessful.\u00a0 All personal data collected will be destroyed within 24 months.", "employment_types": ["Full Time", "Permanent"], "selling_points": ["8 yrs\u2019 exp in database programming, ETL process", "Support to develop property-related data platform", "Data warehouse maintenance, integration projects"], "locations": ["Wan Chai"], "categories": ["Information Technology (IT)", "DBA", "Technical / Functional Consulting", "Data Scientist"], "post_time": "2022-01-06T02:23:36Z", "salary": {"currency": null, "max": null, "min": null, "period": null, "term": null}, "salary_visible": false, "title_keywords": ["system analyst"], "responsibilities": ["ad-hoc", "management", "system documentation", "maintenance", "data", "cleansing", "analysis", "quality", "develop", "maintain", "specifications", "designing"], "requirements": {"degrees": ["degree", "bachelor"], "majors": ["related disciplines", "computer science", "information technology"], "languages": ["english"], "language_level": ["proficiency"], "hard_skills": ["vba", "excel", "plus", "data analytics", "tableau", "aws", "sql", "database programming", "python", "r", "problem solving skills"], "soft_skills": ["detail-minded", "self-motivated", "communication", "interpersonal skills", "problem solving skills"], "languages_combined": [{"language": "english", "language_level": ["proficiency"]}]}, "experience_required": {"duration": ["minimum 8 years"], "field": ["programming", "database"]}}, {"job_id": "100003009011533", "location_code": "hk", "company": "IT Solutions Ltd.", "job_title": "Oracle Database Administrator (DBA) \u2013 Major Bank", "description": "We are searching on behalf of a Major Bank\u00a0for high-calibre\u00a0Oracle DBA\u00a0to\u00a0provide technical support and advice of Database management services\u00a0for a Major Bank.\n\n\nResponsibilities:\u00a0\n\nDatabase administration of Oracle.\n\nMonitor,\u00a0tuning and optimization\u00a0of database systems.\nSQL design & performance tuning.\nOperation, planning & design of multiple enterprise Servers.\nProvide trend analysis to management team.\nImprove and maintain of databases.\n\nRequirements:\u00a0\n\nDegree or above in Computer Science or related discipline.\nExperience in database administration of Oracle Database.\nNo banking experience required.\n\nBenefits:\n\nAttractive remunerations will be offered to the successful candidates.\nExcellent opportunity to further develop your professional skills in a bank.\n\nIf you are interested, please send your resume in MS Word format, specifying your availability, current and expected salaries to:\n\njobs @itsolutions.com.hk\n\nor\n\nPlease click the Apply Now button and attach your cv in MS Word Format, specifying your availability, current and expected salaries.\n\nPersonal data collected will be used for recruitment purposes only.\n\nIT Solutions Ltd.\n\nSuite 2102\n21/F Lucky Building\n39 Wellington Street\nCentral, Hong Kong\n\n(P.S. We do not process applications from overseas for this position)", "employment_types": ["Full Time"], "selling_points": ["5-day Week", "DBA: MySQL/ Mongo/ MS SQL Server/Oracle UDB Server", "Good career prospect in a Major Bank"], "locations": ["Not Specified"], "categories": ["Banking / Finance", "Others", "Information Technology (IT)", "DBA", "Support"], "post_time": "2022-01-02T14:06:35Z", "salary": {"currency": null, "max": null, "min": null, "period": "monthly", "term": null}, "salary_visible": false, "title_keywords": ["administrator"], "responsibilities": ["management team", "analysis", "systems", "monitor", "design", "planning", "maintain", "database", "databases", "administration"], "requirements": {"degrees": ["degree or above"], "majors": ["computer science"], "languages": [], "language_level": [], "hard_skills": ["no", "oracle"], "soft_skills": [], "languages_combined": []}, "experience_required": {"duration": [], "field": ["banking experience", "database", "administration"]}}, {"job_id": "100003009024944", "location_code": "hk", "company": "HKT Consumer Group", "job_title": "Senior Programmer", "description": "Your role:\n\nLead MIS team to provide in-house systems support to both sales and back-end teams\nDevelop, test, implement and maintain in-house web-based applications\nDevelop technical specifications that align with business requirements\nProvide technical support and training on system applications to end users\nAssist in developing ad-hoc reports\n\nTo succeed in this role:\n\nHigher Diploma or above in Information Technology, Computer Science or related discipline\nMinimum 1 year in IT field, with experience in web applications development\nHands on experience in HTML and Web Services is required\nProficient in Visual Studio (visual basic), PHP, server management, SQL & database and schema design (for table creation) would be an advantage\nKnowledge in VBA in excel and FoxPro is a plus\nStrong analytical and problem solving skills\nGood command of written and spoken English and Chinese", "employment_types": ["Full Time"], "selling_points": [], "locations": ["Kowloon Bay"], "categories": ["Information Technology (IT)", "DBA", "IT Auditing"], "post_time": "2022-01-06T02:58:13Z", "salary": {"currency": null, "max": null, "min": null, "period": "monthly", "term": null}, "salary_visible": false, "title_keywords": ["senior programmer"], "responsibilities": ["ad-hoc", "management", "technical support", "systems", "teams", "developing", "design", "develop", "maintain", "specifications", "reports", "database", "visual"], "requirements": {"degrees": ["higher diploma or above"], "majors": ["computer science", "information technology"], "languages": ["english", "chinese"], "language_level": ["good command"], "hard_skills": ["vba", "excel", "plus", "web applications", "php", "html", "sql", "web-based applications", "visual basic", "foxpro", "server", "problem solving skills", "web services"], "soft_skills": ["analytical and problem solving skills", "hands on"], "languages_combined": [{"language": "english", "language_level": ["good command"]}, {"language": "chinese", "language_level": ["good command"]}]}, "experience_required": {"duration": ["minimum 1 year"], "field": ["development", "it", "web applications"]}}, {"job_id": "100003009010274", "location_code": "hk", "company": "China CITIC Bank International Limited", "job_title": "Senior IT Infrastructure Specialist (Database)", "description": "Responsibilities:\nConfiguring and maintaining reliable supports of Oracle/ MYSQL/ MSSQL of the large scale enterprise databases\nMonitoring database to ensure minimum impacts to database performance\nMaintaining the normal database operation including backup and restoration, troubleshooting and SQL performance tuning and monitoring usage etc.\nParticipating in technical and administration tasks of database upgrade, vulnerability checks, migration and troubleshooting etc.\nAssist in SQL optimization and other database performance\nProvide DBA support\nRequirements:\nAt least 4 years\u2019 experience as a Database Administrator, with a degree holder or above in Computer Science, Information Technology or related disciplines;\nExperience with database software Oracle RAC/ MYSQL master-slave replication/ MSSQL, including analysing performance bottleneck and troubleshooting;\nProficient in database architecture design, installation, migration, and upgrade;\nKnowledge of cloud-based database services will be an advantage;\nFamiliar with Non-SQL data stores, such as Redis will be an advantage; and\nFluent spoken and written in both English and Chinese.\nFor more details about career opportunities with the Bank, please visit our website http://www.cncbinternational.com/careers/en/index.jsp. Please apply with full resume stating current and expected salaries.\nPersonal data collected will be used for recruitment related purposes only. Applicants not invited for interview within 6 weeks may consider their applications unsuccessful. However, applicants may be considered for other suitable positions within the Group for a period of not more than 2 years. Personal data will be destroyed at any time after 3 months.\nChina CITIC Bank International is committed to being an equal opportunities employer and intends to provide a work environment free of unlawful discrimination or harassment. All employment decisions will be made in a non-discriminatory manner.\u00a0", "employment_types": ["Full Time", "Permanent"], "selling_points": ["Maintaining the normal database operation", "Provide DBA support", "At least 4 years\u2019 experience as a Database Admin"], "locations": ["Not Specified"], "categories": ["Information Technology (IT)", "DBA", "Software Development", "Technical / Functional Consulting"], "post_time": "2021-12-31T03:25:35Z", "salary": {"currency": null, "max": null, "min": null, "period": "monthly", "term": null}, "salary_visible": false, "title_keywords": ["specialist"], "responsibilities": ["maintaining", "monitoring", "troubleshooting", "configuring", "databases", "database", "migration", "administration"], "requirements": {"degrees": ["master", "degree holder"], "majors": ["related disciplines", "computer science", "information technology"], "languages": ["english", "chinese"], "language_level": ["fluent"], "hard_skills": ["mssql", "sql", "oracle"], "soft_skills": ["committed", "troubleshooting"], "languages_combined": [{"language": "english", "language_level": ["fluent"]}, {"language": "chinese", "language_level": ["fluent"]}]}, "experience_required": {"duration": ["at least 4 years"], "field": ["related", "troubleshooting", "database", "information technology"]}}, {"job_id": "100003009015439", "location_code": "hk", "company": "Hong Kong Broadband Network Limited", "job_title": "Data Architect / Analytics Solution Architect (Data and Analytics)", "description": "To be part of our mission, we are looking for a\u00a0Data Architect to\u2026\n\nWork closely with business divisions and IT to drive digital transformation.\u00a0\u00a0\u00a0\nJoin a dynamic & energetic entrepreneur team!\u00a0\nSupport full cycle of project management with Agile/Scrum approach.\u00a0\nCreate innovations with latest technologies.\u00a0\nWhat efforts you need to make for this role?\n\nSupport large-scale data management framework, implement batch/real-time data pipelines and data models on Hybrid-Cloud environment\nResponsible for visualize, design and prepare data in a framework that can be used by data scientists, data engineers or data analysts\nTranslate business requirements into technology requirements and define data standards and principles\nBridging the gap between business goals and technology, ensuring proper execution of duties and alignment with business vision and objectives\nCollaborating and coordinating with multiple departments, stakeholders, partners and external vendors\n\n\u00a0Let\u2019s check if you are/ have\u2026\n\nBachelor's degree in a Data Engineering, Data Analytics, Computer Science, or related field\nMinimum 4 years of experience with Data Lake/Cloud Data Platform implementation, have a keen understanding of Data Lake Architecture concept\nExperience in cloud-based design and development, preferably AWS or Azure core services\nStrong understanding of data architecture/data modeling/data governance/metadata management/data asset management\nKnowledge in NoSQL, data streaming, data scraping, elastic scaling, data security/governance, DataOps and standard API interfaces\nExperience in SQL/Python/Spark/node.js/Hadoop/Git, agile development processes and data-driven development\nKnowledge in Data Visualization Tool such as Tableau and Power BI\nProfessional, passionate, innovative, self-motivated and able to present solutions to diverse groups of stakeholders\nGood command in both spoken and written Chinese and English\nWe offer great training, a well-defined career path and a fun and challenging work environment where the right candidate will learn and grow with the company\n\n\n\u00a0What you get in return\u2026\n\n\nApart from competitive salary package and benefits, in HKBN, you will work flexibly under our Talent-first\u00a0culture\u00a0and we uphold Life-Work Priority. Examples of our flexible initiatives:\n\nFive-day work week and shorten working hours (8 hours including 1 hour 15 mins meal break)\nHalf Day Off Friday once a month (compensation leave for Talents who work on shift)\nHalf Day Off on Festival Eve (compensation leave for Talents who work on shift)\nUnique leaves arrangement: Family-care leave, Anniversary leave, Bonus leave, Volunteer leave, Sabbatical leave, etc.\nComprehensive medical and life insurance coverage\nUpgraded maternity leave and paternity leave\nDiscounted Talent plan offers including broadband and mobile plans and other promoted products\nEducation subsidies and Examination leave\nYear-end discretionary bonus", "employment_types": ["Full Time", "Permanent"], "selling_points": ["Data Engineering", "Experience in cloud-based design and development", "Knowledge in NoSQL and data streaming"], "locations": ["Kwai Hing"], "categories": ["Information Technology (IT)", "DBA", "Others", "Data Scientist"], "post_time": "2022-01-03T06:43:43Z", "salary": {"currency": null, "max": null, "min": null, "period": "monthly", "term": null}, "salary_visible": false, "title_keywords": [], "responsibilities": ["management", "business goals", "visualization", "power bi", "data", "implementation", "design", "agile development", "project management", "architecture", "asset management"], "requirements": {"degrees": ["degree", "bachelor"], "majors": ["engineering", "computer science"], "languages": ["english", "chinese"], "language_level": ["good command"], "hard_skills": ["bi", "data management", "agile", "azure", "git", "fun", "gap", "tableau", "make", "batch", "spark", "pipelines", "data analytics", "aws", "sql", "dynamic", "python", "project management", "data visualization", "cloud environment"], "soft_skills": ["passionate", "self-motivated", "agile", "responsible", "keen", "innovative", "project management", "diverse", "dynamic", "energetic", "driven"], "languages_combined": [{"language": "english", "language_level": ["good command"]}, {"language": "chinese", "language_level": ["good command"]}]}, "experience_required": {"duration": ["minimum 4 years"], "field": ["sql", "development", "design"]}}, {"job_id": "100003009018670", "location_code": "hk", "company": "Recruit Logic Limited", "job_title": "Data Analyst - Property development - 30 - 40k", "description": "Responsibilities\n\nA well-established and reputable organization engaging in diversified businesses in Hong Kong. To equip the Group for future growth and development, they are inviting candidates with high calibre to join them in the following capacity:\nLiaise with internal users and vendors for various projects activities and manage data projects timeline\nDrive data-driven culture, promote the effective use of data in the company\nPlan and build the company data platform (the platform supports functions and processes of internal parties and external clients)\nPerform statistical analysis and turn information into insights\nDefine the data product requirements which fulfils the business needs\nWork with data engineers to build the data pipeline, data models and reporting tool\n\nRequirements\n\nBachelor Degree in Computer Science / Information System / Statistics / Mathematics or related disciplines\nMinimum 2 years\u2019 working experience in business intelligence / data analytics / data science with knowledge of data pipeline and data infrastructure\nFamiliar with SQL Server / MySQL / pgSQL, Azure product and service (Blob Storage / Data Catalog / Data Factory / Data Warehouse / Power BI / etc.)\nPossess knowledge in programming or scripting languages would be a definite advantage, such as Python, R, HTML5, Java, Golang, etc.\nInterested in working in the latest technologies and highly competent with quantitative data analysis and utilizing data to drive decision-making\nCreative and proactive, detail-minded, logical, responsible, outgoing and able to work under pressure with tight schedules\nStrong communication, presentation and analytical skills\nGood command of both spoken and written English and Chinese is a MUST", "employment_types": ["Full Time"], "selling_points": ["Established innovative business", "young and energetice team", "great work/life balance"], "locations": ["Central & Western Area"], "categories": ["Information Technology (IT)", "Application Specialist - Software", "DBA", "Data Scientist"], "post_time": "2022-01-04T04:17:35Z", "salary": {"currency": null, "max": null, "min": null, "period": "monthly", "term": null}, "salary_visible": false, "title_keywords": ["data analyst"], "responsibilities": ["reporting", "data", "analysis", "plan", "liaise with", "internal parties"], "requirements": {"degrees": ["degree", "bachelor"], "majors": ["related disciplines", "mathematics", "statistics", "computer science"], "languages": ["english", "chinese"], "language_level": ["good command"], "hard_skills": ["java", "bi", "azure", "data warehouse", "data analytics", "analysis", "information system", "python", "sql", "analytical skills", "programming", "server", "r", "business intelligence"], "soft_skills": ["detail-minded", "outgoing", "creative", "responsible", "competent", "interested in", "analytical skills", "communication", "proactive", "presentation", "work under pressure"], "languages_combined": [{"language": "english", "language_level": ["good command"]}, {"language": "chinese", "language_level": ["good command"]}]}, "experience_required": {"duration": ["minimum 2 years"], "field": ["infrastructure", "business"]}}, {"job_id": "100003009007247", "location_code": "hk", "company": "Pinpoint Asia Limited", "job_title": "Database Administrator (MS SQL / AWS RDS) - Leading Enterprise", "description": "Our client, a leading enterprise, is looking for a DBA with MS SQL & Oracle, ideally with AWS cloud exposure. The ideal candidate will be managing the database infrastructure and operations. Perm Position.\n\nResponsibilities:\n\nProvide database administration, configuration, tuning, and maintenance, troubleshooting of the MS SQL, Oracle and AWS RDS database farm.\nLead and manage the 7x24 production support on Databases in Unix / Windows environments.\nLead the investigating and diagnosing production issues or outages;\nManage database migration projects and new database build on AWS Cloud platform.\nProvide constructive database advice to the application and infrastructure teams on effective Database services.\nProvide support and implementation work to application teams including database setup, schema changes, and SQL performance analysis.\nManage the patch installations/upgrades of operating systems and databases.\nProvide project management on database implementation including planning, scheduling, quality control, vendor management, compliance/audit, budget management, etc.\n\nRequirements:\n\nAt least 8 years of experience supporting MS SQL and Oracle.\nProgramming skills on Unix Shell, Perl, PL/SQL, and Powershell Scripting.\nMS SQL & Oracle Server administration, troubleshooting, and tuning.\nServer administration skills in Unix or Windows are a plus.\nCertifications in OCP and/or MCDBA are a good plus.\nKnowledge of Cloud-based database platforms (e.g. AWS RDS) is a huge advantage\nExposure to Cloud environments like AWS, Azure, AliCoud is a great plus.\nGood command of written and spoken English and Cantonese.\nUniversity degree in Computer Science, or relevant field\n\nIf this outstanding opportunity sounds like your next career move, please send your resume in Word format to Danny Kwan at resume(at)pinpointasia(dot)com and put Database Administrator (MS SQL / AWS RDS) - Leading Enterprise\u00a0in the subject header.\n\nData provided is for recruitment purposes only.", "employment_types": ["Full Time", "Permanent"], "selling_points": ["Large Enterprise Opportunity", "MS SQL & Oracle & AWS", "Perm Lead Position"], "locations": ["Not Specified"], "categories": ["Information Technology (IT)", "DBA", "Support", "Network & System"], "post_time": "2021-12-30T02:08:12Z", "salary": {"currency": null, "max": null, "min": null, "period": "monthly", "term": null}, "salary_visible": false, "title_keywords": ["administrator"], "responsibilities": ["budget", "troubleshooting", "audit", "database", "administration", "configuration", "infrastructure", "teams", "implementation", "compliance", "migration", "setup", "operating systems", "provide support", "management", "upgrades", "scheduling", "maintenance", "outages", "analysis", "project management", "databases", "quality control", "planning"], "requirements": {"degrees": ["university degree"], "majors": ["computer science"], "languages": ["cantonese", "english"], "language_level": ["good command"], "hard_skills": ["oracle", "plus", "azure", "server administration", "word", "aws", "sql", "powershell", "programming", "unix shell", "pl", "ms sql", "perl"], "soft_skills": ["administration skills", "troubleshooting"], "languages_combined": [{"language": "cantonese", "language_level": ["good command"]}, {"language": "english", "language_level": ["good command"]}]}, "experience_required": {"duration": ["at least 8 years"], "field": ["sql"]}}, {"job_id": "100003009015861", "location_code": "hk", "company": "China Mobile International Limited", "job_title": "Senior Application Engineer (Billing System) (Ref:CMIJD-1013-SAEDI)", "description": "Responsibilities:\n\n\nResponsible for BOSS (business operation support system), mainly on billing and invoice management modules\nResponsible for billing operation tasks such as monthly bill run, invoice distribution and dispute handling\nCollecting, identifying, and analyzing business requirements\nCoordinating projects and operation tasks with vendor\nConducting UAT and providing training to internal or external users\u00a0\n\nRequirements:\n\nBachelor or above in Computer Science/Engineering or other IT related disciplines\n5+ years of work experiences in IT or telecommunication industry\nExperience in business support systems such as CRM, Order Processing, especially Billing is an advantage\nFamiliar with DBMS and software development lifecycle. Experience in development or maintenance of backend service and database procedure is an advantage\nPositive, persistent, \u201ccan do\u201d personality, passionate with continuous improvement\nGood verbal and written English and Chinese. Fluent Putonghua is a plus\nCandidates with less experience will be considered as Application Engineer\n\nInterested parties please send your full resume with current & expected salary by clicking \"Apply Now\".\u00a0\u00a0\n\nAll personal data provided will be used for consideration of your job application only.", "employment_types": ["Full Time", "Permanent"], "selling_points": ["Billing & Invoice management", "Conducting UAT & providing training", "Project & Vendor management"], "locations": ["Kwai Hing"], "categories": ["Information Technology (IT)", "Application Specialist - Software", "DBA", "Network & System"], "post_time": "2022-01-03T07:47:02Z", "salary": {"currency": null, "max": null, "min": null, "period": "monthly", "term": null}, "salary_visible": false, "title_keywords": ["application engineer"], "responsibilities": ["invoice", "business operation", "management", "uat"], "requirements": {"degrees": ["bachelor"], "majors": ["related disciplines", "it", "engineering", "computer science"], "languages": ["putonghua", "english", "chinese"], "language_level": ["fluent", "good"], "hard_skills": ["dbms", "maintenance", "order processing", "plus"], "soft_skills": ["passionate", "persistent", "positive"], "languages_combined": [{"language": "putonghua", "language_level": ["fluent"]}, {"language": "english", "language_level": ["good"]}, {"language": "chinese", "language_level": ["good"]}]}, "experience_required": {"duration": ["5+ years"], "field": ["billing", "business support", "maintenance", "development", "it", "order processing", "database"]}}, {"job_id": "100003009013610", "location_code": "hk", "company": "Robert Walters (HK)", "job_title": "Application Architect - Data Integration", "description": "The hiring company is sizeable commercial group, looking for talent to join their expanding team, for data application architecture and integration platform.\n\nResponsibilities:\n\nDefine application architecture standards, maintain application design guidelines, and provide development toolkits by following the application architecture strategies, principles, and roadmap\nCollaborate with key business and ITS stakeholders to define solutions according to business requirements and align with the company's long-term strategies\nDrive system/software architecture design using suitable technologies that meet quality and security standards\nUnderstand the data structures, both logical and physical data models, understand metadata and how to move data from source to target locations\nUnderstands Integration architectures, such as publish and subscribe models like an Enterprise Service Bus (ESB)\nBuild and maintains software integrations across various platforms within the company\nImplement solutions by analysing problems and requirements, designing and testing standards and solutions\nExplore new technology and perform proof of concept to enhance design guideline\nMonitor and optimise ETL pipelines for efficient data transfers.\nProvide enhancements to existing enterprise applications and support in business applications\nAdhere to all established risk control guidelines, procedures, and measures to identify, assess, report, mitigate and monitor the risks involved in the day-to-day work\n\nQualifications:\n\nBachelor's Degree in computer science, Information systems, or IT related discipline\nMinimum 8 years of experience in application and data architecture design\nExperience implementing data Integration and migrations\nExperience with on-premises or IPaaS solutions such as MuleSoft, Jitterbit, Dell Boomi, Azure Data Factory or similar data integration, and automation tools\nGood comprehension of micro-services, Docker, containers, and Kubernetes\nExperience with mobile, SOA and API gateway solution architecture\nExpert in relational database design and concepts\nExperience in ETL and data warehouse projects and Power BI and different BI tools\nSound knowledge in IT security, performance tuning, capacity planning, storage, networking, and various database systems such as Oracle and MySQL\nFamiliar with Enterprise Applications Integration (EAI) and Extract, Transform and Load (ETL) tools to integrate applications or to move data to storage locations, such as a Data Warehouse\nExperience in both Agile & Waterfall project methodologies\nGood stakeholder management from business leaders to vendors\nGood command of both written and spoken English and Chinese", "employment_types": ["Full Time", "Permanent"], "selling_points": ["Min 8 yrs exp. in application & data architecture", "Exp on-premises or IPaaS solutions", "Micro-services, Docker, containers, and Kubernetes"], "locations": ["Not Specified"], "categories": ["Information Technology (IT)", "Application Specialist - Software", "DBA", "Software Development"], "post_time": "2022-01-03T02:31:59Z", "salary": {"currency": null, "max": null, "min": null, "period": "monthly", "term": null}, "salary_visible": false, "title_keywords": [], "responsibilities": ["collaborate with", "software", "data", "quality", "design", "maintain", "database", "designing", "control", "monitor", "testing", "architecture", "report", "migrations", "management", "procedures", "power bi", "guidelines", "systems", "planning"], "requirements": {"degrees": ["degree", "bachelor"], "majors": ["it", "computer science"], "languages": ["english", "chinese"], "language_level": ["good command"], "hard_skills": ["bi", "azure", "agile", "data warehouse", "pipelines", "mobile", "integration", "oracle"], "soft_skills": ["efficient", "agile"], "languages_combined": [{"language": "english", "language_level": ["good command"]}, {"language": "chinese", "language_level": ["good command"]}]}, "experience_required": {"duration": ["minimum 8 years"], "field": ["design"]}}, {"job_id": "100003009013187", "location_code": "hk", "company": "Osmium Consulting Group Limited", "job_title": "Data Analyst / Data Engineer ( Up to $40K )", "description": "Responsibilities:\n\nData warehousing and data extract/transform/load (ETL) integration in cloud and on-premise environments\nPerform Data Analytic, Data Visualization, Data Modeling, and Dashboard Building\nTroubleshoot issues on BI reports and dashboards\nWorking with stakeholders across all functions, to understand their needs and how to factor them into the automation and analytics models\nInterpret information requirements from business users and translating them into reporting solutions\n\nRequirements:\n\nDegree in Computer Science/ Engineering/ Information Systems/ Statistics or a related discipline\n1+ years of experience in business intelligence and data analytics\nProficient in converting business requirements into data model solutions and visualization\nStrong commercial and practical experience with data visualization, dashboard, and report development\nExperience in SQL, Power BI, Python is a must; knowledge in tools like AWS would also be an advantage\nHigh energy, self-motivation, and ability to thrive in a fast-paced working environment with a customer-focused attitude\nProficient in spoken and written English is necessary\nCandidates with more experience will be considered for other position", "employment_types": ["Full Time", "Permanent"], "selling_points": ["Data Analytics | Data Engineer | MNC | FinTech", "Python | Power BI | Dynamic and Friendly Culture", "5 Day Work | Attractive Package | Large Scale Firm"], "locations": ["Central"], "categories": ["Professional Services", "Business Analysis / Data Analysis", "Information Technology (IT)", "DBA", "Data Scientist"], "post_time": "2022-01-03T01:40:33Z", "salary": {"currency": "HKD", "max": 44999, "min": 25000, "period": "monthly", "term": null}, "salary_visible": true, "title_keywords": ["data analyst", "data engineer"], "responsibilities": ["warehousing", "reporting", "visualization", "data", "reports", "troubleshoot"], "requirements": {"degrees": ["degree"], "majors": ["statistics", "engineering", "computer science"], "languages": ["english"], "language_level": ["proficient"], "hard_skills": ["bi", "data analytics", "aws", "sql", "data visualization", "python", "business intelligence"], "soft_skills": ["self-motivation", "customer-focused"], "languages_combined": [{"language": "english", "language_level": ["proficient"]}]}, "experience_required": {"duration": ["1+ years"], "field": ["sql", "commercial", "development", "business"]}}, {"job_id": "100003009017546", "location_code": "hk", "company": "Infocast Limited", "job_title": "System Support Engineer", "description": "Responsibilities\n\nProvide technical support for customer service delivery and availability\nAble to manage hot issues by setting customer expectations, devising and implementing action plans and professionally communicating to all parties involved\nSupport Infocast trading system and other Infocast products\nPerform Infocast product upgrade at client offices\nProvide support for internal user and client\n\nRequirements\n\nHigher Diploma or above in Computer Science, Electronic Engineering or related disciplines\nKnowledge in TCP/IP, LAN/WAN, DNS, VMWare and VLAN\nKnowledge in Redhat OpenShift, Docker and Container is preferred.\nExperience in Linux and Windows platform\nProactive, self-motivated, hardworking and a team player with good trouble-shooting and communication skills\nCustomer oriented, independent & able to work under pressure\nGood command of spoken and written in English, Cantonese and Mandarin\nWilling to work overtime in case of emergency call\nOccasional Saturday work is required\n\nWe Offer\n\n5-day work week\nDiscretionary Bonus\nMedical Insurance\nVariety of Leaves (e.g. Birthday, Marriage Leave etc.)\nVariety of company activities and training\n\nTo Apply:\nWe offer attractive package including medical insurance scheme and good career prospects to the right candidate. Interested parties please send your application via the \"Apply Now\" button.\n\nFor more Company information, please feel free to visit our website at www.infocast.com.hk.\n\nAll information received will be kept strictly confidential and only for employment-related purposes.", "employment_types": ["Full Time", "Permanent"], "selling_points": ["Provide on-site technical support", "Linux and Windows platform", "TCP/IP, LAN/WAN, DHCP, DNS and VLAN"], "locations": ["Hung Hom"], "categories": ["Information Technology (IT)", "DBA", "Support", "Application Specialist - Network"], "post_time": "2022-01-04T01:10:25Z", "salary": {"currency": null, "max": null, "min": null, "period": "monthly", "term": null}, "salary_visible": false, "title_keywords": ["system support", "engineer"], "responsibilities": ["technical support", "plans", "provide support", "customer service"], "requirements": {"degrees": ["higher diploma or above"], "majors": ["related disciplines", "engineering", "computer science"], "languages": ["cantonese", "english", "mandarin"], "language_level": ["good command"], "hard_skills": ["linux", "vmware", "dns", "tcp", "ip", "container", "wan"], "soft_skills": ["communication skills", "self-motivated", "work overtime", "independent", "team player", "proactive", "hardworking", "work under pressure"], "languages_combined": [{"language": "cantonese", "language_level": ["good command"]}, {"language": "english", "language_level": ["good command"]}, {"language": "mandarin", "language_level": ["good command"]}]}, "experience_required": {"duration": [], "field": []}}, {"job_id": "100003009019503", "location_code": "hk", "company": "Hong Kong Adventist Hospital - Stubbs Road", "job_title": "Programmer (Full-time) Information Systems & Technology Department", "description": "Job Duties:\nProvide application implementation services for J2EE projects\u00a0\nMainly responsible for J2EE web-application programming\nTo assist the conduction of various level of testing, user training, data conversion, production setup and system nursing.\nRequirement:\nDegree / Diploma holder in Information Technology, Computer Science or related discipline\nKnowledge on web programming technology (Java Bean, JSP, JavaScript) and database accessing skill using SQL are mandatory\nMinimum 2 years hands on experience in Java programming (Fresh graduates will also be considered)\nKnowledge on web-application framework (GWT, Struts, JSF, Spring, Hibernate) will be an added advantage\nSelf-motivated, pro-active to tackle issues and able to drive team members\nGood analytical and communication skills, and able to work under pressure\nWe offer a competitive remuneration package to suitable candidates. Please apply with full resume and expected salary to Human Resources Department, 40 Stubbs Road, Hong Kong or by fax 3651 8865 or by email via \"Apply Now\".\n\nCandidates not invited for interview within 4 weeks may consider their applications unsuccessful.\n\nAll information provided by applicants will be used strictly for recruitment purpose only and they will be destroyed after 6 months.", "employment_types": ["Full Time", "Permanent"], "selling_points": [], "locations": ["Not Specified"], "categories": ["Information Technology (IT)", "DBA", "Software Development", "Network & System"], "post_time": "2022-01-04T07:47:34Z", "salary": {"currency": null, "max": null, "min": null, "period": "monthly", "term": null}, "salary_visible": false, "title_keywords": ["programmer"], "responsibilities": ["data", "implementation", "setup", "testing"], "requirements": {"degrees": ["diploma holder", "degree"], "majors": ["computer science", "information technology"], "languages": [], "language_level": [], "hard_skills": ["java", "hibernate", "web", "struts", "jsf", "sql", "javascript", "programming", "spring"], "soft_skills": ["communication skills", "self-motivated", "hands on", "pro-active", "work under pressure"], "languages_combined": []}, "experience_required": {"duration": ["minimum 2 years"], "field": ["programming"]}}, {"job_id": "100003009014527", "location_code": "hk", "company": "Osmium Consulting Group Limited", "job_title": "Data Engineer ( FinTech/e-Commence/Listed Company/Crypto )", "description": "Responsibilities:\n\nCreate and maintain optimal data pipeline architecture.\nAssemble large, complex data sets that meet functional / non-functional business requirements.\nIdentify, design, and implement internal process improvements: automating manual processes, optimizing data delivery, re-designing infrastructure for greater scalability, etc.\nBuild the infrastructure required for optimal extraction, transformation, and loading of data.\nBuild analytics tools that utilize the data pipeline to provide actionable insights into customer acquisition, operational efficiency, and other key business performance metrics.\nWork with stakeholders including the Data, Digital Marketing, R&D teams to assist with data-related technical issues and support their data infrastructure needs.\nKeep our data separated and secure across national boundaries through multiple data centers and AWS regions.\nCreate data tools for analytics and data scientist team members that assist them in building and optimizing our product into an innovative industry leader.\n\nRequirements:\n\n2 years of experience in a Data Engineer role with experience using the following software/tools:\nExperience with big data tools: Hadoop, Spark, Kafka, etc.\nExperience with relational SQL and NoSQL databases\nExperience with AWS Redshift\nExperience with object-oriented/object function scripting languages: Python, Java, C++, Scala, etc.\nAdvanced working SQL knowledge and experience working with relational databases, query authoring (SQL) as well as working familiarity with a variety of databases.\nExperience building and optimizing \u2018big data\u2019 data pipelines, architectures and data sets.\nExperience performing root cause analysis on internal and external data and processes to answer specific business questions and identify opportunities for improvement.\nStrong analytic skills related to working with unstructured datasets.\nBuild processes supporting data transformation, data structures, metadata, dependency and workload management.\nA successful history of manipulating, processing and extracting value from large disconnected datasets.\nStrong project management and organizational skills.\nExperience supporting and working with cross-functional teams in a dynamic environment.", "employment_types": ["Full Time"], "selling_points": ["International working environment", "Creative, young and energetic team members", "work from home plan"], "locations": ["Tsim Sha Tsui"], "categories": ["Information Technology (IT)", "Application Specialist - Software", "DBA", "Data Scientist"], "post_time": "2022-01-03T03:34:59Z", "salary": {"currency": "HKD", "max": 44999, "min": 25000, "period": "monthly", "term": null}, "salary_visible": true, "title_keywords": ["data engineer"], "responsibilities": ["analytics tools", "data", "infrastructure", "teams", "performance metrics", "design", "maintain", "digital marketing", "designing", "architecture"], "requirements": {"degrees": [], "majors": [], "languages": [], "language_level": [], "hard_skills": ["java", "c++", "pipelines", "analysis", "aws", "sql", "scala", "analytic skills", "project management", "dynamic", "databases", "python", "spark", "processing"], "soft_skills": ["project management", "dynamic environment", "advanced", "organizational skills"], "languages_combined": []}, "experience_required": {"duration": ["2 years"], "field": ["sql", "business"]}}]