[{"job_id": "100003009052077", "location_code": "hk", "company": "Taylor Coulter", "job_title": "Government Project--Information Technology Assistant (ITA) OR \u96fb\u8166\u652f\u63f4\u6280\u8853\u54e1", "description": "Job Responsibilities:\n\nProvide end-user software applications and computer hardware support and troubleshooting in a professional manner.\nKeep\u00a0 record of daily data communication transactions, problems and remedial action taken\nHandle the user requests according to the IT standards/procedures/guidelines\nResponsible to work according to the shift duty assigned and support roster for 24/7 technical support to End users\nReport to Line manager or Supervisor and finish the duties with proper time management\nShift duty required (Public transportation available at their on-duty and off-duty time)\nShift duty on Sunday and Hong Kong Public Holiday required\n\nJob Requirements:\n\nDiploma or above in Information Technology or Computer related disciplines\nHands-on experience in IT Helpdesk and End-User support\nFlexible and able to work both in team and independently\nI.T. Certificates holder is an advantage\nGood command in Cantonese and English, Putonghua is an advantage\nWilling to learn, self-initiative and work independent.\nGood interpersonal skill, telephone manner and service attitude\nMonthly salary HK$17,000-20,000\u00a0\n\nWe offer competitive remuneration package and generous benefits including medical coverage.\u00a0\n\nPersonal data collected will be used for recruitment purpose only.", "employment_types": ["Full Time", "Contract"], "selling_points": ["To provide IT Support Services to the office", "PC troubleshooting and set up", "Setting up, configuring and maintaining hardware"], "locations": ["Not Specified"], "categories": ["Information Technology (IT)", "Hardware", "Support", "Network & System"], "post_time": "2022-01-17T02:02:30Z", "salary": {"currency": "HKD", "max": 19999, "min": 17000, "period": "monthly", "term": null}, "salary_visible": true, "title_keywords": ["assistant"], "responsibilities": ["management", "software", "data", "guidelines", "technical support", "professional manner", "troubleshooting", "transactions", "procedures", "communication", "hardware", "report"], "requirements": {"degrees": ["diploma or above"], "majors": ["computer related", "information technology"], "languages": ["cantonese", "putonghua", "english"], "language_level": ["advantage", "good command"], "hard_skills": [], "soft_skills": ["flexible", "independently", "independent", "willing to learn", "interpersonal skill", "hands-on", "self-initiative", "telephone manner"], "languages_combined": [{"language": "cantonese", "language_level": ["good command"]}, {"language": "putonghua", "language_level": ["advantage", "good command"]}, {"language": "english", "language_level": ["good command"]}]}, "experience_required": {"duration": [], "field": ["it helpdesk"]}}, {"job_id": "100003009054658", "location_code": "hk", "company": "OPM Systems Company Limited", "job_title": "IT Helpdesk Support / Engineer", "description": "We are seeking an\u00a0Government\u00a0Project--Information Technology Assistant (ITA) OR \u96fb\u8166\u652f\u63f4\u6280\u8853\u54e1.\n\nInformation Technology Assistant (ITA)\n\nJob Description\n\nWork as Helpdesk/ Deskside/ Operator Job's Duty.\nProvide network support, including connectivity, IP addressing, direct TCP/IP output, and access control setting.\nSupport Daily IT operations, such as installation/removal/upgrade of hardware and software\u00a0and technical documentation update\nTo maintain and update the divisional equipment and facilities inventory;\nTo maintain, update and improve an user friendly computer database upon establishment of Business Rules on bus operation\n\nRequirement\n\nHigher Diploma in Information Technology / Computer Science or equivalent\nGood communication and interpersonal skills\nGood PC skills in MS Office, Excel and PowerPoint\nPrefer to have 1-2 years relevant experience in Technical Support (Hardware & Software)\nFresh Graduate will also be considered\nImmediate availability is highly preferred\n\n\u8cc7\u8a0a\u79d1\u6280\u652f\u63f4\u54e1\n\n\u8077\u8cac:\n\n\u00a0\u00a0\u00a0\u00a0\u00a0\u00a0\u00a0\u00a0\u00a0\u8ca0\u8cac\u5b89\u88dd\u53ca\u8a2d\u5b9a\u96fb\u8166\u8edf\u4ef6\u53ca\u786c\u4ef6;\n\u00a0\u00a0\u00a0\u00a0\u00a0\u00a0\u00a0\u00a0\u00a0\u70ba\u7528\u6236\u63d0\u4f9b\u6280\u8853\u652f\u63f4\u3001\u8cc7\u6599\u5099\u4efd\u53ca\u7db2\u7d61\u7ba1\u7406;\n\u00a0 \u00a0 \u00a0 \u00a0 \u00a0\u5728\u8077\u57f9\u8a13\u7684\u652f\u63f4;\n\u00a0\u00a0\u00a0\u00a0\u00a0\u00a0\u00a0\u00a0\u00a0\u57f7\u884c\u4e0a\u53f8\u6307\u6d3e\u7684\u5176\u4ed6\u5de5\u4f5c\n\n\u8981\u6c42:\n\n\u00a0 \u00a0 \u00a0 \u00a0 \u00a0\u6301\u6709\u8b49\u66f8\u00a0/\u00a0\u6587\u6191\u8ab2\u7a0b;\n\u00a0\u00a0\u00a0\u00a0\u00a0\u00a0\u00a0\u00a0\u00a0\u6301\u6709\u76f8\u95dc\u96fb\u8166\u00a0/\u00a0\u8cc7\u8a0a\u79d1\u6280\u8b49\u66f8\u6216\u6587\u6191\u8005\u70ba\u512a\u5148\u8003\u616e;\n\u00a0\u00a0\u00a0\u00a0\u00a0\u00a0\u00a0\u00a0\u00a0\u61c2\u95b1\u8b80\u53ca\u66f8\u5beb\u4e2d\u6587\uff0c\u9808\u7565\u61c2\u82f1\u8a9e\n\u00a0 \u00a0 \u00a0 \u00a0\u00a0\u00a0\u7d93\u9a57\u8f03\u5c11\u6216\u7562\u696d\u751f\u4ea6\u4f5c\u8003\u616e", "employment_types": ["Full Time", "Permanent"], "selling_points": ["IT Support", "Shift duties required", "Immediate available preferred"], "locations": ["Tung Chung"], "categories": ["Information Technology (IT)", "Hardware", "Support", "Technical / Functional Consulting"], "post_time": "2022-01-17T10:26:29Z", "salary": {"currency": null, "max": null, "min": null, "period": "monthly", "term": null}, "salary_visible": false, "title_keywords": ["engineer"], "responsibilities": ["installation", "software", "operations", "inventory", "hardware", "maintain", "database", "documentation", "access control"], "requirements": {"degrees": ["diploma", "fresh graduate"], "majors": ["computer science", "information technology"], "languages": [], "language_level": [], "hard_skills": ["excel", "powerpoint", "hardware", "pc skills", "ms office"], "soft_skills": ["communication and interpersonal skills"], "languages_combined": []}, "experience_required": {"duration": ["1-2 years"], "field": ["relevant experience"]}}, {"job_id": "100003009054191", "location_code": "hk", "company": "EZSVS (Hongkong) Co., Limited", "job_title": "Data Center Operator", "description": "Responsibilities\n\n\nProvide technical support and troubleshooting to end users on hardware, software and computer services\u00a0\nPerform maintenance, configuration and monitoring of IT equipment\nPerform management of hardware and software inventory\nAssist in IT documentation, process improvement and equipment procurement\nAssist in project support and perform ad hoc duties as assigned\nRequirements:\n\n\nDegree in Information Technology, Computer Science or related disciplines\nCCNA/CCNP/MCSE certificate holder will be an advantage\n2 years experience in IT Support\nHands on experience in O365 (Teams/SharePoint Online), Win10, Active Directory, VMWare/Hyper-V\nKnowledge in TCP/IP, Wi-Fi, Firewall, network infrastructure and security technology\nA self-motivated and organized individual with good problem solving skills and strong sense of responsibility\nAbility to work independently, flexibly and positively\nGood command in both spoken and written English and Chinese (Cantonese and Mandarin)\u00a0\nApplicants with less experience will be considered as IT Officer.\u00a0 Fresh graduates is also welcomed\nInterested parties please send your resume with your\u00a0current and expected salary\u00a0to email:\u00a0hrd @ win-hanverky.com.hk\u00a0or click \"APPLY NOW\".\u00a0The closing date for application is 17 February 2022.\u00a0All information collected will be kept in strict confidence and will be used for recruitment purpose only.", "employment_types": ["Full Time"], "selling_points": ["Triple overtime allowance", "Double pay\uff0fMedical Insurance", "7x24 Tseung Kwan O"], "locations": ["Tseung Kwan O"], "categories": ["Information Technology (IT)", "DBA", "Hardware", "IT Management"], "post_time": "2022-01-17T08:44:49Z", "salary": {"currency": null, "max": null, "min": null, "period": "monthly", "term": null}, "salary_visible": false, "title_keywords": ["operator"], "responsibilities": ["ad hoc duties", "management", "software", "maintenance", "technical support", "configuration", "inventory", "computer services", "monitoring", "troubleshooting", "hardware", "documentation", "it equipment"], "requirements": {"degrees": ["certificate", "degree"], "majors": ["related disciplines", "computer science", "information technology"], "languages": ["cantonese", "english", "chinese", "mandarin"], "language_level": ["good command"], "hard_skills": ["mcse", "o365", "hyper-v", "vmware", "active directory", "tcp", "wi-fi", "ccnp", "ccna", "ip", "firewall", "problem solving skills"], "soft_skills": ["organized", "self-motivated", "work independently", "sense of responsibility", "hands on", "problem solving skills", "active"], "languages_combined": [{"language": "cantonese", "language_level": ["good command"]}, {"language": "english", "language_level": ["good command"]}, {"language": "chinese", "language_level": ["good command"]}, {"language": "mandarin", "language_level": ["good command"]}]}, "experience_required": {"duration": ["2 years"], "field": ["it", "it support"]}}, {"job_id": "100003009053348", "location_code": "hk", "company": "iCON Business Systems Ltd", "job_title": "System Support Engineer", "description": "RESPONSIBILITIES\n\n- Handle enquiry via Helpdesk Hotline, in person or email and provide technical support to both\nour internal users and agency.\n- Provide 1st level supports on hardware & software troubleshooting\n- Provide PC installation and software deployment\n- Log all incident and request cases on the call logging system and follow up its status\n- Escalate incidents and problems to relevant second-level support team or external service providers\n- Relocation for desktop items and maintains the correct inventory record\n- Handle ad hoc IT support duties as assigned\n- Standby support during non-working hours when required\n\nREQUIREMENTS\n\n- Higher Diploma in Information Technology or related disciplines\n- 3+ years of IT support experience in Banking/Finance\n- Good communication skill in English & Chinese\n\nInterested parties, please click \"APPLY NOW\" or send your application to karis.chan@ambition.com.hk\n\nIf this job isn't quite right for you, but you know someone who would be great at this role, why not take advantage of our referral scheme? We offer HKD1000 in Apple gift cards for every referred candidate who we place in a role. Terms & Conditions Apply. https://www.ambition.com.hk/refer-a-friend", "employment_types": ["Full Time", "Permanent"], "selling_points": ["IT Field Service", "System Support", "Desktop Support"], "locations": ["Cheung Sha Wan"], "categories": ["Information Technology (IT)", "Hardware", "Support"], "post_time": "2022-01-17T06:49:17Z", "salary": {"currency": null, "max": null, "min": null, "period": "monthly", "term": null}, "salary_visible": false, "title_keywords": ["system support", "engineer"], "responsibilities": ["installation", "ad hoc", "software", "technical support", "handle enquiry", "troubleshooting", "inventory record", "hardware", "escalate incidents"], "requirements": {"degrees": ["diploma"], "majors": ["related disciplines", "information technology"], "languages": ["english", "chinese"], "language_level": ["good"], "hard_skills": [], "soft_skills": ["communication skill"], "languages_combined": [{"language": "english", "language_level": ["good"]}, {"language": "chinese", "language_level": ["good"]}]}, "experience_required": {"duration": ["3+ years"], "field": ["finance", "banking", "it support"]}}, {"job_id": "100003009052437", "location_code": "hk", "company": "The Career Works Limited", "job_title": "Part Time IT Support", "description": "Responsibilities\n\nPerform troubleshooting and provide day-to-day support including hardware, software, end-user and helpdesk;\nPerform hardware installation, configuration or maintenance, including PC, notebook, Mac, server, printer and other computer peripheral devices;\nConduct software installation, configuration or maintenance including MS-Office, Outlook, Windows, Mac, Adobe products, AntiVirus and other office applications;\nProvide regular testing of IT equipment and monitoring of IT equipment status and ah hoc on site support;\n\nRequirements\n\nIVE/Diploma holder in Information System, Computer Science, Computer Engineering or related disciplines;\n1 year experience in IT technical / deskside support will be an advantage, fresh graduates are also welcomed;\nKnowledge in Windows;\nKnowledge in AD, DNS, FTP, TCP/IP, POP3, SMTP & SNMP;\nGood computer knowledge of MS-Word, Excel, PowerPoint;\nGood command of spoken and written English and Chinese\nImmediately available will be an advantage\n\nWe offer excellent career development opportunities to unleash your potential, competitive remuneration package including a 5-day work week, medical insurance & dental plan, discretionary bonus, staff training and staff purchasing discount etc.\n\n\nInterest parties, please simply click \"Apply now\" to submit your application with full resume stating current & expected salary and the availability for reporting duty.\u00a0\n\nYou are welcome to visit our website to know more about us:\u00a0www.popular.com.hk\u00a0or http://ephhk.popularworldhk.com.\n\n\nPersonal data provided by job applicants will be kept strictly confidential and will be used solely\u00a0for employment related purpose.\u00a0\u00a0Only short-listed candidates will be contacted.", "employment_types": ["Part Time", "Internship", "Freelance"], "selling_points": ["Part Time", "Video conference Support", "IT Support, Fresh graduate"], "locations": ["Central"], "categories": ["Information Technology (IT)", "Hardware", "Support"], "post_time": "2022-01-17T03:01:49Z", "salary": {"currency": null, "max": null, "min": null, "period": "hourly", "term": null}, "salary_visible": false, "title_keywords": ["it support"], "responsibilities": ["installation", "software", "maintenance", "configuration", "monitoring", "troubleshooting", "testing", "hardware", "it equipment"], "requirements": {"degrees": ["diploma holder"], "majors": ["related disciplines", "computer engineering", "computer science"], "languages": ["english", "chinese"], "language_level": ["good command"], "hard_skills": ["ms-word", "excel", "dns", "tcp", "information system", "powerpoint", "ip"], "soft_skills": [], "languages_combined": [{"language": "english", "language_level": ["good command"]}, {"language": "chinese", "language_level": ["good command"]}]}, "experience_required": {"duration": ["1 year"], "field": ["it"]}}, {"job_id": "100003009053368", "location_code": "hk", "company": "Automated Systems (HK) Ltd", "job_title": "Technical Service Supervisor", "description": "Job\u00a0Responsibilities :\n\nResponsible for the management &technical support of servers/routers/switches/network in Data Center environment\nConfiguration changes of the network and debug of Data Center network, fault troubleshooting, system installation and configuration, equipment operation in Data Center\nManagement of DC Capacity Specification and proactively detect & resolve potential issue related to DC Network or Servers\nPerform changes to system services and configuration\n\nRequirements :\n\nHigher diploma or above in Computer Science/ Telecommunication/ Engineering or a related subject\nMinimum 1-year relevant experience\nBasic knowledge in Data Centre domain\nGood command of Mandarin and Cantonese\nImmediately available is preferred\n\nCompany Benefits :\n\nPublic holiday\nTriple overtime allowance\nDouble pay\nMedical Insurance", "employment_types": ["Full Time", "Permanent"], "selling_points": ["Lead a team to deliver IT support service", "Higher Diploma or above in computer science", "5 years IT helpdesk / deskside support"], "locations": ["Tin Hau"], "categories": ["Information Technology (IT)", "Hardware", "Support", "Network & System"], "post_time": "2022-01-17T06:52:13Z", "salary": {"currency": null, "max": null, "min": null, "period": "monthly", "term": null}, "salary_visible": false, "title_keywords": ["supervisor"], "responsibilities": ["installation", "management", "data", "technical support", "configuration", "troubleshooting"], "requirements": {"degrees": ["higher diploma or above"], "majors": ["engineering", "computer science"], "languages": ["cantonese", "mandarin"], "language_level": ["good command"], "hard_skills": ["basic"], "soft_skills": [], "languages_combined": [{"language": "cantonese", "language_level": ["good command"]}, {"language": "mandarin", "language_level": ["good command"]}]}, "experience_required": {"duration": ["minimum 1-year"], "field": ["relevant experience"]}}, {"job_id": "100003009054219", "location_code": "hk", "company": "Brink's Cash Solutions (Hong Kong) Limited", "job_title": "Security System Officer", "description": "Responsibilities:\n- Reporting to Team Head\n- To Follow company instruction to fulfill job requirements\n- To Attend service job call according to schedule\n- To Complete project on customer site according to customer requirement\n- To Analyze, break and fix and installation and setup for PCs, Servers, peripherals and Networking issue\n\nRequirement:\n- VTC Graduate / F.5 or above, with at least 2 years\u2019 experience in computer field services\n- Be Able to provide good customer service & good communication skill\n- Be Familiar with Microsoft Windows operation and networking\n- Be Hardworking, Mature, Willing to Learn with good team-work spirit\n- Less-experienced or Fresh Graduates will be considered\n\nWe offer comprehensive remuneration and benefits, and excellent career opportunities to the right candidates. Interested parties please state clearly the position you are applying with reference no. if any in the subject line and email a full resume with CURRENT & EXPECTED SALARY to our company HR email address.\n\nAll applications will be treated in the strictest confidence. We regret that only shortlisted candidates will be notified. Data collected will be used for recruitment purpose only.\n", "employment_types": ["Full Time", "Permanent"], "selling_points": ["Oversee the safety & security\u2019s facilities", "Knowledge for Security System is an advantage", "Minimum 2-3 years of working experiences"], "locations": ["Kwai Tsing Area"], "categories": ["Information Technology (IT)", "Hardware", "Security", "Others", "Security / Safety Control"], "post_time": "2022-01-17T08:50:40Z", "salary": {"currency": null, "max": null, "min": null, "period": "monthly", "term": null}, "salary_visible": false, "title_keywords": ["officer"], "responsibilities": ["reporting"], "requirements": {"degrees": [], "majors": [], "languages": [], "language_level": [], "hard_skills": ["servers"], "soft_skills": ["communication skill", "willing to learn", "mature", "customer service", "hardworking"], "languages_combined": []}, "experience_required": {"duration": ["at least 2 years"], "field": []}}, {"job_id": "100003009053416", "location_code": "hk", "company": "HKBN Jos Limited", "job_title": "Senior Technical Consultant", "description": "Job Description:\n\nSupervise and perform on-site technical and operational support and monitoring on the wristband operations at Boundary Control Points\u00a0\nSupervise the front line operation team to ensure the smooth operation of the quarantine-free travel between Mainland and HK\nCommunicate with the outbound passengers and provide guidance and assistance in using the \"Hong Kong Health Code\" system and the code conversion\n\n\nRequirements:\n\nDiploma or above in any disciplines with at least FIVE years IT-related working experience\u00a0\nCandidates should be technically sound in operating Android and iOS mobile phone\nCandidates should be polite, patience and have good communication skill\nGood command of Chinese and English\nFully vaccinated\u00a0\nWorking location: Border Control Points\nWorking on Saturday, Sunday and Public Holidays is required on roster basis\nOvernight work is required on roster basis", "employment_types": ["Full Time", "Permanent"], "selling_points": ["Manage ticket escalation", "Assist Service Manager to ensure all SLAs are met", "Fix incident & change according to ITIL standard"], "locations": ["Not Specified"], "categories": ["Information Technology (IT)", "Hardware", "Support", "Network & System"], "post_time": "2022-01-17T06:57:11Z", "salary": {"currency": null, "max": null, "min": null, "period": "monthly", "term": null}, "salary_visible": false, "title_keywords": ["consultant"], "responsibilities": ["communicate with", "control", "operational support", "operations", "monitoring", "provide guidance"], "requirements": {"degrees": ["diploma or above"], "majors": ["it", "any disciplines"], "languages": ["english", "chinese"], "language_level": ["good command"], "hard_skills": ["mobile", "android"], "soft_skills": ["communication skill", "polite", "patience"], "languages_combined": [{"language": "english", "language_level": ["good command"]}, {"language": "chinese", "language_level": ["good command"]}]}, "experience_required": {"duration": ["at least five years"], "field": ["related", "it"]}}, {"job_id": "100003009048436", "location_code": "hk", "company": "S.F. Express (Hong Kong) Limited", "job_title": "\u96fb\u8166\u652f\u63f4\u6280\u8853\u54e1 - IT Support (\u8f2a\u73ed)", "description": "Responsibilities\n\nOversee the safety and security\u2019s facilities for the company\nEvaluate and review the internal security and safety procedures\nConduct regular security inspections, audits and drill\nMonitor the security operations, access control, alarm system, CCTV system and other security related issues\nCheck the CCTV system logs and review the recorded images\nRepair and maintain the CCTV network and equipment\nPrepare documents and quotations for security system projects \u00a0\nLiaise and supervise the security system vendors\nCommunicate with alarm companies regarding the 7x24\u00a0intruder alarm monitoring system\nMonitor and maintain the vaults system\u00a0 \u00a0 \u00a0 \u00a0 \u00a0\u00a0\n\nRequirements\n\nMinimum 2-3 years of working experiences\nReliable, Proactive and able to work under pressure\nMust be careful, detail-minded & tactful\nQuick response with strong sense of responsibility\nAble to work independently as well as being a team player\nFamiliar with computer applications\nKnowledge for Security System is an advantage\nGood interpersonal and communication skills\nProficiency in spoken and written English and Chinese\nWith driving license preferred\nWorking location at Kwai Chung\nImmediately available is preferred\nWe offer attractive remuneration package fringe benefits including\u00a0Banking Holidays,\u00a0Annual Leave,\u00a0Discretionary Bonus\u00a0&\u00a0Medical Insurance. If you have the desire to join us, please send us your resume immediately with your present and expected salary by clicking \"Apply Now\".\n\n(The information provided will be used for employment related purpose only. All information of unsuccessful applicants will be destroyed within six months.)", "employment_types": ["Full Time", "Permanent"], "selling_points": ["\u591a\u5340\u514d\u8cbb\u516c\u53f8\u63a5\u99c1\u5df4\u58eb\u63a5\u9001", "\u63d0\u4f9b2\u500b\u6708\u6216\u4ee5\u4e0a\u8868\u73fe\u82b1\u7d05", "\u4e00\u500b\u6708\u4e00\u9031\u591c\u66f4\u5de5\u4f5c"], "locations": ["Tsing Yi"], "categories": ["Information Technology (IT)", "Hardware", "Support", "Network & System"], "post_time": "2022-01-14T06:35:01Z", "salary": {"currency": null, "max": null, "min": null, "period": "monthly", "term": null}, "salary_visible": false, "title_keywords": ["it support"], "responsibilities": ["liaise", "communicate with", "operations", "review", "monitor", "procedures", "monitoring", "evaluate", "repair", "maintain", "audits", "access control", "prepare documents"], "requirements": {"degrees": [], "majors": [], "languages": ["english", "chinese"], "language_level": ["proficiency"], "hard_skills": [], "soft_skills": ["detail-minded", "communication skills", "work independently", "proactive", "careful", "sense of responsibility", "team player", "reliable", "tactful", "interpersonal", "work under pressure"], "languages_combined": [{"language": "english", "language_level": ["proficiency"]}, {"language": "chinese", "language_level": ["proficiency"]}]}, "experience_required": {"duration": ["minimum 2-3 years"], "field": []}}, {"job_id": "100003009052112", "location_code": "hk", "company": "Taylor Coulter", "job_title": "Government project------- Data center operator (5 days work)", "description": "You\u00a0will create impact via\u2026\n\n\nAct as a contact point for ticket escalation\nAssist Service Manager to ensure all Service Level Agreements have been met\nManage incident & change according to ITIL standard\nImprove & drive operational efficiency\nProvide documentation for standard procedures\nWrite simple scripts for task automation to enhance monitoring/ reporting/ troubleshooting/ health check procedures\nThe follow attributes will be valued\u2026\n\nUniversity Graduate / Higher Diploma holder in Computer Science or Information Technology, or relate discipline\nMore than 3 years' relevant technical experience in Deskside Support\nExperience in Server/ Network/ Cloud is an advantage\nExcellent verbal and written communication and teamwork skills to effectively connect with both business and technical IT teams\n\nJoin Us Today!\n\nAll information provided by applicants will be treated in strict confidence and used for consideration in relation to the relevant post within the company.\n\nAll personal data of unsuccessful applicants will be destroyed within one year. Applicants who are not invited for an interview within 3 weeks may consider their application unsuccessful.", "employment_types": ["Full Time", "Permanent", "Contract"], "selling_points": ["deliver daily operations for systems in Data Cente", "Carry out data center monitoring", "Perform physical hardware health check annually"], "locations": ["North Point"], "categories": ["Information Technology (IT)", "Hardware", "Support", "Network & System"], "post_time": "2022-01-17T02:07:34Z", "salary": {"currency": "HKD", "max": 19999, "min": 17000, "period": "monthly", "term": null}, "salary_visible": true, "title_keywords": ["operator"], "responsibilities": ["reporting", "monitoring", "procedures", "troubleshooting", "deskside support", "teams", "communication", "contact", "documentation", "personal data"], "requirements": {"degrees": ["university graduate", "higher diploma holder"], "majors": ["computer science", "information technology"], "languages": [], "language_level": [], "hard_skills": ["itil", "server", "documentation", "simple"], "soft_skills": ["communication", "confidence", "teamwork", "troubleshooting"], "languages_combined": []}, "experience_required": {"duration": ["3 years"], "field": []}}, {"job_id": "100003009053262", "location_code": "hk", "company": "Charterhouse Partnership", "job_title": "Helpdesk Support \u2013 Global Law Firm", "description": "\u5de5\u4f5c\u5167\u5bb9 :\n\n\u8ca0\u8cac\u96fb\u8166\u5b89\u88dd\u53ca\u652f\u63f4\u670d\u52d9\n\u63d0\u4f9b\u6280\u8853\u652f\u63f4\u53ca\u4e00\u822c\u7dad\u8b77\u5de5\u4f5c\n\u6bcf\u9031\u5de5\u4f5c3 - 4\u5929\uff0c\u6bcf\u661f\u671f\u5e73\u5747\u5de5\u4f5c40\u5c0f\u6642\n\u5de5\u4f5c\u6642\u9593:\n- \u65e9\u4e0a7\u6642\u81f3\u665a\u4e0a7\u6642\u00a0\n- \u665a\u4e0a7\u6642\u81f3\u65e9\u4e0a7\u6642 (\u4e00\u500b\u6708\u4e00\u9031)\n\u5de5\u4f5c\u8981\u6c42 :\n\n\u4e2d\u4e94 / DSE\u540c\u7b49\u6216\u4ee5\u4e0a\u5b78\u6b77\n1\u5e74\u6216\u4ee5\u4e0a\u76f8\u95dc\u5de5\u4f5c\u7d93\u9a57\n\u826f\u597d\u7cb5\u8a9e\uff0c\u4e00\u822c\u666e\u901a\u8a71\u53ca\u82f1\u8a9e\n\u6709\u8cac\u4efb\u611f\u53ca\u5177\u7368\u7acb\u5de5\u4f5c\u80fd\u529b\n\nWe offer attractive remuneration package and fringe benefits to the right candidates. Interested parties please submit your application to us. If you do not want to apply as JobsDB member, you may send your full resume with your availability, current and expected salaries to recruit01 at sf-express.com.\n\nYou are welcome to visit our website at\u00a0https://htm.sf-express.com/hk/tc/\u00a0for more information about us.\n\nCandidates who are not invited for interview within 1-month may consider their applications unsuccessful.\n\nAll personal data provided by job applicants will be used only for recruitment purposes and will be treated strictly confidential. Unsuccessful applications will be retained for a maximum period of 24-month.", "employment_types": ["Full Time"], "selling_points": ["Law firm IT Support role", "International environment", "Excellent benefits"], "locations": ["Not Specified"], "categories": ["Information Technology (IT)", "Hardware", "Support", "Network & System"], "post_time": "2022-01-17T06:36:22Z", "salary": {"currency": null, "max": null, "min": null, "period": "monthly", "term": null}, "salary_visible": false, "title_keywords": [], "responsibilities": [], "requirements": {"degrees": [], "majors": [], "languages": [], "language_level": [], "hard_skills": [], "soft_skills": [], "languages_combined": []}, "experience_required": {"duration": [], "field": []}}, {"job_id": "100003009052146", "location_code": "hk", "company": "China Tonghai Securities Limited", "job_title": "Technical Support", "description": "Job Responsibilities\n\nTo provide hardware and software maintenance or remote support to solve the IT related problems\nTo provide the system setting and configuration\nTo handle customer technical enquiries and product / system demonstration\nTo assist in managing hardware and software inventory items\n\nRequirements\n\nCertificate / Diploma in IT or relevant discipline\nExperience in IT Industry or relevant experience is highly preferred\nFresh graduate will also be considered, will provide professional training to the right candidate\nGood communication skill, outgoing and self-motivated personality is required\nGood team player, willing to work under pressure and tight schedule\nGood command of both spoken and written English and Chinese\n\nWe offer attractive salary and fringe benefit package to the right candidate. Interested parties please send full resume to us.\n\nPersonal data provided in your application will be kept in the strictest confidence. It will be used for employment-related purposes. Applications not notified within 1 month will be considered as unsuccessful. Unsuccessful application may be kept for another 3 months for new openings before properly shredded.\n\nDBcampaignaviation\n", "employment_types": ["Full Time", "Permanent"], "selling_points": ["5 days work week at Central", "Education allowance, medial, dental and insurance", "Financial services industry"], "locations": ["Central"], "categories": ["Information Technology (IT)", "Hardware", "Support", "Network & System"], "post_time": "2022-01-17T02:16:12Z", "salary": {"currency": null, "max": null, "min": null, "period": "monthly", "term": null}, "salary_visible": false, "title_keywords": ["technical support"], "responsibilities": ["software", "configuration", "inventory", "hardware", "hardware and software maintenance"], "requirements": {"degrees": ["certificate", "diploma", "fresh graduate"], "majors": ["it"], "languages": ["english", "chinese"], "language_level": ["good command"], "hard_skills": [], "soft_skills": ["outgoing", "good team player", "self-motivated", "communication skill", "work under pressure"], "languages_combined": [{"language": "english", "language_level": ["good command"]}, {"language": "chinese", "language_level": ["good command"]}]}, "experience_required": {"duration": [], "field": ["it", "relevant experience"]}}, {"job_id": "100003009047686", "location_code": "hk", "company": "Many Wells Property Agent Ltd", "job_title": "IT Support Technician", "description": "We are seeking for Temp / Intern staffs for our client a major Investment Bank in Hong Kong.\n\nYear 1 or Year 2 university students preferred.\n\nBackground/Experience/Required Skills\n\nFamiliarity with a variety of current PC hardware\nAbility to proficiently disconnect/reconnect PC workstation and peripherals\u00a0\u00a0\u00a0\u00a0\nYou will help with software installs/upgrades, computer/printer maintenance\nVideo Conference equipment support.\nSet up, monitor and manage audio & video conferences remotely.\nResolve Audio Conference (AC) and Video Conference (VC) booking issues.\nExcellent attention to detail\nAble to accurately inventory and document layout of technical equipment including port connections\nExcellent cable management skills\u00a0\nBasic network support such as managing user accounts, user security, back-up operations and desktop support.\n\nWe are flexible on your work schedule and you should anticipate working 8 \u2013 20 hours per week.\n\nThe preferred candidate will possess or be pursuing an Information Technology or related degree", "employment_types": ["Full Time"], "selling_points": [], "locations": ["Tuen Mun Area"], "categories": ["Information Technology (IT)", "Application Specialist - Software", "Hardware", "Support"], "post_time": "2022-01-14T03:44:54Z", "salary": {"currency": null, "max": null, "min": null, "period": "monthly", "term": null}, "salary_visible": false, "title_keywords": ["it support technician"], "responsibilities": ["management", "software", "maintenance", "video conference equipment", "upgrades", "operations", "inventory", "monitor", "hardware", "conferences", "booking", "schedule", "audio"], "requirements": {"degrees": ["degree"], "majors": ["information technology"], "languages": [], "language_level": [], "hard_skills": ["basic", "vc", "maintenance", "hardware", "pc"], "soft_skills": ["flexible", "attention to detail"], "languages_combined": []}, "experience_required": {"duration": [], "field": []}}, {"job_id": "100003009049229", "location_code": "hk", "company": "4PX Express Co., Limited", "job_title": "IT Engineer/ IT \u5de5\u7a0b\u5e2b", "description": "Background:\u00a0My client is a well-known financial services firm who is now looking for an System Administrator to join their IT team.\n\nJob Scope:\n\n\nPerform system installation and rollout\n\nProvide technical support including Server administration, system maintenance,\u00a0basic network connectivity, etc\n\nProvide IT infrastructure support such as installation, configuration, upgrade of hardware and computer applications\nLiaise with vendor/supplier to setup IT infrastructure\nProvide assistance to manager to lead and drive projects\nPerform evaluation, installation, configuration, administration and troubleshooting of resources including VM,OS, hardware & software\nSupport focus on Windows and Virtualization\nProvide basic end-user support service to internal users\u00a0\n\nRequirement:\n\nPossess Higher Diploma or above academic certifications in Computer Science or IT related discipline\n\nSolid experience in Windows Server infrastructure,\u00a0Server Virtualization platform, Storage System or inter-networking\nHands on experience in virtualization solution\nProcess excellent problem solving and communication skills\nProficiency in both written and spoken Chinese and English\nEnergetic, self-motivated, teamwork, dynamic and able to work under pressure\nCandidates with less years of experience will also be considered\u00a0\n\nIf you are interested in this position, please apply online with your latest CV in Word format including current & expected salary. Kindly note that only shortlisted candidates will be notified.", "employment_types": ["Full Time"], "selling_points": ["IT helpdesk, user desktop problems", "equipment and related software maintenance", "installation and troubleshooting of office softwar"], "locations": ["Tin Shui Wai"], "categories": ["Information Technology (IT)", "Hardware", "Support", "Technical / Functional Consulting"], "post_time": "2022-01-14T08:17:37Z", "salary": {"currency": null, "max": null, "min": null, "period": "monthly", "term": null}, "salary_visible": false, "title_keywords": ["engineer"], "responsibilities": ["installation", "it infrastructure", "maintenance", "software", "technical support", "configuration", "work under pressure", "infrastructure", "troubleshooting", "communication", "hardware", "computer applications", "evaluation", "liaise with", "provide assistance", "setup", "administration"], "requirements": {"degrees": ["higher diploma or above"], "majors": ["it", "computer science"], "languages": ["english", "chinese"], "language_level": ["proficiency"], "hard_skills": ["infrastructure support", "basic", "maintenance", "server administration", "vendor", "word", "problem solving", "hardware", "os", "dynamic", "server", "focus", "windows server"], "soft_skills": ["communication skills", "self-motivated", "teamwork", "interested in", "troubleshooting", "problem solving", "hands on", "dynamic", "focus", "energetic", "work under pressure"], "languages_combined": [{"language": "english", "language_level": ["proficiency"]}, {"language": "chinese", "language_level": ["proficiency"]}]}, "experience_required": {"duration": [], "field": ["infrastructure"]}}, {"job_id": "100003009051568", "location_code": "hk", "company": "Maxim's Caterers Ltd", "job_title": "Manager \u2013 Infrastructure & Operations", "description": "Position Summary\n\nA global law firm is looking for a new addition to their Helpdesk Support team. The candidate will be a key member in the team with opportunities to take part in regional wide IT enhancement projects. The position would be ideal for candidates with excellent language skills and are looking to continue their career in an international environment.\n\n\u00a0Duties\n\nProvide Tier 1 & Tier 1 Helpdesk support\nTroubleshooting and assistance to hardware & software\nEngage in system enhancement projects\nMaintain and configure desktop, laptop, mobile phones and equipment\nSupport video conferencing and remote working devices\nAd hoc duties as assigned by team leader\n\nProfile\n\nDegree/diploma holder in Computer Science/Information Systems or related\n2 years or above experience in IT support in professional service firms\nLaw firm experience would be an advantage\nStrong English & Chinese speaking ability\nExperience in supporting remote working & video conferencing\n\nJob Offer\n\nComprehensive employee benefits\nOn-the-job training\nAnnual leave and medical insurance\n\nIf you are interested in finding out more about this career opportunity, please email your resume to Alex Cheung, alex.cheung@ charterhouse.com.hk\u00a0 Web: www.charterhouse.com.hk\n\nCharterhouse Partnership Hong Kong is here to assist you in your job search. Our experienced recruitment consultants will provide you with career advice and assist you to develop a tailored job search strategy.", "employment_types": ["Full Time", "Permanent"], "selling_points": ["Regional IT infrastructure management", "Lead a technical team", "IT infrastructure projects & vendor management"], "locations": ["Lai Chi Kok"], "categories": ["Information Technology (IT)", "Hardware", "IT Management", "Network & System"], "post_time": "2022-01-16T11:09:00Z", "salary": {"currency": null, "max": null, "min": null, "period": null, "term": null}, "salary_visible": false, "title_keywords": ["operations", "manager"], "responsibilities": ["ad hoc duties", "software", "systems", "troubleshooting", "hardware", "maintain", "enhancement projects"], "requirements": {"degrees": ["diploma holder", "degree"], "majors": ["computer science"], "languages": ["english", "chinese"], "language_level": [], "hard_skills": ["hardware", "mobile"], "soft_skills": ["troubleshooting", "ideal"], "languages_combined": [{"language": "english", "language_level": []}, {"language": "chinese", "language_level": []}]}, "experience_required": {"duration": ["2 years"], "field": ["video", "it support"]}}, {"job_id": "100003009054770", "location_code": "hk", "company": "Public Finance Limited", "job_title": "System Security Officer", "description": "Job Responsibilities:\n\nAssemble and repair computers, install software, handle the network\nKnowledge in filmmaking and editing will be an advantage\nMainly work at the head office and go to the branch for handling maintenance work when necessary\n\nJob Requirements:\n\nForm 5 or above\nHardworking and willing work under pressure\nGood communication skill in Chinese\nFresh Graduates are welcome\n\n\n\nInterested parties, please click \"Apply Now\" to submit your application.\n\n(All Personal information will be used for recruitment purpose only.)", "employment_types": ["Full Time", "Permanent"], "selling_points": [], "locations": ["Not Specified"], "categories": ["Information Technology (IT)", "Hardware", "Security", "Network & System"], "post_time": "2022-01-17T11:01:16Z", "salary": {"currency": null, "max": null, "min": null, "period": "monthly", "term": null}, "salary_visible": false, "title_keywords": ["officer"], "responsibilities": ["repair", "software", "maintenance", "editing"], "requirements": {"degrees": ["form 5 or above"], "majors": [], "languages": ["chinese"], "language_level": ["good"], "hard_skills": [], "soft_skills": ["communication skill", "hardworking", "work under pressure"], "languages_combined": [{"language": "chinese", "language_level": ["good"]}]}, "experience_required": {"duration": [], "field": []}}, {"job_id": "100003009049252", "location_code": "hk", "company": "Pacific Textiles Ltd", "job_title": "Technical Support", "description": "Job Description\n\nProvide technical support (off site and on-site) to SMB clients on servers, desktops and network issues.\nAssist project deployment for Hardware and software\n\n\n\nRequirement\n\nAt least 1 year related working experience\nCan work independently and under pressure\nMCSE ,VCP and CCNA is an advantage\nGood communication skill\nCandidate with less experience will be considered.\n\n\n\nWe provide attractive remuneration package to right candidate. Interested parties please send full resume and expected salary to us.\n\nPersonal data will be used for recruitment purpose only.", "employment_types": ["Full Time", "Permanent"], "selling_points": [], "locations": ["Kwai Hing"], "categories": ["Information Technology (IT)", "Hardware", "Support", "Others", "Student / Fresh Graduate / No Experience"], "post_time": "2022-01-14T08:19:29Z", "salary": {"currency": null, "max": null, "min": null, "period": "monthly", "term": null}, "salary_visible": false, "title_keywords": ["technical support"], "responsibilities": ["technical support", "hardware", "network issues", "software"], "requirements": {"degrees": [], "majors": [], "languages": [], "language_level": [], "hard_skills": ["mcse", "ccna"], "soft_skills": ["work independently", "communication skill", "under pressure"], "languages_combined": []}, "experience_required": {"duration": ["at least 1 year"], "field": ["related"]}}, {"job_id": "100003009045759", "location_code": "hk", "company": "Kepro Solutions Limited", "job_title": "Consultant (IT Infrastructure)", "description": "Job Responsibilities\n\nResponsible for IT helpdesk work, quickly responding and dealing with user desktop problems and needs;\nResponsible for the daily maintenance of IT desktops and related equipment, including PCs, printers, scanners, electronic scales, and other equipment and related software maintenance;\nResponsible for the installation and distribution of IT desktop related equipment and systems;\nResponsible for the security and stability of the IT network (including wireless network) environment;\nResponsible for the management and maintenance of CCTV monitoring equipment;\nAssist the asset department in managing and updating assets. Including asset warehousing, issuance, inventory, maintenance, and scrap management.\n\nRequirements\n\nComputer-related major, with practical related work experience;\nPossess strong problem analysis and solving skills, high sense of responsibility, good professional ethics, a strong sense of service, and proactive;\nProficient in Windows, macOS, and other operating systems, proficient in the installation and troubleshooting of office software and common software;\nSkilled in solving the faults of terminal equipment such as PCs, printers, telephones, scanners, electronic scales, etc.;\nMaster the configuration, use, and policy formulation of mainstream VPN, online behavior management, access, firewall, and other security equipment;\nMaster the configuration, maintenance, fault diagnosis, and optimization of routers, switches, WLCs, APs, and other network equipment;\nMaster the basic use and maintenance of CCTV monitoring equipment;\nUnderstand enterprise IT infrastructure, and have a certain understanding of weak current integrated wiring, servers, virtualization, etc.\n\nInterested Parties please feel free to click the button above for APPLYING/ WhatsApp / call 6603 4144\n\n\u5d17\u4f4d\u8077\u8cac\n\n\u8ca0\u8cacIThelpdesk\u5de5\u4f5c\uff0c\u5feb\u901f\u76f8\u61c9\u548c\u8655\u7406\u7528\u6236\u684c\u9762\u7aef\u554f\u984c\u548c\u9700\u6c42\uff1b\n\u8ca0\u8cacIT\u684c\u9762\u53ca\u76f8\u95dc\u8a2d\u5099\u7684\u65e5\u5e38\u7dad\u8b77\u5de5\u4f5c\uff0c\u5305\u62ecPC\u3001\u6253\u5370\u6a5f\u3001\u6383\u63cf\u5100\u3001\u96fb\u5b50\u79e4\u7b49\u8a2d\u5099\u53ca\u76f8\u95dc\u8edf\u4ef6\u7dad\u8b77\uff1b\n\u8ca0\u8cacIT\u684c\u9762\u76f8\u95dc\u8a2d\u5099\u548c\u7cfb\u7d71\u7684\u5b89\u88dd\u3001\u914d\u767c\u5de5\u4f5c\uff1b\n\u8ca0\u8cacIT\u7db2\u7d61\uff08\u5305\u542b\u7121\u7dda\u7db2\u7d61\uff09\u74b0\u5883\u5b89\u5168\u7a69\u5b9a\uff1b\n\u8ca0\u8cacCCTV\u76e3\u63a7\u8a2d\u5099\u7ba1\u7406\u3001\u7dad\u8b77\u5de5\u4f5c\uff1b\n\u5354\u52a9\u8cc7\u7522\u90e8\u9580\u9032\u884c\u8cc7\u7522\u7684\u7ba1\u7406\u8207\u66f4\u65b0\u3002\u5305\u62ec\u8cc7\u7522\u5165\u5eab\u3001\u767c\u653e\u3001\u76e4\u9ede\u3001\u7dad\u4fee\u3001\u5831\u5ee2\u7ba1\u7406\u3002\n\n\u5165\u8077\u8981\u6c42\n\n\u8a08\u7b97\u6a5f\u76f8\u95dc\u5c08\u696d\uff0c\u5177\u6709\u5be6\u969b\u76f8\u95dc\u5de5\u4f5c\u7d93\u9a57\uff1b\n\u5177\u5099\u8f03\u5f37\u7684\u554f\u984c\u5206\u6790\u548c\u89e3\u6c7a\u80fd\u529b\uff0c\u9ad8\u5ea6\u8cac\u4efb\u611f\uff0c\u826f\u597d\u7684\u8077\u696d\u9053\u5fb7\uff0c\u670d\u52d9\u610f\u8b58\u5f37\uff0c\u7a4d\u6975\u9032\u53d6\uff1b\n\u719f\u7df4\u638c\u63e1Windows\u3001MacOS\u7b49\u64cd\u4f5c\u7cfb\u7d71\u76f8\u95dc\u77e5\u8b58\uff0c\u719f\u7df4office\u8fa6\u516c\u8edf\u4ef6\u53ca\u5e38\u7528\u8edf\u4ef6\u7684\u5b89\u88dd\u548c\u6545\u969c\u89e3\u6c7a\uff1b\n\u719f\u7df4\u89e3\u6c7aPC\u6a5f\u3001\u6253\u5370\u6a5f\u3001\u96fb\u8a71\u3001\u6383\u63cf\u5100\u3001\u96fb\u5b50\u79e4\u7b49\u7d42\u7aef\u8a2d\u5099\u7684\u6545\u969c\uff1b\n\u638c\u63e1\u4e3b\u6d41VPN\u3001\u4e0a\u7db2\u884c\u70ba\u7ba1\u7406\u3001\u51c6\u5165\u3001\u9632\u706b\u7246\u7b49\u5b89\u5168\u8a2d\u5099\u7684\u914d\u7f6e\u3001\u4f7f\u7528\u53ca\u7b56\u7565\u7684\u88fd\u5b9a\uff1b\n\u638c\u63e1\u8def\u7531\u5668\u3001\u4ea4\u63db\u6a5f\u3001WLC\u3001AP\u7b49\u7db2\u7d61\u8a2d\u5099\u7684\u914d\u7f6e\u3001\u7dad\u8b77\u3001\u6545\u969c\u8a3a\u65b7\u53ca\u512a\u5316\uff1b\n\u638c\u63e1CCTV\u76e3\u63a7\u8a2d\u5099\u7684\u57fa\u672c\u4f7f\u7528\u548c\u7dad\u8b77\uff1b\n\u4e86\u89e3\u4f01\u696dIT\u57fa\u790e\u67b6\u69cb\uff0c\u5c0d\u5f31\u96fb\u7d9c\u5408\u4f48\u7dda\u3001\u670d\u52d9\u5668\u3001\u865b\u64ec\u5316\u7b49\u65b9\u9762\u6709\u4e00\u5b9a\u8a8d\u8b58\u3002\n\n\u6709\u610f\u8005\u8acb\u96a8\u6642\u9ede\u64ca\u4e0a\u65b9\u6309\u9215\u7533\u8acb/whatsapp/\u81f4\u96fb6603 4144", "employment_types": ["Full Time", "Permanent"], "selling_points": ["Pre-sales role in proposing high-value IT services", "Solid experience in infrastructure solution design", "Competitive remuneration package"], "locations": ["Kwun Tong"], "categories": ["Information Technology (IT)", "Hardware", "Application Specialist - Network", "Technical / Functional Consulting"], "post_time": "2022-01-15T03:49:31Z", "salary": {"currency": null, "max": null, "min": null, "period": "monthly", "term": null}, "salary_visible": false, "title_keywords": ["consultant"], "responsibilities": ["installation", "management", "warehousing", "software", "maintenance", "inventory", "pcs", "systems", "monitoring"], "requirements": {"degrees": ["master"], "majors": [], "languages": [], "language_level": [], "hard_skills": ["printers", "basic", "servers", "maintenance", "analysis", "cctv", "vpn", "firewall", "office software"], "soft_skills": ["high sense of responsibility", "proactive", "troubleshooting"], "languages_combined": []}, "experience_required": {"duration": [], "field": ["related"]}}, {"job_id": "100003009050041", "location_code": "hk", "company": "Drake Overload Ltd", "job_title": "Shift NOC Engineer - Airport", "description": "Opportunity to join a leading Bank!\n\nThe Service Desk Analyst provides support for basic incident resolution and requests reported to the regional service desk.\n\n\nResponsibilities:\n\n\nAct as a single point of contact and support internal staff via phone calls, emails, live chat and self-service tickets from internal staff regarding IT related issues and queries.\n1st line support: troubleshooting of IT related problems\nEscalate unresolved issues / requests to the corresponding helpdesk (L2/L3 support)\nTake ownership of users' problems, follow up the status of problems on behalf of the user and communicate the status to users in a timely manner\nUpdate all taken actions and information into ticketing system in a timely manner\nTo maintain a high degree of customer service for all support queries\nMaintain knowledge database to ensure all information is up-to-date\nDefine / Improve processes and workflows\nCapable to manage projects or tasks given by the manager\n\nProfile Required\n\nRequirements:\n\n\nFluent in English\nExcellent communication skills and telephone manner.\nEffective listening and attentiveness skills\nExcellent organizational skills\nWillingness to improve and to learn\nCustomer service orientation and/or prior customer service training\nTeam player\nBanking experience will be advantageous, but it is not mandatory", "employment_types": ["Full Time", "Contract"], "selling_points": ["CCNP, up to 45K x 13M", "Able to work on 7x24 shift duty in the airport", "Network changes, troubleshooting, and admin"], "locations": ["Airport Area"], "categories": ["Information Technology (IT)", "Hardware", "Support", "Network & System"], "post_time": "2022-01-14T09:40:43Z", "salary": {"currency": "HKD", "max": 44999, "min": 35000, "period": "monthly", "term": null}, "salary_visible": true, "title_keywords": ["noc engineer"], "responsibilities": ["a timely manner", "troubleshooting", "maintain", "customer service", "contact", "database", "manage projects", "phone calls"], "requirements": {"degrees": [], "majors": [], "languages": ["english"], "language_level": ["fluent"], "hard_skills": [], "soft_skills": ["communication skills", "organizational skills", "customer service", "team player", "telephone manner"], "languages_combined": [{"language": "english", "language_level": ["fluent"]}]}, "experience_required": {"duration": [], "field": ["it", "banking experience"]}}, {"job_id": "100003009051811", "location_code": "hk", "company": "Hong Kong Applied Science and Technology Research Institute Company Limited (ASTRI)", "job_title": "Firmware Development - Senior Lead Engineer/ Lead Engineer", "description": "DEAR TALENT, YOUR MOVE!\n\nBeing the new rising airline since 2013, we are the Hong Kong\u2019s only Low Cost Carrier (LCC) offering you safe and flexible service options to Hong Kong and beyond.\n\nWe\u2019re on a mission to inspire you to be different, to shake things up, to inspire the spirit of adventure by bringing you to fascinating destinations that few others serve.\n\nSpread your wings and fly with us!\n\nWhat will you do?\u00a0\n\nLead a small team to maintain daily IT Infrastructure operation to support internal users within SLA under ITIL standard;\nSupport Security team to handle security events in IT infrastructure environment;\nSupport internal audit to assess different IT areas;\nDevelop and maintain formal guidelines, policies, and procedures to ensure the smooth operation;\nManage external vendor to provide technical support on corporate IT Infrastructure with emphasis on the internal network, servers, Microsoft office365 environment and cloud infrastructure;\nManage external vendor to provide technical support on Airport IT Infrastructure with emphasis on Express IP, AviNet, ACARS and EDI about Cargo / Crew / Passenger Information Filing;\nPlan, setup, lead and manage the IT Infrastructure and End-user Technology Strategy including disaster recovery planning;\nResearch on new technology, identify technology gaps, develop and deploy Infrastructure solutions;\nRemediate Risk & Vulnerability for Infrastructure and End-user computing;\nDrive the continuous improvement to all IT Infrastructure related services;\nDetermine how to leverage enabling technologies to implement innovative IT infrastructure solutions to support the business\nCoach and mentor team members;\nTravel occasionally for new station setup/support;\u00a0\nSupport ad-hoc duties as assigned.\n\nWe are a perfect match, if you are:\n\nUniversity graduate in Computer Technology or related discipline;\nMinimum 6 years of related working experiences in IT security with 2 years of supervisor post;\nStrong technical knowledge in all aspects of IT Infrastructure especially in Microsoft Office365, Fortinet, Azure/Alibaba cloud and End-user computing;\nSound Knowledgeable on SOC, DLP and SIEM;\nCertification on networking (such as CCNA, CCNP, CCIE);\nITILv3 Foundation Certification is a must;\nBasic knowledge of common information security management frameworks, such as ISO 27001, CobiT, ITIL, PCI DSS.\n\nYour Future Work Life?\n\nWork flexibly with staggered working hours and flexible workplace\nDress Casual and Smart everyday\nWork in a newly-designed office with open seating, stylish breakout areas, game room, gym and free coffee\u2026\nWork with a group of energetic and multicultural professionals (up to 50 nationalities!)\nHave great fun in Snack Friday, New Year Market, Fly with your Kids Day, Basketball Team\u2026\nHave your voice heard through Townhalls, Crew forums, CEO live sessions etc.\n\nWhat will you enjoy?\n\nFly anywhere we fly for free plus taxes during leisure with your friends and family\nSpecial privileges to buy duty free products\nCareer Express\n\n\nYou will be inspired by our core values.\nYou will be inspired by our vibrant, efficient and entrepreneurial spirit. Join our fun, collaborative and reliable team to ignite your dream!\n\n\nInterested? It\u2019s time to have YOUR MOVE!\nIf you're ready to embark your adventure, start by clicking the \u2018Apply now\u2019 and get on the plane to fly with HK Express!\u00a0", "employment_types": ["Full Time", "Contract"], "selling_points": ["Firmware Development", "Hardware Devices", "Embedded System"], "locations": ["Shatin Area"], "categories": ["Information Technology (IT)", "Application Specialist - Software", "Hardware", "Network & System"], "post_time": "2022-01-17T01:14:52Z", "salary": {"currency": null, "max": null, "min": null, "period": "monthly", "term": null}, "salary_visible": false, "title_keywords": ["engineer", "lead"], "responsibilities": ["cost", "information security", "management", "it infrastructure", "internal audit", "recovery planning", "guidelines", "policies", "lead a small team", "technical support", "procedures", "infrastructure", "ad-hoc duties", "develop", "maintain", "plan", "deploy", "setup"], "requirements": {"degrees": ["university graduate"], "majors": [], "languages": [], "language_level": [], "hard_skills": ["small", "itil", "plus", "azure", "servers", "basic", "security management", "fun", "ccnp", "ccna", "airline", "vendor", "sla", "safe", "ip", "lcc"], "soft_skills": ["flexible", "efficient", "collaborative", "innovative", "smooth", "reliable", "ad-hoc duties", "energetic"], "languages_combined": []}, "experience_required": {"duration": ["2 years", "minimum 6 years"], "field": ["related", "it", "security"]}}, {"job_id": "100003009042035", "location_code": "hk", "company": "EC Healthcare", "job_title": "IT Technical Specialist", "description": "Responsibilities\nPerform daily maintenance activities such as faults investigation, recovering and reporting\nCarry out field services, provide hardware maintenance & installation services\nPerform preventive maintenance activities\nSupport project design, implementation and testing\n\nRequirements\nDiploma / Higher Diploma / Degree in Electronic Engineering / Electrical Engineering / Mechanical Engineering or above\nWith at least 1 year(Technician) / 3 years (Senior Technician) experience of electronic and electrical equipment installation and maintenance\nAbility to work independently and work under pressure\nGood skill in Trouble shooting\nGood knowledge in PC including PCB design, CAD drawing & Microprocessor firmware design is preferable\nGood command of written and spoken English and Chinese\nFresh graduate will be considered\n\nKML is an equal-opportunity employer and welcomes applications from all qualified candidates. If you look for an exciting and rewarding career, please send your resume, your present and expected salary.\nPersonal data collected will only be used for recruitment purposes.\n\nInterested candidates, please click APPLY NOW \u00a0to apply.\n\n\n\n", "employment_types": ["Full Time", "Permanent"], "selling_points": ["End-user technical support", "Hands-on role including desktop installations", "Manage IT inventory"], "locations": ["Mong Kok"], "categories": ["Information Technology (IT)", "Hardware", "Support", "Application Specialist - Network"], "post_time": "2022-01-12T05:30:37Z", "salary": {"currency": null, "max": null, "min": null, "period": "monthly", "term": null}, "salary_visible": false, "title_keywords": ["technical specialist"], "responsibilities": ["reporting", "installation", "maintenance", "implementation", "investigation", "design", "testing", "hardware"], "requirements": {"degrees": ["diploma", "degree", "fresh graduate"], "majors": ["mechanical engineering", "engineering", "electrical engineering"], "languages": ["english", "chinese"], "language_level": ["good command"], "hard_skills": ["pc", "maintenance", "cad"], "soft_skills": ["work independently", "work under pressure"], "languages_combined": [{"language": "english", "language_level": ["good command"]}, {"language": "chinese", "language_level": ["good command"]}]}, "experience_required": {"duration": ["3 years"], "field": ["installation", "maintenance"]}}, {"job_id": "100003009043047", "location_code": "hk", "company": "OT&P Healthcare", "job_title": "IT Technical Support / IT Officer", "description": "Responsible for regional IT infrastructure management, day-to-day IT operations, end-user support and IT facilities management.\u00a0 Working on providing stable and secure IT infrastructure to support business-critical application and services, as well as providing high-quality IT services to internal users.\n\n\nResponsibilities\nLead a technical team to manage and operate the company\u2019s regional infrastructure, which comprises of local and regional networks, colocation data centers, public clouds, server & virtualization platforms\nWork with internal IT teams and support vendors to ensure the reliability and security of IT infrastructure\nOversee IT operation, drive operational excellence and continuous improvement\nLead IT infrastructure projects with efficient vendor management skills\nRequirements\nDegree holder in Computing or related discipline\nMinimum 10 years of experience in IT infrastructure, IT operations, and/or end-user support\nProven experience in managing technical staff and vendor to deliver enterprise-scale IT projects and/or services\nSound knowledge in infrastructure technologies and enterprise applications, e.g. networking, cloud, server & virtualization platform, storage, IT security software, etc.\nExperience in F&B, retail or manufacturing environment will have advantage\nHolder of technical certifications, e.g. MCSE, CCNA/CCNP, VMware, public cloud, ITIL, PMP will have advantage\nGood communication, teamwork, and negotiation skills\nGood problem-solving and analytical skills\nGood command in written & spoken English and Cantonese\nInterested parties please apply with full resume, state current and expected salaries by clicking \"Apply Now\". All applications and data collected will be treated in strict confidence and used exclusively for recruitment purposes.\u00a0 Only short listed candidates will be invited for interview. The company will retain the applications for a maximum period of 24 months and may refer suitable candidates to other vacancies within the Group.", "employment_types": ["Full Time", "Permanent"], "selling_points": ["IT infrastructure, helpdesk, hardware support", "2 years relevant working experience in IT support", "Monitor servers, systems health and routine system"], "locations": ["Sheung Wan"], "categories": ["Information Technology (IT)", "Hardware", "Support", "Network & System"], "post_time": "2022-01-12T09:37:50Z", "salary": {"currency": null, "max": null, "min": null, "period": "monthly", "term": null}, "salary_visible": false, "title_keywords": ["technical support", "it officer"], "responsibilities": ["management", "it infrastructure", "data", "infrastructure", "teams"], "requirements": {"degrees": ["degree holder"], "majors": [], "languages": ["cantonese", "english"], "language_level": ["good command"], "hard_skills": ["itil", "mcse", "vmware", "ccnp", "problem-solving", "ccna", "vendor", "analytical skills", "server", "pmp"], "soft_skills": ["problem-solving", "teamwork", "analytical skills", "communication", "negotiation skills"], "languages_combined": [{"language": "cantonese", "language_level": ["good command"]}, {"language": "english", "language_level": ["good command"]}]}, "experience_required": {"duration": ["minimum 10 years"], "field": ["manufacturing", "infrastructure", "f&b", "it", "retail", "it operations"]}}, {"job_id": "100003009050400", "location_code": "hk", "company": "Bond West Consultants", "job_title": "System Support Engineer / Senior System Support Engineer (18 - 38K)", "description": "Responsibilities\nDesign, develop implement and maintain security infrastructure for corporate-wide computing systems\nManage security equipment and services for network perimeter\nEnsure hardware and software are kept with latest security standards and patches\nPerform risk assessment and introduce mitigation measures to improve security infrastructure for new systems/applications\nRequirements\nDegree in Computer Studies or related disciplines\nAt least 4 years of working experience in Networking with 2 years hands-on experience in managing security services and network devices\nWith certifications recognized by HKMA such as CISSP, CSX, ACsP, etc, is an added advantage\nHigh proficiency in spoken and written English\nBenefits\nDouble Pay\nDiscretionary Bonus\nInsurance Benefits\nStudy subsidy\nApplication Method:\n\nBy Whatsapp : 9309 2925By E-mail via \"Apply Now\"\n\nPersonal data collected will be treated in the strictest confidence in accordance with our\u00a0Personal Information Collection Statement\u00a0and\u00a0Privacy Policy\u00a0and will be handled by authorized personnel for recruitment-related purposes only. All applications will be kept for a maximum period of one year as may be considered for other suitable positions within Public Finance Ltd. and its associated companies. For details, please visit the Company\u2019s website\u00a0http://www.publicfinance.com.hk", "employment_types": ["Full Time", "Permanent"], "selling_points": ["1 - 2 months Bonus", "Stable platform for development", "MNC"], "locations": ["Not Specified"], "categories": ["Information Technology (IT)", "Hardware", "Support", "Network & System"], "post_time": "2022-01-14T10:18:38Z", "salary": {"currency": null, "max": null, "min": null, "period": "monthly", "term": null}, "salary_visible": false, "title_keywords": ["system support", "engineer"], "responsibilities": ["software", "infrastructure", "systems", "design", "develop", "hardware", "maintain"], "requirements": {"degrees": ["degree"], "majors": ["related disciplines", "computer studies"], "languages": ["english"], "language_level": ["proficiency"], "hard_skills": ["hkma"], "soft_skills": ["hands-on"], "languages_combined": [{"language": "english", "language_level": ["proficiency"]}]}, "experience_required": {"duration": ["at least 4 years", "2 years"], "field": ["security"]}}, {"job_id": "100003009046866", "location_code": "hk", "company": "Manmachine Systems Consultants Ltd", "job_title": "SYSTEM TECHNICIAN", "description": "Job Description\n\nWe are looking for a bright Technical Support to provide enterprise level technical support for our colleagues. This technician will provide support via phone, email, chat, in person, and other channels as required. This technician will also be responsible for installing and maintaining server and network hardware. A background in engineering or IT support is required.\n\nResponsibilities\n\n\u00a0\u00a0\u00a0\u00a0\u00a0\u00a0\u00a0\u00a0 Take ownership of customer issues reported and see problems through to resolution\n\u00a0\u00a0\u00a0\u00a0\u00a0\u00a0\u00a0\u00a0 Research, diagnose, troubleshoot and identify solutions to resolve issues\n\u00a0\u00a0\u00a0\u00a0\u00a0\u00a0\u00a0\u00a0 Follow standard procedures for proper escalation of unresolved issues to the appropriate internal teams\n\u00a0\u00a0\u00a0\u00a0\u00a0\u00a0\u00a0\u00a0 Ensure proper recording and closure of all issues; report status regularly\n\u00a0\u00a0\u00a0\u00a0\u00a0\u00a0\u00a0\u00a0 Document knowledge in the form of knowledge base tech notes and articles\n\u00a0\u00a0\u00a0\u00a0\u00a0\u00a0\u00a0\u00a0 Provision/decommission hardware in/out of data center facilities\n\u00a0\u00a0\u00a0\u00a0\u00a0\u00a0\u00a0\u00a0 Diagnose and resolve hardware issues\n\u00a0\u00a0\u00a0\u00a0\u00a0\u00a0\u00a0\u00a0 Assist in ad hoc projects when required\n\nRequirements\n\n\u00a0\u00a0\u00a0\u00a0\u00a0\u00a0\u00a0\u00a0 BS degree in Information Technology, Computer Science or equivalent\n\u00a0\u00a0\u00a0\u00a0\u00a0\u00a0\u00a0\u00a0 Fresh graduation is welcome\n\u00a0\u00a0\u00a0\u00a0\u00a0\u00a0\u00a0\u00a0 Experience in Networking and Microsoft AD is preferred\n\u00a0\u00a0\u00a0\u00a0\u00a0\u00a0\u00a0\u00a0 Basic knowledge of Windows, Linux, networking, utilities and scripting\n\u00a0\u00a0\u00a0\u00a0\u00a0\u00a0\u00a0\u00a0 Strong problem-solving skills\n\u00a0\u00a0\u00a0\u00a0\u00a0\u00a0\u00a0\u00a0 Able to work under pressure with self-motivation.\n\u00a0\u00a0\u00a0\u00a0\u00a0\u00a0\u00a0\u00a0 Excellent written and verbal communication skills in Chinese and English\n\u00a0\u00a0\u00a0\u00a0\u00a0\u00a0\u00a0\u00a0 Immediate available is highly preferred\n\nInterested parties please send your full resume with expected salary and availability by clicking \"Apply Now\".\u00a0\n\nPersonal date provided by job applicants will be used strictly for recruitment related purpose. Those applications do not receive any response from us in 4 weeks may be considered as unsuccessful and their personal data will be destroyed in one month after the vacancy is filled up.", "employment_types": ["Full Time", "Permanent"], "selling_points": ["Provide technical support", "Assist project deployment for Hardware & Sfotware", "Can work independently and under pressure"], "locations": ["Kwai Tsing Area"], "categories": ["Information Technology (IT)", "Hardware", "Support"], "post_time": "2022-01-14T01:30:34Z", "salary": {"currency": null, "max": null, "min": null, "period": "monthly", "term": null}, "salary_visible": false, "title_keywords": ["technician"], "responsibilities": ["provide support", "maintaining", "data", "technical support", "diagnose", "procedures", "teams", "resolution", "hardware", "installing", "ad hoc projects", "troubleshoot", "customer issues", "hardware issues", "report"], "requirements": {"degrees": ["degree"], "majors": ["computer science", "information technology"], "languages": ["english", "chinese"], "language_level": ["excellent"], "hard_skills": ["problem-solving skills", "linux", "basic"], "soft_skills": ["communication skills", "problem-solving skills", "self-motivation", "work under pressure"], "languages_combined": [{"language": "english", "language_level": ["excellent"]}, {"language": "chinese", "language_level": ["excellent"]}]}, "experience_required": {"duration": [], "field": []}}, {"job_id": "100003009045845", "location_code": "hk", "company": "ARINC", "job_title": "IT Hardware/Software Service Technician (Onsite at Airport)", "description": "The job:\nThe successful candidate will be taking\u00a0a pre-sales role in proposing high-value IT services and solutions consultancy for our clients with various IT needs.\n\n\u00a0Responsibilities:\n\nReviewing the customer IT environment, customer strategic goals, existing capabilities, and other factors that influence project direction\nCollecting customer requirements and designing technical solutions\nArticulating in a clear manner, alternatives in terms of cost, benefit, and risk where multiple solutions exist\nWorking with the Delivery team in the creation of technical project plans and scope of work\nEngage and support sales team with the delivery of the assigned solutions\nDevelop infrastructure solution offerings for sales team to sell to customers\n\n\u00a0Requirements:\n\nHigher Diploma or Degree holder in Computer Science or related disciplines\nMinimum 2+ years\u2019 pre-sales solution experience in IT industry\nIn-depth knowledge in server, storage, networking, virtualization and cloud solutions\nSolid experience in infrastructure solution design\nExperience participating in solution configuration, proof of concept, proposal development and competitive analysis\nDynamic, self-motivated and able to work under pressure\nGood communication and presentation skills in both spoken and written English and Chinese\nWith advantage having experience in storage networking solution\n\nWe offer a competitive remuneration package to the right candidate. Interested parties\u00a0please send your full resume with\u00a0present and expected salary\u00a0to us by\u00a0clicking 'Apply Now'.\u00a0\n\nOnline Job Application:\u00a0https://karingroup.com/careers/.\n\nCorporate Website:\u00a0https://karingroup.com/kepro-solutions/\n\n\n(We are an Equal Opportunity Employer and personal data collected would be used for\u00a0 recruitment purpose only.)", "employment_types": ["Full Time"], "selling_points": ["Hardware / Software Service Support Technician", "Good learning and team work environment", "1-2 years of PC Hardware / Software Support"], "locations": ["Airport Area"], "categories": ["Information Technology (IT)", "Hardware", "Support", "Network & System"], "post_time": "2022-01-13T08:53:46Z", "salary": {"currency": null, "max": null, "min": null, "period": "monthly", "term": null}, "salary_visible": false, "title_keywords": ["technician"], "responsibilities": ["cost", "infrastructure", "develop", "sales team", "designing", "plans"], "requirements": {"degrees": ["diploma", "degree holder"], "majors": ["related disciplines", "computer science"], "languages": ["english", "chinese"], "language_level": ["good"], "hard_skills": ["server", "analysis", "dynamic"], "soft_skills": ["self-motivated", "communication", "presentation skills", "dynamic", "work under pressure"], "languages_combined": [{"language": "english", "language_level": ["good"]}, {"language": "chinese", "language_level": ["good"]}]}, "experience_required": {"duration": ["minimum 2+ years"], "field": ["infrastructure", "development", "it", "design"]}}, {"job_id": "100003009054241", "location_code": "hk", "company": "", "job_title": "IT Infrastructure Analyst", "description": "Job Responsibilities:\n\n\nResponsible for IT infrastructure, helpdesk, hardware and application support for offices and clinics\nPerform PC troubleshooting, software and hardware installation\nProvide basic end-user training\nAdministrate hardware and software procurement and inventory\nMonitor servers, systems health and routine system operations\nMaintain administrative records, perform analysis and troubleshooting of system servers, including review server event log for system problems, use active directory to setup / change user accounts\nAssist with covers, audits and any other duties as assigned by Management\nJob Requirements:\n\n\nHigher Diploma or above in Computer Studies or related discipline;\n2 years relevant working experience in IT support\nHands on experience in Active Directory, O365 VMware, FortiGate administration\nKnowledge of network technologies, TCP/IP, network and cyber security\nHolder of MCSE / CCNA is an advantage\nCustomer focus, good problem-solving skill, self-initiative and responsible\nGood command of spoken and written English and Chinese\nFresh graduate will also be considered\n\nPlease apply in confidence with full resume, expected salary and availability to the Human Resources Department, OT&P by emailing us via\u00a0 projob@ otandp.com\u00a0or\u00a0 by clicking \u201cApply Now\u201d button.\n\nThe information provided will be used for selection purpose only. All information of unsuccessful applicants will be destroyed within six months.", "employment_types": ["Full Time", "Permanent"], "selling_points": ["5 years or above in-house IT support", "Software/Hardware/Networking", "Good communication"], "locations": ["Kowloon Bay"], "categories": ["Information Technology (IT)", "Hardware", "Support", "Application Specialist - Network"], "post_time": "2022-01-17T08:54:57Z", "salary": {"currency": null, "max": null, "min": null, "period": null, "term": null}, "salary_visible": false, "title_keywords": ["analyst"], "responsibilities": ["installation", "any other duties", "management", "it infrastructure", "software", "active directory", "operations", "inventory", "systems", "monitor", "troubleshooting", "analysis", "review", "hardware", "hardware and software procurement", "maintain", "audits", "setup"], "requirements": {"degrees": ["higher diploma or above", "fresh graduate"], "majors": ["computer studies"], "languages": ["english", "chinese"], "language_level": ["good command"], "hard_skills": ["o365", "mcse", "vmware", "active directory", "tcp", "cyber security", "problem-solving", "ccna", "ip", "focus"], "soft_skills": ["confidence", "responsible", "problem-solving", "hands on", "self-initiative", "customer focus", "active"], "languages_combined": [{"language": "english", "language_level": ["good command"]}, {"language": "chinese", "language_level": ["good command"]}]}, "experience_required": {"duration": ["2 years"], "field": ["administration", "relevant working experience", "it support"]}}, {"job_id": "100003009055176", "location_code": "hk", "company": "Win Hanverky Holdings Limited", "job_title": "IT Specialist", "description": "Responsibilities\n\n\nProvide technical support and troubleshooting to end users on hardware, software and computer services\u00a0\nPerform maintenance, configuration and monitoring of IT equipment\nPerform management of hardware and software inventory\nAssist in IT documentation, process improvement and equipment procurement\nAssist in project support and perform ad hoc duties as assigned\nRequirements:\n\n\nDegree in Information Technology, Computer Science or related disciplines\nCCNA/CCNP/MCSE certificate holder will be an advantage\n2 years experience in IT Support\nHands on experience in O365 (Teams/SharePoint Online), Win10, Active Directory, VMWare/Hyper-V\nKnowledge in TCP/IP, Wi-Fi, Firewall, network infrastructure and security technology\nA self-motivated and organized individual with good problem solving skills and strong sense of responsibility\nAbility to work independently, flexibly and positively\nGood command in both spoken and written English and Chinese (Cantonese and Mandarin)\u00a0\nApplicants with less experience will be considered as IT Officer.\u00a0 Fresh graduates is also welcomed\nInterested parties please send your resume with your\u00a0current and expected salary\u00a0to email:\u00a0hrd @ win-hanverky.com.hk\u00a0or click \"APPLY NOW\".\u00a0The closing date for application is 17 February 2022.\u00a0All information collected will be kept in strict confidence and will be used for recruitment purpose only.", "employment_types": ["Full Time", "Permanent"], "selling_points": [], "locations": ["Lai Chi Kok"], "categories": ["Information Technology (IT)", "Hardware", "Technical / Functional Consulting", "Others"], "post_time": "2022-01-18T01:38:51Z", "salary": {"currency": null, "max": null, "min": null, "period": "monthly", "term": null}, "salary_visible": false, "title_keywords": ["it specialist"], "responsibilities": ["ad hoc duties", "management", "software", "maintenance", "technical support", "configuration", "inventory", "computer services", "monitoring", "troubleshooting", "hardware", "documentation", "it equipment"], "requirements": {"degrees": ["certificate", "degree"], "majors": ["related disciplines", "computer science", "information technology"], "languages": ["cantonese", "english", "chinese", "mandarin"], "language_level": ["good command"], "hard_skills": ["mcse", "o365", "hyper-v", "vmware", "active directory", "tcp", "wi-fi", "ccnp", "ccna", "ip", "firewall", "problem solving skills"], "soft_skills": ["organized", "self-motivated", "work independently", "sense of responsibility", "hands on", "problem solving skills", "active"], "languages_combined": [{"language": "cantonese", "language_level": ["good command"]}, {"language": "english", "language_level": ["good command"]}, {"language": "chinese", "language_level": ["good command"]}, {"language": "mandarin", "language_level": ["good command"]}]}, "experience_required": {"duration": ["2 years"], "field": ["it", "it support"]}}, {"job_id": "100003009055831", "location_code": "hk", "company": "Ambition", "job_title": "IT Deskside Support (Contract)", "description": "RESPONSIBILITIES\n\n- Handle enquiry via Helpdesk Hotline, in person or email and provide technical support to both\nour internal users and agency.\n- Provide 1st level supports on hardware & software troubleshooting\n- Provide PC installation and software deployment\n- Log all incident and request cases on the call logging system and follow up its status\n- Escalate incidents and problems to relevant second-level support team or external service providers\n- Relocation for desktop items and maintains the correct inventory record\n- Handle ad hoc IT support duties as assigned\n- Standby support during non-working hours when required\n\nREQUIREMENTS\n\n- Higher Diploma in Information Technology or related disciplines\n- 3+ years of IT support experience in Banking/Finance\n- Good communication skill in English & Chinese\n\nInterested parties, please click \"APPLY NOW\" or send your application to karis.chan@ambition.com.hk\n\nIf this job isn't quite right for you, but you know someone who would be great at this role, why not take advantage of our referral scheme? We offer HKD1000 in Apple gift cards for every referred candidate who we place in a role. Terms & Conditions Apply. https://www.ambition.com.hk/refer-a-friend", "employment_types": ["Full Time", "Permanent"], "selling_points": ["Renewable contract", "Financial Services", "Deskside suppor"], "locations": ["Not Specified"], "categories": ["Information Technology (IT)", "Hardware", "Support", "Others"], "post_time": "2022-01-18T02:59:37Z", "salary": {"currency": null, "max": null, "min": null, "period": "monthly", "term": null}, "salary_visible": false, "title_keywords": [], "responsibilities": ["installation", "ad hoc", "software", "technical support", "handle enquiry", "troubleshooting", "inventory record", "hardware", "escalate incidents"], "requirements": {"degrees": ["diploma"], "majors": ["related disciplines", "information technology"], "languages": ["english", "chinese"], "language_level": ["good"], "hard_skills": [], "soft_skills": ["communication skill"], "languages_combined": [{"language": "english", "language_level": ["good"]}, {"language": "chinese", "language_level": ["good"]}]}, "experience_required": {"duration": ["3+ years"], "field": ["finance", "banking", "it support"]}}, {"job_id": "100003009055525", "location_code": "hk", "company": "Educational Publishing House, Limited", "job_title": "System Support Assistant (\u96fb\u8166\u6280\u8853\u54e1)", "description": "Responsibilities\n\nPerform troubleshooting and provide day-to-day support including hardware, software, end-user and helpdesk;\nPerform hardware installation, configuration or maintenance, including PC, notebook, Mac, server, printer and other computer peripheral devices;\nConduct software installation, configuration or maintenance including MS-Office, Outlook, Windows, Mac, Adobe products, AntiVirus and other office applications;\nProvide regular testing of IT equipment and monitoring of IT equipment status and ah hoc on site support;\n\nRequirements\n\nIVE/Diploma holder in Information System, Computer Science, Computer Engineering or related disciplines;\n1 year experience in IT technical / deskside support will be an advantage, fresh graduates are also welcomed;\nKnowledge in Windows;\nKnowledge in AD, DNS, FTP, TCP/IP, POP3, SMTP & SNMP;\nGood computer knowledge of MS-Word, Excel, PowerPoint;\nGood command of spoken and written English and Chinese\nImmediately available will be an advantage\n\nWe offer excellent career development opportunities to unleash your potential, competitive remuneration package including a 5-day work week, medical insurance & dental plan, discretionary bonus, staff training and staff purchasing discount etc.\n\n\nInterest parties, please simply click \"Apply now\" to submit your application with full resume stating current & expected salary and the availability for reporting duty.\u00a0\n\nYou are welcome to visit our website to know more about us:\u00a0www.popular.com.hk\u00a0or http://ephhk.popularworldhk.com.\n\n\nPersonal data provided by job applicants will be kept strictly confidential and will be used solely\u00a0for employment related purpose.\u00a0\u00a0Only short-listed candidates will be contacted.", "employment_types": ["Full Time", "Permanent"], "selling_points": ["5 days work, bonus, medical & dental", "Stable working environment", "IT hardware and software support"], "locations": ["Tsuen Wan Area"], "categories": ["Information Technology (IT)", "Hardware", "Support", "Others"], "post_time": "2022-01-18T02:40:47Z", "salary": {"currency": null, "max": null, "min": null, "period": "monthly", "term": null}, "salary_visible": false, "title_keywords": ["system support", "assistant"], "responsibilities": ["installation", "software", "maintenance", "configuration", "monitoring", "troubleshooting", "testing", "hardware", "it equipment"], "requirements": {"degrees": ["diploma holder"], "majors": ["related disciplines", "computer engineering", "computer science"], "languages": ["english", "chinese"], "language_level": ["good command"], "hard_skills": ["ms-word", "excel", "dns", "tcp", "information system", "powerpoint", "ip"], "soft_skills": [], "languages_combined": [{"language": "english", "language_level": ["good command"]}, {"language": "chinese", "language_level": ["good command"]}]}, "experience_required": {"duration": ["1 year"], "field": ["it"]}}, {"job_id": "100003009055250", "location_code": "hk", "company": "iCON Business Systems Ltd", "job_title": "System Support Engineer", "description": "Responsibilities:\n- Reporting to Team Head\n- To Follow company instruction to fulfill job requirements\n- To Attend service job call according to schedule\n- To Complete project on customer site according to customer requirement\n- To Analyze, break and fix and installation and setup for PCs, Servers, peripherals and Networking issue\n\nRequirement:\n- VTC Graduate / F.5 or above, with at least 2 years\u2019 experience in computer field services\n- Be Able to provide good customer service & good communication skill\n- Be Familiar with Microsoft Windows operation and networking\n- Be Hardworking, Mature, Willing to Learn with good team-work spirit\n- Less-experienced or Fresh Graduates will be considered\n\nWe offer comprehensive remuneration and benefits, and excellent career opportunities to the right candidates. Interested parties please state clearly the position you are applying with reference no. if any in the subject line and email a full resume with CURRENT & EXPECTED SALARY to our company HR email address.\n\nAll applications will be treated in the strictest confidence. We regret that only shortlisted candidates will be notified. Data collected will be used for recruitment purpose only.\n", "employment_types": ["Full Time", "Permanent"], "selling_points": ["IT Field Service", "System Support", "Desktop Support"], "locations": ["Cheung Sha Wan"], "categories": ["Information Technology (IT)", "Hardware", "Support"], "post_time": "2022-01-18T01:55:29Z", "salary": {"currency": null, "max": null, "min": null, "period": "monthly", "term": null}, "salary_visible": false, "title_keywords": ["system support", "engineer"], "responsibilities": ["reporting"], "requirements": {"degrees": [], "majors": [], "languages": [], "language_level": [], "hard_skills": ["servers"], "soft_skills": ["communication skill", "willing to learn", "mature", "customer service", "hardworking"], "languages_combined": []}, "experience_required": {"duration": ["at least 2 years"], "field": []}}, {"job_id": "100003009055151", "location_code": "hk", "company": "Optimum Solutions (Singapore) Pte Ltd", "job_title": "Onsite Helpdesk Support Officers (Multiple openings) (32K)", "description": "Job Description:\n\nSupervise and perform on-site technical and operational support and monitoring on the wristband operations at Boundary Control Points\u00a0\nSupervise the front line operation team to ensure the smooth operation of the quarantine-free travel between Mainland and HK\nCommunicate with the outbound passengers and provide guidance and assistance in using the \"Hong Kong Health Code\" system and the code conversion\n\n\nRequirements:\n\nDiploma or above in any disciplines with at least FIVE years IT-related working experience\u00a0\nCandidates should be technically sound in operating Android and iOS mobile phone\nCandidates should be polite, patience and have good communication skill\nGood command of Chinese and English\nFully vaccinated\u00a0\nWorking location: Border Control Points\nWorking on Saturday, Sunday and Public Holidays is required on roster basis\nOvernight work is required on roster basis", "employment_types": ["Full Time", "Contract"], "selling_points": ["Onsite helpdesk support on mobile apps", "Good communication skills", "5 days work / 8.8 hours per day / Shift work"], "locations": ["Not Specified"], "categories": ["Sales, CS & Business Devpt", "Call Centre", "Information Technology (IT)", "Hardware", "Support"], "post_time": "2022-01-18T01:28:50Z", "salary": {"currency": null, "max": null, "min": null, "period": "monthly", "term": null}, "salary_visible": false, "title_keywords": [], "responsibilities": ["communicate with", "control", "operational support", "operations", "monitoring", "provide guidance"], "requirements": {"degrees": ["diploma or above"], "majors": ["it", "any disciplines"], "languages": ["english", "chinese"], "language_level": ["good command"], "hard_skills": ["mobile", "android"], "soft_skills": ["communication skill", "polite", "patience"], "languages_combined": [{"language": "english", "language_level": ["good command"]}, {"language": "chinese", "language_level": ["good command"]}]}, "experience_required": {"duration": ["at least five years"], "field": ["related", "it"]}}, {"job_id": "100003009055864", "location_code": "hk", "company": "Peoplebank Hong Kong Ltd", "job_title": "Data Center Engineer (1-year renewable contract)", "description": "Duties & Responsibilities\n\nPerform daily IT operations at IT Monitoring Centre\nServices/system monitoring and 1st tier troubleshooting\nDaily scheduled task execution such as system jobs processing, system health check, preparing regular reports, etc\nProvides support to Data Centre facilities operations\nPerform ad-hoc tasks as assigned by supervisor\n7x24 shift works is required\n\n\n\nQualification and Experience\n\nDiploma or above in Computer Science, Electrical Engineering or related disciplines\n2+ years of experience in IT industry\nWork independent, analytical, good problem-solving skills\nIT professional certification (MCSE, CCNA, \u2026etc) is an advantage.\nExposure to cloud and virtualization technologies\nWilling to learn & good sense of responsibilities\nGood command of written and spoken English and Chinese\nLess expereinced / Fresh graduate with internship experience will be considered for junior role\n\nInterested parties please send your resume by Apply Now.", "employment_types": ["Full Time", "Contract"], "selling_points": ["Renewable contract", "With cloud and advance tech exposure", "Shift duty is required"], "locations": ["Sham Shui Po"], "categories": ["Information Technology (IT)", "Hardware", "Support", "Network & System"], "post_time": "2022-01-18T03:01:28Z", "salary": {"currency": null, "max": null, "min": null, "period": "monthly", "term": null}, "salary_visible": false, "title_keywords": ["engineer"], "responsibilities": ["data", "operations", "ad-hoc tasks", "monitoring", "troubleshooting", "reports"], "requirements": {"degrees": ["fresh graduate", "diploma or above"], "majors": ["related disciplines", "electrical engineering", "computer science"], "languages": ["english", "chinese"], "language_level": ["good command"], "hard_skills": ["problem-solving skills", "processing", "ccna", "mcse"], "soft_skills": ["independent", "willing to learn", "troubleshooting", "problem-solving skills", "sense of responsibilities"], "languages_combined": [{"language": "english", "language_level": ["good command"]}, {"language": "chinese", "language_level": ["good command"]}]}, "experience_required": {"duration": ["2+ years"], "field": ["it"]}}, {"job_id": "100003009052961", "location_code": "hk", "company": "NexLen International Limited", "job_title": "Technician / Technical Support Engineer", "description": "Job Responsibilities\n\nTo provide hardware and software maintenance or remote support to solve the IT related problems\nTo provide the system setting and configuration\nTo handle customer technical enquiries and product / system demonstration\nTo assist in managing hardware and software inventory items\n\nRequirements\n\nCertificate / Diploma in IT or relevant discipline\nExperience in IT Industry or relevant experience is highly preferred\nFresh graduate will also be considered, will provide professional training to the right candidate\nGood communication skill, outgoing and self-motivated personality is required\nGood team player, willing to work under pressure and tight schedule\nGood command of both spoken and written English and Chinese\n\nWe offer attractive salary and fringe benefit package to the right candidate. Interested parties please send full resume to us.\n\nPersonal data provided in your application will be kept in the strictest confidence. It will be used for employment-related purposes. Applications not notified within 1 month will be considered as unsuccessful. Unsuccessful application may be kept for another 3 months for new openings before properly shredded.\n\nDBcampaignaviation\n", "employment_types": ["Full Time", "Permanent"], "selling_points": ["Experience in IT Industry or relevant experience", "Fresh graduate will also be considered", "Technician, Technical support engineer"], "locations": ["Kwun Tong"], "categories": ["Engineering", "Engineering Project Management", "Information Technology (IT)", "Hardware", "Support"], "post_time": "2022-01-17T04:42:31Z", "salary": {"currency": null, "max": null, "min": null, "period": "monthly", "term": null}, "salary_visible": false, "title_keywords": ["technician", "technical support engineer"], "responsibilities": ["software", "configuration", "inventory", "hardware", "hardware and software maintenance"], "requirements": {"degrees": ["certificate", "diploma", "fresh graduate"], "majors": ["it"], "languages": ["english", "chinese"], "language_level": ["good command"], "hard_skills": [], "soft_skills": ["outgoing", "good team player", "self-motivated", "communication skill", "work under pressure"], "languages_combined": [{"language": "english", "language_level": ["good command"]}, {"language": "chinese", "language_level": ["good command"]}]}, "experience_required": {"duration": [], "field": ["it", "relevant experience"]}}, {"job_id": "100003009055294", "location_code": "hk", "company": "Wellesley Associates Limited", "job_title": "IT System Administrator/ System Engineer \u2013 Financial Services - 25-40K + Bonus", "description": "Background:\u00a0My client is a well-known financial services firm who is now looking for an System Administrator to join their IT team.\n\nJob Scope:\n\n\nPerform system installation and rollout\n\nProvide technical support including Server administration, system maintenance,\u00a0basic network connectivity, etc\n\nProvide IT infrastructure support such as installation, configuration, upgrade of hardware and computer applications\nLiaise with vendor/supplier to setup IT infrastructure\nProvide assistance to manager to lead and drive projects\nPerform evaluation, installation, configuration, administration and troubleshooting of resources including VM,OS, hardware & software\nSupport focus on Windows and Virtualization\nProvide basic end-user support service to internal users\u00a0\n\nRequirement:\n\nPossess Higher Diploma or above academic certifications in Computer Science or IT related discipline\n\nSolid experience in Windows Server infrastructure,\u00a0Server Virtualization platform, Storage System or inter-networking\nHands on experience in virtualization solution\nProcess excellent problem solving and communication skills\nProficiency in both written and spoken Chinese and English\nEnergetic, self-motivated, teamwork, dynamic and able to work under pressure\nCandidates with less years of experience will also be considered\u00a0\n\nIf you are interested in this position, please apply online with your latest CV in Word format including current & expected salary. Kindly note that only shortlisted candidates will be notified.", "employment_types": ["Full Time"], "selling_points": ["System Administrator", "25-40K + Bonus", "Financial Services/ Good Working Culture"], "locations": ["Not Specified"], "categories": ["Information Technology (IT)", "Hardware", "Support", "Network & System"], "post_time": "2022-01-18T02:05:14Z", "salary": {"currency": null, "max": null, "min": null, "period": "monthly", "term": null}, "salary_visible": false, "title_keywords": ["system engineer", "system administrator"], "responsibilities": ["installation", "it infrastructure", "maintenance", "software", "technical support", "configuration", "work under pressure", "infrastructure", "troubleshooting", "communication", "hardware", "computer applications", "evaluation", "liaise with", "provide assistance", "setup", "administration"], "requirements": {"degrees": ["higher diploma or above"], "majors": ["it", "computer science"], "languages": ["english", "chinese"], "language_level": ["proficiency"], "hard_skills": ["infrastructure support", "basic", "maintenance", "server administration", "vendor", "word", "problem solving", "hardware", "os", "dynamic", "server", "focus", "windows server"], "soft_skills": ["communication skills", "self-motivated", "teamwork", "interested in", "troubleshooting", "problem solving", "hands on", "dynamic", "focus", "energetic", "work under pressure"], "languages_combined": [{"language": "english", "language_level": ["proficiency"]}, {"language": "chinese", "language_level": ["proficiency"]}]}, "experience_required": {"duration": [], "field": ["infrastructure"]}}, {"job_id": "100003009052153", "location_code": "hk", "company": "Manmachine Systems Consultants Ltd", "job_title": "I.T. Support", "description": "Job Description\n\nProvide technical support (off site and on-site) to SMB clients on servers, desktops and network issues.\nAssist project deployment for Hardware and software\n\n\n\nRequirement\n\nAt least 1 year related working experience\nCan work independently and under pressure\nMCSE ,VCP and CCNA is an advantage\nGood communication skill\nCandidate with less experience will be considered.\n\n\n\nWe provide attractive remuneration package to right candidate. Interested parties please send full resume and expected salary to us.\n\nPersonal data will be used for recruitment purpose only.", "employment_types": ["Full Time", "Permanent"], "selling_points": ["Provide technical support", "Assist project deployment for Hardware & software", "MSCE and CCNA holder is an advantage"], "locations": ["Kwai Tsing Area"], "categories": ["Information Technology (IT)", "Application Specialist - Software", "Hardware", "Support"], "post_time": "2022-01-17T02:16:40Z", "salary": {"currency": null, "max": null, "min": null, "period": "monthly", "term": null}, "salary_visible": false, "title_keywords": [], "responsibilities": ["technical support", "hardware", "network issues", "software"], "requirements": {"degrees": [], "majors": [], "languages": [], "language_level": [], "hard_skills": ["mcse", "ccna"], "soft_skills": ["work independently", "communication skill", "under pressure"], "languages_combined": []}, "experience_required": {"duration": ["at least 1 year"], "field": ["related"]}}, {"job_id": "100003009053247", "location_code": "hk", "company": "Classy Wheeler Limited", "job_title": "Senior Infrastructure Team Leader / Systems Engineer", "description": "Senior Infrastructure Team Leader (Hedge funds)\n\nResponsibilities\n\nImplementation and support of our client\u2019s IT Infrastructure\nResponsible for systems/technical support and administration on network, desktop/server hardware and software, and application systems\nProvide Level 3 support for incidents and problem resolution\nInteract with other team members and other teams to progress projects and incidents\nLead a team of Engineers\n\nRequirements\n\nUniversity degree IT / Engineering or equivalent\n4 - 8 years' relevant experience in technical support and administration for All Windows platforms including Microsoft Windows 10/11, Microsoft Office 2019/2016, Windows Server 2019/2016 (Active Directory Administration / Group Policy), Microsoft Exchange Server\nUnderstanding of networking concepts: TCP/IP, LAN/WAN, DHCP, DNS, Routing, Switching/Firewall\nExperience working with Cisco Firewall/switches\nExperience with virtualisation software e.g. VMWare\nExperience in Citrix XenApp, SQL Server, Data Storage, SCCM, HA Cluster, Microsoft Remote Desktop Services and Cloud based Architectures will be an advantage\nCertificate Holders of CCNA, CCNP, CCIE or MCSE is a plus\nSelf-starter who is confident, action and results orientated\nMust be attentive to detail, proactive and have strong troubleshooting skills\nTechnical, analytical, interpersonal and organisation skills required\n\nSystems Engineer (Hedge funds)\n\nResponsibilities\n\nImplementation and support of our client\u2019s IT Infrastructure\nResponsible for systems/technical support and administration on network, desktop/server hardware and software, and application systems\nProvide Level 1 \u2013 3 support for incidents and problem resolution\nInteract with other team members and other teams to progress projects and incidents\n\nRequirements\n\nUniversity degree IT / Engineering or equivalent\n2 - 7 years' relevant experience in technical support and administration for All Windows platforms including Microsoft Windows 10/11, Microsoft Office 2019/2016, Windows Server 2019/2016 (Active Directory Administration / Group Policy), Microsoft Exchange Server\nUnderstanding of networking concepts: TCP/IP, LAN/WAN, DHCP, DNS, Routing, Switching/Firewall\nExperience working with Cisco Firewall/switches\nExperience with virtualisation software e.g. VMWare\nExperience in Citrix XenApp, SQL Server, Data Storage, SCCM, HA Cluster, Microsoft Remote Desktop Services and Cloud based Architectures will be an advantage\nCertificate Holders of CCNA, CCNP, CCIE or MCSE is a plus\nSelf-starter who is confident, action and results orientated\nMust be attentive to detail, proactive and have strong troubleshooting skills\nTechnical, analytical, interpersonal and organisation skills required\n\nSenior Infrastructure Specialist (Listed companies)\n\nResponsibilities\n\nMaintain, improve and optimize the WAN, LAN and WIFI network infrastructure\nManage, implement various storage (e.g. SAN, NAS, DAS, etc) to cope with capacity planning\nHarness virtualization technologies to lower hardware cost, improve efficiency and provide high availability to minimize potential service outage or degrade\nOperate the company Email facilities and server/system infrastructure to assure IT services maximum uptime\nManage, monitor and optimize various cloud platform such as Microsoft O365, AWS\nProtect business data by using various backup strategies to ensure data can be recovered when required\nDesign and implement appropriate technologies and security strategy to protect IT infrastructure\nDevelop and implement IT disaster recovery strategy to protect IT infrastructure and minimize downtime and data loss in the event of a disaster\n\nRequirements\n\nBachelor in Information Technology or related discipline\nMinimum 5 years working experience in IT infrastructure\nStrong technical skill on server and system administration (Windows and Linux), Backup and DR (Veeam), virtualization technology (VMware)\nExperience on IT security products such as EPP, EDR, Endpoint management, patching tools, NAC, DLP. MFA, Email Security, Darktrace etc is preferred\nExperience on administering and maintaining AD, O365 (Teams, OneDrive, Sharepoint online, Exchange online) is preferred\nExperience on storage technologies such as SAN (HPE 3PAR) and NAS is preferred\nFamiliar with network and system monitoring tools (Whatsup gold), Group policy, Powershell scripting\nHands-on experience on project and vendor management\nProactive with strong sense of responsibility and result-oriented\nExcellent interpersonal and communication skills with good analytic and problem solving capacity\n\nSystem Engineer (IT Solutions company)\n\nResponsibilities\n\nInstallation / maintenance of IT infrastructure, servers, IPT, voice, telephone system\nProvide IT support and help desk activity\n\nRequirements\n\nMinimum 1 year experience in IT industry\nFamiliar with MS platform including Windows 7 / 8 / 10 and Windows Server 2008 / 2012 / 2016\nKnowledge and experience of Skype for Business / Teams / Office 365 / Azure is an advantage\nKnowledge and experience of Telephony System, IP PBX or call center system is an advantage\nKnowledge and experience of Voice-Over-IP and networking is an advantage\nKnowledge and experience of DB SQL Statement / Store Procedure is an advantage\nGood command of spoken and written English and Chinese\nResponsible, self-motivated, flexible and with detailed mind\nAble to work independently and under pressure\nWilling to learn\nOvertime work is required\n\nInterested applicants, please email your detailed resume quoting position title, reference number and expected salary.\n\nPersonal data provided by job applicants will be used strictly in accordance with the employer's personal data policies and for recruitment purposes only.", "employment_types": ["Full Time", "Permanent"], "selling_points": ["Finance industry / Listed company", "Exposure to large-scale projects", "Stable environment, attractive renumeration"], "locations": ["Not Specified"], "categories": ["Information Technology (IT)", "Hardware", "Support", "Network & System"], "post_time": "2022-01-17T06:31:27Z", "salary": {"currency": null, "max": null, "min": null, "period": "monthly", "term": null}, "salary_visible": false, "title_keywords": ["team leader", "systems engineer"], "responsibilities": ["it infrastructure", "server hardware", "software", "technical support", "systems", "teams", "implementation", "resolution", "lead a team", "application systems", "administration"], "requirements": {"degrees": ["certificate", "university degree", "bachelor"], "majors": ["it", "engineering", "information technology"], "languages": ["english", "chinese"], "language_level": ["good command"], "hard_skills": ["o365", "plus", "azure", "active directory", "ccnp", "vendor", "server", "wan", "data storage", "microsoft exchange", "exchange", "vmware", "servers", "tcp", "ccna", "problem solving", "firewall", "virtualization technology", "office 365", "sccm", "windows 7", "aws", "sql", "citrix", "mcse", "linux", "dns", "maintenance", "microsoft office", "windows 10", "ip", "hardware", "powershell", "nas", "windows server"], "soft_skills": ["attentive to detail", "under pressure", "troubleshooting", "confident", "problem solving", "overtime work", "detailed mind", "interpersonal", "communication skills", "work independently", "willing to learn", "technical skill", "active", "result-oriented", "detailed", "flexible", "self-motivated", "responsible", "sense of responsibility", "hands-on", "organisation", "proactive"], "languages_combined": [{"language": "english", "language_level": ["good command"]}, {"language": "chinese", "language_level": ["good command"]}]}, "experience_required": {"duration": ["4 - 8 years", "minimum 1 year", "minimum 5 years", "2 - 7 years"], "field": ["management", "call center", "infrastructure", "sql", "it", "relevant experience", "security", "business", "administration"]}}, {"job_id": "100003009055625", "location_code": "hk", "company": "Gravitas Recruitment Group", "job_title": "LEADING IBANK - Service desk anaylst", "description": "Opportunity to join a leading Bank!\n\nThe Service Desk Analyst provides support for basic incident resolution and requests reported to the regional service desk.\n\n\nResponsibilities:\n\n\nAct as a single point of contact and support internal staff via phone calls, emails, live chat and self-service tickets from internal staff regarding IT related issues and queries.\n1st line support: troubleshooting of IT related problems\nEscalate unresolved issues / requests to the corresponding helpdesk (L2/L3 support)\nTake ownership of users' problems, follow up the status of problems on behalf of the user and communicate the status to users in a timely manner\nUpdate all taken actions and information into ticketing system in a timely manner\nTo maintain a high degree of customer service for all support queries\nMaintain knowledge database to ensure all information is up-to-date\nDefine / Improve processes and workflows\nCapable to manage projects or tasks given by the manager\n\nProfile Required\n\nRequirements:\n\n\nFluent in English\nExcellent communication skills and telephone manner.\nEffective listening and attentiveness skills\nExcellent organizational skills\nWillingness to improve and to learn\nCustomer service orientation and/or prior customer service training\nTeam player\nBanking experience will be advantageous, but it is not mandatory", "employment_types": ["Full Time", "Permanent"], "selling_points": ["International environment", "Good work-life balance environment", "Great career development"], "locations": ["Not Specified"], "categories": ["Information Technology (IT)", "Hardware", "Support", "Others"], "post_time": "2022-01-18T02:48:37Z", "salary": {"currency": "HKD", "max": 34999, "min": 20000, "period": "monthly", "term": null}, "salary_visible": true, "title_keywords": [], "responsibilities": ["a timely manner", "troubleshooting", "maintain", "customer service", "contact", "database", "manage projects", "phone calls"], "requirements": {"degrees": [], "majors": [], "languages": ["english"], "language_level": ["fluent"], "hard_skills": [], "soft_skills": ["communication skills", "organizational skills", "customer service", "team player", "telephone manner"], "languages_combined": [{"language": "english", "language_level": ["fluent"]}]}, "experience_required": {"duration": [], "field": ["it", "banking experience"]}}, {"job_id": "100003009055783", "location_code": "hk", "company": "Hong Kong Express Airways Limited", "job_title": "Assistant Manager, Infrastructure Operations", "description": "DEAR TALENT, YOUR MOVE!\n\nBeing the new rising airline since 2013, we are the Hong Kong\u2019s only Low Cost Carrier (LCC) offering you safe and flexible service options to Hong Kong and beyond.\n\nWe\u2019re on a mission to inspire you to be different, to shake things up, to inspire the spirit of adventure by bringing you to fascinating destinations that few others serve.\n\nSpread your wings and fly with us!\n\nWhat will you do?\u00a0\n\nLead a small team to maintain daily IT Infrastructure operation to support internal users within SLA under ITIL standard;\nSupport Security team to handle security events in IT infrastructure environment;\nSupport internal audit to assess different IT areas;\nDevelop and maintain formal guidelines, policies, and procedures to ensure the smooth operation;\nManage external vendor to provide technical support on corporate IT Infrastructure with emphasis on the internal network, servers, Microsoft office365 environment and cloud infrastructure;\nManage external vendor to provide technical support on Airport IT Infrastructure with emphasis on Express IP, AviNet, ACARS and EDI about Cargo / Crew / Passenger Information Filing;\nPlan, setup, lead and manage the IT Infrastructure and End-user Technology Strategy including disaster recovery planning;\nResearch on new technology, identify technology gaps, develop and deploy Infrastructure solutions;\nRemediate Risk & Vulnerability for Infrastructure and End-user computing;\nDrive the continuous improvement to all IT Infrastructure related services;\nDetermine how to leverage enabling technologies to implement innovative IT infrastructure solutions to support the business\nCoach and mentor team members;\nTravel occasionally for new station setup/support;\u00a0\nSupport ad-hoc duties as assigned.\n\nWe are a perfect match, if you are:\n\nUniversity graduate in Computer Technology or related discipline;\nMinimum 6 years of related working experiences in IT security with 2 years of supervisor post;\nStrong technical knowledge in all aspects of IT Infrastructure especially in Microsoft Office365, Fortinet, Azure/Alibaba cloud and End-user computing;\nSound Knowledgeable on SOC, DLP and SIEM;\nCertification on networking (such as CCNA, CCNP, CCIE);\nITILv3 Foundation Certification is a must;\nBasic knowledge of common information security management frameworks, such as ISO 27001, CobiT, ITIL, PCI DSS.\n\nYour Future Work Life?\n\nWork flexibly with staggered working hours and flexible workplace\nDress Casual and Smart everyday\nWork in a newly-designed office with open seating, stylish breakout areas, game room, gym and free coffee\u2026\nWork with a group of energetic and multicultural professionals (up to 50 nationalities!)\nHave great fun in Snack Friday, New Year Market, Fly with your Kids Day, Basketball Team\u2026\nHave your voice heard through Townhalls, Crew forums, CEO live sessions etc.\n\nWhat will you enjoy?\n\nFly anywhere we fly for free plus taxes during leisure with your friends and family\nSpecial privileges to buy duty free products\nCareer Express\n\n\nYou will be inspired by our core values.\nYou will be inspired by our vibrant, efficient and entrepreneurial spirit. Join our fun, collaborative and reliable team to ignite your dream!\n\n\nInterested? It\u2019s time to have YOUR MOVE!\nIf you're ready to embark your adventure, start by clicking the \u2018Apply now\u2019 and get on the plane to fly with HK Express!\u00a0", "employment_types": ["Full Time"], "selling_points": ["Flexible Working Practices, WFH, Travel Benefits", "Maintain daily IT infrastructure operations", "Microsoft Office365; Cloud Infrastructure"], "locations": ["Tung Chung"], "categories": ["Information Technology (IT)", "Hardware", "Network & System", "Technical / Functional Consulting"], "post_time": "2022-01-18T02:56:52Z", "salary": {"currency": null, "max": null, "min": null, "period": "monthly", "term": null}, "salary_visible": false, "title_keywords": ["operations", "assistant manager,"], "responsibilities": ["cost", "information security", "management", "it infrastructure", "internal audit", "recovery planning", "guidelines", "policies", "lead a small team", "technical support", "procedures", "infrastructure", "ad-hoc duties", "develop", "maintain", "plan", "deploy", "setup"], "requirements": {"degrees": ["university graduate"], "majors": [], "languages": [], "language_level": [], "hard_skills": ["small", "itil", "plus", "azure", "servers", "basic", "security management", "fun", "ccnp", "ccna", "airline", "vendor", "sla", "safe", "ip", "lcc"], "soft_skills": ["flexible", "efficient", "collaborative", "innovative", "smooth", "reliable", "ad-hoc duties", "energetic"], "languages_combined": []}, "experience_required": {"duration": ["2 years", "minimum 6 years"], "field": ["related", "it", "security"]}}, {"job_id": "100003009055395", "location_code": "hk", "company": "KML Engineering Limited", "job_title": "Junior Technician / Technician / Senior Technician", "description": "Responsibilities\nPerform daily maintenance activities such as faults investigation, recovering and reporting\nCarry out field services, provide hardware maintenance & installation services\nPerform preventive maintenance activities\nSupport project design, implementation and testing\n\nRequirements\nDiploma / Higher Diploma / Degree in Electronic Engineering / Electrical Engineering / Mechanical Engineering or above\nWith at least 1 year(Technician) / 3 years (Senior Technician) experience of electronic and electrical equipment installation and maintenance\nAbility to work independently and work under pressure\nGood skill in Trouble shooting\nGood knowledge in PC including PCB design, CAD drawing & Microprocessor firmware design is preferable\nGood command of written and spoken English and Chinese\nFresh graduate will be considered\n\nKML is an equal-opportunity employer and welcomes applications from all qualified candidates. If you look for an exciting and rewarding career, please send your resume, your present and expected salary.\nPersonal data collected will only be used for recruitment purposes.\n\nInterested candidates, please click APPLY NOW \u00a0to apply.\n\n\n\n", "employment_types": ["Full Time"], "selling_points": [], "locations": ["Not Specified"], "categories": ["Information Technology (IT)", "Hardware", "Others", "Others", "Technician"], "post_time": "2022-01-18T02:26:49Z", "salary": {"currency": null, "max": null, "min": null, "period": "monthly", "term": null}, "salary_visible": false, "title_keywords": ["junior technician", "technician"], "responsibilities": ["reporting", "installation", "maintenance", "implementation", "investigation", "design", "testing", "hardware"], "requirements": {"degrees": ["diploma", "degree", "fresh graduate"], "majors": ["mechanical engineering", "engineering", "electrical engineering"], "languages": ["english", "chinese"], "language_level": ["good command"], "hard_skills": ["pc", "maintenance", "cad"], "soft_skills": ["work independently", "work under pressure"], "languages_combined": [{"language": "english", "language_level": ["good command"]}, {"language": "chinese", "language_level": ["good command"]}]}, "experience_required": {"duration": ["3 years"], "field": ["installation", "maintenance"]}}, {"job_id": "100003009038954", "location_code": "hk", "company": "Tech One Services Limited", "job_title": "IT Support Engineer", "description": "DEAR TALENT, YOUR MOVE!\n\nBeing the new rising airline since 2013, we are the Hong Kong\u2019s only Low Cost Carrier (LCC) offering you safe and flexible service options to Hong Kong and beyond.\n\nWe\u2019re on a mission to inspire you to be different, to shake things up, to inspire the spirit of adventure by bringing you to fascinating destinations that few others serve.\n\nSpread your wings and fly with us!\n\n\nWhat will you do?\u00a0\n\nSupport the Manager, Ground Operations Commercial in the sourcing of suppliers for ground handling services in order to achieve best value for the company;\nExecute the procurement and contract management activities in accordance with the company policy and procedure;\nConduct supplier pre-assessment to ensure suppliers are able to meet the service requirement of the company;\nCoordinate with all internal and external stakeholders on new port setup, GHA changes and terminal move;\nConduct detailed analysis to support cost management;\nPrepare ground handling services budget and process payment requisition for management approval;\nPerform other ad hoc tasks as required;\nOverseas travel is required.\n\nWe are a perfect match, if you have:\n\nDiploma or above in Business or related disciplines;\nMinimum 5 years of work experience in aviation industry including at least 2 years in a commercial or contract management role;\nKnowledge of IATA Standard Ground Handling Agreement is an advantage;\nKnowledge of airport and/or ground operations is an advantage;\nStrong negotiation, communication and analytical skills with proven track record in performing market analysis and cost evaluation;\nSensitivity to numbers and attention to details;\nAbility to manage multiple tasks at the same time;\nGood command of spoken and written English and Chinese;\nGood proficiency in Excel and other Microsoft Office applications;\nCost conscious mindset;\nProject management skills;\nCandidate with more experience would be considered as Supervisor, Ground Operations Commercial.\n\nYour Future Work Life?\u00a0\n\nWork flexibly with staggered working hours and flexible workplace\nDress Casual and Smart everyday\u00a0\u00a0\nWork in a newly-designed office with open seating, stylish breakout areas, game room, gym and free coffee\u2026\u00a0\nWork with a group of energetic and multicultural professionals (up to 50 nationalities!)\u00a0\nHave great fun in Snack Friday, New Year Market, Fly with your Kids Day, Basketball Team\u2026\u00a0\nHave your voice heard through Townhalls, Crew forums, CEO live sessions etc\u00a0\n\nWhat you\u2019ll enjoy?\u202f\u202f\u202f\u00a0\n\nFly anywhere we fly for free plus taxes during leisure with your friends and family\nSpecial privileges to buy duty free products\n\nYou will be inspired by our core values.\u202f\u00a0\n\nYou will be inspired by our\u00a0vibrant,\u00a0efficient\u00a0and\u00a0entrepreneurial\u00a0spirit. Join our fun,\u00a0collaborative\u00a0and\u00a0reliable\u00a0team to ignite your dream!\u202f\u00a0\n\nInterested?\u00a0It\u2019s time to have YOUR MOVE!\u202f\u00a0\n\nIf you're ready to embark your adventure,\u00a0start by clicking the \u2018Apply now\u2019 and\u00a0get on the plane to fly with HK Express!\u202f\u00a0", "employment_types": ["Full Time"], "selling_points": ["Provide Helpdesk Service / end-users IT Support", "Support: Win OS, MS Office, TCP/IP, PC Clone", "HD with 1 yr's exp, good working attitude"], "locations": ["Not Specified"], "categories": ["Information Technology (IT)", "Hardware", "Support", "Network & System"], "post_time": "2022-01-12T23:26:20Z", "salary": {"currency": null, "max": null, "min": null, "period": "monthly", "term": null}, "salary_visible": false, "title_keywords": ["it support engineer"], "responsibilities": ["cost", "management", "operations", "analysis", "budget", "coordinate with", "contract management", "ad hoc tasks", "communication", "project management", "payment", "market analysis", "evaluation", "setup"], "requirements": {"degrees": ["diploma or above"], "majors": ["related disciplines", "business"], "languages": ["english", "chinese"], "language_level": ["good command"], "hard_skills": ["excel", "plus", "fun", "microsoft office", "analysis", "airline", "analytical skills", "project management", "safe", "lcc"], "soft_skills": ["flexible", "efficient", "negotiation", "multiple tasks", "sensitivity", "project management skills", "collaborative", "analytical skills", "communication", "reliable", "attention to details", "energetic", "detailed"], "languages_combined": [{"language": "english", "language_level": ["good command"]}, {"language": "chinese", "language_level": ["good command"]}]}, "experience_required": {"duration": ["at least 2 years", "minimum 5 years"], "field": ["commercial", "management"]}}, {"job_id": "100003009049369", "location_code": "hk", "company": "HGC Global Communications Limited", "job_title": "End User Computing Support Engineer", "description": "DEAR TALENT, YOUR MOVE!\n\nBeing the new rising airline since 2013, we are the Hong Kong\u2019s only Low Cost Carrier (LCC) offering you safe and flexible service options to Hong Kong and beyond.\n\nWe\u2019re on a mission to inspire you to be different, to shake things up, to inspire the spirit of adventure by bringing you to fascinating destinations that few others serve.\n\nSpread your wings and fly with us!\n\nWhat will you do?\u00a0\n\nResponsible for the implementation of the aviation Security Management System and to support the Manager, Security Management System (MSEMS) in maintaining the Security Management System and Aviation Security Programme;\nMaintain the currency of the Aircraft Operator Security Programme (AOSP) and associated documentation by proposing and drafting amendments;\nPrepare security notices and/or articles for relevant personnel in order to address internal and external security issues;\nParticipate investigations into accidents, incidents and/or irregularities affecting the security of operations;\nConduct audits/inspections/surveys and produce reports to ascertain operational security is achieved;\nConduct assessment on the effectiveness of remedial actions/preventative measures associated with the security deficiency;\nMaintain curriculum and syllabus for Security Training Programme;\nDeliver Security Training as and when required;\nConduct Risk Analysis and Threat Assessment and produce reports to ascertain operational security is achieved;\nCoordinate special security measures during periods/instances of increased threat;\nMaintain the internal security vetting programme;\nCoordinate Quality, Safety and Security Action Group Meeting and Security Exercises/Drills;\nParticipate in IOSA programme as and when directed by MSEMS;\nParticipate in projects as and when directed by MSEMS.\n\nWe are a perfect match, if you are:\n\nBachelor degree or above in an aviation or business\u00a0related discipline;\nAt least 5 years aviation or relevant security experience, including 1 year of supervisory, training delivery and/or audit experience;\nGood command of both spoken and written English;\nKnowledge in Chinese (Cantonese and Putonghua) is preferable;\nGood analytical skills and computer literacy;\nGood interpersonal, presentation and communication skill.\n\nYour Future Work Life?\n\nWork flexibly with staggered working hours and flexible workplace\nDress Casual and Smart everyday\nWork in a newly-designed office with open seating, stylish breakout areas, game room, gym and free coffee\u2026\nWork with a group of energetic and multicultural professionals (up to 50 nationalities!)\nHave great fun in Snack Friday, New Year Market, Fly with your Kids Day, Basketball Team\u2026\nHave your voice heard through Townhalls, Crew forums, CEO live sessions etc.\n\nWhat will you enjoy?\n\nFly anywhere we fly for free plus taxes during leisure with your friends and family\nSpecial privileges to buy duty free products\nCareer Express\n\nYou will be inspired by our core values.\nYou will be inspired by our vibrant, efficient and entrepreneurial spirit. Join our fun, collaborative and reliable team to ignite your dream!\n\nInterested? It\u2019s time to have YOUR MOVE!\nIf you're ready to embark your adventure, start by clicking the \u2018Apply now\u2019 and get on the plane to fly with HK", "employment_types": ["Full Time", "Permanent"], "selling_points": ["Internal IT service and operations support", "Vibrant team culture and atmosphere", "System enhancement exposure"], "locations": ["Tsing Yi"], "categories": ["Information Technology (IT)", "Hardware", "Support", "Others"], "post_time": "2022-01-14T08:31:44Z", "salary": {"currency": null, "max": null, "min": null, "period": "monthly", "term": null}, "salary_visible": false, "title_keywords": ["support engineer"], "responsibilities": ["cost", "management", "irregularities", "maintaining", "operations", "conduct audits", "quality", "implementation", "audit", "coordinate", "communication", "maintain", "reports", "risk analysis", "documentation"], "requirements": {"degrees": ["degree or above", "bachelor"], "majors": ["business"], "languages": ["cantonese", "putonghua", "english", "chinese"], "language_level": ["good command"], "hard_skills": ["plus", "security management", "aircraft", "fun", "analysis", "airline", "analytical skills", "safe", "lcc", "documentation"], "soft_skills": ["flexible", "efficient", "responsible", "presentation", "communication skill", "collaborative", "analytical skills", "computer literacy", "reliable", "energetic", "interpersonal"], "languages_combined": [{"language": "cantonese", "language_level": []}, {"language": "putonghua", "language_level": []}, {"language": "english", "language_level": ["good command"]}, {"language": "chinese", "language_level": []}]}, "experience_required": {"duration": ["at least 5 years", "1 year"], "field": ["supervisory", "training", "security", "audit experience"]}}, {"job_id": "100003009050625", "location_code": "hk", "company": "Walters People (HK)", "job_title": "Network Engineer - Finance", "description": "DEAR TALENT, YOUR MOVE!\n\nBeing the new rising airline since 2013, we are the Hong Kong\u2019s only Low Cost Carrier (LCC) offering you safe and flexible service options to Hong Kong and beyond.\n\nWe\u2019re on a mission to inspire you to be different, to shake things up, to inspire the spirit of adventure by bringing you to fascinating destinations that few others serve.\n\nSpread your wings and fly with us!\n\n\nWhat will you do?\u00a0\u00a0\n\nResponsible for payment settlement including payment status and payment cancellation;\nWork closely with the Accounts Payable team to ensure the payments settled on time;\nEnsure payment vouchers and bank reconciliations are completed in a timely manner for month-end closing;\nAssist in daily treasury operations and prepare treasury-related accounting entries, e.g. inter-account transactions and cash pooling;\nSupport ad-hoc projects and tasks as assigned.\n\nWe are a perfect match, if you have:\n\nUniversity Graduate in Finance, Accounting, Business or related discipline;\n2 years of relevant work experience;\nExperience in using Netsuite System, Electronic banking system is a plus;\nExcellent command of spoken and written English and Chinese and proficient in Microsoft Office Suite;\nExcellent numerical and analytical skills, with strong attention to detail and accuracy;\nA quick learner with the ability to work independently and as a team;\nFresh graduate will\u00a0also be\u00a0considered.\n\nYour Future Work Life?\n\nWork flexibly with staggered working hours and flexible workplace\nDress Casual and Smart everyday\nWork in a newly-designed office with open seating, stylish breakout areas, game room, gym and free coffee\u2026\nWork with a group of energetic and multicultural professionals (up to 50 nationalities!)\nHave great fun in Snack Friday, New Year Market, Fly with your Kids Day, Basketball Team\u2026\nHave your voice heard through Townhalls, Crew forums, CEO live sessions etc.\n\nWhat will you enjoy?\n\nFly anywhere we fly for free plus taxes during leisure with your friends and family\nSpecial privileges to buy duty free products\nCareer Express\n\n\n\nYou will be inspired by our core values.\nYou will be inspired by our vibrant, efficient and entrepreneurial spirit. Join our fun, collaborative and reliable team to ignite your dream!\n\n\n\nInterested? It\u2019s time to have YOUR MOVE!\nIf you're ready to embark your adventure, start by clicking the \u2018Apply now\u2019 and get on the plane to fly with HK Express!\u00a0", "employment_types": ["Full Time", "Permanent"], "selling_points": ["CCNA/CCNP", "Router/Switching/Firewall", "DC Network"], "locations": ["Not Specified"], "categories": ["Information Technology (IT)", "Hardware", "Security", "Network & System"], "post_time": "2022-01-14T11:00:09Z", "salary": {"currency": "HKD", "max": 69999, "min": 45000, "period": "monthly", "term": null}, "salary_visible": true, "title_keywords": ["engineer"], "responsibilities": ["cost", "operations", "a timely manner", "bank reconciliations", "transactions", "payment", "month-end closing", "payments", "banking", "ad-hoc projects", "accounts payable"], "requirements": {"degrees": ["university graduate", "fresh graduate"], "majors": ["business", "finance", "accounting"], "languages": ["english", "chinese"], "language_level": ["excellent", "proficient"], "hard_skills": ["plus", "fun", "airline", "netsuite system", "analytical skills", "microsoft office suite", "safe", "lcc"], "soft_skills": ["flexible", "efficient", "work independently", "responsible", "timely", "collaborative", "quick learner", "analytical skills", "reliable", "attention to detail", "energetic"], "languages_combined": [{"language": "english", "language_level": ["proficient", "excellent"]}, {"language": "chinese", "language_level": ["proficient", "excellent"]}]}, "experience_required": {"duration": ["2 years"], "field": ["banking"]}}, {"job_id": "100003009049457", "location_code": "hk", "company": "SmarTone Telecommunications Limited", "job_title": "Senior Technical Support Engineer", "description": "DEAR TALENT, YOUR MOVE!\n\nBeing the new rising airline since 2013, we are the Hong Kong\u2019s only Low Cost Carrier (LCC) offering you safe and flexible service options to Hong Kong and beyond.\n\nWe\u2019re on a mission to inspire you to be different, to shake things up, to inspire the spirit of adventure by bringing you to fascinating destinations that few others serve.\n\nSpread your wings and fly with us!\n\nWhat will you do?\u00a0\n\nPeople Services team is part of the UO People team that provides services and administration of the end-to-end transactional activities associated with the employee experience for UO employees and business units.\u00a0 The team covers talent acquisition, on-boarding, office administration and off-boarding activities.\n\n1. Provide reliable and efficient people administrative support to employees and People department, ensuring reliable and efficient services are provided throughout the UO People Journey.\n\n2. Undertake the full range of transactional people & office administration responsibilities including but not limited to the following:\n\n\u2022\u00a0 Interview scheduling and room arrangements\n\n\u2022\u00a0 Support the application & renewal of work visa for overseas employees\n\n\u2022\u00a0 Mass recruitment contract issuance and renewal (Cockpit and cabin crew)\n\n\u2022\u00a0 Handle routine, ah-hoc projects and other general office administrative tasks as assigned\n\n3. Ensure consistent people administration support to the whole People Team, within agreed parameters in order to maximize efficiency, effectiveness and reliability.\n\n4. Participate in process optimization initiatives where needed\n\n5. Given the handling of sensitive data, maintain confidentiality and observe data protection and associated guidelines where appropriate\n\nWe are a perfect match, if you are/have:\n\nHigh Diploma or above in business, HR or relevant discipline\n1+ years of experience in general HR administration, fresh graduate will also be considered\nAbility to multi-task and be detailed oriented\nAbility to collaborate and work effectively with internal stakeholders\nCapability to work independently with strong sense of responsibility\nGood written and verbal English communication skills\nOpen-minded in making changes to process to improve efficiency\n\nYour Future Work Life?\u00a0\n\nWork flexibly with staggered working hours and flexible workplace\nDress Casual and Smart everyday\u00a0\u00a0\nWork in a newly-designed office with open seating, stylish breakout areas, game room, gym and free coffee\u2026\u00a0\nWork with a group of energetic and multicultural professionals (up to 50 nationalities!)\u00a0\nHave great fun in Snack Friday, New Year Market, Fly with your Kids Day, Basketball Team\u2026\u00a0\nHave your voice heard through Townhalls, Crew forums, CEO live sessions etc\u00a0\n\nWhat you\u2019ll enjoy?\u202f\u202f\u202f\u00a0\n\nFly anywhere we fly for free plus taxes during leisure with your friends and family\nSpecial privileges to buy duty free products\n\nYou will be inspired by our core values.\u202f\u00a0\n\nYou will be inspired by our\u00a0vibrant,\u00a0efficient\u00a0and\u00a0entrepreneurial\u00a0spirit. Join our fun,\u00a0collaborative\u00a0and\u00a0reliable\u00a0team to ignite your dream!\u202f\u00a0\n\nInterested?\u00a0It\u2019s time to have YOUR MOVE!\u202f\u00a0\n\nIf you're ready to embark your adventure,\u00a0start by clicking the \u2018Apply now\u2019 and\u00a0get on the plane to fly with HK Express!\u202f\u00a0", "employment_types": ["Full Time", "Permanent"], "selling_points": ["Degree in Computer Science", "Support & configuration", "Experience in Linux platform"], "locations": ["Ngau Tau Kok"], "categories": ["Engineering", "Others", "Information Technology (IT)", "Hardware", "Support"], "post_time": "2022-01-14T08:42:07Z", "salary": {"currency": null, "max": null, "min": null, "period": "monthly", "term": null}, "salary_visible": false, "title_keywords": ["technical support engineer"], "responsibilities": ["collaborate", "cost", "administrative support", "data", "office administration", "guidelines", "hr", "communication", "scheduling", "maintain", "recruitment", "administrative tasks", "administration"], "requirements": {"degrees": ["high diploma or above", "fresh graduate"], "majors": ["business"], "languages": ["english"], "language_level": ["good"], "hard_skills": ["plus", "fun", "airline", "safe", "lcc"], "soft_skills": ["flexible", "efficient", "work effectively", "work independently", "multi-task", "detailed oriented", "communication skills", "sense of responsibility", "open-minded", "collaborative", "energetic", "sensitive", "reliable"], "languages_combined": [{"language": "english", "language_level": ["good"]}]}, "experience_required": {"duration": ["1+ years"], "field": ["administration", "hr", "business", "team"]}}, {"job_id": "100003009048306", "location_code": "hk", "company": "ST Engineering Infa Systems Limited", "job_title": "System Engineer/System Specialist (ELV System)", "description": "DEAR TALENT, YOUR MOVE!\u00a0\u00a0\n\nBeing the new rising airline since 2013, we are the Hong Kong\u2019s only Low Cost Carrier (LCC) offering you safe and flexible service options to Hong Kong and beyond.\u00a0\n\nWe\u2019re on a mission to inspire you to be different, to shake things up, to inspire the spirit of adventure by bringing you to fascinating destinations that few others serve.\n\nSpread your wings and fly with us!\u00a0\u00a0\n\nWhat you\u2019ll do?\u00a0\n\nSupport the continued airworthiness function;\nManage technical and commercial evaluation to meet the operational and regulatory requirements;\nProvide AOG and on-site support;\nInteract across Airline departments, FTM service provider, vendors and aircraft manufacturers;\nProvide specialist assistant related to airframe systems to support the line and base maintenance;\nReview ADs, SBs and other OEM technical documentation;\nPerform oversight on modifications and other ad-hoc projects;\nSupport projects to induct new and used aircraft onto the Hong Kong register and entry into service;\nProvide out of hours support in accordance with section policy;\nPerforms and carry out other duties the Manager, Technical Services may assign.\n\nWe are a perfect match, if you have:\n\nHolder of an Engineering degree;\nMinimum 5 years of work experience in aircraft maintenance and aviation engineering; 3 years of work experience in aircraft system;\nAircraft Maintenance & Engineering License is preferred;\nExperience of working with airworthiness authorities;\nOrganization Design experience is preferable;\nPotential candidate with more experience will be considered as Senior Technical Service Engineer (System).\n\nYour Future Work Life?\u00a0\n\nWork flexibly with staggered working hours and flexible workplace\nDress Casual and Smart everyday\u00a0\u00a0\nWork in a newly-designed office with open seating, stylish breakout areas, game room, gym and free coffee\u2026\u00a0\nWork with a group of energetic and multicultural professionals (up to 50 nationalities!)\u00a0\nHave great fun in Snack Friday, New Year Market, Fly with your Kids Day, Basketball Team\u2026\u00a0\nHave your voice heard through Townhalls, Crew forums, CEO live sessions etc.\n\nWhat you\u2019ll enjoy?\u202f\u202f\u202f\u00a0\n\nFly anywhere we fly for free plus taxes during leisure with your friends and family\nSpecial privileges to buy duty free products\n\nYou will be inspired by our core values.\u202f\u00a0\n\nYou will be inspired by our\u00a0vibrant,\u00a0efficient\u00a0and\u00a0entrepreneurial\u00a0spirit. Join our fun,\u00a0collaborative\u00a0and\u00a0reliable\u00a0team to ignite your dream!\u202f\u00a0\n\nInterested?\u00a0It\u2019s time to have YOUR MOVE!\u202f\u00a0\n\nIf you're ready to embark your adventure,\u00a0start by clicking the \u2018Apply now\u2019 and\u00a0get on the plane to fly with HK Express!\u202f\u00a0", "employment_types": ["Full Time", "Permanent"], "selling_points": [], "locations": ["Tsim Sha Tsui"], "categories": ["Engineering", "Electrical / Electronics", "Telecommunication / Wireless / Radio", "Information Technology (IT)", "Hardware"], "post_time": "2022-01-14T06:13:40Z", "salary": {"currency": null, "max": null, "min": null, "period": "monthly", "term": null}, "salary_visible": false, "title_keywords": ["specialist", "system engineer"], "responsibilities": ["support projects", "cost", "maintenance", "other duties", "regulatory requirements", "systems", "review", "design", "evaluation", "documentation", "ad-hoc projects"], "requirements": {"degrees": ["degree"], "majors": ["engineering"], "languages": [], "language_level": [], "hard_skills": ["plus", "aircraft", "maintenance", "fun", "airline", "safe", "airworthiness", "aircraft maintenance", "lcc", "airframe", "documentation"], "soft_skills": ["flexible", "efficient", "collaborative", "energetic", "reliable"], "languages_combined": []}, "experience_required": {"duration": ["3 years", "minimum 5 years"], "field": ["aircraft maintenance", "engineering", "design"]}}, {"job_id": "100003009047191", "location_code": "hk", "company": "Vanguard Business Services Limited", "job_title": "IT Support Engineer", "description": "DEAR TALENT, YOUR MOVE!\n\nBeing the new rising airline since 2013, we are the Hong Kong\u2019s only Low Cost Carrier (LCC) offering you safe and flexible service options to Hong Kong and beyond.\n\nWe\u2019re on a mission to inspire you to be different, to shake things up, to inspire the spirit of adventure by bringing you to fascinating destinations that few others serve.\n\nSpread your wings and fly with us!\n\nWe are looking for a vibrant and people-oriented HR practitioner to join our People Department. You will be a key member to assist in driving the Company\u2019s people strategy, creating a unique people experience for each individual, providing professional HR consultancy advice to line departments and engaging the most qualified candidates by building relationships and promoting the airline\u2019s employer brand.\u00a0\n\nWhat will you do?\u00a0\n\nBusiness Partner & People Processes\n\nAct as a Business Partner to designated business units and to provide professional HR solutions and consultancy to line managers on talent acquisition and retention, employee relations, performance management etc.\nProvide professional HR solutions to staff enquiries from all levels of employees\nPartner with other People Department CoE teams in driving and developing People Experience initiatives to cope with the Company expansion and development plan\nSupport full spectrum of people process operations throughout the UO employee journey including appointment, on & off-boarding, visa application, staff movement logistics, personnel file management, etc.\nAssist in development and implementation of polices and procedures\n\nTalent Acquisition\n\nHandle end-to-end recruitment cycle in a timely manner, which include but not limited to:\nIdentify recruitment need, prepare job description, source talent via appropriate channels, arrange rounds of interview and offer proposal\nEnhance the talent pool and promote the HKE brands among online and offline channels, to find the right fit for the LCC structure\nKeep abreast of the market information and share among the talent acquisition team\nEnhance the onboarding process for key talent and experienced hires\nBuild and maintain relationship with universities and schools to build the brand among the millennials\nManage the talent acquisition budgetary control\n\nPeople Projects\n\nParticipate in People Experience enhancement/transformation/digitalization projects and initiatives as assigned\nProvide support on various projects/tasks in the areas of talent acquisition and development, system enhancement that support the business strategy\n\nWe are a perfect match, if you are/have:\n\nDegree holder with at least 2 year of similar HR BP/TA work experience in Commercial sectors\nWell verse with HK Employment Ordinance and regulations\nProficiencies in office productivity tools (Excel, Word and PowerPoint etc.)\nWillingness to learn and shows an interest in latest HR trend and technologies\nGood command of English and Chinese\nGoal-oriented, self-starter with a high sense of responsibilities\nExcellent team player, can-do attitude with solid communication skills\nExcellent organizational skills with strong attention to details\nAbility to handle and prioritize multiple and varied tasks, while meeting all deadlines\nCan demonstrate customer service orientation and relationship/partnership building\nPositive attitude towards work\n\nYour Future Work Life?\n\nWork flexibly with staggered working hours and flexible workplace\nDress Casual and Smart everyday\nWork in a newly-designed office with open seating, stylish breakout areas, game room, gym and free coffee\u2026\nWork with a group of energetic and multicultural professionals (up to 50 nationalities!)\nHave great fun in Snack Friday, New Year Market, Fly with your Kids Day, Basketball Team\u2026\nHave your voice heard through Townhalls, Crew forums, CEO live sessions etc.\n\nWhat will you enjoy?\n\nFly anywhere we fly for free plus taxes during leisure with your friends and family\nSpecial privileges to buy duty free products\nCareer Express\n\nYou will be inspired by our core values.\nYou will be inspired by our vibrant, efficient and entrepreneurial spirit. Join our fun, collaborative and reliable team to ignite your dream!\n\nInterested? It\u2019s time to have YOUR MOVE!\nIf you're ready to embark your adventure, start by clicking the \u2018Apply now\u2019 and get on the plane to fly with HK Express!\u00a0", "employment_types": ["Full Time", "Contract"], "selling_points": ["Excellent chance to work in a dynamic environment", "One month Gratuity after 1 year service", "Experience working as IT Support"], "locations": ["Quarry Bay"], "categories": ["Information Technology (IT)", "Hardware", "Support"], "post_time": "2022-01-14T02:32:35Z", "salary": {"currency": null, "max": null, "min": null, "period": "monthly", "term": null}, "salary_visible": false, "title_keywords": ["it support engineer"], "responsibilities": ["regulations", "market information", "operations", "communication", "maintain", "customer service", "plan", "file management", "control", "teams", "developing", "implementation", "logistics", "cost", "management", "provide support", "procedures", "hr", "a timely manner", "recruitment"], "requirements": {"degrees": ["degree holder"], "majors": [], "languages": ["english", "chinese"], "language_level": ["good command"], "hard_skills": ["excel", "plus", "fun", "airline", "word", "powerpoint", "goal", "safe", "lcc"], "soft_skills": ["flexible", "communication skills", "organizational skills", "efficient", "can-do attitude", "timely", "collaborative", "unique", "prioritize", "positive attitude", "customer service", "reliable", "people-oriented", "attention to details", "team player", "energetic", "sense of responsibilities"], "languages_combined": [{"language": "english", "language_level": ["good command"]}, {"language": "chinese", "language_level": ["good command"]}]}, "experience_required": {"duration": ["at least 2 year"], "field": ["brand", "development", "hr", "developing", "commercial"]}}, {"job_id": "100003009037804", "location_code": "hk", "company": "Fwone Science & Technology Hong Kong Co., Limited", "job_title": "Helpdesk / Deskside Support Engineer(17K-22K)", "description": "DEAR TALENT, YOUR MOVE!\n\nBeing the new rising airline since 2013, we are the Hong Kong\u2019s only Low Cost Carrier (LCC) offering you safe and flexible service options to Hong Kong and beyond.\n\nWe\u2019re on a mission to inspire you to be different, to shake things up, to inspire the spirit of adventure by bringing you to fascinating destinations that few others serve.\n\nSpread your wings and fly with us!\n\n\nWhat will you do?\u00a0\n\nIT Strategic Direction and Standards\n\nLead strategies and visions to drive IT effectiveness within the Company;\nLead the team to provide technology consulting, architecture design, data integration and cybersecurity;\nLead the team to plan, direct and manage the exploitation of current installed technology and capability;\nWork with the business units to assign application and data ownership to improve the flow of data across the organization;\nDrive effective partnership with stakeholders to achieve the desired business outcomes;\nDefine technology roadmap with ongoing innovation and use of new technologies.\n\nIT Operations\n\nLead and manage a team of IT professionals covering 24x7 IT Support and Security Operation which provides a central point of contact and ensure agreed service level targets are met and appropriate qualitative standards are achieved;\nDeliver best in class and fit-for-purpose infrastructure technology solutions using both internal and external resources to design, build infrastructure platform and services and implement them to production on time, within budget and with good quality;\nAdopt necessary standard and best practices for Infrastructure management and ensure compliance of technical architecture and design.\n\nIT Security\n\nEnsure cybersecurity compliance of Company policies and regulatory requirements;\nManage the risks and impacts of cybersecurity exceptions and threats;\nPrepare the organization for cybersecurity incidents with proper and structured response plan;\nKeep abreast of the latest technological development in cybersecurity and maintain network of market intelligence with the industry.\n\nSolution Formulation and Delivery\n\nOversee the end-to-end solution delivery and subsequent support of solutions;\nUnderstand business requirements, identify and formulate cost effective solutions to address business problems;\nWork with other teams to ensure solutions are fit for purpose and leverage existing capabilities where possible;\nManage the delivery solutions/ projects on time and budget;\nEnsure solutions are delivered in accordance with our policies and standards.\n\nWe are a perfect match, if you are:\n\nBachelor's Degree in Computer Science, Information Management or related discipline;\nMinimum 10 years\u2019 relevant experience with at least 4 years in leadership role;\nProven experience in managing a team of technology professionals (that include in-house, external, off-shore resources) to implement large scale IT infrastructure, security and application projects;\nProven experience in managing 24x7 IT support and security operation;\nCreate and sustain a culture of collaboration, efficiency, reliability and entrepreneurial spirit within the team;\nCertified PM (PMP) is preferred;\nExperience in devising, costing and delivering solutions to meet internal business and customer needs;\nExperience in developing and implementing architecture within a fast-paced organization to meet complex programs with multiple stakeholders;\nStrong business acumen with excellent interpersonal and presentation skills;\nGood command in English and Chinese;\nGood interpersonal and communication skills and ability to build relationships with stakeholders.\n\nYour Future Work Life?\n\nWork flexibly with staggered working hours and flexible workplace\nDress Casual and Smart everyday\nWork in a newly-designed office with open seating, stylish breakout areas, game room, gym and free coffee\u2026\nWork with a group of energetic and multicultural professionals (up to 50 nationalities!)\nHave great fun in Snack Friday, New Year Market, Fly with your Kids Day, Basketball Team\u2026\nHave your voice heard through Townhalls, Crew forums, CEO live sessions etc.\n\nWhat will you enjoy?\n\nFly anywhere we fly for free plus taxes during leisure with your friends and family\nSpecial privileges to buy duty free products\nCareer Express\n\nYou will be inspired by our core values.\nYou will be inspired by our vibrant, efficient and entrepreneurial spirit. Join our fun, collaborative and reliable team to ignite your dream!\n\nInterested? It\u2019s time to have YOUR MOVE!\nIf you're ready to embark your adventure, start by clicking the \u2018Apply now\u2019 and get on the plane to fly with HK Express!\u00a0", "employment_types": ["Full Time"], "selling_points": ["5-day work, On Job Training", "At least 1 year experience in desktop support", "Immediate available preferred"], "locations": ["Kwun Tong"], "categories": ["Information Technology (IT)", "Hardware", "Support", "Technical / Functional Consulting"], "post_time": "2022-01-11T03:54:35Z", "salary": {"currency": "HKD", "max": 24999, "min": 17000, "period": "monthly", "term": null}, "salary_visible": true, "title_keywords": [], "responsibilities": ["consulting", "data", "operations", "regulatory requirements", "budget", "quality", "design", "communication", "plan", "managing a team", "it infrastructure", "infrastructure", "compliance", "teams", "developing", "architecture", "cost", "management", "security operation", "contact", "maintain network", "policies", "ensure compliance"], "requirements": {"degrees": ["degree", "bachelor"], "majors": ["computer science"], "languages": ["english", "chinese"], "language_level": ["good command"], "hard_skills": ["plus", "fun", "airline", "safe", "lcc", "integration", "pmp", "acumen"], "soft_skills": ["flexible", "communication skills", "efficient", "collaborative", "presentation skills", "energetic", "reliable", "business acumen", "structured", "leadership", "interpersonal"], "languages_combined": [{"language": "english", "language_level": ["good command"]}, {"language": "chinese", "language_level": ["good command"]}]}, "experience_required": {"duration": ["at least 4 years", "minimum 10 years"], "field": ["it support", "infrastructure", "developing", "it", "relevant experience", "security", "operation", "business", "managing a team"]}}, {"job_id": "100003009047103", "location_code": "hk", "company": "Fortune Technologies International Ltd", "job_title": "Senior IT Technical Engineer", "description": "Being the new rising airline since 2013, we are the Hong Kong\u2019s only Low Cost Carrier (LCC) offering you safe and flexible service options to Hong Kong and beyond.\u00a0\n\nWe\u2019re on a mission to inspire you to be different, to shake things up, to inspire the spirit of adventure by bringing you to fascinating destinations that few others serve.\u00a0\n\n\nSpread your wings and fly with us!\n\nWhat you\u2019ll do?\u00a0 (Job Duties)\u00a0\u00a0\n\n\nAs an officer in Revenue Management Operation, you will be joining the most dynamic, data analytic team, a team that have embraced data-driven decision making \u2013 Revenue Management Department which is the core of the airline business. You will have the opportunity to maximize the total revenue. Your role will be crucial to Hong Kong Express Airways\u2019 profitability.\n\nYou will interpret and analyze large, complex, multiple sets of data in various dimensions on your assigned routes or portfolio to uncover insights and turn into strategies and actions to maximise revenue.\n\nManage a portfolio of routes and carry out pricing and inventory actions to deliver revenue targets while aligning towards company\u2019s objective\nMonitor demand and analyse against booking curve, historic and future booking activity\nPeriodically review market pricing structure and trends, competitive landscape, and fees;\nPrepare in-depth data analysis (customer profile, booking behavior, ancillary take-up, channel performance, etc.) and provide recommendations to improve revenue optimization\nMaintain regular and promotional fares in the reservation system;\nIdentify holiday, festive, events and ensure pricing and inventory are optimized throughout\nLiaise with the Marketing, Sales and e-Commerce teams to optimize commercial initiatives\nAd-hoc reports and other duties as required\n\nWe are a perfect match, if you are/have:\u00a0\u00a0\n\nFresh graduate or 1 year of working experience\nBachelor\u2019s degree, with a strong interest in quantitative problem solving (Mathematics, Operations Research, Computer Science, Data Science, Statistics, or similar);\nData analysis experience is essential (academic, research, projects);\nSome familiarity with SQL and forecasting and optimization techniques is strongly preferred.\nStrong analytical skill and solid knowledge in analytics, insights and planning\nAbility to work with stakeholders at all levels and across all functions\nAbility to manage and deliver complex implementation projects\nAlways thrive to improve and enhance technical skill\n\nYour Future Work Life?\u00a0\u00a0\n\nWork flexibly with staggered working hours and flexible workplace\nDress Casual and Smart everyday\nWork in a newly-designed office with open seating, stylish breakout areas, game room, gym and free coffee\u2026\u00a0\nWork with a group of energetic and multicultural professionals (up to 50 nationalities!)\u00a0\nHave great fun in Snack Friday, New Year Market, Fly with your Kids Day, Basketball Team\u2026\u00a0\nHave your voice heard through Townhalls, Crew forums, CEO live sessions etc.\u00a0\n\nWhat you\u2019ll enjoy?\u00a0\u00a0\u00a0\n\nFly anywhere we fly for free plus taxes during leisure with your friends and family\u00a0\u00a0\nSpecial privileges to buy duty free products\u00a0\u00a0\n\nYou will be inspired by our core values.\u00a0\n\nYou will be inspired by our\u00a0vibrant,\u00a0efficient\u00a0and\u00a0entrepreneurial\u00a0spirit. Join our fun,\u00a0collaborative\u00a0and\u00a0reliable\u00a0team to ignite your dream!\u00a0\n\nInterested?\u00a0It\u2019s time to have YOUR MOVE!\u00a0\n\nIf you're ready to embark your adventure, start by clicking the \u2018Apply now\u2019 and get on the plane to fly with HK Express!\u00a0", "employment_types": ["Full Time", "Permanent"], "selling_points": [], "locations": ["Wan Chai Area"], "categories": ["Information Technology (IT)", "Hardware", "Security", "Network & System"], "post_time": "2022-01-14T02:19:49Z", "salary": {"currency": null, "max": null, "min": null, "period": "monthly", "term": null}, "salary_visible": false, "title_keywords": ["technical engineer"], "responsibilities": ["ad-hoc", "data", "operations", "inventory", "maintain", "liaise with", "other duties", "monitor", "teams", "implementation", "reports", "analyse", "forecasting", "cost", "management", "review", "data analysis", "provide recommendations", "booking", "planning"], "requirements": {"degrees": ["degree", "bachelor", "fresh graduate"], "majors": ["mathematics", "statistics", "data science", "computer science"], "languages": [], "language_level": [], "hard_skills": ["analytical skill", "plus", "fun", "e-commerce", "analysis", "airline", "problem solving", "sql", "safe", "dynamic", "lcc"], "soft_skills": ["flexible", "efficient", "analytical skill", "collaborative", "problem solving", "energetic", "dynamic", "reliable", "technical skill", "driven", "decision making"], "languages_combined": []}, "experience_required": {"duration": ["1 year"], "field": ["data analysis", "research"]}}, {"job_id": "100003009047094", "location_code": "hk", "company": "ALS International Limited", "job_title": "Storage/Backup Associate (Team Lead)", "description": "About our client\n\nOur client is one of Asia's largest online platforms and has a very large scale IT team. This role will specialize in backup/storage solutions for production environment and will utilise scripting to automate process. Experienced candidate with team managing capability will be considered a team leader role.\u00a0\n\n\n\nKey responsibilities\n\nOversee the technical support such as setup, maintenance and troubleshooting for the overall production and non-production storage environment\nMonitor and\u00a0optimize\u00a0the usage and performance of storage infrastructure\nEnsure storage infrastructure is setup for all environments in timely manner\n\n\nJob requirements\n\nDegree holder in Computer Science, Information Technology or relevant discipline\n5 years' experience handling the building and configuration of Enterprise grade SAN storage\nTechnically proficient with EMC and HPE\nHands-on with automation scripting on system administration\nFluent in communication, both written and spoken, in English\n\n\n\nInterested candidates should send their resume in Word file, please click \"APPLY NOW\" below to contact Kelvin Lau\u00a0for further information.", "employment_types": ["Full Time"], "selling_points": [], "locations": ["Central"], "categories": ["Information Technology (IT)", "Hardware", "Support", "Network & System"], "post_time": "2022-01-14T02:18:50Z", "salary": {"currency": null, "max": null, "min": null, "period": "monthly", "term": null}, "salary_visible": false, "title_keywords": ["associate", "lead"], "responsibilities": ["maintenance", "technical support", "infrastructure", "monitor", "troubleshooting", "setup"], "requirements": {"degrees": ["degree holder"], "majors": ["computer science", "information technology"], "languages": ["english"], "language_level": ["fluent"], "hard_skills": [], "soft_skills": ["communication", "hands-on"], "languages_combined": [{"language": "english", "language_level": ["fluent"]}]}, "experience_required": {"duration": ["5 years"], "field": []}}, {"job_id": "100003009040147", "location_code": "hk", "company": "Hong Kong Baptist Hospital", "job_title": "Senior Analyst Programmer \u2013 Business Support (Contract)", "description": "Key Duties and Responsibilities:\nMaintain, monitor and improve the daily operation of the Hospital mission critical application services\n1st tier support for users enquires on application services\nTroubleshoot and resolve application and system issues that arise across the daily hospital operation\nParticipate in new services transition, change and release management and service daily operation\nPrepare and conduct operational acceptance testing prior to production release\nDevelop documentation and regular reports for departments within Hospital\nNon office hours support as necessary\nRequirements:\nDegree in Computer Science or equivalent\nMinimum 5 years of solid experiences in system design and development in either one of the following areas:\nASP.NET, Visual C#, MS SQL Server\nJSP, Spring, Spring MVC Framework, ExtJS, Oracle (PL/SQL) and MySQL\nReact Native, Redux\nOracle EBS support, Oracle ERP system / Supply Chain Management\nProficient in XML/JSON web services, RESTful API\nProficient in front-end JavaScript, JQuery and CSS\nExperience in database performance tuning and stored procedure development\nExperience in SharePoint and reporting tool (eg. SSRS, Crystal Report or Jasper) would be an advantage\nExperience in IoT technologies and cloud services would be an advantage\nExperiences in Hospital Information System or healthcare related system is a plus\nGood team player, self-motivated and fast learner\nGood interpersonal and communication skills\nCandidate with less experience will be considered as Analyst Programmer\nWe offer attractive remuneration package and fringe benefits to the right candidates. Interested parties please apply with full resume and expected salary to Human Resources Department, Hong Kong Baptist Hospital, 18/F, Tower 2, Enterprise Square, 9 Sheung Yuet Road, Kowloon Bay, Kowloon, by email via \"Apply now\" or by fax to 2339 5769 on or before 26 January 2022.\nThe information provided will only be used for recruitment related purposes. All personal information on unsuccessful candidates will be destroyed within 6 months.", "employment_types": ["Full Time", "Contract"], "selling_points": [], "locations": ["Kowloon Bay"], "categories": ["Information Technology (IT)", "Hardware", "Support", "Software Development"], "post_time": "2022-01-12T01:41:03Z", "salary": {"currency": null, "max": null, "min": null, "period": "monthly", "term": null}, "salary_visible": false, "title_keywords": ["senior analyst programmer"], "responsibilities": ["management", "daily operation", "monitor", "testing", "develop", "maintain", "reports", "troubleshoot", "documentation"], "requirements": {"degrees": ["degree"], "majors": ["computer science"], "languages": [], "language_level": [], "hard_skills": ["restful api", "plus", "ms sql server", "jquery", "c#", "web services", "oracle erp", "information system", "sql", "system design", "react native", "javascript", "spring", "css", "pl", "oracle"], "soft_skills": ["communication skills", "good team player", "self-motivated", "fast learner", "interpersonal"], "languages_combined": []}, "experience_required": {"duration": ["minimum 5 years"], "field": ["healthcare", "related", "development", "system design", "database"]}}, {"job_id": "100003009029280", "location_code": "hk", "company": "Wofoo Plastics Limited", "job_title": "IT Technician", "description": "Responsible for IT support including Server, Networking, Hardware and application\nProvide system and application support for end-users\nUsers\u2019 training and prepare documentation\nOn-site support to associated organizations\nPerform other ad hoc projects assigned by Supervisor\nRequirements:\n\nDiploma holder of Computer Studies, Computer Science or equivalent\nExperience in administrating Microsoft Windows, Sever, Firewall and Networking\nFamiliar with hardware and software installation. Knowledge of Linux and web development is an advantage\nWilling to travel within Hong Kong and PRC (occasionally) to provide technical support of associated companies/organizations\nGood interpersonal and communication skills\nStrong sense of responsibilities, problem solving skills and be proactive\nGood command of English and Chinese\nFresh graduate will also be considered\nInterested parties may apply with resume, stating source of recruitment information, expected salary (application without expected salary will not be considered) and availability to\n\nHuman Resources Department\n25/F Wofoo Commercial Building\n574-576 Nathan Road\nMongkok, Kowloon, Hong Kong\n\nor by clicking \"Apply Now\"\n\nOur website: www.wofoo.com\n\nPersonal data collected will be kept in strict confidence and used for employment-related purpose only.", "employment_types": ["Full Time", "Permanent"], "selling_points": [], "locations": ["Mong Kok"], "categories": ["Information Technology (IT)", "Hardware", "Support", "Network & System"], "post_time": "2022-01-07T04:30:25Z", "salary": {"currency": null, "max": null, "min": null, "period": "monthly", "term": null}, "salary_visible": false, "title_keywords": ["it technician"], "responsibilities": ["installation", "software", "technical support", "communication", "hardware", "ad hoc projects", "documentation"], "requirements": {"degrees": ["diploma holder", "fresh graduate"], "majors": ["computer science", "computer studies"], "languages": ["english", "chinese"], "language_level": ["good command"], "hard_skills": ["linux", "web development", "documentation", "hardware", "firewall", "server", "problem solving skills"], "soft_skills": ["communication skills", "responsible", "problem solving skills", "proactive", "interpersonal", "sense of responsibilities"], "languages_combined": [{"language": "english", "language_level": ["good command"]}, {"language": "chinese", "language_level": ["good command"]}]}, "experience_required": {"duration": [], "field": ["administrating"]}}, {"job_id": "100003009039260", "location_code": "hk", "company": "Advanced Biomedical Instrumentation Centre Limited", "job_title": "IT Officer/Assistant (Ref.: H01/2022/01)", "description": "Applications are invited for appointment as IT Officer/Assistant in the Advanced Biomedical Instrumentation Centre (Ref.: H01/2022/01), on a two-year fixed-term basis, with with contract-end gratuity and centre contribution to a retirement benefits scheme, totalling up to 10% of basic salary and\u00a0the possibility of renewal subject to mutual agreement.\n\nIT Officer/Assistant (Ref.: H01/2022/01)\n\n\nApplicants should possess a Bachelor\u2019s degree or above in Computer Science, Information Technology or related disciplines, with at least 3 years' of relevant work experience. They should have an excellent command of written and spoken English and Chinese; have good communication, interpersonal, customer service and problem-solving skills; be self-motivated and highly organized; possess the ability to handle multi-tasks and work independently and as a team player. Research/project management experience and knowledge of the following areas would be advantageous:\nPC (including Virtual PC, Windows and Mac) configuration, management and support\nIT system and network administration\nServer management\nCloud computing\nAV equipment support and maintenance\nVideo conference equipment and software management and support (preferably with experience in Microsoft Teams and Zoom, and knowledge of different end-point devices)\nThe appointee will manage and maintain the Information Technology and computer systems for the Centre. He/She will provide user support with IT solutions; prepare and maintain system documentations and reports; liaise with internal and external stakeholders; troubleshoot computer hardware and software problems from users; review tender specifications; assist in managing research data; schedule backup and design data recovery solutions; and perform other duties as assigned. The appointee may be required to work outside normal office hours and on weekends.\n\nApplicants with less experience may be appointed as IT Assistant/Senior IT Assistant.\u00a0\n\n\nA highly competitive salary commensurate with qualifications and experience will be offered, in addition to annual leave and medical benefits.\u00a0\nApplicants should submit their up-to-date C.V., quoting the job reference number, with information of current/expected remuneration and availability. Review of applications will commence as soon as possible and continue until 5 February, 2022, or until the posts are filled, whichever is earlier.\nThe information provided will be kept confidential and only be used for those purposes relating to your application. We are an equal opportunities employer and welcomes applications from all qualified candidates.", "employment_types": ["Full Time", "Contract"], "selling_points": [], "locations": ["Shatin Area"], "categories": ["Information Technology (IT)", "Hardware", "Support", "Network & System"], "post_time": "2022-01-11T09:12:43Z", "salary": {"currency": null, "max": null, "min": null, "period": "monthly", "term": null}, "salary_visible": false, "title_keywords": ["it officer", "assistant"], "responsibilities": ["network administration", "software", "data", "design", "communication", "customer service", "maintain", "troubleshoot", "liaise with", "perform other duties", "configuration", "teams", "reports", "schedule", "tender", "management", "equipment support", "video conference equipment", "review", "specifications", "maintenance", "computer systems", "project management", "hardware"], "requirements": {"degrees": ["degree or above", "bachelor"], "majors": ["related disciplines", "computer science", "information technology"], "languages": ["english", "chinese"], "language_level": ["excellent"], "hard_skills": ["network administration", "basic", "maintenance", "problem-solving skills", "scheme", "computer systems", "project management", "hardware", "server", "pc", "documentations"], "soft_skills": ["organized", "self-motivated", "work independently", "advanced", "multi-tasks", "communication", "project management", "customer service", "troubleshoot", "problem-solving skills", "team player", "interpersonal"], "languages_combined": [{"language": "english", "language_level": ["excellent"]}, {"language": "chinese", "language_level": ["excellent"]}]}, "experience_required": {"duration": ["at least 3 years"], "field": ["management", "research", "video", "related", "information technology", "project management", "it"]}}, {"job_id": "100003009036558", "location_code": "hk", "company": "Yew Chung College of Early Childhood Education Limited", "job_title": "IT Technician", "description": "Position Summary\n\nThe main tasks for the appointee are:\n\nOperate and maintain computers, servers and network equipment\nInstall and manage software/OS for computers and servers\nEnhance various web-based applications and materials\nProvide professional support in automation of administrative operations\nEnsure meeting the high standard of data management and security\nProvide professional IT support for staff (administrative and teaching) and students\nManage daily IT, audio and video equipment maintenance\nAssist the department head in procurement and inventory control of IT equipment and software\n\nRequirements\n\nApplicants should meet the following requirements:\n\nHigher Diploma with at least 5 years of experience or;\nBachelor\u2019s degree holder with 1 year of experience\nGood knowledge in MS Window, MacOS, MS Office Suite and Zoom\nSolid experience in Office 365 is an advantage\nExperience in e-learning technologies such as Moodle, Blackboard and Panopto\nHands-on skills in graphic design, multimedia design, knowledge of video production is an advantage\nBe able to communicate in English and Chinese (Cantonese or Mandarin)\n\nSalary and Fringe Benefits:\n\nInitial appointment will normally be made on a renewable 24-month contract.\n\nRemuneration is competitive and will be based on qualifications and relevant experience. The College offers group medical insurance, staff development support, annual leave and sick leave, and Mandatory Provident Fund to eligible appointee(s).\n\nApplication Procedure:\n\nApplicants are invited to:\n\nSubmit an application letter with a full Curriculum Vitae, and copies of all graduate transcripts, and the names and contact details of three references.\nSpecify in the application letter current/latest salary and expected salary\nSend applications to the Yew Chung College of Early Childhood Education by \"Apply Now\".\nThe College will review applications immediately and applications will be accepted until the posts are filled.\u00a0 Only shortlisted candidates will be contacted.\n\nImportant notes to Applicants:\n\nAppointees will have to undergo a medical examination.\u00a0 Reimbursement of costs subject to a ceiling is applicable.\nLocal applicants will have to undergo a Sexual Conviction Record Check / Overseas applicants will have to present a police report before appointment can be confirmed.\u00a0\n\nThe College also reserves the right to make an appointment by invitation.\n\nPersonal data collected will be used for recruitment-related purposes only.", "employment_types": ["Full Time", "Contract"], "selling_points": ["Stable working environment", "IT support", "Working opportunity in Southern District"], "locations": ["Aberdeen"], "categories": ["Information Technology (IT)", "Hardware", "Support", "Network & System"], "post_time": "2022-01-10T11:00:08Z", "salary": {"currency": null, "max": null, "min": null, "period": "monthly", "term": null}, "salary_visible": false, "title_keywords": ["it technician"], "responsibilities": ["multimedia design", "management", "software", "maintenance", "data", "video production", "operations", "graphic design", "maintain", "inventory control", "it equipment", "audio"], "requirements": {"degrees": ["diploma", "bachelor", "degree holder"], "majors": [], "languages": ["cantonese", "english", "chinese", "mandarin"], "language_level": [], "hard_skills": ["office 365", "data management", "servers", "maintenance", "web-based applications", "os", "multimedia", "ms office"], "soft_skills": ["hands-on", "learning"], "languages_combined": [{"language": "cantonese", "language_level": []}, {"language": "english", "language_level": []}, {"language": "chinese", "language_level": []}, {"language": "mandarin", "language_level": []}]}, "experience_required": {"duration": ["at least 5 years", "1 year"], "field": []}}, {"job_id": "100003009034645", "location_code": "hk", "company": "ServiceOne Limited", "job_title": "System Engineer", "description": "Responsibilities:\n\nProvide hardware and software maintenance or solve IT related problem\nResponsible for setup, maintain and troubleshoot on Server / Storage / Network\nProvide IT support service to customer\nAssist in ad-hoc tasks and projects\n\nRequirements:\n\nHigher Diploma or above in IT or related disciplines\nMinimum 3 years relevant experience in IT field\nSolid Experience of HPE Server, Storage\nGood knowledge of networking, Firewall, router and switch, Wi-Fi networks, Azure Active Directory, Exchange Server, O365, Cloud infrastructure, VMware, Hyper-V\nGood communication with strong analytical skill\u00a0\nGood team player and willing to work under pressure\nGood command of both spoken and written English and Chinese\nLess experience will be considered as Senior Engineer\n\n\n\nFor Interested parties, please send your resume with date of availability and expected salary by email for application.\n\nPersonal data collected will be used for recruitment-related purposes only.", "employment_types": ["Full Time", "Permanent"], "selling_points": ["IT, hardware and software maintenance", "Troubleshooting on Server, Storage and Network", "Good communication skills"], "locations": ["Chai Wan"], "categories": ["Information Technology (IT)", "Hardware", "Support", "Network & System"], "post_time": "2022-01-10T03:52:00Z", "salary": {"currency": null, "max": null, "min": null, "period": "monthly", "term": null}, "salary_visible": false, "title_keywords": ["system engineer"], "responsibilities": ["ad-hoc tasks", "maintain", "troubleshoot", "hardware and software maintenance", "setup"], "requirements": {"degrees": ["higher diploma or above"], "majors": ["related disciplines", "it"], "languages": ["english", "chinese"], "language_level": ["good command"], "hard_skills": ["o365", "hyper-v", "analytical skill", "azure", "vmware", "active directory", "wi-fi", "switch", "router", "firewall", "server", "exchange"], "soft_skills": ["good team player", "analytical skill", "communication", "active", "work under pressure"], "languages_combined": [{"language": "english", "language_level": ["good command"]}, {"language": "chinese", "language_level": ["good command"]}]}, "experience_required": {"duration": ["minimum 3 years"], "field": ["senior engineer", "it", "relevant experience"]}}, {"job_id": "100003009034842", "location_code": "hk", "company": "BGC Group (HK) Limited", "job_title": "System Engineer / Helpdesk Support / IT Support / Linux Support", "description": "Our client is a well-known multi-national investment corporation that provides professional asset management and financial services, dedicated to optimize the business of world\u2019s leading companies. We are looking for outstanding talents who are determined in developing their career in the Financial and Insurance Industry to join our project for a global renowned company.\n\nPLEASANT\u00a0company culture with\u00a0RENOWNED\u00a0company background\nFAST-GROWING\u00a0enterprise and\u00a0RAPID\u00a0career advancement\nGUARANTEED\u00a0career prospects with\u00a0EXCELLENT\u00a0remuneration package\n\nResponsibilities:\n\nProvide day-to-day technical support including network connectivity, system maintenance\nPrioritize and schedule problems. Execute problem diagnostic by using advance troubleshooting skills\nContribute IT infrastructure support - Perform installation, configuration, and upgrade of hardware & computer applications\nAnalyze, trouble shoot and provide solution for OS system and network problems;\nPerform post-resolution follow-ups to help users\n\nRequirements:\n\nHigh Diploma in Information and Network Security or related discipline\nHands-on experience in all-rounded technical skills on desktop support\nExperience in Windows and Windows Server administration and software and back-end administration\nExperience in Linux system is a big plus\nGood verbal and written communications skills in English, Cantonese and Mandarin\nProactive, energetic, and positive attitude\n\n**Candidate with less experience or Fresh Graduates will also be considered**\n\nInterested parties can click 'APPLY NOW' or send email with updated CV to\u00a0\u00a0Eden @bgc-group.com.\n\n* Personal data collected will be used for recruitment purposes only.", "employment_types": ["Full Time", "Permanent", "Contract"], "selling_points": ["On-the-job training to reach your potential", "Great work environment and work-life balance", "New trends and cutting-edge technologies to work"], "locations": ["Admiralty"], "categories": ["Information Technology (IT)", "Hardware", "Support", "Network & System"], "post_time": "2022-01-10T04:24:46Z", "salary": {"currency": null, "max": null, "min": null, "period": "monthly", "term": null}, "salary_visible": false, "title_keywords": ["system engineer", "it support"], "responsibilities": ["installation", "it infrastructure", "maintenance", "technical support", "configuration", "troubleshooting", "resolution", "hardware", "schedule", "computer applications"], "requirements": {"degrees": ["high diploma"], "majors": [], "languages": ["cantonese", "english", "mandarin"], "language_level": ["good"], "hard_skills": ["linux", "plus", "windows server"], "soft_skills": ["positive attitude", "hands-on", "energetic", "technical skills", "proactive"], "languages_combined": [{"language": "cantonese", "language_level": ["good"]}, {"language": "english", "language_level": ["good"]}, {"language": "mandarin", "language_level": ["good"]}]}, "experience_required": {"duration": [], "field": ["administration", "server administration"]}}, {"job_id": "100003009043094", "location_code": "hk", "company": "B.S.C. Group Limited", "job_title": "System Engineer", "description": "Responsibilities:\n\nManage helpdesk-reported technical problems, prioritize, track and provide timely workable solutions for end-users\nServe as an end-user advocate, championing O365 technologies to help users on all levels to maximize the value of O365 portal applications including Outlook, OWA, Sharepoint, Forms and Power Automate, Power Apps\nTest new O365 tenant features and functionality, preparing end-user guides and participating in feature production deployments\nMonitor collaborative systems health, escalating issues to team head and work with them to provide solutions for identified issues\nFormulate documentation for administrative knowledge base articles and end-user guides\nParticipate in new application development, testing, customer training, and other support-related activities\nSupport to resolve technical setup/ connection problems across different office locations within the Company (occasional travel is required)\nRequirements:\n\nDegree Holder in Information System, Information Technology, Computer Science or related disciplines\n1-2 years of working experience in IT related field with good programme knowledge\nHands-on basic troubleshoot experience on networking and computer applications\nThe ideal candidate is preferred to have knowledge of existing and emerging Microsoft Office 365 technologies including:Good understanding on the use of computer systems, mobile devices and other technical productsAbility to analyse, diagnose and resolve technical issues\nSharepoint Online and OneDrive Administration\nExchange Online and Hybrid Connectivity\nPower Automate and Microsoft Forms\nPower apps\nOffice 365 Suite\nMicrosoft Teams\nGood understanding on the use of computer systems, mobile devices and other technical products\nAbility to analyse, diagnose and resolve technical issues\nExcellent communication and interpersonal skills\nGood command of both spoken and written English and Chinese\nWe offer attractive remuneration package and comprehensive fringe benefits including\u00a05-day work week,\u00a014-day of annual leave, subsidized medical insurance and\u00a0discretionary bonus\u00a0to the right candidate.\n\nInterested parties please apply with full resume, expected salary and quoting the Job Ref. No. on the subject line to\u00a0Human Resources Department, 19th Floor, Sino Favour Centre, 1 On Yip Street, Chaiwan, Hong Kong, or by clicking 'Apply Now' below.\u00a0For more information about us, please visit our websites at\u00a0http://www.bschk.com\u00a0and http://www.colourliving.com.\n\nPersonal data collected will be used for recruitment purpose only.", "employment_types": ["Full Time", "Permanent"], "selling_points": ["Manage helpdesk reported technical problems", "Degree Holder with 2 yrs of experience in IT field", "5-day work week & 14 days of annual leave"], "locations": ["Chai Wan"], "categories": ["Information Technology (IT)", "Hardware", "Support", "Network & System"], "post_time": "2022-01-12T09:47:53Z", "salary": {"currency": null, "max": null, "min": null, "period": "monthly", "term": null}, "salary_visible": false, "title_keywords": ["system engineer"], "responsibilities": ["systems", "monitor", "provide solutions", "testing", "documentation", "application development", "setup"], "requirements": {"degrees": ["degree holder"], "majors": ["related disciplines", "computer science", "information technology"], "languages": ["english", "chinese"], "language_level": ["good command"], "hard_skills": ["office 365", "basic", "microsoft office", "computer systems", "information system", "mobile", "exchange"], "soft_skills": ["ability to analyse", "hands-on", "communication and interpersonal skills", "comprehensive", "troubleshoot", "ideal"], "languages_combined": [{"language": "english", "language_level": ["good command"]}, {"language": "chinese", "language_level": ["good command"]}]}, "experience_required": {"duration": ["1-2 years"], "field": ["related", "it"]}}, {"job_id": "100003009043765", "location_code": "hk", "company": "", "job_title": "Assistant IT Manager", "description": "Responsibilities:\n\nRecord and report weekly all IT support activities for review and statistics each Friday for previous week\nMaintain IT standards for equipment, software, conventions, settings, etc. to maintain consistency in the company.\nEnsure formal approvals are obtained for any IT requests, access or IT purchases by completing the appropriate forms (Network Users Application, IT Request).\nRegular communications with Manager and IT team for progress and issues.\nIdentify, evaluate, recommend and obtain approval for any new systems before implementation.\nProactively monitor all IT hardware, networks, system jobs, etc. to ensure smooth operations.\nRequirements:\n\nDiploma or above in Computer Science or equivalent discipline\nMinimum 3 years of relevant hands-on experience in.\nAccustomed to responding to user needs and business priorities to provide appropriate response and approach to the resolution of information systems and technology requirements of the user/customer.\nFamiliar with deploying and managing servers and network products is preferred\nSound project management and IT service management skills. Experience in outsourcing and vendor management\nIndependent, self-motivated and innovative with good problem solving skills. Team-player.\n\nWe offer career development opportunity and competitive package to right talent. Interested parties, please send your email with\u00a0salary expectation\u00a0and\u00a0availability or contact 6115 2091 for further information.\n\n(Information provided will be treated in strict confidence and only be used for recruitment purpose)", "employment_types": ["Full Time", "Permanent"], "selling_points": ["Network Users Application", "IP Phone systems", "manage and negotiate with vendors"], "locations": ["Central & Western Area"], "categories": ["Information Technology (IT)", "Hardware", "Network & System", "Technical / Functional Consulting"], "post_time": "2022-01-13T01:59:47Z", "salary": {"currency": null, "max": null, "min": null, "period": "monthly", "term": null}, "salary_visible": false, "title_keywords": ["it manager", "assistant"], "responsibilities": ["communications with", "software", "review", "systems", "implementation", "monitor", "evaluate", "hardware", "maintain", "ensure smooth operations", "report"], "requirements": {"degrees": ["diploma or above"], "majors": ["computer science"], "languages": [], "language_level": [], "hard_skills": ["project management", "problem solving skills", "servers", "vendor"], "soft_skills": ["self-motivated", "independent", "team-player", "project management", "hands-on", "problem solving skills", "innovative"], "languages_combined": []}, "experience_required": {"duration": ["minimum 3 years"], "field": ["management"]}}, {"job_id": "100003009037644", "location_code": "hk", "company": "Joint Electronic Teller Services Limited (\u201cJETCO\u201d)", "job_title": "Senior System Officer", "description": "Responsibilities:\n\n\nProvide helpdesk support on Windows server and desktop\nProvide troubleshooting and problem solving on server and desktop issues\nProvide advice to improve service delivery and daily operations and manage end user complaints\nPrepare daily/weekly/monthly operation reports\nPerform server and desktop patch update\n\nQualifications:\n\nUniversity degree or above in Information System / Computer Studies or related disciplines is preferred\n5 year or above working experience in related field is preferred.\nExperience in supporting windows platform and products such as Active Directory, Exchange server and Microsoft Office (e.g. excel/word/outlook)\nExperience in Windows AD group policy, sever/workstation hardening and Networking and Veeam backup administration\nGood end user management skills and ability to listen, analyze and find solutions\nGood communication and interpersonal skills\nGood command of written and spoken English and Chinese\n\nWe offer competitive remuneration package and career prospects to the right candidate.\u00a0Salary will be commensurate with qualifications and experience.\u00a0Our attractive remuneration package includes 5-day work week, year-end bonus, performance bonus, dental and medical benefits, employer voluntary contributions to MPF, education allowance, staff well-being sponsorship, birthday leave, marriage leave, family care leave, etc.\n\nInterested candidates please send your full resume stating contact details, current and expected salary by clicking \u201cApply Now\u201d.\n\nPersonal data collected will be used for recruitment purpose only. We are an equal opportunity employer.", "employment_types": ["Full Time", "Permanent"], "selling_points": ["Helpdesk support on Windows server and desktop", "5-day work, double pay, performance bonus", "Employer Voluntary Contribution to MPF"], "locations": ["Wan Chai"], "categories": ["Information Technology (IT)", "Hardware", "Support", "Network & System"], "post_time": "2022-01-11T03:22:44Z", "salary": {"currency": null, "max": null, "min": null, "period": "monthly", "term": null}, "salary_visible": false, "title_keywords": ["officer"], "responsibilities": ["service delivery", "management", "active directory", "troubleshooting", "communication", "daily operations", "provide advice", "reports", "administration"], "requirements": {"degrees": ["degree or above"], "majors": ["related disciplines", "computer studies"], "languages": ["english", "chinese"], "language_level": ["good command"], "hard_skills": ["excel", "active directory", "microsoft office", "information system", "word", "problem solving", "outlook", "server", "windows server", "exchange"], "soft_skills": ["problem solving", "active", "troubleshooting", "communication and interpersonal skills"], "languages_combined": [{"language": "english", "language_level": ["good command"]}, {"language": "chinese", "language_level": ["good command"]}]}, "experience_required": {"duration": ["5 year"], "field": ["related", "administration"]}}, {"job_id": "100003009043914", "location_code": "hk", "company": "Be Myjob Company Limited", "job_title": "Network and Voice Engineer (iBank / Securities Firm)", "description": "Responsibilities:\nManaging day to day operations for telephony systems, voice recording preservations\nProvides systems support and problem resolution for Voice Services, and Voice Recording. This includes voice recorder and telephone system management, daily health checks, patching and troubleshooting\nProvide end-user support on voice services/desktop\nCollaborates with the business, along with the technical and operational groups across the firm to ensure alignment of technical solutions to the business strategy, use and deployment of best practices in business support solutions, and the alignment and application of firm operational and security standards.\nResponsible for router, firewall and IP networking equipment installation, administration and maintenance\nVendor and Project management\nManage IT asset and server hardware inventory\nHardware/software setup, maintenance and trouble-shooting\nFollow up ad-hoc task\n\nRequirements:\n\nDegree holder in Computer Science, Information Engineering or related discipline(s)\nMinimum 3 years of experience in switching, routing, and firewall technologies and network security principles. Cisco(R&S), Huawei, wireless, Firewalls (cisco/Palo Alto/Fortinet)\nHands-on experience in managing enterprise voice systems (e.g. Cisco CUCM, Avaya, Siemens\u2026other), Voice Recording platforms (e.g. NICE, Red Box)\nHands-on experience in supporting front office Trade Floor voice systems, working with traders, infrastructure (e.g. IPC, BT, etc.)\nProven strong record of meeting strategic technology targets and deliverables operational demands while under stressful time constraints and demands\nKnowledge in Windows, LINUX and UNIX platform administration would be an advantage Holder of CCNP is definitely an advantage\nOccasionally work in a non-office hours as project needs\nGood command of written and spoken English and Chinese (including Putonghua)", "employment_types": ["Full Time", "Permanent"], "selling_points": ["Listed financial institution", "Network and Voice systems and configuration", "Routers & switches, firewalls"], "locations": ["Central"], "categories": ["Information Technology (IT)", "Hardware", "Application Specialist - Network", "Network & System"], "post_time": "2022-01-13T02:26:37Z", "salary": {"currency": null, "max": null, "min": null, "period": "monthly", "term": null}, "salary_visible": false, "title_keywords": ["engineer"], "responsibilities": ["ad-hoc", "installation", "management", "day to day operations", "maintenance", "server hardware", "software", "inventory", "telephone system", "systems", "troubleshooting", "resolution", "project management", "hardware", "setup", "administration"], "requirements": {"degrees": ["degree holder"], "majors": ["engineering", "computer science"], "languages": ["putonghua", "english", "chinese"], "language_level": ["good command"], "hard_skills": ["linux", "nice", "ccnp", "firewall", "red"], "soft_skills": ["hands-on"], "languages_combined": [{"language": "putonghua", "language_level": ["good command"]}, {"language": "english", "language_level": ["good command"]}, {"language": "chinese", "language_level": ["good command"]}]}, "experience_required": {"duration": ["minimum 3 years"], "field": ["infrastructure", "security"]}}, {"job_id": "100003009036367", "location_code": "hk", "company": "Walters People (HK)", "job_title": "Service Desk Analyst (30k/month) - Asset Management", "description": "Our FS client is looking for a Service Desk Analyst specialized in hardware and mobility support for all IT Customers.\nIn this role, you will be ensuring all IT tickets assigned processed as per the IT Ticket Quality Assurance standards and provide deep technical assistant via remote support tools.\n\nPrimary responsibilities:\n\n2+ years of general experience in one or more of an IT functions\nGeneral understanding in one of the commonly used IT technologies including PC support\nExcellent problem-solving skills\nExplains information to others in straightforward situations\nApplies knowledge of how the team integrates with other teams to achieve objectives\nO365 Access & Authentication methods & procedures\n\nAdditional responsibilities:\n\nMay serve as developing knowledge leader for the team; and provides partnership to team members\nHas limited impact on own work team; works within standardised procedures and practices to achieve objectives and meet deadlines\nImpacts own team and closely related teams through the quality, timeliness and effectiveness of work product\nSolves routine problems using existing procedures and standard practices\nEvaluates and selects solutions from established options", "employment_types": ["Full Time", "Permanent"], "selling_points": ["ServiceNow", "Ticket Support", "Desktop Support"], "locations": ["Not Specified"], "categories": ["Information Technology (IT)", "Hardware", "Support", "Network & System"], "post_time": "2022-01-10T10:10:19Z", "salary": {"currency": "HKD", "max": 29999, "min": 20000, "period": "monthly", "term": null}, "salary_visible": true, "title_keywords": ["analyst", "asset management"], "responsibilities": ["teams", "quality", "developing", "procedures", "hardware"], "requirements": {"degrees": [], "majors": [], "languages": [], "language_level": [], "hard_skills": ["o365", "remote support", "problem-solving skills", "it technologies", "hardware", "pc"], "soft_skills": ["problem-solving skills", "meet deadlines", "deep", "mobility"], "languages_combined": []}, "experience_required": {"duration": ["2+ years"], "field": ["it"]}}, {"job_id": "100003009037878", "location_code": "hk", "company": "China Construction Bank (Asia) Corporation Limited", "job_title": "Help Desk and Desktop Engineer", "description": "Main Responsibilities\n\n- Oversee the daily operation of Help Desk and Desktop services to ensure a stable and secured infrastructure environment is maintained.\n- Maintain a stable environment for the Desktop and OA devices and ensure the patches are deployed per schedule.\n- Provide technical solution on hardware, system software and security for business and infrastructure projects and arrangement of resources to support their development, testing and rollout.\n- Handle Marketing Data related to contract renewal, new products procurement, demand management and regular usage review.\n- Design desk side infrastructure and architecture per business strategy. Assist in IT planning and devising policy/process standard.\n- Oversee to fulfil regulatory and audit and internal control requirement.\n- Improve the productivity and reduce system administration overhead by using innovative technology.\n- Ensure HW and SW are covered by Maintenance Agreement by initiate the review, price negotiation and vendor coordination. Derive the cost allocation of some IT service and maintenance.\n- Provide on-call standby support during non-office hours.\n\nRequirements\n\n- Degree holder in Computer Science or Information Technology or related disciplines.\n- CISSP/CISA, ITIL, MCSE or PMP certification is preferred.\n- Minimum 4 years' experience in Desktop/Help Desk, preferably gained in banking or finance industry.\n- Experience in Marketing Data demand management is an advantage.\n- Proven project management experience in enterprise systems.\n- Management or design experience in Desktop, Office/Outlook, File & Print, SQL, IE.\n- Knowledge in Teller Platform, Check Imaging System, Securities, Online Banking and FX Trading System, Video wall, Videoconferencing and Trading Room support.\n- Reasonable knowledge on DNS, WINS, DHCP, TCP/IP, firewall, proxy.\n- Good command of spoken and written English and Chinese (both Cantonese and Putonghua).\n- Solid interpersonal, communication and organizational skills with good team spirit.\n- Good negotiation, vendor management and influential skill.\n- Able to work independently under pressure.\n", "employment_types": ["Full Time", "Permanent"], "selling_points": ["Help Desk and Desktop services", "Desk side infrastructure and architecture", "Information Technology"], "locations": ["Kowloon Bay"], "categories": ["Information Technology (IT)", "Hardware", "Support", "Network & System"], "post_time": "2022-01-11T04:06:50Z", "salary": {"currency": null, "max": null, "min": null, "period": "monthly", "term": null}, "salary_visible": false, "title_keywords": ["engineer"], "responsibilities": ["price negotiation", "it service", "software", "data", "audit", "design", "maintain", "administration", "internal control", "infrastructure", "testing", "schedule", "architecture", "management", "cost", "review", "maintenance", "daily operation", "hardware", "coordination", "planning"], "requirements": {"degrees": ["degree holder"], "majors": ["related disciplines", "computer science", "information technology"], "languages": ["cantonese", "putonghua", "english", "chinese"], "language_level": ["good command"], "hard_skills": ["itil", "mcse", "dns", "tcp", "vendor", "sql", "project management", "ip", "outlook", "firewall", "pmp"], "soft_skills": ["organizational skills", "work independently", "team spirit", "under pressure", "negotiation", "communication", "project management", "influential", "interpersonal"], "languages_combined": [{"language": "cantonese", "language_level": ["good command"]}, {"language": "putonghua", "language_level": ["good command"]}, {"language": "english", "language_level": ["good command"]}, {"language": "chinese", "language_level": ["good command"]}]}, "experience_required": {"duration": ["minimum 4 years"], "field": ["management", "print", "banking", "design", "sql", "project management", "marketing", "finance industry"]}}, {"job_id": "100003009039044", "location_code": "hk", "company": "Recolo Limited", "job_title": "IT Specialist - HKD $25K (16612)", "description": "\nOur client from a global law firm is looking for an IT Support Engineer to provide technical support on all IT issues relating to hardware, software, networks, communications, mobile and peripherals for 40 internal staffs.\n\n\n\nResponsibilities\n\nProvide tier one technical support to end users over the phone, by email or in person\nLogging and resolving service tickets in a timely manner according to SLA, or when necessary\nPerform root cause analysis, develop checklists for typical problems and recommend procedures and controls for problem prevention\nDevelops and maintains technical documentation\nMaintain IT asset inventories, keeping track of the life cycle and whereabouts of all IT equipment\nMaintain backup schedules and replace backup media to ensure successful server backup processes\nEnd-Point security support such as email spam management and anti-virus support\nSetup conference calls and meeting room\nUser accounts and mailboxes setup and management\nArrange and setup printers and other accessories and peripherals\nWi-Fi and LAN connectivity support, configuration, and troubleshooting\nProvide remote support to users working from home or away from offices\n\nRequirements\n\nBachelor\u2019s Degree in information technology or related\nMinimum 3 years of experience in technical and system support\nA professional IT Certification such as the MCSE, CCNA will be an advantage\nExperience in contemporary Microsoft cloud technologies such as Azure, Office 365\nExperience in Microsoft infrastructure: Windows 2019, Active Directory, Group Policies, PowerShell, DNS, DHCP, TCP/IP networking\nGood command of written and spoken English and Chinese\n\n\n\n\nThank you for your interest with Recolo Careers. For your application to reach directly to our consultant responsible for this job openings please apply via our careers portal below for a quick reply.\u00a0 \u00a0\u00a0\n\nPlease\u00a0Apply Here >\u00a0Confidential & Secure\u00a0<\nProblems?\u00a0+852 2971 2971\u00a0\u00a0\n\nApplication Disclaimer.\u00a0\u00a0\nWe recommend that application is made via our careers portal above. This application process does not sit in an email box but directly notifies the specialist consultant on our in-house systems for processing. Furthermore, our business intelligence systems will try to match other suitable jobs with other consultants that are not advertised externally. This accounts for between 50% \u2013 70% of our job openings in HK alone.\u00a0 \u00a0 \u00a0\n\nYou could apply using other methods but this will end up in our central email inbox. Which means our researchers will need to go through hundreds or even thousands of emails before they can finally match you to the consultant. If you want a rapid response, we suggest Recolo Careers Portal above. Furthermore, Recolo complies with the Personal Data (Privacy) Ordinance and regulated by the Labour Department.\u00a0 \u00a0 \u00a0 \u00a0\u00a0\n\nIf you are interested in other job opportunities, please visit\u00a0-\u00a0http://recolo.consulting/", "employment_types": ["Full Time", "Permanent"], "selling_points": ["Global Law Firm", "Technical Support", "MCSE / CCNA; Azure,Office 365"], "locations": ["Central & Western Area"], "categories": ["Information Technology (IT)", "Hardware", "Support", "Security"], "post_time": "2022-01-11T08:29:13Z", "salary": {"currency": null, "max": null, "min": null, "period": "monthly", "term": null}, "salary_visible": false, "title_keywords": ["it specialist"], "responsibilities": ["management", "technical support", "schedules", "analysis", "configuration", "a timely manner", "procedures", "troubleshooting", "develop", "it asset inventories", "maintain", "documentation", "it equipment", "setup"], "requirements": {"degrees": ["degree", "bachelor"], "majors": ["information technology"], "languages": ["english", "chinese"], "language_level": ["good command"], "hard_skills": ["mcse", "office 365", "azure", "dns", "active directory", "tcp", "ccna", "ip", "go", "powershell", "rapid", "processing", "business intelligence"], "soft_skills": ["interested in", "active", "responsible"], "languages_combined": [{"language": "english", "language_level": ["good command"]}, {"language": "chinese", "language_level": ["good command"]}]}, "experience_required": {"duration": ["minimum 3 years"], "field": ["system support", "infrastructure"]}}, {"job_id": "100003009033285", "location_code": "hk", "company": "Faithful Search Company", "job_title": "(18-25k, 5 day work) Helpdesk / IT Customer Service", "description": "Job\u00a0Description:\n\nResponsible for answer end users\u2019 enquires for various computer problem through telephone and email\nBe able to receive and respond to incoming calls, and/or e-mails regarding workstation and peripheral performance and use requests\nEscalate unresolved cases to relevant second level support team and external service providers\nResponsible for basic application software and OS installation for IT common systems\no-ordinate with external vendors on application software inquiries and maintenance\n\n\n\nJob\u00a0Requirement:\n\nDiploma\u00a0in\u00a0Information\u00a0Technology\u00a0or\u00a0equivalent\n1 - 2 year working experience on IT Services or Engineering would be advantage\nGood\u00a0command\u00a0of\u00a0spoken\u00a0&\u00a0written\u00a0English\u00a0and\u00a0Chinese\nCandidate with more experience will be considered for the Senior position\n\nInterested parties, please apply with full resume with detailed job duties, available date, current & expected salary to\u00a0Faithful Search Co.\n\nAll personal data collected will be used for recruitment purpose only and kept confidential.\n", "employment_types": ["Full Time", "Permanent"], "selling_points": ["18-25k, 5 day work, bank holiday", "Development opportunities", "Exp. IT Services or Engineering"], "locations": ["Not Specified"], "categories": ["Information Technology (IT)", "Hardware", "Support", "Network & System"], "post_time": "2022-01-09T04:48:47Z", "salary": {"currency": null, "max": null, "min": null, "period": "monthly", "term": null}, "salary_visible": false, "title_keywords": ["customer service"], "responsibilities": ["installation", "systems", "software", "maintenance"], "requirements": {"degrees": ["diploma"], "majors": ["information technology"], "languages": ["english", "chinese"], "language_level": ["good command"], "hard_skills": [], "soft_skills": [], "languages_combined": [{"language": "english", "language_level": ["good command"]}, {"language": "chinese", "language_level": ["good command"]}]}, "experience_required": {"duration": ["1 - 2 year"], "field": ["it", "engineering"]}}, {"job_id": "100003009040750", "location_code": "hk", "company": "TransUnion Limited", "job_title": "Sr. Techinical Support", "description": "Dynamics of the Role\n\nThe duties and responsibilities described above are the essential functions of the job. The qualifications below are representative of the knowledge, skills, and/or abilities required. Reasonable accommodations may be made to enable individuals with disabilities to perform the essential functions.\n\nHow You\u2019ll Contribute\n\n\n\nPerform daily system operations, internal users and external customers help desk support, PC/Laptop/Network installation and maintenance, end user application support, data center operations support and non-office hour support\nEnd user computing and mobile device support\nIT inventory and assets management\nIT procurement and vendor management support\nCommunicate with different parties including customers, service provider and office end-users\nRespond to end user/customer service ticket requests and technical support hotline\nInstall and configure computer hardware and operating systems\nDevelop and prepare support documentation and procedures for different supporting tasks\nFlexible working schedule (such as system maintenance work at night time)\nVulnerability management and Security Remediation Support\n\nWhat You\u2019ll Bring\n\nTechnical Institutes graduate or certificate holder or above in Computer Science or Information Technology\nAt least 3 years relevant experience in computer operation support\nSupport knowledge and experience of MS office, Windows operating systems & Exchange Server\u00a0\nAble to work under pressure\nGood in communication and interpersonal skills\nGood knowledge of Windows operation systems and MS products\u00a0\nBasic knowledge of cloud technology, network & security tools is an advantage\n\nWho We Are\n\n\nA global leader in credit information and information management services, TransUnion gives businesses, consumers and the global community the power to achieve their goals. Businesses count on us to better manage risk and customer relationships. Consumers are able to better manage credit to achieve their financial goals. And in communities around the world we help build strong economies and give people the power to achieve their dreams.\n\nExceptional opportunities are coming as we build on this strong foundation. Our ambitious growth strategy includes substantial new investment worldwide, a wide range of new solutions to help our customers succeed like never before, and new ideas for expanding our reach in every part of our dynamic and fast-moving industry. We\u2019re on an exciting journey and you can be a part of it.\n\nWe are an equal opportunity employer and all qualified applicants will receive consideration for employment without regard to race, color, religion, sex, national origin, disability status, protected veteran status, or any other characteristic protected by law.\n\nInterested candidates, please forward your resume and indicate current and expected salary by clicking apply now below\n\nData collected will be treated in strict confidence and used for recruitment purposes only.\n\nYou can also visit our LinkedIN career page at https://www.linkedin.com/company/4310/careers?trk=job_view_topcard_company_image", "employment_types": ["Full Time", "Permanent"], "selling_points": ["Expanding US Listed Business", "Flexible Working Culture", "Friendly Work Enviornment"], "locations": ["Tsim Sha Tsui"], "categories": ["Information Technology (IT)", "Hardware", "Support", "Network & System"], "post_time": "2022-01-12T03:01:06Z", "salary": {"currency": null, "max": null, "min": null, "period": "monthly", "term": null}, "salary_visible": false, "title_keywords": [], "responsibilities": ["data", "operations", "communication", "customer service", "work under pressure", "it procurement", "develop", "schedule", "vulnerability management", "it inventory", "operating systems", "installation", "management", "procedures", "documentation", "communicate with", "maintenance", "technical support", "systems", "hardware"], "requirements": {"degrees": ["certificate"], "majors": ["computer science", "information technology"], "languages": [], "language_level": [], "hard_skills": ["server", "basic", "maintenance", "help desk support", "vendor", "hardware", "exchange", "mobile device", "documentation", "pc", "operation support", "ms office"], "soft_skills": ["flexible", "customer service", "communication and interpersonal skills", "work under pressure"], "languages_combined": []}, "experience_required": {"duration": ["at least 3 years"], "field": ["operation", "relevant experience"]}}, {"job_id": "100003009034042", "location_code": "hk", "company": "Vita Green Health Products Company Limited", "job_title": "(Assistant) IT Officer - Fresh-graduate welcome", "description": "The Role:\n\nThe objective to this role is to provide IT support services to both office users and retail stores. Responsible for hardware and software installation and involving in general server administration and monitoring.\u00a0\n\n\nIf you are...\n\nHigher Diploma or above in Computer Science, System Engineer or related discipline\n1 to 2 years\u2019 relevant experience, preferably in retail environment\nProactive and energetic fast learner with strong can-do attitude\nFresh-graduate / candidates with less experience but with passion in IT\n\nWe will offer you...\n\nA Career opportunity with the market leader in health product sector.\nCasual wear everyday to enjoy your work.\nFun working culture with challenges to learn and grow together\nCareer with the market leader in health product sector from Hong Kong\nRapid growth opportunities for strong performers\nAttractive staff purchase discount to experience our quality products.\nShuttle to/from Taipo,\u202fTuen\u202fMun, Tin Shui Wai, Tsuen Wan, Tai Wai, Kowloon Tong, Yau Tong and Causeway Bay\u202f\n\nInterested parties, please send full resume with last & expected salary and date of available by clicking \u2018Apply Now\u2019\n\nPersonal data collected is for recruitment purpose only. For corporate information, please visit:\u00a0www.vitagreen.com", "employment_types": ["Full Time", "Permanent"], "selling_points": ["Leading health products company", "Fun Working Culture", "Great career opportunity"], "locations": ["Tai Po Area"], "categories": ["Information Technology (IT)", "Application Specialist - Software", "Hardware", "Support"], "post_time": "2022-01-10T02:30:06Z", "salary": {"currency": null, "max": null, "min": null, "period": "monthly", "term": null}, "salary_visible": false, "title_keywords": ["it officer", "assistant"], "responsibilities": ["installation", "software", "support services", "monitoring", "quality", "hardware", "purchase", "administration"], "requirements": {"degrees": ["higher diploma or above"], "majors": ["computer science"], "languages": [], "language_level": [], "hard_skills": ["fun", "server administration", "hardware", "rapid", "wan"], "soft_skills": ["proactive", "responsible", "can-do attitude", "passion in", "energetic", "fast learner"], "languages_combined": []}, "experience_required": {"duration": ["1 to 2 years"], "field": ["retail", "relevant experience", "it"]}}, {"job_id": "100003009035822", "location_code": "hk", "company": "Tradelink Electronic Commerce Ltd", "job_title": "Application Engineer \u2013 Solution Development, Supply Chain Solutions", "description": "Reporting to the Manager/Assistant Manager, Application Engineer is responsible for the maintenance and support of hardware/software applications for supply chain solutions.\n\nThe job holder will work with internal developers, third party contractors, sales, and end users (both internal & external) to support new and existing customers.\n\nDuties and Responsibilities:\n\nResponsible for the hardware system support for the warehouse automation projects.\nSupport solution team to formulate user specification /and or functional specification for system designs.\nReview system designs and modify if necessary to make the system design more efficient and meets Tradelink customer requirements.\nSupport system analysts on project deliveries to meet customer requirements and timelines.\nManage vendors and third-party contractors in fulfilling its obligation and deliver products to the satisfaction of Tradelink and meet all customer requirements.\nResolve problems arising from system errors identified in the testing and production environment.\n\n\u00a0Job Specification:\n\nDegree in Mechanical Engineering / Electrical Engineering / Information Technology, or similar credential.\n1 to 3 years\u2019 experience in hardware support and project management, with solid hands-on experience in AutoCAD and Solidworks.\nKnowledge on automated guided vehicle (AGV), autonomous mobile robot (AMR), and automated storage and retrieval system (ASRS) is an advantage\nGood organisational and project management skills\nVendor management experience is a must.\nWarehouse automation project experience is an advantage\nStrong presentation skills, able to present technical issues in layman terms.\nExcellent analytical skills and strong leadership skills.\nExcellent interpersonal and communication skills.\nMulti-tasking and strong self-initiative\n\nWe offer fringe benefits including 5-day work week, medical insurance, double pay,\u00a0discretionary bonus\u00a0and good career prospects. Interested parties, please apply with a detailed CV with present and expected salary to: The Human Resources Department, Tradelink Electronic Commerce Limited, 11/F & 12/F, Tower B, Regent Centre, 63 Wo Yi Hop Road, Kwai Chung, Hong Kong or by fax : 25991680.\n\nPersonal data provided by job applicants will be used strictly in accordance with Tradelink's Personal Data Collection Policy for Recruitment, a copy of which is available at\u00a0http://www.tradelink.com.hk./", "employment_types": ["Full Time", "Permanent"], "selling_points": ["5-day work week, medical insurance & double pay", "Degree holder in Mechanical Engineering / IT", "Min.1 yr exp. in hardware support & project mgt."], "locations": ["Kwai Tsing Area"], "categories": ["Information Technology (IT)", "Hardware", "IT Project Management / Team Lead", "Transportation & Logistics", "Supply Chain"], "post_time": "2022-01-10T08:28:48Z", "salary": {"currency": null, "max": null, "min": null, "period": "monthly", "term": null}, "salary_visible": false, "title_keywords": ["application engineer"], "responsibilities": ["reporting", "management", "software", "maintenance", "tradelink", "review", "testing", "communication", "hardware", "project management", "system design", "third party"], "requirements": {"degrees": ["degree"], "majors": ["information technology", "electrical engineering", "mechanical engineering"], "languages": [], "language_level": [], "hard_skills": ["maintenance", "vendor", "analytical skills", "hardware", "project management", "make", "system design", "mobile", "solidworks", "autocad"], "soft_skills": ["efficient", "communication skills", "responsible", "project management skills", "leadership skills", "analytical skills", "project management", "hands-on", "autonomous", "presentation skills", "multi-tasking", "self-initiative", "interpersonal"], "languages_combined": []}, "experience_required": {"duration": ["1 to 3 years"], "field": ["project management", "management"]}}, {"job_id": "100003009033387", "location_code": "hk", "company": "Pasha Recruitment Limited", "job_title": "IT Analyst ($22-28K)", "description": "The Firm\n\n\n\nOur client is a reputable international law firm, they are hiring a IT Analyst to join their IT team in Hong Kong and supporting their HK and China office.\n\nThe Opportunity\u00a0\n\n\nProviding 1st and 2nd tier technical support to end users including remote and in-house support\nTroubleshoot, and resolve issues regarding Windows Desktops, Hardware, Software, Network\nEnsure that all relevant incidents, requests and problems are accurately logged, managed and escalated according require service levels\nSupporting the setup, testing, operation and tear down of audio-visual (AV) and video-conference (VTC) equipment as required\nFoster data security policies and best practices\nEnsure application availability, perform regular capacity planning, housekeeping to maintain system healthiness and disaster recovery planning\nProvide backfill support for other regional offices due to local holidays or staff absences as required\nAd-hoc IT-related tasks.\n\nThe Ideal Candidate\n\nHigher Diploma / Degree in Computer Science or related discipline is preferred\nMinimum 4 years of Desktop / Helpdesk support experience in sizable company\nAdvanced to expert proficiency in Microsoft Operating System\nGood communication skills in both written and spoken English and Chinese\nExperience in user support in Windows, MS Office, Networking and Backup Systems\nFlexible personality, positive and proactive and good troubleshooting skill\nStrong sense of responsibility and excellent organizational and time management skills\nAble to work independently with minimal supervision and under pressure\n\nTo Apply\n\nInterested parties please send us your updated resume and application letter together with your latest and expected salary. All information collected will be used for recruitment related purpose only.\n\nCandidates should consider their application unsuccessful if not being invited for interview within 6 weeks from your application. Meanwhile, please feel free to refer to our company profile on Jobs DB and contact us directly for any further enquiries.", "employment_types": ["Full Time", "Permanent"], "selling_points": ["Permanent inhouse opportunity w/good package", "Stable and dynamic working environment and team", "Good benefits and work with international firm"], "locations": ["Central & Western Area"], "categories": ["Information Technology (IT)", "Hardware", "Support", "Network & System"], "post_time": "2022-01-09T13:08:09Z", "salary": {"currency": null, "max": null, "min": null, "period": "monthly", "term": null}, "salary_visible": false, "title_keywords": ["it analyst"], "responsibilities": ["ad-hoc", "software", "data", "troubleshooting", "communication", "maintain system healthiness", "troubleshoot", "testing", "visual", "application availability", "audio", "regular capacity planning", "setup", "management", "recovery planning", "technical support", "policies", "housekeeping", "systems", "hardware"], "requirements": {"degrees": ["diploma", "degree"], "majors": ["computer science"], "languages": ["english", "chinese"], "language_level": ["good"], "hard_skills": ["hardware", "ms office"], "soft_skills": ["flexible", "communication skills", "work independently", "under pressure", "advanced", "sense of responsibility", "time management skills", "organizational", "troubleshooting", "troubleshoot", "proactive", "positive", "ideal"], "languages_combined": [{"language": "english", "language_level": ["good"]}, {"language": "chinese", "language_level": ["good"]}]}, "experience_required": {"duration": ["minimum 4 years"], "field": []}}, {"job_id": "100003009031341", "location_code": "hk", "company": "Hong Huan Group Limited", "job_title": "IT Support Specialist / IT Support Officer (5-day work)", "description": "Responsibilities:\n\nProvide helpdesk and deskside end-user IT support and troubleshooting\nHandle daily technical supports and maintenance, such as back up strategy and network security\nHandle server troubleshooting and Active Directory administration\nResponsible for networking troubleshooting\nMaintain IT asset and software licensing inventory\nWork as part of a team on infrastructure projects with hands-on implementation\nCollaborate with third-party vendors to deliver various kind of\u00a0IT\u00a0projects\nHandle any ad-hoc projects as instructed by supervisor\n\nRequirements:\n\nHigher diploma or above in Information Technology, Computer Science or related discipline\nAt least 2 years\u2019 solid experience in IT support\nExperience in M365, Exchange, Google working space, Window AD and VMware administration\nKnowledge of LAN/WAN, TCP/IP networking, DNS, VPN, AP and firewall router\nResponsible, self-motivated, good communication and interpersonal skills\nStrong in problem-solving and detail-minded\nExperience in managing servers, firewall, switch and backup\nPossess relevant\u00a0IT\u00a0qualifications will be a plus\nCandidate who has less experience will be considered as\u00a0IT Support Officer\nFresh graduates will also be considered\nWe offer competitive remuneration package to the right candidates. Interested parties, please submit your resume (in both English and Chinese), with stating current and expected salary, availability, contact phone number by\u00a0APPLY NOW.\nAll applications and personal information collected will be treated in strict confidence and only be used for the purpose of recruitment and selection. The information collected will be accessed by our authorized personnel only. Unsuccessful applications will be retained for six months of possible future job matching, and will be destroyed after the expiry of six months.", "employment_types": ["Full Time", "Permanent"], "selling_points": [], "locations": ["Ngau Tau Kok"], "categories": ["Information Technology (IT)", "Hardware", "Support", "Network & System"], "post_time": "2022-01-07T09:13:16Z", "salary": {"currency": null, "max": null, "min": null, "period": "monthly", "term": null}, "salary_visible": false, "title_keywords": ["specialist", "it support officer", "it support"], "responsibilities": ["collaborate with", "technical supports", "software", "active directory", "maintenance", "inventory", "infrastructure", "troubleshooting", "implementation", "end-user it support", "maintain", "ad-hoc projects", "administration"], "requirements": {"degrees": ["higher diploma or above"], "majors": ["computer science", "information technology"], "languages": [], "language_level": [], "hard_skills": ["ap", "plus", "vmware", "dns", "tcp", "servers", "problem-solving", "switch", "router", "ip", "vpn", "firewall", "wan", "exchange"], "soft_skills": ["detail-minded", "self-motivated", "responsible", "problem-solving", "communication and interpersonal skills"], "languages_combined": []}, "experience_required": {"duration": ["at least 2 years"], "field": ["administration", "it support"]}}, {"job_id": "100003009037171", "location_code": "hk", "company": "The Kowloon Motor Bus Co (1933) Ltd", "job_title": "Senior Information Technology Officer, Infrastructure & Data Centre Section", "description": "Requirements:\n\nDegree holder in Computer Science or related discipline\nAt least 5 years of various network design and implementation\nGood understanding with ability to adopt latest information technology and standards for the whole company\nGood technical knowledge of operating systems, databases, IT infrastructure, networking, and IT security and applications\nGood communication, presentation, project management, interpersonal and leadership skills\nEffective and efficient problem solving skill\nAble to work independently under pressure with tight project timeline within non-office hour\nGood time management for managing multiples projects at the same time\nFamiliar with WAN/LAN/VLAN/VPN/VoIP/WLAN architecture and switching\nProficiency in CISCO/HUAWEI/RUCKUS/EXTREME router & switch\nHolder of CCNA & CCDA or equivalent certificates are highly preferable\nStrong knowledge in FortiOS & Cisco ISO\nKnowledge on different network topology, including but not limit to STP, M-lag, OSPF, LLDP, etc.\u00a0\nExperience in Linux, Apache, Shell Script\nAbility to work independently\nDealing with ISP / hardware vendors\nKnowledge in data security technology, such as SSL, encryption, secure code would be an advantage\nResponsibilities:\nNetwork routers and switches configuration\nNetwork infrastructure planning and design\nMonitor the healthiness of overall network infrastructure\nSuggest any upgrade / replacement for network equipment\nGood knowledge in network troubleshooting\nOn-site network/user support\nSourcing and testing innovative technology for enhancement of services to passenger and internal operations\nAct as a project team member to deliver critical IT system from end user perspective and to work with contractor according to the service agreement\nDeliver flexible, cost effective and \u201ctime to market\u201d technology solutions to accommodate the business needs\nParticipate in the development and implementation of IT policies and procedures\nProvide ad-hoc system support/ quick win solution to users when required\nWorking Location:\nKowloon Bay\n\nApplicants who are not invited for interview within 6 weeks may consider their applications unsuccessful.\nPersonal data collected will be used for recruitment purpose only. The Company will keep personal data of unsuccessful job applicants for a maximum period of 12 months. After that time, the personal data will be destroyed.", "employment_types": ["Full Time"], "selling_points": [], "locations": ["Kowloon Bay"], "categories": ["Information Technology (IT)", "Hardware", "Network & System", "Others"], "post_time": "2022-01-11T01:58:30Z", "salary": {"currency": null, "max": null, "min": null, "period": "monthly", "term": null}, "salary_visible": false, "title_keywords": ["senior information technology officer"], "responsibilities": ["network infrastructure", "ad-hoc", "cost", "configuration", "operations", "monitor", "implementation", "design", "testing", "it policies", "procedures", "network troubleshooting", "planning"], "requirements": {"degrees": ["degree holder"], "majors": ["computer science"], "languages": [], "language_level": [], "hard_skills": ["linux", "apache", "switch", "ccna", "router", "problem solving", "project management", "hardware", "vpn", "databases", "code", "wan"], "soft_skills": ["efficient", "work independently", "under pressure", "leadership skills", "presentation", "communication", "project management", "problem solving skill", "time management", "interpersonal"], "languages_combined": []}, "experience_required": {"duration": [], "field": []}}, {"job_id": "100003009031197", "location_code": "hk", "company": "Ambition", "job_title": "IT Desktop Support Specialist", "description": "Responsibilities:\n\nBuild and install desktop infrastructure (PCs, telephone, wireless networks etc.)\nProvide routine maintenance via remote and/or on-site support\nProvides advice and guidance to colleagues regarding incidents\nIdentify, log and resolve technical problems with software applications or network systems\nIdentify and report potential changes and system improvements to senior team leaders\nManage PCs from Windows10 and Mac iOS, Migrate from lower to higher versions.\nConduct Inventory Check as required.\n\nRequirements:\n\nProven work experience as Desktop Support Engineer or Support Technician.\nAdvanced knowledge of computer hardware systems, chipsets, memory modules, and peripherals\nAbility to solve complex hardware and software issues.\nAbility to travel and work after hours when necessary.\nGood communication skills in English and Chinese\n\nIf interested you can simply click APPLY NOW or contact River Zhao at (+852)3103-4345 or river.zhao@ambition.com.hk\n\nIf this job isn't quite right for you, but you know someone who would be great at this role, why not take advantage of our referral scheme? We offer HKD1000 in Apple gift cards for every referred candidate who we place in a role. Terms & Conditions Apply. https://www.ambition.com.hk/refer-a-friend", "employment_types": ["Full Time", "Permanent"], "selling_points": ["Hardware and software knowledge", "PC, telephone, network support", "Problem solving skills"], "locations": ["Not Specified"], "categories": ["Information Technology (IT)", "Hardware", "Support", "Technical / Functional Consulting"], "post_time": "2022-01-07T09:02:44Z", "salary": {"currency": "HKD", "max": 24999, "min": 17000, "period": "monthly", "term": null}, "salary_visible": true, "title_keywords": ["specialist"], "responsibilities": ["guidance", "software", "maintenance", "inventory check", "system improvements", "infrastructure", "pcs", "systems", "report"], "requirements": {"degrees": [], "majors": [], "languages": ["english", "chinese"], "language_level": ["good"], "hard_skills": ["hardware", "scheme"], "soft_skills": ["communication skills", "advanced"], "languages_combined": [{"language": "english", "language_level": ["good"]}, {"language": "chinese", "language_level": ["good"]}]}, "experience_required": {"duration": [], "field": []}}, {"job_id": "100003009033105", "location_code": "hk", "company": "Optimum Solutions (Singapore) Pte Ltd", "job_title": "Onsite Helpdesk Support Officers (Multiple openings) (32K)", "description": "Job Description:\n\nSupervise and perform on-site technical and operational support and monitoring on the wristband operations at Boundary Control Points\u00a0\nSupervise the front line operation team to ensure the smooth operation of the quarantine-free travel between Mainland and HK\nCommunicate with the outbound passengers and provide guidance and assistance in using the \"Hong Kong Health Code\" system and the code conversion\n\n\nRequirements:\n\nDiploma or above in any disciplines with at least FIVE years IT-related working experience\u00a0\nCandidates should be technically sound in operating Android and iOS mobile phone\nCandidates should be polite, patience and have good communication skill\nGood command of Chinese and English\nFully vaccinated\u00a0\nWorking location: Border Control Points\nWorking on Saturday, Sunday and Public Holidays is required on roster basis\nOvernight work is required on roster basis", "employment_types": ["Full Time", "Contract"], "selling_points": ["Onsite helpdesk support on mobile apps", "Good communication skills", "5 days work / 8.8 hours per day / Shift work"], "locations": ["Not Specified"], "categories": ["Sales, CS & Business Devpt", "Call Centre", "Information Technology (IT)", "Hardware", "Support"], "post_time": "2022-01-08T08:46:49Z", "salary": {"currency": null, "max": null, "min": null, "period": "monthly", "term": null}, "salary_visible": false, "title_keywords": [], "responsibilities": ["communicate with", "control", "operational support", "operations", "monitoring", "provide guidance"], "requirements": {"degrees": ["diploma or above"], "majors": ["it", "any disciplines"], "languages": ["english", "chinese"], "language_level": ["good command"], "hard_skills": ["mobile", "android"], "soft_skills": ["communication skill", "polite", "patience"], "languages_combined": [{"language": "english", "language_level": ["good command"]}, {"language": "chinese", "language_level": ["good command"]}]}, "experience_required": {"duration": ["at least five years"], "field": ["related", "it"]}}, {"job_id": "100003009032884", "location_code": "hk", "company": "Hong Kong Job Consulting", "job_title": "IT Support Officer", "description": "A global IT infrastructure and Network Company is going to expand the business in Hong Kong and is looking for a high-calibre IT Support Officer to provide on-site support for her client in Hong Kong.\n\nResponsibilities:\n\nProvide on-site support on 100 PCs & 100 servers in daily operations & ensure their normal operations\nPerform basic troubleshooting diagnosis in office applications, printers, networks etc.\nPerform\u00a0well service-oriented mind set and supporting co-ordinate ability\nSupport conference room\u2019s video equipment operations and maintenance for different video conferencing\nMaintain competitive in\u00a0networking, module of server implementation\n\nRequirements:\n\nDiploma or Degree in Computer Science/IT and related discipline\n1-2 years related working experience in technical support role\n\u00a0Familiar with PC hardware & software or Mac\n\u00a0Proficient knowledge of IT asset management work content\n\u00a0Basic server & network knowledge, experience in O365 preferred\n\nInterested parties please send your resume to \"APPLY NOW\u201d\n\n\u00a0***Personal data collected will be used for recruitment purposes only***", "employment_types": ["Full Time", "Permanent", "Contract", "Freelance"], "selling_points": ["Information Technology", "IT Support", "Support for Server and PC"], "locations": ["Not Specified"], "categories": ["Information Technology (IT)", "Hardware", "Support", "Network & System"], "post_time": "2022-01-08T02:04:33Z", "salary": {"currency": null, "max": null, "min": null, "period": "monthly", "term": null}, "salary_visible": false, "title_keywords": ["it support officer"], "responsibilities": ["maintenance", "operations", "pcs", "troubleshooting", "implementation", "daily operations", "maintain"], "requirements": {"degrees": ["diploma", "degree"], "majors": ["it", "computer science"], "languages": [], "language_level": [], "hard_skills": ["o365", "basic", "hardware", "server", "pc"], "soft_skills": [], "languages_combined": []}, "experience_required": {"duration": ["1-2 years"], "field": ["related"]}}, {"job_id": "100003009028452", "location_code": "hk", "company": "Perfect Medical Health Management Limited", "job_title": "Senior/ IT Support Officer(5 day, listed company)", "description": "Pursue a Career with Impact\n\nAt Perfect Medical, we dare to envision, and we strive for perfection.\n\nPerfect Medical is a leading Medical Beauty Group with over 100 treatment centers worldwide. With our passion for innovation and breakthroughs, our business\u2019 global footprint has been extending from Hong Kong Headquarter to China, Macau, Australia and Singapore with over 2,000 employees across regions.\n\nTo cope with the Company\u2019s rapid expansion, we are currently looking for high caliber and visionary candidates to join our team as Senior/ IT Officer.\n\nJob Responsibilities:\u00a0\n\nResponsible for providing day-to-day PC support, handling user's request, coordinating and arranging technical support service activities\nPerform upgrades and deployments of software and hardware\nProvide support for system upgrade and migration\nAssist in IT Projects / Administrative Works / Deskside Support\nProvide administrative support to the IT Department, including but not limited filing and documentation maintenance, record keeping and facility management;\nAssist in IT procurement and IT payment, keep track of all the IT expenses;\nLiaise with vendors for quotation, invoice and delivery;\nRequirements:\u00a0\n\nWith 1-2 years' relevant office I. T. support experience\nIndependent, self-motivated and good communication skills\nGood knowledge of computer hardware and software\nFamiliar with Microsoft products\nF.5 or above major in Information Technology or Computer related disciplines is an advantage\nImmediate available is a big plus\n\nWe offer competitive remuneration package and good prospects to the right candidates. Interested parties please send your full resume with expected salary to apply. Data collected will be kept confidential and used for recruitment purposes only.", "employment_types": ["Full Time", "Permanent"], "selling_points": ["1 year or above experience in technical support", "Perform hardware / software /  IT equipment", "5-day work week, year-end bonus, Medical"], "locations": ["Mong Kok"], "categories": ["Information Technology (IT)", "Hardware", "Support", "Network & System"], "post_time": "2022-01-07T02:20:55Z", "salary": {"currency": null, "max": null, "min": null, "period": "monthly", "term": null}, "salary_visible": false, "title_keywords": ["it support"], "responsibilities": ["provide support", "documentation", "management", "software", "maintenance", "technical support", "upgrades", "invoice", "expenses", "quotation", "deskside support", "hardware", "payment", "liaise with", "provide administrative support", "migration", "it procurement"], "requirements": {"degrees": [], "majors": [], "languages": [], "language_level": [], "hard_skills": ["hardware", "plus"], "soft_skills": ["communication skills", "self-motivated", "independent"], "languages_combined": []}, "experience_required": {"duration": [], "field": []}}, {"job_id": "100003009029304", "location_code": "hk", "company": "Hong Kong Baptist Hospital", "job_title": "Computer Technician", "description": "Key Duties and Responsibilities:\nProviding support on IT services\nResponding to users support queries, support in person, over the phone or via remote access\nCommunicate with users through basic problem-solving processes, and follow up until problem resolved\nDiagnosing issues with computer software, peripherals and hardware\nConduct training for internal users on common office applications\nRequirements:\nDiploma or Bachelor\u2019s degree in computer science, information technology or similar field\nMinimum 3 years working experience on IT support and desktop management\nExcellent analytical and diagnostic skills\nHigh-level communication and customer service skills\nStrong technical knowledge on desktop security and management\nSound knowledge on Microsoft Windows Servers and networking\nManaging multiple tasks simultaneously while maintaining high customer service standards\nProgram certification such as Microsoft, Cisco & ITIL are preferred\nWe offer attractive remuneration package and fringe benefits to the right candidates. Interested parties please apply with full resume and expected salary to Human Resources Department, Hong Kong Baptist Hospital, 18/F, Tower 2, Enterprise Square, 9 Sheung Yuet Road, Kowloon Bay, Kowloon, by email via \"Apply Now\"\u00a0or by fax to 2339 5769 on or before 21 January 2022.\nThe information provided will only be used for recruitment related purposes. All personal information on unsuccessful candidates will be destroyed within 6 months.", "employment_types": ["Full Time", "Contract"], "selling_points": [], "locations": ["Kowloon City"], "categories": ["Information Technology (IT)", "Hardware", "Support", "Network & System"], "post_time": "2022-01-07T04:37:36Z", "salary": {"currency": null, "max": null, "min": null, "period": "monthly", "term": null}, "salary_visible": false, "title_keywords": ["technician"], "responsibilities": ["communicate with", "hardware", "software", "providing support"], "requirements": {"degrees": ["diploma", "degree", "bachelor"], "majors": ["computer science", "information technology"], "languages": [], "language_level": [], "hard_skills": ["itil", "servers"], "soft_skills": ["communication", "customer service skills", "customer service", "multiple tasks"], "languages_combined": []}, "experience_required": {"duration": ["minimum 3 years"], "field": ["management", "it support"]}}, {"job_id": "100003009026238", "location_code": "hk", "company": "Thales Transport & Security (Hong Kong) Limited", "job_title": "Technician (Permanent / Part-Time)", "description": "The Role\n\nThis position is to work on the Revenue Collection Systems (RCS). Thales Revenue Collection Business Line designs and supplies a wide range of ticketing solutions ranging from equipping a line to rolling out multimodal and multi-operator integrated systems based on contactless technologies and suitable for both metro and bus networks.\n\nResponsibilities\n\nPerform daily maintenance activities, which include fault investigation, recovering and reporting under 24 X 7 environment.\nCarry out field services, provide hardware maintenance & installation services\nPerform preventive maintenance activities.\nPerform software upgrade and hardware modifications\n\nRequirements\n\nSchool certificate in Engineering (Computer, Electronics, Electrical, Mechanical) or above\nOn-site service support experience\nElectrical knowledge and installation skills\nGood communication skill, telephone manner, and service attitude\nGood command of Cantonese and English\nShift-duties and site work required\nDriving license will be advantage\nPart-time: Working days (at least 2 days/week is preferred)", "employment_types": ["Full Time", "Permanent"], "selling_points": ["Railway project", "Additional allowance", "Immediately available is desired"], "locations": ["Mong Kok"], "categories": ["Engineering", "Electrical / Electronics", "Information Technology (IT)", "Hardware", "Support"], "post_time": "2022-01-06T07:43:18Z", "salary": {"currency": null, "max": null, "min": null, "period": "monthly", "term": null}, "salary_visible": false, "title_keywords": ["technician"], "responsibilities": ["reporting", "installation", "software", "maintenance", "investigation", "hardware"], "requirements": {"degrees": ["certificate"], "majors": ["engineering"], "languages": ["cantonese", "english"], "language_level": ["good command"], "hard_skills": [], "soft_skills": ["communication skill", "telephone manner"], "languages_combined": [{"language": "cantonese", "language_level": ["good command"]}, {"language": "english", "language_level": ["good command"]}]}, "experience_required": {"duration": [], "field": []}}, {"job_id": "100003009030107", "location_code": "hk", "company": "Tech One Services Limited", "job_title": "IT Support Engineer", "description": "Responsibilities:\n\nProvide Helpdesk & Deskside technical support to end users from receiving IT related incidents and requests\nProvide first line determination and resolution to resolve / fulfill end users incidents / service requests on the basic usage advice on the supported applications and systems related PC usage;\nProvide L1/L2 desktop support experience in OS Installation (Windows 7/10), backup and data migration\nPerform routine installation & troubleshooting on hardware / software, operating system, office applications, Active Directory, antivirus and relevant hardware drivers\nIsolate problems on both software and hardware so as to efficiently address the desktop/laptop problem prior to fixing\nConduct asset inventory and update records\n\n\u00a0Requirements:\u00a0\n\nHigher diploma holders or above in Computer Studies or related subjects\n1 year's or above working experience in IT Support / Technical Support / Helpdesk support field\u00a0\nProficiency in Windows OS, TCP/IP, Cloning / Data Migration and Technical Support (MS Office, Windows OS, Active Directory, Common Desktop Application, Windows Server)\nSelf-motivated, proactive and customer focus attitude\nAble to work independently and cooperate with other parties\nGood command of both written and spoken English, Cantonese and Mandarin\n\n\u00a0\nInterested parties, please send your detail resume and expected salary by email:\u00a0\u00a0talent(a)techone.com.hk\u00a0or by WhatsApp:\u00a0\u00a0https://wa.me/85263605600\n\nAll information gathered will be treated in strict confidence and used for recruitment related purposed only.", "employment_types": ["Full Time"], "selling_points": ["Provide Helpdesk Service / end-users IT Support", "Support: Win OS, MS Office, TCP/IP, PC Clone", "HD with 1 yr's exp, good working attitude"], "locations": ["Central & Western Area"], "categories": ["Information Technology (IT)", "Hardware", "Support", "Network & System"], "post_time": "2022-01-07T06:48:25Z", "salary": {"currency": null, "max": null, "min": null, "period": "monthly", "term": null}, "salary_visible": false, "title_keywords": ["it support engineer"], "responsibilities": ["installation", "software", "active directory", "data", "technical support", "systems", "troubleshooting", "resolution", "hardware", "asset inventory", "migration"], "requirements": {"degrees": ["diploma"], "majors": ["computer studies"], "languages": ["cantonese", "english", "mandarin"], "language_level": ["good command"], "hard_skills": ["active directory", "tcp", "ip", "os", "focus", "windows server", "ms office"], "soft_skills": ["self-motivated", "proactive", "work independently", "customer focus", "active"], "languages_combined": [{"language": "cantonese", "language_level": ["good command"]}, {"language": "english", "language_level": ["good command"]}, {"language": "mandarin", "language_level": ["good command"]}]}, "experience_required": {"duration": ["1 year"], "field": ["it support"]}}, {"job_id": "100003009032276", "location_code": "hk", "company": "Bayou Talent", "job_title": "IT Support Specialist (Permanent role from stable company, work-life balance, up to 32K x 14)", "description": "Job Highlights\n\npermanent role, 18days leave/ year + 2 month bonus\u00a0\nGood career advancement\nwork-life balance job\nA stable financial\u00a0firm is currently seeking a IT Support Specialist to support their internal users on Desktop planform, and assist in server maintenance.\u00a0 \u00a0\n\n\nResponsibilities\n\nProvide 1st\u00a0to 2nd\u00a0tier inhouse IT technical support included Hardware, Software and Applications\nAssist to manage IT system infrastructure included Servers, Desktop, LAN, WAN, Wi-Fi, Mobile devices, etc\nAssist to monitor IT infrastructure and ensure the stability\nPatriciate in company IT projects\u00a0 \u00a0\nHandle ad hoc support duties\n\nRequirements\n\nHigher Diploma or above in Computer Science, Information Technology or related disciplines\nAt least 2 years\u2019 experience in IT technical support\u00a0\nExperience in server maintenance of Windows/ O365/ Active directory is preferred\nGood command of both spoken & written English & Chinese", "employment_types": ["Full Time", "Permanent"], "selling_points": ["permanent role, 18days leave/ year + 2 month bonus", "Good career advancement", "work-life balance job"], "locations": ["Not Specified"], "categories": ["Information Technology (IT)", "Hardware", "Support", "Network & System"], "post_time": "2022-01-08T03:41:24Z", "salary": {"currency": null, "max": null, "min": null, "period": "monthly", "term": null}, "salary_visible": false, "title_keywords": ["specialist", "it support"], "responsibilities": ["ad hoc", "software", "it technical support", "it infrastructure", "infrastructure", "monitor", "hardware", "mobile devices"], "requirements": {"degrees": ["higher diploma or above"], "majors": ["related disciplines", "computer science", "information technology"], "languages": ["english", "chinese"], "language_level": ["good command"], "hard_skills": ["o365", "server maintenance", "active directory"], "soft_skills": ["active"], "languages_combined": [{"language": "english", "language_level": ["good command"]}, {"language": "chinese", "language_level": ["good command"]}]}, "experience_required": {"duration": ["at least 2 years"], "field": ["maintenance", "it technical support"]}}, {"job_id": "100003009026217", "location_code": "hk", "company": "Speedy Group Corp. Limited", "job_title": "IT Operational Support (30K+)", "description": "Job Duties:\n\nAssist in supervising and performing on-site technical and operational support\nProvide technical support to end-user PCs/ Mobile devices including Apps download/ installation\nPerform administrative duties, including preparation of statistical reports\nKeep track of the stock usage and handle logistics arrangement\n\nJob Requirements:\n\nF.5/ Diploma or above\nAt least 3-5 years IT related working experience\nGood knowledge on computer hardware, systems and software applications\nSelf-motivated, strong problem solving and good communication skill\nMay request to perform duties on Saturday, Sunday and Public Holiday", "employment_types": ["Full Time"], "selling_points": ["IT Operational and Logistics Support", "Mobile Apps Support and end-users troubleshooting", "F.5 above plus 3-5 years IT working experience"], "locations": ["Not Specified"], "categories": ["Information Technology (IT)", "Hardware", "Support", "Network & System"], "post_time": "2022-01-06T07:39:29Z", "salary": {"currency": null, "max": null, "min": null, "period": "monthly", "term": null}, "salary_visible": false, "title_keywords": [], "responsibilities": ["installation", "operational support", "supervising", "logistics arrangement", "technical support", "pcs", "administrative duties", "reports", "mobile devices"], "requirements": {"degrees": ["diploma or above"], "majors": [], "languages": [], "language_level": [], "hard_skills": ["problem solving", "hardware"], "soft_skills": ["problem solving", "perform duties", "self-motivated", "communication skill"], "languages_combined": []}, "experience_required": {"duration": ["at least 3-5 years"], "field": ["related", "it"]}}, {"job_id": "100003009023649", "location_code": "hk", "company": "City University of Hong Kong", "job_title": "Assistant IT Officer II in the Computing Services Centre (Appointment for 12 months)", "description": "Assistant IT Officer II in the Computing Services Centre (Appointment for 12 months)\u00a0[Ref. D/R/113/03]\n\nThe Computing Services Centre (CSC) at City University of Hong Kong manages the University\u2019s Information Technology infrastructure and services covering Data Centre Operations, Cloud and System Hosting, Research Computing and High-Performance Computing, Communication and Networking, Workspace and Audio-Visual Technologies, and other related IT functions to support the University\u2019s operations.\u00a0 The Centre has about 110 staff and contractors currently.\n\nDuties\n\nReporting to the Cloud and Virtualization Team, the appointee will:\n\nPerform hardware and software asset verification and data input;\nAssist the IT Manager in setting up the CMCB solution;\nIntegrate asset records to ITIL solution; and\nPerform any other duties as assigned.\nRequirements\nAn Associate Degree/Higher Diploma/Diploma or equivalent;\nAt least 2 years\u2019 post-qualification working experience;\nSophisticated Linux and Windows shell skills and scripting languages;\nBeing reliable, self-motivated, detail-oriented, communicative with strong sense of ownership, analytical, problem solving and interpersonal skills;\nAbility to work independently; and\nGood command of written and spoken English and Chinese are required; and\nKnowledge of ITIL foundation is preferred.\nSalary and Conditions of Service\n\nSalary offered will be highly competitive, commensurate with qualifications and experience.\u00a0 Fringe benefits include leave, medical and dental consultations at the campus clinic.\n\nInformation and Application\n\nFurther information on the post and the University is available at\u00a0http://www.cityu.edu.hk, or from the Human Resources Office, City University of Hong Kong, Tat Chee Avenue, Kowloon Tong, Hong Kong [Fax : 2788 1154 or 3442 0311].\u00a0\n\nTo apply, please submit an online application at\u00a0http://jobs.cityu.edu.hk. The closing date is\u00a021 January 2022. Applications will receive full consideration and only shortlisted applicants will be contacted.\u00a0 The University\u2019s privacy policy is available on the homepage.\n\nCity University of Hong Kong is an equal opportunity employer. We are committed to the principle of diversity. Personal data provided by applicants will be used for recruitment and other employment-related purposes.\n\nWorldwide recognition ranking #53 (QS survey 2022), and #4 among top 50 universities under age 50 (QS survey 2021); #1 in the World\u2019s Most International Universities (THE survey 2020); #1 in Engineering/Technology/Computer Sciences in Hong Kong (ARWU survey 2016); and #1 Business School in Asia-Pacific region (UT Dallas survey 2019).", "employment_types": ["Full Time", "Temporary"], "selling_points": ["An Associate Degree/Higher Diploma/Diploma", "At least 2 years\u2019 working experience", "Leave, medical and dental consultations"], "locations": ["Wong Tai Sin Area"], "categories": ["Information Technology (IT)", "Hardware", "Software Development", "Network & System"], "post_time": "2022-01-06T16:07:37Z", "salary": {"currency": null, "max": null, "min": null, "period": "monthly", "term": null}, "salary_visible": false, "title_keywords": ["assistant it officer"], "responsibilities": ["reporting", "any other duties", "software", "data input", "hardware"], "requirements": {"degrees": ["associate degree", "diploma"], "majors": [], "languages": ["english", "chinese"], "language_level": ["good command"], "hard_skills": ["problem solving", "linux", "itil"], "soft_skills": ["sophisticated", "self-motivated", "work independently", "detail-oriented", "problem solving", "interpersonal skills", "reliable"], "languages_combined": [{"language": "english", "language_level": ["good command"]}, {"language": "chinese", "language_level": ["good command"]}]}, "experience_required": {"duration": ["at least 2 years"], "field": ["post-qualification"]}}, {"job_id": "100003009031583", "location_code": "hk", "company": "Gientech Technology (Hong Kong) Limited", "job_title": "System Specialist (Linux / Windows)", "description": "About us\n\nGientech is a global company offering consulting, digital, technology and operations services to the world\u2019s leading enterprises. From our roots in engineering to the latest in digital transformation, we give customers a competitive edge.\n\nOur Culture\n\nWithin our team, we are about passion to win, value our people, and client orientated. We treat our people with respect and trust and give them a ton of freedom and autonomy to make an impact.\u00a0 Join the growing company using technology to tackle enterprises toughest challenges.\n\nAbout this Job\n\nAs a System Specialist, you will work in an energetic team and involve in the sizable projects across diverse industries such as public institutions, retails, etc.\n\n\n\nKey Responsibilities\n\nParticipate in planning, implementation, and system expansion\nSetup and maintains the availability, and reliability of the customer infrastructure\nPerform installation, configuration, administration and troubleshooting of OS, hardware & software\nSupport focus on Windows or Linux or Virtualization / Cloud\nDeliver projects and negotiate with vendors for cost effective solution to meet business demands\n\nRequirements\n\nFamiliar with Linux (Centos / Redhat) or Windows Server\nFamiliar with middleware, SAN, Tivoli monitoring tools\nExperienced in Linux Shell, Python\nWith strong interpersonal skills\nStrong communication skills in English and Chinese (in both spoken and written)", "employment_types": ["Full Time", "Permanent"], "selling_points": ["Attractive Salary Package depends on ability", "Develop high-performance software for government", "Work Life Balance / Self-management culture"], "locations": ["Wan Chai"], "categories": ["Information Technology (IT)", "Hardware", "Support", "Network & System"], "post_time": "2022-01-07T09:31:21Z", "salary": {"currency": null, "max": null, "min": null, "period": "monthly", "term": null}, "salary_visible": false, "title_keywords": ["specialist"], "responsibilities": ["administration", "installation", "cost", "software", "configuration", "infrastructure", "implementation", "troubleshooting", "hardware", "setup", "planning"], "requirements": {"degrees": [], "majors": [], "languages": ["english", "chinese"], "language_level": [], "hard_skills": ["python", "linux", "centos", "windows server"], "soft_skills": ["communication skills", "interpersonal skills"], "languages_combined": [{"language": "english", "language_level": []}, {"language": "chinese", "language_level": []}]}, "experience_required": {"duration": [], "field": []}}, {"job_id": "100003009026768", "location_code": "hk", "company": "CIAO International Limited (Best Mart 360\u00b0)", "job_title": "I.T support", "description": "Responsibilities:\n\nHandle backend user inquiries, technical troubleshooting, repairing and support.\nProvide onsite or offsite troubleshooting, repairing, installation and maintenance.\nProvide 1st/ 2nd tier technical support via phone, remote & helpdesk support\nTo provide daily operation on pc, servers and network. requirement.\nSystem and Network Support.\n\nRequirements:\n\nHigh diploma or above in related discipline\nGood knowledge of IT systems and applications.\nExperience in IT support and help desk services is highly preferred.\nHigh integrity, pro-active, independent, and willing to learn.\nGood communication and interpersonal skill.\nFresh graduate will also be considered.\n1-3 years related retails experience, more experience will be considered as a senior role.\n\nInterest parties, please send full resume with current and expected salary and date of availability by clicking \"Apply Now\"\n\nPersonal data provided in application will be treated as strictly confidential and used for recruitment purpose by\u00a0CIAO International Limited\u00a0only.\u00a0All unsuccessful applications will be destroyed upon completion of the process.", "employment_types": ["Full Time"], "selling_points": ["Willing to learn, Good communication skills", "Able to work in a team environment", "Good knowledge in Hardware /Software"], "locations": ["Ngau Tau Kok"], "categories": ["Information Technology (IT)", "Hardware", "Support", "Network & System"], "post_time": "2022-01-06T08:36:24Z", "salary": {"currency": null, "max": null, "min": null, "period": "monthly", "term": null}, "salary_visible": false, "title_keywords": [], "responsibilities": ["installation", "maintenance", "technical support", "daily operation", "troubleshooting"], "requirements": {"degrees": ["high diploma or above", "fresh graduate"], "majors": [], "languages": [], "language_level": [], "hard_skills": [], "soft_skills": ["independent", "willing to learn", "integrity", "interpersonal skill", "communication", "pro-active"], "languages_combined": []}, "experience_required": {"duration": ["1-3 years"], "field": ["related", "it support"]}}, {"job_id": "100003009023539", "location_code": "hk", "company": "City University of Hong Kong", "job_title": "Assistant IT Officer II in the Computing Services Centre (Appointment for 12 months)", "description": "Assistant IT Officer II in the Computing Services Centre (Appointment for 12 months)\u00a0[Ref. D/R/109/03]\n\nThe Computing Services Centre (CSC) at City University of Hong Kong manages the University\u2019s Information Technology infrastructure and services covering Data Centre Operations, Cloud and System Hosting, Research Computing and High-Performance Computing, Communication and Networking, Workspace and Audio-Visual Technologies, and other related IT functions to support the University\u2019s operations.\u00a0 The Centre has about 110 staff and contractors currently.\n\nDuties\nHandle user enquiries, service requests and IT incidents via telephone hotline, email, service counter and instant messaging;\nProvide front-line support, remote and on-site troubleshooting for end users; and\nPerform any other duties as assigned.\n\n5-day work, shift duty and working outside office hours on a roster basis are required.\n\nRequirements\nAn Associate Degree/Higher Diploma/Diploma or equivalent in IT or related disciplines preferably with experience in IT support;\nAt least 2 years\u2019 post-qualification working experience;\nAdaptability to change and ability to work independently and as part of a team; and\nGood command of written and spoken English and Chinese are required.\nSalary and Conditions of Service\n\nSalary offered will be highly competitive, commensurate with qualifications and experience.\u00a0 Fringe benefits include leave, medical and dental consultations at the campus clinic.\n\nInformation and Application\n\nFurther information on the post and the University is available at\u00a0http://www.cityu.edu.hk, or from the Human Resources Office, City University of Hong Kong, Tat Chee Avenue, Kowloon Tong, Hong Kong [Fax : 2788 1154 or 3442 0311].\u00a0\n\nTo apply, please submit an online application at\u00a0http://jobs.cityu.edu.hk. The closing date is\u00a021 January 2022. Applications will receive full consideration and only shortlisted applicants will be contacted.\u00a0 The University\u2019s privacy policy is available on the homepage.\n\nCity University of Hong Kong is an equal opportunity employer. We are committed to the principle of diversity. Personal data provided by applicants will be used for recruitment and other employment-related purposes.\n\nWorldwide recognition ranking #53 (QS survey 2022), and #4 among top 50 universities under age 50 (QS survey 2021); #1 in the World\u2019s Most International Universities (THE survey 2020); #1 in Engineering/Technology/Computer Sciences in Hong Kong (ARWU survey 2016); and #1 Business School in Asia-Pacific region (UT Dallas survey 2019).", "employment_types": ["Full Time", "Temporary"], "selling_points": ["An Associate Degree/Higher Diploma/Diploma", "At least 2 years\u2019 working experience", "Leave, medical and dental consultations"], "locations": ["Wong Tai Sin Area"], "categories": ["Information Technology (IT)", "Hardware", "Software Development", "Network & System"], "post_time": "2022-01-06T16:07:36Z", "salary": {"currency": null, "max": null, "min": null, "period": "monthly", "term": null}, "salary_visible": false, "title_keywords": ["assistant it officer"], "responsibilities": ["any other duties", "troubleshooting"], "requirements": {"degrees": ["associate degree", "diploma"], "majors": ["related disciplines", "it"], "languages": ["english", "chinese"], "language_level": ["good command"], "hard_skills": [], "soft_skills": ["work independently", "adaptability"], "languages_combined": [{"language": "english", "language_level": ["good command"]}, {"language": "chinese", "language_level": ["good command"]}]}, "experience_required": {"duration": ["at least 2 years"], "field": ["related", "it", "post-qualification", "it support"]}}, {"job_id": "100003009031443", "location_code": "hk", "company": "ICD Security Solutions (HK) Ltd", "job_title": "Service Engineer", "description": "Main Objectives:\n\n\nService security systems and provide services to our clients. Troubleshooting and solving problems.\nEnsure Customer satisfaction.\nTo be proficient in our products and technology.\u00a0 Always improve ability.\nManage relations with existing clients.\nFinish routine preventive maintenance on time according to ICD standards and policies.\n\n\u00a0Main Responsibilities:\u00a0\n\nWork with the team to solve the client's security system problems in the earliest time.\nProvide support and maintenance services such as routine preventative maintenance.\n\nProduce system diagrams by AutoCAD.\nMaintain long-term relationships with clients.\nIncrease customer satisfaction.\nEnsure quality of ICD services following company standards and policies strictly, to deliver prompt and efficient response to all service requests within assigned region.\nProvide routine preventive maintenance.\nGeneral errand to assist team technically.\nAttend non-business hour's emergency hotline call. (Compensation Leave is applicable)\nKnowledge development such as access control, video, and alarm.\nReport to service department manager.\n\nRequirements:\u00a0\n\nDiploma or above in Electronics, Electrical or related discipline.\nStrong self learning ability, work independently.\nGood communication and interpersonal skills.\nKnowledge in AutoCad.\nOn duty is required.\n\nHave valid Security Personnel Permit (Cat D) is an advantage.\nFresh Graduate will be considered.\nCandidates with less experience will be considered as Junior position\n\n\u00a0We offer 5 days work, competitive salary, bonus, medical & dental benefits, best-in-class training and development, attractive career advancement opportunities to the right candidate.\n\nInterested parties, please send your application letter & CV including current and expected salary, date of availability to us.\u00a0 Please click \"Apply Now\".\n\n\u00a0All information received will be kept in strict confidential and\u00a0only for employment-related purpose.", "employment_types": ["Full Time", "Permanent"], "selling_points": ["Basic IT knowledge in hardware, network & database", "Provide support and maintenance services", "Quarterly Bonus, group medical benefits, training"], "locations": ["Kwun Tong Area"], "categories": ["Engineering", "Electrical / Electronics", "Engineering Project Management", "Information Technology (IT)", "Hardware"], "post_time": "2022-01-07T19:20:38Z", "salary": {"currency": null, "max": null, "min": null, "period": "monthly", "term": null}, "salary_visible": false, "title_keywords": ["service engineer"], "responsibilities": ["provide support", "maintenance", "policies", "quality", "maintain", "maintenance services", "access control", "report"], "requirements": {"degrees": ["fresh graduate", "diploma or above"], "majors": [], "languages": [], "language_level": [], "hard_skills": ["security personnel permit", "autocad"], "soft_skills": ["work independently", "communication and interpersonal skills", "learning ability"], "languages_combined": []}, "experience_required": {"duration": [], "field": []}}, {"job_id": "100003009030607", "location_code": "hk", "company": "Automated Systems (HK) Ltd", "job_title": "Service Desk Specialist (Work location: Shek Mun / Tin Hau)", "description": "Responsibilities\n\nPerform system operations and maintain operations procedures.\nControl data backup and restoration.\nConduct daily walkthroughs and routine checking of the computing services.\nConduct daily system administration, troubleshooting and applying remediation to system problems.\nDaily support the operational tasks\nPerform the change and configuration management under ITIL and ISO compliance\nMeet the corresponding service level agreement (SLA)\nDevelop and maintain operational procedures and performance statistics for all computer systems.\nWrite system scripts to schedule and monitor the performance of systems.\n\nRequirements\n\nHigher Certificate holder or above in IT or related disciplines\nWith 1 year experience in Information Technology services\nKnowledge in Microsoft Windows Active Directory, Exchange Server and AIX/Linux Administration is an advantage\nKnowledge in Data Center Operation is an advantage\nHolding any Professional Certificate is a plus\nGood interpersonal communication skill\nAble to work on-site, 7x24 shift and overnight shift\u00a0\nFluent in spoken English and Cantonese\nCandidate with less experience will be considered as\u00a0Assistant Service Desk Specialist\nFresh graduates are welcome\nWe offer 5-day week, excellent career opportunities, remuneration and benefits to the right candidates. \u00a0If you have the desire for an exciting and rewarding career, please send us your resume,\u00a0stating your notice period, present and expected salary to Human Resources Department by clicking \"Apply Now\".\u00a0\n\u00a0\nTo learn us more, please visit our website:\u00a0 www.asl.com.hk\n\nWe are an equal opportunity employer. All applications will be treated in strict confidence. We regret that only shortlisted candidates will be notified. All personal data will be destroyed within six months after the selection process.", "employment_types": ["Full Time", "Contract"], "selling_points": ["Control data backup and restoration", "Daily support the operational tasks", "With 1 year experience in IT services"], "locations": ["Not Specified"], "categories": ["Information Technology (IT)", "Hardware", "Support", "Network & System"], "post_time": "2022-01-07T07:52:52Z", "salary": {"currency": null, "max": null, "min": null, "period": "monthly", "term": null}, "salary_visible": false, "title_keywords": ["specialist"], "responsibilities": ["control", "management", "data", "configuration", "operations", "operational tasks", "compliance", "procedures", "troubleshooting", "computer systems", "develop", "systems", "maintain", "operational procedures", "schedule", "monitor the performance", "routine checking", "administration"], "requirements": {"degrees": ["certificate", "higher certificate"], "majors": ["related disciplines", "it"], "languages": ["cantonese", "english"], "language_level": ["fluent"], "hard_skills": ["linux", "plus", "active directory", "server", "exchange"], "soft_skills": ["communication skill", "active", "interpersonal"], "languages_combined": [{"language": "cantonese", "language_level": ["fluent"]}, {"language": "english", "language_level": ["fluent"]}]}, "experience_required": {"duration": ["1 year"], "field": ["information technology"]}}, {"job_id": "100003009030042", "location_code": "hk", "company": "Paul Y. Engineering Group", "job_title": "Operation Officer / IT Officer", "description": "Job Description\n\nDaily operations of computers, systems and software implementations and relocation;\nNetwork cabling in both Head office and construction sites; and\nAssist in Ad Hoc projects.\n\nJob Requirements\n\nDiploma or above;\nAt least 5 years of related experience;\nKnowledge in MCSE, CCNE is preferred; and\nProficiency in the latest version of Microsoft Office (Outlook, Word, Excel, PowerPoint).\n\n***What we offer?\n\nCompetitive remuneration package\nAdditional leave (Family Care Leave, Exam Leave, Qualification Leave, etc.)\nDiscretionary bonus\nStudy Subsidies\nComprehensive training and professional career development\n\nInterested parties please apply by clicking \"APPLY NOW\" with detailed CV stating expected salary and date of availability.\n\nCompany Website: \u00a0http://www.pyengineering.com/\n\nAll personal data provided will be used strictly in accordance with our \u201cPersonal Information Collection Statement Pertaining to Recruitment\u201d, a copy of which is available upon written request to us by E-mail.", "employment_types": ["Full Time", "Permanent"], "selling_points": ["PC/System support", "Network cabling", "Diploma with 5 yrs experience"], "locations": ["Kwun Tong"], "categories": ["Information Technology (IT)", "Hardware", "Support"], "post_time": "2022-01-07T19:20:03Z", "salary": {"currency": null, "max": null, "min": null, "period": "monthly", "term": null}, "salary_visible": false, "title_keywords": ["operation officer", "it officer"], "responsibilities": ["daily operations", "systems", "ad hoc projects", "software"], "requirements": {"degrees": ["diploma or above"], "majors": [], "languages": [], "language_level": [], "hard_skills": ["mcse", "excel", "microsoft office", "word", "powerpoint", "outlook"], "soft_skills": [], "languages_combined": []}, "experience_required": {"duration": ["at least 5 years"], "field": ["related"]}}, {"job_id": "100003009024294", "location_code": "hk", "company": "Wilson International Frozen Foods (H.K.) Ltd", "job_title": "IT Technical Support", "description": "Responsibilities:\n\nProvide end-users technical\u00a0support\u00a0and conduct troubleshooting on hardware, software, and other computer services;\nMonitor and maintain Server, desktop PC, Mobile devices, printer and network;\nSoftware / Hardware updates and upgrades;\nRequire off site\u00a0support.\n\u00a0Requirements:\n\nDiploma or above in Computer or Information Technology;\n1 year\u2019s working experience in technical\u00a0support\u00a0role;\nKnowledge in\u00a0supporting the PC/ LAN/ WAN, systems and applications;\nKnowledge of basic networking - (Configure IP, Gateway);\nWork Independent, self-motivated and hardworking;\nImmediate available is highly preferred\nInterested parties please email your application letter and full resume with expected salary for interview.", "employment_types": ["Full Time", "Part Time", "Permanent"], "selling_points": ["1 Year experience", "End-users technical support", "Knowledge of basic networking"], "locations": ["Tsuen Wan Area"], "categories": ["Information Technology (IT)", "Hardware", "Support", "Network & System"], "post_time": "2022-01-05T13:34:46Z", "salary": {"currency": null, "max": null, "min": null, "period": "monthly", "term": null}, "salary_visible": false, "title_keywords": ["technical support"], "responsibilities": ["software", "technical support", "upgrades", "computer services", "monitor", "troubleshooting", "hardware", "mobile devices", "maintain server"], "requirements": {"degrees": ["diploma or above"], "majors": ["information technology"], "languages": [], "language_level": [], "hard_skills": ["pc", "wan", "basic", "ip"], "soft_skills": ["self-motivated", "independent", "hardworking"], "languages_combined": []}, "experience_required": {"duration": ["1 year"], "field": []}}, {"job_id": "100003009023575", "location_code": "hk", "company": "City University of Hong Kong", "job_title": "Assistant IT Officer II in the Computing Services Centre (Appointment for 12 months)", "description": "Assistant IT Officer II in the Computing Services Centre (Appointment for 12 months)\u00a0[Ref. D/R/108/03]\n\nThe Computing Services Centre (CSC) at City University of Hong Kong manages the University\u2019s Information Technology infrastructure and services covering Data Centre Operations, Cloud and System Hosting, Research Computing and High-Performance Computing, Communication and Networking, Workspace and Audio-Visual Technologies, and other related IT functions to support the University\u2019s operations.\u00a0 The Centre has about 110 staff and contractors currently.\n\nDuties\nAssist the Scientific Officer in administering and supporting the HPC systems and storage;\nWrite programme with DB for HPC daily operations; and\nPerform any other duties as assigned.\nRequirements\nAn Associate Degree/Higher Diploma/Diploma or equivalent;\nAt least 2 years\u2019 post-qualification working experience;\nBeing reliable, self-motivated, detail-oriented, communicative with strong sense of ownership, analytical, problem solving and interpersonal skills;\nAbility to work independently; and\nGood command of written and spoken English and Chinese are required;\nKnowledge of MySQL; and\nSophisticated Linux shell skills and scripting languages (e.g. csh, Bash, Awk, perl, and Python) are preferred.\nSalary and Conditions of Service\n\nSalary offered will be highly competitive, commensurate with qualifications and experience.\u00a0 Fringe benefits include leave, medical and dental consultations at the campus clinic.\n\nInformation and Application\n\nFurther information on the post and the University is available at\u00a0http://www.cityu.edu.hk, or from the Human Resources Office, City University of Hong Kong, Tat Chee Avenue, Kowloon Tong, Hong Kong [Fax : 2788 1154 or 3442 0311].\u00a0\n\nTo apply, please submit an online application at\u00a0http://jobs.cityu.edu.hk. The closing date is\u00a021 January 2022. Applications will receive full consideration and only shortlisted applicants will be contacted.\u00a0 The University\u2019s privacy policy is available on the homepage.\n\nCity University of Hong Kong is an equal opportunity employer. We are committed to the principle of diversity. Personal data provided by applicants will be used for recruitment and other employment-related purposes.\n\nWorldwide recognition ranking #53 (QS survey 2022), and #4 among top 50 universities under age 50 (QS survey 2021); #1 in the World\u2019s Most International Universities (THE survey 2020); #1 in Engineering/Technology/Computer Sciences in Hong Kong (ARWU survey 2016); and #1 Business School in Asia-Pacific region (UT Dallas survey 2019).", "employment_types": ["Full Time", "Temporary"], "selling_points": ["An Associate Degree/Higher Diploma/Diploma", "At least 2 years\u2019 working experience", "Leave, medical and dental consultations"], "locations": ["Not Specified"], "categories": ["Information Technology (IT)", "Hardware", "Software Development", "Network & System"], "post_time": "2022-01-06T16:07:36Z", "salary": {"currency": null, "max": null, "min": null, "period": "monthly", "term": null}, "salary_visible": false, "title_keywords": ["assistant it officer"], "responsibilities": ["any other duties", "daily operations", "systems"], "requirements": {"degrees": ["associate degree", "diploma"], "majors": [], "languages": ["english", "chinese"], "language_level": ["good command"], "hard_skills": ["linux", "bash", "python", "problem solving", "csh", "awk", "perl"], "soft_skills": ["sophisticated", "self-motivated", "work independently", "detail-oriented", "problem solving", "interpersonal skills", "reliable"], "languages_combined": [{"language": "english", "language_level": ["good command"]}, {"language": "chinese", "language_level": ["good command"]}]}, "experience_required": {"duration": ["at least 2 years"], "field": ["post-qualification"]}}, {"job_id": "100003009012791", "location_code": "hk", "company": "Tech One Services Limited", "job_title": "Network Engineer", "description": "Job Description:\n\nAdminister, Monitor, maintain and optimize WAN, LAN, WIFI, Voice networks for optimal performance and maximum availability\nFacilitate in problem solving and collaboration\nProvide firmware updates for network devices\nEnsure network infrastructure complies with security policies\nPrepare and Update Network documentations and diagrams\n\nJob Requirements:\n\n\nHigher Diploma or Bachelor's Degree in any IT discipline\nMinimum 2 years of Network Admin related experience\nGood knowledge of the following, but not limited to firewall,\u00a0IP load balancer,\u00a0switches, router configuration\n\nGood oral, written and interpersonal communication skills to interact with both internal and external customers\nA passion for high customer satisfaction and achieving operational excellence\nCertifications: Cisco CCNA or CCNP or any network related course is preferable\n\n\n\nInterested parties, please send your detail resume and expected salary by email:\u00a0\u00a0talent(a)techone.com.hk\u00a0or by WhatsApp:\u00a0\u00a0https://wa.me/85263605600\n\n\n\nAll information gathered will be treated in strict confidence and used for recruitment related purposed only.", "employment_types": ["Full Time", "Permanent"], "selling_points": ["Network Admin and support", "Good at networking switches", "HD / Degree + 2 yrs above,"], "locations": ["Not Specified"], "categories": ["Information Technology (IT)", "Hardware", "Support", "Network & System"], "post_time": "2022-01-07T06:52:10Z", "salary": {"currency": null, "max": null, "min": null, "period": "monthly", "term": null}, "salary_visible": false, "title_keywords": ["engineer"], "responsibilities": ["network infrastructure", "policies", "maintain", "monitor"], "requirements": {"degrees": ["diploma", "degree", "bachelor"], "majors": ["it"], "languages": [], "language_level": [], "hard_skills": ["ccnp", "ccna", "router", "ip", "firewall"], "soft_skills": ["communication skills", "oral", "interpersonal", "passion for"], "languages_combined": []}, "experience_required": {"duration": ["minimum 2 years"], "field": ["related", "admin"]}}, {"job_id": "100003009027735", "location_code": "hk", "company": "Global Technology Integrator Ltd \u2013 GTI", "job_title": "Service Engineer / Trainee (Fresh graduates are also welcome)", "description": "\u00a0Job Description :\n\nTo support users and manage incidents covering head quarter and branches.\nProvide users with first call resolution upon their first time calls.\nInstalling, configuring and managing in computer hardware, software and printers\nDiagnosing and resolving both hardware and software issues.\nDaily system health check and data backup\nLog all incidents into logging system.\nResponsible for tracking and routing incident and requests.\n\n\u00a0Requirement :\n\nDiploma in computer science or related disciplines\nGood knowledge in PC hardware, printer, office equipment, networking and cable patching infrastructure\nExperience in supporting Windows XP, Windows 7, Office 2003, Office 2007, Office 2010 & Office 2013\nAbility to provide basic support to Active Directory and Windows Server 2003, Windows Server 2008, Windows 98, XP & Windows 7/8\n\nWe look forward to hearing from you! \u00a0Welcome to visit our website www.gti.com.hk.", "employment_types": ["Full Time"], "selling_points": ["Diploma in IT", "network and storage support", "fresh graduates willing to learn can be considered"], "locations": ["Ngau Tau Kok"], "categories": ["Information Technology (IT)", "Hardware", "Support", "Network & System"], "post_time": "2022-01-06T11:40:02Z", "salary": {"currency": null, "max": null, "min": null, "period": "monthly", "term": null}, "salary_visible": false, "title_keywords": ["service engineer", "trainee"], "responsibilities": ["software", "data", "resolution", "hardware", "configuring", "installing", "hardware and software issues", "tracking"], "requirements": {"degrees": ["diploma"], "majors": ["related disciplines", "computer science"], "languages": [], "language_level": [], "hard_skills": ["basic", "active directory", "windows 7", "hardware", "pc", "windows server"], "soft_skills": ["active"], "languages_combined": []}, "experience_required": {"duration": [], "field": []}}, {"job_id": "100003009032681", "location_code": "hk", "company": "Cyber World Creations (HK) Limited", "job_title": "IT Engineer / Technical Support", "description": "Job Description\n\nHandle user support services and provide technical advice to end users;\nCarry out operating system and application installation, administration and on-going support;\nSetup and support IT/AV equipment in all activities;\nProvide user training workshops for various systems;\nFollow up with the suppliers or vendors technical issues\nPerform other duties as assigned by the head of department;\nTesting new technology if necessary;\n\n\nRequirements\n\nHigher Diploma or above in Computer Science/ Information Technology or related disciplines;\nMin. 1 year of relevant working experience; Candidates will less experience will be considered as Technical Support;\nHave some experience in IT user support services and audio-visual equipment setup and operations;\nHave strong troubleshooting abilities;\nEager to learn new technology;\nHave strong sense of responsibility and able to work independently on projects as well as collaborate with the team.\nGood command of both English and Chinese, Putonghua is an advantage;\nImmediately available is preferred.\n\nWe offer attractive remuneration and benefits, 5 days per week, annual leave, medical scheme, comprehensive training and career development opportunities to the qualified candidates.\n\nPlease send your application with covering letter, full resume, current and expected salary and date of availability. Candidates without above information will not be considered.\n\nPlease click \"Apply Now\" to submit your application\n\nPersonal data collected will be used for recruitment purpose only.", "employment_types": ["Full Time", "Permanent"], "selling_points": ["5-day work week with flexible working hours", "Performance bonus; Comprehensive training", "Support IT/AV facilities; hard/software install"], "locations": ["Kwun Tong"], "categories": ["Information Technology (IT)", "Application Specialist - Software", "Hardware", "Support"], "post_time": "2022-01-07T14:30:54Z", "salary": {"currency": null, "max": null, "min": null, "period": "monthly", "term": null}, "salary_visible": false, "title_keywords": ["technical support", "engineer"], "responsibilities": ["installation", "perform other duties", "technical advice", "support services", "systems", "testing", "setup", "administration"], "requirements": {"degrees": ["higher diploma or above"], "majors": ["related disciplines", "computer science", "information technology"], "languages": ["putonghua", "english", "chinese"], "language_level": ["advantage", "good command"], "hard_skills": ["scheme"], "soft_skills": ["work independently", "sense of responsibility", "troubleshooting", "eager to learn", "comprehensive"], "languages_combined": [{"language": "putonghua", "language_level": ["advantage", "good command"]}, {"language": "english", "language_level": ["good command"]}, {"language": "chinese", "language_level": ["good command"]}]}, "experience_required": {"duration": ["1 year"], "field": ["it", "relevant working experience"]}}, {"job_id": "100003009027985", "location_code": "hk", "company": "Active Learning Solutions Limited", "job_title": "Project Coordinator / Assistant Project Coordinator", "description": "\u00a0Responsibilities\n\nCoordinate with internal and external parties for daily operation of the section\nAssist to install software and fixed ad-hoc technical problems\nWilling to work outside for on-site support and coordination.\u00a0\u00a0\nCandidate with less experience will be considered for the post of Assistant Project Coordinator\n\nRequirements:\n\nTertiary education in Computer Science, Information Technology or equivalent\nKnowledge on computer hardware, networking, systems and software applications\nKnowledge in MS SQL database is an advantage\nBasic knowledge on HTML and JavaScript\n\n\u00a0 \u00a0Interested parties please send full resume with expected salary and date of availability by clicking \"APPLY NOW\"\n\nShort-listed candidates will be notified for interviews. (Data collected would be used for recruitment purpose only.).", "employment_types": ["Full Time"], "selling_points": [], "locations": ["Lai Chi Kok"], "categories": ["Information Technology (IT)", "Hardware", "Support", "Network & System"], "post_time": "2022-01-07T00:50:08Z", "salary": {"currency": null, "max": null, "min": null, "period": "monthly", "term": null}, "salary_visible": false, "title_keywords": ["assistant project coordinator", "project coordinator"], "responsibilities": ["ad-hoc", "software", "internal and external parties", "daily operation", "coordinate with", "coordination"], "requirements": {"degrees": [], "majors": [], "languages": [], "language_level": [], "hard_skills": ["basic", "html", "hardware", "javascript", "ms sql"], "soft_skills": [], "languages_combined": []}, "experience_required": {"duration": [], "field": []}}, {"job_id": "100003009026226", "location_code": "hk", "company": "Ambition", "job_title": "IT Deskside Support (Contract)", "description": "RESPONSIBILITIES\n\n- Handle enquiry via Helpdesk Hotline, in person or email and provide technical support to both\nour internal users and agency.\n- Provide 1st level supports on hardware & software troubleshooting\n- Provide PC installation and software deployment\n- Log all incident and request cases on the call logging system and follow up its status\n- Escalate incidents and problems to relevant second-level support team or external service providers\n- Relocation for desktop items and maintains the correct inventory record\n- Handle ad hoc IT support duties as assigned\n- Standby support during non-working hours when required\n\nREQUIREMENTS\n\n- Higher Diploma in Information Technology or related disciplines\n- 3+ years of IT support experience in Banking/Finance\n- Good communication skill in English & Chinese\n\nInterested parties, please click \"APPLY NOW\" or send your application to karis.chan@ambition.com.hk\n\nIf this job isn't quite right for you, but you know someone who would be great at this role, why not take advantage of our referral scheme? We offer HKD1000 in Apple gift cards for every referred candidate who we place in a role. Terms & Conditions Apply. https://www.ambition.com.hk/refer-a-friend", "employment_types": ["Full Time", "Permanent"], "selling_points": ["Renewable contract", "Financial Services", "Deskside suppor"], "locations": ["Not Specified"], "categories": ["Information Technology (IT)", "Hardware", "Support", "Others"], "post_time": "2022-01-06T07:41:33Z", "salary": {"currency": null, "max": null, "min": null, "period": "monthly", "term": null}, "salary_visible": false, "title_keywords": [], "responsibilities": ["installation", "ad hoc", "software", "technical support", "handle enquiry", "troubleshooting", "inventory record", "hardware", "escalate incidents"], "requirements": {"degrees": ["diploma"], "majors": ["related disciplines", "information technology"], "languages": ["english", "chinese"], "language_level": ["good"], "hard_skills": [], "soft_skills": ["communication skill"], "languages_combined": [{"language": "english", "language_level": ["good"]}, {"language": "chinese", "language_level": ["good"]}]}, "experience_required": {"duration": ["3+ years"], "field": ["finance", "banking", "it support"]}}, {"job_id": "100003009031500", "location_code": "hk", "company": "AM730 Media Limited", "job_title": "Shift System Support (AWS)", "description": "Requirements:\n\nAWS and Drupal experience is a must\nPrevious experience in Media is preferable\nA good team player with strong analytical skills\nGood interpersonal and communication skills\n\nJob Duties:\n\n\nResponsible for all in-house technical support in hardware and software issues independently\nServer Admin (AD, Windows, Linux, VMWare, Storage)\nNetworking (Switch, Router, Firewall, VPN, Internet)\nOffice Application Support (Windows and Office)\nNight shift duty (Sun-Thur 14:00-23:00)\n\nOur company provide a\u00a0friendly\u00a0and cheerful\u00a0working environment.\u00a0 5-day work and attractive fringe benefits will offer to the right candidate.\u00a0You will work in a fast-paced team that encouragement of developing of new ideas.\u00a0Interested parties, please send your full CV stating your expected salary and availability to HR Department by email or click \"Apply Now\".", "employment_types": ["Full Time", "Permanent"], "selling_points": ["AWS Service Configure Management", "Drupal Website admin", "in-house technical support"], "locations": ["Wan Chai"], "categories": ["Information Technology (IT)", "Hardware", "Support", "Technical / Functional Consulting"], "post_time": "2022-01-07T09:29:12Z", "salary": {"currency": null, "max": null, "min": null, "period": "monthly", "term": null}, "salary_visible": false, "title_keywords": ["system support"], "responsibilities": ["technical support", "hardware and software issues"], "requirements": {"degrees": [], "majors": [], "languages": [], "language_level": [], "hard_skills": ["analytical skills", "aws"], "soft_skills": ["communication skills", "good team player", "interpersonal", "analytical skills"], "languages_combined": []}, "experience_required": {"duration": [], "field": ["media"]}}, {"job_id": "100003009023611", "location_code": "hk", "company": "City University of Hong Kong", "job_title": "Assistant IT Officer II in the Computing Services Centre (Appointment for 12 months)", "description": "Assistant IT Officer II in the Computing Services Centre (Appointment for 12 months)\u00a0[Ref. D/R/114/03]\n\nThe Computing Services Centre (CSC) at City University of Hong Kong manages the University\u2019s Information Technology infrastructure and services covering Data Centre Operations, Cloud and System Hosting, Research Computing and High-Performance Computing, Communication and Networking, Workspace and Audio-Visual Technologies, and other related IT functions to support the University\u2019s operations.\u00a0 The Centre has about 110 staff and contractors currently.\n\nDuties\nProvide onsite support on hardware and software including computer hardware repair, software problem solving and Windows OS installation;\nProvide IT technical consultation services; and\nPerform any other duties as assigned.\nRequirements\nAn Associate Degree/Higher Diploma/Diploma or equivalent in IT or related disciplines preferably with experience in IT support;\nAt least 2 years\u2019 post-qualification working experience;\nAdaptability to change and ability to work independently and as part of a team; and\nGood command of written and spoken English and Chinese are required.\nSalary and Conditions of Service\n\nSalary offered will be highly competitive, commensurate with qualifications and experience.\u00a0 Fringe benefits include leave, medical and dental consultations at the campus clinic.\n\nInformation and Application\n\nFurther information on the post and the University is available at\u00a0http://www.cityu.edu.hk, or from the Human Resources Office, City University of Hong Kong, Tat Chee Avenue, Kowloon Tong, Hong Kong [Fax : 2788 1154 or 3442 0311].\u00a0\n\nTo apply, please submit an online application at\u00a0http://jobs.cityu.edu.hk. The closing date is\u00a021 January 2022. Applications will receive full consideration and only shortlisted applicants will be contacted.\u00a0 The University\u2019s privacy policy is available on the homepage.\n\nCity University of Hong Kong is an equal opportunity employer. We are committed to the principle of diversity. Personal data provided by applicants will be used for recruitment and other employment-related purposes.\n\nWorldwide recognition ranking #53 (QS survey 2022), and #4 among top 50 universities under age 50 (QS survey 2021); #1 in the World\u2019s Most International Universities (THE survey 2020); #1 in Engineering/Technology/Computer Sciences in Hong Kong (ARWU survey 2016); and #1 Business School in Asia-Pacific region (UT Dallas survey 2019).", "employment_types": ["Full Time", "Temporary"], "selling_points": ["An Associate Degree/Higher Diploma/Diploma", "At least 2 years\u2019 working experience", "Leave, medical and dental consultations"], "locations": ["Wong Tai Sin Area"], "categories": ["Information Technology (IT)", "Hardware", "Software Development", "Network & System"], "post_time": "2022-01-06T16:07:37Z", "salary": {"currency": null, "max": null, "min": null, "period": "monthly", "term": null}, "salary_visible": false, "title_keywords": ["assistant it officer"], "responsibilities": ["any other duties", "installation", "software", "hardware", "repair"], "requirements": {"degrees": ["associate degree", "diploma"], "majors": ["related disciplines", "it"], "languages": ["english", "chinese"], "language_level": ["good command"], "hard_skills": [], "soft_skills": ["work independently", "adaptability"], "languages_combined": [{"language": "english", "language_level": ["good command"]}, {"language": "chinese", "language_level": ["good command"]}]}, "experience_required": {"duration": ["at least 2 years"], "field": ["related", "it", "post-qualification", "it support"]}}, {"job_id": "100003009027608", "location_code": "hk", "company": "Manpower Services (Hong Kong) Limited", "job_title": "System Engineer / IT Engineer (Up to 35K)", "description": "Duties:\n\nTo be in charge for the on-going system maintenance support to servers of different hardware and different operating system platforms (Including Windows, Linux, vSphere, Hyper-V)\nTo perform regular Windows Patching and software delivery through Microsoft SCCM\nTo monitor the servers\u2019 healthiness, resources utilization, different kinds of servers like Java, Oracle DB, Microsoft SQL DB and etc.\nTo evaluate impact of server software installation, distribution, patching and updating;\nTo co-ordinate with database teams, application teams and vendors for proper scheduling of system installation and maintenance works;\nTo provide first-line and second-line standby on-call support of servers\nTo assist IT team to handle administration works such as documentation, procurement, hardware / software inventory updating, bill payment and filling.\n\nRequirements:\n\nHolder of Diploma / Higher Diploma OR relevant degree, preferably in Information Technology, Computer Science, Information Systems or related disciplines.\nAt least 3 years relevant experience is preferred\nFamiliar with PC/Server hardware, software support and basic network setup\nGood communication and skills, both written and verbal, in Chinese or English\nGood coordination skills in handling tasks with team members and other parties", "employment_types": ["Contract"], "selling_points": ["5-days work", "Attractive remuneration package", "3 years of working experience in IT Field"], "locations": ["Tsuen Wan Area"], "categories": ["Information Technology (IT)", "Hardware", "Support", "Network & System"], "post_time": "2022-01-06T10:35:47Z", "salary": {"currency": null, "max": null, "min": null, "period": "monthly", "term": null}, "salary_visible": false, "title_keywords": ["system engineer", "engineer"], "responsibilities": ["installation", "software", "maintenance", "co-ordinate with", "maintenance support", "inventory", "monitor", "teams", "evaluate", "hardware", "scheduling", "payment", "database", "documentation", "administration"], "requirements": {"degrees": ["diploma", "degree"], "majors": ["related disciplines", "computer science", "information technology"], "languages": ["english", "chinese"], "language_level": ["good"], "hard_skills": ["server", "pc", "basic", "hardware"], "soft_skills": ["communication", "coordination skills"], "languages_combined": [{"language": "english", "language_level": ["good"]}, {"language": "chinese", "language_level": ["good"]}]}, "experience_required": {"duration": ["at least 3 years"], "field": ["relevant experience"]}}, {"job_id": "100003009029054", "location_code": "hk", "company": "City University of Hong Kong", "job_title": "IT Engineer/IT Officer in the Computing Services Centre [Ref. D/288/03]", "description": "The Computing Services Centre (CSC) at City University of Hong Kong manages the University's Information Technology infrastructure and services covering Data Centre Operations, Cloud and System Hosting, Research Computing and High-Performance Computing, Communication and Networking, Workspace and Audio-Visual Technologies, and other related IT functions to support the University's operations. The Centre has about 110 staff and contractors currently.\n\nDuties\nInstall, configure and maintain Solaris UNIX and LINUX operating systems, analyse and resolve problems for the systems (including both software and hardware platforms);\nWork with the data centre team on the monitoring and regular maintenance of the Solaris UNIX and LINUX related infrastructure;\nSet up and maintain Solaris UNIX and LINUX user accounts and access management systems, responding to user requests and software errors;\nWork with the Senior Scientific Officer in managing the High-Performance Computing (HPC) Research Computing services, provide technical assistance and consultation on the use of the HPC platforms, and perform system performance analysis and benchmarks;\nKeep abreast of the latest Solaris UNIX, LINUX and HPC related technologies and development by attending relevant global conferences; and\nPerform any other duties as assigned.\nRequirements\nA Bachelor\u2019s degree in Computer Science/Physics/Biology or related disciplines, with at least 5 years\u2019 post-qualification working experience;\nExperience in configuring Solaris UNIX and LINUX security baseline using CIS benchmarks;\nGood knowledge of the Solaris UNIX and LINUX account lifecycle management, operating systems, storage environments, file systems, and network protocols;\nLinux shell skills and scripting languages (e.g. csh, Bash, Awk, perl, and Python);\nKnowledge of networking and storage principles (including routing, subnets, TCP/IP, VLANs, NFS, etc.);\nEffective management of multiple projects concurrently while maintaining a keen eye for details;\nWillingness to communicate with users in different disciplines;\nProactive, eager to learn and well-organized with a strong sense of responsibility;\nStrong analytical, good interpersonal and communication skills;\nAdaptability to change, ability to work independently and as a team and under pressure; and\nGood command of written and spoken English and Chinese are required.\n\nCandidates with\u00a0less experience will be considered as IT Officer.\n\nShortlisted candidates will be invited for a written test.\n\n(Those who have responded to the previous advertisements need not re-apply.)\n\nSalary and Conditions of Service\n\nRemuneration package will be highly competitive, commensurate with qualifications and experience.\u00a0 Appointment will be made on a fixed-term contract; fringe benefits include gratuity, leave, medical and dental schemes.\n\nInformation and Application\n\nFurther information on the posts and the University is available at\u00a0http://www.cityu.edu.hk, or from the Human Resources Office, City University of Hong Kong, Tat Chee Avenue, Kowloon Tong, Hong Kong [Fax : 2788 1154 or 3442 0311].\u00a0\n\nTo apply, please submit an online application at\u00a0http://jobs.cityu.edu.hk.\u00a0Applications will be reviewed on a continuing basis until the positions are filled.\u00a0\u00a0Applications will receive full consideration and only shortlisted applicants will be contacted.\u00a0 The University\u2019s privacy policy is available on the homepage.\n\nCity University of Hong Kong is an equal opportunity employer. We are committed to the principle of diversity. Personal data provided by applicants will be used for recruitment and other employment-related purposes.\n\nWorldwide recognition ranking #53 (QS survey 2022), and #4 among top 50 universities under age 50 (QS survey 2021); #1 in the World\u2019s Most International Universities (THE survey 2020); #1 in Engineering/Technology/Computer Sciences in Hong Kong (ARWU survey 2016); and #1 Business School in Asia-Pacific region (UT Dallas survey 2019).", "employment_types": ["Full Time", "Contract"], "selling_points": ["Gratuity, leave, medical and dental schemes", "Install, configure and maintain UNIX and LINUX", "Bachelor\u2019s degree in Computer Science"], "locations": ["Not Specified"], "categories": ["Information Technology (IT)", "Hardware", "Software Development", "Network & System"], "post_time": "2022-01-07T03:52:18Z", "salary": {"currency": null, "max": null, "min": null, "period": "monthly", "term": null}, "salary_visible": false, "title_keywords": ["engineer", "it officer"], "responsibilities": ["any other duties", "management", "software", "maintenance", "data", "analysis", "systems", "monitoring", "infrastructure", "hardware", "conferences", "maintain", "technical assistance", "operating systems", "analyse"], "requirements": {"degrees": ["degree", "bachelor"], "majors": ["related disciplines", "biology", "computer science", "physics"], "languages": ["english", "chinese"], "language_level": ["good command"], "hard_skills": ["linux", "tcp", "bash", "python", "ip", "csh", "awk", "perl"], "soft_skills": ["communication skills", "work independently", "under pressure", "sense of responsibility", "keen", "well-organized", "eager to learn", "adaptability", "proactive", "interpersonal"], "languages_combined": [{"language": "english", "language_level": ["good command"]}, {"language": "chinese", "language_level": ["good command"]}]}, "experience_required": {"duration": ["at least 5 years"], "field": ["related", "it", "post-qualification", "security"]}}, {"job_id": "100003009023335", "location_code": "hk", "company": "The Boys' and Girls' Clubs Association of Hong Kong", "job_title": "System Administrator - IT Department", "description": "Responsibilities:\n\nProvide users technical support and conduct troubleshooting on hardware, software, other computer services\nAdminister and Monitor tasks for Servers (Windows & Linux), MSSQL, Active Directory, Firewall, Switch, VPN, VDI, Data Center, including but not limited to server data backup and restore\nCloud platforms Administrative Monitoring Management (e.g., Office365, Azure / AWS)\nVMware on Hyper Converged Infrastructure maintenance\nManage the IT inventory for hardware & software, and other IT related services\nDocumentation of system, network, and IT infrastructure\nLiaise and coordinate with vendors and suppliers\nEvaluate new technologies and platforms to determine applicability to resolve business challenges\nPerform ad hoc duties as assigned\n\n\u00a0Requirements:\n\nHigher Diploma holder in Computing or Information Technology related disciplines\nAt least 5 years of System administration experience\nHands-on experience in Windows & Linux Server, database (MSSQL, MYSQL) O365, VMWare ESXi, Firewall, networking, server, backup & recovery solution\nKnowledge in IT Security will be an advantage\nResponsible and able to work independently\n\nPlease apply with detailed resume and the application form with e-mail address and expected salary to the Human Resources Department, The Boys\u2019 & Girls\u2019 Clubs Association of Hong Kong, 7/F., 3 Lockhart Road, Wanchai, Hong Kong or by clicking \u2018Apply Now'\u00a0by 16th\u00a0Jan, 2022.\n\nRemarks:\nThe Association is a non-governmental organization which provides professional service for children and youth. With effect from December 1, 2011 staffs are required to complete and pass the Sexual Conviction Record Check\nWe are an equal opportunities employer\nApplication form can be downloaded from our website: http://www.bgca.org.hk\nPersonal data collected will be treated in strict confidence and used exclusively for recruitment purpose.", "employment_types": ["Full Time"], "selling_points": [], "locations": ["Wan Chai"], "categories": ["Information Technology (IT)", "Hardware", "Support", "Network & System"], "post_time": "2022-01-06T16:07:52Z", "salary": {"currency": null, "max": null, "min": null, "period": "monthly", "term": null}, "salary_visible": false, "title_keywords": ["system administrator"], "responsibilities": ["liaise", "software", "active directory", "data", "troubleshooting", "ad hoc duties", "it infrastructure", "computer services", "monitor", "infrastructure", "it inventory", "management", "monitoring", "coordinate with", "documentation", "maintenance", "technical support", "evaluate", "hardware"], "requirements": {"degrees": ["higher diploma holder"], "majors": ["related disciplines", "information technology"], "languages": [], "language_level": [], "hard_skills": ["linux", "o365", "vmware", "mssql", "firewall", "server"], "soft_skills": ["work independently", "confidence", "responsible", "hands-on", "detailed"], "languages_combined": []}, "experience_required": {"duration": ["at least 5 years"], "field": ["database", "administration"]}}, {"job_id": "100003009034668", "location_code": "hk", "company": "Wellesley Associates Limited", "job_title": "Senior Manager, Network Infrastructure - Financial Services/Inhouse \u2013 65-75+K + 2-3 months Bonus", "description": "Background:\u00a0My client is one of the top-tier financial services firms in Hong Kong who is now looking for an experienced Senior Network Manager to join their team.\n\nDuties\n\n\nHave overall responsibility for the development and on-going management and support of Group IT Network Infrastructure\nTo build a deep understanding of key business areas around the region to plan, develop and implement Network infrastructure solutions that will deliver corporate and service specific objectives and meet the strategic priorities of the BU\nSupervise the Network Operation Support Team for Cloud infrastructure Integration, Migration and BAU Support.\nManage, design, and architect On-Premise and Cloud Network and Data Centre infrastructure\nEvaluates New IT Network products or services and suggests changes to existing products or services to better aide the end user\nSupport IT Network Infrastructure Setup & Network Integration/Separation of New business entity\nLiaise with IT application, infra and security architect on the technical development of converged solutions and process to enhance the operations of services\nLead a team with managers and Technical engineers to negotiate with vendors, auditors, consultants.\u00a0\nLead the Network Infrastructure team for management and support of Group IT Network and services availability, capacity and critical support for business system and ensure the service is meet SLA Standard\nLead the Network team to manage and support IT infrastructure projects\nLead the Network Operation Team to support the migration and operation support.\nEnsure the IT Network infrastructure are fulfil compliance/security requirement\nTechnical Evaluation of Network solution, latest technology and management tools on Cloud environment\nAssists in conducting DR Drill and BCP process\nAssist in Vendor and Contract Management to support IT Network infrastructure\n\nRequirements:\n\n\nDegree holder in Computer Science / Information Technology or equivalent with more than 15 years of relevant experience which 6-8 years in managerial level\nITIL foundation certification with relevant experience in this area\nHolder of professional qualification(s) preferred, e.g. Cisco, Checkpoint, Azure, AWS Certification, but not a must\u00a0\nSolid experience in network administration with Strong Knowledge in LAN/MAN/WAN/SD-WAN/Cloud Network Architecture (AWS & AWS), Micro-Segmentation Firewall, Router/Switch, Wireless LAN, VPN, IPS, WAF, SLB, Network Management, Performance Monitoring and Automation Tools\nStrong problem solving, management and analytical skills with in-depth knowledge of Regional Datacentre and Cloud Network Infrastructure, DR Management and Security.\nStrong knowledge on various vendor products such as Cisco, Checkpoint, Palo alto, Imperva, F5, Riverbed, Megaport, MPLS and SDWAN solution. (Either 2 of the following)\u00a0\nGood command of written English and Chinese; fluent in spoken English\n\nIf you are interested in this position, please apply online by submitting your latest CV in Word format including current & expected salary. Kindly note that only shortlisted candidates will be notified.", "employment_types": ["Full Time"], "selling_points": ["FS Group Level In-House", "Senior Manager, Network Infrastructure", "65-75K + 2-3 months Bonus"], "locations": ["Not Specified"], "categories": ["Information Technology (IT)", "Hardware", "Application Specialist - Network", "Network & System"], "post_time": "2022-01-10T03:53:40Z", "salary": {"currency": null, "max": null, "min": null, "period": "monthly", "term": null}, "salary_visible": false, "title_keywords": ["senior manager"], "responsibilities": ["network infrastructure", "management", "it infrastructure", "data", "operations", "infrastructure", "compliance", "contract management", "design", "develop", "lead a team", "network integration", "security requirement", "plan", "evaluation", "liaise with", "migration", "setup"], "requirements": {"degrees": ["degree holder"], "majors": ["computer science", "information technology"], "languages": ["english", "chinese"], "language_level": ["good command", "fluent"], "hard_skills": ["itil", "network administration", "network management", "azure", "switch", "vendor", "word", "aws", "router", "problem solving", "analytical skills", "sd-wan", "vpn", "firewall", "wan"], "soft_skills": ["problem solving", "interested in", "analytical skills"], "languages_combined": [{"language": "english", "language_level": ["fluent", "good command"]}, {"language": "chinese", "language_level": ["fluent", "good command"]}]}, "experience_required": {"duration": ["6-8 years", "15 years"], "field": ["network administration", "managerial", "management", "information technology", "relevant experience"]}}, {"job_id": "100003009028641", "location_code": "hk", "company": "T.S. Lines Limited", "job_title": "SYSTEM SUPPORT **FRESH GRAD, DOUBLE PAY+BONUS**", "description": "Job Description\n\nJob Responsibilities:\n\nResponsible for setup and provide supports to computer hardware, software application, printer, VC and AV equipment to our end users\nMaintain and administrate systems, database, Windows and Linux server, networking and website.\nCoordinate with HQ IT teams on network, application and infrastructure projects.\nMS AD, O365 and applications accounts\u2019 administration and support.\nProvide user guides and\u00a0training\u00a0to improve user experience of IT services\nTroubleshoot inhouse system user daily operation problems\n\nJob Requirements:\n\nBachelor's Degree OR Minimum 3 years of job-related experience required.\u00a0\n< FRESH GRADUATE ARE ALSO WELCOME! >\nGood command of written and spoken Cantonese, Mandarin and English\nImmediate available is preferred\n\n\u00a0Benefits:\n\nExcellent career prospects\nCompetitive salary + Double pay + Performance bonus\nMedical scheme\nMeal allowance + Mobile allowance\n10-14 days annual leave\nAlternative Saturday, Bank Holiday, Marriage Leave, Paternity Leave, Compassionate Leave\n\nWe offer attractive remuneration package and excellent career opportunities to the\u00a0right candidates. Interested parties please send your\u00a0full resume with availability, current and expected salary\u00a0by clicking \u2018Apply Now\u2019.\n\nTo retrieve more information, please visit to our official website at: www.tslines.com\u00a0\n<All the application will keep in confidential and for recruitment purpose only>", "employment_types": ["Full Time", "Permanent"], "selling_points": ["Double Pay + Bonus + Mobile Allowance + Medical", "Bachelor's Degree **OR** 3 yrs related experience", "Immediately available"], "locations": ["Ngau Tau Kok"], "categories": ["Information Technology (IT)", "Hardware", "IT Management", "Network & System"], "post_time": "2022-01-07T02:43:42Z", "salary": {"currency": null, "max": null, "min": null, "period": "monthly", "term": null}, "salary_visible": false, "title_keywords": ["system support"], "responsibilities": ["software", "systems", "coordinate with", "website", "teams", "infrastructure", "user experience", "hardware", "daily operation", "maintain", "troubleshoot", "database", "setup", "administration"], "requirements": {"degrees": ["degree", "bachelor", "fresh graduate"], "majors": [], "languages": ["cantonese", "english", "mandarin"], "language_level": ["good command"], "hard_skills": [], "soft_skills": [], "languages_combined": [{"language": "cantonese", "language_level": ["good command"]}, {"language": "english", "language_level": ["good command"]}, {"language": "mandarin", "language_level": ["good command"]}]}, "experience_required": {"duration": ["minimum 3 years"], "field": ["related"]}}, {"job_id": "100003009020547", "location_code": "hk", "company": "OT&P Healthcare", "job_title": "Technical Support", "description": "Job Responsibilities:\n\n\nResponsible for IT infrastructure, helpdesk, hardware and application support for offices and clinics\nPerform PC troubleshooting, software and hardware installation\nProvide basic end-user training\nAdministrate hardware and software procurement and inventory\nMonitor servers, systems health and routine system operations\nMaintain administrative records, perform analysis and troubleshooting of system servers, including review server event log for system problems, use active directory to setup / change user accounts\nAssist with covers, audits and any other duties as assigned by Management\nJob Requirements:\n\n\nHigher Diploma or above in Computer Studies or related discipline;\n2 years relevant working experience in IT support\nHands on experience in Active Directory, O365 VMware, FortiGate administration\nKnowledge of network technologies, TCP/IP, network and cyber security\nHolder of MCSE / CCNA is an advantage\nCustomer focus, good problem-solving skill, self-initiative and responsible\nGood command of spoken and written English and Chinese\nFresh graduate will also be considered\n\n\n\nPlease apply in confidence with full resume, expected salary and availability to the Human Resources Department, OT&P by emailing us via\u00a0 projob@ otandp.com\u00a0or\u00a0 by clicking \u201cApply Now\u201d button.\n\nThe information provided will be used for selection purpose only. All information of unsuccessful applicants will be destroyed within six months.", "employment_types": ["Full Time", "Permanent"], "selling_points": ["IT infrastructure, helpdesk, hardware support", "2 years relevant working experience in IT support", "Monitor servers, systems health and routine system"], "locations": ["Sheung Wan"], "categories": ["Information Technology (IT)", "Hardware", "Support", "Network & System"], "post_time": "2022-01-04T15:01:41Z", "salary": {"currency": null, "max": null, "min": null, "period": "monthly", "term": null}, "salary_visible": false, "title_keywords": ["technical support"], "responsibilities": ["installation", "any other duties", "management", "it infrastructure", "software", "active directory", "operations", "inventory", "systems", "monitor", "troubleshooting", "analysis", "review", "hardware", "hardware and software procurement", "maintain", "audits", "setup"], "requirements": {"degrees": ["higher diploma or above", "fresh graduate"], "majors": ["computer studies"], "languages": ["english", "chinese"], "language_level": ["good command"], "hard_skills": ["o365", "mcse", "vmware", "active directory", "tcp", "cyber security", "problem-solving", "ccna", "ip", "focus"], "soft_skills": ["confidence", "responsible", "problem-solving", "hands on", "self-initiative", "customer focus", "active"], "languages_combined": [{"language": "english", "language_level": ["good command"]}, {"language": "chinese", "language_level": ["good command"]}]}, "experience_required": {"duration": ["2 years"], "field": ["administration", "relevant working experience", "it support"]}}, {"job_id": "100003009017313", "location_code": "hk", "company": "Vocational Training Council", "job_title": "Technician (IT Services)", "description": "Various Operational Units\nRef. no : C/VOU/TECH(IT)/01/22-AP2\nMajor Duties :\n(a) To operate and maintain the PCs, servers and networking equipment;\n(b) To install and manage software / OS for PCs and servers;\n(c) To provide IT-related technical support for staff and / or students;\n(d) To take charge of day-to-day system maintenance;\n(e) To design and maintain the campus websites, and assist in developing web-based application;\n(f) To compile system reports, update operation documents and guidelines;\n(g) To assist in the procurement and inventory control of relevant stores, software licenses and consumables; and\n(h) To assist in photo and video taking, production of VCD / DVD, graphic design and desktop publishing work, where necessary, in some operational units.\nRequirements :\n(a) (i) A recognized higher diploma in a relevant discipline, plus 1 year\u2019s relevant work experience; OR\n(ii) A recognized diploma or higher certificate in a relevant discipline, plus at least 2 years\u2019 relevant work experience;\n(b) Good knowledge of operation, maintenance and troubleshooting of computer hardware and networking;\n(c) Experience in using Windows PC and Mac;\n(d) Experience / knowledge / skills in some of the following areas will be an advantage:\n(i) Administration of Windows, Linux Server and VM Enterprise Server;\n(ii) Microsoft, Adobe and other common computer / educational software;\n(iii) LAN / WAN technology and TCP / IP;\n(iv) Website development and web programming using languages / software such as Dreamweaver, Flash, RESTful API, AJAX, JavaScript, SQL, .NET, PHP, Java, ASP, HTML and / or CSS; and\n(v) Computer graphics design and video editing;\n(e) Ability to work independently and be a good team player; and\n(f) Good interpersonal and communication skills.\nNotes :\n(1) Appointees may be required to perform shift duties or work in irregular working hours and at different work locations on a need basis.\n(2) In support of the Sexual Conviction Record Check (SCRC) Scheme launched by the Hong Kong Police Force, all prospective appointees who will be posted to Shine Skills Centres will be requested to undergo the SCRC at the advanced stage of the employment process.\nApplication Procedures :\nA completed application form [VTC-1 (Rev. 1/2018)], together with a full curriculum vitae, should be sent to the Human Resources Division by email via \"Apply Now\". Please specify in the subject of the email the reference of the post being applied for.\nCandidates who would like to submit their applications through email are requested to take note of points (1) \u2013 (4) below:\n(1) Completed application form (VTC-1) and detailed curriculum vitae (CV) should be provided in PDF format with total file size below 10MB.\n(2) Attachment(s) to the application by email should be saved with names as\n(a) VTC1-TECH-IT-\u201cyour surname and given name\u201d, e.g. \u201cVTC1-TECH-IT-CHAN Tai Man.pdf\u201d; and\n(b) CV-TECH-IT-\u201cyour surname and given name\u201d, e.g. \u201cCV-TECH-IT-CHAN Tai Man.pdf\u201d.\n(3) For the email subject, please cite \u201cApplication for the Post of Technician (IT Services) (Ref. No.: C/VOU/TECH(IT)/01/22-AP2)\u201d.\n(4) Original and copy of other supporting documents are to be provided at a later stage upon request.\nClosing date for application: 16 January 2021\nApplicants not invited for interview within 10 weeks from the closing date may consider their applications unsuccessful.\nThe Council reserves the right not to fill the post(s).\nPersonal data collected will be used for recruitment purposes only. Information on unsuccessful candidates will normally be destroyed 12 months after the completion of the recruitment exercise.", "employment_types": ["Full Time"], "selling_points": ["Recognized higher diploma", "1 year\u2019s relevant work experience", "To install and manage software / OS"], "locations": ["Not Specified"], "categories": ["Information Technology (IT)", "Hardware", "Support", "Network & System"], "post_time": "2022-01-03T13:02:53Z", "salary": {"currency": null, "max": null, "min": null, "period": "monthly", "term": null}, "salary_visible": false, "title_keywords": ["technician"], "responsibilities": ["software", "maintenance", "technical support", "guidelines", "graphic design", "pcs", "developing", "design", "maintain", "reports", "inventory control", "desktop publishing", "software licenses"], "requirements": {"degrees": ["diploma", "higher certificate"], "majors": [], "languages": [], "language_level": [], "hard_skills": ["plus", "web", "video editing", "adobe", "flash", "server", "wan", "graphics", "java", "tcp", "ajax", "restful api", "html", "sql", "c", "javascript", "pc", "linux", "maintenance", "php", "hardware", "ip", "programming", "dreamweaver", "css"], "soft_skills": ["communication skills", "good team player", "work independently", "troubleshooting", "interpersonal"], "languages_combined": []}, "experience_required": {"duration": ["at least 2 years", "1 year"], "field": []}}]