[{"job_id": "100003009053547", "location_code": "hk", "company": "Plaza Premium Group", "job_title": "Internal Audit Manager (IT Audit)", "description": "The Job\n\nA regional audit position that will execute and lead IT audit engagements, in areas covering IT general controls, application controls, IT infrastructure and IT security, system implementation and project management controls\nAble to assess business impact of IT risks and independently evaluate control efficiency and effectiveness\nSuggest practical and value-added recommendations to management for risk mitigation and process improvement\nProduce reports with audit findings and recommendations in a timely manner, and follow-up on audit findings to ensure implementation of audit recommendations\nProvide business partnering advice to stakeholders on strengthening IT control environment\nSupport Head of IT Audit in preparation of annual audit plan, regular reporting and half-yearly Audit Committee preparation\n\nThe Person\n\nBachelor degree holder in Information Technology, Computer Science or other related disciplines\nRelevant professional qualifications (e.g. CIA, CISA, and CISSP) are preferred\nAt least 2 years' experience in IT or Audit field, preferably in the Retail industry\nExperience working in IT Audits / IT Risk Advisory within a Big Four will be an advantage\nPractical experience and knowledge in IT risk, IT general controls, IT security and IT system implementation / transformation\nProficiency in any data analytical tools will be an advantage (e.g. ACL, Python, SQL, Tableau)\nStrong analytical, project management, communication and presentation, problem solving and leadership skills. Able to work independently and together as a team player\nGood command of both written and spoken English and Chinese\n\nDFI Retail Group is an equal opportunity employer and responsible for ensuring that all personal information collected from each Candidate presented to DFI Retail Group is used for recruitment purposes only and the personal data will be kept and handled confidentially. We will retain the applications of candidates not selected for a period of no more than 24 months. The data collection process is in accordance with all applicable laws and compliant with the Code of Practice on Human Resource Management.\n\nTo find out more about Our Businesses and Our People, please visit our website: https://www.DFIretailgroup.com\n\n\u00a0\nIssued by The Dairy Farm Company, Limited", "employment_types": ["Full Time", "Permanent"], "selling_points": ["Develop risk-based IT audit plan", "Sound understanding of IT applications", "Candidates with Big 4 experiences are welcome"], "locations": ["Airport Area"], "categories": ["Information Technology (IT)", "IT Auditing"], "post_time": "2022-01-17T07:08:17Z", "salary": {"currency": null, "max": null, "min": null, "period": "monthly", "term": null}, "salary_visible": false, "title_keywords": ["manager"], "responsibilities": ["reporting", "control", "management", "it infrastructure", "annual audit", "a timely manner", "implementation", "audit", "evaluate", "project management", "reports", "plan"], "requirements": {"degrees": ["bachelor degree holder"], "majors": ["related disciplines", "computer science", "information technology"], "languages": ["english", "chinese"], "language_level": ["good command"], "hard_skills": ["no", "professional qualifications", "tableau", "python", "sql", "project management", "problem solving", "system implementation", "code"], "soft_skills": ["work independently", "responsible", "leadership skills", "communication", "project management", "problem solving", "team player", "presentation"], "languages_combined": [{"language": "english", "language_level": ["good command"]}, {"language": "chinese", "language_level": ["good command"]}]}, "experience_required": {"duration": ["at least 2 years"], "field": ["retail industry", "audit", "big four", "it", "security"]}}, {"job_id": "100003009054850", "location_code": "hk", "company": "KPMG", "job_title": "Senior Consultant, Information Risk Management, IT Audit", "description": "About the Company\n\nHello! Welcome to Plaza Premium Group, we're people passionate about \"Making Travel Better\". We are a global company with team members from all walks of life, together we are\u00a0#PPGFamily, together we are building a legacy. You don't need to be from this industry, you do need to be passionate.\n\nOur promise to you:\n\nWe will respect and value your background and perspectives\nWe will work together with integrity\nWe will share our incredible pride for job, company and industry\nWhat we ask of you: bring passion to all that you do\nListen, move fast and think innovatively\nSpeak up, have ideas and share them\nBelieve in customer service, and treating every person with kindness\n\nAs industry leaders in innovating global airport hospitality you will work with colleagues from all parts of the world for a truly global experience. You will help and craft services and facilities in over 200 locations in more than 60 international airports across the world.\n\nWho we are\n\nWe were established in HK in 1998 by someone who understood the value of an airport lounge and felt that the experience shouldn't just be limited to a closed-circuit group of travelers. Through the years we have worked incredibly hard to create an experience which is both accessible and quality. Almost 25 years later we now span four core business segments: airport lounges, airport terminal hotels, airport meet & greet services, and a range of airport dining concepts.\n\nIn addition to our own brands, PPG provides airport hospitality solutions to leading airlines, alliances and corporates around the world. Here are a few names you might recognize: Cathay Pacific Airways, Singapore Airlines, Lufthansa etc.\n\nWith the future of travel always in sight, we created Smart Traveler, a mobile-app rewards program underpinned by in-house technology. We are fast-moving and always evolving to drive our purpose of making travel better.\n\nJoin our family today.\n\nTogether, we'll make travel better.\n\n\n\nWhat you'll be doing:\n\nThis is a varied and challenging role where you will be working within a multi-cultural environment, able to input, collaborate with different global teams within the group. The individual will be reporting to the Group Director, Internal Audit & Process Re-engineering while working independently for the delegated business coverage. Some of the duties are:\n\nDevelop IT audit framework based on the IT environment of the Group.\nInitiate, plan and execute the IT audit of the Group under the IT audit framework.\nPlans, monitors, conducts and leads the IT related internal audit assignments including IT general controls, system implementation, change management, cyber and data security risk-based audit, and IT advisory projects and etc.\nIndependently evaluate system controls, document audit results, make recommendations for value efficiency and effectiveness improvement.\nCollaborate with all departments to help drive change and adopt changes in working practices to become more efficient.\nPrepare internal audit reports and perform follow-up and monitoring works to ensure proper implementation of recommendations.\n\nAbout You:\n\nThe ideal candidate will have the ability to work in a diversified, fast-paced and collaborative environment with good problem-solving attitude and business acumen\n\nBachelor's Degree in Accounting/Finance or relevant disciplines with professional qualifications.\n6+ years of internal and/or external audit experience.\nKnowledge in GDPR and ISO 2001.\nUniversity graduate in Finance and Accounting, IT or related discipline.\nCertified as a CPA, CIA, CISA, CISM or CISSP designation is preferable.", "employment_types": ["Full Time"], "selling_points": ["Experience in IT audit and assurance engagement", "Recognised relevant qualification (e.g. CISA)", "Knowledge of systems environments within industry"], "locations": ["Central"], "categories": ["Information Technology (IT)", "IT Auditing"], "post_time": "2022-01-17T11:46:29Z", "salary": {"currency": null, "max": null, "min": null, "period": "monthly", "term": null}, "salary_visible": false, "title_keywords": ["senior consultant"], "responsibilities": ["customer service", "ideas"], "requirements": {"degrees": [], "majors": [], "languages": [], "language_level": [], "hard_skills": ["airports"], "soft_skills": ["passionate", "customer service", "integrity", "passionate about"], "languages_combined": []}, "experience_required": {"duration": [], "field": []}}, {"job_id": "100003009051477", "location_code": "hk", "company": "BDO", "job_title": "Senior Associate / Associate - IT Audit (Ref : RAS)", "description": "In KPMG\u2019s Audit practice, we place Information Risk Management (IRM) at the heart of our Audit process and recognize the vital role that Information Technology plays for both our clients and the effectiveness of Audit as a function. Our team in Hong Kong represents a dynamic and enthusiastic team that always pushes itself to succeed.\u00a0\n\nIRM specialists assist engagement teams in determining the effect of information technology (IT) related risks on the audit, understanding these risks in relation to the IT control environments over the relevant financial reporting related applications and platforms, and determining an audit approach to respond to the risk of material misstatement as a result of the IT risks relevant to the financial statement audit. Our professionals do this by leveraging our strong industry, IT control and technology focus and experience; deploying leading methodologies and tools; applying our objectivity; using a balanced approach to growth and risk; utilizing our comprehensive global breadth and local knowledge; and calling upon our deep understanding of relevant business, financial, and regulatory inter-dependencies.\n\nWe are now seeking a Senior Consultant\u00a0to join the team. The role is client-focused and involves planning, supervising and delivering IT audit and assurance-based engagements for clients, with a focus on audit quality. The role entails being responsible for completing all aspects of the engagement lifecycle, including engagement execution and delivering, supervision and coaching of junior staff, transferring technical knowledge, writing reports, and communicating with engagement partners. The role also has operational accountability and responsibility for the quality of the work in performing information technology audit assistance work.\n\n\n\nResponsibilities\n\nPlan and execute the day-to-day activities of IT audit and assurance engagements, with a focus on audit quality and audit innovation\nSupport the Engagement manager with scoping, financial management, delivery of risk management activities and identification and communication of IT audit findings\nIdentify and use the most appropriate IRM technology tools to complete and document audit work\nAssist with scoping, financial management, delivery risk management and the initial review of deliverables\nConduct fieldwork and manage small project teams to deliver value-added assurance services to clients\nIdentify and communicate IT audit findings to senior management and clients\nHelp identify performance improvement opportunities for assigned clients\nComplete task and deliverables to a high quality standard as part of the audit \u2013 working to an agreed plan, budge and quality\nKeep senior IRM members informed of significant developments and progress on the engagement\u00a0\nCoach junior staff on engagements and provide proper feedback\nDevelop internal networks and maintain excellent relationships with colleagues across KPMG\nPromote a collaborative culture encouraging constructive working relationships with the audit team and others\n\nRequirements\n\nTwo years\u2019 experience in any of the following areas: internal or external IT audit, risk assessment or business process reengineering\nProven experience of successfully delivering IT audit and assurance services (including external/internal audits) to clients within a Big Four firm (or)\nExperience in business analysis and understanding of core business processes within industry sectors\nExperience of systems environments within industry sectors\nRecognized relevant qualification (e.g. CISA or HKICPA)\nBachelor\u2019s/Master\u2019s degree in an appropriate field from an accredited college/university\nExcellent written and verbal communication skills in English and Chinese (Mandarin or Cantonese) and exceptional interpersonal skills; able to gain the confidence and respect of senior level executives\nAbility to identify and assess complex IT risks and controls, to relate them to the wider business environment\nExcellent reporting and presentation skills and ability to express opinion clearly\nAbility to deliver work within tight timelines, on budget and at a high level of quality\nStrong teamwork ability and able to work independently", "employment_types": ["Full Time", "Permanent"], "selling_points": ["Responsible for IT general/ application controls", "At least 1 year of experience", "Excellent Career Prospect"], "locations": ["Sheung Wan"], "categories": ["Accounting", "Audit", "Information Technology (IT)", "IT Auditing", "Security"], "post_time": "2022-01-16T03:49:19Z", "salary": {"currency": null, "max": null, "min": null, "period": "monthly", "term": null}, "salary_visible": false, "title_keywords": ["senior associate", "associate"], "responsibilities": ["management", "review", "quality", "audit", "teams", "develop", "communication", "maintain", "plan", "working relationships", "senior management"], "requirements": {"degrees": ["degree", "bachelor", "master"], "majors": [], "languages": ["cantonese", "english", "chinese", "mandarin"], "language_level": ["excellent"], "hard_skills": ["analysis", "hkicpa"], "soft_skills": ["communication skills", "work independently", "confidence", "teamwork", "presentation skills", "interpersonal skills", "business environment"], "languages_combined": [{"language": "cantonese", "language_level": ["excellent"]}, {"language": "english", "language_level": ["excellent"]}, {"language": "chinese", "language_level": ["excellent"]}, {"language": "mandarin", "language_level": ["excellent"]}]}, "experience_required": {"duration": ["two years"], "field": ["assurance", "audit", "big four", "business", "it", "business analysis"]}}, {"job_id": "100003009049358", "location_code": "hk", "company": "Shanghai Commercial Bank Ltd", "job_title": "Assistant Manager / Manager, IT Audit", "description": "Responsibilities:\n\nConduct IT audit over general/ application controls, network security, cybersecurity, blockchain platform operations, and apply Computer Assisted Auditing Technique (\"CAAT\") for data verification, cyber hacking incident investigation\nObtain good understanding of IT infrastructure, programs, networks and database, IT security, identify areas of improvement and make recommendations\nPrepare accurate documentation and high quality reports\nMaintain relationship with key client personnel, including management of listed companies, MNC or government departments\nUphold team spirit within the team\nSupport and act towards the BDO Global Vision\nBe committed to act with the firm\u2019s core values and competency expectations\n\n\u00a0Requirements:\n\nDegree holder major in IT, preferably computer science, computer and information security, cybersecurity or related disciplines\nAt least 1 year of experience in either IT Audit, IT Security, system implementation (e.g. ERP/banking system), cybersecurity, investigation of cyber hacking incidents, etc.\nQualified in or Participant of either CISA, CISSP, ISO27001, CEH, CISM or CHFI (Computer Hacking Forensic Investigator) are preferred but not a must\nExcellent command of written and spoken English, Cantonese and Mandarin\nAbility to successfully multitask while working independently or within a group environment\nAbility to work in a deadline-driven environment and willing to travel\nBe passionate for providing exceptional quality service and striving for exceeding clients\u2019 expectations\nPosition offered will commensurate with the experience of the right candidate\n\nWe are an equal opportunity employer, and offer excellent prospects and career development for the right candidate.\u00a0 Interested parties please send your application\u00a0with full career history, current and expected salary by clicking\u00a0Apply Now\u00a0button below.\u00a0\n\nApplications will be treated in strict confidence. Personal data collected will be used for recruitment purposes only.", "employment_types": ["Full Time", "Permanent"], "selling_points": ["Conduct IT audit assignments", "Identify and assess risk areas & Propose solutions", "Prepare reports with audit findings"], "locations": ["Kwun Tong"], "categories": ["Banking / Finance", "Others", "Information Technology (IT)", "IT Auditing", "Others"], "post_time": "2022-01-15T03:50:20Z", "salary": {"currency": null, "max": null, "min": null, "period": "monthly", "term": null}, "salary_visible": false, "title_keywords": ["assistant manager", "manager"], "responsibilities": ["make recommendations", "management", "data verification", "it infrastructure", "operations", "quality", "audit", "investigation", "maintain", "reports", "database", "documentation", "auditing"], "requirements": {"degrees": ["degree holder"], "majors": ["related disciplines", "it", "computer science"], "languages": ["cantonese", "english", "mandarin"], "language_level": ["excellent"], "hard_skills": ["system implementation", "erp"], "soft_skills": ["multitask", "independently", "driven", "passionate"], "languages_combined": [{"language": "cantonese", "language_level": ["excellent"]}, {"language": "english", "language_level": ["excellent"]}, {"language": "mandarin", "language_level": ["excellent"]}]}, "experience_required": {"duration": ["at least 1 year"], "field": ["it", "security", "audit"]}}, {"job_id": "100003009054247", "location_code": "hk", "company": "CHOW TAI FOOK JEWELLERY CO LTD", "job_title": "Assistant Manager (IT Project Management Office PMO)", "description": "Responsibilities:\n\nConduct IT audit assignments and review IT systems to assess adequacy and effectiveness of internal controls and systems security\nIdentify and assess risk areas and propose solutions to mitigate potential risks\nPrepare reports with audit findings and recommendations\nPerform follow-up review for proper implementation of audit recommendations\nAssist in developing and maintaining Computer Assisted Auditing Techniques (\u201cCAATs\u201d) Programs\nAssist in conducting ad-hoc projects as assigned\nRequirements:\n\nDegree holder in Computer Science, Information Technology or related disciplines\nProfessional qualifications of CISA, CISSP or equivalent\nMinimum 3 years of experience in IT audit or related fields in system securities, preferably in banking industry\nKnowledge of IT infrastructure, programming languages, network/application security and database management system controls\nWell-organized and independent with strong analytical ability and risk control sense\nGood people, communication and influencing skills\n(Candidates with less experience will be considered for the position of Assistant Manager, IT Audit)\n\n\nAttractive remuneration package will be offered to the right candidates. Interested parties please click \"Apply Now\" to submit your full resume with current and expected salary to the Human Resources Division.\n\nPlease visit us at www.shacombank.com.hk for more information about our Bank.\n\nAll personal data collected will be used for recruitment related purposes strictly in accordance with the Bank's personal data policies, a copy of which will be provided immediately upon request by contacting our Personal Data Compliance Officer. Applicants who are not contacted within two months may consider their applications unsuccessful and the personal data collected from the applicants will be retained for no longer than two years from the date of rejection during which the applicants may be considered for other suitable positions within the Bank.", "employment_types": ["Full Time", "Permanent"], "selling_points": ["IT Governance, Project Management, IT Compliance", "ServiceNow", "ScrumMaster, ITIL, PMP"], "locations": ["Kwai Hing"], "categories": ["Information Technology (IT)", "IT Auditing", "IT Project Management / Team Lead", "Others"], "post_time": "2022-01-17T08:56:58Z", "salary": {"currency": null, "max": null, "min": null, "period": "monthly", "term": null}, "salary_visible": false, "title_keywords": ["assistant manager"], "responsibilities": ["ad-hoc projects", "maintaining", "review", "systems", "audit", "implementation", "developing", "prepare reports", "auditing", "assess risk"], "requirements": {"degrees": ["degree holder"], "majors": ["related disciplines", "computer science", "information technology"], "languages": [], "language_level": [], "hard_skills": ["programming", "professional qualifications"], "soft_skills": ["communication", "independent", "well-organized"], "languages_combined": []}, "experience_required": {"duration": ["minimum 3 years"], "field": ["banking industry", "related", "audit", "it", "securities"]}}, {"job_id": "100003009047649", "location_code": "hk", "company": "Moore Associates Limited", "job_title": "Senior Associate / Associate (IT Audit)", "description": "What You Will Own\n\nConduct project performance analysis and reporting to IT senior management\nHarmonize IT teams to engage and deliver project initiatives within budget and timeline\nProvide both verbal and written communications regarding project status, benefit, risks and issues\nMonitor the impacts and interdependencies between demands and resources to ensure project delivery efficiency\nCommunicate with business leaders to manage multiple demands, identify and resolve conflicting issues\nDevelop and introduce best practice project delivery approach\nDrive process improvements and project governance\nEnsure governance procedures are adhered for all projects throughout their project life cycle\nLead and assist with the deployment and use of IT Project Management tools, methodologies and standards within IT Division\nPerform other ad-hoc projects and tasks as assigned\nWho Will Thrive\nDegree holders with at least 5 to 8 years\u2019 work experience in PMO and IT governance\nProficient in SDLC project management execution and business analysis experience\nPrevious experience in setting up PMO is an advantage\nExperience on PM Tools (e.g. ServiceNow, JIRA) and Data Analytics tools (e.g. PowerBI, Qlik) is an advantage\nCustomer-oriented and self-motivated with excellent communication skill\nSelf-manage, proactive, independent, efficient, able to work under pressure in vague and fast growing environment\nCandidates with less experience will be considered as Officer (IT PMO)\nGood command of written and spoken English and Chinese as well as Putonghua\nHolder of PMP or ScrumMaster certification would be definitely an advantage\n\n\nBenefits\n\n5-day work\nCompetitive salary, staff meal, medical and dental insurance, life insurance\nVarious types of leave, e.g. Family-friendly leave, self-development leave,\u00a0Examination leave, marriage leave, birthday leave, volunteer service leave, etc\n\nWe offer excellent career opportunities, attractive remuneration package & benefits to the right candidate.\u00a0Interested parties please apply by clicking \"Apply Now\" with a full resume stating the latest and expected salary.\n\nAll information collected will be used for recruitment purposes only.", "employment_types": ["Full Time", "Permanent"], "selling_points": ["IT audit engagements", "IT security compliance", "Vulnerability assessment"], "locations": ["Tsim Sha Tsui"], "categories": ["Banking / Finance", "Financial Services", "Information Technology (IT)", "IT Auditing", "Security"], "post_time": "2022-01-15T03:49:47Z", "salary": {"currency": null, "max": null, "min": null, "period": "monthly", "term": null}, "salary_visible": false, "title_keywords": ["senior associate", "associate"], "responsibilities": ["communicate with", "reporting", "analytics tools", "ad-hoc projects", "data", "analysis", "budget", "teams", "monitor", "procedures", "develop", "communication", "project management", "business analysis", "senior management", "work under pressure"], "requirements": {"degrees": ["degree"], "majors": ["it"], "languages": ["putonghua", "english", "chinese"], "language_level": ["good command"], "hard_skills": ["data analytics", "analysis", "project management", "sdlc", "deployment", "pmp"], "soft_skills": ["efficient", "self-motivated", "independent", "communication skill", "project management", "customer-oriented", "proactive", "work under pressure"], "languages_combined": [{"language": "putonghua", "language_level": ["good command"]}, {"language": "english", "language_level": ["good command"]}, {"language": "chinese", "language_level": ["good command"]}]}, "experience_required": {"duration": ["at least 5 to 8 years"], "field": ["business analysis", "project management", "it governance", "it"]}}, {"job_id": "100003009055567", "location_code": "hk", "company": "Hays", "job_title": "Manager - Technology Risk (up to 55k)", "description": "DEAR TALENT, YOUR MOVE!\n\nBeing the new rising airline since 2013, we are the Hong Kong\u2019s only Low Cost Carrier (LCC) offering you safe and flexible service options to Hong Kong and beyond.\n\nWe\u2019re on a mission to inspire you to be different, to shake things up, to inspire the spirit of adventure by bringing you to fascinating destinations that few others serve.\n\nSpread your wings and fly with us!\n\n\nWhat will you do?\u00a0\n\nConduct security risk assessment for new business initiatives and solutions;\nRegular review and apporve security guidelines and procedures to strengthen current Security Operation Framework;\nPerform threat management, threat modeling, identify threat vectors and develop use cases for security monitoring;\nResponsible in reviewing security incident Reports;\nFormulate and direct incident response efforts, prioritize those response efforts;\nDesign and conduct cyber-attack simulation to evaluate the effectiveness of cyber defences across different technology layers;\nEnhance company\u2019s cybersecurity maturity and situational awareness;\nPrepare reports, dashboards, metrics for SOC operations and presentation to Senior Management;\nManage execution of action plans to ensur safety and security of all IT assets;\nManage all aspects of outsourced Security Operation Center;\nDevelop security architecture, security policies, principles and standards;\nParticipate in Audits and help remediate the findings;\nAssist Data Protection Officer in enforcing data privacy requirements for IT systems;\nSupport for emergency, if any;\nOther ad-hoc duties as assigned.\n\nWe are a perfect match, if you are:\n\nBachelor Degree in Computer Science or IT related discipline;\nMinimum 6 years\u2019 working experience, with minimum 3 years\u2019 hands on experience in Information Security, Internal Control or Operations Risk;\nStrong understanding of vulnerability classes, networking protocols, operating systems, and cyber security concepts and technologies;\nExperience in Security Operations, SOC, SIEM, Incident Response, and Threat Intelligence is preferred\nExperience in Penetration testing and common vulnerability assessment tools, as well as, using MITRE ATT&CK or similar frameworks;\nFamiliar with various IT governance framework CobiT, PCI-DSS, NIST, ISO27001, ISO20000, ITIL respectively;\nPassion for cybersecurity and staying up-to-date with current threats, tools and techniques;\nPractical experience of technical and security configuration, operation and administration in Windows OS, Active Directory, Domain Group Policy, Networking, security devices (firewall, NAS, etc.) are essential;\nKnowledge of Cloud environments such as AliClould, Azure and GCP;\nPossess CISSP, CSX, CISA, CISM or other information systems security certifications preferred;\nAbility to communicate about various IT security measures with non-technical audience;\nDemonstrated ability to prioritize and meet scheduled deliverables and commitments while managing multiple tasks;\nAble to work on own initiative with minimal direction and handle multiple assignments independently;\nGood command in both written and spoken English and Chinese.\n\nYour Future Work Life?\n\nWork flexibly with staggered working hours and flexible workplace\nDress Casual and Smart everyday\nWork in a newly-designed office with open seating, stylish breakout areas, game room, gym and free coffee\u2026\nWork with a group of energetic and multicultural professionals (up to 50 nationalities!)\nHave great fun in Snack Friday, New Year Market, Fly with your Kids Day, Basketball Team\u2026\nHave your voice heard through Townhalls, Crew forums, CEO live sessions etc.\n\nWhat will you enjoy?\n\nFly anywhere we fly for free plus taxes during leisure with your friends and family\nSpecial privileges to buy duty free products\nCareer Express\n\n\n\nYou will be inspired by our core values.\nYou will be inspired by our vibrant, efficient and entrepreneurial spirit. Join our fun, collaborative and reliable team to ignite your dream!\n\n\n\nInterested? It\u2019s time to have YOUR MOVE!\nIf you're ready to embark your adventure, start by clicking the \u2018Apply now\u2019 and get on the plane to fly with HK Express!\u00a0", "employment_types": ["Full Time", "Permanent"], "selling_points": ["Information security", "1 & 2 LOD", "Banking"], "locations": ["Not Specified"], "categories": ["Information Technology (IT)", "IT Auditing", "IT Project Management / Team Lead", "Technical Writing"], "post_time": "2022-01-18T02:43:51Z", "salary": {"currency": "HKD", "max": 54999, "min": 45000, "period": "monthly", "term": null}, "salary_visible": true, "title_keywords": ["manager"], "responsibilities": ["business initiatives", "information security", "data", "cyber security", "operations", "active directory", "design", "regular review", "plans", "senior management", "penetration testing", "internal control", "administration", "configuration", "develop", "reports", "architecture", "operating systems", "cost", "management", "monitoring", "procedures", "security operation", "ad-hoc duties", "audits", "guidelines", "policies", "systems", "evaluate", "prepare reports"], "requirements": {"degrees": ["degree", "bachelor"], "majors": ["it", "computer science"], "languages": ["english", "chinese"], "language_level": ["good command"], "hard_skills": ["itil", "plus", "azure", "active directory", "cyber security", "fun", "airline", "safe", "os", "lcc", "firewall", "nas", "internal control"], "soft_skills": ["flexible", "initiative", "efficient", "independently", "responsible", "passion for", "multiple tasks", "collaborative", "prioritize", "energetic", "hands on", "reliable", "ad-hoc duties", "active", "presentation"], "languages_combined": [{"language": "english", "language_level": ["good command"]}, {"language": "chinese", "language_level": ["good command"]}]}, "experience_required": {"duration": ["minimum 6 years", "minimum 3 years"], "field": ["administration", "operation", "security", "testing"]}}, {"job_id": "100003009051478", "location_code": "hk", "company": "BDO", "job_title": "Manager / Senior Associate / Associate (IT Audit / Audit Analytics) - Assurance", "description": "Responsibilities:\n\n\nInvolve in IT governance reviews and technical assessments to evaluate system security and control effectiveness\nCarry out IT audit engagements, including but not limited to IT general control review, application controls and CAATs\nPlan and deliver IT security compliance, based on international IT security standards including but not limited ISO, NIST, COBIT etc.\nCarry out IT security review and auditing services, and perform on-going consultancy work\nAssist in preparing reports with audit findings and recommendations\nTake up other ad-hoc projects as required\u00a0\n\nRequirements:\n\n\nBachelor degree in Information Technology, Computer Science or related discipline\nExperience in IT audit, IT risk advisory, IT security, or related areas\nGood business acumen with knowledge of technology risk, cyber security, and information security\nProfessional qualification such as CISA, CISM, CISSP, CRISC, CIA, CEH holder is a plus but not a must\nCreative, innovative and well-organised personnel with strong communication and interpersonal skills\nSelf-motivated, independent, diligent and able to work under pressure\nExcellent command of written and spoken English and Chinese\nFresh graduate with IT background is also welcomed\n\nCompetitive package will be offered to the right candidate(s), including 5 day work week, paid examination & study leave, birthday leave & medical insurance coverage. Interested parties please send full resume with working experience, academic and professional qualifications, including present & expected salary by clicking the \"Apply Now\" button.\u00a0 Personal data collected will be used for recruitment purposes only.\n\nSimply click the \u201cApply Now\u201d button\n\nPlease visit our website at\u00a0www.moore.hk\u00a0to know more about us.", "employment_types": ["Full Time", "Permanent"], "selling_points": ["Data Modelling, analytics and visualization", "Conduct IT audit / assessment", "Excellent Career Prospects"], "locations": ["Sheung Wan"], "categories": ["Accounting", "Audit", "Professional Services", "Business Analysis / Data Analysis", "Information Technology (IT)", "IT Auditing"], "post_time": "2022-01-16T03:50:00Z", "salary": {"currency": null, "max": null, "min": null, "period": "monthly", "term": null}, "salary_visible": false, "title_keywords": ["senior associate", "associate", "manager"], "responsibilities": ["control", "review", "compliance", "audit", "evaluate", "system security", "plan", "preparing reports", "ad-hoc projects", "auditing"], "requirements": {"degrees": ["degree", "bachelor", "fresh graduate"], "majors": ["it", "computer science", "information technology"], "languages": ["english", "chinese"], "language_level": ["excellent"], "hard_skills": ["cyber security", "plus", "acumen"], "soft_skills": ["self-motivated", "independent", "well-organised", "diligent", "innovative", "communication and interpersonal skills", "business acumen", "creative", "work under pressure"], "languages_combined": [{"language": "english", "language_level": ["excellent"]}, {"language": "chinese", "language_level": ["excellent"]}]}, "experience_required": {"duration": [], "field": ["related", "it", "security", "audit"]}}, {"job_id": "100003009055566", "location_code": "hk", "company": "Hays", "job_title": "Information Security Manager / Specialist (50k-90k , Bank)", "description": "Implement cybersecurity control mechanisms, risk gap analysis and perform maintenance for security devices.\n\nYour new company\nMy client is a Hong Kong based Banking and Financial company.\n\nYour new role\n\n\n\nDesign, develop and maintain Information Security Polices, Standards and Guidelines\nProvide technical guidance to application development and infrastructure tam regarding security designs and configurations\nAssist in communicating risk management standards, policies and procedures to relevant stakeholders\nConduct regular security assessment on internal system, network and infrastructure\nFacilitate risk management committee meeting for enhancing risk governance and oversight\nDesign and apply operational control process to ensure IT operational and control risks are within acceptable risk appetite\nDesign and monitor Key Risk Indicators. Proficiency in risk reporting to facilitate effective management oversight on technology risk and cybersecurity matters\nPlay a governance role on IT outsourcing. Perform regular security assessment on 3rd party IT service provider\nParticipate in developing, tuning and implementing threat detection analytics\nAct as focal point to support internal, external and regulatory audits\nPrepare and conduct security awareness training for internal IT and non-IT users\n\n\n\nWhat you'll need to succeed\n\nMinimum 5 years of relevant work experience in technology risk, information security and cybersecurity\nUniversity graduate in Computer Science / Information Technology or equivalent\nPossess one or more professional certificates listed below:\nISC2 Certified Information Security Professional (CISSP)\nISACA Certified Information System Auditor (CISA)\nISACA Certified Information Security Manager (CISM)\nISC2 Certified Cloud Security Professional (CCSP)\nSolid experience in vulnerability management, penetration test and technology risk assessment\nSound knowledge in Public Key Infrastructure (PKI), Internet vulnerability, cybersecurity, firewalls, Intrusion Detection/Prevention System and application security of finance/banking systems\nSound experience in performing vulnerability scanning, penetration test and technology risk assessment\nSolid experience in regulators' requirement on technology risk management including the Supervisory Policy Manuals of HKMA, Cyber Resilience Assessment Framework (CRAF), Personal Data Privacy Ordinance, PCI Data Security Standard, SFC guidelines and Customer Security Controls Framework of SWIFT\nBanking experience is an advantage\nStrong communication skill, both in Chinese and English\nMature, independent and able to deliver quality results under tight schedule\nGood communication and interpersonal skills\n\n\n\nWhat you need to do now\nIf you're interested in this role, click 'apply now' to forward an up-to-date copy of your CV, or send your CV to kenneth.ling@hays.com.hk\n\nIf this job isn't quite right for you but you are looking for a new position, please contact us for a confidential discussion on your career.", "employment_types": ["Full Time", "Permanent"], "selling_points": ["Banking & Finance", "Information Security", "1.5 LOD"], "locations": ["Not Specified"], "categories": ["Information Technology (IT)", "IT Auditing", "IT Project Management / Team Lead", "Technical Writing"], "post_time": "2022-01-18T02:43:46Z", "salary": {"currency": "HKD", "max": 89999, "min": 55000, "period": "monthly", "term": null}, "salary_visible": true, "title_keywords": ["specialist", "information security manager"], "responsibilities": ["it service", "information security", "data", "quality", "design", "communication", "maintain", "application development", "personal data", "scanning", "control", "infrastructure", "monitor", "developing", "develop", "schedule", "banking", "vulnerability management", "guidance", "management", "reporting", "procedures", "contact", "audits", "maintenance", "guidelines", "policies", "analysis", "systems"], "requirements": {"degrees": ["university graduate"], "majors": ["computer science", "information technology"], "languages": ["english", "chinese"], "language_level": [], "hard_skills": ["focal", "maintenance", "hkma", "analysis", "gap", "information system", "swift"], "soft_skills": ["independent", "interested in", "communication skill", "mature", "communication and interpersonal skills"], "languages_combined": [{"language": "english", "language_level": []}, {"language": "chinese", "language_level": []}]}, "experience_required": {"duration": ["minimum 5 years"], "field": ["risk management", "management", "supervisory", "banking experience", "security"]}}, {"job_id": "100003009048602", "location_code": "hk", "company": "Teki'Spire Limited", "job_title": "Senior IT Audit Manager | Perm | Financial Institution", "description": "Responsibilities:\n\nAssist in planning and scoping of client engagements\nConduct IT audit or independent assessment to evaluate system security and control effectiveness\nDesign and apply appropriate data modelling, analytics and visualization techniques in audit engagements\nCommunicate and report findings to senior management and clients\nSupport and act towards the BDO Global Vision\nBe committed to act with the firm\u2019s core values and competency expectations\n\nRequirements:\n\nBachelor degree or above in Information Technology Management, Computer Science, Mathematics, Accounting or other relevant fields\nExperience in auditing, data analytics or programming is a plus but not a must\nAbility to work independently within a team environment\nExcellent command of written and spoken English and Chinese, including Putonghua\nPosition offered will commensurate with the experience of the right candidate\n\nWe are an equal opportunity employer, and offer excellent prospects and career development for the right candidate.\u00a0 Interested parties please send your application\u00a0with full career history, current and expected salary by clicking the\u00a0Apply Now\u00a0button below.\n\nApplications will be treated in strict confidence. Personal data collected will be used for recruitment purposes only.", "employment_types": ["Full Time", "Permanent"], "selling_points": ["IT Audit, Internal Audit, External Audit", "Financial Institution, FSI", "CISA, CISM"], "locations": ["Central & Western Area"], "categories": ["Information Technology (IT)", "IT Auditing"], "post_time": "2022-01-14T06:53:39Z", "salary": {"currency": null, "max": null, "min": null, "period": "monthly", "term": null}, "salary_visible": false, "title_keywords": ["manager"], "responsibilities": ["control", "visualization", "data", "audit", "design", "evaluate", "system security", "report", "senior management", "planning"], "requirements": {"degrees": ["degree or above", "bachelor"], "majors": ["mathematics", "accounting", "computer science", "information technology"], "languages": ["putonghua", "english", "chinese"], "language_level": ["excellent"], "hard_skills": ["data analytics", "plus", "programming"], "soft_skills": ["work independently"], "languages_combined": [{"language": "putonghua", "language_level": ["excellent"]}, {"language": "english", "language_level": ["excellent"]}, {"language": "chinese", "language_level": ["excellent"]}]}, "experience_required": {"duration": [], "field": ["programming"]}}, {"job_id": "100003009049102", "location_code": "hk", "company": "Hong Kong Interbank Clearing Ltd", "job_title": "Assistant Manager (Internal Audit)", "description": "Our client is a rapidly expanding financial institution and they are now looking for a Senior IT Audit Manager to join their team in Hong Kong.\u00a0\n\nDuties:\n\nLead and execute the full audit cycle for IT Audits including risk assessment and control management\nDevelop and present concise and quality audit reports with practical, effective and actionable recommendations\nParticipate in the development of the annual IT audit plan and the audit methodology.\u00a0 Through regular and proactive interaction with management, as well as analysis of management information and business activities.\nDevelop, build & implement tools to analyse data to improve audit efficiency and effectiveness, (including for risk assessments).\u00a0 Act as a source for analytics to provide business insights or for continuous auditing.\nAssist in the preparation of regular departmental reports\nProactively monitor the completion of corrective audit actions and, as necessary, advise management of past-due actions.\nRemain responsive and partner with management while maintaining independence\nEngage in continuous knowledge development regarding sector\u2019s rules and\u00a0 regulations, best practices, tools, techniques and performance standards\nRequirements:\n\nDegree from a recognized university in IT, Data Analytics, Computer Science, Accounting, or related disciplines;\nAt least 8 years of insurance/finance experience in both external and internal audit, preferably in Asia\nQualifications in information systems and/or accounting (e.g. CISA, CISM);\nPrior experience holding positions in IT Infrastructure/ Security is a definite asset\nSound knowledge of IT application and network controls;\nStrong knowledge of Internal audit methodology and risk management frameworks\nStrong knowledge of Internal audit methodology and risk management frameworks\nHigh attention to detail and have good analytical skills;\nGood report writing skills in English and Chinese.\nExperience in data analytics, data modelling, data mining, database management is a definite asset;\nHands-on experience in any of the business intelligence and analytics tools such as\u00a0 Qlikview, Tableau, SAS, IDEA, ACL, etc. is a definite asset\nApply Now\n\nTo apply online, please click the 'Apply' button.\u00a0Please note that only short-listed candidates will be contacted.\u00a0All information collected will be kept confidential and will be used for recruitment purposes only.\n", "employment_types": ["Full Time", "Permanent"], "selling_points": [], "locations": ["Ngau Tau Kok"], "categories": ["Banking / Finance", "Financial Services", "Others", "Information Technology (IT)", "IT Auditing"], "post_time": "2022-01-14T08:08:11Z", "salary": {"currency": null, "max": null, "min": null, "period": null, "term": null}, "salary_visible": false, "title_keywords": ["assistant manager"], "responsibilities": ["regulations", "control", "management", "maintaining", "data", "analysis", "quality", "audit", "monitor", "develop", "reports", "plan", "audits", "auditing", "business activities", "analyse"], "requirements": {"degrees": ["degree"], "majors": ["related disciplines", "accounting", "it", "computer science"], "languages": ["english", "chinese"], "language_level": ["good"], "hard_skills": ["analytics tools", "qlikview", "sas", "data analytics", "writing skills", "analytical skills", "tableau", "data mining", "business intelligence"], "soft_skills": ["hands-on", "writing skills", "attention to detail", "analytical skills"], "languages_combined": [{"language": "english", "language_level": ["good"]}, {"language": "chinese", "language_level": ["good"]}]}, "experience_required": {"duration": ["at least 8 years"], "field": ["finance", "infrastructure", "audit", "it", "database management", "security", "business", "insurance"]}}, {"job_id": "100003009049108", "location_code": "hk", "company": "Hong Kong Interbank Clearing Ltd", "job_title": "Manager (Internal Audit)", "description": "Our client, a leading bank, is looking for an experienced IT Audit Manager to join their Audit 3LOD team. The successful candidate will be bringing IT audits especially for their Cyber Security and new digital banking initiatives.\u00a0\n\nResponsibilities:\n\nLead the IT Audit across audit plans, and methods across various IT areas including Cyber Security, Digital, Banking Procedures and IT Controls.\nConduct risk assessment, audit planning, audit testings, control evaluation, etc. Provide audits finding reports, follow-up, and verifications.\nDevelop and monitor cybersecurity development initiatives, through design and perform of continuous risk assessment methodology\nPerform Investigation on technology-related frauds and incidents.\nWork closely with the management through tracking and reporting function, to ensure a timely response to executives, board, and regulators.\nStay up-to-date with evolving industry and regulatory change requirements which may impact the business and technology team.\nUpdate and maintain Audit systems and provide suggestions on efficiency and effectiveness improvement.\u00a0\n\n\u00a0Required Skills/Experience:\n\nAt least 4 years of experience in the IT Audit area, ideally with exposure to the banking / financial services industry.\nUnderstanding regulatory requirements including HKMA is highly preferable.\nUnderstanding of banking information security and information technology governance and assessment.\nOutstanding communication and interpersonal skills. Ability to work effectively with all levels of the organization.\nStrong analytical skills required to enable independent research and accurate assessments of risk management process effectiveness and adherence to regulatory requirements.\nCISA, CISM, CISSP, or equivalent industry certification is preferred.\n\nIf this outstanding opportunity sounds like your next career move, please send your resume in Word format to Danny Kwan at resume(at)pinpointasia(dot)com and put IT Audit Manager - Leading Bank in the subject header.\n\nData provided is for recruitment purposes only.", "employment_types": ["Full Time", "Permanent"], "selling_points": [], "locations": ["Ngau Tau Kok"], "categories": ["Banking / Finance", "Financial Services", "Others", "Information Technology (IT)", "IT Auditing"], "post_time": "2022-01-14T08:08:13Z", "salary": {"currency": null, "max": null, "min": null, "period": null, "term": null}, "salary_visible": false, "title_keywords": ["manager"], "responsibilities": ["information security", "cyber security", "data", "regulatory requirements", "audit", "design", "communication", "maintain", "evaluation", "plans", "control", "monitor", "develop", "reports", "banking", "reporting", "management", "procedures", "investigation", "audits", "tracking", "systems", "recruitment", "planning"], "requirements": {"degrees": [], "majors": [], "languages": [], "language_level": [], "hard_skills": ["hkma", "word", "analytical skills", "cyber security"], "soft_skills": ["work effectively", "independent", "timely", "analytical skills", "communication and interpersonal skills", "accurate"], "languages_combined": []}, "experience_required": {"duration": ["at least 4 years"], "field": ["financial services industry", "it", "audit", "banking"]}}, {"job_id": "100003009048404", "location_code": "hk", "company": "Links International", "job_title": "IT Audit Manager (Leading PRC Securities ,Big 4 Welcome )", "description": "Major Responsibilities\n\nAssist in developing internal audit plans, follow up on status of audit issues and coordinate audit reports, etc.\nProvide expertise to maintain and monitor the internal control policies and procedures\nExecute internal audit projects and/or ad hoc reviews/ investigations on different areas to determine the adequacy and effectiveness of internal control and compliance measures\nEnsure risks are effectively identified and constructive advice is provided for solving or mitigating risks and control issues\nAssist in producing regular reports and presentations to the Management and Board of Directors on audit findings and recommendations\nFollow up on remedial status of issues identified during audit work\nRequirements\n\nUniversity degree in Accounting, Finance, Risk Management or other relevant disciplines\nCPA, CIA, CISA or equivalent qualifications\nOver 3 years of experience in internal or external audit field, preferably with IT audit experience and audit experience in Big 4 professional accounting firm(s)\nSound knowledge of auditing standards and regulatory requirements\nStrong interpersonal and analytical skills\nGood command of written and spoken English and Chinese, proficiency in Putonghua will be an advantage\nHow to Apply\n\n\nInterested parties please send your curriculum vitae stating your current and expected salaries, and the contact phone number to the Human Resources Division, Unit B, 25/F, MG Tower, 133 Hoi Bun Road, Kwun Tong, Kowloon\u00a0\u00a0by clicking the \"Apply Now\" button below.\nAll applications and personal information collected will be treated in strict confidence and only be used for the purpose of recruitment and selection.\u00a0 The information collected will be accessed by our authorized personnel only.\u00a0 Those applicants not contacted by the Human Resources Division within two months from their application date should consider their applications filed for future reference which will be retained for one year for possible future job matching, and will be destroyed after the expiry of one year.", "employment_types": ["Full Time", "Permanent"], "selling_points": ["Leading PRC securities", "IT Audit ,Information Security  Focus", "Straight Big 4 Welcome"], "locations": ["Central & Western Area"], "categories": ["Accounting", "Audit", "Banking / Finance", "Financial Services", "Information Technology (IT)", "IT Auditing"], "post_time": "2022-01-14T06:29:00Z", "salary": {"currency": null, "max": null, "min": null, "period": "monthly", "term": null}, "salary_visible": false, "title_keywords": ["manager"], "responsibilities": ["control", "management", "ad hoc", "internal audit", "policies", "compliance", "monitor", "developing", "audit", "procedures", "coordinate", "presentations", "maintain", "reports", "plans", "internal control"], "requirements": {"degrees": ["university degree"], "majors": ["finance", "accounting", "risk management"], "languages": ["putonghua", "english", "chinese"], "language_level": ["advantage", "proficiency", "good command"], "hard_skills": ["cpa", "analytical skills"], "soft_skills": ["interpersonal", "analytical skills"], "languages_combined": [{"language": "putonghua", "language_level": ["proficiency", "good command"]}, {"language": "english", "language_level": ["advantage", "proficiency", "good command"]}, {"language": "chinese", "language_level": ["advantage", "proficiency", "good command"]}]}, "experience_required": {"duration": ["3 years"], "field": ["big 4", "audit", "it", "audit experience", "accounting"]}}, {"job_id": "100003009055236", "location_code": "hk", "company": "ORIENTAL HUMAN RESOURCES LIMITED", "job_title": "Systems Engineer / Junior Systems Engineer", "description": "We are now looking for high calibre and passionate individuals to join us to undertake this multi-billion HK dollar transformation project leading the MPF ecosystem to a new era.\u00a0 If you are passionate about creating a positive impact on the working population of Hong Kong and are keen and willing to work in a start-up style environment, please join our growing team to contribute to the transformation journey.\n\n\nKey Accountabilities\n\nReporting to the Senior Manager (Team Head) \u2013 Application System;\nWorking closely with a major third party supplier as an \u201cintelligent customer\u201d and \u201ccritical friend\u201d on the delivery of the eMPF Platform project, including system analysis, system design, system development, testing, migration and implementation;\nWorking across all system interfaces areas with stakeholder\u2019s systems;\nReviewing contractual deliverables and providing recommendation for acceptance / payment / need for revision;\nManaging the contractors, and providing technical comments to the development activities; and\nAny other duties as assigned.\n\nSkills and Qualification\n\nBachelor\u2019s degree or Master\u2019s degree in Computer Science or related disciplines;\nIdeally CMMI- DEV (Capability Maturity Model Integration \u2013 Development) certified;\nMinimum 8 years of relevant IT - SDLC (System Development Life Cycle) and IT vendor management experience preferably in Financial Services environment;\nSolid experience in working with suppliers in delivering large-scale system solutions including practical experience with web and mobile apps development, data lake and data visualization and involved in 2 large projects in implementing a complex system;\u00a0\nHands-on technical skills and experience in application of modern technology, such as Cloud technology, Cyber security, DevOps, Micro services architecture, Kubernetes, Level 1 to 4 system level definition, mobile and portal development, BI, API, Messaging, Java, JSON, Databases (example: Oracle, Mongo, Microsoft SQL and MYSQL);\nStrong project management experience;\nDriven, positive, highly structured, proactive, and analytical;\nExcellent organization and problem solving skills, and be able to work under pressure;\nGood command of both spoken and written Chinese and English; and\nKeen and willing to work in a start-up style environment with all the flexibility that requires and level of change involved.\n\nRemuneration Package\n\nRank and salary will be commensurate with qualification and experience. The initial appointment will be made on a fixed-term contract.\u00a0 A competitive remuneration and benefits package including discretionary performance-linked variable pay, annual leave, medical, dental and life insurance coverage, and MPF will be offered.\n\nTo Apply\n\nInterested candidates are invited to apply by sending full career details and application letter, quoting the position applied for and job reference number, with information of current and expected remuneration as well as earliest availability\u00a0through the \"Apply Now\" button.\u00a0\n\n\nThe closing date for application is 25 January\u00a02022.\u00a0 Applicants not contacted for follow up within 3 months after the closing date for application may assume that their applications are unsuccessful.\u00a0 Applications not selected for further processing may be considered for relevant openings in the future but their applications will not be retained for more than a period of two years after the closing date.\n\nThe information provided will be kept confidential and only be used for those purposes relating to your application.\u00a0 Please visit our website for the details of the MPFA\u2019s Personal Information Collection Statement at https://www.mpfa.org.hk/en/mpfa/joining-mpfa/job-vacancies/personal-information-collection-statement.\u00a0 The MPFA is an equal opportunities employer and welcomes applications from all qualified candidates.", "employment_types": ["Full Time", "Permanent"], "selling_points": [], "locations": ["Tai Po Area"], "categories": ["Information Technology (IT)", "IT Auditing", "Security", "Technical / Functional Consulting"], "post_time": "2022-01-18T01:53:56Z", "salary": {"currency": null, "max": null, "min": null, "period": "monthly", "term": null}, "salary_visible": false, "title_keywords": ["systems engineer", "junior"], "responsibilities": ["any other duties", "visualization", "data", "cyber security", "payment", "work under pressure", "implementation", "application system", "testing", "migration", "architecture", "reporting", "management", "mpf", "third party", "analysis", "systems", "comments", "project management", "system design", "databases", "insurance"], "requirements": {"degrees": ["degree", "bachelor", "master"], "majors": ["related disciplines", "computer science"], "languages": ["english", "chinese"], "language_level": ["good command"], "hard_skills": ["java", "bi", "web", "cyber security", "analysis", "devops", "vendor", "application system", "sql", "mobile", "sdlc", "system design", "project management", "databases", "data visualization", "integration", "problem solving skills", "oracle"], "soft_skills": ["passionate", "passionate about", "proactive", "keen", "project management", "hands-on", "technical skills", "problem solving skills", "structured", "driven", "positive", "work under pressure"], "languages_combined": [{"language": "english", "language_level": ["good command"]}, {"language": "chinese", "language_level": ["good command"]}]}, "experience_required": {"duration": ["minimum 8 years"], "field": ["management", "development", "devops", "system development", "sql", "project management", "it", "financial services", "security"]}}, {"job_id": "100003009049584", "location_code": "hk", "company": "Mandatory Provident Fund Schemes Authority", "job_title": "Manager (Supervision)", "description": "Major Responsibilities\n\nAssist in developing corporate audit strategies, policies and procedures\nDevelop internal audit plans, follow up on status of audit issues and coordinate audit reports, etc.\nProvide expertise to maintain and monitor the internal control policies and procedures\nSchedule, plan and execute internal audit projects and/or ad hoc reviews/ investigations on different areas to determine the adequacy and effectiveness of internal control and compliance measures\nEnsure risks are effectively identified and constructive advice is provided for solving or mitigating risks and control issues\nProduce regular reports and presentations to the Management and Board of Directors on audit findings and recommendations\nFollow up on remedial status of issues identified during audit work\nRequirements\n\nUniversity degree in Accounting, Finance, Risk Management or other relevant disciplines\nCPA, CIA, CISA, CISM and/or CISSP qualifications\nOver 5 years of experience in internal or external audit field, preferably with IT audit experience; with 3 years in supervisory positions and audit experience in Big 4 professional accounting firm(s)\nSound knowledge of auditing standards and regulatory requirements\nStrong interpersonal, supervisory and analytical skills\nGood command of written and spoken English and Chinese, proficiency in Putonghua will be an advantage\nHow to Apply\n\n\nInterested parties please send your curriculum vitae stating your current and expected salaries, and the contact phone number to the Human Resources Division, Unit B, 25/F, MG Tower, 133 Hoi Bun Road, Kwun Tong, Kowloon\u00a0\u00a0by clicking the \"Apply Now\" button below.\nAll applications and personal information collected will be treated in strict confidence and only be used for the purpose of recruitment and selection.\u00a0 The information collected will be accessed by our authorized personnel only.\u00a0 Those applicants not contacted by the Human Resources Division within two months from their application date should consider their applications filed for future reference which will be retained for one year for possible future job matching, and will be destroyed after the expiry of one year.", "employment_types": ["Full Time"], "selling_points": [], "locations": ["Kwai Hing"], "categories": ["Information Technology (IT)", "IT Auditing", "IT Management", "Security"], "post_time": "2022-01-14T08:54:32Z", "salary": {"currency": null, "max": null, "min": null, "period": "monthly", "term": null}, "salary_visible": false, "title_keywords": ["manager"], "responsibilities": ["internal audit", "audit", "maintain", "plan", "plans", "internal control", "control", "ad hoc", "compliance", "monitor", "developing", "presentations", "develop", "reports", "schedule", "management", "procedures", "policies", "coordinate"], "requirements": {"degrees": ["university degree"], "majors": ["finance", "accounting", "risk management"], "languages": ["putonghua", "english", "chinese"], "language_level": ["advantage", "proficiency", "good command"], "hard_skills": ["cpa", "analytical skills"], "soft_skills": ["interpersonal", "analytical skills"], "languages_combined": [{"language": "putonghua", "language_level": ["proficiency", "good command"]}, {"language": "english", "language_level": ["advantage", "proficiency", "good command"]}, {"language": "chinese", "language_level": ["advantage", "proficiency", "good command"]}]}, "experience_required": {"duration": ["5 years", "3 years"], "field": ["supervisory", "big 4", "audit", "it", "audit experience", "accounting"]}}, {"job_id": "100003009038289", "location_code": "hk", "company": "FWD Life Insurance Company (Bermuda) Limited", "job_title": "Senior Manager, IT Audit", "description": "About the client\n\nOur client is a leading PRC securities .\n\nJob Responsibilities:\n\nConduct yearly IT audits, review and special projects\nPrepare IT audit reports, present investigation findings and offer recommendations\nAssist to develop audit plans of designated areas in IT Audit\nEvaluate the risk management, regulatory compliance processes and internal controls systems\nMaintain and develop internal audit policies, procedures\nConducting IT security monitoring & security assessment for network, systems and applications including but not limited to; vulnerability scanning, penetration test, technical security assessment;\nEstablish a control framework in conducting periodic review and technical assessment when needed, including but not limited to; phishing attack simulation, penetration test, vulnerability scanning;\nIdentify inefficiencies and control weaknesses, explore methods for improvement and implement remediation security controls based on IT initiatives on technology risk perspective;\nProvide proactive consultative advice that leads to improvements in risk control and governance systems;\nPerform business continuity and disaster recovery planning and execution.\n\nJob Requirements:\n\nBachelor degree in Accounting, Finance ,Computer Science or a related subject from an accredited institution;\nHolder of CISSP, CISM or CISA preferred;\n3- 5 years of IT Audit experience in gained in Big 4 and in house\nGood command of English and Chinese\nPassionate in InfoSec and Cybersecurity area", "employment_types": ["Full Time"], "selling_points": ["Participate in the annual IT audit plan", "Analyse data to improve audit efficiency", "Present concise and quality audit reports"], "locations": ["Sheung Wan"], "categories": ["Accounting", "Audit", "Information Technology (IT)", "IT Auditing"], "post_time": "2022-01-11T06:26:30Z", "salary": {"currency": null, "max": null, "min": null, "period": "monthly", "term": null}, "salary_visible": false, "title_keywords": ["senior manager"], "responsibilities": ["business continuity", "internal audit", "audit", "maintain", "plans", "scanning", "control", "compliance", "develop", "reports", "management", "monitoring", "review", "procedures", "investigation", "audits", "recovery planning", "policies", "systems", "evaluate"], "requirements": {"degrees": ["degree", "bachelor"], "majors": ["finance", "accounting", "computer science"], "languages": ["english", "chinese"], "language_level": ["good command"], "hard_skills": [], "soft_skills": ["passionate"], "languages_combined": [{"language": "english", "language_level": ["good command"]}, {"language": "chinese", "language_level": ["good command"]}]}, "experience_required": {"duration": ["3- 5 years"], "field": ["audit experience", "it", "big 4"]}}, {"job_id": "100003009045891", "location_code": "hk", "company": "Kinetix Systems Ltd", "job_title": "Security Consultant", "description": "Responsibilities:\n\nMaintain Multi-network Antivirus Management System\nMaintain SIEM / CDN Alerting System\nManage and Coordinate Security Incident Response and Investigation Process\nResearch and satisfy security related requirements\nON-JOB TRAINING: Hacking & Virus Forensic / Linux / Bash / Python / Windows / MacOS/ Proxmox / Docker / ESMC / KSC / SIEM / Graylog / Elasticsearch / IDS / AlientVault / Encryption / HAProxy / MySQL / Zabbix / etc\n\nRequirements:\n\nDegree / Higher Diploma in Computer Science or related disciplines\nAt least 3 years of IT working experience\nKnowledge of Networking, Web Application Security, Instruction Detection Systems, Penetration Testing, Network Vulnerability Scanners and Scripting Languages (e.g Windows and Linux Platform)\nExperience in Security Systems, including Firewalls, Anti-Virus Software, Authentication System, Log Management, etc\nDedicated, initiative and self-motivated with strong analytical skills and good reporting skills\nGood command of written and spoken Chinese and English\n\n\u00a0(Candidate with less experience will be considered as Junior Systems Engineer)\n\n\nApplication Method\u00a0\n\nWe offer 5-day work week, free shuttle bus, free parking and fringe benefits including medical scheme, discretionary bonus, public holidays together with career growth opportunities to the right candidate. \u00a0Interested parties, please send full resume with expected salary to ORIENTAL\u00a0HUMAN RESOURCES LIMITED\u00a0by clicking \"Apply now\" ;\u00a0or fax to 3600 1900 ( Please quote reference on the application letter )\n\nPersonal Information Collection Statement\n\nPersonal data collected will be treated in accordance with our Personal Data Policy and handled in strict confidence by authorized personnel for recruitment related purpose only.\n\non.cc", "employment_types": ["Full Time", "Permanent"], "selling_points": ["CISA / CISM / CISSP is a must", "Exposure on different projects and clients", "Comprehensive remuneration package"], "locations": ["Kwun Tong"], "categories": ["Information Technology (IT)", "IT Auditing", "IT Management", "Security"], "post_time": "2022-01-13T09:02:41Z", "salary": {"currency": null, "max": null, "min": null, "period": "monthly", "term": null}, "salary_visible": false, "title_keywords": ["consultant"], "responsibilities": ["coordinate", "management", "maintain", "investigation"], "requirements": {"degrees": ["diploma", "degree"], "majors": ["related disciplines", "computer science"], "languages": ["english", "chinese"], "language_level": ["good command"], "hard_skills": ["linux", "web application security", "scheme", "analytical skills"], "soft_skills": ["self-motivated", "initiative", "analytical skills"], "languages_combined": [{"language": "english", "language_level": ["good command"]}, {"language": "chinese", "language_level": ["good command"]}]}, "experience_required": {"duration": ["at least 3 years"], "field": ["management", "it", "security"]}}, {"job_id": "100003009053782", "location_code": "hk", "company": "Hysan Development Co Ltd", "job_title": "Senior Application Analyst", "description": "The Job\n\nThe MPFA has been tasked by the Government to design, develop and operate a digital platform, eMPF Platform, to standardize, streamline and automate the existing MPF scheme administration processes.\u00a0 Through the adoption of new technologies and innovative solution, this user-centric platform will bring about revolutionary change to the MPF ecosystem, thus creating further room for scheme administration fee reduction to benefit all MPF scheme members.\u00a0 On 5 March 2021, the eMPF Platform Company Limited was established as MPFA\u2019s wholly owned subsidiary to take forward the eMPF Platform project.\u00a0 For background and details of the eMPF Platform project, please go to our website https://www.mpfa.org.hk/en/empf/overview.\n\nThe appointee will support the development and implementation of an oversight programme in relation to overseeing the operation of the eMPF Platform to safeguard system integrity and stability.\u00a0 The appointee will also be involved in key projects with a view to supervising the performance of functions assigned to the eMPF Platform Company Limited and the system readiness of MPF trustees for on-boarding the eMPF Platform.\u00a0 The main responsibilities include:\n\nTo support the development of an oversight framework which would effectively oversee and supervise the operation of the eMPF platform to safeguard system integrity and stability;\nTo assist in establishing and enforcing standards and sound practices for and communicate compliance expectations with the eMPF Platform Company Limited;\nTo collaborate with the eMPF Platform Company Limited and oversee its performance of operational functions delivered either directly or through outsourced vendors;\nTo collaborate with eMPF Platform Company Limited to ensure that the eMPF Platform would adopt appropriate technical security measures and proper safeguards to protect the system security and data;\nTo perform evaluation of control design and carry out assessment of the effectiveness of internal controls and risk management concerning eMPF operation processes, IT systems, cyber security and system resilience;\nTo support projects at the MPFA level on reforms of MPF system, supervision of MPF trustees in relation to their system readiness for on-boarding the eMPF Platform, and other related initiatives; and\nTo perform other duties as assigned.\n\nThe Person\n\nA recognized degree in Computer Science, Information Systems, Business or related disciplines;\nAt least eight years of relevant experience in regulatory compliance, retirement schemes / pensions, system auditing, cyber security or technology risk management, of which at least four years should be at supervisory level, preferably gained from sizable or public organizations;\nPossess certifications such as CISA, CRISC or other relevant qualifications;\nStrong knowledge and understanding of the business strategies, challenges and risks in MPF operation and technology project management;\nStrong analytical skills and ability to effectively prioritize and coordinate multiple deliverables simultaneously;\nEffective negotiator and communicator; and\nExcellent interpersonal, leadership and influencing skills, self-motivated, solutions oriented and able to work under pressure.\n\nRemuneration Package\n\nA competitive remuneration and benefits package including a discretionary performance-linked variable pay, annual leave, medical, dental and life insurance coverage, and MPF will be offered.\u00a0 The appointment will be made on a fixed-term contract for two years with the possibility of renewal of the appointment, subject to operational needs and staff performance.\n\nTo Apply\n\nInterested candidates are invited to apply by sending full career details and application letter, quoting the job reference number, with information of current / expected remuneration, availability,\u00a0to the address below or by clicking the \"Apply Now\" button:\n\nHuman Resources Department, MPFA\n\nLevel 8, Tower 1, Kowloon Commerce Centre\n\n51 Kwai Cheong Road, Kwai Chung, Hong Kong\n\nThe closing date for application is 28 January 2022 or postmarked on 28 January 2022. \u00a0Applicants not invited for interview by the end of March 2022 may assume that their applications are unsuccessful and their applications will not be retained for more than two years.\n\nThe information provided will be kept confidential and only be used for those purposes relating to your application.\u00a0 Please visit our website for the details of the MPFA\u2019s Personal Information Collection Statement for Job Applicants at https://www.mpfa.org.hk/en/mpfa/joining-mpfa/job-vacancies/personal-information-collection-statement.\u00a0 The MPFA is an equal opportunities employer and welcomes applications from all qualified candidates.", "employment_types": ["Full Time", "Permanent"], "selling_points": ["Development and maintenance of ERP system", "Degree holder with 6+ years relevant experience", "5-day work, 14-day AL, Dental, Double Pay + Bonus"], "locations": ["Causeway Bay"], "categories": ["Information Technology (IT)", "Application Specialist - Software", "IT Auditing", "Software Development"], "post_time": "2022-01-17T07:30:49Z", "salary": {"currency": null, "max": null, "min": null, "period": "monthly", "term": null}, "salary_visible": false, "title_keywords": ["application analyst"], "responsibilities": ["collaborate with", "supervising", "data", "cyber security", "website", "design", "evaluation", "administration", "support projects", "control", "perform other duties", "compliance", "implementation", "develop", "management", "mpf", "digital platform", "systems", "system security"], "requirements": {"degrees": ["degree"], "majors": ["related disciplines", "business", "computer science"], "languages": [], "language_level": [], "hard_skills": ["project management", "analytical skills", "cyber security"], "soft_skills": ["self-motivated", "prioritize", "analytical skills", "project management", "communicator", "leadership", "interpersonal", "work under pressure"], "languages_combined": []}, "experience_required": {"duration": ["at least four years", "at least eight years"], "field": ["risk management", "compliance", "relevant experience", "security", "supervisory level"]}}, {"job_id": "100003009043864", "location_code": "hk", "company": "Advanced Assembly Materials International Limited", "job_title": "IT Security Administrator", "description": "Established in Asia in 2013 with a trailblazer mentality, FWD is the primary insurance business of investment group, Pacific Century Group (PCG), with minority shareholders Swiss Re Group, GIC Ventures, RRJ Capital and Hopu Investments.\n\nFWD spans 10 markets in Asia including Hong Kong SAR & Macau SAR, Thailand, Indonesia, the Philippines, Singapore, Vietnam, Japan, Malaysia and Cambodia. In Hong Kong, FWD offers life and medical insurance, general insurance, employee benefits, and financial planning. We focus on creating fresh customer experiences and making the insurance journey simpler, faster and smoother, with innovative propositions and easy-to-understand products, supported by digital technology. Through this customer-led approach, FWD aims to be a leading pan-Asian insurer by changing the way people feel about insurance.\n\nIf you are looking for a company where can fuel your inspiration and cultivate your expertise, join us on our exciting journey.\n\nThe Job:\n\nLead and execute the full audit cycle for IT Audits including risk assessment and control management\nDevelop and present concise and quality audit reports with practical, effective and actionable recommendations\nParticipate in the development of the annual IT audit plan and the audit methodology.\u00a0 Through regular and proactive interaction with management, as well as analysis of management information and business activities.\nDevelop, build & implement tools to analyse data to improve audit efficiency and effectiveness, (including for risk assessments).\u00a0 Act as a source for analytics to provide business insights or for continuous auditing.\nAssist in the preparation of regular departmental reports\nProactively monitor the completion of corrective audit actions and, as necessary, advises management of past due actions.\nRemain responsive and partner with management while maintaining independence\nEngage to continuous knowledge development regarding sector\u2019s rules and\u00a0 regulations, best practices, tools, techniques and performance standards\n\nThe Person:\n\nDegree from a recognized university in IT, Data Analytics, Computer Science, Accounting, or related disciplines;\nAt least 8 years of insurance/finance experience in both external and internal audit, preferably in Asia\nQualifications in information systems and/or accounting (e.g. CISA, CISM);\nPrior experience holding positions in IT Infrastructure/ Security is a definite asset\nSound knowledge of IT application and network controls;\nStrong knowledge of Internal audit methodology and risk management frameworks\nStrong knowledge of Internal audit methodology and risk management frameworks\nHigh attention to details and have good analytical skills;\nGood report writing skills in English and Chinese.\nExperience in data analytics, data modelling, data mining, database management is a definite asset;\nHands on experience in any of the business intelligent and analytics tools such as\u00a0 Qlikview, Tableau, SAS, IDEA, ACL, etc. is a definite asset\n\nWe offer 5-day work, 20-22 days annual leaves, excellent learning & development opportunities and an attractive package to the right candidate.\n\nInformation collected will be treated in strict confidence and used solely for recruitment purpose. The company will retain all applications no longer than 24 months of which will be destroyed thereafter. When there are vacancies in any of our subsidiaries, holding companies, associated or affiliated companies of, or companies controlled by, or under common control with the Company during that period, we may transfer your application to them for consideration of employment. We are an equal opportunity employer. We do not discriminate on the basis of race, sex, disability or family status in employment process.", "employment_types": ["Full Time", "Permanent"], "selling_points": ["5-day work", "Flexible working hours", "Competitive remuneration package"], "locations": ["Shatin Area"], "categories": ["Information Technology (IT)", "IT Auditing", "Security", "Network & System"], "post_time": "2022-01-13T02:14:02Z", "salary": {"currency": null, "max": null, "min": null, "period": "monthly", "term": null}, "salary_visible": false, "title_keywords": ["administrator"], "responsibilities": [], "requirements": {"degrees": [], "majors": [], "languages": [], "language_level": [], "hard_skills": [], "soft_skills": [], "languages_combined": []}, "experience_required": {"duration": [], "field": []}}, {"job_id": "100003009050928", "location_code": "hk", "company": "The Hang Seng University of Hong Kong", "job_title": "Assistant Information Security Manager / Senior Information Security Officer", "description": "Job Description\n\nProvide IT security consultancy services for clients\nConduct security assessment and audit for clients' IT systems\nDevelop / evaluate new security products / services\nProvide implementation services for security systems\n\nRequirements\n\nBachelor' degree or above in Computer Science or IT related disciplines\nCertification of CISA / CISM / CISSP is a must\nMinimum 4 years of IT experience with at least 2 years in IT security\nExperience in IT audit, IT risk advisory or related aspects\nGood understanding of IT system platforms and IT security services\nExperience in government's SRAA projects is an advantage\nExperiences in vulnerability scanning on web and mobile applications and code review is an advantage\nIf you enjoy working in a friendly and challenging working environment, please send your full resume with your availability, last/current and expected salary by clicking \u201cApply Now\u201d.\n\n*All information collected will be used for recruitment purpose only and will be kept strictly confidential*", "employment_types": ["Full Time"], "selling_points": [], "locations": ["Shatin Area"], "categories": ["Information Technology (IT)", "IT Auditing", "IT Management", "Application Specialist - Network"], "post_time": "2022-01-14T11:49:37Z", "salary": {"currency": null, "max": null, "min": null, "period": "monthly", "term": null}, "salary_visible": false, "title_keywords": ["information security manager", "senior information security officer", "assistant"], "responsibilities": ["systems", "audit", "implementation", "develop", "evaluate"], "requirements": {"degrees": ["degree or above", "bachelor"], "majors": ["related disciplines", "it", "computer science"], "languages": [], "language_level": [], "hard_skills": ["mobile", "code", "web"], "soft_skills": ["enjoy working", "friendly"], "languages_combined": []}, "experience_required": {"duration": ["minimum 4 years", "at least 2 years"], "field": ["related", "audit", "it experience", "it", "security"]}}, {"job_id": "100003009042798", "location_code": "hk", "company": "Chong Hing Bank Ltd", "job_title": "Assistant Vice President, Internal Audit (Information Technology) - Internal Audit Division", "description": "Job Purpose\nThis role is responsible for development and maintenance of ERP system, and other business\u00a0applications\u00a0in both support activities and department projects to support the company fast-growing development.\n\nKey Responsibilities\n\n\nProvide application support and troubleshoot for various internal application systems\u00a0\nParticipate in business process transformational initiatives\nParticipate in technical analysis, design, application development and system integration\nWork closely with business users, review business needs and drive business process improvement with IT solution\nCoordinate with vendors and infrastructure team to deliver solution to business users\nBe responsible for system analysis, design, development and implementation Assist in ad hoc projects when required\nDeliver project documentation and training materials in professional standard\nAssist in system audit\n\n\u00a0\u00a0\nSkills, Qualifications and Experience Requirements\n\nUniversity graduate in Information Technology/Computer Science or related disciplines\n6 years or above in system development with at least 3 years in system analysis and development in SAP areas\nExperience in SAP ABAP programming and Basis is preferrable\u00a0\nSAP hands-on experience or certification in one or more of the following modules including FI/CO, REFX, MM, BW, BO, HCM\nProven experience in system integration and components including application-to-application integrations and services, internal and external API, file transfer, and EDI / SQL queries\nKnowledge and experience in other business applications is advantage Ideal with project management skills\nExperience in managing 3rd party vendors Good team player with strong interpersonal and communication skills\nDemonstrated commitment working under pressure independently\nCandidate with Finance background will be a plus\nGood command of written and spoken English and Cantonese\n\nAn attractive remuneration package will be offered to the right candidate. Interested parties please press \"Apply now\".\n\nHysan is an equal opportunity employer.\u00a0 All information collected will be kept in strict confidence and used solely for recruitment related purposes within the Hysan Group Companies.\n\nYou may get to know more about us through www.hysan.com.hk", "employment_types": ["Full Time", "Permanent"], "selling_points": ["Conduct audit assignments/control assessments", "Conduct project reviews on IT develop. progm.", "Minimum 5 years\u2019 relevant experience"], "locations": ["Kowloon Bay"], "categories": ["Banking / Finance", "Corporate Banking", "Information Technology (IT)", "IT Auditing"], "post_time": "2022-01-12T08:52:08Z", "salary": {"currency": null, "max": null, "min": null, "period": "monthly", "term": null}, "salary_visible": false, "title_keywords": ["assistant vice president"], "responsibilities": ["3rd party vendors", "maintenance", "application development", "analysis", "review", "coordinate with", "infrastructure", "design", "implementation", "audit", "project management", "communication", "business process", "ad hoc projects", "troubleshoot", "application systems", "project documentation"], "requirements": {"degrees": ["university graduate"], "majors": ["related disciplines", "computer science", "information technology"], "languages": ["cantonese", "english"], "language_level": ["good command"], "hard_skills": ["abap", "documentation", "plus", "maintenance", "sap", "analysis", "technical analysis", "sql", "project management", "erp system", "programming", "integration"], "soft_skills": ["communication skills", "good team player", "independently", "under pressure", "responsible", "project management skills", "hands-on", "troubleshoot", "interpersonal", "ideal"], "languages_combined": [{"language": "cantonese", "language_level": ["good command"]}, {"language": "english", "language_level": ["good command"]}]}, "experience_required": {"duration": [], "field": ["sql", "project management", "business", "programming", "team"]}}, {"job_id": "100003009038221", "location_code": "hk", "company": "Michael Page", "job_title": "Manager - IT Audit (HK Listed Conglomerate)", "description": "Responsibilities:\n\nDeveloping and implementing sufficient measures to detect cyber threats\nImplement IT security policies\nMaintaining IT system integrity\nDetermine potential risks and vulnerabilities inside the system\nRecognize problems within systems by identifying uncharacteristic activity\nAssess current situations with the network security and carry out audits\n\nRequirements:\n\nDegree in IT Security / Computer Science / Information Technology / Information System or relevant disciplines\nMinimum 3 years\u2019 working experience in IT security area\nHands-on experience in firewall, antivirus software and web proxy management administration\nCISA, CISSP holder preferred\nFrequent business travels to Asian countries and day trip to Mainland China are required", "employment_types": ["Full Time", "Permanent"], "selling_points": ["New Headcount", "Energetic Team", "Big 4 background preferred"], "locations": ["Not Specified"], "categories": ["Accounting", "Audit", "Information Technology (IT)", "IT Auditing"], "post_time": "2022-01-11T06:12:24Z", "salary": {"currency": "HKD", "max": 69999, "min": 55000, "period": "monthly", "term": null}, "salary_visible": true, "title_keywords": ["manager"], "responsibilities": ["maintaining", "policies", "systems", "developing", "audits"], "requirements": {"degrees": ["degree"], "majors": ["it", "computer science", "information technology"], "languages": [], "language_level": [], "hard_skills": ["web", "information system", "antivirus", "firewall"], "soft_skills": ["hands-on"], "languages_combined": []}, "experience_required": {"duration": ["minimum 3 years"], "field": ["management", "it", "security", "administration"]}}, {"job_id": "100003009049717", "location_code": "hk", "company": "Drake Overload Ltd", "job_title": "Cyber Security Manager", "description": "Assistant Information Security Manager / Senior Information Security Officer\u00a0\u2013 Information Technology Services Centre (Ref: AISM / SISO (ITSC) 2022-01-14)\n\n(Ref: AISM / SISO (ITSC) 2022-01-14)\n\n\n\nResponsibilities:\n\nreview and update security documents such as policies and guidelines;\nassess risks on applications, systems, networks and adopt security measures in a balance manner for risk mitigation;\naudit and run tests on systems and infrastructure to identity possible issues;\nensure digital assets adequately protected, effectively monitored and managed;\nprovide latest updates on information security to general users to increase their awareness; and\nexplore suitable information security technologies that can better safeguard the information in the university.\n\nApplicants should:\n\npossess a recognised bachelor\u2019s degree or above in Computer Science or related discipline;\npossess updated and relevant qualifications such as CISM, CISSP, CEH, ISO27001;\npreferably have at least 10 years of relevant work experience;\nhave proven records in information security and system auditing in application, networks and system level;\nhave good interpersonal, communication, analytical and problem-solving skills;\nhave good command of written and spoken English and Chinese; and\nbe pleasant with positive mindset, good customer sense and willing to learn new technologies.\n\nThe appointee will be required to work during non-office hours.\u00a0 Work experience in the higher education sector will be an advantage.\u00a0 Applicants with fewer years of experience could be considered as Senior Information Security Officer.\u00a0\n\n\nSalary will be commensurate with qualifications and experience.\u00a0 Interested applicant should visit this link https://recruit.hsu.edu.hk/ and apply on or before 30 January 2022.\u00a0 The University reserves the right not to fill the position in this exercise.\n\nApplicants who are not invited to an interview within three months may consider their applications unsuccessful.\u00a0 All information received will be treated in strict confidence, and the data collected will be used for recruitment purposes only.\u00a0 The Personal Information Collection Statement will be provided upon request.\n\nthe Hang Seng University of Hong Kong, incorporated in Hong Kong with limited liability by guarantee, is an equal opportunity employer.", "employment_types": ["Full Time", "Permanent"], "selling_points": ["Listed company, properties, hospitality, logistics", "Management level role, report to Group IT Director", "Holder of CISA, CISM, CISSP or CCSP"], "locations": ["Central & Western Area"], "categories": ["Information Technology (IT)", "IT Auditing", "Security", "Network & System"], "post_time": "2022-01-14T09:09:23Z", "salary": {"currency": "HKD", "max": 119999, "min": 70000, "period": "monthly", "term": null}, "salary_visible": true, "title_keywords": ["manager"], "responsibilities": ["information security", "data", "guidelines", "policies", "review", "systems", "audit", "infrastructure", "communication", "recruitment", "assess risks", "auditing"], "requirements": {"degrees": ["degree or above", "bachelor"], "majors": ["computer science"], "languages": ["english", "chinese"], "language_level": ["good command"], "hard_skills": ["problem-solving skills"], "soft_skills": ["confidence", "positive mindset", "willing to learn", "pleasant", "communication", "problem-solving skills", "interpersonal"], "languages_combined": [{"language": "english", "language_level": ["good command"]}, {"language": "chinese", "language_level": ["good command"]}]}, "experience_required": {"duration": ["at least 10 years"], "field": ["security", "education"]}}, {"job_id": "100003009039682", "location_code": "hk", "company": "Michael Page", "job_title": "IT Audit Manager (60K) - HK Listed Co", "description": "Responsibilities:\n\nConduct audit assignments/control assessments involving Information Technology (IT) applications, infrastructure controls and regulatory requirements including TM-E-1, TM-G-1, SA-2, CDP and C-RAF\nConduct project reviews on critical IT development programmes to ascertain adequacy of project and change management processes for effective implementation\nIdentify and recommend areas for improvements in internal control and operational efficiency\nManage audit relationship with the related IT units management and conduct continuous monitoring on IT areas to assess the associated risks\nTrack and follow up to ascertain open audit/regulatory issues related to IT are timely and satisfactorily rectified\nAssist in development of Computer Assisted Audit Techniques (CAATs)\n\nRequirements:\n\nDegree holder in Information Systems, Computer Science or related disciplines\nMinimum 5 years\u2019 experience in IT internal/external audit or IT risk management, candidate with less experience will also be considered\nCandidate with substantial system development or IT operations experience is preferred\nSound understanding of IT application, infrastructure controls and regulatory requirements including TM-E-1, TM-G-1, SA-2, CDP and C-RAF\nGood analytical, interpersonal and communication skills\nGood report writing skills in Chinese and English\nProfessional qualifications such as CISA, CISM or CISSP and experience of developing Computer Assisted Audit Techniques (CAATs) would be an advantage", "employment_types": ["Full Time", "Permanent"], "selling_points": ["MNC platform with amazing career prospect", "Renowned market leader", "Group level IT Audit position"], "locations": ["Not Specified"], "categories": ["Accounting", "Audit", "Others", "Information Technology (IT)", "IT Auditing"], "post_time": "2022-01-11T10:29:26Z", "salary": {"currency": null, "max": null, "min": null, "period": "monthly", "term": null}, "salary_visible": false, "title_keywords": ["manager"], "responsibilities": ["control", "management", "change management", "regulatory requirements", "infrastructure", "audit", "implementation", "continuous monitoring", "internal control"], "requirements": {"degrees": ["degree holder"], "majors": ["related disciplines", "computer science"], "languages": ["english", "chinese"], "language_level": ["good"], "hard_skills": ["c", "writing skills", "professional qualifications"], "soft_skills": ["communication skills", "interpersonal", "writing skills"], "languages_combined": [{"language": "english", "language_level": ["good"]}, {"language": "chinese", "language_level": ["good"]}]}, "experience_required": {"duration": ["minimum 5 years"], "field": ["risk management", "audit", "developing", "system development", "it", "it operations"]}}, {"job_id": "100003009046580", "location_code": "hk", "company": "Michael Page", "job_title": "Information Security Analyst / Manager", "description": "You will be responsible for Group IT and Cybersecurity audits and related services of the Group.\n\nClient Details\n\nOur Client is HK Listed Conglomerate with steady expansion.\n\nDescription\n\nYou will work with growing team and act as business partner of management for risk-based audits and controls over IT and Cybersecurity operations. You will cover both financial and operational audits in different BUs to ensure group compliance aligning with all relevant regulations, laws and standards.\n\nProfile\n\nBachelor degree holder in Computer Science, with relevant Professional Qualification such as CISA, CISSP\nMinimum 4 years of work experience in IT Audit / Cyber Security\nAble to multi-task and take ownership of issues and initiatives;\nExcellent in both spoken and written English and Chinese, including Putonghua\nA self-starter, highly motivated and team orientated with a strong delivery focus\nCandidates will be considered as Assistant Manager/Senior Manager depending on experience\n\nJob Offer\n\nOur client offers a competitive package and an encouraging work environment focused on growth, excellence, and success with the company opportunities for career advancement.\n\nTo apply online please click the Apply button below. For a confidential discussion about this role please contact Erin Cheung on +852 2848 9579", "employment_types": ["Full Time", "Contract"], "selling_points": ["Large Conglomerate", "Large Scale digital projects", "Governance, Risk, Compliance, Threat, Data Lost"], "locations": ["Not Specified"], "categories": ["Information Technology (IT)", "IT Auditing", "Security", "Network & System"], "post_time": "2022-01-13T14:51:52Z", "salary": {"currency": null, "max": null, "min": null, "period": "monthly", "term": null}, "salary_visible": false, "title_keywords": ["analyst", "manager"], "responsibilities": ["regulations", "management", "cyber security", "operations", "compliance", "audit", "contact", "audits"], "requirements": {"degrees": ["bachelor degree holder"], "majors": ["computer science"], "languages": ["putonghua", "english", "chinese"], "language_level": ["excellent"], "hard_skills": ["focus", "cyber security"], "soft_skills": ["multi-task", "focused", "responsible", "motivated", "focus"], "languages_combined": [{"language": "putonghua", "language_level": ["excellent"]}, {"language": "english", "language_level": ["excellent"]}, {"language": "chinese", "language_level": ["excellent"]}]}, "experience_required": {"duration": ["minimum 4 years"], "field": ["it", "security", "audit"]}}, {"job_id": "100003009044845", "location_code": "hk", "company": "FWD Life Insurance Company (Bermuda) Limited", "job_title": "Manager, Internal Audit", "description": "Cyber Security Manager\n\nOur client is a publicly listed company with international businesses in properties, hospitality, logistics. They are currently looking for a Cyber Security Manager in group level to join their IT team in Hong Kong.\n\n\nResponsibilities\n\nTo strengthen 24/7 security operations capabilities, especially on incident response\nEnforce good cyber hygiene and conduct cyber security awareness program\nConduct cyber security reviews and risk assessments on new technologies, IT systems and digitization solutions\nDefine and implement cyber security improvement projects to counter latest cyber threats\nDevelop and maintain cyber security policy, standards and guidelines\nOversee IT Disaster Recovery (DR) capability and conduct regular ITDR drills\nPlan and manage cyber security budget and measure its effectiveness\nAutomate security operations and upkeep the technical capabilities of the team\nParticipate in deployment and maintenance of enterprise security documents\n\nRequirements\n\nBachelor Degree in Computer Science, Engineering, information security, related disciplines\n8 years of experience in cyber security, with at least 3 years in management role\nExperience in supporting endpoint security solutions, McAfee, Symantec, Carbon Black, FireEye HX etc.\nGood understanding of common cyber-threats, penetration/intrusion techniques and attack vectors\nUnderstanding of CVSS, CVE, CWE, CPE, CCE, CWE, OVAL, SCAP and/or other standards\nKnowledge in SIEM solutions (Splunk, QRadar, ArcSight, AlienVault, etc.),\u00a0Azure, AWS\nFamiliar with IT protocols, security products, cyber security and data protection standards\nExcellent interpersonal and presentation skills\nFluency in written and spoken English & Cantonese\nHolder of CISA, CISM, CISSP or CCSP\n\nWhat does it mean for you\n\nThis is an excellent opportunity to join a reputable and growing company. The position is ideal for professional in IT security to take a permanent role and seek for career progression in a global enterprise.\n\nTo Apply\n\nIf you feel your experience and professionalism can make an impact with this firm, please click the Apply now button.\n\nDue to a\u00a0high volume of applicants,\u00a0only\u00a0shortlisted candidates will be contacted.\n\nPersonal data provided by job applicants will be used strictly in accordance with the employer's personal data policies and for recruitment services purposes only.", "employment_types": ["Full Time"], "selling_points": ["Present concise and quality audit report", "Monitor the completion of corrective audit actions", "Engage to continuous knowledge development"], "locations": ["Kwun Tong"], "categories": ["Accounting", "Audit", "Information Technology (IT)", "IT Auditing"], "post_time": "2022-01-13T06:27:08Z", "salary": {"currency": null, "max": null, "min": null, "period": "monthly", "term": null}, "salary_visible": false, "title_keywords": ["manager"], "responsibilities": ["maintenance", "cyber security", "guidelines", "operations", "systems", "budget", "develop", "hygiene", "maintain", "plan"], "requirements": {"degrees": ["degree", "bachelor"], "majors": ["related disciplines", "engineering", "computer science"], "languages": ["cantonese", "english"], "language_level": ["fluency"], "hard_skills": ["make", "aws", "azure", "cyber security"], "soft_skills": ["presentation skills", "interpersonal", "ideal"], "languages_combined": [{"language": "cantonese", "language_level": ["fluency"]}, {"language": "english", "language_level": ["fluency"]}]}, "experience_required": {"duration": ["at least 3 years", "8 years"], "field": ["management", "security"]}}, {"job_id": "100003009046037", "location_code": "hk", "company": "Dah Chong Hong Holdings Limited", "job_title": "Senior Security Analyst (CN) \u2013 Cyber and Information Security (GIT-CN)", "description": "Attractive remuneration package\nStable and attractive work platform for career progression\n\nClient Details\n\nOur client is a leading HK Listed Company with a good reputation in the industry. They are now looking for a high-calibre candidate to join as IT Audit Manager.\n\nDescription\n\nReporting to Head of Audit, you will:\n\nConduct IT audit assignments and review IT systems to assess adequacy and effectiveness of internal controls and systems security\nDevelop audit plans for areas including technology general controls, application controls, IT infrastructure\nConduct IT risk assessments and in-depth technology governance review\nConduct Cybersecurity reviews on new technologies, IT systems and digitization solutions\nProvide valuable recommendations to enhance internal controls and mitigate IT risks across the Bank\n\nProfile\n\nBachelor degree in Finance, Business, Information Engineering or Computer Science with professional IT auditing qualification such as CISA, CISSP, CPA or equivalent\nMinimum of 8 years of IT audit experience in Big 4 plus additional in-house experience gained from sizeable organizations\nFamiliar with IT infrastructure, software development, information security, data management, digital transformation and project management\nExperience in emerging technologies, data analytics and business intelligence\nOutstanding interpersonal and communications skills in both English and Chinese\nStrong problem-solving skills with demonstrated ability to drive business performance and change\n\nJob Offer\n\nCompetitive pay and remuneration package\n5-day work week\nStable work environment\nMedical coverage\nShuttle bus offered\nWork-life balance\n\nTo apply online please click the 'Apply' button below. For a confidential discussion about this role please contact Yamen Cheung on +852 2848 9575.", "employment_types": ["Full Time", "Permanent"], "selling_points": [], "locations": ["Kowloon Bay"], "categories": ["Information Technology (IT)", "IT Auditing", "Security", "Others"], "post_time": "2022-01-13T09:30:35Z", "salary": {"currency": null, "max": null, "min": null, "period": "monthly", "term": null}, "salary_visible": false, "title_keywords": ["analyst"], "responsibilities": ["reporting", "management", "it infrastructure", "software", "information security", "data", "review", "systems", "audit", "develop", "project management", "contact", "plans", "auditing"], "requirements": {"degrees": ["degree", "bachelor"], "majors": ["engineering", "finance", "business", "it", "computer science"], "languages": ["english", "chinese"], "language_level": [], "hard_skills": ["plus", "data management", "data analytics", "cpa", "project management", "problem-solving skills", "business intelligence"], "soft_skills": ["problem-solving skills", "project management", "stable", "interpersonal"], "languages_combined": [{"language": "english", "language_level": []}, {"language": "chinese", "language_level": []}]}, "experience_required": {"duration": ["minimum of 8 years"], "field": ["business", "audit experience", "it", "big 4"]}}, {"job_id": "100003009045468", "location_code": "hk", "company": "Michael Page", "job_title": "Information Security Officer / AM (Regional role)", "description": "Support Information security projects, security solution design, deployment, risk assessment and technical advisory under IS policy and compliance.\n\nClient Details\n\nOur client is a renowned conglomerate in HK.\n\nDescription\n\nDevelop, maintain and enforce Information Security Policy in accordance with industry standard, best practice and relevant regulatory requirements\nDrive system's security enhancement programme\nAssist security governance in the corporate\nSupport security solution design, deployment and necessary documentation in order to ensure compliance to the project development lifecycle, and getting endorsement from IT governance board and technical groups\nIntegrate current and emerging security control policies into security systems, and develop and support documentation and SOPs\nCarry out proper configuration of security solutions applied in protecting company asset such that the implemented SIEM solution reports all pertinent events\n\nProfile\n\nBachelor's degree in IT or related disciplines\n5 years of relevant working experience\nHands-on experience in developing and enforcing security policies, standards and guidelines for corporate\nCompetent knowledge and good understanding of Information Security framework, standard and regulations\nHolder of professional certificates in CISSP, GIAC, CEH or equivalent will be advantageous\nAdministrate PKI/ Digital Certificate operations.\nExperience in implementing cyber security and/or compliance systems relevant to Governance, Risk and Compliance platform, Data Lost Prevention, Threat Intelligence and/or Firewall Management.\nGood interpersonal, presentation and communication skills\nBe self-motivated, initiative with good problem solving and analytical skills\nGood command of English and Chinese (Putonghua and Cantonese) in both speaking and writing\n\nJob Offer\n\nCompetitive package\n\nTo apply online please click the 'Apply' button below. For a confidential discussion about this role please contact Connie Mo on +852 2848 9540.", "employment_types": ["Full Time", "Permanent"], "selling_points": ["Global role, NA and APAC", "3-5 years of experience in IT security", "Lead teams for network security projects"], "locations": ["Not Specified"], "categories": ["Information Technology (IT)", "IT Auditing", "Security", "Network & System"], "post_time": "2022-01-13T07:54:50Z", "salary": {"currency": "HKD", "max": 54999, "min": 30000, "period": "monthly", "term": null}, "salary_visible": true, "title_keywords": ["officer"], "responsibilities": ["regulations", "information security", "cyber security", "data", "regulatory requirements", "operations", "design", "communication", "maintain", "control", "configuration", "compliance", "developing", "develop", "reports", "management", "contact", "sops", "documentation", "guidelines", "policies", "systems", "ensure compliance"], "requirements": {"degrees": ["certificate", "degree", "bachelor"], "majors": ["related disciplines", "it"], "languages": ["cantonese", "putonghua", "english", "chinese"], "language_level": ["good command"], "hard_skills": ["cyber security", "analytical skills", "problem solving", "deployment", "firewall", "documentation"], "soft_skills": ["initiative", "communication skills", "self-motivated", "competent", "problem solving and analytical skills", "hands-on", "interpersonal", "presentation"], "languages_combined": [{"language": "cantonese", "language_level": ["good command"]}, {"language": "putonghua", "language_level": ["good command"]}, {"language": "english", "language_level": ["good command"]}, {"language": "chinese", "language_level": ["good command"]}]}, "experience_required": {"duration": ["5 years"], "field": ["management", "compliance", "relevant working experience", "developing", "security"]}}, {"job_id": "100003009043787", "location_code": "hk", "company": "Valuable Capital Limited", "job_title": "Information Security  / System Compliance Manager", "description": "Established in Asia in 2013 with a trailblazer mentality, FWD is the primary insurance business of investment group, Pacific Century Group (PCG), with minority shareholders Swiss Re Group, GIC Ventures, RRJ Capital and Hopu Investments.\n\nFWD spans 10 markets in Asia including Hong Kong SAR & Macau SAR, Thailand, Indonesia, the Philippines, Singapore, Vietnam, Japan, Malaysia and Cambodia. In Hong Kong, FWD offers life and medical insurance, general insurance, employee benefits, and financial planning. We focus on creating fresh customer experiences and making the insurance journey simpler, faster and smoother, with innovative propositions and easy-to-understand products, supported by digital technology. Through this customer-led approach, FWD aims to be a leading pan-Asian insurer by changing the way people feel about insurance.\n\nIf you are looking for a company where can fuel your inspiration and cultivate your expertise, join us on our exciting journey.\n\nThe Job\n\nLead and/or carry out the execution of the full audit cycle including risk assessment and control management over operations\u2019 effectiveness, financial reliability and compliance with all applicable directives and regulations\nDevelop and present concise and quality audit reports with practical, effective and actionable recommendations\nParticipate in the development of the annual audit plan and the audit methodology.\u00a0 Through regular and proactive interaction with management, as well as analysis of management information and business activities.\nAssist in the preparation of regular departmental reports\nProactively monitor the completion of corrective audit actions and, as necessary, advises management of past due actions.\nRemain responsive and partner with management while maintaining independence\nEngage to continuous knowledge development regarding sector\u2019s rules and\u00a0 regulations, best practices, tools, techniques and performance standards\n\nThe Person\n\nDegree from recognized university\nAt least 5 years of insurance/finance experience in both external and internal audit, preferably in Asia\nProfessional qualification internal audit or accountancy e.g. HKICPA, ACCA ICAEW\nSolid knowledge of insurance products, operational processes, accounting principles and control concepts\nStrong knowledge of Internal audit methodology and risk management frameworks\nHigh attention to details and have good analytical skills\nA team player with excellent communication skills\nGood interpersonal, coaching / influencing skill\nAgent for change, where change is needed\nCandidate with more experience will be considered as Senior Manager, Internal Audit\n\nWe offer 5-day work, 20-22 days annual leaves, excellent learning & development opportunities and an attractive package to the right candidate.\u00a0\n\nInformation collected will be treated in strict confidence and used solely for recruitment purpose. The company will retain all applications no longer than 24 months of which will be destroyed thereafter. When there are vacancies in any of our subsidiaries, holding companies, associated or affiliated companies of, or companies controlled by, or under common control with the Company during that period, we may transfer your application to them for consideration of employment. We are an equal opportunity employer. We do not discriminate on the basis of race, sex, disability or family status in employment process.", "employment_types": ["Full Time"], "selling_points": ["System Compliance", "IT Audit", "Fin-tech exposure"], "locations": ["Sheung Wan"], "categories": ["Information Technology (IT)", "IT Auditing", "Professional Services", "Legal & Compliance"], "post_time": "2022-01-13T01:56:53Z", "salary": {"currency": null, "max": null, "min": null, "period": "monthly", "term": null}, "salary_visible": false, "title_keywords": ["compliance manager"], "responsibilities": [], "requirements": {"degrees": [], "majors": [], "languages": [], "language_level": [], "hard_skills": [], "soft_skills": [], "languages_combined": []}, "experience_required": {"duration": [], "field": []}}, {"job_id": "100003009056085", "location_code": "hk", "company": "DFI Retail Group DFI\u96f6\u552e\u96c6\u5718", "job_title": "IT Audit (Assistant) Manager", "description": "The Job\n\nA regional audit position that will execute and lead IT audit engagements, in areas covering IT general controls, application controls, IT infrastructure and IT security, system implementation and project management controls\nAble to assess business impact of IT risks and independently evaluate control efficiency and effectiveness\nSuggest practical and value-added recommendations to management for risk mitigation and process improvement\nProduce reports with audit findings and recommendations in a timely manner, and follow-up on audit findings to ensure implementation of audit recommendations\nProvide business partnering advice to stakeholders on strengthening IT control environment\nSupport Head of IT Audit in preparation of annual audit plan, regular reporting and half-yearly Audit Committee preparation\n\nThe Person\n\nBachelor degree holder in Information Technology, Computer Science or other related disciplines\nRelevant professional qualifications (e.g. CIA, CISA, and CISSP) are preferred\nAt least 2 years' experience in IT or Audit field, preferably in the Retail industry\nExperience working in IT Audits / IT Risk Advisory within a Big Four will be an advantage\nPractical experience and knowledge in IT risk, IT general controls, IT security and IT system implementation / transformation\nProficiency in any data analytical tools will be an advantage (e.g. ACL, Python, SQL, Tableau)\nStrong analytical, project management, communication and presentation, problem solving and leadership skills. Able to work independently and together as a team player\nGood command of both written and spoken English and Chinese\n\nDFI Retail Group is an equal opportunity employer and responsible for ensuring that all personal information collected from each Candidate presented to DFI Retail Group is used for recruitment purposes only and the personal data will be kept and handled confidentially. We will retain the applications of candidates not selected for a period of no more than 24 months. The data collection process is in accordance with all applicable laws and compliant with the Code of Practice on Human Resource Management.\n\nTo find out more about Our Businesses and Our People, please visit our website: https://www.DFIretailgroup.com\n\n\u00a0\nIssued by The Dairy Farm Company, Limited", "employment_types": ["Full Time"], "selling_points": ["Minimum 2 years of IT audit experiences", "Big Four experience is preferred", "Hands-on experience in Cybersecurity"], "locations": ["Quarry Bay"], "categories": ["Information Technology (IT)", "IT Auditing"], "post_time": "2022-01-18T03:15:39Z", "salary": {"currency": null, "max": null, "min": null, "period": "monthly", "term": null}, "salary_visible": false, "title_keywords": ["manager", "assistant"], "responsibilities": ["reporting", "control", "management", "it infrastructure", "annual audit", "a timely manner", "implementation", "audit", "evaluate", "project management", "reports", "plan"], "requirements": {"degrees": ["bachelor degree holder"], "majors": ["related disciplines", "computer science", "information technology"], "languages": ["english", "chinese"], "language_level": ["good command"], "hard_skills": ["no", "professional qualifications", "tableau", "python", "sql", "project management", "problem solving", "system implementation", "code"], "soft_skills": ["work independently", "responsible", "leadership skills", "communication", "project management", "problem solving", "team player", "presentation"], "languages_combined": [{"language": "english", "language_level": ["good command"]}, {"language": "chinese", "language_level": ["good command"]}]}, "experience_required": {"duration": ["at least 2 years"], "field": ["retail industry", "audit", "big four", "it", "security"]}}, {"job_id": "100003009055788", "location_code": "hk", "company": "Hong Kong Express Airways Limited", "job_title": "Assistant Manager, Risk & Security (IT)", "description": "DEAR TALENT, YOUR MOVE!\n\nBeing the new rising airline since 2013, we are the Hong Kong\u2019s only Low Cost Carrier (LCC) offering you safe and flexible service options to Hong Kong and beyond.\n\nWe\u2019re on a mission to inspire you to be different, to shake things up, to inspire the spirit of adventure by bringing you to fascinating destinations that few others serve.\n\nSpread your wings and fly with us!\n\n\nWhat will you do?\u00a0\n\nConduct security risk assessment for new business initiatives and solutions;\nRegular review and apporve security guidelines and procedures to strengthen current Security Operation Framework;\nPerform threat management, threat modeling, identify threat vectors and develop use cases for security monitoring;\nResponsible in reviewing security incident Reports;\nFormulate and direct incident response efforts, prioritize those response efforts;\nDesign and conduct cyber-attack simulation to evaluate the effectiveness of cyber defences across different technology layers;\nEnhance company\u2019s cybersecurity maturity and situational awareness;\nPrepare reports, dashboards, metrics for SOC operations and presentation to Senior Management;\nManage execution of action plans to ensur safety and security of all IT assets;\nManage all aspects of outsourced Security Operation Center;\nDevelop security architecture, security policies, principles and standards;\nParticipate in Audits and help remediate the findings;\nAssist Data Protection Officer in enforcing data privacy requirements for IT systems;\nSupport for emergency, if any;\nOther ad-hoc duties as assigned.\n\nWe are a perfect match, if you are:\n\nBachelor Degree in Computer Science or IT related discipline;\nMinimum 6 years\u2019 working experience, with minimum 3 years\u2019 hands on experience in Information Security, Internal Control or Operations Risk;\nStrong understanding of vulnerability classes, networking protocols, operating systems, and cyber security concepts and technologies;\nExperience in Security Operations, SOC, SIEM, Incident Response, and Threat Intelligence is preferred\nExperience in Penetration testing and common vulnerability assessment tools, as well as, using MITRE ATT&CK or similar frameworks;\nFamiliar with various IT governance framework CobiT, PCI-DSS, NIST, ISO27001, ISO20000, ITIL respectively;\nPassion for cybersecurity and staying up-to-date with current threats, tools and techniques;\nPractical experience of technical and security configuration, operation and administration in Windows OS, Active Directory, Domain Group Policy, Networking, security devices (firewall, NAS, etc.) are essential;\nKnowledge of Cloud environments such as AliClould, Azure and GCP;\nPossess CISSP, CSX, CISA, CISM or other information systems security certifications preferred;\nAbility to communicate about various IT security measures with non-technical audience;\nDemonstrated ability to prioritize and meet scheduled deliverables and commitments while managing multiple tasks;\nAble to work on own initiative with minimal direction and handle multiple assignments independently;\nGood command in both written and spoken English and Chinese.\n\nYour Future Work Life?\n\nWork flexibly with staggered working hours and flexible workplace\nDress Casual and Smart everyday\nWork in a newly-designed office with open seating, stylish breakout areas, game room, gym and free coffee\u2026\nWork with a group of energetic and multicultural professionals (up to 50 nationalities!)\nHave great fun in Snack Friday, New Year Market, Fly with your Kids Day, Basketball Team\u2026\nHave your voice heard through Townhalls, Crew forums, CEO live sessions etc.\n\nWhat will you enjoy?\n\nFly anywhere we fly for free plus taxes during leisure with your friends and family\nSpecial privileges to buy duty free products\nCareer Express\n\n\n\nYou will be inspired by our core values.\nYou will be inspired by our vibrant, efficient and entrepreneurial spirit. Join our fun, collaborative and reliable team to ignite your dream!\n\n\n\nInterested? It\u2019s time to have YOUR MOVE!\nIf you're ready to embark your adventure, start by clicking the \u2018Apply now\u2019 and get on the plane to fly with HK Express!\u00a0", "employment_types": ["Full Time"], "selling_points": ["Conduct security risk assessment", "Enhance company\u2019s cybersecurity maturity", "5-day work/ flexible work place/ flexible working"], "locations": ["Tung Chung"], "categories": ["Information Technology (IT)", "IT Auditing", "IT Project Management / Team Lead", "Security"], "post_time": "2022-01-18T02:57:04Z", "salary": {"currency": null, "max": null, "min": null, "period": "monthly", "term": null}, "salary_visible": false, "title_keywords": ["assistant manager,"], "responsibilities": ["business initiatives", "information security", "data", "cyber security", "operations", "active directory", "design", "regular review", "plans", "senior management", "penetration testing", "internal control", "administration", "configuration", "develop", "reports", "architecture", "operating systems", "cost", "management", "monitoring", "procedures", "security operation", "ad-hoc duties", "audits", "guidelines", "policies", "systems", "evaluate", "prepare reports"], "requirements": {"degrees": ["degree", "bachelor"], "majors": ["it", "computer science"], "languages": ["english", "chinese"], "language_level": ["good command"], "hard_skills": ["itil", "plus", "azure", "active directory", "cyber security", "fun", "airline", "safe", "os", "lcc", "firewall", "nas", "internal control"], "soft_skills": ["flexible", "initiative", "efficient", "independently", "responsible", "passion for", "multiple tasks", "collaborative", "prioritize", "energetic", "hands on", "reliable", "ad-hoc duties", "active", "presentation"], "languages_combined": [{"language": "english", "language_level": ["good command"]}, {"language": "chinese", "language_level": ["good command"]}]}, "experience_required": {"duration": ["minimum 6 years", "minimum 3 years"], "field": ["administration", "operation", "security", "testing"]}}, {"job_id": "100003009051097", "location_code": "hk", "company": "Pinpoint Asia Limited", "job_title": "IT Audit Manager - Leading Bank", "description": "Our client, a leading bank, is looking for an experienced IT Audit Manager to join their Audit 3LOD team. The successful candidate will be bringing IT audits especially for their Cyber Security and new digital banking initiatives.\u00a0\n\nResponsibilities:\n\nLead the IT Audit across audit plans, and methods across various IT areas including Cyber Security, Digital, Banking Procedures and IT Controls.\nConduct risk assessment, audit planning, audit testings, control evaluation, etc. Provide audits finding reports, follow-up, and verifications.\nDevelop and monitor cybersecurity development initiatives, through design and perform of continuous risk assessment methodology\nPerform Investigation on technology-related frauds and incidents.\nWork closely with the management through tracking and reporting function, to ensure a timely response to executives, board, and regulators.\nStay up-to-date with evolving industry and regulatory change requirements which may impact the business and technology team.\nUpdate and maintain Audit systems and provide suggestions on efficiency and effectiveness improvement.\u00a0\n\n\u00a0Required Skills/Experience:\n\nAt least 4 years of experience in the IT Audit area, ideally with exposure to the banking / financial services industry.\nUnderstanding regulatory requirements including HKMA is highly preferable.\nUnderstanding of banking information security and information technology governance and assessment.\nOutstanding communication and interpersonal skills. Ability to work effectively with all levels of the organization.\nStrong analytical skills required to enable independent research and accurate assessments of risk management process effectiveness and adherence to regulatory requirements.\nCISA, CISM, CISSP, or equivalent industry certification is preferred.\n\nIf this outstanding opportunity sounds like your next career move, please send your resume in Word format to Danny Kwan at resume(at)pinpointasia(dot)com and put IT Audit Manager - Leading Bank in the subject header.\n\nData provided is for recruitment purposes only.", "employment_types": ["Full Time", "Permanent"], "selling_points": ["IT Audit", "Cybersecurity", "Leading Well-known Bank"], "locations": ["Not Specified"], "categories": ["Information Technology (IT)", "IT Auditing", "Security", "Technical / Functional Consulting"], "post_time": "2022-01-15T02:10:20Z", "salary": {"currency": "HKD", "max": 69999, "min": 45000, "period": "monthly", "term": null}, "salary_visible": true, "title_keywords": ["manager"], "responsibilities": ["information security", "cyber security", "data", "regulatory requirements", "audit", "design", "communication", "maintain", "evaluation", "plans", "control", "monitor", "develop", "reports", "banking", "reporting", "management", "procedures", "investigation", "audits", "tracking", "systems", "recruitment", "planning"], "requirements": {"degrees": [], "majors": [], "languages": [], "language_level": [], "hard_skills": ["hkma", "word", "analytical skills", "cyber security"], "soft_skills": ["work effectively", "independent", "timely", "analytical skills", "communication and interpersonal skills", "accurate"], "languages_combined": []}, "experience_required": {"duration": ["at least 4 years"], "field": ["financial services industry", "it", "audit", "banking"]}}, {"job_id": "100003009056055", "location_code": "hk", "company": "Mandatory Provident Fund Schemes Authority", "job_title": "Manager \u2013 IT Application Solution (Ref: eMPF2/2022)(eMPF Platform Co Ltd)", "description": "We are now looking for high calibre and passionate individuals to join us to undertake this multi-billion HK dollar transformation project leading the MPF ecosystem to a new era.\u00a0 If you are passionate about creating a positive impact on the working population of Hong Kong and are keen and willing to work in a start-up style environment, please join our growing team to contribute to the transformation journey.\n\n\nKey Accountabilities\n\nReporting to the Senior Manager (Team Head) \u2013 Application System;\nWorking closely with a major third party supplier as an \u201cintelligent customer\u201d and \u201ccritical friend\u201d on the delivery of the eMPF Platform project, including system analysis, system design, system development, testing, migration and implementation;\nWorking across all system interfaces areas with stakeholder\u2019s systems;\nReviewing contractual deliverables and providing recommendation for acceptance / payment / need for revision;\nManaging the contractors, and providing technical comments to the development activities; and\nAny other duties as assigned.\n\nSkills and Qualification\n\nBachelor\u2019s degree or Master\u2019s degree in Computer Science or related disciplines;\nIdeally CMMI- DEV (Capability Maturity Model Integration \u2013 Development) certified;\nMinimum 8 years of relevant IT - SDLC (System Development Life Cycle) and IT vendor management experience preferably in Financial Services environment;\nSolid experience in working with suppliers in delivering large-scale system solutions including practical experience with web and mobile apps development, data lake and data visualization and involved in 2 large projects in implementing a complex system;\u00a0\nHands-on technical skills and experience in application of modern technology, such as Cloud technology, Cyber security, DevOps, Micro services architecture, Kubernetes, Level 1 to 4 system level definition, mobile and portal development, BI, API, Messaging, Java, JSON, Databases (example: Oracle, Mongo, Microsoft SQL and MYSQL);\nStrong project management experience;\nDriven, positive, highly structured, proactive, and analytical;\nExcellent organization and problem solving skills, and be able to work under pressure;\nGood command of both spoken and written Chinese and English; and\nKeen and willing to work in a start-up style environment with all the flexibility that requires and level of change involved.\n\nRemuneration Package\n\nRank and salary will be commensurate with qualification and experience. The initial appointment will be made on a fixed-term contract.\u00a0 A competitive remuneration and benefits package including discretionary performance-linked variable pay, annual leave, medical, dental and life insurance coverage, and MPF will be offered.\n\nTo Apply\n\nInterested candidates are invited to apply by sending full career details and application letter, quoting the position applied for and job reference number, with information of current and expected remuneration as well as earliest availability\u00a0through the \"Apply Now\" button.\u00a0\n\n\nThe closing date for application is 25 January\u00a02022.\u00a0 Applicants not contacted for follow up within 3 months after the closing date for application may assume that their applications are unsuccessful.\u00a0 Applications not selected for further processing may be considered for relevant openings in the future but their applications will not be retained for more than a period of two years after the closing date.\n\nThe information provided will be kept confidential and only be used for those purposes relating to your application.\u00a0 Please visit our website for the details of the MPFA\u2019s Personal Information Collection Statement at https://www.mpfa.org.hk/en/mpfa/joining-mpfa/job-vacancies/personal-information-collection-statement.\u00a0 The MPFA is an equal opportunities employer and welcomes applications from all qualified candidates.", "employment_types": ["Full Time", "Contract"], "selling_points": [], "locations": ["Ngau Tau Kok"], "categories": ["Banking / Finance", "Project Finance", "Information Technology (IT)", "IT Auditing", "IT Project Management / Team Lead"], "post_time": "2022-01-18T03:13:55Z", "salary": {"currency": null, "max": null, "min": null, "period": "monthly", "term": null}, "salary_visible": false, "title_keywords": ["manager"], "responsibilities": ["any other duties", "visualization", "data", "cyber security", "payment", "work under pressure", "implementation", "application system", "testing", "migration", "architecture", "reporting", "management", "mpf", "third party", "analysis", "systems", "comments", "project management", "system design", "databases", "insurance"], "requirements": {"degrees": ["degree", "bachelor", "master"], "majors": ["related disciplines", "computer science"], "languages": ["english", "chinese"], "language_level": ["good command"], "hard_skills": ["java", "bi", "web", "cyber security", "analysis", "devops", "vendor", "application system", "sql", "mobile", "sdlc", "system design", "project management", "databases", "data visualization", "integration", "problem solving skills", "oracle"], "soft_skills": ["passionate", "passionate about", "proactive", "keen", "project management", "hands-on", "technical skills", "problem solving skills", "structured", "driven", "positive", "work under pressure"], "languages_combined": [{"language": "english", "language_level": ["good command"]}, {"language": "chinese", "language_level": ["good command"]}]}, "experience_required": {"duration": ["minimum 8 years"], "field": ["management", "development", "devops", "system development", "sql", "project management", "it", "financial services", "security"]}}, {"job_id": "100003009044526", "location_code": "hk", "company": "Grant Thornton Hong Kong Limited", "job_title": "Assistant Manager / Senior Associate / Associate (Forensic Technology) \u2013 Advisory", "description": "Responsibilities:\n\nPerform forensics technology and eDiscovery services including preserving, imaging, processing and reviewing electronic data\nIdentify and capture anomalies and suspicious information within structured and unstructured data, visualize and present findings to client\nAssist the teams on financial due diligence and forensic investigation assignments requiring data analytics support\nAssist in forensic technology and data analytics practice development\n\nRequirements:\n\nBachelor's degree, preferably in Computer Science, Information Systems, and Engineering or equivalent\n4+ years (Assistant Manager) / 2+ years experience (Senior Associate) relating to Forensic Technology, with experience in using EnCase, FTK, Nuix and/or Relativity\nStrong analytical mindset and solid problem solving skills\nExperience in forensic technology case management for Assistant Manager role\nExcellent written and oral communication skills in English, Cantonese and Mandarin Chinese\nWilling to travel on business needs\nCandidates with less experience will be considered as Associate\nPreferred:\n\n\nPossess relevant professional qualification or vendor related certification such as GCFA, GCFE, EnCE, RCA, etc\nQualified or working towards qualification such as CPA, CFE, CIA, CISSP\nExperience in Data Analytics/AI investigation tools is a definite advantage\nExperience with scripting language such as Python or VBA\n\n\n\n\nWe offer attractive remuneration packages including medical insurance and a 5-day working week. Interested applicants please submit your full resume, current and expected salary by clicking \u201cAPPLY NOW\u201d or by post to The Human Resources Department, Grant Thornton Hong Kong Limited, 11th Floor, Lee Garden Two, 28 Yun Ping Road, Causeway Bay, Hong Kong. www.grantthornton.cn\n\nNote:\u00a0\u00a0\u00a0\u00a0\u00a0\u00a0 You may consider your application unsuccessful if you do not hear from us within 8 weeks. Your personal data will be destroyed within one month after completion of the recruitment process.", "employment_types": ["Full Time", "Permanent"], "selling_points": ["Degree holder in CS, IS, Engineering", "4+ / 2+ years exp relating to Forensic Technology", "5-day working week"], "locations": ["Causeway Bay"], "categories": ["Accounting", "Consulting", "Others", "Information Technology (IT)", "IT Auditing"], "post_time": "2022-01-13T04:27:10Z", "salary": {"currency": null, "max": null, "min": null, "period": "monthly", "term": null}, "salary_visible": false, "title_keywords": ["assistant manager", "associate", "senior associate"], "responsibilities": ["due diligence", "teams", "investigation", "data"], "requirements": {"degrees": ["degree", "bachelor"], "majors": ["engineering", "computer science"], "languages": ["cantonese", "english", "mandarin chinese"], "language_level": ["excellent"], "hard_skills": ["vba", "ai", "data analytics", "vendor", "cpa", "python", "problem solving skills"], "soft_skills": ["communication skills", "problem solving skills", "oral"], "languages_combined": [{"language": "cantonese", "language_level": ["excellent"]}, {"language": "english", "language_level": ["excellent"]}, {"language": "mandarin chinese", "language_level": ["excellent"]}]}, "experience_required": {"duration": ["2+ years", "4+ years"], "field": ["management"]}}, {"job_id": "100003009042067", "location_code": "hk", "company": "Sunny Hose Co Ltd", "job_title": "IT & ERP Support Officer", "description": "\nWe are the PVC Hose Manufacturer located in Tai Po. We are now inviting applications for the following position:\n\nJob Description and Responsibilities\n\nPerform technical support on network, system, hardware devices, software and application systems.\nProvide helpdesk support and solutions to users\nArrange and monitor routine support jobs; and review event logs and escalate key incidents for management attention\nPerform daily security tasks, such as reviewing security risk reports and event logs, performing diagnosis and responding to security incidents and breaches, investigating phishing emails and websites, etc.\u00a0\nResponsible for the overall in-house and branch sites technical support and maintenance of the network, computer, printer accessories\u2026etc.\nInventory update and control\nResponsible for planning, organizing, directing, and coordinating all activities related to the ERP project\nTo provide user training and support\nTo prepare workflow documentation and user guide if necessary\nTo perform any duties related to IT systems as and when required.\u00a0\u00a0\n\n\nRequirements\n\nDegree holders or High Diploma in Information Technology / Computer Science or other related disciplines; MCSE / CCNA would be an advantage\nAt least\u00a02 years of experience in ERP implementation of Manufacturing & Account Systems\nWorking knowledge in IT security operation, preferably with CISSP, CISA, CCSP or CCSK\u00a0\nSolid experience in supporting MS Windows and Office applications and desktop hardware\nSelf-motivated with good interpersonal and task management skills\nDetail-minded, committed to work and able to prioritize effectively\nWell organized and able to work independently under pressure and tight deadlines.\nFluent spoken in both English & Cantonese\nCandidates with less experience will be considered as Assistant IT Support Officer.\n\nWe offer (Double Pay, Alt. Sat Off, $2000\u00a0New Employee Award, Medical Benefit, Shuttle Bus, Education, Traffic, Meal & OT allowance)\n\nAttractive remuneration package will be offered to successful candidate. Interested parties please apply in confidence with full career details,\u00a0date available and expected salary\u00a0to us.\n\nPersonal data provided by job applicants will be used for recruitment administration purposes only and strictly in accordance with the Company\u2019s Personal Data Policy.\u00a0", "employment_types": ["Full Time"], "selling_points": ["2 years of experience in ERP System", "Double Pay, Alt. Sat Off, Shuttle Bus", "Medical, Education, Traffic, Meal & OT allowance"], "locations": ["Tai Po Area"], "categories": ["Information Technology (IT)", "IT Auditing", "IT Project Management / Team Lead", "Network & System"], "post_time": "2022-01-12T23:26:14Z", "salary": {"currency": null, "max": null, "min": null, "period": "monthly", "term": null}, "salary_visible": false, "title_keywords": ["officer"], "responsibilities": ["management", "control", "software", "maintenance", "technical support", "inventory", "review", "monitor", "event logs", "security risk reports", "systems", "hardware", "daily security tasks", "documentation", "application systems", "routine support", "planning"], "requirements": {"degrees": ["high diploma", "degree"], "majors": ["related disciplines", "computer science", "information technology"], "languages": ["cantonese", "english"], "language_level": ["fluent"], "hard_skills": ["mcse", "ms windows", "ccna", "office applications", "erp", "hardware"], "soft_skills": ["detail-minded", "self-motivated", "work independently", "under pressure", "able to prioritize", "well organized", "committed", "interpersonal"], "languages_combined": [{"language": "cantonese", "language_level": ["fluent"]}, {"language": "english", "language_level": ["fluent"]}]}, "experience_required": {"duration": ["at least 2 years"], "field": ["manufacturing", "it support"]}}, {"job_id": "100003009035225", "location_code": "hk", "company": "Hong Kong Exchanges and Clearing Limited", "job_title": "Senior Manager - IT - Compliance & Risk Management - AVP", "description": "Job Responsibilities:\n\n\u00b7 Plan, lead, manage and conduct comprehensive independent reviews based on defined methodology, IT standards and/or industry good practice\n\n\u00b7 Assess adequacy and effectiveness of ITD's internal controls, and properly document the assessment/review procedures performed.\n\n\u00b7 Prepare review reports, articulate and present any issues, root causes and recommended actions to management\n\n\u00b7 Design and implement continuous monitoring controls using automated or data analytics tools \u00b7 Coordinate with other IT teams to address control weaknesses, including design and implement new controls to address known issues\n\n\u00b7 Proactively track, follow-up and report implementation status of issue remediation and risk mitigation\n\n\u00b7 Formulate and manage IT standards and procedures \u00b7 Organise and conduct training to improve awareness of control requirements stated in IT standards, and/or any industry good practices\n\n\u00b7 Work closely with Risk, Compliance and Internal Audit for risk mitigation and control improvements \u00b7 Coach team members and develop their skills in technology risk and compliance\n\nJob Requirements:\n\n\u00b7 University graduate in information technology, information security or related disciplines\n\n\u00b7 Minimum 12 years of relevant experience in technology risk, cybersecurity, technology audit and/or IT compliance gained from financial institutions\n\n\u00b7 Holder of relevant professional certificates, such as, CISA, CISSP, CRISC, CGEIT is preferred \u00b7 Good knowledge of NIST Cybersecurity Framework, ITIL, CMMI, ITSM, COBIT, PMBOK, SDLC, and key IT processes\n\n\u00b7 Practical experience in IT control assessment/auditing, technology risk management, business & system processes review\n\n\u00b7 Experience in designing and implementing new controls to mitigate identified risks\n\n\u00b7 Working knowledge of controls verification using data analytics \u00b7 Experience in reviewing and revising IT standards and procedures\n\n\u00b7 Ability to manage multi-assignments in a dynamic working environment with application of project management skills\n\n\u00b7 Strong problem solving, analytical and presentation skills\n\n\u00b7 Excellent communications skills and advanced reporting writing skill in English and Chinese\n\n\u00b7 Work experience in Big 4 audit firm is an advantage\n\nApplicants who do not hear from us within 6 weeks may consider their applications unsuccessful. Personal data provided will only be used for the purpose of employment application to HKEX.", "employment_types": ["Full Time"], "selling_points": ["IT Compliance", "Internal Controls", "Risk Mitigation"], "locations": ["Tseung Kwan O"], "categories": ["Information Technology (IT)", "IT Auditing", "IT Project Management / Team Lead", "IT Management"], "post_time": "2022-01-10T06:27:16Z", "salary": {"currency": null, "max": null, "min": null, "period": "monthly", "term": null}, "salary_visible": false, "title_keywords": ["senior manager"], "responsibilities": ["analytics tools", "management", "control", "internal audit", "data", "review", "procedures", "coordinate with", "design", "teams", "implementation", "compliance", "develop", "reports", "continuous monitoring", "plan", "report"], "requirements": {"degrees": ["university graduate"], "majors": ["related disciplines", "information technology"], "languages": ["english", "chinese"], "language_level": ["excellent"], "hard_skills": ["itil", "data analytics", "writing skill", "problem solving", "project management", "sdlc", "dynamic", "it processes"], "soft_skills": ["advanced", "project management skills", "writing skill", "problem solving", "presentation skills", "dynamic"], "languages_combined": [{"language": "english", "language_level": ["excellent"]}, {"language": "chinese", "language_level": ["excellent"]}]}, "experience_required": {"duration": ["minimum 12 years"], "field": ["risk management", "compliance", "audit", "big 4", "it", "relevant experience", "business", "financial institutions"]}}, {"job_id": "100003009043293", "location_code": "hk", "company": "Conners Consulting Limited", "job_title": "IT Audit Manager / Assistant Manager  - Listed Bank Group", "description": "Our client, a listed Bank group is seeking for an IT professional to join their management team.\u00a0\n\nYou will be responsible for planning and conducting specialized audits in technology risk area and performing other audits and ad hoc assignments.\u00a0\n\nRequirements\n\nDegree holder in Computer Science or related disciplines\nRelevant professional qualifications (e.g. CISA, CISM, CISSP, ACsP)\nAt least 5 years of experience in IT auditing or banking technology\nSolid knowledge of information technology risk and controls\nWilling to travel to China / Macau occasionally\nGood report writing skills in Chinese and English\n\nTo apply, please send your detailed resume or contact Joe Choi at 2851 7761 for a confidential discussion.\n\nOnly shortlisted candidates will be notified.\nApplicants who are not contacted within two weeks may consider their applications unsuccessful.\nAll data collected will be used for recruitment purpose only & will be used strictly confidential.\n\nConners Consulting Limited\n2005 Kai Tak Commercial Building 317 Des Voeux Road Central Hong Kong\nTel: (852) 3996 8090", "employment_types": ["Full Time"], "selling_points": ["Listed Bank", "IT Audit", "Well established platform & Good prospect"], "locations": ["Central & Western Area"], "categories": ["Information Technology (IT)", "IT Auditing"], "post_time": "2022-01-12T10:30:58Z", "salary": {"currency": null, "max": null, "min": null, "period": "monthly", "term": null}, "salary_visible": false, "title_keywords": ["assistant manager", "manager"], "responsibilities": ["management team", "consulting", "data", "recruitment", "ad hoc assignments", "contact", "banking", "audits", "report", "auditing", "planning"], "requirements": {"degrees": ["degree holder"], "majors": ["related disciplines", "computer science"], "languages": ["english", "chinese"], "language_level": ["good"], "hard_skills": ["writing skills", "professional qualifications"], "soft_skills": ["detailed", "responsible", "writing skills"], "languages_combined": [{"language": "english", "language_level": ["good"]}, {"language": "chinese", "language_level": ["good"]}]}, "experience_required": {"duration": ["at least 5 years"], "field": ["it", "banking"]}}, {"job_id": "100003009044515", "location_code": "hk", "company": "Pinpoint Asia Limited", "job_title": "Data Security Technology Manager - Enterprise Security Office", "description": "Our client, a leading enterprise, is looking for a Data Security Technology Manager in their large Security Technology office in Hong Kong.\u00a0 The successful candidate will be the key person in providing Information Security advisory for their strategic project. Interesting project exposure.\n\nResponsibilities:\n\nManage the IT Security Solutions design, development, and integrations particularly for Data Lake, Data Warehouse, and Analytics. Evaluate the security controls, technical capabilities, and timeline of such technology integrations.\nManage the technical implementation, security solution development across the project development lifecycle working with IT Governance and Technical teams.\nMake decisions and solve technical problems to provide an efficient technical environment for solutions implementation.\nProvide technical support in the security log, feeds, and raw source into SIEM for data security analytics.\nEnable dashboards for monitoring security information for the management and Cyber SOC team, to be able to provide various degrees of visibility in both real-time and past periods of the security events.\n\nRequired:\n\nAround 8 years of technology experience in technology security ideally in a large enterprise environment.\u00a0\nHands-on experience in enterprise security infrastructure and risk assessment.\nBackground and certifications in Information Security and Risk (CISSP, CEH, GIAC, etc)\nWorking experience in information security or IT Audit with consulting firm background is a great plus.\nDeep understanding of database encryption technologies, database proxies, and secure protocols, etc.\nDeep understanding of security threats with respect to SQL injection attacks, virtual private databases and database auditing, searchable encryption.\nAble to implement security solutions such as Demisto, Splunk, ELK, Carbon Black, Darktrace, ALSID, and/or Tufin.\nGood knowledge and experience of Database Security, Data Protection, Database Encryption technologies, Data Flow Mapping etc.\nGood design and solution knowledge of Certificate Authority and PKI infrastructure and operations.\nExperience in managing secure network infrastructure, Anti-DDoS, NG Firewall, IDS/IPS, WAF, Secure MTA, Load Balancer, Internet Proxy, as well as DNS hosting.\nStrong project management and stakeholders management skills.\nExcellent Communications Skills in English.\nBachelor's Degree from a reputable University.\n\nIf this outstanding opportunity sounds like your next career move, please send your resume in Word format to Danny Kwan at resume(at)pinpointasia(dot)com and put Data Security Technology Manager - Enterprise Security Office in the subject header.\n\nData provided is for recruitment purposes only.", "employment_types": ["Full Time", "Permanent"], "selling_points": ["Data Specific Security", "1LOD Blue Team", "Large Enterprise Environment"], "locations": ["Others - Macau"], "categories": ["Information Technology (IT)", "IT Auditing", "IT Management", "Security"], "post_time": "2022-01-13T04:25:10Z", "salary": {"currency": null, "max": null, "min": null, "period": "monthly", "term": null}, "salary_visible": false, "title_keywords": ["technology manager"], "responsibilities": ["information security", "data", "consulting", "operations", "audit", "design", "database", "proxy", "infrastructure", "teams", "implementation", "network infrastructure", "management", "monitoring", "solve technical problems", "dns", "technical support", "evaluate", "project management", "recruitment", "databases", "auditing"], "requirements": {"degrees": ["certificate", "degree", "bachelor"], "majors": ["design"], "languages": ["english"], "language_level": ["excellent"], "hard_skills": ["plus", "dns", "data warehouse", "word", "sql", "make", "project management", "databases", "firewall"], "soft_skills": ["efficient", "project management", "hands-on", "deep"], "languages_combined": [{"language": "english", "language_level": ["excellent"]}]}, "experience_required": {"duration": ["8 years"], "field": ["consulting", "infrastructure", "audit", "it", "security", "database"]}}, {"job_id": "100003009033308", "location_code": "hk", "company": "Michael Page", "job_title": "IT Internal Audit Manager (70K) BIG4 welcome!", "description": "Renowned market leader\nStable and attractive work platform for career progression\n\nClient Details\n\nOur client is a leading HK Listed Company with a good reputation in the industry. It is widely recognised as the market leader and good employer.\n\nDescription\n\nReporting to Head of Audit, you will:\n\nConduct IT audit assignments and review IT systems to assess adequacy and effectiveness of internal controls and systems security\nDevelop audit plans for areas including technology general controls, application controls, IT infrastructure\nConduct IT risk assessments and in-depth technology governance review\nConduct Cybersecurity reviews on new technologies, IT systems and digitization solutions\nProvide valuable recommendations to enhance internal controls and mitigate IT risks across the Bank\n\nProfile\n\nBachelor degree in Finance, Business, Information Engineering or Computer Science with professional IT auditing qualification such as CISA, CISSP, CPA or equivalent\nMinimum of 8 years of IT audit experience in Big 4 plus additional in-house experience gained from sizeable organizations\nFamiliar with IT infrastructure, software development, information security, data management, digital transformation and project management\nExperience in emerging technologies, data analytics and business intelligence\nOutstanding interpersonal and communications skills in both English and Chinese\nStrong problem-solving skills with demonstrated ability to drive business performance and change\n\nJob Offer\n\nCompetitive pay and remuneration package\n5-day work week\nStable work environment\nMedical coverage\nShuttle bus offered\nWork-life balance\n\nTo apply online please click the 'Apply' button below. For a confidential discussion about this role please contact Yamen Cheung on +852 2848 9575.", "employment_types": ["Full Time", "Permanent"], "selling_points": ["Group level IT Audit position", "Stable work environment", "MNC platform with amazing career prospect"], "locations": ["Not Specified"], "categories": ["Accounting", "Audit", "Others", "Information Technology (IT)", "IT Auditing"], "post_time": "2022-01-09T06:26:25Z", "salary": {"currency": null, "max": null, "min": null, "period": "monthly", "term": null}, "salary_visible": false, "title_keywords": ["manager"], "responsibilities": ["reporting", "management", "it infrastructure", "software", "information security", "data", "review", "systems", "audit", "develop", "project management", "contact", "plans", "auditing"], "requirements": {"degrees": ["degree", "bachelor"], "majors": ["engineering", "finance", "business", "it", "computer science"], "languages": ["english", "chinese"], "language_level": [], "hard_skills": ["plus", "data management", "data analytics", "cpa", "project management", "problem-solving skills", "business intelligence"], "soft_skills": ["problem-solving skills", "project management", "stable", "interpersonal"], "languages_combined": [{"language": "english", "language_level": []}, {"language": "chinese", "language_level": []}]}, "experience_required": {"duration": ["minimum of 8 years"], "field": ["business", "audit experience", "it", "big 4"]}}, {"job_id": "100003009045523", "location_code": "hk", "company": "Michael Page", "job_title": "Cyber Security Analyst (Operations)", "description": "Detect, analyse and respond to cyber-attacks, manage incidents and reduce risk\n\nClient Details\n\nOur client is a multinational reputable company with energetic and international teams.\n\nDescription\n\nInstalled, configured, tested and maintained operating systems, application software and system management tools.\nConducted research to test and analyse feasibility, design, operation and performance of SIEM equipment, components and systems.\nInvestigated new and emerging software applications (IDS, IPS, Firewall, Web servers) within SOC to design, select, implement and use administrative information systems effectively.\n\nProfile\n\nExperience with SIEM, incident response and logging environments\nExperience in network-base detection technologies\nGood communication in English\n\nJob Offer\n\nCompetitive package with Double Pay and Performance Bonus\n\nTo apply online please click the 'Apply' button below. For a confidential discussion about this role please contact Connie Mo on +852 2848 9540.", "employment_types": ["Full Time", "Permanent"], "selling_points": ["Multinational reputable company (in-house role)", "Young, energetic and international", "WFH Policy, No Shift"], "locations": ["Not Specified"], "categories": ["Information Technology (IT)", "IT Auditing", "Security", "Network & System"], "post_time": "2022-01-13T08:00:51Z", "salary": {"currency": "HKD", "max": 54999, "min": 35000, "period": "monthly", "term": null}, "salary_visible": true, "title_keywords": ["analyst", "operations"], "responsibilities": ["management", "software", "systems", "teams", "design", "communication", "contact", "analyse", "operating systems"], "requirements": {"degrees": [], "majors": [], "languages": ["english"], "language_level": ["good"], "hard_skills": ["web servers", "firewall"], "soft_skills": ["communication", "energetic"], "languages_combined": [{"language": "english", "language_level": ["good"]}]}, "experience_required": {"duration": [], "field": []}}, {"job_id": "100003009035507", "location_code": "hk", "company": "Grant Thornton Hong Kong Limited", "job_title": "Senior Manager / Manager, IT Advisory", "description": "Grant Thornton\u2019s Advisory professionals are progressive thinkers who create, protect, transform value today, so our clients have the opportunity to thrive and grow. Our advisory practice creates holistic solutions delivered by innovative, curious professionals who bring technical depth and industry insight to our clients. Business risk services protects value.\n\n\nResponsibilities:\n\nLead and execute IT audits and IT-oriented risk advisory projects to multiple listed clients across a variety of industries\nCollaborate on innovative solutions to support the future of the practices\nProvide expertise in at least two or more advanced technology service offerings (e.g. cloud applications, cybersecurity, IT infrastructure, enterprise architecture, etc.).\nAssist clients in applying key frameworks such as COBIT, NIST & ISO\nApply knowledge of IT trends, systems and processes, evaluate findings for significance and risk, and develop recommendations for improvement based on leading practice\nManage business development activities, such as proposals, capture, account teams, whitepapers, conferences, and/or other thought leadership material\nCommunicate potential areas of risk in technology, operations, configuration and user experience in alignment with business stakeholder needs\n\nRequirements:\n\nBachelor's degree in Information Technology, Computer Science, Information Security, Accounting, Finance or a related field (e.g., IT Audit, Enterprise Risk Management, etc.) or equivalent work experience\nCISA, CISSP, CIA, CISM or CPA license/certification preferred\n6 years or above of progressive experience functioning in a technology role, with a strong understanding of IT or cybersecurity, preferably within consulting or professional services environment\nDemonstrate in depth knowledge of IT, cybersecurity, understanding of information security and privacy policies, standards and best practices and knowledgeable on external/internal penetration assessment methodologies\nExperience in performing technology risk assessments, audits as well as process controls review; assessing configuration and controls of Enterprise Resource Planning (ERP) systems (SAP, Oracle, PeopleSoft, Kingdee, etc.); leveraging ACL, IDEA or other data analytics and visualization solutions is a plus\nStrong leadership, business development, project management, recruiting, training, coaching and mentoring skills, coupled with excellent written, interpersonal and presentation skills\nGood command of verbal and written English, Cantonese, and Putonghua\n\nWe offer attractive remuneration packages including medical insurance and a 5-day working week. Interested applicants please submit your full resume, current and expected salary by clicking \u201cAPPLY NOW\u201d or by post to The Human Resources Department, Grant Thornton Hong Kong Limited, 11th Floor, Lee Garden Two, 28 Yun Ping Road, Causeway Bay, Hong Kong. www.grantthornton.cn\n\nNote:\u00a0\u00a0\u00a0\u00a0\u00a0\u00a0 You may consider your application unsuccessful if you do not hear from us within 8 weeks. Your personal data will be destroyed within one month after completion of the recruitment process.", "employment_types": ["Full Time", "Permanent"], "selling_points": ["Degree in IT, CS, Information Security, Acct/ FIN", "6 years\u2019 experience", "5-day working week"], "locations": ["Causeway Bay"], "categories": ["Accounting", "Consulting", "Others", "Information Technology (IT)", "IT Auditing"], "post_time": "2022-01-10T07:29:43Z", "salary": {"currency": null, "max": null, "min": null, "period": "monthly", "term": null}, "salary_visible": false, "title_keywords": ["senior manager", "manager"], "responsibilities": ["collaborate", "it infrastructure", "configuration", "operations", "systems", "teams", "user experience", "develop", "evaluate", "conferences", "audits", "architecture"], "requirements": {"degrees": ["degree", "bachelor"], "majors": ["finance", "accounting", "computer science", "information technology"], "languages": ["cantonese", "putonghua", "english"], "language_level": ["good command"], "hard_skills": ["plus", "sap", "data analytics", "erp", "cpa", "project management", "oracle"], "soft_skills": ["project management", "presentation skills", "progressive", "leadership", "interpersonal"], "languages_combined": [{"language": "cantonese", "language_level": ["good command"]}, {"language": "putonghua", "language_level": ["good command"]}, {"language": "english", "language_level": ["good command"]}]}, "experience_required": {"duration": ["6 years"], "field": ["it", "consulting"]}}, {"job_id": "100003009036180", "location_code": "hk", "company": "West Kowloon Cultural District Authority", "job_title": "Assistant Manager, Business Applications (Ref: R2951)", "description": "You will be responsible for:\n\nassisting in IT solutions from business initiative, system planning, tender preparation to implementation, change management, production deployment, and handling vendor related activities;\nperforming implementation activities including but not limited to business processes mapping, advice for operations improvement, requirements gathering and analysis, system design and analysis, knowledge transfer, and change management processes;\nensuring all applications and solutions operate according to the Authority\u2019s IT standards and industrial best practices, and in a stable and effective manner with good quality, including but not limited to the architecture, coding standards, information security;\ncoordinating post-implementation support and preventative maintenance activities with vendors, IT and business users; and\nkeeping up with the latest technology trend, continuous measure, propose and explore enhancement opportunity to drive operational excellence and effectiveness.\n\nYou should:\n\npossess a recognised university degree in Computer Science, Information Technology or equivalent;\nhave minimum 5 years of relevant IT experience, preferably in sizable organisation;\nhave any prior experience in both functional and technical perspective of Oracle ERP/ Salesforce CRM/ Ticketing System/ Payment Gateway/ Venue and Event Management/ Facility Management/ Workforce Management/ Digital Signage/ E-Tendering/ E-Commerce/ Website Content Management/ Drupal would be an advantage;\nhave knowledge of and experience in digital transformation, mobile app, and cloud technology (AWS or similar) would be an advantage;\nhave solid experience in application development and system design for technology initiatives using a hybrid mix of traditional and agile SDLC methodologies;\nhave strong problem-solving skills, a team player, self-motivated and capable to lead a small team; be innovative with strong enthusiasm in exploring new technologies; and\nbe proficient in written and spoken English and Chinese.\n\nFor interested parties, please submit your application with detailed CV on or before 24 January 2022. Applicants are encouraged to submit their applications as soon as possible.\u00a0 The review of applications will continue until the post is filled.\n\nData collected will only be used for job application processing. Your data may be accessed by our appointed recruitment consultants who have agreed to keep confidence of all personal data in not less than the standards applicable to us. Applicants not being invited for interview within 4 weeks from the submission date may assume their applications unsuccessful.\n\nAll related information will be kept up to 24 months and all personal data will be destroyed afterwards.\n\nFor more information\nhttp://www.westkowloon.hk or contact\nMs. Yuki Ha at 2200-3786", "employment_types": ["Full Time"], "selling_points": ["Assist in IT solutions and implementation activity", "Ensure applications operate according to standards", "Coordinate maintenance activities with vendors"], "locations": ["Tsim Sha Tsui"], "categories": ["Information Technology (IT)", "Application Specialist - Software", "IT Auditing", "Software Development"], "post_time": "2022-01-10T10:05:38Z", "salary": {"currency": null, "max": null, "min": null, "period": null, "term": null}, "salary_visible": false, "title_keywords": ["assistant manager,"], "responsibilities": ["information security", "operations", "quality", "tendering", "coding", "website", "payment", "application development", "mobile app", "implementation", "tender preparation", "architecture", "management", "change management", "maintenance", "analysis", "lead a small team", "system design", "planning"], "requirements": {"degrees": ["university degree"], "majors": ["computer science", "information technology"], "languages": ["english", "chinese"], "language_level": ["proficient"], "hard_skills": ["small", "salesforce", "agile", "maintenance", "e-commerce", "analysis", "vendor", "oracle erp", "aws", "mobile", "sdlc", "system design", "deployment", "problem-solving skills"], "soft_skills": ["self-motivated", "agile", "responsible", "capable", "team player", "organisation", "problem-solving skills", "stable", "innovative", "initiative"], "languages_combined": [{"language": "english", "language_level": ["proficient"]}, {"language": "chinese", "language_level": ["proficient"]}]}, "experience_required": {"duration": ["minimum 5 years"], "field": ["management", "e-commerce", "it experience", "system design", "digital", "application development"]}}, {"job_id": "100003009037856", "location_code": "hk", "company": "China Construction Bank (Asia) Corporation Limited", "job_title": "Information Security Risk Management Professional", "description": "Main Responsibilities\n- Implement systems security polices, perform IT security administration, control, review, and support regular security profile review\n- Manage the technology risk management processes to identify emerging or existing technology-related risks including but not limited to measure the impact, likelihood and direction of technology-related risks, regularly monitor any technology-related issues or incidents and control the risks through preventive, compensating and contingency measures\n- Establish and enforces standard of process related to Technology Risk Management\n- Manage the IT security function to ensure strict adherence to the corporate security control requirements, establishes corporate security policies / standards / baselines and departmental procedures, oversee security administration and control, and conducts regular security profile review\n- Manage and monitor project progress to ensure consistency and uniformity from Information Security Risk perspective\n- Manage cyber security risk and perform investigation of any technology-related frauds and incidents\n- Support internal / external / regulatory audit review and conduct service provider review\n- Ensure awareness of and compliance with IT control policies, corporate standards and regulatory requirements\n- Review security matrix e.g. toxic combination and configuration review\n- On-call standby support is required during non-office hours\n\nRequirements\n- Degree holder in Information Technology or related discipline\n- Minimum 5 years of relevant experience in Technology Risk or Information Security Risk domain, preferably gained from banking / finance industry\n- Experience in technology risk management and IT compliance is an advantage\n- Strong understanding of Information Technology Risk Management\n- Sound knowledge of database, operating systems and information security practices\n- Customer-oriented, good communication and interpersonal skills\n- Holder of ECF-C recognized certification at professional level is required\n- Able to work under pressure and willing to work overtime\n- Strong problem-solving skill and analytical mind set\n- Good command of written and spoken English and Mandarin\n", "employment_types": ["Full Time", "Permanent"], "selling_points": ["Information Security", "Risk Management", "IT compliance"], "locations": ["Kowloon Bay"], "categories": ["Information Technology (IT)", "IT Auditing", "Security"], "post_time": "2022-01-11T04:03:50Z", "salary": {"currency": null, "max": null, "min": null, "period": "monthly", "term": null}, "salary_visible": false, "title_keywords": [], "responsibilities": ["control", "management", "monitor project progress", "information security", "cyber security", "configuration", "policies", "regulatory requirements", "review", "systems", "monitor", "procedures", "investigation", "audit", "compliance", "administration"], "requirements": {"degrees": ["degree holder"], "majors": ["information technology"], "languages": ["english", "mandarin"], "language_level": ["good command"], "hard_skills": ["problem-solving", "c"], "soft_skills": ["work overtime", "problem-solving", "customer-oriented", "communication and interpersonal skills", "analytical mind", "work under pressure"], "languages_combined": [{"language": "english", "language_level": ["good command"]}, {"language": "mandarin", "language_level": ["good command"]}]}, "experience_required": {"duration": ["minimum 5 years"], "field": ["risk management", "compliance", "banking", "it", "relevant experience", "security", "finance industry"]}}, {"job_id": "100003009035982", "location_code": "hk", "company": "Michael Page", "job_title": "Senior Internal Auditor/ IA  - Big 4 are Welcome (35-43K)", "description": "Our client is a very well known and sizable property company in Hong Kong and they are currently seeking for a Senior Internal Auditor / Internal auditor with 2-4 years of audit & accounting experience to join their team to handle internal audit . If you are a candidate who is hoping for a stable yet challenging career, here is your chance!\n\nClient Details\n\nOur client is one of largest property investment, development & management companies in Hong Kong . They are now seeking for a high potential auditing candidate to join their team. They are looking for an IA passionate individual. Candidates with CPA qualification or not are also welcomed\n\nDescription\n\nGroup operation & finance internal audit\nFamiliar with accounting standard and apply knowledges to relevant parties\nMaking sure all the audit reporting are within the deadlines\nBudgeting and operational internal control\n\nProfile\n\nDegree in Accounting, Finance or a related discipline\nBig 4 Trained. 2-4 years of experiences\nGood command of written and spoken English\nGood team player, detail-oriented and responsible\nPassed all CPA exams\n\nJob Offer\n\nCareer development opportunities\nSizable company\nVery stable working environment\n\nTo apply online please click the 'Apply' button below. For a confidential discussion about this role please contact Sunny Chan on +852 3602 2466.", "employment_types": ["Full Time", "Permanent"], "selling_points": ["Group Position", "Property Opportunity", "HK listed"], "locations": ["Central & Western Area"], "categories": ["Accounting", "Audit", "Information Technology (IT)", "IT Auditing"], "post_time": "2022-01-10T08:59:18Z", "salary": {"currency": null, "max": null, "min": null, "period": "monthly", "term": null}, "salary_visible": false, "title_keywords": ["internal auditor"], "responsibilities": ["reporting", "management", "internal audit", "budgeting", "audit", "contact", "career development", "auditing", "internal control"], "requirements": {"degrees": ["degree"], "majors": ["finance", "accounting"], "languages": ["english"], "language_level": ["good command"], "hard_skills": ["cpa", "internal control"], "soft_skills": ["passionate", "good team player", "responsible", "detail-oriented", "stable"], "languages_combined": [{"language": "english", "language_level": ["good command"]}]}, "experience_required": {"duration": ["2-4 years"], "field": ["accounting experience", "audit", "team"]}}, {"job_id": "100003009031228", "location_code": "hk", "company": "Nanyang Commercial Bank", "job_title": "Head of IT Audit Division (IT Audit)", "description": "Reporting to the Department Head, your role is to plan, lead and conduct IT related audit assignments. Involve in IT governance reviews and technical assessments, and recommend internal control improvements. Provide consultancy advices on IT management, security and outsourcing. Enhance audit process and proficiency through implementing audit standards, methodologies, and techniques. Take up ad-hoc projects as required.\n\nRequirements:\n\n\nDegree holder or above in IT, Computer Science, or related disciplines\nMinimum 10-15 years of experience in IT security or audit field, preferably in Banking and Financial industry\nRelevant professional qualifications (e.g. CISA, CISSP)\nExperience in using CAATs (e.g. ACL) and technical skill on network security will be an advantage\nMature, independent and with strong analytical and interpersonal skills\nGood command in both written and spoken English and Chinese, including Putonghua\nCandidate with less experience will be considered as Senior IT Audit Manager.\n\nIf you are flexible enough and zeal for a harmonious and supportive working environment where enables you to grow and succeed professionally, please send a full resume indicating your public examination results (HKCEE and HKALE / HKDSE), your present and expected salary and quoting reference number attention to\u00a0Talent Acquisition Division, Nanyang Commercial Bank, 151 Des Voeux Road Central, Hong Kong or apply through email. For details, please visit https://www.ncb.com.hk/ and select the page Recruit.\n\nWe are an Equal Opportunities Employer. Data collected would be used for recruitment purposes only. Applicants who do not hear from us within 8 weeks may consider their applications unsuccessful and their data will be destroyed within 12 months of receipt.", "employment_types": ["Full Time", "Permanent"], "selling_points": ["Plan,lead and conduct IT related audit assignments", "Involve in IT governance reviews", "Minimum 10-15 years in IT audit field"], "locations": ["Central"], "categories": ["Accounting", "Audit", "Banking / Finance", "Others", "Information Technology (IT)", "IT Auditing"], "post_time": "2022-01-07T09:05:04Z", "salary": {"currency": null, "max": null, "min": null, "period": "monthly", "term": null}, "salary_visible": false, "title_keywords": [], "responsibilities": ["reporting", "data", "audit", "it management", "recruitment", "plan", "banking", "ad-hoc projects", "internal control"], "requirements": {"degrees": ["hkdse", "degree holder"], "majors": ["related disciplines", "it", "computer science"], "languages": ["putonghua", "english", "chinese"], "language_level": ["good command"], "hard_skills": ["professional qualifications", "internal control"], "soft_skills": ["flexible", "supportive", "independent", "harmonious", "mature", "interpersonal skills", "technical skill"], "languages_combined": [{"language": "putonghua", "language_level": ["good command"]}, {"language": "english", "language_level": ["good command"]}, {"language": "chinese", "language_level": ["good command"]}]}, "experience_required": {"duration": ["minimum 10-15 years"], "field": ["financial industry", "audit", "it", "security", "banking"]}}, {"job_id": "100003009026169", "location_code": "hk", "company": "The Bank of East Asia, Limited", "job_title": "IT Audit Manager", "description": "IT Audit Department\n\nIT Audit Manager (Job ID: 2790)\n\nResponsibilities\nTo be a team member of IT Audit Department\nTo assist the supervisor in preparing and implementing annual internal audit plan and pre-audit planning and ensure the internal IT audit function complies with sound internal auditing principles\nTo prepare audit programme and working paper and draft internal audit report\nTo prepare and present audit findings to auditees and ensuring that recommendations are implemented\nTo assist the supervisor in assigning and reviewing internal audit work performed by subordinates\nTo study and comment, where necessary, on issues relating to the internal IT controls of auditees\nTo maintain and enhance rapport and communications with auditees\nTo engage in special project if necessary\nRequirements\nUniversity graduate in Accounting, Finance, Information Systems or business-related discipline\nProfessional qualifications such as CISSP or CISA will be a plus\nAt least 5 years\u2019 relevant experience in banking or financial services with:\nSound knowledge in internal auditing\nStrong technical knowledge of relevant risk management, compliance requirements and banking operations\nIndependent, self-motivated and detail-oriented\nA team player with good communication skills and risk awareness\nGood command of both spoken and written English and Chinese\nPlease apply online via the BEA Careers website at https://careers.hkbea.com/psp/hcmprd/EMPLOYEE/HRMS/c/HRS_HRAM.HRS_APP_SCHJOB.GBL?Page=HRS_APP_JBPST&Action=UFOCUS=Applicant&SiteId=1&JobOpeningId=2790&PostingSeq=1 or by clicking the \"Apply Now\" button below. Kindly note that if you are a new user, you have to first create your User Profile before you can apply.\n\nPersonal data provided by job applicants will be used for recruitment purposes only and will be treated in accordance with the Bank's Personal Information Collection (Employees) Statement and Privacy Policy Statement. Applicants who are not invited for interviews within six weeks may consider their applications unsuccessful and the personal data collected will be destroyed after six months.", "employment_types": ["Full Time", "Permanent"], "selling_points": ["Prepare audit programme and working paper", "Prepare and present audit findings to auditees", "University graduate in Accounting, Finance"], "locations": ["Kwun Tong"], "categories": ["Accounting", "Audit", "Banking / Finance", "Financial Services", "Information Technology (IT)", "IT Auditing"], "post_time": "2022-01-07T19:19:28Z", "salary": {"currency": null, "max": null, "min": null, "period": null, "term": null}, "salary_visible": false, "title_keywords": ["manager"], "responsibilities": ["communications with", "internal audit", "audit", "maintain", "plan", "report", "auditing", "planning"], "requirements": {"degrees": ["university graduate"], "majors": ["business", "finance", "accounting"], "languages": ["english", "chinese"], "language_level": ["good command"], "hard_skills": ["plus", "c", "professional qualifications"], "soft_skills": ["communication skills", "self-motivated", "independent", "detail-oriented", "team player"], "languages_combined": [{"language": "english", "language_level": ["good command"]}, {"language": "chinese", "language_level": ["good command"]}]}, "experience_required": {"duration": ["at least 5 years"], "field": ["financial services", "relevant experience", "banking"]}}, {"job_id": "100003009036108", "location_code": "hk", "company": "CHOW TAI FOOK JEWELLERY CO LTD", "job_title": "Assistant IT Project Manager/ IT Project Manager", "description": "What You Do\nOversee the overall project progress by regular communication with project team to obtain status updates, and escalate unresolved issues and risk to Project Sponsor and IT PMO\nTrack and follow up on defects identified during testing and UAT with Testers, Business Analyst and Development Team\nEnsure the deliverables in each stage of the SDLC process are completed and signed off\nCommunicates with Requestor and other stakeholders regularly on project status, deployment result and changes made on systems\nWork with Infrastructure and Operations Team and Development Team to prepare deployment plan and roll back plan\nCheck for information security concern throughout the SDLC process and follow up on actions required for compliance with Cyber Security Team\nPrepare test plan and coordinate the testing activities\nPerform other ad-hoc projects and tasks as assigned\nWho Will Thrive\nDegree holders or related discipline, with at least 4 years\u2019 working experience and knowledge in PMO, IT governance & IT Compliance is an advantage\nKnowledge and experience in Salesforce or CRM System is preferred\nProficient in SDLC project management execution and business analysis experience\nExperience on PM Tools (e.g. ServiceNow, JIRA, Salesforce) and Data Analysis tools (e.g. PowerBI, Qlikview) is an advantage\nCustomer-oriented and self-motivated with excellent communication skill\nProactive, Independent, efficient, able to work under pressure with tight schedule\nGood command of written and spoken English and Chinese as well as Putonghua\nHolder of PMP, ScrumMaster certification or ITIL would be definitely an advantage\nBenefits:\n5-day work\nCompetitive salary, staff meal,\u00a0medical and dental insurance, life insurance\nVarious types of leave, e.g. Family-friendly leave, self-development leave, Examination leave, marriage leave, birthday leave, volunteer service leave, etc\nWe offer excellent career opportunities, attractive remuneration package & benefits to the right candidate. Interested parties please\u00a0click\u00a0\"Apply Now\"\u00a0below or\u00a0apply with full resume by stating latest and expected salaries to\u00a021/F, Chow Tai Fook Centre, No. 580A-580F Nathan Road, Mongkok, Kowloon, Hong Kong.\u00a0\nAll information collected for recruitment purpose only.", "employment_types": ["Full Time", "Permanent"], "selling_points": ["IT Governance, Project Management, IT Compliance", "Experience in Salesforce / CRM system", "ScrumMaster, ITIL, PMP"], "locations": ["Kwai Hing"], "categories": ["Information Technology (IT)", "IT Auditing", "IT Project Management / Team Lead", "Others"], "post_time": "2022-01-10T09:22:15Z", "salary": {"currency": null, "max": null, "min": null, "period": "monthly", "term": null}, "salary_visible": false, "title_keywords": ["it project manager", "assistant"], "responsibilities": ["information security", "cyber security", "operations", "plan and coordinate", "testing activities", "communication", "plan", "ad-hoc projects", "work under pressure", "uat", "infrastructure", "compliance", "project progress", "testing", "schedule", "data analysis", "systems", "project management", "business analysis"], "requirements": {"degrees": ["degree"], "majors": ["it"], "languages": ["putonghua", "english", "chinese"], "language_level": ["good command"], "hard_skills": ["itil", "qlikview", "salesforce", "cyber security", "analysis", "project management", "sdlc", "deployment", "pmp"], "soft_skills": ["efficient", "self-motivated", "independent", "communication skill", "communication", "project management", "customer-oriented", "proactive", "work under pressure"], "languages_combined": [{"language": "putonghua", "language_level": ["good command"]}, {"language": "english", "language_level": ["good command"]}, {"language": "chinese", "language_level": ["good command"]}]}, "experience_required": {"duration": ["at least 4 years"], "field": ["related", "compliance", "project management", "it", "business analysis", "it governance"]}}, {"job_id": "100003009032280", "location_code": "hk", "company": "Hong Kong Interbank Clearing Ltd", "job_title": "Assistant Manager (Internal Audit)", "description": "Major Responsibilities\n\nAssist in developing internal audit plans, follow up on status of audit issues and coordinate audit reports, etc.\nProvide expertise to maintain and monitor the internal control policies and procedures\nExecute internal audit projects and/or ad hoc reviews/ investigations on different areas to determine the adequacy and effectiveness of internal control and compliance measures\nEnsure risks are effectively identified and constructive advice is provided for solving or mitigating risks and control issues\nAssist in producing regular reports and presentations to the Management and Board of Directors on audit findings and recommendations\nFollow up on remedial status of issues identified during audit work\nRequirements\n\nUniversity degree in Accounting, Finance, Risk Management or other relevant disciplines\nCPA, CIA, CISA or equivalent qualifications\nOver 3 years of experience in internal or external audit field, preferably with IT audit experience and audit experience in Big 4 professional accounting firm(s)\nSound knowledge of auditing standards and regulatory requirements\nStrong interpersonal and analytical skills\nGood command of written and spoken English and Chinese, proficiency in Putonghua will be an advantage\nHow to Apply\n\n\nInterested parties please send your curriculum vitae stating your current and expected salaries, and the contact phone number to the Human Resources Division, Unit B, 25/F, MG Tower, 133 Hoi Bun Road, Kwun Tong, Kowloon\u00a0\u00a0by clicking the \"Apply Now\" button below.\nAll applications and personal information collected will be treated in strict confidence and only be used for the purpose of recruitment and selection.\u00a0 The information collected will be accessed by our authorized personnel only.\u00a0 Those applicants not contacted by the Human Resources Division within two months from their application date should consider their applications filed for future reference which will be retained for one year for possible future job matching, and will be destroyed after the expiry of one year.", "employment_types": ["Full Time", "Permanent"], "selling_points": [], "locations": ["Ngau Tau Kok"], "categories": ["Banking / Finance", "Financial Services", "Others", "Information Technology (IT)", "IT Auditing"], "post_time": "2022-01-07T10:37:50Z", "salary": {"currency": null, "max": null, "min": null, "period": null, "term": null}, "salary_visible": false, "title_keywords": ["assistant manager"], "responsibilities": ["control", "management", "ad hoc", "internal audit", "policies", "compliance", "monitor", "developing", "audit", "procedures", "coordinate", "presentations", "maintain", "reports", "plans", "internal control"], "requirements": {"degrees": ["university degree"], "majors": ["finance", "accounting", "risk management"], "languages": ["putonghua", "english", "chinese"], "language_level": ["advantage", "proficiency", "good command"], "hard_skills": ["cpa", "analytical skills"], "soft_skills": ["interpersonal", "analytical skills"], "languages_combined": [{"language": "putonghua", "language_level": ["proficiency", "good command"]}, {"language": "english", "language_level": ["advantage", "proficiency", "good command"]}, {"language": "chinese", "language_level": ["advantage", "proficiency", "good command"]}]}, "experience_required": {"duration": ["3 years"], "field": ["big 4", "audit", "it", "audit experience", "accounting"]}}, {"job_id": "100003009032273", "location_code": "hk", "company": "Hong Kong Interbank Clearing Ltd", "job_title": "Manager (Internal Audit)", "description": "Major Responsibilities\n\nAssist in developing corporate audit strategies, policies and procedures\nDevelop internal audit plans, follow up on status of audit issues and coordinate audit reports, etc.\nProvide expertise to maintain and monitor the internal control policies and procedures\nSchedule, plan and execute internal audit projects and/or ad hoc reviews/ investigations on different areas to determine the adequacy and effectiveness of internal control and compliance measures\nEnsure risks are effectively identified and constructive advice is provided for solving or mitigating risks and control issues\nProduce regular reports and presentations to the Management and Board of Directors on audit findings and recommendations\nFollow up on remedial status of issues identified during audit work\nRequirements\n\nUniversity degree in Accounting, Finance, Risk Management or other relevant disciplines\nCPA, CIA, CISA, CISM and/or CISSP qualifications\nOver 5 years of experience in internal or external audit field, preferably with IT audit experience; with 3 years in supervisory positions and audit experience in Big 4 professional accounting firm(s)\nSound knowledge of auditing standards and regulatory requirements\nStrong interpersonal, supervisory and analytical skills\nGood command of written and spoken English and Chinese, proficiency in Putonghua will be an advantage\nHow to Apply\n\n\nInterested parties please send your curriculum vitae stating your current and expected salaries, and the contact phone number to the Human Resources Division, Unit B, 25/F, MG Tower, 133 Hoi Bun Road, Kwun Tong, Kowloon\u00a0\u00a0by clicking the \"Apply Now\" button below.\nAll applications and personal information collected will be treated in strict confidence and only be used for the purpose of recruitment and selection.\u00a0 The information collected will be accessed by our authorized personnel only.\u00a0 Those applicants not contacted by the Human Resources Division within two months from their application date should consider their applications filed for future reference which will be retained for one year for possible future job matching, and will be destroyed after the expiry of one year.", "employment_types": ["Full Time", "Permanent"], "selling_points": [], "locations": ["Ngau Tau Kok"], "categories": ["Banking / Finance", "Financial Services", "Others", "Information Technology (IT)", "IT Auditing"], "post_time": "2022-01-07T10:36:23Z", "salary": {"currency": null, "max": null, "min": null, "period": null, "term": null}, "salary_visible": false, "title_keywords": ["manager"], "responsibilities": ["internal audit", "audit", "maintain", "plan", "plans", "internal control", "control", "ad hoc", "compliance", "monitor", "developing", "presentations", "develop", "reports", "schedule", "management", "procedures", "policies", "coordinate"], "requirements": {"degrees": ["university degree"], "majors": ["finance", "accounting", "risk management"], "languages": ["putonghua", "english", "chinese"], "language_level": ["advantage", "proficiency", "good command"], "hard_skills": ["cpa", "analytical skills"], "soft_skills": ["interpersonal", "analytical skills"], "languages_combined": [{"language": "putonghua", "language_level": ["proficiency", "good command"]}, {"language": "english", "language_level": ["advantage", "proficiency", "good command"]}, {"language": "chinese", "language_level": ["advantage", "proficiency", "good command"]}]}, "experience_required": {"duration": ["5 years", "3 years"], "field": ["supervisory", "big 4", "audit", "it", "audit experience", "accounting"]}}, {"job_id": "100003009039185", "location_code": "hk", "company": "Ampd Energy Limited", "job_title": "Document Controller", "description": "Summary of the Position\n\nAmpd Energy is seeking a Document Controller to support the development of Ampd\u2019s lithium-ion battery based Energy Storage systems. You will be responsible for managing Engineering documentation on Ampd\u2019s PLM system.\n\nKey Qualifications\n\n\u00a0\u00a0\u00a0\u00a0\u00a0\u00a0 A college graduate/higher diploma or above with strong computer skills and organisational skills;\n\u00a0\u00a0\u00a0\u00a0\u00a0\u00a0 At least 3 years of relevant document control experience;\n\u00a0\u00a0\u00a0\u00a0\u00a0\u00a0 Experience in setting up and managing PLM systems such as Arena PLM, PTC WindChill or similar;;\n\u00a0\u00a0\u00a0\u00a0\u00a0\u00a0 Familiar with document control processes and procedures for products that have significant compliance and safety requirements.\n\u00a0\u00a0\u00a0\u00a0\u00a0\u00a0 A strong eye for detail.\n\u00a0\u00a0\u00a0\u00a0\u00a0\u00a0 Strong English and Chinese.\n\n\n\nAs examples, specific duties could include:\n\n\u00a0\u00a0\u00a0\u00a0\u00a0\u00a0 Prepare and submit Engineering Change Notices (ECNs) at the direction of engineers.\n\u00a0\u00a0\u00a0\u00a0\u00a0\u00a0 Conduct document audits and create reports showing deficiencies and propose corrective actions.\n\u00a0\u00a0\u00a0\u00a0\u00a0\u00a0 Create new part numbers, maintain existing parts in the Arena PLM database, and create templates where appropriate.\n\u00a0\u00a0\u00a0\u00a0\u00a0\u00a0 Checking for accuracies in existing documentation and filling/correcting any errors.\n\u00a0\u00a0\u00a0\u00a0\u00a0\u00a0 File Retrieval and guidance for Ampd Team.\n\u00a0\u00a0\u00a0\u00a0\u00a0\u00a0 Work with the Engineering teams to ensure documentation is correctly and accurately uploaded and maintained on the Arena PLM database.\n\u00a0\u00a0\u00a0\u00a0\u00a0\u00a0 Work with the Supply Chain team to ensure that the interface between the Arena PLM database and the company\u2019s ERP system is accurate and efficient.\n\n\n\nBenefits\n\n\u00a0\u00a0\u00a0\u00a0\u00a0\u00a0 Competitive salary package.\n\u00a0\u00a0\u00a0\u00a0\u00a0\u00a0 Full medical, dental & travel insurance coverage.\n\u00a0\u00a0\u00a0\u00a0\u00a0\u00a0 Uber travel policy (for business travel & travel after 8pm).\n\n\n\nHow to apply\n\nPlease submit your application via\u00a0https://www.linkedin.com/jobs/view/2868247680.\u00a0\n\nAll information provided will be treated in strict confidence and used solely for recruitment purposes. We regret that we are only able to notify short-listed candidates.\n\nAmpd Energy is an equal opportunity employer. All candidates will be assessed on merit without regard to age, race, gender, sexual orientation, religion, nationality, marital status, political affiliation or any other factor protected by law.", "employment_types": ["Full Time", "Permanent"], "selling_points": ["Rapidly Growing Startup Environment", "3 Years of Relevant Document Control Experience", "Experience in Setting Up and Managing PLM System"], "locations": ["Lai Chi Kok"], "categories": ["Engineering", "Mechanical", "Information Technology (IT)", "IT Auditing", "Others"], "post_time": "2022-01-11T08:57:11Z", "salary": {"currency": null, "max": null, "min": null, "period": "monthly", "term": null}, "salary_visible": false, "title_keywords": [], "responsibilities": ["guidance", "control", "compliance", "systems", "procedures", "checking", "audits", "teams", "maintain", "reports", "database", "documentation"], "requirements": {"degrees": ["higher diploma or above"], "majors": [], "languages": ["english", "chinese"], "language_level": [], "hard_skills": ["documentation", "erp system", "computer skills"], "soft_skills": ["efficient", "responsible", "organisational skills", "eye for detail", "accurate"], "languages_combined": [{"language": "english", "language_level": []}, {"language": "chinese", "language_level": []}]}, "experience_required": {"duration": ["at least 3 years"], "field": []}}, {"job_id": "100003009032827", "location_code": "hk", "company": "ConnectedGroup Limited", "job_title": "Internal Audit, Assistant Director", "description": "Internal Audit, Assistant Director\n\nOur client is a leading local conglomerate, we are now seeking a talented individual to join them as Internal Audit Assistant Director to lead up their internal audit team.\n\nResponsibilities:\n\nResponsible for all audits assignments, audit planning and audit development\nEvaluate the effectiveness of governance, risk management process and controls\nBuild and grow the internal audit team\nResponsible for investigation and improving the current work flow\nPerform other ad hoc duties when required\n\nRequirements\n\nBachelor's degree or above in Finance, Accounting, or relevant disciplines\nA relevant professional qualification (CPA, CIA, CISA)\nGood command of written and spoken English and Putonghua\nKnowledge in IFRS and Internal Controls\nProficient in Excel, Word and PowerPoint\nMinimal business travel is required\n\nThis is an excellent opportunity for individuals seeking an Internal Audit Director role for a reputable company that is able to offer a great package and excellent working environment.", "employment_types": ["Full Time", "Permanent"], "selling_points": ["Group Level Position", "Attractive Remuneration Package", "Well known property developer"], "locations": ["Not Specified"], "categories": ["Accounting", "Audit", "Others", "Information Technology (IT)", "IT Auditing"], "post_time": "2022-01-08T00:00:51Z", "salary": {"currency": "HKD", "max": 119999, "min": 70000, "period": "monthly", "term": null}, "salary_visible": true, "title_keywords": ["assistant director"], "responsibilities": ["ad hoc duties", "management", "internal audit", "audit", "investigation", "evaluate", "audits", "planning"], "requirements": {"degrees": ["degree or above", "bachelor"], "majors": ["finance", "accounting"], "languages": ["putonghua", "english"], "language_level": ["good command"], "hard_skills": ["excel", "ifrs", "word", "powerpoint", "cpa"], "soft_skills": [], "languages_combined": [{"language": "putonghua", "language_level": ["good command"]}, {"language": "english", "language_level": ["good command"]}]}, "experience_required": {"duration": [], "field": []}}, {"job_id": "100003009026100", "location_code": "hk", "company": "Thales Transport & Security (Hong Kong) Limited", "job_title": "Consultant, Cybersecurity & IT Audit", "description": "The Role\nThe role of the Consultant \u2013 Cybersecurity is to provide Consultation and cost effective advice on the management of cybersecurity and information risk consistent with regulations to our clients.\n\nYou\u2019ll be the focal point for resolution of cybersecurity and information risk matters to the client as well as being able to identify, analyse and evaluate cybersecurity and information risks which in turn you will then relay to the risk owners and other stakeholders the causes, likelihood and potential business impacts of cybersecurity and information risks throughout the system lifecycle.\n\nResponsibilities\n\nChecking compliance with applicable regulations, standards, policies and guidance on cybersecurity and information risk management (PCI DSS, NIST, ISO 27000, Privacy, etc)\nConducting application/server/network/middleware security configuration assessment\nPerforming vulnerability assessment on different platforms and technologies\nConduct source code review to identify any potential coding vulnerability (using either manual or automated processes)\nRemain up-to-date on the latest cybersecurity threats, vulnerabilities and regulatory requirements\nTo present risk management options to the business\nTo support the development of appropriate and proportionate documentation to inform risk management decisions, ensuring these are expressed in terms meaningful to the business\nTo provide regular threat guidance\nRequirements\n\nDegree Holder in Computer Science, IT Management, Engineering or equivalent\n1-3 years of client facing working experience\nStrong analytical, problem solving and inter-personal skills that can deliver results\nWorking on the client sites\nWilling to travel overseas on some projects\nPCIP/CISA/CISSP Certified would be a plus\nCandidate with less experience will be considered as Associate Consultant", "employment_types": ["Full Time", "Permanent"], "selling_points": ["Competitive package", "Clear development path", "Certificate allowance"], "locations": ["Mong Kok"], "categories": ["Information Technology (IT)", "IT Auditing", "Security", "Technical / Functional Consulting"], "post_time": "2022-01-06T07:20:06Z", "salary": {"currency": null, "max": null, "min": null, "period": "monthly", "term": null}, "salary_visible": false, "title_keywords": ["consultant"], "responsibilities": ["regulations", "guidance", "management", "configuration", "policies", "regulatory requirements", "compliance", "review", "checking", "coding", "documentation"], "requirements": {"degrees": ["degree holder"], "majors": ["it", "engineering", "computer science"], "languages": [], "language_level": [], "hard_skills": ["problem solving", "plus"], "soft_skills": ["problem solving", "inter-personal skills"], "languages_combined": []}, "experience_required": {"duration": ["1-3 years"], "field": []}}, {"job_id": "100003009025080", "location_code": "hk", "company": "Page Personnel", "job_title": "IT Audit - Renowned Listed Company", "description": "One of the leading HK listed companies is now looking for an IT Audit. Selected candidate will be responsible for providing internal audit, information security and consultancy services\n\nClient Details\n\nOur client is a leading conglomerate based in Hong Kong. With a wide range of business portfolio from property investment to information technology, they have more than 15,000 employees in Hong Kong and 200,000 employees worldwide. With the rapid growth in their global business, they are currently looking for an IT Audit to join their organisation.\n\nDescription\n\nConduct IT governance reviews and technical assessments\nPerform IT audit engagements including IT general control review, application controls and CAATs\nFormulate action plans based on international IT security standards\nAssist in drafting and presenting audit reports to senior management\nPerform IT administration tasks\n\nProfile\n\nBachelor degree in Information Technology, Computer Science or related discipline\nExperience in IT audit, risk advisory, cyber security, or related areas\nWorking experience with Big4 or other Consulting firms would be an advantage\nProfessional qualification such as CISA, CISM, CISSP, CRISC, CIA, CEH holder is a plus but not a must\nExcellent command of written and spoken English and Chinese\n\nJob Offer\n\nPermanent role\nAttractive performance bonus\nAnnual leave\nGreat career exposure\nMedical coverage\n\nTo apply online please click the 'Apply' button below. For a confidential discussion about this role please contact Ray Chanon +852 3602 2432.", "employment_types": ["Full Time", "Permanent"], "selling_points": ["Working experience with Big4 is an advantage", "Cross-regional exposure", "Excellent training ground for future careers"], "locations": ["Not Specified"], "categories": ["Information Technology (IT)", "IT Auditing", "Security", "Others"], "post_time": "2022-01-06T03:24:31Z", "salary": {"currency": null, "max": null, "min": null, "period": "monthly", "term": null}, "salary_visible": false, "title_keywords": [], "responsibilities": ["control", "information security", "internal audit", "cyber security", "consulting", "review", "audit", "reports", "contact", "plans", "senior management", "administration"], "requirements": {"degrees": ["degree", "bachelor"], "majors": ["computer science", "information technology"], "languages": ["english", "chinese"], "language_level": ["excellent"], "hard_skills": ["cyber security", "plus", "rapid"], "soft_skills": ["organisation", "responsible"], "languages_combined": [{"language": "english", "language_level": ["excellent"]}, {"language": "chinese", "language_level": ["excellent"]}]}, "experience_required": {"duration": [], "field": ["consulting firms", "related", "audit", "it", "security"]}}, {"job_id": "100003009032494", "location_code": "hk", "company": "Hong Kong Science & Technology Parks Corporation", "job_title": "Manager, Internal Audit [JDB/MIA/220107]", "description": "Responsibilities:\nPerform audit risk assessment for projects or assigned engagements and contribute innovative ideas to improve the audit methodology\nManage and carry out operational/ compliance/ project audit assignments throughout the planning, field work and reporting phases within specified deadlines\nCo-ordinate and communicate with all levels of management in arriving at practical and value-added audit recommendations\nManage ad hoc investigations and provide ongoing management advices, upon request and where necessary\nFollow through on the implementation of recommendations\nProvide supervision and training to audit team members, where necessary\nPerform any other duties assigned by supervisor\nRequirements:\nDegree holder with relevant professional qualification ; preferably with IT Audit certificates\nA minimum of 8 years of working experience in internal or external audit, preferably in Big-4 firms or sizable organizations\nSolid exposure in IT audit and publicly funded organizations is preferred \u00a0\nBe able to drive change with good influencing skills and work independently\nHands-on, detail-oriented with strong analytical and problem solving skills\nExcellent command of written and spoken English and Chinese\nCandidates with more experience may be considered as Senior Manager\n[This position is open for referral by Recruitment agencies. The profile should be sent to our HR email address\u00a0a g e n c y c v @ h k s t p . o r g ]\nWe offer market competitive compensation, 5-day work week, and generous benefits including medical and life insurance; and voluntary contribution in addition to the legal minimum MPF.\u00a0 To apply, please send your full resume with current and expected salary to the Human Resources & Office Administration Department, Hong Kong Science and Technology Parks Corporation, 5/F, Building 5E, 5 Science Park East Avenue, Hong Kong Science Park, Hong Kong or, by email via \"Apply Now\"\u00a0on or before 20 January 2022.\u00a0 \u00a0Please quote the reference number on the email subject/envelope and the application letter.\u00a0\nPersonal data provided will be treated in strict confidence and used for recruitment purpose only.\u00a0 All personal data collected will be used strictly in accordance with employer\u2019s personal data policies, you can access to HKSTP\u2019s Personal Information Collection Statement at https://www.hkstp.org/hkstp_web/en/hkstp/personal-information-collection-statement-recruitment\nApplicants not invited for interview within four weeks after application deadline may consider their applications unsuccessful.\u00a0 Personal data of unsuccessful applicants will be retained for a maximum of two years.\u00a0\nwww.hkstp.org", "employment_types": ["Full Time"], "selling_points": [], "locations": ["Shatin Area"], "categories": ["Accounting", "Audit", "Finance / Accounting Manager", "Information Technology (IT)", "IT Auditing"], "post_time": "2022-01-07T11:18:50Z", "salary": {"currency": null, "max": null, "min": null, "period": "monthly", "term": null}, "salary_visible": false, "title_keywords": ["manager"], "responsibilities": ["communicate with", "reporting", "management", "any other duties", "ideas", "ad hoc", "compliance", "audit", "implementation", "provide supervision", "planning"], "requirements": {"degrees": ["degree holder"], "majors": [], "languages": ["english", "chinese"], "language_level": ["excellent"], "hard_skills": ["r", "problem solving skills", "c"], "soft_skills": ["analytical and problem solving skills", "work independently", "hands-on", "detail-oriented"], "languages_combined": [{"language": "english", "language_level": ["excellent"]}, {"language": "chinese", "language_level": ["excellent"]}]}, "experience_required": {"duration": ["minimum of 8 years"], "field": ["audit"]}}, {"job_id": "100003009024009", "location_code": "hk", "company": "Morgan McKinley", "job_title": "Senior IT Audit Manager (Projects), Very Large Organisation", "description": "This company is a large leading organisation with expanding and progressive businesses. They are looking for the Senior IT Audit Manager.\n\nResponsibilities\n\nReporting to the Head of IT Audit, you would lead a team of 1-2 on the fields.\nDeliver project audit initiatives and advise on improvement of the project audit methodology\nSchedule projects, project cost control and other relevant controls\nAssess the risks resulted from the project management\nWrite audit reports and submit the findings to the audit leadership and business\nMonitor the audit progress and identify the issues in relation to the IT projects\n\nRequirements\n\nA minimum of 15 years of end-to-end IT project/audit management experience gained from large companies or FI\nHolder of CISA, CISM or other relevant qualification is a plus\nPreferably you should possess system/implementation/management or project auditing experience\nExcellent command of English\nCandidates with lesser experience may be considered as Manager\nOpen for candidates with strong IT project management experience (Agile) but without audit experience\n\nTo apply online, please click the \"Apply\" button below. For a confidential discussion about this role, please contact David Yung on +3907 3932 or dyung@morganmckinley.com", "employment_types": ["Full Time", "Permanent"], "selling_points": ["Exposure to very large projects", "Very sizable company", "Reputable Brand Name"], "locations": ["Not Specified"], "categories": ["Accounting", "Audit", "Information Technology (IT)", "IT Auditing", "IT Project Management / Team Lead"], "post_time": "2022-01-05T10:20:26Z", "salary": {"currency": null, "max": null, "min": null, "period": "monthly", "term": null}, "salary_visible": false, "title_keywords": ["manager"], "responsibilities": ["reporting", "monitor", "audit", "lead a team", "project management", "reports", "schedule", "cost control"], "requirements": {"degrees": [], "majors": [], "languages": ["english"], "language_level": ["excellent"], "hard_skills": ["project management", "plus", "agile"], "soft_skills": ["project management", "agile"], "languages_combined": [{"language": "english", "language_level": ["excellent"]}]}, "experience_required": {"duration": ["minimum of 15 years"], "field": ["management", "audit", "project management", "it", "audit experience"]}}, {"job_id": "100003009032293", "location_code": "hk", "company": "Industrial Bank Co., Ltd.", "job_title": "IT Security Analyst and Technology Risk", "description": "As an integral member of the Information Technology Department, you are an experienced staff member who has the ability to consistently deliver high quality services and results. Your skills and abilities also include:\n\nResponsibilities\u00a0\n\nEvaluate IT systems, the security policies of the bank, requirements of regulators and user departments to establish IT risk and security framework together with the policies and procedures necessary to ensure system security is in place\nDevelop and oversee implementation plans of the policies and procedures\nConduct system vulnerabilities scan and recommend remediation\nProvide training and awareness update on technology risk and security\nConduct security risk assessment of IT systems, assess effectiveness of IT security measures and carry out improvement work\nMonitor security risk, handle security incidents and carry out investigation\nEvaluate, recommend and procure security solutions and tools\u00a0\nCoordinate with head office, regulator, risk management, compliance and audit on technology risk and security matters\nCarry out ad-hoc tasks as required by management\nRequirements:\n\nMinimum 3 years working experience in management of technology risk, IT compliance and security in banking sector\nHolder of CISSP / CISA certification is required\nDegree holder in information technology or related disciplines\nFamiliar with technology risk and security management in banking industry\nSound knowledge in Hong Kong Monetary Authority's requirements in technology related areas e.g. CRAF, TMG, TME, etc.\nGood understanding of banking IT architecture and development process\nPossess project management skills, including analysis, determination and communication\nPrior experience in technology risk management of banking is an added advantage\nHigh proficiency in spoken and written Putonghua, English and Cantonese\nPossess good communication and coordination skills\nDedicated to work, well conducted\nResponsible, attentive to details, a good team player and professional\n\nPlease enclose full C.V. with\u00a0present and expected salary\u00a0to the Head of Human Resources, Industrial Bank Co., Ltd. Hong Kong Branch, 12/F, One International Finance Centre, 1 Harbour View Street, Central, Hong Kong\u00a0or apply directly by clicking \u201cApply Now\u201d.\n\nPersonal data provided by job applicants will be used for recruitment purpose only. Applicants who are not contacted within 8 weeks may consider their applications unsuccessful. All data of unsuccessful applicants will be destroyed in 1 year.", "employment_types": ["Full Time"], "selling_points": ["Minimum 3 years experience in  IT security risk", "Holder of CISSP / CISA certification is required", "Evaluate IT systems and security policies"], "locations": ["Central"], "categories": ["Information Technology (IT)", "IT Auditing", "IT Management", "Security"], "post_time": "2022-01-07T10:40:08Z", "salary": {"currency": null, "max": null, "min": null, "period": "monthly", "term": null}, "salary_visible": false, "title_keywords": ["analyst"], "responsibilities": ["provide training", "management", "policies", "ad-hoc tasks", "systems", "procedures", "implementation", "monitor", "develop", "evaluate", "investigation", "coordinate with", "system security", "compliance", "audit", "plans"], "requirements": {"degrees": ["degree holder"], "majors": ["related disciplines", "information technology"], "languages": ["cantonese", "putonghua", "english"], "language_level": ["proficiency"], "hard_skills": ["harbour", "security management", "analysis", "project management", "c", "tmg"], "soft_skills": ["good team player", "coordination skills", "attentive to details", "responsible", "project management skills", "communication"], "languages_combined": [{"language": "cantonese", "language_level": ["proficiency"]}, {"language": "putonghua", "language_level": ["proficiency"]}, {"language": "english", "language_level": ["proficiency"]}]}, "experience_required": {"duration": ["minimum 3 years"], "field": ["risk management", "management", "compliance", "it", "banking sector", "security", "banking"]}}, {"job_id": "100003009027696", "location_code": "hk", "company": "AsiaPay (HK) Ltd", "job_title": "IT Security Manager", "description": "Responsibilities:\n\n\nSetup, run and manage an IT security management framework to ensure sufficient IT controls are in place to meet statutory, regulation and IT general control requirements\nLead the ongoing development of IT security controls to safeguard the programs and data under the custody of IT, and to maintain a library of IT general control documents for security reviews and audit purpose.\nImplement, manage, support and maintain IT security control related technical systems.\nSetup and run an information security awareness programme covering an information security awareness intranet web portal and promotion campaigns to rise information security awareness of the whole organization.\nWork with training department to setup information security awareness training courses\nContribute to the setup, running, management and maintenance of an IT Service Continuity Management Process to continue provide IT services to enterprise users upon serious service interruption.\nReview IT operations and controls on a regular basis based on IT general control requirements. \u2022 Act as a coordinator to coordinate IT teams to participate in internal and external audits related to IT general controls.\nContribute to the review, planning, improvement and budgeting of IT services with the Senior Manager \u2013 Information Technology (Services & Infrastructure)\nRequirements:\n\n\nUniversity Degree in Electronic Engineering, Information Technology, Information Systems Management, Computer Science or equivalent, a master degree is preferred\nMinimum 5 years\u2019 of relevant experience of which 2 years should be in managerial level\nProficient in English, Cantonese and Putonghua\nFamiliar with security standards like PCI-DSS, ISO 27001, NIST Cybersecurity frameworks, CIS Controls, and / or data privacy.\nPossess experience with business continuity, disaster recovery, risk management, vulnerability assessment and IT audit\nCertified in CISSP, CRISC and CISA is preferred\nAble to explain complex cyber security threat, impact and mitigation in laymen terms to top management\nStrong critical thinking and problem-solving ability\nWorking experience in banking/financial services is a plus.\n\nWe offer remuneration to the right person with fast track career development opportunities and fringe benefits. Interested parties please apply withdetailed resume, current and expected salary.\n\nPersonal data collected will be used for recruitment purpose only. Applicants who are not contacted within 4 weeks should consider their applications unsuccessful and will be filed for opportunities in future.", "employment_types": ["Full Time", "Permanent"], "selling_points": ["Familiar with security standards", "Possess experience with business continuity, audit", "Certified in CISSP, CRISC and CISA is preferred"], "locations": ["North Point"], "categories": ["Information Technology (IT)", "IT Auditing", "Security"], "post_time": "2022-01-06T11:14:22Z", "salary": {"currency": null, "max": null, "min": null, "period": "monthly", "term": null}, "salary_visible": false, "title_keywords": ["manager"], "responsibilities": ["it service", "information security", "data", "operations", "budgeting", "audit", "it security management", "maintain", "promotion campaigns", "control", "infrastructure", "teams", "setup", "management", "review", "internal and external audits", "maintenance", "systems", "coordinate", "planning"], "requirements": {"degrees": ["university degree", "master degree"], "majors": ["engineering", "computer science", "information technology"], "languages": ["cantonese", "putonghua", "english"], "language_level": ["proficient"], "hard_skills": ["problem-solving", "plus", "cyber security"], "soft_skills": ["problem-solving"], "languages_combined": [{"language": "cantonese", "language_level": ["proficient"]}, {"language": "putonghua", "language_level": ["proficient"]}, {"language": "english", "language_level": ["proficient"]}]}, "experience_required": {"duration": ["2 years", "minimum 5 years"], "field": ["managerial", "risk management", "disaster recovery", "audit", "business", "relevant experience", "it", "financial services", "banking"]}}, {"job_id": "100003009033517", "location_code": "hk", "company": "Pinpoint Asia Limited", "job_title": "Security Operations Engineer - FinTech Group", "description": "Our client, a fast-growing Fintech Group is looking for a Security Operations Engineer to join their expanding technology team with a growing business in Asia. Great regional exposure and an opportunity to join an international fast-growing fintech venture.\n\nResponsibilities:\n\nProvide support on IT Security Operations including network, VPN, firewalls etc.\nPerform IT Security tasks like Single Sign-On (SSO) Maintenance, E-mail account management, log scanning etc.\nAnalyze and troubleshoot network platform including routers, switches, load balancers, firewalls, etc.\nDevelop appropriate system and data backup strategies and perform backups accordingly.\nManage and implement security tools including Data Loss Protection, Anti Malware products.\nConduct vulnerability scan and penetration test.\nMonitor and ensure stability and performance requirements.\nManage and monitor security incidents.\nDevelop DR and BCP plan, and perform Disaster Recovery drill.\n\nRequirements:\n\nAt least 3 years of experience with hands-on security operation space.\nExposure to penetration testing, web application security, vulnerability assessment, security risk assessment, cloud security configuration and review, security monitoring, etc.\nExposure to AWS Security configurations and security tools.\nExperience with Application Security testing including static and dynamic testing tools.\nExcellent communication skills both written and oral in English.\nSecurity Certificates in CISSP or equivalent is a great plus\nBachelor's Degree in Computer Science or related field from a reputable University.\n\nIf this outstanding opportunity sounds like your next career move, please send your resume in Word format to Danny Kwan at resume(at)pinpointasia(dot)com and put Security Operations Engineer - FinTech Group in the subject header.\n\nData provided is for recruitment purposes only.", "employment_types": ["Full Time"], "selling_points": ["1LOD SecOps", "Fast Growing Environment", "International Environment"], "locations": ["Not Specified"], "categories": ["Information Technology (IT)", "IT Auditing", "Security", "Network & System"], "post_time": "2022-01-10T00:08:25Z", "salary": {"currency": "HKD", "max": 54999, "min": 35000, "period": "monthly", "term": null}, "salary_visible": true, "title_keywords": ["operations", "engineer"], "responsibilities": ["scanning", "provide support", "management", "maintenance", "data", "operations", "monitor", "develop", "troubleshoot", "plan", "backups", "security tasks"], "requirements": {"degrees": ["degree", "bachelor"], "majors": ["computer science"], "languages": ["english"], "language_level": ["excellent"], "hard_skills": ["plus", "web application security", "word", "aws", "dynamic"], "soft_skills": ["communication skills", "hands-on", "dynamic", "oral"], "languages_combined": [{"language": "english", "language_level": ["excellent"]}]}, "experience_required": {"duration": ["at least 3 years"], "field": ["operation", "security", "testing"]}}, {"job_id": "100003009019748", "location_code": "hk", "company": "Ambition", "job_title": "IT Audit Manager, Big 4 Welcome", "description": "Our client is a renowned Retail and Commercial Bank in Hong Kong with strong local presence. With the team expanding, an excellent opportunity arises for IT Audit professionals.\n\nResponsibilities\n\n\n\nManage & conduct IT audit assignments/ compliance assessment for IT infrastructure & applications in the Bank\nParticipate in IT governance reviews and technical assessments and internal control improvements\nIdentify and assess IT risk areas, enhance audit process through implementing comprehensive audit standards, methodologies & techniques\nPrepare reports with audit findings and recommendations\nAssist in developing and maintaining Computer Assisted Auditing Techniques (\"CAATs\") Programs and re-running routine CAATs programs\n\nTo qualify, individuals must possess:\n\n\n\nDegree holder in Computer Science or related disciplines\nMinimum 3 years of experience in IT audit or related fields in system securities, preferably in banking industry\nProfessional qualifications of CISA, CISSP or equivalent\nIndependent with analytical mind and risk control sense\nProficiency in both English and Chinese\n\nContact Andy Yip at (852) 3103 4309 / andy.yip@ambition.com.hk or APPLY NOW by clicking the button below quoting reference number AY 247566\n\nData provided is for recruitment purposes only\n\n\n\nIf this job isn't quite right for you, but you know someone who would be great at this role, why not take advantage of our referral scheme? We offer HKD1000 in Apple gift cards for every referred candidate who we place in a role. Terms & Conditions Apply. https://www.ambition.com.hk/refer-a-friend", "employment_types": ["Full Time", "Permanent"], "selling_points": ["Open to Big 4", "Well-established bank", "Excellent career prospect"], "locations": ["Not Specified"], "categories": ["Accounting", "Audit", "Banking / Finance", "Others", "Information Technology (IT)", "IT Auditing"], "post_time": "2022-01-04T08:36:07Z", "salary": {"currency": "HKD", "max": 69999, "min": 45000, "period": "monthly", "term": null}, "salary_visible": true, "title_keywords": ["manager"], "responsibilities": ["control", "it infrastructure", "maintaining", "data", "compliance", "audit", "developing", "recruitment", "contact", "banking", "prepare reports", "auditing", "internal control"], "requirements": {"degrees": ["degree holder"], "majors": ["related disciplines", "computer science"], "languages": ["english", "chinese"], "language_level": ["proficiency"], "hard_skills": ["professional qualifications", "scheme", "internal control"], "soft_skills": ["analytical mind", "comprehensive", "independent"], "languages_combined": [{"language": "english", "language_level": ["proficiency"]}, {"language": "chinese", "language_level": ["proficiency"]}]}, "experience_required": {"duration": ["minimum 3 years"], "field": ["banking industry", "related", "audit", "it", "securities"]}}, {"job_id": "100003009008825", "location_code": "hk", "company": "Aston Carter", "job_title": "IT Auditor ( Manager/ Senior Manager ) FI, 50 k +", "description": "New senior IT audit manager role\nLead IT PMO, governance, digital transformation, strategy etc.\nStable work environment\n\n\u5ba2\u6237\u7b80\u4ecb\n\nOur client is a well established organization with constant investment put in IT function. Given the advanced business direction, they are keen to have a new senior IT member joining the team now.\n\n\u5de5\u4f5c\u5185\u5bb9\n\nEstablish IT governance / compliance for the group\nDevelop enhanced standards and policies that govern the use of IT across the group\nProvide IT leadership and influence IT and non-IT departments\nEnsure that all Architecture, Standards and Policies are clearly communicated to stakeholders\nLead the group in adopting innovative IT application to keep its competitive advantage in the industry\nManage IT finance (Capex and Opex) and running IT department like a business\nAccountable for IT portfolio management, demand management, resource planning, IT risk and IT reporting\nDevelop and maintain a core data management capability to ensure that information and data has the appropriate level of integrity and can form the basis for effective business analysis and decision making.\nPromote synergy within IT teams\n\n\u7406\u60f3\u7684\u6c42\u804c\u8005\n\nBachelor Degree or above in Information Technology, Computer Science or equivalent\nMinimum of 10 years in IT audit management ideally with exposure also in IT Advisory, Risk & Governance, digital transformation, data management functions\nHands-on and extensive experience in change and transformation management\nOutstanding skills in stakeholder management, influencing, problem solving, relationship and project management\nThe right talent must be result and goal-driven, self motivated as well\nCandidate must speak fluent Chinese and English\nCandidate with consultancy / vendor background will be at advantage\nCandidate with professional certificates in ITIL, PMP, COBIT, Scrum Master, DevOps are preferred\n\n\u798f\u5229\u5f85\u9047\n\nOutstanding remuneration package and a stable work environment can be provided.\n\nTo apply online please click the Apply button below. For a confidential discussion about this role please contact Michelle J Ma on +852 2258 3539", "employment_types": ["Full Time", "Permanent"], "selling_points": ["Financial Institution", "IT Auditor", "Reputable brand name and culture"], "locations": ["Not Specified"], "categories": ["Banking / Finance", "Retail Banking", "Information Technology (IT)", "IT Auditing", "Security"], "post_time": "2021-12-30T09:19:32Z", "salary": {"currency": null, "max": null, "min": null, "period": "monthly", "term": null}, "salary_visible": false, "title_keywords": ["senior manager", "manager"], "responsibilities": ["reporting", "management", "data", "policies", "compliance", "capex", "audit", "teams", "develop", "opex", "project management", "maintain", "contact", "business analysis", "architecture", "planning"], "requirements": {"degrees": ["degree or above", "bachelor", "master"], "majors": ["computer science", "information technology"], "languages": ["english", "chinese"], "language_level": ["fluent"], "hard_skills": ["itil", "data management", "analysis", "devops", "vendor", "problem solving", "project management", "goal", "pmp"], "soft_skills": ["advanced", "keen", "integrity", "accountable", "extensive", "problem solving", "project management", "hands-on", "self motivated", "stable", "innovative", "leadership", "driven", "decision making"], "languages_combined": [{"language": "english", "language_level": ["fluent"]}, {"language": "chinese", "language_level": ["fluent"]}]}, "experience_required": {"duration": [], "field": ["management"]}}, {"job_id": "100003009016467", "location_code": "hk", "company": "Mazars CPA Limited", "job_title": "Manager - IT, Internal Audit (Ref: HK-M-IT-RAS)", "description": "Job Duties:\n\nDevelop IT policies, standards, and procedures in accordance with industry standard, best practice and relevant regulatory requirements\nAssist in performing IT Compliance and Security Management\nParticipate in the implementation of IT control and process to ensure the compliance with regulatory requirements and company policies\nParticipate in regular compliance checking, IT security assessment and review, audit engagement and inquiries from regulator and/ or auditor\nCommunicate with internal and external auditors in performing IT audit process, risk and compliance monitoring\nCooperate with relevant internal units to implement the rectification opinions proposed by internal and external auditors\nPerform training on IT compliance and security awareness\n\nRequirements:\n\nBachelor degree or above in Information Technology, Computer Science or related disciplines\nMinimum 5 years\u2019 experience in IT auditing and compliance\nExtensive knowledge and understanding of Information Security framework, such as ISO27001/ 27002, GDPR, China Cyber Security\nHolder of professional certificates in ITIL, PMP, CISSP, CISA, CISM\nSolid interpersonal, communication and organizational skills with good team spirit\nAble to work independently under pressure and willing to work overtime\nOutstanding skills in stakeholder management and project management\nGood language communication and writing skills. Proficiency in English and Chinese (in both Cantonese and Putonghua)\n\nInterested candidates please send your resume by email or clicking \u201cApply Now\u201d.\n\nWe are equal opportunities employer. Applicants who are not invited within 2 months may consider their application unsuccessful. All applicants may be considered for other suitable positions with DCH Group / CITIC Pacific Group and will be deleted from our files after 6 months from the date of application.", "employment_types": ["Full Time", "Permanent"], "selling_points": ["IT compliance, risk control & audit advisory", "Attractive and competitive package", "Challenging and resilient"], "locations": ["Wan Chai"], "categories": ["Information Technology (IT)", "IT Auditing"], "post_time": "2022-01-03T09:08:36Z", "salary": {"currency": null, "max": null, "min": null, "period": "monthly", "term": null}, "salary_visible": false, "title_keywords": ["manager"], "responsibilities": ["communicate with", "management", "control", "regulatory requirements", "policies", "compliance", "procedures", "it policies", "implementation", "develop", "checking", "review", "audit", "monitoring", "rectification", "cooperate with", "external auditors"], "requirements": {"degrees": ["degree or above", "bachelor"], "majors": ["related disciplines", "computer science", "information technology"], "languages": ["cantonese", "putonghua", "english", "chinese"], "language_level": ["proficiency"], "hard_skills": ["itil", "cyber security", "writing skills", "project management", "pmp"], "soft_skills": ["organizational skills", "work independently", "team spirit", "under pressure", "work overtime", "writing skills", "communication", "project management", "extensive", "interpersonal"], "languages_combined": [{"language": "cantonese", "language_level": []}, {"language": "putonghua", "language_level": []}, {"language": "english", "language_level": ["proficiency"]}, {"language": "chinese", "language_level": ["proficiency"]}]}, "experience_required": {"duration": ["minimum 5 years"], "field": ["compliance", "it"]}}, {"job_id": "100003009027390", "location_code": "hk", "company": "Guosen Securities (HK) Financial Holdings Company, Limited", "job_title": "Risk Management Officer", "description": "One of the Asia's largest conglomerates based in the United Kingdom is now expanding their business in Hong Kong. They are looking for a security engineer to join their expanding IT team. The successful candidate will be involved in large-scale IT Security related projects.\n\nClient Details\n\nOur client is a highly diversified business group with business around the world. They work in a multitude of sectors across the globe, ranging from property development to marine services. To cope with technology advancement, they are now recruiting a passionate security engineer to join their IT Team. Candidates with more than one year of 2nd line support of security operations experience are highly preferred.\n\nDescription\n\nResponsible for:\n\nPerforming vulnerability scanning, remediation and reporting on both on-premises as well as cloud\nWorking closely with third party SOC for alerting\nProviding with regular patching\nSupporting with penetration test\nFacilitating security mitigation during software development\n\nProfile\n\nQualifications:\n\nDiploma or above in Computer Science or related discipline\nPossess basic cloud knowledge (e.g., Azure and AWS)\nCertificate holders of CEH, CISA, CISSP, CCSP will be considered\nDiligent and knowledgeable\nGood command of English and Chinese\n\nJob Offer\n\nHigh chances to convert to permanent\nWork-Life Balance\nNice working environment\n\nTo apply online please click the 'Apply' button below. For a confidential discussion about this role please contact Crystal Cheuk on +852 2258 3536", "employment_types": ["Full Time", "Permanent"], "selling_points": ["Manage operational risk & review policy", "Familiar with the operations of securities firm", "Familiar with the operations of IT"], "locations": ["Central & Western Area"], "categories": ["Banking / Finance", "Financial Services", "Information Technology (IT)", "IT Auditing", "Risk Management"], "post_time": "2022-01-06T10:04:37Z", "salary": {"currency": null, "max": null, "min": null, "period": "monthly", "term": null}, "salary_visible": false, "title_keywords": ["risk management officer"], "responsibilities": ["scanning", "reporting", "software", "operations", "contact", "third party"], "requirements": {"degrees": ["certificate", "diploma or above"], "majors": ["computer science"], "languages": ["english", "chinese"], "language_level": ["good command"], "hard_skills": ["nice", "basic", "azure", "aws"], "soft_skills": ["passionate", "diligent", "responsible"], "languages_combined": [{"language": "english", "language_level": ["good command"]}, {"language": "chinese", "language_level": ["good command"]}]}, "experience_required": {"duration": ["one year"], "field": ["security"]}}, {"job_id": "100003009016748", "location_code": "hk", "company": "Mazars CPA Limited", "job_title": "Senior / Associate - IT, Internal Audit (Ref: HK-S/A-IT-RAS)", "description": "Responsibilities:\n\nReview project requirements and related documentation such as sitemaps, wireframes, information architecture specifications & functional specifications\nCreate detailed, comprehensive and well-structured test plans and test cases\nExecute the plan and manage all activities in the plan to ensure that all the project objectives are met and the solution works as expected\nTrack and report the QA activities on multiple projects of various size\nConduct Unit Test, System Integration Test, End-to-End and Regression Test on both Front-End and Back-End system\nLiaise with off-site QA teammates to complete testing on multiple projects of various size\nWork closely within the project team (PM, UX, Creative and Developers) to identify, investigate, and resolve system problems and process issues\nAnalyze test results to ensure existing functionality and make appropriate recommendations\nContribute to and monitor test planning, test preparation and scripting, and test execution according to established test standards and procedures\nManage verification and validation activities for all production modifications\nWork closely with development team to review issues or bug reports\nIdentify areas where automated testing can be applied\nParticipate in, and provide opinions on projects\n\nRequirement:\n\n3+ years\u2019 experience in application development with quality assurance/test experience\nDiploma holder or above\u00a0in Computer Science, Information Technology or related disciplines\nSound knowledge of application development (web and app) projects\nKnowledgeable in all processes and procedures utilized for quality assurance\nExperience with different operating systems, common web browsers, HTML and CSS\nKnowledge with Atlassian products Jira\nProficient in quality assurance methodology, change management and communication skills\nExperience in automatic test and framework is a plus\nProficiency in both spoken and written English and Chinese\nIndependent, Self-motivated, detail-oriented and able to work under pressure and meet\u00a0tight\u00a0deadlines\nPositive \u201ccan-do\u201d attitude\nWorking Location: Tseung Kwan O Industrial Estate\n\nInterested parties please click \u201cApply Now\" to submit your complete resume with\u00a0compensation history, expected salary and REFERENCE NUMBER or by\u00a0post to\u00a0Human Resources Department,\u00a03/F,\u00a0Sing Tao News Corporation Building, 7 Chun Cheong Street, Tseung Kwan O Industrial Estate, Tseung Kwan O, New Territories, Hong Kong\n\nWe are an equal opportunity employer and welcome applications from all qualified candidates. Information provided will be treated in strict confidence and only be used for recruitment related purpose. Applicant who is not invited for an interview within 6 weeks may consider their application not successful. All personal data of unsuccessful applicants will be destroyed within 6 months.\n\nwww.singtaonewscorp.com", "employment_types": ["Full Time", "Permanent"], "selling_points": ["IT compliance, risk control & audit advisory", "Birthday leave, staff activities and events", "Challenging and resilient"], "locations": ["Wan Chai"], "categories": ["Information Technology (IT)", "IT Auditing"], "post_time": "2022-01-03T09:47:39Z", "salary": {"currency": null, "max": null, "min": null, "period": "monthly", "term": null}, "salary_visible": false, "title_keywords": ["associate"], "responsibilities": ["project requirements", "related documentation", "review", "monitor", "procedures", "testing", "specifications", "planning", "reports", "plan", "liaise with", "plans", "architecture", "multiple projects", "report"], "requirements": {"degrees": ["diploma holder"], "majors": ["related disciplines", "computer science", "information technology"], "languages": ["english", "chinese"], "language_level": ["proficiency"], "hard_skills": ["plus", "web", "html", "web browsers", "css"], "soft_skills": ["communication skills", "self-motivated", "meet tight deadlines", "independent", "detail-oriented", "can-do", "positive", "work under pressure"], "languages_combined": [{"language": "english", "language_level": ["proficiency"]}, {"language": "chinese", "language_level": ["proficiency"]}]}, "experience_required": {"duration": ["3+ years"], "field": ["application development", "quality assurance"]}}, {"job_id": "100003009016486", "location_code": "hk", "company": "Bank of China (Hong Kong) Limited", "job_title": "Senior Technology Risk Manager / Technology Risk Manager (2nd line of defense)", "description": "My client is a financial\u00a0institution\u00a0in Hong Kong and looking\u00a0for IT Auditor to support their expanding business.\n\nKey Responsibilities:\n\nPerform, support or lead where directed, the planning, fieldwork, and reporting of audit activities in accordance with department and professional standards, and complete assignments in an efficient manner\nActs in an integrated manner with audit colleagues and stakeholders, and demonstrates a proactive and engaging approach during audit cycle\nPerform follow up, tracking, validation and reporting of audit issues\nHighlight forward looking indicators of potential risks within the areas assigned through performing continuous monitoring/auditing activities\nExecute risk assessment, and obtain understanding of business strategy, plans, products, performance and risk-related issues to assist audit planning\nAssist in preparing accurate and timely management reporting\n\nQualifications and Key Requirements\n\nBachelor\u2019s degree in a related discipline and relevant professional qualification such as CIA, CCSP, CISM, CISA, CISSP\nMinimum 7 years experience in IT security or risk and control functions, preferably from financial services or banking industry\nStrong innovative and agile mindset; Flexibility to work across different situations and change priorities at short notice\nSolid knowledge and/or practical experience on cyber security and infrastructure security, good understanding of related regulatory expectations and framework\nGood understanding of the technology best practice (e.g. ITIL, COBIT, ISO2700) and regulatory framework, and general understanding of banking products\nExperience in planning and executing audits in accordance with professional standards, and with minimal supervision\nEnthusiastic, self-motivated, strong interest in learn\nBig 4 Candidates are preferred\n\nFor further details, please send your resume to cherry.lai@astoncarter. com / contact 3473-3253.", "employment_types": ["Full Time"], "selling_points": ["Formulate technology risk management strategies", "Bachelor Degree holder or above", "6 years\u2019 experience or above in IT security"], "locations": ["Central"], "categories": ["Information Technology (IT)", "IT Auditing", "Security"], "post_time": "2022-01-03T09:11:53Z", "salary": {"currency": null, "max": null, "min": null, "period": "monthly", "term": null}, "salary_visible": false, "title_keywords": ["manager"], "responsibilities": ["reporting", "audit", "planning", "continuous monitoring", "management reporting", "plans", "auditing", "tracking"], "requirements": {"degrees": ["degree", "bachelor"], "majors": [], "languages": [], "language_level": [], "hard_skills": ["itil", "agile", "cyber security"], "soft_skills": ["self-motivated", "innovative", "agile", "enthusiastic"], "languages_combined": []}, "experience_required": {"duration": ["minimum 7 years"], "field": ["banking industry", "related", "infrastructure", "it", "financial services", "security", "planning"]}}, {"job_id": "100003009016759", "location_code": "hk", "company": "Bank of China (Hong Kong) Limited", "job_title": "Senior Technology Risk Manager / Technology Risk Manager (2nd line of defense)", "description": "\nMazars, the smart choice.\n\nWhy join us\n\nTechnological change and deep transformations present new and unknown risks, but also new opportunities to create value. In today\u2019s volatile and ever more complex business environment, companies need to have confidence in their governance, risk management and internal control processes. Join Mazars\u2019 IT Audit/Risk Advisory team (HK office) in building the resilience our clients need to protect their long-term performance. The role is based in Hong Kong.\n\nWhat you can expect\u00a0\n\n\nAssist in design and execute the day-to-day activities of IT-related audits and risk assessments, with a focus on strategic, operational and regulatory / compliance related risks\nPlan activities related to development of audit program, and execution of internal audits and IT control assessments\nReview clients' processes and controls against leading practice and industry frameworks, identify gaps in design and execution, and communicate issues and recommendations to engagement leads and senior management of clients\nLead proposal and business development activities by building propositions, identifying of new target clients, building business relationships with key executives, developing/presenting proposals, and assisting with client presentations\nContribute to technology risk knowledge base and internal practice development initiatives\nSupervise and provide performance management for junior staff working on assigned engagements\nWrite and present clear and concise reports and presentations containing meaningful observations and recommendations to clients, and document procedures performed and conclusions reached related to projects\nWho we are looking for\u00a0\n\nA minimum of 4-6 years of experience working within an internal audit, IT risk or IT compliance function as an internal employee or as part of a professional services firm\nBachelor\u2019s/Master\u2019s degree in an appropriate field from an accredited college/university\nMember or finalist of CISA, PMP, CISSP, CGEIT or CRISC certification\nGood reporting and presentation skills\nAbility to deliver work within tight timelines, on budget and at a high level of quality\nStrong teamwork ability and able to work independently\nExcellent written and verbal communication skills in English and Chinese\u00a0(Mandarin or Cantonese)\u00a0and exceptional interpersonal skills; able to gain the confidence and respect of senior level staff\nWilling to travel (more than 50%) and ability to work diligently under pressure\n\nWhat we offer\n\nWe recognise that rewards are important to you. On top of the base salary you will be receiving, we offer a range of staff caring benefits and policies including medical and dental insurance, life insurance, a 5-day working week, discretionary performance bonus, birthday leave and marriage leave. Please apply with detailed resume and public examination results, grade you are applying, contact numbers, current salary and expected salary in strict confidence.\n\nInformation provided will be treated in strict confidence and only be used for recruitment purposes.", "employment_types": ["Full Time"], "selling_points": ["IT Security", "2nd line of defense on technology risk", "Review IT initatives from tech risk perspectives"], "locations": ["Central"], "categories": ["Information Technology (IT)", "IT Auditing"], "post_time": "2022-01-03T09:47:03Z", "salary": {"currency": null, "max": null, "min": null, "period": "monthly", "term": null}, "salary_visible": false, "title_keywords": ["manager"], "responsibilities": ["internal audit", "budget", "quality", "audit", "design", "communication", "plan", "senior management", "internal control", "control", "compliance", "developing", "presentations", "reports", "reporting", "management", "review", "procedures", "audits"], "requirements": {"degrees": ["degree", "bachelor", "master"], "majors": [], "languages": ["cantonese", "english", "chinese", "mandarin"], "language_level": ["excellent"], "hard_skills": ["focus", "pmp", "presentations", "internal control"], "soft_skills": ["communication skills", "work independently", "confidence", "under pressure", "deep", "teamwork", "clear", "presentation skills", "interpersonal skills", "business environment", "focus"], "languages_combined": [{"language": "cantonese", "language_level": ["excellent"]}, {"language": "english", "language_level": ["excellent"]}, {"language": "chinese", "language_level": ["excellent"]}, {"language": "mandarin", "language_level": ["excellent"]}]}, "experience_required": {"duration": ["minimum of 4-6 years"], "field": ["compliance", "it", "audit"]}}, {"job_id": "100003009016939", "location_code": "hk", "company": "Michael Page", "job_title": "Senior Internal Auditor/ IA  - Big 4 are Welcome (35-43K)", "description": "Responsibilities:\n\nWork closely with business units to identify, assess, monitor and control operational risk\nConduct reviews to identify possible operational risks and provide recommendations to address the control weakness; monitor the implementation progress of the enhanced controls\nConduct due diligence pertaining to new products/ services as well as insourced/ outsourced activities, give advice on operational risk management matters\nWork closely with business/ support units to effectively manage operational risk in accordance with legal, regulatory and internal requirements\nProvide training on operational risk management\nAsset management pre trade and post trade compliance checking\nTo perform ad hoc projects as required\n\nRequirements:\n\nDegree or above with major in Finance, Economics, Information system or other related discipline\n3 years\u2019 work experience in operational risk or related areas\nFamiliar with the operations of securities firm\nKnowledge / Experience in Information Technology operations would be advantages\nAttention to details, good analytical and interpersonal skills\nGood command of written and spoken English and Chinese, fluency in Putonghua\n\n\nAttractive remuneration will be offered to the right candidate.\u00a0 Interested parties please email your full resume with present & expected salary and date of availability to hrm @guosen.com.hk or via \"Apply Now\".\n\nPersonal data collected would be used for recruitment purpose only.", "employment_types": ["Full Time", "Permanent"], "selling_points": ["Group Position", "Property Opportunity", "HK listed"], "locations": ["Central & Western Area"], "categories": ["Accounting", "Audit", "Information Technology (IT)", "IT Auditing"], "post_time": "2022-01-03T10:10:00Z", "salary": {"currency": null, "max": null, "min": null, "period": "monthly", "term": null}, "salary_visible": false, "title_keywords": ["internal auditor"], "responsibilities": ["provide training", "due diligence", "control", "management", "compliance", "monitor", "implementation", "checking", "provide recommendations", "ad hoc projects", "asset management"], "requirements": {"degrees": ["degree or above"], "majors": ["finance", "economics"], "languages": ["putonghua", "english", "chinese"], "language_level": ["fluency", "good command"], "hard_skills": ["information system"], "soft_skills": ["interpersonal skills", "attention to details"], "languages_combined": [{"language": "putonghua", "language_level": ["fluency", "good command"]}, {"language": "english", "language_level": ["fluency", "good command"]}, {"language": "chinese", "language_level": ["fluency", "good command"]}]}, "experience_required": {"duration": ["3 years"], "field": ["related", "information technology"]}}, {"job_id": "100003009019611", "location_code": "hk", "company": "Page Group Hong Kong", "job_title": "Contract Security Engineer", "description": "Role Objective:\nTo participate in strengthening the cybersecurity team capacity and capability to carry out information security functions and activities.\n\nJob Duties:\n\nAssist in develop IT security architecture and implement security policies, protocols and procedures\nAssist in security risk assessment, IT audit and daily support of information security related systems\nAssist in software and Cloud service security review\nConducts security assessments (Penetration test, red-team (attack simulation) with an external consultant to identify security risks and follow up mitigation items\nConducts regular review of security control and comply with the company's security policy\nAssist in Implementation and delivery of Cybersecurity solutions and services\nResponsible for operating, administering and serving as a subject matter expert on security tools including but not limited to:\nIdentity and access management tools\nVulnerability management tools\nEndpoint Detection and Response tools\nNetwork security tools\nNetwork behavior anomaly detection tools\nUser and Entity Behavior Analytics tools\nApplication security tools\nResearch on cyber resilience maturity model, information security governance mechanism, and other related topics\nAssist in promotion of cyber security awareness\nPerform vendor and contract management during the procurement\nWork with matrix-ed system engineer to review significant changes\nParticipate in information security related projects\nCoordinate with internal and external auditors to perform information system audits\nPerform vulnerability assessment for major OS platforms and technologies\nHandle daily operation and security event with Security Operation Centre\nDevelop and implement appropriate recovery plans for resilience and to restore IT services that were impaired due to a security incident\nAssist in any security reports, trend analysis and documents preparation\nRequirements:\n\nMinimum 5 years of relevant experience in IT security areas.\nFamiliar with frameworks such as ISO27001, NIST, COBIT, ITIL, PCI\nKnowledge or experience in formulating cyber resilience maturity or management model\nGood knowledge and experience with vulnerability and compliance management products\nGood knowledge and experience with security monitoring, automation products and forensic tools\nGood knowledge and experience with security infrastructure products\nIndependent, self-motivated, and able to work under pressure\nProfessional qualifications and/or certifications holder would be preferred (e.g. CEH, CISM, CISA, CISSP, ISO/IEC 27001 lead auditor, etc.)\nCandidates with less experience may be considered for the System Analyst position\nRemuneration\n\n\nWe offer a 5-day work week and an attractive remuneration package commensurate to the right candidates with qualifications and working experience. Fringe benefits for staff include annual leave, paternity leave, birthday leave, volunteering leave, medical scheme, life insurance, Employee Unit Purchase Plan and performance-based incentives.\n\nApplication\n\nIf you resonate with Link's vision and aspire to develop a rewarding career with us, please apply by clicking \"Apply Now\".\n\nWe are an equal opportunity employer. Personal data provided by job applicants will be treated in strict confidence and used strictly in accordance with our Privacy Policy Statement for recruitment purpose only. A copy of the Statement is available on our website (Linkreit.com). Applicants not hearing from us within 6 months may consider their applications unsuccessful.", "employment_types": ["Full Time", "Contract"], "selling_points": ["Hands on IT Security function", "Great collaborative culture", "Engage with both operation and projects"], "locations": ["Not Specified"], "categories": ["Information Technology (IT)", "IT Auditing", "Security", "Network & System"], "post_time": "2022-01-04T08:07:10Z", "salary": {"currency": "HKD", "max": 29999, "min": 14000, "period": "monthly", "term": null}, "salary_visible": true, "title_keywords": ["engineer"], "responsibilities": ["software", "information security", "cyber security", "audit", "regular review", "plans", "control", "implementation", "develop", "reports", "vulnerability management", "architecture", "management", "review", "procedures", "coordinate with", "security operation", "audits", "analytics tools", "policies", "analysis", "systems", "daily operation", "subject matter expert", "contract management", "external auditors"], "requirements": {"degrees": [], "majors": [], "languages": [], "language_level": [], "hard_skills": ["itil", "professional qualifications"], "soft_skills": ["self-motivated", "independent", "work under pressure"], "languages_combined": []}, "experience_required": {"duration": ["minimum 5 years"], "field": ["management", "compliance", "infrastructure", "it", "relevant experience", "security", "system analyst"]}}, {"job_id": "100003009014116", "location_code": "hk", "company": "Evolution Security Consulting", "job_title": "Auditor / Consultant, Security Audit and Compliance", "description": "\nMazars, the smart choice.\n\nWhy join us\n\nTechnological change and deep transformations present new and unknown risks, but also new opportunities to create value. In today\u2019s volatile and ever more complex business environment, companies need to have confidence in their governance, risk management and internal control processes. Join Mazars\u2019 IT Audit/Risk Advisory Services team (HK office) in building the resilience our clients need to protect their long-term performance. The role is based in Hong Kong.\n\nWhat you can expect\u00a0\n\n\nAssist in design and execute the day-to-day activities of IT-related audits and risk assessments, with a focus on strategic, operational and regulatory / compliance related risks\nSupport in planning activities related to development of audit program, and execution of internal audits and IT control assessments\nTake part in reviewing clients' processes and controls against leading practice and industry frameworks, identify gaps in design and execution, and communicate issues and recommendations to engagement leads and senior management of clients\nContribute to technology risk knowledge base and internal practice development initiatives\nSupport senior and supervise junior staff working on assigned engagements\nContribute to preparing concise reports and presentations containing meaningful observations and recommendations to clients, and document procedures performed and conclusions reached related to projects\n\nWho we are looking for\u00a0\n\nA minimum of 1 year of experience working within an internal audit, IT risk or IT compliance function as an internal employee or as part of a professional services firm\nBachelor\u2019s/Master\u2019s degree in an appropriate field from an accredited college/university\nMember or finalist of CISA, PMP, CISSP, CGEIT or CRISC certification\nGood reporting and presentation skills\nAbility to deliver work within tight timelines, on budget and at a high level of quality\nStrong teamwork ability and able to work independently\nExcellent written and verbal communication skills in English and Chinese\u00a0(Mandarin or Cantonese)\u00a0and exceptional interpersonal skills; able to gain the confidence and respect of senior level staff\nWilling to travel (more than 50%) and ability to work diligently under pressure\n*Candidates with less experience will be considered as Associates.\n\nWhat we offer\n\nWe recognise that rewards are important to you. On top of the base salary you will be receiving, we offer a range of staff caring benefits and policies including medical and dental insurance, life insurance, a 5-day working week, discretionary performance bonus, birthday leave and marriage leave. Please apply with detailed resume and public examination results, grade you are applying, contact numbers, current salary and expected salary in strict confidence.\n\nInformation provided will be treated in strict confidence and only be used for recruitment purposes.", "employment_types": ["Full Time", "Permanent"], "selling_points": ["UK / Asia Firm on IT Assessment and Audit", "Audit Consultant, Various Level of Seniority", "Team Expansion with Attractive Packages"], "locations": ["Not Specified"], "categories": ["Information Technology (IT)", "IT Auditing", "Security", "Technical / Functional Consulting"], "post_time": "2022-01-03T03:03:08Z", "salary": {"currency": null, "max": null, "min": null, "period": "monthly", "term": null}, "salary_visible": false, "title_keywords": ["consultant"], "responsibilities": ["reporting", "management", "control", "internal audit", "compliance", "procedures", "audit", "design", "presentations", "budget", "quality", "communication", "planning", "reports", "audits", "senior management", "internal control"], "requirements": {"degrees": ["degree", "bachelor", "master"], "majors": [], "languages": ["cantonese", "english", "chinese", "mandarin"], "language_level": ["excellent"], "hard_skills": ["focus", "pmp", "presentations", "internal control"], "soft_skills": ["communication skills", "work independently", "confidence", "under pressure", "deep", "teamwork", "presentation skills", "interpersonal skills", "business environment", "focus"], "languages_combined": [{"language": "cantonese", "language_level": ["excellent"]}, {"language": "english", "language_level": ["excellent"]}, {"language": "chinese", "language_level": ["excellent"]}, {"language": "mandarin", "language_level": ["excellent"]}]}, "experience_required": {"duration": ["minimum of 1 year"], "field": ["compliance", "it", "audit"]}}, {"job_id": "100003009017354", "location_code": "hk", "company": "Robert Walters (HK)", "job_title": "Project Manager - Vendor Risk Management", "description": "Responsibilities:\nFormulate technology risk management strategies, policy, processes and work plans.\nReview IT initiatives from technology risk perspectives and provide advisory and recommendation.\nResearch and evaluate latest security threats and technology solutions, such as Cloud, Big Data, Artificial Intelligence, Social Networking and Mobility.\nReview security architecture and relevant policies for the organization infrastructure, applications and cyber resilience.\nPerform 2nd line assurance reviews.\nPrepare management reports on technology risk assessment or review results.\nCoordinate IT related regulatory examinations and enquiries.\nRequirements:\nBachelor Degree holder or above with major in Information Technology or related disciplines.\n6 years\u2019 experience or above in IT security, technology risk or IT audit field of banking industry will be considered for Senior Technology Risk Manager\nHolders of Certified Information Systems Auditor (CISA), Certified Information Systems Security Professional (CISSP) or Certified Information Systems Manager (CISM) is preferred\nSound knowledge in HKMA requirements and industrial security standards. Knowledge / experience in technology risk management in Southeast Asian countries will be an advantage\nBe able to work independently and under pressure. Be a good team player.\nProficiency in Mandarin; good Chinese and English report writing skills", "employment_types": ["Full Time", "Contract"], "selling_points": ["external vendors governance", "vendors and applications SLA review", "vendor risk management or operational risk manage"], "locations": ["Not Specified"], "categories": ["Information Technology (IT)", "IT Auditing", "IT Project Management / Team Lead", "Banking / Finance", "Risk Management"], "post_time": "2022-01-03T14:34:58Z", "salary": {"currency": null, "max": null, "min": null, "period": "monthly", "term": null}, "salary_visible": false, "title_keywords": ["project manager"], "responsibilities": ["management", "policies", "review", "big data", "infrastructure", "evaluate", "coordinate", "management reports", "plans", "architecture"], "requirements": {"degrees": ["bachelor degree holder"], "majors": ["related disciplines", "information technology"], "languages": ["english", "chinese", "mandarin"], "language_level": ["proficiency", "good"], "hard_skills": ["hkma", "writing skills"], "soft_skills": ["good team player", "work independently", "under pressure", "writing skills"], "languages_combined": [{"language": "english", "language_level": ["good"]}, {"language": "chinese", "language_level": ["good"]}, {"language": "mandarin", "language_level": ["proficiency"]}]}, "experience_required": {"duration": ["6 years"], "field": ["banking industry", "risk management", "audit", "it", "security"]}}, {"job_id": "100003009017112", "location_code": "hk", "company": "Caf\u00e9 de Coral Group Limited", "job_title": "IT Security Manager", "description": "Responsibilities:\nFormulate technology risk management strategies, policy, processes and work plans.\nReview IT initiatives from technology risk perspectives and provide advisory and recommendation.\nResearch and evaluate latest security threats and technology solutions, such as Cloud, Big Data, Artificial Intelligence, Social Networking and Mobility.\nReview security architecture and relevant policies for the organization infrastructure, applications and cyber resilience.\nPerform 2nd line assurance reviews.\nPrepare management reports on technology risk assessment or review results.\nCoordinate IT related regulatory examinations and enquiries.\nRequirements:\nBachelor Degree holder or above with major in Information Technology or related disciplines.\n6 years\u2019 experience or above in IT security, technology risk or IT audit field of banking industry will be considered for Senior Technology Risk Manager\nHolders of Certified Information Systems Auditor (CISA), Certified Information Systems Security Professional (CISSP) or Certified Information Systems Manager (CISM) is preferred\nSound knowledge in HKMA requirements and industrial security standards. Knowledge / experience in technology risk management in Southeast Asian countries will be an advantage\nBe able to work independently and under pressure. Be a good team player.\nProficiency in Mandarin; good Chinese and English report writing skills", "employment_types": ["Full Time", "Permanent"], "selling_points": ["IT risk management for the corporation", "Security review of company-wide IT operations", "Degree with 5-10 years of relevant exp."], "locations": ["Shatin Area"], "categories": ["Information Technology (IT)", "IT Auditing", "Security"], "post_time": "2022-01-03T20:52:19Z", "salary": {"currency": null, "max": null, "min": null, "period": "monthly", "term": null}, "salary_visible": false, "title_keywords": ["manager"], "responsibilities": ["management", "policies", "review", "big data", "infrastructure", "evaluate", "coordinate", "management reports", "plans", "architecture"], "requirements": {"degrees": ["bachelor degree holder"], "majors": ["related disciplines", "information technology"], "languages": ["english", "chinese", "mandarin"], "language_level": ["proficiency", "good"], "hard_skills": ["hkma", "writing skills"], "soft_skills": ["good team player", "work independently", "under pressure", "writing skills"], "languages_combined": [{"language": "english", "language_level": ["good"]}, {"language": "chinese", "language_level": ["good"]}, {"language": "mandarin", "language_level": ["proficiency"]}]}, "experience_required": {"duration": ["6 years"], "field": ["banking industry", "risk management", "audit", "it", "security"]}}, {"job_id": "100003008493709", "location_code": "hk", "company": "Vantis Solutions Limited", "job_title": "Cloud SaaS ERP Senior/Solutions Consultant ( Oracle Netsuite )", "description": "Our client is a very well known and sizable property company in Hong Kong and they are currently seeking for a Senior Internal Auditor / Internal auditor with 2-4 years of audit & accounting experience to join their team to handle internal audit . If you are a candidate who is hoping for a stable yet challenging career, here is your chance!\n\nClient Details\n\nOur client is one of largest property investment, development & management companies in Hong Kong . They are now seeking for a high potential auditing candidate to join their team. They are looking for an IA passionate individual. Candidates with CPA qualification or not are also welcomed\n\nDescription\n\nGroup operation & finance internal audit\nFamiliar with accounting standard and apply knowledges to relevant parties\nMaking sure all the audit reporting are within the deadlines\nBudgeting and operational internal control\n\nProfile\n\nDegree in Accounting, Finance or a related discipline\nBig 4 Trained. 2-4 years of experiences\nGood command of written and spoken English\nGood team player, detail-oriented and responsible\nPassed all CPA exams\n\nJob Offer\n\nCareer development opportunities\nSizable company\nVery stable working environment\n\nTo apply online please click the 'Apply' button below. For a confidential discussion about this role please contact Sunny Chan on +852 3602 2466.", "employment_types": ["Full Time", "Permanent"], "selling_points": ["Manage ERP Project Implementation", "5 working day", "Degree holder in IT/ Business related disciplines"], "locations": ["Lai Chi Kok"], "categories": ["Information Technology (IT)", "IT Auditing", "Support", "IT Management"], "post_time": "2022-01-04T02:45:37Z", "salary": {"currency": null, "max": null, "min": null, "period": "monthly", "term": null}, "salary_visible": false, "title_keywords": ["consultant"], "responsibilities": ["reporting", "management", "internal audit", "budgeting", "audit", "contact", "career development", "auditing", "internal control"], "requirements": {"degrees": ["degree"], "majors": ["finance", "accounting"], "languages": ["english"], "language_level": ["good command"], "hard_skills": ["cpa", "internal control"], "soft_skills": ["passionate", "good team player", "responsible", "detail-oriented", "stable"], "languages_combined": [{"language": "english", "language_level": ["good command"]}]}, "experience_required": {"duration": ["2-4 years"], "field": ["accounting experience", "audit", "team"]}}, {"job_id": "100003009012562", "location_code": "hk", "company": "ConnectedGroup Limited", "job_title": "Internal Audit, Assistant Director", "description": "This is a great opportunity to join one of Asia's largest conglomerates, headquartered in the United Kingdom. With many ongoing internal IT projects, there are increasing need in IT Security area. Hence, they are currently looking for a talent that help to providing 2nd line level support on Security Operation. Candidates who has hands on IT Security Operation is a must e.g. SCCM, Rapid 7, Microsoft Defender and so on.\n\n\u5ba2\u6237\u7b80\u4ecb\n\nOur client is a highly diversified global business group, which has been in operation for over 200 years. They work in a multitude of sectors across the globe, ranging from property development to marine services. The group employs over 120,000 people globally.\n\nWith their expanding business, they are currently looking for a skillfull Security Engineer to join their IT team.\n\n\u5de5\u4f5c\u5185\u5bb9\n\nResponsible for:\n\nPerforming vulnerability scanning, remediation and reporting on both on-premise as well as cloud\nProviding with regular patching\nWorks with different internal IT Stakeholders; supporting with penetration test\nParticipating with different IT Security related projects\n\n\u7406\u60f3\u7684\u6c42\u804c\u8005\n\nQualifications:\n\nDiploma or above in Computer Science or related discipline\nMore than 1 years working experience in 2nd level of IT Security Operations including SCCM, Rapid 7, Microsoft Defender and so on\nTeam player, self-motivated, able to multitask and to take initiative to get tasks completed\nGood interpersonal and presentation skills\nGood command of spoken and written English and Chinese\n\n\u798f\u5229\u5f85\u9047\n\nHigh chances to convert to permanent\nMedical Insurance\nDiscretionary Bonus\nWork-Life Balance\nNice working environment\nBetter career path on IT security area\nIn-house opportunity\n\nTo apply online please click the 'Apply' button below. For a confidential discussion about this role please contact Johnson Choy on +852 3602 2467.", "employment_types": ["Full Time", "Permanent"], "selling_points": ["Group Level Position", "Attractive Remuneration Package", "Well known property developer"], "locations": ["Not Specified"], "categories": ["Accounting", "Audit", "Others", "Information Technology (IT)", "IT Auditing"], "post_time": "2022-01-01T03:00:40Z", "salary": {"currency": "HKD", "max": 119999, "min": 90000, "period": "monthly", "term": null}, "salary_visible": true, "title_keywords": ["assistant director"], "responsibilities": ["scanning", "reporting", "operations", "security operation", "contact", "insurance"], "requirements": {"degrees": ["diploma or above"], "majors": ["computer science"], "languages": ["english", "chinese"], "language_level": ["good command"], "hard_skills": ["sccm", "nice", "rapid"], "soft_skills": ["self-motivated", "responsible", "multitask", "presentation skills", "hands on", "team player", "interpersonal", "initiative"], "languages_combined": [{"language": "english", "language_level": ["good command"]}, {"language": "chinese", "language_level": ["good command"]}]}, "experience_required": {"duration": ["1 years"], "field": ["it", "security"]}}, {"job_id": "100003009021035", "location_code": "hk", "company": "PCCW Solutions", "job_title": "Senior Commercial / Contract Manager", "description": "A regional financial institution is now hiring a project manager to join their technology risk team. Successful incumbent should possess vendor risk management experience.\n\nResponsibilities\n- Governance and management of internal & external outsourcing vendors\n- Perform vendors and applications services level review according to Master Service Agreement\n- Risk review and site visit according to Information and physical security requirement of the Banks\n- Ensure all operations of service providers compile to regulatory and groups requirements\n- Track progress of risks identified and mitigation actions until closure\n- Review assess change requests, ensure it aglins with bank compliance\n\nRequirements\n- Min 4 years relevant experience in financial institutions, experience in vendor risk management or operational risk management\n- Good understanding of information and physical security standard, operational risks, Business continuity management\n- Good knowledge of IT Quality and process improvement plan\n- Confidence in dealing with internal and external auditors, IT support, risk and compliance expertise\n- ITIL or CISA related certification will be an advantage but not a MUST", "employment_types": ["Full Time"], "selling_points": ["Conduct project audits", "Assist in reviews and reporting on high risk or distressed projects", "A minimum of 8 years of project leader experience"], "locations": ["Mong Kok"], "categories": ["Information Technology (IT)", "IT Auditing", "IT Project Management / Team Lead", "IT Management"], "post_time": "2022-01-05T02:56:28Z", "salary": {"currency": null, "max": null, "min": null, "period": "monthly", "term": null}, "salary_visible": false, "title_keywords": ["manager"], "responsibilities": ["management", "operations", "review", "compliance", "security requirement"], "requirements": {"degrees": [], "majors": [], "languages": [], "language_level": [], "hard_skills": ["itil", "vendor"], "soft_skills": ["confidence"], "languages_combined": []}, "experience_required": {"duration": ["min 4 years"], "field": ["risk management", "financial institutions", "relevant experience"]}}, {"job_id": "100003009024944", "location_code": "hk", "company": "HKT Consumer Group", "job_title": "Senior Programmer", "description": "Responsibilities\n\nThe applicant will be responsible for oversight of all aspect of information technology risk management (risk identification, measurement, monitoring and control) for the corporation, including but not limited to:\n\nAct as a subject matter expert in information security and technology risk for the organization\nDesign and implement enterprise-wide technology risk program. Assist in planning of technology related risk management strategies, processes and work plans\nReview IT initiatives from technology risk perspectives and work with vendors when necessary\nEstablish policy and security baseline for key IT processes. Establish and maintain security standards and guidelines with focus on application and network security\nReview security architecture for the organization infrastructure and application\nEstablish review processes on information security operation; review the remediation measures performed by IT department to verify the security risks identified have been properly addressed\nEstablish and manage information security incident response program. Develop guidelines to facilitate the communication between relevant stakeholders during incidents\nProvide support in post-incident investigation and forensics\nManage compliance measurement of security patch compliance for corporate infrastructure\nConduct security review of company-wide IT operations, assist in vulnerability assessments, penetration tests and source code review of corporate systems and facilitate improvement\nEstablish and implement the assessment on outsourcing/third party security control\nReport to senior management on the research and evaluation on latest security threats and technology solutions, such as Mobility and Personal Data Privacy\nProactively work with vendors to understand the up-to-date related technology for the possible implementation feasibility\nReport findings on security inefficiencies and provide recommendation for improvement\nIdentify logging, tracking and mitigating potential threats to the Company\nPromote cyber security awareness across the corporation\nRequirements:\n\nDegree or above in Computer Studies, Information Systems or related disciplines\n5-10 years of relevant Information Technology Risk, Information Security experience\nStrong understanding of retail and consumer goods industry, preferable in catering industry, information technology risk concept, and/or experience as IT security auditor/consultant\nSolid experience of risk assessment methodologies, internal controls and information technology risk management frameworks such as ITIL, COBIT 5, and ISO 27001\nGood communication and interpersonal skills across different levels of management\nWell organize, good time management & able to work under pressure\nAbility to work effectively with all levels of the organization\nIndustry certifications such as CISSP, CISM, CISA, CRISC. CEH, ISO Lead Auditor preferred\n\nInterested parties please send full resume with\u00a0PRESENT & EXPECTED SALARY\u00a0to Human Resources Department by clicking\u00a0\"Apply Now\".\n\nWe are an EQUAL OPPORTUNITIES EMPLOYER.\nAll information received will be kept in strict confidence and be used for employment-related purpose only.", "employment_types": ["Full Time"], "selling_points": [], "locations": ["Kowloon Bay"], "categories": ["Information Technology (IT)", "DBA", "IT Auditing"], "post_time": "2022-01-06T02:58:13Z", "salary": {"currency": null, "max": null, "min": null, "period": "monthly", "term": null}, "salary_visible": false, "title_keywords": ["senior programmer"], "responsibilities": ["information security", "cyber security", "operations", "design", "communication", "maintain", "evaluation", "plans", "senior management", "personal data", "control", "infrastructure", "measurement", "compliance", "implementation", "develop", "architecture", "report", "management", "provide support", "monitoring", "review", "investigation", "third party", "tracking", "guidelines", "systems", "subject matter expert", "provide recommendation", "planning"], "requirements": {"degrees": ["degree or above"], "majors": ["related disciplines", "computer studies"], "languages": [], "language_level": [], "hard_skills": ["itil"], "soft_skills": ["time management", "communication and interpersonal skills", "work effectively", "work under pressure"], "languages_combined": []}, "experience_required": {"duration": ["5-10 years"], "field": ["risk management", "information technology", "it", "security", "retail"]}}, {"job_id": "100003009012082", "location_code": "hk", "company": "Moore Associates Limited", "job_title": "Senior Associate / Associate (IT Audit)", "description": "Responsibilities:\n\n\nInvolve in IT governance reviews and technical assessments to evaluate system security and control effectiveness\nCarry out IT audit engagements, including but not limited to IT general control review, application controls and CAATs\nPlan and deliver IT security compliance, based on international IT security standards including but not limited ISO, NIST, COBIT etc.\nCarry out IT security review and auditing services, and perform on-going consultancy work\nAssist in preparing reports with audit findings and recommendations\nTake up other ad-hoc projects as required\u00a0\n\nRequirements:\n\n\nBachelor degree in Information Technology, Computer Science or related discipline\nExperience in IT audit, IT risk advisory, IT security, or related areas\nGood business acumen with knowledge of technology risk, cyber security, and information security\nProfessional qualification such as CISA, CISM, CISSP, CRISC, CIA, CEH holder is a plus but not a must\nCreative, innovative and well-organised personnel with strong communication and interpersonal skills\nSelf-motivated, independent, diligent and able to work under pressure\nExcellent command of written and spoken English and Chinese\nFresh graduate with IT background is also welcomed\n\nCompetitive package will be offered to the right candidate(s), including 5 day work week, paid examination & study leave, birthday leave & medical insurance coverage. Interested parties please send full resume with working experience, academic and professional qualifications, including present & expected salary by clicking the \"Apply Now\" button.\u00a0 Personal data collected will be used for recruitment purposes only.\n\nSimply click the \u201cApply Now\u201d button\n\nPlease visit our website at\u00a0www.moore.hk\u00a0to know more about us.", "employment_types": ["Full Time", "Permanent"], "selling_points": ["IT audit engagements", "IT security compliance", "Vulnerability assessment"], "locations": ["Tsim Sha Tsui"], "categories": ["Banking / Finance", "Financial Services", "Information Technology (IT)", "IT Auditing", "Security"], "post_time": "2021-12-31T16:58:30Z", "salary": {"currency": null, "max": null, "min": null, "period": "monthly", "term": null}, "salary_visible": false, "title_keywords": ["senior associate", "associate"], "responsibilities": ["control", "review", "compliance", "audit", "evaluate", "system security", "plan", "preparing reports", "ad-hoc projects", "auditing"], "requirements": {"degrees": ["degree", "bachelor", "fresh graduate"], "majors": ["it", "computer science", "information technology"], "languages": ["english", "chinese"], "language_level": ["excellent"], "hard_skills": ["cyber security", "plus", "acumen"], "soft_skills": ["self-motivated", "independent", "well-organised", "diligent", "innovative", "communication and interpersonal skills", "business acumen", "creative", "work under pressure"], "languages_combined": [{"language": "english", "language_level": ["excellent"]}, {"language": "chinese", "language_level": ["excellent"]}]}, "experience_required": {"duration": [], "field": ["related", "it", "security", "audit"]}}, {"job_id": "100003009010566", "location_code": "hk", "company": "Springer Professional Group Limited", "job_title": "Head of IT Audit - Bank, HK$ 1.0-1.6 mil + bonus", "description": "Job Description:\n\nMember of the Auditing Team with the core focus of \u00a0delivery of security risk assessments and audits to our clients, based on international regulatory compliance standards including but not limited to PCI DSS, GDPR, TVRA, and various ISO standards.\nEnsure clients' technical readiness on compliance projects.\nLiaise with our clients along with our Red Team in the HKG office to carry out security consultancy projects for our global clients.\n\nRequirements:\n\nDegree in Computer Science or related discipline.\nMinimum 1 years' experience providing security professional service, preferably on risk assessment, auditing, and / or forensic service.\nHands-on assessment\u00a0experiences\u00a0is a major advantage\nGood analytical and project management skills.\nGood command of English and Cantonese.\nProfessional training will be offered.\u00a0\n\nExpected salary must be listed when submitting an application.\n\nWe actively reward and recognize those employees who are the source of our excellence. At Evolution you will find plenty of opportunities to take your career to the next level.\n\nOnly short-listed candidates will be notified. All information provided by applicants will be used for recruitment purposes and will be destroyed after the completion of the selection process. \u00a0", "employment_types": ["Permanent"], "selling_points": ["Certified in CISA or equivalent", "Experience in leading IT audit team", "Bank/financial sector working experience is a must"], "locations": ["Not Specified"], "categories": ["Accounting", "Audit", "Information Technology (IT)", "IT Auditing", "Security"], "post_time": "2021-12-31T16:57:46Z", "salary": {"currency": null, "max": null, "min": null, "period": "monthly", "term": null}, "salary_visible": false, "title_keywords": [], "responsibilities": ["audits", "liaise with", "compliance", "auditing"], "requirements": {"degrees": ["degree"], "majors": ["computer science"], "languages": ["cantonese", "english"], "language_level": ["good command"], "hard_skills": ["project management"], "soft_skills": ["project management skills", "hands-on"], "languages_combined": [{"language": "cantonese", "language_level": ["good command"]}, {"language": "english", "language_level": ["good command"]}]}, "experience_required": {"duration": ["minimum 1 years"], "field": ["security"]}}, {"job_id": "100003009023514", "location_code": "hk", "company": "PERSOLKELLY Hong Kong Limited", "job_title": "Senior Manager \u2013 IT, Asset Management\u2013 Real Estate Property Investment Trust Company", "description": "Job Description:\n\nLead, build and develop IT auditing team for the bank\nManage the team to perform regular IT audits covering banking applications, IT infrastructure, IT operations and security, and regulatory compliance review.\nEnsure the quality of IT audit, prepare audit reports, present investigation findings and offer recommendations to various business units\nEnforce audit standards; prepare policies, procedures and manuals in accordance with internal and external regulatory requirements\nAct as divisional coordinator to prepare annual risk assessment, formulate annual audit plan, devise annual budget plan\n\n\nJob Requirements:\n\n\nBachelor degree\nProfessional qualifications of CISA, CISSP or equivalent\n10 years experience in IT Auditing or IT risk control area with bank or financial services sector\nGood understanding of control requirements of banking industry and external applicable rules and regulations\nAble to work independently or lead a team to execute audit assignment\nStrong analytical, communication and influencing skills\nExcellent command of Chinese (Cantonese and Mandarin) and English\n\n\nLanguages\nFluent in Cantonese, English and Mandarin\u00a0\n\nInterested parties please\u00a0email your resume to hk@springerpg. com\u00a0for consideration. For job enquiries, please call 2114 2625 for more details.\n\nPlease mention your consultant's name on your application if you have already registered with\u00a0Springer.\n\nAll information provided by candidates will be used solely for recruitment purposes only in accordance with the employer\u2019s personal data policies", "employment_types": ["Full Time", "Permanent"], "selling_points": ["Technology, Property development, Large scale,", "vendor management, project management, stakeholdrs", "processing, asset management, systems, accounting,"], "locations": ["Kwun Tong"], "categories": ["Information Technology (IT)", "IT Auditing", "IT Project Management / Team Lead", "IT Management"], "post_time": "2022-01-05T08:59:16Z", "salary": {"currency": null, "max": null, "min": null, "period": "monthly", "term": null}, "salary_visible": false, "title_keywords": ["senior manager", "asset management"], "responsibilities": ["it infrastructure", "annual audit", "operations", "policies", "compliance", "review", "quality", "audit", "develop", "investigation", "procedures", "regulatory requirements", "budget", "reports", "plan", "banking", "audits", "auditing"], "requirements": {"degrees": ["degree", "bachelor"], "majors": [], "languages": ["cantonese", "english", "chinese", "mandarin"], "language_level": ["excellent", "fluent"], "hard_skills": ["professional qualifications"], "soft_skills": ["communication", "work independently"], "languages_combined": [{"language": "cantonese", "language_level": ["fluent", "excellent"]}, {"language": "english", "language_level": ["fluent", "excellent"]}, {"language": "chinese", "language_level": ["fluent", "excellent"]}, {"language": "mandarin", "language_level": ["fluent", "excellent"]}]}, "experience_required": {"duration": ["10 years"], "field": ["it", "financial services"]}}, {"job_id": "100003009010073", "location_code": "hk", "company": "Michael Page", "job_title": "Assistant Manager, Cyber Security (Governance)", "description": "Responsibilities:\n\nManage ERP Project Implementation with best practice adaption\nResponsible for client requirement studies, analyze client business processes and workflows\nDocument the client requirements\nDesign and configure the system to match client requirement\nCoordinate with development team on customization\nDevelop use case and internal testing\nProvide end-user and system administrator training\nProvide support and maintenance service to corporate clients\nOn the job training will be provided\n\n\n\nRequirements:\n\nDegree holder in IT/ Business related disciplines\nAt least 2-3 years experience in Project Implementation\nSolid experience in ERP and/or Oracle NetSuite is an advantage\nHaving solid knowledge and experience in ERP, Supply Chain, Logistics and Accounting will be advancement\nMature, independent, innovate, self-motivated, and able to work under pressure\nPossess a proactive attitude and is able to be a good team player\nGood analytical, presentation and interpersonal skills\nGood command of verbal and written English and Cantonese.\n\nWe offer 5-day work, attractive remuneration and career opportunities to the right candidate.\u00a0\n\nAll applications received will be used strictly for selection purposes only.", "employment_types": ["Full Time", "Permanent"], "selling_points": ["HK listed company", "Good and structured internal IT & security team", "Competitive salary and bonus"], "locations": ["Not Specified"], "categories": ["Information Technology (IT)", "IT Auditing", "Security", "Network & System"], "post_time": "2021-12-31T03:00:24Z", "salary": {"currency": "HKD", "max": 69999, "min": 45000, "period": "monthly", "term": null}, "salary_visible": true, "title_keywords": ["assistant manager,"], "responsibilities": ["implementation"], "requirements": {"degrees": ["degree holder"], "majors": ["business", "related disciplines", "it"], "languages": ["cantonese", "english"], "language_level": ["good command"], "hard_skills": ["oracle", "maintenance", "erp"], "soft_skills": ["self-motivated", "good team player", "independent", "mature", "interpersonal skills", "proactive", "presentation", "work under pressure"], "languages_combined": [{"language": "cantonese", "language_level": ["good command"]}, {"language": "english", "language_level": ["good command"]}]}, "experience_required": {"duration": ["at least 2-3 years"], "field": ["supply chain", "accounting", "logistics"]}}, {"job_id": "100003009002412", "location_code": "hk", "company": "CK Hutchison Holdings Limited", "job_title": "Auditor (IT)", "description": "Internal Audit, Assistant Director\n\nOur client is a leading local conglomerate, we are now seeking a talented individual to join them as Internal Audit Assistant Director to lead up their internal audit team.\n\nResponsibilities:\n\nResponsible for all audits assignments, audit planning and audit development\nEvaluate the effectiveness of governance, risk management process and controls\nBuild and grow the internal audit team\nResponsible for investigation and improving the current work flow\nPerform other ad hoc duties when required\n\nRequirements\n\nBachelor's degree or above in Finance, Accounting, or relevant disciplines\nA relevant professional qualification (CPA, CIA, CISA)\nGood command of written and spoken English and Putonghua\nKnowledge in IFRS and Internal Controls\nProficient in Excel, Word and PowerPoint\nMinimal business travel is required\n\nThis is an excellent opportunity for individuals seeking an Internal Audit Director role for a reputable company that is able to offer a great package and excellent working environment.", "employment_types": ["Full Time"], "selling_points": [], "locations": ["Tsuen Wan Area"], "categories": ["Information Technology (IT)", "IT Auditing", "Security", "Technical / Functional Consulting"], "post_time": "2021-12-28T05:11:58Z", "salary": {"currency": null, "max": null, "min": null, "period": "monthly", "term": null}, "salary_visible": false, "title_keywords": [], "responsibilities": ["ad hoc duties", "management", "internal audit", "audit", "investigation", "evaluate", "audits", "planning"], "requirements": {"degrees": ["degree or above", "bachelor"], "majors": ["finance", "accounting"], "languages": ["putonghua", "english"], "language_level": ["good command"], "hard_skills": ["excel", "ifrs", "word", "powerpoint", "cpa"], "soft_skills": [], "languages_combined": [{"language": "putonghua", "language_level": ["good command"]}, {"language": "english", "language_level": ["good command"]}]}, "experience_required": {"duration": [], "field": []}}, {"job_id": "100003009003930", "location_code": "hk", "company": "SHINEWING Business Advisory Services Limited", "job_title": "IT Audit Consultant \u2013 Business Advisory Services", "description": "The Job\n\n\u00b7\u00a0\u00a0\u00a0\u00a0\u00a0\u00a0\u00a0\u00a0 Reporting to Deal & Project Governance Head, to support monitoring and review on the proper governance of the Group\u2019s portfolio of projects (1000+) according to corporate policies.\n\n\u00b7\u00a0\u00a0\u00a0\u00a0\u00a0\u00a0\u00a0\u00a0 Define strategies and implement processes to identify and mitigate commercial risks in contracts with our customers and subcontractors.\n\n\u00b7\u00a0\u00a0\u00a0\u00a0\u00a0\u00a0\u00a0\u00a0 Assisting in reviews on RFP/Tender T&C issued by our customers and highlight issues and risks to management team. Track corresponding agreed risk mitigation actions are implemented properly.\n\n\u00b7\u00a0\u00a0\u00a0\u00a0\u00a0\u00a0\u00a0\u00a0 Ensure the related quotations from vendors and sub-contractors are properly framed to protect Interests of both PCCWS and Customers.\n\n\u00b7\u00a0\u00a0\u00a0\u00a0\u00a0\u00a0\u00a0\u00a0 Monitor risky or disputed contracts. Work with project delivery teams to safeguard interests of the company.\n\nThe Person\n\n\u00b7\u00a0\u00a0\u00a0\u00a0\u00a0\u00a0\u00a0\u00a0 Holder of degree in Law, Business, Project Management, or related areas.\n\n\u00b7\u00a0\u00a0\u00a0\u00a0\u00a0\u00a0\u00a0\u00a0 A minimum of 8 years of contract management experience. Experience in servicing environment (e.g. IT Service Provider, System Integrator, Construction Contractors) will be advantageous.\n\n\u00b7\u00a0\u00a0\u00a0\u00a0\u00a0\u00a0\u00a0\u00a0 Strong interpersonal skills for working in multicultural environment, with executive stakeholders, sales teams and project managers of different styles and expertise.\n\n\u00b7\u00a0\u00a0\u00a0\u00a0\u00a0\u00a0\u00a0\u00a0 Good analytical skills with a proactive mindset.\n\n\u00b7\u00a0\u00a0\u00a0\u00a0\u00a0\u00a0\u00a0\u00a0 Self-initiator with improvement-oriented mindset to help establish new/improve current processes and tools.\n\n\u00b7\u00a0\u00a0\u00a0\u00a0\u00a0\u00a0\u00a0\u00a0 Good verbal and written communication skills. Mandatory for Putonghua and English, reading Chinese documents, while Cantonese is nice to have.\n\n\u00b7\u00a0\u00a0\u00a0\u00a0\u00a0\u00a0\u00a0\u00a0 Good understanding on project lifecycle, project financials and related contractual T&C.", "employment_types": ["Full Time", "Permanent"], "selling_points": ["Fresh graduate will be considered", "Willingness to travel occasionally", "IT Audit/ cyber security/ consultancy"], "locations": ["Causeway Bay"], "categories": ["Information Technology (IT)", "IT Auditing", "Product Management / Business Analyst", "Technical / Functional Consulting"], "post_time": "2021-12-28T12:31:44Z", "salary": {"currency": null, "max": null, "min": null, "period": "monthly", "term": null}, "salary_visible": false, "title_keywords": ["consultant"], "responsibilities": ["reporting", "management team", "policies", "contracts", "review", "monitoring", "monitor", "teams", "tender"], "requirements": {"degrees": ["degree"], "majors": ["project management", "business", "law"], "languages": ["cantonese", "putonghua", "english", "chinese"], "language_level": [], "hard_skills": ["project management", "nice", "analytical skills"], "soft_skills": ["communication skills", "analytical skills", "project management", "interpersonal skills", "proactive"], "languages_combined": [{"language": "cantonese", "language_level": []}, {"language": "putonghua", "language_level": []}, {"language": "english", "language_level": []}, {"language": "chinese", "language_level": []}]}, "experience_required": {"duration": ["minimum of 8 years"], "field": ["management"]}}, {"job_id": "100003009001148", "location_code": "hk", "company": "Grant Thornton Hong Kong Limited", "job_title": "Associate/ Senior Associate \u2013 IT Audit & Cybersecurity", "description": "Your role:\n\nLead MIS team to provide in-house systems support to both sales and back-end teams\nDevelop, test, implement and maintain in-house web-based applications\nDevelop technical specifications that align with business requirements\nProvide technical support and training on system applications to end users\nAssist in developing ad-hoc reports\n\nTo succeed in this role:\n\nHigher Diploma or above in Information Technology, Computer Science or related discipline\nMinimum 1 year in IT field, with experience in web applications development\nHands on experience in HTML and Web Services is required\nProficient in Visual Studio (visual basic), PHP, server management, SQL & database and schema design (for table creation) would be an advantage\nKnowledge in VBA in excel and FoxPro is a plus\nStrong analytical and problem solving skills\nGood command of written and spoken English and Chinese", "employment_types": ["Full Time", "Permanent"], "selling_points": ["Degree holder", "1-3 yrs relevant exp in IT audit and cybersecurity", "5-day working week"], "locations": ["Causeway Bay"], "categories": ["Accounting", "Consulting", "Information Technology (IT)", "IT Auditing"], "post_time": "2021-12-28T01:43:13Z", "salary": {"currency": null, "max": null, "min": null, "period": "monthly", "term": null}, "salary_visible": false, "title_keywords": ["senior associate", "associate"], "responsibilities": ["ad-hoc", "management", "technical support", "systems", "teams", "developing", "design", "develop", "maintain", "specifications", "reports", "database", "visual"], "requirements": {"degrees": ["higher diploma or above"], "majors": ["computer science", "information technology"], "languages": ["english", "chinese"], "language_level": ["good command"], "hard_skills": ["vba", "excel", "plus", "web applications", "php", "html", "sql", "web-based applications", "visual basic", "foxpro", "server", "problem solving skills", "web services"], "soft_skills": ["analytical and problem solving skills", "hands on"], "languages_combined": [{"language": "english", "language_level": ["good command"]}, {"language": "chinese", "language_level": ["good command"]}]}, "experience_required": {"duration": ["minimum 1 year"], "field": ["development", "it", "web applications"]}}, {"job_id": "100003009006829", "location_code": "hk", "company": "iTalent Company", "job_title": "Senior IT Security Officer - inhouse / 15 months package", "description": "The Job:\n\nProvide level 2 technical support for ITS business\nCoach and uplift ITS skills and knowledge of engineers\nMonitor and check quality of service delivery on ITS services\nStay well-informed of proactive monitoring of IT services and cloud back up services\nThe Person:\n\nBachelor\u2019s degree in computer engineering, information technology, computer science, or equivalent\nMinimum 5 years of IT related experience\nSolid experience in Server deployment, upgrade and migration in Email, AD Domain, VM etc\nKnowledge in infrastructure, cloud platform, HCI, VDI is an advantage\nCertificate in CCNP/ NCAP/AWS is an advantage\nGood analytical and communication skills\nGood command in written and spoken English and Chinese\nCandidate with less experience will be considered as Specialist\nWe offer 5-day work, attractive remuneration and benefits package to the right candidate.\u00a0 \u00a0 \u00a0\u00a0\nInterested parties please forward your full resume (in Microsoft Word or PDF format) with current and expect salary to the Human Resources and Administration Division, Ricoh Hong Kong Limited, by clicking \"Apply Now\" or by fax 2833 7891.\nInformation provided will be treated in strict confidence and only be used for recruitment related purposes. All personal data of unsuccessful candidates will be destroyed on completion of the recruitment exercise.", "employment_types": ["Full Time", "Permanent"], "selling_points": ["IT Security Policy, Change and Release Managment", "ITIL v4 and CISSP or equivalent", "15-16 months package with good career development"], "locations": ["Not Specified"], "categories": ["Information Technology (IT)", "IT Auditing", "IT Management", "Security"], "post_time": "2021-12-29T10:50:32Z", "salary": {"currency": "HKD", "max": 54999, "min": 25000, "period": "monthly", "term": null}, "salary_visible": true, "title_keywords": ["officer"], "responsibilities": ["service delivery", "technical support", "monitoring", "quality", "monitor"], "requirements": {"degrees": ["certificate", "degree", "bachelor"], "majors": ["computer engineering", "computer science", "information technology"], "languages": ["english", "chinese"], "language_level": ["good command"], "hard_skills": ["server", "ccnp", "deployment", "aws"], "soft_skills": ["communication skills"], "languages_combined": [{"language": "english", "language_level": ["good command"]}, {"language": "chinese", "language_level": ["good command"]}]}, "experience_required": {"duration": ["minimum 5 years"], "field": ["related", "it"]}}, {"job_id": "100003009014832", "location_code": "hk", "company": "Ricoh Hong Kong Limited", "job_title": "Technical Services Manager (Quality Assurance Team)", "description": "CK Hutchison, head office of a diversified group of companies with over 18,000 employees in Hong Kong and an additional 279,300 employees worldwide, invites high calibre and self-motivated individuals to join our organisation.\n\nReporting to the Group Finance Director, the Group Management Services Department is responsible for the internal audit, information security and consultancy functions.\u00a0With the rapid growth in our global operations, we are seeking highly motivated individuals with good business sense to join us as Senior Officer (IT).\n\nResponsibilities:\n\nSuccessful candidates will carry out the following duties for the Group\u2019s operating companies (e.g., telecommunications, retail and container ports) on project basis:\n\nConduct IT audit / technical consultancy assignments (including general IT controls, application reviews and cyber security assessments)\nSupport financial and operational audits (e.g., revenue assurance and data governance) and ad-hoc projects (e.g., fraud investigations) with IT expertise (e.g., data analytics and CAAT programs)\nIdentify control weaknesses, analyse evidential information and suggest practical recommendations for risk mitigation and process improvement\nLiaise with clients to formulate action plans and assist in drafting and presenting audit reports to senior management\nPart-time role in carrying out in-house IT administration tasks (e.g. maintain web-based risk assessment applications and configure Audit Management System)\n\nThis position offers ample opportunities (30 - 40%) for overseas travel, e.g. Europe and South East Asia, and exposure to a variety of cultural environments.\n\n\nRequirements:\n\nDegree holder in Information Systems or related fields with relevant professional qualifications (e.g., CISA, CISSP and CPA)\n1 to 5 years of experience relevant to IT audit / cyber security / consultancy\nGeneral knowledge in IT infrastructure (e.g., firewall, virtual machines and IaaS), database query languages (e.g., MySQL), common web development languages (e.g., JavaScript and PHP) and cyber kill chain\u00a0\nDefinite advantage with hands-on experience on vulnerability scanning tools (e.g., Burp and Qualys) and knowledge on IT-related regulations and standards (e.g., ISO 27001, NIST and GDPR)\nTeam player with strong analytical and problem solving skills\u00a0\nGood command of Cantonese, English and Putonghua\n\nSalary and benefits will commensurate with experience and competence. Please click the \u201cAPPLY NOW\u201d button and include a detailed resume with indication of expected salary.\u00a0 \u00a0\n\nWe are an equal opportunity employer and welcome applications from all qualified candidates. Personal data collected will be treated in\u00a0the strictest confidence and handled confidentially by authorised personnel for recruitment-related purposes\u00a0only within the CK Hutchison Group of companies.\u00a0\u00a0\n\nApplicants not\u00a0having heard\u00a0from us within six weeks of the date of application may consider their application unsuccessful.\u00a0The personal data of\u00a0unsuccessful applicants will be destroyed after the recruitment exercise\u00a0pursuant to the requirements of the Personal Data (Privacy) Ordinance in Hong Kong.", "employment_types": ["Full Time", "Permanent"], "selling_points": ["Oversee IT solutions and service quality", "5-year experience in IT operation/maintenance", "Holder of ITIL & technical certification prefered"], "locations": ["Kowloon Bay"], "categories": ["Information Technology (IT)", "IT Auditing", "Testing / QA"], "post_time": "2022-01-03T04:19:57Z", "salary": {"currency": null, "max": null, "min": null, "period": "monthly", "term": null}, "salary_visible": false, "title_keywords": ["manager"], "responsibilities": ["liaise with clients", "administration", "control", "management", "data", "cyber security", "audit", "senior management", "maintain", "reports", "audits", "plans", "ad-hoc projects", "analyse"], "requirements": {"degrees": ["degree holder"], "majors": [], "languages": ["cantonese", "putonghua", "english"], "language_level": ["good command"], "hard_skills": ["web development", "cyber security", "professional qualifications", "php", "cpa", "javascript", "firewall", "problem solving skills"], "soft_skills": ["analytical and problem solving skills", "hands-on", "team player"], "languages_combined": [{"language": "cantonese", "language_level": ["good command"]}, {"language": "putonghua", "language_level": ["good command"]}, {"language": "english", "language_level": ["good command"]}]}, "experience_required": {"duration": ["1 to 5 years"], "field": ["it", "security", "audit"]}}, {"job_id": "100003009007451", "location_code": "hk", "company": "PCCW Global Limited", "job_title": "IT Manager", "description": "Responsibility:\n\nConduct IT audit including risk assessment and control management over operations\u2019 effectiveness by complying with all applicable directives and regulations\nPerform data mining and analyse unstructured data\nSupport implementation of risk & control projects, e.g. process automation\nDevelop and prepare quality and practical reports, effectiveness and actionable proposals\nDesign and advise for the working procedures and reporting presentation\nTake up ad-hoc projects as required\n\nRequirements:\n\nBachelor holder in IT or Business related disciplines\n2-3 years of experience relevant to IT audit / cyber security / consultancy\nBusiness awareness and able to understand commercial terms in accounting/ finance aspect\nA team player with strong communication and analytical skills\nGood command in written and spoken English and Chinese, and fluency in Putonghua\nCritical thinking ability and sound independent judgment\nWillingness to travel occasionally\nFresh graduate will be considered for junior position\n\nPersonal data collected will be used for recruitment purpose only.\n\nhttp://www.shinewing.hk/", "employment_types": ["Full Time"], "selling_points": ["Establish and maintain the IT Service management policies/procedures", "Experience in IT Services Management", "Global exposure"], "locations": ["Wan Chai"], "categories": ["Information Technology (IT)", "IT Auditing", "IT Management", "Others"], "post_time": "2021-12-30T02:56:29Z", "salary": {"currency": null, "max": null, "min": null, "period": "monthly", "term": null}, "salary_visible": false, "title_keywords": ["it manager"], "responsibilities": ["regulations", "reporting", "control", "management", "data", "operations", "quality", "audit", "implementation", "develop", "design", "procedures", "reports", "data mining", "ad-hoc projects", "analyse"], "requirements": {"degrees": ["bachelor", "fresh graduate"], "majors": ["business", "related disciplines", "it"], "languages": ["putonghua", "english", "chinese"], "language_level": ["fluency", "good command"], "hard_skills": ["analytical skills", "cyber security"], "soft_skills": ["communication", "team player", "independent", "analytical skills"], "languages_combined": [{"language": "putonghua", "language_level": ["fluency", "good command"]}, {"language": "english", "language_level": ["fluency", "good command"]}, {"language": "chinese", "language_level": ["fluency", "good command"]}]}, "experience_required": {"duration": ["2-3 years"], "field": ["it", "security", "audit"]}}, {"job_id": "100003009007421", "location_code": "hk", "company": "Mizuho Bank, Ltd", "job_title": "Cybersecurity Specialist - Systems Planning & Development Section", "description": "The Job:\n\n\nProvide technical expertise in evaluating work quality of IT service engineers\nMake recommendations to continuously improve the work quality and competency of engineers\nManage a team of technical staff in delivery of technical training for engineers\nEvaluation and performance management of IT service partners\nLiaise with regional office on product and solution issues\nThe Person:\n\n\nDegree holder, preferably in IT or related disciplines\nAt least 5 years\u2019 relevant experience in IT service management\nExperience in supporting virtualized Windows server\nStrong analytical, interpersonal and organization skills\nFluent spoken and written in both English and Chinese\nKnowledge in ITIL and agile development is an advantage\nCCNP, VMWare (VCAP, DCV), Nutanix (NCAP) and VDI (DTM) certification is an advantage\nWe offer 5-day work, attractive remuneration and benefits package to the right candidate.\u00a0 \u00a0 \u00a0\u00a0\nInterested parties please forward your full resume (in Microsoft Word or PDF format) with current and expect salary to the Human Resources & Facilities Services, Ricoh Hong Kong Limited, by clicking \"Apply Now\".\nInformation provided will be treated in strict confidence and only be used for recruitment related purposes. All personal data of unsuccessful candidates will be destroyed on completion of the recruitment exercise.", "employment_types": ["Full Time", "Permanent"], "selling_points": ["Enhance system security operation procedures", "Perform system and data access security duties", "Min. 5 years' IT experience in financial industry"], "locations": ["Tsim Sha Tsui"], "categories": ["Information Technology (IT)", "IT Auditing", "Security", "Network & System"], "post_time": "2021-12-30T02:50:09Z", "salary": {"currency": null, "max": null, "min": null, "period": "monthly", "term": null}, "salary_visible": false, "title_keywords": ["specialist"], "responsibilities": ["make recommendations", "management", "it service", "work quality", "evaluation", "liaise with"], "requirements": {"degrees": ["degree holder"], "majors": ["related disciplines", "it"], "languages": ["english", "chinese"], "language_level": ["fluent"], "hard_skills": ["itil", "agile", "vmware", "ccnp", "windows server"], "soft_skills": ["organization skills", "interpersonal", "agile"], "languages_combined": [{"language": "english", "language_level": ["fluent"]}, {"language": "chinese", "language_level": ["fluent"]}]}, "experience_required": {"duration": ["at least 5 years"], "field": ["management", "it", "relevant experience"]}}, {"job_id": "100003009003545", "location_code": "hk", "company": "Fwone Science & Technology Hong Kong Co., Limited", "job_title": "IT helpdesk support(18K-22K)", "description": "This role will be part of the Cyber Security team, the role will have the responsibility of identifying and managing Cyber Security risk for the company with various teams to ensure effective implementation and compliance to the Cyber Security policies, standards and procedures.\n\nClient Details\n\nOur client is a reputable listed company in Hong Kong.\n\nDescription\n\nWork with internal teams to review and drive the development and maintenance of Cyber Security policies, standards and procedures\nWork with internal teams to ensure effective implementation of Cyber Security policies, standards and procedures\nWork with internal teams to ensure audit readiness and to prepare for internal and external audits\nConduct formal risk analysis and maturity assessment for various IT systems\nConduct risk assessment for new projects\nConduct compliance review for various IT systems\nLiaise with Internal and external Auditor to track and remediate Cyber security related audit issues\n\nProfile\n\nA Bachelor's degree with a major in Computer Science is preferred\nA minimum of 2 years of experience in IT cyber security\nGood Knowledge in overall IT structure\nHand-on experience supporting the security and compliance assessments\nProfessional security certification such as CISA, CISM or CRISC\nHolder of other security certification (CISSP, CEH, CSSLP, OSCP, CCSP) will be an advantage\nGood command in English and Chinese (Cantonese & Mandarin)\n\nJob Offer\n\nCompetitive package with bonus\n\nTo apply online please click the 'Apply' button below. For a confidential discussion about this role please contact Connie Mo on +852 2848 9540.", "employment_types": ["Full Time"], "selling_points": ["5 days working", "Experience in supporting Microsoft product", "1 year experience on IT support"], "locations": ["Kwun Tong"], "categories": ["Information Technology (IT)", "IT Auditing", "Support", "Technical / Functional Consulting"], "post_time": "2021-12-28T09:31:06Z", "salary": {"currency": null, "max": null, "min": null, "period": "monthly", "term": null}, "salary_visible": false, "title_keywords": [], "responsibilities": ["maintenance", "cyber security", "policies", "compliance", "teams", "implementation", "procedures", "review", "audit", "internal and external audits", "systems", "risk analysis", "contact", "liaise with"], "requirements": {"degrees": ["degree", "bachelor"], "majors": ["computer science"], "languages": ["cantonese", "english", "chinese", "mandarin"], "language_level": ["good command"], "hard_skills": ["analysis", "maintenance", "cyber security"], "soft_skills": [], "languages_combined": [{"language": "cantonese", "language_level": ["good command"]}, {"language": "english", "language_level": ["good command"]}, {"language": "chinese", "language_level": ["good command"]}, {"language": "mandarin", "language_level": ["good command"]}]}, "experience_required": {"duration": ["minimum of 2 years"], "field": ["compliance", "it", "security"]}}, {"job_id": "100003009000167", "location_code": "hk", "company": "Hong Kong Interbank Clearing Ltd", "job_title": "Manager (Internal Audit)", "description": "Major Responsibilities\n\nAssist in developing corporate audit strategies, policies and procedures\nDevelop internal audit plans, follow up on status of audit issues and coordinate audit reports, etc.\nProvide expertise to maintain and monitor the internal control policies and procedures\nSchedule, plan and execute internal audit projects and/or ad hoc reviews/ investigations on different areas to determine the adequacy and effectiveness of internal control and compliance measures\nEnsure risks are effectively identified and constructive advice is provided for solving or mitigating risks and control issues\nProduce regular reports and presentations to the Management and Board of Directors on audit findings and recommendations\nFollow up on remedial status of issues identified during audit work\nRequirements\n\nUniversity degree in Accounting, Finance, Risk Management or other relevant disciplines\nCPA, CIA, CISA, CISM and/or CISSP qualifications\nOver 5 years of experience in internal or external audit field, preferably with IT audit experience; with 3 years in supervisory positions and audit experience in Big 4 professional accounting firm(s)\nSound knowledge of auditing standards and regulatory requirements\nStrong interpersonal, supervisory and analytical skills\nGood command of written and spoken English and Chinese, proficiency in Putonghua will be an advantage\nHow to Apply\n\n\nInterested parties please send your curriculum vitae stating your current and expected salaries, and the contact phone number to the Human Resources Division, Unit B, 25/F, MG Tower, 133 Hoi Bun Road, Kwun Tong, Kowloon\u00a0\u00a0by clicking the \"Apply Now\" button below.\nAll applications and personal information collected will be treated in strict confidence and only be used for the purpose of recruitment and selection.\u00a0 The information collected will be accessed by our authorized personnel only.\u00a0 Those applicants not contacted by the Human Resources Division within two months from their application date should consider their applications filed for future reference which will be retained for one year for possible future job matching, and will be destroyed after the expiry of one year.", "employment_types": ["Full Time", "Permanent"], "selling_points": [], "locations": ["Ngau Tau Kok"], "categories": ["Banking / Finance", "Financial Services", "Others", "Information Technology (IT)", "IT Auditing"], "post_time": "2021-12-24T10:10:43Z", "salary": {"currency": null, "max": null, "min": null, "period": null, "term": null}, "salary_visible": false, "title_keywords": ["manager"], "responsibilities": ["internal audit", "audit", "maintain", "plan", "plans", "internal control", "control", "ad hoc", "compliance", "monitor", "developing", "presentations", "develop", "reports", "schedule", "management", "procedures", "policies", "coordinate"], "requirements": {"degrees": ["university degree"], "majors": ["finance", "accounting", "risk management"], "languages": ["putonghua", "english", "chinese"], "language_level": ["advantage", "proficiency", "good command"], "hard_skills": ["cpa", "analytical skills"], "soft_skills": ["interpersonal", "analytical skills"], "languages_combined": [{"language": "putonghua", "language_level": ["proficiency", "good command"]}, {"language": "english", "language_level": ["advantage", "proficiency", "good command"]}, {"language": "chinese", "language_level": ["advantage", "proficiency", "good command"]}]}, "experience_required": {"duration": ["5 years", "3 years"], "field": ["supervisory", "big 4", "audit", "it", "audit experience", "accounting"]}}, {"job_id": "100003008996451", "location_code": "hk", "company": "China CITIC Bank International Limited", "job_title": "Manager/ Senior Manager, IT Audit", "description": "Responsibilities\n\n\nDevelop audit plans of designated areas in IT Audit.\nConduct audit planning, risk assessment, IT testing and control evaluation.\nPrepare audit reports, verify corresponding issues, present investigation findings and offer recommendation to business units.\nFollow up the corrective actions with business units.\nMonitor cybersecurity development initiatives and performing continuous risk assessments of coverage areas.\nManage audit work in accordance with professional standards and complete assignments in an effective manner.\nEnforce internal audit standards by updating internal audit policies, procedures and manuals according to latest regulatory requirements.\nProvide audit assistance to external auditors or regulators whenever required.\n\n\n\u00a0Requirements\nDegree holder in Accounting, Computer Science or related disciplines.\n3 - 5 years of IT audit experience, preferably in banking or financial industry.\nCISA, CISM or CISSP holder is highly preferred.\nKnowledge of IT controls and cybersecurity related regulatory requirements.\nKnowledge in various platforms, including Mainframe, AS400, Unix, MS Windows and networking is preferred.\nFamiliar with Visual Basic.\nGood analytical, communication and interpersonal skills.\nGood command of written & spoken English and Chinese (including Putonghua).", "employment_types": ["Full Time"], "selling_points": ["Degree holder in Accounting, Computer Science", "3 - 5 years of IT audit experience", "CISA, CISM or CISSP holder is highly preferred"], "locations": ["Quarry Bay"], "categories": ["Banking / Finance", "Others", "Information Technology (IT)", "IT Auditing", "IT Management"], "post_time": "2021-12-23T07:16:25Z", "salary": {"currency": null, "max": null, "min": null, "period": "monthly", "term": null}, "salary_visible": false, "title_keywords": ["senior manager", "manager"], "responsibilities": ["control", "internal audit", "policies", "regulatory requirements", "monitor", "audit", "investigation", "testing", "develop", "procedures", "external auditors", "reports", "evaluation", "plans", "planning"], "requirements": {"degrees": ["degree holder"], "majors": ["related disciplines", "accounting", "computer science"], "languages": ["putonghua", "english", "chinese"], "language_level": ["good command"], "hard_skills": ["visual basic", "ms windows"], "soft_skills": ["communication and interpersonal skills"], "languages_combined": [{"language": "putonghua", "language_level": ["good command"]}, {"language": "english", "language_level": ["good command"]}, {"language": "chinese", "language_level": ["good command"]}]}, "experience_required": {"duration": ["3 - 5 years"], "field": ["audit experience", "it", "financial industry", "banking"]}}, {"job_id": "100003008998214", "location_code": "hk", "company": "RSM Hong Kong \u7f85\u7533\u7f8e\u6703\u8a08\u5e2b\u4e8b\u52d9\u6240", "job_title": "Consultant (IT Audit / IT Risk), Technology & Management Consulting Services", "description": "The successful candidates will be working with a team of experienced professionals in one of the world\u2019s largest accounting and consulting firms to provide world-class services on IT Audit and/or IT Risk engagements.\n\nThe Technology and Management Consulting Practice (TMC) assists clients in managing operational, financial and technology risk as well as designing and implementing process improvements that can lead to increased value, revenue, or cost containment.\u00a0\u00a0 Along with other Consulting divisions, TMC helps clients across various industries address the increasingly complex strategic, operational, compliance, and governance challenges faced by those responsible for managing or overseeing dynamic businesses.\n\nRSM's TMC offerings include:\u00a0 Information Technology (IT) Audit, Security & Privacy Services, ISO/ISAE/Reporting, IT Governance Risk and Compliance, Digital Transformation Advisory, ERP/CRM Implementation, IT migration services.\n\nResponsibilities:\u00a0\n\n\nAnalyze and evaluate client\u2019s IT risks and controls, provide IT risk reduction recommendations, and assist in implementing solutions.\nConduct benchmarking and gap analysis with IT risk related industry frameworks (i.e. NIST, ISO, COBIT etc.) and provide recommendations.\nConduct audit engagements with numerous engagement team members, include assisting with planning, execution and scheduling staff.\nProvide IT general controls and application controls audit support to external audit.\nDetermine the objectives, scope and extent of each audit and ensure that the audit is professionally and efficiently completed within deadlines.\nPrepare and present IT risk reports in a professional and concise manner.\nPerform security and vulnerability assessment, assist in compliance monitoring review to identify control weaknesses and recommend remedial actions.\nProvide an advisory role to business units and IT groups to assess security requirements and controls; to enforce security control policies as planned.\n\nRequirements:\u00a0\n\nBachelor Degree in Accounting, Information Management, Computer Science, or other related disciplines.\n1-2 years\u2019 working experience within financial audit,\u00a0 IT Audit, IT Security or IT Risk is an advantage.\nFresh graduates will also be considered.\nStrong command of written and oral communication skills (English & Chinese).\nConfident with excellent presentation skills.\nGood interpersonal, communication and problem solving skills.\n\nRSM Hong Kong offers attractive rewards package to the right candidates. Applicants please send resume, quoting the\u00a0Ref. TMC,\u00a0with\u00a0full career details, availability and expected salary\u00a0to\u00a0The\u00a0Human Resources\u00a0Department, RSM Hong Kong, 29/F, Lee Garden Two, 28 Yun Ping Road, Causeway Bay, Hong Kong\u00a0or by clicking the\u00a0Apply Now\u00a0button and upload your CV.\u00a0\n\n(Data collected will be used for recruitment purpose only)", "employment_types": ["Full Time", "Permanent"], "selling_points": [], "locations": ["Causeway Bay"], "categories": ["Accounting", "Audit", "Information Technology (IT)", "IT Auditing", "Security"], "post_time": "2021-12-24T02:53:23Z", "salary": {"currency": null, "max": null, "min": null, "period": "monthly", "term": null}, "salary_visible": false, "title_keywords": ["consultant"], "responsibilities": ["control", "policies", "analysis", "compliance", "monitoring", "audit", "review", "evaluate", "scheduling", "provide recommendations", "reports", "planning"], "requirements": {"degrees": ["degree", "bachelor"], "majors": ["related disciplines", "accounting", "computer science"], "languages": ["english", "chinese"], "language_level": [], "hard_skills": ["problem solving skills"], "soft_skills": ["confident", "communication skills", "oral", "communication", "presentation skills", "problem solving skills", "interpersonal"], "languages_combined": [{"language": "english", "language_level": []}, {"language": "chinese", "language_level": []}]}, "experience_required": {"duration": ["1-2 years"], "field": ["it", "security", "audit", "financial"]}}, {"job_id": "100003008989987", "location_code": "hk", "company": "Conners Consulting Limited", "job_title": "Assistant Vice President - IT Audit", "description": "Responsibilities:\n\nEnsure the quality of audit, prepare audit reports, present investigation findings and offer recommendations to various business units\nManage internal audit assignment according to schedule\nIdentify irregularities/errors in audit review process, ensure the corrective actions are followed through\nEnforce audit standards; prepare policies, procedures and manuals in accordance with internal and regulatory requirements\nProvide audit assistance to external auditors or regulators whenever required\n\nRequirements:\n\nDegree holder in Information System, Computer Science or related disciplines\nMinimum 15 years\u2019 IT audit experience,in the banking/financial sector or professional firms\nProcess relevant professional qualifications such as CISA, CISM,CISSP or equivalent is required\nGood analytical, communication and interpersonal skills.\nGood command of written and spoken English and Chinese including Putonghua\nCandidates with less experience will be considered as AVP - IT Audit\n\nTo apply, please send your detailed resume or contact Ernest WU at 2851 7763 for a confidential discussion.\n\nOnly shortlisted candidates will be notified.\n\nApplicants who are not contacted within two weeks may consider their applications unsuccessful.\n\nAll data collected will be used for recruitment purpose only & will be used strictly confidential.\n\nConners Consulting Limited\n\n2005 Kai Tak Commercial Building 317 Des Voeux Road Central Hong Kong\n\nTel: (852) 3996 8090\u00a0", "employment_types": ["Full Time", "Permanent"], "selling_points": ["Ensure the quality of audit, prepare audit reports", "Identify irregularities/errors in review process", "Bank working experience a MUST"], "locations": ["Not Specified"], "categories": ["Accounting", "Audit", "Information Technology (IT)", "IT Auditing", "Banking / Finance", "Risk Management"], "post_time": "2021-12-21T07:07:03Z", "salary": {"currency": null, "max": null, "min": null, "period": "monthly", "term": null}, "salary_visible": false, "title_keywords": ["assistant vice president"], "responsibilities": ["irregularities", "internal audit", "policies", "regulatory requirements", "review", "quality", "audit", "investigation", "procedures", "reports", "schedule", "external auditors"], "requirements": {"degrees": ["degree holder"], "majors": ["related disciplines", "computer science"], "languages": ["putonghua", "english", "chinese"], "language_level": ["good command"], "hard_skills": ["information system", "professional qualifications"], "soft_skills": ["communication and interpersonal skills", "detailed"], "languages_combined": [{"language": "putonghua", "language_level": ["good command"]}, {"language": "english", "language_level": ["good command"]}, {"language": "chinese", "language_level": ["good command"]}]}, "experience_required": {"duration": ["minimum 15 years"], "field": ["audit", "it", "banking", "audit experience", "financial"]}}, {"job_id": "100003008989644", "location_code": "hk", "company": "Ambition", "job_title": "IT Audit Manager - Commerce - Hong Kong", "description": "IT Audit Manager - Commerce - Hong Kong\n\nA top tier commercial client is looking for IT Audit Managers to join their fast growing team. Candidates with less experience will be considered for Assistant Manager grade.\n\nKey Responsibilities\n\nPromote the vision of Group Internal Audit throughout close partnerships with management and working with the senior executives to develop a risk based audit plan for the Company\nConduct and perform IT/cyber/data security, IT governance, risk and regulatory compliance related audits for the Group\nProvide objective assurance and independent review on the adequacy and effectiveness of the Company's risk management and internal control system to safeguard assets, improve cyber security and guide best practices\nAssist the Head of IT Internal Audit to prepare high quality audit committee paper/reports for the Audit Committee meetings regularly; complete the annual audit plan as agreed by the Audit Committee and in any special reviews\nConduct high quality audits through understanding of business and risks, and proper identification of issues; reports are prepared timely with high standards and issues are clearly communicated and agreed with the senior management and executives with effective recommendations and solutions\nAssist in conducting risk assessments; identifies controls in place to mitigate identified risks and opportunities for improvements\n\nRequirements\n\n8+ years' experience in 2nd/3rd line of defence capacity in MNC environment; open to candidates from Financial Services and Non-FS industries\nStrong technical knowledge of risk and control in various IT domains such as IT infrastructure, Agile software development, as well as other key areas including Digital transformation, Project management, Information security and Data management\nGood understanding of emerging technologies and associated risks (including Cloud, Cybersecurity, DevOps and AI)\nAdvantages: Hands on experience in any of data analytics and business intelligence tools such as Power BI, QlikView, Alteryx, Python and O365 etc; CISM/CISSP/CPA/CIA certification\nExcellent communication and interpersonal skills\n\nPlease submit resume to Stephanie Tung: stephanie.tung@ambition.com.hk\n\n\nIf this job isn't quite right for you, but you know someone who would be great at this role, why not take advantage of our referral scheme? We offer HKD1000 in Apple gift cards for every referred candidate who we place in a role. Terms & Conditions Apply. https://www.ambition.com.hk/refer-a-friend", "employment_types": ["Full Time", "Permanent"], "selling_points": ["IT Audit Manager", "Commercial Clients", "Based in Hong Kong"], "locations": ["Not Specified"], "categories": ["Information Technology (IT)", "IT Auditing", "IT Project Management / Team Lead", "IT Management"], "post_time": "2021-12-21T04:46:33Z", "salary": {"currency": "HKD", "max": 89999, "min": 45000, "period": "monthly", "term": null}, "salary_visible": true, "title_keywords": ["manager"], "responsibilities": ["management", "internal audit", "data", "cyber security", "annual audit", "compliance", "review", "audit", "quality", "develop", "reports", "plan", "audits", "senior management", "internal control"], "requirements": {"degrees": [], "majors": [], "languages": [], "language_level": [], "hard_skills": ["qlikview", "o365", "bi", "data management", "agile", "ai", "data analytics", "devops", "scheme", "project management", "cpa", "alteryx", "python", "business intelligence"], "soft_skills": ["project management", "hands on", "agile", "communication and interpersonal skills"], "languages_combined": []}, "experience_required": {"duration": ["8+ years"], "field": ["business"]}}, {"job_id": "100003008995070", "location_code": "hk", "company": "Venturenix Limited", "job_title": "IT Auditor", "description": "Responsibilities:\n\nWork with IT management to identify improvements to existing controls and operational practices\nReview of business, IT, financial, IT risk and security processes and practices to provide value-added solutions and best-practices\nConsult with IT teams and users on systems control methodologies and techniques\nContribute to or prepare reports of audit findings for business managers proposes recommendations for changes\nDevelop and execute annual audit plans focused on the most significant risks in the audit universe\nTest and evaluate controls to verify efficiency and effectiveness of operation, reliability of information and compliance with applicable laws and regulations\n\n\u00a0Requirements:\n\nBachelor degree in Computer Science, Engineering, Information System and related fields\n1 to 5 years of experience in IT audit and/or cyber security\nGeneral knowledge of IT infrastructure, system security, networking, database, applications and electronic messaging\nStrong analytical, interpersonal and communication skills\nExcellent command of spoken and written English and Chinese\nTo apply for this position, please send your full r\u00e9sum\u00e9 to jalice.lo@ venturenix.com or call Jalice Lo at 2670 9018 to have a confidential discussion.", "employment_types": ["Permanent"], "selling_points": ["Multinational conglomerate", "Attractive Remuneration Package", "Stable Working Environment"], "locations": ["Not Specified"], "categories": ["Information Technology (IT)", "IT Auditing", "IT Management", "Technical / Functional Consulting"], "post_time": "2021-12-23T02:54:19Z", "salary": {"currency": null, "max": null, "min": null, "period": "monthly", "term": null}, "salary_visible": false, "title_keywords": [], "responsibilities": ["regulations", "control", "annual audit", "review", "teams", "systems", "audit", "develop", "evaluate", "compliance", "it management", "prepare reports", "plans"], "requirements": {"degrees": ["degree", "bachelor"], "majors": ["engineering", "computer science"], "languages": ["english", "chinese"], "language_level": ["excellent"], "hard_skills": ["information system", "cyber security"], "soft_skills": ["communication skills", "interpersonal"], "languages_combined": [{"language": "english", "language_level": ["excellent"]}, {"language": "chinese", "language_level": ["excellent"]}]}, "experience_required": {"duration": ["1 to 5 years"], "field": ["it", "security", "audit"]}}, {"job_id": "100003008990033", "location_code": "hk", "company": "Grey Anderson Limited", "job_title": "IT SECURITY MANAGER (CYBER RISK & COMPLIANCE)", "description": "Responsibilities:\n\nSupport and drive security management\u2019s directives in priority\nEnhance current practices to mitigate cyber risks and the establishment of a risk framework\nAlign risk appetite and fine-tune processes necessary within the business\nSupport and conduct security compliance and governance exercise and awareness refresh program\nFollow and execute risk management practices with Risk Registers, Issue Management, Risk & Controls Library, Impact Thresholds, Risk Reporting, Controls Testing, and Security Governance\nAssess risks based on policy, standards, technology compliance requirements and best practices IT and business projects and activities\nEnsure security measures properly adopted for risk mitigation\nRisk exception and acceptance must be well governed, timely validated and properly escalated\nPrepare reporting to senior management on the current security posture\nContribute to third-party risk management and well engage with and manage audit activities\n\nRequirements:\n\nUniversity degree or above in IT, Management Information System, cybersecurity and/or risk compliance\nAt least 5 years of experience in IT technical roles and audit, 3 years of hand-on in technology risk assessment and security compliance aspects\nKnowledge of ISMS, ISO27000, ISO31000 and other major information security frameworks/Practices e.g. NIST, COBIT etc.\nStrong knowledge of Audit control framework, IT general controls, Cybersecurity Risk, Tech Risk (including infrastructure, cloud and applications security)\nIT background with operations, enterprise networking, operating systems and database security risk controls\n\u00a0Sound skill across: DevSecOps, cloud security, PII, GDPR, and Cyber security laws in China\nHigh problem solving, risk management and analytical skills\nStrong interpersonal, management, negotiation and presentation skill\nCISA, CISSP, CRISC or equivalent is preferable\nExperience in adopting risk-based assessment methodologies and engaging audit counter-parts\nExperience in performing risk assessment and evaluation\nExperience in reporting risk tailored to IT and business stakeholders about most significant risks to the business\nCompetency consulting background in IT, Cyber Security and/or IT Audit and Control Compliance\nCompetency interacting with seasoned colleagues on Technology and Cybersecurity Risk, Audit and compliance agenda\nExperience in building and promoting risk awareness amongst IT and business staff by providing support and training within the company\nEffectively manage multiple priorities, work independently and in a team-oriented and collaborative environment\nAn aptitude for technical writing e.g. assessment reports, presentations, management dashboard and risk indicators/metrics", "employment_types": ["Full Time"], "selling_points": ["Experience in performing risk assessment", "Strong knowledge of IT control framework", "A team-oriented and collaborative environment"], "locations": ["Others"], "categories": ["Information Technology (IT)", "IT Auditing", "IT Project Management / Team Lead", "Security"], "post_time": "2021-12-21T07:23:56Z", "salary": {"currency": null, "max": null, "min": null, "period": "monthly", "term": null}, "salary_visible": false, "title_keywords": ["manager"], "responsibilities": ["reporting", "management", "business projects", "compliance", "audit", "testing", "assess risks", "senior management"], "requirements": {"degrees": ["degree or above"], "majors": ["it"], "languages": [], "language_level": [], "hard_skills": ["presentation skill", "cyber security", "information system", "presentations", "analytical skills", "problem solving"], "soft_skills": ["presentation skill", "work independently", "negotiation", "collaborative", "analytical skills", "problem solving", "interpersonal"], "languages_combined": []}, "experience_required": {"duration": ["3 years", "at least 5 years"], "field": ["training", "compliance", "audit", "business", "it", "security"]}}, {"job_id": "100003008986159", "location_code": "hk", "company": "Dah Chong Hong Holdings Limited", "job_title": "Senior Security Analyst/Engineer \u2013 Cyber and Information Security (GIT-CIS)", "description": "The incumbent will report to team manager and be responsible on one of the below workstreams to lead the cyber security development in the corporate.\n\na)\u00a0\u00a0\u00a0\u00a0\u00a0 Security Architecture\n\nb)\u00a0\u00a0\u00a0\u00a0\u00a0 Security Infrastructure\n\nc)\u00a0\u00a0\u00a0\u00a0\u00a0 Governance, Risk Management and Compliance (GRC)\n\nJob duties:\n\nDevelop, maintain and enforce Information Security Policy in accordance with industry standard, best practice and relevant regulatory requirements\nLead project team to build tools, perform system integration and support security systems\nAssist security governance in the corporate\nReview and maintain the technology stack to meet the industrial security standards\n\nRequirements:\n\nBachelor\u2019s degree in IT or related disciplines\n5 years of relevant working experience\nHands-on experience in developing and enforcing security policies, standards and guidelines for corporate\nFamiliar with security technology in the market and with solid technical experience in implementing the related security solutions is preferred\nHolder of professional certificates in CISSP, CISA, ISO Lead Auditor\u00a0or equivalent will be advantageous\nGood interpersonal, presentation and communication skills\nBe self-motivated, initiative with good problem solving and analytical skills\nGood command of English and Chinese (Putonghua and Cantonese) in both speaking and writing\nCandidate with less experience will be considered as lower ranked position\n\nWe offer competitive salary, discretionary bonus, medical insurance, life and personal accident insurance, annual leave and staff purchase discount. Interested candidates please send your resume with salary expectation by email or clicking \"Apply Now\".\n\nWe are equal opportunities employer. Applicants who are not invited within 2 months may consider their application unsuccessful. All applicants may be considered for other suitable positions with DCH Group / CITIC Pacific Group and will be deleted from our files after 6 months from the date of application.", "employment_types": ["Full Time", "Permanent"], "selling_points": [], "locations": ["Kowloon Bay"], "categories": ["Information Technology (IT)", "IT Auditing", "Security", "Others"], "post_time": "2021-12-20T02:12:41Z", "salary": {"currency": null, "max": null, "min": null, "period": "monthly", "term": null}, "salary_visible": false, "title_keywords": ["analyst", "engineer"], "responsibilities": ["information security", "regulatory requirements", "systems", "review", "develop", "maintain"], "requirements": {"degrees": ["degree", "bachelor"], "majors": ["related disciplines", "it"], "languages": ["cantonese", "putonghua", "english", "chinese"], "language_level": ["good command"], "hard_skills": ["problem solving", "analytical skills"], "soft_skills": ["initiative", "communication skills", "self-motivated", "problem solving and analytical skills", "hands-on", "interpersonal", "presentation"], "languages_combined": [{"language": "cantonese", "language_level": ["good command"]}, {"language": "putonghua", "language_level": ["good command"]}, {"language": "english", "language_level": ["good command"]}, {"language": "chinese", "language_level": ["good command"]}]}, "experience_required": {"duration": ["5 years"], "field": ["related", "security", "relevant working experience", "developing"]}}, {"job_id": "100003008986442", "location_code": "hk", "company": "Vantis Solutions Limited", "job_title": "Solutions Consultant", "description": "Responsibilities:\n\nManage ERP Project Implementation with best practice adaption\nResponsible for client requirement studies, analyze client business processes and workflows\nDocument the client requirements\nDesign and configure the system to match client requirement\nCoordinate with development team on customization\nProvide end-user and system administrator training\nProvide support and maintenance service to corporate clients\nOn the job training will be provided\n\nhandling the IT consulting job in Business Intelligence, Machine Learning , Big data analysis and Enterprise performance management\u00a0\n\nRequirements:\n\nDegree holder in IT/ Business related disciplines\nHaving solid knowledge and experience in financial consolidation, budget and planning, sales forecasting will be advancement\nKnowledge with programming language\u00a0(Python, R,\u00a0MATLAB),\u00a0Frontend Technologies\u00a0(HTML, CSS, JavaScript) and backend Technologies\u00a0(PHP, SQL)\nMature, independent, innovate, self-motivated, and able to work under pressure\nPossess a proactive attitude and is able to be a good team player\nGood analytical, presentation and interpersonal skills\nGood command of verbal and written English and Cantonese.\n\nWe offer 5-day work, attractive remuneration and career opportunities to the right candidate.\u00a0\n\nAll applications received will be used strictly for selection purposes only.", "employment_types": ["Full Time", "Permanent"], "selling_points": ["Manage ERP Project Implementation", "5 working day", "Degree holder in IT/ Business related disciplines"], "locations": ["Lai Chi Kok"], "categories": ["Information Technology (IT)", "IT Auditing", "Support", "IT Management"], "post_time": "2021-12-20T03:04:33Z", "salary": {"currency": null, "max": null, "min": null, "period": "monthly", "term": null}, "salary_visible": false, "title_keywords": ["consultant"], "responsibilities": ["implementation"], "requirements": {"degrees": ["degree holder"], "majors": ["business", "related disciplines", "it"], "languages": ["cantonese", "english"], "language_level": ["good command"], "hard_skills": ["maintenance", "php", "css", "analysis", "html", "sql", "javascript", "programming", "matlab", "python", "r", "business intelligence"], "soft_skills": ["self-motivated", "good team player", "independent", "mature", "learning", "interpersonal skills", "proactive", "presentation", "work under pressure"], "languages_combined": [{"language": "cantonese", "language_level": ["good command"]}, {"language": "english", "language_level": ["good command"]}]}, "experience_required": {"duration": [], "field": ["planning", "consolidation", "financial"]}}]