[{"job_id": "100003009052512", "location_code": "hk", "company": "China Mobile Hong Kong \u4e2d\u570b\u79fb\u52d5\u9999\u6e2f", "job_title": "Assistant IT System Manager", "description": "CHINA MOBILE HONG KONG COMPANY LIMITED (\"CMHK\") is the wholly-owned subsidiary of China Mobile Limited (HKEx: 941) (NYSE: CHL), which ranks 47th on the Fortune Global 500.\n\nOur company strives to offer superior service experience and to become the preferable digital partner for customers. We are preserving an environment with trust, responsibility and caring. At CMHK, we commit to maximizing people\u2019s potential and paving the way toward success for every striver. We are now inviting high caliber professional to join us.\n\n\u00a0In this position, you will :\n\nLead a team of system and operation members who provide day to day IT system support and enhancement\nDrive adoption of automation and intelligent technology to improve IT operational capability\nEstablish and maintain policy, and operationalize the process for system infrastructure and operation management\nResponsible for securing, optimizing, upgrading, migrating internal IT systems\nResponsible for divisional cloud resources lifecycle management and private cloud migration\nManage, coordinate, monitor, and report on system & process SLA, KPI and change activities\nParticipate in business application migration and transition projects\nAct as a focal point of system change communication and escalation to stakeholders and conduct impact analysis to minimize risk and ensure efficient execution of change activities.\nManage third party vendor to foster communication and continuous services improvement\nAssist Department Manager in strategy & project planning, deployment, budget tracking and team operation and transformation\n\nTo be successful in this position, you should meet the following requirements:\n\nDegree or above in Information Technology or Computer Science;\n7 years experience or above with IT Infrastructure and Operation Management;\nITIL v4, DevOps, IT Infrastructure related certification are preferred;\nProficiency with Linux, Cloud platform (IaaS, PaaS), Docker, VMware, data backup & storage system, \u00a0Middleware, Database, System Monitoring\nProven track record in \u00a0CMDB, Availability and Capacity Management;\nKnowledge of AIOps is an advantage;\nExcellent analytical, problem-solving, and organizational skill;\nExcellent communication skills to facilitate cross team collaboration;\nProactive people management skill to drive for positive team morale;\nSelf-initiative and high sense of responsibility and urgency;\nAbility to always be courteous even when dealing with stressful situation;\nProven multi-tasking skills with ability to work independently;\nStrong innovation mindset, constantly drive new ideas and challenge the status quo with creative approach;\nGood command of Cantonese, Mandarin and English\n\n\n\nWhen you work:\n\n5 days work\n8 hours/day\n\nWhat you enjoy:\n\nDouble pay\nDiscretionary performance bonus\nLife insurance\nMedical insurance\nBirthday gift\nMarriage leave\nBirthday leave\nCompassionate leave\u00a0\nStaff discount\n\nCMHK is committed to be an equal opportunity employer. We offer exceptional benefits package and the opportunity to work in a challenging environment. Personal data provided by applicants will be treated strictly in accordance with our personal data policy and for recruitment purposes only.\n\nPlease submit your application to us by clicking\u00a0the APPLY NOW\u00a0button and send your full resume with your availability, current and expected salary to us", "employment_types": ["Full Time", "Permanent"], "selling_points": ["Degree in Information Technology/Computer Science", "7+ years experience with IT Infrastructure", "Competitive pay, Good fringe benefits"], "locations": ["Kwai Hing"], "categories": ["Information Technology (IT)", "Support", "IT Management", "Network & System"], "post_time": "2022-01-17T03:17:34Z", "salary": {"currency": null, "max": null, "min": null, "period": null, "term": null}, "salary_visible": false, "title_keywords": ["system manager", "assistant"], "responsibilities": ["ideas", "data", "budget", "communication", "maintain", "database", "it infrastructure", "infrastructure", "monitor", "migration", "report", "management", "monitoring", "third party", "tracking", "project planning", "analysis", "systems", "coordinate", "lead a team", "insurance"], "requirements": {"degrees": ["degree or above"], "majors": ["computer science", "information technology"], "languages": ["cantonese", "english", "mandarin"], "language_level": ["good command"], "hard_skills": ["itil", "linux", "focal", "vmware", "analysis", "devops", "problem-solving", "vendor", "sla", "mobile", "deployment"], "soft_skills": ["efficient", "communication skills", "courteous", "work independently", "organizational skill", "creative", "responsible", "urgency", "problem-solving", "high sense of responsibility", "communication", "committed", "self-initiative", "multi-tasking skills", "proactive", "positive", "superior"], "languages_combined": [{"language": "cantonese", "language_level": ["good command"]}, {"language": "english", "language_level": ["good command"]}, {"language": "mandarin", "language_level": ["good command"]}]}, "experience_required": {"duration": ["7 years"], "field": ["digital", "operation management", "it", "infrastructure"]}}, {"job_id": "100003009055374", "location_code": "hk", "company": "Hong Kong Aircraft Engineering Co Ltd", "job_title": "Group IT Manager, Infrastructure & Architecture", "description": "Scope of Duties:\u00a0\n\nLead the development and regular review of the Group IT Policies.\nLead the development and implementation of the Group IT Infrastructure Strategy\nFormulate the IT Infrastructure and integration platform according to the business needs, taking into account scalability and security requirements of the Digital Solutions portfolio.\nEnsure systems availability and performance meets the agreed service levels.\nManage IT budgets\nStrategic Direction and Standards for IT \u2013 Contribute to the development of Group IT Infrastructure strategy. Lead the Group IT Policies development and align the architectural standards to achieve business benefits and cost effectiveness.\nIT Infrastructure Ownership \u2013 Maintain currency on new technologies and platforms. Provides direction on what emerging infrastructure & technologies should be introduced to the group.\nSolution Formulation and Delivery \u2013 Oversee the end-to-end IT Infrastructure solution delivery and subsequent solution support. Ensure solutions are fit for purpose leveraging existing capabilities where possible.\nIT Services Management - Ensure effective management of IT infrastructure facilities and IT supporting services in accordance with agreed service levels and schedules.\nTeam Leadership and Management \u2013 Build and manage a team with a core set of skills for installed and future technologies. Develop, motivate, coach staff to achieve performance excellence.\u00a0\nFinancial Management \u2013 Provide good quality information and analysis for the IT budgeting and planning process; control actual IT Costs to meet operating budgets.\n\nRequirements:\u00a0\n\nA minimum of 12 years of IT Infrastructure and systems integration experience with 6 years of management experience\nTertiary qualifications\nProven experience in managing a team of technology professionals (including in-house, external, off-shore resources) to run strategic IT projects and support IT systems\nAbility to listen and articulate ideas to a broad range of audiences\nStrong interpersonal skills; promoting healthy relationships and team dynamics\nWell-developed analytical, problem-solving, and decision-making skills\nFocus on customer\u2019s needs; ability to set expectations and understand end user behavior\nProven technical management experience of working in a complex IT Infrastructure environment\nDemonstrated leadership and relationship management experience and skills\nDemonstrated ability to lead and motivate staff and to apply skills and techniques to solve dynamic problems\nStrong teamwork and interpersonal skills at all management level\n\nHow to Apply:\n\nPlease send your resume with expected salary, quoting the employer's reference no., to: Human Resources Department - Talent & Partnership Team, Hong Kong Aircraft Engineering Company Limited, 80 South Perimeter Road, Hong Kong International Airport, Lantau, Hong Kong OR submit your application via\u00a0https://careers.haeco.com/hkg/job-openings/\n\nCandidates not contacted 4-6 weeks after submission of applications and/or interviews may consider their application unsuccessful.\n\nAll information provided by candidates will be treated in strict confidence and will be used for employment purpose only.", "employment_types": ["Full Time", "Permanent"], "selling_points": ["A minimum of 12 years of IT Infrastructure", "6 years of management experience", "Ability to listen and articulate ideas"], "locations": ["Airport Area"], "categories": ["Information Technology (IT)", "IT Management", "Network & System", "Others"], "post_time": "2022-01-18T02:24:29Z", "salary": {"currency": null, "max": null, "min": null, "period": "monthly", "term": null}, "salary_visible": false, "title_keywords": ["it manager"], "responsibilities": ["budgets", "it infrastructure", "systems", "implementation", "it policies", "regular review"], "requirements": {"degrees": [], "majors": [], "languages": [], "language_level": [], "hard_skills": [], "soft_skills": [], "languages_combined": []}, "experience_required": {"duration": [], "field": []}}, {"job_id": "100003009055615", "location_code": "hk", "company": "Michael Page", "job_title": "IT Manager", "description": "One man band role to manage and oversee the efficient operation of all Information Technology related functions and processes. In charge of strategic planning, development and management of the IT systems.\n\nClient Details\n\nOur client is a reputable international professional organisation.\n\nDescription\n\nResponsibilties:\n\nManage self imposed action plans for daily operations, whilst still retaining a flexible approach to assisting individuals as and when needed, bearing in mind the IT Manager is the single IT person for the office.\nDefine and discuss priorities, including service level expectations, with Regional IT Manager and with Global IT team where relevant.\nEnsure that all meeting room IT facilities are properly maintained and managed, and assist users where necessary in their operation\nDevelop and monitor budgets for area of responsibility.\nDevelop business case justifications and cost/benefit analyses for proposed areas of spending and initiatives. Includes researching potential technology solutions and implementations in support of new initiatives, opportunities, and procurement efforts.\nKey Operational areas:\n- Customer Support\n- Networking and Communications\n- Messaging\n- Telephony\n- Enterprise Applications\n- Software Deployment and Packaging\n- Development\n- Training\n\nProfile\n\nOne man band experience in sizeable company experience\nMinimum Bachelor's Degree in Computer science or related\nGood understanding of policy/procedure development, standards and frameworks eg ISO 27001 processes and procedures\nExperience Managing desktop and supporting enterprise software application environments and databases\nHands-on experience with computer networks, network administration and network installation\nStrong communication, interpersonal, problem solving and supervisory skills\nGood written and verbal English communication is a must.\n\nJob Offer\n\nCompetitive package\n\nTo apply online please click the 'Apply' button below. For a confidential discussion about this role please contact Connie Mo on +852 2848 9540.", "employment_types": ["Full Time", "Permanent"], "selling_points": ["One man band role", "Global Professional firm", "HK$ 40 - 55k/ month"], "locations": ["Not Specified"], "categories": ["Information Technology (IT)", "Support", "IT Management", "Network & System"], "post_time": "2022-01-18T02:47:51Z", "salary": {"currency": "HKD", "max": 54999, "min": 35000, "period": "monthly", "term": null}, "salary_visible": true, "title_keywords": ["it manager"], "responsibilities": ["network administration", "budgets", "management", "cost", "installation", "strategic planning", "software", "systems", "monitor", "procedures", "develop", "communication", "daily operations", "contact", "databases", "plans"], "requirements": {"degrees": ["degree", "bachelor"], "majors": ["computer science"], "languages": ["english"], "language_level": ["good"], "hard_skills": ["network administration", "problem solving", "deployment", "databases"], "soft_skills": ["efficient", "flexible", "communication", "problem solving", "hands-on", "organisation", "interpersonal"], "languages_combined": [{"language": "english", "language_level": ["good"]}]}, "experience_required": {"duration": [], "field": ["network administration", "installation"]}}, {"job_id": "100003009052321", "location_code": "hk", "company": "Hong Kong Aircraft Engineering Co Ltd", "job_title": "Assistant IT Manager, Infrastructure", "description": "Scope of Duties:\u00a0\n\nEnsure IT Infrastructure and systems availability and responsiveness in accordance with agreed service levels and schedules\nEnsure appropriate and dedicated focus on high severity incident management\nFacilitate the development and implementation of effective and robust disaster recovery plans for HAECO\nFacilitate the development and implementation of business continuity plans for IT\nEnsure effective management of IT Infrastructure Facilities and Data Centres\nEnsure effective management of Cloud based IT services\nProactively drive service delivery improvements\nFormulate cost effective solutions to resolve business issues in accordance with IT policy and strategy\nOversee the end-to-end solution delivery to ensure on time and within budget\nEnsure post-implementation maintenance & support is effective and efficient\nManage vendors in IT project delivery, systems development and support\nBuild and lead a team with the core set of technical skills and business domain knowledge\nDevelop and coach potential staff for performance excellence\n\nRequirements:\u00a0\n\nDegree holder in IT, Computing, Engineering or related disciplines\nOver 8 years IT experience, at least 5 years of IT Infrastructure experience, preferably with team leadership experience\nProfessional certifications (Microsoft \u2013 MCSE (Server specific), VMware \u2013 VCP, ITIL Foundation, PMP or equivalent) will be an advantage.\nProven experience in managing a team of technology professionals (including in-house, external, off-site resources) to run strategic IT projects and support IT systems\nPossess professional competency in at least one technical specialization, with a broad understanding of other current and emerging technologies\nHave experience of leading a team, and be able to demonstrate an effective coaching and mentoring style\nHave experience of developing solutions and making decisions for a team with only minimal management guidance and supervision\nAble to upkeep high standard of outputs from the team\nAble to listen and articulate ideas verbally, and in the written\n\nHow to Apply:\n\nPlease send your resume with expected salary, quoting the employer's reference no., to: Human Resources Department - Talent & Partnership Team, Hong Kong Aircraft Engineering Company Limited, 80 South Perimeter Road, Hong Kong International Airport, Lantau, Hong Kong OR submit your application via\u00a0https://careers.haeco.com/hkg/job-openings/\n\nCandidates not contacted 4-6 weeks after submission of applications and/or interviews may consider their application unsuccessful.", "employment_types": ["Full Time", "Permanent"], "selling_points": ["IT infrastructure development and support", "Degree holder in IT, Computing, Engineering", "8 years IT experience,5 years of IT Infrastructure"], "locations": ["Airport Area"], "categories": ["Information Technology (IT)", "IT Project Management / Team Lead", "IT Management", "Others"], "post_time": "2022-01-17T02:45:26Z", "salary": {"currency": null, "max": null, "min": null, "period": "monthly", "term": null}, "salary_visible": false, "title_keywords": ["it manager", "assistant"], "responsibilities": ["service delivery", "business continuity", "management", "cost", "it infrastructure", "maintenance", "data", "schedules", "systems", "budget", "implementation", "develop", "lead a team", "plans"], "requirements": {"degrees": ["degree holder"], "majors": ["related disciplines", "it", "engineering"], "languages": [], "language_level": [], "hard_skills": ["itil", "mcse", "no", "vmware", "aircraft", "server", "pmp"], "soft_skills": ["articulate", "leadership"], "languages_combined": []}, "experience_required": {"duration": ["at least 5 years", "8 years"], "field": ["management", "infrastructure", "developing", "it experience", "it", "managing a team", "team"]}}, {"job_id": "100003009054062", "location_code": "hk", "company": "EC Healthcare", "job_title": "Manager / Assistant Manager, Business Integration", "description": "Working closely with integration partners as well as internal cross function teams, this position is responsible for the smooth transition of post M&A business integration to achieve the set vision and synergy.\n\n\u00a0Job Responsibilities:\n\nLead discussion and drive execution on vision and strategy of the acquisition\nDevelop deep understanding of responsible pillar / discipline to drive value creation and synergy with group business\nAct as single point of contact for M&A partner\nDevelop and foster close working relationship with M&A partner and internal departments\nProject manage and coordinate with internal departments on integration tasks to ensure smooth integration of the M&A business\nLead business readiness planning and activities including communications, training etc. with relevant departments\nSetup governance structure and lead regular update on integration progress and escalate issues if required\nLead risks and issues management during and post M&A integration\nLead regular review of post M&A performance\n\nJob Requirements:\n\nDegree holder in Business, Communications or related discipline\nAt least 5 years of experience in business programme or project management\nExcellent communications, interpersonal, planning and organizing skills\nExperience in change management will be highly valued\nExperience in healthcare industry a definite advantage\nWilling to understand detail and possess a problem-solving mindset\nAbility to look at big picture and think strategically\nGood command of both spoken & written English and Chinese", "employment_types": ["Full Time"], "selling_points": ["Working closely with integration partners", "Smooth transition of post M&A business integration", "Discussion & drive execution on vision & strategy"], "locations": ["Mong Kok"], "categories": ["Information Technology (IT)", "IT Project Management / Team Lead", "IT Management", "Product Management / Business Analyst"], "post_time": "2022-01-17T08:15:57Z", "salary": {"currency": null, "max": null, "min": null, "period": "monthly", "term": null}, "salary_visible": false, "title_keywords": ["manager", "assistant manager,"], "responsibilities": ["management", "coordinate with", "develop", "regular review", "contact", "setup", "planning"], "requirements": {"degrees": ["degree holder"], "majors": ["business", "communications"], "languages": ["english", "chinese"], "language_level": ["good command"], "hard_skills": ["project management", "problem-solving"], "soft_skills": ["project management", "problem-solving", "interpersonal", "think strategically"], "languages_combined": [{"language": "english", "language_level": ["good command"]}, {"language": "chinese", "language_level": ["good command"]}]}, "experience_required": {"duration": ["at least 5 years"], "field": ["project management", "management", "business", "healthcare industry"]}}, {"job_id": "100003009052348", "location_code": "hk", "company": "Megaman Asia Ltd", "job_title": "IT Manager", "description": "Responsibilities:\n\nSupport local users of Office, warehouse, shop and users from other region\u00a0s\nMaintain systems and data in a desirable and operational status\nManage IT asset, budget and expenses\nAdministrate Microsoft servers, AD, MSSQL, ASP Web, Microsoft Windows, Office 365, VMware, Veeam, Firewall, VPN, antivirus and some other applications\nSupport system implementation of SAP\nRequirements:\n\n\nHigher diploma or above in IT, Computer Science or related disciplines\nWork independently or with supporting vendors\n5 \u2013 8 years\u00a0of working experience in network/server administration\nKnowledgeable in HR, ERP, WMS & POS\nFlexible to adopt new technologies and knowledge\nSelf-motivated, organized, flexible with a can-do attitude\nGood communication, analytical, project management & problem solving skills;\nDetail-minded, committed to work and able to prioritize effectively\nConversant with spoken and written English, Cantonese and Mandarin\nApplicants with less experiences will be considered as Assistant IT Manager\nApplications without expected salary and insufficient information will not be processed\nAll applications applied through our system will be delivered directly to the advertiser and privacy of personal data of the applicant will be ensured with security.\n\n\u6709\u610f\u7533\u8acb\u8005\u8acb \u6309 APPLY NOW\u7533\u8acb", "employment_types": ["Full Time"], "selling_points": [], "locations": ["Kwun Tong"], "categories": ["Information Technology (IT)", "IT Project Management / Team Lead", "IT Management", "Network & System"], "post_time": "2022-01-17T02:49:20Z", "salary": {"currency": null, "max": null, "min": null, "period": "monthly", "term": null}, "salary_visible": false, "title_keywords": ["it manager"], "responsibilities": ["data", "expenses", "budget", "systems", "implementation", "maintain"], "requirements": {"degrees": ["higher diploma or above"], "majors": ["related disciplines", "it", "computer science"], "languages": ["cantonese", "english", "mandarin"], "language_level": [], "hard_skills": ["pos", "server administration", "erp", "project management", "problem solving skills"], "soft_skills": ["flexible", "organized", "work independently", "self-motivated", "detail-minded", "able to prioritize", "can-do attitude", "communication", "project management", "committed", "problem solving skills"], "languages_combined": [{"language": "cantonese", "language_level": []}, {"language": "english", "language_level": []}, {"language": "mandarin", "language_level": []}]}, "experience_required": {"duration": ["8 years"], "field": ["it", "server administration"]}}, {"job_id": "100003009053111", "location_code": "hk", "company": "IT Consulting Solutions Limited", "job_title": "Assistant Manager, IT Service Operation", "description": "Responsibilities\n\n\n\u00a0 \u00a0 \u00a0 \u00a0 \u00a0\u00a0IT Service Management\n\nAct as Escalation point for incidents resolution. Ensuring Business / Customer updates are timely and of sufficient quality, arranging discussions and updates as required.\nAct as Escalation point for Service request resolution. Ensuring Business / Customer updates are timely and of sufficient quality, arranging discussions and updates as required.\nEnsure that all modes of communication are effectively used throughout the Major incident life cycle.\nBuild and Develop relationships from both a customer and technical point of view, driving global interaction with stakeholders and partners\nHelp business understand how to adjust to anticipated technology or product changes\nEffective Monitor, control and support service delivery ensure system methodologies and procedures are followed.\nReview and analyze all planned changes, to mitigate any potential impact to business services.\nReview change impact and \"push back/ reject\" when risk levels exceed\nKnowledge in Data is an advantage.\nKnowledge in cloud is a mandatory.\nProvide support and input for CSIP Continuous Improvement plan) and Service Transition activity\nTimesheet to be completed, as per agreed timeline.\n\n\u00a0 \u00a0 \u00a0 \u00a0 \u00a0\u00a0IT Support and Maintenance Management\n\n\nEnsure all incidents generated problems are managed and resolved within predefined SLAs\nContinuous review and improve operations process to avoid potential incidents\nArrange regular preventive maintenance to mitigate know operation issues\n\n\u00a0 \u00a0 \u00a0 \u00a0 \u00a0 \u00a0IT Finance and Governance\n\nEstablish and enforce IT Governance for all IT process and business touchpoints\n\nRequirement\n\nUniversity degree in Information Technology or related fields\nITIL V3 or V4 Certification in Service Management\nMore than 5 years of working experience in IT with over 3 years working in IT Service Management\nExtensive experience in IT Production Control\nSolid experience in Quality Management, including metrics capture and dashboard reporting\nSolid Experience in working with off-shore service providers to deliver significant portion of daily work from India, Malaysia, Singapore, Philippines and China\nGood Communication and Interpersonal Skills\nWilling and able to work long hours and on-call for high severity Incident escalation\nFluent in English and Cantonese is a must\nFluent in Mandarin is an added advantage\n\n\n", "employment_types": ["Full Time", "Contract"], "selling_points": ["Information Technology", "IT Service Delivery", "Insurance"], "locations": ["Aberdeen"], "categories": ["Information Technology (IT)", "IT Management"], "post_time": "2022-01-17T05:53:27Z", "salary": {"currency": null, "max": null, "min": null, "period": "monthly", "term": null}, "salary_visible": false, "title_keywords": ["assistant manager,"], "responsibilities": ["service delivery", "management", "control", "it service", "provide support", "maintenance", "data", "operations", "review", "quality", "monitor", "procedures", "develop", "resolution", "communication", "plan"], "requirements": {"degrees": ["university degree"], "majors": ["information technology"], "languages": ["cantonese", "english", "mandarin"], "language_level": ["advantage", "fluent"], "hard_skills": ["itil"], "soft_skills": ["communication and interpersonal skills", "extensive"], "languages_combined": [{"language": "cantonese", "language_level": []}, {"language": "english", "language_level": []}, {"language": "mandarin", "language_level": ["fluent", "advantage"]}]}, "experience_required": {"duration": ["5 years", "3 years"], "field": ["management", "it", "quality management"]}}, {"job_id": "100003009050043", "location_code": "hk", "company": "World Vision Hong Kong", "job_title": "IT Manager", "description": "Job Responsibilities:\u00a0\n\n\nLead the IT Department to provide effective information technology services for the whole organization\nProvide & develop IT strategy planning, business plan, policies & guidelines, budget monitoring and procurement recommendation\n\u00a0Oversee the infrastructure operations in supporting network and technical support services\nOversee the software development life cycle for in-house applications and corporate website\nPlan & implement IT security controls to ensure the confidentiality, integrity and availability of the information assets\nSupervise external & internal IT security compliance activities to ensure the compliance standard\n\n\u00a0Job Requirements:\n\n\nBachelor degree or above in Information Technology or related disciplines\nAt least 10 years working experience in project management, programming, system analysis and design\n4 years of experience in managerial role with supervisory duties\nExperience in MS Azure, MS 365 including Power Tools, Windows Servers, SSRS, SQL server, Dynamics 365, .net or .net Core development\nExperience in on-cloud and on-premise infrastructure implementation\nExperience in digital marketing implementation and maintaining PCI-DSS compliance standard will be an added advantage\nGood prioritization skills and flexible to adapt plans with constraints\nA strong leader and a good team player\nStrong passion to serve the poor, especially the children\nOn renewable contract term for the initial two years.\u00a0 Candidates with satisfactory performance may convert to permanent employment afterwards based on business needs.\n\nPlease apply online with your full resume, listing church affiliations (if any), current and expected salary.\n\n\nYou may also send your application to:\nHead of HR & Administration, World Vision Hong Kong, 2/F Mayfair Centre, 4 Anchor Street, Tai Kok Tsui, Kowloon\n\nTo find out more about our job opportunities, please visit our website\u00a0https://www.worldvision.org.hk/get-involved/vacancies\n\nWorld Vision Hong Kong is committed to safeguarding our children and adult beneficiaries from any risk of abuse, exploitation and harm. Candidates selected for interviews will be requested a self-declaration of previous records for any crimes against children or sexual offences, and may be requested to undergo Sexual Conviction Record Check by the HK Police.\n\nPersonal Data provided by job applicants will be used for recruitment purposes only and will be treated in accordance with the organization's personal data privacy policy. Applicants who are not invited for interviews within six weeks may consider their applications unsuccessful and the personal data collected will be destroyed within 12 months.", "employment_types": ["Full Time"], "selling_points": [], "locations": ["Mong Kok"], "categories": ["Information Technology (IT)", "IT Project Management / Team Lead", "IT Management", "Network & System"], "post_time": "2022-01-14T09:41:03Z", "salary": {"currency": null, "max": null, "min": null, "period": "monthly", "term": null}, "salary_visible": false, "title_keywords": ["it manager"], "responsibilities": ["software", "guidelines", "policies", "technical support", "budget", "monitoring", "website", "compliance", "develop", "infrastructure operations", "plan", "business plan", "planning"], "requirements": {"degrees": ["degree or above", "bachelor"], "majors": ["related disciplines", "information technology"], "languages": [], "language_level": [], "hard_skills": ["azure", "servers", "analysis", "sql", "project management", "programming", "server"], "soft_skills": ["flexible", "project management", "good team player", "committed"], "languages_combined": []}, "experience_required": {"duration": ["at least 10 years", "4 years"], "field": ["managerial", "supervisory", "infrastructure", "compliance", "design", "sql", "project management", "digital marketing", "programming"]}}, {"job_id": "100003009052776", "location_code": "hk", "company": "Hong Kong Sports Institute Ltd", "job_title": "INFORMATION TECHNOLOGY MANAGER", "description": "JOB DESCRIPTION\nReporting to the Director, Corporate Services, the Information Technology Manager is responsible for leading the planning and implementation of best-in-class Information Technology activities to support the HKSI\u2019s elite sport and corporate operation needs. Leading the IT Department team, the IT Manger is responsible for the following:\nWorking collaboratively across the organisation to lead the identification, implementation, monitoring and maintenance of all the HKSI\u2019s information and communications technology systems within both short and long term planning frameworks;\nTo regularly review and recommend the most up-to-date application, content and computing platforms to enhance the HKSI\u2019s elite sport and corporate operations data processing and analytic needs;\nTo lead the evaluation, and guide strategic provisioning of applicable technologies to ensure elite sport and corporate systems are interoperable and align with both elite sport and corporate administrative data needs;\nTo direct the future oriented development, implementation monitoring and maintenance\u00a0 of a highly secure, efficient and cost-effective IT infrastructure including hardware, software and storage systems;\nTo ensure a dynamic comprehensive risk-management strategy is in place including disaster recovery plans, and security systems to reduce vulnerabilities such as data leakages etc;\nTo regularly review, enhance, and/or introduce as necessary all IT related policies and procedures and to monitor compliance;\nTo ensure timely and effective technical support, help desk services to all user departments; and\nPerform any other appropriate duties as assigned by supervisor.\n\u00a0THE REQUIREMENTS\n\nA university degree in Information Technology, Computer Science or a relevant disciplines; A Post graduate degree is preferred;\nA minimum of 10 years\u2019 Management experience in a similar role;\nExcellent command of both written and spoken English and Chinese. Ability to speak Putonghua is a definite advantage;\nStrong communication and presentation skills.\u00a0 Excellent interpersonal skill in dealing with all levels of staff across the organisation;\nHighly motivated individual, who places emphasis on teamwork and has excellent strategic thinking and analytical skills.\nAPPLICATIONS\nPlease send the completed\u00a0application form with indication of your current and expected salary to\u00a0The Human Resources Manager, Hong Kong Sports Institute Ltd, 25 Yuen Wo Road, Sha Tin, New Territories\u00a0or email:\u00a0hrdept @ hksi.org.hk\u00a0on or before 30 January 2022. Please quote reference no.\u00a0JD-20220117-ITM\u00a0in the application.\nAppointment will be on a fixed term contract. General information is available at the website http://www.hksi.org.hk.\nApplicants who are not invited for interview within six months may consider their applications unsuccessful.\nAll applications will be treated in the strictest confidence. Data collected will be used for recruitment and other employment-related purposes only.\nTHE HKSI IS AN EQUAL OPPORTUNITIES EMPLOYER", "employment_types": ["Full Time"], "selling_points": [], "locations": ["Shatin Area"], "categories": ["Information Technology (IT)", "IT Project Management / Team Lead", "IT Management", "Others"], "post_time": "2022-01-17T04:01:47Z", "salary": {"currency": null, "max": null, "min": null, "period": "monthly", "term": null}, "salary_visible": false, "title_keywords": ["technology manager"], "responsibilities": ["software", "data", "operations", "evaluation", "plans", "it infrastructure", "compliance", "monitor", "implementation", "reporting", "cost", "management", "monitoring", "review", "procedures", "maintenance", "technical support", "policies", "systems", "data processing", "hardware", "planning"], "requirements": {"degrees": ["university degree", "degree"], "majors": ["computer science", "information technology"], "languages": ["putonghua", "english", "chinese"], "language_level": ["advantage", "excellent"], "hard_skills": ["no", "hksi", "analytical skills"], "soft_skills": ["confidence", "strategic thinking", "teamwork", "interpersonal skill", "communication", "motivated individual", "presentation skills", "analytical skills", "organisation"], "languages_combined": [{"language": "putonghua", "language_level": ["advantage"]}, {"language": "english", "language_level": ["excellent"]}, {"language": "chinese", "language_level": ["excellent"]}]}, "experience_required": {"duration": ["minimum of 10 years"], "field": ["management"]}}, {"job_id": "100003009051220", "location_code": "hk", "company": "Spidernet Recruitment Services", "job_title": "IT Manager", "description": "Responsibilities:\u00a0\n\n\nLeading the IT Team to support the company\u2019s mission\nOversight company wide IT activities\nMaintenance smooth, reliable and secure IT Environment to support the business operation\nAccountable the key metrics of IT project portfolio execution\nFormulate IT policies and procedure\nEnsure the IT governance is enforced and support the business growth\nRequirements:\n\n\nDegree in Computer Science, Information Management, Operation research or relevant disciplines\n8 years or above IT experience with minimum of 3 years management experience\nSolid experience on IT services management\nHands on experience on application development with water-fall, DevOps and CI/CD and project management\nExperience on Vendor management and IT procurement\nSound knowledge on internet technologies and development tools\nStrong knowledge on compliance and Cyber Security is a must\nGood knowledge in networking, Firewall an MS 365\nDetail-minded, able to work independently\nResults orientated with good communication and interpersonal skills\nAble to communicate at different levels\nCISSP, CISA, ITIL, PMP certifications / ScrumMaster is a plus\nGood command of written and spoken in English, Cantonese and Putonghua\nAttractive remuneration and fringe benefits will be offered to the successful candidate.\n\nInterested candidates should apply with detailed resume, present and expected salaries by clicking the Apply Now button.\n\nAll information received will be treated in strict confidence and used for recruitment purpose only.\n\nOnly shortlisted candidates will be notified\n", "employment_types": ["Full Time", "Permanent"], "selling_points": ["Degree / Master in Computer Science, IT", "8 yrs IT services /project management", "Application Dev, Networking, Cyber Security"], "locations": ["Wan Chai Area"], "categories": ["Information Technology (IT)", "IT Project Management / Team Lead", "IT Management", "Network & System"], "post_time": "2022-01-15T05:11:49Z", "salary": {"currency": null, "max": null, "min": null, "period": "monthly", "term": null}, "salary_visible": false, "title_keywords": ["it manager"], "responsibilities": ["business operation", "it policies", "maintenance"], "requirements": {"degrees": ["degree"], "majors": ["computer science"], "languages": ["cantonese", "putonghua", "english"], "language_level": ["good command"], "hard_skills": ["itil", "plus", "cyber security", "devops", "vendor", "project management", "firewall", "pmp"], "soft_skills": ["detail-minded", "work independently", "project management", "hands on", "communication and interpersonal skills"], "languages_combined": [{"language": "cantonese", "language_level": ["good command"]}, {"language": "putonghua", "language_level": ["good command"]}, {"language": "english", "language_level": ["good command"]}]}, "experience_required": {"duration": ["minimum of 3 years", "8 years"], "field": ["management", "devops", "it experience", "project management", "it", "application development", "procurement"]}}, {"job_id": "100003009049478", "location_code": "hk", "company": "", "job_title": "Senior IT Manager - Shenzhen", "description": "Responsibilities :\n\nLead Manufacturing Information System teams to maintain the daily operations of HK office, China offices and manufacturing plants to make sure professional services are delivered\nMonitor and enhance the existing computerized environment of the Group, especially the operation of ERP/Shop floor control manufacturing system\nConsult with management to determine information requirements of various departments and activities to determine boundaries and priorities of new projects, and to discuss system capacity and equipment acquisitions\nAdvise top management on strategic solutions to enhance efficiency and upgrade services\nPrepare IT proposal, budget, technical documentation and system specification\nStrive to improve business performance through effective utilization of IT resources\nLiaise with internal users and external IT vendors on system implementation and enhancement\nPrepare operations manuals and provide training to the end users\n\n\u00a0Requirements :\u00a0 \u00a0 \u00a0 \u00a0 \u00a0 \u00a0 \u00a0 \u00a0 \u00a0\n\nDegree holder in Computer Science or Information System\nMin. 10 years relevant working experience in a sizable EMS/electronics manufacturer, with at least 5 years at managerial level\nFull implementation cycle experience with ERP/MRPII systems and other database applications such as accounting and HRIS systems\nPrior experience in managing IT projects in Quality Management, Manufacturing Quality, Production Planning, Purchasing, Finance, Network Security, Network Maintenance, Operating Systems, IT security\nSolid programming experience on MS SQL server, experience with database design and programming is a must\nPractical experience in Oracle EBS functional knowledge and customization is an advantage;\nGood knowledge in developing Windows network, Linux and PC infrastructure; good knowledge of Power Builder or application development on Windows platform is preferable\nKnowledge of ISO9000, ISO27000 and document control procedures is an asset\nStrong leadership and management skills, proven ability to manage IT team to achieve timelines and objectives\nProficiency in both written and spoken English, Chinese and Mandarin\nWork based in Shenzhen\n\nInterested candidates, please contact us at 92694375 for company details before applying.", "employment_types": ["Full Time", "Permanent"], "selling_points": ["Degree in Information Technology, Computer Science", "10 years solid experience", "Electronics manufacturing companies"], "locations": ["Others - China"], "categories": ["Information Technology (IT)", "IT Project Management / Team Lead", "IT Management"], "post_time": "2022-01-14T08:44:13Z", "salary": {"currency": null, "max": null, "min": null, "period": "monthly", "term": null}, "salary_visible": false, "title_keywords": ["senior it manager"], "responsibilities": ["provide training", "control", "management", "operations", "budget", "teams", "monitor", "implementation", "liaise with", "daily operations", "maintain", "documentation"], "requirements": {"degrees": ["degree holder"], "majors": ["computer science"], "languages": ["english", "chinese", "mandarin"], "language_level": ["proficiency"], "hard_skills": ["linux", "ms sql server", "ems", "network maintenance", "information system", "erp", "programming", "pc", "oracle"], "soft_skills": ["leadership"], "languages_combined": [{"language": "english", "language_level": ["proficiency"]}, {"language": "chinese", "language_level": ["proficiency"]}, {"language": "mandarin", "language_level": ["proficiency"]}]}, "experience_required": {"duration": ["10 years", "at least 5 years"], "field": ["managerial", "manufacturing", "maintenance", "purchasing", "finance", "relevant working experience", "design", "sql", "it", "security", "database", "quality management", "programming", "accounting", "planning"]}}, {"job_id": "100003009053210", "location_code": "hk", "company": "The Hong Kong Federation of Youth Groups", "job_title": "Head of Information Technology\uff08\u8cc7\u8a0a\u79d1\u6280\u7e3d\u76e3\uff09", "description": "Job Duties and Responsibilities:\nSet the technology vision and roadmap for innovation for the organization\nHead up a team and take the lead in driving IT changes to bring about digital transformation to the workplace and services\nCultivate business relationships with various parties, including but not limited to, vendors, funders, business partners; as well as staff\nDevise and implement innovative IT approaches to support the organization\u2019s strategic plans with its focus on digitalization transformation\nManage and execute major system change projects as part of the organization\u2019s digital transformation journey\nStay abreast of trends and advances in IT solutions, monitor changes in the market and apply them to the operations and services to drive change management in the organization\nEntry Requirements:\nStudy Fields\uff1a\nBachelor Degree, or above, in Computer Science, Information System Management or equivalent\nKnowledge, Skills and Abilities:\n15 years, or more, in the IT field with at least recent 8 years as IT Leader / Manager / Head in sizeable organizations\nExtensive IT work experience in managing and leading IT changes and digital transformation programmes\nPersonal Attributes:\nProven ability in leading project execution\nProven leadership, with problem solving, as well as, interpersonal and communication skills\nResourceful, with strong professional network in both private and public sectors, with abilities to build partnerships with key stakeholders\nAdditional Requirements:\nProfessionals who can provide service in flextime may be considered for the role of consultant.\nTo apply, please submit an online application at HKFYG Recruitment Portal https://erecruit.hkfyg.org.hk/ OR complete the application form (downloaded from erecruit.hkfyg.org.hk/ApplicationForm.doc) and email by clicking \"Apply now\" .\u00a0 Candidates may be required to undergo Sexual Conviction Record Check (SCRC) if job duties involve frequent contact with children.\u00a0 Only shortlisted candidates will be notified to attend a written test. hkfyg.org.hk. \u00a0", "employment_types": ["Full Time", "Contract"], "selling_points": [], "locations": ["Quarry Bay"], "categories": ["Information Technology (IT)", "IT Project Management / Team Lead", "IT Management", "Others"], "post_time": "2022-01-17T07:22:51Z", "salary": {"currency": null, "max": null, "min": null, "period": "monthly", "term": null}, "salary_visible": false, "title_keywords": [], "responsibilities": ["operations", "monitor", "strategic plans", "change management"], "requirements": {"degrees": ["degree", "bachelor"], "majors": ["computer science"], "languages": [], "language_level": [], "hard_skills": ["problem solving", "information system"], "soft_skills": ["communication skills", "resourceful", "problem solving", "leadership", "extensive", "interpersonal"], "languages_combined": []}, "experience_required": {"duration": [], "field": ["digital", "it"]}}, {"job_id": "100003009055927", "location_code": "hk", "company": "Chong Hing Bank Ltd", "job_title": "Assistant Vice President, System Infrastructure - IT Operations Department", "description": "Responsibilities:\nPerform 7 x 24 installation, management and support on IT systems of the bank according to defined policies, processes and procedures\n\nConduct performance & availability monitoring, capacity management, system management and tuning, configuration & service level management, problem diagnosis & resolution, security management & patch application, change management, of the supported IT areas\n\nDevelop, establish and review standards, procedures and profiles in the responsible area\n\nPerform infrastructure products or related tools assessment and provide recommendations to management\n\nDesign and review the implemented infrastructure in the supported domains\n\nConduct regular review and monitor all installed systems from infrastructure perspectives and report timely on any performance issues\n\nCarry out assigned tasks and projects with good quality, within budget and meeting pre-defined scopes and schedule\n\nPrepare regular/ad-hoc reports to management on problems, incidents and assigned tasks and project progress on a timely basis\n\nRequirements:\nUniversity graduate in Computer Science or Information Technology related disciplines\n\nMinimum 6 years of working experience in infrastructure administration and support, preferably in financial institution\n\nFamiliar with UNIX, Linus, Windows, SAN Storage, Backup Software, Mail systems and monitoring tools such as HP-UNIX, AIX, Domino Notes and Netbackup\n\nSelf-initiated, ability to work independently and under pressure with integrity\n\nGood analytical & communication skills\n\nInterested candidates, please click APPLY NOW \u00a0to apply.", "employment_types": ["Full Time"], "selling_points": ["Perform infrastructure products", "Design and review the implemented infrastructure", "6 years of working experience"], "locations": ["Not Specified"], "categories": ["Information Technology (IT)", "IT Management", "Network & System", "Others"], "post_time": "2022-01-18T03:05:55Z", "salary": {"currency": null, "max": null, "min": null, "period": "monthly", "term": null}, "salary_visible": false, "title_keywords": ["operations", "assistant vice president"], "responsibilities": ["ad-hoc", "budget", "quality", "design", "regular review", "configuration", "infrastructure", "monitor", "project progress", "develop", "resolution", "reports", "schedule", "report", "installation", "management", "change management", "monitoring", "procedures", "review", "provide recommendations", "policies", "systems"], "requirements": {"degrees": ["university graduate"], "majors": ["related disciplines", "computer science", "information technology"], "languages": [], "language_level": [], "hard_skills": [], "soft_skills": ["communication skills", "work independently", "under pressure", "integrity"], "languages_combined": []}, "experience_required": {"duration": ["minimum 6 years"], "field": ["financial", "infrastructure administration"]}}, {"job_id": "100003009053848", "location_code": "hk", "company": "Konew Financial Express Ltd", "job_title": "Systems and Operations Manager", "description": "Main Duties & Responsibilities:\n\nLead the System Operation and Infrastructure team\nManage the overall system operations and long term direction for network infrastructure and application/database server support functions\nPerform system implementation, monitoring, trouble- shooting and documentation across platform and application domains\nCoordinate with Information Security team on performing security incident management including detection and response\nDevelop and implement IT operation and maintenance work plans according to the requirements of the company\nProactively review and identify potential changes and system improvements for consideration\nManage system related projects to ensure reliable system availability for application development and production and provide regular/timely/accurate status reporting\nManage the complete process of projects, deployments, system changes from preparation, implementation and testing\nHandle ad hoc tasks as assigned from time to time\n\nRequirements:\n\nBachelor\u2019s Degree holder in Computer Science, Information System or related disciplines\nAt least 10 years of relevant working experience in system operation and infrastructure, preferably with management exposure\nFamiliar with infrastructure support and experienced in system implementation\nProblem- solving aptitude, well- organized, self- motivated and able to work under pressure\nStrong leadership, coaching, communication and interpersonal skills\nExcellent command of spoken and written Chinese and English\nWe offer:\n\n\u00a0\u00a0\u00a0\u00a0\u00a0\u00a0\u00a0 Discretionary bonus\n\u00a0\u00a0\u00a0\u00a0\u00a0\u00a0\u00a0 Medical insurance\n\u00a0\u00a0\u00a0\u00a0\u00a0\u00a0\u00a0 Dental insurance\n\u00a0\u00a0\u00a0\u00a0\u00a0\u00a0\u00a0 Hardship allowance\n\u00a0\u00a0\u00a0\u00a0\u00a0\u00a0\u00a0 Competitive annual leave days\n\u00a0\u00a0\u00a0\u00a0\u00a0\u00a0\u00a0 Birthday leave\n\u00a0\u00a0\u00a0\u00a0\u00a0\u00a0\u00a0 Anniversary leave\n\u00a0\u00a0\u00a0\u00a0\u00a0\u00a0\u00a0 Study leave\n\u00a0\u00a0\u00a0\u00a0\u00a0\u00a0\u00a0 Marriage leave\n\u00a0\u00a0\u00a0\u00a0\u00a0\u00a0\u00a0 Compassionate leave\n\nHow to apply:\n\nInterested parties, please send your resume stating your expected salary to Human Capital Department\u00a0by clicking \"APPLY NOW\".\n\n(We are an equal opportunity employer.\u00a0 Personal data collected will be used for recruitment purpose only.\u00a0 The unsuccessful applications will be destroyed after 6 months.)", "employment_types": ["Full Time"], "selling_points": ["Lead the System Operation and Infrastructure team", "Implement IT operation and maintenance work plans", "Identify potential changes and system improvement"], "locations": ["Central"], "categories": ["Information Technology (IT)", "Support", "IT Management", "Network & System"], "post_time": "2022-01-17T07:37:02Z", "salary": {"currency": null, "max": null, "min": null, "period": "monthly", "term": null}, "salary_visible": false, "title_keywords": ["operations manager"], "responsibilities": ["information security", "operations", "database", "plans", "application development", "infrastructure", "implementation", "develop", "testing", "network infrastructure", "reporting", "management", "monitoring", "coordinate with", "review", "ad hoc tasks", "documentation", "system changes", "maintenance", "system improvements"], "requirements": {"degrees": ["bachelor", "degree holder"], "majors": ["related disciplines", "computer science"], "languages": ["english", "chinese"], "language_level": ["excellent"], "hard_skills": ["system implementation", "infrastructure support", "information system"], "soft_skills": ["organized", "motivated", "communication and interpersonal skills", "leadership", "work under pressure"], "languages_combined": [{"language": "english", "language_level": ["excellent"]}, {"language": "chinese", "language_level": ["excellent"]}]}, "experience_required": {"duration": ["at least 10 years"], "field": ["infrastructure", "management", "operation", "relevant working experience"]}}, {"job_id": "100003009051568", "location_code": "hk", "company": "Maxim's Caterers Ltd", "job_title": "Manager \u2013 Infrastructure & Operations", "description": "Responsible for regional IT infrastructure management, day-to-day IT operations, end-user support and IT facilities management.\u00a0 Working on providing stable and secure IT infrastructure to support business-critical application and services, as well as providing high-quality IT services to internal users.\n\n\nResponsibilities\nLead a technical team to manage and operate the company\u2019s regional infrastructure, which comprises of local and regional networks, colocation data centers, public clouds, server & virtualization platforms\nWork with internal IT teams and support vendors to ensure the reliability and security of IT infrastructure\nOversee IT operation, drive operational excellence and continuous improvement\nLead IT infrastructure projects with efficient vendor management skills\nRequirements\nDegree holder in Computing or related discipline\nMinimum 10 years of experience in IT infrastructure, IT operations, and/or end-user support\nProven experience in managing technical staff and vendor to deliver enterprise-scale IT projects and/or services\nSound knowledge in infrastructure technologies and enterprise applications, e.g. networking, cloud, server & virtualization platform, storage, IT security software, etc.\nExperience in F&B, retail or manufacturing environment will have advantage\nHolder of technical certifications, e.g. MCSE, CCNA/CCNP, VMware, public cloud, ITIL, PMP will have advantage\nGood communication, teamwork, and negotiation skills\nGood problem-solving and analytical skills\nGood command in written & spoken English and Cantonese\nInterested parties please apply with full resume, state current and expected salaries by clicking \"Apply Now\". All applications and data collected will be treated in strict confidence and used exclusively for recruitment purposes.\u00a0 Only short listed candidates will be invited for interview. The company will retain the applications for a maximum period of 24 months and may refer suitable candidates to other vacancies within the Group.", "employment_types": ["Full Time", "Permanent"], "selling_points": ["Regional IT infrastructure management", "Lead a technical team", "IT infrastructure projects & vendor management"], "locations": ["Lai Chi Kok"], "categories": ["Information Technology (IT)", "Hardware", "IT Management", "Network & System"], "post_time": "2022-01-16T11:09:00Z", "salary": {"currency": null, "max": null, "min": null, "period": null, "term": null}, "salary_visible": false, "title_keywords": ["operations", "manager"], "responsibilities": ["management", "it infrastructure", "data", "infrastructure", "teams"], "requirements": {"degrees": ["degree holder"], "majors": [], "languages": ["cantonese", "english"], "language_level": ["good command"], "hard_skills": ["itil", "mcse", "vmware", "ccnp", "problem-solving", "ccna", "vendor", "analytical skills", "server", "pmp"], "soft_skills": ["problem-solving", "teamwork", "analytical skills", "communication", "negotiation skills"], "languages_combined": [{"language": "cantonese", "language_level": ["good command"]}, {"language": "english", "language_level": ["good command"]}]}, "experience_required": {"duration": ["minimum 10 years"], "field": ["manufacturing", "infrastructure", "f&b", "it", "retail", "it operations"]}}, {"job_id": "100003009049368", "location_code": "hk", "company": "HGC Global Communications Limited", "job_title": "IT Project Manager", "description": "Responsibilities:\u00a0\n\nManage and lead the planning and implementation of IT technical projects (e.g. Cloud implementation, IT infrastructure\u00a0projects);\nManage project schedule, resources\u00a0and risks. Perform proper\u00a0escalation to ensure project success;\nEnsure all the contractual\u00a0commitments and deliverable\u00a0are successfully delivered by vendors on time and within the budget;\nConduct system analysis, implementation, testing, user training and documentation\u00a0on IT systems;\nInterface with customers on system implementation for business systems projects;\nPerform product evaluation, vendor selection, and procurement of IT solutions / products.\u00a0\n\nRequirement:\n\nDegree in IT/ Computer Sciences/ Computer Engineering or related discipline\n5 years solid experience in IT project management with technical knowledge;\nCertified in any PMP, Agile, or Scrum Master is preferred\nKey competencies:\nLeading others\u00a0\nComposure\nInterpersonal Savvy\u00a0\nBusiness Acumen\nDealing with Ambiguity\n\nWe offer competitive salary package and career development opportunity. \u00a0Free company coach is provided. Interested parties, please quote our reference number and apply with full resume,\u00a0present and expected salary, by clicking \"APPLY NOW\".\u00a0\n\n\nWe are an equal opportunity employer and welcome applications from all qualified candidates. Information provided will be treated in strict confidence and only be used for consideration of your application for the relevant post within the HGC Global Communications Limited. Personal data provided by job applicants will be used strictly according to our Personal Information Collection Statement, a copy of which will be available upon written request. Information of unsuccessful candidates will be destroyed within six months.", "employment_types": ["Full Time", "Permanent"], "selling_points": ["IT Project Management permanent role", "Great exposure on technical transformation", "Dynamic working environment"], "locations": ["Tsing Yi"], "categories": ["Information Technology (IT)", "IT Project Management / Team Lead", "IT Management", "Technical Writing"], "post_time": "2022-01-14T08:31:44Z", "salary": {"currency": null, "max": null, "min": null, "period": "monthly", "term": null}, "salary_visible": false, "title_keywords": ["it project manager"], "responsibilities": ["it infrastructure", "analysis", "budget", "systems", "implementation", "testing", "schedule", "evaluation", "documentation", "planning"], "requirements": {"degrees": ["degree", "master"], "majors": ["it", "computer engineering"], "languages": [], "language_level": [], "hard_skills": ["project management", "pmp", "agile", "acumen"], "soft_skills": ["business acumen", "project management", "interpersonal", "agile"], "languages_combined": []}, "experience_required": {"duration": ["5 years"], "field": ["project management", "it"]}}, {"job_id": "100003009054729", "location_code": "hk", "company": "China Mobile International Limited", "job_title": "IT Service Management Officer (Ref:CMIJD-0117-ITSMOIAMDI)", "description": "\nResponsibilities:\nTo manage and maintain a high quality of IT service delivery\nManage requirement management-related tasks, collaborate with internal customers and sources of requirements\nManage and optimize internal evaluation mechanism. Service and incident record and reporting\nMaintain relations with internal customers, plan and implement relation maintenance activities, setup service brand\nTo assist in management of service delivery team\n\nRequirements:\n\nBachelor or above in Computer Studies or other IT related disciplines\n2+ years of work experiences in IT or telecommunication industry\nKnowledge and skills of operating system platforms, network, VPN, Endpoint Protection\nFamiliar with\u00a0ITIL is an advantage\nSolid skills on MS Visio, Excel, Word, PowerPoint\nProactive, independent and ability to work under pressure\nStrong analytical skills, interpersonal and presentation skills\nGood verbal and written English and Chinese. Fluent Putonghua is essential.\nNon-office hour supports is required where necessary\n\nInterested parties please send your full resume with current & expected salary by clicking \"Apply Now\".\u00a0\u00a0\n\nAll personal data provided will be used for consideration of your job application only.", "employment_types": ["Full Time", "Permanent"], "selling_points": ["Ensure high quality of IT service delivery", "Manage & Optimize internal evaluation mechanism", "Plan & implement relation maintenance activities"], "locations": ["Kwai Hing"], "categories": ["Information Technology (IT)", "IT Management", "Security", "Network & System"], "post_time": "2022-01-17T10:47:40Z", "salary": {"currency": null, "max": null, "min": null, "period": "monthly", "term": null}, "salary_visible": false, "title_keywords": ["officer"], "responsibilities": ["collaborate with", "reporting", "management", "service delivery", "it service", "maintenance", "quality", "maintain", "plan", "evaluation", "setup"], "requirements": {"degrees": ["bachelor"], "majors": ["related disciplines", "it", "computer studies"], "languages": ["putonghua", "english", "chinese"], "language_level": ["fluent", "good"], "hard_skills": ["itil", "excel", "word", "powerpoint", "analytical skills", "vpn"], "soft_skills": ["independent", "analytical skills", "presentation skills", "proactive", "interpersonal", "work under pressure"], "languages_combined": [{"language": "putonghua", "language_level": ["fluent"]}, {"language": "english", "language_level": ["good"]}, {"language": "chinese", "language_level": ["good"]}]}, "experience_required": {"duration": ["2+ years"], "field": ["it"]}}, {"job_id": "100003009044631", "location_code": "hk", "company": "HSH Management Services Limited", "job_title": "Regional IT Manager - Properties and Clubs", "description": "Working alongside a professional team in the Group\u2019s Corporate Head Office, we are seeking for a Regional IT Manager \u2013 Properties and Clubs to join the Information Technology Department.\u00a0 This role will report to the Director, IT Operations and IT Technical Services on providing IT support for three clubs and overview three other operations to achieve the company\u2019s objectives and lead the team to success.\n\nWork for a highly prestigious and renowned hospitality group\nBe part of the professional team\nExceptional benefits such as comprehensive family medical insurance (including dependents) and pension benefits\n\nKey Accountabilities\n\nManage and ensure the IT operations at Properties and Clubs align with the corporate standards\nFormulate standards, seamless IT services and ensure effective utilisation of IT systems and resources by operations\nImplement and maintain effective Disaster Recovery process for all critical applications and IT infrastructures\nLiaise with Corporate IT team, IT vendors and relevant stakeholders for system upgrade and projects\nRecommend IT strategies, policies and procedures by evaluating organization outcomes, identifying problems, evaluating trends and anticipating requirements\nCoordinate and facilitate annual IT review, provide response and follow-up to recommendations and implementation\nWork closely with division and department heads to encourage the productive use of IT resources\n\nGeneral requirements\n\nUniversity Degree or above in Information Technology, Computer Science, or Information Management Science\u00a0\nCertificate or Diploma in networking, windows server administration, IT Security (Vulnerability Management, Windows, Desktop Management)\nAt least 6 years\u2019 experience in IT infrastructure operations, IT service management, or IT business operations\nInnovative and excellent leadership and communication ability with \u00a0\u00a0systematic trouble shooting skill\nGood command of both written and spoken English", "employment_types": ["Full Time"], "selling_points": ["Manage and ensure the IT operations at Properties and Clubs align with the corporate standards", "Formulate standards, seamless IT services and ensure effective utilisation of IT systems and resources by operations", "Implement and maintain effective Disaster Recovery process for all critical applications and IT infrastructures"], "locations": ["Central"], "categories": ["Hospitality / F & B", "Hospitality / Hotel Services", "Information Technology (IT)", "IT Management"], "post_time": "2022-01-13T04:57:05Z", "salary": {"currency": null, "max": null, "min": null, "period": "monthly", "term": null}, "salary_visible": false, "title_keywords": ["regional it manager"], "responsibilities": ["operations", "report"], "requirements": {"degrees": [], "majors": [], "languages": [], "language_level": [], "hard_skills": [], "soft_skills": [], "languages_combined": []}, "experience_required": {"duration": [], "field": []}}, {"job_id": "100003009050397", "location_code": "hk", "company": "Gold Partners (Asia) Asset Management Company Limited", "job_title": "Infrastructure Manager - HQIT", "description": "Job Description\n\nManage and maintain IT infrastructure covering network, server, storage and virtualization etc.\nSelect, evaluate and recommend technologies to meet business needs\nOversee infrastructure project life-cycle from planning, budgeting to installation and troubleshooting\nProvisioning of new site, office relocation, and infrastructure setup\nMaintaining and developing procedures and standards to reflect changing technologies and working practices. Update of technical manuals, process and network schematics. Keep the IT Inventory updated\nManage IT infrastructure and application audits from planning to reporting and closing of audit issues\nSounds knowledge in\u00a0information security standards and security hardening\nLead, coach and develop teams in areas of HK, China and Taiwan\nAt least 3 years of experience in managerial level\n\nThe Successful Applicant\n\nUniversity degree in Computer Science, Information Technology or related field\nProfessional qualification e.g.\u00a0MCSE, CCNA and\u00a0ITIL will be an advantage\nSolid experience to manage large-scale IT infrastructure project, data center management\nHands on experience on SAN storage, VMWare / Citrix virtualization, Microsoft platforms AD / DNS / Exchange / SQL /\u00a0H3C / VOIP / Voice System / Cisco and Fortigate FW\u00a0etc.\nHands on experience in Linux platform with apps like postfix, bind and squid is definitely an advantage\nExperience in Virtual Desktop Infrastructure (VDI), HP Simplivity and Fortigate (FortiAnalyze, FortiManager) would be an advantage\nGood communication skill in\u00a0Mandarin, Cantonese\u00a0and English\nImmediate availability preferred\n\nWe offer:\n\n12 Days Annual Leave\nMedical & Dental Scheme\nOn-the-job Training\nYear-end Bonus\nExcellent Career Advancement Opportunities\nCollaborative working environment\nStaff Caring Benefit, e.g. Festival Gift, Home-made Chinese Herbal Drinks/Soup\n\nInterested applicants please fax your resume with present & expected salary to HR & Admin Department at 8161-6498 or click \"Apply Now\" underneath.\u00a0\n\nFor company information, please visit our website:\u00a0www.goldpartners.com.hk\n\nAll information provided by applicants will be kept confidential and used for recruitment purposes only. The company will retain the information collected for a maximum period of 1 year and may refer suitable applicants to other vacancies within the Group.\u00a0", "employment_types": ["Full Time", "Permanent"], "selling_points": [], "locations": ["Kowloon Bay"], "categories": ["Information Technology (IT)", "IT Management", "Application Specialist - Network", "Network & System"], "post_time": "2022-01-15T03:51:06Z", "salary": {"currency": null, "max": null, "min": null, "period": "monthly", "term": null}, "salary_visible": false, "title_keywords": ["manager"], "responsibilities": ["information security", "data", "budgeting", "troubleshooting", "audit", "communication", "maintain", "it infrastructure", "maintaining", "infrastructure", "teams", "developing", "develop", "it inventory", "setup", "installation", "reporting", "management", "procedures", "audits", "dns", "evaluate", "planning"], "requirements": {"degrees": ["university degree"], "majors": ["computer science", "information technology"], "languages": ["cantonese", "english", "mandarin"], "language_level": ["good"], "hard_skills": ["itil", "mcse", "linux", "vmware", "dns", "ccna", "sql", "citrix", "server", "exchange"], "soft_skills": ["communication skill", "hands on", "troubleshooting"], "languages_combined": [{"language": "cantonese", "language_level": ["good"]}, {"language": "english", "language_level": ["good"]}, {"language": "mandarin", "language_level": ["good"]}]}, "experience_required": {"duration": ["at least 3 years"], "field": ["managerial", "management", "infrastructure", "sql", "it"]}}, {"job_id": "100003009054283", "location_code": "hk", "company": "FUJIFILM Data Management Solutions Asia Limited", "job_title": "Project Manager / Assistant Project Manager", "description": "The Person\n\nDeliver quality business outcomes, ensuring that projects are delivered within given timeframes, budgets, meet user requirements and appropriately handed over to Operations\nEstablish and manage project operations and governance structures in accordance with DMS Project Framework and guidelines\nEffectively control and manage Changes, Issues and Risks associated with projects\nControl project design and planning activities associated with projects\nDefine, source & manage necessary project resources\nDevelop and control project schedules to ensure that necessary activities are completed according to the project plan\nPrepare and report on project budgets, monitoring and tracking project financials and the realization of defined project benefits\nManage customer expectations to ensure customer satisfaction through the application of stakeholder management disciplines\nThe Job\nDegree holder in Information System, Information Technology or other related discipline\nHolder of PMP or PRINCE2 is preferred\nPreferable with ITIL V3.0 qualification and holder of Six Sigma Green Belt is an advantage\n5-7 years\u2019 working experience in customer servicing industries with 2-4 years\u2019 or above relevant project management experience\nGood knowledge on MS Office, MS Project and MS Visio\nExcellent analytical skill and customer/user management skill is required\nExcellent interpersonal and communication skill\nSelf-motivated character with \u201ccan-do\u201d attitude and proven multi-tasking ability to meet critical deadlines\nWell organized, result-oriented and having good problem solving skill with detail analytical mind\nGood command of both written and spoken English and Chinese\nCandidate with less experience will be considered as Assistant Project Manager / Project Executive \u00a0\nWe are an equal opportunity employer, offer\u00a05-day week (from 9am to 5:30pm), attractive incentive, shuttle bus service, training opportunity and medical benefits. Interested applicants shall submit a full resume indicating current and expected salary with soonest availability.\n\nAll information provided will be treated in strict confidence and used for recruitment purposes only. Applicants not hearing from us within six weeks may consider their applications unsuccessful. All data of unsuccessful applications will be destroyed after six months.\n\n", "employment_types": ["Full Time", "Permanent"], "selling_points": ["With 5-7 years\u2019 customer servicing experience", "Monitor the projects' progress and outcomes", "5-day work, 9:00am - 5:30pm"], "locations": ["Chai Wan"], "categories": ["Information Technology (IT)", "IT Project Management / Team Lead", "Support", "IT Management"], "post_time": "2022-01-17T09:02:30Z", "salary": {"currency": null, "max": null, "min": null, "period": "monthly", "term": null}, "salary_visible": false, "title_keywords": ["project manager", "assistant project manager"], "responsibilities": [], "requirements": {"degrees": [], "majors": [], "languages": [], "language_level": [], "hard_skills": [], "soft_skills": [], "languages_combined": []}, "experience_required": {"duration": [], "field": []}}, {"job_id": "100003009054797", "location_code": "hk", "company": "IKEA", "job_title": "IT Technical Specialist (infrastructure)", "description": "WHY YOU WILL LOVE US\n\nWe\u2019re a diverse group of down-to-earth, straightforward people with a passion for home furnishing. We come from all over the world, but we share an inspiring vision: \u201cto create a better everyday life for the many people\u201d. How we realize this vision is based on our shared humanistic values. These values guide our work and build our inclusive, open and honest culture. It\u2019s all based on a spirit of togetherness and enthusiasm. We work hard, but we have fun doing it. We\u2019re always looking for people who share our positive attitude and values.\n\nWHY WE WILL LOVE YOU\n\nYou have 2 years IT-related experience in the retail industry experience, either IKEA or Dairy Farm experience will be the plus\nYou have medium level knowledge of IT infrastructure and basic for Application\nYou have strong passion and comfort to perform daily operational support\nYou are a strong fit with the IKEA Culture and Values\nYou have strong communication and interpersonal skills\nYou are customer service oriented\nYou have logical and creative thinking\nYou have a good command of both written and spoken English\n\nWHAT YOU WILL BE DOING DAY TO DAY\n\nOffer the first tier support service of IT infrastructure to end-users and ensure the robust daily business operation in the stores, services office and warehouse. Infrastructure service scope to cover Store, Service Office and warehouse workplace management, Server operation, Network, Capacity, Basic database administration, IT Security Management, Facility management and appointed projects\nProactive monitor the daily infrastructure or application service and implement the preventive actions & solutions with IKEA IT, Dairy Farm Group IT, contractors or service providers in order to provide first-tier efficient service to store end users\nTo be the store, service office & warehouse focal point of first-tier help desk service, server, storage and network support, record, response or escalate users' incident log to teammates. Ensure the service level was secured and delivered. The purpose is to maintain the high-level service scarification of end-users\nParticipate the in-store, service office and warehouse IT infrastructure projects to assist the planned activities or appointed assignments from line manager\nResponsible for updating the documentation of infrastructure landscape\nAssist to conduct the necessary training to store end users. The purpose to increase the basic IT knowledge of users and reduce the number of incidents\nPerform all daily tasks according to set procedures, rules and guidelines to secure the availability of business application\nEngage with Risk Management for IT security policy to manage and secure the business information in the store. Also, engage with line manager\n\nTOGETHER AS A TEAM\n\nThe Technical Specialist will report to Technical Leader in the market. The key responsibility of this function is to offer excellent professional infrastructure knowledge and engage with practical business operation to fulfill end users requirements. Also, to act as the communication bridge between users and infrastructure service provider to ensure the agreed infrastructure requirement be converted to infrastructure solution for store, services office and warehouse\n\nSTAFF BENEFITS\n\nAnnual Fixed Bonus, 5-Day Work Week, 17 days Public Holiday, Paid Leave (Paid Annual Leave, 14 weeks Maternity Leave, 5 days Paternity Leave, 1 week Marriage Leave), Employee Medical Coverage, Non-Contributory Retirement Plan, Staff Purchase Discount, Birthday Coupon, Referral Bonus, Excellent Career Path\n\nPersonal data collected will be kept and handled confidentially by authorized personnel for recruitment purposes only. It might also be disclosed to our subsidiaries, associates and agencies authorized to process the information for appointment. The Company will retain the applications of candidates not selected for a maximum period of 24 months after the selection process is finalized. Our Personal Information Collection Statement (PICS) is available at our career site and can be provided upon request by contacting our Human Resources Department. Applicants not heard from us within six weeks may consider their applications filed for future reference.\n\nIssued by The Dairy Farm Company, Limited\n", "employment_types": ["Full Time", "Permanent"], "selling_points": ["First tier support service of IT infrastructure", "Monitor daily infrastructure or applications", "Participate in IT infrastructure projects"], "locations": ["Shatin Area"], "categories": ["Information Technology (IT)", "Support", "IT Management", "Others"], "post_time": "2022-01-17T11:08:03Z", "salary": {"currency": null, "max": null, "min": null, "period": "monthly", "term": null}, "salary_visible": false, "title_keywords": ["technical specialist"], "responsibilities": ["business operation", "management", "operational support", "it infrastructure", "guidelines", "infrastructure", "monitor", "procedures", "communication", "it security management", "customer service", "maintain", "database", "documentation", "report", "administration"], "requirements": {"degrees": [], "majors": [], "languages": ["english"], "language_level": ["good command"], "hard_skills": ["plus", "documentation", "basic", "security management", "fun", "focal", "basic it knowledge", "server"], "soft_skills": ["efficient", "proactive", "customer service oriented", "passion for", "responsible", "robust", "positive attitude", "diverse", "communication", "communication and interpersonal skills", "inspiring", "honest", "creative"], "languages_combined": [{"language": "english", "language_level": ["good command"]}]}, "experience_required": {"duration": ["2 years"], "field": ["related", "it", "retail industry"]}}, {"job_id": "100003009054464", "location_code": "hk", "company": "Automated Systems (HK) Ltd", "job_title": "Assistant Project Manager", "description": "Responsibilities:\n\nTo deliver project management service including project planning, task scheduling, control and monitoring of project execution, risk management and progress reporting\nTo manage resource planning, allocation, cost control and ensure the project milestones/deliverables to be completed on time and meet the required quality standard\nTo organize and attend meeting to report progress and resolve any project related issues\nFollow up IT project related issues, co-ordinate and monitor the overall processes and status\nSupport the senior project managers to fulfill their role and provide precise reports and analysis to senior management\n\nRequirements:\n\nBachelor Degree in Computer Science, Information Technology or related disciplines\n1-2 years' experience in end-to-end IT project management with proven track record\nExperience in PC migration and relocation projects is a plus\nExcellent and effective communication skills in both English and Chinese with the ability to engage, influence, and inspire partners and stakeholders to drive collaboration and alignment\nWe offer 5-day week, public holidays, medical benefits, excellent career opportunities, considerable remuneration to the right candidates.\n\n\u201cIf you have the desire for an exciting and rewarding career, please send us your resume, stating your notice period, present and expected salary to Human Resources Department by clicking \"Apply Now\".\n\nTo learn us more, please visit our website: www.asl.com.hk\n\nWe are an equal opportunity employer. All applications will be treated in strict confidence. We regret that only shortlisted candidates will be notified. All personal data will be destroyed within six months after the selection process.\n%MCEPASTEBIN%", "employment_types": ["Full Time", "Contract"], "selling_points": ["To deliver project management service", "Bachelor Degree in Computer Science", "1-2 years' experience"], "locations": ["Lantau Island"], "categories": ["Information Technology (IT)", "IT Project Management / Team Lead", "IT Management", "Software Development"], "post_time": "2022-01-17T09:40:01Z", "salary": {"currency": null, "max": null, "min": null, "period": "monthly", "term": null}, "salary_visible": false, "title_keywords": ["assistant project manager"], "responsibilities": ["reporting", "project planning", "control", "management", "analysis", "monitoring", "quality", "monitor", "project management", "scheduling", "reports", "cost control", "report", "senior management", "planning"], "requirements": {"degrees": ["degree", "bachelor"], "majors": ["related disciplines", "computer science", "information technology"], "languages": ["english", "chinese"], "language_level": ["excellent"], "hard_skills": ["pc", "project management", "plus"], "soft_skills": ["communication skills", "project management"], "languages_combined": [{"language": "english", "language_level": ["excellent"]}, {"language": "chinese", "language_level": ["excellent"]}]}, "experience_required": {"duration": ["1-2 years"], "field": ["project management", "it"]}}, {"job_id": "100003009052978", "location_code": "hk", "company": "JFE Consulting Limited", "job_title": "Project Manager - IT", "description": "Our client, one of the leading IT companies, is looking for high calibres to join their winning team:-\n\nResponsiblities:\n\n\n\nAdvanced computer skills and in-depth knowledge of different operating systems, network administration and service desk administration\nProject management and leadership skills for managing projects and the teams involved with themStrong written and verbal communication skills to coordinate with team members and management and explain technical issues\nAnalytical and problem-solving skills to handle any issues that occur during project completion\n\nRequirements:\n\nBachelor Degree in Information Technology or equivalent.\n10 years of IT experience or above with 6 years or above experience of project management in web application implementation projects\nUnderstanding of MSP ticketing and Alert Management Systems.\nThorough understanding of project management fundamentals.\nUnderstanding of software development life cycle\nOutstanding leadership, organizational, and time management skills.\nOutstanding verbal and written communication skills.\nStrong people skills.", "employment_types": ["Full Time", "Permanent"], "selling_points": ["Project Management", "IT industry", "10+ years of experience, attractive salary"], "locations": ["Quarry Bay"], "categories": ["Information Technology (IT)", "IT Project Management / Team Lead", "IT Management", "Product Management / Business Analyst"], "post_time": "2022-01-17T04:48:24Z", "salary": {"currency": null, "max": null, "min": null, "period": "monthly", "term": null}, "salary_visible": false, "title_keywords": ["project manager"], "responsibilities": ["network administration", "management", "teams", "coordinate with", "communication", "project management", "operating systems", "administration"], "requirements": {"degrees": ["degree", "bachelor"], "majors": ["information technology"], "languages": [], "language_level": [], "hard_skills": ["project management", "web"], "soft_skills": ["communication skills", "time management skills", "organizational", "project management", "thorough", "leadership"], "languages_combined": []}, "experience_required": {"duration": ["6 years", "10 years"], "field": ["project management", "it experience"]}}, {"job_id": "100003009055935", "location_code": "hk", "company": "Crystal International Group Limited", "job_title": "Manager - Finance System", "description": "Responsibilities:\n\nParticipate in SAP S/4HANA migration project planning and deployment\nFormulate user guideline and provide training; monitor the system control, governance and compliance\nLead finance system transformation and process reengineering for the Group\nSupport ad hoc projects as assigned\n\nRequirements:\n\nDegree holder in IT / Computer Science, Finance / Accounting or related discipline\nMinimum 5 years of experience in implementing SAP FICO, SAP certification in FICO will be an advantage, preferably with S/4HANA and manufacturing experience\nSound knowledge in finance operation and understanding of finance, taxation and accounting principles\nLogical, systematic with good presentation skill; Proficiency in MS Excel and PowerPoint\nStrong sense of responsibility and able to prioritize and work under pressure\nProficient in written and spoken English and Chinese including Mandarin\nWilling to take up ad hoc tasks and travel", "employment_types": ["Full Time"], "selling_points": ["Degree holder in IT / Computer Science, Finance / Accounting or related discipline", "Minimum 5 years of experience in implementing SAP FICO", "Double Pay & Discretionary Bonus"], "locations": ["Kwun Tong"], "categories": ["Information Technology (IT)", "Application Specialist - Software", "IT Project Management / Team Lead", "IT Management"], "post_time": "2022-01-18T03:06:18Z", "salary": {"currency": null, "max": null, "min": null, "period": "monthly", "term": null}, "salary_visible": false, "title_keywords": ["manager"], "responsibilities": ["provide training", "project planning", "control", "compliance", "monitor", "ad hoc projects", "migration"], "requirements": {"degrees": ["degree holder"], "majors": ["finance", "it", "accounting", "computer science"], "languages": ["english", "chinese", "mandarin"], "language_level": ["proficient"], "hard_skills": ["presentation skill", "ms excel", "sap", "powerpoint"], "soft_skills": ["presentation skill", "able to prioritize", "sense of responsibility", "systematic", "work under pressure"], "languages_combined": [{"language": "english", "language_level": ["proficient"]}, {"language": "chinese", "language_level": ["proficient"]}, {"language": "mandarin", "language_level": ["proficient"]}]}, "experience_required": {"duration": ["minimum 5 years"], "field": ["manufacturing"]}}, {"job_id": "100003009052809", "location_code": "hk", "company": "HomePlus (Hong Kong) Limited (HOME+)", "job_title": "(Senior) IT Manager", "description": "The purpose to you with this career opportunity will be...\n\nDrive project management and implementation of E-Commerce platform to support E-Commerce Business\nLeading a highly dynamic and innovative team in Agile/Scrum approach, to implement new projects, maintain and support change request\n\nWhat efforts you need to make for this role?\n\nAccountable for managing the design, implementation and delivery of E-Commerce Website to meet the E-Commerce business requirements and needs\nHave a deep understanding and hands-on experience in cloud architecture design, web application development, API development and troubleshooting\nPlan and procure external/internal resources according to the scope and budget of the project; manage and maintain that resource plan\nLiaise with software vendors and the business team to coordinate new website modules implementation, integrating functionalities across applications or modules, and maintenance activities\nProduce and communicate internal and external project status reports and maintain all necessary project documentation\nManage business requirements and lead the analysis, design, development, testing, release and maintenance\nWorks independently with minimal supervision; act as subject matter expert\nFollows applicable standards, policies, procedures, and best practices in the implementation and/or maintenance of applications or application modules\nPerforms other duties as requested\n\nLet's check if you are/ have\u2026\n\nDegree holder in Computer Science, Engineering or equivalent\nMinimum of 10-15 years related professional experience in IT, including\u00a05 years\u00a0at\u00a0management position\nMinimum of 6 years E-Commerce Website Implementation experience\nHas experience for payment gateway implementation e.g. AliPay, Global Payment, PayMe, WeChat Pay, etc.\nDemonstrated ability to understand business processes from a customer perspective, identify technical enablers, procedural re-engineering solutions and process improvements that meet business needs across the organization\nExcellent skills to work in cross-team environment, effectively interacting with internal & external parties, both written & verbal\nProven working experience in Project Management, with solid organizational skills including attention to detail and multitasking skills\nHands on experience on\u00a0Magento 2\u00a0is a plus\nProject Management Professional / Scrum / Agile certification is a plus\nExperience on AWS / Azure / DevOps is an advantage\nExperience on architecture design, Kubernetes, containers, micro-services, message queue is an advantage\n\nWhat you get in return\u2026\n\nApart from competitive salary package and benefits, in HKBN, you will work flexibly under our Talent-first culture\u00a0and we uphold Life-Work Priority. Examples of our flexible initiatives:\n\nFive-day work week and shorten working hours (8 hours including 1 hour 15 mins meal break)\nHalf Day Off Friday once a month (compensation leave for Talents who work on shift)\nHalf Day Off on Festival Eve (compensation leave for Talents who work on shift)\nUnique leaves arrangement: Family-care leave, Anniversary leave, Bonus leave, Volunteer leave, Sabbatical leave, etc.\nComprehensive medical and life insurance coverage\nUpgraded maternity leave and paternity leave\nDiscounted Talent plan offers including broadband and mobile plans and other promoted products\nEducation subsidies and Examination leave\nYear-end discretionary bonus", "employment_types": ["Full Time"], "selling_points": ["Handson exp. in Cloud Architect (AWS) & Magento 2", "Agile & Flexible working culture with great team", "Join Us if You're Passionate about E-commerce"], "locations": ["Kwai Hing"], "categories": ["Information Technology (IT)", "IT Management", "Application Specialist - Network", "E-commerce", "Product Management / Business Analyst"], "post_time": "2022-01-17T04:23:54Z", "salary": {"currency": null, "max": null, "min": null, "period": "monthly", "term": null}, "salary_visible": false, "title_keywords": ["it manager"], "responsibilities": ["software", "budget", "external parties", "website", "design", "troubleshooting", "payment", "maintain", "plan", "liaise with", "application development", "project documentation", "other duties", "implementation", "testing", "reports", "architecture", "re-engineering", "management", "procedures", "maintenance", "policies", "analysis", "subject matter expert", "coordinate", "project management", "e-commerce platform"], "requirements": {"degrees": ["degree holder"], "majors": ["engineering", "computer science"], "languages": [], "language_level": [], "hard_skills": ["plus", "web application development", "agile", "maintenance", "e-commerce", "project management professional", "azure", "analysis", "devops", "wechat", "aws", "project management", "make", "dynamic", "documentation"], "soft_skills": ["organizational skills", "independently", "agile", "deep", "accountable", "troubleshooting", "project management", "hands-on", "dynamic", "hands on", "attention to detail", "innovative"], "languages_combined": []}, "experience_required": {"duration": ["5 years", "minimum of 6 years", "minimum of 10-15 years"], "field": ["e-commerce", "related", "development", "devops", "troubleshooting", "design", "management position", "project management", "it", "application development"]}}, {"job_id": "100003009054275", "location_code": "hk", "company": "CHOW TAI FOOK JEWELLERY CO LTD", "job_title": "Information Technology Manager (Strategic Planning)", "description": "What You Do\nAssist in establishing IT strategic plan, formulating roadmaps for both short and long terms, and setting performance metrics on the expected outcomes\nManage strategic and complex projects according to Group\u2019s IT strategic plan\nDevelop and coordinate annual IT strategies, financial plans and integrated planning processes to ensure IT strategic alignment across the Group\nDevelop reliable performance data and insightful analysis methodology to drive IT strategic planning process and analyze technology trends, regulatory impacts and competitors\u2019 activities\nTake a leading role to engage senior management team across the Group and align the Group\u2019s IT strategic goals and integrated plan\nMonitor and evaluate the progress of key IT initiatives against the Group\u2019s objectives\nBuild strong relationships with other IT members and align departmental priorities, strategies, and resources with the IT department\u2019s mission and strategic goals\nAny other IT projects and assignments as assigned\n\u00a0Who Will Thrive\nBachelor\u2019s degree in information technology, computer science or related discipline with at least 5 years of progressive experience in information application systems, infrastructure or integration development support in a production environment. IT advisory or retail IT experiences is a plus\nExtensive experience in developing IT strategies or other initiatives including measurable plans\nSolid experience in managing large and complex information systems and projects with strong commitment\nKnowledge of administrative practices in an in-house IT environment is an advantage\nExcellent ability in the development of business cases and presentation materials in a clear and concise manner\nA self-starter with strong decision-making skills and ability to work under pressure\nBe able to translate the needs and data into formal designs, and have strong organizational, supervisory and interpersonal skills to work effectively with a wide variety of internal and external resources\nAn active listener with ability to discern fact from various opinions and respond to others with proof\nExcellent written and verbal communication skills (English and Mandarin, where applicable)\nCandidates with less experience will be considered as Assistant Manager\nBenefits\n5-day work\nCompetitive salary, staff meal, medical and dental insurance, life insurance\nVarious types of leave, e.g. Family-friendly leave, self-development leave,\u00a0Examination leave, marriage leave, birthday leave, volunteer service leave, etc\nWe offer excellent career opportunities, attractive remuneration package & benefits to the right candidate.\u00a0Interested parties please apply by clicking \"Apply Now\" with a full resume stating the latest and expected salary.\n\nAll information collected will be used for recruitment purposes only.\n", "employment_types": ["Full Time"], "selling_points": ["Manage strategic and complex projects", "Drive process improvement to cater business needs", "Explore innovative technologies"], "locations": ["Kwai Hing"], "categories": ["Information Technology (IT)", "IT Management"], "post_time": "2022-01-17T09:01:08Z", "salary": {"currency": null, "max": null, "min": null, "period": "monthly", "term": null}, "salary_visible": false, "title_keywords": ["technology manager"], "responsibilities": ["data", "infrastructure", "systems", "developing", "communication", "plans", "application systems", "work under pressure"], "requirements": {"degrees": [], "majors": [], "languages": [], "language_level": [], "hard_skills": ["analysis"], "soft_skills": ["reliable"], "languages_combined": []}, "experience_required": {"duration": [], "field": []}}, {"job_id": "100003009052962", "location_code": "hk", "company": "NexLen Internationl Limited", "job_title": "Technical Manager", "description": "Job Responsibilities\n\nOversee the warehouse, technical support and maintenance department\nHelp define IT infrastructure strategy, architecture, and processes\nConduct pre-sales and consultative activities\nAssess vendors and develop test strategies for new hardware and software\nMonitors warehouse employee productivity / quality\nEstablish and implement training processes and strategies for all technical personnel\nAssigning, checking, organizing, prioritizing, and scheduling work orders to / for Support Technician and Maintenance Technician ensuring work orders and completed in a timely manner\nHold regular technical team meetings to determine progress and address any questions or challenges regarding projects\nRecruit and train exceptional employees to fulfill posted positions within the technical department\u00a0\n\nRequirements\n\n5-8 years' solid working experience in Network and Cybersecurity or Technical Support\nDegree / High Diploma in information engineering or equivalent\nCertifications in IT industry (CISSP / CCNA / CCNP / etc.) is an advantage\nStrong experience in IT technology and system like infrastructure, cloud, networking, WiFi, Firewall, etc. Experience in Electric Engineering would be an advantage\nCustomer-oriented and excellent interpersonal skills, including verbal and written communication in English, Cantonese, and Mandarin\nGood team player, target-oriented with strong analytical and problem-solving skills\nWe offer attractive salary and fringe benefit package to the right candidate. Interested parties please send full resume with expected salary.\n\n\nPersonal data provided in your application will be kept in the strictest confidence. It will be used for employment-related purposes. Applications not notified within 1 month will be considered as unsuccessful. Unsuccessful application may be kept for another 3 months for new openings before properly shredded.", "employment_types": ["Full Time", "Permanent"], "selling_points": ["Attractive salary package", "5-8 years' solid experience in network", "CCNA/CCNP/CISSP/CCSA/MCSE/MCITP"], "locations": ["Kwun Tong"], "categories": ["Information Technology (IT)", "IT Project Management / Team Lead", "IT Management", "Network & System"], "post_time": "2022-01-17T04:42:31Z", "salary": {"currency": null, "max": null, "min": null, "period": "monthly", "term": null}, "salary_visible": false, "title_keywords": ["technical manager"], "responsibilities": ["it infrastructure", "maintenance", "software", "technical support", "quality", "checking", "a timely manner", "develop", "hardware", "scheduling", "architecture"], "requirements": {"degrees": ["high diploma", "degree"], "majors": ["engineering"], "languages": ["cantonese", "english", "mandarin"], "language_level": ["excellent"], "hard_skills": ["problem-solving skills", "ccnp", "ccna", "firewall"], "soft_skills": ["good team player", "communication", "customer-oriented", "interpersonal skills", "problem-solving skills"], "languages_combined": [{"language": "cantonese", "language_level": ["excellent"]}, {"language": "english", "language_level": ["excellent"]}, {"language": "mandarin", "language_level": ["excellent"]}]}, "experience_required": {"duration": ["5-8 years"], "field": ["infrastructure", "it", "engineering"]}}, {"job_id": "100003009053975", "location_code": "hk", "company": "Nanyang Commercial Bank, Limited", "job_title": "Senior Information Technology Manager \u2013 System Operation (JB8006-SO-CT)", "description": "Requirements:\nDegree holder in Computing, Information Technology, Electronic Engineering, Mathematics, Statistics or related disciplines;\n\nAt least 10 years of relevant working experience in the banking industry, with at least 5 years in IT management or system operation aspect;\n\nHands on experience in system operation role;\n\nSound knowledge in the operation on systems, data center, network, information security and etc.\n\nGood experience in open platform, network, SAN/NAS/network;\n\nGood communication skill and project implementation capability with high self-motivation\n\nWith qualification of CCNA/CCNP/CCIE/MCSE will be an added advantage;\n\nProficient in both spoken and written English and Chinese, fluent in Putonghua is preferable.\n\n(Candidate with less experience will be considered as Information Technology Manager.)\n\nIf you are flexible enough and zeal for a harmonious and supportive working environment where enables you to grow and succeed professionally, please send a full resume indicating your public examination results (HKCEE and HKALE / HKDSE), your present and expected salary and quoting reference number attention to Talent Acquisition Division, Nanyang Commercial Bank, 151 Des Voeux Road Central, Hong Kong or apply through email. For details, please visit https://www.ncb.com.hk/ and select the page Recruit .\n\nWe are an Equal Opportunities Employer. Data collected would be used for recruitment purposes only. Applicants who do not hear from us within 8 weeks may consider their applications unsuccessful and their data will be destroyed within 12 months of receipt.", "employment_types": ["Full Time"], "selling_points": [], "locations": ["Not Specified"], "categories": ["Information Technology (IT)", "IT Management", "Network & System"], "post_time": "2022-01-17T07:53:28Z", "salary": {"currency": null, "max": null, "min": null, "period": "monthly", "term": null}, "salary_visible": false, "title_keywords": ["technology manager"], "responsibilities": ["information security", "data", "systems", "implementation", "communication", "it management", "recruitment", "banking"], "requirements": {"degrees": ["hkdse", "degree holder"], "majors": ["mathematics", "engineering", "statistics", "information technology", "related disciplines"], "languages": ["putonghua", "english", "chinese"], "language_level": ["fluent", "proficient"], "hard_skills": ["nas", "mcse", "ccnp", "ccna"], "soft_skills": ["flexible", "supportive", "harmonious", "communication skill", "hands on", "self-motivation"], "languages_combined": [{"language": "putonghua", "language_level": ["fluent", "proficient"]}, {"language": "english", "language_level": ["fluent", "proficient"]}, {"language": "chinese", "language_level": ["fluent", "proficient"]}]}, "experience_required": {"duration": ["at least 10 years", "at least 5 years"], "field": ["banking industry", "management", "relevant working experience", "information technology", "it", "operation"]}}, {"job_id": "100003009050608", "location_code": "hk", "company": "", "job_title": "Deputy Head of Digital Solution", "description": "Responsibilities:\n\nAssist the CTO to drive the IT strategy and direction & work closely with the senior executive leaders to understand the organizational needs and long-term vision.\nManage a large technology division compose of application, infrastructure, and security.\nIdentify the latest technology and development in order to help the organization develop new Fintech initiatives.\nManage and maintain the IT strategy and policies to achieve high safety and efficiency to comply with the regulatory requirements.\nManage the IT budget and resources across all multiple teams involved in the development and/or support activities\n\nRequirements:\n\nBachelor's Degree in Computer Science / Engineering from a reputable University.\nA strong proven track record of leading a large IT division and operations including application development and infrastructure management.\nStrong experience in managing all-rounded IT services, ideally from the Retail / F&B environment.\nProject management experience in planning, budgeting, and architecture design.\nStrong verbal and communication skills to interact with senior management, team members, and vendors, etc.\n\nJob Offer:\n\n5 day work week\nCompetitive Salary Package\n13 months' Guaranteed Salary\nPerformance Incentives\nGroup Medical Scheme\nBirthday Leave\nEnergetic & Dynamic Culture\nInterested candidates, please contact us at 67570958 for company details before applying.", "employment_types": ["Full Time", "Permanent"], "selling_points": ["Drive the IT strategy and direction", "Manage and maintain the IT strategy and policies", "Manage the IT budget and resources"], "locations": ["Lai Chi Kok"], "categories": ["Management", "General Management", "Information Technology (IT)", "IT Management", "Top Executives (CEO, CFO, CTO, GM, MD etc.)"], "post_time": "2022-01-14T11:06:18Z", "salary": {"currency": null, "max": null, "min": null, "period": "monthly", "term": null}, "salary_visible": false, "title_keywords": [], "responsibilities": ["policies", "regulatory requirements", "infrastructure", "teams", "develop", "it budget", "maintain"], "requirements": {"degrees": ["degree", "bachelor"], "majors": ["engineering", "computer science"], "languages": [], "language_level": [], "hard_skills": ["project management", "dynamic", "scheme"], "soft_skills": ["communication skills", "project management", "dynamic", "energetic"], "languages_combined": []}, "experience_required": {"duration": [], "field": ["design", "project management", "f&b", "it", "retail", "planning"]}}, {"job_id": "100003009051820", "location_code": "hk", "company": "John Swire & Sons (HK) Limited", "job_title": "IT & Digital Portfolio Manager", "description": "Our IT & Digital section invites applications for the following position:\n\nIT & Digital Portfolio Manager\n\nThis role provides the opportunity for an experienced IT & Digital expert to influence the development of digital capability for the Company. The job holder would develop a holistic view of different IT & Digital initiatives, define process and value analysis to ensure different initiatives are enabled appropriately.\n\nResponsibilities:\n\nProvide strategic inputs on IT & Digital Portfolio management, define value analysis and mitigate risks to ensure a holistic and balanced investment\nDrive the development of digital capability, especially in innovation, self-service, and experimental mindset in product implementation and data usage\nDevelop framework, guidelines and process for quality governance and project life-cycle management\nOwn and manage IT programme planning, budgeting, reporting, and project governance\nManage internal and external IT communications on programmes and initiatives, document sharing mechanisms, and deliver training on new IT capabilities\nKeep abreast of latest advancement in the industry such as tools, techniques and applications\n\nRequirements:\n\nBachelor\u2019s degree or above in Information Management, Business or related discipline\nAt least 8 years\u2019 experience in managing enterprise project implementation\nProven record in project delivery lifecycle at an enterprise level, and managing investments in multiple and cross-function projects\nExperienced in digital transformation and developing a digital culture for service and produce implementation via experiential learning\nExcellent communication skills, and strong business acumen with an in-depth knowledge on technology enablement\nProfessional qualifications in project management methodology and process management framework would be advantageous\nApplication:\n\nWe offer a competitive package to the right candidate. If you meet the qualifications and are interested in this position, you can send your application by clicking \"Apply Now\". Please note that only shortlisted candidates will be contacted.\n\nWe are an equal opportunity employer. All applications received will be used exclusively for selection purposes and handled confidentially by authorised personnel only. Your application may also be considered for other suitable positions within the Swire group (please indicate clearly on your application if you would not like to be considered for other positions within the group.) Unsuccessful applications will be destroyed after an appropriate time.\n\nThe Swire Group is committed to creating an inclusive and supportive working environment for all our people regardless of their age, gender, gender identity, sexual orientation, relationship, family status, disability, race, ethnicity, nationality, religious or political beliefs. We believe in creating an environment where people feel comfortable at work and able to realise their full potential.", "employment_types": ["Full Time"], "selling_points": ["Portfolio management", "Digital transformation", "Project management"], "locations": ["Quarry Bay"], "categories": ["Information Technology (IT)", "IT Project Management / Team Lead", "IT Management"], "post_time": "2022-01-17T01:17:03Z", "salary": {"currency": null, "max": null, "min": null, "period": null, "term": null}, "salary_visible": false, "title_keywords": ["manager"], "responsibilities": ["reporting", "management", "data", "guidelines", "budgeting", "analysis", "quality", "implementation", "develop", "planning"], "requirements": {"degrees": ["degree or above", "bachelor"], "majors": ["business"], "languages": [], "language_level": [], "hard_skills": ["project management", "professional qualifications", "acumen"], "soft_skills": ["business acumen", "communication skills", "project management", "learning"], "languages_combined": []}, "experience_required": {"duration": ["at least 8 years"], "field": []}}, {"job_id": "100003009053040", "location_code": "hk", "company": "PeopleLink Services Limited", "job_title": "Head Of Information Security (Finance / Insurance)", "description": "Responsibilities:\n\nWork closely with Local and Global Information Security team to develop and implement security policies, protocols and procedures.\nBuild a strong information security team and provide proper leadership and continuous coaching to the team members.\nCommunicate to senior leadership on key strategies and any risk/issues with respect to Information Security.\nEnsure the company comply to regulatory requirements on Information Security.\nInitiate, develop, and maintain information security policies and procedures and to ensure that the security strategies are being followed, so as to meet the organizational security goals and standards.\nIdentify the security risks involved and resolve them, to perform assessment of security risks and to function as an auditor for security.\nDocument all the security policies and to promote activities and procedures to create a general awareness about the significance of security within an organization.\nReview the security plans that have been implemented on the systems throughout the entire network of the organization, thus acting as an information security consultant.\nAct as a liaison to the department of information system and to monitor its compliance and direct the unsolved issues to the appropriate department.\nMonitor the security controls for security breaches and investigate violations.\nDirect the installation and use of security tools (e.g., firewalls, data encryption), to protect sensitive information.\nEnsure that IT security audits are conducted periodically or as needed (e.g., when a security breach occurs)\nResearch the latest information technology security trends\n\nRequirements:\n\nA bachelor\u2019s degree in information technology or computer science is required.\nWith certification in information security (CISSP, CSSLP, CCFP, CISM, etc.) or comparable work experience will be given preference. Cyber Security, Compliance, Risk analysis or assessment experience a plus.\n8 years of related work experience, with 5 or more in an information security position is required.\nGood analytical and problem-solving abilities to identify and fix security risks.\nAble to demonstrate a positive, logical, and proactive approach while executing the assigned tasks.\nGood team working skills to develop security solutions in collaboration with other information technology professionals.\nLess experience will be considered as Senior Information Security Manager\n\nPlease submit your resume with current and expected salary. All applications will be treated strictly confidential for recruitment purpose only. Un-seclected candidates will be considered for other vacancies", "employment_types": ["Full Time", "Permanent"], "selling_points": ["Information Security, Cyber Security", "IT Security Compliance, Audit, Control", "Leadership, People Management"], "locations": ["Not Specified"], "categories": ["Information Technology (IT)", "IT Management", "Security", "Network & System"], "post_time": "2022-01-17T05:19:51Z", "salary": {"currency": null, "max": null, "min": null, "period": "monthly", "term": null}, "salary_visible": false, "title_keywords": [], "responsibilities": ["installation", "information security", "data", "policies", "regulatory requirements", "review", "procedures", "systems", "monitor", "develop", "compliance", "maintain", "audits", "plans"], "requirements": {"degrees": ["degree", "bachelor"], "majors": ["computer science", "information technology"], "languages": [], "language_level": [], "hard_skills": ["problem-solving", "analysis", "plus", "cyber security"], "soft_skills": ["team working", "problem-solving", "proactive", "positive"], "languages_combined": []}, "experience_required": {"duration": ["8 years"], "field": ["related", "compliance", "security"]}}, {"job_id": "100003009048591", "location_code": "hk", "company": "CITIC Telecom International Holdings Limited", "job_title": "IT Security Specialist", "description": "Main Duties & Responsibilities:\n\n\nMonitor and support the information security and IT governance based on international IT security standards including but not limited to ISO 27001\nDevelop, maintain and enforce information security policy, procedure and guideline according to industry standard, company policy and regulatory requirements\nPerform regular cybersecurity assessment for company systems and operation process\nReview and provide professional advice on application logical access and identity management, hardening, security monitoring and vulnerability management\nIntroduce the latest information security technology and policy to the organization\nConduct security incident management, investigation and reporting\nWork closely with project teams and vendors to ensure the development cycle and deliverables comply with all necessary security policies and standards.\nOrganize security training and motivate security awareness among the group\nWork closely with internal and external IT Auditors\n\nRequirements:\n\n\nBachelor\u2019s Degree holder in IT or related disciplines\nAt least 5-10 years of relevant experience in IT security, preferably in FSI\nGood knowledge and experience with security infrastructure (e.g.: Privileges ID management, Endpoint security)\nProblem-solving aptitude, well-organized, self-motivated and able to work under pressure\nExcellent communication, interpersonal skills\nProficiency in Chinese and English, both written and verbal communications\n\nWe offer:\n\n\u00a0\u00a0\u00a0\u00a0\u00a0\u00a0\u00a0 Discretionary bonus\n\u00a0\u00a0\u00a0\u00a0\u00a0\u00a0\u00a0 Medical insurance\n\u00a0\u00a0\u00a0\u00a0\u00a0\u00a0\u00a0 Dental insurance\n\u00a0\u00a0\u00a0\u00a0\u00a0\u00a0\u00a0 Hardship allowance\n\u00a0\u00a0\u00a0\u00a0\u00a0\u00a0\u00a0 Competitive annual leave days\n\u00a0\u00a0\u00a0\u00a0\u00a0\u00a0\u00a0 Birthday leave\n\u00a0\u00a0\u00a0\u00a0\u00a0\u00a0\u00a0 Anniversary leave\n\u00a0\u00a0\u00a0\u00a0\u00a0\u00a0\u00a0 Study leave\n\u00a0\u00a0\u00a0\u00a0\u00a0\u00a0\u00a0 Marriage leave\n\u00a0\u00a0\u00a0\u00a0\u00a0\u00a0\u00a0 Compassionate leave\n\nHow to apply:\n\nInterested parties, please send your resume stating your expected salary to Human Capital Department\u00a0by clicking \"APPLY NOW\".\n\n(We are an equal opportunity employer.\u00a0 Personal data collected will be used for recruitment purpose only.\u00a0 The unsuccessful applications will be destroyed after 6 months.)", "employment_types": ["Full Time", "Permanent"], "selling_points": ["Develop and maintain IT security policies", "Main focal point for IT security related matters", "Double Pay, Bonus, 5-day work, Medical & Dental"], "locations": ["Kwai Fong"], "categories": ["Information Technology (IT)", "IT Management", "Security", "Others"], "post_time": "2022-01-14T06:52:06Z", "salary": {"currency": null, "max": null, "min": null, "period": "monthly", "term": null}, "salary_visible": false, "title_keywords": ["specialist"], "responsibilities": ["reporting", "management", "information security", "regulatory requirements", "policies", "systems", "monitor", "review", "monitoring", "develop", "investigation", "teams", "maintain", "vulnerability management"], "requirements": {"degrees": ["bachelor", "degree holder"], "majors": ["related disciplines", "it"], "languages": ["english", "chinese"], "language_level": ["proficiency"], "hard_skills": ["id", "problem-solving"], "soft_skills": ["self-motivated", "problem-solving", "well-organized", "communication", "interpersonal skills", "work under pressure"], "languages_combined": [{"language": "english", "language_level": ["proficiency"]}, {"language": "chinese", "language_level": ["proficiency"]}]}, "experience_required": {"duration": ["at least 5-10 years"], "field": ["infrastructure", "it", "relevant experience", "security"]}}, {"job_id": "100003009052769", "location_code": "hk", "company": "Konew Financial Express Ltd", "job_title": "Information Security Manager", "description": "Job Description\nWith ever-increasing growth and expansion, we are looking for a new technical Cloud (AWS) Engineer to join our enterprise infrastructure team. Ideally, this technical hand-on Cloud (AWS) Engineer has extensive experience implementing cloud (AWS) and other related security and infrastructure enterprise projects. In addition to this, this Engineer would be providing ongoing technical internal support.\n\nResponsibilities:\n\nCloud, infrastructure and security project implementation, which includes working with the respective vendors.\nPerform and oversee software installation, upgrades and maintenance, remediate vulnerabilities and keep patch updates to systems\nDevice configuration of switch, server, firewall, Email support systems, anti-spam etc.\nL2 technical IT helpdesk support\n\nMinimum Requirements:\n\n3-5 years of technical cloud(AWS) implementation experience\n3-5 years experience in Infrastructure management, network administration, and network security related experience\nStrong team player with a proactive and willingness to learn attitude\nProfessional certification in Cisco Certified Network Associate (CCNA), Microsoft Certificated System Engineer (MCSE), System Administrator (MCSA) or equivalent\nUniversity degree in Computer Science, Information Systems or other technology-related disciplines\nFluent in both spoken and written English and Chinese\n\nHighly Preferred:\n\nExperience with Microsoft 365 (Office 365)\nKnowledge on Cybersecurity market standards like CISSP (Certified Information Systems Security Professional)\nEnterprise financial institution exposure (insurance or banking)\n\nFor strong candidates with less experience, they will be considered for a Cloud Engineer position.", "employment_types": ["Full Time"], "selling_points": ["Protect company asset from cybersecurity risk", "Drive cybersecurity enhancement program", "Comply with all necessary security policies"], "locations": ["Central"], "categories": ["Information Technology (IT)", "IT Management", "Security", "Network & System"], "post_time": "2022-01-17T03:59:26Z", "salary": {"currency": null, "max": null, "min": null, "period": "monthly", "term": null}, "salary_visible": false, "title_keywords": ["information security manager"], "responsibilities": ["installation", "software", "maintenance", "upgrades", "configuration", "infrastructure", "systems", "implementation"], "requirements": {"degrees": ["university degree"], "majors": ["related disciplines", "computer science"], "languages": ["english", "chinese"], "language_level": ["fluent"], "hard_skills": ["network administration", "mcse", "office 365", "ccna", "mcsa", "cisco certified network associate"], "soft_skills": ["team player", "proactive"], "languages_combined": [{"language": "english", "language_level": ["fluent"]}, {"language": "chinese", "language_level": ["fluent"]}]}, "experience_required": {"duration": ["3-5 years"], "field": ["network administration", "management", "related", "infrastructure", "security"]}}, {"job_id": "100003009055044", "location_code": "hk", "company": "Generali Life (Hong Kong) Limited", "job_title": "Cloud (AWS) Engineer / Assistant Manager", "description": "What you will do\n\nAs a Commercial IT Solution Architect you will be part of a team of Architects in our Sales Centre of Excellence who are focused on harnessing the power of technology to enable our sales objectives and excellent customer experience in Johnson Controls.\n\nYou will work with our business and IT stakeholders to conceive and design sales technology solutions and support the mapping of requirements to ensure alignment with our enterprise and commercial roadmap, delivering the best technical architecture to fulfill our business and customer needs.\n\nThe Solution Architect for Commercial IT is accountable for designing solutions that enable the Sales and commercial functions of the Johnson Controls Asia Pacific business across various lines of business including:\n\nHVAC and Controls: air systems, chillers, and building automation\nFire Protection: fire detection, protection, suppression, and alarm monitoring\nSecurity Solutions: intrusion detection, access control, video surveillance, and alarm monitoring.\nIndustrial Refrigeration\nThe position operates within a matrixed IT Operating Model in which the Commercial IT Solution Architect is primarily accountable for the design and architectural governance of IT solutions in the Sales/Commercial platforms.\u00a0You will work in collaboration with a broader team of architects from ERP, Marketing, Analytics, RPA and Enterprise teams along with stakeholders from Information Security, Delivery, Program Management, and Business-IT Engagement.\u00a0\n\n\n\nHow you will do it\n\nUse your technical expertise to review, interpret and respond to business requirements to ensure alignment between customer expectations and current or future technology capability.\nDesign and align technology solutions to our target state ecosystem, provide leadership on platform evolution and maturity of our Commercial IT ecosystem.\nDefine and maintain a target state technology evolution roadmap for Commercial IT platforms and ensure alignment with our overall Enterprise Architecture Strategy, IT and Business Stakeholders.\nProvide insights and thought-leadership on industry/functional trends and best practices to guide technology decisions in context to business priorities.\nProvide technical leadership to coordinate, prioritise and define solutions for Commercial projects.\nPrepare Solution Design Documents and work with stakeholders to ensure they are approved\nUnderstand service inter-dependencies and work with cross-functional teams towards technical solutions for multi-tiered systems.\nProvide mentoring and coaching to the delivery teams, peers and other colleagues in the organization\nUse your hands-on experience with technology and skills in communication and negotiation to enable the success of critical projects.\nEnsure standards for technical reviews, peer reviews, and feedback cycles are set and followed\u200b for architecture designs and implementation\nEnsure technical governance is in place across the Commercial platforms for the region\u200b.\nFoster a culture of technical discipline, craftsmanship, innovation, transparency and collaboration\nSupport risk management, regulatory compliance, cybersecurity, and audit remediation activities.\nSupport business continuity and disaster recovery efforts.\nSupport definition and utilization of IT governance processes and policies.\nCollaborate, negotiate, influence, and build relationships at levels with internal and external parties in alignment with Johnson Controls\u2019 key\u00a0values: integrity, teamwork, excellence, and accountability.\n\nWhat we look for\n\nRequired\n\nBachelor\u2019s Degree in Computer Science/ Electrical/Mechanical/Electronics /Instrumentation\n6 years of hands-on experience working with Sales and Customer Experience technologies (e.g. CRM, CPQ, ecommerce) and a thorough understanding of industry trends, vendors, frameworks and practices\nCertified Salesforce System or Application Architect or equivalent in other enterprise CRM platforms.\u00a0Oracle Customer Experience certification or equivalent in other enterprise sales platforms.\nUnderstanding of agile delivery principles and quality software engineering processes and practice\nExperience in DevOps / CI / CD\nUnderstanding of cloud concepts including IaaS, PaaS, SaaS, and iPaaS\nExperience with the design and development of object-oriented systems, developing solutions, and integrating platforms using enterprise integration software e.g. mulesoft.\nExceptional leadership skills to achieve outcomes in a heavily matrixed management\nExcellent communication and interpersonal skills, across all levels and environments\nExcellent oral and written English.\nExperience in partner engagement with an onshore/offshore delivery model\nAbility to communicate effectively to technical team as well as business audience\nExperience in Application Extensions and BI Reporting\n\nInterest parties please send your application letter & CV including current and expected salary, date by clicking \"Apply Now\".\n\nOnly the shortlisted candidates will be notified. Data collected would be used for recruitment purposes only.", "employment_types": ["Full Time", "Permanent"], "selling_points": [], "locations": ["Tai Koo"], "categories": ["Information Technology (IT)", "IT Management", "Security", "Network & System"], "post_time": "2022-01-18T00:49:18Z", "salary": {"currency": null, "max": null, "min": null, "period": "monthly", "term": null}, "salary_visible": false, "title_keywords": ["assistant manager", "engineer"], "responsibilities": ["provide insights", "business continuity", "software", "information security", "data", "internal and external parties", "quality", "audit", "design", "communication", "maintain", "designing", "collaborate", "compliance", "teams", "implementation", "developing", "architecture", "reporting", "management", "monitoring", "review", "cross-functional teams", "policies", "systems", "coordinate", "recruitment", "access control"], "requirements": {"degrees": ["degree", "bachelor"], "majors": ["computer science"], "languages": ["english"], "language_level": ["excellent"], "hard_skills": ["bi", "salesforce", "agile", "hvac", "devops", "erp", "rpa", "integration", "oracle"], "soft_skills": ["oral", "negotiation", "focused", "accountability", "agile", "leadership skills", "teamwork", "integrity", "accountable", "prioritise", "communication", "hands-on", "communication and interpersonal skills", "thorough", "leadership"], "languages_combined": [{"language": "english", "language_level": ["excellent"]}]}, "experience_required": {"duration": ["6 years"], "field": ["development", "devops", "developing", "design", "solution architect", "commercial", "it", "team"]}}, {"job_id": "100003009052500", "location_code": "hk", "company": "Conrad Hong Kong", "job_title": "Senior Manager, Carrier Sales", "description": "Background:\u00a0My client is one of the top-tier Financial Services firms in Hong Kong who is now looking for an experienced candidate with solid O365 experience to join their team.\n\n\nDuties\n\n\nHave overall responsibility for the development and on-going management of MS O365 and Messaging Infrastructure and support Group IT platform and shared services\nAssist in Managing and Design the Microsoft O365, Corporate Directory Services and Integration of 3rd party\u2019s technology solution.\nSupport cloud adoption with the cloud operation and delivery team aligning to the Technology Strategy\nSupport IT Infrastructure/System setup & migration for new business entity\nLiaise with IT application, application architect and security team on the technical development of converged solutions and process to enhance the operations of services\nTechnical Evaluation of latest IT technology and management tools on Microsoft O365 environment\nLead Technical engineers to negotiate with vendors, auditors, consultants.\nEnsure the managed IT infrastructure are fulfil compliance/security requirement\nAssists in conducting DR Drill and BCP process\n\nRequirements:\n\n\nDegree holder in Computer Science / Information Technology or equivalent with\n5-10 years of relevant experience which 2 years in managerial level (Team/People management experience)\nSolid experience in MS O365, Active Directory Services, MS Exchange, MDM, SCCM, Cloud infrastructure (Azure & AWS), HCI, VMware, SAN Storage Management, SSL Cert Management & Encryption technology, Backup & Disaster Recovery Solution\nStrong problem solving, management and analytical skills with in-depth knowledge of O365, Messaging, Server, Network, DR Management, etc\n\nStrong knowledge in Infrastructure Architecture.\nGood command of written and spoken English and Chinese\n\nIf you are interested in this position, please apply online by submitting your latest CV in Word format including current & expected salary. Kindly note that only shortlisted candidates will be notified.", "employment_types": ["Full Time"], "selling_points": ["Implement sales strategy", "Prepare sales proposal and presentation", "Minimum 8 years relevant experience"], "locations": ["Not Specified"], "categories": ["Admin & HR", "Administration / Operation Manager", "Management", "General Management", "Information Technology (IT)", "IT Management"], "post_time": "2022-01-17T03:14:55Z", "salary": {"currency": null, "max": null, "min": null, "period": "monthly", "term": null}, "salary_visible": false, "title_keywords": ["senior manager", "sales"], "responsibilities": ["management", "it infrastructure", "operations", "infrastructure", "compliance", "design", "security requirement", "evaluation", "liaise with", "migration", "setup"], "requirements": {"degrees": ["degree holder"], "majors": ["computer science", "information technology"], "languages": ["english", "chinese"], "language_level": ["good command"], "hard_skills": ["o365", "azure", "vmware", "active directory", "sccm", "word", "aws", "problem solving", "analytical skills", "server", "exchange"], "soft_skills": ["problem solving", "active", "interested in", "analytical skills"], "languages_combined": [{"language": "english", "language_level": ["good command"]}, {"language": "chinese", "language_level": ["good command"]}]}, "experience_required": {"duration": ["2 years", "5-10 years"], "field": ["managerial", "management", "disaster recovery", "people management", "cloud infrastructure", "relevant experience", "team"]}}, {"job_id": "100003009052043", "location_code": "hk", "company": "Chesterton Consulting Co Limited", "job_title": "IT Infrastructure and Security Manager", "description": "Partner with Chief Executive Officer, the CIO/ Principal Head of IT is supposed to driving company wide's strategic and operational IT initiatives with key responsibilities as follow:\n\n\nAssist CEO in developing the Company in accordance with the long term strategic directions set out by the Board of Directors and exploring the employment of new technology and improvement opportunities;\nCollaborate with senior management to devise and maintain the information technology strategy and policies to achieve high safety and efficiency, compliance with the statutory requirements as well as the committed service standards;\nKeep abreast of market trend and regulatory compliance relating to Banking/Fintech industry and commit to drive for digital transformation as well as ESG responsibilities;\u00a0\nOther IT related administrative activities including resources planning and budgetary control\nOversee daily IT operation no limited to software application and development, IT infrastructure, IT Security, in-house user supports, external vendor management etc.\n\nDevelopment and implementation of application development methodology, quality assurance plan, problem management and change management procedures in compliance with related regulations and requirements;\nMaintaining adequate infrastructure of the Data Centers (including backup sites) and business continuity plan, and directing contingency drills to minimize the threats to the operations; and\nRequirements\n\nSuitable candidates should possess university education in computer science or related discipline with over 20 years of IT experience preferably in banking sector of which at least 8 years at senior executive level, and good knowledge of payment and settlement systems in Hong Kong.\nStrong leadership, interpersonal and management skills, good command in written Chinese and English as well as fluency in spoken English, Cantonese, and Putonghua are essential.\nApplicants with less experience may be considered for the position of Principal Head of IT Department.\nInterested parties, please \"apply\" with detailed CV in word format by stating your current and expected salary package.\u00a0\u00a0 Attractive package will be commensurate with qualification and experiences.\u00a0 Only shortlisted candidates will be contacted for interview.\u00a0\u00a0\u00a0\n\n** All personal data collected is for recruitment purpose only **", "employment_types": ["Full Time", "Permanent"], "selling_points": ["Fast Paced", "Excellent Career Opportunity", "Job Security"], "locations": ["Sai Ying Pun"], "categories": ["Information Technology (IT)", "IT Management", "Security"], "post_time": "2022-01-17T01:55:46Z", "salary": {"currency": null, "max": null, "min": null, "period": "monthly", "term": null}, "salary_visible": false, "title_keywords": ["manager"], "responsibilities": ["collaborate with", "regulations", "business continuity", "software", "data", "operations", "quality", "statutory requirements", "service standards", "maintain", "payment", "plan", "application development", "senior management", "control", "it infrastructure", "maintaining", "compliance", "infrastructure", "developing", "implementation", "banking", "management", "change management", "procedures", "administrative activities", "policies", "systems", "planning"], "requirements": {"degrees": [], "majors": [], "languages": ["cantonese", "putonghua", "english", "chinese"], "language_level": ["fluency", "good command"], "hard_skills": ["no", "vendor"], "soft_skills": ["committed", "leadership", "interpersonal"], "languages_combined": [{"language": "cantonese", "language_level": ["good command"]}, {"language": "putonghua", "language_level": ["good command"]}, {"language": "english", "language_level": ["good command"]}, {"language": "chinese", "language_level": ["fluency", "good command"]}]}, "experience_required": {"duration": ["at least 8 years", "20 years"], "field": ["related", "it experience", "education", "it", "banking sector"]}}, {"job_id": "100003009040109", "location_code": "hk", "company": "Getz Bros. & Co. (Hong Kong) Limited", "job_title": "IT Manager", "description": "Responsibilities\n\nLead the development team to develop, deliver and support the Bank\u2019s data warehouse, business intelligence system, financial GL system and other analytics platform\n\nManage the entire SDLC, including user requirements collection, system design, development, documentation, testing, training and application support; ensure the projects are implemented within budget and agreed schedule\n\nLiaise with internal and external stakeholders, e.g. IT vendors and user department, etc. on system implementation\n\nProvide system support, including user inquiry and problem solving when necessary, irregular working hours may required\n\nEnsure all process and deliverable are comply with internal and regulatory requirements\n\nProvide coaching, training and development to team members\n\nHandle ad hoc projects as required\n\nRequirements:\nDegree Holder in Computer Science or Information Technology related disciplines\n\nMinimum 15 years relevant experience of which at least 8 years at managerial level, preferably in banking industry\n\nStrong business banking knowledge and technical insight with ability to recommend IT solutions to business units\n\nSolid experience in data warehouse and business intelligence platform such as SAS, IBM Business Analytics\n\nSound knowledge in banking financial system such as GL systems, Big Data and Fintech is preferred\n\nStrong project management skills, ability to manage multiple projects simultaneously\n\nExcellent command of written and spoken English and Chinese\n\nInterested candidates, please click APPLY NOW \u00a0to apply.", "employment_types": ["Full Time", "Permanent"], "selling_points": ["5-day work, Competitive Pay and Benefits", "Experiences in FMCG and retail industry", "Develop IT goals, strategies and procedures"], "locations": ["Kwai Tsing Area"], "categories": ["Information Technology (IT)", "IT Project Management / Team Lead", "IT Management", "Product Management / Business Analyst"], "post_time": "2022-01-12T02:53:15Z", "salary": {"currency": null, "max": null, "min": null, "period": "monthly", "term": null}, "salary_visible": false, "title_keywords": ["it manager"], "responsibilities": ["data", "regulatory requirements", "budget", "implementation", "testing", "develop", "liaise with", "system design", "ad hoc projects", "schedule", "documentation"], "requirements": {"degrees": ["degree holder"], "majors": ["related disciplines", "computer science", "information technology"], "languages": ["english", "chinese"], "language_level": ["excellent"], "hard_skills": ["data warehouse", "project management", "business intelligence", "sas"], "soft_skills": ["project management skills", "manage multiple projects simultaneously"], "languages_combined": [{"language": "english", "language_level": ["excellent"]}, {"language": "chinese", "language_level": ["excellent"]}]}, "experience_required": {"duration": ["at least 8 years", "minimum 15 years"], "field": ["managerial", "banking industry", "business", "relevant experience"]}}, {"job_id": "100003009037125", "location_code": "hk", "company": "Win Hanverky Holdings Limited", "job_title": "Senior IT Manager", "description": "Responsibilities:\n\nOversee the project progress and planning on digitalization related projects across the Group\nCraft out the implementation plan on various stages and follow through the implementation status with team members according to agreed timeline, quality and budget\nCommercial terms review, budget control and project P&L management\nIdentify and analyze business processes and requirements, and manage all stages of development including system design, technical specifications, system integration, testing and deployment of applications, and maintenance\nEvaluate technical architectures and solutions, evaluate potential risks and issues with recommendations, and report progress to stakeholders and management\nEvaluate proof-of-concept and new technology/solutions to integrate with existing systems / future systems \u00a0\nProvide training and briefing sessions to users on deployed systems and applications\nPerform vendor and contract management and review vendors\u2019 system documentation\nIT liaison and advisory on system security on various applications\n\nRequirements:\n\nDegree holders in Information Technology, Computer Science, Engineering or related disciplines; preferably with PMP or equivalent qualifications\u00a0\nAt least 12 years\u2019 relevant experience in IT system design, development and management of core projects; including not less than 3 years project management experience on tier one human resources systems.\nCompetence in managing the whole SDLC process including gathering of requirements, analysis, development, UAT, production release and maintenance; plus\u00a0good knowledge of MySQL, MS SQL, VB.Net, Crystal Report, Java, ASP. Net, HTML and PHP\nExperience in SAP SuccessFactors is highly preferred\nExperience with Cloud Computing platform, Business Intelligence System, Data Analytics would be an added advantage\nStrong ability and proven track record in designing and implementing pragmatic solutions under complex business requirements\nMature, detail-minded with strong communication and problem solving skills\nGood command of spoken and written English and Chinese (Cantonese and Putonghua)\n\nWe work 5 days per week.\n\nInterested parties, please click \"APPLY NOW\" and attach with your application letter and full resume.\n\nFor further information of the Wharf Group, please visit our website: www.wharfholdings.com\u00a0", "employment_types": ["Full Time", "Permanent"], "selling_points": [], "locations": ["Lai Chi Kok"], "categories": ["Information Technology (IT)", "IT Project Management / Team Lead", "IT Management", "Others"], "post_time": "2022-01-11T01:48:49Z", "salary": {"currency": null, "max": null, "min": null, "period": "monthly", "term": null}, "salary_visible": false, "title_keywords": ["senior it manager"], "responsibilities": ["provide training", "budget", "quality", "plan", "budget control", "system documentation", "implementation", "project progress", "p&l", "testing", "report", "management", "review", "specifications", "maintenance", "systems", "contract management", "evaluate", "system design", "system security", "planning"], "requirements": {"degrees": ["degree"], "majors": ["related disciplines", "engineering", "computer science", "information technology"], "languages": ["cantonese", "putonghua", "english", "chinese"], "language_level": ["good command"], "hard_skills": ["plus", "java", "maintenance", "php", "sap", "data analytics", "analysis", "html", "project management", "sdlc", "system design", "problem solving skills", "pmp", "business intelligence", "ms sql"], "soft_skills": ["detail-minded", "mature", "communication", "project management", "problem solving skills"], "languages_combined": [{"language": "cantonese", "language_level": ["good command"]}, {"language": "putonghua", "language_level": ["good command"]}, {"language": "english", "language_level": ["good command"]}, {"language": "chinese", "language_level": ["good command"]}]}, "experience_required": {"duration": ["3 years", "at least 12 years"], "field": ["management", "development", "project management", "business", "relevant experience", "it system design", "human resources systems"]}}, {"job_id": "100003009050443", "location_code": "hk", "company": "Hong Kong Productivity Council", "job_title": "Assistant Manager, Technical Advisory (Funding Scheme Branch)(Ref: FSB076/21, 1982/JDB/140122)", "description": "Responsibilities:\nDeliver high quality of vulnerability scanning, various types of penetration tests for the bank systems covering infrastructure, web application, mobile application regularly.\n\nPerform system hardening for e-banking systems.\n\nSupport IT security systems covering tenable security center. Database firewall and WAF.\n\nCollaborate, monitor the cyber threat landscape through open source channels, vendor feeds and analyze of cyber threat intelligence.\n\nAdvise management on the latest trends in cyber intelligence and best practices, through close collaboration and engagement with security industry and government agency.\n\nLead the development and implementation of mitigation proposal to prevent the potential threat.\n\nRequirements:\nDegree holder in Information Systems, Computer Science or related disciplines\n\nMinimum 5 years' working experience in cyber security area, preferably in consulting firm, technology vendor or bank.\n\nProfessional qualifications of CREST relevant certifications are highly preferable while CISA , CISSP or relevant certifications are also considered.\n\nExpert knowledge on penetration tools, e.g. Tenable Nessus, Nmap, Burp, IBM AppScan, Zap, Kali Linux, etc.\n\nProficient to perform variety of penetration test.\n\nHand-on experience on IT security system.\n\nMonitor and maintain up-to-date intelligence of threats of cyber attacks.\n\nStrong communication and good report writing skills in English.\n\nSelf-motivated and able to work independently.\n\nWe offer competitive remuneration package and promising career opportunities to the successful candidates. Interested parties, please send full resume with current & expected salary and the date of availability to The HR Division, G.P.O. Box 2535, HK , or by clicking Apply Now. Please quote reference on your application. Information provided will be treated in strict confidence and only be used for recruitment purposes. Personal data of unsuccessful applications will be destroyed 24 months after the completion of the recruitment and selection exercise.\n\nInterested candidates, please click APPLY NOW \u00a0to apply.", "employment_types": ["Contract"], "selling_points": ["5-day work week", "Bachelor Degree in Computer Science", "At least 3 years\u2019 relevant experience"], "locations": ["Not Specified"], "categories": ["Information Technology (IT)", "IT Project Management / Team Lead", "IT Management", "Product Management / Business Analyst"], "post_time": "2022-01-17T01:17:33Z", "salary": {"currency": null, "max": null, "min": null, "period": "monthly", "term": null}, "salary_visible": false, "title_keywords": ["assistant manager,"], "responsibilities": ["scanning", "collaborate", "management", "infrastructure", "systems", "quality", "monitor", "implementation", "database", "banking"], "requirements": {"degrees": ["degree holder"], "majors": ["related disciplines", "computer science"], "languages": ["english"], "language_level": ["good"], "hard_skills": ["linux", "professional qualifications", "cyber security", "vendor", "writing skills"], "soft_skills": ["communication", "self-motivated", "work independently", "writing skills"], "languages_combined": [{"language": "english", "language_level": ["good"]}]}, "experience_required": {"duration": ["minimum 5 years"], "field": ["it", "security", "consulting"]}}, {"job_id": "100003009051751", "location_code": "hk", "company": "Pinpoint Asia Limited", "job_title": "SOC Security Operations Manager - Enterprise Security Hub", "description": "Our client, a leading bank, is looking for a Head of IT Infrastructure. The selected candidate will be leading a sizeable infrastructure team in Hong Kong. They are also on the pathway in making a cloud transformation. It will be a great leadership role in driving the infrastructure change across the bank.\n\nResponsibilities:\n\nManage the entire HK IT infrastructure operations including Data Centers, Network, Storage, Middleware, Servers, Databases, End User, Cloud, etc.\nEnsuring the high availability and security of all technology systems, networks, and related applications.\nDefine technology strategy aligning with the bank's business direction. Identify the latest technology and development in order to help the firm be ahead of the industry competitions.\nManage infrastructure projects across various vendors and technology teams. Ensure the use of best practices in the design and build of infrastructure.\nWork with the IT Security team in defining appropriate IT Security measures, policies, best practices, and guidelines.\nStreamline office automation support, IT operation in routine processing, backup, and disaster recovery to reduce the cost of ownership and/or maximize the return of IT investment.\nManage and control various infrastructure projects\u2019 budgets and expenses.\nManage a regional technology team, with appropriate job training, coaching, and performance review.\n\nRequirements:\n\nAt least 15 years of experience in enterprise-level infrastructure management.\nStrong experience in design, building, and operating a large scale of infrastructure supporting mission-critical systems.\nStrong experience in building infrastructure solutions across web applications, internal applications,\u00a0 and data centers.\nExperience with designing, building, and operating private/public cloud technologies and virtualization would be a great plus.\nExperience with managing servers, networking, databases, desktop, middleware, and mobile technologies.\nStrong management experience across an infrastructure prospect. Strong ability to perform team transformation and changes.\nProject management experience in planning, budgeting, and architecture design.\nStrong verbal and communication skills in English and Chinese (Mandarin and Cantonese) to interact with senior management, team members, and vendors, etc.\nStrong experience in infrastructure management in the banking domain.\nCore / Professional level qualification of Relevant Practitioner under HKMA ECF on Cybersecurity such as certified in CISSP, CISA, CISM or other recognized certificate.\nBachelor / Master Degree in Computer Science / Engineering from a reputable University.\n\nIf this outstanding opportunity sounds like your next career move, please send your resume in Word format to Danny Kwan at resume(at)pinpointasia(dot)com and put Head of IT Infrastructure - Leading BankBankin the subject header.\n\nData provided is for recruitment purposes only.", "employment_types": ["Full Time", "Permanent"], "selling_points": ["Large Security Center", "Sophisticated Technology", "SOC Operations"], "locations": ["Not Specified"], "categories": ["Information Technology (IT)", "IT Management", "Security", "Technical / Functional Consulting"], "post_time": "2022-01-17T00:14:13Z", "salary": {"currency": "HKD", "max": 89999, "min": 70000, "period": "monthly", "term": null}, "salary_visible": true, "title_keywords": ["operations manager"], "responsibilities": ["budgets", "cost", "control", "it infrastructure", "data", "guidelines", "operations", "policies", "systems", "infrastructure", "teams", "design", "expenses", "review", "databases"], "requirements": {"degrees": ["certificate", "bachelor", "master degree"], "majors": ["engineering", "computer science"], "languages": ["cantonese", "english", "chinese", "mandarin"], "language_level": [], "hard_skills": ["plus", "web applications", "servers", "hkma", "word", "mobile", "project management", "databases"], "soft_skills": ["communication skills", "project management"], "languages_combined": [{"language": "cantonese", "language_level": []}, {"language": "english", "language_level": []}, {"language": "chinese", "language_level": []}, {"language": "mandarin", "language_level": []}]}, "experience_required": {"duration": ["at least 15 years"], "field": ["management", "web applications", "infrastructure", "design", "project management", "banking", "planning"]}}, {"job_id": "100003009043981", "location_code": "hk", "company": "Peninsula Merchandising Limited", "job_title": "Director of Finance", "description": "Background:\u00a0My client is a leading Financial Services in Hong who is now looking for an experienced Information Security Manager to join the team.\n\nJob Scope:\n\n\nTo support and overseeing the IT Security operations for the Bank\nEnsure network based security risks are identified, managed and monitored to ensure successful mitigation and risk reduction.\nSupport day to day IT security operations including user access management, security monitoring, cyber threat intelligence collection, analysis, investigation, escalation and reporting, etc.\u00a0\nSupport and maintain IT Security systems covering Anti-DDoS, Anti-Malware, IPS, PAM, and DBF, etc.\nConduct IT security control assessment/review on new technology projects, system upgrade, or incident follow up.\u00a0\nWork closely with IT Management and IT teams to ensure effective security design and operation of both business and technical controls.\nDevelop and maintain an information security dashboard and metrics that provide an accurate representation of the information security risk profile and relevant cyber threats.\nCoordinate and oversee timely completion of internal and external audits and control assurance findings\nAssist in develop and maintain information security documents, guidelines and control baselines, etc.\nPerform other IT Security related duties and/or special projects as assigned\n\nRequirement:\n\n\nMust have a relevant University degree in Computer Science, Information Management or related field, or equivalent experience.\nMust have good understanding of regulatory technology risk frameworks such as HKMA TM-G-1\nIt will be a good advantage to have solid experience in Identity Access Management (IAM)\nMore than 5-10 year working experience in information security/technology risk management.\nKnowledge of network technologies, TCP/IP, network security, cyber security, privileged identity management and various encryption methodologies.\nHands-on experience in security solutions such as: Firewall, NIPS/NIDS, WAF, Anti-malware, PAM, etc.\nGood to have security risk assessment and security audit relevant experience\nExcellent communication skills in Chinese and English\n\nIf you are interested in this position, please apply by submitting your latest CV in Word format including current & expected salary. Kindly note that only shortlisted candidates will be notified.\n", "employment_types": ["Full Time", "Permanent"], "selling_points": ["Join a highly prestigious retail brand", "At least 12 years of relevant experience", "Competitive benefits with family medical coverage"], "locations": ["Tsim Sha Tsui"], "categories": ["Accounting", "Financial Controller", "Others", "Information Technology (IT)", "IT Management"], "post_time": "2022-01-13T02:40:13Z", "salary": {"currency": null, "max": null, "min": null, "period": "monthly", "term": null}, "salary_visible": false, "title_keywords": ["director"], "responsibilities": ["information security", "cyber security", "operations", "audit", "design", "communication", "maintain", "control", "teams", "develop", "reporting", "management", "monitoring", "review", "internal and external audits", "investigation", "it management", "guidelines", "analysis", "systems", "coordinate"], "requirements": {"degrees": ["relevant university degree"], "majors": ["computer science"], "languages": ["english", "chinese"], "language_level": ["excellent"], "hard_skills": ["cyber security", "hkma", "tcp", "analysis", "word", "ip", "firewall"], "soft_skills": ["communication skills", "timely", "interested in", "hands-on", "accurate"], "languages_combined": [{"language": "english", "language_level": ["excellent"]}, {"language": "chinese", "language_level": ["excellent"]}]}, "experience_required": {"duration": ["5-10 year"], "field": ["risk management", "management", "related", "audit", "it", "relevant experience", "security"]}}, {"job_id": "100003009044801", "location_code": "hk", "company": "Bureau Veritas Hong Kong Limited", "job_title": "Assistant Manager, Systems", "description": "Responsibilities:\n\nTo oversee the daily IT operation of the Company and to supervise the IT support team on deployment\nTo manage the IT infrastructure and program development and enhancement\nTo work collaboratively with all counterparts to proactively understand business needs and develop solutions to improve business efficiency\nTo manage all IT related projects, planning, analysis, implementation and documentation\nTo ensure the maintenance of up-to-date inventory database for computer hardware and software\nTo be responsible for the sourcing and procurement for all IT related equipment or services\nAny other ad hoc projects as instructed by supervisors\n\nJob Requirements:\n\n\nDegree holder or above in IT related disciplines\n5 to 10 years experience in managing complex IT environments across multiple countries\nProficient in Windows, Linux Server, VMWare, MS SQL, MySQL, SAN Storage, Backup solutions and Data Security\nAt least one-year working experience in Cloud Service\nStrong knowledge and hands-on technical skills on Active Directory configuration, GPO, SCCM, VMware, Powershell and blackberry UEM\nStrong technical profile in infrastructure and application implementation\nExperience in cross-cultural people management\nStrong interpersonal and communication skills\nGood written and verbal communication skills\nAble to work under pressure and meet deadlines\nAble to demonstrate a high degree of flexibility including out of hours working when\u00a0incidents arise\nStrong organizational skills\nAble to manage sensitive and confidential information\nSelf-motivation and able to take responsibility\nAble to manage and prioritize tasks and time efficiently\n\nWe offer competitive salary and benefits to the right candidate.\u00a0 Interested parties please send your application with date of availability, present & expected salary to the\u00a0Human Resources Department,\u00a0Bureau Veritas Hong Kong\u00a0Limited\u00a0by mail\u00a0or\u00a0clicking \u201cAPPLY NOW\u201d.\u00a0 To submit your application by mail, please mark \"Confidential\" and position applied on the envelope.\n\nOur Benefits:\n\nExcellent Training & Career Advancement Opportunities\n13th monthly salary, Performance Bonus\n5-day Work Week\nPublic Holiday, Annual Leave, Marriage Leave, Maternity Leave & Paternity Leave\nLife & Medical Insurance Benefits\nMandatory Provident Fund Contribution\nEducation & Training Subsidies\n\nJoin us on Linkedin:\u00a0\u00a0https://www.linkedin.com/company/bureau-veritas\n\nMail\u00a0\n7/F,\u00a0Harbourside HQ\n8 Lam Chak Street\nKowloon Bay, Kowloon\n\nPersonal data collected will be used for recruitment purposes only.", "employment_types": ["Full Time", "Permanent"], "selling_points": ["Global Leader in Testing Industry", "Training & Career Advancement Opportunities", "13th Month Salary, Performance Bonus"], "locations": ["Kowloon Bay"], "categories": ["Information Technology (IT)", "IT Management", "Network & System", "Others"], "post_time": "2022-01-13T08:17:00Z", "salary": {"currency": null, "max": null, "min": null, "period": "monthly", "term": null}, "salary_visible": false, "title_keywords": ["assistant manager,"], "responsibilities": ["it infrastructure", "maintenance", "software", "analysis", "inventory", "implementation", "develop", "hardware", "ad hoc projects", "database", "documentation", "planning"], "requirements": {"degrees": ["degree", "degree holder"], "majors": ["related disciplines", "it"], "languages": [], "language_level": [], "hard_skills": ["linux", "vmware", "active directory", "sccm", "powershell", "server", "ms sql", "gpo"], "soft_skills": ["communication skills", "organizational skills", "prioritize", "hands-on", "self-motivation", "sensitive", "technical skills", "meet deadlines", "active", "interpersonal", "work under pressure"], "languages_combined": []}, "experience_required": {"duration": ["5 to 10 years"], "field": ["people management", "it"]}}, {"job_id": "100003009053343", "location_code": "hk", "company": "ELM Computer Technologies Ltd", "job_title": "System Engineer", "description": "Founded in 1990, ELM Computer Technologies Limited (ELM) has been providing state-of-the-art IT solutions and professional services to our clients for thirty (30) years. The wide area of expertise in IT that ELM possesses under its belt has enabled the company to offer services on the lines of Multi-cloud Management, DevOps and Microservices Management, Business Analytics, Application Performance Management, Access and Identity Management, Enterprise Facilities and Asset Management, IT Services Management, Data Protection, and Enterprise Mobility Management.\u00a0\n\nWith modern technologies such as cloud computing, business analytics, IoT, mobility, blockchain coming to mainstream prominence, constant adaption and innovation to cope with the evolving market has become a mandate that will continue to shape markets worldwide for the near foreseeable future. ELM under its strong technical capability will continue growing with its team members and clients together in the new digital world.\u00a0\n\n\n\nResponsibilities:\u00a0\n\nResponsible for Unix/Linux/Wintel Server administration, installation, configuration, maintenance and troubleshooting\nConducting system/user acceptance test\nAssist in preparing technical documentation\nProvide 1st tier support\nCapable to work during non office hour\n\nRequirements:\u00a0\n\nUniversity holder or Diploma in Computer Science, Information Systems or related disciples\nWith 2 years of working experience\nKnowledge in shell script programming\nKnowledge/experience in IBM AIX & Middleware (WAS/MQ)\u00a0 is an advantage\nExcellent command in spoken and written English and Chinese\u00a0\n\nWe offer a comprehensive package to the right candidates. Please send your resume (IN MS WORDFORMAT) with contact phone number and EXPECTED SALARY (MUST) to Human Resources Department, 16/F, Topsail Plaza, 11 On Sum Street, Shatin, Hong Kong or email us. For more information, please visit our web site www.elm.com.hk\n\nAll information provided by applicants will be treated in strict confidence and will only be used for recruitment related purposes. All personal data supplied will be destroyed within six months after the selection process.", "employment_types": ["Contract"], "selling_points": ["2 years of working experience", "Knowledge in IBM AIX & Middleware (WAS/MQ)", "Knowledge in shell script programming"], "locations": ["Shatin Area"], "categories": ["Information Technology (IT)", "Application Specialist - Software", "IT Management", "Network & System"], "post_time": "2022-01-17T06:48:43Z", "salary": {"currency": null, "max": null, "min": null, "period": "monthly", "term": null}, "salary_visible": false, "title_keywords": ["system engineer"], "responsibilities": ["installation", "maintenance", "configuration", "troubleshooting", "documentation", "administration"], "requirements": {"degrees": ["diploma"], "majors": ["computer science"], "languages": ["english", "chinese"], "language_level": ["excellent"], "hard_skills": ["programming"], "soft_skills": [], "languages_combined": [{"language": "english", "language_level": ["excellent"]}, {"language": "chinese", "language_level": ["excellent"]}]}, "experience_required": {"duration": ["2 years"], "field": []}}, {"job_id": "100003009055719", "location_code": "hk", "company": "BOCI", "job_title": "Application Support, Front Office, Information Technology  (Renewable contract)", "description": "The role\n\nApplication Support, Front Office, Information Technology\u00a0 (Renewable contract)\n\nKey accountabilities\n\nSupport Front Office Trading Systems\nProvide hands-on technical support for users, troubleshoot and diagnose functional and technical issues\nRun production outages, track and follow up on root cause analysis and remediation\nEnsure adequate performance and operation of the systems - monitor the performance \u2044 operation, diagnose and address any problems.\nResponsible for change release preparation and Exchange Market Rehearsal\n\nSkills & experience\n\nBachelor degree or diploma holder in Computer Science or related discipline(s)\nExperienced with financial industry and highly regulated environment is preferred\nSelf-motivated and a quick learner in dynamic environment\nAbility to perform under pressure\nA team player with good communication and problem solving skills\nPrefer some end user support experience ideally on Front Office systems\nFamiliar with Windows and Unix/Linux operating environment\nGood technical skills with shell scripts and database SQL queries\nFIX knowledge and client connectivity a plus\nBusiness knowledge on Cash Equities, Derivatives and research market a plus\nBilingual in Chinese and English\n\nOther\n\nNotes to applicants:\n\nPlease apply in strict confidence with full resume, academic record, current and expected salaries.\nThe personal data provided will be used for consideration of recruitment only. All personal data of unsuccessful candidate will be destroyed within 24 months.\nCandidates with Enhanced Competency Framework (ECF): please state on the CV.\n\nAbout us\n\nAs a leading investment bank in China and Hong Kong region, the investment banking arm of Bank of China, BOC International Holdings Limited (\u201cBOCI\u201d), is now seeking highly motivated, creative and success-oriented professional who would like to pursue the career for supporting our group.", "employment_types": ["Full Time"], "selling_points": ["Entry Level", "Excellent opportunity in investment banking", "Front office application support"], "locations": ["Kwai Hing"], "categories": ["Information Technology (IT)", "IT Management"], "post_time": "2022-01-18T02:53:17Z", "salary": {"currency": null, "max": null, "min": null, "period": "monthly", "term": null}, "salary_visible": false, "title_keywords": ["application support"], "responsibilities": ["technical support", "outages", "analysis", "systems", "diagnose", "banking", "communication", "recruitment", "troubleshoot", "monitor the performance", "database", "personal data"], "requirements": {"degrees": ["diploma holder", "degree", "bachelor"], "majors": ["computer science"], "languages": ["english", "chinese"], "language_level": [], "hard_skills": ["linux", "plus", "analysis", "sql", "dynamic", "problem solving skills", "exchange"], "soft_skills": ["self-motivated", "dynamic environment", "under pressure", "confidence", "responsible", "quick learner", "communication", "hands-on", "problem solving skills", "motivated", "troubleshoot", "technical skills", "team player", "creative"], "languages_combined": [{"language": "english", "language_level": []}, {"language": "chinese", "language_level": []}]}, "experience_required": {"duration": [], "field": []}}, {"job_id": "100003009046566", "location_code": "hk", "company": "KOS International Limited", "job_title": "IT Manager - POS operation", "description": "About our client\n\nOur client is a renowned local digital retailer, and they are looking for an IT Manager with good knowledge in POS operation to join their team.\n\nAbout the role\n\n\nOverseeing the operation, development, management of POS and related IT components\n\nSupervising and health checking on the daily operation on the application side\n\nCooperating with the internal infrastructure team to establish a smooth operation of the application\n\nPerforming data management and reporting when required\n\nPerforming managerial tasks, including risk management, budgeting, team structuring, etc.\n\nManaging vendor for development and solutions planning on the application\n\n\nRequirements\n\n\nBachelor degree holder in Computer Science, Information Technology, Mathematics or related discipline\n\n8 years or above experience in application operation/service delivery. With managerial experience is a plus\n\nExperience in reporting tools, such as PowerBI/Tableau/QlikView/Qlik Sense\n\nWith practical and hands-on experience in managing applications/E-commerce platforms is a plus\n\nInsight in DevOps environment on AWS/Azure/GCP environment is a plus\n\nGood command of English and Chinese(Cantonese & Mandarin)\n\nGood interpersonal and communication skills\n\n\nClick \"Apply Now\" to apply for this position or call Harry Yau at +852 3180 4936 for a confidential discussion. All information collected will be kept in strict confidence and will be used for recruitment purpose only.", "employment_types": ["Full Time", "Permanent"], "selling_points": ["Renowned and well-established Enterprise", "8+ years experience on application operation", "In-house, Permanent, 5-day work"], "locations": ["Not Specified"], "categories": ["Information Technology (IT)", "IT Project Management / Team Lead", "IT Management", "Software Development"], "post_time": "2022-01-13T14:21:54Z", "salary": {"currency": null, "max": null, "min": null, "period": "monthly", "term": null}, "salary_visible": false, "title_keywords": ["it manager"], "responsibilities": ["service delivery", "reporting", "management", "supervising", "data", "budgeting", "infrastructure", "daily operation", "checking", "e-commerce platforms", "communication", "recruitment", "planning"], "requirements": {"degrees": ["bachelor degree holder"], "majors": ["mathematics", "computer science", "information technology"], "languages": ["english", "mandarin"], "language_level": ["good command"], "hard_skills": ["qlikview", "plus", "data management", "azure", "pos", "e-commerce", "devops", "vendor", "tableau", "aws"], "soft_skills": ["communication skills", "confidence", "hands-on", "smooth", "interpersonal"], "languages_combined": [{"language": "english", "language_level": ["good command"]}, {"language": "mandarin", "language_level": ["good command"]}]}, "experience_required": {"duration": ["8 years"], "field": ["managerial", "operation", "e-commerce"]}}, {"job_id": "100003009049584", "location_code": "hk", "company": "Mandatory Provident Fund Schemes Authority", "job_title": "Manager (Supervision)", "description": "The Job\n\nThe MPFA has been tasked by the Government to design, develop and operate a digital platform, eMPF Platform, to standardize, streamline and automate the existing MPF scheme administration processes.\u00a0 Through the adoption of new technologies and innovative solution, this user-centric platform will bring about revolutionary change to the MPF ecosystem, thus creating further room for scheme administration fee reduction to benefit all MPF scheme members.\u00a0 On 5 March 2021, the eMPF Platform Company Limited was established as MPFA\u2019s wholly owned subsidiary to take forward the eMPF Platform project.\u00a0 For background and details of the eMPF Platform project, please go to our website https://www.mpfa.org.hk/en/empf/overview.\n\nThe appointee will support the development and implementation of an oversight programme in relation to overseeing the operation of the eMPF Platform to safeguard system integrity and stability.\u00a0 The appointee will also be involved in key projects with a view to supervising the performance of functions assigned to the eMPF Platform Company Limited and the system readiness of MPF trustees for on-boarding the eMPF Platform.\u00a0 The main responsibilities include:\n\nTo support the development of an oversight framework which would effectively oversee and supervise the operation of the eMPF platform to safeguard system integrity and stability;\nTo assist in establishing and enforcing standards and sound practices for and communicate compliance expectations with the eMPF Platform Company Limited;\nTo collaborate with the eMPF Platform Company Limited and oversee its performance of operational functions delivered either directly or through outsourced vendors;\nTo collaborate with eMPF Platform Company Limited to ensure that the eMPF Platform would adopt appropriate technical security measures and proper safeguards to protect the system security and data;\nTo perform evaluation of control design and carry out assessment of the effectiveness of internal controls and risk management concerning eMPF operation processes, IT systems, cyber security and system resilience;\nTo support projects at the MPFA level on reforms of MPF system, supervision of MPF trustees in relation to their system readiness for on-boarding the eMPF Platform, and other related initiatives; and\nTo perform other duties as assigned.\n\nThe Person\n\nA recognized degree in Computer Science, Information Systems, Business or related disciplines;\nAt least eight years of relevant experience in regulatory compliance, retirement schemes / pensions, system auditing, cyber security or technology risk management, of which at least four years should be at supervisory level, preferably gained from sizable or public organizations;\nPossess certifications such as CISA, CRISC or other relevant qualifications;\nStrong knowledge and understanding of the business strategies, challenges and risks in MPF operation and technology project management;\nStrong analytical skills and ability to effectively prioritize and coordinate multiple deliverables simultaneously;\nEffective negotiator and communicator; and\nExcellent interpersonal, leadership and influencing skills, self-motivated, solutions oriented and able to work under pressure.\n\nRemuneration Package\n\nA competitive remuneration and benefits package including a discretionary performance-linked variable pay, annual leave, medical, dental and life insurance coverage, and MPF will be offered.\u00a0 The appointment will be made on a fixed-term contract for two years with the possibility of renewal of the appointment, subject to operational needs and staff performance.\n\nTo Apply\n\nInterested candidates are invited to apply by sending full career details and application letter, quoting the job reference number, with information of current / expected remuneration, availability,\u00a0to the address below or by clicking the \"Apply Now\" button:\n\nHuman Resources Department, MPFA\n\nLevel 8, Tower 1, Kowloon Commerce Centre\n\n51 Kwai Cheong Road, Kwai Chung, Hong Kong\n\nThe closing date for application is 28 January 2022 or postmarked on 28 January 2022. \u00a0Applicants not invited for interview by the end of March 2022 may assume that their applications are unsuccessful and their applications will not be retained for more than two years.\n\nThe information provided will be kept confidential and only be used for those purposes relating to your application.\u00a0 Please visit our website for the details of the MPFA\u2019s Personal Information Collection Statement for Job Applicants at https://www.mpfa.org.hk/en/mpfa/joining-mpfa/job-vacancies/personal-information-collection-statement.\u00a0 The MPFA is an equal opportunities employer and welcomes applications from all qualified candidates.", "employment_types": ["Full Time"], "selling_points": [], "locations": ["Kwai Hing"], "categories": ["Information Technology (IT)", "IT Auditing", "IT Management", "Security"], "post_time": "2022-01-14T08:54:32Z", "salary": {"currency": null, "max": null, "min": null, "period": "monthly", "term": null}, "salary_visible": false, "title_keywords": ["manager"], "responsibilities": ["collaborate with", "supervising", "data", "cyber security", "website", "design", "evaluation", "administration", "support projects", "control", "perform other duties", "compliance", "implementation", "develop", "management", "mpf", "digital platform", "systems", "system security"], "requirements": {"degrees": ["degree"], "majors": ["related disciplines", "business", "computer science"], "languages": [], "language_level": [], "hard_skills": ["project management", "analytical skills", "cyber security"], "soft_skills": ["self-motivated", "prioritize", "analytical skills", "project management", "communicator", "leadership", "interpersonal", "work under pressure"], "languages_combined": []}, "experience_required": {"duration": ["at least four years", "at least eight years"], "field": ["risk management", "compliance", "relevant experience", "security", "supervisory level"]}}, {"job_id": "100003009042922", "location_code": "hk", "company": "Tahoe Life Insurance Company Limited", "job_title": "Senior Manager, IT Infrastructure and Operations", "description": "Job Purpose:\n\nManage IT infrastructure and operations through internal IT teams, secondment staff, outsourced service providers and contractors, to ensure continuity of service for infrastructure, proper staffing levels for projects, support functions and efficient execution.\nDevelop strategic roadmaps and best practices for deployment of latest infrastructure technologies in line with the strategic and long-range planning of the Company.\nStep-by-step transform the traditional IT infrastructure to a hybrid, multi-cloud infrastructure.\nOversee the enterprise infrastructure standards, governance processes and performance metrics to ensure IT delivers value to the Company.\nParticipate in the development and control of IT budgets and ensure they comply with stated business goals and objectives and the investments are effectively spent.\n\nMain Responsibilities:\u00a0\n\nManage the infrastructure team, the governance team, along with a number of managed service providers to deliver a 24x7 operations of data center, print center and in-house server rooms.\nLead the IT services team to support and deliver technology services and capabilities which cope with the rapid changing business needs.\nManage relationships the key IT vendors, their performance and SLA, incident handling and issue/problem resolution and escalation.\nManage and deliver a portfolio of Corporate IT Infrastructure and service re-engineering projects for improvement of IT services, the stability and scalability, operational efficiencies and long-term cost savings.\nProvide leadership and guidance related to business continuity plans and contingencies helping management understand disaster scenarios, the costs for point of recovery (RPO) and time to recovery (RTO) decisions for key applications and services.\nLead the annual capital planning process and make recommendations on priorities and new infrastructure investments\nImplement best practice process improvements based on industry standards\nKeeps abreast of all industry standards and latest technology trends relating to IT infrastructure, IT services and operations.\n\nIncumbent Requirements:\n\nUniversity graduate or equivalent professional qualification in Information Technology, Computer Science or relate discipline.\nMinimum of 15 years of experience in a complex IT organization role.\nMinimum of 5 years of experience managing infrastructure projects.\nProficiency with cloud technologies, IaaS and PaaS, VMware, storage systems, data protection, network technologies and data center facilities, etc.\nExperience in managing email systems, mobile platforms, VDI, collaboration tools and phone systems.\nIn-depth understanding and experience with ITIL framework and ITSM best practices.\nGood team management and organization skills with proven record of building high performing teams.\nGood verbal, written and presentation skills.\nGood interpersonal skills with the ability to maintain effective working relationships with all levels of peers, management, and internal customers.\nAbility to work effectively under pressure, and adopt effectively to changing business priorities.", "employment_types": ["Full Time", "Permanent"], "selling_points": ["IT Infrastructure and Operations", "IT Support", "Cloud Technologies"], "locations": ["Tai Koo"], "categories": ["Information Technology (IT)", "IT Project Management / Team Lead", "Support", "IT Management"], "post_time": "2022-01-12T09:14:39Z", "salary": {"currency": null, "max": null, "min": null, "period": "monthly", "term": null}, "salary_visible": false, "title_keywords": ["senior manager", "operations"], "responsibilities": ["make recommendations", "guidance", "cost", "business continuity", "management", "it infrastructure", "data", "operations", "infrastructure", "planning process", "resolution", "costs", "plans", "re-engineering"], "requirements": {"degrees": ["university graduate"], "majors": ["computer science", "information technology"], "languages": [], "language_level": [], "hard_skills": ["itil", "mobile", "vmware"], "soft_skills": ["work effectively", "under pressure", "presentation skills", "interpersonal skills", "organization skills"], "languages_combined": []}, "experience_required": {"duration": ["minimum of 15 years", "minimum of 5 years"], "field": ["infrastructure", "it"]}}, {"job_id": "100003009053009", "location_code": "hk", "company": "JFE Consulting Limited", "job_title": "Database Administrator", "description": "Our client, one of the leading IT companies, is looking for high calibres to join their winning team:\n\nResponsibilities\n\n\n\nWorking with database software to find ways to store, organise and manage data\nTroubleshooting\nKeeping databases up to date\nHelping with database design and development\nManaging database access\nDesigning maintenance procedures and putting them into operation\nIn-depth knowledge of Oracle database including RAC, ASM, Data Guard, RMAN.\nPerform database performance tuning, patching, change management and upgrade.\n\nQualifications:\n\n5+ years relevant work experience in Oracle database support.\n10 years relevant IT experiences.\nExperience in DB2 / MS SQL is a plus.\nExperience in Government projects is an advantage.\nProblem-solving skills\nGood organisational skills\nCommunication and interpersonal skills", "employment_types": ["Full Time", "Permanent"], "selling_points": ["Database Administrator", "Experienced in DB2/MS SQL", "attractive salary"], "locations": ["Quarry Bay"], "categories": ["Information Technology (IT)", "DBA", "IT Management", "Data Scientist"], "post_time": "2022-01-17T05:00:33Z", "salary": {"currency": null, "max": null, "min": null, "period": "monthly", "term": null}, "salary_visible": false, "title_keywords": ["administrator"], "responsibilities": ["change management", "software", "maintenance", "data", "designing", "troubleshooting", "design", "procedures", "communication", "databases", "database"], "requirements": {"degrees": [], "majors": [], "languages": [], "language_level": [], "hard_skills": ["plus", "maintenance", "databases", "problem-solving skills", "ms sql", "oracle"], "soft_skills": ["problem-solving skills", "organisational skills", "troubleshooting", "communication and interpersonal skills"], "languages_combined": []}, "experience_required": {"duration": ["10 years", "5+ years"], "field": ["sql", "it", "database"]}}, {"job_id": "100003009051937", "location_code": "hk", "company": "PwC", "job_title": "Senior Manager / Manager - Solution Architect - Technology Consulting (Salesforce)", "description": "Job Description & Summary\n\nA career within General Consulting services, will provide you with the opportunity to help clients seize essential advantages by working alongside business leaders to solve their toughest problems and capture their greatest opportunities. We work with some of the world\u2019s largest and most complex companies to understand their unique business issues and opportunities in an ever changing environment. We help create sustainable change by stimulating innovation, unlocking data possibilities, navigating risk and regulatory complexity, optimising deals, and aligning costs with business strategy to create a competitive advantage.To really stand out and make us fit for the future in a constantly changing world, each and every one of us at PwC needs to be a purpose-led and values-driven leader at every level. To help us achieve this we have the PwC Professional; our global leadership development framework. It gives us a single set of expectations across our lines, geographies and career paths, and provides transparency on the skills we need as individuals to be successful and progress in our careers, now and in the future.\n\nAs a Senior Manager/Manager, you'll work as part of a team of problem solvers, helping to solve complex business issues from strategy to execution. PwC Professional skills and responsibilities for this management level include but are not limited to:\n\nEncourage everyone to have a voice and invite opinion from all, including quieter members of the team.\nDeal effectively with ambiguous and unstructured problems and situations.\nInitiate open and candid coaching conversations at all levels.\nMove easily between big picture thinking and managing relevant detail.\nAnticipate stakeholder needs, and develop and discuss potential solutions, even before the stakeholder realises they are required.\nContribute technical knowledge in area of specialism.\nContribute to an environment where people and technology thrive together to accomplish more than they could apart.\nNavigate the complexities of cross-border and/or diverse teams and engagements.\nInitiate and lead open conversations with teams, clients and stakeholders to build trust.\nUphold the firm's code of ethics and business conduct.\n\nAbout Technology Consulting\n\nTechnology is an important tool for business transformation. Economic climate, regulatory concerns, industry consolidation, virtual workforces - these are just a few of the many issues impacting businesses today. Faced with these issues, companies find that improving performance has become essential as they strive to remain competitive and effective in this challenging environment.\n\nWe bring in-depth knowledge in the following fields:\n\n- CRM/SalesForce\n\n-\u00a0IT transformation\n\n- Enterprise architecture\n\n- Application\n\n- Data management\n\n- IT sourcing\n\n- Deal support\n\nRequirements\n\nA bachelor\u2019s/Master\u2019s degree in Computer Science or Engineer related studies\nOver Eight years experience as a Solution Architect or technology team lead in CRM / SaaS / eCommerce system implementation preferably in Consumer and Financial Services industry\nConsulting Experience is a preferable;\nExperienced in providing wide range of Technology Consulting services to clients, e.g. system implementation & integration, system development life cycle etc.\nExperienced in Salesforce.com technology including VisualForce, APEX class, Salesforce 1\nDeep expertise and hands on experience with Web Applications and programming languages such as HTML, CSS, Java, JavaScript, JQuery, Web Services (REST, SOAP, etc), API's\nSalesforce.com certifications are preferred\nStrong analytical and creative problem solving capabilities\nA proven ability to translate client objectives into deliverable design, and develop deliverables that address complex situations\nGroup facilitation and presentation skills\nThe ability to work directly with senior management and employees throughout client organizations\nFluency in English and Cantonese\n\nKey personal attributes\n\n- In addition, candidates should illustrate the following personal attributes:\n\nDemonstrates courage and integrity\nAcquires and applies commercial and technical expertise by staying up to date in industry and with market trends\nManages projects and economics efficiently; planning and performing work in accordance with client requirements and professional standards\nOpen minded, agile with change and practical\nCommitted to self develop and coaching of others for growth\nCommunicates with impact and empathy\nActively shares ideas and knowledge and is innovate\nLead and contribute to team success\nIs passionate about client service\nWorks hard to build and sustain relationships\n\u6709\u610f\u7533\u8acb\u8005\u8acb \u6309 APPLY NOW\u7533\u8acb\n\n", "employment_types": ["Full Time"], "selling_points": [], "locations": ["Not Specified"], "categories": ["Information Technology (IT)", "Application Specialist - Software", "IT Project Management / Team Lead", "IT Management"], "post_time": "2022-01-17T01:32:56Z", "salary": {"currency": null, "max": null, "min": null, "period": "monthly", "term": null}, "salary_visible": false, "title_keywords": ["senior manager", "manager"], "responsibilities": ["management", "consulting", "data", "teams", "develop", "architecture", "costs"], "requirements": {"degrees": ["degree", "bachelor", "master"], "majors": ["computer science"], "languages": ["cantonese", "english"], "language_level": ["fluency"], "hard_skills": ["java", "salesforce", "apex", "integration", "web applications", "problem solving capabilities", "agile", "jquery", "html", "javascript", "programming", "system implementation", "css", "web services"], "soft_skills": ["agile", "deep", "integrity", "problem solving", "committed", "presentation skills", "hands on", "open minded", "creative", "empathy", "passionate about"], "languages_combined": [{"language": "cantonese", "language_level": ["fluency"]}, {"language": "english", "language_level": ["fluency"]}]}, "experience_required": {"duration": ["eight years"], "field": ["ecommerce", "web applications", "consulting", "solution architect", "programming", "financial services industry", "team"]}}, {"job_id": "100003009036458", "location_code": "hk", "company": "Animoca Brands Limited", "job_title": "IT Manager", "description": "Job Responsibilities\n\nRunning regular checks on network and data security\nIdentifying and acting on opportunities to improve and update software and systems\nDeveloping and implementing IT policy and best practice guides for the organisation\nDesigning training programs and workshops for staff\nConducting regular system audits\nRunning and sharing regular operation system reports with senior staff\nOverseeing and determining timeframes for major IT projects including system updates, upgrades, migrations and outages\nManaging and reporting on allocation of IT budget\nProviding direction for IT team members\nIdentifying opportunities for team training and skills advancement\n\nJob Requirements\n\nBachelor degree in Information Technology, Computer Science or equivalent\nMinimum 8 years\u2019 experience at management level and supervising both development and infrastructure team of a sizeable MNC is essential\nSolid experience in project management and daily IT operation support\nKnowledge in Agile Project Management Model and Software Development Life Cycle (SDLC) would be advantage\nExperience and maturity to work cultural diversities and ability to communicate ideas, standards and policies with confidence\nExcellent verbal and written communication in English\n\nThe Perks:\n\n5-day work week\n15 days annual leave\nMedical, Life & Personal Accident insurance\nCasual work attire\nFree coffee, tea and fruit daily\nMulticultural work environment (15 nationalities and counting!)\nFlat company structure: your ideas get heard by the right people very quickly\nRegular (and fun) company activities\n\nBenefits\n\nA competitive salary and access to a future token / NFT supply as part of the core incentive package\nThe opportunity to join a fast growing unicorn company and make a significant impact\nWork in an inspiring environment and receive ongoing training to develop your technical, leadership and interpersonal skills\n\nInformation provided will be treated in strict confidence and will only be used for recruitment-related purposes. Only short-listed candidates will be contacted. Information of unsuccessful applicants will be destroyed after six months.", "employment_types": ["Full Time", "Permanent"], "selling_points": ["IT Management", "Blockchain", "Infrastructure"], "locations": ["Pok Fu Lam"], "categories": ["Information Technology (IT)", "IT Management"], "post_time": "2022-01-10T10:30:05Z", "salary": {"currency": null, "max": null, "min": null, "period": "monthly", "term": null}, "salary_visible": false, "title_keywords": ["it manager"], "responsibilities": ["migrations", "reporting", "software", "data", "system updates", "upgrades", "outages", "systems", "developing", "it budget", "major it projects", "reports", "designing", "audits", "providing direction"], "requirements": {"degrees": ["degree", "bachelor"], "majors": ["computer science", "information technology"], "languages": ["english"], "language_level": ["excellent"], "hard_skills": ["tea", "agile", "fun", "project management", "sdlc", "operation support"], "soft_skills": ["communication", "project management", "confidence", "agile"], "languages_combined": [{"language": "english", "language_level": ["excellent"]}]}, "experience_required": {"duration": ["minimum 8 years"], "field": ["management", "development", "infrastructure", "project management", "it", "operation", "team"]}}, {"job_id": "100003009048074", "location_code": "hk", "company": "Centre for Intelligent Multidimensional Data Analysis Limited", "job_title": "Computer Programmer (Post A) /  Engineer (Post B) / IT Systems Officer (Post C)", "description": "Duties\nPost A and B\nPerform and maintain application development\nIdentify user requirement and propose solution alternatives\nResponsible for system design, programming, testing and system delivery\nPrepare system documentation and deliver training and support to users\nWork on ad-hoc projects and perform any other duties as assigned\nPost C\nOversees the IT Service Management, Email communication and Special Projects\nDrive project management framework and manage projects life cycle\nResponsible for the implementation of software and hardware asset management\nDrive digital transformations\nDesign, build, and implement enterprise IT architecture\nResponsible for root cause analysis and keep track of corrective actions status\nManage IT budget and procurement\nWork on ad-hoc projects and perform any other duties as assigned\nRequirements\nPost A and B\nHigher Diploma or above in\u00a0Computer Science, Information System or a related discipline with 1-3 years\u2019 relevant working experience\nSolid experience in C/C++, Python, Django and Javascript or other programming languages\nProcess data structure, networking and algorithm knowledge\nPost C\nHigher Diploma or above\u00a0in Computer Science, Computer Engineering, Information Technology or a relevant discipline\nExperience with computer and network management and/or AI and data analysis application software instalments and maintenance\nProgramming and software development skills on desktop and mobile platforms and parallel processors will be an advantage\nAll posts\nGood command of written and spoken English\nExcellent analytical, problem-solving and communication skills\nGood organisational and interpersonal skills\nSelf-motivated, attentive to details and multi-task oriented\nAbility to work under tight schedule is essential\nSalary and Conditions of Service\nRemuneration package will be highly competitive, commensurate with qualifications and experience.\u00a0 Initial appointment will be made on a fixed-term contract.\nWhat you enjoy\n5-day work with stable hours\n18 days annual leave\nMedical and Dental Insurance\nPublic holidays\nCompensation leave\nMPF scheme\nGreat platform to learn and develop new skills in an encouraging environment\nFriendly team\nExcellent office environment (Newly renovated)\nShuttle bus from various locations in Hong Kong\nRecreational facilities in Science Park\nInformation and Application\nInterested parties please apply with full resume including expected salary and available date through email.\nApplications will receive full consideration and only shortlisted and selected applicants will be contacted.\nAn applicant who does not hear from us within 1 month after an interview may assume his/her application is not selected.\nAll information provided by applicants will be treated in strict confidence and used for recruitment purpose only. All personal data of unsuccessful applicants will be retained for 12 months for future recruitment purpose and will then be destroyed.", "employment_types": ["Full Time"], "selling_points": ["18 AL, Medical and Dental Insurance, friendly team", "Programmer, IT Officer, Engineer", "Artificial intelligence & Big Data Analysis"], "locations": ["Shatin Area"], "categories": ["Information Technology (IT)", "IT Management", "Software Development", "UI/UX Designer"], "post_time": "2022-01-14T04:41:39Z", "salary": {"currency": null, "max": null, "min": null, "period": "monthly", "term": null}, "salary_visible": false, "title_keywords": ["officer", "programmer", "engineer"], "responsibilities": ["any other duties", "it service", "software", "system delivery", "design", "communication", "maintain", "manage projects", "ad-hoc projects", "application development", "user requirement", "system documentation", "implementation", "testing", "architecture", "management", "it budget", "analysis", "project management", "hardware", "system design", "asset management"], "requirements": {"degrees": ["higher diploma or above"], "majors": ["computer engineering", "computer science", "information technology"], "languages": ["english"], "language_level": ["good command"], "hard_skills": ["network management", "c++", "ai", "maintenance", "analysis", "problem-solving", "information system", "scheme", "mobile", "c", "javascript", "programming", "python"], "soft_skills": ["communication skills", "self-motivated", "attentive to details", "multi-task oriented", "problem-solving", "interpersonal skills", "friendly", "stable"], "languages_combined": [{"language": "english", "language_level": ["good command"]}]}, "experience_required": {"duration": ["1-3 years"], "field": ["management", "maintenance", "related", "relevant working experience", "data analysis", "programming"]}}, {"job_id": "100003009049301", "location_code": "hk", "company": "The Bank of East Asia, Limited", "job_title": "Senior IT Project Manager", "description": "To be a team member of Information Technology Department\nTo supervise a project team to manage and monitor the implementation of digital solutions projects and large scale projects\nTo plan, control and oversee all phases of the projects and deliver the projects within budget and time\nTo plan IT related projects in scope, schedule, cost, resources, security, quality, and communication according to the objectives\nTo monitor and control IT project executions, and resolve the constraints in scope, schedule, cost, resources, quality, security and risk\nTo plan and conduct tendering or procurement activities including the acquisition of necessary total system solutions, implementation services, hardware and software, services for security risk assessment and audit\nTo liaise with business users to ensure project scope, schedule, cost and progress as planned\nTo be proactively manage, lead, and guide the following IT parties to collaborate for achieving the project objectives\nTo define the communication plan and report the project status with risk efficiently to the project stakeholders\nTo comply with all applicable regulations, rules, codes, guidelines and standards set by regulators and the Bank, and carry out duties with high integrity\n\n\nRequirements\n\n\n\n\nBachelor Degree in in Business Administration, Finance, Management Information System, Computer Science or related discipline is preferred\nWith over 10 years experience in IT sector, project management, banking experience is preferable\nPossess strong planning, decision making, management as well as verbal and written communication skills, with extensive experience in managing large-scale projects\nPossess extensive implementation / support experience in system development and multi-vendor mission critical system\nExperience in implementation / support of Wealth Management / Treasury systems / FinTech / Mobile is an added advantage\nProficient in in leading and motivating team members, collaborating with users and managing contractors as well as other external stakeholders\nHighly sensitive to any factors affecting schedule and resources, with planning ahead before the risks realised\nProvide responsive and appropriate actions to resolve difficulties in order to steer towards the project goals\nStrong communication and report writing skills; Good command of both written and spoken English and Chinese\n\u6709\u610f\u7533\u8acb\u8005\u8acb \u6309 APPLY NOW\u7533\u8acb", "employment_types": ["Full Time"], "selling_points": [], "locations": ["Not Specified"], "categories": ["Information Technology (IT)", "IT Project Management / Team Lead", "IT Management", "Software Development"], "post_time": "2022-01-14T08:24:32Z", "salary": {"currency": null, "max": null, "min": null, "period": "monthly", "term": null}, "salary_visible": false, "title_keywords": ["it project manager"], "responsibilities": ["regulations", "software", "budget", "quality", "tendering", "audit", "communication", "plan", "liaise with", "administration", "collaborate", "control", "monitor", "implementation", "schedule", "banking", "report", "cost", "management", "guidelines", "systems", "hardware", "project management", "planning"], "requirements": {"degrees": ["degree", "bachelor"], "majors": ["finance", "business administration", "computer science"], "languages": ["english", "chinese"], "language_level": ["good command"], "hard_skills": ["information system", "vendor", "writing skills", "hardware", "project management", "mobile", "codes"], "soft_skills": ["communication skills", "responsive", "integrity", "writing skills", "communication", "project management", "sensitive to", "team member", "extensive", "decision making"], "languages_combined": [{"language": "english", "language_level": ["good command"]}, {"language": "chinese", "language_level": ["good command"]}]}, "experience_required": {"duration": ["10 years"], "field": ["management", "banking experience", "system development", "project management", "it", "planning"]}}, {"job_id": "100003009050928", "location_code": "hk", "company": "The Hang Seng University of Hong Kong", "job_title": "Assistant Information Security Manager / Senior Information Security Officer", "description": "Assistant Information Security Manager / Senior Information Security Officer\u00a0\u2013 Information Technology Services Centre (Ref: AISM / SISO (ITSC) 2022-01-14)\n\n(Ref: AISM / SISO (ITSC) 2022-01-14)\n\n\n\nResponsibilities:\n\nreview and update security documents such as policies and guidelines;\nassess risks on applications, systems, networks and adopt security measures in a balance manner for risk mitigation;\naudit and run tests on systems and infrastructure to identity possible issues;\nensure digital assets adequately protected, effectively monitored and managed;\nprovide latest updates on information security to general users to increase their awareness; and\nexplore suitable information security technologies that can better safeguard the information in the university.\n\nApplicants should:\n\npossess a recognised bachelor\u2019s degree or above in Computer Science or related discipline;\npossess updated and relevant qualifications such as CISM, CISSP, CEH, ISO27001;\npreferably have at least 10 years of relevant work experience;\nhave proven records in information security and system auditing in application, networks and system level;\nhave good interpersonal, communication, analytical and problem-solving skills;\nhave good command of written and spoken English and Chinese; and\nbe pleasant with positive mindset, good customer sense and willing to learn new technologies.\n\nThe appointee will be required to work during non-office hours.\u00a0 Work experience in the higher education sector will be an advantage.\u00a0 Applicants with fewer years of experience could be considered as Senior Information Security Officer.\u00a0\n\n\nSalary will be commensurate with qualifications and experience.\u00a0 Interested applicant should visit this link https://recruit.hsu.edu.hk/ and apply on or before 30 January 2022.\u00a0 The University reserves the right not to fill the position in this exercise.\n\nApplicants who are not invited to an interview within three months may consider their applications unsuccessful.\u00a0 All information received will be treated in strict confidence, and the data collected will be used for recruitment purposes only.\u00a0 The Personal Information Collection Statement will be provided upon request.\n\nthe Hang Seng University of Hong Kong, incorporated in Hong Kong with limited liability by guarantee, is an equal opportunity employer.", "employment_types": ["Full Time"], "selling_points": [], "locations": ["Shatin Area"], "categories": ["Information Technology (IT)", "IT Auditing", "IT Management", "Application Specialist - Network"], "post_time": "2022-01-14T11:49:37Z", "salary": {"currency": null, "max": null, "min": null, "period": "monthly", "term": null}, "salary_visible": false, "title_keywords": ["information security manager", "senior information security officer", "assistant"], "responsibilities": ["information security", "data", "guidelines", "policies", "review", "systems", "audit", "infrastructure", "communication", "recruitment", "assess risks", "auditing"], "requirements": {"degrees": ["degree or above", "bachelor"], "majors": ["computer science"], "languages": ["english", "chinese"], "language_level": ["good command"], "hard_skills": ["problem-solving skills"], "soft_skills": ["confidence", "positive mindset", "willing to learn", "pleasant", "communication", "problem-solving skills", "interpersonal"], "languages_combined": [{"language": "english", "language_level": ["good command"]}, {"language": "chinese", "language_level": ["good command"]}]}, "experience_required": {"duration": ["at least 10 years"], "field": ["security", "education"]}}, {"job_id": "100003009045015", "location_code": "hk", "company": "St. James' Settlement", "job_title": "Information Technology Manager (Contract)\u3008Ref: SSPDH/04722\u3009", "description": "District Health Centre\n\n\n\nRequirement:\n\nlBachelor Degree or above in Computer Science, Information System or related disciplines\n\nlAt least 5 years post degree experiences in IT system project coordination and vendor management\n\nlPrior experience in non-governmental organization (NGO), welfare or medical sector an added advantage\n\nlExcellent IT/software knowledge is required and has good ability to work with government officials, business partners and various stakeholders\n\nlTechnical certifications in PMP and/or SCRUM is an advantage\n\nlGood team player, work independent, good communication skills and hardworking\n\n\u00a0\nJob Duties:\n\nlResponsible to lead the IT development of applications and infrastructure as well as to provide project management, vendor management and audit support\n\nlCompleting technical studies, prepare cost estimation, interface with project contractors and keep track of their deliverables\n\nlCapable to deliver project control and monitoring, suggest solutions for any charge and difficulty\n\nlSecure in-house IT system to maintain daily operation smoothly\n\nlAssist to provide user training and user guide for existing or new system\n\nInterested persons please apply with full resume via APPLY NOW\u00a0on or before 04/02/2022.\n**When recruiting staff for job positions relating to services for child or mentally incapacitated persons, we shall request applicants to undergo the Sexual Conviction Record Check.**\n\n\u300cPersonal data collected will be strictly used for the recruitment exercise only. Unsuccessful applications will be destroyed one year after the closing date.\u300d", "employment_types": ["Full Time", "Contract"], "selling_points": ["degree in Computer Science, Information System", "At least 5 yrs exp. in IT", "Excellent IT/software knowledge is required"], "locations": ["Sham Shui Po"], "categories": ["Information Technology (IT)", "IT Management", "Network & System"], "post_time": "2022-01-13T06:54:12Z", "salary": {"currency": null, "max": null, "min": null, "period": "monthly", "term": null}, "salary_visible": false, "title_keywords": ["technology manager"], "responsibilities": ["management", "control", "cost estimation", "infrastructure", "monitoring", "audit", "daily operation", "project management", "maintain", "recruitment", "personal data"], "requirements": {"degrees": ["degree or above", "degree"], "majors": ["related disciplines", "it", "computer science"], "languages": [], "language_level": [], "hard_skills": ["pmp", "information system", "vendor"], "soft_skills": ["communication skills", "independent", "coordination", "team player", "hardworking"], "languages_combined": []}, "experience_required": {"duration": ["least 5 years"], "field": ["management", "it", "medical"]}}, {"job_id": "100003009048391", "location_code": "hk", "company": "Shun Tak Holdings Ltd", "job_title": "Assistant Manager, Technical Infrastructure & Support Services (Ref.STHL1706)", "description": "Key Responsibilities\n\nResponsible for growing the cybersecurity program and evolving the Group's transition to a mature secure and operational robust environment;\nProvide day to day services delivery, infrastructure architecture & operate excellence improvement program;\nEnsure the IT strategy for infrastructure and security requirements support the business growth and strategy;\nImplement and oversee the deployment of information security and IT infrastructure technologies;\nDevelop and implement business continuity plans, security best practice, threat intelligence, and incident response;\nDrive a continuing program of engagement to ensure everyone in the company is part of our cybersecurity defense;\nLead the technical infrastructure & support services team to deliver best-in-class technology services & minimize the risk of cyber-attacks;\nAssist Associate Director of Group Information System on developing the IT strategy for infrastructure and cybersecurity requirements.\n\nRequirement\n\nDegree in Computer Science / Computing in Information System / Data Science & Analytics or Digital / Technology or related discipline;\nAppropriate industry-recognized security qualifications or equivalent;\nMore than 6-8 years' experience in technical infrastructure & services tear for developer & proven track record for successfully managing and implementing technical infrastructure projects;\nGood command of both written and spoken English and Chinese, including Mandarin;\nExcellent communication skills to demonstrate clear interpretation and presentation of results to various stakeholders.\n\nWe offer long-term career prospect and competitive remuneration package to the appointed candidate. Please apply in confidence with your detailed resume stating your current and expected salary to\u00a0Group Human Resources Department\n\nby email to\u00a0recruit(at)shuntakgroup.com\n\nor mail to\u00a0Penthouse 39/F, West Tower, Shun Tak Centre, 200 Connaught Road Central, Hong Kong\n\n(Please quote reference number and applied position)\n\nThe information supplied by the applicants will be used in accordance with the Personal Data (Privacy) Policy of Shun Tak Group (a copy of which will be provided upon request). Only shortlisted candidates will be notified.\n\n\nwww.shuntakgroup.com", "employment_types": ["Full Time", "Permanent"], "selling_points": ["Provide day to day services delivery", "Develop IT strategy", "Growing the cybersecurity program & infrastructure"], "locations": ["Sheung Wan"], "categories": ["Information Technology (IT)", "IT Management", "Security", "Network & System"], "post_time": "2022-01-14T06:27:39Z", "salary": {"currency": null, "max": null, "min": null, "period": "monthly", "term": null}, "salary_visible": false, "title_keywords": ["assistant manager,"], "responsibilities": ["business continuity", "it infrastructure", "information security", "infrastructure", "support services", "developing", "develop", "plans", "architecture"], "requirements": {"degrees": ["degree"], "majors": ["data science", "computer science"], "languages": ["english", "chinese", "mandarin"], "language_level": ["good command"], "hard_skills": ["information system"], "soft_skills": ["clear", "communication skills", "presentation"], "languages_combined": [{"language": "english", "language_level": ["good command"]}, {"language": "chinese", "language_level": ["good command"]}, {"language": "mandarin", "language_level": ["good command"]}]}, "experience_required": {"duration": ["6-8 years"], "field": ["developer", "infrastructure"]}}, {"job_id": "100003009054641", "location_code": "hk", "company": "China Mobile Hong Kong \u4e2d\u570b\u79fb\u52d5\u9999\u6e2f", "job_title": "Business Analyst/Senior Business Analyst", "description": "CHINA MOBILE HONG KONG COMPANY LIMITED\u00a0(\"CMHK\") is the wholly-owned subsidiary of China Mobile Limited (HKEx: 941) (NYSE: CHL), which ranks 56th on the Fortune Global 500.\n\nOur company strives to offer superior service experience and to become the preferable digital partner for customers. We are preserving an environment with trust, responsibility and caring. At CMHK, we commit to maximizing people\u2019s potential and paving the way toward success for every striver. We are now inviting high caliber professional to join us.\n\nIn this position, you will:\n\nManage business requirements gathering, analysis and documentation. Act as a bridge between business users, technical team and vendors to ensure the business requirements well address business needs\nDevelop, review, and edit requirements, specifications, business processes and recommendations related to a proposed solution\nWork closely with development team and external vendors to ensure the requirements can be completed timely\u00a0\nPrepare and maintain technical specification and documentation\n\nTo be successful in this position, you should meet the following requirements:\n\n\nBachelor Degree in Computer Science, Business Analytics, Information Technology, Logistics or other related discipline\n3 years related working experience, preferably in Telecom Industry\nPractical experience in understanding, analyzing and verifying user requirement versus business processes to develop programmable documents\nGood command of written and spoken English and Chinese (including Putonghua)\nHave good learning and communication skills.\nSelf-motivated, positive, able to work under pressure with emphasis on deliverables\nGood communication and interpersonal skills\n\n\n\nWhen you work:\n\n5 days work\n8 hours/day\n\nWhat you enjoy:\n\nDouble pay\nDiscretionary performance bonus\nLife insurance\nMedical insurance\nBirthday gift\nMarriage leave\nBirthday leave\nCompassionate leave\u00a0\nStaff discount\n\nCMHK is committed to be an equal opportunity employer. We offer exceptional benefits package and the opportunity to work in a challenging environment. Personal data provided by applicants will be treated strictly in accordance with our personal data policy and for recruitment purposes only.\n\nPlease submit your application to us by clicking the APPLY NOW button and send your full resume with your availability, current and expected salary to us", "employment_types": ["Full Time", "Permanent"], "selling_points": ["3 years related working experience", "Bachelor Degree in IT/Business Analyst", "Excellent career development with good benefit"], "locations": ["Kwai Hing"], "categories": ["Information Technology (IT)", "IT Management", "Software Development", "Network & System"], "post_time": "2022-01-17T10:23:16Z", "salary": {"currency": null, "max": null, "min": null, "period": null, "term": null}, "salary_visible": false, "title_keywords": ["senior business analyst", "business analyst"], "responsibilities": ["user requirement", "analysis", "review", "develop", "communication", "specifications", "maintain", "logistics", "documentation", "insurance", "work under pressure"], "requirements": {"degrees": ["degree", "bachelor"], "majors": ["business analytics", "computer science", "information technology"], "languages": ["putonghua", "english", "chinese"], "language_level": ["good command"], "hard_skills": ["documentation", "mobile", "analysis"], "soft_skills": ["communication skills", "self-motivated", "work under pressure", "timely", "committed", "learning", "communication and interpersonal skills", "positive", "superior"], "languages_combined": [{"language": "putonghua", "language_level": ["good command"]}, {"language": "english", "language_level": ["good command"]}, {"language": "chinese", "language_level": ["good command"]}]}, "experience_required": {"duration": ["3 years"], "field": ["related", "digital", "business"]}}, {"job_id": "100003009055634", "location_code": "hk", "company": "Gravitas Recruitment Group", "job_title": "Global Insurance Firm - Cloud (AWS) Engineer", "description": "Great opportunity to join a global insurance firm.\n\nWe are looking for a new technical Cloud (AWS) Engineer to join our enterprise infrastructure team. Ideally, this technical hand-on Cloud (AWS) Engineer has extensive experience implementing cloud (AWS) and other related security and infrastructure enterprise projects. In addition to this, this Engineer would be providing ongoing technical internal support.\n\nResponsibilities:\n\nCloud, infrastructure and security project implementation, which includes working with the respective vendors.\nPerform and oversee software installation, upgrades and maintenance, remediate vulnerabilities and keep patch updates to systems\nDevice configuration of switch, server, firewall, Email support systems, anti-spam etc.\nL2 technical IT helpdesk support\n\nMinimum Requirements:\n\n3-5 years of technical cloud(AWS) implementation experience\n3-5 years experience in Infrastructure management, network administration, and network security related experience\nStrong team player with a proactive and willingness to learn attitude\nProfessional certification in Cisco Certified Network Associate (CCNA), Microsoft Certificated System Engineer (MCSE), System Administrator (MCSA) or equivalent\nUniversity degree in Computer Science, Information Systems or other technology-related disciplines\nFluent in both spoken and written English and Chinese\n\nHighly Preferred:\n\nExperience with Microsoft 365 (Office 365)\nKnowledge on Cybersecurity market standards like CISSP (Certified Information Systems Security Professional)\nEnterprise financial institution exposure (insurance or banking)", "employment_types": ["Full Time", "Permanent"], "selling_points": ["Broad project exposure opportunities", "Good work-life balance environment", "Great career development"], "locations": ["Not Specified"], "categories": ["Information Technology (IT)", "IT Project Management / Team Lead", "IT Management", "Others"], "post_time": "2022-01-18T02:48:52Z", "salary": {"currency": "HKD", "max": 54999, "min": 30000, "period": "monthly", "term": null}, "salary_visible": true, "title_keywords": ["engineer"], "responsibilities": ["installation", "software", "maintenance", "upgrades", "configuration", "infrastructure", "systems", "implementation"], "requirements": {"degrees": ["university degree"], "majors": ["related disciplines", "computer science"], "languages": ["english", "chinese"], "language_level": ["fluent"], "hard_skills": ["network administration", "mcse", "office 365", "ccna", "mcsa", "cisco certified network associate"], "soft_skills": ["team player", "proactive"], "languages_combined": [{"language": "english", "language_level": ["fluent"]}, {"language": "chinese", "language_level": ["fluent"]}]}, "experience_required": {"duration": ["3-5 years"], "field": ["network administration", "management", "related", "infrastructure", "security"]}}, {"job_id": "100003009043854", "location_code": "hk", "company": "Top Form International Limited", "job_title": "IT Project Manager", "description": "Job Responsibilities:\n\n\nReport to Group Technology Director, the incumbent will collaborate amongst business units, IT Teams and external vendors to drive technical development work of key upgrade and digital transformation initiatives that are aligned to group business objectives\nAssist in the formulation and realization of information technology strategies and digital transformation programs that can enable the success of business initiatives\nPerform master planning, organizing, staffing, controlling of programs and project activities to ensure successful project delivery with expected results and benefits within budget and on-time\nPlay an important role in the development of the next generation ERP platform to optimize vertical business operation for the Group\nWork closely with application, infrastructure and business process optimization projects\nOccasional travel is required\n\nJob Requirements:\n\n\nDegree holder in Information Technology, Information Management or related disciplines\nHolder of Project Management Certifications such as PMP, PRINCE2 or equivalent\nMinimum 5 years\u2019 solid experience in designing, developing, deploying and enhancing enterprise class web based application systems for regional multiple locations, manufacturing and supply chain businesses\nFamiliar with problem solving and programming methodology, able to identify system and programming issues and resourceful in providing solutions\nFamiliar with current technology such as RPA, BI reporting, AI, and IoT\nAble to perform Proof-of-Concept for new technology adoption\nExcellent interpersonal and leadership skills\nGood command of written and spoken English, Cantonese and Mandarin\nSelf-starter, hands-on, result-oriented, good team player and high level of integrity\nGarment manufacturing experience is an advantage\n\nWe offer competitive remuneration package including 5-day work week, birthday leave, personal accident insurances as well as excellent career prospects to the right candidate. Interested parties please send full resume with current and expected salary to the Group HR & Administration\u00a0Department.\u00a0\n\nFor more details about our Group, please visit our website at http://www.topformbras.com/\n\nWe are an equal opportunity employer. We value the diversity of individuals, ideas, perspectives, insights and values, and what they bring to the workplace. Applications from all qualified candidates are welcome. Personal data collected will be kept and handled confidentially by authorized personnel for recruitment purpose only. It may also be disclosed to our subsidiaries or associates to process the information for appointment. Applicants who are not contacted within four weeks may consider their application unsuccessful. The applications will be retained for a maximum period of 12 months after the selection process is finalized and we may refer suitable applicants to other vacancies within the Group. A copy of our Personal Information Collection Statement can be provided upon request by contacting Group HR & Administration Department at the above email address.", "employment_types": ["Full Time", "Permanent"], "selling_points": ["Collaborate amongst team for technical development", "Formulate and realize IT strategies and programs", "5-days work, 13-mth salary, Birthday Leave"], "locations": ["Wong Tai Sin Area"], "categories": ["Manufacturing", "Garment / Textile", "Information Technology (IT)", "IT Project Management / Team Lead", "IT Management"], "post_time": "2022-01-13T02:11:26Z", "salary": {"currency": null, "max": null, "min": null, "period": "monthly", "term": null}, "salary_visible": false, "title_keywords": ["it project manager"], "responsibilities": ["collaborate", "business operation", "business initiatives", "budget", "technology strategies", "teams", "infrastructure", "business process", "master planning", "report"], "requirements": {"degrees": ["degree holder"], "majors": ["related disciplines", "information technology"], "languages": ["cantonese", "english", "mandarin"], "language_level": ["good command"], "hard_skills": ["bi", "web", "ai", "problem solving", "project management", "rpa", "programming", "pmp"], "soft_skills": ["result-oriented", "good team player", "resourceful", "leadership skills", "integrity", "problem solving", "project management", "hands-on", "interpersonal"], "languages_combined": [{"language": "cantonese", "language_level": ["good command"]}, {"language": "english", "language_level": ["good command"]}, {"language": "mandarin", "language_level": ["good command"]}]}, "experience_required": {"duration": ["minimum 5 years"], "field": ["garment", "manufacturing", "supply chain", "developing", "application systems"]}}, {"job_id": "100003009037870", "location_code": "hk", "company": "Seamatch Asia Limited", "job_title": "Assistant IT Manager / System Administrator / Assistant Project Manager (inhouse, 5 days work)", "description": "Responsibilities:\n\nResponsible for IT Infrastructure support, system performance and service monitoring, proactive system tuning, backup operation, Intranet / website maintenance\nUnderstand and apply system wide workflow and processes as well as relationships with other internal and external parties\nAssist company to achieve Digital Transformation through internal process automation.\nAssist and enhance IT security in Corporate standard\nBe an Administrator of Office 365 infrastructure and daily operations on system support\nWork with Development Team for in-house application enhancement\nOversee and assist IT department on IT system, cost control, analyses company needs and implement improvement solution\n\n\u00a0Requirements:\n\nMinimum 5-8 years of working experience in IT infrastructure, application system support, and or end user support, with experience in ERP, PLM, SAP\nExperience on setup, maintain oversea offices enterprise infrastructure, Active Directory, Group Policy, O365, Identify and Access Management, Windows, Linux, and cloud services (Azure)\nKnowledge in Programming language (Java / Python / C++)\nKnowledge in IT security\nWith detail minded, high accuracy and be sensitive in numbers\nWith leadership of responsibility and willing to corporate with teammates\nProficient in both spoken and written English", "employment_types": ["Full Time"], "selling_points": ["Assistant IT Manager", "System Administrator", "Project Manager"], "locations": ["Not Specified"], "categories": ["Information Technology (IT)", "IT Management", "Application Specialist - Network", "Security"], "post_time": "2022-01-11T04:06:30Z", "salary": {"currency": null, "max": null, "min": null, "period": "monthly", "term": null}, "salary_visible": false, "title_keywords": ["assistant project manager", "system administrator", "it manager", "assistant"], "responsibilities": ["it infrastructure", "monitoring", "internal and external parties", "website maintenance", "infrastructure", "daily operations", "cost control"], "requirements": {"degrees": [], "majors": [], "languages": ["english"], "language_level": ["proficient"], "hard_skills": ["o365", "linux", "java", "azure", "active directory", "sap", "c++", "application system", "erp", "programming", "python"], "soft_skills": ["active", "leadership", "sensitive"], "languages_combined": [{"language": "english", "language_level": ["proficient"]}]}, "experience_required": {"duration": ["minimum 5-8 years"], "field": ["infrastructure", "system support", "it", "management"]}}, {"job_id": "100003009046848", "location_code": "hk", "company": "Nexify Limited", "job_title": "Project Manager - IT Project", "description": "Nexify Limited is one of the leading IT solution providers specialized in system integration in Hong Kong. We encourage innovation, teamwork and personal growth. With continuous business expansion, we need high calibre candidates to join our professional team and we offer exciting job opportunities to the right talents. If you want to work in a fun and energetic environment, please do not hesitate to apply!\n\n\nJob Description\n\n\nDeliver projects within budget and time\nPlan and control all phases of IT project including feasibility study, systems analysis and design, procurement and installation of computer systems, programming, implementation, system nursing and maintenance\nSchedule and assign duties to subordinates\nEstablish procedures and performance measurements to monitor the technical accomplishment and progress of projects\nDevelop project management plans and quality control parameters\nOther duties as assigned\u00a0\n\n\u00a0Job Requirements\n\nDegree holder in Computer Science, Information Systems or related disciplines\nAt least\u00a08\u00a0years of post-qualification IT experience including at least\u00a04\u00a0years of project management experience in system design and implementation and/or system maintenance and support of IT systems\nBe a certified Project Management Professional (PMP) and/or a certified PRINCE2 practitioner\nSelf-motivated and able to work under pressure to meet project deadlines\nProficient in written and spoken English and Chinese\nPossessing work experiences for the HKSARG would be an advantage\n\nBenefits:\n\n5-Day Work Week\nPerformance bonus\nMarriage Leave\nPaternity Leave\nBirthday Leave\nMedical allowance\nCompassionate Leave\nExamination Leave\nPromotion opportunities\nIn-service training course\n\nWe offer 5-day work with good career prospects and excellent fringe benefits to the right candidates. Different areas of IT solution training (Such as Microsoft, IBM, Oracle or Mobile Application Development) will be provided. \u00a0Please send a full resume in MS Word Format including current and expected salary by clicking \"Apply Now\".", "employment_types": ["Full Time", "Permanent"], "selling_points": ["Plan and control all phases of IT project", "Certified PMP / PRINCE2 practitioner", "Attractive remuneration package & 5 days work"], "locations": ["Kwun Tong"], "categories": ["Information Technology (IT)", "IT Project Management / Team Lead", "IT Management", "Software Development"], "post_time": "2022-01-14T01:27:50Z", "salary": {"currency": null, "max": null, "min": null, "period": "monthly", "term": null}, "salary_visible": false, "title_keywords": ["project manager"], "responsibilities": ["installation", "control", "maintenance", "other duties", "analysis", "budget", "systems", "computer systems", "design", "implementation", "procedures", "monitor", "develop", "project management", "schedule", "plan", "quality control", "plans"], "requirements": {"degrees": ["degree holder"], "majors": ["related disciplines", "computer science"], "languages": ["english", "chinese"], "language_level": ["proficient"], "hard_skills": ["maintenance", "project management professional", "project management", "system design", "pmp"], "soft_skills": ["project management", "self-motivated", "work under pressure"], "languages_combined": [{"language": "english", "language_level": ["proficient"]}, {"language": "chinese", "language_level": ["proficient"]}]}, "experience_required": {"duration": ["at least 8 years", "at least 4 years"], "field": ["post-qualification", "maintenance", "it experience", "project management", "system design", "it"]}}, {"job_id": "100003009049454", "location_code": "hk", "company": "United Search Group (Asia) Limited", "job_title": "Project Coordinator (A.I. Technology Firm-Good Salary Package)", "description": "Our client is a leading A.I. tech company for smart city solution in Hong Kong. They build patented safety AI technology especially for smart buildings and smart infrastructure.\u00a0They offer AI SaaS solution as well as AI services for property owners and property management companies and government.\u00a0Their solution dramatically increases the safety co-efficient of buildings and infrastructure by boosting the inspection and monitoring efficiency and accuracy with lower costs. Their technology has been well-proven with numerous reputable landmark properties in Hong Kong.\u00a0They are looking for a Project Coordinator\u00a0to join their professional team in Hong Kong.\n\nWhat you\u2019ll be doing?\n\nResponsible for day-to-day project management, manage quality, scope, cost, and time of projects, ensure all aspects are fulfilled as agreed\nLiaise with internal and external parties to ensure smooth project operations\nProvide timely update on project status, ensure all stakeholders are on the same page with same info\nManage project management system and related components for projects assigned\nProvide insights and recommendations for process improvement\nTo perform ad hoc project as required\n\nWho\u00a0are they looking\u00a0for?\n\nUniversity degree in Engineering, Project Management or related discipline\nMin. 2 years\u2019 solid experience in project and workflow management, exposure in engineering or IT industry preferred\nThorough understanding of different stages and performance identifiers of a project\nGood communication and language skills, including verbal and written English and Cantonese\nStrong problem solving skills\nStrong sense of ownership, business acumen, performance driven and target oriented\nCandidate with more experience will be considered as managing role\n\nWhat are they offering?\n\n5-day work with work life balance\nConvenient location, MTR and shopping complex within 5 mins walk\nYoung, energetic team with casual dress code and flexible lunch\nStocked pantry with variety of snack and your choice of coffee\nCompetitive package with good career path to the right candidate\n\nIf you are qualified and interested, please send your full resume with current & expected salary and availability by clicking \"Apply now\"., or send your CV at info @ usgroupasia.com", "employment_types": ["Full Time", "Permanent"], "selling_points": ["A.I. Technology Firm with good career development", "5-day work with work life balance & good salary", "Engineering / Project Management Experience"], "locations": ["Kowloon City Area"], "categories": ["Building & Construction", "Building / Construction / QS", "Information Technology (IT)", "IT Project Management / Team Lead", "IT Management"], "post_time": "2022-01-14T08:41:49Z", "salary": {"currency": null, "max": null, "min": null, "period": "monthly", "term": null}, "salary_visible": false, "title_keywords": ["project coordinator"], "responsibilities": ["provide insights", "management", "cost", "ad hoc", "operations", "infrastructure", "monitoring", "quality", "internal and external parties", "inspection", "communication", "project management", "liaise with", "costs"], "requirements": {"degrees": ["university degree"], "majors": ["project management", "engineering"], "languages": ["cantonese", "english"], "language_level": ["good"], "hard_skills": ["ai", "project management", "code", "problem solving skills", "acumen"], "soft_skills": ["efficient", "flexible", "responsible", "timely", "communication", "project management", "thorough", "smooth", "business acumen", "problem solving skills", "energetic", "driven"], "languages_combined": [{"language": "cantonese", "language_level": ["good"]}, {"language": "english", "language_level": ["good"]}]}, "experience_required": {"duration": ["2 years"], "field": ["management", "it", "engineering"]}}, {"job_id": "100003009047000", "location_code": "hk", "company": "AXA Hong Kong", "job_title": "IT Service Management Director", "description": "Responsibilities:\n\n\u00b7 Design and deliver a platform for a robust support and service management & cyber security model for the General Insurance, Life and Enterprise business units in AXA Hong Kong in line with ITIL SM, drive quality and stability of the production environment\n\u00b7 Ensure consistency between the production and UAT environments\n\u00b7 Monitoring the effectiveness of the team and suppliers against SLA/KPI\u201fs, driving through change as needed to deliver continual service improvement, quality and stability\n\u00b7 Ensure operational procedures and practices are well defined, documented and consistently applied\n\u00b7 Instil a high performance culture in the team with a focus on team work, service excellence and ownership for resolving customer issues\n\u00b7 Be capable of identifying and implementing change within the team to ensure it can take on new service offerings.\n\u00b7 Contribute proactively to new service development.\n\u00b7 Work closely with the project teams to ensure new solutions are on-boarded with seamless handover / transition into production service\n\u00b7 Encourage open communication between team members, allowing the team to bring forward ideas on how they can collectively deliver a more effective service\n\u00b7 Set and cascade business objectives and targets to the team\n\u00b7 Ensure teams are skilled, trained and developed to enable them to deliver high quality service and support\n\u00b7 Manage and develop strategic partnerships with third party suppliers and other internal stakeholders\n\u00b7 Ensure quality, up-to-date documentation exists for all service arrangements\n\u00b7 Provide input into the divisional strategy with particular focus into opportunities to grow and/or enhance the service offered\n\u00b7 Provide leadership and direction to the service management function ensuring appropriate and robust service management and review frameworks are in place\n\u00b7 Take responsibility for customer escalations and act as a point of escalation and communication both in and out of hours as required\n\u00b7 Drive a continual service improvement programme to optimize and drive efficiencies in support operations for the systems\n\nRequirements:\n\n\u00b7 Bachelor's degree in Computer Science, related field (e.g., Engineering), or Business Management\n\u00b7 Operational experience that includes working across a broad section of IT services\n\u00b7 Strong background in IT service delivery (ten years minimum)\n\u00b7 Experience in a direct IT- business engagement role\n\u00b7 Has participated in design and/or implementation of major IT projects\n\u00b7 Communicates well with customers who are not tech savvy\n\u00b7 Has experience dealing with vendors and other people who are supplying the product or service\n\u00b7 Ability to set strategy\n\u00b7 Ability to develop and assess progress on a complex financial plan\n\u00b7 Good at managing relationships and networking across the IT function\n", "employment_types": ["Full Time", "Permanent"], "selling_points": ["IT Service Delivery", "IT- business engagement", "Team management"], "locations": ["Not Specified"], "categories": ["Information Technology (IT)", "IT Project Management / Team Lead", "Support", "IT Management"], "post_time": "2022-01-14T02:00:06Z", "salary": {"currency": null, "max": null, "min": null, "period": "monthly", "term": null}, "salary_visible": false, "title_keywords": ["director"], "responsibilities": ["management", "ideas", "uat", "cyber security", "operations", "monitoring", "quality", "teams", "design", "develop", "communication", "review", "systems", "operational procedures", "documentation", "customer issues", "insurance", "third party"], "requirements": {"degrees": ["degree", "bachelor"], "majors": ["computer science"], "languages": [], "language_level": [], "hard_skills": ["business management"], "soft_skills": [], "languages_combined": []}, "experience_required": {"duration": [], "field": ["business", "it"]}}, {"job_id": "100003009042721", "location_code": "hk", "company": "Arup", "job_title": "Operations Manager - East Asia", "description": "A career at Arup offers you the chance to make a positive difference in the world. Independently owned and independently minded, we attract a diverse mix of people to work on ground-breaking global projects. We have an ambitious commitment to be the digital leader in the built environment and have digital teams and experts all over the world who collaborate on world-leading software, data and technology projects and products. Being a global team means we value people with diverse experiences, backgrounds, specialisms and skills.\n\nOur Digital Technology team are proud winners of the IT Team of the Year for 2021 at the Chartered Institute of IT\u2019s UK IT Industry Awards.\n\nThe role\n\nGeographically dispersed, delivering a \u2018follow-the-sun\u2019 operational model, Digital Technology provides support and consultancy services for internal and external clients. We have an exciting opportunity within our global operations management team focussed on providing high-quality IT support services across the East Asia Region (EAR) which includes offices in Hong Kong, mainland China, Thailand, Vietnam, Manila, South Korea and Japan. Of these, the majority of our business colleagues are hosted within either Hong Kong or mainland China; this new role is for a mature, self-motivated full-time individual to be based at our Hong Kong office.\n\nYou will work with specialist IT support teams that manage global infrastructure services (e.g. Networking, Cloud Services, Compute & Storage, Endpoint Management & Unified Communications) and core applications, including SaaS services such as Microsoft O365 & Teams and IaaS/PaaS services within Azure, AWS and on-premises within Co-location suites. The role reports to the infrastructure and operations leader who is based in the UK.\n\nThe role may require occasional working outside of standard office hours (09:00am - 17:30pm, Monday to Friday) and for the candidate to be flexible to meet the requirements of our follow-the-sun operational demand.\u00a0 The candidate may also be required to take part in on-call rota to provide support coverage in the event of a major incident.\n\n\u201cI really enjoy working alongside great\u00a0colleagues\u00a0in a multicultural environment at Arup.\u00a0I have developed a lot during my five years with Arup\u00a0- people are very generous in sharing knowledge with the aim to make technology work better for colleagues.\u00a0\u00a0Everyone in the team has a chance to contribute and share their opinion, and that makes me feel valued.\u201d\u00a0\u00a0\nAnna, Hong Kong\u00a0\n\n\nYou should apply for this role if:\n\nYou have an analytical mind and a methodical and practical approach to solving complex IT problems\nYou enjoy working with a diverse team and sharing your knowledge with others\nYou are motivated by the potential of technology to transform a global business\n\nThe responsibilities of the role include:\n\nCreate, own and maintain global standard operating procedures, delivering agreed standards and consistent systems and services across all time zones\nPlay a key role as part of the global DT operations management team, collaborating with colleagues across other regions, and liaise closely with the head of infrastructure & operations to inform of local/regional operational matters\nWork closely with operations managers in other regions to help ensure globally agreed standards are adhered to\nUse existing data/intelligence to underpin decision-making as part of a continuous improvements initiative within the global operations management team and to investigate options to improve automation and orchestration activities, rather than chasing manual solutions to problems\nManage incidents through to resolution, ensuring post incident reviews are actionable and completed\nRepresent Arup in a professional capacity with external vendors\n\nPlease don\u2019t be discouraged if you don\u2019t meet every point below \u2013 if you\u202fmeet most, and are strongly motivated by the role, and willing to learn, we are still interested in hearing from you.\u202f\n\nRequirements and skills\n\nEssential skills and knowledge:\n\nStrong, technical knowledge covering a broad range of Digital Technology services including infrastructure, platforms and applications. Candidates will ideally have a minimum 5yrs experience in a similar role\nExcellent verbal and written communication skills in both English and Chinese (Mandarin), for both technical and non-technical subjects, along with strong customer service management and client support skills when liaising with local management and end-users\nSolid people management skills and coordination ability for product delivery; strong analytical and/or problem-solving skills during major incident resolution, and be able to work effectively under pressure when required\nExperience of performing quality assurance reviews of Digital Technology systems and services to ensure they remain fit for purpose\nAbility to identify operational risks, prepare remediation or mitigation plans and to oversee their delivery with positive impact\nAbility to identify localised technology skills and resource gaps and to assist in local/regional recruitment activities to address those gaps, assisting in building a strong technology support function in the East Asia Region\nA good understanding of ITIL v4 practices and processes including: Incident (& Major Incident), change and problem management, request fulfilment, etc. and how to apply these effectively within the support organisation\n\nDesirable:\n\nService Now for IT service management\nManaging multi-disciplinary IT teams across multiple geographic locations\nIT project delivery\nVendor management\nCisco networking infrastructures\nNetApp storage infrastructures\nMicrosoft technologies\nTelstra WAN and internet services\n\nRequired behaviours:\n\nYou have a passion for diversity, recognising the innovation and competitive edge that comes from a diverse highly skilled team where equal opportunities are truly valued\nYou will be eager to take on new challenges and inquisitive, to identify opportunities to continuously improve current solutions on your own or working collaboratively within the team\nYou have an appreciation for strategic and tactical decision-making, ensuring that business and technology initiatives are mutually beneficial and aligned\nYou will make yourself available to technical and non-technical Arup staff, supportive in addressing problems and issues and eager to collect feedback and comments to build strong relationships in and across regions\nYou will have good English written/verbal communication skills with both non-technical as well as technical audiences maintaining successful communications with various stakeholders\nYou will possess a natural curiosity for all things technical and will take responsibility for keeping yourself up to date with new and emerging trends\nYou will have an ability to engage and positively influence internal and external stakeholders to adopt IT initiatives\n\nEducation and qualifications\n\nProfessional certification and/or chartership is desirable but not essential\n\nWe offer a competitive remuneration package commensurate with qualifications and experience to the right candidate including Global Profit Share scheme, additional fringe benefits of maternity / paternity leave and long-term career development opportunities.\n\nFor interested applicants, please click \u201cApply Now\u201d to submit your online application.\n\nPersonal data collected will be used for recruitment purpose only. Applicants not contacted within 8 weeks may consider their applications unsuccessful.", "employment_types": ["Full Time", "Permanent"], "selling_points": [], "locations": ["Kowloon City"], "categories": ["Information Technology (IT)", "IT Project Management / Team Lead", "IT Management", "Others"], "post_time": "2022-01-12T08:31:55Z", "salary": {"currency": null, "max": null, "min": null, "period": null, "term": null}, "salary_visible": false, "title_keywords": ["operations manager"], "responsibilities": ["liaise", "management team", "continuous improvements", "data", "operations", "systems", "procedures", "infrastructure", "resolution", "maintain", "operational matters"], "requirements": {"degrees": [], "majors": [], "languages": ["english", "chinese", "mandarin"], "language_level": ["excellent", "good"], "hard_skills": ["itil", "vendor", "scheme", "make", "problem-solving skills", "wan"], "soft_skills": ["work effectively", "communication skills", "supportive", "under pressure", "passion for", "diverse", "customer service", "coordination", "organisation", "problem-solving skills", "positive"], "languages_combined": [{"language": "english", "language_level": ["good", "excellent"]}, {"language": "chinese", "language_level": ["good", "excellent"]}, {"language": "mandarin", "language_level": ["excellent"]}]}, "experience_required": {"duration": [], "field": ["digital", "development", "quality assurance"]}}, {"job_id": "100003009048737", "location_code": "hk", "company": "Gimmick House Ltd", "job_title": "IT Project Executive / Assistant", "description": "Responsibilities:\nJoin the team to provide end-to-end IT Solution and digital related project delivery\u00a0\nProvide project assistance on project initiation including scoping, costing, planning and feasibility for products, platform and app development\nSupport project governance, risk management and change management\nWork closely with clients to gather requirements and technical details to fully scope out solution\nCollaborate with UX, marketing, creative, technical teams through all stages of project from strategy and concept, design, technical planning, prototyping, production, QA to deployment or other supporting activities\nSource, plan and manage both internal resources and external partners/vendors\u00a0\nMust posses an active understanding of digital including strategy, information and visual design, technology, social media and rich media\nAssist to prepare documents to pitch clients, e.g. marketing plan, schedule, budget etc.\nParticipate in ad-hoc projects and other assigned duties\nRequirements:\nBachelor's degree in Information Systems or related disciplines\nExecutive grade with 2+ years of experience in project management\nA recognised qualification such as CSM or PMP would be an advantage\nRelevant experience in website revamp and Digital project development\nAbility to follow and implement Agile project management methodologies\nExperience\u00a0managing large scale projects\nExperience running a variety of digital projects, from web apps, banners to platforms, using a variety of technologies and mediums\nExcellent communication skills with spoken and written English, Cantonese preferred\nImmediately available is highly preferred", "employment_types": ["Full Time", "Permanent"], "selling_points": ["IT Solution & Digital Projects Management", "Innovative, break non-rules, challenge yourself", "Work-life balance, Asia regional exposure"], "locations": ["Kwun Tong"], "categories": ["Information Technology (IT)", "IT Project Management / Team Lead", "IT Management", "Technical / Functional Consulting"], "post_time": "2022-01-14T09:04:34Z", "salary": {"currency": null, "max": null, "min": null, "period": "monthly", "term": null}, "salary_visible": false, "title_keywords": ["assistant", "it project executive"], "responsibilities": ["collaborate with", "social media", "management", "change management", "budget", "teams", "design", "marketing plan", "schedule", "plan", "visual", "ad-hoc projects", "prepare documents", "planning"], "requirements": {"degrees": ["degree", "bachelor"], "majors": ["related disciplines"], "languages": ["cantonese", "english"], "language_level": ["excellent"], "hard_skills": ["project management", "pmp", "web apps", "agile"], "soft_skills": ["communication skills", "project management", "agile"], "languages_combined": [{"language": "cantonese", "language_level": ["excellent"]}, {"language": "english", "language_level": ["excellent"]}]}, "experience_required": {"duration": ["2+ years"], "field": ["project management", "development", "relevant experience", "digital"]}}, {"job_id": "100003009051264", "location_code": "hk", "company": "Crossings Executive Search", "job_title": "IT Security Manager (Ref: ITSM/SL)", "description": "Our client is a reputable life insurance company, actively and successfully expanding its business and IT team recently.\u00a0 They are now looking for an all-rounded IT Security Manager to join their IT Security team, reporting directly to the Chief IT Security Architect with all-rounded IT security duty and responsibility.\nThe position is required to oversees all aspects of IT security systems, including application and infrastructure, and responsible for performing information security analysis, implementation and consultation, as well as to assist information security architecture, define and implement security policies and measurements. For ad-hoc activities, the position is required to assist security incident response (IR) process and working together with other teams or managing external vendors for solutions.\nRequirements:\nDegree holder majoring in Computer Science or equivalent\nMinimum seven (7) years of IT experience, of which five (5) years in information security preferably in financial service industry\nHands on experience in managing information security projects and solutions\nGood experience in dealing with business partner and managing external vendors\nProfessional qualification in Information Security such as CISSP, CISA or CISM\nKnowledge of industrial practices such as ISO27001, COBIT and NIST CSF would be a plus\n\nFor all applications, kindly send us your updated CV quoting reference ITSM/SL", "employment_types": ["Full Time"], "selling_points": ["IT Security Manager", "Hands-on information security experience", "Financial service or insurance company"], "locations": ["Ngau Tau Kok"], "categories": ["Information Technology (IT)", "IT Management", "Security"], "post_time": "2022-01-15T06:40:39Z", "salary": {"currency": null, "max": null, "min": null, "period": "monthly", "term": null}, "salary_visible": false, "title_keywords": ["manager"], "responsibilities": ["ad-hoc", "reporting", "information security", "policies", "analysis", "infrastructure", "systems", "implementation", "teams", "insurance", "architecture"], "requirements": {"degrees": ["degree holder"], "majors": ["computer science"], "languages": [], "language_level": [], "hard_skills": ["analysis", "plus"], "soft_skills": ["hands on", "responsible"], "languages_combined": []}, "experience_required": {"duration": [], "field": ["service industry", "business partner", "it experience", "security", "financial"]}}, {"job_id": "100003009035463", "location_code": "hk", "company": "WPPLHK Advisory", "job_title": "IT Manager - Leading Fashion Company", "description": "Brief Description:\n\nStrong in POS handling (Shop HK x 11, or more in china, japan, SG later)\n\nProficient to Microsoft Hyper-V\n\nNo online exp is needed\n\nReport to boss and work very closely with COO\n\nDuties and Responsibilities:\n\nManage and monitor all installed computer systems, server, storage, network, and telephony infrastructure on-premise and cloud-based.\n\nProactively ensure the highest levels of system and infrastructure availability.\u00a0\n\nMonitor and test application performance for potential bottlenecks, identify possible solutions and work with vendors and developers to implement those fixes.\u00a0\n\nInstall, configure, test and maintain network operating systems, application software, system management tools and systems integrations.\u00a0\n\nPerforms hands-on configuration and troubleshooting on various infrastructure and operations related tasks/platforms as necessary\n\nEnsures that IT infrastructure aligns with internal security policies and procedures as well as a regulatory requirement.\n\nResponsible for any technological duties associated with cloud computing, including design, planning, management, maintenance, and support\n\nWork with vendors and other IT staff for project development and problem resolution.\n\nDevelop and maintain custom scripts to increase associate and system efficiency.\u00a0\n\nImplement production changes in accordance with the change management policy\n\nMaintain and test backup and disaster recovery strategies\n\nRecommend, establish and maintain Cyber tools and processes.\u00a0\n\nTasked with working across the aisle of departments to get everyone on the same Cyber Security page.\n\nEvaluate technology tools, software and practices and helping implement any controls that might mitigate the risk of its operation.\n\nRegularly audit the policies and controls that you establish. Based on audit and Cyber related scans, the Cyber Manager will establish remediation plans and be\u00a0responsible for executing remediation\u00a0tasks.\n\nWell-defined and documented plan of action to put into place in the event of a security incident.\u00a0\n\nThe cybersecurity manager should ensure that this program is tested throughout the organization and that every high-level manager knows his or her duties during such an incident.\n\nExperience / Qualification Requirements\n\nBachelor's degree or appropriate combination of education and related experience.\u00a0\n\n8+ years of operational IT network administration experience and in progressive IT infrastructure, and support roles required.\u00a0\n\n5+ years\u2019 experience with Cyber Security Management tools and projects supporting Infrastructure, Cloud Applications, On-premise applications, BCP and DR plans.\u00a0\n\nStrong organizational skills and attention to detail to ensure issues are resolved in a timely manner.\u00a0\n\nStrong analytical and project management skills.\u00a0\n\nExcellent oral and written communication skills and the ability to interact professionally with a diverse group of executives, managers, and subject matter experts.\u00a0\n\nAbility to identify, document and track issues and risk management functions.\u00a0\n\nMust be able to work without organizational authority across organizational boundaries to identify business information needs and to implement actions to fulfill them.\u00a0\n\nProven ability to work independently and as in a team environment.\u00a0\n\nMust be able to meet after-hours on-call availability requirements.\u00a0\n\nExcellent knowledge of current protocols and standards, including Active Directory, Group Policies, MS Exchange, Core Switching/Routing, SSL/IPSec, SAN, Virtualization, Business Continuity, Disaster Recovery.\u00a0\n\nExperience with VMWare and Hyper-V.\u00a0\n\nExperience with Cloud platform eg. Aliyun, Microsoft Azure, Amazon Web Services.\u00a0", "employment_types": ["Full Time"], "selling_points": ["Microsoft Hyper-V", "VM Ware", "POS Systems"], "locations": ["Others"], "categories": ["Information Technology (IT)", "IT Management"], "post_time": "2022-01-10T07:17:13Z", "salary": {"currency": null, "max": null, "min": null, "period": "monthly", "term": null}, "salary_visible": false, "title_keywords": ["it manager"], "responsibilities": ["software", "cyber security", "operations", "troubleshooting", "design", "audit", "maintain", "plan", "plans", "it infrastructure", "configuration", "infrastructure", "monitor", "develop", "resolution", "operating systems", "management", "change management", "procedures", "executing", "maintain network", "maintenance", "policies", "systems", "computer systems", "evaluate", "planning"], "requirements": {"degrees": ["degree", "bachelor"], "majors": [], "languages": [], "language_level": [], "hard_skills": ["network administration", "hyper-v", "azure", "vmware", "active directory", "cyber security", "amazon web services", "project management", "exchange"], "soft_skills": ["organizational skills", "oral", "communication skills", "work independently", "project management skills", "timely", "organizational", "diverse", "attention to detail", "progressive", "active"], "languages_combined": []}, "experience_required": {"duration": ["8+ years", "5+ years"], "field": ["network administration", "management", "related", "infrastructure", "education", "it", "security"]}}, {"job_id": "100003009048766", "location_code": "hk", "company": "Gimmick House Ltd", "job_title": "IT Business Analyst", "description": "Responsibilities:\nEstablish a deep understanding of the client\u2019s business, processes, and procedures and apply that knowledge to affect the project\u2019s success\nResponsible for project definition (e.g., scope, objectives, constraints, assumptions, benefits, issues, risks, etc.), create and maintain a detailed project plan\nOversee full project life cycle, including requirement gathering, planning, system analysis, implementation, deployment, testing and training\nManage and supervise the project progress and proactively identify & solve potential risks\nProvide comprehensive supports to project documentations, plans and reports\nLiaise with internal and external teams and stakeholders in addressing and resolving issues in system development and quality assurance\nRequirements:\nBachelor's degree in Information Systems/Computer Science/Software Engineering or equivalent experience required\n3 to 5 years of project management experience, preferably within a digital agency or consulting firm with experience in managing complex, overseas and/or enterprise-level projects.\u00a0\nStrong familiarity with project management software tools, methodologies, and best practices\nQuick learner with good analytical, time management and troubleshooting skills and able to work under pressure\nGood presentation and interpersonal skills to work with all level of stakeholders\nProfessional certification in Project Management (e.g. PMP, PRINCE) would be an advantage\nExcellent communication skills with spoken and written English and Chinese\nImmediately available is highly preferred", "employment_types": ["Full Time", "Permanent"], "selling_points": ["Good project presentation and documentation skils", "Competitive package", "Immediately available is highly preferred"], "locations": ["Kwun Tong"], "categories": ["Information Technology (IT)", "IT Project Management / Team Lead", "IT Management", "Marketing / Public Relations", "Management"], "post_time": "2022-01-14T07:14:47Z", "salary": {"currency": null, "max": null, "min": null, "period": "monthly", "term": null}, "salary_visible": false, "title_keywords": ["business analyst"], "responsibilities": ["procedures"], "requirements": {"degrees": [], "majors": [], "languages": [], "language_level": [], "hard_skills": [], "soft_skills": [], "languages_combined": []}, "experience_required": {"duration": [], "field": []}}, {"job_id": "100003009051295", "location_code": "hk", "company": "Letlink Technology Limited", "job_title": "IT Project Executive", "description": "Job Descriptions:\n\nIdentify and close the gap between clients and internal teams when evaluating the digital platform solutions and approach with system and business knowledge\nResponsible for day-to-day IT project management, user experience design, UAT, platform support\nCollaborate with UX team to create and review the UX/UI and GUI of the solutions\nConduct SIT & UAT of the system\nProvide administrative support to the solutions manager, including task scheduling, presentation materials, documentation and projects\u2019 activities\n\n\u00a0Requirements:\n\nBachelor\u2019s Degree in Management Information Systems, Computer Science or related disciplines\nA minimum of 2 years working experience\nSolid experience in IT & digital project management (Website/Mobile APP Projects)\nMagento/elearning platform experience is a plus\nMySQL, Coding (PHP, JSON) & API Integration knowledge is a plus (not a must)\nAnalytical, detail-oriented and organized person with problem solving attitude\nReady to accept responsibility and take challenges\nLess Experience will be considered as Asst Project Executive", "employment_types": ["Full Time"], "selling_points": [], "locations": ["Shatin Area"], "categories": ["Information Technology (IT)", "Support", "IT Management", "Product Management / Business Analyst"], "post_time": "2022-01-15T07:23:44Z", "salary": {"currency": null, "max": null, "min": null, "period": "monthly", "term": null}, "salary_visible": false, "title_keywords": ["it project executive"], "responsibilities": ["collaborate with", "documentation", "uat", "review", "teams", "user experience", "digital platform", "design", "project management", "scheduling", "provide administrative support", "ui"], "requirements": {"degrees": ["degree", "bachelor"], "majors": ["related disciplines", "computer science"], "languages": [], "language_level": [], "hard_skills": ["plus", "php", "problem solving", "project management", "mobile", "integration"], "soft_skills": ["organized", "project management", "problem solving", "detail-oriented"], "languages_combined": []}, "experience_required": {"duration": ["minimum of 2 years"], "field": ["digital", "project management", "it"]}}, {"job_id": "100003009053603", "location_code": "hk", "company": "JFE Consulting Limited", "job_title": "Senior Database Administrator (DBA)", "description": "Our client, one of the leading IT companies, is looking for high calibres to join their winning team:-\n\nResponsibilities:\n\nInstall, design and maintain database system software and implement database security.\nMonitor and analyze database performance and ensure effective and efficient utilization of database systems/processes.\nMaintain database dictionaries and support tools; develop and maintain accurate system documentation.\nParticipate in the development and maintenance of strategic, architectural and tactical plans for the database and data warehouse environments; be conversant with, and cognizant of, the future direction of systems, how that direction impacts the company and how future and current database systems can be exploited for the company\u2019s benefit. \u00a0\nYou will design, execute and supervise DML/DDL according to business requirements.\n\nRequirements:\n\nBS degree in Information Technology/Computer Science or equivalent combination of education and experience.\nFive or more years of SQL server database experience as Database Administrator (DBA), including experience installing, configuring, designing, patching, archiving, and monitoring to include performance tuning databases with indexing.\nYou have strong experience with database software (especially MySQL),\u00a0\nYou are proficient in SQL programming and Shell;", "employment_types": ["Full Time", "Permanent"], "selling_points": ["MySQL DBA", "Redis, HBase, Shell", "5-day work; attractive salary"], "locations": ["Not Specified"], "categories": ["Information Technology (IT)", "DBA", "IT Management", "Data Scientist"], "post_time": "2022-01-17T07:13:37Z", "salary": {"currency": null, "max": null, "min": null, "period": "monthly", "term": null}, "salary_visible": false, "title_keywords": ["administrator"], "responsibilities": ["software", "system documentation", "maintenance", "data", "systems", "monitor", "design", "develop", "maintain", "database", "plans"], "requirements": {"degrees": ["degree"], "majors": ["computer science", "information technology"], "languages": [], "language_level": [], "hard_skills": ["sql", "server", "programming", "databases"], "soft_skills": [], "languages_combined": []}, "experience_required": {"duration": [], "field": ["sql", "education", "database", "information technology"]}}, {"job_id": "100003009050534", "location_code": "hk", "company": "KEK Consultancy Company Limited", "job_title": "Assistant Product Manager (ITS/IoT/eHealth/Web/mobile app) \u2013 few posts \u2013 Ref. 632", "description": "\u00a0One of our clients (a big corp.) is now looking for high calibre candidates to fill the following position:\nDegree holder in Information Technology, Computer Science or related disciplines;\n3 years relevant experience in product development / project management;\nExperience in project management in Web portal, mobile app platform;\nKnowledge in IoT, e-health products and technologies is preferable;\nStrong knowledge and hands-on software development experience is an advantage;\nPassionate in new technology;\nGood command in both written and spoken English and Chinese (Cantonese & Mandarin).\n\nRemarks:\n\nMonthly salary:\u00a0Basic HK$30-40K (depends on experience/ skill);\n5-day work;\nWorking Location:\u00a0Tai Koo City;\nGood fringe benefits will be provided.\n\nIf the above position is not suitable for you, please also feel free to send your CV to us for our job matching.\n\nInterested parties please click \"APPLY NOW\"\u00a0or send to\u00a0OUR EMAIL\u00a0and attach your updated resume with expected salary in \"MS WORD\" format.\n\nPlease quote the\u00a0Job Ref. No.\u00a0and\u00a0Applied Post\u00a0on the subject of your application.\n\nInterest to know our candidates' and clients' comments about our service? Please click\u00a0HERE.\n\nCompany website:\u00a0www.kek.com.hk\n\nThe information provided will only be used for recruitment related purposes.", "employment_types": ["Full Time", "Permanent"], "selling_points": ["5-day", "3 years experience in product development", "Good fringe benefits"], "locations": ["Tai Koo"], "categories": ["Engineering", "Engineering Project Management", "Information Technology (IT)", "IT Project Management / Team Lead", "IT Management"], "post_time": "2022-01-15T03:51:10Z", "salary": {"currency": null, "max": null, "min": null, "period": "monthly", "term": null}, "salary_visible": false, "title_keywords": ["assistant product manager"], "responsibilities": ["project management", "mobile app", "software"], "requirements": {"degrees": ["degree holder"], "majors": ["related disciplines", "computer science", "information technology"], "languages": ["cantonese", "english", "chinese", "mandarin"], "language_level": ["good command"], "hard_skills": ["project management", "basic", "mobile", "web"], "soft_skills": ["passionate", "project management", "hands-on"], "languages_combined": [{"language": "cantonese", "language_level": ["good command"]}, {"language": "english", "language_level": ["good command"]}, {"language": "chinese", "language_level": ["good command"]}, {"language": "mandarin", "language_level": ["good command"]}]}, "experience_required": {"duration": ["3 years"], "field": ["project management", "product development", "relevant experience", "software development"]}}, {"job_id": "100003009054007", "location_code": "hk", "company": "Impacts Technology Limited", "job_title": "Web / Mobile Developer", "description": "Job Description and Responsibilities\n\nDesign and Develop corporate training platforms for corporate in Hong Kong;\nPerform AI-related research for applying AI-related functions to e-learning systems.\u00a0\n\n\u00a0Job Openings\n\n2+\n\n\u00a0Job Requirements\n\nAt least 1 year of working experience (Fresh graduate will also be considered)\nExperience in e-learning platform development is a plus\nFamiliar with at least one of the following areas\nWeb Programming (HTML, CSS, JavaScript, PHP, MySQL) + Laravel (PHP Framework)\nSystem administration or Database administration (e.g. linux-based server, cloud based servers, MySQL administration, etc.)\niOS Programming (Objective-C / Swift)\nAndroid Programming (Java)\nFull-time working mode (5-day work)\n\n\u00a0Monthly Salary & Bonus:\n\nSalary will be offered based on experience, skills and education level\nRanged from 18,000 to 28,000 per month\nPerformance-based bonus will be considered at the end of the year\n\n\u00a0Team's Focus:\n\nCorporate Training Platform Development\nMobile Learning Platforms (Apps & Web)\nSoftware Product Development\n\n\u00a0Products and Services Highlight\n\niTrain - Self-learning corporate training platform\n\nA self-learning corporate training platform developed for MNC. Over 100,000 users have been enrolled to our system.", "employment_types": ["Full Time"], "selling_points": [], "locations": ["Pok Fu Lam"], "categories": ["Engineering", "Others", "Information Technology (IT)", "IT Management", "Software Development"], "post_time": "2022-01-17T16:21:02Z", "salary": {"currency": null, "max": null, "min": null, "period": "monthly", "term": null}, "salary_visible": false, "title_keywords": ["developer"], "responsibilities": ["systems", "design and develop"], "requirements": {"degrees": ["fresh graduate"], "majors": [], "languages": [], "language_level": [], "hard_skills": ["linux", "plus", "java", "servers", "web", "php", "swift", "html", "objective-c", "mobile", "javascript", "programming", "server", "css", "focus", "android"], "soft_skills": ["focus", "learning"], "languages_combined": []}, "experience_required": {"duration": ["at least 1 year"], "field": ["development", "education"]}}, {"job_id": "100003009053669", "location_code": "hk", "company": "JFE Consulting Limited", "job_title": "Senior Technical Analyst - Oracle, MongoDB Database Administrator", "description": "Our client, one of the leading Logistics companies, is looking for high calires to join their winning team.\n\nResponsibilities:\n\n\nDevelop technical specification\nEnforce, refine and document database standards\nWork with technical/development leads to design, or review designs for databases\nAssess and identify database server resource requirements\nDevelop and maintain data models\nDemonstrate advanced understanding of multiple database platforms\nCode, test and deploy database changes\nLead efforts to develop and improve procedures for automated monitoring and proactive intervention, preventing customer impact\n\nRequirements:\n\n\n\nBachelor\u2019s Degree (in lieu of degree \u2013 9 years of work experience in Engineering and/or IT environment\n5 years of work experience in Engineering and/or IT environment\n5 years of work experience as a Database Administrator on multiple database platforms\nDemonstrated experience with computer or network systems hardware and software development methodology/process obtained through formal training, education, and/or work experience\nIT experiences and exposures to Oracle technology e.g. Oracle DB 10g or above, MongoDB or MYSQL.", "employment_types": ["Full Time", "Permanent"], "selling_points": ["Knowledge in ORacle DB, MongoDB, MYSQL", "Exposure to Oracle technology, e.g. Oracle DB&OEM", "Attractive salary"], "locations": ["Shatin Area"], "categories": ["Information Technology (IT)", "DBA", "IT Management", "Data Scientist"], "post_time": "2022-01-17T07:19:09Z", "salary": {"currency": null, "max": null, "min": null, "period": "monthly", "term": null}, "salary_visible": false, "title_keywords": ["analyst", "administrator"], "responsibilities": ["server resource", "monitoring", "procedures", "review designs", "design", "develop", "deploy", "databases", "database", "maintain data"], "requirements": {"degrees": ["degree", "bachelor"], "majors": ["it", "engineering"], "languages": [], "language_level": [], "hard_skills": ["hardware", "oracle"], "soft_skills": [], "languages_combined": []}, "experience_required": {"duration": ["5 years", "9 years"], "field": ["training", "engineering", "education", "it", "database", "software development"]}}, {"job_id": "100003009056166", "location_code": "hk", "company": "Osmium Consulting Group Limited", "job_title": "Business Coordinator / Business Analyst - 20K - 35K ( FinTech Company )", "description": "Responsibilities\n\nCoordinate and communicate with business users for production products\nAssist Business Analysts to ensure IT deliverables that would satisfy business requirements and would achieve anticipated business benefits\nWork with key project members e.g. project manager, developers, QA to help them understand business requirements and the processes, to ensure finished product complies with users and business specifications\n\nRequirements\n\nExcellent communication skills with possession of good problem-solving ability\nWilling to learn and work under pressure\nProactive, confident, can-do attitude\nAble to work effectively with business users and technical team\nExperience in Finance products / projects is a big plus!\nNative Cantonese Speaker\u00a0\nBenefits\n\nPassionate and Young Team\nMedical, Dental Insurance\n18 days AL\nOn-site Training\n5 days Work Week", "employment_types": ["Full Time", "Permanent"], "selling_points": ["FinTech inHouse / Global Vendor Company", "Young and Passionate Team !", "18 days AL !"], "locations": ["Wan Chai"], "categories": ["Information Technology (IT)", "IT Management", "Product Management / Business Analyst", "Software Development"], "post_time": "2022-01-18T03:27:41Z", "salary": {"currency": "HKD", "max": 34999, "min": 20000, "period": "monthly", "term": null}, "salary_visible": true, "title_keywords": ["coordinator", "business analyst"], "responsibilities": ["coordinate", "communicate with"], "requirements": {"degrees": [], "majors": [], "languages": [], "language_level": [], "hard_skills": [], "soft_skills": [], "languages_combined": []}, "experience_required": {"duration": [], "field": []}}, {"job_id": "100003009044533", "location_code": "hk", "company": "Titanicom Tech Limited", "job_title": "Technical Project Manager", "description": "Job Description and Responsibilities:\n1. Act as a Team Lead to lead and supervise all network/IT/system project management work and server maintenance related business service, ensure that team members comply with the company project delivery framework and continually optimize it. Ensuring Project deliver in line with the contract and implemented according to the implementation plan, and take responsibility for achieving project objectives.\n2. To lead and manage project team and subcontractors to resolve project issues throughout project implementation and ensure operational compliance of the project and its delivery in line with the company's management systems and regulations.\n3. To plan and coordinate, clear division of roles, communicating, monitoring goals, coaching and motivating all members regularly and positively by knowledge transfer to team members via mentoring, workshop and etc. It is estimated team members will be 4 people.\n4. Ensure stability of all the business lines in Hong Kong by developing a communication plan and managing communications to ensure customers alignment\n5. Identify & mitigate all the network project and server maintenance case SLA risk\n6. Conduct proper escalation of issues/risks where and when appropriate and required. Maintain direct and transparent communication with superiors, and maintain internal and external personnel to fully perform their duties\n7. Review project progress, financial matters and performance metrics with management on a regular basis\n\nJob Requirements:\n1. Bachelor degree or above, major in computer, network engineering, communications, and management;\n2. More than 2 years of project management experience and have managed network projects, familiar with the data center environment, such as cabinet placement, data communication/IT equipment, integrated wiring is preferred;\n3. Experience in server operation and maintenance experience are bonus points;\n4. Able to perform the work under high pressure with minimal guidedance, experience in remote project management is preferred, PMP certification is preferred;\n5.Exhibit good leadership skills without prejudice, and be good at dealing with the shortcomings of team members;\n6.Highly adhere to the company's goals, good crisis management skills to deal with the pressure from project challenges and achieve company goal;\n7.Ability to influence and motivate cross-functional teams to deliver successful project outcomes.", "employment_types": ["Full Time", "Permanent"], "selling_points": ["Flexible Working Hours", "Flexible Working Place", "International Management"], "locations": ["Kwai Tsing Area"], "categories": ["Information Technology (IT)", "IT Management"], "post_time": "2022-01-13T04:28:58Z", "salary": {"currency": null, "max": null, "min": null, "period": "monthly", "term": null}, "salary_visible": false, "title_keywords": ["technical project manager"], "responsibilities": ["regulations", "management", "performance metrics", "maintenance", "workshop", "compliance", "systems", "implementation", "plan and coordinate", "monitoring", "developing", "project management", "communication", "maintain", "review", "project progress", "plan"], "requirements": {"degrees": ["degree or above", "bachelor"], "majors": ["engineering", "communications"], "languages": [], "language_level": [], "hard_skills": ["maintenance", "project management", "goal", "server", "pmp"], "soft_skills": ["communication", "project management", "leadership skills", "work under high pressure"], "languages_combined": []}, "experience_required": {"duration": ["2 years"], "field": ["project management", "it", "operation", "maintenance"]}}, {"job_id": "100003009036025", "location_code": "hk", "company": "Teki'Spire Limited", "job_title": "Director and Head of Services and Operation", "description": "Our client, a renowned financial institution is hiring a perm role for Director/ Head of Services and Operation.\n\nDuties:\u00a0\n\nLead the team to design, create and rollout central IT Operations\u00a0\nOversee the management and prioritize the service request/production release\nGovern the efficient operation management and related provisioning / de-provisioning process\nOrganize and review the Business Continuity (BC) and Disaster Recovery (DR) Operation\nManage the printing outsourcing service provider to deliver the IT operation service\nRecommend and drive the operation solution to improve application releases and batches performance\nManage the communications between the application team, internal users and the printing outsourcing service provider\nDrive Service Level Review meeting with printing outsourcing service provider\nRespond to the operation technical issues and IT Operation security compliant in a professional and timely manner\nManage the operation related project, such as printing outsourcing services, batches automation and etc.\nRequirements:\n\nAt least 12 years of experience in supporting central IT Operations, of which 4 years in a managerial position\u00a0\n10 years of experience in banking and finance domain is a MUST\nBachelor\u2019s degree in computer science, Information Technology or related disciplines\nSolid experience with Operation management for application and infrastructure services\nProven track record of setting up IT operation processes\nStrong coordination, communication and multitasking skills, able to communicate effectively with all relevant parties at different levels\nRequire being on call and the ability to respond to emergency issues during off-hours\nPast experience in managing NOC, experience with performing batch fixes, batch release tools like Control-M\nExcellent written and verbal communication skills in English with the ability to effectively tailor communication of technical issues to various audiences\n\nApply Now\nTo apply online, please click the 'Apply' button.\u00a0Please note that only short-listed candidates will be contacted.\u00a0All information collected will be kept confidential and will be used for recruitment purposes only.", "employment_types": ["Full Time", "Permanent"], "selling_points": ["IT Operations, Infrastructure", "Service Level Review", "Business Continuity, Disaster Recovery"], "locations": ["Central & Western Area"], "categories": ["Information Technology (IT)", "IT Management"], "post_time": "2022-01-10T09:06:49Z", "salary": {"currency": null, "max": null, "min": null, "period": "monthly", "term": null}, "salary_visible": false, "title_keywords": ["director"], "responsibilities": ["business continuity", "management", "operations", "review", "design"], "requirements": {"degrees": ["degree", "bachelor"], "majors": ["related disciplines", "computer science", "information technology"], "languages": ["english"], "language_level": ["excellent"], "hard_skills": ["batch"], "soft_skills": ["communication", "communication skills", "coordination"], "languages_combined": [{"language": "english", "language_level": ["excellent"]}]}, "experience_required": {"duration": ["4 years", "at least 12 years", "10 years"], "field": ["managerial", "finance", "infrastructure", "operation management", "banking", "it operations"]}}, {"job_id": "100003009054060", "location_code": "hk", "company": "eCloudvalley Technology (HK) Limited", "job_title": "Cloud Engineer/Cloud Developer", "description": "Do you like helping enterprise clients implement innovative cloud solutions and solve technical problems? Do you want to be the leader and demonstrate how the emerging technologies (such as A.I., Big Data, Cloud, DevOps) can be applied to businesses? With business growth and global expansion opportunities, we are looking for a highly motivated\u00a0Cloud Engineer/Cloud Developer to help accelerate our growing technical team. This is an excellent opportunity to join a world class technical team, working with some of the best and brightest engineers and account managers while also developing your skills and furthering your career within one of the most innovative and progressive technology young companies in Hong Kong.\n\nResponsibilities includes but is not limited to:\n\n\u00b7 Understanding clients\u2019 requirements and design technical solutions on AWS that address clients\u2019 requirements for scalability, reliability, security, and performance.\n\n\u00b7 Work closely and support sales team from technical perspective.\n\n\u00b7 Work closely with a team of architects and engineers to create technical documents and proposals.\n\n\u00b7 Conduct proof-of-concept demonstrations, technical presentations, and sharing.\n\n\u00b7 Respond to technical issues in a professional and timely manner.\n\n\u00b7 Maintain technical skills and knowledge of market trends and competitive insights; collaborate and share with the technical community.\n\nRequirements:\n\n\u00b7 Bachelor's degree in Computer Science, Computer Engineering, Information Technology or relevant field.\n\n\u00b7 2-4+ years' experience designing, executing and supporting IT cloud solutions.\n\n\u00b7 Experience architecting, designing and programming applications in an AWS Cloud environment.\n\n\u00b7 Hands-on experience with cloud computing technologies in AWS preferred\n\n\u00b7 Current AWS Certified Solutions Architect \u2013 Professional preferred\n\n\u00b7 Knowledge of cloud computing technologies on AWS and current computing trends.\n\n\u00b7 Architectural knowledge of data center infrastructure including networking, servers, storage infrastructure and virtualization.\n\n\u00b7 Positive attitude and a strong commitment to delivering quality work.\n\n\u00b7 Effective communication skills (written and verbal)\n\n\u00b7 Putonghua and English are mandatory", "employment_types": ["Full Time", "Permanent"], "selling_points": [], "locations": ["Wan Chai"], "categories": ["Information Technology (IT)", "Support", "IT Management", "Security"], "post_time": "2022-01-17T08:15:51Z", "salary": {"currency": null, "max": null, "min": null, "period": "monthly", "term": null}, "salary_visible": false, "title_keywords": ["developer", "engineer"], "responsibilities": ["collaborate", "presentations", "design", "maintain", "sales team"], "requirements": {"degrees": ["degree", "bachelor"], "majors": ["computer engineering", "computer science", "information technology"], "languages": ["putonghua", "english"], "language_level": [], "hard_skills": ["servers", "computing technologies", "aws", "programming", "cloud environment"], "soft_skills": ["positive attitude", "communication skills", "hands-on"], "languages_combined": [{"language": "putonghua", "language_level": []}, {"language": "english", "language_level": []}]}, "experience_required": {"duration": ["4+ years"], "field": ["it", "programming"]}}, {"job_id": "100003009047517", "location_code": "hk", "company": "AXA Hong Kong", "job_title": "IT Service Management Director", "description": "\u00b7 Design and deliver a platform for a robust support and service management & cyber security model for the General Insurance, Life and Enterprise business units in AXA Hong Kong in line with ITIL SM, drive quality and stability of the production environment\n\u00b7 Ensure consistency between the production and UAT environments\n\u00b7 Monitoring the effectiveness of the team and suppliers against SLA/KPI\u201fs, driving through change as needed to deliver continual service improvement, quality and stability\n\u00b7 Ensure operational procedures and practices are well defined, documented and consistently applied\n\u00b7 Instil a high performance culture in the team with a focus on team work, service excellence and ownership for resolving customer issues\n\u00b7 Be capable of identifying and implementing change within the team to ensure it can take on new service offerings.\n\u00b7 Contribute proactively to new service development.\n\u00b7 Work closely with the project teams to ensure new solutions are on-boarded with seamless handover / transition into production service\n\u00b7 Encourage open communication between team members, allowing the team to bring forward ideas on how they can collectively deliver a more effective service\n\u00b7 Set and cascade business objectives and targets to the team\n\u00b7 Ensure teams are skilled, trained and developed to enable them to deliver high quality service and support\n\u00b7 Manage and develop strategic partnerships with third party suppliers and other internal stakeholders\n\u00b7 Ensure quality, up-to-date documentation exists for all service arrangements\n\u00b7 Provide input into the divisional strategy with particular focus into opportunities to grow and/or enhance the service offered\n\u00b7 Provide leadership and direction to the service management function ensuring appropriate and robust service management and review frameworks are in place\n\u00b7 Take responsibility for customer escalations and act as a point of escalation and communication both in and out of hours as required\n\u00b7 Drive a continual service improvement programme to optimize and drive efficiencies in support operations for the systems\n\nJob Requirement\n\n\u00b7 Bachelor's degree in Computer Science, related field (e.g., Engineering), or Business Management\n\u00b7 Operational experience that includes working across a broad section of IT services\n\u00b7 Strong background in IT service delivery (ten years minimum)\n\u00b7 Experience in a direct IT- business engagement role\n\u00b7 Has participated in design and/or implementation of major IT projects\n\u00b7 Communicates well with customers who are not tech savvy\n\u00b7 Has experience dealing with vendors and other people who are supplying the product or service\n\u00b7 Ability to set strategy\n\u00b7 Ability to develop and assess progress on a complex financial plan\n\u00b7 Good at managing relationships and networking across the IT function\n", "employment_types": ["Full Time", "Permanent"], "selling_points": ["Corporate role in AXA", "IT Service Management", "Location at Wong Chuk Hang"], "locations": ["Southern Area"], "categories": ["Information Technology (IT)", "IT Management"], "post_time": "2022-01-14T03:21:58Z", "salary": {"currency": null, "max": null, "min": null, "period": "monthly", "term": null}, "salary_visible": false, "title_keywords": ["director"], "responsibilities": ["ideas", "it service", "cyber security", "operations", "quality", "design", "communication", "plan", "customer issues", "uat", "teams", "implementation", "develop", "major it projects", "operational procedures", "management", "monitoring", "review", "documentation", "third party", "systems", "insurance"], "requirements": {"degrees": ["degree", "bachelor"], "majors": ["computer science"], "languages": [], "language_level": [], "hard_skills": ["itil", "business management", "cyber security", "sla", "documentation", "focus"], "soft_skills": ["capable", "robust", "communication", "focus", "leadership"], "languages_combined": []}, "experience_required": {"duration": [], "field": ["business", "it"]}}, {"job_id": "100003009054191", "location_code": "hk", "company": "EZSVS (Hongkong) Co., Limited", "job_title": "Data Center Operator", "description": "Job\u00a0Responsibilities :\n\nResponsible for the management &technical support of servers/routers/switches/network in Data Center environment\nConfiguration changes of the network and debug of Data Center network, fault troubleshooting, system installation and configuration, equipment operation in Data Center\nManagement of DC Capacity Specification and proactively detect & resolve potential issue related to DC Network or Servers\nPerform changes to system services and configuration\n\nRequirements :\n\nHigher diploma or above in Computer Science/ Telecommunication/ Engineering or a related subject\nMinimum 1-year relevant experience\nBasic knowledge in Data Centre domain\nGood command of Mandarin and Cantonese\nImmediately available is preferred\n\nCompany Benefits :\n\nPublic holiday\nTriple overtime allowance\nDouble pay\nMedical Insurance", "employment_types": ["Full Time"], "selling_points": ["Triple overtime allowance", "Double pay\uff0fMedical Insurance", "7x24 Tseung Kwan O"], "locations": ["Tseung Kwan O"], "categories": ["Information Technology (IT)", "DBA", "Hardware", "IT Management"], "post_time": "2022-01-17T08:44:49Z", "salary": {"currency": null, "max": null, "min": null, "period": "monthly", "term": null}, "salary_visible": false, "title_keywords": ["operator"], "responsibilities": ["installation", "management", "data", "technical support", "configuration", "troubleshooting"], "requirements": {"degrees": ["higher diploma or above"], "majors": ["engineering", "computer science"], "languages": ["cantonese", "mandarin"], "language_level": ["good command"], "hard_skills": ["basic"], "soft_skills": [], "languages_combined": [{"language": "cantonese", "language_level": ["good command"]}, {"language": "mandarin", "language_level": ["good command"]}]}, "experience_required": {"duration": ["minimum 1-year"], "field": ["relevant experience"]}}, {"job_id": "100003009043213", "location_code": "hk", "company": "", "job_title": "Manager/Senior Manager \u2013 IT", "description": "Responsibilities:\n\nResponsible for IT strategic planning, budgeting and execution to align the group's vision and sustainable development\nLead and drive the digital transformation and development of the Group through working closely with internal stakeholders and 3rd\u00a0party vendors\nProvide overall IT governance, establish and maintain company-wide security and compliance policies\nWorking closely with senior stakeholders to understand their business needs and recommend innovative solutions to meet their expectations\nEffective resource planning, management, reporting and coordination of projects/initiatives\nResponsible for overall IT administration, logistic and procurement of IT equipment, development of best practices and documentation\nOversee the Group's IT infrastructure and perform system monitoring for security purposes\n\nRequirements:\n\nDegree holder or above in Information Technology, Computer Science / Engineering or other related discipline\nMinimum 10 years of IT related experience with at least 5 years as IT Lead or similar role; experience in Healthcare industry is highly preferable\nStrong project management and multi-tasking skills gained from complex digital transformation projects in a challenging environment\nStrong digital and technology concepts, trends and capabilities\nSelf-starter with innovation / strategic mindset and good business acumen\nMature and flexible with good interpersonal skills, able to transform the technical jargon into business terms\nExcellent command of spoken and written skill in English and Chinese\n\nWe offer attractive remuneration package, includes\u00a05 days work\u00a0commensurate with qualification and experience to the right candidate. Interested parties please send us email to Human Resources Department.\n\n* Only shortlisted candidates will be notified. All information collected will be kept strictly confidential and for recruitment-related purpose only.\nInterested candidates, please contact us at 39748026 for company details before applying.", "employment_types": ["Full Time", "Permanent"], "selling_points": ["Responsible for IT strategic planning", "Minimum 10 years of IT related experience", "Medical insurance include family members"], "locations": ["Tsim Sha Tsui"], "categories": ["Information Technology (IT)", "IT Project Management / Team Lead", "IT Management", "Others"], "post_time": "2022-01-12T10:14:55Z", "salary": {"currency": null, "max": null, "min": null, "period": "monthly", "term": null}, "salary_visible": false, "title_keywords": ["senior manager", "manager"], "responsibilities": ["administration", "reporting", "3rd party vendors", "management", "strategic planning", "it infrastructure", "budgeting", "policies", "compliance", "monitoring", "maintain", "coordination", "documentation", "it equipment", "planning"], "requirements": {"degrees": ["degree holder"], "majors": ["engineering", "computer science", "information technology"], "languages": ["english", "chinese"], "language_level": ["excellent"], "hard_skills": ["project management", "acumen"], "soft_skills": ["flexible", "business acumen", "mature", "project management", "interpersonal skills", "multi-tasking skills"], "languages_combined": [{"language": "english", "language_level": ["excellent"]}, {"language": "chinese", "language_level": ["excellent"]}]}, "experience_required": {"duration": ["at least 5 years", "minimum 10 years"], "field": ["related", "healthcare industry", "it"]}}, {"job_id": "100003009042609", "location_code": "hk", "company": "GDC Technology Limited", "job_title": "MIS Manager", "description": "Responsibilities:\n\nLead the MIS team of the group\nManage and provide reliable IT infrastructure environment (WAN, LAN, Servers, network security, OA s/w)\nStrategic decision making for appropriate technology for group\u2019s overall development and infrastructure projects, define project scope, approach, budget and timeline\nStandardizing IT service implementation processes and methodologies\nDevelop budget and project plans to support IT infrastructure expansion in accordance with the business expansion plan\nRoll out global / regional infrastructure project and ERP solutions\nEnsure an appropriate level of Information Security in line with business demands and associated risks\nResponsible for overall IT security management implementation including security control and assessment\nEnsure an effective & timely service delivery\n\nRequirements:\n\nBachelor\u2019s Degree or above in Computer Science, IT or equivalent\nMore than 10 years overall technical/IT working experience in which 5 years in a managerial position\nProven track record of developing and supervising technical operations for a fast moving company\nStrong working knowledge of development technologies / concepts including back-end architecture, processing / capabilities, networking\nSolid experience in large scale Wintel & Linux system administration with project experience in Active Directory and ERP solution\nAbility to communicate technical concepts to technical and non-technical audiences\nFluency in spoken and written English. Cantonese and Mandarin are a big plus\n\nAttractive remuneration package will be offered.\n\nAll information provided by applicants will be treated as strictly confidential and used only for processing their application.", "employment_types": ["Full Time"], "selling_points": [], "locations": ["North Point"], "categories": ["Information Technology (IT)", "IT Project Management / Team Lead", "IT Management", "Network & System"], "post_time": "2022-01-12T08:10:38Z", "salary": {"currency": null, "max": null, "min": null, "period": "monthly", "term": null}, "salary_visible": false, "title_keywords": ["manager"], "responsibilities": ["service delivery", "control", "it service", "it infrastructure", "information security", "infrastructure", "budget", "implementation", "develop", "it security management", "plan", "plans"], "requirements": {"degrees": ["degree or above", "bachelor"], "majors": ["it", "computer science"], "languages": ["cantonese", "english", "mandarin"], "language_level": ["fluency"], "hard_skills": ["linux", "plus", "active directory", "erp", "processing"], "soft_skills": ["active"], "languages_combined": [{"language": "cantonese", "language_level": []}, {"language": "english", "language_level": ["fluency"]}, {"language": "mandarin", "language_level": []}]}, "experience_required": {"duration": ["5 years", "10 years"], "field": ["managerial", "it", "administration"]}}, {"job_id": "100003009047750", "location_code": "hk", "company": "ABeam Consulting LTD. (HK Branch)", "job_title": "Project Manager (\u226560k)", "description": "Responsibilities:\n\nPD & Management\uff1aIn charge of project PD and implementation management\n\nBusiness\uff1aFamiliar with business needs, then reasonably transform into information technology needs, while providing professional advice to clients.\n\nSolution\uff1aProviding technical guidance and methods to SAP team\n\nBudget\uff1aManaging the project budget and controlling the rationality of business requirements\n\nResource\uff1aCoordinate internal and external resources to complete the project\n\nRequirements:\n\nHandled \u226510 projects before\n\nHighly experienced in field of PD and have successful case(s)\n\nMultiple project handling working experience\n\n\nFluent in Japanese is preferred", "employment_types": ["Full Time", "Permanent"], "selling_points": ["Guaranteed 13 months salary, Performance bonus", "13 days AL and Up to 20 days/ 24 days SL", "Training, Medical, Dental"], "locations": ["Sheung Wan"], "categories": ["Information Technology (IT)", "IT Project Management / Team Lead", "IT Management", "Technical / Functional Consulting"], "post_time": "2022-01-14T03:51:17Z", "salary": {"currency": null, "max": null, "min": null, "period": "monthly", "term": null}, "salary_visible": false, "title_keywords": ["project manager"], "responsibilities": ["guidance", "management", "budget", "implementation"], "requirements": {"degrees": [], "majors": [], "languages": ["japanese"], "language_level": ["fluent"], "hard_skills": [], "soft_skills": [], "languages_combined": [{"language": "japanese", "language_level": ["fluent"]}]}, "experience_required": {"duration": [], "field": []}}, {"job_id": "100003009052966", "location_code": "hk", "company": "JFE Consulting Limited", "job_title": "Analyst Programmer", "description": "Our client, one of the Manufacturing companies, is looking for high calibres to join their winning team:-\n\nResponsibilities\n\n\n\nDesign, develop, document, analyze, create, test and modify computer systems, programs and integrations\nApply system-analyst techniques and procedures, including consulting with users to determine hardware, software or systems functional specification\nArrange project requirements in programming sequence by analyzing requirements; preparing a work flow chart and diagram using knowledge of computer capabilities, subject matter, programming language, and logic.\nProgram the computer by encoding project requirements in computer language; entering coded information into the computer\nAnalyze user information system needs.\nRequirements:\n\nBS degree in Information Technology/Computer Science or equivalent combination of education and experience.\nFive or more years of SQL server database experience as Database Administrator (DBA), including experience installing, configuring, designing, patching, archiving, and monitoring to include performance tuning databases with indexing.\nExperience utilizing various high availability (HA) and disaster recovery (DR) options for MS SQL Server.\nExperience with backup/recovery best practices.\nExtensive experience with query tuning and troubleshooting.\nWorking knowledge of data encryption techniques and database querying and management tools.\nMicrosoft certifications (preferred)", "employment_types": ["Full Time", "Permanent"], "selling_points": ["Web application development", "Experienee in ERP system", "Next to Wong Chung Hang MTR station"], "locations": ["Not Specified"], "categories": ["Information Technology (IT)", "Application Specialist - Software", "IT Management", "Product Management / Business Analyst"], "post_time": "2022-01-17T04:43:43Z", "salary": {"currency": null, "max": null, "min": null, "period": "monthly", "term": null}, "salary_visible": false, "title_keywords": ["analyst programmer"], "responsibilities": ["project requirements", "software", "consulting", "systems", "procedures", "computer systems", "design", "develop", "hardware"], "requirements": {"degrees": ["degree"], "majors": ["computer science", "information technology"], "languages": [], "language_level": [], "hard_skills": ["sql", "server", "ms sql server", "databases"], "soft_skills": ["extensive", "troubleshooting"], "languages_combined": []}, "experience_required": {"duration": [], "field": ["disaster recovery", "troubleshooting", "education", "sql", "information technology", "database"]}}, {"job_id": "100003009051910", "location_code": "hk", "company": "Neo Derm (HK) Ltd", "job_title": "Technical Lead", "description": "About us\nWith the trend towards\u00a0Industrial Revolution 4.0, our IT department, the strategic technology enabler with more than 70 staff,\u00a0has established a comprehensive personalized customer-centric platform (gratus) and operation management system, i.e. Customer Behavioral Tracking System, Recommendation Engine, Business Intelligence Dashboard and Campaign Monitoring System, to support the fast-changing business transformation needs across the Group.\n\nTo support the Group\u2019s continuous development, we are looking for high caliber talent who is enthusiastic in system development to join our strong & fast-growing IT team.\n\nResponsibilities:\n\n\nResponsible for all digital & eCommerce\u00a0platforms development to support company regional growth\nResponsible for application & architecture design and whole software development\u00a0life-cycle\nTake a lead of feasibility study and implementation of IT projects, and participate in gathering requirements\nHelp business users define application workflow for various business scenarios\nCoordinate with system developers for application development and enhancement projects, and follow IT standards for implementations\nResponsible for project schedule, documentation, progress reporting and status update meeting\n\n\u00a0Requirements:\n\nUniversity degree holder in Computer Science, Information Technology or relevant disciplines\nWith at least 5 years of software development experience, 3 years in team leading experience, especially in retail industry with regional exposure\nProven experience in micro-services API Development\nKnowledge of vue.js / react.js / Angular, node.js, JavaScript, HTML & CSS\nSolid hands-on development experience in database, i.e. MySQL, MongoDB, SQL Server\nAble to cope with tight project schedule, perform work effectively and be flexible to work under dynamic environment\nExcellent supervisory skill, business analytic and problem solving skills\nIndependent, self-motivated, result-oriented, innovative with excellent interpersonal and communication skills\nGood command of English, Mandarin and Cantonese\n\nBenefits:\n\nFive-day work week\nDiscretionary year-end bonus\nMedical insurance\nDental insurance\nStaff purchase discount\nExcellent career development", "employment_types": ["Full Time", "Permanent"], "selling_points": ["5yr system development + 3yr team lead experience", "Hands-on MySQL, MongoDB, SQL Server", "Vue.js,React.js,Angular.js,Node.js,JavaScript"], "locations": ["Tai Koo"], "categories": ["Information Technology (IT)", "Application Specialist - Software", "IT Management", "Software Development"], "post_time": "2022-01-17T01:30:10Z", "salary": {"currency": null, "max": null, "min": null, "period": "monthly", "term": null}, "salary_visible": false, "title_keywords": ["lead"], "responsibilities": ["reporting", "software", "enhancement projects", "coordinate with", "implementation", "design", "schedule", "documentation", "application development", "architecture"], "requirements": {"degrees": ["university degree"], "majors": ["computer science", "information technology"], "languages": ["cantonese", "english", "mandarin"], "language_level": ["good command"], "hard_skills": ["react", "html", "sql", "javascript", "dynamic", "angular", "server", "css", "problem solving skills"], "soft_skills": ["work effectively", "flexible", "dynamic environment", "self-motivated", "independent", "communication skills", "interpersonal", "hands-on", "problem solving skills", "innovative", "result-oriented"], "languages_combined": [{"language": "cantonese", "language_level": ["good command"]}, {"language": "english", "language_level": ["good command"]}, {"language": "mandarin", "language_level": ["good command"]}]}, "experience_required": {"duration": ["3 years", "at least 5 years"], "field": ["retail industry", "development", "database", "software development", "team"]}}, {"job_id": "100003009051091", "location_code": "hk", "company": "Pinpoint Asia Limited", "job_title": "Head of Quality Assurance CoE - Leading Financial Institution", "description": "Our client, a leading financial institution, is looking for a\u00a0Head of Quality Assurance CoE\u00a0for their large technology delivery. The selected candidate will drive a high-quality testing delivery across core technology platforms, digital and cloud API services.\n\n\nRequirements:\n\nDevelop and build test strategies for manual, automated, and performance testing which assist the application teams to maintain high-quality software delivery.\nDefine and maintain quality assurance guidelines and standards across the whole firm.\nWork with the key business and technology stakeholders in building the required testing strategy and framework.\nManage the testing teams on building test plans, testing scripts, test reports.\nLead the testing function in the development division and drive testing governance plan for best practices.\nLead the testing in CI/CD environment.\nContributes to testing best practices across the firm.\nManage testing resources across the firm, including in-house testing teams, contractors, external vendors, and offshore resources.\n\nResponsibilities:\n\nExtensive experience in leading a testing function with leadership responsibilities.\nExperience in leading a testing functionality with testing strategy and direction.\nStrong understanding of QA including SAT, and UAT.\nExperience with at least one hybrid automation modern test framework.\nExperience using testing tools including Cucumber and JBehave is a great plus.\nHands-on experience using Atlassian Jira and Confluence.\nStrong knowledge of the Software Development Life Cycle with expertise in QA processes and methodology, specifically in Agile.\nExperience with various test methods, tools, and toolkits: Functional, Automated, Performance.\nStrong working experience in an Agile / DevOps environment.\nExcellent communication skills in English and Chinese (Mandarin & Cantonese)\nBachelor's degree from a reputed University.\n\nIf this outstanding opportunity sounds like your next career move, please send your resume in Word format to Danny Kwan at resume(at)pinpointasia(dot)com and put\u00a0Head of Quality Assurance CoE - Leading Financial Institution in\u00a0the subject header.\n\nData provided is for recruitment purposes only.", "employment_types": ["Full Time", "Permanent"], "selling_points": ["Enterprise System Testing", "Test Strategy and Management", "Leadership position"], "locations": ["Not Specified"], "categories": ["Information Technology (IT)", "IT Project Management / Team Lead", "IT Management", "Testing / QA"], "post_time": "2022-01-15T02:08:19Z", "salary": {"currency": "HKD", "max": 159999, "min": 90000, "period": "monthly", "term": null}, "salary_visible": true, "title_keywords": [], "responsibilities": ["sat", "uat", "software", "data", "quality", "testing", "communication", "recruitment"], "requirements": {"degrees": [], "majors": [], "languages": [], "language_level": [], "hard_skills": [], "soft_skills": [], "languages_combined": []}, "experience_required": {"duration": [], "field": []}}, {"job_id": "100003009050364", "location_code": "hk", "company": "Bond West Consultants", "job_title": "IT Project Team Leader (Finance Client) (45 - 60K)", "description": "(Ref Number: jobs@0114ew)\n\nOur client, an IT solution provider is now looking for high caliber candidates as follows:\n\nIT Project Team Leader\n\nResponsibilities:\n\nImplementation and support of Client's IT Infrastructure\nHandle the project of servers/ firewalls/ switches setting up\nProvide Level 3 support\nResponsible for systems/ technical support and administration on network, desktop/server hardware and software, and application systems\n\n\nRequirements:\n\nDiploma\u00a0holder of IT or others related\nAt least 4 years experience for Windows platforms support, such Microsoft Windows 8/10, Microsoft Office 2016/ 2013, Windows Server 2016/ 2012 and Microsoft Exchange Server\nKnowledge of TCP/ IP, LAN/ WAN, DHCP, DNS, Routing and Switching/ Firewall\nCisco Firewall/switches, VMWare exp. is a must\nCertificate Holders of CCNP, CCIE or MCSE is a plus\nGood command of written & spoken English and Mandarin\nImmediate availability is highly preferred\n\nPlease send in your full resume with last drawn, expected salary and availability\u00a0to Bond West Application Email Address\u00a0\"Click Here\"\u00a0or via\u00a0\"APPLY\" button.\n\nFor any query, please feel free to contact\u00a0Mr. Wongat 2957 8079.\n\nFor more job opportunity, please visit our website:\u00a0www.bondwest.com.hk\n\n(Data collected is only for recruitment purpose)", "employment_types": ["Full Time"], "selling_points": ["Exp. of handle finance clients", "Leading a small size team", "Focus on Infrastructure/ Network project"], "locations": ["Central"], "categories": ["Information Technology (IT)", "IT Project Management / Team Lead", "IT Management", "Application Specialist - Network"], "post_time": "2022-01-14T10:12:18Z", "salary": {"currency": null, "max": null, "min": null, "period": "monthly", "term": null}, "salary_visible": false, "title_keywords": ["team leader"], "responsibilities": ["it infrastructure", "server hardware", "software", "technical support", "systems", "implementation", "application systems", "administration"], "requirements": {"degrees": ["diploma holder", "certificate"], "majors": ["it"], "languages": ["english", "mandarin"], "language_level": ["good command"], "hard_skills": ["mcse", "plus", "dns", "vmware", "tcp", "microsoft office", "ccnp", "ip", "firewall", "server", "wan", "windows server", "microsoft exchange"], "soft_skills": [], "languages_combined": [{"language": "english", "language_level": ["good command"]}, {"language": "mandarin", "language_level": ["good command"]}]}, "experience_required": {"duration": ["at least 4 years"], "field": []}}, {"job_id": "100003009044859", "location_code": "hk", "company": "Mad Mobile Application Development Limited", "job_title": "IT Project Manager", "description": "The Role\n\nWork with all stake holders, regional partners and customer to complete project within defined schedule and achieve set targets.\nPrepare documents for the whole project implementation.\nDrive internal and third-party service review meetings covering performance, service improvements, quality and processes.\nCoordinate with various parties for service launch.\nLead & control the project related risk management process & ad-hoc tasks as assigned.\n\nTo Qualify\n\nDegree holder in Information Technology or related disciplines.\nAt least 5 years of working experience in IT with at least 3 years project management experience.\nAble to work independently and meet project deadlines.\nA good team player that is self-motivated, detail-oriented and able to work under pressure.\nGood command of spoken and written English and Chinese (Cantonese and Mandarin).\n\n(Candidate with less experience will be considered as Senior Project Coordinator)\n\nWe Offer\n\nMAD MAD offers the right candidate 5-day work week, competitive salary package and fringe benefits, discretionary bonus, and a friendly and wonderful working environment.\n\nTo Apply\n\nThis is definitely a golden opportunity to gain valuable experience in an excellent company.\n\nDue to the high volume of applicants, only shortlisted candidates will be notified. All personal data collected will be used for recruitment purpose only.", "employment_types": ["Full Time"], "selling_points": [], "locations": ["Tsuen Wan Area"], "categories": ["Information Technology (IT)", "IT Project Management / Team Lead", "IT Management", "Product Management / Business Analyst"], "post_time": "2022-01-13T06:28:21Z", "salary": {"currency": null, "max": null, "min": null, "period": "monthly", "term": null}, "salary_visible": false, "title_keywords": ["it project manager"], "responsibilities": ["control", "management", "ad-hoc tasks", "review", "quality", "implementation", "coordinate with", "project management", "schedule", "prepare documents", "work under pressure"], "requirements": {"degrees": ["degree holder"], "majors": ["related disciplines", "information technology"], "languages": ["cantonese", "english", "chinese", "mandarin"], "language_level": ["good command"], "hard_skills": ["project management"], "soft_skills": ["work independently", "self-motivated", "good team player", "detail-oriented", "project management", "work under pressure"], "languages_combined": [{"language": "cantonese", "language_level": ["good command"]}, {"language": "english", "language_level": ["good command"]}, {"language": "chinese", "language_level": ["good command"]}, {"language": "mandarin", "language_level": ["good command"]}]}, "experience_required": {"duration": ["at least 3 years", "at least 5 years"], "field": ["project management", "it"]}}, {"job_id": "100003009035039", "location_code": "hk", "company": "Macleans Consulting International Limited", "job_title": "Senior IT Manager, Enterprise Architect - MNC (Group Level) [ERP]", "description": "About our client:\n\nOur client is a MNC Manufacturing Group having offices in Hong Kong, China, Asia, UK and US.\u00a0 Due to their continuous expansion and re-engineering & New coming Cloud projects, this role reports to the Group IT Director, opportunity to be promoted to Director Level.\n\n\nStrong Enterprise Architecture and systems Roadmap\n\n*TOGAF Certification is a MUST\nImplemented large-scaled ERP Systems\n\n\nResponsibilities:\n\nPlans, organizes, coordinates, and directs the activities of IT EA/Solutions Service teams to initially establish sound enterprise architecture and systems roadmap; effectively deliver, deploy and review appropriate IT solutions;\nIn conjunction and collaboration with business units, plans and establishes an appropriate enterprise architecture and roadmap that align IT with business, articulates the business and applications, defining the information flow, and mapping the transition;\nEstablishes and maintains appropriate enterprise architectural framework, governance, and documentation;\nContributes to the formulation and implementation of IT strategies, policies, plans, programs, processes, guides and standards of the IT Department;\nRecruits, selects,evaluates and motivate staff; assigns and reviews projects with project managers to determine work priorities and monitor progress and risks; ensures adherence to standards and procedures; identifies, recommends and initiates staff training and development;\nCollaborates and works closely with other IT sections and Business Units to identify opportunities and initiatives to satisfy business requirements or enhance efficiency, and acts as a catalyst for innovation and change;\nContribute to the preparation of IT budget and monitoring of expenditures.\nRequirements & Qualifications:\n\nBachelor Degree in Information Technology / Information Systems / Computing or relevant discipline, a relevant Higher Degree is preferred;\n*TOGAF Certification is a MUST\nSound project management track record, PMI Certified is an advantage;\nPractical experience on Agile development;\nKnowledge and experience in Enterprise Architecture and SDLC methodology\nMinimum 10 years\u2019 experience in software development with minimum 6 years in managing systems developments and project management;\nKnowledge and experience on large-scaled ERP System implementation (e.g. Oracle EBS and Microsoft Dynamics AX) and supply chain management, experience Manufacturing is a plus;\nFluent in English, Mandarin and Cantonese\nAble to present complex ideas or situations to senior management in a clear, concise and precise;\nWilling to initiate change in a challenging environment, able to deal with people at different levels;\nBased in Hong Kong, with extensive travelling to South China on a regular basis, and travelling periodically to overseas factories;\nOpportunity to be promoted to Director Level\n\nTo apply, please click on the \u2018Apply Now\u2019 button below or contact Nick Chow at (852)-3502 2637 for a confidential discussion.\u00a0 Alternatively, email your resume (with your notice period, current and expected salary) to\u00a0nick.chow@macleansgroup .com\n\nYour interest will be treated in strict confidence and only shortlisted candidates will be notified.\n\nPrivacy Statement\n\nData collected will be used for recruitment purposes only. Personal data provided will be used strictly in accordance with the relevant data protection law of Hong Kong Special Administration Region.\n\n\u00a0\u00a0\u00a0\u00a0\u00a0\u00a0\u00a0\u00a0\u00a0\u00a0\u00a0\u00a0\u00a0\u00a0\u00a0\u00a0\u00a0\u00a0\u00a0\u00a0\u00a0", "employment_types": ["Full Time", "Permanent"], "selling_points": ["*TOGAF + Enterprise Architecture and Roadmap", "Large ERP ; opportunity to Director Grade", "Manufacturing/ Logistics/ Supply Chain/ Retail"], "locations": ["Not Specified"], "categories": ["Information Technology (IT)", "IT Project Management / Team Lead", "IT Management", "Network & System"], "post_time": "2022-01-10T05:34:40Z", "salary": {"currency": null, "max": null, "min": null, "period": "monthly", "term": null}, "salary_visible": false, "title_keywords": ["senior it manager"], "responsibilities": ["monitor progress", "policies", "systems", "teams", "review", "implementation", "procedures", "it budget", "monitoring", "deploy", "documentation", "plans", "architecture"], "requirements": {"degrees": ["degree", "bachelor"], "majors": ["information technology"], "languages": ["cantonese", "english", "mandarin"], "language_level": ["fluent"], "hard_skills": ["plus", "agile", "project management", "sdlc", "erp system", "oracle"], "soft_skills": ["confidence", "agile", "clear", "project management", "deal with people", "precise", "extensive"], "languages_combined": [{"language": "cantonese", "language_level": ["fluent"]}, {"language": "english", "language_level": ["fluent"]}, {"language": "mandarin", "language_level": ["fluent"]}]}, "experience_required": {"duration": ["minimum 10 years", "minimum 6 years"], "field": ["management", "manufacturing", "development", "supply chain", "project management", "erp system", "software development"]}}, {"job_id": "100003009047727", "location_code": "hk", "company": "Public Bank (Hong Kong) Ltd", "job_title": "Project Manager - Mobile & Internet Application (Ref: CO-PM)", "description": "Manage IT projects (related to Mobile and Internet), plan and control all phases of SDLC including feasibility study, systems analysis and design, system development, implementation and maintenance.\nPrepare project planning, resources management, project budget management and vendor management.\nMonitor and keep track on milestones and facilitate mitigation of issues and risks.\nFormulate, consult, and instruct project members to provide quality deliverables.\nCollaborate with internal and external stakeholders to execute system project plan.\nMaintain open and clear relationships with project stakeholders to facilitate decision making and resolve issues with relevant teams.\nLead the project team members to accomplish the project goals.\nDegree holder in Information Technology or related discipline with at least 8 years of working experience on application development and support in financial sector.\nStrong project management equipped with problem solving, analytical skills, and decision making skills.\nExcellent communication and coordination skills to liaise project teams to achieve project goals.\nSolid experience in managing SDLC on Mobile and Internet application.\nExperience in J2EE, Java, Spring Boot, Swift, Objective-c, Android, Oracle, MSSQL, IBM WebSphere, IBM MQ, AIX, Linux is an advantage.\nExperienced or Certified in FinTech technology such as AI and Big Data Stream, Distributed Ledger Technology Stream, Open Banking and API Stream, and/or Regtech stream is an advantage.\nGood sense in FinTech market trends is a plus.\n\n\n\nTo apply, interested parties please follow the application methods available in the Bank\u2019s career website https://www.publicbank.com.hk/en/aboutus/careeropportunities. You can send us your resume quoting our job reference number together with present & expected salary (a must) to the Human Resources Department by email or fax at 2815 3157 or by post to Human Resources Department, 12/F, Public Bank Centre, 120 Des Voeux Road Central, Hong Kong. You may also visit our career website for other career opportunities available within our Group.\n\nPersonal data collected will be used for recruitment purpose only and will be treated in accordance with the Bank\u2019s Personal Information Collection Statement, a copy of which has been available in the Bank\u2019s career website.", "employment_types": ["Full Time", "Permanent"], "selling_points": [], "locations": ["Not Specified"], "categories": ["Information Technology (IT)", "IT Project Management / Team Lead", "IT Management", "Network & System"], "post_time": "2022-01-15T03:49:01Z", "salary": {"currency": null, "max": null, "min": null, "period": null, "term": null}, "salary_visible": false, "title_keywords": ["project manager"], "responsibilities": ["collaborate with", "liaise", "budget", "quality", "big data", "design", "communication", "maintain", "plan", "application development", "control", "monitor", "implementation", "teams", "banking", "management", "project planning", "maintenance", "analysis", "systems", "project plan", "project management", "coordination"], "requirements": {"degrees": ["degree holder"], "majors": ["information technology"], "languages": [], "language_level": [], "hard_skills": ["plus", "ai", "vendor", "budget management", "java", "problem solving", "mssql", "analytical skills", "objective-c", "sdlc", "oracle", "linux", "maintenance", "analysis", "mobile", "project management", "spring", "swift", "android"], "soft_skills": ["decision making skills", "coordination skills", "analytical skills", "clear", "project management", "problem solving", "communication", "decision making"], "languages_combined": []}, "experience_required": {"duration": ["at least 8 years"], "field": ["related", "application development", "financial", "information technology"]}}, {"job_id": "100003009051073", "location_code": "hk", "company": "Lenovo Group Limited", "job_title": "Technical Account Manager", "description": "Day-To-Day Responsibilities:\n\nRelationship:\n\nAble to maximize the value of the customer\u2019s investment in Lenovo products and services throughout the end to end customer lifecycle. The TAM manages customer escalations and acts as the customer\u2019s advocate.\nEffective ownership, communication, coordination, and facilitation of support service activities between the Customer and support teams, account teams, field service personnel, and customers.\n\nEscalation management:\n\nActs as a single point of contact for customer escalations and owns the coordination and oversight to problem solving efforts between customers, Support engineers, field service personnel, software support, investigation and analysis of product problems.\nDevelops and delivers post incident reports on all critical support incidents, adheres to customer support plans and relationships.\nUses complex analytical skills to recognize trends and improve performance.\n\nPrevention:\n\nRequires a general understanding of and technical competence in PC technologies.\nDevelops and coordinates proactive maintenance initiatives based on industry best practices and statistical data trends.\n\nOptimization:\n\nIdentifies and leads continuous improvement activities in support of customer or internal business processes.\n\nSupport:\n\nLeads complex service delivery processes, develops creative resolutions to complex problems and ensures contractual support service deliverables are understood and managed effectively.\n\nCollaboration:\n\nCompiles, analyzes and interprets statistical data and trends relating to service level and operational effectiveness.\n\nIn this role, you will be reporting to a Premier TAM Manager.\n\nKey Competencies Needed:\n\nSuperior knowledge of PC technology, market trends, vendor competition. Strong understanding of sales strategies and management principles.\nAbility to effectively interact and communicate with different levels of people.\nExcellent presentation, communications and interpersonal skills.\nProficient in Microsoft Office programs and PC technologies.\nExcellent organization skills, must be a self-starter who has experience in managing multiple initiatives simultaneously in a demanding and changing environment.\nAbility to build effective virtual teams and drive results through others in a complex cross-functional organization required.", "employment_types": ["Full Time"], "selling_points": ["An exciting client facing role", "Robust, fast-growing organization", "Take ownership of working with your stakeholders"], "locations": ["Quarry Bay"], "categories": ["Information Technology (IT)", "IT Project Management / Team Lead", "Support", "IT Management"], "post_time": "2022-01-15T01:50:26Z", "salary": {"currency": null, "max": null, "min": null, "period": "monthly", "term": null}, "salary_visible": false, "title_keywords": ["account manager"], "responsibilities": ["service delivery", "reporting", "management", "communicate with", "software", "maintenance", "data", "analysis", "teams", "investigation", "communication", "reports", "contact", "coordination", "plans"], "requirements": {"degrees": [], "majors": [], "languages": [], "language_level": [], "hard_skills": ["maintenance", "microsoft office", "analysis", "vendor", "analytical skills", "problem solving", "pc"], "soft_skills": ["creative", "analytical skills", "communication", "problem solving", "interpersonal skills", "coordination", "organization skills", "proactive", "presentation", "superior"], "languages_combined": []}, "experience_required": {"duration": [], "field": []}}, {"job_id": "100003009047501", "location_code": "hk", "company": "CITIC Telecom International Holdings Limited", "job_title": "System Analyst / Assistant Manager", "description": "\u00a0Responsibilities:\u00a0\n\nMaintain and support Company\u2019s management system (ERP system and MSS management system)\nResponsible for system configurations, architecture design and planning\nPerform system upgrade, backup and recovery of ERP & MSS systems\nFormulate project plans and timeline to fulfill business requirements\nProvide technical training for team members\n\nRequirements:\n\nDegree holder in Computer Science, Computer Engineering, Information Technology or related\u00a0disciplines\nMinimum 3 years of experience in IT\u00a0or telecommunications industry\nExperience in Oracle EBS R12 ERP system implementation and management\nExperience in IBM AIX, WebLogic, Oracle Forms and Report\u00a0would be an advantage\nStrong problem solving and communication skills\nGood command in both spoken and written English and Chinese (Cantonese & Mandarin)\nCandidates with more experience will be considered as Assistant Manager\n\nFringe Benefits:\n\nDouble pay\nAttractive performance bonus\nTransportation allowance\nMedical & dental insurance\nFree meals\nFree shuttle bus service\nTraining subsidies\nStaff discount\n\n\nWe offer competitive salary and benefit package including double pay, medical and dental benefits, 5-day work, 14 days paid annual leave and free shuttle bus service to the capable candidate. If you are interested, please immediately send your application stating\u00a0your current & expected salary and date availability with full resume\u00a0to\u00a0Human Resources Department\u00a0by email by clicking \"Apply Now\". Please clearly indicate the applied position and reference number on your application.\n\n\nAll personal data received will be treated strictly confidential and will be used for employment related purpose only.", "employment_types": ["Full Time", "Permanent"], "selling_points": ["Manage ERP, MSS", "Experience in IT or telecommunications industry", "Double Pay, Bonus, 5-day work, Medical & Dental"], "locations": ["Kwai Fong"], "categories": ["Information Technology (IT)", "Application Specialist - Software", "IT Project Management / Team Lead", "IT Management"], "post_time": "2022-01-14T03:20:35Z", "salary": {"currency": null, "max": null, "min": null, "period": "monthly", "term": null}, "salary_visible": false, "title_keywords": ["assistant manager", "system analyst"], "responsibilities": ["management", "systems", "design", "maintain", "plans", "architecture", "planning"], "requirements": {"degrees": ["degree holder"], "majors": ["related disciplines", "computer engineering", "computer science", "information technology"], "languages": ["cantonese", "english", "chinese", "mandarin"], "language_level": ["good command"], "hard_skills": ["problem solving", "erp system", "oracle"], "soft_skills": ["problem solving", "communication skills"], "languages_combined": [{"language": "cantonese", "language_level": ["good command"]}, {"language": "english", "language_level": ["good command"]}, {"language": "chinese", "language_level": ["good command"]}, {"language": "mandarin", "language_level": ["good command"]}]}, "experience_required": {"duration": ["minimum 3 years"], "field": ["telecommunications", "erp system", "it", "management"]}}, {"job_id": "100003009053835", "location_code": "hk", "company": "Konew Financial Express Ltd", "job_title": "Quality Assurance Analyst", "description": "Konew Financial Express is one of the leading FinTech companies in money lending industry at Hong Kong, Taiwan and Mainland China. Konew aims to bring great customer experience to everyone\u2019s financial journey. We strive to improve people\u2019s lives by reinventing financial services through innovative digital technology. We put our people first, whether it\u2019s our customers or our employees.\n\nDue to expansion of the business, this is a new hiring position of\u00a0Quality Assurance Analyst to join our high growth and dynamic Digital team. You will be responsible for our FinTech product testing and rollout, as well as the quality of the overall process. To succeed in this role, you should be creative, willing to learn new technology and a problem-solver with passion for the FinTech industry.\n\nMain Duties & Responsibilities:\n\n\nCollaborate with project manager, product manager, development teams and other key stakeholders\nDesign and prepare Test plans, Test Scenarios, and Test Cases according to user requirements\nEnsure the deliverables meet the planned level of performance and comply with established quality standards\nIdentify application issues, report discrepancies, prepare test reports and recommend improvements\nIdentify areas for shift left and shift right as part of early testing and maximize reusability\nDue diligence of DEV and QA processes, identify gaps and suggest improvements\nReview / Prepare Playbook, Guideline, Standard and Templates\n\nRequirements:\n\n\nAt least 5 years of relevant experience in software testing and System Development Life Cycle\nStrong knowledge of QA methodologies, tools and processes\nExperience in performing testing of banking applications\nSolid experience in engaging in Testing (e.g. functional, Stress, UAT) for Mobile App/ Website/ System projects\n\u00a0Experience on test cases automation will be an advantage\nExperience in product lifecycle management, preferably in agile framework\nExcellent communication, interpersonal and presentation skills\n\u00a0Problem-solving aptitude, Well-organized, self-motivated and able to work under pressure\nExperience on financial institutes background will be an advantage\nExcellent command of spoken and written Chinese and English\n\nWe offer:\n\nDiscretionary bonus\nMedical insurance\nDental insurance\nHardship allowance\nCompetitive annual leave days\nBirthday leave\nAnniversary leave\nStudy leave\nMarriage leave\nCompassionate leave\n\nHow to apply:\n\nInterested parties, please send your resume stating your expected salary to Human Capital Department\u00a0by clicking \"APPLY NOW\".\n\n(We are an equal opportunity employer.\u00a0 Personal data collected will be used for recruitment purpose only.\u00a0 The unsuccessful applications will be destroyed after 6 months.)", "employment_types": ["Full Time", "Permanent"], "selling_points": ["Design and execute functional test plans", "Prepare Project Test Strategy/Plan", "At least 5 years of relevant testing experience"], "locations": ["Central"], "categories": ["Information Technology (IT)", "IT Management", "Software Development", "Testing / QA"], "post_time": "2022-01-17T07:36:08Z", "salary": {"currency": null, "max": null, "min": null, "period": "monthly", "term": null}, "salary_visible": false, "title_keywords": ["quality assurance analyst"], "responsibilities": ["collaborate with", "due diligence", "review", "teams", "quality", "design", "testing", "reports", "suggest improvements", "plans", "report"], "requirements": {"degrees": [], "majors": [], "languages": ["english", "chinese"], "language_level": ["excellent"], "hard_skills": ["mobile", "problem-solving", "agile"], "soft_skills": ["self-motivated", "agile", "problem-solving", "well-organized", "communication", "presentation skills", "interpersonal", "work under pressure"], "languages_combined": [{"language": "english", "language_level": ["excellent"]}, {"language": "chinese", "language_level": ["excellent"]}]}, "experience_required": {"duration": ["at least 5 years"], "field": ["management", "system development", "testing", "relevant experience", "banking", "financial"]}}, {"job_id": "100003009048244", "location_code": "hk", "company": "FromDB Limited", "job_title": "IT Project Manager Internship (SYSTEM) \u898b\u7fd2\u9805\u76ee\u7d93\u7406(\u7cfb\u7d71)", "description": "\n\u898b\u7fd2IT\u9805\u76ee\u7d93\u7406\n\u85aa\u916c\u6c34\u5e73: \u898b\u7fd2\u7d1a\u5225\n\u6700\u9ad8\u6708\u85aa: 12000\n\u5408\u7d04\u5f62\u5f0f\n\u6c92\u6709\u56fa\u5b9a\u4e0a\u73ed\u6642\u9593\u3001\u4f46\u9808\u6e96\u6642\u4ea4\u4ed8\u9805\u76ee\n\u672c\u9805\u76ee\u662f\u958b\u767c\u4e00\u500b\u5eab\u5b58\u53ca\u6703\u8a08\u7cfb\u7d71\n\u5728\u6b63\u5f0f\u958b\u767c\u4e3b\u7ba1\u6307\u5c0e\u4e0b,\u968e\u6bb5\u5f62\u5f0f,\u5354\u52a9\u958b\u767c\u4eba\u54e1\u958b\u767c\u7cfb\u7d71\u4ea4\u4ed8\u4e88\u5ba2\u4eba\n\u6027\u683c\u8981\u6c42: \u7406\u6027\u53ca\u908f\u8f2f\u5f37\u3001\n\u6280\u80fd\u8981\u6c42: \u6587\u5b57\u8868\u9054\u529b\u4f73\u3001\u7565\u61c2\u6d41\u7a0b\u5716\n\n\u9810\u671f\u5408\u7d04\u671f: 3 \u500b\u6708\n\u8fa6\u516c\u5ba4\u6700\u4f4e\u6642\u6578: \u6bcf\u661f\u671f 12\n\n\u6c42\u8077\u7533\u8acb\u622a\u6b62\u65e5\u671f: 31/1/2022\n\n", "employment_types": ["Full Time"], "selling_points": [], "locations": ["Kwun Tong"], "categories": ["Information Technology (IT)", "IT Management", "Product Management / Business Analyst"], "post_time": "2022-01-14T06:02:30Z", "salary": {"currency": null, "max": null, "min": null, "period": "monthly", "term": null}, "salary_visible": false, "title_keywords": ["it project manager", "internship"], "responsibilities": [], "requirements": {"degrees": [], "majors": [], "languages": [], "language_level": [], "hard_skills": [], "soft_skills": [], "languages_combined": []}, "experience_required": {"duration": [], "field": []}}, {"job_id": "100003009051174", "location_code": "hk", "company": "IT Solutions Ltd.", "job_title": "Quality Assurance Officers (Treasury System Project) - Major Bank", "description": "We are searching for a number of high-calibre\u00a0QA Officers\u00a0to work on the QA and testing of Treasury System software for major projects in a Major Bank.\n\nResponsibilities:\n\nWork on QA of IT Software\nPrepare test plan and test cases.\nPerform User Acceptance Test.\nPrepare testing report and UAT logs.\n\nRequirements:\n\nDegree in Finance, Business Administration, Computer Science or related.\nStrong written communications skills\u00a0in English and Chinese.\nGood knowledge of MS Office applications.\nTraining will be provided\nFresh Graduates are also welcome to apply.\n\nBenefits:\u00a0\n\nAttractive remuneration will be offered to the successful candidates.\n\u00a0Excellent opportunity to further develop your professional skills in Banking Sector.\n\nIf you are interested, please send your resume in MS Word format, specifying your availability, current and expected salaries to:\n\njobs @itsolutions.com.hk\u00a0\n\nor\n\nPlease click the Apply Now button and attach your cv in MS Word Format, specifying your availability, current and expected salaries.\n\nPersonal data collected will be used for recruitment purposes only.\n\nIT Solutions Ltd.\nSuite 2102\n21/F Lucky Building\n39 Wellington Street\nCentral, Hong Kong\n\n(P.S. We do not process applications from overseas for this position)", "employment_types": ["Full Time"], "selling_points": ["Gain Knowledge & Experience in Banking", "Develop career in IT field", "5-day Work Week"], "locations": ["Central"], "categories": ["Information Technology (IT)", "IT Management", "Testing / QA"], "post_time": "2022-01-15T04:07:39Z", "salary": {"currency": null, "max": null, "min": null, "period": "monthly", "term": null}, "salary_visible": false, "title_keywords": [], "responsibilities": ["uat", "software", "testing", "plan", "report"], "requirements": {"degrees": ["degree"], "majors": ["finance", "business administration", "computer science"], "languages": ["english", "chinese"], "language_level": [], "hard_skills": ["ms office"], "soft_skills": [], "languages_combined": [{"language": "english", "language_level": []}, {"language": "chinese", "language_level": []}]}, "experience_required": {"duration": [], "field": []}}, {"job_id": "100003009051178", "location_code": "hk", "company": "IT Solutions Ltd.", "job_title": "Major Bank: IT Project Management Assistants / Project Coordinators", "description": "We are searching\u00a0for a number of high-calibre\u00a0IT\u00a0Project Management Assistants / Project Coordinators\u00a0in\u00a0Major Bank.\n\nResponsibilities:\n\nAssist Project Manager in updating project plans, budgets and work schedules\nCoordinate relevant parties for meetings and prepare minutes\nPrepare presentation materials and\u00a0executive reports\nCommunicate with end user\nExecute the administrative tasks\n\nRequirements:\n\n\nDegree in Business Administration, Information Technology or related discipline\n0-3 years in\u00a0project coordination or administrative work\u00a0\nFamiliar with MS Excel, Work & PowerPoint\nGood communication & writing skills (both Chinese & English)\nImmediate available is preferred\nWelcome Fresh Graduates or less experience candidates to apply\n\u00a0Benefits:\n\nAttractive remunerations will be offered to the successful candidates.\nExcellent opportunity to further develop your Project Management professional skills in a Major Bank.\n\nIf you are interested, please send your resume in MS Word format, specifying your availability, current and expected salaries to:\n\njobs @itsolutions.com.hk\n\n\nor\n\nPlease click the Apply Now button and attach your cv in MS Word Format, specifying your availability, current and expected salaries.\n\n\nPersonal data collected will be used for recruitment purposes only.\n\n\nIT Solutions Ltd.\nSuite 2102\n21/F Lucky Building\n39 Wellington Street\nCentral, Hong Kong\n\n(P.S. We do not process applications from overseas for this position)", "employment_types": ["Full Time"], "selling_points": ["Develop Career in banking", "Project Coordination", "0-3 years Experience"], "locations": ["Not Specified"], "categories": ["Admin & HR", "Clerical / Admin Staff", "Banking / Finance", "Others", "Information Technology (IT)", "IT Management"], "post_time": "2022-01-15T04:09:25Z", "salary": {"currency": null, "max": null, "min": null, "period": "monthly", "term": null}, "salary_visible": false, "title_keywords": ["coordinators"], "responsibilities": ["communicate with", "budgets", "schedules", "coordinate", "reports", "administrative tasks", "plans"], "requirements": {"degrees": ["degree"], "majors": ["business administration", "information technology"], "languages": ["english", "chinese"], "language_level": ["good"], "hard_skills": ["ms excel", "powerpoint", "writing skills"], "soft_skills": ["communication", "coordination", "writing skills"], "languages_combined": [{"language": "english", "language_level": ["good"]}, {"language": "chinese", "language_level": ["good"]}]}, "experience_required": {"duration": [], "field": []}}, {"job_id": "100003009047900", "location_code": "hk", "company": "Public Bank (Hong Kong) Ltd", "job_title": "System Project Manager (Ref: JD-SPM)", "description": "To collect and deliver user requirements that best meet business needs. Properly document all the requirements and act as a bridge between IT and user departments.\nTo have a good understanding of operation flow, process flow, journey maps, etc. that can facilitate the re-engineering of customer journey or user workflow\nTo create a detailed business analysis, outlining problems, opportunities and solutions for a business and workflow automation\nTo liaise with relevant channel teams, technology teams, digital teams, legal, risk and compliance teams, to document design options and recommendations\nTo participate in all phases of the Software Development Life Cycle (SDLC) and perform user acceptance testing\nDegree holder in Business Administration, Computer Science, Information Technology or other related disciplines;\nMinimum 10 years working experience in Information Technology, with at least three years project management experience\n3-5 years of experience in banking industry is preferred.\nStrong English writing skill.\nAbility to work independently.\nStrong analytical thinking, system sense and decision making.\nTechnical experience in Java, VB.NET, SQL Server, Oracle and /or AS400 in advantage.\nExperience in banking systems, especially in stock trading, loans and treasury, is preferred.\n\n\nTo apply, interested parties please follow the application methods available in the Bank\u2019s career website https://www.publicbank.com.hk/en/aboutus/careeropportunities. You can send us your resume quoting our job reference number together with present &\u00a0expected salary (a must)\u00a0to the Human Resources Department by email or fax at\u00a02815 3157\u00a0or by post to\u00a0Human Resources Department, 12/F, Public Bank Centre, 120 Des Voeux Road Central, Hong Kong. You may also visit our career website for other career opportunities available within our Group.\n\nPersonal data collected will be used for recruitment purpose only and will be treated in accordance with the Bank\u2019s Personal Information Collection Statement, a copy of which has been available in the Bank\u2019s career website.", "employment_types": ["Full Time", "Permanent"], "selling_points": [], "locations": ["Not Specified"], "categories": ["Banking / Finance", "Others", "Information Technology (IT)", "IT Project Management / Team Lead", "IT Management"], "post_time": "2022-01-15T03:49:02Z", "salary": {"currency": null, "max": null, "min": null, "period": null, "term": null}, "salary_visible": false, "title_keywords": ["project manager"], "responsibilities": ["software", "compliance", "teams", "document design", "systems", "testing", "liaise with", "project management", "banking", "business analysis", "re-engineering", "administration"], "requirements": {"degrees": ["degree holder"], "majors": ["related disciplines", "business administration", "computer science", "information technology"], "languages": ["english"], "language_level": [], "hard_skills": ["java", "analysis", "writing skill", "sql", "project management", "sdlc", "server", "oracle"], "soft_skills": ["work independently", "detailed", "writing skill", "project management", "decision making"], "languages_combined": [{"language": "english", "language_level": []}]}, "experience_required": {"duration": ["minimum 10 years", "at least three years", "3-5 years"], "field": ["banking industry", "information technology", "project management", "banking", "trading"]}}, {"job_id": "100003009048931", "location_code": "hk", "company": "A-1 Bakery Co., (HK) Limited", "job_title": "IT Officer", "description": "Responsibilities:\n\nWork closely with end-users to collect business requirements & needs into functional requirement specifications.\nInvolved in all stages of the Software Development Life Cycle, including development, system integration test and UAT support.\nAble to do a program development independently, and code review.\nDocument composition such as design specification, deployment guide, admin guide, user guide, etc.\nIn charge of daily operation and administration of ERP system\nFacilitating the enhancement and maintenance of ERP system and related hardware/equipment, including UAT testing, support, trouble-shoot and evaluation\nDesign, configure and maintain for Hardware, Network, VM Machine, Backup Structure\nDesign and configure Active Directory\nInvestigate, diagnose and solve hardware & software problems\nAble to analyst and identify the problems and provide solutions during project cycles.\nAd-hoc assignments as per requested\n\nRequirements:\n\nDegree holder in Computer Science, Information Systems and/or related disciplines.\nMinimum 3 years' experience in IT industry with at least 2 years in system development\nExperienced in system development in system analysis, design and coding.\nProven experience in software design and development using .NET, C#, VB.NET, ASP.NET, and /or other programming languages.\nFamiliar of database management system (e.g. MS SQL Server, MySQL, MS Access).\n1-2 years\u2019 experience with Enterprise Resource Planning systems (ERP) eg, SAP, Oracle JD Edwards, Microsoft Dynamics or other ERP systems.\nExperience in functional / technical architecture design of ERP or applications is an advantage.\nExcellent in analytical, problem solving and interpersonal skills.\nGood command of both written and spoken English and Cantonese.\nVerbal and written communication skills in Japanese are an advantage.\n\u2018Can do\u2019 attitude and able to take new challenges.", "employment_types": ["Full Time", "Permanent"], "selling_points": ["Degree holder", "Minimum 3 years' experience in IT industry", "Immediate available is preferred"], "locations": ["Shatin Area"], "categories": ["Information Technology (IT)", "Support", "IT Management", "Product Management / Business Analyst"], "post_time": "2022-01-14T07:44:14Z", "salary": {"currency": null, "max": null, "min": null, "period": "monthly", "term": null}, "salary_visible": false, "title_keywords": ["it officer"], "responsibilities": ["software", "uat", "maintenance", "active directory", "ad-hoc assignments", "review", "daily operation", "uat testing", "design", "diagnose", "provide solutions", "hardware", "specifications", "maintain", "evaluation", "collect business requirements", "administration"], "requirements": {"degrees": ["degree holder"], "majors": ["related disciplines", "computer science"], "languages": ["cantonese", "japanese", "english"], "language_level": ["advantage", "good command"], "hard_skills": ["erp systems", "oracle", "sap", "ms sql server", "analysis", "erp", "problem solving", "programming", "c#"], "soft_skills": ["problem solving", "communication skills", "interpersonal skills"], "languages_combined": [{"language": "cantonese", "language_level": ["good command"]}, {"language": "japanese", "language_level": ["advantage"]}, {"language": "english", "language_level": ["good command"]}]}, "experience_required": {"duration": ["at least 2 years", "1-2 years", "minimum 3 years"], "field": ["development", "design", "system development", "software design", "it", "planning"]}}, {"job_id": "100003009049151", "location_code": "hk", "company": "Hong Kong Interbank Clearing Ltd", "job_title": "Manager (Risk Management)", "description": "Major Responsibilities\n\nProvide overall coordination of risk management processes\nAssist in development and implementation of enterprise risk management framework, strategies, policy and procedures\nPartner with business units on implementation of process to identify risk, design and implement control measures and monitor the on-going effectiveness of internal controls over operational risk, liquidity and financial risk, data privacy risk, third-party risk and business continuity management\nCoordinate and conduct risk assessment on existing and new services\nAssist business units in remediation of internal control weaknesses identified in audit reviews and assessments\nPrepare regular reporting and metrics to present the risk posture of the company\nProvide advice to all business units on the company\u2019s new initiatives and existing operations from a risk and control perspective\nPerform other duties as assigned by supervisor(s)\nRequirements\n\nUniversity degree preferably in business, risk management, information system or related discipline\nMinimum 7 years of risk management experience preferably gained from major financial institutions with at least 3 years\u2019 experience at managerial level\nExpertise in various aspects of risk management as well as the services and operations of the financial sector\nKnowledge of risk management frameworks and relevant global / local regulatory requirements\nGood analytical, interpersonal, communication and presentation skills\nGood command of written and spoken English and Chinese, proficiency in Putonghua is an advantage\n\n\nHow to Apply\nInterested parties please send your curriculum vitae stating your current and expected salaries, and the contact phone number to the Human Resources Division, Unit B, 25/F, MG Tower, 133 Hoi Bun Road, Kwun Tong, Kowloon\u00a0\u00a0by clicking the \"Apply Now\" button below.\nAll applications and personal information collected will be treated in strict confidence and only be used for the purpose of recruitment and selection.\u00a0 The information collected will be accessed by our authorized personnel only.\u00a0 Those applicants not contacted by the Human Resources Division within two months from their application date should consider their applications filed for future reference which will be retained for one year for possible future job matching, and will be destroyed after the expiry of one year.", "employment_types": ["Full Time", "Permanent"], "selling_points": [], "locations": ["Ngau Tau Kok"], "categories": ["Banking / Finance", "Financial Services", "Information Technology (IT)", "IT Management", "Risk Management"], "post_time": "2022-01-14T08:11:01Z", "salary": {"currency": null, "max": null, "min": null, "period": null, "term": null}, "salary_visible": false, "title_keywords": ["manager"], "responsibilities": ["business continuity", "management", "control", "reporting", "perform other duties", "data", "operations", "procedures", "implementation", "design", "monitor", "coordinate", "audit", "provide advice", "coordination", "internal control"], "requirements": {"degrees": ["university degree"], "majors": ["risk management", "business"], "languages": ["putonghua", "english", "chinese"], "language_level": ["advantage", "proficiency", "good command"], "hard_skills": ["information system"], "soft_skills": ["communication", "presentation skills", "interpersonal"], "languages_combined": [{"language": "putonghua", "language_level": ["proficiency", "advantage", "good command"]}, {"language": "english", "language_level": ["proficiency", "advantage", "good command"]}, {"language": "chinese", "language_level": ["proficiency", "advantage", "good command"]}]}, "experience_required": {"duration": ["at least 3 years", "minimum 7 years"], "field": ["risk management", "financial institutions", "managerial"]}}, {"job_id": "100003009056175", "location_code": "hk", "company": "Master Communications Limited", "job_title": "Senior System Analyst / System Analyst", "description": "Responsibilities:\n\nDesign, implement new development projects and enhance existing applications\nContribute in all stages of the software development lifecycle (SDLC) including system integrations and UAT\nProvide on-going support, enhancement and maintenance to Company ERP and BI platform\nLiaise and coordinate with software vendors, contractors and user departments\nHandle ad-hoc tasks as assigned\n\nRequirements:\n\n\nDegree in Computer Science, Information Technology or related discipline\nMinimum 8-10 years IT working experience\nProficiency in ASP.NET C#, MSSQL, stored procedure, CSS and JavaScript\nKnowledge in Microsoft Dynamics NAV, C/AL programming or QlikView is an added advantage\nResponsible, independent and able to work under pressure\n\nPlease apply in confidence with full resume, listing present and expected salary and availability by clicking the \"Apply Now\" below.\n\nAll information will be used for recruitment purpose only.\n\nYou are\u00a0welcome to visit our website at\u00a0http://wilsoncomm.com.hk to get more Company information and our personal data privacy policy and practice..", "employment_types": ["Full Time", "Permanent"], "selling_points": ["5-day, Kwai Fong, free shuttle bus", "Proficiency in ASP.NET C#, MSSQL, CSS", "8-10 years relevant working experience"], "locations": ["Kwai Fong"], "categories": ["Information Technology (IT)", "Application Specialist - Software", "IT Management", "Software Development"], "post_time": "2022-01-18T03:29:03Z", "salary": {"currency": null, "max": null, "min": null, "period": "monthly", "term": null}, "salary_visible": false, "title_keywords": ["system analyst"], "responsibilities": ["liaise", "software", "maintenance", "uat", "ad-hoc tasks", "coordinate with", "design"], "requirements": {"degrees": ["degree"], "majors": ["computer science", "information technology"], "languages": [], "language_level": [], "hard_skills": ["qlikview", "c", "javascript", "programming", "mssql", "css", "c#"], "soft_skills": ["confidence", "independent", "responsible", "work under pressure"], "languages_combined": []}, "experience_required": {"duration": ["minimum 8-10 years"], "field": ["it"]}}, {"job_id": "100003009034344", "location_code": "hk", "company": "NewTrek Systems Limited", "job_title": "Project Manager", "description": "Job Responsibilities:\n\nBe responsible for project management of major IT Projects such as feasibility studies, IT strategy planning, infrastructure consulting, system development, and system maintenance\nAssess project scope / schedule, human resource requirements, and cost estimation in project bidding process\nBe responsible for composition and guiding IT technical staff to write the full spectrum of system documentation according to industry standards and to meet client requirements\nBe responsible to lead and supervise one or more teams of IT technical professionals to deliver IT solutions to clients\n\n\u00a0Requirements:\n\nHolder of Higher Diploma or degree in IT or equivalent\nMinimum 12 years IT experiences with the last 3 years in project management position\nMust be holder of Project Management Professional (PMP) Certification or PRINCE2 Registered Practitioner\nExperience in project management of Government projects a big advantage\nHands on past experience in system implementation preferred\nAdditional certification in IT security / audits also an advantage\nGood verbal and written communication skills in English is a must\nApplicant must provide present and expected salary.\u00a0", "employment_types": ["Full Time", "Permanent"], "selling_points": ["project management", "Assess project scope / schedule", "lead and supervise one or more teams"], "locations": ["Kwun Tong"], "categories": ["Information Technology (IT)", "Application Specialist - Software", "IT Project Management / Team Lead", "IT Management"], "post_time": "2022-01-10T03:12:38Z", "salary": {"currency": null, "max": null, "min": null, "period": "monthly", "term": null}, "salary_visible": false, "title_keywords": ["project manager"], "responsibilities": ["cost estimation", "consulting", "maintenance", "system documentation", "infrastructure", "teams", "project management", "major it projects", "schedule", "planning"], "requirements": {"degrees": ["diploma", "degree"], "majors": ["it"], "languages": ["english"], "language_level": ["good"], "hard_skills": ["system implementation", "project management", "pmp", "project management professional"], "soft_skills": ["communication skills", "project management", "hands on"], "languages_combined": [{"language": "english", "language_level": ["good"]}]}, "experience_required": {"duration": ["3 years", "minimum 12 years"], "field": ["project management", "it"]}}, {"job_id": "100003009045355", "location_code": "hk", "company": "Endeavour Search Limited", "job_title": "Senior IT Business Partner \u2013 Change Management & APAC Project Leadership", "description": "Executive Summary:\n\nPublic Listed firm with global market especially in Asia, North America, Europe, etc.\nStable, competitive salary, strong business growth - 700 staffs in Hong Kong \u2013 over 48,000 staffs globally\nMultinational, dynamic and employee driven working cultures and exposure\nNewly created role to lead internal IT change management and APAC project delivery; The successful job holder should be coming from a MNC background with strong stakeholder management experience across all levels; Enterprise level ERP/CRM/e-commerce experience will be a strong advantage; Consulting background is an advantage\nReport directly into company C-level business leaders\n\nMajor Responsibilities:\n\nOwn the overall IT roadmap of the corresponding business unit (BU)\nLead and facilitate the communication between the BU stakeholders and IT department\nEnsure successful projects/solutions executions with high quality deliverables\nWork with Operation Head to proactively identify business needs and opportunities and propose appropriate solutions\nCollaborate with Regional IT communities on different projects\nWork with different BU stakeholders/users to ensure successful roll out of different initiatives and solutions\nEnsure compliance with external regulatory requirements, internal control standards and company policies\n\nKey Requirements:\n\nDegree in Information Technology, Computer Science or related disciplines\nAt least 8 years relevant experience, preferable in an MNC environment with APAC exposure\nBusiness oriented and strives for appropriate solution and continuous enhancement\nGood business knowledge in manufacturing operation, supply chain, and product development process,\nExcellent verbal, written and inter-personal communication skills, with the ability to clearly articulate findings, considerations, recommendation and execution plans to different levels of stakeholders\nAble to take a holistic approach in planning out solutions for various business requirements\nAbility to adapt to new technologies, learn quickly and pass on this knowledge to others\nSolid experience in system implementation and project management\nWilling to take a very hands-on approach when necessary\nPrevious experience with start-up operations or new setups a definite asset\nPrevious experience with Oracle, WMS, and MES an advantage\nPrevious experience with e-commerce projects a strong plus\n\n\nTo apply, please send your CV in word document to peter(a)endeavourasia.com or call Peter at 3956-1828 for a confidential discussion.\n\n", "employment_types": ["Full Time", "Permanent"], "selling_points": ["Report directly to C-Level Business leaders", "MNC APAC Regional exposure an advantage", "Enterprise CRM/ERP/ECOM experience a plus"], "locations": ["Kwai Tsing Area"], "categories": ["Information Technology (IT)", "IT Project Management / Team Lead", "IT Management", "Technical / Functional Consulting"], "post_time": "2022-01-13T18:55:07Z", "salary": {"currency": null, "max": null, "min": null, "period": "monthly", "term": null}, "salary_visible": false, "title_keywords": [], "responsibilities": ["collaborate with", "regulatory requirements", "policies", "quality", "ensure compliance", "communication", "it roadmap", "internal control"], "requirements": {"degrees": ["degree"], "majors": ["related disciplines", "computer science", "information technology"], "languages": [], "language_level": [], "hard_skills": ["plus", "e-commerce", "word", "project management", "system implementation", "oracle"], "soft_skills": ["communication skills", "inter-personal", "project management", "hands-on", "articulate"], "languages_combined": []}, "experience_required": {"duration": ["at least 8 years"], "field": ["project management", "relevant experience", "e-commerce"]}}]