[{"job_id": "100003009054062", "location_code": "hk", "company": "EC Healthcare", "job_title": "Manager / Assistant Manager, Business Integration", "description": "Working closely with integration partners as well as internal cross function teams, this position is responsible for the smooth transition of post M&A business integration to achieve the set vision and synergy.\n\n\u00a0Job Responsibilities:\n\nLead discussion and drive execution on vision and strategy of the acquisition\nDevelop deep understanding of responsible pillar / discipline to drive value creation and synergy with group business\nAct as single point of contact for M&A partner\nDevelop and foster close working relationship with M&A partner and internal departments\nProject manage and coordinate with internal departments on integration tasks to ensure smooth integration of the M&A business\nLead business readiness planning and activities including communications, training etc. with relevant departments\nSetup governance structure and lead regular update on integration progress and escalate issues if required\nLead risks and issues management during and post M&A integration\nLead regular review of post M&A performance\n\nJob Requirements:\n\nDegree holder in Business, Communications or related discipline\nAt least 5 years of experience in business programme or project management\nExcellent communications, interpersonal, planning and organizing skills\nExperience in change management will be highly valued\nExperience in healthcare industry a definite advantage\nWilling to understand detail and possess a problem-solving mindset\nAbility to look at big picture and think strategically\nGood command of both spoken & written English and Chinese", "employment_types": ["Full Time"], "selling_points": ["Working closely with integration partners", "Smooth transition of post M&A business integration", "Discussion & drive execution on vision & strategy"], "locations": ["Mong Kok"], "categories": ["Information Technology (IT)", "IT Project Management / Team Lead", "IT Management", "Product Management / Business Analyst"], "post_time": "2022-01-17T08:15:57Z", "salary": {"currency": null, "max": null, "min": null, "period": "monthly", "term": null}, "salary_visible": false, "title_keywords": ["manager", "assistant manager,"], "responsibilities": ["management", "coordinate with", "develop", "regular review", "contact", "setup", "planning"], "requirements": {"degrees": ["degree holder"], "majors": ["business", "communications"], "languages": ["english", "chinese"], "language_level": ["good command"], "hard_skills": ["project management", "problem-solving"], "soft_skills": ["project management", "problem-solving", "interpersonal", "think strategically"], "languages_combined": [{"language": "english", "language_level": ["good command"]}, {"language": "chinese", "language_level": ["good command"]}]}, "experience_required": {"duration": ["at least 5 years"], "field": ["project management", "management", "business", "healthcare industry"]}}, {"job_id": "100003009054247", "location_code": "hk", "company": "CHOW TAI FOOK JEWELLERY CO LTD", "job_title": "Assistant Manager (IT Project Management Office PMO)", "description": "What You Will Own\n\nConduct project performance analysis and reporting to IT senior management\nHarmonize IT teams to engage and deliver project initiatives within budget and timeline\nProvide both verbal and written communications regarding project status, benefit, risks and issues\nMonitor the impacts and interdependencies between demands and resources to ensure project delivery efficiency\nCommunicate with business leaders to manage multiple demands, identify and resolve conflicting issues\nDevelop and introduce best practice project delivery approach\nDrive process improvements and project governance\nEnsure governance procedures are adhered for all projects throughout their project life cycle\nLead and assist with the deployment and use of IT Project Management tools, methodologies and standards within IT Division\nPerform other ad-hoc projects and tasks as assigned\nWho Will Thrive\nDegree holders with at least 5 to 8 years\u2019 work experience in PMO and IT governance\nProficient in SDLC project management execution and business analysis experience\nPrevious experience in setting up PMO is an advantage\nExperience on PM Tools (e.g. ServiceNow, JIRA) and Data Analytics tools (e.g. PowerBI, Qlik) is an advantage\nCustomer-oriented and self-motivated with excellent communication skill\nSelf-manage, proactive, independent, efficient, able to work under pressure in vague and fast growing environment\nCandidates with less experience will be considered as Officer (IT PMO)\nGood command of written and spoken English and Chinese as well as Putonghua\nHolder of PMP or ScrumMaster certification would be definitely an advantage\n\n\nBenefits\n\n5-day work\nCompetitive salary, staff meal, medical and dental insurance, life insurance\nVarious types of leave, e.g. Family-friendly leave, self-development leave,\u00a0Examination leave, marriage leave, birthday leave, volunteer service leave, etc\n\nWe offer excellent career opportunities, attractive remuneration package & benefits to the right candidate.\u00a0Interested parties please apply by clicking \"Apply Now\" with a full resume stating the latest and expected salary.\n\nAll information collected will be used for recruitment purposes only.", "employment_types": ["Full Time", "Permanent"], "selling_points": ["IT Governance, Project Management, IT Compliance", "ServiceNow", "ScrumMaster, ITIL, PMP"], "locations": ["Kwai Hing"], "categories": ["Information Technology (IT)", "IT Auditing", "IT Project Management / Team Lead", "Others"], "post_time": "2022-01-17T08:56:58Z", "salary": {"currency": null, "max": null, "min": null, "period": "monthly", "term": null}, "salary_visible": false, "title_keywords": ["assistant manager"], "responsibilities": ["communicate with", "reporting", "analytics tools", "ad-hoc projects", "data", "analysis", "budget", "teams", "monitor", "procedures", "develop", "communication", "project management", "business analysis", "senior management", "work under pressure"], "requirements": {"degrees": ["degree"], "majors": ["it"], "languages": ["putonghua", "english", "chinese"], "language_level": ["good command"], "hard_skills": ["data analytics", "analysis", "project management", "sdlc", "deployment", "pmp"], "soft_skills": ["efficient", "self-motivated", "independent", "communication skill", "project management", "customer-oriented", "proactive", "work under pressure"], "languages_combined": [{"language": "putonghua", "language_level": ["good command"]}, {"language": "english", "language_level": ["good command"]}, {"language": "chinese", "language_level": ["good command"]}]}, "experience_required": {"duration": ["at least 5 to 8 years"], "field": ["business analysis", "project management", "it governance", "it"]}}, {"job_id": "100003009054464", "location_code": "hk", "company": "Automated Systems (HK) Ltd", "job_title": "Assistant Project Manager", "description": "Responsibilities:\n\nTo deliver project management service including project planning, task scheduling, control and monitoring of project execution, risk management and progress reporting\nTo manage resource planning, allocation, cost control and ensure the project milestones/deliverables to be completed on time and meet the required quality standard\nTo organize and attend meeting to report progress and resolve any project related issues\nFollow up IT project related issues, co-ordinate and monitor the overall processes and status\nSupport the senior project managers to fulfill their role and provide precise reports and analysis to senior management\n\nRequirements:\n\nBachelor Degree in Computer Science, Information Technology or related disciplines\n1-2 years' experience in end-to-end IT project management with proven track record\nExperience in PC migration and relocation projects is a plus\nExcellent and effective communication skills in both English and Chinese with the ability to engage, influence, and inspire partners and stakeholders to drive collaboration and alignment\nWe offer 5-day week, public holidays, medical benefits, excellent career opportunities, considerable remuneration to the right candidates.\n\n\u201cIf you have the desire for an exciting and rewarding career, please send us your resume, stating your notice period, present and expected salary to Human Resources Department by clicking \"Apply Now\".\n\nTo learn us more, please visit our website: www.asl.com.hk\n\nWe are an equal opportunity employer. All applications will be treated in strict confidence. We regret that only shortlisted candidates will be notified. All personal data will be destroyed within six months after the selection process.\n%MCEPASTEBIN%", "employment_types": ["Full Time", "Contract"], "selling_points": ["To deliver project management service", "Bachelor Degree in Computer Science", "1-2 years' experience"], "locations": ["Lantau Island"], "categories": ["Information Technology (IT)", "IT Project Management / Team Lead", "IT Management", "Software Development"], "post_time": "2022-01-17T09:40:01Z", "salary": {"currency": null, "max": null, "min": null, "period": "monthly", "term": null}, "salary_visible": false, "title_keywords": ["assistant project manager"], "responsibilities": ["reporting", "project planning", "control", "management", "analysis", "monitoring", "quality", "monitor", "project management", "scheduling", "reports", "cost control", "report", "senior management", "planning"], "requirements": {"degrees": ["degree", "bachelor"], "majors": ["related disciplines", "computer science", "information technology"], "languages": ["english", "chinese"], "language_level": ["excellent"], "hard_skills": ["pc", "project management", "plus"], "soft_skills": ["communication skills", "project management"], "languages_combined": [{"language": "english", "language_level": ["excellent"]}, {"language": "chinese", "language_level": ["excellent"]}]}, "experience_required": {"duration": ["1-2 years"], "field": ["project management", "it"]}}, {"job_id": "100003009052895", "location_code": "hk", "company": "Haven of Hope Christian Service", "job_title": "Executive Manager - Information Technology (Ref : SSO/IT/EM/JDB)", "description": "Responsibilities:\nReport to the Senior Executive Manager \u2013 Information Technology (\u201cSEM/IT\u201d)\nAssist SEM/IT to define IT strategies for infrastructure that support organizational goals and plans\nManage IT infrastructure resources including infrastructure and helpdesk\nSupervise the IT Infrastructure Team to deliver high quality IT support service to the organisation\nManage IT procurement, service contracts and vendors\nCollaborate with users of multidiscipline in various projects\nCollaborate with IT Application Team to recommend and deliver solutions to the organisation\nRequirements:\nDegree or above in Information Technology or related discipline\nMinimum 10 years of relevant experience in IT infrastructure support, with at least 4 years\u2019 managerial experience\nIn-depth knowledge and hands-on experience in Microsoft Windows Server 2016, Exchange Server 2016 or later versions, Linux, VMware vSphere, Veeam, WAN, VPN, end-point security software\nAdvanced understanding in mobile and web technology, IT security requirements and issues\nAbility to manage vendors to deliver high quality and effective service to the organization\nProven track records for planning, implementation and maintenance of IT infrastructure with multiple and dispersed remote sites.\nStrong leadership, analytical and problem-solving skills\nGreat team player, independent, strong sense of responsibility and self- motivated\nGood verbal and written communications skills in English and Cantonese\nAlign with the Vision, Mission and Core Values of the Haven of Hope Christian Service\nPlease send full resume with expected salary and reference no. quoted to Haven of Hope Christian Service, Staff Engagement Department, 7 Haven of Hope Road, Tseung Kwan O, New Territories or via email by clicking \"Apply Now\", or via Whatsapp no. 6507 8148 (with reference no. quoted at the caption) on or before 5 February 2022. Only short-listed candidates will be notified.\nEnquiry: 2703 3227 (Phone); 6507 8148 (Whatsapp).\nFor details about our organization, please visit www.hohcs.org.hk.\nProspective employees are requested to undergo/submit Sexual Conviction Record Check for work relating to children or mentally incapacitated persons before employment. Data collected will be used for recruitment purpose only.\nThis advertisement should not be reproduced, in whole or in part, to other recruitment websites without our prior written permission.", "employment_types": ["Full Time", "Permanent"], "selling_points": [], "locations": ["Tseung Kwan O"], "categories": ["Information Technology (IT)", "Application Specialist - Software", "IT Project Management / Team Lead", "IT Management"], "post_time": "2022-01-17T04:27:45Z", "salary": {"currency": null, "max": null, "min": null, "period": "monthly", "term": null}, "salary_visible": false, "title_keywords": ["executive", "manager"], "responsibilities": ["collaborate with", "service contracts", "it infrastructure", "infrastructure", "quality", "sem", "it procurement", "plans", "report"], "requirements": {"degrees": ["degree or above"], "majors": ["information technology"], "languages": ["cantonese", "english"], "language_level": ["good"], "hard_skills": ["hope", "linux", "no", "infrastructure support", "vmware", "web", "maintenance", "mobile", "whatsapp", "vpn", "server", "problem-solving skills", "wan", "windows server", "exchange"], "soft_skills": ["independent", "advanced", "sense of responsibility", "hands-on", "motivated", "problem-solving skills", "team player", "leadership"], "languages_combined": [{"language": "cantonese", "language_level": ["good"]}, {"language": "english", "language_level": ["good"]}]}, "experience_required": {"duration": ["at least 4 years", "minimum 10 years"], "field": ["managerial", "infrastructure", "it", "relevant experience", "security"]}}, {"job_id": "100003009052348", "location_code": "hk", "company": "Megaman Asia Ltd", "job_title": "IT Manager", "description": "Responsibilities:\n\nSupport local users of Office, warehouse, shop and users from other region\u00a0s\nMaintain systems and data in a desirable and operational status\nManage IT asset, budget and expenses\nAdministrate Microsoft servers, AD, MSSQL, ASP Web, Microsoft Windows, Office 365, VMware, Veeam, Firewall, VPN, antivirus and some other applications\nSupport system implementation of SAP\nRequirements:\n\n\nHigher diploma or above in IT, Computer Science or related disciplines\nWork independently or with supporting vendors\n5 \u2013 8 years\u00a0of working experience in network/server administration\nKnowledgeable in HR, ERP, WMS & POS\nFlexible to adopt new technologies and knowledge\nSelf-motivated, organized, flexible with a can-do attitude\nGood communication, analytical, project management & problem solving skills;\nDetail-minded, committed to work and able to prioritize effectively\nConversant with spoken and written English, Cantonese and Mandarin\nApplicants with less experiences will be considered as Assistant IT Manager\nApplications without expected salary and insufficient information will not be processed\nAll applications applied through our system will be delivered directly to the advertiser and privacy of personal data of the applicant will be ensured with security.\n\n\u6709\u610f\u7533\u8acb\u8005\u8acb \u6309 APPLY NOW\u7533\u8acb", "employment_types": ["Full Time"], "selling_points": [], "locations": ["Kwun Tong"], "categories": ["Information Technology (IT)", "IT Project Management / Team Lead", "IT Management", "Network & System"], "post_time": "2022-01-17T02:49:20Z", "salary": {"currency": null, "max": null, "min": null, "period": "monthly", "term": null}, "salary_visible": false, "title_keywords": ["it manager"], "responsibilities": ["data", "expenses", "budget", "systems", "implementation", "maintain"], "requirements": {"degrees": ["higher diploma or above"], "majors": ["related disciplines", "it", "computer science"], "languages": ["cantonese", "english", "mandarin"], "language_level": [], "hard_skills": ["pos", "server administration", "erp", "project management", "problem solving skills"], "soft_skills": ["flexible", "organized", "work independently", "self-motivated", "detail-minded", "able to prioritize", "can-do attitude", "communication", "project management", "committed", "problem solving skills"], "languages_combined": [{"language": "cantonese", "language_level": []}, {"language": "english", "language_level": []}, {"language": "mandarin", "language_level": []}]}, "experience_required": {"duration": ["8 years"], "field": ["it", "server administration"]}}, {"job_id": "100003009051892", "location_code": "hk", "company": "Automated Systems (HK) Ltd", "job_title": "Assistant Project Manager / Project Manager (Software development)", "description": "Job Type:\u00a0Full-Time\n\nReports to:\u00a0Director IT, Enterprise Software\n\n\n\nJob duties:\n\nEnsure all IT projects are delivered on-time and within scope\nMeet with stakeholders to gather and clarify business requirements of each project\nAnalyze structure of a business to determine how it operates and determine its objectives\nTransform business requirements to user stories for software development\nAssist to define the project scope and objectives, to ensure technical feasibility and perform risk management\nDevelop a detailed project plan to monitor and track progress\nCreate and maintain comprehensive project documentation\nManage stakeholders\u2019 expectation with on-going communication\nManage in-house/offshore/3rd party software development team to deliver software solution\nDraft test cases and perform test on UAT\nManage change requests of systems\nPerform training to end-users and draft user manual\nProvide on-going support to end-users and troubleshoot issues via ticketing system, emails and phone calls when necessary\n\nQualifications:\n\nDegree holder in Information Technology, Computer Science, Business Administrations or Commerce;\nAt least 5-8 years\u2019 relevant experience in IT / project / service management\nExperience in Agile methodologies and DevOps practices within Technology teams (e.g. Scrum, Kanban)\nExtensive Knowledge of Business Process and back end Automation initiatives\nExperience of Incident and Problem Management\nDemonstrate an ability to work on an international team but can also do so independently on a wide variety of projects across a series of workstreams, building stakeholder buy-in around plans, commitments and change\nExperience as a IT Project Manager with the delivery of major Transformational programs or migration project is a plus\nExperience in project management for corporate or enterprise is a plus\nUnderstanding of basic API and Database knowledge is a plus\nGood command of communication skill in both Cantonese and English", "employment_types": ["Full Time", "Contract"], "selling_points": ["Project Management", "Software development life cycle", "There are opportunities for your career promotion"], "locations": ["Shatin Area"], "categories": ["Information Technology (IT)", "Application Specialist - Software", "IT Project Management / Team Lead", "Software Development"], "post_time": "2022-01-17T01:27:14Z", "salary": {"currency": null, "max": null, "min": null, "period": "monthly", "term": null}, "salary_visible": false, "title_keywords": ["assistant project manager", "project manager"], "responsibilities": ["software", "communication", "maintain", "business process", "troubleshoot", "database", "plans", "phone calls", "project documentation", "uat", "monitor", "teams", "develop", "reports", "migration", "management", "systems", "project plan", "project management"], "requirements": {"degrees": ["degree holder"], "majors": ["business", "computer science", "information technology"], "languages": ["cantonese", "english"], "language_level": ["good command"], "hard_skills": ["plus", "basic", "agile", "devops", "project management", "documentation"], "soft_skills": ["independently", "agile", "communication skill", "communication", "project management", "comprehensive", "troubleshoot", "extensive", "detailed"], "languages_combined": [{"language": "cantonese", "language_level": ["good command"]}, {"language": "english", "language_level": ["good command"]}]}, "experience_required": {"duration": ["at least 5-8 years"], "field": ["management", "devops", "project management", "it", "relevant experience"]}}, {"job_id": "100003009055344", "location_code": "hk", "company": "Optimum Solutions (Hong Kong) Limited", "job_title": "Project Manager", "description": "\u00a0Project Manager (Application Projects)\n\nHK$65K to HK$75K per month\n\n\n\nThe Ideal Candidate:\nDegree or above\u00a0 in Computer Science / Information Technology\nMinimum 8 years of\u00a0 experience in project management\nSolid experience in vendor management\nVery experienced in\u00a0 handling different types of application projects\nGood knowledge of\u00a0 project management methodology\nGood knowledge of budgeting and resource allocation procedures\nGood influencing skills managing to internal and external stakeholder\nGood communication and interpersonal skills\nFluent in written and spoken English\n\nKey Duties:\n\nPlanning overall programs and monitoring the progress\nManaging financials of programs\nManaging risks and issues and taking corrective measurements\nCoordinating different projects and their interdependencies\nResolving conflicts between projects\nNegotiating changes in plans\nManaging and utilizing resources across different projects\nExperience in Data Warehouse projects,\u00a0 Hotel Management System (Opera), application\u00a0 and software experience is highly preferred\u00a0\nValue-added to Project Management Office (PMO)\u00a0with continuous improvement\nEnsure delivery of different programs effectively\u00a0", "employment_types": ["Full Time", "Permanent", "Contract"], "selling_points": ["Min. 10 years experience in project management", "Well experienced in application projects", "Project exp for F& B, Retail highly preferred"], "locations": ["Others"], "categories": ["Information Technology (IT)", "Application Specialist - Software", "IT Project Management / Team Lead", "Software Development"], "post_time": "2022-01-18T02:14:44Z", "salary": {"currency": null, "max": null, "min": null, "period": "monthly", "term": null}, "salary_visible": false, "title_keywords": ["project manager"], "responsibilities": ["management", "software", "data", "budgeting", "monitoring", "procedures", "communication", "project management", "plans", "planning"], "requirements": {"degrees": ["degree or above"], "majors": ["computer science", "information technology"], "languages": ["english"], "language_level": ["fluent"], "hard_skills": ["data warehouse", "project management", "vendor"], "soft_skills": ["project management", "communication and interpersonal skills", "ideal"], "languages_combined": [{"language": "english", "language_level": ["fluent"]}]}, "experience_required": {"duration": ["minimum 8 years"], "field": ["project management", "management", "hotel management"]}}, {"job_id": "100003009054283", "location_code": "hk", "company": "FUJIFILM Data Management Solutions Asia Limited", "job_title": "Project Manager / Assistant Project Manager", "description": "The Person\n\nDeliver quality business outcomes, ensuring that projects are delivered within given timeframes, budgets, meet user requirements and appropriately handed over to Operations\nEstablish and manage project operations and governance structures in accordance with DMS Project Framework and guidelines\nEffectively control and manage Changes, Issues and Risks associated with projects\nControl project design and planning activities associated with projects\nDefine, source & manage necessary project resources\nDevelop and control project schedules to ensure that necessary activities are completed according to the project plan\nPrepare and report on project budgets, monitoring and tracking project financials and the realization of defined project benefits\nManage customer expectations to ensure customer satisfaction through the application of stakeholder management disciplines\nThe Job\nDegree holder in Information System, Information Technology or other related discipline\nHolder of PMP or PRINCE2 is preferred\nPreferable with ITIL V3.0 qualification and holder of Six Sigma Green Belt is an advantage\n5-7 years\u2019 working experience in customer servicing industries with 2-4 years\u2019 or above relevant project management experience\nGood knowledge on MS Office, MS Project and MS Visio\nExcellent analytical skill and customer/user management skill is required\nExcellent interpersonal and communication skill\nSelf-motivated character with \u201ccan-do\u201d attitude and proven multi-tasking ability to meet critical deadlines\nWell organized, result-oriented and having good problem solving skill with detail analytical mind\nGood command of both written and spoken English and Chinese\nCandidate with less experience will be considered as Assistant Project Manager / Project Executive \u00a0\nWe are an equal opportunity employer, offer\u00a05-day week (from 9am to 5:30pm), attractive incentive, shuttle bus service, training opportunity and medical benefits. Interested applicants shall submit a full resume indicating current and expected salary with soonest availability.\n\nAll information provided will be treated in strict confidence and used for recruitment purposes only. Applicants not hearing from us within six weeks may consider their applications unsuccessful. All data of unsuccessful applications will be destroyed after six months.\n\n", "employment_types": ["Full Time", "Permanent"], "selling_points": ["With 5-7 years\u2019 customer servicing experience", "Monitor the projects' progress and outcomes", "5-day work, 9:00am - 5:30pm"], "locations": ["Chai Wan"], "categories": ["Information Technology (IT)", "IT Project Management / Team Lead", "Support", "IT Management"], "post_time": "2022-01-17T09:02:30Z", "salary": {"currency": null, "max": null, "min": null, "period": "monthly", "term": null}, "salary_visible": false, "title_keywords": ["project manager", "assistant project manager"], "responsibilities": [], "requirements": {"degrees": [], "majors": [], "languages": [], "language_level": [], "hard_skills": [], "soft_skills": [], "languages_combined": []}, "experience_required": {"duration": [], "field": []}}, {"job_id": "100003009052978", "location_code": "hk", "company": "JFE Consulting Limited", "job_title": "Project Manager - IT", "description": "Our client, one of the leading IT companies, is looking for high calibres to join their winning team:-\n\nResponsiblities:\n\n\n\nAdvanced computer skills and in-depth knowledge of different operating systems, network administration and service desk administration\nProject management and leadership skills for managing projects and the teams involved with themStrong written and verbal communication skills to coordinate with team members and management and explain technical issues\nAnalytical and problem-solving skills to handle any issues that occur during project completion\n\nRequirements:\n\nBachelor Degree in Information Technology or equivalent.\n10 years of IT experience or above with 6 years or above experience of project management in web application implementation projects\nUnderstanding of MSP ticketing and Alert Management Systems.\nThorough understanding of project management fundamentals.\nUnderstanding of software development life cycle\nOutstanding leadership, organizational, and time management skills.\nOutstanding verbal and written communication skills.\nStrong people skills.", "employment_types": ["Full Time", "Permanent"], "selling_points": ["Project Management", "IT industry", "10+ years of experience, attractive salary"], "locations": ["Quarry Bay"], "categories": ["Information Technology (IT)", "IT Project Management / Team Lead", "IT Management", "Product Management / Business Analyst"], "post_time": "2022-01-17T04:48:24Z", "salary": {"currency": null, "max": null, "min": null, "period": "monthly", "term": null}, "salary_visible": false, "title_keywords": ["project manager"], "responsibilities": ["network administration", "management", "teams", "coordinate with", "communication", "project management", "operating systems", "administration"], "requirements": {"degrees": ["degree", "bachelor"], "majors": ["information technology"], "languages": [], "language_level": [], "hard_skills": ["project management", "web"], "soft_skills": ["communication skills", "time management skills", "organizational", "project management", "thorough", "leadership"], "languages_combined": []}, "experience_required": {"duration": ["6 years", "10 years"], "field": ["project management", "it experience"]}}, {"job_id": "100003009052321", "location_code": "hk", "company": "Hong Kong Aircraft Engineering Co Ltd", "job_title": "Assistant IT Manager, Infrastructure", "description": "Scope of Duties:\u00a0\n\nEnsure IT Infrastructure and systems availability and responsiveness in accordance with agreed service levels and schedules\nEnsure appropriate and dedicated focus on high severity incident management\nFacilitate the development and implementation of effective and robust disaster recovery plans for HAECO\nFacilitate the development and implementation of business continuity plans for IT\nEnsure effective management of IT Infrastructure Facilities and Data Centres\nEnsure effective management of Cloud based IT services\nProactively drive service delivery improvements\nFormulate cost effective solutions to resolve business issues in accordance with IT policy and strategy\nOversee the end-to-end solution delivery to ensure on time and within budget\nEnsure post-implementation maintenance & support is effective and efficient\nManage vendors in IT project delivery, systems development and support\nBuild and lead a team with the core set of technical skills and business domain knowledge\nDevelop and coach potential staff for performance excellence\n\nRequirements:\u00a0\n\nDegree holder in IT, Computing, Engineering or related disciplines\nOver 8 years IT experience, at least 5 years of IT Infrastructure experience, preferably with team leadership experience\nProfessional certifications (Microsoft \u2013 MCSE (Server specific), VMware \u2013 VCP, ITIL Foundation, PMP or equivalent) will be an advantage.\nProven experience in managing a team of technology professionals (including in-house, external, off-site resources) to run strategic IT projects and support IT systems\nPossess professional competency in at least one technical specialization, with a broad understanding of other current and emerging technologies\nHave experience of leading a team, and be able to demonstrate an effective coaching and mentoring style\nHave experience of developing solutions and making decisions for a team with only minimal management guidance and supervision\nAble to upkeep high standard of outputs from the team\nAble to listen and articulate ideas verbally, and in the written\n\nHow to Apply:\n\nPlease send your resume with expected salary, quoting the employer's reference no., to: Human Resources Department - Talent & Partnership Team, Hong Kong Aircraft Engineering Company Limited, 80 South Perimeter Road, Hong Kong International Airport, Lantau, Hong Kong OR submit your application via\u00a0https://careers.haeco.com/hkg/job-openings/\n\nCandidates not contacted 4-6 weeks after submission of applications and/or interviews may consider their application unsuccessful.", "employment_types": ["Full Time", "Permanent"], "selling_points": ["IT infrastructure development and support", "Degree holder in IT, Computing, Engineering", "8 years IT experience,5 years of IT Infrastructure"], "locations": ["Airport Area"], "categories": ["Information Technology (IT)", "IT Project Management / Team Lead", "IT Management", "Others"], "post_time": "2022-01-17T02:45:26Z", "salary": {"currency": null, "max": null, "min": null, "period": "monthly", "term": null}, "salary_visible": false, "title_keywords": ["it manager", "assistant"], "responsibilities": ["service delivery", "business continuity", "management", "cost", "it infrastructure", "maintenance", "data", "schedules", "systems", "budget", "implementation", "develop", "lead a team", "plans"], "requirements": {"degrees": ["degree holder"], "majors": ["related disciplines", "it", "engineering"], "languages": [], "language_level": [], "hard_skills": ["itil", "mcse", "no", "vmware", "aircraft", "server", "pmp"], "soft_skills": ["articulate", "leadership"], "languages_combined": []}, "experience_required": {"duration": ["at least 5 years", "8 years"], "field": ["management", "infrastructure", "developing", "it experience", "it", "managing a team", "team"]}}, {"job_id": "100003009051054", "location_code": "hk", "company": "The Wharf Group", "job_title": "HRIS Project Manager", "description": "Responsibilities:\n\nOversee the project progress and planning on digitalization related projects across the Group\nCraft out the implementation plan on various stages and follow through the implementation status with team members according to agreed timeline, quality and budget\nCommercial terms review, budget control and project P&L management\nIdentify and analyze business processes and requirements, and manage all stages of development including system design, technical specifications, system integration, testing and deployment of applications, and maintenance\nEvaluate technical architectures and solutions, evaluate potential risks and issues with recommendations, and report progress to stakeholders and management\nEvaluate proof-of-concept and new technology/solutions to integrate with existing systems / future systems \u00a0\nProvide training and briefing sessions to users on deployed systems and applications\nPerform vendor and contract management and review vendors\u2019 system documentation\nIT liaison and advisory on system security on various applications\n\nRequirements:\n\nDegree holders in Information Technology, Computer Science, Engineering or related disciplines; preferably with PMP or equivalent qualifications\u00a0\nAt least 12 years\u2019 relevant experience in IT system design, development and management of core projects; including not less than 3 years project management experience on tier one human resources systems.\nCompetence in managing the whole SDLC process including gathering of requirements, analysis, development, UAT, production release and maintenance; plus\u00a0good knowledge of MySQL, MS SQL, VB.Net, Crystal Report, Java, ASP. Net, HTML and PHP\nExperience in SAP SuccessFactors is highly preferred\nExperience with Cloud Computing platform, Business Intelligence System, Data Analytics would be an added advantage\nStrong ability and proven track record in designing and implementing pragmatic solutions under complex business requirements\nMature, detail-minded with strong communication and problem solving skills\nGood command of spoken and written English and Chinese (Cantonese and Putonghua)\n\nWe work 5 days per week.\n\nInterested parties, please click \"APPLY NOW\" and attach with your application letter and full resume.\n\nFor further information of the Wharf Group, please visit our website: www.wharfholdings.com\u00a0", "employment_types": ["Full Time", "Permanent"], "selling_points": [], "locations": ["Tsim Sha Tsui"], "categories": ["Information Technology (IT)", "IT Project Management / Team Lead", "IT Management", "Technical / Functional Consulting"], "post_time": "2022-01-15T19:11:48Z", "salary": {"currency": null, "max": null, "min": null, "period": null, "term": null}, "salary_visible": false, "title_keywords": ["hris project manager"], "responsibilities": ["provide training", "budget", "quality", "plan", "budget control", "system documentation", "implementation", "project progress", "p&l", "testing", "report", "management", "review", "specifications", "maintenance", "systems", "contract management", "evaluate", "system design", "system security", "planning"], "requirements": {"degrees": ["degree"], "majors": ["related disciplines", "engineering", "computer science", "information technology"], "languages": ["cantonese", "putonghua", "english", "chinese"], "language_level": ["good command"], "hard_skills": ["plus", "java", "maintenance", "php", "sap", "data analytics", "analysis", "html", "project management", "sdlc", "system design", "problem solving skills", "pmp", "business intelligence", "ms sql"], "soft_skills": ["detail-minded", "mature", "communication", "project management", "problem solving skills"], "languages_combined": [{"language": "cantonese", "language_level": ["good command"]}, {"language": "putonghua", "language_level": ["good command"]}, {"language": "english", "language_level": ["good command"]}, {"language": "chinese", "language_level": ["good command"]}]}, "experience_required": {"duration": ["3 years", "at least 12 years"], "field": ["management", "development", "project management", "business", "relevant experience", "it system design", "human resources systems"]}}, {"job_id": "100003009052776", "location_code": "hk", "company": "Hong Kong Sports Institute Ltd", "job_title": "INFORMATION TECHNOLOGY MANAGER", "description": "JOB DESCRIPTION\nReporting to the Director, Corporate Services, the Information Technology Manager is responsible for leading the planning and implementation of best-in-class Information Technology activities to support the HKSI\u2019s elite sport and corporate operation needs. Leading the IT Department team, the IT Manger is responsible for the following:\nWorking collaboratively across the organisation to lead the identification, implementation, monitoring and maintenance of all the HKSI\u2019s information and communications technology systems within both short and long term planning frameworks;\nTo regularly review and recommend the most up-to-date application, content and computing platforms to enhance the HKSI\u2019s elite sport and corporate operations data processing and analytic needs;\nTo lead the evaluation, and guide strategic provisioning of applicable technologies to ensure elite sport and corporate systems are interoperable and align with both elite sport and corporate administrative data needs;\nTo direct the future oriented development, implementation monitoring and maintenance\u00a0 of a highly secure, efficient and cost-effective IT infrastructure including hardware, software and storage systems;\nTo ensure a dynamic comprehensive risk-management strategy is in place including disaster recovery plans, and security systems to reduce vulnerabilities such as data leakages etc;\nTo regularly review, enhance, and/or introduce as necessary all IT related policies and procedures and to monitor compliance;\nTo ensure timely and effective technical support, help desk services to all user departments; and\nPerform any other appropriate duties as assigned by supervisor.\n\u00a0THE REQUIREMENTS\n\nA university degree in Information Technology, Computer Science or a relevant disciplines; A Post graduate degree is preferred;\nA minimum of 10 years\u2019 Management experience in a similar role;\nExcellent command of both written and spoken English and Chinese. Ability to speak Putonghua is a definite advantage;\nStrong communication and presentation skills.\u00a0 Excellent interpersonal skill in dealing with all levels of staff across the organisation;\nHighly motivated individual, who places emphasis on teamwork and has excellent strategic thinking and analytical skills.\nAPPLICATIONS\nPlease send the completed\u00a0application form with indication of your current and expected salary to\u00a0The Human Resources Manager, Hong Kong Sports Institute Ltd, 25 Yuen Wo Road, Sha Tin, New Territories\u00a0or email:\u00a0hrdept @ hksi.org.hk\u00a0on or before 30 January 2022. Please quote reference no.\u00a0JD-20220117-ITM\u00a0in the application.\nAppointment will be on a fixed term contract. General information is available at the website http://www.hksi.org.hk.\nApplicants who are not invited for interview within six months may consider their applications unsuccessful.\nAll applications will be treated in the strictest confidence. Data collected will be used for recruitment and other employment-related purposes only.\nTHE HKSI IS AN EQUAL OPPORTUNITIES EMPLOYER", "employment_types": ["Full Time"], "selling_points": [], "locations": ["Shatin Area"], "categories": ["Information Technology (IT)", "IT Project Management / Team Lead", "IT Management", "Others"], "post_time": "2022-01-17T04:01:47Z", "salary": {"currency": null, "max": null, "min": null, "period": "monthly", "term": null}, "salary_visible": false, "title_keywords": ["technology manager"], "responsibilities": ["software", "data", "operations", "evaluation", "plans", "it infrastructure", "compliance", "monitor", "implementation", "reporting", "cost", "management", "monitoring", "review", "procedures", "maintenance", "technical support", "policies", "systems", "data processing", "hardware", "planning"], "requirements": {"degrees": ["university degree", "degree"], "majors": ["computer science", "information technology"], "languages": ["putonghua", "english", "chinese"], "language_level": ["advantage", "excellent"], "hard_skills": ["no", "hksi", "analytical skills"], "soft_skills": ["confidence", "strategic thinking", "teamwork", "interpersonal skill", "communication", "motivated individual", "presentation skills", "analytical skills", "organisation"], "languages_combined": [{"language": "putonghua", "language_level": ["advantage"]}, {"language": "english", "language_level": ["excellent"]}, {"language": "chinese", "language_level": ["excellent"]}]}, "experience_required": {"duration": ["minimum of 10 years"], "field": ["management"]}}, {"job_id": "100003009051930", "location_code": "hk", "company": "Octopus Holdings Limited", "job_title": "Assistant Technical Project Manager", "description": "Job Responsibilities:\n\nParticipate in full Software Development Life Cycle (SDLC) in performing Requirement Gathering & Analysis, Process & System Design, Development, Testing, Release Management and Maintenance of automated fare collection (AFC) systems\nOver 70% involvement in system design and development\nCoordinate with project team and external customers for the implementation of projects and system enhancements\nEnsure on-time and quality delivery\nFulfill subsequent system changes and post-launch support duties\nFulfill system maintenance and support duties to clients\nDeliver project documents\nIdentify and manage project issues and dependencies and manage change holistically\n\nRequirements:\n\nBachelor Degree in Computer Science, Information Technology, MIS or equivalent\nMinimum 6 years of experience in IT industry with focus on information systems design and development\nHands-on experience in Java Development\nKnowledgeable in web application development\nKnowledgeable in Linux environment and RDBMS such as Oracle and SQL Server\nProficient in written and spoken English and Chinese with strong communication skills\nStrong collaborative and interpersonal skills\nDirect client facing experience is preferred\nProject experience with external clients is preferred\nA good team player that is self-motivated, detail-oriented and able to work under pressure\nOrganized and focused on planning and preparation\nCandidate with less experience will be considered as Senior System Engineer\n\nWe offer successful candidate an attractive remuneration package and excellent career prospects. Interested parties please send your resume, present and expected salary, contact details and quoting the reference number by clicking \"Apply Now\"Visit our web site:\u00a0http://www.octopus.com.hk/\n\nThe personal data collected will be used for recruitment purposes only. If you are not contacted by us within six weeks, you may consider your application unsuccessful. Personal data with an unsuccessful applicant will be destroyed 12 months after rejection of the application. During this retention period, you have the right to request for correction or destruction of your personal data at any time. Any request for the correction or destruction of personal data should be addressed in writing to our Human Resources & Administration Department.\n\nOctopus is an equal opportunity employer and all employment decisions and Human Resources policies are administered; especially those relating to recruitment & selection, compensation & benefits, promotion & transfer, training & development and termination & redundancy; without discrimination on the basis of age, race, colour, religion, sex, national origin, marital status, pregnancy, physical and mental disability and family status but on genuine occupational qualification, job performance, employees\u2019 ability and internal/ external relativities.", "employment_types": ["Full Time", "Permanent"], "selling_points": ["Focus on system design and development", "Coordinate with project team and external customer", "Cand with less experience will also be considered"], "locations": ["Kowloon Bay"], "categories": ["Information Technology (IT)", "IT Project Management / Team Lead", "Software Development"], "post_time": "2022-01-17T01:32:43Z", "salary": {"currency": null, "max": null, "min": null, "period": null, "term": null}, "salary_visible": false, "title_keywords": ["technical project manager", "assistant"], "responsibilities": ["management", "software", "maintenance", "analysis", "systems", "coordinate with", "quality", "testing", "implementation of projects", "project documents", "system design", "system changes"], "requirements": {"degrees": ["degree", "bachelor"], "majors": ["computer science", "information technology"], "languages": ["english", "chinese"], "language_level": ["proficient"], "hard_skills": ["linux", "java", "web application development", "sql", "server", "focus", "oracle"], "soft_skills": ["communication skills", "good team player", "self-motivated", "organized", "focused", "collaborative", "detail-oriented", "hands-on", "interpersonal skills", "focus", "work under pressure"], "languages_combined": [{"language": "english", "language_level": ["proficient"]}, {"language": "chinese", "language_level": ["proficient"]}]}, "experience_required": {"duration": ["minimum 6 years"], "field": ["development", "it", "design"]}}, {"job_id": "100003009050043", "location_code": "hk", "company": "World Vision Hong Kong", "job_title": "IT Manager", "description": "Job Responsibilities:\u00a0\n\n\nLead the IT Department to provide effective information technology services for the whole organization\nProvide & develop IT strategy planning, business plan, policies & guidelines, budget monitoring and procurement recommendation\n\u00a0Oversee the infrastructure operations in supporting network and technical support services\nOversee the software development life cycle for in-house applications and corporate website\nPlan & implement IT security controls to ensure the confidentiality, integrity and availability of the information assets\nSupervise external & internal IT security compliance activities to ensure the compliance standard\n\n\u00a0Job Requirements:\n\n\nBachelor degree or above in Information Technology or related disciplines\nAt least 10 years working experience in project management, programming, system analysis and design\n4 years of experience in managerial role with supervisory duties\nExperience in MS Azure, MS 365 including Power Tools, Windows Servers, SSRS, SQL server, Dynamics 365, .net or .net Core development\nExperience in on-cloud and on-premise infrastructure implementation\nExperience in digital marketing implementation and maintaining PCI-DSS compliance standard will be an added advantage\nGood prioritization skills and flexible to adapt plans with constraints\nA strong leader and a good team player\nStrong passion to serve the poor, especially the children\nOn renewable contract term for the initial two years.\u00a0 Candidates with satisfactory performance may convert to permanent employment afterwards based on business needs.\n\nPlease apply online with your full resume, listing church affiliations (if any), current and expected salary.\n\n\nYou may also send your application to:\nHead of HR & Administration, World Vision Hong Kong, 2/F Mayfair Centre, 4 Anchor Street, Tai Kok Tsui, Kowloon\n\nTo find out more about our job opportunities, please visit our website\u00a0https://www.worldvision.org.hk/get-involved/vacancies\n\nWorld Vision Hong Kong is committed to safeguarding our children and adult beneficiaries from any risk of abuse, exploitation and harm. Candidates selected for interviews will be requested a self-declaration of previous records for any crimes against children or sexual offences, and may be requested to undergo Sexual Conviction Record Check by the HK Police.\n\nPersonal Data provided by job applicants will be used for recruitment purposes only and will be treated in accordance with the organization's personal data privacy policy. Applicants who are not invited for interviews within six weeks may consider their applications unsuccessful and the personal data collected will be destroyed within 12 months.", "employment_types": ["Full Time"], "selling_points": [], "locations": ["Mong Kok"], "categories": ["Information Technology (IT)", "IT Project Management / Team Lead", "IT Management", "Network & System"], "post_time": "2022-01-14T09:41:03Z", "salary": {"currency": null, "max": null, "min": null, "period": "monthly", "term": null}, "salary_visible": false, "title_keywords": ["it manager"], "responsibilities": ["software", "guidelines", "policies", "technical support", "budget", "monitoring", "website", "compliance", "develop", "infrastructure operations", "plan", "business plan", "planning"], "requirements": {"degrees": ["degree or above", "bachelor"], "majors": ["related disciplines", "information technology"], "languages": [], "language_level": [], "hard_skills": ["azure", "servers", "analysis", "sql", "project management", "programming", "server"], "soft_skills": ["flexible", "project management", "good team player", "committed"], "languages_combined": []}, "experience_required": {"duration": ["at least 10 years", "4 years"], "field": ["managerial", "supervisory", "infrastructure", "compliance", "design", "sql", "project management", "digital marketing", "programming"]}}, {"job_id": "100003009055824", "location_code": "hk", "company": "Randstad Hong Kong Limited", "job_title": "Project Manager/ Assistant Project Manager (Insurance)", "description": "about the company.\n\nOur client is a MNC insurance company based in Hong Kong, who is currently looking for an Project Manager/Assistant to cater with the team's expansion and different projects\n\nabout the job.\n\nYou will be focusing mainly in tasks below:\n\nResponsible for web application & e-Commerce platform implementation and enhancement to drive the sales\nResponsible for overall project management and resource planning\nDevelop business process flow and performance review to improve customer operational efficiency\nEvaluate current business model and operation workflow\nOrganise and conduct UAT\nskills & experiences required.\nDegree Holder in Business, Computer Science, IT or equivalent\nMin 3 years of related project management experience, with web application exposure\nPrevious experience in insurance industry is preferred, but not a must\nA good team player with good analytical and interpersonal skills, able to work under pressure and independently\nOpen-minded, attention to detail and self-disciplined\nExcellent communication skill with good command of written and spoken Cantonese and English\n\nInterested parties, please click \"Apply Now\" or contact Cheryl Lau at cheryl.lau@randstad.com.hk", "employment_types": ["Full Time", "Permanent"], "selling_points": ["MNC insurance company based in Hong Kong", "Web application & e-Commerce platform", "Young and energetic team environment"], "locations": ["Not Specified"], "categories": ["Information Technology (IT)", "IT Project Management / Team Lead", "Marketing / Public Relations", "Digital Marketing", "E-commerce", "Product Management / Business Analyst"], "post_time": "2022-01-18T02:59:17Z", "salary": {"currency": "HKD", "max": 44999, "min": 30000, "period": "monthly", "term": null}, "salary_visible": true, "title_keywords": ["project manager", "assistant project manager"], "responsibilities": ["uat", "work under pressure", "review", "implementation", "develop", "evaluate", "project management", "communication", "business process", "e-commerce platform", "insurance", "planning"], "requirements": {"degrees": ["degree holder"], "majors": ["business", "it", "computer science"], "languages": ["cantonese", "english"], "language_level": ["excellent", "good command"], "hard_skills": ["project management", "web", "e-commerce"], "soft_skills": ["good team player", "independently", "responsible", "open-minded", "communication skill", "project management", "interpersonal skills", "attention to detail", "work under pressure"], "languages_combined": [{"language": "cantonese", "language_level": ["excellent", "good command"]}, {"language": "english", "language_level": ["excellent", "good command"]}]}, "experience_required": {"duration": ["min 3 years"], "field": ["related", "project management", "insurance industry"]}}, {"job_id": "100003009051870", "location_code": "hk", "company": "LAWSGROUP", "job_title": "Assistant IT Manager", "description": "Job Description:\nProvide application support & troubleshooting including system / server configurations / data patching\nWork with overseas local IT team to provide user training /end user support\nPerform system testing & daily routine job\nHandle overseas IT Projects\nPerform system support to overseas factory\nPerform ad hoc project as assigned by immediate supervisor\nJob Requirements:\nDegree or above in Computer Science, Information Technology or related discipline\nMinimum 5 years relevant experience with proven project implement/ system support/ helpdesk experience\nHands on experience in Oracle / MSSQL / Informix DBMS administration, AD/ Windows server / VMWare / VSAN administration\nSolid programming experience in SQL\nKnowledge in RPA / QlikView is an advantage\nExcellent problem solving, independently, able to work under pressure\nGood interpersonal communication and presentation skills\nGood command in both spoken and written English and Chinese\nWilling to travel and support different overseas projects and travel among factories is required\nWe\u00a0offer\u00a0attractive remuneration package to the right candidate. Interested parties please click the \"APPLY NOW\" button below and send your application together with a detailed resume including current & expected salary and availability to Human Resources Department.\nCompany website:\u00a0https://www.lawsgroup.com\n(Data collected will be treated in strict confidence and used for recruitment purpose only)", "employment_types": ["Full Time", "Permanent"], "selling_points": ["Minimum 5 years exprience in system support", "Degree or above in Computer Science", "Provide application support & troubleshooting"], "locations": ["Lai Chi Kok"], "categories": ["Information Technology (IT)", "IT Project Management / Team Lead", "Product Management / Business Analyst", "Others"], "post_time": "2022-01-17T01:25:48Z", "salary": {"currency": null, "max": null, "min": null, "period": "monthly", "term": null}, "salary_visible": false, "title_keywords": ["it manager", "assistant"], "responsibilities": ["testing", "ad hoc", "troubleshooting", "data"], "requirements": {"degrees": ["degree or above"], "majors": ["computer science", "information technology"], "languages": ["english", "chinese"], "language_level": ["good command"], "hard_skills": ["qlikview", "informix", "vmware", "vsan", "dbms", "sql", "rpa", "problem solving", "programming", "mssql", "windows server", "oracle"], "soft_skills": ["independently", "problem solving", "communication", "presentation skills", "hands on", "interpersonal", "work under pressure"], "languages_combined": [{"language": "english", "language_level": ["good command"]}, {"language": "chinese", "language_level": ["good command"]}]}, "experience_required": {"duration": ["minimum 5 years"], "field": ["project implement", "system support", "helpdesk experience", "sql", "relevant experience", "programming", "administration"]}}, {"job_id": "100003009053783", "location_code": "hk", "company": "Hysan Development Co Ltd", "job_title": "Project Manager, E-Commerce & Digital", "description": "Job Purpose\nTo manage and support business technology related projects and operations on digital solutions such as mobile APP, E-commerce, CRM, Carpark system, Digital Signage system and marketing technology solutions.\n\nKey Responsibilities\n\n\nLead the requirement studies, technical analysis, design and development of digital solutions independently\nDevelop a holistic understanding of project interdependencies in order to manage project risks and stakeholders' expectations\u00a0\nMaintain and manage technical partners to handle and follow up on project items and daily operations related to digital platforms\nHave solid knowledge and experiences on digital transformation to drive the movement from conceptual ideas to marketable products\nExcellent communication and coordination skills to liaise project stakeholders and project teams to achieve project goals\n\nSkills, Qualifications and Experience Requirements\n\nDegree holder of Information Systems, Information Technology, Computer Science, Business Management or related discipline\nMinimum 8 years of experience in digital transformation, marketing technology and project management roles\u00a0\nCertificates in PMP or PRINCE2 or Scrum Master is required\nExperienced in managing end-to-end project life cycles and leading projects involving multiple internal or external stakeholders\u00a0\nExperience in influencing change in ways of working/ collaboration within a cross-domain/ market or functional context\u00a0\nAble to work under pressure and meet deadlines\nExcellent communication, project management and organizational skills\n\n\n\nAn attractive remuneration package will be offered to the right candidate. Interested parties please press \"Apply now\".\n\nHysan is an equal opportunity employer.\u00a0 All information collected will be kept in strict confidence and used solely for recruitment related purposes within the Hysan Group Companies.\n\nYou may get to know more about us through www.hysan.com.hk", "employment_types": ["Full Time", "Permanent"], "selling_points": ["Manage and support BT projects and operations", "Degree holder with 8+ years relevant experience", "5-day work, 16-day AL, Dental, Double Pay + Bonus"], "locations": ["Causeway Bay"], "categories": ["Information Technology (IT)", "IT Project Management / Team Lead", "Software Development", "E-commerce", "Product Management / Business Analyst"], "post_time": "2022-01-17T07:30:50Z", "salary": {"currency": null, "max": null, "min": null, "period": "monthly", "term": null}, "salary_visible": false, "title_keywords": ["project manager"], "responsibilities": ["liaise", "management", "mobile app", "ideas", "operations", "analysis", "systems", "teams", "design", "develop", "communication", "project management", "daily operations", "maintain", "coordination", "work under pressure"], "requirements": {"degrees": ["master", "degree holder"], "majors": ["business", "computer science", "information technology"], "languages": [], "language_level": [], "hard_skills": ["business management", "e-commerce", "technical analysis", "mobile", "project management", "pmp"], "soft_skills": ["organizational skills", "independently", "coordination skills", "communication", "project management", "meet deadlines", "work under pressure"], "languages_combined": []}, "experience_required": {"duration": ["minimum 8 years"], "field": ["digital", "project management", "marketing"]}}, {"job_id": "100003009052324", "location_code": "hk", "company": "Capgemini Hong Kong Limited", "job_title": "Project Manager - Digital", "description": "Job description\n\nWe are looking for a creative and visionary Digital Project Manager to be part of our dynamic team. The incumbent will be accountable for the initial project feasibility study and end-to-end project execution. He / She will work closely with agencies, internal IT and business stakeholders on planning, management, execution and delivery of digital products/platforms.\n\nResponsibilities:\n\nDrive digital projects across multiple business units, as well as be part of the cross-functional team to achieve project goals\nDetermine the viability of new projects, identify the requirements, provide possible options/solutions to execute new ideas, and ensure a project is technically and operationally feasible as well as economically justifiable\nEstablish detailed and realistic project scopes after identifying and validating both business and technical parameters\nAssure quality in deliverables by closely managing project implementation, communicating efficiently with different parties, identifying project risks in advance, running comprehensive QA tests; maintaining a clear set of project and technical documentations\nTrack budget and provide project status reports regularly\nEnsure knowledge sharing on both project management and technical know-how between project teams (business unit and digital team)\n\nTogether with creativity, integrity and passion, our ideal staff should have:\n\nDegree in Computer Science, IT or Digital-related discipline is preferred\nMinimum of 8 years\u2019 solid experience in running digital projects, experience in website and mobile application is a must. Experience in Sitecore is a plus.\nKnowledge in retail digital solution is a plus\nExperiences in China digital products is a plus\nPMP\u00ae or PRINCE2\u00ae certification is required\nConfident in working closely with both technical and business team\nAbility to conduct technical feasibility study for new ideas and digital projects\nStrong in project management, vendor and stakeholder management\nSelf-motivated and capable to work with minimal supervision; ability to work under pressure\nDigital savvy. Passionate about the latest technology, data and problem solving\nA strong and confident communicator who can work independently and interact effectively with all levels of people\nLiteracy in English, Traditional and Simplified Chinese is mandatory. Fluent in English & Cantonese", "employment_types": ["Full Time", "Permanent", "Contract"], "selling_points": ["PMP or Prince 2", "Agile Methodology", "Program Management"], "locations": ["Others"], "categories": ["Information Technology (IT)", "IT Project Management / Team Lead"], "post_time": "2022-01-17T02:45:56Z", "salary": {"currency": null, "max": null, "min": null, "period": "monthly", "term": null}, "salary_visible": false, "title_keywords": ["project manager"], "responsibilities": ["management", "ideas", "maintaining", "data", "work under pressure", "budget", "quality", "implementation", "teams", "website", "project management", "reports", "planning"], "requirements": {"degrees": ["degree"], "majors": ["it", "computer science"], "languages": ["cantonese", "english", "chinese"], "language_level": ["fluent"], "hard_skills": ["plus", "vendor", "problem solving", "project management", "mobile", "dynamic", "pmp", "documentations"], "soft_skills": ["confident", "self-motivated", "work independently", "ideal", "capable", "work under pressure", "integrity", "accountable", "clear", "project management", "problem solving", "dynamic", "comprehensive", "visionary", "communicator", "creative", "passionate about", "detailed"], "languages_combined": [{"language": "cantonese", "language_level": ["fluent"]}, {"language": "english", "language_level": ["fluent"]}, {"language": "chinese", "language_level": []}]}, "experience_required": {"duration": ["minimum of 8 years"], "field": ["digital"]}}, {"job_id": "100003009054189", "location_code": "hk", "company": "Nexperia Hong Kong Limited", "job_title": "Project Manager \u2013 ERP selection and implementation (2 years contract)", "description": "About the role\n\nProject manager to manage the process of selection & implementation of a new ERP system, that is fitting for the ITEC organization, size, growth ambition and business model. Ensure cost optimization and standard IT functionality with as much out-of-the-box functionality as possible.\n\nThis is a 2 years contract role to setup the new ERP system.\n\nWhat you will do\n\nGather ITEC business requirements needed to enable a RFP process for an ITEC ERP system\nManage RFP process for vendor selection (long list, short list, demo, commercials, etc.) together with IT Procurement\nManage and deliver implementation of ERP system for ITEC\n\nWhat you will need\n\nExperienced project manager (5-10 years)\nCertified in any of the project methodologies (Prince2, Agile, Waterfall, Scrum, etc.)\nExperience with projects related to manufacturing processes, preferably with Equipment Manufacturing processes\nExperience with ERP solutions for manufacturing processes (SAP, MS Dynamics, etc.)\nPreferably experience with RFP processes (i.e.\nvendor long list, short list, demo, commercial, etc.)\nIT procurement will be in the lead, but the project manager will be responsible for managing day-to-day activities\nAbility to work with multi-cultural teams that are located in different time zones (mainly Netherlands and Hong Kong)\nAbility to manage global, full-cycle implementation projects (> 2M$)", "employment_types": ["Full Time", "Contract"], "selling_points": ["Global Semiconductor Company", "Opportunity to lead ERP Project", "Exciting job scope"], "locations": ["Shatin Area"], "categories": ["Information Technology (IT)", "IT Project Management / Team Lead"], "post_time": "2022-01-17T08:44:28Z", "salary": {"currency": null, "max": null, "min": null, "period": "monthly", "term": null}, "salary_visible": false, "title_keywords": ["project manager"], "responsibilities": ["cost optimization", "teams", "implementation", "setup", "it procurement"], "requirements": {"degrees": [], "majors": [], "languages": [], "language_level": [], "hard_skills": ["agile", "sap", "vendor", "erp", "erp system"], "soft_skills": ["agile", "responsible"], "languages_combined": []}, "experience_required": {"duration": [], "field": ["related", "manufacturing"]}}, {"job_id": "100003009055739", "location_code": "hk", "company": "NP Solution Limited", "job_title": "Senior Project Officer - Digital Projects", "description": "Job Overview:\nThe role of Senior Project Officer is to drive Digital Projects delivery for our clients in an effective manner. This role is key in maintaining a close relationship with the clients by ensuring the projects are delivered as planned with quality, within budget, and in a timely manner.\n\nResponsibilities:\n\nWork independently and take full responsibility of managing projects of various sizes from ideation to completion\nFirst point of contact to liaise between client and internal project team\nBe accountable for delivering all the deliverables of a project\nCompile a project plan, functional specifications and other project documents and to ensure that requirements are properly documented and that there is consensus between client and project team\nConduct sprint review meetings at the end of every sprint\nMonitor, identify, and manage any potential risks and escalate in a timely manner\nMonitor and control projects to ensure delivery is within planned cost and time\nManage change requests raised by client\nMaintain relationship and morale with clients and project team\nCoach and mentor by providing guidelines and teaching new ways of working to teammates for team growth\nAssist Sales team in presales and tendering processes\nCandidates with more experience will be considered for the position of Project Manager\n\nRequirements:\n\n2 years of solid working experience in IT related project management (less experience may be considered for Project Officer)\nProven record of successful completion of small to medium scale projects\nMust be a team player and quick learner\nGood working attitude and self-discipline\nFluent in written and spoken English and Cantonese\n\n\nTo apply for this position, please simply click on the \u201cAPPLY NOW\u201d bottom.\n\nAll information provided will be treated in strict confidence and used solely for recruitment purpose.\nFor more job opportunities, please visit our website: https://npsl.com.hk/", "employment_types": ["Full Time", "Permanent"], "selling_points": ["remote work", "mobile and digital transform project", "Scrum"], "locations": ["Not Specified"], "categories": ["Information Technology (IT)", "IT Project Management / Team Lead"], "post_time": "2022-01-18T02:54:26Z", "salary": {"currency": null, "max": null, "min": null, "period": "monthly", "term": null}, "salary_visible": false, "title_keywords": ["senior project officer"], "responsibilities": ["liaise", "control", "cost", "guidelines", "review", "monitor", "project plan", "a timely manner", "tendering", "project documents", "specifications", "maintain", "contact", "sales team"], "requirements": {"degrees": [], "majors": [], "languages": ["cantonese", "english"], "language_level": ["fluent"], "hard_skills": ["small", "project management"], "soft_skills": ["good working attitude", "confidence", "quick learner", "project management", "team player"], "languages_combined": [{"language": "cantonese", "language_level": ["fluent"]}, {"language": "english", "language_level": ["fluent"]}]}, "experience_required": {"duration": ["2 years"], "field": ["related", "project management", "it"]}}, {"job_id": "100003009055042", "location_code": "hk", "company": "Generali Life (Hong Kong) Limited", "job_title": "Business Project Manager \u2013 GI & Life Insurance", "description": "Job Description\nThis is a fantastic opportunity for an Insurance Business Project Manager to partake in different career defining business transformation initiatives, such as industry first new channel partnerships or market only product launches.\n\nFor strong candidates with less experience will be considered for an Assistant Project Manager position.\n\nKey Responsibilities & Requirements:\n\nProven track record of delivering projects on a tight timeline, with budget control of HKD2M plus and of excellent quality.\nStrong stakeholder management to manage the expectation of business channel (bancassurance and alt channels) senior management (C-levels and functional Heads).\nWriting business case, partaking in project steering committee and manage vendor partners.\nLeveraging your knowledge on General Insurance (GI) or Life Insurance products.\n\nAdditional Requirements:\n\n4- 8 years insurance business and project management experience\nProfessional certified with a PMP, PRINCE2 or equivalent\nUniversity degree from a reputable university\nLanguage: Cantonese, Mandarin (strongly preferred) and English", "employment_types": ["Full Time", "Permanent"], "selling_points": [], "locations": ["Tai Koo"], "categories": ["Banking / Finance", "Project Finance", "Information Technology (IT)", "IT Project Management / Team Lead", "Sales, CS & Business Devpt", "Channel / Distribution"], "post_time": "2022-01-18T00:49:18Z", "salary": {"currency": null, "max": null, "min": null, "period": "monthly", "term": null}, "salary_visible": false, "title_keywords": ["project manager"], "responsibilities": ["insurance"], "requirements": {"degrees": ["university degree"], "majors": [], "languages": ["cantonese", "english", "mandarin"], "language_level": [], "hard_skills": ["plus", "vendor", "project management", "c", "pmp"], "soft_skills": ["project management"], "languages_combined": [{"language": "cantonese", "language_level": []}, {"language": "english", "language_level": []}, {"language": "mandarin", "language_level": []}]}, "experience_required": {"duration": ["4- 8 years"], "field": ["business", "project management", "insurance"]}}, {"job_id": "100003009052962", "location_code": "hk", "company": "NexLen Internationl Limited", "job_title": "Technical Manager", "description": "Job Responsibilities\n\nOversee the warehouse, technical support and maintenance department\nHelp define IT infrastructure strategy, architecture, and processes\nConduct pre-sales and consultative activities\nAssess vendors and develop test strategies for new hardware and software\nMonitors warehouse employee productivity / quality\nEstablish and implement training processes and strategies for all technical personnel\nAssigning, checking, organizing, prioritizing, and scheduling work orders to / for Support Technician and Maintenance Technician ensuring work orders and completed in a timely manner\nHold regular technical team meetings to determine progress and address any questions or challenges regarding projects\nRecruit and train exceptional employees to fulfill posted positions within the technical department\u00a0\n\nRequirements\n\n5-8 years' solid working experience in Network and Cybersecurity or Technical Support\nDegree / High Diploma in information engineering or equivalent\nCertifications in IT industry (CISSP / CCNA / CCNP / etc.) is an advantage\nStrong experience in IT technology and system like infrastructure, cloud, networking, WiFi, Firewall, etc. Experience in Electric Engineering would be an advantage\nCustomer-oriented and excellent interpersonal skills, including verbal and written communication in English, Cantonese, and Mandarin\nGood team player, target-oriented with strong analytical and problem-solving skills\nWe offer attractive salary and fringe benefit package to the right candidate. Interested parties please send full resume with expected salary.\n\n\nPersonal data provided in your application will be kept in the strictest confidence. It will be used for employment-related purposes. Applications not notified within 1 month will be considered as unsuccessful. Unsuccessful application may be kept for another 3 months for new openings before properly shredded.", "employment_types": ["Full Time", "Permanent"], "selling_points": ["Attractive salary package", "5-8 years' solid experience in network", "CCNA/CCNP/CISSP/CCSA/MCSE/MCITP"], "locations": ["Kwun Tong"], "categories": ["Information Technology (IT)", "IT Project Management / Team Lead", "IT Management", "Network & System"], "post_time": "2022-01-17T04:42:31Z", "salary": {"currency": null, "max": null, "min": null, "period": "monthly", "term": null}, "salary_visible": false, "title_keywords": ["technical manager"], "responsibilities": ["it infrastructure", "maintenance", "software", "technical support", "quality", "checking", "a timely manner", "develop", "hardware", "scheduling", "architecture"], "requirements": {"degrees": ["high diploma", "degree"], "majors": ["engineering"], "languages": ["cantonese", "english", "mandarin"], "language_level": ["excellent"], "hard_skills": ["problem-solving skills", "ccnp", "ccna", "firewall"], "soft_skills": ["good team player", "communication", "customer-oriented", "interpersonal skills", "problem-solving skills"], "languages_combined": [{"language": "cantonese", "language_level": ["excellent"]}, {"language": "english", "language_level": ["excellent"]}, {"language": "mandarin", "language_level": ["excellent"]}]}, "experience_required": {"duration": ["5-8 years"], "field": ["infrastructure", "it", "engineering"]}}, {"job_id": "100003009055717", "location_code": "hk", "company": "Gravitas Recruitment Group", "job_title": "IT Business Analyst Up to 40k", "description": "Responsibilities:\n\n* Guide and mentor business analysts to plan requirement gathering activities/approach and achieve expected outcomes\n\n* Support project manager and scrum master to plan releases and sprints - Identify dependencies between systems, requirements and sprint outcomes\n\n* Help testing team to define a minimum viable scope across multiple systems that can be tested incrementally\n\n* Work with business leads to plan for business team resource allocation and gather support needed for the project\n\n* Ensure change requests are very minimum during later testing phases by ensuring coverage during initial scoping and requirement stages\n\n* Expected to perform hands on work for some critical and complex requirements\n\nEducation & Experience:\n\n* Around 5 years of experience in Business Analyst Role\n\n* Experience working in building or maintaining or integrating with insurance policy admin systems\n\n* Work experience and broad knowledge of digital applications and backend systems in an insurance organization\n\n* Experience leading or managing a team of business analysts\n\n* Good knowledge of insurance products.\n\n* Proven experience of multi-vendor environment and cross functional teams\n\n* Expert knowledge of complex and interdependent projects and continuous improvement methodologies, techniques, tools and controls\n\n*Agile methodology and ways of working experience\n\n* Worked on investment project is a PLUS\n\nWhat you will get in return:\n\n-Global leading Insurance Company\n\n-Opportunities to work on Large Scale Projects\n\nWe Offer You a competitive total rewards package, continuing education & training, and tremendous potential with a growing worldwide organisation. Please send an updated CV to P.chan@gravitasgroup.com for immediate consideration.", "employment_types": ["Full Time", "Permanent"], "selling_points": ["Life Insurance", "Business Analyst", "Digital Transformation"], "locations": ["Not Specified"], "categories": ["Information Technology (IT)", "IT Project Management / Team Lead", "IT Management", "Mobile / Wireless Communications"], "post_time": "2022-01-18T02:52:57Z", "salary": {"currency": "HKD", "max": 10999, "min": 0, "period": "monthly", "term": null}, "salary_visible": true, "title_keywords": ["business analyst"], "responsibilities": ["maintaining", "systems", "teams", "testing", "plan", "managing a team", "insurance"], "requirements": {"degrees": ["master"], "majors": [], "languages": [], "language_level": [], "hard_skills": ["plus", "vendor", "agile"], "soft_skills": ["hands on", "agile"], "languages_combined": []}, "experience_required": {"duration": ["5 years"], "field": ["education", "admin", "business", "digital", "managing a team", "insurance"]}}, {"job_id": "100003009055778", "location_code": "hk", "company": "Michael Page", "job_title": "Digital Transformation Project Manager (HKD65-70K)", "description": "Be responsible for internal group IT digital applications projects and manage overall projects implementation with offshore development team/ vendors;\nManage IT vendors to ensure quality in deliverables of products and services on time;\n\nClient Details\n\nOur client is the largest and first property investment trust firm in Hong Kong and Asia Pacific; They're going through a digital transformation right now within the group, we're looking for a IT Project Manager for business re-engineering and project management;\n\nDescription\n\nJob Responsibilities:\n\nBe responsible for internal group IT digital applications projects and manage overall projects implementation with offshore development team/ vendors;\nManage IT vendors to ensure quality in deliverables of products and services on time;\nCoordinate with stakeholders and manage expectations;\nConsolidate and analyze business requirements to propose feasible and practical solution(s), and corresponding requirements and design are required to be documented;\nRequirement collection, project planning, scheduling, vendor management, SIT, UAT and launch planning;\nPrepare training material and provide end user training;\nResource planning and communicate with various internal teams and cope with a fast-paced environment.\n\nProfile\n\nJob Requirements:\n\nUniversity in Information Technology/ Computer Science/ E-commerce, or related disciplines;\nGood command in spoken Mandarin is a MUST;\nStrong vendors/ Offshore Development Team management skills;\nAt least 7+ years of Project Management experience in digital application(s)/ work-flow automation/ eCommerce system projects;\nStrong communication, negotiation, and interpersonal skills;\nAbility to conduct technical feasibility study for new ideas and digital projects;\nSelf-motivated, detail-oriented, able to manage multiple projects under pressure with tight deadlines.\nExperience in Regional role will be a plus but not mandatory.\n\nJob Offer\n\nHealth insurance;\nPaid time off (PTO) such as sick days and vacation days;\nFlexible and remote working options;\nLife insurance;\nFinancial planning resources;\nProfessional development;\nIdentity theft protection\nHome office improvement incentives for remote workers;\n13th Guaranteed Month Bonus\n\nTo apply online please click the 'Apply' button below.\nFor a confidential discussion about this role please contact Joe Tsoi on +852 2848 9539.", "employment_types": ["Full Time", "Permanent"], "selling_points": ["Responsible for Group IT digital applications;", "Manage vendors to ensure quality in deliverables;", "HKD 65,000 to HKD 72,000 Per Month"], "locations": ["Central & Western Area"], "categories": ["Information Technology (IT)", "IT Project Management / Team Lead"], "post_time": "2022-01-18T02:56:32Z", "salary": {"currency": "HKD", "max": 69999, "min": 55000, "period": "monthly", "term": null}, "salary_visible": true, "title_keywords": ["project manager"], "responsibilities": ["communicate with", "project planning", "management", "uat", "quality", "implementation", "design", "teams", "scheduling", "coordinate with stakeholders", "planning"], "requirements": {"degrees": [], "majors": [], "languages": ["mandarin"], "language_level": ["good command"], "hard_skills": ["project management", "plus", "e-commerce"], "soft_skills": ["flexible", "self-motivated", "under pressure", "negotiation", "detail-oriented", "communication", "project management", "interpersonal skills"], "languages_combined": [{"language": "mandarin", "language_level": ["good command"]}]}, "experience_required": {"duration": ["at least 7+ years"], "field": ["ecommerce", "project management", "digital"]}}, {"job_id": "100003009051820", "location_code": "hk", "company": "John Swire & Sons (HK) Limited", "job_title": "IT & Digital Portfolio Manager", "description": "Our IT & Digital section invites applications for the following position:\n\nIT & Digital Portfolio Manager\n\nThis role provides the opportunity for an experienced IT & Digital expert to influence the development of digital capability for the Company. The job holder would develop a holistic view of different IT & Digital initiatives, define process and value analysis to ensure different initiatives are enabled appropriately.\n\nResponsibilities:\n\nProvide strategic inputs on IT & Digital Portfolio management, define value analysis and mitigate risks to ensure a holistic and balanced investment\nDrive the development of digital capability, especially in innovation, self-service, and experimental mindset in product implementation and data usage\nDevelop framework, guidelines and process for quality governance and project life-cycle management\nOwn and manage IT programme planning, budgeting, reporting, and project governance\nManage internal and external IT communications on programmes and initiatives, document sharing mechanisms, and deliver training on new IT capabilities\nKeep abreast of latest advancement in the industry such as tools, techniques and applications\n\nRequirements:\n\nBachelor\u2019s degree or above in Information Management, Business or related discipline\nAt least 8 years\u2019 experience in managing enterprise project implementation\nProven record in project delivery lifecycle at an enterprise level, and managing investments in multiple and cross-function projects\nExperienced in digital transformation and developing a digital culture for service and produce implementation via experiential learning\nExcellent communication skills, and strong business acumen with an in-depth knowledge on technology enablement\nProfessional qualifications in project management methodology and process management framework would be advantageous\nApplication:\n\nWe offer a competitive package to the right candidate. If you meet the qualifications and are interested in this position, you can send your application by clicking \"Apply Now\". Please note that only shortlisted candidates will be contacted.\n\nWe are an equal opportunity employer. All applications received will be used exclusively for selection purposes and handled confidentially by authorised personnel only. Your application may also be considered for other suitable positions within the Swire group (please indicate clearly on your application if you would not like to be considered for other positions within the group.) Unsuccessful applications will be destroyed after an appropriate time.\n\nThe Swire Group is committed to creating an inclusive and supportive working environment for all our people regardless of their age, gender, gender identity, sexual orientation, relationship, family status, disability, race, ethnicity, nationality, religious or political beliefs. We believe in creating an environment where people feel comfortable at work and able to realise their full potential.", "employment_types": ["Full Time"], "selling_points": ["Portfolio management", "Digital transformation", "Project management"], "locations": ["Quarry Bay"], "categories": ["Information Technology (IT)", "IT Project Management / Team Lead", "IT Management"], "post_time": "2022-01-17T01:17:03Z", "salary": {"currency": null, "max": null, "min": null, "period": null, "term": null}, "salary_visible": false, "title_keywords": ["manager"], "responsibilities": ["reporting", "management", "data", "guidelines", "budgeting", "analysis", "quality", "implementation", "develop", "planning"], "requirements": {"degrees": ["degree or above", "bachelor"], "majors": ["business"], "languages": [], "language_level": [], "hard_skills": ["project management", "professional qualifications", "acumen"], "soft_skills": ["business acumen", "communication skills", "project management", "learning"], "languages_combined": []}, "experience_required": {"duration": ["at least 8 years"], "field": []}}, {"job_id": "100003009055913", "location_code": "hk", "company": "Randstad Hong Kong Limited", "job_title": "Project Manager (Insurance)", "description": "about the company.\nA leading global insurer with presence in 54 markets and serving 105 million customers worldwide\nabout the job.\nMonitor and coordinate the projects to ensure the timeliness and quality of deliverable\nCommunicate with various stakeholders and manage the expectation with business channel (bancassurance and alt channels) senior management (C-levels and functional Heads)\nManage project processes, documentation, progress reporting, status meeting\nMaintain good relationship with users, business Units and vendors\nskills & experiences required.\nBachelor degree or above in information technology, business administration, financial engineering related disciplines or other relevant qualifications\nAt least 4 years of relevant experience\nStrong presentation and problem solving skills; Multi-tasking skills is necessary\nProfessional certified with a PMP, PRINCE2 or equivalent\nKnowledge in GI ( General insurance) Or Life insurance Product\n\nInterested parties, please click \"Apply Now\" or contact Cheryl Lau at cheryl.lau@randstad.com.hk", "employment_types": ["Full Time", "Permanent"], "selling_points": ["Global insurance firm", "General Life and Life Insurance", "At least 4 years of PM exp."], "locations": ["Not Specified"], "categories": ["Information Technology (IT)", "IT Project Management / Team Lead", "Product Management / Business Analyst"], "post_time": "2022-01-18T03:04:53Z", "salary": {"currency": "HKD", "max": 54999, "min": 35000, "period": "monthly", "term": null}, "salary_visible": true, "title_keywords": ["project manager"], "responsibilities": ["communicate with", "reporting", "quality", "monitor", "maintain good relationship", "coordinate", "documentation", "senior management", "insurance", "administration"], "requirements": {"degrees": ["degree or above", "bachelor"], "majors": ["related disciplines", "business administration", "engineering", "information technology"], "languages": [], "language_level": [], "hard_skills": ["documentation", "problem solving skills", "c", "pmp"], "soft_skills": ["multi-tasking skills", "problem solving skills", "presentation"], "languages_combined": []}, "experience_required": {"duration": ["at least 4 years"], "field": ["relevant experience"]}}, {"job_id": "100003009055134", "location_code": "hk", "company": "Seamatch Asia Limited", "job_title": "Project Manager / Business Analyst / PMO/ UAT officer / Project Trainee (Fresh ok)", "description": "Our client is a large\u00a0corporation, due to expansion, they need to\u00a0 \u00a0recruit many IT / project professionals to join their\u00a0IT team.\n\n(for either application and infrastructure team projects)\u00a0 \u00a0 \u00a0\u00a0\n\n\n\nProject Manager / (Senior) Project Specialist /\n\nPMO Support / (Senior) Business Analyst\n\nProject Officer / Project Trainee (with training)\u00a0 \u00a0\u00a0\n\n\u00a0 \u00a0\u00a0\nResponsibilities\n\nHandle user requirement collection, business analysis of\u00a0various\u00a0 \u00a0application, Project Management\nLiaise with business users on scope, testing plans\nPerform\u00a0Quality Assurance and provide User Acceptance Testing (UAT) and production support of the application\nPrepare System Specification and user documentation writing up\nProject coordination and management (application and / or infrastructure projects)\u00a0\nProper training will be provided to the junior / fresh\n\nRequirements\n\nDegree in Business, Finance, Computer Science or related disciplines\nMin 2 years relevant experience in project management /business analysis\nStrong communication skills\nProficiency in both English and Chinese\u00a0\nFresh graduate or less experience also considered and proper training will be provided\nMore experience will consider as Senior Business Analyst / Project Specialist\u00a0\nFocus on UAT / Quality Assurance experience will be consider as QA specialist\n7 year or above experience will be considered as Project Manager / Business Analyst Lead", "employment_types": ["Full Time", "Permanent", "Contract"], "selling_points": ["Business analyst, Project Manager, QA", "Project Management", "SDLC UAT User requirement collection"], "locations": ["Central & Western Area"], "categories": ["Information Technology (IT)", "IT Project Management / Team Lead", "Product Management / Business Analyst", "Others"], "post_time": "2022-01-18T01:21:48Z", "salary": {"currency": null, "max": null, "min": null, "period": "monthly", "term": null}, "salary_visible": false, "title_keywords": ["project manager", "business analyst", "officer", "trainee"], "responsibilities": ["user requirement", "management", "documentation", "uat", "project coordination", "infrastructure", "quality", "testing", "project management", "liaise with", "business analysis", "plans"], "requirements": {"degrees": ["degree", "fresh graduate"], "majors": ["related disciplines", "finance", "business", "computer science"], "languages": ["english", "chinese"], "language_level": ["proficiency"], "hard_skills": ["project management", "analysis", "focus"], "soft_skills": ["communication skills", "project management", "focus"], "languages_combined": [{"language": "english", "language_level": ["proficiency"]}, {"language": "chinese", "language_level": ["proficiency"]}]}, "experience_required": {"duration": ["min 2 years", "7 year"], "field": ["training", "qa", "project management", "business", "relevant experience", "business analysis", "quality assurance"]}}, {"job_id": "100003009054519", "location_code": "hk", "company": "Fano Labs Limited", "job_title": "Project Manager", "description": "Working Location: Hong Kong Science Park\n\nResponsibilities:\n\nHandle hands-on project management and system architecture activities to ensure AI systems are implemented in a timely and well managed manner\nCapable in mastering product functionality and to map client\u2019s requirement with out-of-the-box features to implement & deliver Project goal and deliverables\nEnsure solid alignment with key stakeholders of a project, including business owners/users, project team, consultants and vendors\nProvide leadership on project deliverables and approaches, including technical direction\nImplement effective support and operational processes to ensure efficient support of global & regional deployments\nDefine and document the scope, requirement, work plan, quality, risk and communication plan for the project\nEnrol and encourage project stakeholders to provide support and involvement required to ensure the project\u2019s success\nActively cooperate with Business Development team to up-sell the new products and services\u00a0\nRequirements:\nPrior experience as an IT consultant is preferred\nPossess strong analytical skills and leadership\nSound experience and posses knowledge in application development, system implementation integration technologies and technical architectures\nGood Experience in project cost, timeline, resources and user expectation management, vendor management, contract and change management\nExperience in troubleshooting, software development processes and able to understand and implement client requirements\nSelf-motivated, energetic and organized. Flexible and be able to work under pressure\nFluent in English, Mandarin and Cantonese\nMinimum of 3+ experience as Project Manager role in software requirement understanding and project management\nAble to Travel\n\nPlus\n\nExperience with AI technology, microservice architectures and Kubernetes & Docker is an advantage\u00a0\nPMP Holder\u00a0", "employment_types": ["Full Time"], "selling_points": [], "locations": ["Shatin Area"], "categories": ["Information Technology (IT)", "IT Project Management / Team Lead"], "post_time": "2022-01-17T09:51:25Z", "salary": {"currency": null, "max": null, "min": null, "period": "monthly", "term": null}, "salary_visible": false, "title_keywords": ["project manager"], "responsibilities": ["provide support", "project deliverables", "systems", "quality", "communication", "project management", "plan", "architecture", "cooperate with"], "requirements": {"degrees": [], "majors": [], "languages": ["cantonese", "english", "mandarin"], "language_level": ["fluent"], "hard_skills": ["plus", "integration", "ai", "vendor", "analytical skills", "project management", "system implementation", "pmp"], "soft_skills": ["flexible", "organized", "self-motivated", "troubleshooting", "analytical skills", "project management", "energetic", "leadership", "work under pressure"], "languages_combined": [{"language": "cantonese", "language_level": ["fluent"]}, {"language": "english", "language_level": ["fluent"]}, {"language": "mandarin", "language_level": ["fluent"]}]}, "experience_required": {"duration": [], "field": ["management", "troubleshooting", "project management", "it", "software development", "application development"]}}, {"job_id": "100003009055667", "location_code": "hk", "company": "The Executive Centre Limited", "job_title": "IT Project Manager (1 year contract)", "description": "Job Type:\u00a0Full-Time\n\nReports to:\u00a0Director IT, Enterprise Software\n\n\n\nJob duties:\n\nEnsure all IT projects are delivered on-time and within scope\nMeet with stakeholders to gather and clarify business requirements of each project\nAnalyze structure of a business to determine how it operates and determine its objectives\nTransform business requirements to user stories for software development\nAssist to define the project scope and objectives, to ensure technical feasibility and perform risk management\nDevelop a detailed project plan to monitor and track progress\nCreate and maintain comprehensive project documentation\nManage stakeholders\u2019 expectation with on-going communication\nManage in-house/offshore/3rd party software development team to deliver software solution\nDraft test cases and perform test on UAT\nManage change requests of systems\nPerform training to end-users and draft user manual\nProvide on-going support to end-users and troubleshoot issues via ticketing system, emails and phone calls when necessary\n\nQualifications:\n\nDegree holder in Information Technology, Computer Science, Business Administrations or Commerce;\nAt least 5-8 years\u2019 relevant experience in IT / project / service management\nExperience in Agile methodologies and DevOps practices within Technology teams (e.g. Scrum, Kanban)\nExtensive Knowledge of Business Process and back end Automation initiatives\nExperience of Incident and Problem Management\nDemonstrate an ability to work on an international team but can also do so independently on a wide variety of projects across a series of workstreams, building stakeholder buy-in around plans, commitments and change\nExperience as a IT Project Manager with the delivery of major Transformational programs or migration project is a plus\nExperience in project management for corporate or enterprise is a plus\nUnderstanding of basic API and Database knowledge is a plus\nGood command of communication skill in both Cantonese and English", "employment_types": ["Full Time", "Contract"], "selling_points": ["Reports to Director IT, Enterprise Software", "Experience in IT / project / service management", "5 minutes walk to  MTR station"], "locations": ["Southern Area"], "categories": ["Information Technology (IT)", "IT Project Management / Team Lead"], "post_time": "2022-01-18T02:50:28Z", "salary": {"currency": null, "max": null, "min": null, "period": "monthly", "term": null}, "salary_visible": false, "title_keywords": ["it project manager"], "responsibilities": ["software", "communication", "maintain", "business process", "troubleshoot", "database", "plans", "phone calls", "project documentation", "uat", "monitor", "teams", "develop", "reports", "migration", "management", "systems", "project plan", "project management"], "requirements": {"degrees": ["degree holder"], "majors": ["business", "computer science", "information technology"], "languages": ["cantonese", "english"], "language_level": ["good command"], "hard_skills": ["plus", "basic", "agile", "devops", "project management", "documentation"], "soft_skills": ["independently", "agile", "communication skill", "communication", "project management", "comprehensive", "troubleshoot", "extensive", "detailed"], "languages_combined": [{"language": "cantonese", "language_level": ["good command"]}, {"language": "english", "language_level": ["good command"]}]}, "experience_required": {"duration": ["at least 5-8 years"], "field": ["management", "devops", "project management", "it", "relevant experience"]}}, {"job_id": "100003009049368", "location_code": "hk", "company": "HGC Global Communications Limited", "job_title": "IT Project Manager", "description": "Responsibilities:\u00a0\n\nManage and lead the planning and implementation of IT technical projects (e.g. Cloud implementation, IT infrastructure\u00a0projects);\nManage project schedule, resources\u00a0and risks. Perform proper\u00a0escalation to ensure project success;\nEnsure all the contractual\u00a0commitments and deliverable\u00a0are successfully delivered by vendors on time and within the budget;\nConduct system analysis, implementation, testing, user training and documentation\u00a0on IT systems;\nInterface with customers on system implementation for business systems projects;\nPerform product evaluation, vendor selection, and procurement of IT solutions / products.\u00a0\n\nRequirement:\n\nDegree in IT/ Computer Sciences/ Computer Engineering or related discipline\n5 years solid experience in IT project management with technical knowledge;\nCertified in any PMP, Agile, or Scrum Master is preferred\nKey competencies:\nLeading others\u00a0\nComposure\nInterpersonal Savvy\u00a0\nBusiness Acumen\nDealing with Ambiguity\n\nWe offer competitive salary package and career development opportunity. \u00a0Free company coach is provided. Interested parties, please quote our reference number and apply with full resume,\u00a0present and expected salary, by clicking \"APPLY NOW\".\u00a0\n\n\nWe are an equal opportunity employer and welcome applications from all qualified candidates. Information provided will be treated in strict confidence and only be used for consideration of your application for the relevant post within the HGC Global Communications Limited. Personal data provided by job applicants will be used strictly according to our Personal Information Collection Statement, a copy of which will be available upon written request. Information of unsuccessful candidates will be destroyed within six months.", "employment_types": ["Full Time", "Permanent"], "selling_points": ["IT Project Management permanent role", "Great exposure on technical transformation", "Dynamic working environment"], "locations": ["Tsing Yi"], "categories": ["Information Technology (IT)", "IT Project Management / Team Lead", "IT Management", "Technical Writing"], "post_time": "2022-01-14T08:31:44Z", "salary": {"currency": null, "max": null, "min": null, "period": "monthly", "term": null}, "salary_visible": false, "title_keywords": ["it project manager"], "responsibilities": ["it infrastructure", "analysis", "budget", "systems", "implementation", "testing", "schedule", "evaluation", "documentation", "planning"], "requirements": {"degrees": ["degree", "master"], "majors": ["it", "computer engineering"], "languages": [], "language_level": [], "hard_skills": ["project management", "pmp", "agile", "acumen"], "soft_skills": ["business acumen", "project management", "interpersonal", "agile"], "languages_combined": []}, "experience_required": {"duration": ["5 years"], "field": ["project management", "it"]}}, {"job_id": "100003009054282", "location_code": "hk", "company": "FUJIFILM Data Management Solutions Asia Limited", "job_title": "Service Delivery Manager", "description": "The Job\n\nManaging service delivery to the client accounts, promoting the continuous improvement of productivity, service quality and customer satisfaction, preferably in the industry of document outsourcing, Print Room, Mail Room and BPS services\nDelivering service in best practice service delivery model to achieve SLA and enhance customer satisfaction\nDeveloping strong customer relationships and networks effectively to ensure service excellence\nAchieving productivity improvements resulting in high value for customer, margin enhancement and good P&L performance\nTransforming and growing the business for further profitable service revenue\nPerforming team leadership and people management\n\n\u00a0The Person\n\nUniversity graduate in Information Technology, Business Administration with relevant professional qualifications, e.g. ITIL, Lean Six Sigma, PMP is preferred\nAt least 5 years' industry-related operations management experience\nExperience of having successfully operated at prime customer contact level\nService delivery management experience with high standard and quality service delivered to customer(s)\nDemonstrate proven experience in implementing productivity and customer satisfaction enhancement programs\nStrong people management and development skills\nPreferred experience in outsourcing bids, from pre-sales to successful implementation\nPossess experience of contract negotiation/supplier management\nFluent in both spoken and written English and Cantonese\n\nWe are an equal opportunity employer, offer\u00a05-day week (from 9am to 5:30pm), attractive incentive, shuttle bus service, training opportunity and medical benefits. Interested applicants shall submit a full resume indicating current and expected salary with soonest availability.\n\nAll information provided will be treated in strict confidence and used for recruitment purposes only. Applicants not hearing from us within six weeks may consider their applications unsuccessful. All data of unsuccessful applications will be destroyed after six months.", "employment_types": ["Full Time", "Permanent"], "selling_points": ["Managing service delivery to the client accounts", "5 years\u2019 experience in operations management", "5-day work, 9:00am - 5:30pm"], "locations": ["Chai Wan"], "categories": ["Information Technology (IT)", "IT Project Management / Team Lead", "Sales, CS & Business Devpt", "Account Servicing"], "post_time": "2022-01-17T09:01:49Z", "salary": {"currency": null, "max": null, "min": null, "period": "monthly", "term": null}, "salary_visible": false, "title_keywords": ["manager"], "responsibilities": ["service delivery", "management", "quality", "developing", "p&l"], "requirements": {"degrees": ["university graduate"], "majors": ["business administration", "information technology"], "languages": ["cantonese", "english"], "language_level": ["fluent"], "hard_skills": ["itil", "lean", "professional qualifications", "six sigma", "pmp"], "soft_skills": ["confidence", "negotiation"], "languages_combined": [{"language": "cantonese", "language_level": ["fluent"]}, {"language": "english", "language_level": ["fluent"]}]}, "experience_required": {"duration": ["at least 5 years"], "field": ["related", "management", "operations management"]}}, {"job_id": "100003009056055", "location_code": "hk", "company": "Mandatory Provident Fund Schemes Authority", "job_title": "Manager \u2013 IT Application Solution (Ref: eMPF2/2022)(eMPF Platform Co Ltd)", "description": "We are now looking for high calibre and passionate individuals to join us to undertake this multi-billion HK dollar transformation project leading the MPF ecosystem to a new era.\u00a0 If you are passionate about creating a positive impact on the working population of Hong Kong and are keen and willing to work in a start-up style environment, please join our growing team to contribute to the transformation journey.\n\n\nKey Accountabilities\n\nReporting to the Senior Manager (Team Head) \u2013 Application System;\nWorking closely with a major third party supplier as an \u201cintelligent customer\u201d and \u201ccritical friend\u201d on the delivery of the eMPF Platform project, including system analysis, system design, system development, testing, migration and implementation;\nWorking across all system interfaces areas with stakeholder\u2019s systems;\nReviewing contractual deliverables and providing recommendation for acceptance / payment / need for revision;\nManaging the contractors, and providing technical comments to the development activities; and\nAny other duties as assigned.\n\nSkills and Qualification\n\nBachelor\u2019s degree or Master\u2019s degree in Computer Science or related disciplines;\nIdeally CMMI- DEV (Capability Maturity Model Integration \u2013 Development) certified;\nMinimum 8 years of relevant IT - SDLC (System Development Life Cycle) and IT vendor management experience preferably in Financial Services environment;\nSolid experience in working with suppliers in delivering large-scale system solutions including practical experience with web and mobile apps development, data lake and data visualization and involved in 2 large projects in implementing a complex system;\u00a0\nHands-on technical skills and experience in application of modern technology, such as Cloud technology, Cyber security, DevOps, Micro services architecture, Kubernetes, Level 1 to 4 system level definition, mobile and portal development, BI, API, Messaging, Java, JSON, Databases (example: Oracle, Mongo, Microsoft SQL and MYSQL);\nStrong project management experience;\nDriven, positive, highly structured, proactive, and analytical;\nExcellent organization and problem solving skills, and be able to work under pressure;\nGood command of both spoken and written Chinese and English; and\nKeen and willing to work in a start-up style environment with all the flexibility that requires and level of change involved.\n\nRemuneration Package\n\nRank and salary will be commensurate with qualification and experience. The initial appointment will be made on a fixed-term contract.\u00a0 A competitive remuneration and benefits package including discretionary performance-linked variable pay, annual leave, medical, dental and life insurance coverage, and MPF will be offered.\n\nTo Apply\n\nInterested candidates are invited to apply by sending full career details and application letter, quoting the position applied for and job reference number, with information of current and expected remuneration as well as earliest availability\u00a0through the \"Apply Now\" button.\u00a0\n\n\nThe closing date for application is 25 January\u00a02022.\u00a0 Applicants not contacted for follow up within 3 months after the closing date for application may assume that their applications are unsuccessful.\u00a0 Applications not selected for further processing may be considered for relevant openings in the future but their applications will not be retained for more than a period of two years after the closing date.\n\nThe information provided will be kept confidential and only be used for those purposes relating to your application.\u00a0 Please visit our website for the details of the MPFA\u2019s Personal Information Collection Statement at https://www.mpfa.org.hk/en/mpfa/joining-mpfa/job-vacancies/personal-information-collection-statement.\u00a0 The MPFA is an equal opportunities employer and welcomes applications from all qualified candidates.", "employment_types": ["Full Time", "Contract"], "selling_points": [], "locations": ["Ngau Tau Kok"], "categories": ["Banking / Finance", "Project Finance", "Information Technology (IT)", "IT Auditing", "IT Project Management / Team Lead"], "post_time": "2022-01-18T03:13:55Z", "salary": {"currency": null, "max": null, "min": null, "period": "monthly", "term": null}, "salary_visible": false, "title_keywords": ["manager"], "responsibilities": ["any other duties", "visualization", "data", "cyber security", "payment", "work under pressure", "implementation", "application system", "testing", "migration", "architecture", "reporting", "management", "mpf", "third party", "analysis", "systems", "comments", "project management", "system design", "databases", "insurance"], "requirements": {"degrees": ["degree", "bachelor", "master"], "majors": ["related disciplines", "computer science"], "languages": ["english", "chinese"], "language_level": ["good command"], "hard_skills": ["java", "bi", "web", "cyber security", "analysis", "devops", "vendor", "application system", "sql", "mobile", "sdlc", "system design", "project management", "databases", "data visualization", "integration", "problem solving skills", "oracle"], "soft_skills": ["passionate", "passionate about", "proactive", "keen", "project management", "hands-on", "technical skills", "problem solving skills", "structured", "driven", "positive", "work under pressure"], "languages_combined": [{"language": "english", "language_level": ["good command"]}, {"language": "chinese", "language_level": ["good command"]}]}, "experience_required": {"duration": ["minimum 8 years"], "field": ["management", "development", "devops", "system development", "sql", "project management", "it", "financial services", "security"]}}, {"job_id": "100003009055140", "location_code": "hk", "company": "Johnson Controls Hong Kong Limited", "job_title": "Commercial IT Solution Architect, APAC", "description": "What you will do\n\nAs a Commercial IT Solution Architect you will be part of a team of Architects in our Sales Centre of Excellence who are focused on harnessing the power of technology to enable our sales objectives and excellent customer experience in Johnson Controls.\n\nYou will work with our business and IT stakeholders to conceive and design sales technology solutions and support the mapping of requirements to ensure alignment with our enterprise and commercial roadmap, delivering the best technical architecture to fulfill our business and customer needs.\n\nThe Solution Architect for Commercial IT is accountable for designing solutions that enable the Sales and commercial functions of the Johnson Controls Asia Pacific business across various lines of business including:\n\nHVAC and Controls: air systems, chillers, and building automation\nFire Protection: fire detection, protection, suppression, and alarm monitoring\nSecurity Solutions: intrusion detection, access control, video surveillance, and alarm monitoring.\nIndustrial Refrigeration\nThe position operates within a matrixed IT Operating Model in which the Commercial IT Solution Architect is primarily accountable for the design and architectural governance of IT solutions in the Sales/Commercial platforms.\u00a0You will work in collaboration with a broader team of architects from ERP, Marketing, Analytics, RPA and Enterprise teams along with stakeholders from Information Security, Delivery, Program Management, and Business-IT Engagement.\u00a0\n\n\n\nHow you will do it\n\nUse your technical expertise to review, interpret and respond to business requirements to ensure alignment between customer expectations and current or future technology capability.\nDesign and align technology solutions to our target state ecosystem, provide leadership on platform evolution and maturity of our Commercial IT ecosystem.\nDefine and maintain a target state technology evolution roadmap for Commercial IT platforms and ensure alignment with our overall Enterprise Architecture Strategy, IT and Business Stakeholders.\nProvide insights and thought-leadership on industry/functional trends and best practices to guide technology decisions in context to business priorities.\nProvide technical leadership to coordinate, prioritise and define solutions for Commercial projects.\nPrepare Solution Design Documents and work with stakeholders to ensure they are approved\nUnderstand service inter-dependencies and work with cross-functional teams towards technical solutions for multi-tiered systems.\nProvide mentoring and coaching to the delivery teams, peers and other colleagues in the organization\nUse your hands-on experience with technology and skills in communication and negotiation to enable the success of critical projects.\nEnsure standards for technical reviews, peer reviews, and feedback cycles are set and followed\u200b for architecture designs and implementation\nEnsure technical governance is in place across the Commercial platforms for the region\u200b.\nFoster a culture of technical discipline, craftsmanship, innovation, transparency and collaboration\nSupport risk management, regulatory compliance, cybersecurity, and audit remediation activities.\nSupport business continuity and disaster recovery efforts.\nSupport definition and utilization of IT governance processes and policies.\nCollaborate, negotiate, influence, and build relationships at levels with internal and external parties in alignment with Johnson Controls\u2019 key\u00a0values: integrity, teamwork, excellence, and accountability.\n\nWhat we look for\n\nRequired\n\nBachelor\u2019s Degree in Computer Science/ Electrical/Mechanical/Electronics /Instrumentation\n6 years of hands-on experience working with Sales and Customer Experience technologies (e.g. CRM, CPQ, ecommerce) and a thorough understanding of industry trends, vendors, frameworks and practices\nCertified Salesforce System or Application Architect or equivalent in other enterprise CRM platforms.\u00a0Oracle Customer Experience certification or equivalent in other enterprise sales platforms.\nUnderstanding of agile delivery principles and quality software engineering processes and practice\nExperience in DevOps / CI / CD\nUnderstanding of cloud concepts including IaaS, PaaS, SaaS, and iPaaS\nExperience with the design and development of object-oriented systems, developing solutions, and integrating platforms using enterprise integration software e.g. mulesoft.\nExceptional leadership skills to achieve outcomes in a heavily matrixed management\nExcellent communication and interpersonal skills, across all levels and environments\nExcellent oral and written English.\nExperience in partner engagement with an onshore/offshore delivery model\nAbility to communicate effectively to technical team as well as business audience\nExperience in Application Extensions and BI Reporting\n\nInterest parties please send your application letter & CV including current and expected salary, date by clicking \"Apply Now\".\n\nOnly the shortlisted candidates will be notified. Data collected would be used for recruitment purposes only.", "employment_types": ["Full Time"], "selling_points": ["Design & architectural governance of IT solutions", "Design solutions for Sales functions", "Define solutions for Commercial projects"], "locations": ["Kwun Tong"], "categories": ["Information Technology (IT)", "IT Project Management / Team Lead", "IT Management", "E-commerce", "Product Management / Business Analyst"], "post_time": "2022-01-18T01:25:40Z", "salary": {"currency": null, "max": null, "min": null, "period": "monthly", "term": null}, "salary_visible": false, "title_keywords": [], "responsibilities": ["provide insights", "business continuity", "software", "information security", "data", "internal and external parties", "quality", "audit", "design", "communication", "maintain", "designing", "collaborate", "compliance", "teams", "implementation", "developing", "architecture", "reporting", "management", "monitoring", "review", "cross-functional teams", "policies", "systems", "coordinate", "recruitment", "access control"], "requirements": {"degrees": ["degree", "bachelor"], "majors": ["computer science"], "languages": ["english"], "language_level": ["excellent"], "hard_skills": ["bi", "salesforce", "agile", "hvac", "devops", "erp", "rpa", "integration", "oracle"], "soft_skills": ["oral", "negotiation", "focused", "accountability", "agile", "leadership skills", "teamwork", "integrity", "accountable", "prioritise", "communication", "hands-on", "communication and interpersonal skills", "thorough", "leadership"], "languages_combined": [{"language": "english", "language_level": ["excellent"]}]}, "experience_required": {"duration": ["6 years"], "field": ["development", "devops", "developing", "design", "solution architect", "commercial", "it", "team"]}}, {"job_id": "100003009055825", "location_code": "hk", "company": "Mattel Asia Pacific Sourcing Ltd", "job_title": "Business Analyst Specialist- IT, QMS", "description": "The Opportunity:\u00a0\n\nMattel is currently seeking a Business Analyst Specialist in our Global Technology Organization. This role will report directly to the Director, IT, responsible for delivering technology solutions across our Brands, Global Supply Chain and Corporate back office solutions.\n\nThis role will oversee QMS, Quality, Laboratory Management, Safety, Regulatory Compliance, and Sustainability platforms, which helps drive business drive quality, safety, and compliance.\u00a0\n\nResponsibilities:\n\nPartner with the business process owners to gain an in-depth knowledge for process improvement\nDevelop business requirement and business case documents, along with financial justification and ROI for all initiatives\nWork with business to identify issues, problems, and opportunities; compare data from different sources to draw conclusions; use effective approaches for developing appropriate actions and solutions\u00a0\nDevelop and sustain productive customer relationships\nLead User Acceptance testing, to ensure that the system addresses the business needs from the user\u2019s point of view\nManage multiple projects and personnel to coordinate all aspects of implementation and delivery of tasks\u00a0\nCoordinate Organization Change Management in alignment with the \u201cto be\u201d state\nMaintain effective knowledge of the Quality Management processes,\u00a0 thorough awareness and evaluation of trends and developments of emerging technologies\nEvaluate timing of software version upgrades and facilitate migrations\nPartner with GTO Client Services, to ensure timely and effective support/break/fix and add/change services\n\nRequirements:\n\n\nDegree holder with 5+ years of relevant experience working in IT in a global delivery function\nMust have working knowledge in 2 or more of the following domains: Product Lifecycle Management, Quality Management, or Sustainability\nExperience with managing a Quality Management System, with various modules that satisfy Quality, Safety, and Compliance requirements preferred.\nExperience with quality applications such as Polarion, STARLIMS, Chemical Management Database, Dexi \u2013 Data Scrapping Tool, and iCiX is preferred.\nExperience with PowerBI, Cognos, Tableau, and Google Data Lake is preferred.\u00a0Oracle Agile PLM, or Salesforce Service Cloud experiences a plus\nExperience in Consumer Packaged Goods or Fast Fashion industries preferred\nStrong analytical and reporting skills, able to create dashboards and establishing KPIs.\nAble to work with contractors and consultants to drive outcome and presenting to\u00a0business stakeholders on a regular basis\nExperience with compliance documentation management and support.\nOpen to travel as needed (approximately 10%)\n\nWho Should Join Us:\n\nWe are not only looking for the right experience and skill set, but also for attitude, potential & cultural fit.\n\nIf you are creative, energetic, passionate with a growth mindset and devoted to developing your future career in the world\u2019s leading toy company, you are welcome to be a part of our team and we will play & grow together!\u00a0\n\nWhat We Offer:\n\nAs a caring company, we are committed to providing engaging and work-life balance environment, competitive remuneration, comprehensive fringe benefits, and progressive career opportunities to our people.\u00a0 \u00a0\n\nOur benefits include:\n\n5-day work week; 2 Half-Day off every month\nFlexi Working Hours\n13th Month Salary and Performance Bonus\nAnnual Leave and Company Holidays\nGroup Medical, Dental and Life Insurance\nMPF/ Mattel Retirement Scheme (ORSO Scheme)\nTraining Sponsorship & Education Subsidy\nComprehensive Wellness Programs\nHow To Apply:\n\nInterested parties please click \u201cApply Now\u201d to send your full resume (in Microsoft Word or PDF format), current and expected salary to us for review.\n\nApplicants not invited for interview within 6 weeks may assume their application unsuccessful. All information will be treated in strictest confidence and used solely for recruitment purpose.", "employment_types": ["Full Time", "Permanent"], "selling_points": ["Degree holder in IT/  5+ years of relevant exp", "QMS Project Experience required", "Regional system project support"], "locations": ["Tsim Sha Tsui"], "categories": ["Information Technology (IT)", "IT Project Management / Team Lead", "Product Management / Business Analyst"], "post_time": "2022-01-18T02:59:18Z", "salary": {"currency": null, "max": null, "min": null, "period": "monthly", "term": null}, "salary_visible": false, "title_keywords": ["specialist", "business analyst"], "responsibilities": ["migrations", "management", "change management", "software", "data", "upgrades", "quality", "developing", "manage multiple projects", "testing", "develop", "coordinate", "implementation", "business process", "maintain", "evaluate", "evaluation"], "requirements": {"degrees": ["degree holder"], "majors": ["it"], "languages": [], "language_level": [], "hard_skills": ["plus", "salesforce", "agile", "tableau", "documentation", "oracle"], "soft_skills": ["passionate", "creative", "agile", "devoted", "energetic"], "languages_combined": []}, "experience_required": {"duration": ["5+ years"], "field": ["management", "compliance", "it", "relevant experience", "quality management", "database"]}}, {"job_id": "100003009053171", "location_code": "hk", "company": "Johnson Electric Industrial Manufactory Limited", "job_title": "Cyber Security Manager", "description": "Responsibilities:\n\n\nManage SOC level 1 outsourced vendor KPI and SLA\nLead a global 24x7 SOC level 2 team (based in Hong Kong) on advanced threat hunting and simulation\nFormulate and manage organizational compliance using ISO 27001:2013 and TISAX standards\nEstablish an ISMS platform and processes to manage organizational risk management in both IT/OT areas\nOversee technological execution of the recommended cyber security related roadmap across project teams and stakeholders\nManage cyber security design review of proposed security related solutions across project teams and IT stakeholders\nPerform other duties as assigned by supervisor\n\nRequirements:\n\n\nBachelor or master\u2019s degree in computer science/Information Security\n6 years of increasing responsibility in information security and technology operations\n3 years in a SOC management role at a regional or global level\nISO 27001 lead auditor certification preferred\nCertificates in CISSP, CISA, CISM, CEH, or GIAC preferred\nTechnical knowledges of Cyber Security tools\nStrong knowledge in area of Cloud & Network Security, Application Security, Cyber Defense, Security Compliance and Identity and Access Management\nAbility to make problem solving decisions under pressure\nPositive attitude and strong commitment to the delivery of quality work\nGood command of written and spoken English and Chinese, with proficiency in Putonghua an advantage\nAble to work with oversea colleagues and drive results\nAbility to work outside of normal office hour and host conference call is required\n\nWe regret only shortlisted candidates will be notified.\n\nPersonal data provided by job applicants will be used strictly for recruitment purpose only, a copy of which will be provided upon request. Unless otherwise instructed in writing by the applicant concerned, applicants may be considered for other suitable positions within the Company. Applicants who do not hear from us within 8 weeks may consider their application unsuccessful and their data will be destroyed within 24 months of receipt.", "employment_types": ["Full Time", "Permanent"], "selling_points": ["Globally Leading Motor Manufacturer", "Innovative Team Environment", "Attractive Salary Remuneration Package"], "locations": ["Tai Po Area"], "categories": ["Information Technology (IT)", "IT Project Management / Team Lead", "Security", "Network & System"], "post_time": "2022-01-17T06:14:52Z", "salary": {"currency": null, "max": null, "min": null, "period": "monthly", "term": null}, "salary_visible": false, "title_keywords": ["manager"], "responsibilities": ["management", "perform other duties", "cyber security", "compliance", "teams", "review", "design"], "requirements": {"degrees": ["degree", "bachelor", "master"], "majors": ["computer science"], "languages": ["putonghua", "english", "chinese"], "language_level": ["advantage", "proficiency", "good command"], "hard_skills": ["problem solving", "make", "cyber security"], "soft_skills": ["problem solving", "positive attitude", "under pressure"], "languages_combined": [{"language": "putonghua", "language_level": ["proficiency", "advantage", "good command"]}, {"language": "english", "language_level": ["proficiency", "advantage", "good command"]}, {"language": "chinese", "language_level": ["proficiency", "advantage", "good command"]}]}, "experience_required": {"duration": [], "field": []}}, {"job_id": "100003009054831", "location_code": "hk", "company": "Hong Kong Disneyland", "job_title": "Associate Manager, Program Management Office", "description": "Job Summary:\nProvide support and consultancy to management and teams in technology and digital around all matters relating to portfolio, program management and data governance.\nResponsibilities:\nAssist team head in preparing presentations and communications related to Tech & Digital Team\nCoordinate and facilitate meetings, prepare and consolidate regular reports for submitting to management and segments\nTrack business concepts and consolidate the Tech & Digital portfolio for management approval. Monitor, track and report on the interdependencies of key projects and key progress (including milestones, status, costs/budget, resource allocation, issues and action items)\nManage budgeting and prioritization for CAPEX, OPEX and expansion projects relating to Tech & Digital teams\nAssist in Tech & Digital center of excellence (COE) and data governance toward quality and data improvement\nMaintain application repository, legal related documents, Tech & Digital project management/ monitoring and relating processes and tools\nRecommend to Tech & Digital management the opportunities for process improvement relating to project management. Coaching the other cast in Tech & Digital team in adopting the best practices\nAct as focal point of Tech & Digital in collaboration with other Line Of Business and integrate in Tech & Digital internally, for consolidating Tech & Digital collaborative efforts in resort-wide initiatives or campaigns\nBasic Qualifications:\nBachelor Degree with 7 years in in technology, planning, project management and/or financial reporting or relevant areas\nExperience in portfolio management and program management is preferred\nGeneral management skills and sound knowledge of business case development, budget calculating and contract management.\nProject Management Professional (PMP) or PRINCE2 Practitioner holder is preferred\nMicrosoft Office including Excel, PowerPoint, SharePoint, Power BI, etc.\nAdditional Information:\nSUBMITTING YOUR APPLICATION\nAfter clicking \u201cApply for this job\u201d below, the employment application will open in a new window. Please complete ALL pages of the application in ENGLISH by clicking \u201cNext\u201d on each page, then \u201cSubmit\u201d on the final page.\n#LI-CW1 HKProfessional\nAbout Hong Kong Disneyland Resort:\nHong Kong Disneyland Resort brings unforgettable, culturally distinctive Disney experiences for guests of all ages and nationalities. Hong Kong is home to the fifth Disney Resort in the world. The city's landscape and vibrant, diverse culture has inspired our Imagineers to create a variety of entertainment that is unique to Hong Kong Disneyland Resort.\n\nHong Kong Disneyland consists of the following seven themed areas: Adventureland, Fantasyland, Grizzly Gulch, Main Street U.S.A., Mystic Point, Tomorrowland and Toy Story Land. These areas feature themed attractions, entertainment and interactive experiences, restaurants, merchandise shops and refreshment stands. Additionally, there are daily parades and nighttime events. The Resort has three theme resort hotels: Hong Kong Disneyland Hotel, Disney Explorers Lodge and Disney\u2019s Hollywood Hotel.\n\nTo date, Hong Kong Disneyland Resort has welcomed millions of Guests. Since 2006, Hong Kong Disneyland has ranked among the top five most popular places to visit in Hong Kong, according to the Hong Kong Tourism Board's annual Statistical Review.", "employment_types": ["Full Time", "Permanent"], "selling_points": ["Assist team head in preparing presentations", "Bachelor Degree", "7 years in in technology, planning"], "locations": ["Lantau Island"], "categories": ["Admin & HR", "Secretary", "Information Technology (IT)", "IT Project Management / Team Lead", "Product Management / Business Analyst"], "post_time": "2022-01-17T11:27:38Z", "salary": {"currency": null, "max": null, "min": null, "period": "monthly", "term": null}, "salary_visible": false, "title_keywords": ["associate manager"], "responsibilities": ["data", "budgeting", "budget", "capex", "quality", "opex", "maintain", "costs", "teams", "monitor", "presentations", "reports", "report", "provide support", "management", "related documents", "monitoring", "review", "power bi", "contract management", "coordinate", "project management", "financial reporting", "planning"], "requirements": {"degrees": ["degree", "bachelor"], "majors": ["project management"], "languages": ["english"], "language_level": [], "hard_skills": ["excel", "bi", "basic", "focal", "project management professional", "microsoft office", "presentations", "powerpoint", "project management", "pmp"], "soft_skills": ["project management", "collaborative", "unique", "diverse"], "languages_combined": [{"language": "english", "language_level": []}]}, "experience_required": {"duration": [], "field": ["management"]}}, {"job_id": "100003009055589", "location_code": "hk", "company": "Randstad Hong Kong Limited", "job_title": "Product Manager - Digital Transformation (60K - 70K + Bonus)", "description": "about the company.\n\nRandstad are currently working with a well established MNC who are currently looking for a Product Manager for their digital transformation projects based around their in-house platform. The right candidate will be responsible for heading up the product side and managing relationships with stakeholders/end-users in terms of what needs to be built and helping to land these into the organisation.\n\n\nabout the job.\n\nWork closely with IT development team and other business stakeholders to define and advocate product strategy, roadmap and user stories for the digital transformation projects\nOwn and drive the product backlogs and prioritise using appropriate techniques\nDefine the business value for each feature adds to the product by ROI analysis, and prepare acceptance criteria in conjunction with other teams and support delivery of these features\nGather requirements from senior stakeholders to determine the underlying business process required to support the user stories defined and the development of business cases to ensure that there is clarity on the benefits expected and these can be measured clearly\nBe obsessed with constant improvement, scalability, reusability, and operational excellence based on the feedbacks from end-users\nLead and coach the junior teammates in the team for the industry best practices\n\nskills & experiences required.\n\nBachelor Degree or above in Computer Science/Business Administration or relevant discipline\nMinimum 6+ years of experience as a senior level Business Analyst or Product Owner ideally with software development/digital transformation project experience\nProven experience in managing requirements, stakeholders, while developing and maintaining an impactful product roadmap and backlogs to support its delivery\nAbility for communicating clearly, concisely and confidently across all levels in the business especially influencing business stakeholders especially Director/C-level is a must\nSolid experience in using customer centric approaches to define user stories, acceptance criteria and delivery of these with both internal IT development team and 3rd party vendors\nPrevious experience in Agile methodology / Scrum environment\nProficient in spoken and written English\nPMP/CSM/Lean Six Sigma certification is a plus\n\nabout the benefits.\n\nPerformance Bonus (Average 1.5 - 2 Months Salary)\n18 Days Annual Leave\nMedical, Dental and Life Insurance\nPermanent Headcount\n5 Days Work\n\nIf you're interested in this exciting opportunity please don't delay and click APPLY NOW or for more information, you can reach out to Kelvin Chu at kelvin.chu@randstad.com.hk", "employment_types": ["Full Time", "Permanent"], "selling_points": ["Permanent Headcount", "Multinational Environment", "In-house Platform Digital Transformation"], "locations": ["Not Specified"], "categories": ["Information Technology (IT)", "IT Project Management / Team Lead", "Product Management / Business Analyst", "Software Development"], "post_time": "2022-01-18T02:46:11Z", "salary": {"currency": "HKD", "max": 69999, "min": 55000, "period": "monthly", "term": null}, "salary_visible": true, "title_keywords": ["product manager"], "responsibilities": ["3rd party vendors", "software", "maintaining", "analysis", "teams", "developing", "business process", "administration"], "requirements": {"degrees": ["degree or above", "bachelor"], "majors": ["business administration", "computer science"], "languages": ["english"], "language_level": ["proficient"], "hard_skills": ["lean", "plus", "agile", "analysis", "six sigma", "c", "pmp"], "soft_skills": ["prioritise", "agile", "organisation", "responsible"], "languages_combined": [{"language": "english", "language_level": ["proficient"]}]}, "experience_required": {"duration": ["minimum 6+ years"], "field": ["it development", "developing", "business", "software development", "digital", "team"]}}, {"job_id": "100003009055607", "location_code": "hk", "company": "AXA Hong Kong", "job_title": "Senior Manager, Core systems", "description": "Solution Delivery\n\n\nCoordinate with Release Management to plan systems deployment to production.\nManage a group of application specialists and consultants to perform application analysis, design, development (where applicable) and quality assurance activities of all IT projects assigned.\nManage and engage the vendors to build, integrate and deliver RLS.\nMonitor daily activities to ensure application solutions meet AXA's policies, standards and quality requirement.\n\nProject Management\n\n\nManage projects throughout the delivery life cycle aim at controlling the scope, schedule and cost for IT projects.\n\nPeople Management\n\n\nDevelop and manage the performance of the team to ensure knowledge retention for key platforms via proper resource planning and backup.\nDrive capability development of the team to build specialization in their responsible application domain area.\n\nVendor Management\n\n\nFacilitate discussions and help vendors understand business requirements and improve vendor performance.\nReview and approve deliverables to ensure quality assurance.\nOversee the delivery of trainings and knowledge transfer to the production support teams to ensure necessary knowledge is transferred.\nManage vendor resources to ensure a right mix of external vendors to support multiple IT projects running in parallel, achieve utilization goal and on/offshore work ratio target.\nDefine, monitor and track overall vendor and project performance against SLA and KPIs to ensure value achievement.\n\nPlanning and Budgeting\n\n\nWith strong business acumen, negotiate and liaise with business divisions to define project scope and planning during project initiation phases with clarity on business objectives and outcomes.\nDefine the project timeline for the implementation approaches.\nMonitor the project costs against the budget.\n\nBusiness Advisory\n\n\nHelp customers fully understand the value of the applications to the business. Provide inputs to business proposals to ensure technical contents are covered correctly.\n\nSolution Architecture\n\n\nReview, challenge and contribute to the Solution Architect's proposed solution architecture to ensure the architecture meets the demand of applications.\n\nExperience and qualifications:\n\n\nUniversity degree in Computer Science or related fields.\nMinimum 13 years' experience in IT solution delivery, with at least 5 years' experience in the insurance/financial services field.\n\nSkills\n\n\nExperience in managing teams of technical professionals to evaluate solution on technical suitability, especially implementation and future maintenance, according to business requirements.\nIn-depth understanding of Insurance solution delivery\nIn-depth formal system development experience, preferably in AS400 RPGILE system development, Individual Life products, operations, finance and actuarial functional knowledge.\nSolid experience in large scale project delivery involving multiple teams, applications from both AS400 and non-AS400 platforms, and transition of the application implementation and maintenance to Delivery Centre / Vendor.\nExcellent analytical and problem-solving skills.\nExcellent written and verbal English communication skills.\nWorking experience in Asia countries, with understandings of the country characteristics, cultures and work style, is an advantage", "employment_types": ["Full Time", "Permanent"], "selling_points": ["AS400", "Solution Delivery", "Project Management"], "locations": ["Not Specified"], "categories": ["Information Technology (IT)", "IT Project Management / Team Lead", "Product Management / Business Analyst", "Technical / Functional Consulting"], "post_time": "2022-01-18T02:47:16Z", "salary": {"currency": null, "max": null, "min": null, "period": "monthly", "term": null}, "salary_visible": false, "title_keywords": ["senior manager"], "responsibilities": ["budgeting", "operations", "budget", "quality", "design", "communication", "manage projects", "plan", "liaise with", "costs", "monitor", "teams", "implementation", "develop", "schedule", "kpis", "architecture", "management", "cost", "review", "coordinate with", "contents", "maintenance", "policies", "analysis", "systems", "evaluate", "project management", "insurance", "planning"], "requirements": {"degrees": ["university degree"], "majors": ["computer science"], "languages": ["english"], "language_level": ["excellent"], "hard_skills": ["maintenance", "analysis", "vendor", "project management", "goal", "sla", "deployment", "problem-solving skills", "acumen"], "soft_skills": ["communication skills", "responsible", "project management", "business acumen", "problem-solving skills"], "languages_combined": [{"language": "english", "language_level": ["excellent"]}]}, "experience_required": {"duration": ["minimum 13 years", "at least 5 years"], "field": ["maintenance", "finance", "system development", "business", "it", "financial services", "insurance"]}}, {"job_id": "100003009053843", "location_code": "hk", "company": "LSG Catering Hong Kong Ltd", "job_title": "Assistant Manager IT Network \u2013 Asia Pacific", "description": "Report directly to the Regional Director of IT, APAC, the job holder will be responsible to provide technical support and maintain IT Infrastructure in good condition.\n\n\u00a0Responsibilities:\n\nNetwork support & trouble shooting includes structure cabling, network device and servers.\u00a0\nDesktop support & trouble shooting includes software installation, configuration and setup.\nProvide support & advices in daily system administration and maintain the good condition of IT infrastructure includes WAN, LAN, Server, and Desktop.\nSystem administration on operating system level such as maintenance of user authorization, system configuration, version upgrade, system patching, server / client security and regular system backup and maintenance.\nPerform periodic system performance monitoring includes capacity utilization, system log, software update and preventive maintenance to maintain at 99.99% system availability.\nFollow the standard procedure and to ensure the compliance of corporate standard are maintained at all time.\nMaintain system documentation, testing plan and job scheduling.\nPlan and implement future network/system enhancements and upgrade/migration.\nAssist and support project deployment in the region\n\nRequirements:\n\nDegree holder in Computer Science\nHolding of MCSE and/or MCSA and CCNA certificates\nMinimum 5 years of solid experience in in both IT on-going support, and IT project management\nSolid experience in managing sizable IT infrastructures, helpdesk and end-user support\nPractical experience in Windows, Linux, TCP/IP, VPN, VLAN, WAN, Active Directory, IPT, Switch configuration, VM, Firewall, Proxy, and ITIL best practices, etc.\nExcellent analytical, problem-solving, strong communication and interpersonal skills\nProactive and service oriented, self-motivated, able to work independently and under pressure, open-minded to work in multi-cultural environment\nEffective vendor management and contract negotiation skills\nExcellent in written and spoken English and Chinese\nCandidate with less experience will be considered as Senior Network Administrator\n\nWe offer an attractive remuneration package in commensurate with the qualifications and experience to the right candidate. Interested parties please apply with full resume, present and expected salaries and availability by clicking \"Apply Now\".\n\nAll applications received will be used exclusively for employment purpose only. Applications not invited for interview within 6 weeks may consider their applications unsuccessful.\n\nFor more details, please visit our Website\u00a0https://www.lsgskychefs.com\n", "employment_types": ["Full Time", "Permanent"], "selling_points": [], "locations": ["Airport Area"], "categories": ["Information Technology (IT)", "IT Project Management / Team Lead", "Application Specialist - Network", "Network & System"], "post_time": "2022-01-17T07:36:34Z", "salary": {"currency": null, "max": null, "min": null, "period": "monthly", "term": null}, "salary_visible": false, "title_keywords": ["assistant manager"], "responsibilities": ["installation", "provide support", "software", "it infrastructure", "maintenance", "configuration", "system documentation", "monitoring", "compliance", "testing", "scheduling", "maintain", "plan", "migration", "setup", "administration"], "requirements": {"degrees": ["degree holder"], "majors": ["computer science"], "languages": ["english", "chinese"], "language_level": ["excellent"], "hard_skills": ["itil", "mcse", "linux", "firewall", "active directory", "tcp", "switch", "problem-solving", "ccna", "vendor", "project management", "ip", "vpn", "mcsa", "wan"], "soft_skills": ["self-motivated", "proactive", "work independently", "under pressure", "open-minded", "problem-solving", "project management", "negotiation skills", "communication and interpersonal skills", "active"], "languages_combined": [{"language": "english", "language_level": ["excellent"]}, {"language": "chinese", "language_level": ["excellent"]}]}, "experience_required": {"duration": ["minimum 5 years"], "field": ["project management", "it"]}}, {"job_id": "100003009055935", "location_code": "hk", "company": "Crystal International Group Limited", "job_title": "Manager - Finance System", "description": "Responsibilities:\n\nParticipate in SAP S/4HANA migration project planning and deployment\nFormulate user guideline and provide training; monitor the system control, governance and compliance\nLead finance system transformation and process reengineering for the Group\nSupport ad hoc projects as assigned\n\nRequirements:\n\nDegree holder in IT / Computer Science, Finance / Accounting or related discipline\nMinimum 5 years of experience in implementing SAP FICO, SAP certification in FICO will be an advantage, preferably with S/4HANA and manufacturing experience\nSound knowledge in finance operation and understanding of finance, taxation and accounting principles\nLogical, systematic with good presentation skill; Proficiency in MS Excel and PowerPoint\nStrong sense of responsibility and able to prioritize and work under pressure\nProficient in written and spoken English and Chinese including Mandarin\nWilling to take up ad hoc tasks and travel", "employment_types": ["Full Time"], "selling_points": ["Degree holder in IT / Computer Science, Finance / Accounting or related discipline", "Minimum 5 years of experience in implementing SAP FICO", "Double Pay & Discretionary Bonus"], "locations": ["Kwun Tong"], "categories": ["Information Technology (IT)", "Application Specialist - Software", "IT Project Management / Team Lead", "IT Management"], "post_time": "2022-01-18T03:06:18Z", "salary": {"currency": null, "max": null, "min": null, "period": "monthly", "term": null}, "salary_visible": false, "title_keywords": ["manager"], "responsibilities": ["provide training", "project planning", "control", "compliance", "monitor", "ad hoc projects", "migration"], "requirements": {"degrees": ["degree holder"], "majors": ["finance", "it", "accounting", "computer science"], "languages": ["english", "chinese", "mandarin"], "language_level": ["proficient"], "hard_skills": ["presentation skill", "ms excel", "sap", "powerpoint"], "soft_skills": ["presentation skill", "able to prioritize", "sense of responsibility", "systematic", "work under pressure"], "languages_combined": [{"language": "english", "language_level": ["proficient"]}, {"language": "chinese", "language_level": ["proficient"]}, {"language": "mandarin", "language_level": ["proficient"]}]}, "experience_required": {"duration": ["minimum 5 years"], "field": ["manufacturing"]}}, {"job_id": "100003009054742", "location_code": "hk", "company": "Public Finance Limited", "job_title": "Assistant Manager, Applications Development", "description": "Responsibilities\nAssist the Department Head to oversee the Applications Development team for performing functions such as application development, database design and support, etc.\nSupervise the team members in analyzing user requirements, conducting system design and programming, implementing system enhancements, and preparing system documentations\nLead and manage various projects\nRequirements\nUniversity degree or above in Computer Science or related disciplines\nAt least 8 years experience in applications development of which minimum 3 years in managerial role preferably gained in banking and finance industry\nBe proficient in database design and project management\nResult-oriented, self-motivated, strong leadership, good communication and interpersonal skills\nAble to work independently and well under pressure\nBenefits\nDouble Pay\nDiscretionary Bonus\nInsurance Benefits\nStudy Subsidy\nApplication Method:\nBy E-mail via \"Apply Now\"", "employment_types": ["Full Time", "Permanent"], "selling_points": [], "locations": ["Not Specified"], "categories": ["Information Technology (IT)", "IT Project Management / Team Lead", "Software Development", "Network & System"], "post_time": "2022-01-17T10:51:31Z", "salary": {"currency": null, "max": null, "min": null, "period": "monthly", "term": null}, "salary_visible": false, "title_keywords": ["assistant manager,"], "responsibilities": ["application development", "system design", "database", "design"], "requirements": {"degrees": ["degree or above"], "majors": ["related disciplines", "computer science"], "languages": [], "language_level": [], "hard_skills": ["project management"], "soft_skills": ["self-motivated", "work independently", "under pressure", "project management", "communication and interpersonal skills", "leadership", "result-oriented"], "languages_combined": []}, "experience_required": {"duration": ["at least 8 years", "minimum 3 years"], "field": ["development", "managerial", "finance industry", "banking"]}}, {"job_id": "100003009052287", "location_code": "hk", "company": "PwC", "job_title": "Manager / Senior Associate - Tax Technology - PwC Tax - Hong Kong", "description": "About Tax\n\nTax and regulatory issues are on top of the mind for many companies operating around the world today. As a tax professional, you will help organisations and individuals maximise their tax efficiency and manage their tax risks. You achieve this through the advice you give your clients on how to conduct proper tax planning, and helping your clients to fully meet their tax compliance obligations.\n\nTaxation in a fast-paced business environment is exciting and intellectually stimulating. In order for you to face up to the challenges, you will need to constantly develop your tax knowledge and research skills. As you progress, you will likely become specialised in certain tax speciality area and particular industries.\n\nAbout Tax Technology Team\n\nThe Tax Technology team is responsible for all technology based business solutions for the Tax division in the China and Hong Kong region. Moreover, the team serves as a contact point and liaison for other territories within as well as outside the Asia-Pacific region in relation to tax technology. We work closely with both the tax professionals and IT specialists within the Firm to support the systems life cycle of concurrent tax technology projects so as to deliver best-in-class technology-based business solutions.\n\nJob description and responsibilities:\n\nUnderstand business and client needs and derive business requirements, functional design, and process design\nPerform systems and/or proposal comparisons, analysis, and evaluations with engagement team\nAssist in analysing business processes, identifying potential automation opportunities and creating Process Description Document, and Solution Design Document\nAssist in planning and tracking projects tasks and timeline\nPerform testing and handle related issues during development and implementation of software projects\nCollect feedback and monitor on software projects after launch\n\nRequirements:\n\nGreat written and verbal communications skills in both English and Chinese\nAbility to work well and communicate effectively with other professionals\nProficiency in ASP, .NET ,C# , JAVA or any kind of programming language\nFunctional knowledge of SQL and object-oriented programmingcoding methodologies\nDemonstrate understanding of different software development life-cycle methodologies\nStrong organizational and analytical skills to research, compile and clearly present information and data\nMust be proficient in Word, Excel and PowerPoint\nAbility to function well in a fast-paced, dynamic environment with competing priorities and tight deadlines\nHands-on experience with system design, implementation and quality assurance is a plus\nBSc / BEng in Computer Science, Math, Physics or Engineering is preferred\nJunior candidates will be considered as Associate", "employment_types": ["Full Time", "Permanent"], "selling_points": ["Technology Based Business Solutions for Tax", "Fast-paced and Intellectually Stimulating", "ASP NET C# JAVA"], "locations": ["Central"], "categories": ["Accounting", "Taxation", "Information Technology (IT)", "IT Project Management / Team Lead", "Software Development"], "post_time": "2022-01-17T02:39:03Z", "salary": {"currency": null, "max": null, "min": null, "period": "monthly", "term": null}, "salary_visible": false, "title_keywords": ["senior associate", "manager"], "responsibilities": ["software", "analysis", "systems", "monitor", "implementation", "design", "testing", "planning", "tracking"], "requirements": {"degrees": ["bsc"], "majors": ["math", "engineering", "computer science", "physics"], "languages": ["english", "chinese"], "language_level": [], "hard_skills": ["excel", "java", "plus", "word", "powerpoint", "analytical skills", "sql", "dynamic", "system design", "programming", "math", "c#"], "soft_skills": ["organizational", "dynamic environment", "hands-on", "analytical skills"], "languages_combined": [{"language": "english", "language_level": []}, {"language": "chinese", "language_level": []}]}, "experience_required": {"duration": [], "field": ["system design", "quality assurance"]}}, {"job_id": "100003008977003", "location_code": "hk", "company": "IT Consulting Solutions Limited", "job_title": "IT Project Assistant / Administrator / Junior Business Analyst", "description": "Responsibilities:\u00a0\n\nProvide assistance and administrative support to IT projects\nCoordinate internal users and external vendors for project arrangement\nCoordinate and participate in team meetings, prepare and/or edit meeting minutes, presentations and reports\nEnsure coordination of the interfaces between clients and project / delivery team\nMinutes-taking, reporting and documentation\nPerform admin and ad hoc tasks as required\n\n\u00a0Requirements:\n\nAt least 2 years related working experience\nExcellent analytical, interpersonal and communication skills\nGood command in both spoken and written English and Chinese\nExperience working with Microsoft Office (Excel, Word and PowerPoint)\nIT knowledge is a plus", "employment_types": ["Contract"], "selling_points": ["World's leading insurance company", "Stable work hours: 9AM-6PM; MON-FRI", "Pathway to become a Business Analyst"], "locations": ["Aberdeen"], "categories": ["Admin & HR", "Administration / Operation Manager", "Information Technology (IT)", "IT Project Management / Team Lead", "Product Management / Business Analyst"], "post_time": "2022-01-17T14:38:52Z", "salary": {"currency": null, "max": null, "min": null, "period": "monthly", "term": null}, "salary_visible": false, "title_keywords": ["business analyst", "administrator", "junior", "project assistant"], "responsibilities": ["reporting", "administrative support", "ad hoc tasks", "presentations", "coordinate", "reports", "coordination", "documentation", "provide assistance"], "requirements": {"degrees": [], "majors": [], "languages": ["english", "chinese"], "language_level": ["good command"], "hard_skills": ["excel", "plus", "it knowledge", "microsoft office", "word", "powerpoint"], "soft_skills": ["communication skills", "interpersonal"], "languages_combined": [{"language": "english", "language_level": ["good command"]}, {"language": "chinese", "language_level": ["good command"]}]}, "experience_required": {"duration": ["at least 2 years"], "field": ["related"]}}, {"job_id": "100003009055811", "location_code": "hk", "company": "Randstad Hong Kong Limited", "job_title": "Business Analyst Manager (Insurance)", "description": "\nabout the company.\n\nA leading global insurer with presence in 54 markets and serving 105 million customers worldwide.\nabout the job.\nYou will provide business analysis supports on all projects under the Department\nResponsible for preparing business requirements and translate to IT specifications\nEnsure the specifications are align with the final system design and/or work flow\nTake lead on the change management activities e.g workshops, training to understand business concerns and manage user expectations\nWork with various stakeholders to deliver the best solution; including IT vendor, Internal departments, IT, Operations, Marketing, Product, Legal & Compliance, Finance\nLead, plan and execute user acceptance testings\nPrepare data tracking report to evaluate the implementation outcome\nskills & experiences required.\nBachelor degree or above in information technology, business administration, financial engineering related disciplines or other relevant qualifications\nAt least 5 years Project Management experience in insurance industry\nSolid Business analysis skills, stakeholder management skills, change management skills\nStrong presentation and problem solving skills; Multi-tasking skills is necessary\nShort notice will be a plus\n\nInterested parties, please click \"Apply Now\" or contact Cheryl Lau at cheryl.lau@randstad.com.hk", "employment_types": ["Full Time", "Permanent"], "selling_points": ["Leading global insurance company", "Stakeholder management, change management", "At least 5 years relevant experience"], "locations": ["Not Specified"], "categories": ["Information Technology (IT)", "IT Project Management / Team Lead", "IT Management", "Product Management / Business Analyst"], "post_time": "2022-01-18T02:58:22Z", "salary": {"currency": "HKD", "max": 54999, "min": 35000, "period": "monthly", "term": null}, "salary_visible": true, "title_keywords": ["manager", "business analyst"], "responsibilities": ["administration", "management", "change management", "data", "operations", "compliance", "implementation", "evaluate", "project management", "specifications", "system design", "plan", "business analysis", "report", "insurance", "tracking"], "requirements": {"degrees": ["degree or above", "bachelor"], "majors": ["related disciplines", "business administration", "engineering", "information technology"], "languages": [], "language_level": [], "hard_skills": ["plus", "analysis", "vendor", "project management", "system design", "workshops", "problem solving skills"], "soft_skills": ["responsible", "project management", "multi-tasking skills", "problem solving skills", "presentation"], "languages_combined": []}, "experience_required": {"duration": ["at least 5 years"], "field": ["project management", "insurance industry"]}}, {"job_id": "100003009047973", "location_code": "hk", "company": "Convoy Global Holdings Limited", "job_title": "IT Project Manager (Healthcare)", "description": "OnePlatform, a technology-enabled financial B2B platform, provides all-around services and integrates a full range of financial products. Our mission is to accelerate the business growth of our B2B partners and unleash their potentials at ease.\n\nWe\u2019re building an amazing team in Hong Kong and we\u2019re looking for an ambitious and purpose-driven Project Manager to jump on board. You will be intellectually curious, resourceful and enthusiastic, and hungry for a new challenge in a fast-paced and forward-thinking environment.\n\nResponsibilities:\n\nServe as the primary project manager, facilitator and coordinator of Healthcare related\u00a0projects\nDrive digital transformation and business process reengineering projects\nDesign solution and develop work plans for projects, identifies resource requirements\nConduct feasibility studies and draft proposals for evaluation and planning\nReview IT development documents to ensure alignment of understanding between users and IT team\nFacilitate and negotiate buy-in from key stakeholders to obtain the best outcome for the company and to ensure smooth implementation and change.\nKeep track and monitor the progress of projects to meet negotiated and targeted deadlines and deliverables.\nPerform system testing to ensure project delivery quality\n\nRequirements:\n\nDegree or above in Computer science or Information Technology or other related discipline\nMinimum 6 to 8 years experience on IT Project Management, solution design, system analysis. Preferably in the medical/ healthcare industry\nAbility to analyze, communicate, articulate governance and compliance trends and program requirement\nAbility to work effectively with all levels of personnel across the organization\nEffective interpersonal skills with a clear, concise and relevant communication style, including excellent presentation skills.\nGood command of spoken and written English and Chinese and excellent report writing skills\nProficiency in MS Word, Excel, PowerPoint, and project management tools\nWe offer competitive remuneration including career prospects to the right candidate. Interested parties please send detailed resume with availability, current and expected salaries to\u00a0Human Resources Department\u00a0by clicking the\u00a0Apply Now\u00a0button and upload your CV and cover letter.\n(All applications will be treated in strict confidence and used for recruitment purpose within Convoy Global Holdings Limited only. All applicants are kept on file 6 months from the date of the application.)", "employment_types": ["Full Time", "Permanent"], "selling_points": ["Drive digital transformation", "Conduct feasibility studies and draft proposals", "Review IT development documents"], "locations": ["Wan Chai"], "categories": ["Information Technology (IT)", "IT Project Management / Team Lead", "Product Management / Business Analyst", "Network & System"], "post_time": "2022-01-14T04:24:23Z", "salary": {"currency": null, "max": null, "min": null, "period": "monthly", "term": null}, "salary_visible": false, "title_keywords": ["it project manager"], "responsibilities": ["review", "monitor", "implementation", "design", "develop", "testing", "quality", "business process", "evaluation", "plans", "planning"], "requirements": {"degrees": ["degree or above"], "majors": ["computer science", "information technology"], "languages": ["english", "chinese"], "language_level": ["excellent", "good command"], "hard_skills": ["excel", "analysis", "writing skills", "powerpoint", "project management", "ms word"], "soft_skills": ["work effectively", "writing skills", "ability to analyze", "project management", "clear", "communication", "interpersonal skills", "presentation skills", "articulate"], "languages_combined": [{"language": "english", "language_level": ["excellent", "good command"]}, {"language": "chinese", "language_level": ["excellent", "good command"]}]}, "experience_required": {"duration": ["minimum 6 to 8 years"], "field": ["project management", "it", "design"]}}, {"job_id": "100003009056219", "location_code": "hk", "company": "Hays", "job_title": "Manager, Project Management (1 year contract), 50k", "description": "A local leading financial services group is looking for IT Project Manager to join the team\n\nYour new company\nA local leading financial services group is looking for a caliber to lead core banking projects in business analysis department\n\nYour new role\nYou will be primarily responsible for planning and execution of business related implementation activities prior to new system launch reporting to the Business Analysis Lead of Core Banking Project.\n\nWhat you'll need to succeed\n\nPlay a leading role in ensuring new system functions fulfils user requirements\nDevelop requirement definition, changes in business processes/ workflows, solution design and forms design\nLead, drive and plan key activities, such as user training, dress rehearsal, simulation run, system cutover, user communication throughout SDLC prior to system implementation\nAbility to coordinate and control a wide range of activities and make decisions independently\nAt least 7 years' working experience in business analysis and system implementation with at least 3 years banking exposure\n\n\n\nWhat you'll get in return\n\nExtendable contract if perform well\nHigh interest account opening (up to 10%)\nOpportunities to work on multiple new tech projects\n\n\nWhat you need to do now\nIf you're interested in this role, click 'apply now' to forward an up-to-date copy of your CV, or call us now.\nIf this job isn't quite right for you but you are looking for a new position, please contact us for a confidential discussion on your career.", "employment_types": ["Full Time", "Permanent"], "selling_points": ["High interest rate account opening", "stability", "competitive compensation packages"], "locations": ["Not Specified"], "categories": ["Information Technology (IT)", "IT Project Management / Team Lead"], "post_time": "2022-01-18T03:36:21Z", "salary": {"currency": null, "max": null, "min": null, "period": "monthly", "term": null}, "salary_visible": false, "title_keywords": ["manager"], "responsibilities": ["reporting", "control", "account opening", "implementation", "design", "develop", "communication", "coordinate", "contact", "plan", "banking", "business analysis", "planning"], "requirements": {"degrees": [], "majors": [], "languages": [], "language_level": [], "hard_skills": ["account opening", "analysis", "make", "sdlc", "system implementation"], "soft_skills": ["communication", "independently", "interested in", "responsible"], "languages_combined": []}, "experience_required": {"duration": ["at least 3 years", "at least 7 years"], "field": ["business analysis", "banking"]}}, {"job_id": "100003009055394", "location_code": "hk", "company": "Dah Sing Financial Group", "job_title": "Project Assistant, Testing (12 months Contract)", "description": "Summary:\nYou will be responsible to manage and support on User Acceptance Test (UAT) for the rollout of Core Banking System and assist in designing UAT test cases and performing UAT testing according to the pre-defined test cases.\nKey Role and Responsibilities: \u00a0\nAssist in project management in terms of User Acceptance Testing (UAT) planning, UAT co-ordination, UAT environment setup, UAT test cases preparation and execution\nDesign test scenarios and test case based on business requirement, functional requirement specification (FRS), test plan and ensure comprehensive coverage of test cases\nManage execution of test case manually or using automated testing tools\nCompile test result to respective handling staff assigned by project team for upload to defect management system and monitor the defect fixing progress\nMonitor UAT schedule and progress and support the rollout of bank Teller systems\nUnderstand the limitations and issues of existing testing processes and recommend improvement initiatives\nProvide guidance and coaching to junior UAT tester of the team\nJob Requirements:\nMatriculated or degree holder\nAround 1 - 3 working experiences, preferably in IT/ Banking sectors\nExperience in performing testing of banking systems\nProduct Knowledge on Retail Banking / Corporate Banking is essential\nSelf-initiative, able to work independently and under pressure, and meet tight deadline\nMeticulous and well organized\nExcellent communication and interpersonal skills\nGood command of both written and spoken English and Chinese\nPlease note that only shortlisted candidates will be notified.", "employment_types": ["Contract"], "selling_points": ["Manage execution of test case manually", "Matriculated or degree holder", "Around 1 - 3 working experiences"], "locations": ["North Point"], "categories": ["Information Technology (IT)", "IT Project Management / Team Lead", "Testing / QA", "Network & System"], "post_time": "2022-01-18T02:27:06Z", "salary": {"currency": null, "max": null, "min": null, "period": "monthly", "term": null}, "salary_visible": false, "title_keywords": ["project assistant"], "responsibilities": ["management", "uat", "systems", "monitor", "design", "testing", "project management", "schedule", "plan", "provide guidance", "setup", "planning"], "requirements": {"degrees": ["degree holder"], "majors": [], "languages": ["english", "chinese"], "language_level": ["good command"], "hard_skills": [], "soft_skills": ["meticulous", "work independently", "under pressure", "well organized", "communication and interpersonal skills", "self-initiative", "meet tight deadline"], "languages_combined": [{"language": "english", "language_level": ["good command"]}, {"language": "chinese", "language_level": ["good command"]}]}, "experience_required": {"duration": [], "field": ["testing", "it", "banking"]}}, {"job_id": "100003009055254", "location_code": "hk", "company": "Accenture Company Limited", "job_title": "Strategy & Consulting - Insurance Consulting Manager", "description": "Your Role:\nThere will never be a typical day at Accenture, but that\u2019s why people love it here. The opportunities to make a difference within exciting client initiatives are limitless in this ever-changing business landscape.\n\nKey Responsibilities:\n\nLead a project delivery team to solve client\u2019s burning issues and help clients to achieve new performance highs.\nProvide intellectual leadership for the team and ensure that the project is delivered on time and within budget, harnessing the team's diversity to ensure the development of creative solutions to complex problems.\nDemonstrate strong analytical capabilities and apply knowledge of selected tools and techniques, drawing logical conclusions\nDevelop expertise in customer insight & growth experience practice areas to increase the breadth and depth of our knowledge base and capabilities\nManage work-streams/project delivery on time with the appropriate use of resources, working within and lead Accenture and/or Client teams\nManage and develop junior team members on the project by providing coaching, mentoring and regular feedback\nExperience, Attributes and Qualifications:\n\nUniversity Degree from reputable university, MBA preferred.\nMinimum 6 years of working experience with insurance clients or insurance companies, and experience working with workflow / business process management solutions.\nKnowledge in Insurance Products/Process and Insurance Core System\nKnowledge in project management (Waterfall/Agile Scrum)\uff0cLean Six Sigma qualification is a plus\nExperience in end-to-end Insurance or retirement operating model design, business process design initiatives\nExperience in business process re-engineering\n\u00a0Able to lead and drive project delivery independently, willing to mentor junior team members\nStrong stakeholder management with business/IT stakeholders and subject matter experts, able to create and deliver high-impact communication to senior audiences (written and oral in English, Mandarin and Cantonese)", "employment_types": ["Full Time"], "selling_points": ["Management Consulting", "Insurance Core System", "Digital Transformation"], "locations": ["Quarry Bay"], "categories": ["Professional Services", "Business Consultancy", "Information Technology (IT)", "IT Project Management / Team Lead"], "post_time": "2022-01-18T01:55:31Z", "salary": {"currency": null, "max": null, "min": null, "period": "monthly", "term": null}, "salary_visible": false, "title_keywords": ["manager"], "responsibilities": ["management", "budget", "teams", "design", "develop", "business process re-engineering", "project management", "communication", "business process", "insurance"], "requirements": {"degrees": ["university degree"], "majors": [], "languages": ["cantonese", "english", "mandarin"], "language_level": [], "hard_skills": ["plus", "agile", "make", "six sigma", "project management"], "soft_skills": ["oral", "independently", "agile", "communication", "project management", "creative", "leadership"], "languages_combined": [{"language": "cantonese", "language_level": []}, {"language": "english", "language_level": []}, {"language": "mandarin", "language_level": []}]}, "experience_required": {"duration": ["minimum 6 years"], "field": ["management", "engineering", "design", "business", "insurance"]}}, {"job_id": "100003009055696", "location_code": "hk", "company": "Tata Consultancy Services Limited", "job_title": "Test Lead", "description": "Objective of the role:\n\nLead the digital quality assurance for the entire project.\nImplement automated testing services for digital platforms that will improve service quality and speed of delivery.\nImplement processes, procedures and measures that ensures performance, resilience and quality objectives are met.\nImplement a roadmap for continual improvement for testing and quality assurance.\u00a0\n\n\u00a0Roles and Responsibilities:\n\nMaintain and improve digital solution testing delivery.\nBe a contact and escalation point for testing and release issues.\nImplement and maintain testing standards and automation procedures for digital platforms.\u00a0\nEngage with Release and Change Management teams for effective change delivery into the group digital platform production platform\nEngage with development teams to embed Agile best practices for the release of quality deliverables.\u00a0\nProvide quality assurance reporting and setting of continual improvement goals.\u00a0\nImplement and manage industry standard toolsets to improve quality and speed of delivery.\nGreat communicator that can bridge communications gaps between culturally diverse vendor(s) and internal stakeholders", "employment_types": ["Full Time", "Permanent"], "selling_points": ["Maintain and improve digital solution testing.", "Provide quality assurance reporting", "Lead the digital quality assurance"], "locations": ["Others"], "categories": ["Information Technology (IT)", "IT Project Management / Team Lead"], "post_time": "2022-01-18T02:51:40Z", "salary": {"currency": null, "max": null, "min": null, "period": "monthly", "term": null}, "salary_visible": false, "title_keywords": ["lead"], "responsibilities": ["reporting", "change management", "quality", "procedures", "teams", "testing", "digital platform", "maintain", "contact"], "requirements": {"degrees": [], "majors": [], "languages": [], "language_level": [], "hard_skills": ["agile"], "soft_skills": ["diverse", "communicator", "agile"], "languages_combined": []}, "experience_required": {"duration": [], "field": []}}, {"job_id": "100003009054789", "location_code": "hk", "company": "The Education University of Hong Kong", "job_title": "Computer Officer (User Services \u2013 User Support) (Ref: 2200009)", "description": "Office of the Chief Information Officer\n\nThe Office of the Chief Information Officer (OCIO) has a vision to be a world-class provider of information and communications technology services and solutions to support and enhance teaching, learning, research and administration of the University.\n\nThe OCIO provides quality services to support all central information systems in support of teaching, learning, research and administration. It places emphasis on staff\u2019s career/professional development. The Office is looking for quality professionals to fill the vacancy of Computer Officer\n\nThe appointee will be responsible for supervising a team of technical staff to provide quality IT support services, including on-site and telephone services; answering enquiries through the IT Help Desk email account; coordinating and conducting IT services orientation workshops for new students. He/she has to assist the IT Manager in planning, budgeting and tendering computing resources for all departments and teaching venues; as well as maintaining an accurate and up-to-date inventory record of computing equipment for the University.\n\nApplicants should have a recognized Bachelor\u2019s Degree in Computer Science/Information Technology or related disciplines, with at least 7 years of relevant full-time post-qualification working experience gained in a sizeable IT environment. They should have supervisory experience and in-depth knowledge in support of PC, Microsoft Windows and Macintosh systems. Applicants should have good problem-solving, analytical and interpersonal skills; and be proficient in both English and Chinese with good communication skills. They should also work proactively and independently; be able to handle multiple tasks simultaneously and be a good team player.\n\nSalary will be commensurate with qualifications and experience.\n\nInitial appointment will be made on a fixed-term contract.\u00a0Fringe benefits include contract-end gratuity, leave, medical and dental benefits.\n\nThe University only accepts and considers applications submitted online for this post.\u00a0 Applicants should complete the online application form and upload a full CV.\u00a0 Review of applications will start from 28 January 2022, and will continue until the post is filled.\u00a0 Applications which are incomplete or without the required documents may not be considered. \u00a0Personal data provided by applicants will be used for recruitment and other employment-related purposes. \u00a0For details of the Personal Information Collection Statement, please refer to http://www.eduhk.hk/jobsopp/index.php?glang=en.\n\nAll applications will be treated in strict confidence.\u00a0 Only those who are shortlisted will be contacted.\u00a0 The University reserves the right not to fill the position(s) advertised.\u00a0 \u00a0\u00a0\n\nFurther information about the University is available at http://www.eduhk.hk.\n\nEdUHK is an Equal Opportunities Employer.", "employment_types": ["Full Time"], "selling_points": [], "locations": ["Not Specified"], "categories": ["Information Technology (IT)", "IT Project Management / Team Lead", "Support", "Others"], "post_time": "2022-01-17T11:05:34Z", "salary": {"currency": null, "max": null, "min": null, "period": "monthly", "term": null}, "salary_visible": false, "title_keywords": ["officer"], "responsibilities": ["supervising", "maintaining", "budgeting", "support services", "systems", "quality", "tendering", "inventory record", "communication", "planning", "administration"], "requirements": {"degrees": ["degree", "bachelor"], "majors": ["related disciplines", "it", "computer science", "information technology"], "languages": ["english", "chinese"], "language_level": ["good", "proficient"], "hard_skills": ["workshops", "pc", "problem-solving"], "soft_skills": ["communication skills", "good team player", "independently", "responsible", "problem-solving", "handle multiple tasks", "learning", "interpersonal skills", "accurate", "world-class"], "languages_combined": [{"language": "english", "language_level": ["proficient", "good"]}, {"language": "chinese", "language_level": ["proficient", "good"]}]}, "experience_required": {"duration": ["at least 7 years"], "field": ["post-qualification", "related", "information technology", "it", "supervisory experience"]}}, {"job_id": "100003009046848", "location_code": "hk", "company": "Nexify Limited", "job_title": "Project Manager - IT Project", "description": "Nexify Limited is one of the leading IT solution providers specialized in system integration in Hong Kong. We encourage innovation, teamwork and personal growth. With continuous business expansion, we need high calibre candidates to join our professional team and we offer exciting job opportunities to the right talents. If you want to work in a fun and energetic environment, please do not hesitate to apply!\n\n\nJob Description\n\n\nDeliver projects within budget and time\nPlan and control all phases of IT project including feasibility study, systems analysis and design, procurement and installation of computer systems, programming, implementation, system nursing and maintenance\nSchedule and assign duties to subordinates\nEstablish procedures and performance measurements to monitor the technical accomplishment and progress of projects\nDevelop project management plans and quality control parameters\nOther duties as assigned\u00a0\n\n\u00a0Job Requirements\n\nDegree holder in Computer Science, Information Systems or related disciplines\nAt least\u00a08\u00a0years of post-qualification IT experience including at least\u00a04\u00a0years of project management experience in system design and implementation and/or system maintenance and support of IT systems\nBe a certified Project Management Professional (PMP) and/or a certified PRINCE2 practitioner\nSelf-motivated and able to work under pressure to meet project deadlines\nProficient in written and spoken English and Chinese\nPossessing work experiences for the HKSARG would be an advantage\n\nBenefits:\n\n5-Day Work Week\nPerformance bonus\nMarriage Leave\nPaternity Leave\nBirthday Leave\nMedical allowance\nCompassionate Leave\nExamination Leave\nPromotion opportunities\nIn-service training course\n\nWe offer 5-day work with good career prospects and excellent fringe benefits to the right candidates. Different areas of IT solution training (Such as Microsoft, IBM, Oracle or Mobile Application Development) will be provided. \u00a0Please send a full resume in MS Word Format including current and expected salary by clicking \"Apply Now\".", "employment_types": ["Full Time", "Permanent"], "selling_points": ["Plan and control all phases of IT project", "Certified PMP / PRINCE2 practitioner", "Attractive remuneration package & 5 days work"], "locations": ["Kwun Tong"], "categories": ["Information Technology (IT)", "IT Project Management / Team Lead", "IT Management", "Software Development"], "post_time": "2022-01-14T01:27:50Z", "salary": {"currency": null, "max": null, "min": null, "period": "monthly", "term": null}, "salary_visible": false, "title_keywords": ["project manager"], "responsibilities": ["installation", "control", "maintenance", "other duties", "analysis", "budget", "systems", "computer systems", "design", "implementation", "procedures", "monitor", "develop", "project management", "schedule", "plan", "quality control", "plans"], "requirements": {"degrees": ["degree holder"], "majors": ["related disciplines", "computer science"], "languages": ["english", "chinese"], "language_level": ["proficient"], "hard_skills": ["maintenance", "project management professional", "project management", "system design", "pmp"], "soft_skills": ["project management", "self-motivated", "work under pressure"], "languages_combined": [{"language": "english", "language_level": ["proficient"]}, {"language": "chinese", "language_level": ["proficient"]}]}, "experience_required": {"duration": ["at least 8 years", "at least 4 years"], "field": ["post-qualification", "maintenance", "it experience", "project management", "system design", "it"]}}, {"job_id": "100003009048950", "location_code": "hk", "company": "Heep Hong Society", "job_title": "Manager, Project Management Office", "description": "Responsibilities:\n\nAlign & maintain the projects portfolio priorities & strategic visions with the senior management team\nAct as project manager for specifically attributed projects\nSupport departments with project management resources, methodologies, reports\nCreate, manage and execute the project schedules across the function, including defining the required steps to achieve project objectives, the required resources and work allocation, and the management of dependencies to ensure delivery within agreed time frames\nDevelop and draft change management and communication plans, messaging, and supporting documentation to help drive transformation in the business\nRisk and issue management, with a strong focus on the identification, analysis, response and escalation of key project risks; communicate risk effectively in order to protect project schedule\nCommunicate with business leaders to manage multiple demands, identify and resolve conflicting issues\n\nRequirements:\n\nUniversity graduate in Computer Science, Information Technology / Information System or a related discipline\nAt least 10+ years\u2019 solid experience in project management and vendor management\nExperience in leading large scale projects. Team leading experience\nHolder of Project Management Professional (PMP) and/or Scrum Master would be an advantage\nProficient in SDLC project management execution and business analysis experience\nPrevious experience in setting up PMO is an advantage\nExperience on PM Tools (e.g. Teamworks, JIRA) and Data Analytics tools (e.g. PowerBI, Qlik) is an advantage\nCustomer-oriented and self-motivated with excellent communication skill\nSelf-manage, proactive, independent, efficient, able to work under pressure in vague and fast growing environment\nGood communication and problem solving skills\nGreat sense of ownership and servicing mindset to ensure successful project implementation\nAttentive and willing to work under tight schedule and multi-task\nPossess a \u201ccan-do\u201d attitude\nGood command of both written and spoken English and Chinese\n\nPlease click\u00a0\u201cApply Now\u201d\u00a0to apply for this position or\u00a0send full resume with expected salary and earliest available date to\u00a0WhatsApp: 6875 0346.\n\n(Personal data collected will be used for recruitment purpose only)", "employment_types": ["Full Time"], "selling_points": ["Analyse & manage proj. priorities, strategy, risk", "Deg. in Computer Science, IT/Information System", "Min. 10+ yrs' exp. in project & vendor management"], "locations": ["Ngau Tau Kok"], "categories": ["Information Technology (IT)", "IT Project Management / Team Lead", "IT Management", "Security"], "post_time": "2022-01-14T11:33:15Z", "salary": {"currency": null, "max": null, "min": null, "period": "monthly", "term": null}, "salary_visible": false, "title_keywords": ["manager"], "responsibilities": ["communicate with", "management", "change management", "schedules", "analysis", "develop", "communication", "project management", "maintain", "reports", "schedule", "documentation", "plans", "senior management"], "requirements": {"degrees": ["university graduate", "master"], "majors": ["project management", "computer science", "information technology"], "languages": ["english", "chinese"], "language_level": ["good command"], "hard_skills": ["project management professional", "data analytics", "analysis", "information system", "vendor", "project management", "sdlc", "problem solving skills", "whatsapp", "pmp"], "soft_skills": ["efficient", "attentive", "self-motivated", "independent", "multi-task", "communication skill", "communication", "project management", "customer-oriented", "can-do", "problem solving skills", "proactive", "work under pressure"], "languages_combined": [{"language": "english", "language_level": ["good command"]}, {"language": "chinese", "language_level": ["good command"]}]}, "experience_required": {"duration": ["at least 10+ years"], "field": ["business analysis", "project management", "management", "team"]}}, {"job_id": "100003009051336", "location_code": "hk", "company": "Maxim's Caterers Ltd", "job_title": "Assistant Manager, Digital Projects (Project Management)", "description": "Responsibilities\nBe responsible for Digital projects and manage overall projects implementation. Report project status to management on regular base.\nManage vendors to ensure quality in deliverables of products and services on time.\nCoordinate with stakeholders and manage expectations.\nConsolidate and analyze requirements to propose feasible and practical solution(s), and corresponding Requirements and Design are required to be documented.\nRequirement collection, project planning, scheduling, vendor management, SIT, UAT and launch planning.\nPrepare training material and provide end user training.\nResource planning and communicate with various internal teams and cope with a fast-paced environment.\nRequirements\nUniversity in Information Technology, Computer Science, E-commerce, or related disciplines\nAt least 6 years of experience in project management, digital/ eCommerce system and application projects\nStrong communication, negotiation, and interpersonal skills.\nStrong analytical and problem-solving skills.\nExperience in Retail/ Digital solution related; such as Mobile App, E-commerce, CRM Applications and Web development.\nStrong knowledge in SEO and Analytics.\nAbility to conduct technical feasibility study for new ideas and digital projects.\nSelf-motivated, detail-oriented, able to manage multiple projects under pressure with tight deadlines.\nGood command in spoken and written English.\nExperience in F&B industry will be a plus.\nKnowledge in technical development will be a plus.\nExperience working in digital agency or SI vendor will be a plus.\nExperience in Regional role will be a plus but not mandatory.\nInterested parties please apply with full resume, state current and expected salaries by clicking \"Apply Now\". All applications and data collected will be treated in strict confidence and used exclusively for recruitment purposes.\u00a0 Only short listed candidates will be invited for interview. The company will retain the applications for a maximum period of 24 months and may refer suitable candidates to other vacancies within the Group.", "employment_types": ["Full Time", "Permanent"], "selling_points": ["Responsbile for Digital projects", "Manage vendors to ensure quality in deliverables", "Provide end user training and prepare materials"], "locations": ["Lai Chi Kok"], "categories": ["Information Technology (IT)", "IT Project Management / Team Lead"], "post_time": "2022-01-15T09:38:50Z", "salary": {"currency": null, "max": null, "min": null, "period": null, "term": null}, "salary_visible": false, "title_keywords": ["assistant manager,"], "responsibilities": ["communicate with", "management", "project planning", "uat", "quality", "implementation", "design", "teams", "scheduling", "planning", "coordinate with stakeholders", "report"], "requirements": {"degrees": [], "majors": [], "languages": ["english"], "language_level": ["good command"], "hard_skills": ["web development", "plus", "seo", "e-commerce", "vendor", "project management", "mobile", "problem-solving skills"], "soft_skills": ["self-motivated", "under pressure", "negotiation", "detail-oriented", "communication", "project management", "interpersonal skills", "problem-solving skills"], "languages_combined": [{"language": "english", "language_level": ["good command"]}]}, "experience_required": {"duration": ["at least 6 years"], "field": ["ecommerce", "related", "agency", "project management", "f&b", "digital", "retail"]}}, {"job_id": "100003009046928", "location_code": "hk", "company": "Global Executive Consultants Ltd.", "job_title": "Project Manager (HK$50 - 60K) (Ref. No.: 25332)", "description": "Our client is a one of fintech company looking for high-caliber person to fill the position.\n\nResponsibilities:-\n\nLead and manage various projects (e-commerce or fintech) to ensure timeliness and quality of deliverables\nManage tenders and RFPs and prepare proposals with various internal teams and potential vendors;\nDevelop and maintain project plans, effectively track project statuses, issues, signoffs\nBuild and maintain good relationships with clients and partners in local and regional markets\nEnsure project design and specification documentation and provide blueprint for implementation\n\nRequirements:-\n\nUniversity degree in IT or related disciplines\nMinimum of 6 years IT or project experience plus technical\u00a0skill with at least 2 years in project management\nGood experience and knowledge in fintech, eCommerce system projects preferred\nCertification in standards and methodologies is an added advantage, e.g. PMP, Agile PM, Scrum Master, etc.\nStrong presentation, interpersonal, communication and problem-solving skills\nGood command of both spoken and written English and Chinese", "employment_types": ["Full Time", "Permanent", "Contract"], "selling_points": ["Project Management", "Digital project", "PMP, Agile, etc"], "locations": ["Not Specified"], "categories": ["Information Technology (IT)", "IT Project Management / Team Lead", "Product Management / Business Analyst", "Testing / QA"], "post_time": "2022-01-14T09:02:22Z", "salary": {"currency": null, "max": null, "min": null, "period": "monthly", "term": null}, "salary_visible": false, "title_keywords": ["project manager"], "responsibilities": ["teams", "quality", "design", "develop", "implementation", "maintain", "documentation", "plans"], "requirements": {"degrees": ["university degree", "master"], "majors": ["related disciplines", "it"], "languages": ["english", "chinese"], "language_level": ["good command"], "hard_skills": ["plus", "agile", "project management", "problem-solving skills", "pmp"], "soft_skills": ["agile", "interpersonal", "communication", "project management", "problem-solving skills", "technical skill", "presentation"], "languages_combined": [{"language": "english", "language_level": ["good command"]}, {"language": "chinese", "language_level": ["good command"]}]}, "experience_required": {"duration": ["at least 2 years", "minimum of 6 years"], "field": ["ecommerce", "project management", "it"]}}, {"job_id": "100003009049148", "location_code": "hk", "company": "Hong Kong Interbank Clearing Ltd", "job_title": "Senior Project Manager (Application Development)", "description": "Major Responsibilities\n\nManage a team of application system development professionals to perform feasibility study, design, development and implementation of the Company's computer systems as well as to provide production support\nEnsure that the deadlines of the projects are met\nEvaluate systems effectiveness, undertake management of problem analysis and diagnosis, maintenance and enhancement of the application systems\nAssist in reviewing and streamlining the workflow and improving the overall effectiveness of the team\nEnsure efficient and effective system development processes are in place and enforce compliance by the team\nProvide supervision and guidance of staff and monitor their performance\nManage the budgets and costs of projects and report regularly to the management on progress\nRequirements\n\nUniversity education in computer science or related discipline\nAt least 15 years\u2019 computing experience of which 5 years at project management position in financial sector, preferably with exposure to mission critical payment or clearing and settlement systems\nProven experience in project management, business requirement analysis and application system development and implementation\nHands-on experience in application system development process, design methodologies and multi-tier application integration in a project manager role\nKnowledge of z/OS, COBOL, CICS, open platform and web-based systems will be an advantage\nGood planning, organising, communication and interpersonal skills, and able to work under pressure\nFast learner, willing to take initiatives to learn legacy and new businesses\nCandidates with less experience would be considered for the position of Project Manager (Application Development)\nHow to Apply\nInterested parties please send your curriculum vitae stating your current and expected salaries, and the contact phone number to the Human Resources Division, Unit B, 25/F, MG Tower, 133 Hoi Bun Road, Kwun Tong, Kowloon\u00a0\u00a0by clicking the \"Apply Now\" button below.\nAll applications and personal information collected will be treated in strict confidence and only be used for the purpose of recruitment and selection.\u00a0 The information collected will be accessed by our authorized personnel only.\u00a0 Those applicants not contacted by the Human Resources Division within two months from their application date should consider their applications filed for future reference which will be retained for one year for possible future job matching, and will be destroyed after the expiry of one year.", "employment_types": ["Full Time", "Permanent"], "selling_points": [], "locations": ["Ngau Tau Kok"], "categories": ["Management", "General Management", "Information Technology (IT)", "IT Project Management / Team Lead", "Software Development"], "post_time": "2022-01-14T08:11:00Z", "salary": {"currency": null, "max": null, "min": null, "period": null, "term": null}, "salary_visible": false, "title_keywords": ["senior project manager"], "responsibilities": ["guidance", "management", "budgets", "maintenance", "analysis", "systems", "compliance", "computer systems", "implementation", "application system", "evaluate", "design", "provide supervision", "monitor", "application systems", "costs", "report"], "requirements": {"degrees": [], "majors": [], "languages": [], "language_level": [], "hard_skills": ["analysis", "cics", "application system", "project management", "os", "web-based systems", "integration", "cobol"], "soft_skills": ["project management", "hands-on", "communication and interpersonal skills", "fast learner", "work under pressure"], "languages_combined": []}, "experience_required": {"duration": ["5 years", "at least 15 years"], "field": ["design", "system development", "project management", "business", "application development", "financial"]}}, {"job_id": "100003009048147", "location_code": "hk", "company": "Miniwork Limited", "job_title": "Project Executive / Assistant", "description": "The position is responsible for planning and executing project management and business activities in the Project Management team for the information Technology department.\n\n\u00a0Manage project scope, timeline, release schedule and quality.\n\u00a0Manage and work with key project stakeholders.\n\u00a0Maintain, analyze and monitor performance of existing services/\u00a0 \u00a0 \u00a0products\n\u00a0Prepare and report on progress and success\n\u00a0Co-ordinate with internal department and business partners to\u00a0 \u00a0ensure the delivery of project information\n\nRequirements\n\nDegree holder in Information System, Information Technology, Project Management or other related discipline\nCreative, responsible, well-organized, detailed-minded and self-motivated\n2+ years relevant experience is preferable, less experience will be considered for project assistant, passionate fresh graduates are welcome\nExcellent communication skills with good command of spoken and written English, Chinese and fluency in Putonghua and Cantonese\nExcellent analytical skill and customer/user management skill is required, especially the ability to analyses business workflow and process\u00a0\nA good team player with strong interpersonal skills and willing to work with tight schedule\u00a0\nKnowledge of cloud computing are advantages", "employment_types": ["Full Time", "Permanent"], "selling_points": ["5 days\u2019 work", "Medical insurance, 12 days A.L.", "Project management / implementation"], "locations": ["Tsuen Wan Area"], "categories": ["Information Technology (IT)", "IT Project Management / Team Lead"], "post_time": "2022-01-14T05:20:39Z", "salary": {"currency": null, "max": null, "min": null, "period": "monthly", "term": null}, "salary_visible": false, "title_keywords": ["project executive", "assistant"], "responsibilities": ["management", "co-ordinate with", "monitor performance", "quality", "communication", "project management", "maintain", "executing", "schedule", "report", "business activities", "planning"], "requirements": {"degrees": ["degree holder"], "majors": ["project management", "information technology"], "languages": ["cantonese", "putonghua", "english", "chinese"], "language_level": ["fluency", "excellent", "good command"], "hard_skills": ["project management", "analytical skill", "information system"], "soft_skills": ["passionate", "communication skills", "self-motivated", "analytical skill", "good team player", "responsible", "well-organized", "project management", "interpersonal skills", "creative", "detailed"], "languages_combined": [{"language": "cantonese", "language_level": ["excellent", "good command"]}, {"language": "putonghua", "language_level": ["excellent", "good command"]}, {"language": "english", "language_level": ["fluency", "excellent", "good command"]}, {"language": "chinese", "language_level": ["fluency", "excellent", "good command"]}]}, "experience_required": {"duration": ["2+ years"], "field": ["relevant experience"]}}, {"job_id": "100003009055689", "location_code": "hk", "company": "Tata Consultancy Services Limited", "job_title": "Technical Lead", "description": "Good expertise in Java, Spring boot and Mule Soft , knowledge of AWS is added advantage.\nExpert in analysis of requirements and able to provide technical inputs and estimation quickly.\nGood ability to guide team and improve the maturity of the team in technical skills.\nFollow all processes and guideline for zero defects and follow guidelines for quality and delivery set in organization.\nAbility for innovations and improving the velocity of team.\nAbility to solve queries and issues quickly and correctly by unblocking the blockers.\nAble to give good support for production issues and CR deployments.\nAble to effectively communicate with stakeholders and external teams.\nAble to highlight risk and blockers in advance , with the impact on timelines and delivery.\nA go to person who can lead the team technically and as and when required in sprint and PI events.\nAbility to learn new technology as needed by the project.\nWell versed with JIRA and keep track of its hygiene.\nWell versed with scrum and SAFE agile framework.", "employment_types": ["Full Time", "Permanent"], "selling_points": ["Good expertise in Java, Spring boot and Mule Soft.", "Ability for innovations and improving", "Ability to learn new technology"], "locations": ["Others"], "categories": ["Information Technology (IT)", "IT Project Management / Team Lead"], "post_time": "2022-01-18T02:51:14Z", "salary": {"currency": null, "max": null, "min": null, "period": "monthly", "term": null}, "salary_visible": false, "title_keywords": ["lead"], "responsibilities": ["communicate with", "guidelines", "analysis", "quality", "teams", "hygiene"], "requirements": {"degrees": [], "majors": [], "languages": [], "language_level": [], "hard_skills": ["java", "agile", "analysis", "aws", "safe", "spring", "go"], "soft_skills": ["technical skills", "agile"], "languages_combined": []}, "experience_required": {"duration": [], "field": []}}, {"job_id": "100003009056041", "location_code": "hk", "company": "Tata Consultancy Services Limited", "job_title": "SAP ARIBA Lead", "description": "Solution Lead\n\nTo ensure requirements are mapped and documented to functional and technical specifications for software development of complex and cross-departmental / cross domains projects / Programmes through working with various internal and external stakeholders and leveraging external and internal resources to deliver quality and working software application(s) that is aligned with business vision and goal in the delivered software application.\n\nKey Responsibilites:\n\nLead assigned projects in technical aspect.\nEnsure functional and technical specifications are fully mapped and meeting requirements as well as defined solutions.\nCritically evaluate and analyze requirements gathered from multiple sources, reconcile conflicts and leverage project team members to deliver functional and technical specifications.\nIdentify and document technical constraints, assumptions and risks associated with requirements\nEnsure provided functional and technical specifications, are managed, accessed and archived across the enterprise aligned within quality, availability, compliance and security requirements\nDocument functional specifications and technical specifications utilizing natural language, diagrams and models using techniques such as activity diagrams, use cases, flowcharts, sequence diagrams, etc.\nEnsure compliance and support existing and future Software Development Methodologies\nSupport the implementation of the solution.\nCarry out level 2 and level 3 incident supports for in-production systems and manage end user expectations.\nWork closely and collaboratively with internal stakeholders.\nCollaborate with other IT domains to drive innovation\nKeep abreast of the latest trends in software development technology and practice\nKeep abreast of business domain\u2019s strategy, business plan and latest industrial trends.\nProvide mentoring to system analysts and promote knowledge sharing on analysis practices\nLiaise between SAP consultants and Business SME's are met in the implemented SAP Solution which will span Ariba and S4/HANA in conjunction with the Ariba Design Authority\nAriba S2C, P2P, Integration with SAP S4HANA system on cloud\nThe SAP Ariba Consultant will be responsible for the successful delivery of functional and technical components of procurement, strategic sourcing, catalog management, sourcing analytics using SAP Ariba and its components.\nThis role will apply functional and technical integration knowledge of SAP Ariba tools, S4H systems and functional procurement/sourcing processes.\nThe consultant will implement leading practices within the business planning cycles, including strategic, financial and operational planning.\nThe consultant will perform hands-on Ariba design and configuration (reports, input schedules, script logic, allocations, distributions, etc).\n\nRequirements:\n\n\n\nMinimum 8 years of IT experience\nBachelor\u2019s / Master\u2019s degree (or equivalent education qualifications) in Computer Science, Computer Engineering, or related disciplines\nKnowledge and experience in SDLC and development methodologies\nAbility and experience to work with onshore/off-shore/near-shore teams\nAbility to listen and articulate ideas verbally and in written formats to a broad range of audiences; ability to ask probing questions and deliver presentations\nAbility to work well with others\nWell-developed analytical, problem-solving, decision-making, and leadership skills, leveraging both logic and creativity; strong troubleshooting skills; ability to identify patterns and generate ideas\nFocus on the end user\u2019s or customer\u2019s needs; ability to set expectations and understand end user behaviour\nAbility and willingness to proactively accept and drive change to accomplish positive outcomes\nAbility to understand strategy and align tactical and strategic work in a well balanced way\nGood understanding of applicable technology concepts, trends and capabilities\nGood business domain and industry knowledge\nA consulting background with airline exposure would be advantageous\nExperience with SAP Ariba Modules will be a huge advantage for any candidate", "employment_types": ["Full Time", "Permanent"], "selling_points": ["Minimum 8 years of IT experience", "Lead assigned projects in technical aspect.", "Knowledge and experience in SDLC."], "locations": ["Others"], "categories": ["Information Technology (IT)", "IT Project Management / Team Lead"], "post_time": "2022-01-18T03:13:06Z", "salary": {"currency": null, "max": null, "min": null, "period": "monthly", "term": null}, "salary_visible": false, "title_keywords": ["lead"], "responsibilities": ["collaborate with", "liaise", "software", "schedules", "quality", "design", "sme", "configuration", "compliance", "implementation", "reports", "business plan", "management", "specifications", "analysis", "systems", "ensure compliance", "evaluate", "planning"], "requirements": {"degrees": ["degree", "bachelor", "master"], "majors": ["related disciplines", "computer engineering", "computer science"], "languages": [], "language_level": [], "hard_skills": ["sap", "problem-solving", "airline", "presentations", "sdlc", "focus"], "soft_skills": ["problem-solving", "leadership skills", "troubleshooting", "articulate", "focus", "positive"], "languages_combined": []}, "experience_required": {"duration": ["minimum 8 years"], "field": ["development", "it experience"]}}, {"job_id": "100003009049011", "location_code": "hk", "company": "SmarTone Telecommunications Limited", "job_title": "Project Manager (E&M Site)", "description": "Responsibilities:\n\n\nResponsible for full project lifecycle with vendor management\nDefine project scope and communicate effectively to cross functional team\nDevelop, track and update project status using appropriate project management techniques and tools (e.g. meetings, status tracking tools)\nIdentify project issues and risk and develop projects scopes, plans, schedules and budget\nManage resources and risks, escalate potential issues to management\nFacilitate onsite construction co-ordination, meetings and supervision works\nProactively drive solutions to problems while involving key stakeholders\nObtain appropriate information necessary for the proper carrying out and completion of the project in accordance with the contract conditions\nIdentify gaps in the contract and support VO discussion with Sales\n\nRequirements:\n\n\nHD holders or above in in Mechanical/ Electrical Engineering/ Building Service\nAt least 5 years practical experience in E&M design and co-ordination, prefer in client or consultant side\nKnowledge of building and interior fitting-out works is required\nPC and AutoCAD knowledge\nExperience for luxury residential development and house is an advantage\nGood leadership and communication skills, able to works with people at all levels, strong in coordination with contractor\nClose attention to details and ability to handle multi-tasks\nExperience in IoT and network cabling structure is a plus\nWith valid Construction Industry Safety Training Certificate (commonly known as \"Green Card\") would be advantage or obtain a certificate within 1 month\nComplete Safety Supervisor certificate by an authorized institution within 3 months\nGood command of written and spoken English and Cantonese\n\nInterested parties please apply with full resume stating our reference code, present and expected salary by clicking \"Apply Now\"\u00a0via JobsDB\n\nYou are welcome to visit our website :\u00a0www.smartone.com\u00a0\n\nSmarTone is an equal-opportunity employer. All data supplied will be kept in strict confidence and will be used for employment related purpose. We may transfer such data to any agent, contractor or third party who provides services to us with respect to matters relating to your application. Only short-listed candidates will be contacted.", "employment_types": ["Full Time", "Permanent"], "selling_points": ["Manage project lifecycle with vendor management", "Facilitate onsite construction co-ordination works", "Experienced in E&M design"], "locations": ["Ngau Tau Kok"], "categories": ["Information Technology (IT)", "IT Project Management / Team Lead", "Network & System", "Mobile / Wireless Communications"], "post_time": "2022-01-14T07:54:25Z", "salary": {"currency": null, "max": null, "min": null, "period": "monthly", "term": null}, "salary_visible": false, "title_keywords": ["project manager"], "responsibilities": ["management", "schedules", "budget", "develop", "project management", "plans", "tracking"], "requirements": {"degrees": ["certificate"], "majors": [], "languages": ["cantonese", "english"], "language_level": ["good command"], "hard_skills": ["pc", "plus", "green card", "autocad"], "soft_skills": ["communication skills", "multi-tasks", "attention to details", "coordination", "leadership"], "languages_combined": [{"language": "cantonese", "language_level": ["good command"]}, {"language": "english", "language_level": ["good command"]}]}, "experience_required": {"duration": ["at least 5 years"], "field": ["development", "design"]}}, {"job_id": "100003009054383", "location_code": "hk", "company": "Wellesley Associates Limited", "job_title": "Software Product Manager  - IoT / Smart Home - MNC", "description": "Our client is a start-up company of IoT/Smart Home. Currently they are expanding in Hong Kong and seeking for a high calibre to be responsible to oversee their product team.\u00a0The ideal candidate will be responsible for whole product development process including, pricing, go-to-market planning and strategies. You will collaborate with internal and external parties to develop our strategy for product launches and product positioning.\u00a0\n\nResponsibilities\n\nDrive internet services and solutions decisions through industry/technology trend, performance tracking and analysis of vertical and horizontal enterprise solutions\nDesign & execute product strategy to achieve product growth\nDevelop and execute go-to-market planning and strategies, identify key target customers for different solutions and derive and develop solutions messaging and positioning\nUnderstand customer needs and liaise with sales and products teams to solve challenges of enterprises and penetrate solutions into the market\nDesign customer experience from consultancy, onboarding, delivery and post-sales stages\nBuild and develop the partner relationship management\nConduct product briefing/training session to support sales team & pre-sales consultant team\n\nQualifications\n\nBachelor's degree in computer science, Engineering/IT\n5+ years' experience in IoT, Smart Home or wearables\u00a0\nHands-on experience the formulation and implementation of product plan is a MUST\nKnowledge and hands-on working experience of Agile, Scrum and Kanban or related project management frameworks\u00a0\nStrong understanding in cloud service, embedded systems or mobile app development is preferred\u00a0\nExcellent communication and organizational skills with great attention to detail.\nGood command of spoken and written English, Cantonese and Mandarin\u00a0\nIf you would like to apply for this role or find out more, please contact\u00a0Boris LAW\u00a0on 2847 9960 or apply online with your latest CV in word format with expected salary, quoting the job role \u2013 Product Manager. Kindly note that only shortlisted candidates will be notified.", "employment_types": ["Full Time"], "selling_points": ["MNC", "IoT, Smart Home or wearables", "Agile and Scrum"], "locations": ["Not Specified"], "categories": ["Information Technology (IT)", "IT Project Management / Team Lead", "Product Management / Business Analyst", "Technical / Functional Consulting"], "post_time": "2022-01-17T09:19:29Z", "salary": {"currency": null, "max": null, "min": null, "period": "monthly", "term": null}, "salary_visible": false, "title_keywords": ["product manager"], "responsibilities": ["collaborate with", "understand customer needs", "internal and external parties", "design", "communication", "plan", "liaise with", "mobile app", "internet services", "teams", "implementation", "develop", "management", "contact", "tracking", "analysis", "systems", "project management", "sales team", "planning"], "requirements": {"degrees": ["degree", "bachelor"], "majors": ["it", "engineering", "computer science"], "languages": ["cantonese", "english", "mandarin"], "language_level": ["good command"], "hard_skills": ["agile", "analysis", "word", "project management", "mobile", "go"], "soft_skills": ["organizational skills", "agile", "responsible", "communication", "project management", "hands-on", "attention to detail", "ideal"], "languages_combined": [{"language": "cantonese", "language_level": ["good command"]}, {"language": "english", "language_level": ["good command"]}, {"language": "mandarin", "language_level": ["good command"]}]}, "experience_required": {"duration": ["5+ years"], "field": ["related", "project management", "design"]}}, {"job_id": "100003009044629", "location_code": "hk", "company": "Top Pine Technology Ltd", "job_title": "IT Project Manager", "description": "\u00a0Job\u00a0Accountabilities:\n\nMonitoring progress to ensure smooth implementation of the project\nHandling ad-hoc tasks or projects\nUnderstand and collect information from the product owner which is related to the project specifications and requirements\nProvide enhancement, improvements and maintenance tasks on existing applications\nPrepare documents for the project implementation\nCoordinate project activities / meeting\n\nJob Requirements:\n\n\n\u00a0Higher diploma or University Graduates in Computer Science or equivalent;\u00a0 \u00a0 \u00a0\n\u00a0Good experience in Java / .NET / Mobile (iOS, Android) / PHP / SQL Server\nStrong interpersonal, presentation and communication skills\nTeam Work and Good communication in Cantonese and English\nImmediate available will be an advantage", "employment_types": ["Full Time"], "selling_points": [], "locations": ["Ngau Tau Kok"], "categories": ["Information Technology (IT)", "IT Project Management / Team Lead"], "post_time": "2022-01-13T05:09:27Z", "salary": {"currency": null, "max": null, "min": null, "period": "monthly", "term": null}, "salary_visible": false, "title_keywords": ["it project manager"], "responsibilities": ["ad-hoc tasks", "monitoring", "implementation", "maintenance tasks", "coordinate", "communication", "specifications", "prepare documents"], "requirements": {"degrees": ["diploma"], "majors": ["computer science"], "languages": ["cantonese", "english"], "language_level": ["good"], "hard_skills": ["java", "maintenance", "php", "sql", "mobile", "server", "android"], "soft_skills": ["communication skills", "communication", "smooth", "interpersonal", "presentation"], "languages_combined": [{"language": "cantonese", "language_level": ["good"]}, {"language": "english", "language_level": ["good"]}]}, "experience_required": {"duration": [], "field": []}}, {"job_id": "100003009045341", "location_code": "hk", "company": "Macroview Telecom Limited", "job_title": "Assistant Project Manager / Project Executive", "description": "The Job, you will:\n\nDeliver project implementation service to the customer\nDevelop a project plan, organize activities and manage resources to accomplish project goals in terms of timelines, budget and service quality\nParticipate in initiation, planning, execution, monitoring and closing phases of the project implementation\nManage project progress and achieve key milestones\nProvide regular status updates & report\nFacilitate technical teams on requirement gathering, design, development, test and deployment during the project lifecycle\nCoordinate with all project stakeholders including internal parties, customers, vendors and subcontractors to ensure smooth project implementation\n\nAbout You:\n\nA good team member and team leader with good communication skills\nGood interpersonal skill and presentation skill\nInterested in problem-solving\nSelf-motivated\nDegree or High Diploma holders in Computer Science, Engineering, Information System or related disciplines\nMore than 1-year relevant working experience in implementing ICT project\nGood command of both written and spoken English as well as for Putonghua\nFresh graduates can apply for Project Executive", "employment_types": ["Full Time", "Permanent"], "selling_points": ["2 year PM experience or above", "Coordinate with all project stakeholders", "Deliver project implementation service"], "locations": ["Tsing Yi"], "categories": ["Engineering", "Engineering Project Management", "Information Technology (IT)", "IT Project Management / Team Lead", "Others"], "post_time": "2022-01-13T07:39:18Z", "salary": {"currency": null, "max": null, "min": null, "period": "monthly", "term": null}, "salary_visible": false, "title_keywords": ["assistant project manager", "project executive"], "responsibilities": ["budget", "quality", "project plan", "implementation", "develop", "monitoring", "project progress", "teams", "design", "coordinate with", "communication", "report", "internal parties", "planning"], "requirements": {"degrees": ["high diploma", "degree"], "majors": ["related disciplines", "engineering", "computer science"], "languages": ["putonghua", "english"], "language_level": ["good command"], "hard_skills": ["presentation skill", "problem-solving", "deployment", "information system"], "soft_skills": ["presentation skill", "communication skills", "self-motivated", "problem-solving", "interested in", "interpersonal skill", "smooth", "team member"], "languages_combined": [{"language": "putonghua", "language_level": ["good command"]}, {"language": "english", "language_level": ["good command"]}]}, "experience_required": {"duration": ["1-year"], "field": ["relevant working experience"]}}, {"job_id": "100003009054045", "location_code": "hk", "company": "NEC Hong Kong Limited", "job_title": "Senior System Analyst  / System Analyst - C#, JAVA", "description": "Our Clients are in the E-Commerce, Fintech and Commercial space. They're currently expanding their team and looking to hire IT Project Managers (Permanent Role) to join their progressive team!\u00a0\n\n\n\nResponsibilities:\n\nAnalyse project requirements and determine development scope and provide time estimates for completion.\nPerform System Design, Build and Test new Application\nProvide enhancement, improvements and maintenance tasks on existing applications\nProactively make recommendations for process improvement and automation\nMake decisions on appropriate design or development techniques\n\nRequirements:\n\nHigher Diploma or University Graduates in Computer Science or equivalent;\nGood experience in Java / .NET / Mobile (iOS, Android, ARVR) / PHP / Oracle EBS / Oracle Forms Reports / SAP / ABAP\nTeam Work and Good communication in Cantonese and English\n\n\n\n\n\u00a0We offer attractive remuneration and fringe benefits to the right candidates. Please send us the application by clicking the \"Apply Now\" button, together with a detailed resume, stating current and expected salary.\u00a0\n\n(All personal data provided by job applicants are used only for recruitment purpose and will be treated strictly confidential.)\u00a0", "employment_types": ["Full Time", "Permanent"], "selling_points": ["Lead a technical team on system design and coding", "With at least 5 yrs. relevant experience", "Knowledge in .Net, C#, JAVA  and JavaScript"], "locations": ["Hung Hom"], "categories": ["Information Technology (IT)", "Application Specialist - Software", "IT Project Management / Team Lead", "Software Development"], "post_time": "2022-01-17T08:11:37Z", "salary": {"currency": null, "max": null, "min": null, "period": "monthly", "term": null}, "salary_visible": false, "title_keywords": ["system analyst"], "responsibilities": ["make recommendations", "project requirements", "design", "maintenance tasks", "system design", "analyse"], "requirements": {"degrees": ["diploma"], "majors": ["computer science"], "languages": ["cantonese", "english"], "language_level": ["good"], "hard_skills": ["java", "abap", "sap", "php", "mobile", "android", "oracle"], "soft_skills": ["communication"], "languages_combined": [{"language": "cantonese", "language_level": ["good"]}, {"language": "english", "language_level": ["good"]}]}, "experience_required": {"duration": [], "field": []}}, {"job_id": "100003009052733", "location_code": "hk", "company": "Quality HealthCare Medical Services Ltd", "job_title": "Application Specialist / Lead (System Analyst) - Web & Mobile", "description": "In the Heart of the Role:\n\nConduct system development, coding and design including documentation following by company IT policy.\nProvide daily support to maintain the system up and running smoothly to support day-to-day business operation.\nDesign and develop mobile apps and website to fulfil business\u2019s need.\nUser and vendor management\nLead a web and mobile app team\nResponsible for performing system and database design, coding and development for project or system enhancement to meet business goals and objectives, as well as providing technical support to business department\nSystem supports and project implementation\nPerform daily system operations, administrations and maintenance.\nDiagnose and troubleshoot system errors.\nOther adhoc assignment as assigned\nDesired Qualifications & Experience:\u00a0\n\nDegree holder or above in Computer Science/Information Technology or related disciplines\nMinimum 5 years\u2019 hands-on experience in Web & Mobile application development\nExperience in\u00a0React, JAVA, JavaScript, jQuery, HTML5, CSS3, RESTful API\nMagento will be plus\nKnowledge of DevOps or Azure Cloud environment is an advantage\nExperience on leading developers or vender management\nKnowledge in application design on MVC, MVVM structure\nGood command of spoken and written English and Chinese\nSelf-motivated, good analytical skills and able to work under pressure\nCandidate with more experience will be considered as Application Lead\nWe offer\u00a0competitive pay\u00a0and fringe benefits. Interested parties please send your full resume with\u00a0current salary and expected salary\u00a0 to\u00a0People Department, Quality HealthCare Medical Services Limited, 3/F, Skyline Tower, 39 Wang Kwong Road, Kowloon Bay, Kowloon\u00a0or by clicking 'Apply Now\".\n\n(All applications will be treated in strict confidence and data collected will be used for recruitment purposes only)", "employment_types": ["Full Time", "Permanent"], "selling_points": ["Performing system and database design", "Coding and development for project", "System enhancement to meet business goals"], "locations": ["Kowloon Bay"], "categories": ["Information Technology (IT)", "Application Specialist - Software", "IT Project Management / Team Lead", "Mobile / Wireless Communications"], "post_time": "2022-01-17T03:52:03Z", "salary": {"currency": null, "max": null, "min": null, "period": "monthly", "term": null}, "salary_visible": false, "title_keywords": ["system analyst", "lead", "application specialist"], "responsibilities": ["business goals", "operations", "design and develop", "website", "coding", "design", "maintain", "troubleshoot", "database", "application development", "work under pressure", "mobile app", "diagnose", "implementation", "management", "documentation", "business operation", "maintenance", "technical support"], "requirements": {"degrees": ["degree holder"], "majors": ["related disciplines", "computer science", "information technology"], "languages": ["english", "chinese"], "language_level": ["good command"], "hard_skills": ["java", "restful api", "plus", "azure", "maintenance", "web", "react", "jquery", "devops", "vendor", "analytical skills", "mobile", "web & mobile", "javascript", "documentation", "cloud environment"], "soft_skills": ["self-motivated", "responsible", "analytical skills", "hands-on", "troubleshoot", "work under pressure"], "languages_combined": [{"language": "english", "language_level": ["good command"]}, {"language": "chinese", "language_level": ["good command"]}]}, "experience_required": {"duration": ["minimum 5 years"], "field": ["application development", "management"]}}, {"job_id": "100003009047727", "location_code": "hk", "company": "Public Bank (Hong Kong) Ltd", "job_title": "Project Manager - Mobile & Internet Application (Ref: CO-PM)", "description": "Manage IT projects (related to Mobile and Internet), plan and control all phases of SDLC including feasibility study, systems analysis and design, system development, implementation and maintenance.\nPrepare project planning, resources management, project budget management and vendor management.\nMonitor and keep track on milestones and facilitate mitigation of issues and risks.\nFormulate, consult, and instruct project members to provide quality deliverables.\nCollaborate with internal and external stakeholders to execute system project plan.\nMaintain open and clear relationships with project stakeholders to facilitate decision making and resolve issues with relevant teams.\nLead the project team members to accomplish the project goals.\nDegree holder in Information Technology or related discipline with at least 8 years of working experience on application development and support in financial sector.\nStrong project management equipped with problem solving, analytical skills, and decision making skills.\nExcellent communication and coordination skills to liaise project teams to achieve project goals.\nSolid experience in managing SDLC on Mobile and Internet application.\nExperience in J2EE, Java, Spring Boot, Swift, Objective-c, Android, Oracle, MSSQL, IBM WebSphere, IBM MQ, AIX, Linux is an advantage.\nExperienced or Certified in FinTech technology such as AI and Big Data Stream, Distributed Ledger Technology Stream, Open Banking and API Stream, and/or Regtech stream is an advantage.\nGood sense in FinTech market trends is a plus.\n\n\n\nTo apply, interested parties please follow the application methods available in the Bank\u2019s career website https://www.publicbank.com.hk/en/aboutus/careeropportunities. You can send us your resume quoting our job reference number together with present & expected salary (a must) to the Human Resources Department by email or fax at 2815 3157 or by post to Human Resources Department, 12/F, Public Bank Centre, 120 Des Voeux Road Central, Hong Kong. You may also visit our career website for other career opportunities available within our Group.\n\nPersonal data collected will be used for recruitment purpose only and will be treated in accordance with the Bank\u2019s Personal Information Collection Statement, a copy of which has been available in the Bank\u2019s career website.", "employment_types": ["Full Time", "Permanent"], "selling_points": [], "locations": ["Not Specified"], "categories": ["Information Technology (IT)", "IT Project Management / Team Lead", "IT Management", "Network & System"], "post_time": "2022-01-15T03:49:01Z", "salary": {"currency": null, "max": null, "min": null, "period": null, "term": null}, "salary_visible": false, "title_keywords": ["project manager"], "responsibilities": ["collaborate with", "liaise", "budget", "quality", "big data", "design", "communication", "maintain", "plan", "application development", "control", "monitor", "implementation", "teams", "banking", "management", "project planning", "maintenance", "analysis", "systems", "project plan", "project management", "coordination"], "requirements": {"degrees": ["degree holder"], "majors": ["information technology"], "languages": [], "language_level": [], "hard_skills": ["plus", "ai", "vendor", "budget management", "java", "problem solving", "mssql", "analytical skills", "objective-c", "sdlc", "oracle", "linux", "maintenance", "analysis", "mobile", "project management", "spring", "swift", "android"], "soft_skills": ["decision making skills", "coordination skills", "analytical skills", "clear", "project management", "problem solving", "communication", "decision making"], "languages_combined": []}, "experience_required": {"duration": ["at least 8 years"], "field": ["related", "application development", "financial", "information technology"]}}, {"job_id": "100003009052942", "location_code": "hk", "company": "Haven of Hope Christian Service", "job_title": "Assistant Business Analyst (Ref: SSO/IT/ABA/JDB)", "description": "Responsibilities:\nCollect business requirement, analyze, formulate and document business flows and process\nConduct business and in-house user requirement analysis\nPerform feasibility study, solution design, system support and develop user manual\nCreate functional specifications for enhancement and new development\nDevelop test plan and conduct system UAT\nData analysis\nRequirements:\nDiploma or above in Computer Science, Information Systems, Statistics or related discipline\nFresh graduates are welcome\nExperience in project management, project lifecycle and direct interaction with end user\nProficiency in SQL, Power BI, SharePoint, Excel and Google Analytics\nKnowledge of data analysis\nCustomer-oriented, good analytical, presentation, communication, problem solving and project management skills\nProficiency in both written and spoken English and Chinese\nPlease send full resume with expected salary and reference no. quoted to Haven of Hope Christian Service, Staff Engagement Department, 7 Haven of Hope Road, Tseung Kwan O, New Territories or via email by clicking \"Apply Now\", or via Whatsapp no. 6507 8148 (with reference no. quoted at the caption) on or before 5 February 2022. Only short-listed candidates will be notified.\nEnquiry: 2703 3227 (Phone); 6507 8148 (Whatsapp).\nFor details about our organization, please visit www.hohcs.org.hk.\nProspective employees are requested to undergo/submit Sexual Conviction Record Check for work relating to children or mentally incapacitated persons before employment. Data collected will be used for recruitment purpose only.\nThis advertisement should not be reproduced, in whole or in part, to other recruitment websites without our prior written permission.", "employment_types": ["Full Time", "Permanent"], "selling_points": [], "locations": ["Tseung Kwan O"], "categories": ["Professional Services", "Business Analysis / Data Analysis", "Information Technology (IT)", "IT Project Management / Team Lead", "Product Management / Business Analyst"], "post_time": "2022-01-17T04:38:35Z", "salary": {"currency": null, "max": null, "min": null, "period": "monthly", "term": null}, "salary_visible": false, "title_keywords": ["business analyst", "assistant"], "responsibilities": ["user requirement", "uat", "analysis", "design", "develop", "data analysis", "specifications", "plan"], "requirements": {"degrees": ["diploma or above"], "majors": ["statistics", "computer science"], "languages": ["english", "chinese"], "language_level": ["proficiency"], "hard_skills": ["hope", "google analytics", "excel", "bi", "no", "analysis", "sql", "project management", "problem solving", "whatsapp"], "soft_skills": ["project management skills", "communication", "project management", "customer-oriented", "problem solving", "presentation"], "languages_combined": [{"language": "english", "language_level": ["proficiency"]}, {"language": "chinese", "language_level": ["proficiency"]}]}, "experience_required": {"duration": [], "field": ["project management"]}}, {"job_id": "100003009055933", "location_code": "hk", "company": "Randstad Hong Kong Limited", "job_title": "Enterprise Solution Architect (Up to 70K + 3 Months Bonus)", "description": "about the company.\nMy client is one of the most famous retail businesses and they are looking for an IT Enterprise Solution Architect for the existing and upcoming new businesses who have solid experience and track record especially in enterprise level solution architecture design and cloud project delivery.\n\n\nabout the job.\n\nWork closely with the digital team and business stakeholders for contributing to the architecture development and implementation of the IT strategies and long-term technology roadmap\nLead the creation of solution architectures by considering business needs and technology limitations, with the selection of technology standards, describe configuration paradigms, and identify demand for the reference architecture\nDefine and maintain the enterprise architecture principles and the best practices with IT policies to govern the usage and technology adoption across different IT domains\nSupport the group business to adopt new technologies such as digital transformation, cloud computing, big data and machine learning etc.\nCollaborate with project team and 3rd party vendors for ensuring the delivery is able to meet the agreed standards\n\nskills & experiences required.\n\nBachelor Degree or above in Computer Science or related discipline is preferred\nMinimum 10+ years of relevant experience, previous project experience for group-level is a plus\nStrong experience in solution design and relevant experience including at least 2 technical domains but not limited to enterprise solution architecture/network management and security/application development/database management or operations etc.\nPrevious experience in any of cloud platforms and architecture is a must; cloud related certifications would be advantageous\nGood communication skills and business mindset, with the ability to manage the relationship with business stakeholders and other departments\nProficient in spoken Cantonese, English and Mandarin\n\nabout the benefits.\n\nPerformance Bonus (Average 3-4 Months Salary)\n20 Days Annual Leave\nMedical Insurance\nORSO Scheme\nPermanent Headcount\n\n\nIf you're interested in this exciting opportunity please don't delay and click APPLY NOW or for more information, you can reach out to Kelvin Chu on kelvin.chu@randstad.com.hk", "employment_types": ["Full Time", "Permanent"], "selling_points": ["Permanent Headcount", "Well-known & Stable Business", "In-house Transformation Projects"], "locations": ["Not Specified"], "categories": ["Information Technology (IT)", "IT Project Management / Team Lead", "Product Management / Business Analyst", "Software Development"], "post_time": "2022-01-18T03:06:08Z", "salary": {"currency": "HKD", "max": 89999, "min": 70000, "period": "monthly", "term": null}, "salary_visible": true, "title_keywords": [], "responsibilities": ["collaborate with", "3rd party vendors", "management", "configuration", "operations", "big data", "implementation", "design", "it policies", "communication", "maintain", "database", "application development", "architecture"], "requirements": {"degrees": ["degree or above", "bachelor"], "majors": ["computer science"], "languages": ["cantonese", "english", "mandarin"], "language_level": ["proficient"], "hard_skills": ["network management", "plus"], "soft_skills": ["communication skills", "learning"], "languages_combined": [{"language": "cantonese", "language_level": ["proficient"]}, {"language": "english", "language_level": ["proficient"]}, {"language": "mandarin", "language_level": ["proficient"]}]}, "experience_required": {"duration": ["minimum 10+ years"], "field": ["management", "design", "solution architect", "it", "relevant experience", "security", "database management", "application development", "retail"]}}, {"job_id": "100003009049147", "location_code": "hk", "company": "Hong Kong Interbank Clearing Ltd", "job_title": "Manager (Technology Solutions)", "description": "\nMajor Responsibilities\n\nSupporting the Technology Solutions Department in the development of FinTech and Cloud infrastructure/applications, the incumbent is mainly responsible for the following duties:\n\nAssist in development of strategies and policies of the company\nAssist in business development, formulate proposals of FinTech and Cloud projects and other technology initiatives\nConduct research and analysis on industry trend to facilitate the development of technological initiatives and solutions\nAssist in developing KPIs as a yardstick of success of approved projects and initiatives\nCoordinate all cross-functional programs, projects and activities, including resource planning\nAssist in coordinating meetings with internal and external stakeholders to discuss different projects and initiatives\nPrepare discussion papers, presentation materials and other relevant documents for all meetings of committees and working groups\nProvide administrative and business support to the project teams of the department\nPerform other duties as assigned by supervisor(s)\n\nRequirements\nUniversity degree in business, information systems, FinTech or related discipline\nMinimum 7 years of relevant experience preferably gained from digital banking/FinTech development or consulting of banking sector with at least 3 years\u2019 experience at managerial level\nSound business analysis with project management office experience preferred\nKnowledge of emerging technologies in the FinTech domain is preferred\nStrong analytical, interpersonal, communication and presentation skills\nGood command of written and spoken English and Chinese, proficiency in Putonghua is an advantage\n\n\nHow to Apply\nInterested parties please send your curriculum vitae stating your current and expected salaries, and the contact phone number to the Human Resources Division, Unit B, 25/F, MG Tower, 133 Hoi Bun Road, Kwun Tong, Kowloon\u00a0\u00a0by clicking the \"Apply Now\" button below.\nAll applications and personal information collected will be treated in strict confidence and only be used for the purpose of recruitment and selection.\u00a0 The information collected will be accessed by our authorized personnel only.\u00a0 Those applicants not contacted by the Human Resources Division within two months from their application date should consider their applications filed for future reference which will be retained for one year for possible future job matching, and will be destroyed after the expiry of one year.", "employment_types": ["Full Time", "Permanent"], "selling_points": [], "locations": ["Ngau Tau Kok"], "categories": ["Banking / Finance", "Financial Services", "Information Technology (IT)", "IT Project Management / Team Lead", "Others"], "post_time": "2022-01-14T08:10:59Z", "salary": {"currency": null, "max": null, "min": null, "period": null, "term": null}, "salary_visible": false, "title_keywords": ["manager"], "responsibilities": ["perform other duties", "coordinating meetings", "policies", "analysis", "infrastructure", "teams", "developing", "coordinate", "kpis", "conduct research", "planning"], "requirements": {"degrees": ["university degree"], "majors": ["business"], "languages": ["putonghua", "english", "chinese"], "language_level": ["advantage", "proficiency", "good command"], "hard_skills": ["project management", "analysis"], "soft_skills": ["communication", "project management", "presentation skills", "interpersonal"], "languages_combined": [{"language": "putonghua", "language_level": ["proficiency", "advantage", "good command"]}, {"language": "english", "language_level": ["proficiency", "advantage", "good command"]}, {"language": "chinese", "language_level": ["proficiency", "advantage", "good command"]}]}, "experience_required": {"duration": ["at least 3 years", "minimum 7 years"], "field": ["managerial", "consulting", "development", "project management", "relevant experience", "banking sector", "banking", "business analysis", "digital"]}}, {"job_id": "100003009054832", "location_code": "hk", "company": "Hong Kong Disneyland", "job_title": "Systems Analyst I / II (Digital Product Management)", "description": "Job Summary:\n\nCareer with a Difference\nHong Kong Disneyland delivers world-class service and lifetime memories for our Guests. As a Cast Member, you will be an important part of the Disney Show. Working at Hong Kong Disneyland offers you the opportunity to participate in comprehensive training and experience excellent career development opportunities. Interested in a career with a difference? Join us now!\n\n\nResponsibilities:\nEngage directly with the line of businesses in order to capture application demand, provide guidance on the strategic initiatives and assist with prioritization\nAssist to formulate Customer 360 and data strategy\nDevelop Business Intelligence tools / Dashboards to facilitate efficient cross-platform data analysis\nParticipate in projects of customer data model and data flow amongst integrated systems\nCoordinate between Technology and Digital teams and end users as second line support with vendors to handle daily support and enhancement activities on data warehouse and various applications including problem management\nCollaborate with internal control, security & compliance team and external auditor to ensure systems meet compliance standard and policies\nBasic Qualifications:\nBachelor\u2019s degree or above in Computer Science, Information Systems or equivalent with minimum 5 years of relevant experience\nHand on experience on enterprise database environment and complex data warehouse project\nSolid experience in database design, BI tool, ETL and data warehousing\nProficiency in data analytics, CRM, Salesforce and cloud solutions\nWell-organized, self-motivated and a good team player\nAble to manage multiple tasks, anticipate project needs, prioritize work and meet deadlines\nGood communication skills for both verbal and written in English and Chinese\nAdditional Information:\nSUBMITTING YOUR APPLICATION\nAfter clicking \u201cApply for this job\u201d below, the employment application will open in a new window. Please complete ALL pages of the application in ENGLISH by clicking \u201cNext\u201d on each page, then \u201cSubmit\u201d on the final page.\n#LI-GN1 HKProfessional", "employment_types": ["Full Time", "Permanent"], "selling_points": ["Assist to formulate Customer 360 and data strategy", "Participate in projects of customer data model", "Minimum 5 years of relevant experience"], "locations": ["Lantau Island"], "categories": ["Information Technology (IT)", "IT Project Management / Team Lead", "Software Development", "Data Scientist"], "post_time": "2022-01-17T11:27:38Z", "salary": {"currency": null, "max": null, "min": null, "period": "monthly", "term": null}, "salary_visible": false, "title_keywords": ["analyst"], "responsibilities": ["collaborate with", "warehousing", "management", "data", "policies", "systems", "teams", "customer data", "compliance", "develop", "data analysis", "coordinate", "design", "communication", "database", "career development", "provide guidance", "internal control"], "requirements": {"degrees": ["degree or above", "bachelor"], "majors": ["computer science"], "languages": ["english", "chinese"], "language_level": ["good"], "hard_skills": ["bi", "basic", "salesforce", "data warehouse", "data analytics", "analysis", "business intelligence", "internal control"], "soft_skills": ["efficient", "communication skills", "self-motivated", "good team player", "multiple tasks", "interested in", "well-organized", "prioritize", "comprehensive", "meet deadlines", "world-class"], "languages_combined": [{"language": "english", "language_level": ["good"]}, {"language": "chinese", "language_level": ["good"]}]}, "experience_required": {"duration": ["minimum 5 years"], "field": ["training", "development", "design", "relevant experience", "database"]}}, {"job_id": "100003009041943", "location_code": "hk", "company": "Green Tomato Limited", "job_title": "Project Executive/ Senior Project Executive / Assistant Project Manager", "description": "We are hiring talent like you!\n\nProject Executive is a key member to deliver Projects (Web/Mobile/System) to our clients in an effective manner. He/ She is responsible for monitoring, organizing, and coordinating project activities and ensuring projects are completed on time and on budget.\n\nYou will do the following in this job:\n\nWork with the Business team as a task force to manage a full set of project\nMonitors the progress of project deliveries\nRequirements gathering, analysis to meet clients\u2019 need in a responsive manner\nCoordinates with internal team (technical and design) for the project progression\nSupport system rollout, deployment, and on-going support\n\nWhat Talents we want:\n\nDegree holder\u00a0preferable\u00a0in Business/Marketing/Computer Science or related discipline\nUnderstand mobile and digital service operation\nPractical experience in the mobile or advertising agency industry will be preferred.\nWork experience or assist in preparing user requirement specifications, test plan, and test case would be an advantage\nDetail-minded, good coordination and\u00a0communication skills\nA good team player who is mature and can work\u00a0independently\nCandidates with more experience will be consider as more senior position\u00a0\n\nBenefits we offered:\n\n5-day work week\nBirthday Leave\u00a0\nCompetitive remuneration\nDiscretionary Bonus\nMedical Allowance\nHappy and harmonious working environment\nValuable working experience\n\nWe offer an attractive remuneration package, comprehensive on the job training on new technologies, and excellent career development opportunities to the right candidate.\u00a0\n\nFinal and Most Important Requirement\n\n\"Enjoy What You Do!!\"\u00a0\u00a0\n\nCandidates not contacted within 4 weeks may consider their application for this role unsuccessful. Unless advised otherwise, unsuccessful candidates will be kept on file for future job opportunities. Personal data collected will be used for recruitment-related purposes only and all personal data of applicants will be kept in strict accordance with the Personal Data Privacy Ordinance.\u00a0", "employment_types": ["Full Time", "Permanent"], "selling_points": ["Birthday Leave", "Competitive Remuneration", "Happy and harmonious working environment"], "locations": ["Kwun Tong"], "categories": ["Information Technology (IT)", "IT Project Management / Team Lead", "Software Development", "Mobile / Wireless Communications"], "post_time": "2022-01-12T04:44:42Z", "salary": {"currency": null, "max": null, "min": null, "period": "monthly", "term": null}, "salary_visible": false, "title_keywords": ["assistant project manager", "senior project executive", "project executive"], "responsibilities": ["user requirement", "advertising", "analysis", "monitoring", "budget", "design", "communication", "specifications", "plan", "coordination"], "requirements": {"degrees": ["degree holder"], "majors": ["business", "computer science", "marketing"], "languages": [], "language_level": [], "hard_skills": ["mobile", "analysis", "deployment", "web"], "soft_skills": ["detail-minded", "communication skills", "good team player", "work independently", "responsible", "mature", "coordination", "responsive"], "languages_combined": []}, "experience_required": {"duration": [], "field": ["advertising agency"]}}, {"job_id": "100003009053415", "location_code": "hk", "company": "Kazoo Technology (Hong Kong) Limited", "job_title": "\u8cc7\u8a0a\u79d1\u6280\u9805\u76ee\u7d93\u7406", "description": "\u8077\u8cac :\n\n- \u8207\u5916\u90e8\u548c\u5167\u90e8\u5404\u65b9\u5354\u8abf\u4ee5\u5b8c\u6210\u65b0\u7684\u548c\u73fe\u6709\u7684\u8edf\u4ef6(IT)\u958b\u767c\u9805\u76ee\n- \u9805\u76ee\u898f\u5283\u548c\u65bd\u5de5\u7ba1\u7406, \u5354\u8abf\u9805\u76ee\u6703\u8b70, \u89e3\u91cb\u5be6\u65bd\u6d41\u7a0b\u3001\u6642\u9593\u6846\u67b6\u548c\u76f8\u95dc\u7684\u6a19\u6e96\u505a\u6cd5\u548c\u7a0b\u5e8f -\u00a0\u5354\u52a9\u5236\u5b9a\u9805\u76ee\u8def\u7dda\u5716\n- \u7ba1\u7406\u548c\u76e3\u7763\u9805\u76ee\u7684\u5404\u500b\u968e\u6bb5, \u4f8b\u5982\u9700\u6c42\u5be9\u67e5\u3001\u8a2d\u8a08\u3001\u958b\u767c\u3001\u4ea4\u4ed8\u3001\u6e2c\u8a66\u3001\u9805\u76ee\u8b8a\u66f4\u8acb\u6c42\u7b49\n- \u78ba\u4fdd\u9805\u76ee\u91cd\u8981\u968e\u6bb5/\u91cc\u7a0b\u7891\u5f97\u5230\u660e\u78ba\u5b9a\u7fa9\u548c\u76e3\u63a7\n-\u00a0\u8a08\u5283\u6e2c\u8a66\u968e\u6bb5\u7684\u57f7\u884c\u3001\u7cfb\u7d71\u529f\u80fd\u7684\u7528\u6236\u6e2c\u8a66\u3001\u754c\u9762\u5b9a\u7fa9\u3001\u5831\u544a\u5de5\u5177\u548c\u8f49\u63db\u7a0b\u5e8f\n\n\n\u8cc7\u6b77 :\n\n\u5c08\u4e0a\u6559\u80b2\uff1a\u5b78\u58eb\u5b78\u4f4d; 3\u5e74\u7d93\u9a57; \u826f\u597d\u7cb5\u8a9e; \u4e00\u822c\u666e\u901a\u8a71; \u826f\u597d\u82f1\u8a9e; \u61c2\u8b80\u5beb\u4e2d\u6587; \u61c2\u8b80\u5beb\u82f1\u6587\n\n\u5f85\u9047 :\n\n\u6bcf\u6708$25,000 + ((\u6309\u7d93\u9a57)\u00a0, \u6709\u85aa\u5e74\u504715\u5929, \u9280\u884c\u5047\u671f\u53ca\u5176\u4ed6\u6d25\u8cbc/\u798f\u5229, \u661f\u671f\u4e00\u81f3\u4e94: \u4e0a\u53489\u6642\u81f3\u4e0b\u53486\u6642, \u6bcf\u9031\u5de5\u4f5c5\u5929, \u6bcf\u5929\u5de5\u4f5c 8 \u5c0f\u6642\n\n\u7533\u8acb\u9808\u77e5 :\u6c42\u8077\u8005\u53ef\u96fb\u90f5(Apply Now)\u5c65\u6b77\u8868\u7d66\u5be6\u7acb\u79d1\u6280(\u9999\u6e2f)\u6709\u9650\u516c\u53f8\u3002", "employment_types": ["Full Time"], "selling_points": [], "locations": ["Shatin Area"], "categories": ["Information Technology (IT)", "IT Project Management / Team Lead", "Product Management / Business Analyst", "Software Development"], "post_time": "2022-01-17T06:57:27Z", "salary": {"currency": null, "max": null, "min": null, "period": "monthly", "term": null}, "salary_visible": false, "title_keywords": [], "responsibilities": [], "requirements": {"degrees": [], "majors": [], "languages": [], "language_level": [], "hard_skills": [], "soft_skills": [], "languages_combined": []}, "experience_required": {"duration": [], "field": []}}, {"job_id": "100003009045076", "location_code": "hk", "company": "Peoplebank Hong Kong Ltd", "job_title": "Project Manager (Contract + Welcome Freelancers)", "description": "More than 1 positions from FSI / SI / utility\n\nResponsibilities\n\n\n\nResponsible for the end-to-end delivery of a project or workstream, proactively balancing scope, schedule, budget, risks, outcomes and benefits.\nProvide the end-to-end project management from managing the project, resources, budget, timeline to deliverables.\nResponsible for budgeting and overall planning, developments and to deliver multiple projects\nProficient to develop a detailed project plan and monitor progress\nWork closely with vendors, Business Outcome Leads, Technology Leads and Delivery Leads to ensure alignment of initiatives.\nEnsure compliance with external regulatory requirements, internal control standards and Group compliance policies.\nLead change initiatives as well as manage stakeholders and senior management relationships.\nEvaluate and implement plans to resolve issues related to IT risk and business protection.\n\n\nRequirement\n\n\n\nStrong Project Management experience, with at least 7 years PM experience.\nPrevious experience managing Infrastructure, application, or data centre relocation /set-up projects\nPrevious Digital Transformation project experience would be a plus.\nStrong people and project management skills\nSolid experience in managing and delivering large-scale projects and ability to manage multiple projects at the same time\nAbility to plan, manage, analyse, design, propose and communicate business needs\nStrong technical, analytical and problem-solving skills.\nAny Project Management Certification or Agile\nGood Communication skills\nLess experienced will be considered as Assistant Project Manager.\n\nInterested parties please share your resume by Apply Now.\n\n", "employment_types": ["Full Time", "Contract"], "selling_points": ["More than 1 position", "Working at FSI / SI", "Renewable contract"], "locations": ["Not Specified"], "categories": ["Information Technology (IT)", "Application Specialist - Software", "IT Project Management / Team Lead"], "post_time": "2022-01-13T07:05:51Z", "salary": {"currency": null, "max": null, "min": null, "period": "monthly", "term": null}, "salary_visible": false, "title_keywords": ["project manager"], "responsibilities": [], "requirements": {"degrees": [], "majors": [], "languages": [], "language_level": [], "hard_skills": [], "soft_skills": [], "languages_combined": []}, "experience_required": {"duration": [], "field": []}}, {"job_id": "100003009055568", "location_code": "hk", "company": "PeopleLink Services Limited", "job_title": "Business Analyst / Senior Business Analyst | Up to HK$60k + Bonus", "description": "\u00a0Responsibilities:\n\nUnderstand business and user requirement and translate to project scope and work closely with Product Owner, Project Managers and Development Teams\nLiaise and communicate with project stakeholders to ensure project deliverable meet user expectations\nTest deliverables regularly to ensure project on track and prepare document report to management\nQualifications\n\u00a0\n\nBachelor's degree in Computer Science, Information Technology, Business Analytics or equivalent\n5+ years of experience in business analyst on medium-sized to large projects involving multiple stakeholders. Experience in systems revamp in insurance business is preferred.\nSolid work experience in collect user requirements, change management, UAT\nParticipated in full SDLC for at least one of the projects below:\nArtificial Intelligence / Machine Learning application development\nData Management / Data Warehousing\nCloud Infrastructure\nAbility to work effectively with all levels of personnel across the organization\nEffective interpersonal skills with a clear, concise and relevant communication style, including excellent presentation skills.\nExperience in using project tools such as Jira, Confluence\nFluent English and excellent report writing skills", "employment_types": ["Full Time", "Permanent"], "selling_points": ["5+ yrs experience as Business Analyst", "Participate in AI/ML, Data, Cloud projects", "Large scale project exposure, Perm, Great Benefits"], "locations": ["Not Specified"], "categories": ["Information Technology (IT)", "IT Project Management / Team Lead", "Product Management / Business Analyst", "Technical Writing"], "post_time": "2022-01-18T02:43:58Z", "salary": {"currency": "HKD", "max": 54999, "min": 45000, "period": "monthly", "term": null}, "salary_visible": true, "title_keywords": ["senior business analyst", "business analyst"], "responsibilities": ["liaise", "user requirement", "communicate with", "management", "revamp", "change management", "uat", "data", "warehousing", "systems", "teams", "infrastructure", "communication", "application development", "insurance", "report"], "requirements": {"degrees": ["degree", "bachelor"], "majors": ["business analytics", "computer science", "information technology"], "languages": ["english"], "language_level": ["excellent", "fluent"], "hard_skills": ["sdlc", "data management", "writing skills"], "soft_skills": ["work effectively", "writing skills", "communication", "clear", "presentation skills", "learning", "interpersonal skills"], "languages_combined": [{"language": "english", "language_level": ["fluent", "excellent"]}]}, "experience_required": {"duration": ["5+ years"], "field": ["management", "business", "insurance"]}}, {"job_id": "100003009054592", "location_code": "hk", "company": "RGF HR Agent Hong Kong Limited", "job_title": "Japanese Speaking Pre/Post Sales Engineer  - Japanese Network Service Company", "description": "Our client, a Japanese\u00a0network services company, is looking for a suitable candidate to join their company:\n\n<Job Responsibilities>\n\n\u2022 Pre-sales support\n\u2022 Project scheduling, tracking, and reporting;\n\u2022 Project management work such as technical documents including system documentation, network diagrams, etc.;\n\u2022 Installation, configuration, maintenance, and operation support of routers/ switches, firewall, Server, and PC equipment;\n\u2022 Development of new IT solution product/service;\n\u2022 Finish project on time with quality and cost control\n\n<Necessary Skill / Experience >\n\n\u2022 University graduate in Computer Science or related disciplines.\n\u2022 At least 5 years of relevant working experience. Preferably in the telecommunications field in a global/regional carrier or vendor environment.\n\u2022 Fluent in Japanese and English, Chinese ability is an advantage\n\u2022 System administration experience on MS and Linux platforms is essential\n\u2022 Knowledge and hands-on experience of VMware, Citrix virtualization technology preferred\n\u2022 Vendor certification at professional or above level is preferred, e.g. CCNP/CCDP/MCSE\n\u2022 Knowledge of firewall configuration and network security technologies, e.g. Fotigate/SRX/SSG.\n\u2022 Solid understandings of networking protocols such as routing (BGP, OSPF), VLAN (STP, 802.1P, 802.1Q, etc.), IP-based audio \\video (SIP, H.323), etc.\n\nInterested parties please send us your resume in MS Word/PDF format in English.\u00a0All information received will be kept in strict confidential and only for recruitment purpose.", "employment_types": ["Full Time", "Permanent"], "selling_points": ["Japanese Speaking Pre/Post Sales Engineer", "5 yrs + related exp /JLPT N2 ( fluent JP)", "HK Island/ DP / Up to 30K"], "locations": ["Others"], "categories": ["Sales, CS & Business Devpt", "Business Development", "Information Technology (IT)", "IT Project Management / Team Lead", "Technical / Functional Consulting"], "post_time": "2022-01-17T10:10:20Z", "salary": {"currency": null, "max": null, "min": null, "period": "monthly", "term": null}, "salary_visible": false, "title_keywords": ["sales engineer"], "responsibilities": ["administration", "reporting", "installation", "system documentation", "maintenance", "configuration", "quality", "project management", "project scheduling", "cost control", "audio", "tracking"], "requirements": {"degrees": ["university graduate"], "majors": ["related disciplines", "computer science"], "languages": ["japanese", "english", "chinese"], "language_level": ["advantage", "fluent"], "hard_skills": ["server", "virtualization technology", "mcse", "sales support", "vmware", "maintenance", "linux platforms", "ccnp", "vendor", "project management", "ip", "citrix", "firewall", "documentation", "pc", "operation support"], "soft_skills": ["project management", "hands-on"], "languages_combined": [{"language": "japanese", "language_level": ["advantage", "fluent"]}, {"language": "english", "language_level": ["advantage", "fluent"]}, {"language": "chinese", "language_level": ["fluent"]}]}, "experience_required": {"duration": ["at least 5 years"], "field": ["relevant working experience", "administration"]}}, {"job_id": "100003009049385", "location_code": "hk", "company": "Sontec Technology Company Ltd", "job_title": "Sales Manager (POS / HR Solution)", "description": "Established in Asia in 2013 with a trailblazer mentality, FWD is the primary insurance business of investment group, Pacific Century Group (PCG), with minority shareholders Swiss Re Group, GIC Ventures, RRJ Capital and Hopu Investments.\n\nFWD spans 10 markets in Asia including Hong Kong SAR & Macau SAR, Thailand, Indonesia, the Philippines, Singapore, Vietnam, Japan, Malaysia and Cambodia. In Hong Kong, FWD offers life and medical insurance, general insurance, employee benefits, and financial planning. We focus on creating fresh customer experiences and making the insurance journey simpler, faster and smoother, with innovative propositions and easy-to-understand products, supported by digital technology. Through this customer-led approach, FWD aims to be a leading pan-Asian insurer by changing the way people feel about insurance.\n\nIf you are looking for a company where can fuel your inspiration and cultivate your expertise, join us on our exciting journey.\n\nThe Job\n\nCarry out feasibility study of any new requirements\nLead and perform system design and program specifications preparation\nLead and perform program development, maintain and enhance environments\nLead and perform system implementation and enhancement\nLead and prepare documentation on requirement, technical specification and user manual\nLead and perform system design, development, testing, implementation, support, maintenance and enhancement\nCoordinate with IT and user team on system deployment arrangement\nLead and prepare SIT / UAT test plan and manage test execution and documentation to ensure completeness and traceability\nLead and perform user training and prepare user manual\nLead IT project team\nAd-hoc duties as assigned\nEnsure delivery of all projects are in accordance with the Company\u2019s requirements and corporate objectives and adhere to scope, schedule and budgets, all within the PMO framework\nEnsure adherence to project prioritization mechanism and facilitate the required process\nCoordinate with application team to execute resource planning and monitoring\nLiaise and work with key stakeholders to streamline production support process\n\nThe Person\n\nUniversity degree in Computer Science or equivalent, minimum 7 years working experience in Information Technology and insurance/banking industry\nSolid experience in development and implementation of large/middle scale applications in insurance company\nGood knowledge in Life Insurance products and business flow is preferable\nProficient in programming skill on MS SQL/Oracle, JAVA, .NET, Angular/React and client-server technologies\nGood communication skills, able to work with various user departments, technical teams and vendors\nGood analytical mind and problem-solving skills\nSolid understanding Software Development Life Cycle\nHands on experience on Agile Methodology is preferable\nDevelopment experience in WEB and Mobile application is preferable\nCapable to work under pressure\n\nWe offer 5-day work, 20-22 days annual leaves, excellent learning & development opportunities and an attractive package to the right candidate.\n\nInformation collected will be treated in strict confidence and used solely for recruitment purpose. The company will retain all applications no longer than 24 months of which will be destroyed thereafter. When there are vacancies in any of our subsidiaries, holding companies, associated or affiliated companies of, or companies controlled by, or under common control with the Company during that period, we may transfer your application to them for consideration of employment. We are an equal opportunity employer. We do not discriminate on the basis of race, sex, disability or family status in employment process.", "employment_types": ["Full Time", "Permanent"], "selling_points": [], "locations": ["Kwun Tong"], "categories": ["Information Technology (IT)", "IT Project Management / Team Lead", "Software Development", "Others"], "post_time": "2022-01-14T08:32:33Z", "salary": {"currency": null, "max": null, "min": null, "period": "monthly", "term": null}, "salary_visible": false, "title_keywords": ["hr", "sales manager"], "responsibilities": [], "requirements": {"degrees": [], "majors": [], "languages": [], "language_level": [], "hard_skills": [], "soft_skills": [], "languages_combined": []}, "experience_required": {"duration": [], "field": []}}, {"job_id": "100003009046769", "location_code": "hk", "company": "KOS International Limited", "job_title": "Group IT Project Manager - Infrastructure or Network Security", "description": "Great opportunity to join a global insurance firm.\n\nWe are looking for a new technical Cloud (AWS) Engineer to join our enterprise infrastructure team. Ideally, this technical hand-on Cloud (AWS) Engineer has extensive experience implementing cloud (AWS) and other related security and infrastructure enterprise projects. In addition to this, this Engineer would be providing ongoing technical internal support.\n\nResponsibilities:\n\nCloud, infrastructure and security project implementation, which includes working with the respective vendors.\nPerform and oversee software installation, upgrades and maintenance, remediate vulnerabilities and keep patch updates to systems\nDevice configuration of switch, server, firewall, Email support systems, anti-spam etc.\nL2 technical IT helpdesk support\n\nMinimum Requirements:\n\n3-5 years of technical cloud(AWS) implementation experience\n3-5 years experience in Infrastructure management, network administration, and network security related experience\nStrong team player with a proactive and willingness to learn attitude\nProfessional certification in Cisco Certified Network Associate (CCNA), Microsoft Certificated System Engineer (MCSE), System Administrator (MCSA) or equivalent\nUniversity degree in Computer Science, Information Systems or other technology-related disciplines\nFluent in both spoken and written English and Chinese\n\nHighly Preferred:\n\nExperience with Microsoft 365 (Office 365)\nKnowledge on Cybersecurity market standards like CISSP (Certified Information Systems Security Professional)\nEnterprise financial institution exposure (insurance or banking)", "employment_types": ["Full Time", "Permanent"], "selling_points": ["New Headcount", "Digital Transformation", "5 days work week"], "locations": ["Not Specified"], "categories": ["Information Technology (IT)", "IT Project Management / Team Lead"], "post_time": "2022-01-14T00:58:00Z", "salary": {"currency": null, "max": null, "min": null, "period": "monthly", "term": null}, "salary_visible": false, "title_keywords": ["it project manager"], "responsibilities": ["installation", "software", "maintenance", "upgrades", "configuration", "infrastructure", "systems", "implementation"], "requirements": {"degrees": ["university degree"], "majors": ["related disciplines", "computer science"], "languages": ["english", "chinese"], "language_level": ["fluent"], "hard_skills": ["network administration", "mcse", "office 365", "ccna", "mcsa", "cisco certified network associate"], "soft_skills": ["team player", "proactive"], "languages_combined": [{"language": "english", "language_level": ["fluent"]}, {"language": "chinese", "language_level": ["fluent"]}]}, "experience_required": {"duration": ["3-5 years"], "field": ["network administration", "management", "related", "infrastructure", "security"]}}, {"job_id": "100003009043537", "location_code": "hk", "company": "Mainetti (HK) Ltd", "job_title": "ERP Manager", "description": "Implement cybersecurity control mechanisms, risk gap analysis and perform maintenance for security devices.\n\nYour new company\nMy client is a Hong Kong based Banking and Financial company.\n\nYour new role\n\n\n\nDesign, develop and maintain Information Security Polices, Standards and Guidelines\nProvide technical guidance to application development and infrastructure tam regarding security designs and configurations\nAssist in communicating risk management standards, policies and procedures to relevant stakeholders\nConduct regular security assessment on internal system, network and infrastructure\nFacilitate risk management committee meeting for enhancing risk governance and oversight\nDesign and apply operational control process to ensure IT operational and control risks are within acceptable risk appetite\nDesign and monitor Key Risk Indicators. Proficiency in risk reporting to facilitate effective management oversight on technology risk and cybersecurity matters\nPlay a governance role on IT outsourcing. Perform regular security assessment on 3rd party IT service provider\nParticipate in developing, tuning and implementing threat detection analytics\nAct as focal point to support internal, external and regulatory audits\nPrepare and conduct security awareness training for internal IT and non-IT users\n\n\n\nWhat you'll need to succeed\n\nMinimum 5 years of relevant work experience in technology risk, information security and cybersecurity\nUniversity graduate in Computer Science / Information Technology or equivalent\nPossess one or more professional certificates listed below:\nISC2 Certified Information Security Professional (CISSP)\nISACA Certified Information System Auditor (CISA)\nISACA Certified Information Security Manager (CISM)\nISC2 Certified Cloud Security Professional (CCSP)\nSolid experience in vulnerability management, penetration test and technology risk assessment\nSound knowledge in Public Key Infrastructure (PKI), Internet vulnerability, cybersecurity, firewalls, Intrusion Detection/Prevention System and application security of finance/banking systems\nSound experience in performing vulnerability scanning, penetration test and technology risk assessment\nSolid experience in regulators' requirement on technology risk management including the Supervisory Policy Manuals of HKMA, Cyber Resilience Assessment Framework (CRAF), Personal Data Privacy Ordinance, PCI Data Security Standard, SFC guidelines and Customer Security Controls Framework of SWIFT\nBanking experience is an advantage\nStrong communication skill, both in Chinese and English\nMature, independent and able to deliver quality results under tight schedule\nGood communication and interpersonal skills\n\n\n\nWhat you need to do now\nIf you're interested in this role, click 'apply now' to forward an up-to-date copy of your CV, or send your CV to kenneth.ling@hays.com.hk\n\nIf this job isn't quite right for you but you are looking for a new position, please contact us for a confidential discussion on your career.", "employment_types": ["Full Time", "Permanent"], "selling_points": ["Solid experience and understanding of ERP systems", "Direct application support and troubleshooting", "Assist and involve in JDE upgrade project"], "locations": ["Ngau Tau Kok"], "categories": ["Information Technology (IT)", "Application Specialist - Software", "IT Project Management / Team Lead", "Product Management / Business Analyst"], "post_time": "2022-01-12T17:18:42Z", "salary": {"currency": null, "max": null, "min": null, "period": "monthly", "term": null}, "salary_visible": false, "title_keywords": ["manager"], "responsibilities": ["it service", "information security", "data", "quality", "design", "communication", "maintain", "application development", "personal data", "scanning", "control", "infrastructure", "monitor", "developing", "develop", "schedule", "banking", "vulnerability management", "guidance", "management", "reporting", "procedures", "contact", "audits", "maintenance", "guidelines", "policies", "analysis", "systems"], "requirements": {"degrees": ["university graduate"], "majors": ["computer science", "information technology"], "languages": ["english", "chinese"], "language_level": [], "hard_skills": ["focal", "maintenance", "hkma", "analysis", "gap", "information system", "swift"], "soft_skills": ["independent", "interested in", "communication skill", "mature", "communication and interpersonal skills"], "languages_combined": [{"language": "english", "language_level": []}, {"language": "chinese", "language_level": []}]}, "experience_required": {"duration": ["minimum 5 years"], "field": ["risk management", "management", "supervisory", "banking experience", "security"]}}, {"job_id": "100003009040848", "location_code": "hk", "company": "Nigel Frank International", "job_title": "Assistant Manager/ Project Manager - Digital Commerce", "description": "Executive Summary:\n\nPublic Listed firm with global market especially in Asia, North America, Europe, etc.\nStable, competitive salary, strong business growth - 700 staffs in Hong Kong \u2013 over 48,000 staffs globally\nMultinational, dynamic and employee driven working cultures and exposure\nNewly created role to lead internal IT change management and APAC project delivery; The successful job holder should be coming from a MNC background with strong stakeholder management experience across all levels; Enterprise level ERP/CRM/e-commerce experience will be a strong advantage; Consulting background is an advantage\nReport directly into company C-level business leaders\n\nMajor Responsibilities:\n\nOwn the overall IT roadmap of the corresponding business unit (BU)\nLead and facilitate the communication between the BU stakeholders and IT department\nEnsure successful projects/solutions executions with high quality deliverables\nWork with Operation Head to proactively identify business needs and opportunities and propose appropriate solutions\nCollaborate with Regional IT communities on different projects\nWork with different BU stakeholders/users to ensure successful roll out of different initiatives and solutions\nEnsure compliance with external regulatory requirements, internal control standards and company policies\n\nKey Requirements:\n\nDegree in Information Technology, Computer Science or related disciplines\nAt least 8 years relevant experience, preferable in an MNC environment with APAC exposure\nBusiness oriented and strives for appropriate solution and continuous enhancement\nGood business knowledge in manufacturing operation, supply chain, and product development process,\nExcellent verbal, written and inter-personal communication skills, with the ability to clearly articulate findings, considerations, recommendation and execution plans to different levels of stakeholders\nAble to take a holistic approach in planning out solutions for various business requirements\nAbility to adapt to new technologies, learn quickly and pass on this knowledge to others\nSolid experience in system implementation and project management\nWilling to take a very hands-on approach when necessary\nPrevious experience with start-up operations or new setups a definite asset\nPrevious experience with Oracle, WMS, and MES an advantage\nPrevious experience with e-commerce projects a strong plus\n\n\nTo apply, please send your CV in word document to peter(a)endeavourasia.com or call Peter at 3956-1828 for a confidential discussion.\n\n", "employment_types": ["Full Time", "Permanent"], "selling_points": ["Web, Mobile App, CRM, Digital Transformation", "Regional Coverage", "Well-known Brands"], "locations": ["Not Specified"], "categories": ["Information Technology (IT)", "IT Project Management / Team Lead", "Software Development", "E-commerce", "Product Management / Business Analyst"], "post_time": "2022-01-12T03:08:43Z", "salary": {"currency": "HKD", "max": 44999, "min": 35000, "period": "monthly", "term": null}, "salary_visible": true, "title_keywords": ["assistant manager", "project manager"], "responsibilities": ["collaborate with", "regulatory requirements", "policies", "quality", "ensure compliance", "communication", "it roadmap", "internal control"], "requirements": {"degrees": ["degree"], "majors": ["related disciplines", "computer science", "information technology"], "languages": [], "language_level": [], "hard_skills": ["plus", "e-commerce", "word", "project management", "system implementation", "oracle"], "soft_skills": ["communication skills", "inter-personal", "project management", "hands-on", "articulate"], "languages_combined": []}, "experience_required": {"duration": ["at least 8 years"], "field": ["project management", "relevant experience", "e-commerce"]}}, {"job_id": "100003009043679", "location_code": "hk", "company": "Legato Technologies Limited", "job_title": "Senior Project Executive / Project Executive", "description": "Our client, a first tier investment bank is looking to hire a senior project manager to handle a variety of network & infrastructure related projects,\u00a0\n\nJob Description and What We Want:\u00a0\nCandidates must have considerable IT infrastructure/ network project management experience within a financial institution or vendor serving the industry.\n8-12 years experience in total\nFirst rate PM skills with a recognized certification\nExperienced with regional and global projects and teams\nWide variety of large scale infrastructure/ network projects to handle\u00a0\nExcellent stakeholder, vendor management and documentations skills\u00a0\nExcellent communication skills in English is essential\nIdeally come from a technical background\nUniversity degree is a must, preferably those related to banking/ finance or computer science.\u00a0\nWe encourage you to apply even if you not entirely sure whether you're qualify or not, and do reach out so that we can share more information to you.\u00a0\n", "employment_types": ["Full Time", "Permanent"], "selling_points": [], "locations": ["Kowloon Bay"], "categories": ["Information Technology (IT)", "IT Project Management / Team Lead", "IT Management", "Technical / Functional Consulting"], "post_time": "2022-01-13T01:27:30Z", "salary": {"currency": null, "max": null, "min": null, "period": "monthly", "term": null}, "salary_visible": false, "title_keywords": ["senior project executive", "project executive"], "responsibilities": ["management", "it infrastructure", "infrastructure", "teams", "communication", "project management", "banking"], "requirements": {"degrees": ["university degree"], "majors": ["finance", "computer science"], "languages": ["english"], "language_level": ["excellent"], "hard_skills": ["project management", "vendor", "documentations"], "soft_skills": ["communication skills", "project management"], "languages_combined": [{"language": "english", "language_level": ["excellent"]}]}, "experience_required": {"duration": ["8-12 years"], "field": ["infrastructure", "project management", "it", "financial"]}}, {"job_id": "100003009043889", "location_code": "hk", "company": "Chandler Macleod Group (HK) Limited", "job_title": "SAP Project Manager (SD/MM)", "description": "About our client\n\nOur client is a renowned local digital retailer, and they are looking for an IT Manager with good knowledge in POS operation to join their team.\n\nAbout the role\n\n\nOverseeing the operation, development, management of POS and related IT components\n\nSupervising and health checking on the daily operation on the application side\n\nCooperating with the internal infrastructure team to establish a smooth operation of the application\n\nPerforming data management and reporting when required\n\nPerforming managerial tasks, including risk management, budgeting, team structuring, etc.\n\nManaging vendor for development and solutions planning on the application\n\n\nRequirements\n\n\nBachelor degree holder in Computer Science, Information Technology, Mathematics or related discipline\n\n8 years or above experience in application operation/service delivery. With managerial experience is a plus\n\nExperience in reporting tools, such as PowerBI/Tableau/QlikView/Qlik Sense\n\nWith practical and hands-on experience in managing applications/E-commerce platforms is a plus\n\nInsight in DevOps environment on AWS/Azure/GCP environment is a plus\n\nGood command of English and Chinese(Cantonese & Mandarin)\n\nGood interpersonal and communication skills\n\n\nClick \"Apply Now\" to apply for this position or call Harry Yau at +852 3180 4936 for a confidential discussion. All information collected will be kept in strict confidence and will be used for recruitment purpose only.", "employment_types": ["Full Time", "Permanent"], "selling_points": ["Large corporation", "Global project initiative", "Consumer product industry"], "locations": ["Not Specified"], "categories": ["Information Technology (IT)", "Application Specialist - Software", "IT Project Management / Team Lead", "IT Management"], "post_time": "2022-01-13T02:19:51Z", "salary": {"currency": null, "max": null, "min": null, "period": "monthly", "term": null}, "salary_visible": false, "title_keywords": ["project manager"], "responsibilities": ["service delivery", "reporting", "management", "supervising", "data", "budgeting", "infrastructure", "daily operation", "checking", "e-commerce platforms", "communication", "recruitment", "planning"], "requirements": {"degrees": ["bachelor degree holder"], "majors": ["mathematics", "computer science", "information technology"], "languages": ["english", "mandarin"], "language_level": ["good command"], "hard_skills": ["qlikview", "plus", "data management", "azure", "pos", "e-commerce", "devops", "vendor", "tableau", "aws"], "soft_skills": ["communication skills", "confidence", "hands-on", "smooth", "interpersonal"], "languages_combined": [{"language": "english", "language_level": ["good command"]}, {"language": "mandarin", "language_level": ["good command"]}]}, "experience_required": {"duration": ["8 years"], "field": ["managerial", "operation", "e-commerce"]}}, {"job_id": "100003009049004", "location_code": "hk", "company": "Ambitious People Group", "job_title": "IT Lead (Node/PHP) | No prior leadership exp. needed", "description": "Company Description\n\nOur company is a market leader in financial publishing, research and business-to-business events and is building a global coverage on Asia's financial markets. Our regular virtual and physical events bring together the leading stalwarts of the financial services industry to discuss and debate topical issues affecting financial markets in Asia, Europe, Greater China Region, Asean, and other emerging markets. Our online channels deliver daily news to a growing base of subscribers interested to learn more about the Asia-Pacific region.\u00a0 Our research department conducts specialized client feedback surveys providing important market intelligence in a wide range of financial products. Our\u00a0monthly magazine covers capital flows and the activity of Asian issuers and global institutional investors.\u00a0\u00a0\n\nIT Project Manager (Web/Mobile App Developer)\n\nLead a team of developers to perform full software development life cycle\nAssist in operating systems development and maintenance projects\nManage the IT projects assigned by supervisor\nStudy, analyst, design, program, test, document, implement and support\nConduct user requirement studies and recommend appropriate automations\nAnalyse, design and develop procedures for process improvement\nPlan and coordinate application system testing, installation, training and support\nAd-hoc duties as assigned\n\nJob requirements\n\nTertiary educated in Computer Science or relevant disciplines\nMinimum 3-5 years\u2019 relevant working experience\nExperience in Web/Mobile App Development, CRM, CMS\nStrong knowledge in PHP, MySQL, Laravel, javascript, html CSS\nExcellent command of spoken and written English\nStrong negotiation skills and experienced with problem resolution", "employment_types": ["Full Time", "Permanent"], "selling_points": ["Startup working environment", "Hands on IT Lead", "Leadership training will be provided"], "locations": ["Not Specified"], "categories": ["Information Technology (IT)", "Application Specialist - Software", "IT Project Management / Team Lead", "Software Development"], "post_time": "2022-01-14T07:54:02Z", "salary": {"currency": "HKD", "max": 54999, "min": 35000, "period": "monthly", "term": null}, "salary_visible": true, "title_keywords": ["lead"], "responsibilities": ["user requirement", "online channels", "installation", "mobile app", "software", "maintenance", "ad-hoc duties", "design and develop", "procedures", "design", "plan and coordinate", "application system", "lead a team", "testing", "resolution", "analyse", "operating systems"], "requirements": {"degrees": [], "majors": [], "languages": ["english"], "language_level": ["excellent"], "hard_skills": ["maintenance", "web", "php", "application system", "html", "mobile", "javascript", "css"], "soft_skills": ["negotiation skills", "ad-hoc duties"], "languages_combined": [{"language": "english", "language_level": ["excellent"]}]}, "experience_required": {"duration": ["minimum 3-5 years"], "field": ["development", "relevant working experience"]}}, {"job_id": "100003009051492", "location_code": "hk", "company": "Asia Airfreight Terminal Co., Ltd.", "job_title": "Programmer - Fresh graduates are welcome", "description": "Responsibilities\n\nOversee the infrastructure support and responsible for in-house application system design, development and deployment for offshore offices.\nEnsure IT operation is meeting with compliance standards.\nSupport our business needs for IT system and tools for different offshore offices.\nPerform any ad-hoc duties as assigned.\n\nRequirements\n\nDegree holder in Computer Science or relevant discipline.\n7 or above years exp in development/supporting ERP application or similar web-based applications.\nProficient in PHP, HTML, JS, CSS, jQuery, MySQL.\nDevelopment exposure and knowledge in ASP.NET, C#, VB.NET, MSSQL Server, etc will be plus.\nProficient in both written and spoken English and Chinese.\nPrevious work experience in printing industry will be an advantage.\nBe passionate about supporting our business needs for IT system and tools as well as giving good service to all users.\nWilling to travel upon request.\nStation in Dongguan\n\n\u00a0Candidate with more experience will be considered for the role of Asst. IT Manager\n\nWe offer a competitive remuneration package to successful candidate. Interested parties please send your full resume and expected salary by clicking \u2018Apply Now\u2019.\n\nThe right candidate may join our company before or after Lunar New Year Holiday.\n\n\n(All personal information will be treated in strict confidentiality)", "employment_types": ["Full Time", "Permanent"], "selling_points": ["5-day week, double pay, performance bonus", "Bachelor Degree in Computer Science", "Fresh graduates are welcome"], "locations": ["Airport Area"], "categories": ["Information Technology (IT)", "IT Project Management / Team Lead", "Software Development", "Others", "Student / Fresh Graduate / No Experience"], "post_time": "2022-01-16T04:38:40Z", "salary": {"currency": null, "max": null, "min": null, "period": "monthly", "term": null}, "salary_visible": false, "title_keywords": ["programmer"], "responsibilities": ["compliance", "infrastructure", "application system", "design", "ad-hoc duties"], "requirements": {"degrees": ["degree holder"], "majors": ["computer science"], "languages": ["english", "chinese"], "language_level": ["proficient"], "hard_skills": ["server", "plus", "php", "jquery", "html", "erp", "web-based applications", "mssql", "css", "c#"], "soft_skills": ["passionate about"], "languages_combined": [{"language": "english", "language_level": ["proficient"]}, {"language": "chinese", "language_level": ["proficient"]}]}, "experience_required": {"duration": [], "field": []}}, {"job_id": "100003009045820", "location_code": "hk", "company": "Kinetix Systems Ltd", "job_title": "Pre-sales Solution Manager / Consultant", "description": "Main Responsibilities:\n\nDefine the overall objective of the project and the related key requirements in collaboration with other key stakeholders.\nDevelop Requests for Proposals (RFP) for external services\nIdentify the resources required locally and globally as well as the schedules for project implementation.\nPlan and schedule project milestones and track progress against goals in each phase to ensure that projects remain on track.\nCoordinate and collaborate with the market, vendors, regional and global teams to ensure that all parties are aligned and working successfully towards the end outcome.\nProactively identify and resolve issues and obstacles to ensure minimal disruption to the progress of the project.\nDesign and maintain technical and project documentation to ensure information is recorded and accessible when required.\nEnsure all deliverables and delivered on schedule within the scope and within budget\nReport on progress updates regularly to keep key stakeholders informed.\n\nJob Qualifications:\n\nDegree holder in Computer Science, Information Technology or related discipline.\nAt least 3 years of\u00a0experience in IT Project Management, with hands-on experience in a vendor environment.\nUnderstanding of systems analysis and design.\nAbility to handle multiple projects simultaneously.\nExperience working in an Agile development environment.\nExcellent written and verbal communication skills in both English and Chinese.\nFlexible for stationing in China or frequent travel between HK & China is a must\nImmediately available is highly preferred\n\nWe offer:\n\nFive-day work week\nAttractive remuneration package\nYear-end bonus\nMedical, dental and life insurance\nBirthday leave\nFree products and staff discount\nPlease send your full resume (with your availability, current and expected salary) via\u00a0APPLY NOW\u00a0button.\u00a0 You may consider your application unsuccessful if you do not hear from us within 6 weeks. Personal data collected will be used for recruitment purpose only.", "employment_types": ["Full Time", "Permanent"], "selling_points": ["Excellent in client facing & communication skills", "Key person in Inter-departmental collaboration", "Comprehensive remuneration package"], "locations": ["Kwun Tong"], "categories": ["Information Technology (IT)", "IT Project Management / Team Lead", "Technical / Functional Consulting", "Others"], "post_time": "2022-01-13T08:48:45Z", "salary": {"currency": null, "max": null, "min": null, "period": "monthly", "term": null}, "salary_visible": false, "title_keywords": ["manager", "consultant", "sales"], "responsibilities": ["collaborate with", "schedules", "budget", "agile development", "design", "communication", "maintain", "plan", "project documentation", "teams", "implementation", "develop", "schedule", "report", "analysis", "systems", "coordinate", "project management", "multiple projects"], "requirements": {"degrees": ["degree holder"], "majors": ["computer science", "information technology"], "languages": ["english", "chinese"], "language_level": ["excellent"], "hard_skills": ["agile", "analysis", "vendor", "project management", "documentation"], "soft_skills": ["flexible", "communication skills", "agile", "project management", "hands-on"], "languages_combined": [{"language": "english", "language_level": ["excellent"]}, {"language": "chinese", "language_level": ["excellent"]}]}, "experience_required": {"duration": ["at least 3 years"], "field": ["project management", "development", "it"]}}, {"job_id": "100003009042265", "location_code": "hk", "company": "Pathsight Limited", "job_title": "Project Manager / Assistant Project Manager - AV/ ELV projects", "description": "Key Responsibilities:\n\nSystem Support Manager shall oversee the overall technical and functional design and lead the support team of the System to set up and maintain the System environment including producing documentation.\n\nRequirements:\n\nThe System Support Manager shall possess:\n\na degree or above in computer science or equivalent;\nproficiency in both spoken and written English, Cantonese and Putonghua is a MUST;\nat least 8 years of IT experience including at least 4 years of system suuport experience for implementing at least one or more IT system on public Cloud infrastructure with auto-provisioning capability; solid experience from Implementation and Maintenance of Government project is highly preferred; and\nat least 4 years IT experience that covers the following areas:\n\nImplementing and supporting system architecture for a large scale of IT system with high-availability design features;\nResolving any problems arising during system design or implementation and on-going maintenance;\nGenerating a set of acceptance test requirements, together with the architects, test engineers, and the user, which determine that all of the high level requirements have been met and participating all related tests;\nActing as the Assistant Project Manager to assist Project Manager and work with other Maintenance Team members to provide System Support and Maintenance Services on the system architecture and infrastructure.\nBase in HK with occasional travelling to China;\nImmediate available is preferred.\nCompetitive remuneration package will be offered to the right candidate. Interested parties please send your full resume with\u00a0CURRENT\u00a0and\u00a0EXPECTED\u00a0SALARY\u00a0by clicking \"APPLY NOW\".", "employment_types": ["Full Time", "Permanent"], "selling_points": ["Minimum 4 years\u2019 relevant working experience", "Solid experience in AV / ELV Projects", "Project installation design & document submission"], "locations": ["Not Specified"], "categories": ["Information Technology (IT)", "Hardware", "IT Project Management / Team Lead", "Network & System"], "post_time": "2022-01-12T06:46:27Z", "salary": {"currency": null, "max": null, "min": null, "period": "monthly", "term": null}, "salary_visible": false, "title_keywords": ["project manager", "assistant project manager"], "responsibilities": ["documentation", "maintain", "design"], "requirements": {"degrees": ["degree or above"], "majors": ["computer science"], "languages": ["cantonese", "putonghua", "english"], "language_level": ["proficiency"], "hard_skills": ["system design", "maintenance"], "soft_skills": [], "languages_combined": [{"language": "cantonese", "language_level": ["proficiency"]}, {"language": "putonghua", "language_level": ["proficiency"]}, {"language": "english", "language_level": ["proficiency"]}]}, "experience_required": {"duration": ["at least 8 years", "at least 4 years"], "field": ["cloud infrastructure", "it", "maintenance", "it experience"]}}, {"job_id": "100003009044118", "location_code": "hk", "company": "Seamatch Asia Limited", "job_title": "Project Manager/ Business Analyst/ Project officer/ QA Trainee/ UAT Tester (Welcome Fresh)", "description": "Day-To-Day Responsibilities:\n\nRelationship:\n\nAble to maximize the value of the customer\u2019s investment in Lenovo products and services throughout the end to end customer lifecycle. The TAM manages customer escalations and acts as the customer\u2019s advocate.\nEffective ownership, communication, coordination, and facilitation of support service activities between the Customer and support teams, account teams, field service personnel, and customers.\n\nEscalation management:\n\nActs as a single point of contact for customer escalations and owns the coordination and oversight to problem solving efforts between customers, Support engineers, field service personnel, software support, investigation and analysis of product problems.\nDevelops and delivers post incident reports on all critical support incidents, adheres to customer support plans and relationships.\nUses complex analytical skills to recognize trends and improve performance.\n\nPrevention:\n\nRequires a general understanding of and technical competence in PC technologies.\nDevelops and coordinates proactive maintenance initiatives based on industry best practices and statistical data trends.\n\nOptimization:\n\nIdentifies and leads continuous improvement activities in support of customer or internal business processes.\n\nSupport:\n\nLeads complex service delivery processes, develops creative resolutions to complex problems and ensures contractual support service deliverables are understood and managed effectively.\n\nCollaboration:\n\nCompiles, analyzes and interprets statistical data and trends relating to service level and operational effectiveness.\n\nIn this role, you will be reporting to a Premier TAM Manager.\n\nKey Competencies Needed:\n\nSuperior knowledge of PC technology, market trends, vendor competition. Strong understanding of sales strategies and management principles.\nAbility to effectively interact and communicate with different levels of people.\nExcellent presentation, communications and interpersonal skills.\nProficient in Microsoft Office programs and PC technologies.\nExcellent organization skills, must be a self-starter who has experience in managing multiple initiatives simultaneously in a demanding and changing environment.\nAbility to build effective virtual teams and drive results through others in a complex cross-functional organization required.", "employment_types": ["Full Time"], "selling_points": ["Project Manager, Business analyst, QA", "Project Management", "SDLC, UAT, user requirement collection"], "locations": ["Not Specified"], "categories": ["Information Technology (IT)", "IT Project Management / Team Lead", "Product Management / Business Analyst", "Testing / QA"], "post_time": "2022-01-13T03:07:38Z", "salary": {"currency": null, "max": null, "min": null, "period": "monthly", "term": null}, "salary_visible": false, "title_keywords": ["trainee", "uat tester", "project officer", "project manager", "business analyst"], "responsibilities": ["service delivery", "reporting", "management", "communicate with", "software", "maintenance", "data", "analysis", "teams", "investigation", "communication", "reports", "contact", "coordination", "plans"], "requirements": {"degrees": [], "majors": [], "languages": [], "language_level": [], "hard_skills": ["maintenance", "microsoft office", "analysis", "vendor", "analytical skills", "problem solving", "pc"], "soft_skills": ["creative", "analytical skills", "communication", "problem solving", "interpersonal skills", "coordination", "organization skills", "proactive", "presentation", "superior"], "languages_combined": []}, "experience_required": {"duration": [], "field": []}}, {"job_id": "100003009050220", "location_code": "hk", "company": "STA Pacific Limited", "job_title": "Assistant Manager - IT Infrastructure (Fintech, 45 - 50K)", "description": "We are searching on behalf of a major bank for\u00a0IT Business Analyst/ Senior Business Analyst\u00a0to work on\u00a0Life Insurance System Projects\u00a0in a\u00a0Major Bank.\n\nResponsibilities:\n\nPerform business analysis and user requirement studies for various banking systems\nAct as the key interface between business users and technical developers\nGuide technical developers to provide a business solution\nFormulate Test Plans and conduct User Acceptance Test\nPrepare system documentation such as requirements specifications\nManage IT project implementation and testing\u00a0\n\nRequirements:\n\n\nDegree in Computer Science, Actuarial Science, Finance or Accounting or IT related discipline\nSolid working experience in Insurance Company or Banking Industry\nGood knowledge in Life Insurance Products\nGood communication skill with business users\nBenefits:\nAttractive remuneration will be offered to the successful candidates.\nExcellent opportunity to further develop your professional skills in working on a major Financial Banking Project in a\u00a0major bank.\n\nIf you are interested, please send your resume in MS Word format, specifying your availability, current and expected salaries to:\n\njobs @itsolutions.com.hk\n\nor\n\nPlease click the Apply Now button and attach your cv in MS Word Format, specifying your availability, current and expected salaries.\n\nPersonal data collected will be used for recruitment purposes only.\n\nIT Solutions Ltd.\nSuite 2102, 21st Floor\nLucky Building\n39 Wellington Street\nCentral, Hong Kong\n\n(P.S.\u00a0 We do not process applications from overseas for this position)", "employment_types": ["Full Time", "Permanent"], "selling_points": ["6-10 yrs IT infrastructure design & engineer exp.", "Bachelor Degree of Computer Science / IT", "Solid exp on System & Server, Network and Security"], "locations": ["Yau Ma Tei"], "categories": ["Information Technology (IT)", "IT Project Management / Team Lead", "Security", "Network & System"], "post_time": "2022-01-15T03:50:56Z", "salary": {"currency": null, "max": null, "min": null, "period": "monthly", "term": null}, "salary_visible": false, "title_keywords": ["assistant manager"], "responsibilities": ["user requirement", "system documentation", "systems", "testing", "specifications", "banking", "business analysis", "plans", "it project implementation"], "requirements": {"degrees": ["degree"], "majors": ["actuarial science", "finance", "it", "computer science", "accounting"], "languages": [], "language_level": [], "hard_skills": [], "soft_skills": ["communication skill"], "languages_combined": []}, "experience_required": {"duration": [], "field": ["banking industry", "insurance"]}}, {"job_id": "100003009037339", "location_code": "hk", "company": "ServiceOne Limited", "job_title": "IT Project Coordinator/ Assistant Project Manager", "description": "Job Responsibilities\u00a0\n\n\n\nAssist the Department to lead the customer services team and help monitoring the overall performance of the team with quality deliverables in term of accuracy and completeness within the agreed turnaround time (TAT).\nManage regular quality assurance checking on processes of all customer and policy services.\u00a0 Coach and develop staff members to ensure the development of talent and that the team is well-trained and equipped with the appropriate knowledge for work.\nHandle and review complaints received from all channels, carry out investigation and liaise with relevant parties to obtain necessary information for fact finding, propose resolutions, obtain approval from higher level and proper documentation of complaint details for further analysis and regular reporting to senior management.\nPrepare monthly KPI reports and ensure that all performance, risk and compliance reporting is completed timely with quality.\nEnsure all incoming / outgoing calls, customer feedback and complaints are handled properly in accordance with the respective procedures within the required service standard.\u00a0\u00a0 Provide professional and excellent customer services in resolving day-to-day enquiries and requests from customers and various distribution channels within the service pledge.\nAuthorize and approve all necessary policy changes transactions or exceptions as per the agreed scheme of delegation.\u00a0 Monitor operational performance and risks, addressing trends and issues as appropriate.\nParticipate in system enhancement projects for business growth and enhancing service efficiency.\u00a0\u00a0 Provide related system requirements, prepare test plans and conduct testing accordingly while ensuring the target timeline is met.\nMaintain an understanding and awareness on key aspects of life insurance, legislation, compliance and the market\u2019s best practices.\nWork closely with the Department Head to develop effective working practices which ensure effective and timely responses to the queries from customer and various distribution channels.\u00a0 Ensure the internal operational procedures and processes are most up to date and all activities are compliant with local regulations and company policies.\nKeep abreast of changing customer expectation by collecting feedback from internal / external customer groups periodically and initiate service enhancement plan to deliver the customer expectation as identified.\nSupport cross-selling opportunities and /or up-selling business initiatives as and when required.\nPerform other ad-hoc tasks/projects as assigned by the Department Head.\n\nJob Requirements\n\n\nUniversity graduate with FLMI & ACS would be an advantage\nSeasoned, respected leader with a minimum of 5 years of experience in Customer Services and Operations\nSolid organizational, management, administrative and human relations skills in a style which exhibits maturity, leadership and teamwork\nDemonstrated strong planning, organization, leadership and change management capabilities\nAbility to develop relationships across all levels of the Company, as well as externally\nStrong communication, interpersonal and presentation skills\nStrong ability to multi-tasking and work under pressure with tight deadlines, while working effectively with the team\nAbility to succeed in a highly matrix environment with competing priorities\nKnowledge of life insurance products and solid understanding of insurance operations\nSelf-driven, able to make sound and high impact decision under high pressure environment\nCustomer focused and result oriented with strong interpersonal skills\nCommit to building a high performing team, drive result and always look for improvements\nExcellent time management and people management skill\nDemonstrate quality leadership and ability to inspire and motivate subordinates\nGood command of both spoken and written English and Chinese\nProficiency in MS applications\n\n\u00a0We are an equal opportunity employer and welcome applications from all qualified candidates.\n\nPlease send your full resume both in English and Chinese stating present and expected salary to Human Resources Manager by clicking APPLY NOW.\n\nAll data provided will be treated in the strictest confidence and used only for recruitment related purposes. All applications will be destroyed after 6 months of submission.\n\nOnly short listed candidates will be contacted.", "employment_types": ["Full Time", "Permanent"], "selling_points": ["Multi-vendors & regional exposure", "Good interpersonal & communication skills", "Retail industry"], "locations": ["Kwun Tong"], "categories": ["Information Technology (IT)", "IT Project Management / Team Lead", "IT Management", "Technical / Functional Consulting"], "post_time": "2022-01-11T02:33:41Z", "salary": {"currency": null, "max": null, "min": null, "period": "monthly", "term": null}, "salary_visible": false, "title_keywords": ["assistant project manager", "it project coordinator"], "responsibilities": ["regulations", "business initiatives", "service standard", "quality", "transactions", "maintain", "plan", "liaise with", "plans", "senior management", "compliance", "monitor", "develop", "customer services", "testing", "operational procedures", "reports", "reporting", "monitoring", "review", "checking", "investigation", "procedures", "documentation", "enhancement projects", "policies", "analysis", "ad-hoc tasks", "insurance"], "requirements": {"degrees": ["university graduate"], "majors": [], "languages": ["english", "chinese"], "language_level": ["good command"], "hard_skills": ["make", "ms applications"], "soft_skills": ["confidence", "focused", "organizational", "teamwork", "driven", "communication", "presentation skills", "multi-tasking", "result oriented", "interpersonal skills", "time management", "leadership", "interpersonal", "work under pressure"], "languages_combined": [{"language": "english", "language_level": ["good command"]}, {"language": "chinese", "language_level": ["good command"]}]}, "experience_required": {"duration": ["minimum of 5 years"], "field": ["customer services"]}}, {"job_id": "100003009050148", "location_code": "hk", "company": "OCBC Wing Hang Bank Limited", "job_title": "Business Analyst -- Securities Brokerage Trading and Settlement Systems", "description": "Requirements:\nHigher Diploma or above in Computer Science, Information System or related disciplines\nAt least 3 years\u2019 working experience in IT projects and IT technical support. Prior experience in non-governmental organization (NGO), welfare or medical sector will be an added advantage\nSolid experiences in information technologies support, ICT, VC (e.g. Zoom, Teams, Google Meet) support, Windows administration, networking troubleshooting, WIFI, firewalls and IT security issues handling\nProficient in Microsoft Windows technologies, Office applications and O365\nAttention to details with sound knowledge of technical implementation and documentation\nGood communication skills, time management, able to manage and prioritize tasks effectively\nGood team player with strong interpersonal, organizing and problem solving ability\nGood command of both written and spoken Chinese and English\nResponsibilities:\nProvide IT technical support in software and hardware, VC (e.g. Zoom, Teams, Google Meet), and desktops troubleshooting, installation and configuration, IT security issues; and provide technical support in different service units of Pok Oi Hospital\nProvide daily IT administrative support, documentation and procurement assistance to IT team including upkeeping project documentation, technical and user manuals etc.\nAssist in project support including requirements collection from different stakeholders and consolidation of user requirements, and project implementation\nCoordinate with users, external vendors to ensure quality job and project tasks delivery\nResponsible for system testing including user acceptance testing (UAT) and help in production rollouts including end-user training\nWork as a team proactively and constantly to look for potential system improvement opportunities\nAssist in ad hoc projects and IT related tasks as assigned\nCandidate with less experiences will be considered as Assistant IT Officer\nThe appointment will be made on a fixed-term contract basis. Interested candidates are invited to apply by sending full resume with current salary, expected salary and date available to Human Resources Department, Pok Oi Hospital Board, UG/F., Pok Oi Hospital Jockey Club Care & Attention Home Building, Au Tau, Yuen Long or by email via \"Apply Now\"\u00a0on or before 26 January 2022.\u00a0 For more details of Pok Oi Hospital, please visit our website http://www.pokoi.org.hk.\n\u00a0(All personal data collected from applicants will be kept confidential and used for employment-related purpose only. \u00a0The Board is an equal opportunity employer.)", "employment_types": ["Full Time", "Permanent"], "selling_points": ["Trading & settlement system projects", "5 yrs in business analysis/digital project manage", "Familiar with SFC/HKMA related trading system"], "locations": ["Sheung Wan"], "categories": ["Banking / Finance", "Dealing & Trading", "Equities / Capital Markets", "Information Technology (IT)", "IT Project Management / Team Lead"], "post_time": "2022-01-14T09:52:10Z", "salary": {"currency": null, "max": null, "min": null, "period": "monthly", "term": null}, "salary_visible": false, "title_keywords": ["business analyst"], "responsibilities": ["installation", "software", "it technical support", "uat", "configuration", "technical support", "teams", "troubleshooting", "implementation", "it administrative support", "coordinate with", "hardware", "quality", "testing", "ad hoc projects", "documentation", "project documentation"], "requirements": {"degrees": ["higher diploma or above"], "majors": ["related disciplines", "computer science"], "languages": ["english", "chinese"], "language_level": ["good command"], "hard_skills": ["o365", "vc", "office applications", "information system", "problem solving", "documentation"], "soft_skills": ["communication skills", "good team player", "troubleshooting", "prioritize", "problem solving", "attention to details", "time management", "interpersonal"], "languages_combined": [{"language": "english", "language_level": ["good command"]}, {"language": "chinese", "language_level": ["good command"]}]}, "experience_required": {"duration": ["at least 3 years"], "field": ["it", "it technical support", "medical"]}}, {"job_id": "100003009048749", "location_code": "hk", "company": "United Asia Finance Limited", "job_title": "Assistant Vice President, Enterprise Application  (FinTech and Innovation Department)", "description": "A large bank urgently requires following high calibre to join their team:\n\nResponsibilities:\n\n\u00a0Support Financial projects for participation in system enhancements relating to FPS projects and the systems involved FPS system, Payment systems, AML systems, Reporting system and other related systems.\n\u00a0Work between users and IT team for the interpretation of the business requirement\nAssist users to review the project deliverables such as Functional Requirements & Cell logic provided by Vendor\nCoordinates with IT colleagues and vendors in setup and configuration of systems.\nSupport system implementation among Software Development Life Cycle\nCoordinates with users and IT colleagues in arranging the system testing, create UAT test cases and conduct testing\nMaintain and support the full ranges of defects management and processes \u00a0\nAssist to perform ad hoc assignments as required\n\nRequirements:\n\nDegree Holder in Information Technology or related disciplines\nAt least 3 years\u2019 experience in banking or financial industry or having relevant job experience\nKnowledge in payment system\nExperience to handle project with skill set on managing the whole project timeline\nGood communication skills, self-motivated and well-organized\nGood command of written and spoken English and Chinese\n\nOur client offers attractive remuneration package to right candidates. Interested parties please send full resume with present and expected salary to us.\n\n(Data collected will be used for recruitment purpose only)", "employment_types": ["Full Time", "Permanent"], "selling_points": ["Double pay and discretionary bonus", "Minimum 8 years of IT experiences", "Degree or above in Computer Science"], "locations": ["Wan Chai"], "categories": ["Information Technology (IT)", "IT Project Management / Team Lead", "IT Management", "Software Development"], "post_time": "2022-01-14T07:12:58Z", "salary": {"currency": null, "max": null, "min": null, "period": "monthly", "term": null}, "salary_visible": false, "title_keywords": ["assistant vice president"], "responsibilities": ["reporting", "management", "aml", "software", "uat", "project deliverables", "configuration", "review", "systems", "implementation", "testing", "payment", "maintain", "ad hoc assignments", "setup"], "requirements": {"degrees": ["degree holder"], "majors": ["related disciplines", "information technology"], "languages": ["english", "chinese"], "language_level": ["good command"], "hard_skills": [], "soft_skills": ["communication skills", "self-motivated", "well-organized"], "languages_combined": [{"language": "english", "language_level": ["good command"]}, {"language": "chinese", "language_level": ["good command"]}]}, "experience_required": {"duration": ["at least 3 years"], "field": ["financial industry", "banking"]}}, {"job_id": "100003009050219", "location_code": "hk", "company": "ICO Limited", "job_title": "System Analyst (Java and Banking project)", "description": "We are looking for a detail-minded and motivated ERP Manager to join our friendly, professional and dedicated in IT Department based here in Hong Kong.\u00a0\n\nKey Responsibilities:\u00a0\u00a0 \u00a0 \u00a0 \u00a0 \u00a0 \u00a0 \u00a0 \u00a0 \u00a0 \u00a0 \u00a0 \u00a0 \u00a0 \u00a0 \u00a0 \u00a0 \u00a0 \u00a0 \u00a0 \u00a0 \u00a0 \u00a0 \u00a0 \u00a0 \u00a0 \u00a0 \u00a0 \u00a0 \u00a0 \u00a0 \u00a0 \u00a0 \u00a0 \u00a0 \u00a0\u00a0\nAssist and involve in JDE upgrade project\nDirect application support and troubleshooting to resolve problem correctly\nIdentify and communicate risks associated with process, systems and projects\nEnsure that application support is conducted in a controlled manner and is aligned to IT and business requirements\u00a0\nAssist in the maintenance of user and procedure manuals and the creation and maintenance of application support documentations\nDomestic and international travel may be required (Pending during pandemic)\nWhat you will need to succeed:\u00a0 \u00a0\u00a0\nBachelor's degree holder in IT relevant disciplines\nSolid experience and understanding of ERP systems (JD Edwards E1 preferred) and supporting integration with Third-Party systems (EDI, API etc.)\nExcellent analytical and business analysis skills with a keen attention to details\nGood problem solving and root cause analysis skills\nKnowledge of JDE E1 Orchestrator configuration and support would be advantageous\u00a0\nExcellent customer service skills and international skills, with a focus on rapport-building, listening, questioning and clear communication\nHighly self-motivated and directed\nProficient in written and spoken in Cantonese, Mandarin and English\nWe offer competitive remuneration package including 5-days\u2019 work, flexible working hours, medical & group life insurance, extra caring leaves and discretionary bonus\u00a0to the right candidate. Interested parties please send your full resume with current & expected salary by clicking\u00a0\"Apply Now\"\u00a0with attention to\u00a0Human Resources Department.\nAll applications and enquiries will be handled in the strictest confidence and personal data collected will be used for recruitment purposes only. All the applicant contact details will be kept for 6 months only.", "employment_types": ["Full Time"], "selling_points": ["13 months salary. near MTR station", "Well structured project team", "Banking App & development"], "locations": ["Eastern Area"], "categories": ["Information Technology (IT)", "Application Specialist - Software", "IT Project Management / Team Lead", "Software Development"], "post_time": "2022-01-15T19:11:42Z", "salary": {"currency": null, "max": null, "min": null, "period": "monthly", "term": null}, "salary_visible": false, "title_keywords": ["system analyst"], "responsibilities": ["maintenance", "configuration", "analysis", "systems", "troubleshooting", "communication", "customer service", "business analysis", "insurance"], "requirements": {"degrees": ["bachelor", "degree holder"], "majors": ["it"], "languages": ["cantonese", "english", "mandarin"], "language_level": ["proficient"], "hard_skills": ["erp systems", "maintenance", "analysis", "erp", "problem solving", "integration", "focus", "documentations"], "soft_skills": ["detail-minded", "customer service skills", "self-motivated", "flexible", "keen", "troubleshooting", "problem solving", "clear", "communication", "motivated", "friendly", "attention to details", "controlled", "focus"], "languages_combined": [{"language": "cantonese", "language_level": ["proficient"]}, {"language": "english", "language_level": ["proficient"]}, {"language": "mandarin", "language_level": ["proficient"]}]}, "experience_required": {"duration": [], "field": []}}, {"job_id": "100003009044860", "location_code": "hk", "company": "Wellesley Associates Limited", "job_title": "IT Project Specialist - Premium MNC (European Brand) - ERP/SQL - Perm - 35K + Bonus", "description": "Responsibilities:\n\nPlanning and coordination of Web/Mobile application projects, ensuring project is on time, according to the specification and\u00a0delivery with quality standards\nRequirements gathering, documentations and be able to communicate with customers independently\nLiaise with internal external parties for project development\nCapable to handle customer's requests and expectation through out the development cycle\n\n\nRequirements:\n\nDegree holder with project experiences in Mobile/Web development\nExcellent interpersonal and analytical skills\nWell time management with multi-tasking skills\nAttention to details\nLess experienced candidate will be considered as Project Executive\nImmediate availability is preferred\n\n\nBenefits:\n\nFive-day work week (Flexible working hours)\nMedical allowance\nPerformance bonus\nBirthday leave\n\nInterested parties please send full resume with availability and expected salary to us by clicking \"Apply Now\"\n\nPersonal data will be used for recruitment purposes only.", "employment_types": ["Full Time"], "selling_points": ["IT Project Specialist", "ERP Software/ SQL Database/ SQL Query", "Retail MNC/ Western Culture"], "locations": ["Not Specified"], "categories": ["Information Technology (IT)", "IT Project Management / Team Lead", "Support", "Product Management / Business Analyst"], "post_time": "2022-01-13T06:28:18Z", "salary": {"currency": null, "max": null, "min": null, "period": "monthly", "term": null}, "salary_visible": false, "title_keywords": ["specialist"], "responsibilities": ["communicate with", "external parties", "quality", "coordination", "liaise with", "planning"], "requirements": {"degrees": ["degree holder"], "majors": [], "languages": [], "language_level": [], "hard_skills": ["mobile", "web development", "analytical skills"], "soft_skills": ["analytical skills", "attention to details", "multi-tasking skills", "time management", "interpersonal"], "languages_combined": []}, "experience_required": {"duration": [], "field": ["development"]}}, {"job_id": "100003009042245", "location_code": "hk", "company": "Fairwood Fast Food Ltd", "job_title": "Digital Engagement Manager", "description": "Responsibilities\n\nUtilize Infrastructure as a Service (IaaS) from cloud providers, such as AWS, Aliyun and Huawei, to provide computing resources for running the company\u2019s enterprise applications;\nInstall, configure and maintain Linux and Microsoft Windows Servers on cloud platform and company\u2019s own data center;\nAdminister the company networks connecting offices, shops, clinics, remote offices and data center;\nAdminister Cisco, FortiGate and Dell firewall and switch;\nInstall system patches and rollout new system;\nAssist in formulating ITSM policies and procedures;\nFormulate system and data backup and recovery procedures;\nDocument disaster recovery and incident response procedures;\nDocument systems infrastructure; and\nManage the team and resolve system incidents.\n\nRequirements\n\nBachelor / Higher Diploma holder in Computer Studies or related disciplines;\n5 years working experience in Information Technology or telecommunication field;\n3+ years of experience in administering cloud platforms (AWS or Aliyun or Huawei);\nHolder of IT Certificate, e.g. ITIL, Linux, CCNP, CISSP certification or equivalent will be an advantage;\nFamiliar with ITSM policies and procedures;\nHands-on experience on Cisco/FortiGate/Dell firewall and switch;\nHaving knowledge on telephony systems and contact center solutions will be an advantage.\nSelf-motivated, detail-oriented, and able to work under pressure independently;\nStrong sense of responsibility, willing to take ownership of assigned tasks;\nGood in analytical, problem-solving, interpersonal and communication skills;\nGood command of both written and spoken in Cantonese, Mandarin and English; and\n5-days work and shift duty required on Saturday", "employment_types": ["Full Time", "Permanent"], "selling_points": ["Drive digital initatives in line with business", "Ensure the deliverable quality and communication", "Degree w/10-yr exp digital/ eCommerce system"], "locations": ["North Point"], "categories": ["Hospitality / F & B", "Food & Beverage", "Information Technology (IT)", "IT Project Management / Team Lead", "IT Management"], "post_time": "2022-01-12T06:43:17Z", "salary": {"currency": null, "max": null, "min": null, "period": "monthly", "term": null}, "salary_visible": false, "title_keywords": ["manager"], "responsibilities": ["systems infrastructure", "data", "policies", "infrastructure", "procedures", "maintain"], "requirements": {"degrees": ["certificate", "bachelor", "higher diploma holder"], "majors": ["related disciplines", "it", "computer studies"], "languages": ["cantonese", "english", "mandarin"], "language_level": ["good command"], "hard_skills": ["itil", "linux", "ccnp", "switch", "problem-solving", "aws", "firewall"], "soft_skills": ["communication skills", "self-motivated", "independently", "sense of responsibility", "problem-solving", "detail-oriented", "hands-on", "interpersonal", "work under pressure"], "languages_combined": [{"language": "cantonese", "language_level": ["good command"]}, {"language": "english", "language_level": ["good command"]}, {"language": "mandarin", "language_level": ["good command"]}]}, "experience_required": {"duration": ["5 years", "3+ years"], "field": ["information technology"]}}, {"job_id": "100003009035782", "location_code": "hk", "company": "Macroview Telecom Limited", "job_title": "Senior Project Manager / Project Manager", "description": "Our client is a well-known banking corporation with solid business in different areas. As part of their technological transformation, they are looking for an IT Project Manager to work on their internal system enhancement. Candidates must have strong knowledge of banking products and their relevant operations. Fluency in both English and Cantonese is mandatory.\n\nClient Details\n\nOur client is a well-known banking corporation with solid business in different areas. With more than 100 years of history operating in major financial hubs, this bank has continued to provide top-tier services to its clients. They have been providing banking and financial solutions across the retail, commercial, and corporate sectors.\n\nIn response to the trend of digitalization in banking, they are currently going through a major technological transformation. With that said, our client will be looking for an IT Project Manager to join their team, leading the project members in delivering the latest IT solutions to various business units. The successful candidates will work with stakeholders across different regions while having exposure to the most updated tools. Candidates must have strong knowledge of retail banking products and their relevant operations. Fluency in both English and Cantonese is mandatory.\n\nDescription\n\nJob Responsibilities:\n\nManage the delivery of project and system implementation for the bank\nProvide project budgeting and monitor the end-to-end project activities\nWork closely with different stakeholders within the business\nProactively manage external vendors in the project deliverable\nMaintain the best practices of the Agile/Scrum project methodology\n\nProfile\n\nJob Requirements:\n\nBachelors Degree or above in Information Technology, Finance, Banking, or related disciplines\nExperience in Project Management, with a track record in delivering banking projects\nProven experience in managing sizeable Agile/Scrum projects\nCapable of managing multiple projects simultaneously with complex requirements\nProficient in English and Chinese communication, both written and spoken\nEligible to work in Hong Kong\n\nJob Offer\n\nCareer Progression in Banking\nExposure to Sizeable Scale Project\nExperience in Full Project Life-cycle\nAgile Project Management Tools\nDynamic Working Environment\nCompetitive Salary\nGenerous Balance of Annual Leaves\nConvenient Working Location\n\nTo apply online please click the 'Apply' button below. For a confidential discussion about this role please contact Sedrick Chan on +852 2258 3417.", "employment_types": ["Full Time", "Permanent"], "selling_points": ["3+ years PM experience or above", "Coordinate with all project stakeholders", "Deliver project implementation service"], "locations": ["Tsing Yi"], "categories": ["Engineering", "Engineering Project Management", "Information Technology (IT)", "IT Project Management / Team Lead", "Others"], "post_time": "2022-01-10T08:25:02Z", "salary": {"currency": null, "max": null, "min": null, "period": "monthly", "term": null}, "salary_visible": false, "title_keywords": ["project manager", "senior project manager"], "responsibilities": ["budgeting", "maintain", "monitor", "implementation"], "requirements": {"degrees": ["degree or above"], "majors": ["related disciplines", "finance", "information technology"], "languages": ["english", "chinese"], "language_level": ["proficient"], "hard_skills": ["project management", "dynamic", "agile"], "soft_skills": ["capable", "agile", "communication", "project management", "dynamic"], "languages_combined": [{"language": "english", "language_level": ["proficient"]}, {"language": "chinese", "language_level": ["proficient"]}]}, "experience_required": {"duration": [], "field": ["project management", "banking"]}}, {"job_id": "100003009042922", "location_code": "hk", "company": "Tahoe Life Insurance Company Limited", "job_title": "Senior Manager, IT Infrastructure and Operations", "description": "Responsibilities:\n\nParticipate in In-house application development including\u00a0design, development, and testing.\nDevelop frontend interfaces or backend systems, and APIs for mobile and web applications\nGathering user requirements and ensuring the platforms are able to meet the business needs.\nPerform cloud-native application development\nPrepare related technical documents.\u00a0\nRequirements:\n\nDegree / Higher Diploma in Computer Science, Information Technology or related disciplines.\n1+ years' relevant experience or above will be considered as\u00a0Software Engineer.\nFresh graduation with relevant project/ internship experience will also be considered.\nGood to have either programming of Node JS/ React JS/ Angular/ Vue.JS/ NoSQL\nHands-on development experience\u00a0\nFintech project experience is preferable\u00a0\nGood communication, presentation, and interpersonal skills\nCandidate with more experience\u00a0will be considered\u00a0as a\u00a0 Project Lead", "employment_types": ["Full Time", "Permanent"], "selling_points": ["IT Infrastructure and Operations", "IT Support", "Cloud Technologies"], "locations": ["Tai Koo"], "categories": ["Information Technology (IT)", "IT Project Management / Team Lead", "Support", "IT Management"], "post_time": "2022-01-12T09:14:39Z", "salary": {"currency": null, "max": null, "min": null, "period": "monthly", "term": null}, "salary_visible": false, "title_keywords": ["senior manager", "operations"], "responsibilities": ["systems", "design", "develop", "testing", "application development"], "requirements": {"degrees": ["diploma", "degree"], "majors": ["related disciplines", "computer science", "information technology"], "languages": [], "language_level": [], "hard_skills": ["angular", "programming", "react"], "soft_skills": ["communication", "hands-on", "interpersonal skills", "presentation"], "languages_combined": []}, "experience_required": {"duration": ["1+ years"], "field": ["development", "relevant experience"]}}, {"job_id": "100003009038435", "location_code": "hk", "company": "New Media Group", "job_title": "Project Executive/Assistant Project Manager(IT)", "description": "Job Responsibilities:\n\nResponsible for planning, directing and coordinating the system development / IT projects to ensure the project is delivered as scheduled and quality of deliverables\nResponsible for system design, development and support of the application systems\nManage project processes, documentation, progress reporting, status meeting and escalation effectively\nWork closely with users and vendors for system requirement analysis, effort estimation, design, development, implementation and testing on banking project\nIdentify dependencies and potential risks across project, take measure to resolve issues and mitigate risks\nManage change control in different stages throughout the project life cycle\nTroubleshoot problems and propose the recommendation to resolve the issue and liaise with developers on fixing and resolving technical issue\nLiaison and coordinate effectively with both internal and external parties for system integration design\n\nJob Requirements:\n\nDegree or above with major in Information Technology, Computer Science or related disciplines\nOver 8 years of application development experience in Banking Systems with proven experience in leading and managing the delivery of system development projects in a structured environment\nProven track record of designing, running, and managing sizable banking projects is a plus\nGood knowledge of modern web and app development practices, including security and databases\nFamiliarity with frontend, backend web technologies and RESTFUL APIs\nExperience in Agile methodologies (Scrum, Kanban) and tools such as Jira and Confluence.\nProficiency with DevOps and CI/CD tools and methodology\nStrong presentation, negotiation, organization, analytical and problem-solving skills\nGood command in both written and spoken English and Chinese\n\nWe offer attractive remuneration package which includes double pay and discretionary bonus. Interested parties please send your CV indicating your current salary, expected salary and availability to HR Department, by clicking \u201cApply Now\u201d\n\n(Personal data collected will be treated in the strictest confidence and will be handled by authorized personnel for recruitment-related purposes only. Applicants who do not hear from us within 3 months may consider their application unsuccessful and their data will be destroyed within 24 months of receipt.)", "employment_types": ["Full Time", "Permanent"], "selling_points": ["Project Implementation", "Collaborating with different parties", "Fresh graduates are welcome"], "locations": ["Kwun Tong"], "categories": ["Information Technology (IT)", "IT Project Management / Team Lead", "Product Management / Business Analyst"], "post_time": "2022-01-11T06:53:19Z", "salary": {"currency": null, "max": null, "min": null, "period": null, "term": null}, "salary_visible": false, "title_keywords": ["project executive", "assistant"], "responsibilities": ["reporting", "control", "analysis", "internal and external parties", "quality", "implementation", "design", "testing", "coordinate", "liaise with", "system design", "troubleshoot", "banking", "documentation", "application systems", "planning"], "requirements": {"degrees": ["degree or above"], "majors": ["related disciplines", "computer science", "information technology"], "languages": ["english", "chinese"], "language_level": ["good command"], "hard_skills": ["plus", "agile", "web", "devops", "databases", "problem-solving skills", "web technologies"], "soft_skills": ["negotiation", "agile", "problem-solving skills", "structured", "presentation"], "languages_combined": [{"language": "english", "language_level": ["good command"]}, {"language": "chinese", "language_level": ["good command"]}]}, "experience_required": {"duration": ["8 years"], "field": ["system development", "application development", "banking"]}}, {"job_id": "100003009034717", "location_code": "hk", "company": "Multisoft Limited", "job_title": "Project Coordinator / Project Manager (IT Project)", "description": "One of our clients is now looking for a high calibre candidate to fill the following position:\n\nDegree or above in computer science or related degree;\nGood experience in software development in AI, BI and IoT Technology;\nExperience in managing software team;\n\nRemarks:\n\nSalary package: Basic HK$55-60K or above (neg.);\n5-day work;\nWorking location: Shatin.\n\nInterested parties please click \"APPLY NOW\"\u00a0or send to\u00a0OUR EMAIL\u00a0and attach your updated resume with expected salary in \"MS WORD\" format.\n\nPlease quote the\u00a0Job Ref. No.\u00a0and\u00a0Applied Post\u00a0on the subject of your application.\n\nCompany website: www.kek.com.hk\n\nThe information provided will only be used for recruitment related purposes.", "employment_types": ["Full Time", "Permanent"], "selling_points": ["Min. 2 years of relevant working experience", "Troubleshoot with solution specialist", "Project and resources management"], "locations": ["Kwun Tong"], "categories": ["Information Technology (IT)", "IT Project Management / Team Lead", "IT Management", "Technical / Functional Consulting"], "post_time": "2022-01-10T04:03:39Z", "salary": {"currency": null, "max": null, "min": null, "period": "monthly", "term": null}, "salary_visible": false, "title_keywords": ["project manager", "project coordinator"], "responsibilities": ["software"], "requirements": {"degrees": ["degree or above", "degree"], "majors": ["computer science"], "languages": [], "language_level": [], "hard_skills": ["bi", "basic", "ai"], "soft_skills": [], "languages_combined": []}, "experience_required": {"duration": [], "field": ["team", "software development"]}}, {"job_id": "100003009034907", "location_code": "hk", "company": "Master Concept (Hong Kong) Limited", "job_title": "Project Manager", "description": "Duties\n\nParticipate in the design, development, implementation and maintenance of enterprise applications\nParticipate in the project implementation and support services\nSupervise vendors to perform system development duties\n\nRequirements\n\nBachelor Degree in Computer Science or related discipline\u00a0\nKnowledge in J2EE and RDBMS (Oracle, Microsoft SQL), C#, .NET, Business Intelligence and mobile development would be an added advantage\nAbility to work independently\nGood communication, presentation, documentation and demonstrated people/vendor management skills\n\nWe offer the right incumbent attractive remuneration package including 12 days annual leave, 5-day week, double pay, performance bonus, medical scheme, life insurance, travel allowance and education subsidy.\u00a0\n\nInterested parties please send your full resume with reference no., recent and expected salary to:\u00a0Human Resources Department, Asia Airfreight Terminal Co. Ltd., 10 Chun Ping Road, Hong Kong International Airport, Lantau, Hong Kong\u00a0OR Fax to\u00a02286 0374\u00a0OR\u00a0Please click \u201cApply Now\u201d to submit your application.\n\nTo know more about AAT, please visit http://www.aat.com.hk/\n\nWe are an equal opportunity employer and welcome applications from all qualified candidates. We will not be responsible for any disclosure or the loss of personal data during transmission. All personal data collected will be used for recruitment only. Information of unsuccessful candidates will be destroyed after 3 months from the date of application.", "employment_types": ["Full Time"], "selling_points": ["5 yrs experience in facilitating IT projects", "Innovative, Organizing & Execution abilities", "Funny & Creative Startup working environment"], "locations": ["Kwun Tong"], "categories": ["Information Technology (IT)", "IT Project Management / Team Lead", "IT Management", "Product Management / Business Analyst"], "post_time": "2022-01-10T04:35:58Z", "salary": {"currency": null, "max": null, "min": null, "period": "monthly", "term": null}, "salary_visible": false, "title_keywords": ["project manager"], "responsibilities": ["maintenance", "support services", "implementation", "design"], "requirements": {"degrees": ["degree", "bachelor"], "majors": ["computer science"], "languages": [], "language_level": [], "hard_skills": ["oracle", "vendor", "scheme", "sql", "mobile", "documentation", "business intelligence", "c#"], "soft_skills": ["communication", "work independently", "presentation"], "languages_combined": []}, "experience_required": {"duration": [], "field": []}}, {"job_id": "100003009049721", "location_code": "hk", "company": "Tak Jin Management Services Limited", "job_title": "System Analyst / Analyst Programmer (HK$35K - HK$55K)", "description": "Responsibilities\n\nTake lead on technical aspects of solutions, such as product and solution briefings, proposal preparations, pricing strategy, proof-of-concept work, coordination of supporting technical resources etc.\nEvaluate clients' project needs and propose the most optimal solutions and approaches\nGather user requirements and define scope of work\nCollaborate between professional services department and customers on-going project when required\nPrepare user guide and solution comparison reports\nWork with Sales Department to identify business opportunities\nRequirements\n\n5+ years of experience in pre-sales role\nEquip with commercial and business sense, experience in technical product management cycle\nEquip with presentation skills, with experience in presenting to senior management/client\u00a0\nUnderstand application development lifecycle, workflow, integration and infrastructure design\nAcquire and able to apply commercial and technical expertise by staying up-to-date in industry and market trends\nGood command of both spoken and written English and Cantonese, and Mandarin\nFamiliar with production solution will be a definite advantage\nIf you enjoy working in a friendly and challenging working environment, please send your full resume with your availability, last/current and expected salary by clicking \u201cApply Now\u201d.\n\n*All information collected will be used for recruitment purpose only and will be kept strictly confidential*", "employment_types": ["Full Time", "Permanent"], "selling_points": ["System design,development & configuration", "3-5 yrs of exp, Python and JavaScript proficiency", "Exp in SQL,CSS,GIT,REST APIs and HTML"], "locations": ["North Point"], "categories": ["Information Technology (IT)", "IT Project Management / Team Lead", "Network & System", "Technical / Functional Consulting"], "post_time": "2022-01-14T09:22:23Z", "salary": {"currency": null, "max": null, "min": null, "period": "monthly", "term": null}, "salary_visible": false, "title_keywords": ["analyst programmer", "system analyst"], "responsibilities": ["collaborate", "identify business opportunities", "evaluate", "reports", "coordination"], "requirements": {"degrees": [], "majors": [], "languages": ["cantonese", "english", "mandarin"], "language_level": ["good command"], "hard_skills": ["integration"], "soft_skills": ["enjoy working", "presentation skills", "friendly", "business sense"], "languages_combined": [{"language": "cantonese", "language_level": ["good command"]}, {"language": "english", "language_level": ["good command"]}, {"language": "mandarin", "language_level": ["good command"]}]}, "experience_required": {"duration": ["5+ years"], "field": ["product management", "commercial", "management", "business"]}}, {"job_id": "100003009042447", "location_code": "hk", "company": "CLPS Technology (Hong Kong) Co., Limited", "job_title": "Project Manager/ Business Analyst  (Financial Institution)", "description": "\n\n\nResponsibilities:\n\n\nExecute Audiovisual projects professionally\nAssist sales team and solution team to handle business opportunities\nCommunicate with client and fully understand requirement\nManage external resources and support teammates to complete project fully\u00a0\nAV products knowledge such as: Crestron, Extron, AMX, Biamp, QSC etc.\nELV such as: CCTV, Access Control, Video & Alarms,\u00a0Radio Frequency etc\u00a0\nRequirements\u00a0\n\nDiploma or above in Electronic Engineering, Building Services Engineer or related disciplines\nMinimum 4 years\u00a0working experiences\u00a0\nProficient in MS Office & AutoCAD &\u00a0knowledge of\u00a0Photoshop\nIndustry certifications would be an advantage (such as PMP, CTS from InfoComm)\nCandidates with less experience will be considered as Assistant Project Engineer\nGood command of spoken and written English & Chinese", "employment_types": ["Full Time"], "selling_points": ["Business Analysis & Stakeholder management", "Competitive Salary package", "5-days work"], "locations": ["Central & Western Area"], "categories": ["Banking / Finance", "Financial Services", "Information Technology (IT)", "IT Project Management / Team Lead", "Product Management / Business Analyst"], "post_time": "2022-01-12T07:34:04Z", "salary": {"currency": null, "max": null, "min": null, "period": "monthly", "term": null}, "salary_visible": false, "title_keywords": ["project manager", "business analyst"], "responsibilities": ["communicate with client", "business opportunities", "access control", "sales team"], "requirements": {"degrees": ["diploma or above"], "majors": ["related disciplines", "building services", "engineering"], "languages": ["english", "chinese"], "language_level": ["good command"], "hard_skills": ["pmp", "autocad", "photoshop", "ms office"], "soft_skills": [], "languages_combined": [{"language": "english", "language_level": ["good command"]}, {"language": "chinese", "language_level": ["good command"]}]}, "experience_required": {"duration": ["minimum 4 years"], "field": []}}, {"job_id": "100003009036440", "location_code": "hk", "company": "Animoca Brands Limited", "job_title": "Senior Project Manager", "description": "About Accenture\uff1a\n\nAccenture is a global professional services company with leading capabilities in digital, cloud and security. Combining unmatched experience and specialized skills across more than 40 industries, we offer Strategy and Consulting, Interactive, Technology and Operations services\u2014all powered by the world\u2019s largest network of Advanced Technology and Intelligent Operations centers. Our 506,000 people deliver on the promise of technology and human ingenuity every day, serving clients in more than 120 countries. We embrace the power of change to create value and shared success for our clients, people, shareholders, partners and communities.\n\nThe company has been operating in Greater China for over 30 years. Today, it has more than 17,000 people servicing clients across the region with offices in the cities including Beijing, Shanghai, Dalian, Chengdu, Guangzhou, Shenzhen, Hong Kong and Taipei. As a trusted Partner of Choice for digital transformation, Accenture is bringing more innovation to the business and technology ecosystems and helping Chinese enterprises and the government to embrace digitization and enhance global competitiveness to succeed in the new era.\n\nFor more information about Accenture, please visit its corporate homepage www.accenture.com and its Greater China homepage www.accenture.cn .\n\n\n\nAbout Accenture Interactive\uff1a\n\nAs one of the key services under Accenture, Accenture Interactive is in the\u00a0business of Experience. We connect deep human and business insights with the possibilities of technology to define and deliver new realities. We're committed to helping clients design, build, communicate and run Experiences that make peoples' lives better, more productive and more meaningful. Visit http://www.accentureinteractive.com to find out more about us.\n\nKey Responsibilities\n\nProvide the end-to-end project management from managing the client, resources, budget, timeline to deliverables\nResponsible for budgeting and overall planning, developments and to deliver different kinds of digital projects\nProficient to develop a detailed project plan and monitor progress against it\nCollaborate with internal teams to design, develop and implement digital projects\nCapable to handle impediment and provides alternatives\nDeliver projects on time with ensuring certain quality standards are met\nDevelop support documentation example with risk logs and requirement specifications\nCommunicate with the team and ensure all members are on board with delegated tasks\nHighlight potential risks or malfunctions and act proactively to resolve issues\nIncrease efficiency of team cooperation by improving communication and process\nSupport pre-sales activities including overall solutioning, project sizing, proposal preparation and presentation\n\nExperience, Attributes and Qualifications:\n\nUniversity degree holder in Information Technology, Information System, or related disciplines\n5+ years hands-on experience in large scale digital project management and software delivery\nExcellent organization and time management skills\nEffective communicator to different levels of stakeholders and can present complex ideas and technical details into layman terms\nDemonstrate a proactive working attitude to achieve common goals with good influential and negotiation skills\nStrong knowledge on different kinds of project management tools (e.g.: MS Project, JIRA, etc.)\nStrong oral and written English language skills\nProficiency in Cantonese and Putonghua (written and spoken) is an advantage\nScrum Master certification (CSM / PSM 1) is an advantage\nExperience in working in DevOps environment is an advantage", "employment_types": ["Full Time", "Permanent"], "selling_points": ["Project Management", "Blockchain", "Crypto"], "locations": ["Pok Fu Lam"], "categories": ["Information Technology (IT)", "IT Project Management / Team Lead", "Product Management / Business Analyst"], "post_time": "2022-01-10T10:26:32Z", "salary": {"currency": null, "max": null, "min": null, "period": "monthly", "term": null}, "salary_visible": false, "title_keywords": ["senior project manager"], "responsibilities": ["collaborate with", "ideas", "software", "consulting", "monitor progress", "operations", "budgeting", "budget", "quality", "design", "communication", "teams", "develop", "management", "specifications", "documentation", "communicate with", "sales activities", "project plan", "project management", "planning"], "requirements": {"degrees": ["university degree", "master"], "majors": ["related disciplines", "information technology"], "languages": ["cantonese", "putonghua", "english", "chinese"], "language_level": ["advantage", "proficiency"], "hard_skills": ["devops", "information system", "make", "project management", "documentation"], "soft_skills": ["productive", "oral", "advanced", "responsible", "capable", "time management skills", "deep", "communication", "committed", "project management", "hands-on", "influential", "negotiation skills", "communicator", "proactive", "presentation", "detailed"], "languages_combined": [{"language": "cantonese", "language_level": ["proficiency", "advantage"]}, {"language": "putonghua", "language_level": ["proficiency", "advantage"]}, {"language": "english", "language_level": []}, {"language": "chinese", "language_level": []}]}, "experience_required": {"duration": ["5+ years"], "field": ["consulting", "devops", "design", "project management", "business", "digital"]}}]