[{"job_id": "100003009054563", "location_code": "hk", "company": "Incredible Action Limited", "job_title": "Front-end Web Developer / Programmer", "description": "\nIn this role, you'll be helping to:\nBuild SPA web applications with payment and social platform integration\nBuild reusable UI components to accelerate long-term development\nBuild reliable software with test-driven development\n\nWe're looking for a member who graduated with a computer science/ information technology diploma / degree. If you say yes to below questions, you're very likely to be one of us!\n\nDo you have experience building web applications and web components?\nDo you enjoy finding solutions that improve the product?\nDo you enjoy collaborating with a team?\nDo you have a positive working attitude?\nWell, last but not the least, some tech things this role will use:\n\n\u00a0Vue.js, Vuex, Flexbox, Node.js, Git, Docker\n\nSend us your CV and portfolio if you're interested!\n(Personal data collected will be used for recruitment purpose only.)", "employment_types": ["Full Time"], "selling_points": [], "locations": ["Yau Ma Tei"], "categories": ["Information Technology (IT)", "Application Specialist - Software", "IT - Webmaster / SEO"], "post_time": "2022-01-17T10:00:36Z", "salary": {"currency": null, "max": null, "min": null, "period": "monthly", "term": null}, "salary_visible": false, "title_keywords": ["developer", "programmer"], "responsibilities": ["software", "payment", "recruitment", "personal data", "ui"], "requirements": {"degrees": ["diploma", "degree"], "majors": ["computer science", "information technology"], "languages": [], "language_level": [], "hard_skills": ["integration", "git", "web applications", "web"], "soft_skills": ["positive working attitude", "reliable", "driven"], "languages_combined": []}, "experience_required": {"duration": [], "field": ["web applications"]}}, {"job_id": "100003009054494", "location_code": "hk", "company": "Open Creative Limited", "job_title": "Full Stack Web Developers", "description": "Open Creative is looking for highly motivated and hands-on candidates, ready to take on the challenge of building large, scalable web and mobile solutions that real people use everyday!\n\nWhat we're looking for:\n\nFull stack web development for new web projects.\nMaintain, develop & support existing big & small web projects.\nGather client user requirements & perform analysis of the requirements.\nProvide daily client technical troubleshooting.\nSolid experience in Linux servers administration is needed.\nKey skills & requirements:\n\nDegree in Computer Science or equivalent.\nAt least 2.0 years of solid hands-on programming experience.\nExpert in HTML5, CSS3, Javascript, React.js is a must.\nExcellent working experience in PHP programming environment is a must.\nExperience in Node.js developing server-side & Github/Redux for secure networking application deployment is a big advantage.\nWorking experience with AWS / Azure Linux builds a big advantage.\nExperience in implementing responsive UI & UX for web & mobile apps using Bootstrap is a bonus.\nStrong knowledge of cross-platform compatibility, new web technologies & e-commerce best practices.\nSound logic-problem solving, self-motivated & good time-management.\nGood communication in spoken & written English & Chinese.\nDoes this sound like you? Then send us your current resume, expected salary & a brief cover letter about yourself via email to jobs at opencreative.com. All personal information collected will be used for recruitment purposes only.", "employment_types": ["Full Time", "Permanent"], "selling_points": ["HTML5, CSS, JavaScript, React.js, Bootstrap, Linux", "Develop & support stack-based PHP & Node.js builds", "Good spoken & written English & Chinese"], "locations": ["Sheung Wan"], "categories": ["Information Technology (IT)", "Application Specialist - Software", "IT - Webmaster / SEO", "Software Development"], "post_time": "2022-01-17T09:46:43Z", "salary": {"currency": "HKD", "max": 34999, "min": 30000, "period": "monthly", "term": null}, "salary_visible": true, "title_keywords": [], "responsibilities": ["management", "analysis", "troubleshooting", "developing", "develop", "communication", "maintain", "recruitment", "ui", "administration"], "requirements": {"degrees": ["degree"], "majors": ["computer science"], "languages": ["english", "chinese"], "language_level": ["good"], "hard_skills": ["azure", "web", "e-commerce", "server", "web projects", "servers", "problem solving", "web technologies", "small", "web development", "aws", "web & mobile", "javascript", "linux", "react", "php", "analysis", "mobile", "deployment", "programming"], "soft_skills": ["self-motivated", "troubleshooting", "problem solving", "communication", "hands-on", "motivated", "creative", "responsive"], "languages_combined": [{"language": "english", "language_level": ["good"]}, {"language": "chinese", "language_level": ["good"]}]}, "experience_required": {"duration": ["0 years"], "field": ["programming", "administration"]}}, {"job_id": "100003009052562", "location_code": "hk", "company": "LinkedU Overseas Education Limited", "job_title": "Wordpress Developer (Part-Time / Freelance)", "description": "You'll be responsible for...\n\n\nPerform keywords research and analysis\nMonitor and enhance keywords ranking performance to deliver KPIs\nPlan and optimize on-page website content and landing pages\nLead, develop and execute content and technical SEO strategies\nRecommend changes to website architecture, layouts, content and other factors to improve keywords ranking\nConduct technical SEO and backlink audit, and draw insights for improvement\nDevelop and implement link building strategy\nIdentify SEO trend & Implement best practices\n\nIf you are...\n\n\nDegree holder in Marketing/Information Technology/Communications/e-Commerce or related disciplines\nMinimum 2 years working experience in SEO or online marketing or digital agency.\u00a0Candidates with more experience will consider as Senior Digital Marketing Specialist\nExperience in using SEO tools i.e. SEMRush, Ahrefs, Screaming Frog (or similar) is a MUST;\nExperience in using Google tools i.e. Google Analytics, Google Tag Manager, Google Search Console is a MUST;\nExperience in on-site content writing, technical SEO and link building is a MUST\nGood communication and interpersonal skills\nExcellent in Chinese and English written skill\n\nWe offer...\u00a0\n\nFive-days work per week + Bank Holiday\nSeasonal Project Completion Bonus\nEducation Allowance\nMedical Allowance\nSnacks and drinks\nTraining + Good career prospect in growing Digital Marketing Industry\n\nIf this sounds interesting to you, Apply Now!!\u00a0\n\nPlease come with a portfolio that will demonstrate our required fields as mentioned above. Interested parties, please apply with full resume, portfolio, current, and expected salary.\n\nData collected would be used for recruitment purposes only. Applicants who do not hear from us within 8 weeks may consider their application unsuccessful and their data will be destroyed within 24 months of receipt.", "employment_types": ["Part Time", "Temporary"], "selling_points": ["Proficient in Front-End & Back-End Web Programming", "Familiar with SEO is a plus", "fast-growing overseas education industry"], "locations": ["Central"], "categories": ["Education", "Others", "Information Technology (IT)", "IT - Webmaster / SEO", "Software Development"], "post_time": "2022-01-17T03:25:18Z", "salary": {"currency": null, "max": null, "min": null, "period": "hourly", "term": null}, "salary_visible": false, "title_keywords": ["developer"], "responsibilities": ["seo", "analysis", "monitor", "website", "audit", "develop", "communication", "digital marketing", "plan", "kpis", "architecture"], "requirements": {"degrees": ["degree holder"], "majors": ["e-commerce", "information technology", "related disciplines", "marketing", "communications"], "languages": ["english", "chinese"], "language_level": ["excellent"], "hard_skills": ["google analytics", "analysis", "seo", "e-commerce"], "soft_skills": ["communication and interpersonal skills", "responsible"], "languages_combined": [{"language": "english", "language_level": ["excellent"]}, {"language": "chinese", "language_level": ["excellent"]}]}, "experience_required": {"duration": ["minimum 2 years"], "field": ["agency", "marketing", "digital marketing", "content writing", "digital"]}}, {"job_id": "100003009046512", "location_code": "hk", "company": "Strategic Digital Marketing Company Limited", "job_title": "SEO Specialist (5 days work)", "description": "Responsibilities\n\n* Participate in system development, testing and implementation\n\n* Responsible for API development, implementation, maintenance and training\n\n* Cooperate with Web and App teams to develop websites and Apps\n\n* Assist in SQL optimization and other database performance\n\n* Keen interest in exploring new technology\n\nRequirements\n\n* Bachelor Degree or Diploma in Computer Science, Information Technology or related disciplines\n\n* Experience in one of the programming languages such as\n\n.NET programming(C#), Node.js, SQL, mongoDB, elasticsearch\n\n,HTML5, VueJs, Docker, Nginx is a plus\n\n* Experience in software development using OOP, design patterns would be an advantage\n\n* Can work independently and be self-motivated\n\n* Fresh Graduates will also be considered\n\n* Candidate with more experience will be considered as Senior Programmer\n\n* Immediate available is preferred", "employment_types": ["Full Time", "Permanent"], "selling_points": ["2 years experience in SEO", "Friendly and energetic working environment", "Bank Holiday, Birthday Leave & Performance Bonus"], "locations": ["Lai Chi Kok"], "categories": ["Information Technology (IT)", "IT - Webmaster / SEO", "Sales, CS & Business Devpt", "Account Servicing", "Marketing / Public Relations", "Digital Marketing"], "post_time": "2022-01-17T16:21:08Z", "salary": {"currency": null, "max": null, "min": null, "period": "monthly", "term": null}, "salary_visible": false, "title_keywords": ["specialist"], "responsibilities": ["maintenance", "teams", "implementation", "testing", "develop", "database", "cooperate with"], "requirements": {"degrees": ["diploma", "degree", "bachelor"], "majors": ["related disciplines", "computer science", "information technology"], "languages": [], "language_level": [], "hard_skills": ["sql", "plus", "programming"], "soft_skills": ["work independently", "self-motivated"], "languages_combined": []}, "experience_required": {"duration": [], "field": ["design", "programming", "software development"]}}, {"job_id": "100003009053268", "location_code": "hk", "company": "Centaline Data Technology Limited", "job_title": "Programmer / Senior Programmer  (5-day Work)", "description": "You'll be responsible for...\n\nDay-to-day project management on search (SEO, Paid Ad) and social media marketing (Facebook, Instagram, LinkedIn) accounts\nServe as key person between client, multi-function teams, internal work counterparts and external parties for service designs and implementation\nAnalyze and evaluate campaign's performance and provide suggestions for improvement\nPrepare pitching proposals\u00a0\nBrainstorm and prepare presentation and reports to clients\nPerform ad-hoc duties as assigned\n\nIf you are...\n\nDegree holder in any\u00a0related\u00a0disciplines (Marketing/ e-Commerce/ Communications or Business);\nWith at least 2 years working experience in Digital Marketing field or related disciplines\nExperienced in search & social media marketing is a must;\nFluency in written and spoken English, Cantonese and Mandarin;\nExcellent communication and interpersonal skills;\nGood in Microsoft Offices (Word, Excel, PowerPoint) and Chinese and English typing;\nKnowledge in Digital Marketing Tools (eg. Google Adwords, Google Analytics, Facebook Ad Manager, etc) is a must;\nTeam leader, highly independent, self-motivated responsive,\u00a0innovative,\u00a0well-organized, presentable with strong analytical skills and business sense;\nWilling to learn and explore new knowledge and technology;\nCandidate with more experience will be considered as Senior Account Executive\n\nWe offer...\u00a0\n\nFive-days work per week + Bank Holiday\nProject Completion Bonus\nEducation Allowance\nMedical Allowance\nSnacks and drinks\nTraining + Good career prospect in growing Digital Marketing Industry\n\nIf this sounds interesting to you, Apply Now!!\u00a0\n\nPlease come with a portfolio that will demonstrate our required fields as mentioned above. Interested parties, please apply with full resume, portfolio, current and expected salary.\n\nData collected would be used for recruitment purposes only. Applicants who do not hear from us within 8 weeks may consider their application unsuccessful and their data will be destroyed within 24 months of receipt.", "employment_types": ["Full Time", "Permanent"], "selling_points": ["API development and application system developme", "SQL optimization / On-job training", "Quarterly Bonus / Medical / Education Allowance"], "locations": ["Tsim Sha Tsui"], "categories": ["Information Technology (IT)", "IT - Webmaster / SEO", "Mobile / Wireless Communications", "Data Scientist"], "post_time": "2022-01-17T06:37:11Z", "salary": {"currency": null, "max": null, "min": null, "period": "monthly", "term": null}, "salary_visible": false, "title_keywords": ["programmer", "senior programmer"], "responsibilities": ["social media", "seo", "external parties", "teams", "implementation", "evaluate", "project management", "communication", "reports", "digital marketing", "ad-hoc duties", "facebook"], "requirements": {"degrees": ["degree holder"], "majors": ["e-commerce", "related disciplines", "marketing", "business", "communications"], "languages": ["cantonese", "english", "chinese", "mandarin"], "language_level": ["fluency", "good"], "hard_skills": ["excel", "google analytics", "seo", "e-commerce", "adwords", "word", "powerpoint", "typing", "analytical skills", "project management", "facebook"], "soft_skills": ["highly independent", "self-motivated", "responsible", "business sense", "well-organized", "willing to learn", "presentable", "analytical skills", "project management", "communication and interpersonal skills", "ad-hoc duties", "innovative", "responsive", "presentation"], "languages_combined": [{"language": "cantonese", "language_level": ["fluency"]}, {"language": "english", "language_level": ["fluency", "good"]}, {"language": "chinese", "language_level": ["good"]}, {"language": "mandarin", "language_level": ["fluency"]}]}, "experience_required": {"duration": ["at least 2 years"], "field": ["related", "digital marketing field"]}}, {"job_id": "100003009054867", "location_code": "hk", "company": "Strategic Digital Marketing Company Limited", "job_title": "Account Executive (5 days work)", "description": "sor\uff0c\u5176\u5be6\u90fd\u4fc2\u7121\u5716\uff0c\u5443\u5de6\u5927\u5bb6\u5165\u4f86\n\n\u662f\u5481\u7684\uff0c\u6211\u5730\u4fc2\u505a event technology \u5605\uff0c\u6703\u505a\u5572\u540c event \u5462\u884c\u76f8\u95dc\u5605\u91ce\uff0c\u4f8b\u5982 pre event \u8981\u780c\u5f35 RSVP form \u6bd4\u4eba\u586b\u8cc7\u6599\uff0cevent \u55f0\u6642\u8981\u505a\u500b app \u6bd4\u4eba check-in \u7528\uff0cpost event \u53c8\u8981 send \u8fd4\u5c01 thank you email \u6bd4\u4eba\n\n\u4e4b\u524d\u4ea6\u90fd\u8a66\u904e\u73a9 AR (AR.js)\uff0c\u53c8\u6216\u8005\u55ba IG \u5230 down \u5572\u76f8\u843d\u4f86\uff0c\u53c8\u8a66\u904e\u7528 Raspberry Pi \u4f86\u780c\u500b on-site server\uff0c\u90fd\u5e7e\u591a\u82b1\u81e3\u91ce\n\n\u6280\u8853\u65b9\u9762\u4e3b\u8981\u4fc2\u505a Web\uff0cbackend \u6211\u5730\u7528\u958b PHP (Laravel)\uff0cfrontend \u7528\u958b React \u540c\u57cb Vue\uff0c\u6211\u5730\u5e0c\u671b\u5462\u5e7e\u6a23\u91ce\u4f60\u90fd\u8981\u6709\u8fd4\u591a\u5c11 knowledge\uff0c\u5514\u6d17\u7531\u982d\u5b78\u8d77\n\n\u5462\u4efd\u5de5\u6709\u6311\u6230\u5605\u4f4d\u4fc2\u5b78\u8b58\u9ede\u6a23\u505a\u500b scale up \u5230\u5605\u7db2\u7ad9\uff0c\u56e0\u70ba\u6211\u5730\u505a\u89aa\u55f0\u5572\u7db2\u901a\u5e38\u5572\u6d41\u91cf\u90fd\u6703\u55ba\u77ed\u6642\u9593\u5167\u7a81\u7136\u6e67\u5165\u4f86\uff0c\u8981\u5b78\u8b58\u9ede tune \u4e0b\u5572 server\uff0c\u6216\u8005\u6539 code \u53bb support \u5230\u597d\u591a\u4eba\u540c\u6642\u5728\u7dda\u800c\u53c8\u5514\u6703\u6b7b\u6a5f\u4e4b\u985e\n\n\u76ee\u524d\u9700\u8981\u4f60\u8b58\u5605\u4fc2\uff1a\n\nPHP - Laravel\nSQL - MySQL\nHTML, CSS, JS\n\u8b58\u5462\u5572\u6709\u5206\u52a0\uff1a\n\nWordpress\nReact Native\n\u4eba\u5de5\u65b9\u9762\u5c31\u7747\u4f60\u7d93\u9a57\u540c\u8b58\u5e7e\u591a\u91ce\u518d\u5b9a\uff0c\u4eca\u6b21\u60f3\u6435\u500b Junior \u5c11\u5c11\u5605\u4f86\u5e6b\u624b\uff0c1 - 3 \u5e74\u7d93\u9a57\u90fd\u6703\u8003\u616e\n\nSEO: web developer, PHP, programmer", "employment_types": ["Full Time", "Permanent"], "selling_points": ["Project management for top-tier companies and SME", "Friendly and energetic working environment", "Challenging, an once in a lifetime opportunity!"], "locations": ["Lai Chi Kok"], "categories": ["Information Technology (IT)", "IT - Webmaster / SEO", "Sales, CS & Business Devpt", "Account Servicing", "Marketing / Public Relations", "Digital Marketing"], "post_time": "2022-01-17T16:21:09Z", "salary": {"currency": null, "max": null, "min": null, "period": "monthly", "term": null}, "salary_visible": false, "title_keywords": ["account executive"], "responsibilities": ["seo", "ar"], "requirements": {"degrees": [], "majors": [], "languages": [], "language_level": [], "hard_skills": ["seo", "ar", "web", "react", "php", "css", "html", "sql", "wordpress", "react native", "code"], "soft_skills": [], "languages_combined": []}, "experience_required": {"duration": [], "field": []}}, {"job_id": "100003009047365", "location_code": "hk", "company": "Episode Limited", "job_title": "[\u591a\u5716] \u7559\u4e0b\u4f86\u7684\u4eba\u8acb\u9032 [SEO: Laravel, PHP, web developer]", "description": "\n\nHandle new development & maintenance to the company's WordPress website and service portals\nImplement appropriate and tidy codes and test them in various environments, enhance and/or modify them if necessary\nCarry out testing, bug fixing and troubleshooting\nConduct WordPress performance test and tuning\nCustom WordPress theme and plugins\nMonitor the performance of the website\nJob Requirements:\n\nDegree holder in Web design, web development or related technical disciplines\nProficient in web development on WordPress with minimum 2 years hands-on experience\nProven experience and understanding of responsive design\nKnowledge of front-end technologies including CSS3, JavaScript, HTML5, and jQuery\nKnowledge of back-end integration such as database, JSON API integration\nFamiliar with SEO tracking code installation (eg. GTM, GA, Facebook Pixel, etc.) will be a plus\nGood command of written Chinese and English", "employment_types": ["Full Time", "Permanent", "Freelance"], "selling_points": ["1 - 3 \u5e74\u7d93\u9a57\u90fd\u6703\u8003\u616e", "\u5e74\u5c3e\u8996\u4e4e\u8868\u73fe\u767c\u82b1\u7d05\uff0c\u51fa\u8272\u5605\u5169\u4e09\u500b\u6708\u82b1\u7d05\u90fd\u6709", "\u5e6b\u624b apply \u4e0b\uff0cHR \u90fd\u8981\u8dd1\u6578"], "locations": ["Wong Tai Sin Area"], "categories": ["Information Technology (IT)", "IT - Webmaster / SEO", "Support", "Software Development"], "post_time": "2022-01-17T01:33:44Z", "salary": {"currency": null, "max": null, "min": null, "period": "monthly", "term": null}, "salary_visible": false, "title_keywords": ["developer"], "responsibilities": ["installation", "seo", "maintenance", "troubleshooting", "website", "testing", "design", "monitor the performance", "database", "facebook", "tracking"], "requirements": {"degrees": ["degree holder"], "majors": ["web design"], "languages": ["english", "chinese"], "language_level": ["good command"], "hard_skills": ["web design", "web development", "plus", "seo", "maintenance", "jquery", "wordpress", "javascript", "integration", "code", "facebook", "codes"], "soft_skills": ["hands-on", "responsive", "troubleshooting"], "languages_combined": [{"language": "english", "language_level": ["good command"]}, {"language": "chinese", "language_level": ["good command"]}]}, "experience_required": {"duration": ["minimum 2 years"], "field": ["development", "design"]}}, {"job_id": "100003009051129", "location_code": "hk", "company": "Orca Base Limited", "job_title": "Full-Stack Web Developer", "description": "DEAR TALENT, YOUR MOVE!\n\nBeing the new rising airline since 2013, we are the Hong Kong\u2019s only Low Cost Carrier (LCC) offering you safe and flexible service options to Hong Kong and beyond.\n\nWe\u2019re on a mission to inspire you to be different, to shake things up, to inspire the spirit of adventure by bringing you to fascinating destinations that few others serve.\n\nSpread your wings and fly with us!\n\n\nWhat will you do?\u00a0\n\nLead a small team to maintain daily IT Web Infrastructure operation to support internal users within SLA under ITIL standard;\nProvide technical implementation and support on cloud infrastructure in terms of OS, network, and database, e.g. Microsoft Office 365 applications, AliCloud, Google Cloud, Azure and other IaaS Cloud services providers;\nManage the service providers to provide technical support;\nPerform vendor management, work closely with outsourcing partners on daily operation;\nSupport internal audit to assess Web environment;\nSupport Security team to handle security events;\nSupport Infrastructure & Security projects delivery;\nOversee and develop IT security policies and guidelines for web infrastructure environments;\nPlan, design and implement appropriate technological solutions to defend against cyber-attacks and intrusion;\nCoordinate with other business and IT teams for application enhancements;\nEvaluate and assess emerging web technologies to maintain a cost-effective web environment;\nDevelop and input into key technology Infrastructures Engineering Lifecycle documentation, such as component version and patch management decisions;\nDrive continuous improvement to support the business;\nCoach and mentor team members;\nOn-call for emergency production incidents to provide fire-fighting support and perform shift duties as required;\nPerform other ad-hoc projects and tasks as assigned.\n\nWe are a perfect match, if you are:\n\nUniversity degree preferably in Information Technology, Information Security, Computer Science or related discipline;\nMinimum 6 years of experience in Web Infrastructure, Security, Architecture, including 3 years of managing experience in a supervisory role;\nKnowledge of Cloud-based security, architecture, and development;\nKnowledge of any security product (CyberArk, Qualys, DLP, SIEM);\nKnowledge of applications Cloud-native & containerize solution with RDS on AliCloud, Google Cloud, Azure, FlashGrid Launcher (Infrastructure-as-code, storage fabric, cloud area network, patching Grid infrastructure, database patching, ASM disk group, EC2 instances, VPC networking);\nKnowledge of VDI technology to strengthen access control;\nBasic knowledge of DNS, DHCP, TCP/IP, LAN & WAN, IPsec, and OpenVPN concepts;\nProficient with Linux cmd, Windows cmd, and scripting;\nKnowledge and experience with Windows 10, Windows Server 2016-19, and Active Directory;\nVirtualization knowledge (Hyper-V, VMWare) is an advantage;\nTeam player who is self-driven and organized;\nExcellent communication, facilitation, interpersonal skills, problem solving and team building skills;\nGreat sense of ownership and servicing mindset to ensure efficient / effective customer service process;\nProficiency in both English and Chinese;\nCandidate with less experience will be considered as Specialist, Web Infrastructure Operations.\n\nYour Future Work Life?\n\nWork flexibly with staggered working hours and flexible workplace\nDress Casual and Smart everyday\nWork in a newly-designed office with open seating, stylish breakout areas, game room, gym and free coffee\u2026\nWork with a group of energetic and multicultural professionals (up to 50 nationalities!)\nHave great fun in Snack Friday, New Year Market, Fly with your Kids Day, Basketball Team\u2026\nHave your voice heard through Townhalls, Crew forums, CEO live sessions etc.\n\nWhat will you enjoy?\n\nFly anywhere we fly for free plus taxes during leisure with your friends and family\nSpecial privileges to buy duty free products\nCareer Express\n\n\n\nYou will be inspired by our core values.\nYou will be inspired by our vibrant, efficient and entrepreneurial spirit. Join our fun, collaborative and reliable team to ignite your dream!\n\n\n\nInterested? It\u2019s time to have YOUR MOVE!\nIf you're ready to embark your adventure, start by clicking the \u2018Apply now\u2019 and get on the plane to fly with HK Express!\u00a0", "employment_types": ["Full Time", "Permanent"], "selling_points": ["Fast-growing AI Startup", "5-days Work Week", "Excellent Career Growth Opportunities"], "locations": ["Quarry Bay"], "categories": ["Information Technology (IT)", "IT - Webmaster / SEO", "UI/UX Designer"], "post_time": "2022-01-15T03:04:08Z", "salary": {"currency": null, "max": null, "min": null, "period": "monthly", "term": null}, "salary_visible": false, "title_keywords": ["developer"], "responsibilities": ["internal audit", "information security", "active directory", "design", "infrastructure operations", "communication", "maintain", "customer service", "database", "plan", "ad-hoc projects", "infrastructure", "teams", "implementation", "develop", "patch management", "architecture", "cost", "management", "coordinate with", "documentation", "dns", "technical support", "policies", "lead a small team", "guidelines", "daily operation", "evaluate", "access control"], "requirements": {"degrees": ["university degree"], "majors": ["computer science", "information technology"], "languages": ["english", "chinese"], "language_level": ["proficiency"], "hard_skills": ["itil", "plus", "azure", "web", "active directory", "vendor", "safe", "wan", "hyper-v", "vmware", "fun", "tcp", "problem solving", "os", "lcc", "web technologies", "small", "basic", "airline", "sla", "documentation", "linux", "dns", "microsoft office", "ip", "windows 10", "code", "windows server"], "soft_skills": ["flexible", "organized", "efficient", "collaborative", "communication", "problem solving", "energetic", "customer service", "interpersonal skills", "reliable", "team player", "active", "driven"], "languages_combined": [{"language": "english", "language_level": ["proficiency"]}, {"language": "chinese", "language_level": ["proficiency"]}]}, "experience_required": {"duration": ["3 years", "minimum 6 years"], "field": ["supervisory", "infrastructure", "security"]}}, {"job_id": "100003009047685", "location_code": "hk", "company": "Many Wells Property Agent Ltd", "job_title": "Web Developer/ Senior Programmer/ Programmer", "description": "Job Responsibilities:\n\nMaintain the company's Website and related Websites Design & Contents\u00a0\nAssist in user requirement study, system analysis and design, implementation, testing and deployment\n\n\u00a0Job Requirements:\n\nDiploma or above in Computer Science, I.T. or equivalent discipline\nKnowledge in PHP, Mysql, Javascript, C, Java, shell Script\nKnowledge in Linux will be an advantage\nHardworking and willing work under pressure\nSelf-motivated, strong problem solving and analytical skills\nGood communication skill in Chinese\nFresh Graduates are welcome\n\nInterested parties, please click \"Apply Now\" to submit your application.\n(All Personal information will be used for recruitment purpose only.)", "employment_types": ["Full Time"], "selling_points": [], "locations": ["Tuen Mun Area"], "categories": ["Information Technology (IT)", "IT - Webmaster / SEO", "Software Development", "Network & System"], "post_time": "2022-01-14T03:44:53Z", "salary": {"currency": null, "max": null, "min": null, "period": "monthly", "term": null}, "salary_visible": false, "title_keywords": ["developer", "programmer", "senior programmer"], "responsibilities": ["user requirement", "analysis", "website", "design", "implementation", "testing", "maintain", "contents"], "requirements": {"degrees": ["diploma or above"], "majors": ["computer science"], "languages": ["chinese"], "language_level": ["good"], "hard_skills": ["linux", "java", "php", "analytical skills", "problem solving", "c", "javascript"], "soft_skills": ["self-motivated", "communication skill", "problem solving and analytical skills", "hardworking", "work under pressure"], "languages_combined": [{"language": "chinese", "language_level": ["good"]}]}, "experience_required": {"duration": [], "field": []}}, {"job_id": "100003009046057", "location_code": "hk", "company": "Adhoc Fun Limited", "job_title": "Software Engineer (Web)", "description": "Job Description\n\nResponsibilities:\n\nPerform system design, development, testing and maintenance of applications\nFull system development life cycle experience\nWork closely with users, developers, stakeholders and other offices to deliver solutions\nDeliver high-quality work within committed project schedules\n\n\u00a0Requirements:\n\nUniversity Degree in Computer Science/Engineering, Information Technology/System, or other relevant disciplines desirable\nSolid knowledge or experience in PHP/ Python/ Node.js/ Golang/ Java\nExperience web development in ReactJS/ Angular, HTML and CSS\nKnowledge in Azure / AWS cloud services\nKnowledge in Microservices and docker is a plus\nGood team player with strong interpersonal and communication skills\nSelf-motivated and quality-focused\n\n\u00a0We offer attractive remuneration and fringe benefits to the right candidates. Please send us the application by clicking the \"Apply Now\" button, together with a detailed resume, stating current and expected salary.\u00a0\n\n(All personal data provided by job applicants are used only for recruitment purpose and will be treated strictly confidential. Unsuccessful applications will be properly disposed within 3 months.)", "employment_types": ["Full Time", "Permanent"], "selling_points": ["Happy, fun and harmonious working environment", "5 days work / Flexible working hours", "Fresh graduates will be considered"], "locations": ["Ngau Tau Kok"], "categories": ["Information Technology (IT)", "Application Specialist - Software", "IT - Webmaster / SEO"], "post_time": "2022-01-13T09:30:46Z", "salary": {"currency": null, "max": null, "min": null, "period": "monthly", "term": null}, "salary_visible": false, "title_keywords": ["software engineer"], "responsibilities": ["maintenance", "schedules", "quality", "testing", "system design"], "requirements": {"degrees": ["university degree"], "majors": ["engineering", "computer science", "information technology"], "languages": [], "language_level": [], "hard_skills": ["web development", "java", "azure", "plus", "php", "microservices", "html", "aws", "angular", "python", "css"], "soft_skills": ["communication skills", "good team player", "self-motivated", "focused", "interpersonal"], "languages_combined": []}, "experience_required": {"duration": [], "field": ["development"]}}, {"job_id": "100003009045819", "location_code": "hk", "company": "Babelland Technology Ltd", "job_title": "App and Web Developer", "description": "Responsibilities:\n\nSupport the entire application lifecycle (concept, design, deployment, testing, implementation, enhancement, and maintenance)\nResponsible for full lifecycle of web-based business solutions\nEngage in both front-end and back-end development\nDeliver beautiful interfaces that improve user experience\nTroubleshoot and debug to optimize\u00a0the app\u00a0performance\n\nRequirements:\n\nDegree/Higher Diploma in Computer Science, Computer Engineering or equivalent disciplines\nDemonstrable experience in web development and data visualisation (e.g. GitHub projects, degree coursework, UI/UX design portfolio on Codepen or JSFiddle)\nUnderstanding of at least one Python web framework (Django, Flask)\nProficiency in at least one JavaScript framework (React.js or Vue.js)\nWorking experience with Git version control\nAbility to learn new technologies and integrate them effectively into the platform\nKnowledge about AWS, Azure or other cloud technology is an advantage\nGood analytical, problem solving, communication and presentation skills\nGood sense of UI / UX design is a plus\n\nInterested parties, please send full resume with last & expected salary and date of available by clicking \u2018Apply Now\u2019.\u00a0 All information received will be kept in strict confidential and only for recruitment purpose.", "employment_types": ["Full Time"], "selling_points": ["Flexible working hours", "5 days work", "Performance Bonus"], "locations": ["Kwun Tong"], "categories": ["Information Technology (IT)", "Application Specialist - Software", "IT - Webmaster / SEO", "Software Development"], "post_time": "2022-01-13T08:48:17Z", "salary": {"currency": null, "max": null, "min": null, "period": "monthly", "term": null}, "salary_visible": false, "title_keywords": ["developer"], "responsibilities": ["maintenance", "user experience", "implementation", "design", "testing", "troubleshoot"], "requirements": {"degrees": ["diploma", "degree"], "majors": ["computer engineering", "computer science", "design"], "languages": [], "language_level": [], "hard_skills": ["web development", "git", "azure", "plus", "react", "aws", "problem solving", "javascript", "python", "web framework"], "soft_skills": ["problem solving", "presentation skills", "communication"], "languages_combined": []}, "experience_required": {"duration": [], "field": ["development"]}}, {"job_id": "100003009044093", "location_code": "hk", "company": "Goodbye Dear Company Limited", "job_title": "Web Developer", "description": "Job Highlights:\n\nInvolved in works in app and web development projects.\nOne or more knowledge of: Native App (Android Java, iOS Swift), React Native, WordPress customization, Front end and back end tailor-made system\u00a0\nExperienced candidate could apply for senior position\nFast growing, 5 Days Work, Flexible hours, Birthday Leave\nWork-file balance,\u00a0Joyful working environment\n\nJob Description:\n\nParticipate in various projects including large tender projects in App and Web\nReporting to the Project Manager\nAnalysis the needs and Formulate Solutions\nPlan strategies and drive resources\nDesign, develop and deliver applications\nForesee problems and Master time schedule\nCommunicate with clients for development issue\nLead and coach junior team members (for senior position)\n\nRequirements:\n\nDiploma / Higher Diploma / Degree holder in computer science or programming disciplines\nFresh Graduate also welcomed\nFor Apps Programmer: Hands-on experience in any of the following programming languages: Android Java, swift, Objective-C, React Native, Flutter\nFor Web Programmer: Hands-on experience in PHP, HTML5, CSS, MySQL, Bootstrap, javascript, Wordpress and customization\nAbility to read english technical documents and write in english\nGood communication skill\n\nBenefit:\n\nFlexible working hours\n5 days work\nPerformance Bonus\n\nInterested candidates are invited to send us the followings:\n\nFull Resume\nCurrent Salary and\u00a0Expected Salary\nEarliest available date", "employment_types": ["Full Time", "Contract"], "selling_points": [], "locations": ["Kwun Tong"], "categories": ["Information Technology (IT)", "IT - Webmaster / SEO"], "post_time": "2022-01-13T03:02:37Z", "salary": {"currency": null, "max": null, "min": null, "period": "monthly", "term": null}, "salary_visible": false, "title_keywords": ["developer"], "responsibilities": ["communicate with", "reporting", "analysis", "design", "develop", "schedule", "tender", "plan"], "requirements": {"degrees": ["diploma", "fresh graduate", "degree holder"], "majors": ["computer science"], "languages": ["english"], "language_level": [], "hard_skills": ["java", "web", "php", "objective-c", "wordpress", "javascript", "react native", "programming", "swift", "css", "android"], "soft_skills": ["hands-on", "communication skill"], "languages_combined": [{"language": "english", "language_level": []}]}, "experience_required": {"duration": [], "field": ["programming"]}}, {"job_id": "100003009051461", "location_code": "hk", "company": "ADECCO", "job_title": "UI/UX Designer - 45-50k - Urgent Immediate Available - Global Media Powerhouse - Western Culture.", "description": "Responsibility:\n\nTranslate wireframes design to frontend implementation; produce visual interactive elements of web application.\nProactively communicate with different parties, act as bridge between UIUX team and IT Application team.\nInvolve in designing user flow, looks and feel and keep align with corporate styling;\nPerform on-going review and fine tune for web performance.\n\nRequirements:\n\nDegree in Information Technology, Web Development, Computer Science or related;\nExpert in writing thoughtful, well-formed: HTML5, and CSS3;\nExperience in any JavaScript framework/library (Angular / React or relevant)\nExpert in standards-based, cross-browser, multi-device development and responsive web;\nKnowledge on RESTful API / any other backend technologies will be an added advantage.\nSensitivity to user-system interaction and up-to-date with the latest UI trends, techniques, and technologies;\n1 year or above experiences\n(Fresh graduate with solid skill set is also welcome)\n\nOur Offer:\n\nAttractive remuneration;\nCareer development prospect;\n5-day working week;\n21+ days Annual Leave for all staff;\nPerformance bonus and company shares;\nMedical, Dental, Life Insurance;\nEducation allowance and monthly sports allowance.\n\nOur company is an equal opportunities employer and welcomes applications from all qualified candidates.\u00a0Information provided will be treated with strict confidentiality and be used for the purpose of selection only.\u00a0Applicants who are not invited for an interview within 10 weeks may consider their applications unsuccessful. Personal data of unsuccessful applicants will be destroyed within 12 months.", "employment_types": ["Full Time"], "selling_points": ["Lead all Web UI/UX design initiatives.", "Designing mobile-based features.", "Optimizing web pages for maximum speed and scalabi"], "locations": ["Central & Western Area"], "categories": ["Information Technology (IT)", "IT - Webmaster / SEO", "Technical Writing", "UI/UX Designer"], "post_time": "2022-01-16T03:00:57Z", "salary": {"currency": null, "max": null, "min": null, "period": "monthly", "term": null}, "salary_visible": false, "title_keywords": ["ux designer"], "responsibilities": ["communicate with", "review", "implementation", "design", "visual", "designing"], "requirements": {"degrees": ["degree", "fresh graduate"], "majors": ["computer science", "information technology"], "languages": [], "language_level": [], "hard_skills": ["web development", "restful api", "web", "react", "javascript", "angular"], "soft_skills": ["sensitivity", "responsive"], "languages_combined": []}, "experience_required": {"duration": ["1 year"], "field": []}}, {"job_id": "100003009048894", "location_code": "hk", "company": "iFAST ePension Services Limited", "job_title": "Frontend / Web Developer", "description": "Responsibilities:\n\nDesign and develop web applications with social media platform integration\u00a0\nEnsure code reusability, data security and applications scalability\nCommunicate with other team members and report to management to make sure the entire project production is on the right track\nContinuously improve the product and develop new features\n\nRequirements:\n\nHigh Diploma or above in Computer Science, Information Technology, or equivalent disciplines\nMinimum 1 years\u2019 relevant experience\u00a0\nInterest in social media analytics\nExperience in at least one modern JS framework (e.g. VueJS, AngularJS, ReactJS).\nFamiliar with web technologies (Javascript , CSS3, HTML5 )\nExperience with public cloud service providers (AWS/GCP) is an advantage.\nWillingness to learn new technologies\nFast learner and independent team player\nGood team player with good interpersonal and communication skills\n\nWe Offer:\n\n5 Days work\nFlexible Working Hour\nBirthday Leave & Anniversary Leave\nMedical Coverage\nFun, young and joyful office environment\u00a0\n\nInterested candidates, please email full resume with 1.) EXPECTED SALARY 2.) AVAILABILITY 3.) WORK REFERENCE\u00a0 to HR department by clicking 'Apply Now'.\n\nFor company information, please refer to the website http://www.presslogic.com/.\n\nAll information received will be kept in strict confidence and only for employment-related purposes.", "employment_types": ["Full Time", "Permanent"], "selling_points": ["Translate wireframes to frontend implementation", "Fresh graduates are welcome", "21 days+ annual leave and company shares (SGX:AIY)"], "locations": ["Central"], "categories": ["Information Technology (IT)", "IT - Webmaster / SEO", "IT Project Management / Team Lead", "Others"], "post_time": "2022-01-14T07:37:29Z", "salary": {"currency": null, "max": null, "min": null, "period": "monthly", "term": null}, "salary_visible": false, "title_keywords": ["developer"], "responsibilities": ["communicate with", "social media", "management", "data", "design and develop", "develop", "report"], "requirements": {"degrees": ["high diploma or above"], "majors": ["computer science", "information technology"], "languages": [], "language_level": [], "hard_skills": ["javascript", "web technologies", "aws"], "soft_skills": ["communication skills", "good team player", "independent", "team player", "fast learner", "interpersonal"], "languages_combined": []}, "experience_required": {"duration": ["minimum 1 years"], "field": ["relevant experience"]}}, {"job_id": "100003009041468", "location_code": "hk", "company": "MediaPlace Limited", "job_title": "Web Developer (Social Media Analytics)", "description": "Job Highlights\n\nWeb Application Development WordPress, PHP\nSelf-motivated,\nResult-orientated\n\n\nJob Responsibilities:\n\nMaintain, troubleshoot and develop features on web-based applications.\nWork closely with the UI/UX team.\nFollower the requirements and implement creativity from the Product team.\nDeliver quality work under the right schedules.\n\nJob Requirements:\n\n\n\nGood technical skills in Javascript(ES5/ES6), HTML, CSS.\nFamiliar with MVVM/MVP/MVC frameworks such as Vue/Angular/React will be an advantage.\nKnowledge of frontend system architecture and common design patterns will be an advantage.\nExperience on Vue3.0/Typescript is a big plus.\n\n\n*Immediate availability is preferred\n\nWorking hour\n\n5-days work\nWork in Kwun Tong", "employment_types": ["Full Time", "Permanent"], "selling_points": ["Fun, young and joyful office environment", "Birthday Leave & Anniversary Leave", "Specializing in developing BrandTech products"], "locations": ["Lai Chi Kok"], "categories": ["Information Technology (IT)", "IT - Webmaster / SEO", "Application Specialist - Network", "Network & System"], "post_time": "2022-01-12T03:55:11Z", "salary": {"currency": null, "max": null, "min": null, "period": "monthly", "term": null}, "salary_visible": false, "title_keywords": ["developer"], "responsibilities": ["schedules", "quality", "develop", "maintain", "troubleshoot", "ui"], "requirements": {"degrees": [], "majors": [], "languages": [], "language_level": [], "hard_skills": ["plus", "react", "html", "typescript", "angular", "css"], "soft_skills": ["technical skills"], "languages_combined": []}, "experience_required": {"duration": [], "field": []}}, {"job_id": "100003009039538", "location_code": "hk", "company": "Price.com.hk Limited", "job_title": "Senior Web Developer / Web Developer", "description": "We have adopted the latest web technologies and open-source software for developing successful websites and in-house platforms, and constantly enhanced and upgraded the technologies to take advantage of the market technology advancements.\u00a0\n\nCurrently, we have projects that are based on the full-stack development framework, such as, ReactJS, NodeJS and cutting edge approaches like DevOps and NoSQL. We need well-experienced IT practitioners to grow with us.\n\nYour role with us involves:\n\neCommerce website development and maintenance, including revamp\nCollaborating with UXUI, Product Management, and QA teams to deliver the best-in-class e-commerce experience on both web and mobile platforms\nDelivering the work in high quality and efficiency\nUtilizing latest and exciting technologies, frameworks, libraries, and development tools\n\nAs an employer, our role is to empower you by bringing your true talents and best self to this dynamic digital world and people we serve. We welcome individuals from all backgrounds, ideally with skills and traits as below:\n\nHigher diploma/certificate or above in Computer Science or other related disciplines\nGreat team player, independent, a strong sense of responsibility and self-motivated\nHands-on experience in SDLC and web development, including but not limited to these skill sets: Node.js, JS, HTML5, CSS3\nExperience in Restful API, RWD, MySQL is preferred\nFamiliar with Agile, cloud platform, Linux, Git, would be an advantage\nStrong sense of web technologies and standards\nTech-savvy and willing to share new technical knowledge\n1 years or above relevant working experience\nCandidates with more experience/skill sets will be considered as Senior Web Developer\nGood communication skills, fluent written and spoken Cantonese and English\n\nBe part of us, you will enjoy:\n\nDiscretionary Bonus\n5-day Work Week\nFlexible Working Hour\nBirthday, Marriage, Maternity and Paternity Leave\nBirthday Gift\nMedical Insurance\nMonthly Birthday Party\nTeam Event and Team Building Activities\nHappy and Dynamic Environment\nCasual Dress Code\n\nWorking Location: Shatin (5 minutes from Shek Mun MTR station)\u00a0\n\n\nInterested parties, please click \"Apply now\" to submit your portfolio and resume with the availability and expected salary to us.\n\n\n\nPersonal data collected will be kept strictly confidential and only be used for recruitment related purposes.", "employment_types": ["Full Time", "Permanent"], "selling_points": ["Fast Growing Industry", "An Expanding E-Commerce Company", "Offer Training & Development"], "locations": ["Shatin Area"], "categories": ["Information Technology (IT)", "IT - Webmaster / SEO", "IT Management", "Network & System"], "post_time": "2022-01-11T10:01:21Z", "salary": {"currency": null, "max": null, "min": null, "period": "monthly", "term": null}, "salary_visible": false, "title_keywords": ["developer"], "responsibilities": ["management", "revamp", "software", "maintenance", "teams", "website", "developing", "quality", "communication", "insurance"], "requirements": {"degrees": ["certificate", "diploma"], "majors": ["related disciplines", "computer science"], "languages": ["cantonese", "english"], "language_level": ["fluent", "good"], "hard_skills": ["linux", "web development", "restful api", "git", "agile", "web", "maintenance", "e-commerce", "devops", "mobile", "sdlc", "dynamic", "code", "web technologies"], "soft_skills": ["flexible", "communication skills", "self-motivated", "dynamic environment", "independent", "agile", "sense of responsibility", "hands-on", "dynamic", "team player"], "languages_combined": [{"language": "cantonese", "language_level": ["fluent", "good"]}, {"language": "english", "language_level": ["fluent", "good"]}]}, "experience_required": {"duration": ["1 years"], "field": ["qa", "e-commerce", "development", "relevant working experience", "product management", "developer"]}}, {"job_id": "100003009041959", "location_code": "hk", "company": "Speedy Group Corp. Limited", "job_title": "IT Helpdesk/ Customer Support (Web Hosting)", "description": "My Client is Asia Pacific\u2019s largest broadcast and media systems integrator. This role is within the special division of the firm that focuses on providing cloud integration and proprietary software solutions for media industry-based clientele as well as Audio-Visual Clients.\n\nJob Overview\u00a0\n\nThe UI/UX Designer is responsible for all the visual elements that users see and interact within company-wide suite of web applications. They will work with the product owners and software engineers in making improvements on current websites, as well as creating new ones from the ground up through developing prototypes and generating the code. They will be the core in creation of well-designed, user-centred, interfaces.\n\nResponsibilities and Duties\n\nLead all Web UI/UX design initiatives.\nWork with stakeholders in developing new user-facing features.\nBuilding high-quality mock-ups and design different wireframes and prototypes.\nStriking a balance between functional and aesthetic design.\nOptimizing web pages for maximum speed and scalability.\nWhere necessary be able to perform SEO.\nDesigning *GREENFIELD* mobile-based features.\nMaintaining brand consistency throughout design.\n\nSkills and Qualifications\u00a0Required:\n\nEither a related university degree or rich UI/UX design experience.\nExperience with the UI/UX workflow, from initial communication to final signoff is necessary.\nFamiliarity with tools such as Sketch, Adobe XD and Figma.\nKnowledge of usability principles across different platforms is important.\nStrong communication skills in English.\nExperience of working with cloud technology, such as AWS, particularly content delivery such as CloudFront and Route 53, is beneficial.\nWorking knowledge of HTML5, CSS3 and ES6 is especially useful.\nExpertise in JavaScript frameworks such as React and Material-UI is advantageous.\nExperience in working with source control, such has GitLab or GitHub.\nUnderstanding of Agile methods and developments tools such as Jira is valuable.\nStrong positive working attitude, quick-learner and able to work independently.\n\nPlease click the apply button or send through your updated CV direct to it.pl.hk (AT ) adecco.com.\u00a0 For more information feel free to call +852 28996179 and ask for Philip for a confidential discussions.", "employment_types": ["Full Time"], "selling_points": ["5-day work week, Medical benefits", "Stable and friendly working environment", "Knowledge in web technology/ common email platform"], "locations": ["Not Specified"], "categories": ["Information Technology (IT)", "IT - Webmaster / SEO", "Support", "Sales, CS & Business Devpt", "Technical Sales / Sales Engineer"], "post_time": "2022-01-12T04:51:17Z", "salary": {"currency": null, "max": null, "min": null, "period": "monthly", "term": null}, "salary_visible": false, "title_keywords": [], "responsibilities": ["control", "seo", "software", "systems", "quality", "developing", "design", "mock-ups", "designing", "communication", "maintaining brand consistency", "visual", "audio", "ui"], "requirements": {"degrees": ["university degree"], "majors": ["design"], "languages": ["english"], "language_level": [], "hard_skills": ["web applications", "seo", "web", "react", "adobe xd", "agile", "web pages", "aws", "mobile", "javascript", "integration", "code", "pl"], "soft_skills": ["communication skills", "work independently", "agile", "responsible", "communication", "positive working attitude"], "languages_combined": [{"language": "english", "language_level": []}]}, "experience_required": {"duration": [], "field": ["related", "design"]}}, {"job_id": "100003009033804", "location_code": "hk", "company": "Nixon Technology Co Ltd", "job_title": "Web Developer / Senior Web Developer", "description": "Job Duties:\n\nHandle technical support via online helpdesk, email, phone call, etc.\nIdentify, diagnose, and resolve problems related to mobile device, operating system, email, network and web/ email server issues\nLog customer requests into the system, follow up and troubleshooting\nMonitor and maintain service quality\n\nJob Requirements:\n\nCertificate/ Diploma or above in Information Technology\nRelated experience in troubleshooting and providing web/ email hosting support\nKnowledge in web technology/ common email platforms is highly advantage\nGood interpersonal, communication skills\nAbility to multi-task\nPositive attitude with good communication skill and teamwork\nWilling to learn new technologies", "employment_types": ["Full Time"], "selling_points": ["Experience in Java/Cloud-based development", "Familiar with frontend build, unit testing and CI", "Knowledge in UX/UI design skill"], "locations": ["Kwun Tong"], "categories": ["Information Technology (IT)", "IT - Webmaster / SEO", "Software Development", "Testing / QA"], "post_time": "2022-01-10T01:49:16Z", "salary": {"currency": null, "max": null, "min": null, "period": "monthly", "term": null}, "salary_visible": false, "title_keywords": ["developer"], "responsibilities": ["technical support", "monitor", "diagnose", "troubleshooting", "quality", "maintain", "customer requests"], "requirements": {"degrees": ["certificate", "diploma or above"], "majors": ["information technology"], "languages": [], "language_level": [], "hard_skills": ["web"], "soft_skills": ["communication skills", "multi-task", "communication skill", "teamwork", "troubleshooting", "willing to learn", "positive attitude", "interpersonal"], "languages_combined": []}, "experience_required": {"duration": [], "field": ["related", "troubleshooting"]}}, {"job_id": "100003009047764", "location_code": "hk", "company": "Public Bank (Hong Kong) Ltd", "job_title": "Assistant Banking Projects Manager (Ref: JD-APM)", "description": "Job Overview:\nThe role of Project Administrator is to assist the Project Manager in driving Digital Projects delivery for our clients in an effective manner. This role is key in maintaining a close relationship with the clients by coordinating and delivering administrative support in a timely manner.\n\nResponsibilities:\n\nAssist Project Manager and the project team with project documentation and coordinate with client\nAssist Business Development team on issuing quotations and invoices\nHandling roster planning, leave records and administration task\nAssist in project coordination\nAssist in office administration\nAssist in ad-hoc assignments and tasks\nCandidates with more experience will be considered for the position of Project Officer.\n\nRequirements:\n\n2 years of solid working experience at administrative capacity\nEffective multitasking skills in a fast-paced IT environment\nExcellent organizational and administrative skills with the ability to work independently and in a team environment\nStrong attention to detail and accuracy\nGood working attitude and self-discipline\nTo apply for this position, please simply click on the \u201cAPPLY NOW\u201d bottom.\n\nAll information provided will be treated in strict confidence and used solely for recruitment purpose.\nFor more job opportunities, please visit our website: https://npsl.com.hk/\n\nFluent in written and spoken English and Cantonese\nComprehensive computer skills is a plus", "employment_types": ["Full Time", "Permanent"], "selling_points": [], "locations": ["Not Specified"], "categories": ["Banking / Finance", "Retail Banking", "Information Technology (IT)", "IT - Webmaster / SEO", "Professional Services", "Legal & Compliance"], "post_time": "2022-01-15T03:49:05Z", "salary": {"currency": null, "max": null, "min": null, "period": null, "term": null}, "salary_visible": false, "title_keywords": ["manager", "assistant"], "responsibilities": ["invoices", "project coordination", "office administration", "ad-hoc assignments", "coordinate with", "planning", "project documentation", "administration"], "requirements": {"degrees": [], "majors": [], "languages": ["cantonese", "english"], "language_level": ["fluent"], "hard_skills": ["plus", "computer skills"], "soft_skills": ["good working attitude", "work independently", "confidence", "organizational", "comprehensive", "attention to detail"], "languages_combined": [{"language": "cantonese", "language_level": ["fluent"]}, {"language": "english", "language_level": ["fluent"]}]}, "experience_required": {"duration": ["2 years"], "field": ["administrative"]}}, {"job_id": "100003009050958", "location_code": "hk", "company": "Links International", "job_title": "Senior Manager, Web & Mobile Marketing", "description": "Manage and co-ordinate bank-wide projects from initiation to implementation\nEstablish / Review bank\u2019s policies and guidelines, procedures, etc. for compliance and/or operational efficiency\nEnsure projects delivered meet with the business requirements and fulfill legal / regulatory requirements\nAttend to regulatory requirement and provide recommendations\nUniversity degree holder in Business, Banking & Finance or IT related disciplines with minimum 3 years in banking operations and/or project management experience\nInitiative,\u00a0independent with ability in handling multi-tasks\nExcellent communication, interpersonal and presentation skills with good command of written and spoken English and Chinese\nCandidate with less experience will be considered as Senior Banking Projects Officer\n\n\nTo apply, interested parties please follow the application methods available in the Bank\u2019s career website\u00a0https://www.publicbank.com.hk/en/aboutus/careeropportunities. You can send us your resume quoting our job reference number together with present &\u00a0expected salary (a must)\u00a0to the Human Resources Department by email or fax at\u00a02815 3157\u00a0or by post to\u00a0Human Resources Department, 12/F, Public Bank Centre, 120 Des Voeux Road Central, Hong Kong. You may also visit our career website for other career opportunities available within our Group.\n\n\n\nPersonal data collected will be used for recruitment purpose only and will be treated in accordance with the Bank\u2019s Personal Information Collection Statement, a copy of which has been available in the Bank\u2019s career website.", "employment_types": ["Full Time", "Permanent"], "selling_points": ["Global financial trading platform", "Web marketing strategy planning", "In-depth knowledge in SEO / search engines"], "locations": ["Not Specified"], "categories": ["Information Technology (IT)", "IT - Webmaster / SEO", "Marketing / Public Relations", "Management", "Others"], "post_time": "2022-01-14T12:02:05Z", "salary": {"currency": null, "max": null, "min": null, "period": "monthly", "term": null}, "salary_visible": false, "title_keywords": ["senior manager"], "responsibilities": ["bank\u2019s policies", "guidelines", "regulatory requirements", "review", "procedures", "implementation", "compliance", "operations", "communication", "project management", "provide recommendations", "banking"], "requirements": {"degrees": ["university degree"], "majors": ["finance", "related disciplines", "project management", "business", "it"], "languages": ["english", "chinese"], "language_level": ["excellent", "good command"], "hard_skills": ["project management"], "soft_skills": ["independent", "multi-tasks", "communication", "project management", "presentation skills", "interpersonal", "initiative"], "languages_combined": [{"language": "english", "language_level": ["excellent", "good command"]}, {"language": "chinese", "language_level": ["excellent", "good command"]}]}, "experience_required": {"duration": ["minimum 3 years"], "field": ["related", "finance", "project management", "business", "it", "banking"]}}, {"job_id": "100003009048369", "location_code": "hk", "company": "KGI Hong Kong Limited", "job_title": "Assistant Vice President, Digital Marketing", "description": "Our client is a leading Financial Trading company. They are expanding the team and looking for Senior Manager, Web & Mobile Marketing to join their team.\n\nJob Description\n\nDevelop website and mobile marketing strategies for all markets including Greater China, India, Korea, etc.\nLead the team in monitoring, maintaining and optimizing the performance of digital platforms\nDrive website re-built project to deliver new websites for targeted markets\nCollaborate closely with product team and technology team for website optimization, covering structure, performance, UX, content perspectives through data analysis\nMaintain strong online presence for the brands across desktop and mobile environments\n\nJob Requirements\n\nDegree holder, with minimum 6 years of related web or mobile marketing\nIn-depth knowledge and experience in website technology, SEO & PPC\nHands-on experience in SEO optimization, preferably gained from financial industry\nKnowledgeable in search engines (google insight, metadata, WeChat integration), data analytic tools (Google Adwords), organic & paid traffics\nExperience in online community growth & maintenance is a plus\nData driven, good problem-solving and tech savvy\nExperiece Highly fluent in both English and Mandarin", "employment_types": ["Full Time"], "selling_points": [], "locations": ["Not Specified"], "categories": ["Information Technology (IT)", "IT - Webmaster / SEO", "Marketing / Public Relations", "Marketing - Marketing Communication"], "post_time": "2022-01-14T06:26:25Z", "salary": {"currency": null, "max": null, "min": null, "period": "monthly", "term": null}, "salary_visible": false, "title_keywords": ["digital marketing", "assistant vice president"], "responsibilities": ["collaborate", "marketing strategies", "maintaining", "monitoring", "website", "develop", "data analysis", "maintain"], "requirements": {"degrees": ["degree holder"], "majors": ["marketing"], "languages": ["english", "mandarin"], "language_level": ["fluent"], "hard_skills": ["plus", "seo", "web", "maintenance", "adwords", "problem-solving", "wechat", "mobile", "integration"], "soft_skills": ["problem-solving", "hands-on", "driven"], "languages_combined": [{"language": "english", "language_level": ["fluent"]}, {"language": "mandarin", "language_level": ["fluent"]}]}, "experience_required": {"duration": [], "field": ["financial industry", "maintenance"]}}, {"job_id": "100003009034458", "location_code": "hk", "company": "Laboratory JaneClare Limited", "job_title": "Web Programmer", "description": "Responsibilities\u00a0\n\nAssist the development of digital channel, customer journey, business cases, use cases, process flows, business requirement and wireframes\nProactively develop, implement and manage the day-to-day tactics and execution of marketing activities across all channels and platforms, including online events and digital marketing campaigns\nManage (content and technical support) website, mobile app and other digital enablement\nWork closely with all related internal & external partners on operation procedural update, including internal procedures, business partners\u2019 policy and regulatory requirements\nManage and liaise with creative and media agencies for SEO, SEM, Facebook and WeChat, etc. Hands-on experience on China Cross-border eCommerce, Social Media, Influencer Marketing is highly appreciated\nMonitor competitors\u2019 activities, conduct market research and prepare analytic report for the best practice\n\nRequirement\n\nBachelor Degree in Marketing or relevant discipline\n10-12 years of relevant experience in a product development or related role. Previous experience in financial institutions, Fintech or Ecommerce industry is highly preferred\nGood understanding in Fintech, Ecommerce and industry players in the markets\nHands-on experience working with both business and technical teams\nSolid experience in Google Analytics, SEO or other media technologies that can drive the digital marketing efforts\nFamiliar with the operation of online social platforms and promotion\nCan-do attitude, ability to work independently as well as a good team player, and strong drive to get things done\nBoth agency and inhouse experience is an advantage\nEmbrace agile methodology\u00a0\n\n(Personal data collected will be used for recruitment purpose only.)\n\nFor more details about career opportunities in KGI, please visit our website: http://www.kgieworld.com/Careers.aspx?sc_lang=en\n\nPlease send application with resume and expected salary quoting the job reference to\u00a0[via APPLY NOW]\u00a0\u00a0 or mail to HR Department, 41/F Central Plaza, 18 Harbour Road, Wanchai, Hong Kong", "employment_types": ["Full Time"], "selling_points": [], "locations": ["Wong Tai Sin Area"], "categories": ["Information Technology (IT)", "IT - Webmaster / SEO"], "post_time": "2022-01-10T03:25:55Z", "salary": {"currency": null, "max": null, "min": null, "period": "monthly", "term": null}, "salary_visible": false, "title_keywords": ["web programmer"], "responsibilities": ["social media", "mobile app", "seo", "technical support", "digital marketing campaigns", "regulatory requirements", "conduct market research", "procedures", "website", "monitor", "develop", "sem", "liaise with", "facebook", "report"], "requirements": {"degrees": ["degree", "bachelor"], "majors": ["marketing"], "languages": [], "language_level": [], "hard_skills": ["google analytics", "harbour", "seo", "agile"], "soft_skills": ["good team player", "work independently", "agile", "can-do attitude", "hands-on"], "languages_combined": []}, "experience_required": {"duration": ["10-12 years"], "field": ["ecommerce", "related", "agency", "financial institutions", "business", "relevant experience", "digital marketing", "product development", "media"]}}, {"job_id": "100003009050809", "location_code": "hk", "company": "Ztore HK Limited", "job_title": "Analyst Programmer (Node.js)", "description": "We are expanding our team and looking for a number of passionate and talented IT professionals to join us and support our business to grow innovatively.\nAs an Analyst Programmer, you will work closely with internal team to study and analysis user requirement. You need to design, develop, test, and implement a Middleware software project that support the business growth.\n\n\nResponsibilities:\n\n\nCommunicating with commercial side colleague, translating business idea and use cases into functional applications\nDesign, build, and maintain efficient, reusable, and reliable code\nEnsure the best possible performance, quality, and responsiveness of the applications\nIdentify bottlenecks and bugs, and devise solutions to these problems\nHelp maintain code quality, organisation, and automatization\nUnderstanding the business domain deeply and working closely with business stakeholders\nRequirement:\n\n\nMinimum 4 Year of web development experience working with Javascript, Node.js, MySQL\nExperience in web framework like Express, Koa, NestJS etc.\nFamiliar with commonly used design patterns\nStrong understanding of TDD development approaches\nExperience in GraphQL, WebSocket is a plus\nExperience in PHP development is a plus\nExperienced in Docker and Kubernetes will be an added advantage\nAbility to quickly grasp any new technologies\nGood communication skill in both Chinese & English\nWhat you will learn:\n\n\nAuto CI/CD\nVersioning tools, such as Git\nContainerized Application (Docker, AWS Fargate, Kubernetes)\nAWS Cloud Services\nHow to solve a business problem\nHow to manage a project\nExperienced in a well-planned software development cycle", "employment_types": ["Full Time"], "selling_points": ["Node.js, Microservices Architecture", "GraphQL, Docker, Kubernetes, AWS Cloud", "Test Driven Development"], "locations": ["Lai Chi Kok"], "categories": ["Information Technology (IT)", "IT - Webmaster / SEO", "IT Management", "Software Development"], "post_time": "2022-01-14T11:26:50Z", "salary": {"currency": null, "max": null, "min": null, "period": "monthly", "term": null}, "salary_visible": false, "title_keywords": ["analyst programmer"], "responsibilities": ["maintain", "communicating with", "quality", "design"], "requirements": {"degrees": [], "majors": [], "languages": ["english", "chinese"], "language_level": ["good"], "hard_skills": ["web development", "plus", "git", "php", "aws", "javascript", "web framework"], "soft_skills": ["communication skill"], "languages_combined": [{"language": "english", "language_level": ["good"]}, {"language": "chinese", "language_level": ["good"]}]}, "experience_required": {"duration": ["minimum 4 year"], "field": ["development"]}}, {"job_id": "100003009049405", "location_code": "hk", "company": "KOS International Limited", "job_title": "Assistant Manager - Performance Marketing (DSP)", "description": "Our clients are looking for a high calibre to join their marketing team.\n\nKey responsibilities\n\nOperate and manage paid media platforms' campaigns and performance\nReport on the performance of different paid media platform and provide campaign insights to assess campaign effectiveness and identify optimisation opportunities\nLead a team for social media marketing ad strategies on Google Ads, Facebook & Instagram\nDrive social media engagement to elevate client experience\n\nBasic Requirements\n\nAt least 3 to 5 years' experience in using demand side platform\nDigital savvy with business and market awareness\nProficiency in Cantonese, Mandarin and English\n\nClick \"Apply Now\" to apply for this position or call Martin Tsang at +852 3180 4971 for a confidential discussion. All information collected will be kept in strict confidence and will be used for recruitment purpose only.", "employment_types": ["Full Time", "Permanent"], "selling_points": ["Able to use demand side platform", "Programmatic media buy", "Paid Advertising"], "locations": ["Not Specified"], "categories": ["Information Technology (IT)", "IT - Webmaster / SEO", "Marketing / Public Relations", "Digital Marketing"], "post_time": "2022-01-14T08:34:01Z", "salary": {"currency": null, "max": null, "min": null, "period": "monthly", "term": null}, "salary_visible": false, "title_keywords": ["assistant manager"], "responsibilities": ["lead a team", "facebook", "social media", "report"], "requirements": {"degrees": [], "majors": [], "languages": ["cantonese", "english", "mandarin"], "language_level": ["proficiency"], "hard_skills": ["basic"], "soft_skills": ["confidence"], "languages_combined": [{"language": "cantonese", "language_level": ["proficiency"]}, {"language": "english", "language_level": ["proficiency"]}, {"language": "mandarin", "language_level": ["proficiency"]}]}, "experience_required": {"duration": ["at least 3 to 5 years"], "field": []}}, {"job_id": "100003009039250", "location_code": "hk", "company": "GP Acoustics Group", "job_title": "Operations Specialist (E-Commerce Platform)", "description": "About the Role\nAs an Operation Specialist (E-Commerce Platform) for both KEF and GP Batteries, you will execute creative projects and ensure all web content is accurately published and up-to-date according to the digital brand guideline. You will work closely with Digital Creative Team based in Kuala Lumpur and Global Digital Marketing team in Hong Kong Headquarter.\n\nKey responsibilities:\n\nPlans and conceptualizes the necessary tests to be carried out for each project.\nPerform UAT occasionally to ensure website content is published accurately, and web applications are working as expected.\nProvide support for the development and maintenance of web content, experience on using ecommerce platform like Shopify will be an advantage.\nAdapt and build content on websites in local context and languages by referring to the branded wireframes and mock-ups.\nReview & crosscheck all graphics, layouts before and after publishing pages.\nAble to work with members from regional teams, and manage multiple projects simultaneously.\nManage digital contents of marketing campaigns across all regional markets.\nEducation & Experience:\n2-4 years of professional experience in CMS operation (preferable in Shopify & Magento), digital design for web, desktop and mobile.\nProven work experience as a web content editor with knowledge in E-Commerce/Mobile Commerce platforms\nPortfolio of completed work experience on websites and E-Commerce/Mobile Commerce platforms\nBasic knowledge of HTML and web development systems\nAn ability to manage multiple projects and meet deadlines in a timely manner\nCreative problem solver with attention to detail\nHands-on experience with graphic design software and image editing tools (e.g. Photoshop and Adobe Illustrator) is preferred\nAdditional qualification in Graphic Design is a plus\nHighly organised with strong project management skills (Fluency with Asana preferred)\nWe offer 5-day work, double pay, medical benefit, free company coaches and bright career prospect to the right candidate. Interested parties please send your application letter with detailed resume stating current salary, expected salary and date of available to hr @ kef.com .\n\nWe are an equal opportunities employer. Personal data collected will be treated as strictly confidential and used for recruitment purpose only.", "employment_types": ["Full Time", "Permanent"], "selling_points": ["Execute creative projects", "2-4 years of professional exp in CMS operation", "Web content development & maintenance"], "locations": ["Shatin Area"], "categories": ["Information Technology (IT)", "IT - Webmaster / SEO", "Marketing / Public Relations", "Digital Marketing", "E-commerce", "Software Development"], "post_time": "2022-01-11T09:10:16Z", "salary": {"currency": null, "max": null, "min": null, "period": "monthly", "term": null}, "salary_visible": false, "title_keywords": ["specialist", "operations"], "responsibilities": ["software", "mock-ups", "website", "design", "plans", "editing", "graphics", "uat", "teams", "manage multiple projects", "marketing campaigns", "provide support", "review", "digital marketing", "contents", "maintenance", "graphic design", "systems", "a timely manner", "project management", "e-commerce platform"], "requirements": {"degrees": [], "majors": [], "languages": [], "language_level": [], "hard_skills": ["graphics", "web development", "plus", "web applications", "basic", "maintenance", "web", "e-commerce", "shopify", "html", "adobe illustrator", "mobile", "project management", "photoshop"], "soft_skills": ["manage multiple projects simultaneously", "problem solver", "project management skills", "timely", "hands-on", "attention to detail", "organised", "meet deadlines", "creative"], "languages_combined": []}, "experience_required": {"duration": ["2-4 years"], "field": ["ecommerce", "maintenance", "e-commerce", "editor", "development", "graphic design", "design", "education", "operation", "digital", "editing"]}}, {"job_id": "100003009043955", "location_code": "hk", "company": "Evergreen System Limited", "job_title": "Analyst Programmer", "description": "Responsibilities:\n\nCloud-based system design and development\nWeb-based application development and cloud configuration\nReport and document test results\nPrepare technical documentation, system test plan and test case\nAssist in analysis of system malfunctions and troubleshooting\n\n\u00a0Requirements:\n\nBachelor degree in Computer Science,\u00a0 Information Technology, Engineering or relevant discipline\n3 year working experience is preferred as\u00a0Senior Web Developer\u00a0\nHands-on experience in Java/Cloud-based development\nFamiliar with popular frontend build tools\nFamiliar with unit testing and CI/CD\nKnowledge in UX/UI design skill is an advantage.\nWilling to learn and open-minded\nLess experience will be considered as\u00a0Web Developer\u00a0\nImmediately available is highly preferred", "employment_types": ["Full Time"], "selling_points": ["Year and Performance Bonus", "5 working day per week", "Fresh graduate are welcome."], "locations": ["Hung Hom"], "categories": ["Information Technology (IT)", "Application Specialist - Software", "IT - Webmaster / SEO", "Technical Writing"], "post_time": "2022-01-13T02:35:25Z", "salary": {"currency": null, "max": null, "min": null, "period": "monthly", "term": null}, "salary_visible": false, "title_keywords": ["analyst programmer"], "responsibilities": ["configuration", "analysis", "troubleshooting", "system design", "plan", "documentation", "application development", "report"], "requirements": {"degrees": ["degree", "bachelor"], "majors": ["engineering", "computer science", "information technology"], "languages": [], "language_level": [], "hard_skills": ["java", "web"], "soft_skills": ["open-minded", "hands-on", "willing to learn"], "languages_combined": []}, "experience_required": {"duration": ["3 year"], "field": ["developer", "development"]}}, {"job_id": "100003009038311", "location_code": "hk", "company": "Nautilus Technology Limited", "job_title": "Front-end Web Developer \u524d\u7aef\u958b\u767c\u5de5\u7a0b\u5e2b", "description": "Job Responsibilities:\n\n1. Be responsible for acquiring user requirement, development to testing, maintenance, enhancements and system support of websites and front-end applications\n\n2. Optimize front-end for maximum speed and scalability\n\n3. Work closely with internal teams, such as back-end and infrastructure, on the assigned projects and conduct project implementation\n\n4. Provide support during system assurance and user acceptance tests\n\n5. Support ad-hoc tasks and requests by the management\n\n\n\nRequirements:\n\n1. Bachelor\u2019s Degree in Computer Science or relevant field\n\n2. At least 1 year of front-end project experience, able to independently undertake front-end development work\n\n3. Professional experience with Vue or React\n\n4. A solid understanding in core web and browser concepts (eg. how the browser parses and constructs a web page) - A solid understanding of semantic HTML, CSS, and core JavaScript concepts.\n\n5. Demonstrated capacity to clearly and concisely communicate about complex technical, architectural, and/or organizational problems and propose thorough iterative solutions\n\n6. Experience using Git in a professional/workplace environment\n\n7. Strong command of both written and spoken English and Chinese (Especially in Mandarin)", "employment_types": ["Full Time", "Permanent"], "selling_points": [], "locations": ["Tsim Sha Tsui"], "categories": ["Information Technology (IT)", "IT - Webmaster / SEO", "Network & System", "Technical Writing"], "post_time": "2022-01-11T06:35:07Z", "salary": {"currency": null, "max": null, "min": null, "period": "monthly", "term": null}, "salary_visible": false, "title_keywords": ["developer"], "responsibilities": ["user requirement", "provide support", "management", "maintenance", "ad-hoc tasks", "infrastructure", "teams", "implementation", "testing"], "requirements": {"degrees": ["degree", "bachelor"], "majors": ["computer science"], "languages": ["english", "chinese", "mandarin"], "language_level": [], "hard_skills": ["git", "web", "react", "html", "javascript", "css"], "soft_skills": ["organizational", "independently", "thorough"], "languages_combined": [{"language": "english", "language_level": []}, {"language": "chinese", "language_level": []}, {"language": "mandarin", "language_level": []}]}, "experience_required": {"duration": ["at least 1 year"], "field": ["development"]}}, {"job_id": "100003009039535", "location_code": "hk", "company": "Price.com.hk Limited", "job_title": "Analyst Programmer", "description": "Job Duties:\n-\u00a0 \u00a0Take care of a one-page skincare retail website with RESTful API connections to third-party modules\n-\u00a0 \u00a0Work with designers to come up with website frontend designs\u00a0 \u00a0\u00a0\n-\u00a0 \u00a0 Build up basic website frontend and maintain backend system\n-\u00a0 \u00a0 Responsible for various programming and coding tasks\n-\u00a0 \u00a0 Undertake any other ad hoc duties as assigned\n\nRequirements:\n-\u00a0Experience in programming (HTML, Javascript, PHP, MYSQL, etc.)\n-\u00a0Must be experienced in working with remote data via third-party modules\n- Understanding of RESTful API, JSON, etc. is essential\n- Knowledge in Python, Tensorflow and ML/DL principles is appreciated\n- With frontend/design experience or with good artistic senses will be of advantage\n-\u00a0Good analytical & problem solving skills, teamwork, communication and interpersonal skills", "employment_types": ["Full Time", "Permanent"], "selling_points": ["Fast Growing Industry", "An Expanding E-Commerce Company", "Offer Training & Development"], "locations": ["Shatin Area"], "categories": ["Information Technology (IT)", "IT - Webmaster / SEO", "IT Management", "Network & System"], "post_time": "2022-01-11T10:01:20Z", "salary": {"currency": null, "max": null, "min": null, "period": "monthly", "term": null}, "salary_visible": false, "title_keywords": ["analyst programmer"], "responsibilities": ["ad hoc duties", "maintain", "website", "coding"], "requirements": {"degrees": [], "majors": [], "languages": [], "language_level": [], "hard_skills": ["restful api", "php", "html", "ml", "javascript", "programming", "python", "problem solving skills"], "soft_skills": ["problem solving skills", "teamwork", "communication and interpersonal skills"], "languages_combined": []}, "experience_required": {"duration": [], "field": ["programming", "design"]}}, {"job_id": "100003009054930", "location_code": "hk", "company": "SunnyVision Limited", "job_title": "Web Developer", "description": "Responsibilities:\n-To develop web applications using PHP, React, Laravel, MySQL,\u00a0Redis and other APIs\n-To follow up customer for system requirements and feedbacks\n\nRequirements:\n- Minimum 1 year of relevant experience in web programming with past job reference\n- Proven knowledge\u00a0 in PHP, API, SQL, JavaScript, CSS are essentials.\n- Proven knowledge in development tools of Git, PhpUnit\u00a0are essentials.\n- Familiar with Shell Scripts / Linux (CentOS)Server knowledge\u00a0will be a plus.\n- Familiar with docker, CD/CI knowledge\u00a0will be a plus.\n- Good command of written Chinese, English\n- Self-motivated, responsible, able to work independently under tight deadline and willing to work under pressure\n- Experienced/Outstanding candidates will be considered as Analyst Developer\n- Immediately available preferred\n\nWe Offer:\n- Attractive remuneration package (Basic + Bonus)\n- Bank Holiday\n\nWant to know more about us, please visit http://www.sunnyvision.com\n\n9:00am-6:00pm, 5 days week, Mon-Fri (3 months probation)\n\nInterest party, please send your full resume with CURRENT & EXPECTED SALARY by email to jobs at sunnyvision.com\u00a0for an interview.\n\nAll applications will be treated in the strictest confidence. We regret that only shortlisted candidates will be notified. Data collected will be used for recruitment purpose only.\u00a0", "employment_types": ["Full Time", "Permanent"], "selling_points": ["Develop web applications using PHP, MySQL, Redis", "Proven knowledge in PHP, React, Laravel, MySQL", "Familiar with Linux, CD/CI, Docker will be a plus"], "locations": ["Wong Tai Sin Area"], "categories": ["Information Technology (IT)", "Application Specialist - Software", "IT - Webmaster / SEO", "Software Development"], "post_time": "2022-01-17T14:20:31Z", "salary": {"currency": null, "max": null, "min": null, "period": "monthly", "term": null}, "salary_visible": false, "title_keywords": ["developer"], "responsibilities": ["develop"], "requirements": {"degrees": [], "majors": [], "languages": ["english", "chinese"], "language_level": ["good command"], "hard_skills": ["linux", "plus", "git", "web", "php", "sql", "javascript", "programming", "css"], "soft_skills": ["self-motivated", "work independently", "responsible", "work under pressure"], "languages_combined": [{"language": "english", "language_level": ["good command"]}, {"language": "chinese", "language_level": ["good command"]}]}, "experience_required": {"duration": ["minimum 1 year"], "field": ["relevant experience", "programming"]}}, {"job_id": "100003009055782", "location_code": "hk", "company": "Hong Kong Express Airways Limited", "job_title": "Assistant Manager, Web Infrastructure Operations", "description": "DEAR TALENT, YOUR MOVE!\n\nBeing the new rising airline since 2013, we are the Hong Kong\u2019s only Low Cost Carrier (LCC) offering you safe and flexible service options to Hong Kong and beyond.\n\nWe\u2019re on a mission to inspire you to be different, to shake things up, to inspire the spirit of adventure by bringing you to fascinating destinations that few others serve.\n\nSpread your wings and fly with us!\n\n\nWhat will you do?\u00a0\n\nLead a small team to maintain daily IT Web Infrastructure operation to support internal users within SLA under ITIL standard;\nProvide technical implementation and support on cloud infrastructure in terms of OS, network, and database, e.g. Microsoft Office 365 applications, AliCloud, Google Cloud, Azure and other IaaS Cloud services providers;\nManage the service providers to provide technical support;\nPerform vendor management, work closely with outsourcing partners on daily operation;\nSupport internal audit to assess Web environment;\nSupport Security team to handle security events;\nSupport Infrastructure & Security projects delivery;\nOversee and develop IT security policies and guidelines for web infrastructure environments;\nPlan, design and implement appropriate technological solutions to defend against cyber-attacks and intrusion;\nCoordinate with other business and IT teams for application enhancements;\nEvaluate and assess emerging web technologies to maintain a cost-effective web environment;\nDevelop and input into key technology Infrastructures Engineering Lifecycle documentation, such as component version and patch management decisions;\nDrive continuous improvement to support the business;\nCoach and mentor team members;\nOn-call for emergency production incidents to provide fire-fighting support and perform shift duties as required;\nPerform other ad-hoc projects and tasks as assigned.\n\nWe are a perfect match, if you are:\n\nUniversity degree preferably in Information Technology, Information Security, Computer Science or related discipline;\nMinimum 6 years of experience in Web Infrastructure, Security, Architecture, including 3 years of managing experience in a supervisory role;\nKnowledge of Cloud-based security, architecture, and development;\nKnowledge of any security product (CyberArk, Qualys, DLP, SIEM);\nKnowledge of applications Cloud-native & containerize solution with RDS on AliCloud, Google Cloud, Azure, FlashGrid Launcher (Infrastructure-as-code, storage fabric, cloud area network, patching Grid infrastructure, database patching, ASM disk group, EC2 instances, VPC networking);\nKnowledge of VDI technology to strengthen access control;\nBasic knowledge of DNS, DHCP, TCP/IP, LAN & WAN, IPsec, and OpenVPN concepts;\nProficient with Linux cmd, Windows cmd, and scripting;\nKnowledge and experience with Windows 10, Windows Server 2016-19, and Active Directory;\nVirtualization knowledge (Hyper-V, VMWare) is an advantage;\nTeam player who is self-driven and organized;\nExcellent communication, facilitation, interpersonal skills, problem solving and team building skills;\nGreat sense of ownership and servicing mindset to ensure efficient / effective customer service process;\nProficiency in both English and Chinese;\nCandidate with less experience will be considered as Specialist, Web Infrastructure Operations.\n\nYour Future Work Life?\n\nWork flexibly with staggered working hours and flexible workplace\nDress Casual and Smart everyday\nWork in a newly-designed office with open seating, stylish breakout areas, game room, gym and free coffee\u2026\nWork with a group of energetic and multicultural professionals (up to 50 nationalities!)\nHave great fun in Snack Friday, New Year Market, Fly with your Kids Day, Basketball Team\u2026\nHave your voice heard through Townhalls, Crew forums, CEO live sessions etc.\n\nWhat will you enjoy?\n\nFly anywhere we fly for free plus taxes during leisure with your friends and family\nSpecial privileges to buy duty free products\nCareer Express\n\n\n\nYou will be inspired by our core values.\nYou will be inspired by our vibrant, efficient and entrepreneurial spirit. Join our fun, collaborative and reliable team to ignite your dream!\n\n\n\nInterested? It\u2019s time to have YOUR MOVE!\nIf you're ready to embark your adventure, start by clicking the \u2018Apply now\u2019 and get on the plane to fly with HK Express!\u00a0", "employment_types": ["Full Time"], "selling_points": ["Flexible Working Practices, WFH, Travel Benefits", "Maintain daily IT web infrastructure operations", "Develop a cost-effective web environment"], "locations": ["Tung Chung"], "categories": ["Information Technology (IT)", "IT - Webmaster / SEO", "Security", "Network & System"], "post_time": "2022-01-18T02:56:52Z", "salary": {"currency": null, "max": null, "min": null, "period": "monthly", "term": null}, "salary_visible": false, "title_keywords": ["operations", "assistant manager,"], "responsibilities": ["internal audit", "information security", "active directory", "design", "infrastructure operations", "communication", "maintain", "customer service", "database", "plan", "ad-hoc projects", "infrastructure", "teams", "implementation", "develop", "patch management", "architecture", "cost", "management", "coordinate with", "documentation", "dns", "technical support", "policies", "lead a small team", "guidelines", "daily operation", "evaluate", "access control"], "requirements": {"degrees": ["university degree"], "majors": ["computer science", "information technology"], "languages": ["english", "chinese"], "language_level": ["proficiency"], "hard_skills": ["itil", "plus", "azure", "web", "active directory", "vendor", "safe", "wan", "hyper-v", "vmware", "fun", "tcp", "problem solving", "os", "lcc", "web technologies", "small", "basic", "airline", "sla", "documentation", "linux", "dns", "microsoft office", "ip", "windows 10", "code", "windows server"], "soft_skills": ["flexible", "organized", "efficient", "collaborative", "communication", "problem solving", "energetic", "customer service", "interpersonal skills", "reliable", "team player", "active", "driven"], "languages_combined": [{"language": "english", "language_level": ["proficiency"]}, {"language": "chinese", "language_level": ["proficiency"]}]}, "experience_required": {"duration": ["3 years", "minimum 6 years"], "field": ["supervisory", "infrastructure", "security"]}}, {"job_id": "100003009055852", "location_code": "hk", "company": "NP Solution Limited", "job_title": "Project Administrator - Digital Projects", "description": "Job Overview:\nThe role of Project Administrator is to assist the Project Manager in driving Digital Projects delivery for our clients in an effective manner. This role is key in maintaining a close relationship with the clients by coordinating and delivering administrative support in a timely manner.\n\nResponsibilities:\n\nAssist Project Manager and the project team with project documentation and coordinate with client\nAssist Business Development team on issuing quotations and invoices\nHandling roster planning, leave records and administration task\nAssist in project coordination\nAssist in office administration\nAssist in ad-hoc assignments and tasks\nCandidates with more experience will be considered for the position of Project Officer.\n\nRequirements:\n\n2 years of solid working experience at administrative capacity\nEffective multitasking skills in a fast-paced IT environment\nExcellent organizational and administrative skills with the ability to work independently and in a team environment\nStrong attention to detail and accuracy\nGood working attitude and self-discipline\nTo apply for this position, please simply click on the \u201cAPPLY NOW\u201d bottom.\n\nAll information provided will be treated in strict confidence and used solely for recruitment purpose.\nFor more job opportunities, please visit our website: https://npsl.com.hk/\n\nFluent in written and spoken English and Cantonese\nComprehensive computer skills is a plus", "employment_types": ["Full Time", "Part Time", "Permanent"], "selling_points": ["remote work", "mobile and digital transform project", "Scrum & Agile"], "locations": ["Not Specified"], "categories": ["Information Technology (IT)", "IT - Webmaster / SEO", "Support", "Others"], "post_time": "2022-01-18T03:00:53Z", "salary": {"currency": null, "max": null, "min": null, "period": "monthly", "term": null}, "salary_visible": false, "title_keywords": ["project administrator"], "responsibilities": ["invoices", "project coordination", "office administration", "ad-hoc assignments", "coordinate with", "planning", "project documentation", "administration"], "requirements": {"degrees": [], "majors": [], "languages": ["cantonese", "english"], "language_level": ["fluent"], "hard_skills": ["plus", "computer skills"], "soft_skills": ["good working attitude", "work independently", "confidence", "organizational", "comprehensive", "attention to detail"], "languages_combined": [{"language": "cantonese", "language_level": ["fluent"]}, {"language": "english", "language_level": ["fluent"]}]}, "experience_required": {"duration": ["2 years"], "field": ["administrative"]}}, {"job_id": "100003009035801", "location_code": "hk", "company": "Macroview Telecom Limited", "job_title": "Application Developer / Programmer", "description": "Descriptions:\n\nAssist in the overall software development life cycle of IT systems\nImplement systems and conduct testing\nSoftware and technology evaluation\nRequirements:\n\nHigher Diploma or Degree in Computer Science or related disciplines\nHands-on experience in Microsoft C#.Net, MySQL, ReactJS - Familiar with HTML5, CSS3, JavaScript, REST API, .Net Core, Linux\nKnowledge in Mobile Apps development and tools (e.g. React Native) or Responsive UI design will be an advantage\nGood team player with good communication skills\nProactive, hard-working and self-motivated\nFresh graduates are also welcome", "employment_types": ["Full Time", "Permanent"], "selling_points": ["Higher diploma or above in programming", "C#.Net, MySQL, ReactJS", "Web-based project implementation"], "locations": ["Quarry Bay"], "categories": ["Information Technology (IT)", "IT - Webmaster / SEO", "Software Development", "Others", "Student / Fresh Graduate / No Experience"], "post_time": "2022-01-10T08:27:05Z", "salary": {"currency": null, "max": null, "min": null, "period": "monthly", "term": null}, "salary_visible": false, "title_keywords": ["developer", "programmer"], "responsibilities": ["software", "systems", "design", "testing", "communication", "evaluation", "ui"], "requirements": {"degrees": ["diploma", "degree"], "majors": ["related disciplines", "computer science"], "languages": [], "language_level": [], "hard_skills": ["linux", "mobile", "javascript", "react native", "c#"], "soft_skills": ["communication skills", "good team player", "self-motivated", "hands-on", "hard-working", "proactive", "responsive"], "languages_combined": []}, "experience_required": {"duration": [], "field": []}}, {"job_id": "100003009036135", "location_code": "hk", "company": "BOCI", "job_title": "AVP, Java Developer, Information Technology", "description": "We are expanding our team and looking for a number of passionate and talented IT professionals to join us and support our business to grow innovatively.\n\nAs a Java Analyst Programmer, you will work closely with internal Development Team to design, develop, test, and implement a Middleware software project that support the business growth.\n\n\nResponsibilities:\n\n\nCommunicating with internal development team and use cases into functional applications\nParticipate in full development life cycle from system design, coding, development, testing, debug, document and implement\nEnsure the best possible performance, quality, and responsiveness of the applications\nIdentify bottlenecks and bugs, and devise solutions to these problems\nHelp maintain code quality, organisation, and automatization\nUnderstanding the business domain deeply and working closely with business stakeholders\n\nRequirement:\n\n\nMinimum 6 Year of web development experience working with Java, Spring Boot, Spring MVC, Spring Cloud and MySQL in Microservices architecture\nProficient in Java 8, familiar with OOP, Java multi-threading, high concurrency, IO / NIO, network communication, etc\nFamiliar with commonly used design patterns, with experience in design and development of large-scale distributed, high concurrency, high load, high availability systems \u2022 Strong understanding of TDD development approaches\nExperienced in Docker and Kubernetes will be an added advantage\nKnowledge on Kafka, MQ and AWS Cloud is a plus\nAbility to quickly grasp any new technologies\nGood communication skill in both Chinese & English\n\nWhat you will learn:\n\n\nAuto CI/CD\nVersioning tools, such as Git\nContainerized Application (Docker, AWS Fargate, Kubernetes)\nAWS Cloud Services\nHow to solve a business problem\nHow to manage a project\nExperienced in a well-planned software development cycle", "employment_types": ["Full Time"], "selling_points": ["JAVA Development", "Implementation of technical solution", "Investment Banking"], "locations": ["Kwai Hing"], "categories": ["Information Technology (IT)", "IT - Webmaster / SEO", "IT Management"], "post_time": "2022-01-10T09:25:51Z", "salary": {"currency": null, "max": null, "min": null, "period": "monthly", "term": null}, "salary_visible": false, "title_keywords": ["developer"], "responsibilities": ["quality", "coding", "testing", "communicating with", "system design", "maintain"], "requirements": {"degrees": [], "majors": [], "languages": ["english", "chinese"], "language_level": ["good"], "hard_skills": ["web development", "java", "plus", "io", "git", "microservices", "aws", "spring"], "soft_skills": ["communication", "communication skill"], "languages_combined": [{"language": "english", "language_level": ["good"]}, {"language": "chinese", "language_level": ["good"]}]}, "experience_required": {"duration": ["minimum 6 year"], "field": ["development", "design"]}}, {"job_id": "100003009029689", "location_code": "hk", "company": "The Egg Company Limited", "job_title": "Junior SEO Specialist / Digital Editor / Digital Marketing Executive", "description": "The Role\n\nOur development team is looking for a motivated, versatile full stack web developer to help create and operate front-office trading and back-office settlement systems. The ideal candidate will be able to utilize their technical skills, communication skills, and creativity to provide technical solutions for our business needs.\u00a0\n\nKey Accountabilities\n\nDeveloping front to back website in microservices architecture.\nDesigning and developing microservices APIs\nImplementation of technical solution with development standards, best practice and security policy.\nPrepare and maintain technical documentation\nTesting environment management\n2nd line production support\n\nSkills & Experience\n\n5+ years of web application development experience.\nFamiliarity with front end coding and JavaScript frameworks, such as HTML, CSS, Angular JS, and React.\nProficient in Java back end coding, such as core Java, JMS, JDBC, Spring Cloud, Spring Boot, TCP/IP socket programming and multi-threaded programming.\nStrong SQL and DB tuning skill\nKnowledge of Maven, Gradle and Jenkins build tool\nKnowledge of MS SQL, Oracle and Sybase DB\nKnowledge of Windows Server, Linux and Unix environment\nFocus on quality, responsiveness, efficiency, and innovation.\n\nOther Information\n\nNotes to applicants:\n\nPlease apply in strict confidence with full resume, academic record, current and expected salaries.\nThe personal data provided will be used for consideration of recruitment only. All personal data of unsuccessful candidate will be destroyed within 24 months.\nCandidates with Enhanced Competency Framework (ECF): please state on the CV.\n\nAbout BOCI\n\nAs a leading investment bank in China and Hong Kong region, the investment banking arm of Bank of China, BOC International Holdings Limited (\u201cBOCI\u201d), is now seeking highly motivated, creative and success-oriented professional who would like to pursue the career in our group", "employment_types": ["Full Time", "Permanent"], "selling_points": ["Work with an international digital marketing team", "Work with the newest tools and tactics in digital", "Great exposure across a wide range of industries"], "locations": ["Causeway Bay"], "categories": ["Media & Advertising", "Editorial / Journalism", "Information Technology (IT)", "IT - Webmaster / SEO", "Marketing / Public Relations", "Marketing - Marketing Communication"], "post_time": "2022-01-07T07:24:19Z", "salary": {"currency": null, "max": null, "min": null, "period": "monthly", "term": null}, "salary_visible": false, "title_keywords": ["specialist", "digital marketing executive", "digital editor", "junior"], "responsibilities": ["management", "systems", "quality", "developing", "website", "implementation", "communication", "coding", "personal data", "maintain", "recruitment", "banking", "designing", "documentation", "testing environment", "application development", "architecture"], "requirements": {"degrees": [], "majors": [], "languages": [], "language_level": [], "hard_skills": ["web application development", "jenkins", "web", "focus", "java", "tcp", "microservices", "ms sql", "html", "sql", "javascript", "angular", "documentation", "oracle", "linux", "react", "ip", "spring", "programming", "css", "windows server"], "soft_skills": ["communication skills", "confidence", "versatile", "motivated", "technical skills", "focus", "creative", "ideal"], "languages_combined": []}, "experience_required": {"duration": ["5+ years"], "field": ["application development"]}}, {"job_id": "100003009039083", "location_code": "hk", "company": "We Create Limited", "job_title": "PHP back-end Developer", "description": "Job Highlights\n- 5-day Work Week, Flexible Working Hour\n- Medical allowance\n- Casual Dress Code\n- Competitive Pay\n- Performance Bonus\n\nResponsibilities:\n1. Perform technical microservice architecture design, development, unit testing and development integration testing to deliver high performance, flexible and reliable software systems\n2. Responsible for applications development and maintenance\n3. Working on design and development of the infrastructure\n4. Ensure code quality and operational efficiency, and have the ability to adjust and optimize project code.\n5. Willing to learn, hardworking, committed and proactive\n\nRequirements:\n- 2-3 years experience in software development\n- Higher diploma/certificate or above in Computer Science or other related disciplines\n- Familiar with java/golang development experience is preferred\n- Knowledge in SQL(MySQL), NoSQL(MongoDB, Redis)\n- Familiar with Git and/or GitHub\n- Experience in Docker / Kubernetes and CI/CD will be a plus\n- Good Logical-thinking, Research-spirit, Passion on technology\n- Fluent in English, good written and verbal communication skills\n\nBonus experience:\n- Flutter / Dart\n- Docker\n- Linux\n- Node.js\n\nLess relevant experienced candidates / Fresh graduate are welcome to apply.", "employment_types": ["Full Time", "Permanent"], "selling_points": ["PHP back-end Developer for 2+ years", "Superb career growth opportunities and 20% WFH", "Experience with WordPress and WooCommerce"], "locations": ["Aberdeen"], "categories": ["Information Technology (IT)", "Application Specialist - Software", "IT - Webmaster / SEO", "Software Development"], "post_time": "2022-01-11T08:39:31Z", "salary": {"currency": null, "max": null, "min": null, "period": "monthly", "term": null}, "salary_visible": false, "title_keywords": ["developer"], "responsibilities": ["software", "maintenance", "systems", "infrastructure", "quality", "design", "testing", "architecture"], "requirements": {"degrees": ["certificate", "diploma", "fresh graduate"], "majors": ["related disciplines", "computer science"], "languages": ["english"], "language_level": ["good", "fluent"], "hard_skills": ["linux", "java", "git", "plus", "dart"], "soft_skills": ["communication skills"], "languages_combined": [{"language": "english", "language_level": ["fluent", "good"]}]}, "experience_required": {"duration": ["2-3 years"], "field": ["development", "software development"]}}, {"job_id": "100003009022806", "location_code": "hk", "company": "Hong Kong Adventist College", "job_title": "IT TECHNICIAN", "description": "Key Responsibilities:\nSupport all aspects of Search Engine Optimization (SEO) campaigns from strategy development, planning, execution, optimization to analysis and reporting.\nUnderstand the key concepts of keyword research, on-site optimization and link building techniques.\nMonitor key metrics and analyze results to provide recommendations and strategies for continued campaign improvement.\nManage client campaigns to ensure deliverables and performance goals are met.\nDemonstrate passion for the search engine and online marketing space by staying abreast of industry news.\nNo programming is required in the job role.\nRequirements:\nNative Cantonese speaker with high level of English.\nUniversity degree holder.\nAny relevant experience in blogging/web development is a strong plus.\nProficiency in Microsoft Office applications, especially Excel functions such as vlookup, pivot table, etc.\nSoft Skills:\nAttentive to details and well organized.\nPatience and flexibility to handle multiple ongoing tasks.\nProblem solving skills.\nExcellent communicator.\nAbility to work with little supervision.\nCooperative team player.\nPossesses strong business ethics, is reliable and dependable.\n\nPlease send your cover letter, resume and expected salary to us.", "employment_types": ["Full Time", "Permanent"], "selling_points": ["Bachelor\u2019s degree in information technology", "To develop and maintain the school's website", "To provide day-to-day technical support"], "locations": ["Not Specified"], "categories": ["Information Technology (IT)", "IT - Webmaster / SEO", "Support", "Network & System"], "post_time": "2022-01-10T03:38:40Z", "salary": {"currency": null, "max": null, "min": null, "period": "monthly", "term": null}, "salary_visible": false, "title_keywords": ["it technician"], "responsibilities": ["reporting", "seo", "analysis", "monitor", "provide recommendations", "planning"], "requirements": {"degrees": ["university degree"], "majors": [], "languages": ["cantonese", "english"], "language_level": ["native"], "hard_skills": ["excel", "web development", "plus", "microsoft office", "pivot table", "problem solving skills", "vlookup"], "soft_skills": ["attentive to details", "cooperative", "well organized", "team player", "patience", "problem solving skills", "reliable", "communicator"], "languages_combined": [{"language": "cantonese", "language_level": ["native"]}, {"language": "english", "language_level": ["native"]}]}, "experience_required": {"duration": [], "field": ["development", "relevant experience"]}}, {"job_id": "100003009039840", "location_code": "hk", "company": "GoGoChart Technology Limited", "job_title": "Senior/Digital Marketing Executive", "description": "PHP back-end Developer\n\nAre you an highly experienced, ambitious PHP and WordPress developer looking for a challenging role where you can learn lots more? We are looking for a motivated PHP and WordPress developer to come join our fast-paced, fun and rewarding agile team of professionals.\n\nIf you are passionate about technology, constantly seeking to learn and improve skill set, then you are the type of person we are looking for!\n\nWe are offering superb career growth opportunities, great compensation and benefits.\n\nJob Description\n\nWe are looking to hire a talented PHP developer to manage our back-end services and ensure a seamless interchange of data between the server and our users. As a PHP developer, you will be responsible for developing and coding all server-side logic. You will also be required to maintain the central database and respond to requests from front-end developers.\n\nYou should have in-depth knowledge of object-oriented PHP programming, understanding of MVC design, and working knowledge of front-end technologies including HTML5, JavaScript, and CSS3. Ultimately, you should be able to build efficient and reusable PHP modules while seamlessly integrating front-end technologies.\n\nPHP Developer duties and responsibilities\n\n- Develop, record and maintain cutting edge web-based PHP applications on portal plus premium service platforms.\n- Build innovative, state-of-the-art applications and collaborate with the User Experience (UX) and User Interface (UI) team.\n- Lead the entire web application development life cycle right from concept stage to delivery and post launch support.\n- Refactor, optimize and improve the existing codebase for maintenance and scale.\n- Prepare and maintain all applications utilizing standard development tools.\n- Utilize backend data services and contribute to increase existing data services API.\n- Convey effectively with all task progress, evaluations, suggestions, schedules along with technical and process issues.\n- Document the development process, architecture, and standard components.\n- Use test driven development and acceptance tests to ensure feature quality.\n- Coordinate with co-developers, UX/UI designers and keeps project managers well informed of the status of development effort and serve as liaison between development staff and project manager.\n\nPHP Developer requirements and qualifications\n\n- Previous working experience as a PHP Developer for 2+ years\n- BS/MS\u00a0 in Computer Science, Engineering or a similar relevant field\n- Experience with WordPress and WooCommerce\n- Experience with PHP MVC frameworks (Laravel/CodeIgniter)\n- Excellent relational database skills with MySQL\n- Experience with code versioning tool; Git\n- Knowledge of front-end technologies including HTML5, CSS3, JavaScript and jQuery\n- Experience with building REST API and JSON Web Services\n- Agile methodology of web development\n\nHighly Beneficial\n\n- Wordpress Custom Theme experience\n- Node.js, Strapi CMS experience\n- Plesk, Google Cloud/AWS experience\n- Bootstrap, React, Flutter experience\n- Apache management\n- Agency work experience\n\nPlease note\n\nPlease add your expected salary when applying, your Git and any URL\u2019s of sites you have worked on.\n\nFor candidates selected for interviews please bring along samples of websites, e-commerce platforms and apps\u00a0 you have created.\n\nRecent graduates with Laravel or Wordpress experience will also be considered.\n\nIf you have previously applied for a position at WECREATE before please feel free to\u00a0apply again.", "employment_types": ["Full Time", "Permanent"], "selling_points": ["Group Medical, Dental, Work-life balance provided", "Fun and Dynamic Working Environment", "Attractive leave entitlement and unlimited snacks"], "locations": ["Lai Chi Kok"], "categories": ["Media & Advertising", "Creative / Design", "Information Technology (IT)", "IT - Webmaster / SEO", "Marketing / Public Relations", "Digital Marketing"], "post_time": "2022-01-11T11:53:36Z", "salary": {"currency": null, "max": null, "min": null, "period": "monthly", "term": null}, "salary_visible": false, "title_keywords": ["digital marketing executive"], "responsibilities": [], "requirements": {"degrees": [], "majors": [], "languages": [], "language_level": [], "hard_skills": [], "soft_skills": [], "languages_combined": []}, "experience_required": {"duration": [], "field": []}}, {"job_id": "100003009034414", "location_code": "hk", "company": "Simatelex Manufactory Co., Ltd.", "job_title": "Analyst Programmer", "description": "GoGoChart is a fast expanding start-up company, we are seeking different talent and expert in various division to join our dynamic and energetic team.\n\nWe willing to offer a competitive package and fringe benefits if you are the ideal candidate.\n\nWe believe our employees are the essential assets to lead the company to successful.\n\nResponsibilities:\n\nDrive Leads for business development team to follow up\nStay up-to-date with industry developments, generate new ideas and experiment with new tools to feed into wider marketing strategy\nDevise & create marketing material across multiple channels, including social media, blog, newsletter, website to support business objectives\nKeep track of marketing effectiveness and constantly evaluating which combination of channels, campaigns, demographics, and budget allocation produces the best results\nImplement media strategies via multiple online & offline platforms and keep up to date with advertising metrics (CTR, CPM, ROAS, ROI, etc) & organic / paid content to optimize campaign performance\nManage & design tags for capturing data for re-targeting & conversion tracking\nCompile regular report on performance of all digital platforms and provide insights to gain in-depth understanding on customer behavior\nA dynamic & expanding team focusing on start-up and early-stage project\nProvide marketing operation support and assist in other projects as assigned\nRequirements:\n\nDegree holder or above in Marketing, Digital Marketing, Business Communication or any related disciplines\nMinimum 3 years marketing experience (Agency background is preferred)\nHands-on experience in Website development, SEO, SEM, social media management, Google Analytics and content development\nProficiency in design and video editing software such as Photoshop, AI, Premiere Pro is preferred\nAble to handle multi-tasks with strong problem-solving skills with a can-do attitude\nGood team player, self-motivated, hard-working and able to work under pressure\nExcellent command of Chinese and English writing\nPlease apply immediately if you are the ideal candidate!", "employment_types": ["Full Time", "Permanent"], "selling_points": [], "locations": ["Aberdeen"], "categories": ["Information Technology (IT)", "Application Specialist - Software", "IT - Webmaster / SEO", "Software Development"], "post_time": "2022-01-10T03:21:08Z", "salary": {"currency": null, "max": null, "min": null, "period": null, "term": null}, "salary_visible": false, "title_keywords": ["analyst programmer"], "responsibilities": [], "requirements": {"degrees": [], "majors": [], "languages": [], "language_level": [], "hard_skills": [], "soft_skills": [], "languages_combined": []}, "experience_required": {"duration": [], "field": []}}, {"job_id": "100003009038282", "location_code": "hk", "company": "BOCI", "job_title": "System Engineer (Renewable Contract)", "description": "The role\n\nThe position is responsible for supporting the enterprise infrastructure within Windows & Virtualization Platform.\n\nKey accountabilities\n\nGeneral system administration and reporting\nInstallation, configuration & operation of Windows and VMware virtualization platform\nTroubleshooting, monitoring, tuning and optimization of Windows and VMware virtualization platform\nLogging and documenting production / service problems; identifying recurring problems and implementing preventative measures.\nResponsible for system backups, recoveries, patches and upgrades\nCo-ordinate with developers to build new systems to support applications need\nDocument, implement and perform operational procedures\n\nSkills & experience\n\nAt least four years of working experience as enterprise system administrator in a mid to large enterprise environment\nA solid understanding on Windows 2008/2012/2016 Servers, Active Directory, Citrix XenApp and XenDesktop, VMWare (VM and VDI) infrastructure\nExperience in system performance tuning and capacity planning\nExperience with implementing monitoring solutions, VB scripts and PowerShell scripts, experience with monitoring tool like SolarWinds, IPmon is a plus\nKnowledge of asset management, inventory control , software deployment and patch management\nAbility to provide level 1 and 2 technical support to end users, Helpdesk and application development teams\nGood verbal communication skill is required. Good verbal and written English, ability to speak Putonghua is a plus\nA demonstrated ability in problem-solving, management of multiple tasks and personal time management is required\nA detail minded individual who is willing to learn new skills and work overtime as needed\nParticipate in 24x7 on-call support, respond to alerts in a timely fashion, escalate issues as needed\n\nOther\n\nNotes to applicants:\n\nPlease apply in strict confidence with full resume, academic record, current and expected salaries.\nThe personal data provided will be used for consideration of recruitment only. All personal data of unsuccessful candidate will be destroyed within 24 months.\nCandidates with Enhanced Competency Framework (ECF): please state on the CV.\n\nAbout us\n\nAs a leading investment bank in China and Hong Kong region, the investment banking arm of Bank of China, BOC International Holdings Limited (\u201cBOCI\u201d), is now seeking highly motivated, creative and success-oriented professional who would like to pursue the career for supporting our group.", "employment_types": ["Full Time"], "selling_points": ["System Engineering", "Renewable contract", "Investment Banking"], "locations": ["Kwai Hing"], "categories": ["Information Technology (IT)", "IT - Webmaster / SEO", "IT Management"], "post_time": "2022-01-11T06:25:55Z", "salary": {"currency": null, "max": null, "min": null, "period": "monthly", "term": null}, "salary_visible": false, "title_keywords": ["system engineer"], "responsibilities": ["software", "active directory", "co-ordinate with", "troubleshooting", "communication", "recurring problems", "application development", "personal data", "administration", "configuration", "infrastructure", "teams", "operational procedures", "system backups", "patch management", "banking", "reporting", "installation", "management", "upgrades", "monitoring", "inventory control", "technical support", "systems", "asset management", "recruitment", "planning"], "requirements": {"degrees": [], "majors": [], "languages": ["putonghua", "english"], "language_level": ["good"], "hard_skills": ["plus", "vmware", "active directory", "servers", "problem-solving", "citrix", "powershell", "deployment"], "soft_skills": ["work overtime", "confidence", "creative", "responsible", "multiple tasks", "problem-solving", "communication skill", "willing to learn", "troubleshooting", "timely", "time management", "motivated", "active"], "languages_combined": [{"language": "putonghua", "language_level": ["good"]}, {"language": "english", "language_level": ["good"]}]}, "experience_required": {"duration": ["at least four years"], "field": ["planning"]}}, {"job_id": "100003009034647", "location_code": "hk", "company": "HANSEL INTERNATIONAL Executive Search Limited", "job_title": "Digital Marketing/SEO Specialist - Internet Broker/Mobile Trading Apps Company", "description": "Our client is a a fast growing internet broker recently launched their stock trading APP.\u00a0 To cope with their rapid expansion, they are currently looking for an\u00a0Digital Marketing/SEO Specialist to join their marketing team.\n\nResponsibilities:\nAssists developing and executing strategies to improve organic search rankings and maximize both client acquisition and qualified web traffic.\nPrioritize keywords and landing pages to attract our target audience for mobile investment application.\nMonitor and analyze SEO statistics such as redirects, click rate, bounce rate, and more. \u2022 Collaborate with other stakeholders including Content team to ensure smooth execution.\nWork with web developers, content strategists, and web designers, to build a scalable and SEO-friendly website.\nCommunicate results to the executive leadership team.\nPerform regular SEO audits and drive work items as necessary.\nFollow and digest popular SEO publications and blogs to stay updated on the latest innovations, tools, and techniques.\nDisseminate this information to UX designers, and content strategists\nRequirements:\u00a0\n\n\nAt least 5 years of solid experience in digital marketing, specially in handling SEM & SEI\nUnderstanding of web-crawling and indexing and how Google applies those techniques.\nExperience using information architecture and internal linking to boost ranks.\nAbility to analyze data and provide evidence-based recommendations.\nStrong command of analytics tools like Google Analytics, Search Console, and SEO tools like STAT, SEMrush, Ahrefs, OnCrawl, Screaming Frog.\nExcellent verbal and written communication in English, fluency in Cantonese and Mandarin would be a plus .\nSolid Excel/Google Sheets and reporting skills .\nFor interested candidates, please send us your updated resume with your 1) current salary 2) expected salary 3)notice period.\u00a0 All personal information collected will be strictly used for recruitment purpose only.", "employment_types": ["Full Time"], "selling_points": ["SEM / SEO", "Friendly and energetic working environment", "US Fintech Company"], "locations": ["Tin Hau"], "categories": ["Information Technology (IT)", "IT - Webmaster / SEO", "Marketing / Public Relations", "Others", "Digital Marketing"], "post_time": "2022-01-10T03:52:14Z", "salary": {"currency": null, "max": null, "min": null, "period": "monthly", "term": null}, "salary_visible": false, "title_keywords": ["specialist", "digital marketing"], "responsibilities": ["collaborate with", "seo", "monitor", "developing", "website", "executing", "audits"], "requirements": {"degrees": [], "majors": [], "languages": ["cantonese", "english", "mandarin"], "language_level": ["fluency", "excellent"], "hard_skills": ["analytics tools", "google analytics", "plus", "seo", "excel", "web", "sem"], "soft_skills": ["ability to analyze", "communication"], "languages_combined": [{"language": "cantonese", "language_level": ["fluency", "excellent"]}, {"language": "english", "language_level": ["fluency", "excellent"]}, {"language": "mandarin", "language_level": ["fluency", "excellent"]}]}, "experience_required": {"duration": ["at least 5 years"], "field": ["digital marketing"]}}, {"job_id": "100003009038120", "location_code": "hk", "company": "Hong Kong International School", "job_title": "PowerSchool Administrator", "description": "The PowerSchool System Specialist (PSSS) at HKIS will be responsible for leading the technical administration of PowerSchool SIS, PowerTeacher Pro, PowerScheduler, and any additional PowerSchool modules. They will also manage the data integration with other HKIS information systems (Schoology, Schoolsbuddy, FinalSite, etc.). The PSSS helps inform school leadership about enrollments, grading, scheduling, and the development of our system. They provide training to all faculty and staff. Additionally, the position works to extend PowerSchool functionality with an eye towards enhancing user experience, fluid communications from HKIS to students/parents, the inclusion of non-academic activities, and improved data analytics.\nRequirements:\nAssociate degree in Computer Science, Database Administration, Data Analytics, Information Systems or relevant field and/or equal experience and/or certifications preferred.\n3+ years of practical in-depth experience with SQL/Oracle\n2+ years of web development\nExperience:\nAt least 5 - 8 years of PowerSchool experience with knowledge of all aspects of PS including but not limited to the creation, maintenance of custom pages, reports, plugins, registration process, scheduling, grading, APIs, PowerTools, PowerTeacher, GradeBook, Parent/Student Portal, storing grades, EOY procedures, report card setup and training and integration with other LMS (preferably Schoology) and 3rd party tools\nMust have strong technical expertise in PowerSchool, SQL, DBA, and Microsoft Office Suite (including Excel formulas) preferred\nExperienced in data collection of raw data files across multiple departments and multiple systems for data requests for data analyses\nHighly detail-oriented with the ability to manage daily activities and short/long term projects under pressure with accuracy and responsiveness\nExperience with school admissions and fundraising software preferred\nSkills:\nSolid English communication skills, verbal and written. Cantonese and Mandarin are also an advantage\nExcellent customer service and communication skills.\nAbility to work with people of various backgrounds with all levels of technical knowledge\nAbility to work well individually and in a team\nWilling to work with and support our students and learning community\nWilling to work outside office hours when required, especially during busy periods\nAbility to handle confidential files and information in a professional manner\n\nWe invite you to learn more about our school and discover for yourself career opportunities in our remarkable HKIS community at www.hkis.edu.hk\n\nInterested candidates please forward your updated resume together with a cover letter and references by clicking \"Apply Now\"\n\nWe look forward to hearing from you!", "employment_types": ["Full Time", "Permanent"], "selling_points": ["Associate degree in Computer Science", "3+ years of practical in-depth experience with SQL", "At least 5 - 8 years of PowerSchool experience"], "locations": ["Not Specified"], "categories": ["Information Technology (IT)", "DBA", "IT - Webmaster / SEO", "Others"], "post_time": "2022-01-11T05:17:20Z", "salary": {"currency": null, "max": null, "min": null, "period": "monthly", "term": null}, "salary_visible": false, "title_keywords": ["administrator"], "responsibilities": ["provide training", "software", "maintenance", "data", "systems", "procedures", "user experience", "professional manner", "communication", "scheduling", "customer service", "reports", "database", "data collection", "report", "setup", "administration"], "requirements": {"degrees": ["associate degree"], "majors": ["computer science"], "languages": ["cantonese", "english", "mandarin"], "language_level": ["advantage"], "hard_skills": ["excel", "inform", "web development", "hkis", "maintenance", "data analytics", "sql", "microsoft office suite", "integration", "oracle"], "soft_skills": ["communication skills", "under pressure", "responsible", "detail-oriented", "customer service", "learning", "leadership"], "languages_combined": [{"language": "cantonese", "language_level": ["advantage"]}, {"language": "english", "language_level": []}, {"language": "mandarin", "language_level": ["advantage"]}]}, "experience_required": {"duration": ["at least 5 - 8 years", "3+ years"], "field": ["training", "maintenance", "sql", "database", "administration"]}}, {"job_id": "100003009036127", "location_code": "hk", "company": "BOCI", "job_title": "Web Developer (renewable contract)", "description": "Work from Home - Hong Kong\n\nMedia Search Analyst - An exciting work from home opportunity related to Music, Video App Store and HomePod! We offer a flexible schedule of up to 20 hours per week completing tasks in a web-based evaluation tool.\n\nThe Role:\u00a0\n\nEvaluation of online task types related to Music, Video, App Store and HomePod to help improve the overall quality and relevance of online content and research.\n\nWhat are the main requirements for the job?\n\nFluency in English & Cantonese is essential\nYou must be living in Hong Kong for a minimum of 1 year\nApple user - Your email address must be associated with an Apple ID\nExperience/know-how of Apple products is mandatory\nAll candidates will need to pass online evaluations to demonstrate capability of reading and applying the guidelines.\n\n\u00a0Benefits & Perks:\n\nFlexible hours to work around home life\nBetter Work-Life balance\nRemote work & location independence\nPositive environmental impact\nIndependent contractor role\n\nWhat\u2019s next?\u00a0\n\nDon\u2019t Delay! Submit your application through the following link and a member of our\n\nrecruitment team will review your application:\n\nhttps://e-recruit.sap.lionbridge.com/sap(bD1lbiZjPTEwMCZkPW1pbg==)/bc/bsp/sap/unrg_appl/application.do?param=cGluc3RfZ3VpZD1FQkJGQzY1NjdFNDA2RUYxQTg0NzAwMTU1RDAwQUMwOQ%3d%3d&amp%3bsap-client=100&amp%3bsap-client=100&amp%3bsap-language=EN&amp%3brcfcontext=GR&rcfcontext=GR\n\nWant to know more? Please visit:\n\nhttps://jobs.telusinternational.com/en_US/careers/PipelineDetail/Media-Search-Analyst-Hong-Kong-Cantonese-language/24930\n\n", "employment_types": ["Full Time"], "selling_points": ["Web Development", "Investment Banking", "Team work environment"], "locations": ["Kwai Hing"], "categories": ["Information Technology (IT)", "IT - Webmaster / SEO", "IT Project Management / Team Lead", "IT Management"], "post_time": "2022-01-10T09:25:26Z", "salary": {"currency": null, "max": null, "min": null, "period": "monthly", "term": null}, "salary_visible": false, "title_keywords": ["developer"], "responsibilities": ["guidelines", "quality", "schedule", "evaluation"], "requirements": {"degrees": [], "majors": [], "languages": ["cantonese", "english"], "language_level": ["fluency"], "hard_skills": ["id", "web"], "soft_skills": ["flexible"], "languages_combined": [{"language": "cantonese", "language_level": ["fluency"]}, {"language": "english", "language_level": ["fluency"]}]}, "experience_required": {"duration": [], "field": []}}, {"job_id": "100003009030980", "location_code": "hk", "company": "First Page Limited", "job_title": "Senior SEO Tech Specialist", "description": "The role\n\nWeb Developer (Contract position)\u00a0\n\nKey accountabilities\n\nOur development team is looking for a motivated, versatile developer to help create and support in-house developed web applications. The ideal candidate will be able to utilize their technical skills, communication skills, and creativity to provide the solutions for our business needs.\u00a0 \u00a0\n\nImplementation of technical solution by development manager with consideration of development standards, guideline and processes\nSupporting the systems.\nMaintain technical document \u00a0\nTesting environment management \u00a0\n\nSkills & experience\n\n5+ years of web based application development experience, HTML5, CSS3, AJAX, JavaScript frameworks (e.g. vue,js, react.js).\nCore Java, Spring Boot, Spring Framework\nMicro-services and REST API development experience.\nKnowledge of MS SQL, Oracle and Sybase DB\nKnowledge of Windows Server and Linux environment\nFocus on quality, responsiveness, efficiency, and innovation.\n\nOther\n\nNotes to applicants:\n1. Please apply in strict confidence with full resume, academic record, current and expected salaries.\n2. The personal data provided will be used for consideration of recruitment only. All personal data of unsuccessful candidate will be destroyed within 24 months.\n3. Candidates with Enhanced Competency Framework (ECF): please state on the CV.\n\nAbout us\n\nAs a leading investment bank in China and Hong Kong region, the investment banking arm of Bank of China, BOC International Holdings Limited (\u201cBOCI\u201d), is now seeking highly motivated, creative and success-oriented professional who would like to pursue the career for supporting our group.", "employment_types": ["Full Time"], "selling_points": ["Award winning global agency!", "Great salary & benefits.", "Fun, dynamic company on the move."], "locations": ["Wan Chai"], "categories": ["Media & Advertising", "Strategic Planning", "Information Technology (IT)", "IT - Webmaster / SEO", "Software Development"], "post_time": "2022-01-07T08:45:33Z", "salary": {"currency": null, "max": null, "min": null, "period": "monthly", "term": null}, "salary_visible": false, "title_keywords": ["specialist"], "responsibilities": ["management", "systems", "quality", "implementation", "banking", "communication", "maintain", "recruitment", "personal data", "testing environment", "application development"], "requirements": {"degrees": [], "majors": [], "languages": [], "language_level": [], "hard_skills": ["linux", "java", "web applications", "web", "react", "javascript", "spring", "ajax", "focus", "windows server", "ms sql", "oracle"], "soft_skills": ["communication skills", "confidence", "versatile", "motivated", "technical skills", "focus", "creative", "ideal"], "languages_combined": []}, "experience_required": {"duration": ["5+ years"], "field": ["development", "application development"]}}, {"job_id": "100003009038243", "location_code": "hk", "company": "The Hong Kong Polytechnic University", "job_title": "Assistant Officer", "description": "Responsible for handling internal workflow systems, web application development, conducting user requirement studies, conducting user training and providing support for project enquiries.\n\n\nBachelor Degree in Computing Science, Information Technology or related disciplines\n\nExperience in ERP (Enterprise Resource Planning) software and manufacturing\u00a0 industry\u00a0 is an advantage\n\n2-5 years experience in web application development\nCompetence with Python and SQL is a must. Knowledge in Linux, simple Bash scripting, Git, and Windows\n\nExperience in PostgreSQL, MS SQL, MySQL, ASP.NET, C#, PHP programming, Java EE and Django or Flask is an advantage\u00a0\nMVC architecture is preferable\nKnowledge in Chinese Word Processing is preferable\nStrong analytical, organizational and interpersonal skills\nCandidates with less experience or fresh graduates will also be considered\nWorking location: Wong Chuk Hang (3 minutes' walk from MTR station)\n\nWe offer\u00a0attractive remuneration package including 5-day work, bank holidays, group medical insurance etc to the right candidates. Interested parties please send your full resume including expected salary and date available to Human Resources Department by clicking \"Apply Now\" button.\n\nFor more details, please\u00a0visit our web-site at www.simatelex.com.hk", "employment_types": ["Full Time"], "selling_points": [], "locations": ["Not Specified"], "categories": ["Admin & HR", "Clerical / Admin Staff", "Others", "Information Technology (IT)", "IT - Webmaster / SEO"], "post_time": "2022-01-11T06:18:36Z", "salary": {"currency": null, "max": null, "min": null, "period": null, "term": null}, "salary_visible": false, "title_keywords": ["assistant officer"], "responsibilities": ["user requirement", "software", "systems", "providing support", "application development", "architecture", "planning"], "requirements": {"degrees": ["degree", "bachelor"], "majors": ["related disciplines", "science", "information technology"], "languages": ["chinese"], "language_level": [], "hard_skills": ["simple", "linux", "java", "git", "web application development", "chinese word processing", "php", "erp", "bash", "sql", "programming", "python", "ms sql", "c#"], "soft_skills": ["organizational", "interpersonal skills", "responsible"], "languages_combined": [{"language": "chinese", "language_level": []}]}, "experience_required": {"duration": ["2-5 years"], "field": ["sql", "application development", "manufacturing", "planning"]}}, {"job_id": "100003009035800", "location_code": "hk", "company": "Macroview Telecom Limited", "job_title": "Analyst Programmer / Senior Analyst Programmer", "description": "Looking to take your SEO and Digital Marketing career to a whole new level? This role is for you!\n\nFirst Page Digital is looking for a technically astute and confident Sr. SEO Tech\u00a0Specialist who loves to drive unprecedented traffic and money keywords rankings for our clients. We're looking for someone who self-driven and who loves to work with inspired (and inspiring) teams. First Page Digital prides itself on being a leader, not only in Hong Kong but also throughout Australasia in the field of digital marketing. We've won numerous rewards because we love what we do! Passion breeds success!\n\nWith offices in Australia, Hong Kong, Singapore, Malaysia, Thailand, Dubai and now Brazil and Panama, you'll be joining a company that rewards success and strives to be the best in the industry. We provide a strong entrepreneurial environment, which has seen the organization ranked #1 fastest growing digital group in Australia 3 years straight.\n\nRewards you deserve:\n\n\n\u00a0\u00a0\u00a0\u00a0\u00a0\u00a0 Generous remuneration & medical and class pass corporate membership\n(Salary will commensurate with qualification and experience)\n\u00a0\u00a0\u00a0\u00a0\u00a0\u00a0 Collaborate with a strong, dynamic team.\n\u00a0\u00a0\u00a0\u00a0\u00a0\u00a0 Always new and exciting projects.\n\u00a0\u00a0\u00a0\u00a0\u00a0\u00a0 Fun company that\u2019s on the move!\n\nWhat you'll be doing:\n\n\n\u00a0\u00a0\u00a0\u00a0\u00a0\u00a0 Being part of an inhouse team of 8 SEO Specialists to execute SEO strategies, implementations and update on the project planning to ensure smooth workflow\n\u00a0\u00a0\u00a0\u00a0\u00a0\u00a0 Be on the cutting edge of SEO, finding new strategies to implement on behalf of our clients to drive their organic traffic\n\u00a0\u00a0\u00a0\u00a0\u00a0\u00a0 Developing and implementing effective SEO strategies for the improvement of organic traffic and search ranking and the maximization of ROI\n\u00a0\u00a0\u00a0\u00a0\u00a0\u00a0 Well versed in preparing SEO reports on a fortnightly and monthly basis to be shared with client and identifying areas for improvement\n\u00a0\u00a0\u00a0\u00a0\u00a0\u00a0 Use a variety of tools, competitive research and other methods to discover optimal keyword targets appropriate to the business needs of the client\n\u00a0\u00a0\u00a0\u00a0\u00a0\u00a0 Oversee SEO campaigns which encompass Technical Auditing and Onsite Implementation, Link Outreach and Content development\n\u00a0\u00a0\u00a0\u00a0\u00a0\u00a0 Collaborate with a multitude of divisions from Content, Account Management Team, Sales to Performance media team.\n\u00a0\u00a0\u00a0\u00a0\u00a0\u00a0 Format reports and provide top-line insights for on-going performance reviews\n\u00a0\u00a0\u00a0\u00a0\u00a0\u00a0 Able to demonstrate understanding of how duplicate content and page load speed affects SEO by advising clients on best practices for successful implementation and improvement\n\u00a0\u00a0\u00a0\u00a0\u00a0\u00a0 Have the ability to audit prospects & existing clients organic performance.\u00a0 Everything from a backlink profile to analysing server logs\n\u00a0\u00a0\u00a0\u00a0\u00a0\u00a0 Demonstrate a hunger to stay abreast of the latest industry developments, and factor these into your day to day work.\n\u00a0\u00a0\u00a0\u00a0\u00a0\u00a0 Understand metrics and KPIs and continually suggest optimizations to improve performance\n\u00a0\u00a0\u00a0\u00a0\u00a0\u00a0 Apply, and be able to explain, SEO best practices for site navigation, breadcrumbing, internal links (including anchor text optimization), and HTML sitemaps to client websites\n\u00a0\u00a0\u00a0\u00a0\u00a0\u00a0 Apply, and be able to explain, SEO best practices for domain, sub-domain and directory structure to client websites\n\u00a0\u00a0\u00a0\u00a0\u00a0\u00a0 Have the ability to talk tech with developers, but also be able to explain concepts in layman terms.\n\u00a0\u00a0\u00a0\u00a0\u00a0\u00a0 Monitor clients sites regularly for crawling and indexing issues. Issues identified will be surfaced to the respective Campaign Manager and SEO specialist, documented for client communication/follow-up\n\u00a0\u00a0\u00a0\u00a0\u00a0\u00a0 Use a variety of tools, competitive research and other methods to discover quality potential outreach link building opportunities\n\nWhat we need:\n\n\n\u00a0\u00a0\u00a0\u00a0\u00a0\u00a0 Minimum of 2-3 years relevant, hands-on SEO experience \u2013 not just creating documentation for developers to implement\n\u00a0\u00a0\u00a0\u00a0\u00a0\u00a0 Experience using SEO tools such as Screaming Frog, Ahrefs, SEMRush, Google Analytics, Google Tag Manager, SEO related excel/Google sheets functions\n\u00a0\u00a0\u00a0\u00a0\u00a0\u00a0 Experience working with web developers internally & externally\n\u00a0\u00a0\u00a0\u00a0\u00a0\u00a0 You have the ability to implement onsite SEO on most CMS types & static websites, along with familiarity with cloud hosting environments\n\u00a0\u00a0\u00a0\u00a0\u00a0\u00a0 You have a proven track record of organic success.\u00a0 When asked about a website you\u2019ve worked on, you can walk someone through exactly how you did so\n\u00a0\u00a0\u00a0\u00a0\u00a0\u00a0 Able to produce high quality work within a fast paced, dynamic environment.\n\u00a0\u00a0\u00a0\u00a0\u00a0\u00a0 Excellent verbal and written communication skills (fluency in English expected, Cantonese is a plus)\n\u00a0\u00a0\u00a0\u00a0\u00a0\u00a0 Has strong familiarity with the web development process, including the important points at which SEO must be considered\n\u00a0\u00a0\u00a0\u00a0\u00a0\u00a0 Experienced with international SEO.\u00a0 At a level where you can sculpt a website\u2019s international SEO strategy from scratch\n\u00a0\u00a0\u00a0\u00a0\u00a0\u00a0 Develops knowledge of client\u2019s business, competition and latest industry news and trends\n\u00a0\u00a0\u00a0\u00a0\u00a0\u00a0 Effective time management skills with an ability to multitask and prioritize\n\u00a0\u00a0\u00a0\u00a0\u00a0\u00a0 Strong attention to detail\n\u00a0\u00a0\u00a0\u00a0\u00a0\u00a0 Ability to present and communicate ideas in a coherent and effective manner.\u00a0 Always focussing on driving organic traffic\n\u00a0\u00a0\u00a0\u00a0\u00a0\u00a0 Prior experience in a media agency preferred\n\u00a0\u00a0\u00a0\u00a0\u00a0\u00a0 A \u2018Can Do\u2019 attitude\n\nWhy us:\n\n\nWe want Hong Kong\u2019s top talent and recognise that means paying them accordingly. Our office is a great space to inspire creativity, as well as being close to cafes and public transport in the heart of Wan Chai. You'll be amongst a highly engaged team of the country's most talented digital marketers and growth experts, with solid prospects for upward mobility.\n\nPlease attach your CV and we'll be in touch for a confidential chat. Let's do great things together!\u00a0", "employment_types": ["Full Time", "Permanent"], "selling_points": ["Container,Microservice,Kubernetes,C#,React,API", "2 years web application experience", "Experience in Git, Kubernetes, React Native, Jenki"], "locations": ["Quarry Bay"], "categories": ["Information Technology (IT)", "IT - Webmaster / SEO", "Others", "UI/UX Designer"], "post_time": "2022-01-10T08:27:05Z", "salary": {"currency": null, "max": null, "min": null, "period": "monthly", "term": null}, "salary_visible": false, "title_keywords": ["analyst programmer", "senior analyst programmer"], "responsibilities": ["teams", "seo", "digital marketing"], "requirements": {"degrees": [], "majors": [], "languages": [], "language_level": [], "hard_skills": ["seo", "sr"], "soft_skills": ["confident", "inspiring", "unprecedented", "driven"], "languages_combined": []}, "experience_required": {"duration": [], "field": []}}, {"job_id": "100003009033379", "location_code": "hk", "company": "Robert Half Hong Kong Limited", "job_title": "Web Master - Financial Industry inhouse perm (up to 900k)", "description": "OFFICE OF UNDERGRADAUTE STUDIES\nAssistant Officer (Ref. 22011101-JCS)\nDuties\nThe appointee will be required to:\n(a)\u00a0\u00a0 \u00a0assist in providing administrative and secretarial support to the Head of Unit;\n(b)\u00a0\u00a0 assist in providing administrative support for the planning and provision of subject / programmes meeting the General University Requirements (GUR) and related activities;\n(c)\u00a0\u00a0 \u00a0assist in maintaining the office website and database system;\n(d)\u00a0\u00a0 \u00a0liaise effectively with internal units and external organizations; and\n(e)\u00a0\u00a0 \u00a0perform any other duties as assigned by the Head of Unit or his/her delegates.\nQualifications\nApplicants should:\n(a)\u00a0\u00a0 \u00a0have a recognised degree with at least three years of relevant administrative experience;\n(b)\u00a0\u00a0 \u00a0have a good command of both written and spoken English and Chinese, preferably with fluency in Putonghua;\n(c)\u00a0\u00a0 \u00a0be attentive to details and able to work independently and proactively;\n(d)\u00a0\u00a0 \u00a0have good computer literacy especially in MS Word, Excel and PowerPoint; and\n(e)\u00a0\u00a0 \u00a0have good interpersonal and communication skills.\nPreference will be given to those with knowledge of website construction, database management and e-Learning.\nShortlisted candidates may be invited to sit for a written test.\n[Applicants who have responded to the previous advertisement need not re-apply.]\nRemuneration and Conditions of Service\nA highly competitive remuneration package will be offered.\u00a0 Appointment will be on a one-year gratuity-bearing contract.\u00a0 Applicants should state their current and expected salary in the application.\nApplication\nPlease send a completed application form by post to Human Resources Office, 13/F, Li Ka Shing Tower, The Hong Kong Polytechnic University, Hung Hom, Kowloon, Hong Kong or via email via \"Apply Now\".\u00a0 Application forms can be downloaded from https://www.polyu.edu.hk/hro/careers/guidelines_and_forms/forms.\u00a0 If a separate curriculum vitae is to be provided, please still complete the application form which will help speed up the recruitment process.\u00a0 Consideration of applications will commence on 25 January 2022 until the position is filled.\u00a0 The University\u2019s Personal Information Collection Statement for recruitment can be found at https://www.polyu.edu.hk/hro/careers/guidelines_and_forms/pics_for_recruitment.\nPolyU is an equal opportunity employer committed to diversity and inclusivity.\u00a0 All qualified applicants will receive consideration for employment without regard to gender, ethnicity, nationality, family status or physical or mental disabilities.\u00a0 \u00a0", "employment_types": ["Full Time", "Permanent"], "selling_points": ["Technical owner of the CMS and websites platform", "Regional / Country level management and governance", "Web system migration and revamp"], "locations": ["Central"], "categories": ["Information Technology (IT)", "IT - Webmaster / SEO", "IT Project Management / Team Lead", "IT Management"], "post_time": "2022-01-09T12:28:20Z", "salary": {"currency": null, "max": null, "min": null, "period": "monthly", "term": null}, "salary_visible": false, "title_keywords": [], "responsibilities": ["liaise", "any other duties", "management", "maintaining", "administrative support", "website", "communication", "recruitment", "secretarial support", "database", "recruitment process", "planning"], "requirements": {"degrees": ["degree"], "majors": [], "languages": ["putonghua", "english", "chinese"], "language_level": ["fluency", "good command"], "hard_skills": ["excel", "c", "powerpoint", "ms word"], "soft_skills": ["communication skills", "work independently", "attentive to details", "computer literacy", "committed", "learning", "interpersonal"], "languages_combined": [{"language": "putonghua", "language_level": ["fluency", "good command"]}, {"language": "english", "language_level": ["good command"]}, {"language": "chinese", "language_level": ["good command"]}]}, "experience_required": {"duration": ["at least three years"], "field": ["administrative"]}}, {"job_id": "100003009036129", "location_code": "hk", "company": "BOCI", "job_title": "AVP, System Analyst, EABS, Information Technology", "description": "Job Descriptions:\n\nParticipate in development of applications and microservices\nAssist in requirements gathering and systems analysis & design\nInvolve in implementation, application testing, prepare test cases, UAT & user training\nSupport application deployment in container platform\nEvaluate new technologies and solutions\nRequirements:\u00a0\n\nHigh Diploma / Degree holders in Computer Science or Software Engineering related disciplines\nAt least 2 years solid experience in C#, .Net/.Net Core, React, web and database application\nKnowledge or experience in Git, Kubernetes, React Native, Jenkins will be an advantage\nGood in both spoken and written Cantonese and English\nA self-motivated team player with good interpersonal and communication skills\nAble to work independently\nCandidates with less experience will be considered for the Senior Programmer position", "employment_types": ["Full Time"], "selling_points": ["Software design & development", "Business Analysis", "Investment banking"], "locations": ["Kwai Hing"], "categories": ["Information Technology (IT)", "IT - Webmaster / SEO", "IT Project Management / Team Lead", "IT Management"], "post_time": "2022-01-10T09:25:36Z", "salary": {"currency": null, "max": null, "min": null, "period": "monthly", "term": null}, "salary_visible": false, "title_keywords": ["system analyst"], "responsibilities": ["uat", "analysis", "systems", "implementation", "design", "testing", "evaluate"], "requirements": {"degrees": ["high diploma", "degree"], "majors": ["related disciplines", "software engineering", "computer science"], "languages": ["cantonese", "english"], "language_level": ["good"], "hard_skills": ["git", "jenkins", "web", "react", "react native", "c#"], "soft_skills": ["communication skills", "self-motivated", "work independently", "team player", "interpersonal"], "languages_combined": [{"language": "cantonese", "language_level": ["good"]}, {"language": "english", "language_level": ["good"]}]}, "experience_required": {"duration": ["at least 2 years"], "field": []}}, {"job_id": "100003009028769", "location_code": "hk", "company": "Fluxus Productions Limited", "job_title": "Website Developer", "description": "The Role\n\nAVP, System Analyst, EABS, Information Technology\n\nKey Accountabilities\n\nResponsible for system software application design and development\nProvide business analyst (BA) technical support to help business analysts and users design system requirements documents\nDevelop software systems based on system requirements documents to achieve user requirements\nLead junior programmers to develop the system, manage the development tasks of system developers, and submit software according to the project progress\nPrioritize development according to the resources and tasks of the project and BAU to optimize the use of resources\nManage vendors for system development according to project plan and business requirement\nPrepare technical documents and manage source code versions\nSupport system testing for business analysts and users\nPrepare deployment documents to deployment team to deploy the system online\nProvide support for online systems to production support team to solve online systems problems\n\nSkills & Experience\n\nUniversity degree majored in Computer Science\n5-10 years relevant working experience in development in financial institutions\nGood time management and organizational skills. Multitasking ability is required\nStrong Vendor management skills. Experience to manage offshore development team is an advantage\nStrong SQL skills e.g. Oracle PL/ SQL\nSolid experience in J2EE framework (spring hibernate, springboot etc)\nFront End Development experience has advantages, but not a must\nUnderstanding on programming techniques, analysis and system implementation methodologies\nFlexibility to learn and work in dynamic environment\nProactive attitude, with sense of ownership and strong team player\n\nOther Information\n\nNotes to applicants:\n\nPlease apply in strict confidence with full resume, academic record, current and expected salaries.\nThe personal data provided will be used for consideration of recruitment only. All personal data of unsuccessful candidate will be destroyed within 24 months.\nCandidates with Enhanced Competency Framework (ECF): please state on the CV.\n\nAbout BOCI\n\nAs a leading investment bank in China and Hong Kong region, the investment banking arm of Bank of China, BOC International Holdings Limited (\u201cBOCI\u201d), is now seeking highly motivated, creative and success-oriented professional who would like to pursue the career in our group.", "employment_types": ["Full Time", "Permanent", "Contract"], "selling_points": ["Build and maintain company website", "Self-motivated and strong problem-solving skills", "Familiar with HTML, JavaScript and CSS"], "locations": ["Tsuen Wan Area"], "categories": ["Information Technology (IT)", "IT - Webmaster / SEO", "IT Management", "Software Development"], "post_time": "2022-01-07T03:07:23Z", "salary": {"currency": null, "max": null, "min": null, "period": "monthly", "term": null}, "salary_visible": false, "title_keywords": ["developer"], "responsibilities": ["provide support", "management", "software", "technical support", "analysis", "systems", "project progress", "design", "develop", "project plan", "testing", "implementation", "banking", "recruitment", "deploy", "personal data"], "requirements": {"degrees": ["university degree"], "majors": ["computer science"], "languages": [], "language_level": [], "hard_skills": ["hibernate", "analysis", "vendor", "sql", "dynamic", "deployment", "spring", "programming", "system implementation", "code", "pl", "oracle"], "soft_skills": ["organizational skills", "dynamic environment", "proactive", "confidence", "creative", "responsible", "prioritize", "motivated", "team player", "time management"], "languages_combined": []}, "experience_required": {"duration": ["5-10 years"], "field": ["development", "financial institutions", "relevant working experience", "team"]}}, {"job_id": "100003009029965", "location_code": "hk", "company": "Compass Offices", "job_title": "Digital Marketing Specialist, SEO", "description": "Job description / Requirements\n\n1.\u00a0 Higher Diploma or above in Computer Studies or equivalent with focus on system development and\u00a0 programming\n2.\u00a0 At least 3 years solid experience in program and system development\n3.\u00a0 Solid Experience in WEB based applications, Visual Studio, Entity Framework,\u00a0 VB.NET, ASP.NET, C#, MS SQL Server \u00a0\u00a0\u00a0\u00a0\u00a0\n4.\u00a0 Support experience in manufacturing, production, accounting applications are preferred\n5.\u00a0 Mobile apps development is an advantage\n6.\u00a0 Able to work independently and self-motivated\n7.\u00a0 5-day work, double pay, bonus, medical\n\n\nWe offer attractive remuneration and benefits to the right candidate.\u00a0 Interest parties please email full resume with present and expected salary to us.\u00a0", "employment_types": ["Full Time", "Permanent"], "selling_points": ["Leading Flexible Office Provider in APAC", "Regional role in a multi-cultural company", "5-day work, medical & dental"], "locations": ["Sheung Wan"], "categories": ["Information Technology (IT)", "IT - Webmaster / SEO", "Marketing / Public Relations", "Digital Marketing"], "post_time": "2022-01-07T06:30:54Z", "salary": {"currency": null, "max": null, "min": null, "period": "monthly", "term": null}, "salary_visible": false, "title_keywords": ["digital marketing specialist"], "responsibilities": [], "requirements": {"degrees": ["higher diploma or above"], "majors": ["computer studies"], "languages": [], "language_level": [], "hard_skills": ["web", "ms sql server", "mobile", "programming", "focus", "c#"], "soft_skills": ["focus", "work independently", "self-motivated"], "languages_combined": []}, "experience_required": {"duration": ["at least 3 years"], "field": ["manufacturing", "accounting", "system development"]}}, {"job_id": "100003009029736", "location_code": "hk", "company": "EVISU Group Limited", "job_title": "Assistant E-commerce Project Manager", "description": "Digital Marketing Specialist, SEO\n\nWe are looking for a dynamic and result-orientated SEO professional to join our Marketing Team in our Hong Kong head office. Your role will be driving the SEO activities, including but not limited to content strategy, link building, optimizing keyword ranking and implementing the best practices for our corporate websites and landing pages to maximize the ROI from organic search across major search engines.\n\nResponsibilities\n\nLead, develop and execute content and technical SEO strategies to improve organic search performance across APAC markets\nRecommend and execute changes to website architecture, layouts, content, etc. to improve keyword ranking and optimize conversion\nPerform ongoing keyword research and link building to boost organic traffic and domain authority\nWork closely with the marketing team and agencies to ensure the best practices of SEO are implemented\nPrepare report and analysis on website traffic, customer funnels and user engagement metrics for lead generation\nStay up-to-date with the SEO strategy, search engine algorithms, industry and market trends to initiate new ideas to support the company\u2019s growth\n\n\u00a0Requirements\n\nMinimum 5 years of work experience in digital marketing; with at least 3 years focusing on SEO\nDemonstrate a good understanding of the diverse search landscape in APAC markets to support and grow the SEO initiatives\nProven experience in on-page optimization, keyword research and discovery, link building, lead generation, Google My Business optimization, etc.\nProficiency in Web Analytics, Keyword Research Tools and Content Management Systems (CMS), such as Google Analytics, WordPress, Active Campaign, etc.\nExcellent spoken and written English\nKnowledge of HTML, CSS and JavaScript is an added advantage\nBSc degree in Marketing, Computer Science or relevant field\nAll applications will be treated strictly confidential for recruitment purpose only.\n", "employment_types": ["Full Time", "Permanent"], "selling_points": ["Double Pay + Medical Insurance", "Min 5 years Exp in Ecomm website management", "Experience in Magento"], "locations": ["Kwun Tong"], "categories": ["Information Technology (IT)", "IT - Webmaster / SEO", "E-commerce", "Product Management / Business Analyst", "Software Development"], "post_time": "2022-01-07T06:04:57Z", "salary": {"currency": null, "max": null, "min": null, "period": "monthly", "term": null}, "salary_visible": false, "title_keywords": ["project manager", "assistant"], "responsibilities": ["optimize conversion", "prepare report", "seo", "ideas", "analysis", "website", "develop", "architecture"], "requirements": {"degrees": ["degree", "bsc"], "majors": ["marketing", "computer science"], "languages": ["english"], "language_level": ["excellent"], "hard_skills": ["google analytics", "seo", "html", "wordpress", "javascript", "web analytics", "css"], "soft_skills": ["web analytics", "diverse", "active"], "languages_combined": [{"language": "english", "language_level": ["excellent"]}]}, "experience_required": {"duration": ["minimum 5 years"], "field": ["business", "research", "digital marketing"]}}, {"job_id": "100003009036222", "location_code": "hk", "company": "Alexis Services Limited", "job_title": "QA Lead / Senior QA Engineer #FINTECH", "description": "\nOur client with a global\u00a0based cutting-edge technology design of\u00a0 fintech industry and operated by strong financial backing and operating structure, good people and great strategy, they have grown tremendously in the last couple of years.\n\nWith strong partnerships in the region and hence potential growth plans, they are looking to hire\u00a0 QA Lead / Senior QA Engineer\u00a0in the right direction.\n\nTitle:\u00a0QA Lead / Senior QA Engineer\u00a0\u00a0\n\nResponsibilities:\nDevelop end-to-end tests for mobile, web and API.\nWrite automation tests using TDD / BDD approach.\nDevelop automated scripts for various tests: integration, regression, and performance.\nCreate and maintain test cases and results.\nReport bugs and errors to engineering teams.\nWork closely with engineering teams and product managers\n\nRequirements:\n\n2+ years\u2019 experience in software QA and testing.\nFamiliar with the SDLC/STLC process and methodology\nFamiliarity with automation tools such as Cucumber, Selenium, Appium, Mocha, K6, JMeter is an advantage.\nExperience with agile development process.\nKnowledge of CI/CD with automation tests.\nExperience in testing mobile, web, and API with automated approach.\nwork closely with software engineers and product managers.\nPassion for quality and attention to details.\n\n", "employment_types": ["Full Time"], "selling_points": ["Quality Assurance Engineer / Solidity Developer", "Crypto Quant Trader / Growth Hacker / NFT Designer", "DAO Smart Contact Developer / DevOps / Blockchain"], "locations": ["Central & Western Area"], "categories": ["Information Technology (IT)", "Application Specialist - Software", "IT - Webmaster / SEO"], "post_time": "2022-01-10T09:42:51Z", "salary": {"currency": "HKD", "max": 34999, "min": 25000, "period": "monthly", "term": null}, "salary_visible": true, "title_keywords": ["engineer", "lead"], "responsibilities": ["report", "maintain", "teams", "develop"], "requirements": {"degrees": [], "majors": [], "languages": [], "language_level": [], "hard_skills": ["mobile", "sdlc", "agile", "web"], "soft_skills": ["agile", "attention to details", "passion for"], "languages_combined": []}, "experience_required": {"duration": ["2+ years"], "field": ["development", "qa", "testing"]}}, {"job_id": "100003009035942", "location_code": "hk", "company": "Gravitas Recruitment Group", "job_title": "Hedge fund - Web Developer - Full stack  - Great Opportunity", "description": "Our client is one of the Hedge Funds who is looking for passionate Full Stack Developer to join their team. For this role, you will be working on the platform team, working closely with the Front and Middle Office to build a quality full stack solution to completely replace their existing system.\n\nThey are looking for passionate Full Stack developer to join their high performance technology team.\n\nFresh Graduate with minimum GPA 3.0 is welcome.\n\nThis is a rare opportunity for full stack specialists to get into a Hedge fund. This is a great opportunity you don't want to miss.\n\nFull Stack Developer - Why Apply?\n\nFace off to traders bespoke full stack developer.\nWork on Greenfield projects with the latest technology.\nInternal promotion opportunity for top performance.\nWork in a multicultural team including global users.\n\n\nFull Stack Developer - What is required?\n\nDegree holder in Computer Science/Information Technology or related disciplines\nWelcome Fresh Graduate with minimum GPA 3.0.\nWeb development experience.\nNeed React/ Node for front-end and Java & Python for back-end skill.\nBusiness Level English to communicate with foreign team members.\n\nPlease send your CV to k.ching@gravitas if you are interested to apply.", "employment_types": ["Full Time", "Permanent"], "selling_points": ["Hedge Fund", "Web developer", "Full Stack"], "locations": ["Not Specified"], "categories": ["Information Technology (IT)", "IT - Webmaster / SEO", "Software Development"], "post_time": "2022-01-10T08:53:18Z", "salary": {"currency": "HKD", "max": 54999, "min": 20000, "period": "monthly", "term": null}, "salary_visible": true, "title_keywords": ["developer"], "responsibilities": ["communicate with", "quality"], "requirements": {"degrees": ["fresh graduate", "degree holder"], "majors": ["related disciplines", "computer science", "information technology"], "languages": ["english"], "language_level": [], "hard_skills": ["python", "web development", "java", "react"], "soft_skills": ["passionate"], "languages_combined": [{"language": "english", "language_level": []}]}, "experience_required": {"duration": [], "field": ["development"]}}, {"job_id": "100003009027878", "location_code": "hk", "company": "M & R Forwarding (HK) Limited", "job_title": "Web Developer / Senior Web Developer", "description": "Role description:\n\nDesign and develop state-of-the-art web applications to enhance the company\u2019s competitiveness\nCarry out application development utilizing modern technologies and tools\nPlan and manage software development initiatives, including scoping, timeline and resource planning\nProactively propose and drive innovation in the development process\nEnsure application meets all requirements of quality, security, modifiability, extensibility etc. with comprehensive system testing\nProvide technical support to external and internal users\n\nWe are looking for you if you have these qualities:\n\n\nBachelor or above degree in Computer Science, I.T. or equivalent disciplines.\nMinimum 2 years working experience in web application development.\nHands-on experience in C#, .NET Framework, Responsive Web, HTML5, CSS3, ReactJS, JQuery, AJAX, JSON, and MSSQL\nExperience in Azure Cloud Services, Azure DevOps\nHaving team leading experience, strong analytical and problem-solving skills.\nGood team player with positive thinking and willingness to learn.\nStrong sense of responsibility, able to handle multi-tasks and meet deadlines under pressure.\nExperience in logistics, supply chain, freight forwarding industry is an advantage.\nGood command in English and Chinese.\n\nPlease send your resume with expected salary and availability by clicking \"Apply Now\".\n\n\u00a0\u00a0For further information, please visit our company homepage\n\n\u00a0www.mrspedag.com\n\n(All information collected will be used for recruitment purpose only.)", "employment_types": ["Full Time", "Permanent"], "selling_points": [">2 years\u2019 exp. in web application development", "5 days work, flexible working arrangement", "Double pay & performance bonus"], "locations": ["Kowloon Bay"], "categories": ["Information Technology (IT)", "Application Specialist - Software", "IT - Webmaster / SEO", "Software Development"], "post_time": "2022-01-06T16:07:23Z", "salary": {"currency": null, "max": null, "min": null, "period": "monthly", "term": null}, "salary_visible": false, "title_keywords": ["developer"], "responsibilities": ["software", "technical support", "design and develop", "quality", "testing", "logistics", "recruitment", "plan", "application development", "planning"], "requirements": {"degrees": ["degree", "bachelor"], "majors": ["computer science"], "languages": ["english", "chinese"], "language_level": ["good command"], "hard_skills": ["web application development", "web applications", "web", "azure", "jquery", "devops", "ajax", "mssql", "problem-solving skills", "c#"], "soft_skills": ["good team player", "under pressure", "multi-tasks", "sense of responsibility", "positive thinking", "hands-on", "comprehensive", "problem-solving skills", "meet deadlines", "responsive"], "languages_combined": [{"language": "english", "language_level": ["good command"]}, {"language": "chinese", "language_level": ["good command"]}]}, "experience_required": {"duration": ["minimum 2 years"], "field": ["analytical", "supply chain", "devops", "logistics", "application development", "team"]}}, {"job_id": "100003009028497", "location_code": "hk", "company": "Rich Fame International Limited", "job_title": "PHP Programmer", "description": "Responsibilities\n\nMaintain an understanding of latest web applications and programming practice\nDesign and update company website\nEdit, write and design Website content\nBack up files from website to local directories for recovery\nGather and process raw data at scale that can be easily analyzed\nIdentify and correct problems uncovered by customer feedback and testing\nEvaluate code to make sure it meets industry standard\nRequirements\n\nBachelor's degree in CS or equivalent\nProficient in JavaScript, HTML, CSS\nHigh degree of independent judgment", "employment_types": ["Full Time", "Permanent"], "selling_points": ["2 to 3 years experience in programming", "Strong knowledge of DB design in MySQL", "Performance Bonus"], "locations": ["Kwai Fong"], "categories": ["Information Technology (IT)", "IT - Webmaster / SEO", "Transportation & Logistics", "Freight Forwarding", "E-commerce", "Supply Chain"], "post_time": "2022-01-07T02:26:04Z", "salary": {"currency": null, "max": null, "min": null, "period": "monthly", "term": null}, "salary_visible": false, "title_keywords": ["programmer"], "responsibilities": ["data", "website", "design", "testing", "evaluate", "maintain", "company website"], "requirements": {"degrees": ["degree", "bachelor"], "majors": [], "languages": [], "language_level": [], "hard_skills": ["css", "javascript", "html"], "soft_skills": ["independent"], "languages_combined": []}, "experience_required": {"duration": [], "field": []}}, {"job_id": "100003009028866", "location_code": "hk", "company": "Pricerite Home Ltd", "job_title": "Officer, Digital Marketing", "description": "\u00a0Responsibilities\n\n\u00a0Strategic Performance Marketing\n\nBe at the forefront overall Performance Marketing knowledge by keeping up to date with industry news and developments\nHave an understanding of the various digital media channels (SEM, Display, Programmatic, Social Media) and the potential for them in your clients marketing activity\nDevelop advanced Excel, Word and Power Point skills\nStart building an understanding of the client\u2019s business and digital marketing objectives\nStart developing an understanding of the target audiences\u2019 attitudes,\u00a0behaviour\u00a0and perceptions, using a variety of market information and research data\nEstablish an understanding of all areas of the Dentsu Aegis Network expertise and the products/services we can provide to your clients\nHelp in preparation for and attend client reviews as required\nParticipate in and learn about social marketing and the impact for our clients\n\nCampaign / Project Management\n\nFulfil relevant daily, weekly, monthly and quarterly tasks ensuring that all campaigns are executed to plan and meet the targets\nHelp in preparing performance review presentations\nProvide regular results analysis, reporting and recommendations\nUnder the guidance of your manager, develop and distribute accurate contact reports from meetings and conversations\nCoordinate and distribute regular status reports\nKeep clients and account team updated on the status of account activities\nHave input in developing short and long term search strategies for the client\nExcellence in Client Service and\u00a0effectively manage client expectations\nObtain client approval of briefs and schedules prior to campaign launches\nWork with your Digital Performance Manager to ensure that:\u00a0\ncampaigns / projects timelines, cost estimates, schedules and forecasts are accurately developed and adhered to\ncampaigns are set up and optimized in the correct way, according to brief and best practices.\nbudgets are spent within daily / monthly limits and invoices are correctly reconciled at the end of each\u00a0month\ncampaigns are monitored regularly and hit relevant targets\nreports and presentations are delivered to the highest level of quality and integrity\u00a0 \u00a0\n\n\u00a0Requirements\u00a0\u00a0\n\nAt least 2 years within digital performance (search and/or display)responsible for delivering against performance targets\u00a0\nKnowledge and understanding of Web Analytics\nStrong technical skills\nDigital media planning and buying\nRelevant qualification from Google and Bing\nExcellent knowledge and passion for digital\nStrong client-facing skills: understanding client needs, maintaining relationships, building partnerships\nCommunicates effectively at all levels, both up and down\nStrong numerical skills and attention to detail\nAble to work in high pressure environment and resolve client issues\nAble to work collaboratively across teams\nAnalytical and strategic\nDemonstrates entrepreneurialism and initiative taking\nDemonstrates honesty and integrity\nFluent in English and Cantonese\n\nWe offer 5 days work and attractive compensation package to suitable candidates. Interested parties, please send your full resume including your present & expected salary by using \"Quick Apply\".\n\nPlease note that only short-listed applicants will be notified. All information provided will be treated in strictly confidential and used solely for recruitment purpose.", "employment_types": ["Full Time", "Permanent"], "selling_points": ["Social media", "Google ads & Google Analytics", "Digital Communications"], "locations": ["Kowloon Bay"], "categories": ["Information Technology (IT)", "IT - Webmaster / SEO", "Marketing / Public Relations", "Digital Marketing", "E-commerce", "Marketing - Brand / Product Management"], "post_time": "2022-01-07T03:26:06Z", "salary": {"currency": null, "max": null, "min": null, "period": "monthly", "term": null}, "salary_visible": false, "title_keywords": ["officer", "digital marketing"], "responsibilities": ["market information", "data", "schedules", "quality", "media channels", "plan", "invoices", "developing", "presentations", "develop", "reports", "social media", "reporting", "guidance", "cost", "review", "digital marketing", "contact", "budgets", "analysis", "coordinate", "project management", "sem"], "requirements": {"degrees": [], "majors": [], "languages": ["cantonese", "english"], "language_level": ["fluent"], "hard_skills": ["web analytics", "numerical skills"], "soft_skills": ["passion for", "technical skills", "integrity", "attention to detail", "client-facing skills", "web analytics", "initiative"], "languages_combined": [{"language": "cantonese", "language_level": ["fluent"]}, {"language": "english", "language_level": ["fluent"]}]}, "experience_required": {"duration": [], "field": []}}, {"job_id": "100003009022840", "location_code": "hk", "company": "iProspect Hong Kong Limited", "job_title": "Digital Performance Specialist/ Senior Digital Performance Specialist", "description": "Main Duties:\n\nResponsible for websites, web applications development, enhancement, maintenance, testing and documentation\nCollect the business flow and requirements from internal user\nCollaborate with internal user to deliver the service and enhance user experience\nImplementation of change request on servers, systems and applications\nEnsure website and applications are compatible across different browsers including mobile platforms\nConducting unit-test for robustness, including edge cases, usability, and general reliability\n\n\u00a0Requirements:\n\nHigher Diploma or above in Computer Science or related disciplines\nAt least 4 years\u2019 experience in Web application or related system development\nStrong hands-on development skills in LAMP Web Stack (Linux, Apache, MySQL, PHP)\nSolid knowledge in PHP, Angular, CSS, HTML\nFamiliar with React.js, Node.js, .Net, RESTful APIs integration\nExperience building web service architecture on cloud computing platforms (e.g. Amazon AWS) or TMall Business Platform Maintenance will be an advantage\nCandidate with less experience will be considered as Analyst Programmer / Programmer\nAble to work under pressure and deliver on schedule\nSelf-motivated and keen on learning\nStrong team player and communicator\nDisciplinary, punctual\n\nWe offer 5-days work, Monthly incentive, 12\u00a0days annual leave, Birthday leave, 10 days paternity leave, Employee\u00a0purchase discount,Medical insurance and Annual body check to the above position.\n\nInterested parties please send Full resume to HK JEBN LIMITED, including the following details:\u00a0\n\nAvailability\u00a0\nExpected salary\u00a0\nPresent salary\u00a0\n\n\u00a0\u00a0*HK JEBN Group policies on non-recruitment of smokers or other tobacco users.\n\nAll personal data collected will be treated in strict confidential and used for recruitment purpose solely.\n\n\n", "employment_types": ["Full Time", "Permanent"], "selling_points": ["5 days work", "Excellent working environment", "Group medical and dental insurance"], "locations": ["Quarry Bay"], "categories": ["Media & Advertising", "Strategic Planning", "Information Technology (IT)", "IT - Webmaster / SEO", "Marketing / Public Relations", "Marketing - Market Research"], "post_time": "2022-01-05T06:40:18Z", "salary": {"currency": null, "max": null, "min": null, "period": "monthly", "term": null}, "salary_visible": false, "title_keywords": ["digital performance specialist"], "responsibilities": ["collaborate with", "maintenance", "systems", "user experience", "implementation", "testing", "website", "documentation"], "requirements": {"degrees": ["higher diploma or above"], "majors": ["related disciplines", "computer science"], "languages": [], "language_level": [], "hard_skills": ["linux", "apache", "computing platforms", "amazon", "web", "php", "react", "maintenance", "html", "aws", "angular", "integration", "css"], "soft_skills": ["self-motivated", "keen", "hands-on", "learning", "team player", "communicator", "work under pressure"], "languages_combined": []}, "experience_required": {"duration": ["at least 4 years"], "field": ["related", "system development"]}}, {"job_id": "100003009024070", "location_code": "hk", "company": "\u6a13\u4e0a\u6709\u9650\u516c\u53f8 / HK JEBN LIMITED", "job_title": "System Analyst / Analyst Programmer (Web Development)", "description": "We have been working hard on leveraging technology to facilitate transactions of business of all sizes, and improve end consumer\u2019s quality of life. Right now, RichFame is providing applications and services across different sectors, from e-commerce, e-logistics.\n\nWe\u2019re a small, focused, and rapidly growing team with an abundance of opportunities. If you want to make a real impact and you\u2019re up for challenges, RichFame is the ideal place for you.\n\nHighlight of Benefits\uff1a\n12 Days annual leave\nFriendly, open and complaisant working environment\nPerformance Bonus\nGreat Career Exposure\nComprehensive medical Coverage\nOn Job training\n\n\nResponsibilities\n\n\nCollaborate with Frontend Team Lead and other teammates in development team to design and develop a well-structured front-end architecture for the in-house products in an agile approach\nCollaborate with Backend developers to integrate new features and unique consumer-facing products\nResearch and provide suggestions for product development strategies\nRequirement\n\nProgramming skills in HTML5, CSS3, JavaScript\nExperience in Node.js, React.js/Vue.js is a plus\nProficient in web development on WordPress\nExperience in open-source control systems such as Git and automated testing suites such as Jest\nStrong analytical, problem-solving skill and able to pick up new technologies\nGood understanding in TDD mindset and functional programming\nGood sense of UI / UX design\nLocation: near Kwai Fong MTR Station\n\nInterested parties please send your resume with your current and expected salary by clicking the Apply Now.\nPlease visit our website at: www.richfame.hk for more information about us", "employment_types": ["Full Time"], "selling_points": ["At least 4 years\u2019 experience in Web application", "Web, PHP, Angular, JSON, Node", ".Net, MySQL, React, REST"], "locations": ["Shatin Area"], "categories": ["Information Technology (IT)", "IT - Webmaster / SEO"], "post_time": "2022-01-05T10:34:41Z", "salary": {"currency": null, "max": null, "min": null, "period": "monthly", "term": null}, "salary_visible": false, "title_keywords": ["analyst programmer", "system analyst"], "responsibilities": [], "requirements": {"degrees": [], "majors": [], "languages": [], "language_level": [], "hard_skills": [], "soft_skills": [], "languages_combined": []}, "experience_required": {"duration": [], "field": []}}, {"job_id": "100003009028445", "location_code": "hk", "company": "Fluxus Productions Limited", "job_title": "Marketing Executive", "description": "Responsibilities:\n\nMonitor organic search performance across several markets\nLead, develop and execute content and technical SEO strategies\nPlan, execute and optimize on-page website content and landing pages\nPerform ongoing keyword research including discovery and expansion, prioritization and optimization\nRecommend changes to website architecture, layouts, content and other factors to improve SEO positions for target keywords\nDevelop and improve search rankings of key webpages\nTrack, and analyze ranking performance on an ongoing basis, and optimize SEO campaigns as necessary\nMonitor, analyse and report keyword, traffic and SEO performance such as bounce rate, ranking and conversion rate\nIdentify opportunities and trends in SEO & Implement best practices\nManage and optimize SEO to deliver KPIs\nEnsure site is optimized for search engine visibility\nWork closely with regional product, engineers, editorial and sales teams\nAd hoc web-project that related to monetization\n\n\n\nRequirements:\n\nDegree holder in Statistics/ Mathematics/ Data mining/ information technology or related disciplines\n3 - 5+ years working experience in Search Engine Optimization or online marketing or digital agency\nResponsible for the company's entire network of SEO operations, can develop a comprehensive search engine optimization strategy\nOptimize the website according to the SEO indicator.\nFamiliar with SEO, and related analytics tools: Google Search Console\u3001Bing Webmaster Tools\u3001Screaming Frog\u3001ahrefs.com and Google Analytics\n\n\n\nWe Offer:\n\n5 Days Work\nFlexible Working Hour\nBirthday Leave and Work Anniversary Leave\nMedical Coverage\nFun, Young and Joyful Office Environment\n\n\n\nInterested parties please send detailed resume with 1.) EXPECTED SALARY 2.) AVAILABILITY 3.) WORK REFERENCE to HR Department by clicking 'Apply Now'.\n\nFor company information, please refer to the website http://www.presslogic.com/ .\n\nAll information received will be kept in strict confidence and only for employment-related purpose.", "employment_types": ["Full Time"], "selling_points": ["Product/ Branding marketing in Blockchain market", "Great development opportunities", "Conduct research to gain access to updated trend"], "locations": ["Tsuen Wan Area"], "categories": ["Information Technology (IT)", "IT - Webmaster / SEO", "Marketing / Public Relations", "Marketing - General / Support", "Digital Marketing"], "post_time": "2022-01-07T02:20:21Z", "salary": {"currency": null, "max": null, "min": null, "period": "monthly", "term": null}, "salary_visible": false, "title_keywords": ["marketing executive"], "responsibilities": ["seo", "ad hoc", "monitor", "website", "teams", "develop", "plan", "kpis", "report", "architecture", "analyse"], "requirements": {"degrees": ["degree holder"], "majors": ["related disciplines", "mathematics", "statistics", "information technology"], "languages": [], "language_level": [], "hard_skills": ["data mining", "analytics tools", "seo", "google analytics"], "soft_skills": ["comprehensive", "responsible"], "languages_combined": []}, "experience_required": {"duration": ["5+ years"], "field": ["agency", "digital", "marketing"]}}, {"job_id": "100003009022778", "location_code": "hk", "company": "Huawei Tech. Investment Co., Ltd", "job_title": "(Senior/Principal) Software Engineer (Web Frontend/Full-stack)", "description": "Highlight of Benefits\uff1a\n\n\n12 Days annual leave\nFriendly, open and complaisant working environment\nPerformance Bonus\nGreat Career Exposure\nComprehensive medical Coverage\nOn Job training\n\n\nWho is our Right Fit\uff1a\n\n\nCertificate or above in Information Technology, Information System or related computing subjects\n2 to 3 years experience in programming\nExperience in PHP, MVC, OOP and design patterns\nSome experience with frontend development in JS\nKnowledge in React and Angular would be nice\nFamiliar with the web development constructs, e.g. GitHub, XML, HTML/XHTML, CSS, AJAX, JSON\nFamiliar with one of the PHP framework such as Yii, Laravel, Thinkphp, WorkerMan\nStrong knowledge of DB design in MySQL\nExperience in developing API\nGood team player and able to work independently\nWorking location: Kwai Fong MTR Station\u00a0\n\nWhat you will be doing\uff1a\nThis position will be Backend focused; PHP\n\nInterested parties please send your resume with your current and expected salary by clicking the Apply Now.\n\nPlease visit our website at: www.richfame.hk for more information about us.\n\nAll applications will be treated in the strictest confidence and personal data collected will be used for recruitment related purposes only.", "employment_types": ["Full Time"], "selling_points": ["Bachelor degree or above in CSE, EE", "5yrs work exp as web frontend or full-stack dvlpr", "JavaScript/TypeScript, Vue.js/React, HTML5, CSS3"], "locations": ["Tsim Sha Tsui"], "categories": ["Engineering", "Telecommunication / Wireless / Radio", "Information Technology (IT)", "IT - Webmaster / SEO", "Software Development"], "post_time": "2022-01-05T06:31:11Z", "salary": {"currency": null, "max": null, "min": null, "period": "monthly", "term": null}, "salary_visible": false, "title_keywords": ["software engineer"], "responsibilities": [], "requirements": {"degrees": [], "majors": [], "languages": [], "language_level": [], "hard_skills": [], "soft_skills": [], "languages_combined": []}, "experience_required": {"duration": [], "field": []}}, {"job_id": "100003009017479", "location_code": "hk", "company": "VTech Corporate Services Limited", "job_title": "Web Marketing Analyst (VCO210/J02)", "description": "Job Responsibilities:\nPropose and execute digital marketing & advertising planning to support overall brand & marketing strategies\nHandle and manage digital related projects, e.g. source & form strategic partnership with digital agencies or drive brand website development\nManage digital platform to support brand building, sales promotions and marketing activities for raising brand awareness and driving traffic to social media platforms/stores\nHighlight latest marketing trends on digital development and proposing best practices on social media channels\nHandle ad hoc projects assigned by management\nJob Requirement:\n\nDegree holder in Digital Communications, Marketing\u00a0or related disciplines\n2 years or above experience in digital marketing and project management in retail industry, experience in digital agency is definitely an advantage\nSolid experience on managing popular social media platforms\nSolid experience in eCommerce, SEO, SEM, email marketing and social media\nGood communication and presentation skills\nGood Command in MS Office (Excel & Powerpoint)\n\nWe offer an attractive package commensurate with your qualifications and experience.\u00a0 Please apply with full resume,\u00a0present and expected salary, quoting the ref. no. to the Human Resources Department, Pricerite Home Limited, 28/F Manhattan Place, 23 Wang Tai Road, Kowloon Bay, Kowloon, HK; or fax to 2820 0651 or press \"APPLY NOW\"\n\nAll information provided by applicants will be treated in strict confidentiality and used for recruitment purpose only.\u00a0 We will retain your application for a maximum period of 6 months and may refer it to other vacancies within the Group.", "employment_types": ["Full Time", "Permanent"], "selling_points": ["Degree in Marketing or related disciplines", "Passionate in digital communication technologies", "5 day work, flexible working hour, double pay"], "locations": ["Tai Po Area"], "categories": ["Design", "Web Designer", "Information Technology (IT)", "IT - Webmaster / SEO", "Marketing / Public Relations", "Digital Marketing"], "post_time": "2022-01-04T00:41:21Z", "salary": {"currency": null, "max": null, "min": null, "period": "monthly", "term": null}, "salary_visible": false, "title_keywords": ["analyst"], "responsibilities": ["social media", "management", "advertising", "marketing strategies", "social media platforms", "website", "digital platform", "digital marketing", "ad hoc projects", "planning"], "requirements": {"degrees": ["degree holder"], "majors": ["related disciplines", "marketing", "communications"], "languages": [], "language_level": [], "hard_skills": ["excel", "seo", "powerpoint", "project management", "sem", "ms office"], "soft_skills": ["communication", "project management", "presentation skills"], "languages_combined": []}, "experience_required": {"duration": ["2 years"], "field": ["retail industry", "social media", "ecommerce", "agency", "project management", "marketing", "digital marketing", "digital"]}}, {"job_id": "100003009025417", "location_code": "hk", "company": "AFM Ltd", "job_title": "Senior Programmer", "description": "Responsibilities:\n\nPrepare marketing materials, and maintain website content, electronic direct mailers, social media platforms and e-commerce\nIdentify improvement opportunities in SEM & SEO growth and efficiency\nWork closely with IT and global marketing teams to optimize website content, architecture and layouts\nLead or assist in any ad hoc projects as assigned\n\nRequirements:\n\nDegree or above in Marketing or related disciplines\nMinimum 4 years of experience in SEM, SEO and website project\nExperience in digital marketing and emerging digital technology, social trends and insights\nPassion for digital communication techniques and technologies\nStrong knowledge in Google AdWords and Google Analytics\nKnowledge in graphic design and website development would be an asset\nExcellent command of written & spoken English & Chinese with strong interpersonal skill\nCandidates with less experiences will be considered as Web Marketing Developer\n\nWe offer attractive remuneration package including 5-day work, flexible work hours and other benefits to the right candidate. Interested parties please forward full resume with expected salary and quote job reference number to\n\n\nVTech Group of Companies,\nThe Human Resources and Administration Department,\n23/F, Tai Ping Industrial Centre, Block 1,\n57 Ting Kok Road, Tai Po, Hong Kong\n\nOR\u00a0apply on-line directly through our corporate website at www.vtech.com/en/careers/.\n\nFor more information about\u00a0us, please visit our website at\u00a0www.vtech.com.\n\nAll applications will be used for the purpose of recruitment only. Applicants not invited for interview within 4 weeks may consider their applications unsuccessful. We will retain the applications for a maximum period of six months and may refer them to suitable openings within our Group.", "employment_types": ["Full Time"], "selling_points": ["Holder of Diploma or Degree in Computer Science", "Minimum 3 years\u2019 working experience", "Experience in programming for the MSSQL."], "locations": ["Lai Chi Kok"], "categories": ["Information Technology (IT)", "Application Specialist - Software", "IT - Webmaster / SEO", "Software Development"], "post_time": "2022-01-06T04:26:59Z", "salary": {"currency": null, "max": null, "min": null, "period": "monthly", "term": null}, "salary_visible": false, "title_keywords": ["senior programmer"], "responsibilities": ["seo", "social media platforms", "teams", "website", "maintain", "ad hoc projects", "sem", "architecture", "prepare marketing materials"], "requirements": {"degrees": ["degree or above"], "majors": ["related disciplines", "marketing"], "languages": ["english", "chinese"], "language_level": ["excellent"], "hard_skills": ["google analytics", "seo", "web", "adwords", "sem"], "soft_skills": ["communication", "interpersonal skill", "passion for"], "languages_combined": [{"language": "english", "language_level": ["excellent"]}, {"language": "chinese", "language_level": ["excellent"]}]}, "experience_required": {"duration": ["minimum 4 years"], "field": ["developer", "digital", "marketing", "digital marketing"]}}, {"job_id": "100003009024677", "location_code": "hk", "company": "iProspect Hong Kong Limited", "job_title": "Digital Performance Manager/ Associate Digital Performance Manager", "description": "Responsibilities\n\nPlan and execute marketing campaigns\nWork with internal and external parties to execute offline media buying\nCoordinate with functional support and distribute on new product planning and launches\nProvide support of business analysis and report\nDevelop CRM systems\nManage content for digital platform (e.g. Google Ad, SEO) and social media channels to build brand awareness and website management\n\nRequirement\n\nTertiary qualifications in marketing, Business or equivalent\nMinimum 1 year Marketing experience\nCreative, independent, able to multitask\nGood command of both spoken and written English and Chinese\nKnowledge on website design or management", "employment_types": ["Full Time", "Permanent"], "selling_points": ["Business Development & Driving Agency Growth", "Strategic Performance Marketing", "5 days work and attractive compensation package"], "locations": ["Quarry Bay"], "categories": ["Media & Advertising", "Strategic Planning", "Information Technology (IT)", "IT - Webmaster / SEO", "Marketing / Public Relations", "Marketing - Market Research"], "post_time": "2022-01-06T02:09:56Z", "salary": {"currency": null, "max": null, "min": null, "period": "monthly", "term": null}, "salary_visible": false, "title_keywords": ["associate", "manager"], "responsibilities": ["social media", "provide support", "management", "seo", "internal and external parties", "coordinate with", "systems", "digital platform", "develop", "website", "marketing campaigns", "plan", "business analysis", "report", "planning"], "requirements": {"degrees": [], "majors": [], "languages": ["english", "chinese"], "language_level": ["good command"], "hard_skills": [], "soft_skills": ["multitask", "creative", "independent"], "languages_combined": [{"language": "english", "language_level": ["good command"]}, {"language": "chinese", "language_level": ["good command"]}]}, "experience_required": {"duration": ["minimum 1 year"], "field": ["marketing"]}}, {"job_id": "100003009016489", "location_code": "hk", "company": "First Page Limited", "job_title": "Senior Frontend Web Developer", "description": "Responsibilities:\n\nResponsible for the development and enhancement of the existing application.\nAssist in leading a team of junior programmer to solve problems and system tuning.\n\nRequirements:\n\nHolder of Diploma or Degree in Computer Science / Information Systems / Software Engineering or related discipline.\nMinimum 3 years\u2019 working experience in Web / Apps application development.\nSolid experience in using Java / J2EE / JavaScript for Web application development.\nExperience in programming for the MSSQL.\nGood communication, analytical and problem-solving skills.\nResponsible and be a good team player.\nLess experience will be considered for the role of Programmer / Junior Programmer.\n\n\n\nWe offer\u00a0competitive remuneration package,\u00a05-day work, OT allowance, hospitalization insurance, dental benefits\u00a0and\u00a0excellent career prospect\u00a0to the right candidate.\u00a0 Interested parties, please send your detailed resume with\u00a0Current\u00a0and\u00a0Expected salary\u00a0via \u201cApply Now\u201d.\n\nFor more details about our company, please visit our website www.afm.cc\u00a0\n\nApplicant information will be kept confidentially for one year or to be referred to other appropriate positions within our company. Personal Data provided by job applicants will be used strictly by the employer's personal data policies.", "employment_types": ["Full Time", "Permanent"], "selling_points": ["Fulltime Senior Frontend Web Developer", "Market-leading technical SEO execution", "Work with a leading APAC digital agency"], "locations": ["Wan Chai"], "categories": ["Information Technology (IT)", "IT - Webmaster / SEO", "Technical / Functional Consulting", "Marketing / Public Relations", "Digital Marketing"], "post_time": "2022-01-03T09:12:07Z", "salary": {"currency": null, "max": null, "min": null, "period": "monthly", "term": null}, "salary_visible": false, "title_keywords": ["developer"], "responsibilities": [], "requirements": {"degrees": ["diploma", "degree"], "majors": ["software engineering", "computer science"], "languages": [], "language_level": [], "hard_skills": ["java", "web application development", "web", "javascript", "programming", "mssql", "problem-solving skills"], "soft_skills": ["communication", "problem-solving skills", "good team player", "responsible"], "languages_combined": []}, "experience_required": {"duration": ["minimum 3 years"], "field": ["application development", "programming"]}}, {"job_id": "100003009019560", "location_code": "hk", "company": "We Create Limited", "job_title": "Flutter Developer", "description": "Job Requirements (Please read!)\n\n\u00a0\u00a0\u00a0\u00a0\u00a0\u00a0 Experience with WordPress, Shopify, and other popular CMSs\n\u00a0\u00a0\u00a0\u00a0\u00a0\u00a0 Knowledge of multiple front-end languages (backend languages is a plus)\n\u00a0\u00a0\u00a0\u00a0\u00a0\u00a0 UX know-how and can translate wireframes into HTML reality\n\u00a0\u00a0\u00a0\u00a0\u00a0\u00a0 Must be comfortable working in a team environment\n\u00a0\u00a0\u00a0\u00a0\u00a0\u00a0 Sounds like you? Then read on!\n\nLooking to rocket your web development career to a whole new level? Then this role is for you!\n\nFirst Page is looking for a Senior Front End Developer who is super passionate and talented about web design execution and SEO. We're looking for someone who is self-driven, a collaborator, and who loves solving technical problems. Preferably you will have WordPress and SEO knowledge and love to tackle a variety of web development projects. Never a dull moment!\n\nFirst Page prides itself on being a leader in Hong Kong and globally in digital marketing. We've won numerous rewards because we love what we do! Passion breeds success!\n\nWith offices in Australia, Hong Kong, California, Malaysia, Panama, Singapore, Thailand & Dubai, you'll be joining a company that rewards success and strives to be the best in the industry. We offer a strong entrepreneurial environment that has seen the organization ranked as the #1 fastest growing digital group in Australia for 3 years straight.\n\nRewards you deserve:\n\n\u00a0\u00a0\u00a0\u00a0\u00a0\u00a0 Generous remuneration and company medical\n\u00a0\u00a0\u00a0\u00a0\u00a0\u00a0 Salary will commensurate with qualification and experience\n\u00a0\u00a0\u00a0\u00a0\u00a0\u00a0 Collaborate with a strong, dynamic team.\n\u00a0\u00a0\u00a0\u00a0\u00a0\u00a0 Working side by side with talented individuals.\n\u00a0\u00a0\u00a0\u00a0\u00a0\u00a0 Always new and exciting projects.\n\u00a0\u00a0\u00a0\u00a0\u00a0\u00a0 Fun company that's on the move!\n\nWorking for a wide range of large MNCs to local SMEs, you'll be:\n\n\u00a0\u00a0\u00a0\u00a0\u00a0\u00a0 Learn to execute technical SEO strategies\n\u00a0\u00a0\u00a0\u00a0\u00a0\u00a0 Identify and repair SEO issues on popular CMSs (WordPress, Shopify, Magento)\n\u00a0\u00a0\u00a0\u00a0\u00a0\u00a0 Convert comprehensive layout and wireframes into working HTML pages\n\u00a0\u00a0\u00a0\u00a0\u00a0\u00a0 Use basic programming and web design skills to optimize websites for SEO\n\u00a0\u00a0\u00a0\u00a0\u00a0\u00a0 Optimize themes/plugins for speed (page performance)\n\nWhat we are looking for:\n\n\u00a0\u00a0\u00a0\u00a0\u00a0\u00a0 Minimum 3-5 years experience as a front-end website developer\n\u00a0\u00a0\u00a0\u00a0\u00a0\u00a0 Knowledge of multiple front-end languages (e.g. HTML/ CSS, JavaScript, XML, jQuery)\n\u00a0\u00a0\u00a0\u00a0\u00a0\u00a0 Ideally, knowledge of multiple backend languages (e.g. PHP, Python), JavaScript frameworks (e.g. Angular, React, Node.js), and template language (e.g. Liquid and Twig)\n\u00a0\u00a0\u00a0\u00a0\u00a0\u00a0 Problem-solving skills \u2013 an aptitude for solving practical problems\n\u00a0\u00a0\u00a0\u00a0\u00a0\u00a0 Good design and UX (User experience) sense\n\u00a0\u00a0\u00a0\u00a0\u00a0\u00a0 Excellent verbal and written communication skills (English, Mandarin and Cantonese)\n\u00a0\u00a0\u00a0\u00a0\u00a0\u00a0 Effective time management skills\n\u00a0\u00a0\u00a0\u00a0\u00a0\u00a0 Strong attention to detail\n\u00a0\u00a0\u00a0\u00a0\u00a0\u00a0 Online portfolio website is a must\n\u00a0\u00a0\u00a0\u00a0\u00a0\u00a0 A 'Can Do' attitude\n\nWhy us:\n\nWe want Hong Kong's top talent and recognize that means paying them accordingly. Our newly transformed office is a great space to inspire creativity, as well as being close to cafes and public transport. You'll be amongst a highly engaged team of the country's most talented digital marketers and growth experts, with solid prospects for upward mobility.", "employment_types": ["Full Time", "Permanent"], "selling_points": ["Passionate and experienced Flutter Developer", "Superb career growth opportunities,", "Great compensation, WFH and Medical Insurance"], "locations": ["Aberdeen"], "categories": ["Information Technology (IT)", "Application Specialist - Software", "IT - Webmaster / SEO", "Software Development"], "post_time": "2022-01-04T08:08:12Z", "salary": {"currency": null, "max": null, "min": null, "period": "monthly", "term": null}, "salary_visible": false, "title_keywords": ["developer"], "responsibilities": ["collaborate with", "management", "seo", "website", "design", "user experience", "communication", "repair", "digital marketing"], "requirements": {"degrees": [], "majors": [], "languages": ["cantonese", "english", "mandarin"], "language_level": ["excellent"], "hard_skills": ["web design", "plus", "shopify", "jquery", "fun", "web development", "seo", "basic", "html", "wordpress", "dynamic", "javascript", "angular", "python", "problem-solving skills", "php", "react", "programming", "css"], "soft_skills": ["passionate", "communication skills", "time management skills", "comprehensive", "dynamic", "attention to detail", "problem-solving skills", "mobility", "driven"], "languages_combined": [{"language": "cantonese", "language_level": ["excellent"]}, {"language": "english", "language_level": ["excellent"]}, {"language": "mandarin", "language_level": ["excellent"]}]}, "experience_required": {"duration": ["minimum 3-5 years"], "field": ["developer", "design"]}}, {"job_id": "100003009012875", "location_code": "hk", "company": "Chicle Communications Limited", "job_title": "Web Developer / Programmer (5 days work)", "description": "Position Responsibilities\n\nBusiness Development & Driving Agency Growth\n\nSupport the management team in prospecting clients and revenue tracking to drive the agency to achieving growth and revenue targets.\nContribute in developing new products and ways of working to drive sustained agency growth\nRepresent iProspect in developing strategic partnerships with various publishers and suppliers to drive better support and commercial agreements.\nPlay an active role in representing iProspect in various trade and industry events including participating in relevant industry awards to build the iProspect reputation in Hong Kong and on a regional level.\nHelp in strategic input, preparation for and attend business pitches as required\n\nStrategic Performance Marketing\n\nBe at the forefront of Digital knowledge (focusing on SEM, Display, Social, Analytics) by keeping up to date with industry news and developments\nDevelop an understanding of the various digital media channels and the potential for them in your clients marketing activity\nContribute in developing new products and ways of working to drive sustained agency growth\nEstablish an understanding of all areas of iProspect\u2019s expertise and the products/services we can provide to your clients\nHelp in preparation for and attend business pitches as required\n\nLeadership & Management\n\nBecome of Lead of the \u2018performance media\u201d business stream at iProspect Hong Kong, driving growth and best practices, working proactively with business directors and regional/global teams to roll out key initiatives including Programmatic expertise and Performance First programs to set iProspect apart from the competition\nPlay a proactive and leading role within the agency to drive a culture of learning and innovation\nLead the day to day client relationship, campaign or project development and execution for key Tier One clients\nSet and manage expectations of client and internal teams, especially to ensure iProspect has the optimal time scale to deliver quality work and service\nDevelop your presence, your perception as an authority / expert, your authentic confidence\nBe a master of our internal processes\nPrepare and lead performance review presentations\nLead development of regular results & resource analysis & reporting, recommendations and presentations\n\nInnovation & Initiative\n\nUse your personal passion and creativity to help develop intelligent, innovative and effective ideas and process improvements for your clients\nContribute your own ideas and opinions on your client\u2019s business, how we work, and the industry we\u2019re in; establish a presence in the agency; have a voice in meetings\nWork with an attitude of \u2018it\u2019s up to me to make it happen\u2019\n\nClient Relationships\n\nDevelop positive relationships that reflect true partnership in achieving the objectives of the client\u2019s business and the goals of the client\nWork to understand your client\u2019s pressures and internal demands to ensure iProspect provides the right response at the right\u00a0time in the right manner\nAchieve a level of relationship with your clients whereby they trust and value your opinions and advice on their digital\u00a0marketing activity\n\nPeople Management\n\nActively nurture the goal of making iProspect an enjoyable and extraordinary place for staff to work and for clients to engage with\nDevelop the skills and knowledge of the Digital Coordinator / Specialist through mentoring, supervision and\nproviding continual feedback on performance\nDelegate the appropriate tasks and the appropriate amount of tasks to ensure an acceptable workload\nIdentify opportunities for Digital Coordinator / Specialist to take ownership of tasks or projects \u2013 under your supervision \u2013 to\naid in her/his development; give adequate room for them to grow within their roles and eventually beyond\nCarry out Digital Coordinator / Specialist performance appraisals\n\n1. Key Performance Indicators:\n\nContribution to new business targets\nContribution to product and agency development (blog and press publications, awards/case studies, supporting new\u00a0business initiatives)\nClient satisfaction and retention\nContribution to Supplier relationship and commercial partnerships\nContribution to overall agency Learning and Development\nAchievement of annual objectives\n\nWe offer 5 days work and attractive compensation package to suitable candidates. Interested parties, please send your full resume including your present & expected salary by using \"Quick Apply\".\n\nPlease note that only short-listed applicants will be notified. All information provided will be treated in strictly confidential and used solely for recruitment purpose.", "employment_types": ["Full Time"], "selling_points": ["Opportunity to work on global-scale projects", "Young, energetic and joyful working environment", "Experienced in web-based application development"], "locations": ["Tsuen Wan Area"], "categories": ["Information Technology (IT)", "Application Specialist - Software", "IT - Webmaster / SEO", "E-commerce", "Software Development"], "post_time": "2022-01-02T14:29:04Z", "salary": {"currency": null, "max": null, "min": null, "period": "monthly", "term": null}, "salary_visible": false, "title_keywords": ["developer", "programmer"], "responsibilities": ["management team", "management", "reporting", "ideas", "business initiatives", "analysis", "review", "teams", "developing", "quality", "develop", "presentations", "media channels", "digital marketing", "sem", "tracking"], "requirements": {"degrees": ["master"], "majors": [], "languages": [], "language_level": [], "hard_skills": ["analysis", "presentations", "make", "goal", "sem"], "soft_skills": ["confidence", "proactive", "innovative", "learning", "active", "leadership", "initiative", "positive"], "languages_combined": []}, "experience_required": {"duration": [], "field": []}}, {"job_id": "100003009018146", "location_code": "hk", "company": "Strategic Digital Marketing Company Limited", "job_title": "Digital Marketing Manager (SEO+SEM) (5 days work)", "description": "Flutter Developer\n\nAre you an experienced and ambitious Flutter developer ready to engineer applications that will run across Android, iOS and the web?\n\nAre passionate about performance, reliability and design with the experience to back up that passion? Then we are looking for you!\n\nWe are offering superb career growth opportunities, great compensation and benefits.\n\nJob Description\n\nWe are looking for an experienced Flutter developer to grow with our Dev Team. You will be involved from conception to completion with projects that are technologically sound and aesthetically impressive.\n\nYou will work together with project Managers, UX/UI designers, backend developers and QA specialists to create world class apps.\n\nThe ideal candidate will have experience building native applications, JavaScript knowledge, and a portfolio of applications already published either in the app store or self-hosted.\n\nFlutter Developer Requirements and qualifications\n\n- Two or more iOS/Android apps developed with Flutter. Either deployed on the\u00a0 AppStore/Google Play or available on Github;\n- 3+ years in mobile software development;\n- Over one year\u2019s developing Flutter applications for mobile;\n- Experience with third-party libraries and APIs;\n- Understanding of the Agile development life-cycle;\n- Experience with automated testing and building;\n- Experience with Git, SVN, or other version control tools;\n- Proven experience in writing readable code, creating extensive documentation for existing code, and refactoring previously written code\n\nHighly Beneficial\n\n- Fluency with Java\u00a0and/or swift\n- Basic understanding of Android extensions/custom keyboards\n- Experience creating Material Design styled apps\n- Agency work experience\n\nPlease note\n\nPlease add your expected salary when applying, your Git and any URL\u2019s of sites you have worked on.\n\nFor candidates selected for interviews please bring along samples of websites, e-commerce platforms and apps\u00a0 you have created.\n\nRecent graduates with Flutter experience will also be considered.\n\nIf you have previously applied for a position at WECREATE before please feel free to apply again.", "employment_types": ["Full Time", "Permanent"], "selling_points": ["2-4 years experience in SEO & SEM", "Friendly and energetic working environment", "Bank Holiday, Birthday Leave & Performance Bonus"], "locations": ["Lai Chi Kok"], "categories": ["Information Technology (IT)", "IT - Webmaster / SEO", "Sales, CS & Business Devpt", "Account Servicing", "Marketing / Public Relations", "Digital Marketing"], "post_time": "2022-01-04T16:20:25Z", "salary": {"currency": null, "max": null, "min": null, "period": "monthly", "term": null}, "salary_visible": false, "title_keywords": ["digital marketing manager"], "responsibilities": ["design"], "requirements": {"degrees": [], "majors": [], "languages": [], "language_level": [], "hard_skills": ["web", "android"], "soft_skills": ["passionate about"], "languages_combined": []}, "experience_required": {"duration": [], "field": ["design"]}}, {"job_id": "100003009017929", "location_code": "hk", "company": "KPMG Executive Recruitment Limited", "job_title": "Digital Experience Manager", "description": "Responsibilities\n\nDevelopment and deployment of websites and/or web-based applications;\nImplement appropriate and tidy codes and test them in various environments, enhance and/or modify them if necessary;\nFollow standardized procedures to ensure the smoothness of development;\nHandle multiple projects simultaneously in a timely and professional manner.\n\nRequirements\n\nDiploma, associate degree or bachelor degree in Computer Science, I.T. or related disciplines;\n1-2 years relevant working experience in related fields;\nSolid knowledge in web technologies and frameworks: HTML, SCSS, jQuery, PHP, MySQL, Bootstrap, Symfony;\nProficiency in front-end development would be a bonus;\nSelf-motivated, energetic and passionate in exploring new technology;\nStrong problem solving, interpersonal & communication skills and team player;\nAbility to work under pressure by handling multiple assignments and meeting tight deadlines;\nDetailed mind, proactive and willing to take responsibility;\nFresh graduates will also be considered\nImmediate availability would be a high priority.\u00a0\n\nWe offer:\n\n5-day work\nMedical Insurance\nYoung and joyful working environment\nComprehensive training and career development opportunities\n\nInterested parties please send your application with a full resume stating your present and expected salary to the Company.\n\nJOIN OUR CHICLE'S FAMILY. APPLY NOW!\n\n**All information will be used for recruitment purposes only**", "employment_types": ["Full Time"], "selling_points": ["Implement strategies to improve digital experience", "Creation and enhancement digital content", "Web analytics, customer insight and UX/UI"], "locations": ["Not Specified"], "categories": ["Information Technology (IT)", "IT - Webmaster / SEO", "E-commerce", "Marketing - Brand / Product Management", "UI/UX Designer"], "post_time": "2022-01-04T02:29:06Z", "salary": {"currency": null, "max": null, "min": null, "period": "monthly", "term": null}, "salary_visible": false, "title_keywords": ["manager"], "responsibilities": ["multiple projects", "procedures", "professional manner"], "requirements": {"degrees": ["associate degree", "diploma", "degree", "bachelor"], "majors": ["computer science"], "languages": [], "language_level": [], "hard_skills": ["php", "jquery", "html", "problem solving", "web technologies"], "soft_skills": ["passionate", "communication skills", "self-motivated", "proactive", "meeting tight deadlines", "detailed mind", "problem solving", "team player", "energetic", "interpersonal", "work under pressure"], "languages_combined": []}, "experience_required": {"duration": ["1-2 years"], "field": ["related", "relevant working experience"]}}, {"job_id": "100003009014812", "location_code": "hk", "company": "EVISU Group Limited", "job_title": "Senior E-commerce Project Executive", "description": "You'll responsible for...\n\n\nPerform keywords research and analysis\nMonitor and enhance keywords ranking performance to deliver KPIs\nPlan and optimize on-page website content and landing pages\nLead, develop and execute content and technical SEO strategies\nRecommend changes to website architecture, layouts, content and other factors to improve keywords ranking\nConduct technical SEO and backlink audit, and draw insights for improvement\nDevelop and implement link building strategy\nIdentify SEO trend & Implement best practices\n\nIf you are...\n\n\nDegree holder in Marketing/Information Technology/Communications/e-Commerce or related disciplines\nMinimum 4 years working experience in SEO or online marketing or digital agency.\u00a0Candidates with less experience will consider as Senior Digital Marketing Specialist\nExperience in using SEO tools i.e. SEMRush, Ahrefs, Screaming Frog (or similar) is a MUST;\nExperience in using Google tools i.e. Google Analytics, Google Tag Manager, Google Search Console is a MUST;\nExperience in on-site content writing, technical SEO and link building is a MUST\nGood communication and interpersonal skills\nExcellent in Chinese and English written skill\n\nWe offer...\u00a0\n\nFive-days work per week + Bank Holiday\nSeasonal Project Completion Bonus\nEducation Allowance\nMedical Allowance\nSnacks and drinks\nTraining + Good career prospect in growing Digital Marketing Industry\n\nIf this sounds interesting to you, Apply Now!!\u00a0\n\nPlease come with a portfolio that will demonstrate our required fields as mentioned above. Interested parties, please apply with full resume, portfolio, current, and expected salary.\n\nData collected would be used for recruitment purposes only. Applicants who do not hear from us within 8 weeks may consider their application unsuccessful and their data will be destroyed within 24 months of receipt.", "employment_types": ["Full Time", "Permanent"], "selling_points": ["Double Pay + Medical Insurance", "Min 4 years Exp in E-comm website management", "Experience in Magento"], "locations": ["Kwun Tong"], "categories": ["Information Technology (IT)", "IT - Webmaster / SEO", "E-commerce", "Product Management / Business Analyst", "Software Development"], "post_time": "2022-01-03T04:12:58Z", "salary": {"currency": null, "max": null, "min": null, "period": "monthly", "term": null}, "salary_visible": false, "title_keywords": ["project executive"], "responsibilities": ["seo", "analysis", "monitor", "website", "audit", "develop", "communication", "digital marketing", "plan", "kpis", "architecture"], "requirements": {"degrees": ["degree holder"], "majors": ["e-commerce", "information technology", "related disciplines", "marketing", "communications"], "languages": ["english", "chinese"], "language_level": ["excellent"], "hard_skills": ["google analytics", "analysis", "seo", "e-commerce"], "soft_skills": ["communication and interpersonal skills", "responsible"], "languages_combined": [{"language": "english", "language_level": ["excellent"]}, {"language": "chinese", "language_level": ["excellent"]}]}, "experience_required": {"duration": ["minimum 4 years"], "field": ["agency", "marketing", "digital marketing", "content writing", "digital"]}}, {"job_id": "100003009013878", "location_code": "hk", "company": "LATITUDE LIMITED", "job_title": "ASSISTANT WEB PROGRAMMING MANAGER", "description": "Job Responsibilities:\n\nWork closely with both internal and external parties to manage the e-commerce site to ensure the success of all deliverables as per schedule;\nManage new features implementation from collecting user requirements, defining project scope, specification, timeline/resource, and final testing;\nManage third party and external providers\u2019 contracts and Statement of Work;\nTrack project deliverables and prepare reports defining project progress, issues and solutions;\nOptimize user experience on various devices according to best practices;\nConstantly strive for new/innovated ideas and solutions for the business & improve operation efficiency of the team;\nPropose solutions with options to solve the problems arising out of the website development;\nSupport ecommerce operation on routine operation tasks\n\n\u00a0Requirement\n\nDegree holder in Computer Science, IT or other related discipline\nAt least 4 years relevant experience in E-commerce website management\nProficient PC skills in MS Excel, Word and Power Point\nExperience in Magento is an advantage\nAbility to handle multi-task, target-oriented, work under pressure and meet deadlines required\nWork independently, self-motivated, detail-minded, good attitude, strong sense of responsibility\nGood team player and good in communicating with different levels within the organization\nGood command in both oral and written English, Cantonese and Mandarin\n\nWe offer 5-day work week, medical and dental insurance, MPF, bank holidays and competitive remuneration package to the right candidate.\n\nAll information collected will be used for recruitment related purpose only and will be treated in strict confidence. Applicants who are not notified within 8 weeks may consider their application unsuccessful. All applications will be retained for maximum 6 months and will be destroyed.", "employment_types": ["Full Time", "Permanent"], "selling_points": [], "locations": ["Tsuen Wan Area"], "categories": ["Information Technology (IT)", "IT - Webmaster / SEO", "Software Development", "Network & System"], "post_time": "2022-01-03T02:49:43Z", "salary": {"currency": null, "max": null, "min": null, "period": "monthly", "term": null}, "salary_visible": false, "title_keywords": ["manager", "assistant"], "responsibilities": ["ideas", "project deliverables", "contracts", "internal and external parties", "implementation", "project progress", "testing", "user experience", "website", "schedule", "prepare reports", "third party"], "requirements": {"degrees": ["degree holder"], "majors": ["it", "computer science"], "languages": ["cantonese", "english", "mandarin"], "language_level": ["good command"], "hard_skills": ["e-commerce", "word", "ms excel", "power point", "pc skills"], "soft_skills": ["detail-minded", "work independently", "self-motivated", "multi-task", "good team player", "oral", "sense of responsibility", "meet deadlines", "work under pressure"], "languages_combined": [{"language": "cantonese", "language_level": ["good command"]}, {"language": "english", "language_level": ["good command"]}, {"language": "mandarin", "language_level": ["good command"]}]}, "experience_required": {"duration": ["at least 4 years"], "field": ["management", "relevant experience", "e-commerce"]}}, {"job_id": "100003009020228", "location_code": "hk", "company": "APM Monaco Limited", "job_title": "Full Stack Web Developer", "description": "About KPMG\n\nKPMG is a global network of professional services firms providing Audit, Tax and Advisory services. KPMG Executive Search and Recruitment is a business unit of KPMG China and is one of the few recruitment consultancy firms in Hong Kong that is part of a large professional organisation.\u00a0 We work alongside a group of professionals and advisors who provide us with a high level of insights and awareness about a wide range of businesses and professions. We support the clients and aim to provide a pleasant working experience for the clients and candidates.\u00a0 \u00a0\n\nDigital Experience Manager\n\nOur client is a government-funded institution with sizable operation in Hong Kong.\n\nResponsibilities:\n\nManage the Digital Experience team to create and support the implementation of strategies to improve digital customer experience, satisfaction, and conversion\nResponsible for the creation and enhancement of relevant and engaging digital content for the institution\u2019s website\nBlend web analytics, customer insight and UX/UI best practices to develop strategies for outstanding digital customer experience\nCoordinate with business users to understand users\u2019 requirements and operational needs\nAssist business user to plan and implement digital marketing activities\nLead the planning, implementation, maintenance of CMS solutions\nFormulate post campaign analysis and provide recommendations for future projects\u2019 communication to stakeholders\nEstablish effective partnerships with stakeholders\nProvide advice on all digital customer experience related issues to stakeholders and the institution\nEnsure the institution has appropriate knowledge, guidance, support, and training\nHandle ad hoc IT projects and assignments as assigned\n\nRequirements:\n\nBachelor\u2019s Degree or above in Computer Science, Information Technology, or related discipline.\nMinimum 8 years\u2019 experience in IT, in which 4 years\u2019 experience in digital marketing, content strategy, marketing campaigns, digital commerce and Digital channel.\nSound knowledge in new tools in digital experience and customer experience, along with established tools such as Google Analytics, Tag Manager, and Webmaster tools\nExperience in content management systems and web content management\nStrong understanding of digital marketing principles\nStrong understanding of the ranking factors and search engine optimisation practices Knowledge of best practices and trends in digital channels for sales and customer feedback such as social media, chatbots, ecommerce, websites, digital advertising, etc\nAbility in building websites with Enterprise content management systems\nExperience in both UX and CX platform\nAbility to work under pressure\nExcellent planning and implementation skills\nGood team player with strong interpersonal and negotiation skills, able to communicate effectively with internal and external parties\nProficiency in both written and spoken English and Chinese (Proficiency in Mandarin is an advantage)\n\nTo apply, please send your CV with expected salary to Mr. Bernard Ng by clicking below \"APPLY NOW\" button or 8th Floor, Prince\u2019s Building, 10 Chater Road, Central, Hong Kong. By submitting your application, you agree to receive communications from us and agree our Personal Information Collection Statement in the following link: www.kpmg.com.cn/KER-opportunities\n\n\u00a92021 KPMG Executive Recruitment Limited, a Hong Kong limited liability company and a member firm of the KPMG network of independent member firms affiliated", "employment_types": ["Full Time"], "selling_points": ["Strong in Golang & Vue.js development", "JavaScrip, HTML & CSS", "Familiar with GIT or other versioning tools"], "locations": ["Central"], "categories": ["Information Technology (IT)", "IT - Webmaster / SEO"], "post_time": "2022-01-04T10:14:21Z", "salary": {"currency": null, "max": null, "min": null, "period": "monthly", "term": null}, "salary_visible": false, "title_keywords": ["developer"], "responsibilities": ["guidance", "develop strategies", "ad hoc", "maintenance", "analysis", "coordinate with", "implementation", "website", "communication", "provide advice", "digital marketing", "provide recommendations", "plan", "ui", "planning"], "requirements": {"degrees": ["degree or above", "bachelor"], "majors": ["computer science", "information technology"], "languages": ["english", "chinese", "mandarin"], "language_level": ["advantage", "proficiency"], "hard_skills": ["google analytics", "web"], "soft_skills": ["good team player", "independent", "negotiation skills", "interpersonal", "work under pressure"], "languages_combined": [{"language": "english", "language_level": ["advantage"]}, {"language": "chinese", "language_level": ["advantage"]}, {"language": "mandarin", "language_level": ["proficiency"]}]}, "experience_required": {"duration": ["4 years", "minimum 8 years"], "field": ["management", "it", "digital marketing", "marketing", "digital"]}}, {"job_id": "100003009020006", "location_code": "hk", "company": "Hong Leong Insurance (Asia) Limited", "job_title": "Analyst Programmer / Senior Analyst Programmer", "description": "About the Role:\n\nWe are looking for a talented Full Stack Web Developer to be responsible for the development, monitoring, integration and innovation on our internal Website(s). Our web developers are capable of full cycle project leadership including application architecture, design input, site layout/user interface, database design/programming.\n\nThe right individual for this role will be a motivated and energetic developer who is proactive, independent, enjoys finding solutions to a varying number of challenges, is detail-oriented, willing to learn and work forwards.\n\nResponsibilities:\n\nBe responsible for maintaining, expanding our internal websites\nDevelop Vue.js website with Golang\nStay plugged into emerging technologies/industry trends and apply them into operations and activities\nCooperate with web designers to adapt visual design intent\nWrite well designed, efficient code\u00a0\nIntegrate data from various back-end services and databases\n\nDesired Skills:\n\nStrong Experience in Golang and Vue.js development\u00a0\nAbility to generate standards-compliant HTML and CSS\nExperience with JavaScript\nExperience on Progressive Web Apps would be a plus\nFamiliar with GIT or versioning tools in general\nAdequate knowledge of relational database systems, and web application development\u00a0\nBasic knowledge of Linux(Ubuntu) would be a plus\nAggressive problem diagnosis and creative problem solving skills\nAbility to communicate professionally, both written and spoken in English and Cantonese.\nProactive and quick-witted\nBS in computer science or a related field\n\nDon't wait to join APM Monaco! Click on APPLY NOW!", "employment_types": ["Full Time", "Permanent"], "selling_points": [], "locations": ["North Point"], "categories": ["Information Technology (IT)", "IT - Webmaster / SEO", "Software Development", "UI/UX Designer"], "post_time": "2022-01-04T09:40:46Z", "salary": {"currency": null, "max": null, "min": null, "period": "monthly", "term": null}, "salary_visible": false, "title_keywords": ["analyst programmer", "senior analyst programmer"], "responsibilities": ["maintaining", "data", "operations", "monitoring", "systems", "website", "design", "develop", "bs", "user interface", "database", "visual", "databases", "application development", "architecture", "cooperate with"], "requirements": {"degrees": [], "majors": [], "languages": ["cantonese", "english"], "language_level": [], "hard_skills": ["plus", "git", "web application development", "basic", "web", "css", "web apps", "html", "visual design", "javascript", "programming", "databases", "integration", "code", "problem solving skills"], "soft_skills": ["efficient", "proactive", "independent", "capable", "responsible", "creative", "willing to learn", "detail-oriented", "motivated", "progressive", "problem solving skills", "energetic", "leadership"], "languages_combined": [{"language": "cantonese", "language_level": []}, {"language": "english", "language_level": []}]}, "experience_required": {"duration": [], "field": []}}, {"job_id": "100003009008084", "location_code": "hk", "company": "Adhoc Fun Limited", "job_title": "Software Engineer (Web)", "description": "Job Responsibilities:\n\n\nResponsible for web application development and UI/UX design\nProvide production support upon user requests and maintain system stability\nPrepare documentation on programs and operational tasks\nRequirements:\n\nBachelor Degree, Associate Degree or Higher Diploma in Computer Science or related discipline\n2 years or above relevant working experience in website development\nSolid experience in frontend technologies e.g. JavaScript, HTML5, CSS, and backend technologies e.g. Java, Spring, SQL, Node.js\nExperience in MVC framework and CMS administration\nKnowledge in Web Analytics / BI reporting is preferred\nSelf-motivated, responsible, and able to solve problems independently\nGood time management, communication and interpersonal skills\nPlease apply (preferably in Word or PDF format) with present and expected salaries, quoting job reference (JDBI/0401/AP_1) to Head of Human Resources, 50/F The Center, 99 Queen\u2019s Road Central, Hong Kong or email to us or fax to 2285 3209. You are invited to visit our website at: http://www.hl-insurance.com.\n\n\n\nAll applications will be treated in strict confidence and used for recruitment purpose within Guoco Group Limited, or Hong Leong Group of which Guoco is a member (together, \u201cthe Group\u201d) only. A copy of our personal data policy is available on request.\n\nApplicants not hearing from us within 8 weeks may consider their applications unsuccessful. We may also consider their application for other or future vacancies within the Group. Personal data of unsuccessful applicants will be retained by the Group for a maximum period of one year.", "employment_types": ["Full Time", "Permanent"], "selling_points": ["Happy, fun and harmonious working environment", "5 days work / Flexible working hours", "Fresh graduates will be considered"], "locations": ["Ngau Tau Kok"], "categories": ["Information Technology (IT)", "Application Specialist - Software", "IT - Webmaster / SEO"], "post_time": "2021-12-30T06:40:52Z", "salary": {"currency": null, "max": null, "min": null, "period": "monthly", "term": null}, "salary_visible": false, "title_keywords": ["software engineer"], "responsibilities": ["operational tasks", "system stability", "design", "maintain", "documentation", "application development", "ui"], "requirements": {"degrees": ["associate degree", "diploma", "degree", "bachelor"], "majors": ["computer science"], "languages": [], "language_level": [], "hard_skills": ["java", "bi", "word", "sql", "javascript", "spring", "web analytics", "css"], "soft_skills": ["self-motivated", "independently", "confidence", "responsible", "solve problems", "communication and interpersonal skills", "web analytics", "time management"], "languages_combined": []}, "experience_required": {"duration": ["2 years"], "field": ["development", "relevant working experience", "administration"]}}, {"job_id": "100003009009318", "location_code": "hk", "company": "Pontac Company Limited", "job_title": "PHP Programmer / Developer (Backend)", "description": "RESPONSIBILITIES :\n\nDesign and develop the database architecture, including container hosting and orchestration;\nResponsible for coding, application implementation, and documentation of the various project;\nConduct data migration and support various types of testing;\nSupport application lifecycle.\n\nREQUIREMENTS :\n\nDegree in Computer Science, Information Technology or related disciplines;\n5 years or above relevant post-qualification experience;\nSolid hands-on development experience in Web API development;\nFamiliar with JavaScript, HTML/HTML5, MySQL, Jquary, CSS/CSS3, PHP;\nCreative, Self--motivated, Initiative, Well-organized, Details-oriented, and willing to work under pressure;\nA good team player with excellent interpersonal and communication skills.\n\n\u00a0**DATA COLLECTED WILL BE USED FOR RECRUITMENT PURPOSE ONLY**", "employment_types": ["Full Time"], "selling_points": ["5-day work week", "Performance bonus", "Medical insurance"], "locations": ["Kowloon Bay"], "categories": ["Information Technology (IT)", "Application Specialist - Software", "IT - Webmaster / SEO", "Network & System"], "post_time": "2021-12-30T15:04:35Z", "salary": {"currency": null, "max": null, "min": null, "period": "monthly", "term": null}, "salary_visible": false, "title_keywords": ["developer", "programmer"], "responsibilities": ["data", "design and develop", "implementation", "coding", "testing", "database", "documentation", "migration", "architecture"], "requirements": {"degrees": ["degree"], "majors": ["related disciplines", "computer science", "information technology"], "languages": [], "language_level": [], "hard_skills": ["php", "html", "web api", "javascript", "css"], "soft_skills": ["communication skills", "good team player", "interpersonal", "well-organized", "hands-on", "motivated", "creative", "initiative", "work under pressure"], "languages_combined": []}, "experience_required": {"duration": ["5 years"], "field": ["development", "post-qualification"]}}, {"job_id": "100003009010272", "location_code": "hk", "company": "Cornerstone Technologies Holdings Limited", "job_title": "Frontend or Web Developer (Programmer)", "description": "Job Description\n\nResponsibilities:\n\nPerform system design, development, testing and maintenance of applications\nFull system development life cycle experience\nWork closely with users, developers, stakeholders and other offices to deliver solutions\nDeliver high-quality work within committed project schedules\n\n\u00a0Requirements:\n\nUniversity Degree in Computer Science/Engineering, Information Technology/System, or other relevant disciplines desirable\nSolid knowledge or experience in PHP/ Python/ Node.js/ Golang/ Java\nExperience web development in ReactJS/ Angular, HTML and CSS\nKnowledge in Azure / AWS cloud services\nKnowledge in Microservices and docker is a plus\nGood team player with strong interpersonal and communication skills\nSelf-motivated and quality-focused\n\n\u00a0We offer attractive remuneration and fringe benefits to the right candidates. Please send us the application by clicking the \"Apply Now\" button, together with a detailed resume, stating current and expected salary.\u00a0\n\n(All personal data provided by job applicants are used only for recruitment purpose and will be treated strictly confidential. Unsuccessful applications will be properly disposed within 3 months.)", "employment_types": ["Full Time", "Permanent"], "selling_points": ["Degree in Information Technology/Computer Science", "Min. 1-3 years experiences in web development", "Proficient in HTML, CSS, JavaScript frameworks"], "locations": ["Wong Tai Sin Area"], "categories": ["Information Technology (IT)", "Application Specialist - Software", "IT - Webmaster / SEO", "Testing / QA"], "post_time": "2021-12-31T03:25:11Z", "salary": {"currency": null, "max": null, "min": null, "period": "monthly", "term": null}, "salary_visible": false, "title_keywords": ["developer", "programmer"], "responsibilities": ["maintenance", "schedules", "quality", "testing", "system design"], "requirements": {"degrees": ["university degree"], "majors": ["engineering", "computer science", "information technology"], "languages": [], "language_level": [], "hard_skills": ["web development", "java", "azure", "plus", "php", "microservices", "html", "aws", "angular", "python", "css"], "soft_skills": ["communication skills", "good team player", "self-motivated", "focused", "interpersonal"], "languages_combined": []}, "experience_required": {"duration": [], "field": ["development"]}}, {"job_id": "100003009009317", "location_code": "hk", "company": "Pontac Company Limited", "job_title": "Senior Web Developer / Frontend Developer", "description": "Job Highlights\n\u00a0Solid experience in web development\n\u00a0Diploma or above in Computer Science / Software Engineering or related disciplines\n\u00a0Knowledge of network platform API\n\nJob Responsibilities\n\nBuild, and maintain efficient, reusable, and reliable PHP code and API\nEnsure the best possible performance, quality, and responsiveness of the applications\nMaintain system stability and bug fixing\nWorking in highly collaborative teams and building quality code\nKeep up with the latest web technologies and trends\nOptimizing components for maximum performance across a vast array of web-capable devices and browsers\n\nJob Requirement\n\nDiploma or above in Computer Science /\u00a0Software Engineering or related disciplines\nMinimum 2 year of backend development experience working with PHP, MySQL, RESTful API, HTML5, JavaScript, jQuery, Ajax,\nProficiency in PHP, MVC, OOP and design patterns\nFamiliar with Linux OS, like CentOS, Ubuntu\nExperienced in PHP framework such as Laravel is an added advantage\nExperience with cloud computing server in AWS, Azure or Google\nExperience with SQL, NoSQL\nHands-on experience with Git, NPM or related building tools is an added advantage\nSelf-motivated team player and able to display passion in web development\nStrong problem solving, quality-oriented, responsible and initiative\nAble to work independently and fast learner\nImmediately available is preferred\nLess experience will be considered as Junior position\n\n\u00a0Benefits\n\n5-day work week\nPerformance bonus\nMedical insurance\nDental\u00a0insurance\nBirthday leave\n\nWe offer attractive compensation package to suitable candidates. Interested parties, please click \"Apply Now\" to submit your application including your present & expected salary.", "employment_types": ["Full Time"], "selling_points": ["5-day work week", "Performance bonus", "Medical insurance"], "locations": ["Kowloon Bay"], "categories": ["Information Technology (IT)", "Application Specialist - Software", "IT - Webmaster / SEO", "Network & System"], "post_time": "2021-12-30T15:01:50Z", "salary": {"currency": null, "max": null, "min": null, "period": "monthly", "term": null}, "salary_visible": false, "title_keywords": ["developer"], "responsibilities": ["teams", "maintain", "quality", "system stability"], "requirements": {"degrees": ["diploma or above"], "majors": ["related disciplines", "software engineering", "computer science"], "languages": [], "language_level": [], "hard_skills": ["linux", "restful api", "git", "azure", "web development", "php", "jquery", "centos", "aws", "sql", "problem solving", "javascript", "os", "ajax", "server"], "soft_skills": ["self-motivated", "work independently", "responsible", "passion in", "problem solving", "hands-on", "team player", "fast learner", "initiative"], "languages_combined": []}, "experience_required": {"duration": ["minimum 2 year"], "field": ["sql", "development", "related"]}}, {"job_id": "100003009007867", "location_code": "hk", "company": "EC Healthcare", "job_title": "Web Programmer", "description": "Job Highlights\n\u00a0Solid experience in web development\n\u00a0Diploma or above in Computer Science / Multimedia or related disciplines\n\u00a0Knowledge of network platform API\n\nJob Responsibilities\n\nBuilding reusable components and front-end libraries for future use\nDevelopment of website or web applications\nCollaborate closely with the development and design team\nKeep up with the latest web technologies and trends\nOptimizing components for maximum performance across a vast array of web-capable devices and browsers\n\nJob Requirement\n\nDiploma or above in Computer Science /\u00a0Multimedia or related disciplines\nMinimum 3 years of solid experience in development\nProficiency in HTML5, jQuery and JavaScript framework like Vue.js / React.js\nProficiency in CSS framework like tailwindcss, bootstrap\nExperienced in three.js, webAR, Unity 3D is an added advantage\nHands-on experience with Git, NPM, gulp, webpack or related building tools\nBasic understanding of server-side CSS pre-processing platforms, such as LESS and SASS\nHands-on experience\u00a0with RESTful API\nSelf-motivated team player and able to display passion in web development\nStrong problem solving, quality-oriented, responsible and initiative\nAble to work independently and fast learner\nImmediately available is preferred\nCandidates with less experience will be considered as Web Developer\n\n\u00a0Benefits\n\n5-day work week\nPerformance bonus\nMedical insurance\nDental\u00a0insurance\nBirthday leave\n\nWe offer attractive compensation package to suitable candidates. Interested parties, please click \"Apply Now\" to submit your application including your present & expected salary.", "employment_types": ["Full Time"], "selling_points": ["Develop responsive websites and web applications", "To implement best practice on UX/UI design", "Collaborate project teams, designers & external"], "locations": ["Mong Kok"], "categories": ["Information Technology (IT)", "IT - Webmaster / SEO", "Testing / QA", "UI/UX Designer"], "post_time": "2021-12-30T04:54:55Z", "salary": {"currency": null, "max": null, "min": null, "period": "monthly", "term": null}, "salary_visible": false, "title_keywords": ["web programmer"], "responsibilities": ["collaborate", "website", "design"], "requirements": {"degrees": ["diploma or above"], "majors": ["related disciplines", "computer science"], "languages": [], "language_level": [], "hard_skills": ["restful api", "git", "basic", "web development", "web", "react", "jquery", "problem solving", "javascript", "multimedia", "server", "css", "processing", "unity"], "soft_skills": ["self-motivated", "work independently", "responsible", "passion in", "problem solving", "hands-on", "team player", "fast learner", "initiative"], "languages_combined": []}, "experience_required": {"duration": ["minimum 3 years"], "field": ["related", "development", "developer"]}}, {"job_id": "100003009012776", "location_code": "hk", "company": "Terminal 1 Limited", "job_title": "Growth & Digital Acquisition Manager (Team Lead)", "description": "Responsibilities:\n\nTo develop web applications using PHP, MySQL, HTML5, CSS3, Bootstrap, jQuery, JavaScript, Ajax, etc.\nTo follow up with users for system requirements and feedbacks.\nDevelop new websites for front end and back end programming.\nWebsites maintenance.\nCarry out testing, bug fixing and troubleshooting in order to provide solutions to meet user's requirements.\n\nRequirements:\n\nDegree in Information Technology, Computer Science or equivalent.\nMinimum 1 year of relevant experience in web programming with past job reference.\nProven knowledge in PHP, API, MySQL, JavaScript, CSS3, HTML5, jQuery, Ajax are essential.\nExperience in Wordpress, Wix or CodeIgniter is an advantage.\nFamiliar with Adobe Illustrator, Photoshop will be a plus.\nFamiliar with SEO tracking code installation (eg. GTM, GA, Facebook Pixel, etc.) will be a plus.\nGood command of written Chinese and English.\nSelf-motivated, responsible, able to work independently under tight deadline and willing to work under pressure.\nImmediately available preferred.", "employment_types": ["Full Time"], "selling_points": ["New headcount, team lead, build own team", "Strong leadership, scalable products", "Established platform, stable turnover"], "locations": ["Others"], "categories": ["Information Technology (IT)", "IT - Webmaster / SEO", "Marketing / Public Relations", "Digital Marketing", "E-commerce", "Marketing - Brand / Product Management"], "post_time": "2022-01-02T22:54:15Z", "salary": {"currency": "HKD", "max": 69999, "min": 45000, "period": "monthly", "term": null}, "salary_visible": true, "title_keywords": ["manager", "lead"], "responsibilities": ["maintenance", "troubleshooting", "provide solutions", "testing", "develop"], "requirements": {"degrees": ["degree"], "majors": ["computer science", "information technology"], "languages": ["english", "chinese"], "language_level": ["good command"], "hard_skills": ["plus", "seo", "web", "php", "jquery", "adobe illustrator", "wordpress", "javascript", "programming", "ajax", "code", "facebook", "photoshop"], "soft_skills": ["self-motivated", "work independently", "responsible", "work under pressure"], "languages_combined": [{"language": "english", "language_level": ["good command"]}, {"language": "chinese", "language_level": ["good command"]}]}, "experience_required": {"duration": ["minimum 1 year"], "field": ["relevant experience", "programming"]}}, {"job_id": "100003009010212", "location_code": "hk", "company": "Cornerstone Global Partners", "job_title": "Frontend Developer (React.js) - Top tier MNC insurance firm - Up to 60K+", "description": "Our client is an HK Listed Company which was established for over 30 years. It is one of the top five media groups in Hong Kong.\n\nThe management has planned for a group-wide digital transformation and has added new headcounts in building the Digital Transformation Department to drive the process.\n\nThe Digital Transformation Department will take charge of all digital initiatives, including revamping the existing products, developing new products as well as promoting new digital acquisitions by using UX, UI, CRM, Performance Marketing, Social Media, etc.\n\nThe current opening is a new headcount, Team Lead position, report to the Digital Transformation Lead.\u00a0\n\nYour job duties will include the following:\n\nOversee the growth (retention and activation) and acquisition campaigns to acquire new users, retain and activate the existing users\nDevelop and lead the annual digital marketing strategies, including performance marketing, social media community engagement, etc.\nSetup performance metrics, formulate growth models using organic and paid growth loops\nTrack and analyze the performance with conversion funnel metrics\nWork closely Product Development team on tracking and tagging, and to explore and enhance the customer journey, customer experience, product functions and product features in the digital channels (website and mobile app)\nCreate and review existing reporting dashboards and share relevant insights to the content team\nRequirements:\n\nBachelor\u2019s or Master's degree in Business Management, Marketing, e-Commerce, or any other discipline\nAt least 5 years of working experience in growth marketing, performance marketing, or digital marketing\nHands-on experience in Google Analytics and comfortable with other analytics tools\nSolid knowledge in the latest growth practices including paid acquisition, technical SEO, SEM, etc.\nAnalytical, sensitive to numbers, and possesses a data-driven mindset in problem-solving\nStart-up experience is a plus\n\nCandidates with no media experience will be considered\nInterested parties, please send your cv to us with your contact details as well as salary information and notice period. You can contact Karen Yim at Terminal 1 for details.\n\nAll personal data collected will be used for recruitment purposes only.", "employment_types": ["Full Time"], "selling_points": ["Work from home", "Local team", "Attractive Salary Package"], "locations": ["Not Specified"], "categories": ["Information Technology (IT)", "Application Specialist - Software", "IT - Webmaster / SEO", "Software Development"], "post_time": "2021-12-31T03:18:23Z", "salary": {"currency": null, "max": null, "min": null, "period": "monthly", "term": null}, "salary_visible": false, "title_keywords": ["developer"], "responsibilities": ["data", "website", "digital marketing strategies", "mobile app", "developing", "develop", "ui", "setup", "report", "social media", "management", "reporting", "seo", "review", "digital marketing", "tracking", "analytics tools", "performance metrics", "sem"], "requirements": {"degrees": ["degree", "bachelor", "master"], "majors": ["business", "e-commerce", "marketing"], "languages": [], "language_level": [], "hard_skills": ["business management", "analytics tools", "google analytics", "plus", "seo", "no", "e-commerce", "problem-solving", "mobile", "sem"], "soft_skills": ["problem-solving", "hands-on", "sensitive to numbers", "driven"], "languages_combined": []}, "experience_required": {"duration": ["at least 5 years"], "field": ["marketing", "digital marketing", "digital", "product development", "media", "team"]}}, {"job_id": "100003009004391", "location_code": "hk", "company": "VICO Systems Limited", "job_title": "PHP / Drupal Web Developer", "description": "Job Description\n\nResponsibilities:\n\nPerform system design, development, testing and maintenance of applications\nFull system development life cycle experience\nWork closely with users, developers, stakeholders and other offices to deliver solutions\nDeliver high-quality work within committed project schedules\n\n\u00a0Requirements:\n\nUniversity Degree in Computer Science/Engineering, Information Technology/System, or other relevant disciplines desirable\nSolid knowledge or experience in PHP/ Python/ Node.js/ Golang/ Java\nExperience web development in ReactJS/ Angular, HTML and CSS\nKnowledge in Azure / AWS cloud services\nKnowledge in Microservices and docker is a plus\nGood team player with strong interpersonal and communication skills\nSelf-motivated and quality-focused\n\n\u00a0We offer attractive remuneration and fringe benefits to the right candidates. Please send us the application by clicking the \"Apply Now\" button, together with a detailed resume, stating current and expected salary.\u00a0\n\n(All personal data provided by job applicants are used only for recruitment purpose and will be treated strictly confidential. Unsuccessful applications will be properly disposed within 3 months.)", "employment_types": ["Full Time", "Permanent"], "selling_points": ["2+ Years of working experience w/ PHP or Drupal", "Familiar with Drupal 8 or Drupal 9 is an advantage", "Five-day work week, Flexible working hours"], "locations": ["Kwun Tong"], "categories": ["Information Technology (IT)", "IT - Webmaster / SEO", "IT Project Management / Team Lead", "Software Development"], "post_time": "2021-12-29T02:15:40Z", "salary": {"currency": null, "max": null, "min": null, "period": "monthly", "term": null}, "salary_visible": false, "title_keywords": ["developer"], "responsibilities": ["maintenance", "schedules", "quality", "testing", "system design"], "requirements": {"degrees": ["university degree"], "majors": ["engineering", "computer science", "information technology"], "languages": [], "language_level": [], "hard_skills": ["web development", "java", "azure", "plus", "php", "microservices", "html", "aws", "angular", "python", "css"], "soft_skills": ["communication skills", "good team player", "self-motivated", "focused", "interpersonal"], "languages_combined": []}, "experience_required": {"duration": [], "field": ["development"]}}, {"job_id": "100003009002885", "location_code": "hk", "company": "ExcLand Company Limited", "job_title": "I.T. Officer \u2013 (E-commerce and Digital)", "description": "Job Descriptions:\n\nTo be responsible for maintenance and enhance the existing web esp.woocommerce in high efficiency in HK.\u00a0\nWork closely with the designers, developers and marketing team for system design, software development and deployment of e-Commerce website platform with B2B and B2C function for China / Japan market.\nCollaborating with UXUI, Product Management, and QA teams to deliver the best-in-class e-commerce experience on both web and mobile Apps platforms.\u00a0\u00a0\nMonitor and maintain performance and quality of established platforms and websites, offer solution and recommendation if necessary.\nUtilizing latest and exciting technologies, frameworks and development tools to improve the web , Built-in programme, payment etc.\u00a0\nJob Requirements:\n\n\nBachelor Degree in Computer Science/ Information Technology or related discipline.\n2 years IT working experience.\nAt least 1 year working experience in e-Commerce website administration.\nSolid knowledge in HTML, CSS, JavaScript, etc.\nGood command of written and spoken Cantonese, English & Mandarin.", "employment_types": ["Full Time", "Permanent"], "selling_points": ["I.T.", "E-commerce and Digital", "Website Maintenance"], "locations": ["Cheung Sha Wan"], "categories": ["Information Technology (IT)", "IT - Webmaster / SEO", "Support", "UI/UX Designer"], "post_time": "2021-12-28T07:31:24Z", "salary": {"currency": null, "max": null, "min": null, "period": "monthly", "term": null}, "salary_visible": false, "title_keywords": ["officer"], "responsibilities": ["management", "software", "maintenance", "teams", "website", "monitor", "quality", "payment", "system design", "maintain"], "requirements": {"degrees": ["degree", "bachelor"], "majors": ["computer science", "information technology"], "languages": ["cantonese", "english", "mandarin"], "language_level": ["good command"], "hard_skills": ["css", "javascript", "html", "e-commerce"], "soft_skills": [], "languages_combined": [{"language": "cantonese", "language_level": ["good command"]}, {"language": "english", "language_level": ["good command"]}, {"language": "mandarin", "language_level": ["good command"]}]}, "experience_required": {"duration": ["2 years", "at least 1 year"], "field": ["administration", "it", "e-commerce"]}}, {"job_id": "100003008996197", "location_code": "hk", "company": "LPM Group Limited", "job_title": "PHP Full Stack Web Developer", "description": "A leading MNC insurance company is hiring multiple Frontend Engineer for their new web app project.\u00a0\n\nYour new role:\n\n\nWork closely with the core team in Hong Kong to implement and develop the frontend services\nParticipate in scrum activities and practice Agile methodologies\nWork closely with our fellow business product owners, business analysts, UI designers, UI developers and other key stakeholders\nResponsible for server-side web application logic and integration of the frontend applications\nResponsible for optimizing and implementing the web development\n\n\u00a0What we are looking for?\n\nDegree in Computer Science\u00a0or equivalent\n3 years+ of solid experience in commercial web development projects\nFluent in JavaScript, React.js or other related tech stacks\nGreat team player, independent, strong sense of responsibility and self-motivated\nCreative, proactive, and passionate with latest technologies\u00a0 \u00a0", "employment_types": ["Full Time", "Permanent"], "selling_points": ["Western style working environment", "Double Pay, 5 day works, Medical", "Fresh graduates is welcome"], "locations": ["Central"], "categories": ["Information Technology (IT)", "IT - Webmaster / SEO", "Technical Writing"], "post_time": "2021-12-23T05:56:12Z", "salary": {"currency": null, "max": null, "min": null, "period": "monthly", "term": null}, "salary_visible": false, "title_keywords": ["developer"], "responsibilities": ["insurance", "ui", "develop"], "requirements": {"degrees": ["degree"], "majors": ["computer science"], "languages": [], "language_level": [], "hard_skills": ["web development", "agile", "web", "integration", "react", "javascript", "server"], "soft_skills": ["passionate", "self-motivated", "proactive", "independent", "agile", "responsible", "sense of responsibility", "team player", "creative"], "languages_combined": []}, "experience_required": {"duration": [], "field": ["commercial", "development projects"]}}, {"job_id": "100003009008316", "location_code": "hk", "company": "Linkers International Limited", "job_title": "Full Stack Developer ( JAVA / JavaScript )  - 30K - 45K!", "description": "VICOSYS is seeking a passionate, detail-oriented Full Stack Drupal Developer\u00a0with a strong understanding of modern web application tools and best practices to join our team.\n\nWHAT YOU'LL BE DOING:\n\nDesign, Develop and Support PHP or Drupal based application.\nGather business requirements, perform analysis and work out project prioritization\n\nWHO WE ARE LOOKING FOR:\n\n1+ years of software engineering experience\n\u00a0Solid experience with application development using PHP or Drupal\nExperience with RESTful web services, HTML, CSS, Javascript & Responsive design\nSolid problem-solving capacity with an outcome focus\nSelf-motivated and responsible\nCandidate with less experience will also be considered", "employment_types": ["Full Time", "Permanent"], "selling_points": ["Full-stack development using JAVA, React , Angular", "Expending team. Friendly working envrioment", "5 days work, permanent job with bonus"], "locations": ["Not Specified"], "categories": ["Information Technology (IT)", "Application Specialist - Software", "IT - Webmaster / SEO", "Software Development"], "post_time": "2021-12-30T07:37:00Z", "salary": {"currency": null, "max": null, "min": null, "period": "monthly", "term": null}, "salary_visible": false, "title_keywords": ["developer"], "responsibilities": ["software", "analysis", "design", "develop", "application development"], "requirements": {"degrees": [], "majors": [], "languages": [], "language_level": [], "hard_skills": ["web", "php", "analysis", "problem-solving", "html", "javascript", "css", "focus", "web services"], "soft_skills": ["passionate", "self-motivated", "responsible", "problem-solving", "detail-oriented", "focus", "responsive"], "languages_combined": []}, "experience_required": {"duration": ["1+ years"], "field": ["application development", "engineering", "design"]}}, {"job_id": "100003008997269", "location_code": "hk", "company": "Simatelex Manufactory Co., Ltd.", "job_title": "Analyst Programmer", "description": "Responsibilities\n\n\nAnalyze user requirements, perform feasibility studies and impact analysis\nPerform technical design, development, unit testing and development integration testing to deliver high performance, scalable, flexible and reliable software systems\nProduce high quality deliverables based on thorough understanding of business requirements\n\nQualifications\n\nProficiency on JAVA software development\u00a0\nExperienced in SpringBoot, Spring MVC, JavaScript, Angular, React, Oracle, SQL, Linux\nPassionate about learning new technology and producing quality and efficient software\nGood command of written and spoken English and Cantonese\nTo apply online, \u00a0please click the Apply button below. For a confidential discussion about this role please contact us on +852 2391 2813.\n\n\n\nPersonal data collected will be used for recruitment purposes only.", "employment_types": ["Full Time", "Permanent"], "selling_points": [], "locations": ["Aberdeen"], "categories": ["Information Technology (IT)", "Application Specialist - Software", "IT - Webmaster / SEO", "Software Development"], "post_time": "2021-12-28T02:01:03Z", "salary": {"currency": null, "max": null, "min": null, "period": null, "term": null}, "salary_visible": false, "title_keywords": ["analyst programmer"], "responsibilities": ["software", "analysis", "systems", "quality", "design", "testing", "recruitment", "contact", "personal data"], "requirements": {"degrees": [], "majors": [], "languages": ["cantonese", "english"], "language_level": ["good command"], "hard_skills": ["linux", "java", "react", "analysis", "sql", "javascript", "spring", "angular", "integration", "oracle"], "soft_skills": ["flexible", "efficient", "learning", "thorough", "reliable", "passionate about"], "languages_combined": [{"language": "cantonese", "language_level": ["good command"]}, {"language": "english", "language_level": ["good command"]}]}, "experience_required": {"duration": [], "field": []}}, {"job_id": "100003009009070", "location_code": "hk", "company": "TY Property HK Limited", "job_title": "(Part Time) Digital Marketing Assistant", "description": "Job Description:\n\n\n2-3 days a week\u00a0\nWork Location : Lai Chi Kok\n\nResponsibilities:\n\nMainly focus on digital platform (Facebook, Instagram,\u00a0etc.)\nCreate social media content\nCreate graphic design for\u00a0social media\nProficient in design related software, such as AI, Photoshop, etc.\u00a0\n\nYou can find more information about our company: http://ty-property.com\n\nInterested parties please send your resume with expected salary by clicking \"Apply Now\".\u00a0\u00a0", "employment_types": ["Part Time"], "selling_points": ["2-3 days work a week", "Create graphic design for multimedia & layouts", "Manage social media (Facebook/Instagram)"], "locations": ["Lai Chi Kok"], "categories": ["Design", "Graphics", "Information Technology (IT)", "IT - Webmaster / SEO", "Marketing / Public Relations", "Digital Marketing"], "post_time": "2021-12-30T10:03:55Z", "salary": {"currency": null, "max": null, "min": null, "period": "monthly", "term": null}, "salary_visible": false, "title_keywords": ["digital marketing", "assistant"], "responsibilities": [], "requirements": {"degrees": [], "majors": [], "languages": [], "language_level": [], "hard_skills": [], "soft_skills": [], "languages_combined": []}, "experience_required": {"duration": [], "field": []}}, {"job_id": "100003009002691", "location_code": "hk", "company": "CL Technical Services Ltd.", "job_title": "Application Software Engineer (C#.Net)", "description": "Responsible for handling internal workflow systems, web application development, conducting user requirement studies, conducting user training and providing support for project enquiries.\n\n\nBachelor Degree in Computing Science, Information Technology or related disciplines\n\nExperience in ERP (Enterprise Resource Planning) software and manufacturing\u00a0 industry\u00a0 is an advantage\n\n2-5 years experience in web application development\nCompetence with Python and SQL is a must. Knowledge in Linux, simple Bash scripting, Git, and Windows\n\nExperience in PostgreSQL, MS SQL, MySQL, ASP.NET, C#, PHP programming, Java EE and Django or Flask is an advantage\u00a0\nMVC architecture is preferable\nKnowledge in Chinese Word Processing is preferable\nStrong analytical, organizational and interpersonal skills\nCandidates with less experience or fresh graduates will also be considered\nWorking location: Wong Chuk Hang (3 minutes' walk from MTR station)\n\nWe offer\u00a0attractive remuneration package including 5-day work, bank holidays, group medical insurance etc to the right candidates. Interested parties please send your full resume including expected salary and date available to Human Resources Department by clicking \"Apply Now\" button.\n\nFor more details, please\u00a0visit our web-site at www.simatelex.com.hk", "employment_types": ["Full Time"], "selling_points": ["Hands-on experience in ASP.NET, SQL, etc.", "Flexible working hours", "Young and energetic team"], "locations": ["Kowloon Bay"], "categories": ["Information Technology (IT)", "Application Specialist - Software", "IT - Webmaster / SEO", "Software Development"], "post_time": "2021-12-28T06:54:12Z", "salary": {"currency": null, "max": null, "min": null, "period": "monthly", "term": null}, "salary_visible": false, "title_keywords": ["software engineer"], "responsibilities": ["user requirement", "software", "systems", "providing support", "application development", "architecture", "planning"], "requirements": {"degrees": ["degree", "bachelor"], "majors": ["related disciplines", "science", "information technology"], "languages": ["chinese"], "language_level": [], "hard_skills": ["simple", "linux", "java", "git", "web application development", "chinese word processing", "php", "erp", "bash", "sql", "programming", "python", "ms sql", "c#"], "soft_skills": ["organizational", "interpersonal skills", "responsible"], "languages_combined": [{"language": "chinese", "language_level": []}]}, "experience_required": {"duration": ["2-5 years"], "field": ["sql", "application development", "manufacturing", "planning"]}}, {"job_id": "100003008994336", "location_code": "hk", "company": "Get Clicks Limited", "job_title": "SEO Specialist (Junior)", "description": "We are now looking for an experience website manager to help manage our various websites from different entities and business lines as we look to revamp and redesign our current sites to maximise our branding, information sharing and user experience.\u00a0\n\nResponsibilities:\n\nPlan, implement, manage and upgrade web properties\nAssist and drive improvement and design of current webpages\u00a0\nSupport updates and manage new web pages and content uploads\nImprove overall site experience, conversion and engagement metrics as required\u00a0\nEnsure that the website is protected by enabling the appropriate security measures\nEnsure website quality and efficiency by conducting regular test plans\nCollaborate with all staff and management to ensure that the website aligns with brand strategy and meets the organisation\u2019s standards\nKeep up-to-date with industry best practices and monitor competitor websites\nImplement and work with marketing team if required to best optimise website and marketing campaigns\u00a0\n\nRequirements\u00a0\n\n3+\u00a0 years of work experience as a website manager or building / designing websites\u00a0\nHas experience with Wordpress, HTML, CSS, and JavaScript\nAbility to troubleshoot website issues in a fast-paced environment\nStrong attention to detail with an analytical mind and problem-solving skills\nExpertise with Digital marketing, Google analytics, HotJar, Optimize tooling, testing tools will all be good to have\u00a0\u00a0", "employment_types": ["Full Time"], "selling_points": [], "locations": ["Sheung Wan"], "categories": ["Information Technology (IT)", "IT - Webmaster / SEO", "Marketing / Public Relations", "Marketing - Marketing Communication", "Digital Marketing"], "post_time": "2021-12-23T00:23:21Z", "salary": {"currency": "HKD", "max": 24999, "min": 14000, "period": "monthly", "term": null}, "salary_visible": true, "title_keywords": ["specialist", "junior"], "responsibilities": ["collaborate with", "management", "quality", "website", "design", "monitor", "plan", "marketing campaigns", "plans"], "requirements": {"degrees": [], "majors": [], "languages": [], "language_level": [], "hard_skills": ["google analytics", "css", "html", "wordpress", "javascript", "problem-solving skills"], "soft_skills": ["fast-paced environment", "analytical mind", "troubleshoot", "attention to detail", "problem-solving skills"], "languages_combined": []}, "experience_required": {"duration": [], "field": []}}, {"job_id": "100003008993952", "location_code": "hk", "company": "iProspect Hong Kong Limited", "job_title": "Digital Performance Executive (Fresh Graduate Welcome)", "description": "Get Clicks is an SEO company located in Hong Kong that helps businesses based in Asia and Europe, to improve their visibility in search engines.\n\nGet Clicks is looking for a Junior SEO Specialist,\u00a0fluent in English and Cantonese.\n\nMain duties:\n\nConducting SEO audits.\nPerform keyword research and content optimizations.\nAssist the clients to help them to implement the necessary changes.\nDrive bloggers outreach and link-building projects.\nWork\u00a0with copywriters and define content marketing roadmaps.\nSkills:\n\nMust be fluent in English and Cantonese.\nBeing fluent in Mandarin would be a plus.\nMinimum 1 years SEO experience.\nExcellent communication skills (oral/written).\nA good understanding of the main SEO tools like Google Keyword planner, Search Console, SEMrush (or similar), Screaming Frog (or similar) Ahrefs and Majestic.\nProactive, can-do attitude and willing to learn.\nBenefits:\n\n5 working days\nMPF\nFlexible working hours and location\nMedical insurance (for full-time employees)\n15 paid leaves (for full-time employees)\nTo know more about our company, please visit Get Clicks.", "employment_types": ["Full Time", "Permanent"], "selling_points": ["5 days work", "excellent working environment", "Fresh Graduates are welcome"], "locations": ["Quarry Bay"], "categories": ["Media & Advertising", "Account Servicing", "Information Technology (IT)", "IT - Webmaster / SEO", "Marketing / Public Relations", "Marketing - Market Research"], "post_time": "2021-12-22T09:53:56Z", "salary": {"currency": null, "max": null, "min": null, "period": "monthly", "term": null}, "salary_visible": false, "title_keywords": ["performance executive"], "responsibilities": ["audits", "seo", "communication"], "requirements": {"degrees": [], "majors": [], "languages": ["cantonese", "english", "mandarin"], "language_level": ["fluent"], "hard_skills": ["planner", "plus", "seo"], "soft_skills": ["communication skills", "oral", "can-do attitude", "willing to learn", "proactive"], "languages_combined": [{"language": "cantonese", "language_level": []}, {"language": "english", "language_level": []}, {"language": "mandarin", "language_level": ["fluent"]}]}, "experience_required": {"duration": ["minimum 1 years"], "field": []}}, {"job_id": "100003008988767", "location_code": "hk", "company": "Hong Kong Adventist College", "job_title": "IT TECHNICIAN", "description": "Responsibilities\n\nPerformance Marketing Expertise\n\nDevelop a solid knowledge across SEM, SEO, Display, Social Media and Affiliates by attending training, obtaining relevant qualification and keeping up to date with industry news and developments\n\nContribute in developing new products and ways of working that improve Performance results\n\nCampaign / Project Management\n\nFulfil relevant daily, weekly, monthly and quarterly tasks (see Authority Matrix) ensuring\u00a0that all campaigns are executed to plan and meet the targets\nWork with your Digital Performance Manager to ensure that:\ncampaigns / projects timelines, cost estimates, schedules and forecasts are accurately developed and adhered to\ncampaigns are set up and optimized in the correct way, according to brief and\nSearch Best Practice\nbudgets are spent within daily / monthly limits and are correctly reconciled at the\u00a0end of each month\ncampaigns are monitored daily and hit relevant targets\neach search query for the relevant campaign is served with maximum level of relevancy (copy and landing page)\nreports and presentations are delivered to the highest level of quality and integrity\nObtain client approval of search briefs and schedules prior to campaign launches\nHelp in preparing performance review presentations\nProvide regular results analysis, reporting and recommendations\nUnder the guidance of manager, develop and distribute accurate contact reports from\u00a0meetings and conversations\nKeep clients and account team updated on the status of account activities\nHave input in developing short and long term search strategies for the client\nExcellence in Client Service and effectively manage client expectations\n\n\u00a0Requirements\n\nUniversity graduate\nShould demonstrate passion for Digital Marketing\nCommunicates effectively at all levels, both up and down\nStrong numerical skills and attention to detail\nAble to work in high pressure environment and resolve client issues\nAble to work collaboratively across teams\nAnalytical and strategic\nWorking knowledge of Excel, Word and Power Point\n\nWe offer 5 days work and attractive compensation package to suitable candidates. Interested parties, please send your full resume including your present & expected salary by using \"Quick Apply\".\n\nPlease note that only short-listed applicants will be notified. All information provided will be treated in strictly confidential and used solely for recruitment purpose.\n\n%MCEPASTEBIN%", "employment_types": ["Full Time", "Permanent"], "selling_points": ["Bachelor\u2019s degree in information technology", "To develop and maintain the school's website", "To provide day-to-day technical support"], "locations": ["Not Specified"], "categories": ["Information Technology (IT)", "IT - Webmaster / SEO", "Support", "Network & System"], "post_time": "2021-12-21T03:44:36Z", "salary": {"currency": null, "max": null, "min": null, "period": "monthly", "term": null}, "salary_visible": false, "title_keywords": ["it technician"], "responsibilities": ["social media", "cost", "budgets", "seo", "reporting", "guidance", "schedules", "analysis", "review", "quality", "developing", "presentations", "develop", "project management", "reports", "contact", "sem", "plan"], "requirements": {"degrees": ["university graduate"], "majors": [], "languages": [], "language_level": [], "hard_skills": ["power point", "excel", "numerical skills", "word"], "soft_skills": ["attention to detail", "passion for"], "languages_combined": []}, "experience_required": {"duration": [], "field": []}}]