[{"job_id": "100003009054299", "location_code": "hk", "company": "K. Wah International Holdings Ltd", "job_title": "System Analyst", "description": "Job Responsibilities\n\nResponsible for mobile platforms (iOS / Android) and web application software development\nConduct detailed system analysis, problem diagnosis, purpose, develop and implement IT solutions\nPrepare requirement specifications of IT solutions\nMonitor service provision and prepare cases for testing IT solutions\nMaintain system documentation and reports of IT solutions\n\nJob Requirements\n\nDegree / Higher Diploma / Diploma in Computer Science, Computer Engineering or related disciplines\n5 years of working experience, with at least 2 years of hands-on experience in mobile (IOS/Android) and web application programming\nKnowledge of mobile development Java-Android SDK, Objective-C / SwiftUI\nKnowledge of web development WAMP, HTML JavaScript, CSS, JSON and PHP\nKnowledge of mobile cross-platform development VueJS, React or Flutter is in advance\nPassionate about mobile & web application development, cloud platforms (e.g. AWS, GC) and new technologies\nGood analytical and problem-solving skills\nWell organized, disciplined and responsible with a good work ethic\nAble to work independently and be self-driven to meet project schedules\nA self-motivated team player with good interpersonal and communication skills\nA good team player\nInterested parties please send resume with salary expectation and availability to\u00a0Human Resources Department, K. Wah International Holdings Limited, 29/F, K. Wah Centre, 191 Java Rd., North Point, H.K.\u00a0or by clicking\u00a0Apply Now\u00a0.\n\nAll Personal data collected will be used for recruitment purpose only. All applications will be retained for a maximum period of 2 years and may be considered for other suitable positions within the Group.\n\n", "employment_types": ["Full Time", "Permanent"], "selling_points": ["Web application programming", "Mobile platforms (iOS / Android)", "Cross-platform development"], "locations": ["North Point"], "categories": ["Information Technology (IT)", "Application Specialist - Software", "Software Development", "Mobile / Wireless Communications"], "post_time": "2022-01-17T09:05:23Z", "salary": {"currency": null, "max": null, "min": null, "period": "monthly", "term": null}, "salary_visible": false, "title_keywords": ["system analyst"], "responsibilities": ["software", "system documentation", "analysis", "monitor", "develop", "testing", "specifications", "maintain", "reports"], "requirements": {"degrees": ["diploma", "degree"], "majors": ["related disciplines", "computer engineering", "computer science"], "languages": [], "language_level": [], "hard_skills": ["java", "web development", "web application development", "web", "android sdk", "php", "react", "problem-solving skills", "html", "objective-c", "aws", "mobile", "javascript", "programming", "css", "android"], "soft_skills": ["communication skills", "work independently", "self-motivated", "good team player", "responsible", "well organized", "hands-on", "work ethic", "problem-solving skills", "team player", "interpersonal", "driven", "passionate about"], "languages_combined": []}, "experience_required": {"duration": ["5 years", "at least 2 years"], "field": ["programming"]}}, {"job_id": "100003009054812", "location_code": "hk", "company": "EY Mtel Solutions Limited", "job_title": "Mobile Application Developer (iOS / Android / React Native)", "description": "Our client is a well-known and fast expanding IT solution provider and now looking for high calibre to join their group.\n\nResponsibilities:\n\n\nDevelop and maintain and test mobile application\nResponsible for system design and development process and progress\nCollaborate with the team to deliver the services on time and meet the milestones\nCommunicate with project manager and clients to gather meaningful requirement\nAnalyze requirement and assign tasks to colleagues in order the meet the schedule\nRequirements:\n\nDegree in Computer Science or other related disciplines\nJava programming / Objective-C programming skills\nSensitive to technologies in mobile industry\nExperience on Kotlin programming is a plus\nPassionate in the development in Internet and Mobile\nGood communication & interpersonal skills\n\nTo apply, please send your detailed resume to travis[at]connersconsulting[dot]com or contact Travis Poon at 3460 2011 for a confidential discussion.\n\nOnly shortlisted candidates will be notified.\n\nApplicants who are not contacted within two weeks may consider their applications unsuccessful.\n\nAll data collected will be used for recruitment purpose only & will be used strictly confidential.\n\nConners Consulting Limited\n2005 Kai Tak Commercial Building 317 Des Voeux Road Central Hong Kong\nTel: (852) 3996 8090\nWebsite:\u00a0www.connersconsulting.com\n\n\n", "employment_types": ["Full Time", "Permanent"], "selling_points": ["Develop and maintain cool mobile applications", "Work with a great team, for great brands", "Apply latest mobile technologies and techniques"], "locations": ["Kwun Tong"], "categories": ["Information Technology (IT)", "Software Development", "Technical / Functional Consulting", "Mobile / Wireless Communications"], "post_time": "2022-01-17T11:16:09Z", "salary": {"currency": null, "max": null, "min": null, "period": "monthly", "term": null}, "salary_visible": false, "title_keywords": ["developer"], "responsibilities": ["collaborate with", "communicate with", "assign tasks", "develop", "maintain", "system design", "schedule"], "requirements": {"degrees": ["degree"], "majors": ["related disciplines", "computer science"], "languages": [], "language_level": [], "hard_skills": ["java", "plus", "objective-c", "mobile", "programming", "kotlin"], "soft_skills": ["passionate", "communication", "sensitive to", "interpersonal skills", "detailed"], "languages_combined": []}, "experience_required": {"duration": [], "field": ["programming"]}}, {"job_id": "100003009052237", "location_code": "hk", "company": "ORIENTAL HUMAN RESOURCES LIMITED", "job_title": "Mobile App Developer (Android / iOS)", "description": "Responsibilities:\n\nDevelop new mobile apps (iOS / Android / React Native)\nMaintain and enhance existing apps\nTroubleshoot and debug\nCollaborate with project managers, UX designers, backend developers and quality assurance to deliver client projects\n\nRequirements:\n\n\nTo qualify for the role you must have:\n\nHigher Diploma or Degree in Computer Science / IT or related disciplines\nGood communication and interpersonal skills\nResponsible and able to work under pressure\nProficiency in Objective-C / Swift / Java / Kotlin\nSolid experience in iOS / Android development\nKnowledge on cross platform development is an advantage\n1 - 2 year experience in mobile app development (Fresh graduates are also welcome)\n\nWhat working at EY offers:\n\nSupport, coaching and feedback from some of the most engaging colleagues around\nOpportunities to develop new skills and progress your career\nThe freedom and flexibility to handle your role in a way that\u2019s right for you\n\nIf you can confidently demonstrate that you meet the criteria above, please contact us as soon as possible.\n\nJoin us in building a better working world.\n\nApply now.", "employment_types": ["Full Time", "Permanent"], "selling_points": [], "locations": ["Tai Po Area"], "categories": ["Information Technology (IT)", "Application Specialist - Software", "Software Development", "Mobile / Wireless Communications"], "post_time": "2022-01-17T02:31:41Z", "salary": {"currency": null, "max": null, "min": null, "period": "monthly", "term": null}, "salary_visible": false, "title_keywords": ["developer"], "responsibilities": ["collaborate with", "quality", "develop", "maintain", "troubleshoot"], "requirements": {"degrees": ["diploma", "degree"], "majors": ["related disciplines", "it", "computer science"], "languages": [], "language_level": [], "hard_skills": ["android development", "java", "objective-c", "mobile", "swift", "kotlin"], "soft_skills": ["communication and interpersonal skills", "responsible", "work under pressure"], "languages_combined": []}, "experience_required": {"duration": ["1 - 2 year"], "field": ["development"]}}, {"job_id": "100003009053268", "location_code": "hk", "company": "Centaline Data Technology Limited", "job_title": "Programmer / Senior Programmer  (5-day Work)", "description": "Responsibilities\n\nDevelop and maintain portal sites and web applications for finance and stock market\u00a0\nDesign and develop mobile applications by usingHTML5/React app platform\nAnalyze the user requirements and related documentation\n\nRequirements\n\nDegree holder or above major in Computer Science or equivalent\u00a0\nAt least 2-3 years working experiences in mobile development\nExperience on development using Java technologies, such as JSP, JSF, MVC frameworks, Spring, Hibernate\nExperience with front-end JavaScript, JQuery and CSS, Ajax\u00a0\nExperience in mobile device software development, developing equities and financial software will be an advantage\u00a0\nGood communication skills in both English and Chinese\u00a0\nTeam player and self-motivated\nGood analytical and problem-solving skills\u00a0\nAble to work under pressure and able to meet tight deadlines\nLess experiences will be considered as Developer\n\nWe Offer\n\n5-day work week\nDiscretionary Bonus\nMedical Insurance\nVariety of Leaves (e.g. Birthday, Marriage Leave etc.)\nVariety of company activities and training\n\nTo Apply:\nWe offer attractive package including medical insurance scheme and good career prospects to the right candidate. Interested parties please send your application via \"Apply Now\" button.\n\nFor more Company information, please feel free to visit our website at www.infocast.com.hk.\n\nAll information received will be kept in strict confidential and only for employment-related purposes.", "employment_types": ["Full Time", "Permanent"], "selling_points": ["API development and application system developme", "SQL optimization / On-job training", "Quarterly Bonus / Medical / Education Allowance"], "locations": ["Tsim Sha Tsui"], "categories": ["Information Technology (IT)", "IT - Webmaster / SEO", "Mobile / Wireless Communications", "Data Scientist"], "post_time": "2022-01-17T06:37:11Z", "salary": {"currency": null, "max": null, "min": null, "period": "monthly", "term": null}, "salary_visible": false, "title_keywords": ["programmer", "senior programmer"], "responsibilities": ["maintain", "design and develop", "related documentation", "develop"], "requirements": {"degrees": ["degree holder"], "majors": ["computer science"], "languages": ["english", "chinese"], "language_level": ["good"], "hard_skills": ["java", "hibernate", "mobile device", "problem-solving skills", "jquery", "jsf", "mobile", "javascript", "spring", "ajax", "css"], "soft_skills": ["communication skills", "self-motivated", "meet tight deadlines", "problem-solving skills", "team player", "work under pressure"], "languages_combined": [{"language": "english", "language_level": ["good"]}, {"language": "chinese", "language_level": ["good"]}]}, "experience_required": {"duration": ["at least 2-3 years"], "field": ["development", "developing", "software development", "developer", "financial"]}}, {"job_id": "100003009054393", "location_code": "hk", "company": "Virtual Gaming Technology Limited", "job_title": "Analyst Programmer / Senior Analyst Programmer (Flutter/React Native/iOS/Android)", "description": "Let there be CHANGE\n\nReady to fast-track your career? Ready to solve complex problems? Advance your skills? Deliver next-generation technology solutions? Join Accenture and help transform leading organizations and communities around the world. Working in highly collaborative teams for world-leading clients, we\u2019ll nurture your talent in an inclusive\n\nYour career is about what you want to be and who you want to be. It\u2019s about bringing your skills, your curiosity and your best true self to your work.\n\nHere, you\u2019ll match your ingenuity with the latest technology to make incredible things.\u00a0Let\u2019s create something together.\n\nYou can enjoy:\n\nComprehensive Medical (24-hour worldwide) coverage, including your spouse/ life partner and children!\nDental insurance, Life insurance, Total and perm disability, accidental death & dismemberment insurance!\nVision care benefits, Health check, Housing benefits!\nPurchase of Accenture stocks at attractive discount!\nReimbursement of Professional Membership costs\nProfessional training and career advancement opportunities!\nValuable project exposure for different technologies and industry domains!\n\nWhen you work with us, change\u00a0becomes the most dynamic, powerful source of progress you have!\n\n\n\nJob duties of this Role:\n\nInvolve in project implementation, business requirements analysis, business process design, SAP system design and configuration, system testing and user training and go-live support\nGathering user requirement, translating functional document into technical specification\nAbility to analyze business problems and provide technical advice\n\n\u00a0Come JOIN US if you have:\n\nDegree in Computer Science, Information Technology, Finance or related disciplines\nAt least 2 years hands-on experience and 1 full cycle in SAP Projects Implementation (FI, CO/ SD Modules)\nExperience in business requirements analysis, business process design, SAP system design and configuration, system testing and user training and go-live support\nSAP Certification in FI, CO, SD Modules, SuccessFactor / SAP HANA / C/4HANA experience will be an advantage\nIndependent, self-motivated and able to work under pressure\nGood command of English and Mandarin", "employment_types": ["Full Time", "Permanent", "Contract"], "selling_points": ["Passionate & willing to learn new tech", "Flexible working hours & work-life balance", "Free snacks & drinks"], "locations": ["Tsim Sha Tsui"], "categories": ["Information Technology (IT)", "Software Development", "Mobile / Wireless Communications"], "post_time": "2022-01-17T09:21:20Z", "salary": {"currency": null, "max": null, "min": null, "period": "monthly", "term": null}, "salary_visible": false, "title_keywords": ["analyst programmer", "senior analyst programmer"], "responsibilities": ["insurance", "teams"], "requirements": {"degrees": [], "majors": [], "languages": [], "language_level": [], "hard_skills": ["make"], "soft_skills": ["comprehensive", "collaborative"], "languages_combined": []}, "experience_required": {"duration": [], "field": []}}, {"job_id": "100003009055633", "location_code": "hk", "company": "Conners Consulting Limited", "job_title": "Mobile App Developer", "description": "Our client is a well-known and fast expanding IT solution provider and now looking for high calibre to join their group.\n\nResponsibilities:\n\n\nDevelop and maintain and test mobile application\nResponsible for system design and development process and progress\nCollaborate with the team to deliver the services on time and meet the milestones\nCommunicate with project manager and clients to gather meaningful requirement\nAnalyze requirement and assign tasks to colleagues in order the meet the schedule\nRequirements:\n\nDegree in Computer Science or other related disciplines\nJava programming / Objective-C programming skills\nSensitive to technologies in mobile industry\nExperience on Kotlin programming is a plus\nPassionate in the development in Internet and Mobile\nGood communication & interpersonal skills\n\nTo apply, please send your detailed resume to travis[at]connersconsulting[dot]com or contact Travis Poon at 3460 2011 for a confidential discussion.\n\nOnly shortlisted candidates will be notified.\n\nApplicants who are not contacted within two weeks may consider their applications unsuccessful.\n\nAll data collected will be used for recruitment purpose only & will be used strictly confidential.\n\nConners Consulting Limited\n2005 Kai Tak Commercial Building 317 Des Voeux Road Central Hong Kong\nTel: (852) 3996 8090\nWebsite:\u00a0www.connersconsulting.com\n\n\n", "employment_types": ["Full Time", "Permanent"], "selling_points": ["iOS or Android App developing", "Design and development of mobile App", "Java / Objective-C / Kotlin exposure"], "locations": ["Hung Hom"], "categories": ["Information Technology (IT)", "Software Development", "Mobile / Wireless Communications"], "post_time": "2022-01-18T02:48:51Z", "salary": {"currency": null, "max": null, "min": null, "period": "monthly", "term": null}, "salary_visible": false, "title_keywords": ["developer"], "responsibilities": ["collaborate with", "communicate with", "assign tasks", "develop", "maintain", "system design", "schedule"], "requirements": {"degrees": ["degree"], "majors": ["related disciplines", "computer science"], "languages": [], "language_level": [], "hard_skills": ["java", "plus", "objective-c", "mobile", "programming", "kotlin"], "soft_skills": ["passionate", "communication", "sensitive to", "interpersonal skills", "detailed"], "languages_combined": []}, "experience_required": {"duration": [], "field": ["programming"]}}, {"job_id": "100003009055264", "location_code": "hk", "company": "Infocast Limited", "job_title": "Analyst Developer (Hybrid Mobile Development)", "description": "Responsibilities\n\nDevelop and maintain portal sites and web applications for finance and stock market\u00a0\nDesign and develop mobile applications by usingHTML5/React app platform\nAnalyze the user requirements and related documentation\n\nRequirements\n\nDegree holder or above major in Computer Science or equivalent\u00a0\nAt least 2-3 years working experiences in mobile development\nExperience on development using Java technologies, such as JSP, JSF, MVC frameworks, Spring, Hibernate\nExperience with front-end JavaScript, JQuery and CSS, Ajax\u00a0\nExperience in mobile device software development, developing equities and financial software will be an advantage\u00a0\nGood communication skills in both English and Chinese\u00a0\nTeam player and self-motivated\nGood analytical and problem-solving skills\u00a0\nAble to work under pressure and able to meet tight deadlines\nLess experiences will be considered as Developer\n\nWe Offer\n\n5-day work week\nDiscretionary Bonus\nMedical Insurance\nVariety of Leaves (e.g. Birthday, Marriage Leave etc.)\nVariety of company activities and training\n\nTo Apply:\nWe offer attractive package including medical insurance scheme and good career prospects to the right candidate. Interested parties please send your application via \"Apply Now\" button.\n\nFor more Company information, please feel free to visit our website at www.infocast.com.hk.\n\nAll information received will be kept in strict confidential and only for employment-related purposes.", "employment_types": ["Full Time", "Permanent"], "selling_points": ["Java, JavaScript, mobile app", "Develop finance & stock market portal sites", "5 Days work week"], "locations": ["Hung Hom"], "categories": ["Information Technology (IT)", "Application Specialist - Software", "Mobile / Wireless Communications"], "post_time": "2022-01-18T01:58:25Z", "salary": {"currency": null, "max": null, "min": null, "period": "monthly", "term": null}, "salary_visible": false, "title_keywords": ["developer", "analyst"], "responsibilities": ["maintain", "design and develop", "related documentation", "develop"], "requirements": {"degrees": ["degree holder"], "majors": ["computer science"], "languages": ["english", "chinese"], "language_level": ["good"], "hard_skills": ["java", "hibernate", "mobile device", "problem-solving skills", "jquery", "jsf", "mobile", "javascript", "spring", "ajax", "css"], "soft_skills": ["communication skills", "self-motivated", "meet tight deadlines", "problem-solving skills", "team player", "work under pressure"], "languages_combined": [{"language": "english", "language_level": ["good"]}, {"language": "chinese", "language_level": ["good"]}]}, "experience_required": {"duration": ["at least 2-3 years"], "field": ["development", "developing", "software development", "developer", "financial"]}}, {"job_id": "100003009054511", "location_code": "hk", "company": "Hong Kong Education City Limited", "job_title": "Software Engineer / Analyst Programmer / Web Application Developer", "description": "Job Duty:\n\nWork and interact with software developers, test engineers, and systems admins to understand the whole software development lifecycle\nDefine DevOps framework based on industrial best practices\nParticipate in project planning\nProvision DevOps tooling\nSetup and maintain CI/CD pipelines\nMakes changes to methods and designs where necessary\nCreate documentation for DevOps tooling and process\nProvide DevOps guidance to developers, test engineers and system admins Write up automation test script\n\nKey Competencies & Experience Requirement:\n\n3 years of experience in software engineering or IT operations\nHands on experience on using below tools:\nPublic cloud platform: AWS/Azure/GCP\nContainerization: Kubernetes/Helm\nGit repository: e.g. GitHub/GitLab/BitBucket\nOrchestration tools: e.g. Jenkins/CircleCI/TeamCity\nArtifact Repository: Nexus/Artifactory\nConfiguration Management tools: e.g. Puppet/Chef/Ansible\nApplication Release Automation tools: e.g. XL Deploy/CA Nolio\nExperience with BDD test automation development is preferable\nExperience with agile software development is preferable\nStrong communication skills, both verbal and written\nStrong initiative, and a desire to lear\nCandidate with more experience will be considered Specialist and Assistant Manager", "employment_types": ["Full Time"], "selling_points": ["5-day workweek and happy & friendly environment", "14-21 days AL, medical, dental & life insurance", "Competitive pay, Incentive Pay & MPFVC"], "locations": ["Shatin Area"], "categories": ["Information Technology (IT)", "Application Specialist - Software", "Software Development", "Mobile / Wireless Communications"], "post_time": "2022-01-17T09:50:03Z", "salary": {"currency": null, "max": null, "min": null, "period": "monthly", "term": null}, "salary_visible": false, "title_keywords": ["software engineer", "developer", "analyst programmer"], "responsibilities": ["guidance", "project planning", "management", "software", "configuration", "operations", "systems", "communication", "maintain", "deploy", "documentation", "setup"], "requirements": {"degrees": [], "majors": [], "languages": [], "language_level": [], "hard_skills": ["git", "azure", "jenkins", "xl", "agile", "pipelines", "devops", "aws", "ansible", "documentation"], "soft_skills": ["initiative", "communication skills", "hands on", "agile"], "languages_combined": []}, "experience_required": {"duration": ["3 years"], "field": ["development", "engineering", "it operations", "software development"]}}, {"job_id": "100003009052733", "location_code": "hk", "company": "Quality HealthCare Medical Services Ltd", "job_title": "Application Specialist / Lead (System Analyst) - Web & Mobile", "description": "Job Duty:\n\nWork and interact with software developers, test engineers, and systems admins to understand the whole software development lifecycle\nDefine DevOps framework based on industrial best practices\nParticipate in project planning\nProvision DevOps tooling\nSetup and maintain CI/CD pipelines\nMakes changes to methods and designs where necessary\nCreate documentation for DevOps tooling and process\nProvide DevOps guidance to developers, test engineers and system admins Write up automation test script\n\nKey Competencies & Experience Requirement:\n\n2 years of experience in software engineering or IT operations\nHands on experience on using below tools:\nPublic cloud platform: AWS/Azure/GCP or\nContainerization: Kubernetes/Helm or\u00a0\nGit repository: e.g. GitHub/GitLab/BitBucket or\u00a0\nOrchestration tools: e.g. Jenkins/CircleCI/TeamCity or\u00a0\nArtifact Repository: Nexus/Artifactory or\u00a0\nConfiguration Management tools: e.g. Puppet/Chef/Ansible or\u00a0\nApplication Release Automation tools: e.g. XL Deploy/CA Nolio\nExperience with BDD test automation development is preferable\nExperience with agile software development is preferable\nStrong communication skills, both verbal and written\nStrong initiative, and a desire to lear\nCandidate with more experience will be considered Specialist and Assistant Manager", "employment_types": ["Full Time", "Permanent"], "selling_points": ["Performing system and database design", "Coding and development for project", "System enhancement to meet business goals"], "locations": ["Kowloon Bay"], "categories": ["Information Technology (IT)", "Application Specialist - Software", "IT Project Management / Team Lead", "Mobile / Wireless Communications"], "post_time": "2022-01-17T03:52:03Z", "salary": {"currency": null, "max": null, "min": null, "period": "monthly", "term": null}, "salary_visible": false, "title_keywords": ["system analyst", "lead", "application specialist"], "responsibilities": ["guidance", "project planning", "management", "software", "configuration", "operations", "systems", "communication", "maintain", "deploy", "documentation", "setup"], "requirements": {"degrees": [], "majors": [], "languages": [], "language_level": [], "hard_skills": ["git", "azure", "jenkins", "xl", "agile", "pipelines", "devops", "aws", "ansible", "documentation"], "soft_skills": ["initiative", "communication skills", "hands on", "agile"], "languages_combined": []}, "experience_required": {"duration": ["2 years"], "field": ["development", "engineering", "it operations", "software development"]}}, {"job_id": "100003009055717", "location_code": "hk", "company": "Gravitas Recruitment Group", "job_title": "IT Business Analyst Up to 40k", "description": "Responsibilities:\n\n* Guide and mentor business analysts to plan requirement gathering activities/approach and achieve expected outcomes\n\n* Support project manager and scrum master to plan releases and sprints - Identify dependencies between systems, requirements and sprint outcomes\n\n* Help testing team to define a minimum viable scope across multiple systems that can be tested incrementally\n\n* Work with business leads to plan for business team resource allocation and gather support needed for the project\n\n* Ensure change requests are very minimum during later testing phases by ensuring coverage during initial scoping and requirement stages\n\n* Expected to perform hands on work for some critical and complex requirements\n\nEducation & Experience:\n\n* Around 5 years of experience in Business Analyst Role\n\n* Experience working in building or maintaining or integrating with insurance policy admin systems\n\n* Work experience and broad knowledge of digital applications and backend systems in an insurance organization\n\n* Experience leading or managing a team of business analysts\n\n* Good knowledge of insurance products.\n\n* Proven experience of multi-vendor environment and cross functional teams\n\n* Expert knowledge of complex and interdependent projects and continuous improvement methodologies, techniques, tools and controls\n\n*Agile methodology and ways of working experience\n\n* Worked on investment project is a PLUS\n\nWhat you will get in return:\n\n-Global leading Insurance Company\n\n-Opportunities to work on Large Scale Projects\n\nWe Offer You a competitive total rewards package, continuing education & training, and tremendous potential with a growing worldwide organisation. Please send an updated CV to P.chan@gravitasgroup.com for immediate consideration.", "employment_types": ["Full Time", "Permanent"], "selling_points": ["Life Insurance", "Business Analyst", "Digital Transformation"], "locations": ["Not Specified"], "categories": ["Information Technology (IT)", "IT Project Management / Team Lead", "IT Management", "Mobile / Wireless Communications"], "post_time": "2022-01-18T02:52:57Z", "salary": {"currency": "HKD", "max": 10999, "min": 0, "period": "monthly", "term": null}, "salary_visible": true, "title_keywords": ["business analyst"], "responsibilities": ["maintaining", "systems", "teams", "testing", "plan", "managing a team", "insurance"], "requirements": {"degrees": ["master"], "majors": [], "languages": [], "language_level": [], "hard_skills": ["plus", "vendor", "agile"], "soft_skills": ["hands on", "agile"], "languages_combined": []}, "experience_required": {"duration": ["5 years"], "field": ["education", "admin", "business", "digital", "managing a team", "insurance"]}}, {"job_id": "100003009050423", "location_code": "hk", "company": "SmarTone Telecommunications Limited", "job_title": "Senior Engineer, Cloud Virtualization", "description": "\u00a0Responsibilities:\u00a0\n\nDevise the strategy on Cloud Infrastructure deployment in mobile infrastructure as well as associated cloud application under 5G\nDefine the best practice for Cloud Infrastructure engineering against NFV/SDN\nPlan and execute the collaboration with the IT environment to facilitate Network Service Orchestration, Network Service Catalogue with OSS/BSS\nProvide robust and scalable technology solutions to enable mobile service applications to scale into private/public cloud\nParticipate in the evaluation of evolved 5G technology to facilitate best services (e.g. Edge Computing)\nPerform network & capacity planning and system dimensioning of Cloud Infrastructure in Core Network\nPerform capacity expansion, acceptance of new platforms, commissioning and deployment of Cloud Infrastructure\nPerform software & hardware upgrade, verification and deployment of Cloud Infrastructure\nResponsible for Ericsson Cloud Infrastructure and handle the CR Job request from internal and external project\nCoordinator of VNF & CNF testing, and provisioning of VNF & CNF support\nSupport of Operation & Maintenance, alarm handling, system fault analysis and hardware fault replacement\nPerform Cloud Infrastructure ECO duty, execute the service restoration task in a timely manner\n\nRequirements:\u00a0\n\nDegree holder in Electronics Engineering / Computer Engineering / Information Technology or related disciplines with at least 5 years in managing a sizeable IP infrastructure\nHands-on TCP/IP Networking experiences in IT/Telecom related field \u2022 Solid experience in Agile / DevOps methodology\nIn-depth knowledge in IP networking, Virtualization, SDN topology and associated technologies such as OpenStack\nProfessional Certification such as CCNP, CISSP or equivalent\nHolder of the following certificates will be advantageous: Google Cloud Architect/ AWS Certified Solutions Architect/ AWS Certified DevOps Engineer/ Certified OpenStack Administrator (COA)\nKnow-how of information security practices and procedures\nWell verse with tools such as Ansible and various scripting techniques\nSystem admin knowledge in Linux and Windows, OS Patch management, Network Management tools and vulnerability scanner\nGood communication and interpersonal skill to collaborate with different system support teams and vendor\nCandidates with less experience may also be considered as Engineer, Cloud Virtualization\n\nInterested parties please apply with full resume stating present and expected salary by clicking \"Apply Now\" or visiting our Website:\u00a0www.smartone.com/tc/about_us/careers/\n\nSmarTone is an equal-opportunity employer. All data supplied will be kept in strict confidence and will be used for employment related purpose. We may transfer such data to any agent, contractor or third party who provides services to us with respect to matters relating to your application. Only short-listed candidates will be contacted.\n\n\nYou are welcome to visit our website : www.smartone.com\u00a0\u00a0", "employment_types": ["Full Time", "Permanent"], "selling_points": ["Cloud Infrastructure engineering in Core Netowork", "Network & capacity planning & system dimensioning", "IP networking, Virtualization, SDN topology"], "locations": ["Kowloon Bay"], "categories": ["Information Technology (IT)", "Security", "Network & System", "Mobile / Wireless Communications"], "post_time": "2022-01-14T10:22:49Z", "salary": {"currency": null, "max": null, "min": null, "period": "monthly", "term": null}, "salary_visible": false, "title_keywords": ["senior engineer"], "responsibilities": ["commissioning", "software", "maintenance", "analysis", "infrastructure", "a timely manner", "testing", "hardware", "plan", "evaluation", "catalogue", "planning"], "requirements": {"degrees": ["degree holder"], "majors": ["related disciplines", "computer engineering", "engineering", "information technology"], "languages": [], "language_level": [], "hard_skills": ["linux", "network management", "agile", "tcp", "devops", "ccnp", "vendor", "aws", "ansible", "ip", "os"], "soft_skills": ["communication", "hands-on", "agile", "interpersonal skill"], "languages_combined": []}, "experience_required": {"duration": [], "field": ["related", "devops", "it"]}}, {"job_id": "100003009041943", "location_code": "hk", "company": "Green Tomato Limited", "job_title": "Project Executive/ Senior Project Executive / Assistant Project Manager", "description": "We are hiring talent like you!\n\nProject Executive is a key member to deliver Projects (Web/Mobile/System) to our clients in an effective manner. He/ She is responsible for monitoring, organizing, and coordinating project activities and ensuring projects are completed on time and on budget.\n\nYou will do the following in this job:\n\nWork with the Business team as a task force to manage a full set of project\nMonitors the progress of project deliveries\nRequirements gathering, analysis to meet clients\u2019 need in a responsive manner\nCoordinates with internal team (technical and design) for the project progression\nSupport system rollout, deployment, and on-going support\n\nWhat Talents we want:\n\nDegree holder\u00a0preferable\u00a0in Business/Marketing/Computer Science or related discipline\nUnderstand mobile and digital service operation\nPractical experience in the mobile or advertising agency industry will be preferred.\nWork experience or assist in preparing user requirement specifications, test plan, and test case would be an advantage\nDetail-minded, good coordination and\u00a0communication skills\nA good team player who is mature and can work\u00a0independently\nCandidates with more experience will be consider as more senior position\u00a0\n\nBenefits we offered:\n\n5-day work week\nBirthday Leave\u00a0\nCompetitive remuneration\nDiscretionary Bonus\nMedical Allowance\nHappy and harmonious working environment\nValuable working experience\n\nWe offer an attractive remuneration package, comprehensive on the job training on new technologies, and excellent career development opportunities to the right candidate.\u00a0\n\nFinal and Most Important Requirement\n\n\"Enjoy What You Do!!\"\u00a0\u00a0\n\nCandidates not contacted within 4 weeks may consider their application for this role unsuccessful. Unless advised otherwise, unsuccessful candidates will be kept on file for future job opportunities. Personal data collected will be used for recruitment-related purposes only and all personal data of applicants will be kept in strict accordance with the Personal Data Privacy Ordinance.\u00a0", "employment_types": ["Full Time", "Permanent"], "selling_points": ["Birthday Leave", "Competitive Remuneration", "Happy and harmonious working environment"], "locations": ["Kwun Tong"], "categories": ["Information Technology (IT)", "IT Project Management / Team Lead", "Software Development", "Mobile / Wireless Communications"], "post_time": "2022-01-12T04:44:42Z", "salary": {"currency": null, "max": null, "min": null, "period": "monthly", "term": null}, "salary_visible": false, "title_keywords": ["assistant project manager", "senior project executive", "project executive"], "responsibilities": ["user requirement", "advertising", "analysis", "monitoring", "budget", "design", "communication", "specifications", "plan", "coordination"], "requirements": {"degrees": ["degree holder"], "majors": ["business", "computer science", "marketing"], "languages": [], "language_level": [], "hard_skills": ["mobile", "analysis", "deployment", "web"], "soft_skills": ["detail-minded", "communication skills", "good team player", "work independently", "responsible", "mature", "coordination", "responsive"], "languages_combined": []}, "experience_required": {"duration": [], "field": ["advertising agency"]}}, {"job_id": "100003009052479", "location_code": "hk", "company": "BSI Pacific Ltd", "job_title": "Key Account and Business Development Manager", "description": "We are looking for talent to achieve sales targets to grow existing large customers and expand new accounts by focusing on the ICT and financial sector, and representing BSI products and services.\n\nResponsibilities\n\nProspect and pursue new business to expand the client reach of BSI.\nDevelop and manage relationships with targeted accounts and their business leaders to ensure BSI is well placed to win new business and/ or maintain and grow existing business.\nWork with customers to meet assigned targets for profitable sales volume and strategic objectives in assigned accounts.\nCoordinate requirements, develop and negotiate contracts and integrate contract requirements with business operations to close new business deals.\nManage, maintain and update key stakeholders\u2019 information in CRM system to ensure current contacts remain relevant.\nKeep well informed on industry changes and participate where possible in organizations directly involved with the prime markets to maintain a strong industry awareness.\nImplement global key account strategy, develop account plans.\nDevelop and expand into selected strategic market segments.\nSet up and schedule regular account reviews to explore & identify further opportunities.\nProvide monthly feedback of actual verses target for the team, by individual, to monitor sales performance in detail and to suggest improvements to individuals and teams.\nGather competitor information to identify and prioritize opportunities to refine sales messaging.\n\nRequirements\n\nUniversity Degree level, ideally in Computer Science or E&E or equivalent education\nMBA is a plus\nAt least 5 years relevant work experience in B2B sales and business development\nGood command of spoken and written English, Chinese Cantonese & Mandarin\nKnowledge on ISO Standards will be advantageous\nStrong connection with ICT, Financial sectors\nStrong relationship with Local Chinese, Foreign investment organization & Government bodies in Hong Kong\nSolid management experience in sales & marketing field with good track record\nPositive and approachable, analytical, influential with strong conflict resolution, communication and leadership skills\n\nInterested parties please send us a full resume with your\u00a0CURRENT & EXPECTED SALARY\u00a0simply click \"APPLY NOW\".\u00a0\u00a0\n\nPersonal data provided by applicants will be treated in strict confidence and used for recruitment purposes only for no more than 6 months.", "employment_types": ["Full Time", "Permanent"], "selling_points": ["Business Development in ICT & financial sector", "Great Potential with flexible working environment", "MNC, 5 Days Work, Bonus, Medical & Life"], "locations": ["Quarry Bay"], "categories": ["Sales, CS & Business Devpt", "Business Development", "Sales - Sales Management", "Information Technology (IT)", "Mobile / Wireless Communications"], "post_time": "2022-01-17T03:09:21Z", "salary": {"currency": null, "max": null, "min": null, "period": "monthly", "term": null}, "salary_visible": false, "title_keywords": ["business development manager"], "responsibilities": ["contracts", "operations", "sales performance", "monitor", "teams", "develop", "coordinate", "maintain", "schedule", "suggest improvements", "plans"], "requirements": {"degrees": ["university degree"], "majors": ["computer science"], "languages": ["cantonese", "english", "chinese", "mandarin"], "language_level": ["good command"], "hard_skills": ["plus"], "soft_skills": ["approachable", "leadership skills", "communication", "influential", "positive"], "languages_combined": [{"language": "cantonese", "language_level": ["good command"]}, {"language": "english", "language_level": ["good command"]}, {"language": "chinese", "language_level": ["good command"]}, {"language": "mandarin", "language_level": ["good command"]}]}, "experience_required": {"duration": ["at least 5 years"], "field": ["management", "business development", "marketing"]}}, {"job_id": "100003009050375", "location_code": "hk", "company": "WiseSpot Company Limited", "job_title": "Engineer/Engineer Trainee - Technical Support", "description": "Job responsibilities:\n\nProvide Tier 1 7X24 emergency on-call support and trouble shooting\u00a0service for the Company's customer\u00a0\nCustomer system being supported include both telecom and enterprise solutions running on various operation system including Cloud, VM, Linux, MS Windows systems and vendor/proprietary platform etc.. The task mainly includes to support and resolve customer network incident/complaint/issue.\nAssist implementation/Engineering team in the installation, testing and maintenance for new project/service rollout.\u00a0 Create and update documentation for project needs.\nProvide internal IT Support\n\nThe candidate we are looking for\n\nHigh Diploma holder or above\n2 years hands-on experience in administration and operation support for Cloud Platform, VM, Linux and MS Windows systems.\u00a0Fresh graduates with less experience, knowledge and skills are welcome to join under our Trainee program\nWiling to learn and pick up knowledge in Telecom system/solution and VoIP system\nFluent in Cantonese, Knowledge of Putonghua is an advantage\nGood in spoken and written English to communicate with overseas vendors\nSystematic training on the above areas will be given to the right candidates\nAll personal data collected will be used for recruitment purpose only.", "employment_types": ["Full Time", "Permanent"], "selling_points": ["On call fee scheme for weekly support rotation", "High Diploma or above in IT or related disciplines", "Fresh Graduates Are Welcome.  Training Provided"], "locations": ["North Point"], "categories": ["Information Technology (IT)", "Support", "Network & System", "Mobile / Wireless Communications"], "post_time": "2022-01-15T03:51:03Z", "salary": {"currency": null, "max": null, "min": null, "period": "monthly", "term": null}, "salary_visible": false, "title_keywords": ["technical support", "engineer", "trainee"], "responsibilities": ["communicate with", "installation", "maintenance", "systems", "implementation", "testing", "recruitment", "documentation", "personal data", "administration"], "requirements": {"degrees": ["high diploma"], "majors": [], "languages": ["cantonese", "putonghua", "english"], "language_level": ["advantage", "good", "fluent"], "hard_skills": ["linux", "maintenance", "ms windows", "vendor", "documentation", "operation support"], "soft_skills": ["hands-on", "systematic"], "languages_combined": [{"language": "cantonese", "language_level": ["fluent", "advantage"]}, {"language": "putonghua", "language_level": ["advantage"]}, {"language": "english", "language_level": ["good"]}]}, "experience_required": {"duration": ["2 years"], "field": ["operation", "administration"]}}, {"job_id": "100003009046561", "location_code": "hk", "company": "Cathay Pacific Airways Ltd", "job_title": "Assistant Manager Digital Experience - Mobile App", "description": "Reports to:\u00a0Digital Experience Manager \u2013 Mobile App\nDepartment:\u00a0Customer Experience & Design (CED)\n\nRole Introduction\n\nThis position will involve working as a digital product owner on the Cathay Pacific Mobile App. The successful candidate will be collaborating closely with developers, designers, commercial teams, airport service delivery teams & other stakeholders to help develop deliver a seamless app experience that supports our vision to be one of the the world\u2019s leading service brands.\n\nKey Responsibilities\n\nWork with the product manager, stakeholders, designers & development teams to form a deep understanding of our customer\u2019s needs, pain points and potential solutions\nAssist in developing a product roadmap for the app that supports our vision & strategic objectives while prioritising customer experience\nYou\u2019ll be a champion for the customer by collaborating with the design & development team to develop user stories, wireframes, and workflows that solve real problems for our customers\nYou\u2019ll ensure development teams are clear about why features are prioritized and that they are motivated to help build products and features that are seamless and drive value to air travelers\nYou\u2019ll help define & manage testing and QA processes to ensure the overall quality of the app\nYou\u2019ll work with peers across departments to define milestones and ensure on-time and in-scope delivery\n\nRequirements\n\nDegree holder with more than 3 years of digital product owner/manager experience ideally within a mobile app environment\nExperience working in an agile/scrum environment and working with technical teams to define user stories and acceptance criteria\nExcellent interpersonal skills including an ability to collaborate with and help motivate teams Experience using work management platforms such Confluence & Jira\nExperience developing test plans & processes to ensure a high quality product is delivered\nA love for building quality software that delights customers & addresses customer needs\nPassionate about using data and insights during the discovery phase of product development, not as an afterthought\nAsking why is second nature \u2013 we want someone who takes time to understand the problem before throwing out a solution\nAble to break down complex problems express them in simple terms to non-technical stakeholders\nAn understanding of airline services and products & operation flows is preferred\nFluent in Cantonese, English & ideally Mandarin\nIndustry certifications such as SAFe, CSPO, or PSPO highly desirable\n\nApplication Deadline: 27 January 2022\n\nPersonal & Application Information\n\nCathay Pacific is an Equal Opportunities Employer. Personal data provided by job applicants will be used strictly in accordance with our personal data policy and for recruitment purposes only. Candidates not notified within eight weeks may consider their application unsuccessful. All related information will be kept in our file for up to 24 months. A copy of our Personal Information Collection Statement will be provided upon request by contacting our Data Protection Officer.\n\nPlease note that with effect from 1 December 2021, all employees must be vaccinated in order to access Cathay City and all other Cathay Group Company premises in Hong Kong. Consideration will be given to those who are unable to get vaccinated for valid medical reasons.\n\n", "employment_types": ["Full Time", "Permanent"], "selling_points": ["3 years digital product owner/manager experience", "Working as a digital product owner", "Travel Benefits, 5-day work, Medical Benefits"], "locations": ["Lantau Island"], "categories": ["Transportation & Logistics", "Aviation Services", "Information Technology (IT)", "Mobile / Wireless Communications", "E-commerce", "Business Development"], "post_time": "2022-01-14T01:23:30Z", "salary": {"currency": null, "max": null, "min": null, "period": "monthly", "term": null}, "salary_visible": false, "title_keywords": ["assistant manager"], "responsibilities": ["teams", "developing", "design", "testing", "develop", "quality"], "requirements": {"degrees": ["degree holder"], "majors": [], "languages": ["cantonese", "english", "mandarin"], "language_level": ["fluent"], "hard_skills": ["simple", "agile", "airline", "mobile", "safe"], "soft_skills": ["interpersonal skills", "agile", "passionate about"], "languages_combined": [{"language": "cantonese", "language_level": ["fluent"]}, {"language": "english", "language_level": ["fluent"]}, {"language": "mandarin", "language_level": ["fluent"]}]}, "experience_required": {"duration": ["3 years"], "field": ["digital", "management", "developing"]}}, {"job_id": "100003009046532", "location_code": "hk", "company": "Foris Limited", "job_title": "Senior / Mobile Developer (Android) - Global Fintech Startup", "description": "About Crypto.com\n\nCrypto.com was founded in 2016, Crypto.com today serves over 10 million customers with the world\u2019s fastest growing crypto app, along with the Crypto.com Visa Card \u2014 the world\u2019s largest crypto card program \u2014 the Crypto.com Exchange and Crypto.com DeFi Wallet. Recently launched, Crypto.com NFT is the premier platform for collecting and trading NFTs, carefully curated from the worlds of art, design, entertainment and sports.\n\nCrypto.com is built on a solid foundation of security, privacy and compliance and is the first cryptocurrency company in the world to have ISO/IEC 27701:2019, ISO27001:2013 and PCI:DSS 3.2.1, Level 1 compliance, and independently assessed at Tier 4, the highest level for both NIST Cybersecurity and Privacy Frameworks. With over 3,000 people in offices across the Americas, Europe and Asia, Crypto.com is accelerating the world\u2019s transition to cryptocurrency.\n\nFind out more: https://crypto.com\n\nAbout the role:\n\nWe're looking for self-starting engineers with strong experience developing sophisticated applications. You will be Involved in end-to-end mobile application development life cycle.\n\nRequirements (Android):\n\nInterested in building first-class product to solve real world problems\nExperienced with various technologies, a fast learner and have a \u201cget things done\u201d mentality\nStrong organisational skills and interpersonal skills and the ability to juggle conflicting requirements from many different stakeholders\nHumble to embrace better ideas from others, eager to make things better, open to challenges and possibilities\nExperience building complex applications for the Android using Kotlin/Java\nMobile application development at the user interface and system levels\n\nGood to have:\n\nExperience and good understanding on Test-Driven-Development (TDD), implement instrumented unit tests\nExperience with MVVM, Reactive Patterns using RxJava/RxAndroid and the multi-module architecture\nExperience in building real time graph, displaying real time data etc.\nWilling to learn\n\nBenefits\n\nWe offer an attractive compensation package working in a cutting-edge field of Fintech\nHuge responsibilities from Day 1. Be the owner of your own learning curve. The possibilities are limitless and depend on you\nYou get to work in a very dynamic environment and be part of an international team\nYou will get to have involvement in developing a brand new product from scratch alongside with a talented team", "employment_types": ["Full Time", "Permanent"], "selling_points": ["3+ years in Android Development", "Familiar with Kotlin, RxJava/RxAndroid", "Interested in Fintech, blockchain, cryptocurrency"], "locations": ["Sai Ying Pun"], "categories": ["Information Technology (IT)", "Software Development", "Others", "Mobile / Wireless Communications"], "post_time": "2022-01-13T13:24:17Z", "salary": {"currency": null, "max": null, "min": null, "period": "monthly", "term": null}, "salary_visible": false, "title_keywords": ["developer"], "responsibilities": [], "requirements": {"degrees": [], "majors": [], "languages": [], "language_level": [], "hard_skills": ["java", "make", "mobile", "kotlin", "android"], "soft_skills": ["first-class", "interested in", "willing to learn", "organisational skills", "interpersonal skills", "fast learner", "driven"], "languages_combined": []}, "experience_required": {"duration": [], "field": ["development"]}}, {"job_id": "100003009047482", "location_code": "hk", "company": "WiZ Connected Lighting Co. Limited", "job_title": "Mobile development engineer", "description": "We\u2019re looking for a Mobile engineer to join our team in Hong Kong.\n\nWorking for Signify means being creative and adaptive. Our culture of continuous learning and commitment to diversity and inclusion creates an environment that allows you to build your skills and career. Together, we\u2019re transforming our industry.\n\nAs the world leader in lighting, we\u2019re constantly ahead of the curve. Through our leadership in connected lighting and the Internet of Things, we\u2019re breaking new grounds in data analytics, AI, and smart homes, offices, cities and more!\n\nSignify is one of the few companies in the world to achieve carbon neutrality and our next sustainability goals are even bolder: doubling our positive impact on the environment and society by 2025.\n\nOur mobile tech stack:\n\nSwift/Kotlin\nFlutter/Dart\nReactiveExtensions (RxSwift/RxJava)\nRealmDB\nFastlane\nTeamCity\nGitHub\n\nWhat you\u2019ll do\nAs we continue to position our app as the best among IoT platforms, you will be part of a talented team that delivers quality experiences to our customers. Here are some of the things you will be doing:\n\nWork closely with firmware and cloud teams to establish technical communication between all parts of the system\nTranslate requirements from the product team into features in the app\nContribute to the roadmap planning and give feedback to the product owner\nRefactor - we never miss an opportunity to repay our technical debt\nReduce our bug count to zero\n\nWho you\u00a0are\n\nExperienced in mobile development with either Objective-C/Swift or Java/Kotlin\nPassionate about producing high quality products\nA team player who knows how to have fun\nAble to communicate effectively in English (both written and verbal)\n\nNice\u00a0to have\n\nDegree in Computer Science or related discipline\nHave an eye towards the future of IoT, smart lighting, and home automation\nInterested in software architecture and design patterns\nExperience with continuous integration and continuous deployment\nExperience with automated unit testing\n\nWhat we can offer\n\nAn attractive remuneration package, including double pay\nA flexible and multicultural environment that promotes a work-life balance\nA talented team from all over the world to work with\n\nWe\u2019re offering multiple opportunities for career development, like mentoring, coaching and stretch assignments, with strong international exposure for dynamic profiles. Learning is fundamental to our culture. Through continuous learning, we are transforming the industry. You have the chance to learn every day, acquire new skills and perspectives through customized online programs, and on-the-job experiences.\n\nSee\u00a0#SignifyLife\u00a0through the eyes of our employees!\n\nJob Description", "employment_types": ["Full Time"], "selling_points": ["mobile development", "either Objective-C/Swift or Java/Kotli", "Degree in Computer Science or related discipline"], "locations": ["Kowloon Bay"], "categories": ["Information Technology (IT)", "Mobile / Wireless Communications"], "post_time": "2022-01-14T03:15:55Z", "salary": {"currency": null, "max": null, "min": null, "period": "monthly", "term": null}, "salary_visible": false, "title_keywords": ["engineer"], "responsibilities": [], "requirements": {"degrees": ["degree"], "majors": ["computer science"], "languages": ["english"], "language_level": [], "hard_skills": ["java", "fun", "integration", "nice", "objective-c", "mobile", "deployment", "swift", "kotlin"], "soft_skills": ["team player", "interested in", "passionate about"], "languages_combined": [{"language": "english", "language_level": []}]}, "experience_required": {"duration": [], "field": ["testing"]}}, {"job_id": "100003009042587", "location_code": "hk", "company": "ESD Services Limited (ESDlife)", "job_title": "Mobile Application Developer (iOS/Android)", "description": "You will:\n\n\nDevelop mobile application\nResponsible for system design and development\nCollaborate with teammates to deliver the services and meet project milestones and deadlines\nCommunicate with project lead\u00a0or clients to gather requirement\nAnalyze requirement\nSchedule and assign tasks\n\nYou should have/be:\n\n\nDegree in Computer Science or other computer programming related disciplines\nA solid understanding of Java programming / Objective-C programming\nWilling to learn new technologies in mobile industry\nExperience on Kotlin programming is a plus\nStrong passion and sensitive to the trend of development in Internet and Mobile\nGood communication & interpersonal skills\nCandidate with more experience will be considered for the position as\u00a0'Senior Mobile Application Developer'\n\nIn addition, you will be able to:\u00a0\n\nEnjoy an attractive and competitive remuneration package\nReceive training and development opportunities\n\nSalary and benefit will commensurate with qualifications and experience.\u00a0\u00a0Interested party, please send in your\u00a0full resume and expected salary\u00a0by clicking the button\u00a0\u2018APPLY NOW\u2019.\n\nTo know more about us, please visit our website\n\n\nhttps://corporate.esdlife.com/\nhttp://solutions.esdlife.com\n\n\n\nWe are an equal opportunity employer and welcome applications from all qualified candidates. The information provided will be treated in strict confidence and used only for consideration of application for relevant/similar post(s) within the Hutchison Group of Companies.\n\nApplicants not having heard from us within four weeks from the date of this advertisement may consider their application unsuccessful. All personal data of unsuccessful applicants will be destroyed after the recruitment exercise when no longer required.", "employment_types": ["Full Time", "Permanent"], "selling_points": [], "locations": ["Hung Hom"], "categories": ["Information Technology (IT)", "Software Development", "Mobile / Wireless Communications"], "post_time": "2022-01-12T08:06:01Z", "salary": {"currency": null, "max": null, "min": null, "period": "monthly", "term": null}, "salary_visible": false, "title_keywords": ["developer"], "responsibilities": ["collaborate with", "communicate with", "assign tasks", "website", "develop", "communication", "system design", "recruitment", "schedule", "personal data"], "requirements": {"degrees": ["degree"], "majors": ["related disciplines", "computer science"], "languages": [], "language_level": [], "hard_skills": ["java", "plus", "no", "objective-c", "mobile", "system design", "programming", "kotlin"], "soft_skills": ["confidence", "responsible", "willing to learn", "communication", "sensitive to", "interpersonal skills"], "languages_combined": []}, "experience_required": {"duration": [], "field": ["developer", "programming"]}}, {"job_id": "100003009045491", "location_code": "hk", "company": "HKT Consumer Group", "job_title": "Software Engineer, DrGo & eSmartHealth", "description": "Your Role\n\nResponsible for mobile applications design, development, testing, implementation, enhancement and maintenance\nWork closely with clients and internal teams on project requirement and UX/UI design\nPrepare documentations including user requirements, functional specifications, test plans and user manuals\nWork with device vendors and external business partners to develop new products and enhance our product competitiveness\nProvide user support and on-site troubleshooting for our integrated solutions\n\nTo Succeed in this Role\n\nDegree holder in Computer Science, Information Technology, or related disciplines\nAt least 3 years solid experience in native iOS/Android development, or cross-platform solutions like React Native or Flutter\nExperience in graphic/artwork design and web programming is an advantage\nKnowledge of e-Health products/platforms and their integration via BLE/API is definitely an advantage\nUnderstanding of common data structures, cryptography, threading, RESTful APIs, etc\nCreative, self-motivated, and able to work independently and under tight schedule\nA good team player with excellent presentation and interpersonal skills\nGood command of written and spoken Chinese and English, Mandarin is an advantage", "employment_types": ["Full Time"], "selling_points": [], "locations": ["Quarry Bay"], "categories": ["Information Technology (IT)", "Application Specialist - Software", "Technical Writing", "Mobile / Wireless Communications"], "post_time": "2022-01-13T07:56:51Z", "salary": {"currency": null, "max": null, "min": null, "period": "monthly", "term": null}, "salary_visible": false, "title_keywords": ["software engineer"], "responsibilities": ["maintenance", "data", "teams", "implementation", "design", "testing", "develop", "troubleshooting", "specifications", "schedule", "plans", "ui"], "requirements": {"degrees": ["degree holder"], "majors": ["related disciplines", "computer science", "information technology"], "languages": ["english", "chinese", "mandarin"], "language_level": ["advantage", "good command"], "hard_skills": ["android development", "maintenance", "web", "mobile", "react native", "programming", "integration", "documentations"], "soft_skills": ["self-motivated", "work independently", "good team player", "responsible", "troubleshooting", "interpersonal skills", "creative", "presentation"], "languages_combined": [{"language": "english", "language_level": ["advantage", "good command"]}, {"language": "chinese", "language_level": ["advantage", "good command"]}, {"language": "mandarin", "language_level": ["advantage", "good command"]}]}, "experience_required": {"duration": ["at least 3 years"], "field": ["programming", "development", "graphic", "design"]}}, {"job_id": "100003009048760", "location_code": "hk", "company": "United Asia Finance Limited", "job_title": "Programmer / Analyst Programmer [new credit card business]", "description": "Job Responsibilities:\n\nResponsible for development, testing and implementation of company websites, mobile apps and other digital solutions\nPerform coding, unit testing and technical documentations according to system design and development standards\nWork closely with project team and end users to ensure technical compatibility and user satisfaction\nProvide support and maintenance to existing systems\n\nJob Requirements:\n\nDegree or above in Computer Science, IT or related discipline\nWorking experience in building Android / IOS mobile app using React Native\nSolid experience in Java, Spring Boot, Oracle/MySQL and Linux\nFamiliar with at least one of below areas\nMicro service Framework (e.g. Spring Cloud Framework)\nResponsive web application (Angular, JavaScript, TypeScript, PHP, Bootstrap) and REST API\nBuild automation and deployment tools such as Jenkins, Maven\nGood analytical, communication and problem-solving skills\nMore experience will be considered as Analyst Programmer\n\nWe offer attractive remuneration package which includes double pay and discretionary bonus. Interested parties please send your CV indicating your current salary, expected salary and availability to HR Department, by clicking \u201cApply Now\u201d\n\n(Personal data collected will be treated in the strictest confidence and will be handled by authorized personnel for recruitment-related purposes only. Applicants who do not hear from us within 3 months may consider their application unsuccessful and their data will be destroyed within 24 months of receipt.)", "employment_types": ["Full Time", "Permanent"], "selling_points": ["Degree in Computer Science, IT or related", "Exp in Android / IOS mobile app using React Native", "Double pay and Discretionary Bonus"], "locations": ["Wan Chai"], "categories": ["Information Technology (IT)", "Application Specialist - Software", "Software Development", "Mobile / Wireless Communications"], "post_time": "2022-01-14T07:13:49Z", "salary": {"currency": null, "max": null, "min": null, "period": "monthly", "term": null}, "salary_visible": false, "title_keywords": ["analyst programmer", "programmer"], "responsibilities": ["company websites", "provide support", "maintenance", "systems", "implementation", "coding", "testing", "system design"], "requirements": {"degrees": ["degree or above"], "majors": ["it", "computer science"], "languages": [], "language_level": [], "hard_skills": ["linux", "java", "jenkins", "web", "php", "mobile", "javascript", "react native", "typescript", "spring", "angular", "deployment", "problem-solving skills", "android", "oracle"], "soft_skills": ["communication", "problem-solving skills", "responsive"], "languages_combined": []}, "experience_required": {"duration": [], "field": []}}, {"job_id": "100003009046531", "location_code": "hk", "company": "Foris Limited", "job_title": "Senior / Mobile Developer (iOS) - Global Fintech Startup", "description": "About Crypto.com\n\nCrypto.com was founded in 2016, Crypto.com today serves over 10 million customers with the world\u2019s fastest growing crypto app, along with the Crypto.com Visa Card \u2014 the world\u2019s largest crypto card program \u2014 the Crypto.com Exchange and Crypto.com DeFi Wallet. Recently launched, Crypto.com NFT is the premier platform for collecting and trading NFTs, carefully curated from the worlds of art, design, entertainment and sports.\n\nCrypto.com is built on a solid foundation of security, privacy and compliance and is the first cryptocurrency company in the world to have ISO/IEC 27701:2019, ISO27001:2013 and PCI:DSS 3.2.1, Level 1 compliance, and independently assessed at Tier 4, the highest level for both NIST Cybersecurity and Privacy Frameworks. With over 3,000 people in offices across the Americas, Europe and Asia, Crypto.com is accelerating the world\u2019s transition to cryptocurrency.\n\nFind out more: https://crypto.com\n\nAbout the role:\n\nWe're looking for self-starting engineers with strong experience developing sophisticated applications. You will be involved in end-to-end mobile application development life cycle.\n\n\u00a0Responsibilities (iOS):\n\nWork closely with product team and play an active role in providing feedbacks, to help shape our features\nPassionate about software engineering and love to build mobile apps and systems\nCare about code quality, robustness and end user experience\n3+ year experience in iOS App Development\n2+ year experience in Swift\nFamiliar with Reactive Programming (e.g. RxSwift / ReactiveSwift / Combine)\nBuilt projects you are proud of (big plus if they are side projects)\n\n\u00a0What you can expect from us?\u00a0\n\nWe offer an attractive compensation package working in a cutting-edge field of Fintech.\nFlat team. Work side by side with the co-founding team\nHuge responsibilities from Day 1. Be the owner of your own learning curve. The possibilities are limitless and depend on you\nYou get to work in a very dynamic environment and be part of an international team\nYou will get to have involvement in developing a brand new product from scratch alongside with a talented team", "employment_types": ["Full Time", "Permanent"], "selling_points": ["3+ years experience in iOS development", "Familiar with Swift, RxSwift", "Interested in Fintech, blockchain, cryptocurrency"], "locations": ["Sai Ying Pun"], "categories": ["Information Technology (IT)", "Software Development", "Others", "Mobile / Wireless Communications"], "post_time": "2022-01-13T13:22:41Z", "salary": {"currency": null, "max": null, "min": null, "period": "monthly", "term": null}, "salary_visible": false, "title_keywords": ["developer"], "responsibilities": ["software", "compliance", "systems", "developing", "design", "quality", "user experience", "application development"], "requirements": {"degrees": [], "majors": [], "languages": [], "language_level": [], "hard_skills": ["plus", "crypto", "mobile", "programming", "cryptocurrency", "swift", "code", "exchange"], "soft_skills": ["sophisticated", "active", "independently", "passionate about"], "languages_combined": []}, "experience_required": {"duration": ["3+ year", "2+ year"], "field": ["development", "developing"]}}, {"job_id": "100003009050681", "location_code": "hk", "company": "Hutchison Telecommunications (Hong Kong) Limited", "job_title": "Senior Engineer - Data Network & Packet Core Development", "description": "Responsibilities\u00a0\n\nMobile core technology development\u00a0\nMobile policy and charging technology (PCRF, PCEF, Diameter)\nNetwork enabling technology (AAA, DRA, Traffic Load Balancing)\nVendor management\nProject management\nBusiness user requirement collection\nWork with vendor to finalize the solution details\n\nRequirements\n\nBachelor degree holder in Electronic\u00a0Engineering / Computer Science / Engineering /\u00a0Telecommunication Engineering\u00a0\n3 years of relevant working experience or above\nGood command of written and spoken Chinese and English\n\nApart from competitive remuneration package and exciting opportunity for career development within the Group, we provide attractive employee benefits such as free company shuttle, free company SIM card and preferential SIM plan offers, comprehensive medical & insurance schemes, as well as full range of other employee well-being provisions.\n\nInterested parties, please apply with full resume, present and expected salary, by clicking \u201cAPPLY NOW\u201d. Please quote the reference number on the e-mail subject.\n\nWe are an equal opportunity employer and welcome applications from all qualified candidates. Personal data collected will be treated in the strictest confidence and handled confidentially by authorised personnel for recruitment-related purposes only within the CK Hutchison Group of companies. The personal data of unsuccessful applicants will be destroyed after the recruitment exercise pursuant to the requirements of the Personal Data (Privacy) Ordinance in Hong Kong.", "employment_types": ["Full Time", "Permanent"], "selling_points": [], "locations": ["Tsing Yi"], "categories": ["Engineering", "Electrical / Electronics", "Telecommunication / Wireless / Radio", "Information Technology (IT)", "Mobile / Wireless Communications"], "post_time": "2022-01-14T11:10:24Z", "salary": {"currency": null, "max": null, "min": null, "period": "monthly", "term": null}, "salary_visible": false, "title_keywords": ["senior engineer"], "responsibilities": ["project management", "management"], "requirements": {"degrees": ["bachelor degree holder"], "majors": ["engineering", "computer science"], "languages": ["english", "chinese"], "language_level": ["good command"], "hard_skills": ["vendor"], "soft_skills": ["comprehensive"], "languages_combined": [{"language": "english", "language_level": ["good command"]}, {"language": "chinese", "language_level": ["good command"]}]}, "experience_required": {"duration": ["3 years"], "field": ["relevant working experience"]}}, {"job_id": "100003009049257", "location_code": "hk", "company": "SmarTone Telecommunications Limited", "job_title": "Engineer, Operation Systems Support", "description": "Responsibilities:\n\nResponsible for system operations and administration of OSSs and NMSs that supports SmarTone's 2G/3G, LTE and IMS mobile network surveillance and operations\nAssist in system administration activities and in-house programming development\nTrouble-shooting on hardware / software and hands-on problem diagnosis for end users.\nParticipate OSS major upgrade/ migrations project execution\nLiaise with vendor for all sorts of system hardware/software troubleshooting and system recovery actions.\nProvide after office hours on-call emergency support services upon request.\n\nRequirements:\u00a0\n\nDegree in Electronic Engineering, Computer Science, Information Technology or related disciplines\n2 years\u2019 relevant experience in system administration is preferred, fresh graduates will also be considered as junior position\nSolid experience in computer operating systems such as HP Blade platform, Oracle Solaris, Linux and Window platform\nKnowledge in Shell, Perl, PHP, SQL, Python and Java Programming\nExperience in telecommunication network management systems or operations support systems is preferred\nGood interpersonal and analytical skills\nAble to work independently and under pressure\n\nInterested parties please apply with full resume stating present and expected salary by clicking \"Apply Now\" or visiting our Website:\u00a0www.smartone.com/tc/about_us/careers/\n\nSmarTone is an equal-opportunity employer. All data supplied will be kept in strict confidence and will be used for employment related purpose. We may transfer such data to any agent, contractor or third party who provides services to us with respect to matters relating to your application. Only short-listed candidates will be contacted.\n\n\nYou are welcome to visit our website :\u00a0www.smartone.com\u00a0\u00a0", "employment_types": ["Full Time", "Permanent", "Contract"], "selling_points": ["Operations Support System operations and admin", "System upgrade/ migrations project execution", "In-house programming development"], "locations": ["Kowloon Bay"], "categories": ["Engineering", "Telecommunication / Wireless / Radio", "Information Technology (IT)", "Support", "Mobile / Wireless Communications"], "post_time": "2022-01-14T08:19:53Z", "salary": {"currency": null, "max": null, "min": null, "period": "monthly", "term": null}, "salary_visible": false, "title_keywords": ["engineer"], "responsibilities": ["migrations", "software", "operations", "support services", "troubleshooting", "hardware", "liaise with", "administration"], "requirements": {"degrees": ["degree"], "majors": ["related disciplines", "engineering", "computer science", "information technology"], "languages": [], "language_level": [], "hard_skills": ["linux", "oracle", "java", "network management", "php", "analytical skills", "sql", "programming", "python", "perl"], "soft_skills": ["work independently", "under pressure", "interpersonal", "analytical skills"], "languages_combined": []}, "experience_required": {"duration": ["2 years"], "field": ["management", "relevant experience", "administration"]}}, {"job_id": "100003009050370", "location_code": "hk", "company": "Hays", "job_title": "Senior Digital Engineering (AD) - Insurance MNC", "description": "Senior position in Mobile architecture with a Regional exposure.\n\nYour new company\n\nOur client is a major Insurance company in Hong Kong. Their contributions have supported social and economic progress across Asia, while also advancing the reach and impact of life insurance across the region.\n\nThey have the ambition to be a global industry leader in Environmental, Social, Governance (ESG), shaping a sustainable future for the communities they serve and creating long-term value for their stakeholders.\n\nYour new role\n\n\nYou will be responsible to create and lead component designs into code and place them into a curated repository Storybook/Git/NPM for other developers to create their digital applications.\nIntegrate the best practice of the digital development (mobile and web) into automation tools as part of the SDLC2.0 (Agile adapted) practice with DevOps, Automated Testing.\nProvide technical leadership to senior technical leads and vendor leads to ensure best practices are adhered to for maximum reuse across the group.\nSet an example of what \"good\" looks like and lead from the front.\nWork closely with UX designers and co-create solutions that are easy to implement, scalable, yet engaging for our customers.\nCreate and manage a governance best practice to maintain the quality and security of code across all the local BUs.\nCreate and update coding guidelines for local BUs as a part of our DLS (Design Language System).\nMeasure, collaborate and lift capability within the company's near shore capabilities in and vendor development teams to ensure that components/screens produce are readily consumable in implementation.\nWork closely with offsite teams to ensure that implementation of the components/screens will produce desired UI solutions.\nWork closely with security and DevOps teams to ensure the delivery of secure and stable applications.\nWork within the existing framework but always suggest improvements in how we work, and choice of platforms/technologies.\nStay informed and in tune with the latest methodologies, best practices, trends in the web/ app development.\nAdoption of standards and frameworks by Bus.\nCommunication:\nInternal: You must communicate regularly with the other project stakeholders, BU project members, technical leads and enterprise architecture team members, aligning the Application Architecture with the Business, Integration, Security and Infrastructure architectures.\nExternal: You will work with the Vendors, LBUs IT teams, technical leads and architects on assigned local initiatives and ensure Group standards are followed through engagement\n\n\nWhat you'll need to succeed\n\n\nYou will need at least 6 years of hands-on experience with Mobile.\nExpert in React Native, Kotlin, ReactJS, VueJS, Java Script, JSON, XML, HTML, CSS, JQuery integration coding.\nKnowledge and awareness emerging technologies such as flutter and protbuff.\nAbility to provide leadership to development teams.\nMust be organized, flexible to switch between different projects, and manage your own time well.\nAble to think strategically and develop scalable solutions.\nGood attention to UI/interaction/animation details.\nAble to look at issues from customer and business perspectives in addition to technology perspective.\n\n\nWhat you'll get in return\n\n\nThis position will give you the opportunity to be part of an innovative team in a very well-known and large insurance group.\nOur client pays competitive base salaries, and they reward performance with bonuses.\nIn addition, you will be eligible to participate in their comprehensive benefits program including medical insurance and MPF with additional employer voluntary contributions.\n\n\nWhat you need to do now\n\nIf you have the drive to succeed in this role or are interested in roles within insurance, please contact me with an attached CV at Doriane.madec@hays.com.hk or feel free to call me at 2230-7433.", "employment_types": ["Full Time", "Permanent"], "selling_points": ["Large insurance Group", "Digital architecture: Mobile and Front End", "Around 15 years of experience required"], "locations": ["Not Specified"], "categories": ["Information Technology (IT)", "IT Project Management / Team Lead", "IT Management", "Mobile / Wireless Communications"], "post_time": "2022-01-14T10:13:10Z", "salary": {"currency": null, "max": null, "min": null, "period": "monthly", "term": null}, "salary_visible": false, "title_keywords": [], "responsibilities": ["quality", "coding", "design", "communication", "maintain", "suggest improvements", "collaborate", "infrastructure", "teams", "implementation", "testing", "develop", "architecture", "ui", "mpf", "contact", "guidelines", "insurance", "animation"], "requirements": {"degrees": [], "majors": [], "languages": [], "language_level": [], "hard_skills": ["java script", "git", "agile", "web", "css", "devops", "jquery", "switch", "vendor", "html", "mobile", "react native", "integration", "code", "kotlin"], "soft_skills": ["flexible", "organized", "agile", "responsible", "interested in", "communication", "hands-on", "comprehensive", "think strategically", "stable", "innovative", "leadership"], "languages_combined": []}, "experience_required": {"duration": ["at least 6 years"], "field": []}}, {"job_id": "100003009044289", "location_code": "hk", "company": "OCBC Wing Hang Bank Limited", "job_title": "IT Mobile Developer", "description": "Responsibilities\n\u200bCode, test, debug for mobile and other e-channel systems\nDesign interfaces to improve user experience\nLiaise with business user to plan new features of mobile applications\nEnsure new and legacy applications meet quality standards\nResearch and suggest new mobile products, applications and protocols\nAssist in technical acceptance test and user acceptance test activities\nPerform application code review\nPerform roll-out and conversion activities\nOwn and implement product backlog items\nCollaborate with internal teams and vendors to support the application lifecycle\nRequirements\n\u200bUniversity, Diploma or Certificate in Computer-related Studies\n1-3 years of mobile programming in native (iOS & Android) and hybrid mobile applications\nExperience in Java, Spring, JSON/XML, SQL, React, Cordova\nKnowledge of Rest API, Java Hibernate, DevOps (Eclipse, Jenkins, Maven, UCD, Docker)\nStrong communication skill\nProficient in English & Chinese (verbal & written)\n\nAttractive remuneration package will be offered to the right candidate. Please apply with full resume stating present & expected salary and contact phone number\u00a0to\u00a0The Human Resources Manager, 10/F, 161 Queen\u2019s Road Central, Hong Kong.\u00a0Please quote the reference.\n\nPersonal data collected will be used for recruitment purpose only. For more information, please visit our website:\u00a0http://www.ocbcwhhk.com.", "employment_types": ["Full Time", "Permanent"], "selling_points": ["Code, test, debug for mobile", "Design interfaces", "Ensure new and legacy applications"], "locations": ["Shau Kei Wan"], "categories": ["Information Technology (IT)", "Software Development", "Others", "Mobile / Wireless Communications"], "post_time": "2022-01-13T03:40:28Z", "salary": {"currency": null, "max": null, "min": null, "period": "monthly", "term": null}, "salary_visible": false, "title_keywords": ["developer"], "responsibilities": ["collaborate with", "systems", "quality", "user experience", "design", "review", "teams", "plan", "liaise with"], "requirements": {"degrees": ["certificate", "diploma"], "majors": [], "languages": ["english", "chinese"], "language_level": ["proficient"], "hard_skills": ["java", "hibernate", "jenkins", "react", "devops", "sql", "mobile", "spring", "programming", "android"], "soft_skills": ["communication skill"], "languages_combined": [{"language": "english", "language_level": ["proficient"]}, {"language": "chinese", "language_level": ["proficient"]}]}, "experience_required": {"duration": [], "field": ["sql"]}}, {"job_id": "100003009049011", "location_code": "hk", "company": "SmarTone Telecommunications Limited", "job_title": "Project Manager (E&M Site)", "description": "Responsibilities:\n\n\nResponsible for full project lifecycle with vendor management\nDefine project scope and communicate effectively to cross functional team\nDevelop, track and update project status using appropriate project management techniques and tools (e.g. meetings, status tracking tools)\nIdentify project issues and risk and develop projects scopes, plans, schedules and budget\nManage resources and risks, escalate potential issues to management\nFacilitate onsite construction co-ordination, meetings and supervision works\nProactively drive solutions to problems while involving key stakeholders\nObtain appropriate information necessary for the proper carrying out and completion of the project in accordance with the contract conditions\nIdentify gaps in the contract and support VO discussion with Sales\n\nRequirements:\n\n\nHD holders or above in in Mechanical/ Electrical Engineering/ Building Service\nAt least 5 years practical experience in E&M design and co-ordination, prefer in client or consultant side\nKnowledge of building and interior fitting-out works is required\nPC and AutoCAD knowledge\nExperience for luxury residential development and house is an advantage\nGood leadership and communication skills, able to works with people at all levels, strong in coordination with contractor\nClose attention to details and ability to handle multi-tasks\nExperience in IoT and network cabling structure is a plus\nWith valid Construction Industry Safety Training Certificate (commonly known as \"Green Card\") would be advantage or obtain a certificate within 1 month\nComplete Safety Supervisor certificate by an authorized institution within 3 months\nGood command of written and spoken English and Cantonese\n\nInterested parties please apply with full resume stating our reference code, present and expected salary by clicking \"Apply Now\"\u00a0via JobsDB\n\nYou are welcome to visit our website :\u00a0www.smartone.com\u00a0\n\nSmarTone is an equal-opportunity employer. All data supplied will be kept in strict confidence and will be used for employment related purpose. We may transfer such data to any agent, contractor or third party who provides services to us with respect to matters relating to your application. Only short-listed candidates will be contacted.", "employment_types": ["Full Time", "Permanent"], "selling_points": ["Manage project lifecycle with vendor management", "Facilitate onsite construction co-ordination works", "Experienced in E&M design"], "locations": ["Ngau Tau Kok"], "categories": ["Information Technology (IT)", "IT Project Management / Team Lead", "Network & System", "Mobile / Wireless Communications"], "post_time": "2022-01-14T07:54:25Z", "salary": {"currency": null, "max": null, "min": null, "period": "monthly", "term": null}, "salary_visible": false, "title_keywords": ["project manager"], "responsibilities": ["management", "schedules", "budget", "develop", "project management", "plans", "tracking"], "requirements": {"degrees": ["certificate"], "majors": [], "languages": ["cantonese", "english"], "language_level": ["good command"], "hard_skills": ["pc", "plus", "green card", "autocad"], "soft_skills": ["communication skills", "multi-tasks", "attention to details", "coordination", "leadership"], "languages_combined": [{"language": "cantonese", "language_level": ["good command"]}, {"language": "english", "language_level": ["good command"]}]}, "experience_required": {"duration": ["at least 5 years"], "field": ["development", "design"]}}, {"job_id": "100003009050679", "location_code": "hk", "company": "Hutchison Telecommunications (Hong Kong) Limited", "job_title": "Software Engineer (Digital Workforce & Contact Center)", "description": "Responsibilities:\n\nCommunicate effectively with users and vendors to understand business requirements, and follow up during SDLC\nPerform system development & testing on IT application using Java, Javascript, React JS and Oracle SQL\nPerform system support, development & maintenance, testing and deployment on Corporate Nomination, Corporate Project Management, Contract Management and E-quotation systems\u00a0\nPerform daily IT application support\n\nRequirements:\n\nDegree / higher Diploma holder in Information Technology, Computer Science, Computer studies or related discipline\nMinimum 1-2 years working exp. in Telecom / IT system development and maintenance\nDevelopment exp. with React JS, Spring boot, Restful API, Java, J2EE, Javascript, Redis, Jquery, bootstrap, Angular, Web service, Oracle RDBMS, Oracle PL/SQL, UNIX shell script\u00a0\nAdditional skills and knowledge on docker, kubernetes, Openshift, CI/CD, WebLogic, Apache, Tomcat, Windows / Linux / Unix Server OS, IT architecture is an advantage\u00a0\nStrong analytical and problem solving skills\nGood interpersonal skill and a good team player\u00a0\nMature, dynamic, work independent and self-motivated\u00a0\nFluent in spoken and written English and Cantonese, Mandarin is a plus\n\nApart from competitive remuneration package and exciting opportunity for career development within the Group, we provide attractive employee benefits such as free company shuttle, free company SIM card and preferential SIM plan offers, comprehensive medical & insurance schemes, as well as full range of other employee well-being provisions.\n\nInterested parties, please apply with full resume, present and expected salary, by clicking \u201cAPPLY NOW\u201d. Please quote the reference number on the e-mail subject.\n\nWe are an equal opportunity employer and welcome applications from all qualified candidates. Personal data collected will be treated in the strictest confidence and handled confidentially by authorised personnel for recruitment-related purposes only within the CK Hutchison Group of companies. The personal data of unsuccessful applicants will be destroyed after the recruitment exercise pursuant to the requirements of the Personal Data (Privacy) Ordinance in Hong Kong.\n", "employment_types": ["Full Time", "Permanent"], "selling_points": [], "locations": ["Tsing Yi"], "categories": ["Information Technology (IT)", "Network & System", "Technical / Functional Consulting", "Mobile / Wireless Communications"], "post_time": "2022-01-14T11:10:23Z", "salary": {"currency": null, "max": null, "min": null, "period": "monthly", "term": null}, "salary_visible": false, "title_keywords": ["software engineer"], "responsibilities": ["maintenance", "quotation", "systems", "contract management", "testing", "project management"], "requirements": {"degrees": ["degree", "higher diploma holder"], "majors": ["computer studies", "computer science", "information technology"], "languages": ["cantonese", "english", "mandarin"], "language_level": ["fluent"], "hard_skills": ["plus", "web", "jquery", "server", "java", "os", "restful api", "sql", "javascript", "dynamic", "angular", "oracle", "linux", "apache", "maintenance", "react", "spring", "unix shell", "problem solving skills", "pl"], "soft_skills": ["good team player", "self-motivated", "independent", "mature", "interpersonal skill", "analytical and problem solving skills", "dynamic", "comprehensive"], "languages_combined": [{"language": "cantonese", "language_level": ["fluent"]}, {"language": "english", "language_level": ["fluent"]}, {"language": "mandarin", "language_level": ["fluent"]}]}, "experience_required": {"duration": [], "field": []}}, {"job_id": "100003009043931", "location_code": "hk", "company": "Evergreen System Limited", "job_title": "Mobile Apps Developer (iOS)", "description": "Responsibilities:\nDevelop applications on mobile platforms (iOS)\nResponsible for mobile application development, testing, implementation, enhancement and maintenance\nCollaborating with team members to deliver the projects\n\nRequirements:\n\nDegree / Higher Diploma / Diploma in Computer Science, Computer Engineering or related disciplines\nAt least 1 years relevant experience in iOS mobile application development\nWorking knowledge of JAVA Android SDK programming/ Swift SDK programming\nExperience in JSON, RESTful API, SQL\nExperience in Flutter is a plus\nWell organized, disciplined and responsible with a good work ethic\nA self-motivated team player with good interpersonal and communication skill\nFresh graduates are welcome.\nCandidates with more experience will be considered for Senior Mobile App Developer.", "employment_types": ["Full Time"], "selling_points": ["Year and Performance Bonus", "5 working day per week", "Fresh graduates are welcome"], "locations": ["Hung Hom"], "categories": ["Information Technology (IT)", "Application Specialist - Software", "Software Development", "Mobile / Wireless Communications"], "post_time": "2022-01-13T02:30:04Z", "salary": {"currency": null, "max": null, "min": null, "period": "monthly", "term": null}, "salary_visible": false, "title_keywords": ["developer"], "responsibilities": ["maintenance", "implementation", "testing", "develop", "application development"], "requirements": {"degrees": ["diploma", "degree"], "majors": ["related disciplines", "computer engineering", "computer science"], "languages": [], "language_level": [], "hard_skills": ["java", "restful api", "plus", "sql", "mobile", "programming", "swift", "android sdk"], "soft_skills": ["self-motivated", "responsible", "communication skill", "well organized", "work ethic", "team player", "interpersonal"], "languages_combined": []}, "experience_required": {"duration": ["at least 1 years"], "field": ["sql", "developer", "application development", "relevant experience"]}}, {"job_id": "100003009048122", "location_code": "hk", "company": "ESD Services Limited (ESDlife)", "job_title": "Software Trainee", "description": "Our Software Trainee Programme enables you to use what you\u2019ve learned, expand your knowledge and benefit from invaluable on-the-job experience. It\u2019s a great way to explore the career choices that you could be developed an IT professional. We offer an opportunity to gain hands-on experience working for one of a leading digital solutions company. You'll work with a team of IT professionals and apply your knowledge learnt from the academy in the business environment.\n\nWho We Hire\nWe're looking for passionate graduates who had a Bachelor Degree OR Higher Diploma in computer science, management information systems, or a related technical field.\n\nProgramme Details\nThe Trainees will work with our professionals to tackle the business challenges and deliver solutions in practical environment. During the 12-month programme, you will be rotated across the projects to develop your skills in areas such as backend development for various web/mobile portal, system maintenance and daily operation support.\u00a0 In the training programme, you will learn:\nUser Requirement Gathering\nBusiness Workflow\nWeb Programming \u2013 JAVA / PHP / .Net / node / react.JS / Mobile native (iOS / Android)\nDatabase Programming\nStaff Benefits\nHealthcare Program including In-patient, Out-patient and dental\nHutchison Provident Fund / Mandatory Provident Fund\nAnnual Leaves, Marriage Leaves, Compassionate Leaves, Maternity Leaves and Iron-man/ Iron-lady Leaves\nLong Services Award\nTraining Subsidy for job related courses\nStaff Discount at HWL outlets\nCash Coupons for employees who become bride/ groom or Father/ Mother\nApplication\n\nIf you identify yourself with the above profile and would be keen to take on this opportunity, we would be delighted to hear from you. Please send in your full resume and expected salary via\u00a0Application Portal.\n\n\nTo know more about us, please visit our website at https://ds.esdlife.com/\n\n\nWe are an equal opportunity employer and welcome applications from all qualified candidates. The information provided will be treated in strict confidence and used only for consideration of application for relevant/similar post(s) within the\u00a0CK\u00a0Hutchison Group of Companies.\n\nApplicants not having heard from us within four weeks from the date of this advertisement may consider their application unsuccessful. All personal data of unsuccessful applicants will be destroyed after the recruitment exercise when no longer required.", "employment_types": ["Full Time"], "selling_points": [], "locations": ["Hung Hom"], "categories": ["Information Technology (IT)", "Software Development", "Others", "Mobile / Wireless Communications"], "post_time": "2022-01-14T05:04:51Z", "salary": {"currency": null, "max": null, "min": null, "period": "monthly", "term": null}, "salary_visible": false, "title_keywords": ["trainee"], "responsibilities": ["software"], "requirements": {"degrees": [], "majors": [], "languages": [], "language_level": [], "hard_skills": [], "soft_skills": [], "languages_combined": []}, "experience_required": {"duration": [], "field": []}}, {"job_id": "100003009044634", "location_code": "hk", "company": "HKT Consumer Group", "job_title": "Assistant Product Manager, DrGo and eSmartHealth (MedTech)", "description": "DrGo team offers you an excellent career path and working experience. As Assistant Product Manager of our DrGo\u00a0team, your major job responsibilities include:\n\nDefine product requirements, use cases, work flow and manage the overall product life cycle\n\nProduct design of DrGo/ Health Store features and solution\u00a0\n\nAs Product anchor to orchestrate and facilitate cross-functional development among internal parties e.g. marketing, design, developer, operation, CS\n\nPerform UAT and functional QA to ensure product in good quality\n\nProvide on-site training and support business partners\n\nAssist team manger in daily operation support\u00a0\n\nTo succeed in this role\n\nDegree holder in Computer Science, Information Technology, Electronic Engineering or related discipline;\nMinimum 5 years product development and management experience with solid project management skills; Lesser working experience would as Senior Product Executive\nMobile App and web solution is necessary for this role\nSolid knowledge and hands-on software development/ e-comm related experience is an advantage\nPassionate about new telecommunications and information technology;\nCreative, self-motivated and able to work independently;\nA good team player with excellent presentation and interpersonal skills;\nGood command of written and spoken English and Chinese, Mandarin is an advantage.", "employment_types": ["Full Time"], "selling_points": [], "locations": ["Quarry Bay"], "categories": ["Information Technology (IT)", "IT Project Management / Team Lead", "Software Development", "Mobile / Wireless Communications"], "post_time": "2022-01-13T04:57:20Z", "salary": {"currency": null, "max": null, "min": null, "period": "monthly", "term": null}, "salary_visible": false, "title_keywords": ["assistant product manager"], "responsibilities": ["management", "mobile app", "uat", "software", "quality", "daily operation", "design", "project management", "product design", "internal parties"], "requirements": {"degrees": ["degree holder"], "majors": ["engineering", "computer science", "information technology"], "languages": ["english", "chinese", "mandarin"], "language_level": ["advantage", "good command"], "hard_skills": ["project management", "web", "mobile", "operation support"], "soft_skills": ["self-motivated", "work independently", "good team player", "project management skills", "hands-on", "interpersonal skills", "creative", "presentation", "passionate about"], "languages_combined": [{"language": "english", "language_level": ["advantage", "good command"]}, {"language": "chinese", "language_level": ["advantage", "good command"]}, {"language": "mandarin", "language_level": ["advantage", "good command"]}]}, "experience_required": {"duration": ["minimum 5 years"], "field": ["management", "related", "project management", "software development", "product development", "team"]}}, {"job_id": "100003009049348", "location_code": "hk", "company": "HGC Global Communications Limited", "job_title": "Engineer (Network Configuration)", "description": "Responsibilities:\n\nWork closely with service order and project management team for daily service order fulfillment and follow up the order processing status;\nMaintain good network resources assignment record and prepare related report for capacity monitoring;\nPerform network data configuration work and ensure the completeness and correctness of service order requirements;\nPerform other administrative support and urgent requests from clients or superior.\n\nRequirements:\n\nDiploma / Degree holder in Computer Science, Information Technology or related disciplines;\n2 years' working experience in IT networking;\nGood knowledge in TCP/IP networking, switch, routers, DNS, ets;\nExperience in hardware and software installation and troubleshooting;\nCan work independently under limited supervision;\nAbility to work nights and weekends as required;\nGood communication skills.\nWe offer competitive salary package and career development opportunity. Free company coach is provided.\u00a0 Interested parties, please quote our reference number and apply with full resume, present and expected salary, by clicking \u201cAPPLY NOW\u201d.\u00a0\n\nWe are an equal opportunity employer and welcome applications from all qualified candidates. Information provided will be treated in strict confidence and only be used for consideration of your application for the relevant post within HGC Global Communications Limited. Personal data provided by job applicants will be used strictly according to our Personal Information Collection Statement, a copy of which will be available upon written request. Information of unsuccessful candidates will be destroyed within six months.", "employment_types": ["Full Time", "Permanent"], "selling_points": ["Perform network data configuration work", "Diploma in Computer Science / IT", "2 years' working experience in IT networking"], "locations": ["Tsing Yi"], "categories": ["Engineering", "Telecommunication / Wireless / Radio", "Information Technology (IT)", "Network & System", "Mobile / Wireless Communications"], "post_time": "2022-01-14T08:30:54Z", "salary": {"currency": null, "max": null, "min": null, "period": "monthly", "term": null}, "salary_visible": false, "title_keywords": ["engineer"], "responsibilities": ["data", "configuration", "administrative support", "monitoring", "project management", "maintain", "order fulfillment", "order processing", "report"], "requirements": {"degrees": ["diploma", "degree holder"], "majors": ["related disciplines", "computer science", "information technology"], "languages": [], "language_level": [], "hard_skills": ["dns", "tcp", "switch", "hardware", "ip"], "soft_skills": ["communication skills", "work independently", "troubleshooting"], "languages_combined": []}, "experience_required": {"duration": ["2 years"], "field": ["hardware and software installation", "it networking", "troubleshooting"]}}, {"job_id": "100003009050682", "location_code": "hk", "company": "Hutchison Telecommunications (Hong Kong) Limited", "job_title": "Senior Engineer - Data Network & Packet Core Development", "description": "Responsibilities\u00a0\n\nMobile core technology development\u00a0\nMobile policy and charging technology (PCRF, PCEF, Diameter)\nNetwork enabling technology (AAA, DRA, Traffic Load Balancing)\nVendor management\nProject management\nBusiness user requirement collection\nWork with vendor to finalize the solution details\n\nRequirements\n\nBachelor degree holder in Electronic\u00a0Engineering / Computer Science / Engineering /\u00a0Telecommunication Engineering\u00a0\n5 years of relevant working experience or above, focus on Mobile Policy, Charging Technology and Network Enabling Technology.\nBiz requirement collection, project management ad vendor management.\u00a0\nProficiency in Microsoft Office\nFamiliar with Linux and Windows\nMature, self-motivated and excellent communication skill.\u00a0\nGood command of both written & spoken English and Chinese, including Mandarin.\n\nApart from competitive remuneration package and exciting opportunity for career development within the Group, we provide attractive employee benefits such as free company shuttle, free company SIM card and preferential SIM plan offers, comprehensive medical & insurance schemes, as well as full range of other employee well-being provisions.\n\nInterested parties, please apply with full resume, present and expected salary, by clicking \u201cAPPLY NOW\u201d. Please quote the reference number on the e-mail subject.\n\nWe are an equal opportunity employer and welcome applications from all qualified candidates. Personal data collected will be treated in the strictest confidence and handled confidentially by authorised personnel for recruitment-related purposes only within the CK Hutchison Group of companies. The personal data of unsuccessful applicants will be destroyed after the recruitment exercise pursuant to the requirements of the Personal Data (Privacy) Ordinance in Hong Kong.", "employment_types": ["Full Time", "Permanent"], "selling_points": [], "locations": ["Tsing Yi"], "categories": ["Engineering", "Electrical / Electronics", "Telecommunication / Wireless / Radio", "Information Technology (IT)", "Mobile / Wireless Communications"], "post_time": "2022-01-14T11:10:24Z", "salary": {"currency": null, "max": null, "min": null, "period": "monthly", "term": null}, "salary_visible": false, "title_keywords": ["senior engineer"], "responsibilities": ["project management", "management"], "requirements": {"degrees": ["bachelor degree holder"], "majors": ["engineering", "computer science"], "languages": ["english", "chinese", "mandarin"], "language_level": ["good command"], "hard_skills": ["linux", "microsoft office", "vendor", "mobile", "project management", "focus"], "soft_skills": ["self-motivated", "communication skill", "mature", "project management", "comprehensive", "focus"], "languages_combined": [{"language": "english", "language_level": ["good command"]}, {"language": "chinese", "language_level": ["good command"]}, {"language": "mandarin", "language_level": ["good command"]}]}, "experience_required": {"duration": ["5 years"], "field": ["relevant working experience"]}}, {"job_id": "100003009050097", "location_code": "hk", "company": "Worldmoney Blockchain Management Co., Limited", "job_title": "Programmer / Software Engineer", "description": "Job Responsibilities:\n\nDevelop systems/ functions according to the requirements\nPerform project implementation including documentation, coding testing\nWork closely with the project team to ensure technical compatibility and user satisfaction\nJob Requirement:\n\n\nHigher Diploma or above in IT/ Computer Science or related discipline\nExperience in C# andPython development\nExperience in Java, C++, or other programming languages is a plus\nExperience in NFT trading platform development is a plus\nKnowledge in quantitative trading is a plus\nSmart and quick learner\nPassionate, independent, and a strong sense of responsibility", "employment_types": ["Full Time"], "selling_points": ["Develop systems/ functions", "Perform project implementation", "Work closely with the project team"], "locations": ["Wan Chai"], "categories": ["Information Technology (IT)", "Application Specialist - Software", "Software Development", "Mobile / Wireless Communications"], "post_time": "2022-01-14T09:46:54Z", "salary": {"currency": null, "max": null, "min": null, "period": "monthly", "term": null}, "salary_visible": false, "title_keywords": ["software engineer", "programmer"], "responsibilities": [], "requirements": {"degrees": ["higher diploma or above"], "majors": ["it", "computer science"], "languages": [], "language_level": [], "hard_skills": ["java", "plus", "c++", "programming", "documentation", "c#"], "soft_skills": ["passionate", "independent", "quick learner", "sense of responsibility"], "languages_combined": []}, "experience_required": {"duration": [], "field": ["development", "trading", "programming"]}}, {"job_id": "100003009049375", "location_code": "hk", "company": "HGC Global Communications Limited", "job_title": "Senior Technical Officer / Technical Officer (Blockwiring)", "description": "Job Responsibilities:\n\nTo prepare purchase order;\nTo prepare proposals to contractors for installation works;\nCoordinate internal & external stakeholders (i.e. builders, management office, contractors) for works commencement;\nSite / Progress monitoring;\nSite inspection after works completion and measurement report verification;\nData update in system and project handover.\n\nJob Requirements:\n\nDiploma holder in IT or related discipline;\n1-2 years relevant working experience;\nHands on experience in MS Office Applications ;\nGood analytical, PC / device trouble shooting, and problem solving skills;\nGood interpersonal skill and a good team player;\nMature, dynamic, work independent and self-motivated;\nGood spoken and written English and Cantonese, Mandarin a plus.\n\nWe offer competitive salary package and career development opportunity. Free company coach is provided.\u00a0 Interested parties, please quote our reference number and apply with full resume, present and expected salary, by clicking \u201cAPPLY NOW\u201d.\u00a0\n\nWe are an equal opportunity employer and welcome applications from all qualified candidates. Information provided will be treated in strict confidence and only be used for consideration of your application for the relevant post within HGC Global Communications Limited. Personal data provided by job applicants will be used strictly according to our Personal Information Collection Statement, a copy of which will be available upon written request. Information of unsuccessful candidates will be destroyed within six months.", "employment_types": ["Full Time", "Permanent"], "selling_points": ["Coordinate internal & external stakeholders", "Diploma holder in IT / related discipline", "1-2 years relevant working experience"], "locations": ["Tsing Yi"], "categories": ["Engineering", "Mechanical", "Telecommunication / Wireless / Radio", "Information Technology (IT)", "Mobile / Wireless Communications"], "post_time": "2022-01-14T08:31:47Z", "salary": {"currency": null, "max": null, "min": null, "period": "monthly", "term": null}, "salary_visible": false, "title_keywords": ["technical officer", "senior technical officer"], "responsibilities": ["installation", "management", "data", "monitoring", "measurement", "site inspection", "coordinate", "project handover", "purchase", "report"], "requirements": {"degrees": ["diploma holder"], "majors": ["it"], "languages": ["cantonese", "english", "mandarin"], "language_level": ["good"], "hard_skills": ["plus", "dynamic", "pc", "problem solving skills", "ms office"], "soft_skills": ["good team player", "self-motivated", "independent", "mature", "interpersonal skill", "hands on", "dynamic", "problem solving skills"], "languages_combined": [{"language": "cantonese", "language_level": ["good"]}, {"language": "english", "language_level": ["good"]}, {"language": "mandarin", "language_level": ["good"]}]}, "experience_required": {"duration": ["1-2 years"], "field": ["relevant working experience"]}}, {"job_id": "100003009047003", "location_code": "hk", "company": "Hong Kong Education City Limited", "job_title": "Software Engineer / Analyst Programmer / Web Application Developer", "description": "Responsibilities:\n\nDesign, implement and document Web based and mobile application services.\nAssist in system, database and architectural design according to project requirements, as well as program testing and deployment of systems.\nProvide various technical and programming supports to the project team.\nTake up any other duties as assigned by supervisor or Division Head.\n\nRequirements:\n\nDegree or above in Computer Science / Information Technology or related discipline.\nAt least 2 years of experience in web based application development.\nAble to perform system analysis and design process.\nSolid knowledge in PHP, JavaScript and major Database systems such as MySQL and MongoDB.\nGood knowledge in Web based development technologies: XML, CSS, HTML5 and Ajax.\nKnowledge\u00a0in development on mobile application, Cloud computing platforms, Microsoft D365, Laravel and Vue.js is an advantage.\nGood command of spoken and written Chinese and English.\nAbility to work under pressure, proactively to meet strict deadlines.\nSelf-motivated and able to work independently.\nTeam player and positive can-do attitude.\nCandidates with less experience will also be considered as Assistant Software Engineer.\n\n\nWe provide attractive remuneration and fringe benefits to the right candidates:\n\n5-day workweek\n14 Days Annual Leave + 7 days seniority annual leave\nPerformance Incentive\nMedical and Dental Insurance\u00a0(Including dependents)\nAnnual Health Check-up Benefit\nLife Insurance\nEmployer MPF Voluntary Contribution (No cap)\nTraining Subsidies\n\n\nInterested parties looking for a promising career, please send your application letter and resume stating your academic result in public examination(s), current and expected salary\u00a0\u00a0by clicking \"Apply Now\" on or before 27 January\u00a02022.\n\nPersonal data provided will be used strictly for recruitment and other employment-related purposes. Details of the Personal Information Collection Statement - Recruitment of the Company can be found at https://www.hkedcity.net/hq/recruit/statement\n\nApplicants please submit one application for each post. Applicants not invited for interview after 8 weeks from the closing date may consider their applications unsuccessful. The Company reserves the right not to fill the post(s).", "employment_types": ["Full Time"], "selling_points": [], "locations": ["Shatin Area"], "categories": ["Information Technology (IT)", "Application Specialist - Software", "Software Development", "Mobile / Wireless Communications"], "post_time": "2022-01-14T02:01:12Z", "salary": {"currency": null, "max": null, "min": null, "period": "monthly", "term": null}, "salary_visible": false, "title_keywords": ["software engineer", "developer", "analyst programmer"], "responsibilities": ["project requirements", "any other duties", "systems", "design", "testing", "database"], "requirements": {"degrees": ["degree or above"], "majors": ["computer science", "information technology"], "languages": ["english", "chinese"], "language_level": ["good command"], "hard_skills": ["computing platforms", "web", "php", "analysis", "mobile", "javascript", "ajax", "css"], "soft_skills": ["self-motivated", "work independently", "can-do attitude", "team player", "positive", "work under pressure"], "languages_combined": [{"language": "english", "language_level": ["good command"]}, {"language": "chinese", "language_level": ["good command"]}]}, "experience_required": {"duration": ["at least 2 years"], "field": ["application development"]}}, {"job_id": "100003009050678", "location_code": "hk", "company": "Hutchison Telecommunications (Hong Kong) Limited", "job_title": "System Analyst (Digital Workforce & Contact Center)", "description": "Responsibilities:\n\nGather and analyze user requirements\nCommunicate effectively with users and vendors to understand business requirements, and follow up during SDLC\nPerform system design, development & testing on IT application using Java, Javascript and Oracle SQL\nPerform system support, development & maintenance, testing and deployment on 3ichat, whatsapp portal, MCPM, CS survey and Room booking systems\u00a0\nPerform daily IT application support\n\nRequirements:\n\nDegree / higher Diploma holder in Information Technology, Computer Science, Computer studies or related discipline\nMinimum 6-8 years working exp. in Telecom / IT system development and maintenance\nDevelopment exp. with Java, React JS, Spring boot, J2EE, Servlet, Javascript, Web service, Oracle RDBMS, Oracle PL/SQL, UNIX shell script\u00a0\nAdditional skills and knowledge on docker, Tomcat, WebLogic, MySQL, Windows / Linux / Unix Server OS, IT architecture is an advantage\u00a0\nStrong analytical and problem solving skills\nGood interpersonal skill and a good team player\u00a0\nMature, dynamic, work independent and self-motivated\u00a0\nFluent in spoken and written English and Cantonese, Mandarin is a plus\n\nApart from competitive remuneration package and exciting opportunity for career development within the Group, we provide attractive employee benefits such as free company shuttle, free company SIM card and preferential SIM plan offers, comprehensive medical & insurance schemes, as well as full range of other employee well-being provisions.\n\nInterested parties, please apply with full resume, present and expected salary, by clicking \u201cAPPLY NOW\u201d. Please quote the reference number on the e-mail subject.\n\nWe are an equal opportunity employer and welcome applications from all qualified candidates. Personal data collected will be treated in the strictest confidence and handled confidentially by authorised personnel for recruitment-related purposes only within the CK Hutchison Group of companies. The personal data of unsuccessful applicants will be destroyed after the recruitment exercise pursuant to the requirements of the Personal Data (Privacy) Ordinance in Hong Kong.\n", "employment_types": ["Full Time", "Permanent"], "selling_points": [], "locations": ["Tsing Yi"], "categories": ["Information Technology (IT)", "Network & System", "Technical / Functional Consulting", "Mobile / Wireless Communications"], "post_time": "2022-01-14T11:10:23Z", "salary": {"currency": null, "max": null, "min": null, "period": "monthly", "term": null}, "salary_visible": false, "title_keywords": ["system analyst"], "responsibilities": [], "requirements": {"degrees": ["degree", "higher diploma holder"], "majors": ["computer studies", "computer science", "information technology"], "languages": ["cantonese", "english", "mandarin"], "language_level": ["fluent"], "hard_skills": ["plus", "web", "server", "java", "os", "sql", "sdlc", "javascript", "whatsapp", "dynamic", "oracle", "linux", "maintenance", "react", "system design", "deployment", "spring", "unix shell", "problem solving skills", "pl"], "soft_skills": ["good team player", "self-motivated", "independent", "mature", "interpersonal skill", "analytical and problem solving skills", "dynamic", "comprehensive"], "languages_combined": [{"language": "cantonese", "language_level": ["fluent"]}, {"language": "english", "language_level": ["fluent"]}, {"language": "mandarin", "language_level": ["fluent"]}]}, "experience_required": {"duration": [], "field": []}}, {"job_id": "100003009038234", "location_code": "hk", "company": "Centaline Data Technology Limited", "job_title": "Android Application Developer / Programmer (5-day work)", "description": "To cope with our continuous growth and business expansion, we are looking for energetic and high calibre of candidates to join.\u00a0\n\nResponsibilities:\n\nDevelop new Android apps;\nMaintain and test Android apps;\nTroubleshoot and debug\u00a0\u00a0\n\nRequirements:\n\nDiploma\u00a0or above in Computer Science, Information Technology\u00a0or related discipline;\nAt least 2 year's experience in Android app development;\nProficiency in Kotlin & Java;\nExperience in RESTful API & JSON, Git, Android app publishing;\nKnowledge on MVVM & Andriod Jetpack is an advantage;\nGood team player with communication and interpersonal skills;\nAble to work independently with strong sense of responsibility & problem solving skills;\nAble to communicate with Putonghua is an advantage;\nImmediate available is preferred;\nAttaching Android demo code within cover letter for review is an advantage\n\n- - - - - - - - - - - - - - - - - - - - - - - - - - - - - - - - - - - - - - - - - - - - - - - - - - - - - - -\u00a0\n\nInterested parties, please send full resume with CURRENT & EXPECTED SALARY to Centaline Data Technology Limited.", "employment_types": ["Full Time", "Permanent"], "selling_points": ["Diploma or above in IT with 2 year's exp.", "Develop, maintain & test Android apps", "Medical /Study allowance / Quarterly Bonus, etc"], "locations": ["Wan Chai"], "categories": ["Information Technology (IT)", "Application Specialist - Software", "Software Development", "Mobile / Wireless Communications"], "post_time": "2022-01-11T06:16:11Z", "salary": {"currency": null, "max": null, "min": null, "period": "monthly", "term": null}, "salary_visible": false, "title_keywords": ["developer", "programmer"], "responsibilities": ["maintain", "troubleshoot", "develop"], "requirements": {"degrees": ["diploma or above"], "majors": ["computer science", "information technology"], "languages": ["putonghua"], "language_level": ["advantage"], "hard_skills": ["restful api", "git", "java", "problem solving skills", "code", "kotlin", "android"], "soft_skills": ["good team player", "work independently", "sense of responsibility", "communication and interpersonal skills", "problem solving skills"], "languages_combined": [{"language": "putonghua", "language_level": ["advantage"]}]}, "experience_required": {"duration": ["at least 2 year"], "field": ["development", "publishing"]}}, {"job_id": "100003009045085", "location_code": "hk", "company": "Master Dynamic Limited", "job_title": "Senior Analyst Programmer", "description": "Responsibilities\n\nDevelop and maintain Web, Mobile Apps, Web services and Blockchain system application.\nWork closely with technical lead, PM, user experience design, software development teams follow by Agile development work flow.\nUnderstand project requirement, support system design and define test cases for development.\nProvide advice and technical documentation for system, software implementation and deployment.\nAny ad-hoc assignments as requested by the supervisor.\n\n\u00a0Requirements\n\nBachelor Degree or above in computer science, I.T. or equivalent discipline.\nAt least 3 years\u2019 practical work experience in Software Development and Information Technology.\nSolid experiences in JAVA, JavaScript, Node.js, jQuery, AngularJS, HTML, CSS, PHP, Python programming.\nSolid experiences in Restful API, Web services development\nSound knowledge in well-known Java development framework (Spring, Hibernate).\nSound knowledge and experiences in Docker, Kubernetes, DevOps and CI/CD pipeline.\nSolid experiences in relational and NoSQL databases management and development.\nFamiliar with Window server and Linux (Ubuntu).\nFamiliar with AWS/Alibaba/Huawei/Azure Cloud solution deployment and administration.\nExperience with jQuery, AngularJS, Vue, React development is a plus.\nPassionate about programming and problem-solving in a collaborative team environment.\nSelf-motivate in learning new technique and adopting industry best practice.\nGreat sense of responsibility, able to work independently.\nGood communication and interpersonal skills.\nBe a great team-player.\nCandidates with less experience may be considered as Analyst Programmer.\n\nWe offer attractive remuneration with excellent opportunities to the right\u00a0candidate.\u00a0 Interested parties please apply with detailed resume stating present and expected salary, and date of availability to us. All personal information is collected for recruitment purpose solely.", "employment_types": ["Full Time", "Permanent"], "selling_points": ["Web, Mobile Apps, Web services", "Blockchain", "System Design"], "locations": ["Shatin Area"], "categories": ["Information Technology (IT)", "Application Specialist - Software", "Mobile / Wireless Communications"], "post_time": "2022-01-13T07:07:12Z", "salary": {"currency": null, "max": null, "min": null, "period": "monthly", "term": null}, "salary_visible": false, "title_keywords": ["senior analyst programmer"], "responsibilities": ["software", "ad-hoc assignments", "teams", "user experience", "design", "develop", "agile development", "implementation", "maintain", "system design", "provide advice", "documentation"], "requirements": {"degrees": ["degree or above", "bachelor"], "majors": ["computer science"], "languages": [], "language_level": [], "hard_skills": ["plus", "azure", "jquery", "server", "java", "problem-solving", "restful api", "hibernate", "devops", "html", "aws", "javascript", "python", "linux", "php", "react", "deployment", "programming", "spring", "databases", "css", "web services"], "soft_skills": ["work independently", "sense of responsibility", "team-player", "problem-solving", "collaborative", "learning", "communication and interpersonal skills", "passionate about"], "languages_combined": []}, "experience_required": {"duration": ["at least 3 years"], "field": ["management", "development", "devops", "information technology", "software development"]}}, {"job_id": "100003009038706", "location_code": "hk", "company": "AAStocks.com Limited", "job_title": "Android Application Developer (5-day work)", "description": "Job Responsibilities:\n\nDesign and develop innovative applications on Android platforms\nUnderstand and execute technology roadmaps for applications on the Android platform\nJob Requirements:\n\nBachelor Degree in Computer Science or equivalent\nMinimum 2 years\u2019 experience in mobile applications development on Android platform\nStrong programming skills, good object-oriented programming concepts\nSolid experience in Java/Kotlin\nExperience in Flutter will be a plus\nStrong passion for mobile application development, able and willing to learn new technologies quickly\nGood critical thinking, problem solving and presentation skills\nCandidates with more experience will be considered as Senior Mobile Application Developer\nPlease click \"Apply Now\" to submit your application.\n\nPersonal data collected will be used for recruitment purpose only.", "employment_types": ["Full Time", "Permanent"], "selling_points": ["Design and develop innovative applications", "Understand and execute technology roadmaps", "Bachelor Degree in Computer Science or equivalent"], "locations": ["Kwun Tong"], "categories": ["Information Technology (IT)", "Application Specialist - Software", "Software Development", "Mobile / Wireless Communications"], "post_time": "2022-01-11T07:39:34Z", "salary": {"currency": null, "max": null, "min": null, "period": "monthly", "term": null}, "salary_visible": false, "title_keywords": ["developer"], "responsibilities": ["design and develop"], "requirements": {"degrees": ["degree", "bachelor"], "majors": ["computer science"], "languages": [], "language_level": [], "hard_skills": ["java", "plus", "problem solving", "mobile", "programming", "kotlin", "android"], "soft_skills": ["problem solving", "presentation skills", "willing to learn", "passion for"], "languages_combined": []}, "experience_required": {"duration": ["minimum 2 years"], "field": ["developer", "development"]}}, {"job_id": "100003009046829", "location_code": "hk", "company": "Global Executive Consultants Ltd.", "job_title": "Team Head \u2013 Customer Innovation (HK$70K - $85K) (Ref. No.: 25218)", "description": "Our client, a Chinese based insurance company is now urgently looking for a high caliber candidate to lead their Customer Innovation team.\n\nResponsibilities:-\n\nStrategic insights on defining the overall digital vision and lead projects for the implementation of the digital strategies\nDevelop and plan the digital initiatives with appropriate frameworks, methods and best practices from solution sourcing to delivery\nDevelop proposition development plans for innovation digital ecosystem including digital marketing strategy, channel planning, customer journey, etc.\nDrive digital customer engagement, improve of customer\u2019s online and offline experience as well as the application of customer data to improve the company's service offerings and business performance\nSupport a cross-functional strategy with marketing, branding and CRM, particularly drive progress for sales channel growth and to build a comprehensive and effective media strategy for digital proposition\nProvide adequate guidelines for the use of platform and assist in providing better customer experiences\nLiaise with internal and external stakeholders to inform the development of the latest business directions and digital initiatives\nStay abreast of the latest business strategy, technology trends and market intelligence\n\nRequirements:-\n\nDegree holder with minimum 10 years of relevant experience\nStrong digital and marketing network with solid understanding of the latest trends of digital technologies and concepts\nStrong commercial acumen and interpersonal skills\nStrong business acumen with the ability to leverage data and analytics to gain customer insights\nExcellent leadership skill in developing segment sales and communication strategies\nWith exposure in insurance industry preferred\nStrong project management skill\nExcellent of written and spoken English and Chinese (Cantonese and Mandarin)", "employment_types": ["Full Time", "Permanent"], "selling_points": ["Customer Innovation", "Value Proposition", "Insurance sector"], "locations": ["Not Specified"], "categories": ["Marketing / Public Relations", "Marketing - Brand / Product Management", "Marketing - Marketing Communication", "Information Technology (IT)", "Mobile / Wireless Communications"], "post_time": "2022-01-14T08:57:52Z", "salary": {"currency": null, "max": null, "min": null, "period": "monthly", "term": null}, "salary_visible": false, "title_keywords": [], "responsibilities": ["guidelines", "implementation", "develop", "liaise with", "digital marketing", "plan", "customer data", "digital strategies", "plans", "planning"], "requirements": {"degrees": ["degree holder"], "majors": [], "languages": ["cantonese", "english", "chinese", "mandarin"], "language_level": ["excellent"], "hard_skills": ["project management", "acumen"], "soft_skills": ["communication", "interpersonal skills", "project management skill", "business acumen", "leadership skill"], "languages_combined": [{"language": "cantonese", "language_level": ["excellent"]}, {"language": "english", "language_level": ["excellent"]}, {"language": "chinese", "language_level": ["excellent"]}, {"language": "mandarin", "language_level": ["excellent"]}]}, "experience_required": {"duration": ["minimum 10 years"], "field": ["relevant experience"]}}, {"job_id": "100003009050248", "location_code": "hk", "company": "Robert Walters (HK)", "job_title": "Java programmer (Crypto)", "description": "Our client is one of the leading crypto prop trading firm across the globe, providing coins exchange, crypto wallet and trading platform to all individuals and institutional clients. They are now looking for potential candidate to join their technology team!\n\nResponsibilities:\n* Participate in global payment system core architecture design, development, and enhancement.\n* Ensure development efficiency, concurrency stability, system optimization, performance, and maintenance sustainability\n* Carry through the implementation of various payment modules, such as exchange platform, order management, channeling, reconciliation, etc.\n* Ensure clear boundaries between different modules for further features.\n* Continuously research on edge-cutting technologies and foster business expansion and efficient iteration\n* Ensure the security, stability and performance of customers'/clients' cash accounts and transaction/payment services.\n* Coaching juniors' coding and design capabilities, and problem-solving skills.\n\nRequirements:\n* Bachelor's degree or above in computer science or other relevant disciplines.\n* Solid Java hands-on experience, familiar with Java open-source framework, such as Spring/Spring Boot, MyBatis, etc., with solid understanding in JVM.\n* Familiar with algorithmic calculation, design pattern and data architecture.\n* Expertise in database, data storage/cache technical know-how, SQL/Oracle database tuning.\n* Experience in overseas payment system, account management/client onboarding, clearing related IT project experience would be advantageous.", "employment_types": ["Full Time", "Permanent"], "selling_points": ["Global Crypto Firm", "Attractive Package", "Spring/SpringBoot etc."], "locations": ["Not Specified"], "categories": ["Information Technology (IT)", "Application Specialist - Software", "Software Development", "Mobile / Wireless Communications"], "post_time": "2022-01-14T10:01:04Z", "salary": {"currency": null, "max": null, "min": null, "period": "monthly", "term": null}, "salary_visible": false, "title_keywords": ["programmer"], "responsibilities": ["order management", "maintenance", "implementation", "design", "coding", "payment", "architecture"], "requirements": {"degrees": ["degree or above", "bachelor"], "majors": ["computer science"], "languages": [], "language_level": [], "hard_skills": ["java", "sql", "spring", "data storage", "oracle"], "soft_skills": ["hands-on"], "languages_combined": []}, "experience_required": {"duration": [], "field": ["related", "it", "account management"]}}, {"job_id": "100003009048090", "location_code": "hk", "company": "Convoy Global Holdings Limited", "job_title": "Senior/ Full Stack Developer (Digital B2B Platform)", "description": "OnePlatform, a technology-enabled financial B2B platform, provides all-around services and integrates a full range of financial products. Our mission is to accelerate the business growth of our B2B partners and unleash their potentials at ease.\n\nWe\u2019re building an energetic team in Hong Kong and we\u2019re looking for an ambitious and purpose-driven Full Stack Developer to jump on board. You will be intellectually curious, resourceful and enthusiastic, and hungry for a new challenge in a fast-paced and forward-thinking environment.\n\nResponsibilities:\n\nInvolve all aspects of the software life cycle including gathering requirements from the business, analysis of existing systems/functionality, design and implementation, all the way through to production rollout and subsequent support\nDevelop, enhance, and maintain web applications for the digital financial platform, including coding, debugging, testing for the system\nPerform system development according to functional and technical requirements\nWork closely with different teams on system integration\nHandle other ad-hoc tasks as assigned\n\n\u00a0Requirements:\n\nBachelor degree in Computer Science, Computer Engineering or other relevant disciplines.\n\n2 - 5 years of experience with Java, JavaScript, Spring Framework, Angular/AngularJS and MS SQL\nKnowledge of Scala and TypeScript is a definite advantage\nExperience with agile scrum methodology is highly preferred\nSelf-motivated, eager to learn, responsible, able to work in a team\nGood command of written and spoken English, Cantonese and Mandarin\nCandidate with more experience will be considered as Senior Full Stack Developer\n\n\u00a0We offer competitive remuneration including career prospects to the right candidate. Interested parties please send detailed resume with availability, current and expected salaries to\u00a0Human Resources Department\u00a0by clicking the\u00a0Apply Now\u00a0button and upload your CV and cover letter.\n\n(All applications will be treated in strict confidence and used for recruitment purpose within Convoy Financial Group only. All applicants will be kept for 6 months from the date of the application.)", "employment_types": ["Full Time", "Permanent"], "selling_points": ["Fintech, Digital Technology, Financial Platform", "Excellent opportunity, Energetic Environment", "New Technology, Java, AngularJS, TypeScript, Agile"], "locations": ["Wan Chai"], "categories": ["Information Technology (IT)", "Application Specialist - Software", "Software Development", "Mobile / Wireless Communications"], "post_time": "2022-01-14T04:46:51Z", "salary": {"currency": null, "max": null, "min": null, "period": "monthly", "term": null}, "salary_visible": false, "title_keywords": ["developer"], "responsibilities": ["software", "analysis", "systems", "teams", "implementation", "design", "develop", "coding", "testing", "ad-hoc tasks", "maintain"], "requirements": {"degrees": ["degree", "bachelor"], "majors": ["computer engineering", "computer science"], "languages": ["cantonese", "english", "mandarin"], "language_level": ["good command"], "hard_skills": ["java", "agile", "scala", "javascript", "typescript", "angular", "spring", "ms sql"], "soft_skills": ["eager to learn", "self-motivated", "agile", "responsible"], "languages_combined": [{"language": "cantonese", "language_level": ["good command"]}, {"language": "english", "language_level": ["good command"]}, {"language": "mandarin", "language_level": ["good command"]}]}, "experience_required": {"duration": ["2 - 5 years"], "field": ["sql", "developer"]}}, {"job_id": "100003009045221", "location_code": "hk", "company": "Cornerstone Global Partners", "job_title": "Junior Software Engineer (Top tier Bank)", "description": "Overview:\n\nAs a Junior Software Developer, you will be supervised by a senior development professional and the RTB team-lead, both of whom have extensive expertise in the financial business and in the use of technology;\nCreate solutions that help all aspects of the company;\nWhether on-premises or in the cloud, build and deploy system improvements, scripts, tools, and APIs to production;\nThe majority of the enhancements will focus on monitoring integrations, automated recoveries, and work flow optimization;\nYou'll be interacting with end-users and the development community on a daily basis;\nGain an understanding of the various technologies in our stack (PostgreSQL, MongoDB, ActiveMQ, gRPC, Kafka, Kotlin, Python, C#, React, and so on) as well as how to develop software to a professional quality;\nGain knowledge on how to maintain a stable and secure environment;\nGain an understanding of how a hedge fund functions.\n\nRequirements:\n\nSystem administration experience at a financial institution with growth capabilities of up to 3 years. Applicants who will be graduating in 2021 and have worked in the financial sector are encouraged to apply;\nA bachelor's degree in computer science or an equivalent degree with software development experience is required;\nExperience with object-oriented programming in at least one of the following languages: Kotlin, Java, C#, or Python. A strong suit is web development, particularly with React;\nExperience with AWS and/or Azure public cloud services is desired;\nAbility to operate under duress in order to produce value in the face of real-world limitations;\nConfident in technical communication and willing to explore different methods and best practices;\nTakes the effort to seek out better long-term solutions while sticking to short-term ones;\nEnglish proficiency is required, as is the ability to communicate complex concepts clearly to a non-technical audience vocally or in writing.", "employment_types": ["Full Time"], "selling_points": ["fresh grad welcome (CS/IS major)", "gd starting point as a software engineer", "young culture+ exposure in banking"], "locations": ["Central & Western Area"], "categories": ["Information Technology (IT)", "Application Specialist - Software", "Software Development", "Mobile / Wireless Communications"], "post_time": "2022-01-13T07:26:58Z", "salary": {"currency": null, "max": null, "min": null, "period": "monthly", "term": null}, "salary_visible": false, "title_keywords": ["software engineer", "junior"], "responsibilities": ["software", "system improvements", "monitoring", "quality", "develop", "communication", "maintain", "deploy", "administration"], "requirements": {"degrees": ["degree", "bachelor"], "majors": ["computer science"], "languages": ["english"], "language_level": ["proficiency"], "hard_skills": ["java", "web development", "azure", "react", "aws", "kotlin", "programming", "python", "focus", "c#"], "soft_skills": ["confident", "communication", "focus", "extensive", "stable"], "languages_combined": [{"language": "english", "language_level": ["proficiency"]}]}, "experience_required": {"duration": ["3 years"], "field": ["software development", "programming", "financial", "administration"]}}, {"job_id": "100003009036119", "location_code": "hk", "company": "Red Soldier Limited", "job_title": "Frontend Web / Mobile App Developer", "description": "Highlights\n* For developers who love to work with a passionated team\n* Develop both Web and Mobile App\n* Coached by senior developers\n* Learn the cutting edge technology\n\nWhat we use\n* Web: ReactJS, VueJS\n* Mobile: Swift, Kotlin, ReactNative\n* Backend: Python, NodeJS\n* DB / Cache: MySQL, Datastore, MongoDB, Redis, Elastic Search\n* DevOps: docker, kubernetes\n* Tools: Trello, JIRA, Github, overflow.io, zeplin.io\n\nKey responsibilities\n* Work closely with designers and other developers to create modern web / and mobile apps.\n* Keep up-to-date on the latest frontend related technology and technique\n* Responsible for web and mobile application development, enhancement and maintenance\n* Work as a team to develop high quality products.\n\nRequirements\n* Experienced in Web / iOS / Android native development\n* Basic knowledge of multi-threading\n* Experienced in React Native is a PLUS\n* Love Programming. Enjoy Programming. Willing to take challenges.\n* Degree / Higher Diploma in Computing, Computer Science, Information Technology or related disciplines\n* Love to work in a small team with agility\n* Fresh graduates will be considered.\n* Candidates with 4 years or more frontend applications development experience can be considered as Senior Developer\n* Any special skills or experience which can expand the skill set of our company is highly valued\n\nBenefits\n* Free coffee, drinks and snacks\n* 5-day work\n* Birthday leave\n* Performance Bonus\n* Medical insurance\n* Spectacles subsidy\n* Working with a great team\n* Monthly Boutir shopping Voucher\n\nFor more information about RedSo, find us on youtube.\u00a0\n\nYou may download and try out our current highlighted products (boutir.com/app)\n(Job Reference No. R202201_FE)", "employment_types": ["Full Time"], "selling_points": ["Great Team, Growing Company, Love Programming", "Develop both Web and Mobile App", "Coached by senior developers"], "locations": ["Ngau Tau Kok"], "categories": ["Information Technology (IT)", "Application Specialist - Software", "Software Development", "Mobile / Wireless Communications"], "post_time": "2022-01-10T09:24:26Z", "salary": {"currency": null, "max": null, "min": null, "period": "monthly", "term": null}, "salary_visible": false, "title_keywords": ["developer"], "responsibilities": ["application development", "quality", "maintenance", "develop"], "requirements": {"degrees": ["diploma", "degree"], "majors": ["related disciplines", "computer science", "information technology"], "languages": [], "language_level": [], "hard_skills": ["small", "plus", "basic", "web", "react native", "programming", "android"], "soft_skills": [], "languages_combined": []}, "experience_required": {"duration": ["4 years"], "field": ["developer", "development"]}}, {"job_id": "100003009038430", "location_code": "hk", "company": "Ricacorp Properties Limited", "job_title": "Mobile App Developer", "description": "Responsibilities\nSupport the entire application lifecycle (concept, design, test, release and support)\nProduce fully functional mobile applications writing clean code\nGather specific requirements and suggest solutions\nWrite unit and UI tests to identify malfunctions\nTroubleshoot and debug to optimize performance\nDesign interfaces to improve user experience\nLiaise with Product development team to plan new features\nEnsure new and legacy applications meet quality standards\nResearch and suggest new mobile products, applications and protocols\nStay up-to-date with new technology trends\nRequirements\nProven work experience as a Mobile developer\nDemonstrable portfolio of released applications on the App store or the Android market\nIn-depth knowledge of at least one programming language like Swift and Java\nExperience with third-party libraries and APIs\nExperience with Firebase is preferred\nKnowledge on cross-platform SDK, like React Native and Flutter is an advantage\nFamiliarity with OOP design principles\nExcellent analytical skills with a good problem-solving attitude\nAbility to perform in a team environment\nBSc degree in Computer Science or relevant field", "employment_types": ["Full Time"], "selling_points": ["Seasonal bonus", "Birthday leave", "Education allowance"], "locations": ["Wan Chai"], "categories": ["Information Technology (IT)", "Mobile / Wireless Communications"], "post_time": "2022-01-11T06:52:31Z", "salary": {"currency": null, "max": null, "min": null, "period": "monthly", "term": null}, "salary_visible": false, "title_keywords": ["developer"], "responsibilities": ["quality", "user experience", "design", "troubleshoot", "plan", "liaise with", "ui"], "requirements": {"degrees": ["degree", "bsc"], "majors": ["computer science"], "languages": [], "language_level": [], "hard_skills": ["java", "problem-solving", "analytical skills", "mobile", "react native", "programming", "swift", "android"], "soft_skills": ["problem-solving", "analytical skills"], "languages_combined": []}, "experience_required": {"duration": [], "field": ["developer"]}}, {"job_id": "100003009047118", "location_code": "hk", "company": "Zero Finance Hong Kong Limited", "job_title": "IT Business Analyst", "description": "In this role, you will perform:\n\nManage business requirements gathering, analysis and documentation. Act as a bridge between business users, technical team and vendors to ensure the business requirements well address business needs\nDevelop, review, and edit requirements, specifications, business processes and recommendations related to a proposed solution\nWork closely with development team and external vendors to ensure the requirements can be completed timely.\nPrepare test plans, conduct testing, coordinate UAT and provide user training.\nProvide technical support to Sales / Business Unit team on product development, pre- and post-sales process\n\nTo be successful in this role, you should meet the following requirements:\u00a0\n\nDiploma holder or above in Computer Science / Information Technology or other related disciplines\nPreferably 1 to 3 years relevant experience\nKnowledge in banking / finance operations and mobile technology is a plus\nProficiency in design and prototyping tools, ideally MS Office, Axrue RP, MS Visio\nPractical experience in analyzing and verifying user requirements versus business processes to develop programmable documents\nGood command of written and spoken English and Chinese (including Putonghua)\nSelf-motivated, positive, able to work under pressure with emphasis on deliverables\nGood communication and interpersonal skills\n\n\n\nCompany Website:\u00a0https://www.zerofinance.hk/zh/\u00a0\n\nAttractive remuneration package will be offered to the right candidate. Please apply with full resume stating present and expected salary to us by\u00a0clicking\u00a0\u201cAPPLY NOW\u201d.\n\n(Personal data collected will be used for recruitment purpose only.)", "employment_types": ["Full Time", "Permanent"], "selling_points": ["IT Business Analyst", "Design and prototyping tools", "Knowledge in banking / finance operations"], "locations": ["Sheung Wan"], "categories": ["Professional Services", "Business Analysis / Data Analysis", "Information Technology (IT)", "Product Management / Business Analyst", "Mobile / Wireless Communications"], "post_time": "2022-01-14T02:22:43Z", "salary": {"currency": null, "max": null, "min": null, "period": "monthly", "term": null}, "salary_visible": false, "title_keywords": ["business analyst"], "responsibilities": ["uat", "technical support", "analysis", "review", "design", "develop", "testing", "coordinate", "finance operations", "specifications", "communication", "recruitment", "banking", "documentation", "plans", "personal data", "company website", "work under pressure"], "requirements": {"degrees": ["diploma holder"], "majors": ["related disciplines", "computer science", "information technology"], "languages": ["putonghua", "english", "chinese"], "language_level": ["good command"], "hard_skills": ["plus", "analysis", "mobile", "documentation", "ms office"], "soft_skills": ["self-motivated", "timely", "communication and interpersonal skills", "positive", "work under pressure"], "languages_combined": [{"language": "putonghua", "language_level": ["good command"]}, {"language": "english", "language_level": ["good command"]}, {"language": "chinese", "language_level": ["good command"]}]}, "experience_required": {"duration": ["1 to 3 years"], "field": ["business", "relevant experience"]}}, {"job_id": "100003009044030", "location_code": "hk", "company": "Hong Kong Sheng Kung Hui Welfare Council Limited", "job_title": "System Support Engineer \u7cfb\u7d71\u652f\u63f4\u5de5\u7a0b\u5e2b (CA/SSE/20211217-3)", "description": "Creating Brighter Futures\n\nThe Welfare Council always keep abreast of the times and introduce technology integration in social services. The motto of our Information Technology Services Department is\u00a0\"Dare to Dream, Dare to Do\" (\u300c\u6562\u60f3\ufe52\u6562\u505a\u300d)\u00a0to provide world class product to our customers.\n\nDue to our rapid development, we are now launching a new round of recruitment, and inviting passionate, people-oriented and creative persons, who are committed in providing high quality professional information technology services to users.\n\nFor further information about the Welfare Council, please visit our website at\u00a0http://www.skhwc.org.hk/.\n\nJob Responsibilities:\n\n\nTo provide phone, remote and onsite support to Council Users, external customers and council events\nCarry out daily system & network administration, and application support\nMaintain system and network documentation\nProject planning and implementation\nUser training\nPerform assigned tasks\n\nRequirements:\n\nDegree in Computer Science or related subject\n3 to 5 years of solid experience in technical support, installation and administration for computing devices, network equipment and server (Windows + Linux)\nHolder of CCNA and MCSE is highly preferable\nGood spoken and written skills in English and Chinese\nGood team player and able to solve problem independently\nProactive, well discipline, hardworking and willing to learn\n\nRemuneration packages will commensurate with qualifications and experience. Interested parties please apply with full curriculum vitae with\u00a0Expected Salary and Available Date\u00a0clicking\u00a0\"Apply Now\".\n\nAll applications will be treated in strict confidence for the recruitment purpose only. Candidates not invited for interview within 8 weeks may consider their applications unsuccessful, and the application papers will be retained for a maximum period of 6 months.", "employment_types": ["Full Time", "Contract"], "selling_points": [], "locations": ["Sai Wan Ho"], "categories": ["Information Technology (IT)", "Support", "Network & System", "Mobile / Wireless Communications"], "post_time": "2022-01-13T18:54:54Z", "salary": {"currency": null, "max": null, "min": null, "period": "monthly", "term": null}, "salary_visible": false, "title_keywords": ["system support", "engineer"], "responsibilities": ["network administration", "project planning", "implementation", "maintain", "documentation"], "requirements": {"degrees": ["degree"], "majors": ["computer science"], "languages": ["english", "chinese"], "language_level": ["good"], "hard_skills": ["server", "linux", "ccna", "mcse"], "soft_skills": ["good team player", "independently", "willing to learn", "proactive", "hardworking"], "languages_combined": [{"language": "english", "language_level": ["good"]}, {"language": "chinese", "language_level": ["good"]}]}, "experience_required": {"duration": ["3 to 5 years"], "field": ["installation", "administration"]}}, {"job_id": "100003009038708", "location_code": "hk", "company": "AAStocks.com Limited", "job_title": "iOS Application Developer (5-day work)", "description": "Job Responsibilities:\n\nDesign and develop innovative applications on iOS platforms\nUnderstand and execute technology roadmaps for applications on the iOS platform\nJob Requirements:\n\nBachelor Degree in Computer Science or equivalent\nMinimum 2 years\u2019 experience in mobile applications development on iOS platform\nStrong programming skills, good object-oriented programming concepts\nSolid experience in Objective-C/Swift\nExperience in Flutter will be a plus\nStrong passion for mobile application development, able and willing to learn new technologies quickly\nGood critical thinking, problem solving and presentation skills\nCandidates with more experience will be considered as Senior Mobile Application Developer\nPlease click \"Apply Now\" to submit your application.\n\nPersonal data collected will be used for recruitment purpose only.", "employment_types": ["Full Time", "Permanent"], "selling_points": ["Design and develop innovative applications", "Understand and execute technology roadmaps", "Bachelor Degree in Computer Science or equivalent"], "locations": ["Kwun Tong"], "categories": ["Information Technology (IT)", "Application Specialist - Software", "Software Development", "Mobile / Wireless Communications"], "post_time": "2022-01-11T07:39:35Z", "salary": {"currency": null, "max": null, "min": null, "period": "monthly", "term": null}, "salary_visible": false, "title_keywords": ["developer"], "responsibilities": ["design and develop"], "requirements": {"degrees": ["degree", "bachelor"], "majors": ["computer science"], "languages": [], "language_level": [], "hard_skills": ["plus", "objective-c", "problem solving", "mobile", "programming", "swift"], "soft_skills": ["problem solving", "presentation skills", "willing to learn", "passion for"], "languages_combined": []}, "experience_required": {"duration": ["minimum 2 years"], "field": ["developer", "development"]}}, {"job_id": "100003009042749", "location_code": "hk", "company": "SmarTone Telecommunications Limited", "job_title": "Project Engineer / Project Manager", "description": "Responsibilities:\n\nResponsible for full project lifecycle with vendor management\nDefine project scope and communicate effectively to cross functional team.\nDevelop, track and update project status using appropriate project management techniques and tools (e.g. meetings, status tracking tools)\nIdentify project issues and risk, and develop projects scopes, plans, schedules and budget\nManage resources and risks, escalate potential issues to management\nProactively drive solutions to problems while involving key stakeholders\nAssist to design future process model and to build business and system requirements\nWork closely with various stakeholders to provide professional advices and recommendations on development and deployment of solutions\nTo obtain appropriate information necessary for the proper carrying out and completion of the project in accordance with the contract conditions\n\nRequirements:\n\n\nDegree holders or above in Computer Science, IT or related disciplines\nOver 3 years' experience in customer project management\nSound knowledge in network, enterprise and IoT solution with customization experience\nExcellent communications and interpersonal skills\nClose attention to details and ability to handle multi-tasks\nSelf-starter/highly motivated team player\nGood command of written and spoken Chinese and English\nPMP Certified\nCertificate Holders of CCNA / CCNP / MCSE or cloud services would be advantage\nExperience in building services or construction field is a plus\n\nInterested parties please apply with full resume stating our reference code, present and expected salary by clicking \"Apply Now\"\u00a0via JobsDB\n\nYou are welcome to visit our website :\u00a0www.smartone.com\u00a0\n\nSmarTone is an equal-opportunity employer. All data supplied will be kept in strict confidence and will be used for employment related purpose. We may transfer such data to any agent, contractor or third party who provides services to us with respect to matters relating to your application. Only short-listed candidates will be contacted.", "employment_types": ["Full Time", "Permanent"], "selling_points": ["Manage project lifecycle with vendor management", "Customer project management", "Experience in IoT & network cabling is a plus"], "locations": ["Ngau Tau Kok"], "categories": ["Information Technology (IT)", "IT Project Management / Team Lead", "Network & System", "Mobile / Wireless Communications"], "post_time": "2022-01-12T08:39:47Z", "salary": {"currency": null, "max": null, "min": null, "period": "monthly", "term": null}, "salary_visible": false, "title_keywords": ["project manager", "project engineer"], "responsibilities": ["management", "schedules", "budget", "design", "develop", "project management", "plans", "tracking"], "requirements": {"degrees": ["certificate", "degree"], "majors": ["related disciplines", "it", "computer science"], "languages": ["english", "chinese"], "language_level": ["good command"], "hard_skills": ["mcse", "plus", "ccnp", "ccna", "project management", "pmp"], "soft_skills": ["multi-tasks", "project management", "motivated", "interpersonal skills", "attention to details", "team player"], "languages_combined": [{"language": "english", "language_level": ["good command"]}, {"language": "chinese", "language_level": ["good command"]}]}, "experience_required": {"duration": ["3 years"], "field": ["project management", "building services", "construction"]}}, {"job_id": "100003009043690", "location_code": "hk", "company": "Primetech Technology Limited", "job_title": "Network Consultant / Network Engineer (Junior )", "description": "Summary:\n\nWe are currently seeking Network Consultant /\u00a0Network Engineer, to be located in Hong Kong. The position will be responsible for deploy and support\u00a0network infrastructure. The candidate will be hired for Network\u00a0Consultant or Network\u00a0Engineer according to their working experiences and qualification.\n\nResponsibilities:\n\nPut together network designs, complete design documentations, attend project and engineering meetings, hands-on implementation, manage vendors, travel within the region, and\nProvide 1st level Network Operations support for projects.\nInstall, Configure, test, and maintain Cisco LAN/WAN, Security and Basic IPT equipment and related services\nIdentify, diagnose, and resolve network problems\nCreate and maintain comprehensive documentation for all implemented networks\nDocuments network problems and resolution for future reference\nNetwork Monitoring and Liaison with carriers for resolution\nDaily maintenance and problem resolution, operating system patches and software\nUpgrade and routine hardware configuration\n\nJob Requirements:\n\nHigher Diploma in Networking,\u00a0Information Technology or related disciplines\n1 years of working experience in Networking / Telecommunications\nCCNA/ CCNP holder is preferred\nSolid experience on Cisco product is an advantage\nSelf-motivated and willing to learn new technology\n\nCandidates with more experiences will be considered for a senior position; Less experience considered as junior level with on-job training provided", "employment_types": ["Full Time", "Temporary"], "selling_points": ["CCNA or CCNP cert holder is prefered", "5 days work", "training is provided"], "locations": ["Not Specified"], "categories": ["Engineering", "Telecommunication / Wireless / Radio", "Information Technology (IT)", "Network & System", "Mobile / Wireless Communications"], "post_time": "2022-01-13T01:31:09Z", "salary": {"currency": "HKD", "max": 34999, "min": 14000, "period": "monthly", "term": null}, "salary_visible": true, "title_keywords": ["engineer", "consultant", "junior"], "responsibilities": ["software", "maintenance", "configuration", "operations", "monitoring", "diagnose", "implementation", "design", "resolution", "hardware", "maintain", "documentation"], "requirements": {"degrees": ["diploma"], "majors": ["related disciplines", "information technology"], "languages": [], "language_level": [], "hard_skills": ["ccnp", "ccna"], "soft_skills": ["self-motivated", "willing to learn"], "languages_combined": []}, "experience_required": {"duration": ["1 years"], "field": ["telecommunications", "training"]}}, {"job_id": "100003009040238", "location_code": "hk", "company": "New Media Group Publishing Limited", "job_title": "Senior Mobile App Developer/ Mobile App Developer/Software Engineer (IOS/Android)", "description": "Job Nature:\n\nLead a team of mobile app developers\nAnalyze requirements from product owner, ux designer etc and translate the requirements to tech design for developers.\nWork with Product Owner, UX designer, Backend Team and Project manager closely to deliver quality mobile app\nResponsible for iOS and Android applications design, testing and development\nMaintenance and enhancements of existing mobile app\nKeep up with current trends in mobile app development industry\nCharacters / Qualifications:\n\nDiploma, associate degree or bachelor\u2019s degree in Computer Science or related discipline or equivalent industry experience\nMinimum 5 years relevant experience\nGood communication skills and able to translate technical concept to layman is a must\nGood Knowledge in Swift or Kotlin and App Deployment is a must\nGood Knowledge of firebase is an advantage\nKnowledge in Google Flutter would be an advantage\nFamiliar with below is a plus\n- AWS cloud\n- Git Flow\n- Mobile App Unit Test process\nExperience in handling JSON and RESTful APIs integration\nGood understanding of OOP and Design Patterns\n\nWe offer competitive salary and benefits package( 5 days work, 14 days AL up, birthday leave, medical & dental insurance) with great opportunity for career development to the successful candidate.\n\nPlease send your detailed resume and expected salary to our Human Resources Department by clicking \"Apply Now\" (please put position applied on subject line).", "employment_types": ["Full Time", "Permanent"], "selling_points": ["Responsible for app design, testing & development", "AWS cloud, Git Flow, Mobile App Unit Test process", "Great development opportunity, competitive package"], "locations": ["Kwun Tong"], "categories": ["Media & Advertising", "Others", "Information Technology (IT)", "Others", "Mobile / Wireless Communications"], "post_time": "2022-01-12T01:58:31Z", "salary": {"currency": null, "max": null, "min": null, "period": null, "term": null}, "salary_visible": false, "title_keywords": ["software engineer", "developer"], "responsibilities": ["mobile app", "maintenance", "quality", "design", "testing", "communication", "lead a team", "career development", "insurance"], "requirements": {"degrees": ["associate degree", "diploma", "degree", "bachelor"], "majors": ["computer science"], "languages": [], "language_level": [], "hard_skills": ["plus", "git", "maintenance", "integration", "aws", "mobile", "deployment", "swift", "kotlin", "android"], "soft_skills": ["communication skills", "responsible", "detailed"], "languages_combined": []}, "experience_required": {"duration": ["minimum 5 years"], "field": ["related", "relevant experience"]}}, {"job_id": "100003009045165", "location_code": "hk", "company": "Newrecs Consultancy Limited", "job_title": "Full Stack Developer (React.js/ Node.js) - Blockchain/ eCommerce", "description": "Our decent clients in Blockchain/ eCommerce field, are now expanding and looking for Full Stack Developer (React.js/ Node.js) to join their dynamic and professional team.\n\nFull Stack Developer (React.js/ Node.js)\n\n\n\nKey Responsibilities\n\nUnderstand requirements to build a user friendly application with extendable functionalities\nHands-on development on web services and/or software components\nCommunicate requests to different teams for any new APIs needed and optimization of existing APIs\nBuild UI based on design by writing clean front-end code with minimal guidance\nHandle other ad-hoc tasks as assigned\n\n\n\nRequirements\n\nDiploma or above in Computer Science / Information Technology or related disciplines\u00a0\nAt least 2 year of experience in software development\u00a0\nExperience in\u00a0React.js, Node.js, JavaScript, HTML, CSS\nFamiliar with Typescript would be an advantage\nFamiliar with iOS/Android using React Native would be an advantage\nKnowledge of Blockchain/ Crypto/ Shopify would be an advantage", "employment_types": ["Full Time", "Permanent"], "selling_points": ["Perm role with attractive package", "Blockchain/ eCommerce projects", "Full stack development with new tech exposure"], "locations": ["Not Specified"], "categories": ["Information Technology (IT)", "Application Specialist - Software", "Software Development", "Mobile / Wireless Communications"], "post_time": "2022-01-13T07:21:08Z", "salary": {"currency": null, "max": null, "min": null, "period": "monthly", "term": null}, "salary_visible": false, "title_keywords": ["developer"], "responsibilities": ["guidance", "software", "ad-hoc tasks", "teams", "design", "ui"], "requirements": {"degrees": ["diploma or above"], "majors": ["related disciplines", "computer science", "information technology"], "languages": [], "language_level": [], "hard_skills": ["blockchain", "crypto", "react", "shopify", "html", "typescript", "javascript", "react native", "css", "android"], "soft_skills": [], "languages_combined": []}, "experience_required": {"duration": ["at least 2 year"], "field": ["software development"]}}, {"job_id": "100003009040091", "location_code": "hk", "company": "SmarTone Telecommunications Limited", "job_title": "Enterprise Solution Consultant (pre-sales)", "description": "Responsibilities:\n\n\nConduct pre-sales and consultative activities\nDrive\u00a0Information and Communication Technologies (ICT) solution sales to meet departmental target via professional consultancy\nUnderstand and translate business & functional requirements into solution proposals, presentations and scope of work\nProduce technical drawing and documentation based on industry standard\nWork closely with internal departments to deliver benchmark pre-sales and post-sales support to business clients\nKeep abreast of the industries focused\u00a0ICT\u00a0development and sensibly integrate them into sales pitches and eventually a solution offer\nManage joint activities with external hardware and software vendors for ICT solution\n\nRequirements:\u00a0\u00a0\n\nUniversity graduate in Information Technology or other related disciplines\n3 years' solid working experience in either ICT Solution Pre-sales Consultancy or Project Management\nHands on experience in ICT project management with different hardware and software vendors, system integrators (SI), etc\nKnowledge and experience in IoT Solution and/or\u00a0Cyber Security Practices is an absolute advantage\nExcellent\u00a0analytical and presentation skills\nGood\u00a0command of\u00a0written and spoken English and Chinese\u00a0\n\nInterested parties please apply with full resume stating our reference code, present and expected salary by clicking \"Apply Now\"\u00a0via JobsDB or\u00a0visiting our website:\u00a0www.smartone.com/tc/about_us/careers/.\n\n\nYou are welcome to visit our website :\u00a0www.smartone.com\u00a0\n\n\nSmarTone is an equal-opportunity employer. All data supplied will be kept in strict confidence and will be used for employment related purpose. We may transfer such data to any agent, contractor or third party who provides services to us with respect to matters relating to your application. Only short-listed candidates will be contacted.", "employment_types": ["Full Time", "Permanent"], "selling_points": ["Presales Consultant (ICT solutions)", "Good presentation skill", "Basic salary with monthly incentive"], "locations": ["Ngau Tau Kok"], "categories": ["Information Technology (IT)", "Technical / Functional Consulting", "Mobile / Wireless Communications"], "post_time": "2022-01-12T01:41:31Z", "salary": {"currency": null, "max": null, "min": null, "period": "monthly", "term": null}, "salary_visible": false, "title_keywords": ["consultant", "sales"], "responsibilities": ["software", "presentations", "communication", "hardware", "documentation", "technical drawing"], "requirements": {"degrees": ["university graduate"], "majors": ["related disciplines", "information technology"], "languages": ["english", "chinese"], "language_level": ["good command"], "hard_skills": ["project management", "hardware", "cyber security"], "soft_skills": ["project management", "presentation skills", "hands on"], "languages_combined": [{"language": "english", "language_level": ["good command"]}, {"language": "chinese", "language_level": ["good command"]}]}, "experience_required": {"duration": ["3 years"], "field": ["project management", "security"]}}, {"job_id": "100003009036317", "location_code": "hk", "company": "Centaline Data Technology Limited", "job_title": "Senior / iOS Application Developer / Programmer", "description": "To cope with our continuous growth and business expansion, we are looking for energetic and high calibre of candidates to join.\u00a0\n\nResponsibilities:\n\n\u00a0Develop new mobile app;\nMaintain and test iOS apps;\nTroubleshoot and debug\u00a0\n\nRequirements:\n\nDiploma\u00a0or above in Computer Science, Information Technology\u00a0or related discipline;\nAt least\u00a03 year's experience in iOS app development;\nProficiency in Objective-C / Swift;\nExperience in RESTful API & JSON, Sourcetree, iOS app publishing;\nKnowledge on MVVM / MVC pattern is an advantage;\nGood team player with communication and interpersonal skills;\nAble to work independently with strong sense of responsibility & problem solving skills;\nAble to communicate with Putonghua is an advantage;\nImmediate available is preferred;\nAttaching iOS demo code within cover letter for review is an advantage\n\nInterested parties, please send full resume with current and expected salary by e-mail to Centaline Data Technology Limited.", "employment_types": ["Full Time", "Permanent"], "selling_points": ["Diploma or above in IT with 3 year's exp.", "Develop, maintain & test iOS apps", "Medical /Study allowance / Quarterly Bonus, etc"], "locations": ["Tsim Sha Tsui"], "categories": ["Information Technology (IT)", "Application Specialist - Software", "Software Development", "Mobile / Wireless Communications"], "post_time": "2022-01-10T10:05:51Z", "salary": {"currency": null, "max": null, "min": null, "period": "monthly", "term": null}, "salary_visible": false, "title_keywords": ["developer", "programmer"], "responsibilities": ["maintain", "mobile app", "troubleshoot", "develop"], "requirements": {"degrees": ["diploma or above"], "majors": ["computer science", "information technology"], "languages": ["putonghua"], "language_level": ["advantage"], "hard_skills": ["restful api", "objective-c", "swift", "code", "problem solving skills"], "soft_skills": ["good team player", "work independently", "sense of responsibility", "communication and interpersonal skills", "problem solving skills"], "languages_combined": [{"language": "putonghua", "language_level": ["advantage"]}]}, "experience_required": {"duration": ["at least 3 year"], "field": ["development", "publishing"]}}, {"job_id": "100003009047335", "location_code": "hk", "company": "Hong Kong Applied Science and Technology Research Institute Company Limited (ASTRI)", "job_title": "Mixed Signal / RF Circuit Design - Senior Engineer / Engineer", "description": "Reference #:\u00a0CTO/IOTSEN/14\nJob Responsibilities\nAssist in ITF R&D project as assigned\nHand on RF and electronic sub-system design\nPCB schematic design and layout optimization\nPrototypes assemble and circuit validation and failure analysis\nPrepare testing data for the deliverables, write reports documenting detail methods and results\nRequirements\nPhD holder or Master\u2019s degree in Electronic Engineering, Information Engineering, or relevant disciplines with a minimum of 3 years of related experience. Candidates with fewer experience may also be considered.\nExperiences in PCB schematic & layout design, mixed signal IC design, digital & analog signal processing\nFamiliar with EDA software such as Altium/Cadence/Mentor/Synopsys, etc.\nFamiliar with EE equipment like oscilloscope, multimeter etc.\nGood command of written and spoken English and Chinese\nApplication\n\nThe appointment will be on renewable contract terms with a competitive salary and performance-linked variable pay. Fringe benefits include paid leave, medical and dental benefits, insurance coverage and contribution to MPF. The incumbent will normally work\u00a0a five-day week.\n\nInterested candidates, please send an application (quoting Ref. No.) with a detailed resume, current and expected salary to\u00a0Talent Acquisition by clicking \"APPLY NOW\".\u00a0The resume should\u00a0not\u00a0include any sensitive personal information such as HKID or passport number, photo, etc.\u00a0\n\nPosition offer is subject to the applicant\u2019s experience and academic qualification. The application will be open until the position is filled. Only short-listed candidates will be notified. ASTRI reserves the right not to fill the position.\n\nASTRI is an Equal Opportunities Employer. Personal data provided by job applicants will be used\u00a0exclusively\u00a0for recruitment\u00a0only. For details, please refer to\u00a0Privacy - ASTRI - Hong Kong Applied Science and Technology Research Institute Company Limited, in particular section 9.", "employment_types": ["Full Time", "Contract"], "selling_points": ["Mixed Signal / RF Circuit Design", "Hand on RF and electronic sub-system design", "PCB schematic design"], "locations": ["Shatin Area"], "categories": ["Engineering", "Electrical / Electronics", "Telecommunication / Wireless / Radio", "Information Technology (IT)", "Mobile / Wireless Communications"], "post_time": "2022-01-14T02:50:59Z", "salary": {"currency": null, "max": null, "min": null, "period": "monthly", "term": null}, "salary_visible": false, "title_keywords": ["senior engineer", "engineer"], "responsibilities": ["data", "analysis", "design", "testing", "system design", "reports"], "requirements": {"degrees": ["degree", "master"], "majors": ["engineering"], "languages": ["english", "chinese"], "language_level": ["good command"], "hard_skills": ["processing", "signal"], "soft_skills": [], "languages_combined": [{"language": "english", "language_level": ["good command"]}, {"language": "chinese", "language_level": ["good command"]}]}, "experience_required": {"duration": ["minimum of 3 years"], "field": ["related", "digital", "engineering", "design"]}}, {"job_id": "100003009037019", "location_code": "hk", "company": "Syniverse Technologies Asia Pacific Ltd", "job_title": "Pre-Sales Consultant / Solutions Engineer", "description": "General Summary:\nThis position provides global pre-sales technical leadership and support in the identification, creation, and integration of solutions and strategies within a given solution area. \u00a0Incumbents work with Sales to identify opportunities, providing technical support throughout the sales process, focusing on sales closures. \u00a0They are responsible for communicating and working with Proposal and Technology teams to respond to RFXs as needed including creating documentation such as Statement of Work and Network designs. \u00a0They liaise with product managers to provide feedback and input into business requirements for future products and releases, enhancements, or customized solutions. \u00a0As operational issues arise, they will bring them to the attention of Customer Support and Operations. \u00a0They will identify customer needs and product gaps in the Company\u2019s existing portfolio and work with senior-level Solutions Engineers to define solutions.\n\nPrincipal Duties and Responsibilities:\n\u2022 Provide technical pre-sales subject matter expertise and sales support to global account teams throughout all stages of the sales cycle for a defined product set.\n\u2022 Develop and present to customers technical system solutions and associated sales proposals.\n\u2022 Act as the principal liaison on behalf of Sales with other parts of the organization regarding technical solutions associated with an opportunity in a defined solution area.\n\u2022 Assist in closing complex technical sales for a defined product set.\n\u2022 Provide frontline technical support in sales presentations, product demonstrations and system installations.\n\u2022 Drive customer /market requirements back to senior Solutions Engineer, influencing product investment plans and roadmaps.\n\u2022 Responsible for helping to achieve and exceed sales targets within assigned solution set.\n\u2022 Develop solution-specific \u201cAttack Plans\u201d for global customer segments.\n\u2022 Execute ongoing customer competitive analyses and market studies.\n\u2022 Assist sales team as technical lead in pursuit of identified revenue opportunities.\n\u2022 Prepare and deliver presentations for their assigned product/subject area at trade shows.\n\u2022 Participate on product teams for defined solution set to provide input to team concerning customer needs, market information and competitive insight.\n\nJob Requirements:\n\u2022 Degree in Engineering , Information Technology or related disciplines (or equivalent job-related experience)\n\u2022 Typically 7+ years general business experience including:\no Developing and managing product portfolios; and/or\no Proven success in organizational / technical leadership positions; and/or\no Telecommunications industry or related technology background, particularly IP networking. \u00a0Knowledges in Telecom Signalling, Roaming, Messaging, IoT and Mobile Core Networks will be an advantage.\n\u2022 Pre-sales engineering or sales support experience desirable\n\u2022 Strong leadership, analytical and organization skills\n\u2022 Good English written and verbal communications skills.\u00a0 Good Chinese written and verbal communications skills (Mandarin, Cantonese) will be an advantage.\n\u2022 Proficient in Microsoft Office applications including Word, PowerPoint, Excel\n\u2022 Strong public speaking abilities", "employment_types": ["Full Time", "Permanent"], "selling_points": ["Pre-sales technical support", "Telecom Solutions Design", "Have good command of IT and Telecom Technologies"], "locations": ["Kwun Tong"], "categories": ["Engineering", "Telecommunication / Wireless / Radio", "Sales, CS & Business Devpt", "Technical Sales / Sales Engineer", "Information Technology (IT)", "Mobile / Wireless Communications"], "post_time": "2022-01-11T01:21:15Z", "salary": {"currency": null, "max": null, "min": null, "period": "monthly", "term": null}, "salary_visible": false, "title_keywords": ["sales consultant", "engineer"], "responsibilities": ["market information", "technical support", "teams", "presentations", "develop", "sales team", "plans"], "requirements": {"degrees": ["degree"], "majors": ["related disciplines", "engineering", "information technology"], "languages": ["cantonese", "english", "chinese", "mandarin"], "language_level": ["advantage", "good"], "hard_skills": ["excel", "sales support", "microsoft office", "word", "powerpoint", "ip", "mobile"], "soft_skills": ["organization skills", "organizational", "leadership"], "languages_combined": [{"language": "cantonese", "language_level": []}, {"language": "english", "language_level": ["good"]}, {"language": "chinese", "language_level": ["good", "advantage"]}, {"language": "mandarin", "language_level": []}]}, "experience_required": {"duration": ["7+ years"], "field": ["sales support", "engineering", "related", "information technology", "business"]}}, {"job_id": "100003009034262", "location_code": "hk", "company": "SmarTone Telecommunications Limited", "job_title": "Enterprise Solution Specialist (Corporate Sales)", "description": "\u00a0Responsibilities:\n\nPromote\u00a0Mobile, Fixed and Information and Communication Technologies (ICT) Solutions to corporate clients\nExplore and develop enterprise solutions to fit the business needs of corporate clients\nDevelop sales leads, identify customer requirements and establish long term relationships with corporate accounts\nAchieve\u00a0assigned sales targets and objectives in\u00a0order to increase\u00a0the market share and\u00a0Company's revenue\u00a0\n\nRequirements:\u00a0\n\nTertiary education or above\n2 years of experience\u00a0in corporate sales or account servicing\nWith\u00a0ICT knowledge will be an advantage\nGood interpersonal and communication skills\nEnergetic, aggressive, pro-active and hardworking\nProficiency in written\u00a0and spoken English and Chinese;\u00a0knowledge in Mandarin is preferred\u00a0\n\nInterested parties please apply with full resume stating our reference code, present and expected salary by clicking \"Apply Now\" via JobsDB\n\n\nYou are welcome to visit our website :\u00a0www.smartone.com\u00a0\n\nSmarTone is an equal-opportunity employer. All data supplied will be kept in strict confidence and will be used for employment related purpose. We may transfer such data to any agent, contractor or third party who provides services to us with respect to matters relating to your application. Only short-listed candidates will be contacted.\n", "employment_types": ["Full Time", "Permanent"], "selling_points": ["Promote mobile, ICT solutions to corporate clients", "High Commission; Training will be provided", "Fresh graduates are welcome"], "locations": ["Ngau Tau Kok"], "categories": ["Sales, CS & Business Devpt", "Business Development", "Account Servicing", "Information Technology (IT)", "Mobile / Wireless Communications"], "post_time": "2022-01-10T03:03:11Z", "salary": {"currency": null, "max": null, "min": null, "period": "monthly", "term": null}, "salary_visible": false, "title_keywords": ["enterprise solution specialist", "sales"], "responsibilities": ["communication", "develop"], "requirements": {"degrees": [], "majors": [], "languages": ["english", "chinese", "mandarin"], "language_level": ["proficiency"], "hard_skills": [], "soft_skills": ["communication skills", "pro-active", "energetic", "interpersonal", "hardworking"], "languages_combined": [{"language": "english", "language_level": ["proficiency"]}, {"language": "chinese", "language_level": ["proficiency"]}, {"language": "mandarin", "language_level": []}]}, "experience_required": {"duration": ["2 years"], "field": ["corporate sales", "account servicing"]}}, {"job_id": "100003009042329", "location_code": "hk", "company": "KOS International Limited", "job_title": "Programmer/Analyst Programmer (PHP)", "description": "About The Client\n\nOur client is a fintech company that applies fintech, big data & AI technologies to develop a unique eMarketplace in APAC region. To cope with business expansion, they are seeking for multiple Analyst Programmers to join their IT team. Welcome fresh graduate!\n\nJob Description\n\nDesign, develop and implement different features across their web, mobile app and SaaS platform\nGather and analyse user requirement, support on SDLC including development, UAT and debug\nPropose and conduct new design and solutions to tackle existing issues\nMaintain and support the existing application to ensure its stability and sustainability\n\nQualifications\n\nBachelor's degree in Technology, Computer Science, Engineering or related disciplines\n1 year of programming experience in application development using PHP & MVC frameworks\nFamiliar with AngularJS/VueJS or other mobile development tools is an advantage\nSelf-initiated and a good team player\nStrong communication skills in both verbal and written English and Chinese\nFresh graduate will also be considered\n\nClick \"Apply Now\" to apply for this position or call Sharon Tsu at +852 3180 4950 for a confidential discussion. All information collected will be kept in strict confidence and will be used for recruitment purpose only.", "employment_types": ["Full Time", "Permanent"], "selling_points": ["SaaS Platform, PHP, MVC", "Kowloon Site and Closed to MTR", "Young Culture and Energetic Team"], "locations": ["Not Specified"], "categories": ["Information Technology (IT)", "Application Specialist - Software", "Software Development", "Mobile / Wireless Communications"], "post_time": "2022-01-12T07:04:38Z", "salary": {"currency": null, "max": null, "min": null, "period": "monthly", "term": null}, "salary_visible": false, "title_keywords": ["analyst programmer", "programmer"], "responsibilities": ["user requirement", "mobile app", "uat", "big data", "design", "develop", "communication", "maintain", "recruitment", "application development", "analyse"], "requirements": {"degrees": ["degree", "bachelor", "fresh graduate"], "majors": ["related disciplines", "engineering", "computer science"], "languages": ["english", "chinese"], "language_level": [], "hard_skills": ["web", "ai", "php", "mobile", "sdlc", "programming"], "soft_skills": ["communication skills", "good team player", "confidence", "unique"], "languages_combined": [{"language": "english", "language_level": []}, {"language": "chinese", "language_level": []}]}, "experience_required": {"duration": ["1 year"], "field": ["application development", "programming"]}}, {"job_id": "100003009034712", "location_code": "hk", "company": "GoAnimate Hong Kong Limited", "job_title": "Senior Engineer (Mobile)", "description": "Senior Engineer (Mobile)\n\n\nAbout the company\n\nAt\u00a0Vyond, our mission is to put the power of video in the hands of everyone.\u00a0Vyond\u00a0allows people of all skill levels in all industries and job roles to create dynamic and powerful media. With features that go\u00a0beyond\u00a0moving text and images, you can build character-driven stories or compelling data visualizations that engage audiences and deliver results.\n\nFounded as GoAnimate in 2007,\u00a0Vyond\u00a0has helped Global 2000 organizations, small businesses, and individuals produce more than 30 million videos.\n\nWith offices in Silicon Valley, Hong Kong, and Taiwan,\u00a0Vyond\u00a0employs a team of people whose creativity extends well\u00a0beyond\u00a0our office walls. We are passionate about the power of video and how it makes the static dynamic and transforms the mundane into the captivating.\u00a0\n\nVYOND\u2122 is a trademark of GoAnimate, Inc. \u00a0\n\n\nPosition Summary\u00a0\n\nResponsibilities\n- Develop features for our mobile app\n- Own small to medium projects and work under supervision\n- Lead the technical design for medium features (e.g. Features can be completed within one sprint) with guidance\n- Produce clear, concise, and standard compliant documentation\n- Produce technical specs with guidance\n- Use code reviews to filter anti patterns\n\nRequirements\n- Degree in Computer Science or related fields.\n- Experience in developing, releasing iOS (Swift) or Android (JAVA / Kotlin) applications.\n- Deep understanding of Agile processes\n- Knowledge of full stack architecture.\n- Fluent English with excellent communication skills.", "employment_types": ["Full Time"], "selling_points": ["iOS (Swift) or Android (JAVA / Kotlin)", "Computer Science or related fields", "English mandatory"], "locations": ["Sheung Wan"], "categories": ["Information Technology (IT)", "Software Development", "Others", "Mobile / Wireless Communications"], "post_time": "2022-01-10T04:02:08Z", "salary": {"currency": null, "max": null, "min": null, "period": "monthly", "term": null}, "salary_visible": false, "title_keywords": ["senior engineer"], "responsibilities": ["guidance", "mobile app", "design", "develop", "documentation"], "requirements": {"degrees": ["degree"], "majors": ["computer science"], "languages": ["english"], "language_level": ["excellent", "fluent"], "hard_skills": ["java", "agile", "swift", "kotlin", "android"], "soft_skills": ["communication skills", "deep", "agile"], "languages_combined": [{"language": "english", "language_level": ["fluent", "excellent"]}]}, "experience_required": {"duration": [], "field": ["developing"]}}, {"job_id": "100003009039143", "location_code": "hk", "company": "PastelLink Technology Limited", "job_title": "Analyst Programmer", "description": "We are expanding our team and looking for a number of passionate and talented IT related professionals to join us and support our continuously growing business. We are looking for Analyst Programmers to join us to work with our software development team for developing enterprise-grade IT solutions.\n\nResponsibility\n\nParticipate in software development of mobile apps, web or backend server\nWork closely with the team in software development cycle, including user requirement study, system analysis, development, testing and implementation\nPrepare system design and documentation of software development projects\nPrepare test plan and conduct tests for system\nAssist in maintaining production software system\nOn-site support at client\u2019s location might be required\n\nSkills & Requirements\n\nBachelor degree in Computer Science, Information Engineering or related disciplines\n2 years of experience in software development is preferred\nCandidates with more experience will be considered as senior position\nFresh graduates with passion will also be considered\nExperience with any of the following tools / libraries is preferred\nReact Native\nReact\n.NET (Core)\nExperience of any of the following would also be a plus\nHands-on experience in CI/CD tools, such as Azure DevOps, Jenkins, Maven, etc.\nHands-on experience in cloud solutions such as Microsoft Azure\nHands-on experience in MAM / MDM solutions such as Microsoft Intune\nHands-on experience in SharePoint Online or SharePoint 2019 would be a plus\nProactive problem solver\nFast learner with strong ability in planning, reporting and problem solving\nAbility to build strong collaborative and meaningful relationships with team colleagues in IT and business groups\nGood command of both spoken & written Chinese and English\n\nWe offer a competitive remuneration package to the right candidates. Interested parties please send your full resume and references of past jobs (if any) with this job reference, current and expected salary and availability by clicking [Apply Now].", "employment_types": ["Full Time", "Permanent", "Contract"], "selling_points": ["Opportunities to experience latest technologies", "Attractive packages with flexible working hours", "Experience in React Native, React or .NET"], "locations": ["Lai Chi Kok"], "categories": ["Information Technology (IT)", "Application Specialist - Software", "Software Development", "Mobile / Wireless Communications"], "post_time": "2022-01-12T10:21:22Z", "salary": {"currency": "HKD", "max": 34999, "min": 20000, "period": "monthly", "term": null}, "salary_visible": true, "title_keywords": ["analyst programmer"], "responsibilities": ["user requirement", "software", "maintaining", "analysis", "implementation", "testing", "system design", "plan", "documentation"], "requirements": {"degrees": ["degree", "bachelor"], "majors": ["related disciplines", "engineering", "computer science"], "languages": ["english", "chinese"], "language_level": ["good command"], "hard_skills": ["plus", "azure", "jenkins", "react", "devops", "problem solving", "react native"], "soft_skills": ["problem solver", "collaborative", "problem solving", "hands-on", "proactive", "fast learner"], "languages_combined": [{"language": "english", "language_level": ["good command"]}, {"language": "chinese", "language_level": ["good command"]}]}, "experience_required": {"duration": ["2 years"], "field": ["devops", "software development"]}}, {"job_id": "100003009033710", "location_code": "hk", "company": "Hutchison Telecommunications (Hong Kong) Limited", "job_title": "Graduate Engineer Programme 2022", "description": "Develop your career in 3HK and excel yourself to explore more in the new 5G era. We need more high potential talents who longed for and committed a successful career in a promising and progressive company \u2013 3HK.\n\n\nRoad to Professional\n\nIoT, Radio Frequency & smart gadgets are indivisible and evergreen technologies\nYou will start your ICT engineering career in core functions of our mobile network, which is one of the most in-demand engineering role in the industry\nWhere to go from here. Your career path could go in several directions, depending on your area of specialization in our mobile network engineering professional stream\n\nDiscover the Programme\n\n\nThe 3HK Graduate Engineer Programme features a 1-year intensive, accelerated development path for graduate talents, and equip you to become an ICT Engineering Professional.\n\nAs a start to develop your career, you will gain exposure in Radio Network & Technology Evolution, Radio Planning & Optimization, Transmission Engineering, etc.\nJob rotation with cross functional exposures to build up holistic knowledge\nProfessional knowledge transfer & project engagement bring you practical experience in applying your knowledge and hands-on delivery in functional works\nCompetencies & technical training to expedite your advancement in personal effectiveness and technical knowhow\nMentor to provide guidance & coaching\n\nDiscover Yourself\n\nAttributes\u00a0that will earn your early success as a 3HK Graduate Engineer in mobile network engineering professional team\n\nFresh graduates or graduates from recent years (Year 2019 to 2021) with Degree in Engineering disciplines\nPassionate with strong sense of responsibility\nProactive mindset with good teamwork\nGood interpersonal & communication skills\n\nDiscover More\n\nApart from the unique opportunity to fast-track your career as a GE, you will enjoy competitive remuneration package, attractive employee benefits such as free company shuttle, free company SIM card and preferential SIM plan offers, comprehensive medical & insurance schemes, as well as full range of other employee well-being provisions.\n\n\nProgramme Timeline\n\nDec 2021 \u2013 Jan 2022\u00a0 Application\nJan \u2013 Feb 2022\u00a0 \u00a0 \u00a0 \u00a0 \u00a0 \u00a0Interview assessment\nFeb \u2013 Mar 2022\u00a0 \u00a0 \u00a0 \u00a0 \u00a0 \u00a0On Board\n\n\nInterested parties, please send in your profile with your salary expectation to career@ hthk.com\u00a0\n\n\nWe are an equal opportunity employer and welcome applications from all qualified candidates. Personal data collected will be treated in the strictest confidence and handled confidentially by authorised personnel for recruitment-related purposes only within the CK Hutchison Group of companies. The personal data of unsuccessful applicants will be destroyed after the recruitment exercise pursuant to the requirements of the Personal Data (Privacy) Ordinance in Hong Kong.", "employment_types": ["Full Time", "Permanent"], "selling_points": ["Road to Professional Engineer", "Job rotation among telecom engineering functions", "Welcome recent engineering graduates (from 2019)"], "locations": ["Tsing Yi"], "categories": ["Engineering", "Electrical / Electronics", "Telecommunication / Wireless / Radio", "Information Technology (IT)", "Mobile / Wireless Communications"], "post_time": "2022-01-10T01:37:56Z", "salary": {"currency": null, "max": null, "min": null, "period": "monthly", "term": null}, "salary_visible": false, "title_keywords": ["graduate engineer"], "responsibilities": ["develop", "communication", "plan", "insurance", "provide guidance", "planning"], "requirements": {"degrees": ["degree"], "majors": ["engineering"], "languages": [], "language_level": [], "hard_skills": ["excel", "go", "mobile"], "soft_skills": ["passionate", "communication skills", "sense of responsibility", "teamwork", "unique", "committed", "hands-on", "comprehensive", "progressive", "proactive", "interpersonal"], "languages_combined": []}, "experience_required": {"duration": [], "field": []}}, {"job_id": "100003009034109", "location_code": "hk", "company": "iAsia Online Systems Limited", "job_title": "Analyst Programmer (Web / Mobile Application)", "description": "Responsibilities\n\nResponsible for\u00a0implementation of financial trading systems including development, testing, systems maintenance and support\nResponsible for designing and implementing mobile-based financial applications\nParticipate in the assigned projects and conduct project implementation\n\nRequirements\n\nAssociate Degree or Degree in Computer Science or related disciplines\n2 years or above experience in software development / Web applications / Mobile applications\nProven records in developing applications in Java, C#, .Net, Web Services is an advantage\nExperience in Mobile Development (iOS /Android) is an advantage\nKnowledge in Node.js,HTML/CSS/Javascript/JQuery/AJAX/Spring/PHP is an advantage\nBasic knowledge in database systems, preferably MS SQL servers\nEnergetic,\u00a0self-motivated, teamwork, dynamic and able to work under pressure\n\n\u00a0We Offer\n\nCareer advancement opportunities\nAttractive remuneration package\n5-day work week and bank holiday\u00a0\nCompany medical insurance, life insurance and dental insurance\nYear End Discretionary Bonus\nOn job training and training allowance\nEducation sponsorship\nFriendly working environment\nStaff Activities & Events e.g. Happy Friday Gathering, Annual Dinner, Festival Gift, Christmas Party, etc\n\nInterested parties should apply with academic qualifications, full resume, present and expected salary and availability date by click \"Apply Now\"\n\nAll information gathered will be treated in strict confidence and solely used for recruitment purposes", "employment_types": ["Full Time", "Permanent"], "selling_points": ["Friendly working environment, Discretionary Bonus", "Java, C#, .Net,Node.js, HTML, CSS, JQuery, PHP", "2 years or above exp. in software development"], "locations": ["Yau Tsim Mong Area"], "categories": ["Information Technology (IT)", "Application Specialist - Software", "Software Development", "Mobile / Wireless Communications"], "post_time": "2022-01-10T02:42:19Z", "salary": {"currency": null, "max": null, "min": null, "period": "monthly", "term": null}, "salary_visible": false, "title_keywords": ["analyst programmer"], "responsibilities": ["maintenance", "systems", "implementation", "testing", "designing"], "requirements": {"degrees": ["associate degree", "degree"], "majors": ["related disciplines", "computer science"], "languages": [], "language_level": [], "hard_skills": ["java", "web applications", "basic", "servers", "php", "jquery", "html", "mobile", "javascript", "dynamic", "spring", "ajax", "css", "web services", "ms sql", "android", "c#"], "soft_skills": ["self-motivated", "teamwork", "dynamic", "energetic", "work under pressure"], "languages_combined": []}, "experience_required": {"duration": ["2 years"], "field": ["development", "web applications", "software development"]}}, {"job_id": "100003009040760", "location_code": "hk", "company": "ORIENTAL HUMAN RESOURCES LIMITED", "job_title": "Analyst Programmer", "description": "Degree holder in Computer Science or equivalent\n2 years working experience of programming\nExperience in Java, JQuery, VB.Net, C#\nKnowledge of Mobile Apps Development is preferable\nKnowledge in Oracle Financials EBS or Oracle Developer Suite is an advantage\nStrong problem solving and analytical skills\n\n(Candidate with less experience or fresh graduates will be considered as Programmer)\n\nApplication Method\n\nWe offer 5-day work week, free shuttle bus, free parking and fringe benefits including medical scheme, discretionary bonus, public holidays together with career growth opportunities to the right candidate. Interested parties, please send full resume with expected salary to ORIENTAL HUMAN RESOURCES LIMITED by clicking \"Apply now\" ; or fax to 3600 1900 ( Please quote reference on the application letter )\n\nPersonal Information Collection Statement\n\nPersonal data collected will be treated in accordance with our Personal Data Policy and handled in strict confidence by authorized personnel for recruitment related purpose only.\n\non.cc", "employment_types": ["Full Time", "Permanent"], "selling_points": [], "locations": ["Tai Po Area"], "categories": ["Information Technology (IT)", "Application Specialist - Software", "Software Development", "Mobile / Wireless Communications"], "post_time": "2022-01-12T03:01:47Z", "salary": {"currency": null, "max": null, "min": null, "period": "monthly", "term": null}, "salary_visible": false, "title_keywords": ["analyst programmer"], "responsibilities": [], "requirements": {"degrees": ["degree holder"], "majors": ["computer science"], "languages": [], "language_level": [], "hard_skills": ["java", "oracle", "jquery", "scheme", "analytical skills", "problem solving", "mobile", "programming", "c#"], "soft_skills": ["problem solving and analytical skills"], "languages_combined": []}, "experience_required": {"duration": ["2 years"], "field": ["programming"]}}, {"job_id": "100003009041440", "location_code": "hk", "company": "HGC Global Communications Limited", "job_title": "(Senior) Engineer - Network Transmission", "description": "Roles & Responsibilities\n\n\nTo coordinate and participate in global transmission network setup in different countries.\n\nCarrying out transmission network planning, network maintenance and upgrade to ensure the highest levels of network and infrastructure availability.\nCarrying out transmission network monitoring and performing network analysis to drive network efficiency, work with external and internal parties coordinating and troubleshooting network events.\nSupporting delivery and testing of projects.\nMaintaining up-to-date network inventory records.\nRequirements\n\n\nMinimum 3 years\u2019 relevant experience in\u00a0transmission operation.\n\nHigher Diploma/Diploma in Telecommunications, Engineering or related disciplines.\nSolid knowledge of OTN,\u00a0SDH and DWDM transmission technology.\nTechnical experience in transmission systems and project implementation will be an advantage.\nKnowledge of major transmission test equipment and network operation system.\nProactive, responsible and a good team player.\nExcellent command in spoken and written English and Chinese.\n\n\n\nWe offer competitive salary package and career development opportunity. Free company coach is provided.\u00a0 Interested parties, please quote our reference number and apply with full resume, present and expected salary, by clicking \u201cAPPLY NOW\u201d.\u00a0\n\nWe are an equal opportunity employer and welcome applications from all qualified candidates. Information provided will be treated in strict confidence and only be used for consideration of your application for the relevant post within HGC Global Communications Limited. Personal data provided by job applicants will be used strictly according to our Personal Information Collection Statement, a copy of which will be available upon written request. Information of unsuccessful candidates will be destroyed within six months.", "employment_types": ["Full Time"], "selling_points": ["Global transmission network setup", "Transmission network monitoring", "Troubleshooting"], "locations": ["Chai Wan"], "categories": ["Engineering", "Telecommunication / Wireless / Radio", "Information Technology (IT)", "Network & System", "Mobile / Wireless Communications"], "post_time": "2022-01-12T03:53:06Z", "salary": {"currency": null, "max": null, "min": null, "period": "monthly", "term": null}, "salary_visible": false, "title_keywords": ["engineer"], "responsibilities": ["maintenance", "maintaining", "analysis", "infrastructure", "monitoring", "troubleshooting", "inventory", "testing", "coordinate", "internal parties", "setup", "planning"], "requirements": {"degrees": ["diploma"], "majors": ["related disciplines", "engineering"], "languages": ["english", "chinese"], "language_level": ["excellent"], "hard_skills": [], "soft_skills": ["good team player", "proactive", "responsible"], "languages_combined": [{"language": "english", "language_level": ["excellent"]}, {"language": "chinese", "language_level": ["excellent"]}]}, "experience_required": {"duration": ["minimum 3 years"], "field": ["operation", "relevant experience"]}}, {"job_id": "100003009035487", "location_code": "hk", "company": "The Hong Kong Jockey Club", "job_title": "(Senior) Business Analyst (Web Solutions & Services) (Job ref: 20007475)", "description": "The Department\n\nThe Web Solutions and Services Department is responsible for day to day execution, project management, design & development, analytics, editorial and operations of the HKJC.com and affiliated event sites. As part of the Corporate Business Planning and Programme Management, the Web Marketing and Services department, in addition to being an operational business unit, plays a critical role at web innovation and strategy formulation, aligning and binding multiple internal and external stakeholders into a long term Club wide consistent web perspective.\n\n\u00a0You will:\n\nFacilitate meetings and presentation for the requirement gathering, share ideas, findings, and solutions between business users and IT for HKJC Membership Digital projects (Members\u2019 Website, Mobile App & Portal)\nEvaluating business process, anticipating requirements, uncovering areas for improvement, and development and implementing solutions\nReview System Requirement Specification to ensure all user requirements are properly and accurately documented\nManage digital development project with IT, Web Team and Business Users and to develop innovative digital customer experiences\nFacilitate the development of the workflow, SOP and manage resources planning\nCoordinate and conduct comprehensive and exhaustive UAT\nReview the training documents and facilitate the training arrangement\nProperly plan and execute the implementation plan\nMaintain and keep track on the Project Plan\nHousekeeping the project documents\n\nYou should have:\n\nA university degree in Accounting, Finance, Business, Information Technology or Hotel Management discipline\nMinimum of 5 years relevant working experience in IT System Project / Mobile Application implementation.\u00a0Experience in Hospitality, Marketing or Call Centre industry will be an advantage.\nGood project management skills, multi-tasking and time management skills as well as a strong interest in Mobile App / Web Application development with back-end integration\nUnderstanding of the latest digital trend in the market with hands-on digital experience is an advantage\nProficiency in PowerPoint, Process Mapping Tool (Visio or Miro)\nExcellent communication and interpersonal skills with proficiency in both English and Chinese\nAbility to work independently and under pressure", "employment_types": ["Full Time"], "selling_points": ["IT System Project / Mobile Application", "Mobile App / Web Application development", "Web Solutions & Services"], "locations": ["Causeway Bay"], "categories": ["Information Technology (IT)", "Mobile / Wireless Communications"], "post_time": "2022-01-10T07:23:17Z", "salary": {"currency": null, "max": null, "min": null, "period": null, "term": null}, "salary_visible": false, "title_keywords": ["business analyst"], "responsibilities": ["ideas", "operations", "website", "design", "communication", "business process", "maintain", "plan", "application development", "mobile app", "uat", "implementation", "develop", "management", "review", "housekeeping", "project plan", "coordinate", "project management", "project documents", "planning"], "requirements": {"degrees": ["university degree"], "majors": ["hotel", "finance", "information technology", "business", "accounting"], "languages": ["english", "chinese"], "language_level": ["excellent", "proficiency"], "hard_skills": ["web solutions", "web application development", "web", "powerpoint", "project management", "mobile", "integration"], "soft_skills": ["exhaustive", "work independently", "under pressure", "responsible", "time management skills", "project management skills", "project management", "multi-tasking", "comprehensive", "hands-on", "communication and interpersonal skills", "innovative", "presentation"], "languages_combined": [{"language": "english", "language_level": ["proficiency", "excellent"]}, {"language": "chinese", "language_level": ["proficiency", "excellent"]}]}, "experience_required": {"duration": ["minimum of 5 years"], "field": ["development", "relevant working experience", "business", "it", "marketing", "digital", "team"]}}, {"job_id": "100003009038886", "location_code": "hk", "company": "CL Technical Services Ltd.", "job_title": "Project Manager, Over $65K", "description": "Responsibilities:\n\nSupervise in-house and/or contractor teams to perform enhancement and maintenance of the backend systems,\nApplication Programming Interfaces (APIs), and Mobile Apps including but not\u00a0limited to authentication, form filling, notification and digital signing to facilitate online services\nProvide technical advice and assistance to organizations in API\nPerform quality assurance on all deliverables of contractor teams\nReport to a Senior Systems Manager and perform any other duties assigned by the supervisor\n\n\nRequirement Details:\n\nHigher Diploma / Degree or above in Information Technology or related subjects\n8 years of relevant working experience\nAt least 2 years of experience on application development with API, cloud environments, microservices, and mobile apps\nKnowledge and experience in implementing and supporting systems using Public Key Infrastructure (PKI),\u00a0digital certificate and identity management related technologies\nExperience in project management using standard methodologies such as PRINCE or PMP\nGood understanding on system architecture and networking fundamentals, system integration,\u00a0and information security management frameworks\nStrong sense of analytical and problem solving skills\nGood command of English and writing skills\nAble to communicate in Putonghua and Simplified Chinese in technical terms with contractors\nGood communication and interpersonal skills\n\nFor more job opportunity, please visit our website: www.clts.com\n\nThe personal information collected is strictly for recruitment purpose only.", "employment_types": ["Full Time"], "selling_points": ["API, Cloud and Mobile Apps", "Monthly salary over $65K", "Location in Wanchai"], "locations": ["Wan Chai"], "categories": ["Information Technology (IT)", "Application Specialist - Software", "IT Project Management / Team Lead", "Mobile / Wireless Communications"], "post_time": "2022-01-11T08:49:12Z", "salary": {"currency": null, "max": null, "min": null, "period": "monthly", "term": null}, "salary_visible": false, "title_keywords": ["project manager"], "responsibilities": ["any other duties", "form filling", "maintenance", "technical advice", "systems", "teams", "quality", "report"], "requirements": {"degrees": ["certificate", "diploma", "degree or above"], "majors": ["information technology"], "languages": ["putonghua", "english", "chinese"], "language_level": ["good command"], "hard_skills": ["security management", "microservices", "writing skills", "mobile", "project management", "problem solving skills", "integration", "pmp"], "soft_skills": ["project management", "communication and interpersonal skills", "analytical and problem solving skills", "writing skills"], "languages_combined": [{"language": "putonghua", "language_level": []}, {"language": "english", "language_level": ["good command"]}, {"language": "chinese", "language_level": []}]}, "experience_required": {"duration": ["at least 2 years", "8 years"], "field": ["management", "related", "infrastructure", "relevant working experience", "project management", "digital", "application development"]}}, {"job_id": "100003009030003", "location_code": "hk", "company": "Sing Tao Management Services Limited", "job_title": "Software Engineer / Mobile Application Developer (iOS/Android) (New Media Business)", "description": "Responsibilities:\n\nParticipate in the entire System Development Life Cycle (SDLC)\nResponsible for mobile application development, implementation and maintenance according to specifications\nPrepare documentations including functional and technical specification\nPerform system test, assist user acceptance test and performance test\nResponsible for Agile process, DevOps, Automation Test\nConduct user training\nKeep abreast of current trends in mobile application development industry\nPerform other jobs as assigned\n\nRequirements:\n\nHigher diploma or Degree holder in Computer Science / Information Technology / Software Engineering /Multimedia or related disciplines\nAt least 2+ year experience in mobile application development\nCandidates with at least 2+ year experience in mobile application development\nFamiliar with Xcode (iOS) or Android Studio (Android) development tools and release console management Experience in design patterns MVVM and MVC\nWilling to learn new technologies in mobile industry\nStrong passion and sensitive to the trend of development in Internet and Mobile\nGood communication & interpersonal skills\nKnowledge about AWS, Alibaba or other cloud technology is an advantage\nExperience\u00a0in the digital marketing, E-commerce is an advantage\nFluent Mandarin is a plus\nWorking Location: Tseung Kwan O Industrial Estate\n\nInterested parties please click \u201cApply Now\" to submit your complete resume with\u00a0compensation history, expected salary and REFERENCE NUMBER or by\u00a0post to\u00a0Human Resources Department,\u00a03/F,\u00a0Sing Tao News Corporation Building, 7 Chun Cheong Street, Tseung Kwan O Industrial Estate, Tseung Kwan O, New Territories, Hong Kong\n\nWe are an equal opportunity employer and welcome applications from all qualified candidates. Information provided will be treated in strict confidence and only be used for recruitment related purpose. Applicant who is not invited for an interview within 6 weeks may consider their application not successful. All personal data of unsuccessful applicants will be destroyed within 6 months.\n\nwww.singtaonewscorp.com", "employment_types": ["Full Time", "Permanent"], "selling_points": [], "locations": ["Tseung Kwan O"], "categories": ["Information Technology (IT)", "Software Development", "Network & System", "Mobile / Wireless Communications"], "post_time": "2022-01-07T06:35:10Z", "salary": {"currency": null, "max": null, "min": null, "period": "monthly", "term": null}, "salary_visible": false, "title_keywords": ["software engineer", "developer"], "responsibilities": ["application development", "specifications", "implementation", "maintenance"], "requirements": {"degrees": ["diploma", "degree holder"], "majors": ["related disciplines", "software engineering", "computer science", "information technology"], "languages": ["mandarin"], "language_level": ["fluent"], "hard_skills": ["plus", "e-commerce", "android studio", "aws", "mobile", "multimedia", "android"], "soft_skills": ["communication", "sensitive to", "willing to learn", "interpersonal skills"], "languages_combined": [{"language": "mandarin", "language_level": ["fluent"]}]}, "experience_required": {"duration": ["at least 2+ year"], "field": ["management", "e-commerce", "development", "design", "digital marketing", "application development"]}}, {"job_id": "100003009036503", "location_code": "hk", "company": "Primetech Technology Limited", "job_title": "Technical Support Trainee (Kwai Chung / Airport)", "description": "Job Description:\n\nProvide technical support for desktop PCs \u2013 both software and hardware\nAssist with installation and configuration of computer systems\nPerform installation, administration, maintenance and operation of various servers and networking, system monitoring and System Upgrade\nOccasional on-site hardware and software installation/support for branch Service Units\n\nJob Requirement:\n\nDiploma/certificate\u00a0in\u00a0Information Technology\u00a0or equivalent\nFresh grad/ Passionate in I.T. filed is welcomed\nOn-work training will be provided for less experienced candidates", "employment_types": ["Full Time"], "selling_points": ["Fresh graduates are welcome", "On job training & career development provided", "5-day work"], "locations": ["Kwai Tsing Area"], "categories": ["Information Technology (IT)", "Hardware", "Support", "Mobile / Wireless Communications"], "post_time": "2022-01-10T10:46:20Z", "salary": {"currency": "HKD", "max": 19999, "min": 14000, "period": "monthly", "term": null}, "salary_visible": true, "title_keywords": ["technical support", "trainee"], "responsibilities": ["installation", "software", "maintenance", "technical support", "configuration", "pcs", "monitoring", "computer systems", "hardware", "administration"], "requirements": {"degrees": ["certificate", "diploma"], "majors": ["information technology"], "languages": [], "language_level": [], "hard_skills": [], "soft_skills": ["passionate"], "languages_combined": []}, "experience_required": {"duration": [], "field": []}}, {"job_id": "100003009040879", "location_code": "hk", "company": "Robert Walters (HK)", "job_title": "Associate Full-stack Software Engineer", "description": "Our client, one of the top performer among the field of IFP is now looking for candidate to perform software building, coding, testing and maintainance in Agile methodology.\n\nRequirements:\n\nUniversity Graduate in Computer Science preferred or equivalent professional experience\n3 to 5 years solid development experience\nFamiliarity with agile and DevOps principles, test-driven development, continuous integration, and other approaches to accelerate the delivery of new features\nGood DevOps and API skills (technologies such as JAVA/AngularJS/PCF/SprintBoot/JQuery/RabbitMQ..etc)\nHand on Experience in Cloud platform(AWS/Azure/AKS)\n\nResponsibilities:\n\nBuilds, codes, tests, maintain high quality software and complies to specifications and standards\nPromotes agile principles and methodology and participates in Agile sprints and ceremonies\nTranslates user requirements into software requirements\nDesigns, develops, tests, delivers, maintains and improves business applications as a member of a team, works across full-stack through entire software development lifecycle\nProvide coaching to teammates and squad team members\nApplies creative problem solving that bring software designs to life\nCompletes and ensures completion of any required documentation required e.g. deployment, maintenance, support and business needs", "employment_types": ["Full Time", "Permanent"], "selling_points": ["Financial Service", "Global Business", "Java/Angular JS/AWS"], "locations": ["Not Specified"], "categories": ["Information Technology (IT)", "Software Development", "Insurance", "Others", "Mobile / Wireless Communications"], "post_time": "2022-01-12T03:10:38Z", "salary": {"currency": null, "max": null, "min": null, "period": "monthly", "term": null}, "salary_visible": false, "title_keywords": ["software engineer", "associate"], "responsibilities": ["software", "maintenance", "quality", "specifications", "maintain", "documentation"], "requirements": {"degrees": ["university graduate"], "majors": ["computer science"], "languages": [], "language_level": [], "hard_skills": ["java", "pcf", "azure", "agile", "devops", "jquery", "integration"], "soft_skills": ["driven", "agile"], "languages_combined": []}, "experience_required": {"duration": ["3 to 5 years"], "field": ["development"]}}, {"job_id": "100003009038676", "location_code": "hk", "company": "Gravitas Recruitment Group", "job_title": "IT Business Analyst Up to 40k", "description": "Responsibilities:\n\n* Guide and mentor business analysts to plan requirement gathering activities/approach and achieve expected outcomes\n\n* Support project manager and scrum master to plan releases and sprints - Identify dependencies between systems, requirements and sprint outcomes\n\n* Help testing team to define a minimum viable scope across multiple systems that can be tested incrementally\n\n* Work with business leads to plan for business team resource allocation and gather support needed for the project\n\n* Ensure change requests are very minimum during later testing phases by ensuring coverage during initial scoping and requirement stages\n\n* Expected to perform hands on work for some critical and complex requirements\n\nEducation & Experience:\n\n* Around 5 years of experience in Business Analyst Role\n\n* Experience working in building or maintaining or integrating with insurance policy admin systems\n\n* Work experience and broad knowledge of digital applications and backend systems in an insurance organization\n\n* Experience leading or managing a team of business analysts\n\n* Good knowledge of insurance products.\n\n* Proven experience of multi-vendor environment and cross functional teams\n\n* Expert knowledge of complex and interdependent projects and continuous improvement methodologies, techniques, tools and controls\n\n*Agile methodology and ways of working experience\n\n* Worked on investment project is a PLUS\n\nWhat you will get in return:\n\n-Global leading Insurance Company\n\n-Opportunities to work on Large Scale Projects\n\nWe Offer You a competitive total rewards package, continuing education & training, and tremendous potential with a growing worldwide organisation. Please send an updated CV to P.chan@gravitasgroup.com for immediate consideration.", "employment_types": ["Full Time", "Permanent"], "selling_points": ["Life Insurance", "Business Analyst", "Digital Transformation"], "locations": ["Not Specified"], "categories": ["Information Technology (IT)", "IT Project Management / Team Lead", "IT Management", "Mobile / Wireless Communications"], "post_time": "2022-01-11T07:37:26Z", "salary": {"currency": "HKD", "max": 10999, "min": 0, "period": "monthly", "term": null}, "salary_visible": true, "title_keywords": ["business analyst"], "responsibilities": ["maintaining", "systems", "teams", "testing", "plan", "managing a team", "insurance"], "requirements": {"degrees": ["master"], "majors": [], "languages": [], "language_level": [], "hard_skills": ["plus", "vendor", "agile"], "soft_skills": ["hands on", "agile"], "languages_combined": []}, "experience_required": {"duration": ["5 years"], "field": ["education", "admin", "business", "digital", "managing a team", "insurance"]}}, {"job_id": "100003009034889", "location_code": "hk", "company": "Top Executive Talent Engineering", "job_title": "Developer/ Programmer (Fresh Grad welcome) 19K+/- Top General Insurance Firm", "description": "GREAT STEPPING STONE FOR IT GRADUATES\n\nJob Descriptions:\n\nl\u00a0 Develop in-house finance and insurance services related application programs\n\nl\u00a0 Assist in program testing, modification and documentation\n\nl\u00a0 Provide technical support to end users\n\nl\u00a0 Compile regular reports\n\nRequirements:\n\nl\u00a0 \u00a0University graduate in computing, information technology or related disciplines\n\nl\u00a0 Knowledge of Java, Visual Basic and web application\n\nl\u00a0 Interested in financial industry is an advantage\n\nWe offer 5-day work, discretionary bonus, medical benefits, retirement fund and public holiday, etc\n\n\n\n", "employment_types": ["Full Time", "Permanent"], "selling_points": ["Fresh IT Grad, enjoy web/ app coding", "Full on the job training provided", "Great prospect, $$ and benefits"], "locations": ["Wan Chai"], "categories": ["Information Technology (IT)", "Application Specialist - Software", "Technical Writing", "Mobile / Wireless Communications"], "post_time": "2022-01-10T04:30:26Z", "salary": {"currency": null, "max": null, "min": null, "period": "monthly", "term": null}, "salary_visible": false, "title_keywords": ["developer", "programmer"], "responsibilities": ["technical support", "testing", "develop", "reports", "documentation", "insurance"], "requirements": {"degrees": ["university graduate"], "majors": ["related disciplines", "information technology"], "languages": [], "language_level": [], "hard_skills": ["java", "visual basic", "web"], "soft_skills": ["interested in"], "languages_combined": []}, "experience_required": {"duration": [], "field": []}}, {"job_id": "100003009041441", "location_code": "hk", "company": "HGC Global Communications Limited", "job_title": "(Senior) Engineer - International IP Network", "description": "Roles & Responsibilities\nInternational IP and VPN network implementation and Operations & Maintenance\nIP and VPN services provisioning\nTechnical arrangement with overseas carrier in network interconnection implementation\nLayer 2, layer 3 and application equipment evaluation\nTier 2 fault support\u00a0\nNetwork performance review\nRequirements\n3-7 year experience in IP engineering, operations and maintenance\nHolder of CCNP or equivalent\nIn-depth and operational experience in routers and internet protocols such as BGP, OSPF, MPLS, VPLS.\nHand on experience in Layer 2 switch protocols such as spanning tree, Bridging protocol, IEEE802.3, Ethernet, VLAN, Trunking and etc.\nGood coordination of works and able to handle multiple tasks in organized and efficient manner.\nBasic understanding in SDH, PDH and TDM.\nGood communications skills with good spoken English, Mandarin and Cantonese.\n\n\n\nWe offer competitive salary package and career development opportunity. Free company coach is provided.\u00a0 Interested parties, please quote our reference number and apply with full resume, present and expected salary, by clicking \u201cAPPLY NOW\u201d.\u00a0\n\nWe are an equal opportunity employer and welcome applications from all qualified candidates. Information provided will be treated in strict confidence and only be used for consideration of your application for the relevant post within HGC Global Communications Limited. Personal data provided by job applicants will be used strictly according to our Personal Information Collection Statement, a copy of which will be available upon written request. Information of unsuccessful candidates will be destroyed within six months.", "employment_types": ["Full Time"], "selling_points": ["International IP and VPN network implementation", "Operations & Maintenance, Service provisioning", "Network performance review"], "locations": ["Chai Wan"], "categories": ["Engineering", "Telecommunication / Wireless / Radio", "Information Technology (IT)", "Network & System", "Mobile / Wireless Communications"], "post_time": "2022-01-12T03:53:06Z", "salary": {"currency": null, "max": null, "min": null, "period": "monthly", "term": null}, "salary_visible": false, "title_keywords": ["engineer"], "responsibilities": ["maintenance", "operations", "review", "implementation", "evaluation"], "requirements": {"degrees": [], "majors": [], "languages": ["cantonese", "english", "mandarin"], "language_level": ["good"], "hard_skills": ["basic", "maintenance", "switch", "ccnp", "ip"], "soft_skills": ["handle multiple tasks", "organized", "efficient", "coordination"], "languages_combined": [{"language": "cantonese", "language_level": ["good"]}, {"language": "english", "language_level": ["good"]}, {"language": "mandarin", "language_level": ["good"]}]}, "experience_required": {"duration": ["3-7 year"], "field": ["engineering", "maintenance"]}}, {"job_id": "100003009035837", "location_code": "hk", "company": "Macroview Telecom Limited", "job_title": "Senior Network Engineer / Network Engineer (Fresh Graduate Welcome)", "description": "How you will contribute:\nDevelop technical skill and product knowledge to deliver technical tasks to the customer\nDevelop soft skill to respond to customer\u2019s request and monitor the project progress\nImplement project, perform testing, install and configure equipment, contain and execute change, prepare document and provide maintenance support for customer\u2019s infrastructure and system\nProvide technical support and troubleshooting for marketing leading ICT products including network infrastructure products, network security products, collaboration solutions and cloud applications etc.\nPerform cross platform system integration & end-to-end process automation\nOpportunity in customer-centric digital solutions development\n\nWho Are We Looking For:\n\n\n\nDegree or Higher Diploma holders in Computer Science, Engineering, Information System or related disciplines\nKnowledge and experience in switches, routers, wireless equipment, firewall, cloud or collaboration/voice\nA quick learner to explore new technologies and solutions\nA good team player with good communication skills\nMore than 1 year relevant working experience in related technologies\nGood command of both written and spoken English\nDegree holders with less experience or fresh graduate can apply for Assistant Engineer\nWe offer attractive remuneration package, medical benefits and marriage leave to the right candidate. Interested parties please send full resume with expected salary by clicking 'Apply Now'.\nAll information collected will be used for recruitment purpose only.\nTo know more about Macroview, please visit:\u00a0http://www.macroview.com", "employment_types": ["Full Time", "Permanent"], "selling_points": ["Firewall, wireless, router", "Cisco, Huawei, Aruba, Arista, Fortinet, Juniper", "Fresh graduate will be considered"], "locations": ["Quarry Bay"], "categories": ["Information Technology (IT)", "Support", "Network & System", "Mobile / Wireless Communications"], "post_time": "2022-01-10T08:30:05Z", "salary": {"currency": null, "max": null, "min": null, "period": "monthly", "term": null}, "salary_visible": false, "title_keywords": ["engineer"], "responsibilities": ["network infrastructure", "technical support", "maintenance support", "infrastructure", "monitor", "project progress", "troubleshooting", "testing", "develop", "communication"], "requirements": {"degrees": ["diploma", "degree", "fresh graduate"], "majors": ["related disciplines", "engineering", "computer science"], "languages": ["english"], "language_level": ["good command"], "hard_skills": ["integration", "information system", "maintenance", "firewall"], "soft_skills": ["communication skills", "good team player", "troubleshooting", "quick learner", "technical skill"], "languages_combined": [{"language": "english", "language_level": ["good command"]}]}, "experience_required": {"duration": ["1 year"], "field": ["related", "relevant working experience"]}}, {"job_id": "100003009038193", "location_code": "hk", "company": "Anywhere Everywhere Six Degrees Link Limited", "job_title": "DevOps Engineer ( Global FinTech Company ) | Attractive Package", "description": "Job Responsibilities:\nSystems and solution design as well as the implementation of new solutions to meet market/client needs;\nAutomate and streamline operations and processes;\nBuild and extend evolving continuous delivery technology platform;\nDevelop in cloud environments such as AWS and Azure;\nContribute to system architecture design.\nRequirements:\n2+ years of deep expertise with Continuous Integrate/Delivery & Dependency Management (Maven, Git). \u00a0Candidate with more experiences will be considered as Senior DevOps Engineer;\nProficiency in DevOps tooling (Ansible, Docker Swarm, Puppet, Chef);\n2 years solid coding experience in Java and hands-on experience in bash scripting and python;\nStrong knowledge of IP networking, DNS, load balancing and CDN\u2019s;\nExperience with continuous monitoring tools, including Nagios and Splunk;\nExperience with Cloud Service Providers (CSP), including AWS and Azure;\nExperience with Apache, NGINX or similar web servers;\nExperience with using Agile software development methods in a DevOps environment;\nB.S. or M.S. in Computer Science, Engineering or equivalent;\nPassionate about new technology, motivate and fast-learner;\nStrong communication skills to both business and technical audiences.", "employment_types": ["Full Time"], "selling_points": ["Work Life Balance | 16 ALs | Bonus", "Salary : 25K - 45K + Bonus ( 1 - 2 Months )", "Friendly Environment & Clear Career Path"], "locations": ["Tsim Sha Tsui"], "categories": ["Information Technology (IT)", "Application Specialist - Software", "Software Development", "Mobile / Wireless Communications"], "post_time": "2022-01-11T05:58:54Z", "salary": {"currency": null, "max": null, "min": null, "period": "monthly", "term": null}, "salary_visible": false, "title_keywords": ["engineer"], "responsibilities": ["operations", "systems", "implementation", "design", "develop", "architecture"], "requirements": {"degrees": [], "majors": [], "languages": [], "language_level": [], "hard_skills": ["java", "git", "azure", "dns", "apache", "agile", "devops", "bash", "aws", "ansible", "ip", "csp", "python", "web servers"], "soft_skills": ["communication skills", "agile", "deep", "hands-on", "passionate about"], "languages_combined": []}, "experience_required": {"duration": ["2 years"], "field": ["devops", "software development"]}}, {"job_id": "100003009026221", "location_code": "hk", "company": "New Media Group Publishing Limited", "job_title": "Mobile App Developer ( Swift / Kotlin )", "description": "Responsibilities\n\nDevelop applications on mobile platforms (iOS and/or Android)\nResponsible for mobile application development, testing, implementation, enhancement and maintenance\nCollaborating with team members to deliver projects\nEnsure the best possible performance, quality, and responsiveness of the applications\n\nRequirements\n\nDegree / Higher Diploma / Diploma in Computer Science, Computer Engineering or related disciplines\nSolid experience in Swift (iOS) and/or Kotlin (Android)\nSolid experience in integrating with RESTful API\nHands-on experience in user behavior tracking with firebase analytics\nWell organized, disciplined and responsible with a good work ethic\nAble to work independently and be self-driven to meet project schedules\n1-2 years relevant experience in mobile application development (iOS and/or Android) is preferred, but more or less years of experience will also be considered\n\nWe offer competitive salary and benefits package( 5 days work, 14 days AL up, birthday leave, medical & dental insurance) with great opportunity for career development to the successful candidate.\n\nPlease send your detailed resume and expected salary to our Human Resources Department by clicking \"Apply Now\" (please put position applied on subject line).", "employment_types": ["Full Time", "Permanent"], "selling_points": ["Experience in Swift (iOS) and/or Kotlin (Android)", "More / less years of experience will be considered", "Great development opportunity, competitive package"], "locations": ["Kwun Tong"], "categories": ["Information Technology (IT)", "Software Development", "Others", "Mobile / Wireless Communications"], "post_time": "2022-01-06T07:39:58Z", "salary": {"currency": null, "max": null, "min": null, "period": null, "term": null}, "salary_visible": false, "title_keywords": ["developer"], "responsibilities": ["maintenance", "quality", "implementation", "testing", "develop", "application development"], "requirements": {"degrees": ["diploma", "degree"], "majors": ["related disciplines", "computer engineering", "computer science"], "languages": [], "language_level": [], "hard_skills": ["restful api", "mobile", "swift", "kotlin", "android"], "soft_skills": ["work independently", "responsible", "well organized", "hands-on", "work ethic", "driven", "detailed"], "languages_combined": []}, "experience_required": {"duration": ["1-2 years"], "field": ["application development", "relevant experience"]}}, {"job_id": "100003009015304", "location_code": "hk", "company": "Top Pine Technology Ltd", "job_title": "Mobile App Developer (Android / iOS)", "description": "Job Description\n\n\nResponsibilities:\n\n\nDevelop applications on mobile platforms (Android/iOS)\nResponsible for mobile application development, testing, implementation, enhancement and maintenance\nCollaborating with team members to deliver the projects\n\nRequirements:\n\nDegree / Higher Diploma / Diploma in Computer Science, Computer Engineering or related disciplines\nExperience in JSON, RESTful API, SQL\nExperience in Flutter is a plus\nWell organized, disciplined and responsible with a good work ethic\nA self-motivated team player with good interpersonal and communication skill\nCandidates with more or less years of experience e will also be considered\n\nInterested parties please email your full resume with availability and expected salary.\n(Personal data collected will strictly be used for recruitment purposes only)", "employment_types": ["Permanent"], "selling_points": [], "locations": ["Ngau Tau Kok"], "categories": ["Information Technology (IT)", "Mobile / Wireless Communications"], "post_time": "2022-01-03T06:29:15Z", "salary": {"currency": null, "max": null, "min": null, "period": "monthly", "term": null}, "salary_visible": false, "title_keywords": ["developer"], "responsibilities": ["maintenance", "implementation", "testing", "develop", "application development"], "requirements": {"degrees": ["diploma", "degree"], "majors": ["related disciplines", "computer engineering", "computer science"], "languages": [], "language_level": [], "hard_skills": ["sql", "restful api", "plus"], "soft_skills": ["self-motivated", "responsible", "communication skill", "well organized", "work ethic", "team player", "interpersonal"], "languages_combined": []}, "experience_required": {"duration": [], "field": ["sql"]}}, {"job_id": "100003009024078", "location_code": "hk", "company": "Manpower Services (Hong Kong) Limited", "job_title": "(Senior) Backend Engineer (in-house, up to 60K)", "description": "Job Responsibilities\n\nDeveloping backend APIs to support the mobile app functions and integrate with other existing systems\nCommunicating closely with other development teams to design the backend architecture of the app and web\nPreparing technical requirements for development, integration and testing\nIntroducing the best practice and market trends on architecture design to the company\nAny other duties assigned by management\n\nJob Requirements\n\nDegree holder in Information System, Business or other related disciplines\nMinimum 5 years of backend system programming, API development and database maintenance\nExperience in .Net programming and Microsoft related tools like MS Power Platform, SharePoint, etc.\nExperience in developing low-latency applications for mission-critical business systems would be a plus\nExperience in cloud-based software development, particularly web-based / CRM systems and fast-paced SDLC, is preferred\nDemonstrate DevOps-in-practice & Agile principles\nKnowledge in container technologies such as Docker/Kubernetes\nAn analytical mindset with good interpersonal, presentation and communication skills", "employment_types": ["Contract"], "selling_points": ["At least 5 yr exp. in backend & API development", "Experience in .Net & Cloud & DevOps implementation", "Agile/Scrum Team"], "locations": ["Southern Area"], "categories": ["Information Technology (IT)", "Application Specialist - Software", "Software Development", "Mobile / Wireless Communications"], "post_time": "2022-01-05T10:35:57Z", "salary": {"currency": null, "max": null, "min": null, "period": "monthly", "term": null}, "salary_visible": false, "title_keywords": ["engineer"], "responsibilities": ["any other duties", "management", "mobile app", "systems", "teams", "developing", "design", "testing", "architecture"], "requirements": {"degrees": ["degree holder"], "majors": ["related disciplines", "business"], "languages": [], "language_level": [], "hard_skills": ["plus", "agile", "maintenance", "web", "devops", "information system", "sdlc", "container", "programming"], "soft_skills": ["communication skills", "presentation", "interpersonal", "agile"], "languages_combined": []}, "experience_required": {"duration": [], "field": ["business", "developing", "software development"]}}, {"job_id": "100003009012927", "location_code": "hk", "company": "China Mobile Hong Kong \u4e2d\u570b\u79fb\u52d5\u9999\u6e2f", "job_title": "Project Engineer (Electrical), Home Broadband Service Provision", "description": "CHINA MOBILE HONG KONG COMPANY LIMITED (\"CMHK\") is the wholly-owned subsidiary of China Mobile Limited (HKEx: 941) (NYSE: CHL), which ranks 65th on the Fortune Global 500.\n\nOur company strives to offer superior service experience and to become the preferable digital partner for customers. We are preserving an environment with trust, responsibility and caring. At CMHK, we commit to maximizing people\u2019s potential and paving the way toward success for every striver. We are now inviting high caliber professional to join us.\n\nDivision: Home Business Operation Centre / Home Broadband Service Provision\n\n\n\u00a0In this position, you will:\n\nResponsible for coordination with contractors, site inspection and assistance for solution design\nParticipate in site activities and implementation works management including task planning, scheduling and etc.\nPerform the quality control and acceptance check of contractor installation works\nBe able to manage multiple projects simultaneously. Ensure proper health, safety conduct and standards of all site operations\nProvide support to the project team. Assist in coordination of meetings, monitor project progress and etc.\nPerform ad hoc assignments as required\n\nTo be successful in this position, you should meet the following requirements:\u00a0\n\nHigher diploma or above in related disciplines;\nHolder of registered electrical worker license A or above, and green card\nBe proactive, detailed-mined, responsive and adaptable team player;\nGood command of both written and spoken English and Chinese, including Cantonese and Mandarin.\nBe proficient in MS Office. Experience with Visio and MS project is preferred.\nAt least 5 years of experience in electrical/ELV/smart home projects\nExperience in design, implement, maintenance and site supervisory works for home automation, building management, structural cabling and security projects\nProficiency/experience in Auto-CAD is an advantage\nStrong communication, analytical and negotiation skills\n\nWhen you work:\n\n\n5 days work\n8 hours/day\n\nWhat you enjoy:\n\nDouble pay\nDiscretionary Performance bonus\nLife insurance\nMedical insurance\nEducation subsidies\nBirthday gift\nMarriage leave\nBirthday leave\nStaff discount\n\nCMHK is committed to be an equal opportunity employer. We offer exceptional benefits package and the opportunity to work in a challenging environment. Personal data provided by applicants will be treated strictly in accordance with our personal data policy and for recruitment purposes only.\n\nPlease submit your application to us by clicking the APPLY NOW button and send your full resume with your availability, current and expected salary to us.", "employment_types": ["Full Time", "Permanent"], "selling_points": ["\u96fb\u5de5A/B\u724c, \u7da0\u54ad, 14 AL, 5 days work", "Double pay, Dis. Performance Bonus", "staff sim, staff offer"], "locations": ["Kwai Hing"], "categories": ["Engineering", "Telecommunication / Wireless / Radio", "Others", "Information Technology (IT)", "Mobile / Wireless Communications"], "post_time": "2022-01-02T22:53:01Z", "salary": {"currency": null, "max": null, "min": null, "period": null, "term": null}, "salary_visible": false, "title_keywords": ["project engineer"], "responsibilities": ["site activities", "operations", "coordination with", "design", "communication", "building management", "implementation", "manage multiple projects", "site inspection", "installation", "management", "provide support", "scheduling", "business operation", "monitor project progress", "maintenance", "ad hoc assignments", "quality control", "coordination", "insurance", "planning"], "requirements": {"degrees": ["higher diploma or above"], "majors": ["related disciplines"], "languages": ["cantonese", "english", "chinese", "mandarin"], "language_level": ["good command"], "hard_skills": ["maintenance", "cad", "green card", "mobile", "ms office"], "soft_skills": ["manage multiple projects simultaneously", "responsible", "adaptable", "detailed", "communication", "committed", "negotiation skills", "coordination", "team player", "proactive", "responsive", "superior"], "languages_combined": [{"language": "cantonese", "language_level": ["good command"]}, {"language": "english", "language_level": ["good command"]}, {"language": "chinese", "language_level": ["good command"]}, {"language": "mandarin", "language_level": ["good command"]}]}, "experience_required": {"duration": ["at least 5 years"], "field": ["supervisory", "management", "maintenance", "structural", "design", "security", "digital"]}}, {"job_id": "100003009025249", "location_code": "hk", "company": "PCCW Solutions", "job_title": "System Analyst / Developer - Salesforce", "description": "Summary\n\nThe successful candidate will participate in a Digital Transformation Project for the largest telecommunications company in Hong Kong \u2013 by transforming the legacy systems through the latest digital solution on agile architecture to support the next generation of CRM & Billing systems.\u00a0 The new CRM & Billing Systems will provide the first class Customer Experience via innovative functions and features.\n\nJob Duties\n\nThe candidate will be responsible for defining software frameworks, development methods and tools to support advanced digital solutions.\u00a0 He / She will be involved in developing application software and supporting frameworks with the following scope of duties:\n\nDesign and architect the end-to-end BSS solutions, including integration with other systems such as CRM, Campaign Management, Customer Data Platform, Customer Order Management, Customer Information Management, Customer 360 View, Product Catalog, Resource Management, etc.\nBuild and cultivate relationship with stakeholders including users and \u00a0senior technical individuals from both development teams and user groups\nAct as a technical liaison between users, technical teams and support\nWork with solution architect and business analyst to design the solution from scratch, including building core components, business processes, data model, integration points with other systems, interface definition and protocol.\u00a0 Define related implementation and migration plans with consideration of all functional and non-functional requirements such as access management, security, disaster recovery, reporting requirements, etc.\nLead the developers by providing guidelines and\u00a0 assistance to enable solution development and implementation, with passion to be hands-on with coding\nEnsure smooth development, implementation and migration of the whole solution\n\nThe Person\n\nBachelor\u2019s degree in Computer Science, Information Technology or related disciplines\nA minimum of\u00a06\u00a0years\u2019 experience in technical role within a service or IT organization.\u00a0\nFor Developer post with less experience, the candidate should have hands-on experience in design, prototyping, development, configurations, testing and other implementation activities.\nExperience in developing CRM system or related application(s) is a plus\nDemonstrated experience in leading and developing top-notch, enterprise grade software products with adoption of a structured system development lifecycle (such as Waterfall and agile approaches) and developing micro services and/or digital services will be an advantage\nExperience in programming applications backed by cloud services such as AWS \u00a0\nTechnical knowledge is preferred across the following areas:\nApplication Frameworks for cloud application development and integration, web/mobile digital services and APIs\nJava development (Angular 9+, JavaScript, Restful API, Springboot experience)\u00a0\nSelf-starter who can investigate and apply new technologies with minimal direction\nExperience in CRM package solution such as SalesForce or Vlocity is advantageous\nGood command of spoken and written English (and Chinese is also preferred but not essential)\nGood analytical, inter-personal and problem-solving skills\nPositive attitude, fast-learning, energetic and able to perform in stressful and challenging environment\nCandidates with less qualification and experience will be considered as Developer", "employment_types": ["Full Time"], "selling_points": [], "locations": ["Mong Kok"], "categories": ["Information Technology (IT)", "Application Specialist - Software", "Software Development", "Mobile / Wireless Communications"], "post_time": "2022-01-06T03:56:33Z", "salary": {"currency": null, "max": null, "min": null, "period": "monthly", "term": null}, "salary_visible": false, "title_keywords": ["developer", "system analyst"], "responsibilities": ["reporting", "order management", "management", "software", "data", "guidelines", "systems", "teams", "developing", "design", "implementation", "coding", "customer data", "plans", "migration", "campaign management"], "requirements": {"degrees": ["degree", "bachelor"], "majors": ["related disciplines", "computer science", "information technology"], "languages": ["english", "chinese"], "language_level": ["good command"], "hard_skills": ["plus", "java", "restful api", "agile", "web", "salesforce", "aws", "mobile", "javascript", "programming", "angular", "integration", "problem-solving skills"], "soft_skills": ["agile", "inter-personal", "fast-learning", "positive attitude", "hands-on", "energetic", "problem-solving skills", "structured"], "languages_combined": [{"language": "english", "language_level": ["good command"]}, {"language": "chinese", "language_level": ["good command"]}]}, "experience_required": {"duration": ["minimum of 6 years"], "field": ["related", "development", "digital", "developing", "design", "testing", "system development", "it", "programming", "developer"]}}, {"job_id": "100003009025341", "location_code": "hk", "company": "China Unicom (Hong Kong) Operations Limited", "job_title": "ICT Pre-sales Manager", "description": "Job Description:\n\n\u2022 Responsible for the pre-sales of ICT solutions including Cloud Computing, CDN, Data Centre, Managed Security, VoIP, IP/ SDH/ Metro Ethernet/ MPLS WAN.\n\n\u2022 Propose telecommunication and ICT solutions to Government sector, NGO, Public Utility sectors, University etc sales to cope with customer needs\n\n\u2022 Participant in the whole pre-sales cycle, including customer meeting, user requirement study, design, presentation, demonstration, proposal and the RFP/bidding phases\n\n\u2022 Work closely with Product Managers and ICT Managers to differentiate the company\u2019s solutions and assist in product marketing of technical designs\n\n\u2022 Coordinate and provide solution related training to Sales Department throughout the globe\u00a0\n\nQualification Required:\n\n\u2022 Degree or above in Telecommunications, Computer Studies, Electrical Engineering or related disciplines\n\n\u2022 5 years\u2019 experience or above in pre-sales and knowledge of ICT Project or solutions in Telecommunication/SI/Solutions provider will be an advantage\n\n\u2022 Candidates with less experiences can be considered as Executive/Specialist\n\n\u2022 Professional certificates (i.e. CCNP,CCIE, CISSP, PMP) will be advantageous\n\n\u2022 Proficiency in Visio and MS Office is a MUST\n\n\u2022 Able to maintain good working relationships with both technical and non-technical users, including the effective communication with a large user base of various levels of IT knowledge\n\n\u2022 Quick learner with superior analytic problem solving and presentation skills\n\n\u2022 Good command of both written and spoken English and Chinese, including Cantonese and Mandarin; language fluency is a prerequisite for this role\n\n\u2022 Willing to take occasionally travel", "employment_types": ["Full Time", "Permanent"], "selling_points": ["5-day work, 9am-530pm", "double pay + OT pay", "performance bonus + festival allowance"], "locations": ["Tsim Sha Tsui"], "categories": ["Information Technology (IT)", "Others", "Mobile / Wireless Communications"], "post_time": "2022-01-06T04:11:56Z", "salary": {"currency": null, "max": null, "min": null, "period": "monthly", "term": null}, "salary_visible": false, "title_keywords": ["sales manager"], "responsibilities": ["user requirement", "data", "design", "coordinate", "communication", "maintain", "working relationships"], "requirements": {"degrees": ["degree or above"], "majors": ["related disciplines", "electrical engineering", "computer studies"], "languages": ["cantonese", "english", "chinese", "mandarin"], "language_level": ["good command"], "hard_skills": ["it knowledge", "ccnp", "problem solving", "ip", "pmp", "wan", "ms office"], "soft_skills": ["responsible", "quick learner", "communication", "problem solving", "presentation skills", "presentation", "superior"], "languages_combined": [{"language": "cantonese", "language_level": ["good command"]}, {"language": "english", "language_level": ["good command"]}, {"language": "chinese", "language_level": ["good command"]}, {"language": "mandarin", "language_level": ["good command"]}]}, "experience_required": {"duration": ["5 years"], "field": []}}, {"job_id": "100003009021473", "location_code": "hk", "company": "iDigital Technology Solutions Limited", "job_title": "PHP programmer / Developer (Work from Home)", "description": "Responsibilities:\n\nResponsible for\u00a0in development, testing and implementation of web-based applications\nAssist in ad-hoc projects and data fixing\nAssist in preparing project and system documentation;\nRequirements:\n\nDiploma holder in Computer Science, IT or related disciplines\n2 years or above in IT application development experience.\nExperience in PHP / WordPress for web-based applications\nExperience in\u00a0Ionic for\u00a0mobile applications is an advantage,\u00a0No experiences will also be considered.\nDatabase running on MySQL and MSSQL.\nResponsible, a good team player with good communication skills\nAbility to work\u00a0independently\u00a0in a fast-paced environment\nOur company culture:\n\nWe treat people with courtesy, politeness, and kindness\nDon\u2019t insult people or talk behind their back.\nTreat people the same no matter their race, religion, age, etc.\nNo\u00a0Unnecessary Meetings\nEncourage other coworkers to share their valuable ideas.\nWe offer a competitive remuneration package to the right candidates. Interested parties please send your full resume, current and expected salary and availability by clicking \"Apply Now\".", "employment_types": ["Part Time", "Temporary", "Freelance"], "selling_points": ["2yrs in software development", "Flexible Working Hours, Work from Home", "PHP/ Laravel/ WordPress"], "locations": ["Not Specified"], "categories": ["Information Technology (IT)", "Application Specialist - Software", "Software Development", "Mobile / Wireless Communications"], "post_time": "2022-01-05T15:05:51Z", "salary": {"currency": null, "max": null, "min": null, "period": "hourly", "term": null}, "salary_visible": false, "title_keywords": ["developer", "programmer"], "responsibilities": ["system documentation", "data", "implementation", "testing", "ad-hoc projects"], "requirements": {"degrees": ["diploma holder"], "majors": ["related disciplines", "it", "computer science"], "languages": [], "language_level": [], "hard_skills": ["no", "php", "mobile", "wordpress", "web-based applications", "mssql"], "soft_skills": ["communication skills", "good team player", "work independently", "responsible", "fast-paced environment"], "languages_combined": []}, "experience_required": {"duration": ["2 years"], "field": ["application development", "it"]}}, {"job_id": "100003009025239", "location_code": "hk", "company": "Recruit Logic Limited", "job_title": "Senior Developer / Developer (MNC; 30k-35k)", "description": "Responsibilities:\u00a0\n\nParticipate as a team member for developing and implementing high-end Retail Management Software for International markets;\u00a0\nResponsible for application system design, program development, integration test and user test support\n\nRequirements:\u00a0\n\nDegree or Higher Diploma in Computer Science or related disciplines;\u00a0\nMinimum 2 years\u2019 experience in system design and development;\u00a0\nSolid knowledge of C#, ASP.NET , MS-SQL Server;\u00a0\nExperience in ANY of Flutter Mobile Apps,VB.NET, WPF, VB6, is highly preferable;\u00a0\nGood understanding of REST API design and development;\u00a0\nExperiences in Retail industry will be an advantage;\u00a0\nGood command in written and spoken English and Chinese;\u00a0\nGood interpersonal, communication and problem solving skills;\u00a0\nFresh graduate will be considered for Developer position\nWe offer attractive remuneration packages with a wide range of fringe benefits include medical & dental insurance, education allowance, performance bonus and excellent career prospect to the right candidate. We also offer on-the-job training and specialised training programme to uplift potential of our staff.", "employment_types": ["Full Time", "Permanent"], "selling_points": ["C#, ASP.NET, MS-SQL Server", "Flutter Mobile Apps, VB.NET, WPF, VB6", "Fresh graduate will also be considered"], "locations": ["Pok Fu Lam"], "categories": ["Information Technology (IT)", "Application Specialist - Software", "Software Development", "Mobile / Wireless Communications"], "post_time": "2022-01-06T03:55:44Z", "salary": {"currency": "HKD", "max": 34999, "min": 30000, "period": "monthly", "term": null}, "salary_visible": true, "title_keywords": ["developer"], "responsibilities": ["management", "software", "developing", "application system", "design"], "requirements": {"degrees": ["diploma", "degree", "fresh graduate"], "majors": ["related disciplines", "computer science"], "languages": ["english", "chinese"], "language_level": ["good command"], "hard_skills": ["mobile", "system design", "ms-sql", "server", "problem solving skills", "c#"], "soft_skills": ["communication", "problem solving skills", "interpersonal"], "languages_combined": [{"language": "english", "language_level": ["good command"]}, {"language": "chinese", "language_level": ["good command"]}]}, "experience_required": {"duration": ["minimum 2 years"], "field": ["retail industry", "development", "system design"]}}, {"job_id": "100003009026998", "location_code": "hk", "company": "Hang Seng Bank Ltd", "job_title": "Lead Enterprise Architect", "description": "DBS - Information Technology\n\n\n\nPrincipal responsibilities\n\nThe Lead Enterprise Architect is responsible for the following activities:\n\nResponsible for the ongoing maintenance, optimization and planning of HASE\u2019s application portfolio and technology landscape, with the objectives to provide fit for purpose, high performing, resilient, secure and cost effective solution to support and align with business priorities\nProactively engage with business partners to understand priorities, provide preliminary solution and cost estimation. Demonstrate and show business value of enterprise wide, shared infrastructure or to show value of any new strategic platforms being considered.\nResponsible for creating & refining technology solution, architecture designs and patterns, with alignment and adoption of Group technology standards and policies, by taking into account of HASE\u2019s own needs and comply with Regulatory and Compliance requirements\nResponsible for ensuring the architecture solution adhere to agreed architecture standards, principles and the overall roadmap, as part of architecture governance\nIntroduce new practices, processes, operating models, techniques, products, services, technologies and standards where needed against identified use cases, via the appropriate governance bodies\nResponsible for the timely maintenance and freshness of the enterprise landscape, target state architecture, technology stack and capability model\nAct as the virtual leader in the collaboration with architects from other domains to provide enterprise solutions. Work to settle architecture differences or conflicts existing across the various architecture layers in the enterprise.\nEvangelize and promote service oriented architecture, integration and other architecture principles, benefits and technical solutions to business and technical audiences.\u00a0\nWork with project business and technical staff to capture and validate integration requirements for the project, using industry standard integration and service oriented architecture\nStay abreast of technology trends and advise Technology and the business about potential benefits/impact\nRequirements\nDegree or above in a technology, engineering or science related disciplines.\nMinimum 5 years hands on application design or solution architect experience. Exposure on critical projects related to financial service is preferred\nIn-depth knowledge in one or more technology domains: digital, mobile, data, analytic, API and Cloud Computing.\nTOGAF certificate would be an advantage.\nExpert level of relevant IT architecture, strategy or solution design experience in delivery role in financial services environment.\nProven ability and experience to work with senior stakeholders and business sponsors to make strategic recommendations and transformation roadmap planning. Presenting to large technical audiences, and business governance boards.\nExperience using model-based representations that can be adjusted as required to collect, aggregate or disaggregate complex and conflicting information about the business\nDiverse experience and a variety of skills related to supporting large and complex change including people, process and technology development\nExcellent communication and interpersonal skills, with strong oral, written and presentation skills.\nStrong analytical, problem solving, negotiation, influencing skills and possess logical and critical thinking in architecture. Business thinking and highly strategic in order to define practical solutions that align with corporate strategy\nProficiency in both English and Chinese, Putonghua speaking is an advantage.\n\nIf you would like to explore other opportunities at Hang Seng Hong Kong, please visit\u00a0www.hangseng.com/careers/\u00a0for details.\n\nThe health and safety of our employees and candidates is very important to us. Due to the current situation related to the Novel Coronavirus (2019-nCoV), we\u2019re leveraging our digital capabilities to ensure we can continue to recruit top talent at the HSBC Group.\u00a0 As your application progresses, you may be asked to use one of our digital tools to help you through your recruitment journey.\u00a0 If so, one of our\u00a0 Resourcing colleagues will explain how our video-interviewing technology will be used throughout the recruitment process and will be on hand to answer any questions you might have.\n\nAll information provided by applicants will be used only for recruitment purposes and will be used strictly in accordance with the Bank's personal data policies, a copy of which may be obtained by the applicant upon request. Unless otherwise instructed in writing by the applicant concerned, applicants may be considered for other suitable positions within the Bank and its related companies. The personal data of unsuccessful job applicants may be retained for a maximum of two years from the date when the job application is rejected and such data may be retained for a longer period if there is a subsisting reason that obliges the Bank to do so, after which the personal data will be destroyed.", "employment_types": ["Full Time", "Permanent"], "selling_points": [], "locations": ["Not Specified"], "categories": ["Information Technology (IT)", "Application Specialist - Software", "Network & System", "Mobile / Wireless Communications"], "post_time": "2022-01-07T03:05:24Z", "salary": {"currency": null, "max": null, "min": null, "period": "monthly", "term": null}, "salary_visible": false, "title_keywords": ["lead"], "responsibilities": ["cost", "cost estimation", "maintenance", "policies", "infrastructure", "compliance", "architecture", "planning"], "requirements": {"degrees": [], "majors": [], "languages": [], "language_level": [], "hard_skills": [], "soft_skills": [], "languages_combined": []}, "experience_required": {"duration": [], "field": []}}, {"job_id": "100003009016996", "location_code": "hk", "company": "China Everbright Securities International Company Limited", "job_title": "Assistant Vice President, Systems Support and Development (iOS / Android / React Native)", "description": "\u00a0Ref: AVPSSD/ITAC/030122DB/91\n\nResponsibilities\n\n\nParticipate in the entire system development life cycle including system design, programming, user acceptance testing (UAT), documentation and deployment activities\nDevelop and support of React Native mobile trading apps\nCollect and analyze business requirements\nDevelop software requirements and technical specification\nPerform system testing and QA\nMonitor production applications and provides technical support\nPerform any ad hoc special projects as requested\nRequirements\n\nHigher Diploma or above in Computer Science or related discipline\nMinimum 5 years\u2019 relevant experience\nHands-on experience in ES6+ JavaScript, React JS, React Native and Redux architecture\nKnowledge of Mobile Programming (Java / Objective-C / Kotlin / Swift)\nExperience in RESTful API design and good sense of UI / UX design\nStrong analytical skills preferably with knowledge of financial services industry\nQuality conscious, good negotiation and communication skills with improvement attitude\nGood command of both written and spoken English and Chinese\nWe offer a competitive remuneration package to the right candidate. If you are interested in the post, please send your resume together with your present and expected salaries by clicking \u201cApply Now\u201d.\u00a0\n\n\nFor more information about China Everbright Securities International Company Limited, please visit www.ebshk.com.\n\nWe are an equal opportunity employer and welcome applications from all qualified candidates. All applications will be treated in the strictest confidence. Personal data provided will be used for recruitment purposes only. The job applicant will assume all or any risks arising out of or in connection with the job application transmission process prior to our actual receipt of the same including but not limited to accidental or unauthorized loss or disclosure of personal information, to which we will not be responsible in any way.\n\nUnder the Personal Data (Privacy) Ordinance, you may request access to, and / or correction of your personal data in relation to your application. If you wish to do so, please email to us.", "employment_types": ["Full Time", "Permanent"], "selling_points": [], "locations": ["Causeway Bay"], "categories": ["Information Technology (IT)", "Application Specialist - Software", "Software Development", "Mobile / Wireless Communications"], "post_time": "2022-01-03T10:18:23Z", "salary": {"currency": null, "max": null, "min": null, "period": "monthly", "term": null}, "salary_visible": false, "title_keywords": ["assistant vice president"], "responsibilities": ["uat", "develop", "testing", "system design", "documentation"], "requirements": {"degrees": ["higher diploma or above"], "majors": ["computer science"], "languages": ["english", "chinese"], "language_level": ["good command"], "hard_skills": ["java", "restful api", "react", "objective-c", "analytical skills", "mobile", "javascript", "react native", "programming", "swift", "kotlin"], "soft_skills": ["communication skills", "hands-on", "negotiation", "analytical skills"], "languages_combined": [{"language": "english", "language_level": ["good command"]}, {"language": "chinese", "language_level": ["good command"]}]}, "experience_required": {"duration": ["minimum 5 years"], "field": ["relevant experience", "design"]}}, {"job_id": "100003009017679", "location_code": "hk", "company": "Chief Group Limited", "job_title": "Mobile Apps Developer (iOS / Android)", "description": "Responsibilities:\n\nResponsible for designing and building advanced applications on iOS / Android platform\nCollaborate with the teams iOS or Android mobile Apps about technical design, development, enhancement, maintenance and testing etc.\nArticulate with both internal and external data sources and APIs\nAccountable for bug fixing and application performance improvements\nParticipate in multiple projects simultaneously\n\nRequirements:\n\nDegree holder in Computer Science, Computer Engineering, I.T. or related disciplines\nProficient in iOS \u2013 Swift or Android ADK, Kotlin and Java\nExperience in apps development cycle and remote data driving via REST & JSON;\u00a0 would be a plus\nA team player with solid communication skill, problem solving skill and time-management skill\nA quick learner, who is willing to learn and craving for improvement\nPassionate in exploring, learning and implementing new technologies to excel development efficiency\n\nDespite friendly working environment and work-life balance culture, we offer an attractive remuneration package including:\n\nPerformance Bonus\nStaff Discount for Company Products/Services\nBirthday Leave\nScholarships & Training Sponsorship\n\nTo apply, please click \u201cAPPLY NOW\u201d and submit your resume with expected salary.\n\n\u00a0(Personal data collected will be kept strictly confidential and used for recruitment purpose only.)", "employment_types": ["Full Time", "Permanent"], "selling_points": ["Designing and building advanced applications", "Design, development, enhancement, maintenance", "Autonomy to try new mobile apps technologies"], "locations": ["Sheung Wan"], "categories": ["Information Technology (IT)", "Application Specialist - Software", "Others", "Student / Fresh Graduate / No Experience", "Mobile / Wireless Communications"], "post_time": "2022-01-04T01:41:48Z", "salary": {"currency": null, "max": null, "min": null, "period": "monthly", "term": null}, "salary_visible": false, "title_keywords": ["developer"], "responsibilities": ["collaborate with", "maintenance", "data", "teams", "design", "testing", "designing", "multiple projects"], "requirements": {"degrees": ["degree holder"], "majors": ["computer engineering", "computer science"], "languages": [], "language_level": [], "hard_skills": ["excel", "java", "plus", "problem solving", "swift", "kotlin", "android"], "soft_skills": ["passionate", "communication skill", "willing to learn", "quick learner", "learning", "problem solving skill", "team player"], "languages_combined": []}, "experience_required": {"duration": [], "field": ["development"]}}, {"job_id": "100003009024561", "location_code": "hk", "company": "HKT", "job_title": "Senior Product Manager", "description": "Your Role\n\n\nDefine and execute product strategies on merchant acquiring for both open-loop and close-loop payments including Stored Value Facility and emerging payments\nManaging payment products (e.g. mobile POS) lifecycle including product requirement gathering, design, development, deployment, enhancement, support and exit\nManaging integration process with merchant for in-app and online payments\nConstantly review and enhance operational processes and workflow for merchant on-boarding, merchant transactions and merchant supports\nDrive and manage initiatives (e.g. workflow automation) to improve operational efficiency\nIdentify both merchant\u2019s and consumer\u2019s pain points, develop right payment solutions for them\nUnderstanding merchant business portfolio and deriving insights through regular review and analysing of data and monitoring of product performance\nSupport sales team by executing go to market strategies\nManage existing partners and vendors relationship as well as team up more payments partnerships\n\nTo succeed in this role:\n\nDegree holder in Business Administration, Computer Science or related disciplines\nWith minimum 8 years' relevant working experience\nExperience in payment business especially card payment is a plus\nGood knowledge of Merchant Acquiring Business, roles & responsibilities of various parties involved in the ecosystem\nStrong problem solving, analytical thinking, negotiation and conflict resolution skills\nCreative, self-motivated, and able to work independently in a dynamic business environment, under pressure and tight timeline\nAble to productively work in a matrix management organization\nExcellent command of spoken and written Chinese and English, proficiency in Mandarin", "employment_types": ["Full Time", "Permanent"], "selling_points": ["Payment products lifecycle", "Product strategies on merchant acquiring", "Creative, self-motivated, work independently"], "locations": ["Quarry Bay"], "categories": ["Information Technology (IT)", "Product Management / Business Analyst", "Banking / Finance", "Order Processing & Operation / Settlement", "Mobile / Wireless Communications"], "post_time": "2022-01-06T01:43:55Z", "salary": {"currency": null, "max": null, "min": null, "period": null, "term": null}, "salary_visible": false, "title_keywords": ["senior product manager"], "responsibilities": ["management", "data", "review", "monitoring", "transactions", "design", "develop", "regular review", "payment", "resolution", "payments", "sales team", "executing", "administration"], "requirements": {"degrees": ["degree holder"], "majors": ["related disciplines", "business administration", "computer science"], "languages": ["english", "chinese", "mandarin"], "language_level": ["excellent", "proficiency"], "hard_skills": ["plus", "pos", "problem solving", "mobile", "dynamic", "deployment", "integration", "go"], "soft_skills": ["self-motivated", "work independently", "under pressure", "negotiation", "problem solving", "dynamic", "business environment", "creative"], "languages_combined": [{"language": "english", "language_level": ["excellent", "proficiency"]}, {"language": "chinese", "language_level": ["excellent", "proficiency"]}, {"language": "mandarin", "language_level": ["excellent", "proficiency"]}]}, "experience_required": {"duration": ["minimum 8 years"], "field": ["business", "relevant working experience"]}}, {"job_id": "100003009020762", "location_code": "hk", "company": "Shiseido Hong Kong Limited", "job_title": "Network & Security Specialist, Information and Technology Transformation", "description": "The Role:\nTo maintain the network performance and ensure network availability, we are looking for a Specialist who can oversee the security of all systems and the network.\n\nReports to: Manager - Infrastructure, ITT\n\nResponsibilities\n\nAct as a Network Specialist and participate in network design discussion with external support partners and internal technical teams\nProvide L2-L3 support on various network systems (LAN, WAN, Wireless, Firewall, Load Balancer, WAN, Optimizer, etc.)\nPlan and manage implementation of networking system projects\nCollaborate with various stakeholders including other technical teams for project delivery\nExplore the latest Networking Technologies with the team\nImprove internal security monitoring and protection\nPerform network maintenance and system upgrades including service packs, patches, hot fixes and security configurations\nSupport infrastructure related projects\n\nRequirements\n\nBachelor\u2019s Degree in Information Technology or related disciplines\nNetworking related certificates such as CCNP or CCIE holder is preferred\nMore than 3-5 years\u2019 working experience in infrastructure side specializing in network\nProven support and configuration experience on network and security product\nStrong knowledge in Cloud Network and Cloud Security is a big plus, preferably in MS Azure\nStrong knowledge on Cisco/HP/Dell Technologies such as LAN/WAN/WiFi, etc. technologies\nSolid hands-on experience in Firewall (Fortinet/Palo Alto/Sangfor), Proxy and Load Balancer, LAN, WAN, FireEye, Cloudflare\nNetwork Monitoring Tools, PRTG, NMAP\nStrong knowledge & experience across network monitoring products\nSound technical knowledge in VPN / SD-WAN gateways, intrusion detection systems, routers, switches, firewalls, proxies, network load balancers, wireless controllers, and access points\nSecurity Skills (Good to have)\nNetwork Policy Enforcement\nGood command of written and spoken English and Chinese\n\nWhat's on offer:\u00a0\nBe part of a growing global organization with a portfolio of around 17 brands, competitive discretionary bonus, quarterly free goods across brands, medical benefits, birthday leave, flexible working hours, wellness facilities, learning sponsorship, and more.\u00a0\n\n\nInterested?\nPlease apply with your latest resume stating your notice period, current and expected remuneration package.\u00a0\n\n\nWe regret that only shortlisted candidates will be contacted.\u00a0\n\nShiseido Hong Kong is an Equal Opportunities Employer. All applications received will be\u00a0treated in strict confidential and be used exclusively for employment purpose only.", "employment_types": ["Permanent"], "selling_points": ["Provide L2-L3 support on various network systems", "Specializing in network", "Oversee the security of all systems"], "locations": ["Kowloon Bay"], "categories": ["Information Technology (IT)", "Application Specialist - Network", "Network & System", "Mobile / Wireless Communications"], "post_time": "2022-01-05T01:56:23Z", "salary": {"currency": null, "max": null, "min": null, "period": "monthly", "term": null}, "salary_visible": false, "title_keywords": ["specialist"], "responsibilities": ["collaborate with", "maintenance", "upgrades", "systems", "teams", "implementation", "design", "monitoring", "infrastructure", "plan"], "requirements": {"degrees": ["degree", "bachelor"], "majors": ["related disciplines", "information technology"], "languages": ["english", "chinese"], "language_level": ["good command"], "hard_skills": ["plus", "azure", "ccnp", "access points", "sd-wan", "vpn", "firewall", "wan"], "soft_skills": ["flexible", "hands-on", "learning"], "languages_combined": [{"language": "english", "language_level": ["good command"]}, {"language": "chinese", "language_level": ["good command"]}]}, "experience_required": {"duration": ["3-5 years"], "field": ["infrastructure", "security"]}}, {"job_id": "100003009020551", "location_code": "hk", "company": "One Click Go Live Limited", "job_title": "System Administrator", "description": "One Click Go Live Limited (\u201cONE CLICK GO LIVE\u201d)\u00a0is a live streaming technology company focuses on enterprise broadcast-grade video live streaming solutions with offerings including live streaming platforms, products and services.\u00a0ONE CLICK GO LIVE enables corporates to conduct professional live streaming through one single button \u2013 ONE CLICK GO LIVE, delivering a seamless user experience in combination with patented technologies.\n\nServing over 300 corporates for over 9,000 live streaming events,\u00a0ONE CLICK GO LIVE leverages its technical expertise while corporates focus on generating growth and revenue with video content.\u00a0\n\nOur successful cases:\u00a0www.oneclickgolive.com\n\nWe are looking for candidate(s) who is/are interested to join our fast growing team.\u00a0 Training will be offered for potential candidate(s).\n\n\nJob responsibility:\n\nTo install, maintain and support the IT infrastructure, security, networking, server computers and messaging systems;\nManage Internal IT systems (i.e. web, email, applications and server, etc.);\u00a0\nResponsible for the installation, administration, maintenance, configuration and support the smooth running of the enterprise network;\nManage infrastructure projects in a quality and timely manner;\nManage system databases and servers to ensure smooth on-going operation and up-time according to service standards.\u00a0 Plan and perform database version upgrades;\nPerform regular network scanning, analysis and threat identification;\nManage and maintain documentation of all IT assets and ensure all processes & procedure are compliant with the company policies;\nManage service transition and release to production process to ensure network infrastructure setup and its components are complied with enterprise technical standard;\nDesign, deploy, and administer the network infrastructure and supporting systems;\nTo assist and provide support to solve end user's technical problems including but not limited to any hardware, software and network systems (Operating System, MS Office suite, antivirus, email- client, office printing system, networking, etc.) ;\nProvide off-hours operational support for emergency maintenance and deployment events when necessary;\n\n\u00a0Job requirement:\n\nDiploma or Degree holders in Computer Science, Information Technology, or related discipline\n\nAt least 3-5 years' working experience in server administration and server networking or performing in system support role\nExposure in Live audio/video streaming support will be an advantage\nSound knowledge and technical skills and Microsoft Windows\u00a0\nSolid experience in Windows Server platform, Active directory, Group Policy, VMare, Networking, Firewall, switch and router\nExperience with MacOS will have an added advantage\nWilling to provide ad hoc support in non-office hours, if required\nStrong problem solving and good interpersonal skills\nInterested applicants please send us full CV with current and expected salary and availability.\n\nBenefits : Medical Allowance, Birthday and Childcare Leave\u00a0\n\nThe information provided will be treated in strict confidence and used only for consideration of application for relevant/similar post(s).\u00a0 All personal data of unsuccessful applicants will be destroyed within 6 months.", "employment_types": ["Full Time", "Permanent"], "selling_points": ["Perform server maintenance, administration,back up", "Strong problem solving and interpersonal skills", "3-5 years experience in System Administration"], "locations": ["Others"], "categories": ["Media & Advertising", "Broadcasting - TV / Radio", "Information Technology (IT)", "Mobile / Wireless Communications"], "post_time": "2022-01-04T15:27:04Z", "salary": {"currency": null, "max": null, "min": null, "period": "monthly", "term": null}, "salary_visible": false, "title_keywords": ["system administrator"], "responsibilities": ["operational support", "production process", "software", "quality", "design", "service standards", "maintain", "plan", "database", "deploy", "administration", "scanning", "it infrastructure", "configuration", "infrastructure", "setup", "network infrastructure", "installation", "provide support", "upgrades", "maintenance", "policies", "analysis", "systems", "hardware", "databases", "maintain documentation"], "requirements": {"degrees": ["diploma", "degree"], "majors": ["computer science", "information technology"], "languages": [], "language_level": [], "hard_skills": ["active directory", "server administration", "switch", "vmare", "router", "problem solving", "firewall", "server", "windows server"], "soft_skills": ["technical skills", "active", "interpersonal skills", "problem solving"], "languages_combined": []}, "experience_required": {"duration": ["at least 3-5 years"], "field": ["server networking", "system support", "server administration"]}}, {"job_id": "100003009024077", "location_code": "hk", "company": "Manpower Services (Hong Kong) Limited", "job_title": "(URGENT)Junior Programmer/ Programmer/ Analyst Programmer (UP TO 45K)", "description": "Job Description:\n\nPerform system development, testing, implementation, maintenance support and user training\nDevelop, enhance, and provide supports to existing systems and applications\nProvide ad hoc support to daily operation\n\nRequirements:\n\nHigher Diploma or above in Computer Science, Information Technology or related disciplines\n0-6 working experiences after graduation (Less experience will be considered as Junior Programmer/ Programmer)\nStrong programming skills, preferably using JAVA/ C#/ C++, Microsoft Access, J2EE, HTML, JavaScript, ReactJS, ReactNative, etc.\nWelcome Fresh Grads", "employment_types": ["Contract"], "selling_points": ["JAVA/C#/C++ Programmer", "Renewable contract", "5-days work, Attractive remuneration"], "locations": ["Kowloon City Area"], "categories": ["Information Technology (IT)", "Application Specialist - Software", "Software Development", "Mobile / Wireless Communications"], "post_time": "2022-01-05T10:35:52Z", "salary": {"currency": null, "max": null, "min": null, "period": "monthly", "term": null}, "salary_visible": false, "title_keywords": ["analyst programmer", "programmer"], "responsibilities": ["ad hoc", "maintenance support", "systems", "daily operation", "implementation", "develop", "testing"], "requirements": {"degrees": ["higher diploma or above"], "majors": ["related disciplines", "computer science", "information technology"], "languages": [], "language_level": [], "hard_skills": ["java", "c++", "html", "javascript", "programming", "c#"], "soft_skills": [], "languages_combined": []}, "experience_required": {"duration": [], "field": []}}, {"job_id": "100003009013611", "location_code": "hk", "company": "Walters People (HK)", "job_title": "Mobile App Developer, React Native", "description": "A fast growing e-commerce platform in retail industry is now looking for an energetic talents to join and grow together with the team!\n\nExpectation on role:\n\nHelp with the development & deployment of mobile applications.\nWork alongside our IT Project Manager to manage product requirements and progress to ensure deadlines are met.\nTake responsibility for your projects; sharing responsibilities, communicating clearly, setting deadlines and demonstrating results\nWork closely with the team to share recommendations and get a great understanding of our business operations\n\nRequirements:\n\nDegree majoring in Computer Science, Information Technology or related discipline\nAt least 3 year experiences in hybrid mobile apps development\nFamiliar with React Native, Redux, Hook, GraphQL and RESTful API\nKnowledge in Kotlin will be an added advantage", "employment_types": ["Full Time", "Permanent"], "selling_points": ["1 Year experience in React Native", "E-commerce industry", "Attractive package"], "locations": ["Not Specified"], "categories": ["Information Technology (IT)", "Application Specialist - Software", "Technical Writing", "Mobile / Wireless Communications"], "post_time": "2022-01-03T02:32:01Z", "salary": {"currency": null, "max": null, "min": null, "period": "monthly", "term": null}, "salary_visible": false, "title_keywords": ["developer"], "responsibilities": ["operations"], "requirements": {"degrees": ["degree"], "majors": ["computer science", "information technology"], "languages": [], "language_level": [], "hard_skills": ["mobile", "restful api", "react native", "kotlin"], "soft_skills": [], "languages_combined": []}, "experience_required": {"duration": ["at least 3 year"], "field": ["development"]}}, {"job_id": "100003009024079", "location_code": "hk", "company": "Manpower Services (Hong Kong) Limited", "job_title": "Programmer / (Senior) Analyst Programmer", "description": "Job Responsibilities\n\nUndertake the development of web applications including programming, testing, implementation and other related support services\nPrepare design documentations, functional specifications and users guides related to the applications developed\nProvide end-user training and technical support on the user of applications developed\nSupport daily operations and assist the supervisor with day-to-day tasks and projects\n\nJob Requirements\n\nHave a recognized degree / high diploma in Computer Science, Information Technology or a related discipline\nMinimum 1 year of working experience in application / web development\nExperience/knowledge in backend development, e.g. Java, Spring, Hibernate, etc.\nKnowledge in React, Vue.js, Angular, API development and Git is preferred\nHave strong communication and analytical skills\nProficiency in written and spoken English and Chinese, including Putonghua", "employment_types": ["Permanent"], "selling_points": ["Java, Spring, Hibernate, etc.", "Knowledge in front-end tech/tools is preferred", "1-year\u2019s experience in web/system development"], "locations": ["Cheung Sha Wan"], "categories": ["Information Technology (IT)", "Application Specialist - Software", "Software Development", "Mobile / Wireless Communications"], "post_time": "2022-01-05T10:36:02Z", "salary": {"currency": null, "max": null, "min": null, "period": "monthly", "term": null}, "salary_visible": false, "title_keywords": ["analyst programmer", "programmer"], "responsibilities": ["technical support", "support services", "implementation", "design", "testing", "daily operations", "specifications"], "requirements": {"degrees": ["high diploma", "degree"], "majors": ["computer science", "information technology"], "languages": ["putonghua", "english", "chinese"], "language_level": ["proficiency"], "hard_skills": ["web development", "hibernate", "java", "git", "react", "analytical skills", "spring", "angular"], "soft_skills": ["communication", "analytical skills"], "languages_combined": [{"language": "putonghua", "language_level": ["proficiency"]}, {"language": "english", "language_level": ["proficiency"]}, {"language": "chinese", "language_level": ["proficiency"]}]}, "experience_required": {"duration": ["minimum 1 year"], "field": ["development"]}}, {"job_id": "100003009023216", "location_code": "hk", "company": "Mad Head App Limited", "job_title": "Senior Programmer/Programmer (Client App)", "description": "Duties include but not limited to:\n\nCollaborate with assistant producer and designers to develop iPhone and Android games\nDesign, implement, test, bug-fixing and document program logic\nWrite test cases, carry out unit testing and execute the deployment process\nResearch new technologies and standards on IT\nEnsure the coding style consistent with company standard\nSupervise one or more programmers to maintain the code in good standard\n\nRequirements:\n\nBachelor Degree in Computer Science, Computer Engineering or related disciplines\nStrong experience in mobile platform development\nKnowledge in Unity 3D will be an advantage\nProactive, self-motivated and willing to work under pressure\nGamer of Tower of Saviors (\u795e\u9b54\u4e4b\u5854) is an advantage\nCandidate with less experience will be considered as Programmer\n\nWorking Location & Hours:\u00a0\nHong Kong Science Park\n5-day work, 10:00 \u2013 19:00 (Lunch hour 13:45 \u2013 15:00)\nExcellent career development opportunity and attractive remuneration package with wide range of fringe benefits including discretionary bonus, public holiday, paternity leave, training subsidy & sponsorship for professional qualifications, medical insurance coverage, annual medical check-up, dental scheme etc. will be offered to the right candidate.\n\nWe are an equal opportunity employer and welcome applications from all qualified candidates. All information provided will be treated in strict confidence and used for recruitment purposes only.", "employment_types": ["Full Time"], "selling_points": ["Proficient in Unity 3D & C#", "Dental, body check up, and tuition allowance", "Long service award and birthday leave, etc"], "locations": ["Shatin Area"], "categories": ["Information Technology (IT)", "Application Specialist - Software", "Software Development", "Mobile / Wireless Communications"], "post_time": "2022-01-05T07:48:43Z", "salary": {"currency": null, "max": null, "min": null, "period": "monthly", "term": null}, "salary_visible": false, "title_keywords": ["programmer", "senior programmer"], "responsibilities": ["collaborate with", "coding", "testing", "design", "develop", "maintain", "recruitment", "career development", "insurance", "work under pressure"], "requirements": {"degrees": ["degree", "bachelor"], "majors": ["related disciplines", "computer engineering", "computer science"], "languages": [], "language_level": [], "hard_skills": ["professional qualifications", "scheme", "mobile", "android games", "deployment", "code", "unity"], "soft_skills": ["self-motivated", "proactive", "confidence", "work under pressure"], "languages_combined": []}, "experience_required": {"duration": [], "field": ["development"]}}, {"job_id": "100003009018982", "location_code": "hk", "company": "VW-VES (HK) Limited", "job_title": "IT Assistant", "description": "Main task:\n\nResponsible for assisting proposal, project and overall IT support activity; assist the quality, purchase, installation and maintenance of business and engineering systems, on schedule and within the prescribed resource limits. Also be responsible for the installation and operation of computer networks and office automation systems in the Facility.\n\nResponsibilities include:\n\nPlans, develops, implements and maintains necessary actions to maintain soft and hardware systems in optimal condition and in compliance with the contractual and company requirements in the most efficient, effective and cost effective manner\nPlans and implements upgrades of the soft and hardware systems to ensure optimal function and repair ability\nProvides administrative and programming support for administrative soft and hardware systems\nCoordinates and conducts trouble-shooting and repair of administrative soft and hardware systems\nAssist in the proper function, maintenance, trouble-shooting, repair and performance testing of the PLC/SCADA system\nThe above is a summary of the main tasks and responsibilities of the post, other duties within the scope and spirit of the job as instructed by Management\n\nPerson Specification:\n\nKnowledge / Qualifications\n\nHigher Diploma or Degree in Computer Science / Computer Engineering / Information Technology / Information System or relevant disciplines\nRelevant experience in IT support, system installation and maintenance\nHave relevant experience in Windows Servers, VMware or Cisco\nMCSA / CCNA / VCTA or higher is preferable\nAbility / Experience\n\n2 or more years of IT experience\nGood analytical, problem solving, interpersonal and communication skills\nAbility to communicate in English and Cantonese and/or Mandarin.\n\nMotivation\n\nSelf-motivated, able to prioritize tasks\nAbility to work independently with minimal supervision\nAn effective team member, able to communicate well orally and in writing\nInterested parties please send resume with full career details, expected salary and contact number to us.", "employment_types": ["Full Time", "Permanent"], "selling_points": ["Higher Diploma or Degree in Computer Science", "experience in IT support, system installation", "experience in Windows Servers, VMware or Cisco"], "locations": ["Tuen Mun Area"], "categories": ["Information Technology (IT)", "Hardware", "Support", "Mobile / Wireless Communications"], "post_time": "2022-01-04T06:18:20Z", "salary": {"currency": null, "max": null, "min": null, "period": "monthly", "term": null}, "salary_visible": false, "title_keywords": ["assistant"], "responsibilities": ["installation", "cost", "management", "maintenance", "performance testing", "upgrades", "other duties", "systems", "quality", "compliance", "communication", "hardware", "purchase", "maintain", "repair", "schedule", "plans"], "requirements": {"degrees": ["diploma", "degree"], "majors": ["computer engineering", "computer science", "information technology"], "languages": ["cantonese", "english", "mandarin"], "language_level": [], "hard_skills": ["servers", "maintenance", "vmware", "plc", "ccna", "information system", "problem solving", "hardware", "programming", "mcsa"], "soft_skills": ["efficient", "communication skills", "self-motivated", "work independently", "responsible", "able to prioritize", "problem solving", "orally", "team member", "interpersonal"], "languages_combined": [{"language": "cantonese", "language_level": []}, {"language": "english", "language_level": []}, {"language": "mandarin", "language_level": []}]}, "experience_required": {"duration": [], "field": ["installation", "maintenance", "it support", "it experience", "relevant experience"]}}, {"job_id": "100003009016100", "location_code": "hk", "company": "Qookia Limited", "job_title": "QA Tester / \u904a\u6232\u6e2c\u8a66\u54e1 (Welcome Fresh graduates)", "description": "Job Description:\n\n\u00a0Develop comprehensive test plans and detailed test cases from documented\u00a0 \u00a0 \u00a0 \u00a0game requirements\n\u00a0Create\u00a0detailed\u00a0tracking reports to track\u00a0bugs and errors\n\u00a0Follow test plans to complete QA for each game version release\n\u00a0Perform directed ad-hoc testing on focused areas\n\u00a0Compose daily and weekly progress reports\n\nRequirements:\n\n\u00a0 Minimum 1 years of experience in\u00a0game QA testing,\u00a0developing test plans and\u00a0 \u00a0 \u00a0 \u00a0 test cases\n\u00a0 Strong communication\u00a0and\u00a0analytical skills\n\u00a0 Familiar with the popular mobile games released in past 5 years\n\u00a0 Able to work under pressure on a tight schedule\n\u00a0 Loves playing games\n\nBenefits:\n\n5-day work\nPaid birthday leave\nBirthday pocket money\nPerformance bonus\nMedical insurance\nDental subsidy\nFree snack and beverage\nFriendly working environment\n\nInterested parties please apply with the following details:\n\nResume\nExpected Salary\nEarliest Availability\n\nPlease ensure ALL of the information above are true and up-to-date. All information collected will be used for recruitment purposes only.", "employment_types": ["Full Time", "Permanent"], "selling_points": ["Joyful working environment with free snacks/drinks", "5 days work performance bonus", "Birthday Leave + pocket money"], "locations": ["Kwai Fong"], "categories": ["Information Technology (IT)", "Software Development", "Testing / QA", "Mobile / Wireless Communications"], "post_time": "2022-01-03T08:17:43Z", "salary": {"currency": null, "max": null, "min": null, "period": "monthly", "term": null}, "salary_visible": false, "title_keywords": [], "responsibilities": ["ad-hoc", "progress reports", "develop", "testing", "reports", "plans", "tracking"], "requirements": {"degrees": [], "majors": [], "languages": [], "language_level": [], "hard_skills": ["mobile", "analytical skills"], "soft_skills": ["communication", "work under pressure", "analytical skills"], "languages_combined": []}, "experience_required": {"duration": ["minimum 1 years"], "field": ["developing", "qa", "testing"]}}, {"job_id": "100003009018395", "location_code": "hk", "company": "HKT", "job_title": "Assistant Manager, Mobile Product Development", "description": "Your Role\n\n\n\nYou are responsible for mobile\u00a0service\u00a0development and management on consumer and commercial areas. You have to work closely with Marketing, Presales/Sales, Engineering and IT teams, so as to manage the deliverables to meet the requirement.\n\nMajor responsibilities include :\n\nTo deliver/maintain messaging service to both consumer and commercial segment.\nCollect user requirement, convert into detail requirement and work with technical teams to deliver on time in good quality.\nProvide training and consultancy to internal team (e.g. Customer Service, pre-sales/sales team)\nGenerate and analyze performance reports, for service monitoring\n\nTo succeed in this role:\n\n\nDegree holder in Information Technologies, Computer Science/Engineering, Telecommunication, IT or equivalent with professional accreditations\n\nAt least 3-4 years relevant experience. Candidates with more experience will be considered as Manager\nHave experience in communicating and managing technical teams.\nGood understanding in mobile messaging (e.g. SMS, MMS)\nGood understanding in OTT messaging (e.g. WhatsApp, Facebook messenger, Instagram) will be an advantage.\nExperience in managing corporate clients\u00a0will be an advantage\nPassionate to study new technology and IT knowledge\nA fast learner with strong analytical mind\nAble to work independently in a dynamic business environment\nStrong business acumen, dedicated and self-motivated\nGood interpersonal and presentation skills", "employment_types": ["Full Time", "Permanent"], "selling_points": ["Mobile service/solution development", "Product life cycle", "Vendor management"], "locations": ["Quarry Bay"], "categories": ["Engineering", "Telecommunication / Wireless / Radio", "Information Technology (IT)", "Product Management / Business Analyst", "Mobile / Wireless Communications"], "post_time": "2022-01-04T03:31:07Z", "salary": {"currency": null, "max": null, "min": null, "period": null, "term": null}, "salary_visible": false, "title_keywords": ["product development", "assistant manager,"], "responsibilities": ["provide training", "user requirement", "management", "performance reports", "monitoring", "teams", "quality", "maintain", "customer service", "sales team", "facebook"], "requirements": {"degrees": ["degree holder"], "majors": ["it", "engineering", "computer science"], "languages": [], "language_level": [], "hard_skills": ["it knowledge", "mobile", "whatsapp", "dynamic", "facebook", "acumen"], "soft_skills": ["passionate", "work independently", "self-motivated", "responsible", "business acumen", "presentation skills", "analytical mind", "customer service", "dynamic", "business environment", "fast learner", "interpersonal"], "languages_combined": []}, "experience_required": {"duration": ["at least 3-4 years"], "field": ["relevant experience"]}}, {"job_id": "100003009023215", "location_code": "hk", "company": "Mad Head App Limited", "job_title": "Senior Programmer (Web Developer)", "description": "We are hiring!\nCome to join our team of professionals passionate to games!\n\nDuties include but not limited to:\n\nResponsible for development and maintenance of Web applications and Application design\nBuild improvements to performance, reliability, and product polish \u2014 for example, improving the efficiency and performance of our game API server.\nRegularly report working progress to Development Lead\nUnit Testing using PHPUnit/ Jest/ Mocha\n\nRequirements:\n\nBachelor Degree in Computer Science, Computer Engineering or related disciplines\n3 years experience in developing web applications\nPassion in game industry\nFamiliar with one of the following: PHP/ TypeScript/ Node.js\nKnowledge in\u00a0Kubernetes/ Docker/ NoSQL/ MySQL/ Git will be an advantage\u00a0\nBasic knowledge in AWS / GCP will be an advantage\u00a0\n\nWorking Location & Hours:\nHong Kong Science Park\n5-day work, 10:00 \u2013 19:00 (Lunch hour 13:45 \u2013 15:00)\n\nWe Offer:\u00a0\n\n\n5-day Work Week with Flexible Working Hours\nDiscretionary Performance Bonus\nMedical Coverage (Annual Medical Check\u2013up and Dental)\nOvertime Meal and Transportation Subsidy\nBirthday and Marriage Leave\nFun, Exciting and Creative Working Environment\n\nInterested parties please send your resume with expected salary to us.\n\nExcellent career development opportunity and attractive remuneration package with wide range of fringe benefits including discretionary bonus, public holiday, paternity leave, training subsidy & sponsorship for professional qualifications, medical insurance coverage, annual medical check-up, dental scheme etc. will be offered to the right candidate.\n\nWe are an equal opportunity employer and welcome applications from all qualified candidates. All information provided will be treated in strict confidence and used for recruitment purposes only.", "employment_types": ["Full Time", "Permanent"], "selling_points": ["Fluent with TypeScript, Node.js, MySQL", "3 years experience in developing web applications", "Dental, body check up & birthday leave, etc"], "locations": ["Shatin Area"], "categories": ["Information Technology (IT)", "Application Specialist - Software", "Software Development", "Mobile / Wireless Communications"], "post_time": "2022-01-05T07:48:42Z", "salary": {"currency": null, "max": null, "min": null, "period": "monthly", "term": null}, "salary_visible": false, "title_keywords": ["developer", "senior programmer"], "responsibilities": ["maintenance", "developing", "design", "testing", "report"], "requirements": {"degrees": ["degree", "bachelor"], "majors": ["related disciplines", "computer engineering", "computer science"], "languages": ["polish"], "language_level": [], "hard_skills": ["git", "web applications", "basic", "maintenance", "php", "aws", "typescript", "server"], "soft_skills": ["passionate", "responsible", "passion in"], "languages_combined": [{"language": "polish", "language_level": []}]}, "experience_required": {"duration": ["3 years"], "field": ["web applications", "developing"]}}, {"job_id": "100003009017227", "location_code": "hk", "company": "Randstad Hong Kong Limited", "job_title": "Technical Support Engineer (shift duty) - 15K-20K", "description": "about the company.\n\n\nMy Client is a transportation service expert.\n\nabout the team.\n\n\nWell established team-oriented environment.\n\nabout the job.\n\nResponsible for 1st Level technical support\nProvide troubleshooting and basic problem solving on system, software, hardware and network issues\nInvestigate production issues and participate in system operation improvement\nPerform system maintenance and health checks;\n\nskills & experiences required.\n\nDegree or diploma in IT, computer science or similar\nTwo or more years of experience in PC support and system admin\nFresh graduate is welcome for junior position with guidance from the senior\n\n\nInterested parties, please click \"Apply Now\" or contact ChristalChristal Wong at christalchristal.wong@randstad.com.hk", "employment_types": ["Full Time", "Permanent"], "selling_points": [], "locations": ["Not Specified"], "categories": ["Information Technology (IT)", "Support", "Others", "Mobile / Wireless Communications"], "post_time": "2022-01-03T11:27:02Z", "salary": {"currency": "HKD", "max": 19999, "min": 17000, "period": "monthly", "term": null}, "salary_visible": true, "title_keywords": ["technical support engineer"], "responsibilities": ["guidance", "software", "maintenance", "technical support", "network issues", "troubleshooting", "hardware"], "requirements": {"degrees": ["diploma", "degree", "fresh graduate"], "majors": ["it", "computer science"], "languages": [], "language_level": [], "hard_skills": ["basic", "maintenance", "problem solving", "hardware", "pc"], "soft_skills": ["problem solving", "troubleshooting", "responsible"], "languages_combined": []}, "experience_required": {"duration": [], "field": ["admin"]}}, {"job_id": "100003009019151", "location_code": "hk", "company": "TalentQuest HR Limited", "job_title": "Senior iOS / iOS Developer", "description": "Our Client is a leading, fully integrated multimedia and entertainment company headquartered in Hong Kong.\nResponsibilities\n\nResponsible for implementation, maintenance, and release of our iOS music service applications\nImplement app functionalities based on product requirements under iteration cycles and participate in R&D and prototyping\nEnsure that architectural design and solution can balance business needs and technical/security standards\nRequirements\n\nUniversity Graduate or High Diploma in Computer Science or related discipline\nMinimum 3+ years of relevant experience\nStrong knowledge and hands-on experience in both Swift and Objective C\nSolid understanding of the full mobile development life cycle\nGood problem solving and analytical skills\nOrganized, self-motivated and teamwork oriented\nCandidate with more experience will be considered as senior position\nInterested parties, please send your full resume with current/expected salary and the date of availability to WhatsApp https://wa.me/85296177281 . Please feel free to contact Mr Salay at 96177281 for more information.\n", "employment_types": ["Full Time", "Permanent"], "selling_points": ["iOS Development, Objective-C, Swift", "SDLC", "Hands On Mobile Development"], "locations": ["Not Specified"], "categories": ["Information Technology (IT)", "Application Specialist - Software", "Software Development", "Mobile / Wireless Communications"], "post_time": "2022-01-04T06:50:21Z", "salary": {"currency": null, "max": null, "min": null, "period": "monthly", "term": null}, "salary_visible": false, "title_keywords": ["developer"], "responsibilities": ["implementation", "maintenance", "design"], "requirements": {"degrees": ["high diploma", "university graduate"], "majors": ["computer science"], "languages": [], "language_level": [], "hard_skills": ["analytical skills", "problem solving", "mobile", "c", "swift"], "soft_skills": ["organized", "self-motivated", "teamwork", "problem solving and analytical skills", "hands-on"], "languages_combined": []}, "experience_required": {"duration": ["minimum 3+ years"], "field": ["relevant experience"]}}, {"job_id": "100003009020554", "location_code": "hk", "company": "One Click Go Live Limited", "job_title": "Full Stack Software Developer", "description": "One Click Go Live Limited (\u201cONE CLICK GO LIVE\u201d)\u00a0is a live streaming technology company focuses on enterprise broadcast-grade video live streaming solutions with offerings including live streaming platforms, products and services.\u00a0ONE CLICK GO LIVE enables corporates to conduct professional live streaming through one single button \u2013 ONE CLICK GO LIVE, delivering a seamless user experience in combination with patented technologies.\n\nServing over 300 corporates for over 9,000 live streaming events,\u00a0ONE CLICK GO LIVE leverages its technical expertise while corporates focus on generating growth and revenue with video content.\u00a0\n\nOur successful cases:\u00a0www.oneclickgolive.com\n\nWe are looking for candidate(s) who is/are interested to join our fast growing team.\u00a0 Training will be offered for potential candidate(s).\n\n\nJob responsibility:\n\nDevelop high-quality, robust, scalable and supportable video-related software systems and cloud-based services in an Agile development environment\nDevelop sufficient automated tests to assure product quality\nResearch into new technologies as necessary\nCollaborate with the team members and work with product team in enhancing product features\n\n\u00a0Job requirement:\n\nBachelor degree or above in Computer Science or related disciplines\n1-3 years relevant experience\nProficient in Javascript, Python, Golang, Java, Kotlin, C/C++\nExperience with a common relational or NoSQL database\nKnowledge or experience in Docker, Kubernetes, cloud computing on AWS/GCP/Azure/AliCloud, VueJS, OTT video streaming will be an advantage\nFast learner and good team player\nGood communication and interpersonal skills\nFresh graduates are welcome to apply\nInterested applicants please send us full CV with current and expected salary and availability.\n\nBenefits : Medical Allowance, Birthday and Childcare Leave\u00a0\n\nThe information provided will be treated in strict confidence and used only for consideration of application for relevant/similar post(s).\u00a0 All personal data of unsuccessful applicants will be destroyed within 6 months.", "employment_types": ["Full Time", "Permanent"], "selling_points": ["Software Development with cutting-edge technology", "Fresh graduate", "Career growth"], "locations": ["Others"], "categories": ["Media & Advertising", "Broadcasting - TV / Radio", "Information Technology (IT)", "Mobile / Wireless Communications"], "post_time": "2022-01-04T15:39:00Z", "salary": {"currency": null, "max": null, "min": null, "period": "monthly", "term": null}, "salary_visible": false, "title_keywords": ["developer"], "responsibilities": ["collaborate with", "software", "systems", "quality", "agile development", "develop"], "requirements": {"degrees": ["degree or above", "bachelor"], "majors": ["related disciplines", "computer science"], "languages": [], "language_level": [], "hard_skills": ["java", "azure", "c++", "aws", "c", "javascript", "python", "kotlin"], "soft_skills": ["good team player", "communication and interpersonal skills", "fast learner"], "languages_combined": []}, "experience_required": {"duration": ["1-3 years"], "field": ["video", "relevant experience", "database"]}}, {"job_id": "100003009017252", "location_code": "hk", "company": "Synnex Technology International (HK) Ltd", "job_title": "Presales Engineer / System Specialist (Infrastructure/Networking)", "description": "Responsibilities :\n\nPresent and demonstrate IT solutions of leading brands like VMWare, HPE, Huawei, Sophos to partners and users\nStudy latest IT solutions and represent vendors to the market\nIdentify user requirements and generate BOM to meet users\u2019 needs\nArchitect POC or demo environment, and demonstrate to clients\nTrain and support partners to sell and provide system integration services on VM, Cloud, network security, VDI, etc.\n\nRequirements :\n\nDiploma or above with IT related working experience\nGood presentation and interpersonal skills\nFamiliar with network and security solutions are required\nSelf-motivated, strong analytical reasoning and problem solving skills\nProficient in both spoken and written English and Chinese\n\n\n\nWe offer attractive remuneration package to the right candidate.\u00a0 Interested parties, please send us your resume with current and expected salary by clicking \"Apply Now\".\u00a0\n\nFor more information about Synnex, please visit\u00a0http://www.synnex.com.hk\n\nAll information will be treated in strict confidence and will be used exclusively for recruitment related purpose only.", "employment_types": ["Full Time", "Permanent"], "selling_points": [], "locations": ["Kowloon Bay"], "categories": ["Information Technology (IT)", "Network & System", "Technical / Functional Consulting", "Mobile / Wireless Communications"], "post_time": "2022-01-03T11:43:53Z", "salary": {"currency": null, "max": null, "min": null, "period": "monthly", "term": null}, "salary_visible": false, "title_keywords": ["specialist", "engineer"], "responsibilities": [], "requirements": {"degrees": ["diploma or above"], "majors": ["it"], "languages": ["english", "chinese"], "language_level": ["proficient"], "hard_skills": ["problem solving skills"], "soft_skills": ["self-motivated", "interpersonal skills", "presentation", "problem solving skills"], "languages_combined": [{"language": "english", "language_level": ["proficient"]}, {"language": "chinese", "language_level": ["proficient"]}]}, "experience_required": {"duration": [], "field": ["related", "it"]}}]