[{"job_id": "100003009052416", "location_code": "hk", "company": "Ebroker Systems Ltd", "job_title": "IT Support Engineer-Fintech (Fresh Graduates are welcome)", "description": "Responsibilities\n\nPerform troubleshooting and provide day-to-day support including hardware, software, end-user and helpdesk;\nPerform hardware installation, configuration or maintenance, including PC, notebook, Mac, server, printer and other computer peripheral devices;\nConduct software installation, configuration or maintenance including MS-Office, Outlook, Windows, Mac, Adobe products, AntiVirus and other office applications;\nProvide regular testing of IT equipment and monitoring of IT equipment status and ah hoc on site support;\n\nRequirements\n\nIVE/Diploma holder in Information System, Computer Science, Computer Engineering or related disciplines;\n1 year experience in IT technical / deskside support will be an advantage, fresh graduates are also welcomed;\nKnowledge in Windows;\nKnowledge in AD, DNS, FTP, TCP/IP, POP3, SMTP & SNMP;\nGood computer knowledge of MS-Word, Excel, PowerPoint;\nGood command of spoken and written English and Chinese\nImmediately available will be an advantage\n\nWe offer excellent career development opportunities to unleash your potential, competitive remuneration package including a 5-day work week, medical insurance & dental plan, discretionary bonus, staff training and staff purchasing discount etc.\n\n\nInterest parties, please simply click \"Apply now\" to submit your application with full resume stating current & expected salary and the availability for reporting duty.\u00a0\n\nYou are welcome to visit our website to know more about us:\u00a0www.popular.com.hk\u00a0or http://ephhk.popularworldhk.com.\n\n\nPersonal data provided by job applicants will be kept strictly confidential and will be used solely\u00a0for employment related purpose.\u00a0\u00a0Only short-listed candidates will be contacted.", "employment_types": ["Full Time"], "selling_points": ["Happy & friendly environment", "Great career exposure", "Provides on-the-job training, 5-day work week"], "locations": ["Tsim Sha Tsui"], "categories": ["Information Technology (IT)", "Support", "Others", "Others", "Student / Fresh Graduate / No Experience"], "post_time": "2022-01-17T03:05:23Z", "salary": {"currency": null, "max": null, "min": null, "period": "monthly", "term": null}, "salary_visible": false, "title_keywords": ["it support engineer"], "responsibilities": ["installation", "software", "maintenance", "configuration", "monitoring", "troubleshooting", "testing", "hardware", "it equipment"], "requirements": {"degrees": ["diploma holder"], "majors": ["related disciplines", "computer engineering", "computer science"], "languages": ["english", "chinese"], "language_level": ["good command"], "hard_skills": ["ms-word", "excel", "dns", "tcp", "information system", "powerpoint", "ip"], "soft_skills": [], "languages_combined": [{"language": "english", "language_level": ["good command"]}, {"language": "chinese", "language_level": ["good command"]}]}, "experience_required": {"duration": ["1 year"], "field": ["it"]}}, {"job_id": "100003009051858", "location_code": "hk", "company": "Huawei International Co., Ltd", "job_title": "Supply Chain Management Assistant (Welcome Fresh Graduates)", "description": "Responsibilities:\n\n\nTo provide first level support to existing clients and to carry out daily health check of systems\nTo provide system and application support\nTo handle deployment of system modules\nProactively follow up technical issues and incidents\nTo assist clients to participate HKEx Market Rehearsal and to perform system tests\u00a0\nTo carry mobile and handle non-office hours call\n\nRequirements:\n\nHigher Diploma or above in\u00a0Computer Science, Computer Engineering, Information Technology or related disciplines\u00a0\nKnowledge in MS SQL Server, MS Windows administrative and configuration\nKnowledge and experience in trading solutions, equity/futures trading rules of HK and China is preferable\nAnalytical, creative mind and able to work under pressure\nResponsible, good interpersonal skill and good team player\nGood command of both written and spoken Mandarin/English is preferable\nJoin us to work in a Hong Kong\u00a0listed leading Fintech company!\n\nFor application, please email your detailed resume and expected salary to us.\n\nAll applications will be treated in strict confidence and will be handled by authorized personnel only. Information provided will be used for the purpose of employment application to eBroker Systems Limited and will be destroyed within 6 months from the date of receipt.", "employment_types": ["Full Time", "Contract"], "selling_points": ["New ICT technology and solutions", "International Insight", "1- 5 years of experience are preferred"], "locations": ["Tsim Sha Tsui"], "categories": ["Engineering", "Engineering Project Management", "Information Technology (IT)", "Others", "Transportation & Logistics", "Supply Chain"], "post_time": "2022-01-17T01:23:47Z", "salary": {"currency": null, "max": null, "min": null, "period": "monthly", "term": null}, "salary_visible": false, "title_keywords": ["assistant"], "responsibilities": ["systems"], "requirements": {"degrees": ["higher diploma or above"], "majors": ["related disciplines", "computer engineering", "computer science", "information technology"], "languages": ["english", "mandarin"], "language_level": ["good command"], "hard_skills": ["ms sql server", "ms windows"], "soft_skills": ["good team player", "confidence", "responsible", "detailed", "interpersonal skill", "creative", "work under pressure"], "languages_combined": [{"language": "english", "language_level": ["good command"]}, {"language": "mandarin", "language_level": ["good command"]}]}, "experience_required": {"duration": [], "field": ["trading"]}}, {"job_id": "100003009049409", "location_code": "hk", "company": "Shanghai Commercial Bank Ltd", "job_title": "IT Operations Support", "description": "This is a Yearly Renewable Contract Position. (Service Provider: Manpower). As a global ICT company with a presence in over 170 countries and regions, we provide a broad platform where employees can realize their personal value. This is an excellent opportunity to build up your career in ICT industry where you be enriched with our Huawei innovative business solutions.\n\nResponsibilities:\n\n- Be responsible for customer requirements and demand plans of key projects by supporting the operation of comprehensive plans;\n- Organize project and assist supply chain managers to participate in project bidding;\n- Identify supply requirement risks and make supply solutions accordingly;\n- Monitor the fulfillment of contracts and key projects and resolve abnormal cases to ensure the goods supplied timely and accurately.\n\nRequirements:\n\n- Bachelor Degree or above in procurement and/ or supply chain management or other related disciplines;\n- Basic understanding on general software knowledge and equipped with excellent IT and MS software skills;\u00a0\n- Strong interpersonal and communication skills, ability to establish and maintain cooperative and harmonious working relationship within a multicultural work environment;\n- Ability to work in a team and build up good relations with all projects stakeholders;\n- With integrated decision-making skills, ability to prioritize and focus;\n- To be positive and have that \"never give up and work under pressure\"\u00a0attitudes;\n- Good Command of written and spoken English and Cantonese. Knowledge of Mandarin is an advantage.\n\nExperienced candidates will be considered as specialist position\u00a0\n\n\n", "employment_types": ["Full Time", "Permanent"], "selling_points": ["Plan & control IT operations job flow & execution", "Administer and maintain user access rights", "Perform ad hoc data updates"], "locations": ["Kwai Hing"], "categories": ["Banking / Finance", "Others", "Information Technology (IT)", "Support", "Others"], "post_time": "2022-01-15T03:50:24Z", "salary": {"currency": null, "max": null, "min": null, "period": "monthly", "term": null}, "salary_visible": false, "title_keywords": ["operations"], "responsibilities": [], "requirements": {"degrees": [], "majors": [], "languages": [], "language_level": [], "hard_skills": [], "soft_skills": [], "languages_combined": []}, "experience_required": {"duration": [], "field": []}}, {"job_id": "100003009051851", "location_code": "hk", "company": "Sinowittech (Hong Kong) Technology Co., Limited", "job_title": "System Analyst", "description": "Responsibilities\n\nPlan and control IT operations job flow and execution\nAdminister and maintain user access rights to application systems\nPerform ad hoc data updates and parameter changes of application systems in production environment\nProvide administrative support on program version controls\n\nRequirements\n\nHigher Diploma holder in Information Technology or related disciplines\nMinimum 1 year of relevant experience in computer operations and support, preferably with experience in operating AIX, LINUX, Windows system platforms.\nKnowledge in job schedule tools, shell script programming, IBM Mainframe (Z/OS, JCL, CLIST, TSO)\n\nIndependent with logical thinking\nGood communication and interpersonal skills\n\nAttractive remuneration package will be offered to the right candidates. Interested parties please click \"Apply Now\" to submit your full resume with current and expected salary to the Human Resources Division.\n\n\nPlease visit us at www.shacombank.com.hk for more information about our Bank.\n\nAll personal data collected will be used for recruitment related purposes strictly in accordance with the Bank's personal data policies, a copy of which will be provided immediately upon request by contacting our Personal Data Compliance Officer. Applicants who are not contacted within two months may consider their applications unsuccessful and the personal data collected from the applicants will be retained for no longer than two years from the date of rejection during which the applicants may be considered for other suitable positions within the Bank.", "employment_types": ["Full Time"], "selling_points": ["Double pay", "Five-day work week", "Travel allowance"], "locations": ["Tai Po Area"], "categories": ["Information Technology (IT)", "Network & System", "Technical / Functional Consulting", "Others"], "post_time": "2022-01-17T01:22:34Z", "salary": {"currency": "HKD", "max": 44999, "min": 35000, "period": "monthly", "term": null}, "salary_visible": true, "title_keywords": ["system analyst"], "responsibilities": ["control", "ad hoc", "data", "operations", "maintain", "plan", "provide administrative support", "application systems"], "requirements": {"degrees": ["higher diploma holder"], "majors": ["related disciplines", "information technology"], "languages": [], "language_level": [], "hard_skills": ["linux", "jcl", "clist", "os", "programming"], "soft_skills": ["communication and interpersonal skills", "independent"], "languages_combined": []}, "experience_required": {"duration": ["minimum 1 year"], "field": ["relevant experience"]}}, {"job_id": "100003009052934", "location_code": "hk", "company": "Haven of Hope Christian Service", "job_title": "Assistant System Analyst (Ref: SSO/IT/ASA/JDB)", "description": "Responsibilities\n\n\nProvide technical support and troubleshooting to end users on hardware, software and computer services\u00a0\nPerform maintenance, configuration and monitoring of IT equipment\nPerform management of hardware and software inventory\nAssist in IT documentation, process improvement and equipment procurement\nAssist in project support and perform ad hoc duties as assigned\nRequirements:\n\n\nDegree in Information Technology, Computer Science or related disciplines\nCCNA/CCNP/MCSE certificate holder will be an advantage\n2 years experience in IT Support\nHands on experience in O365 (Teams/SharePoint Online), Win10, Active Directory, VMWare/Hyper-V\nKnowledge in TCP/IP, Wi-Fi, Firewall, network infrastructure and security technology\nA self-motivated and organized individual with good problem solving skills and strong sense of responsibility\nAbility to work independently, flexibly and positively\nGood command in both spoken and written English and Chinese (Cantonese and Mandarin)\u00a0\nApplicants with less experience will be considered as IT Officer.\u00a0 Fresh graduates is also welcomed\nInterested parties please send your resume with your\u00a0current and expected salary\u00a0to email:\u00a0hrd @ win-hanverky.com.hk\u00a0or click \"APPLY NOW\".\u00a0The closing date for application is 17 February 2022.\u00a0All information collected will be kept in strict confidence and will be used for recruitment purpose only.", "employment_types": ["Full Time"], "selling_points": [], "locations": ["Not Specified"], "categories": ["Information Technology (IT)", "Network & System", "Others"], "post_time": "2022-01-17T04:36:33Z", "salary": {"currency": null, "max": null, "min": null, "period": "monthly", "term": null}, "salary_visible": false, "title_keywords": ["system analyst", "assistant"], "responsibilities": ["ad hoc duties", "management", "software", "maintenance", "technical support", "configuration", "inventory", "computer services", "monitoring", "troubleshooting", "hardware", "documentation", "it equipment"], "requirements": {"degrees": ["certificate", "degree"], "majors": ["related disciplines", "computer science", "information technology"], "languages": ["cantonese", "english", "chinese", "mandarin"], "language_level": ["good command"], "hard_skills": ["mcse", "o365", "hyper-v", "vmware", "active directory", "tcp", "wi-fi", "ccnp", "ccna", "ip", "firewall", "problem solving skills"], "soft_skills": ["organized", "self-motivated", "work independently", "sense of responsibility", "hands on", "problem solving skills", "active"], "languages_combined": [{"language": "cantonese", "language_level": ["good command"]}, {"language": "english", "language_level": ["good command"]}, {"language": "chinese", "language_level": ["good command"]}, {"language": "mandarin", "language_level": ["good command"]}]}, "experience_required": {"duration": ["2 years"], "field": ["it", "it support"]}}, {"job_id": "100003009054789", "location_code": "hk", "company": "The Education University of Hong Kong", "job_title": "Computer Officer (User Services \u2013 User Support) (Ref: 2200009)", "description": "Responsibilities:\n\nResponsible for the requirements gathering, system analysis, design and development of the back office system as well as customer online platform and mobile applications;\nProvide technical solution in the enterprise architecture design and implementation;\nPerform proof-of-concepts of technical solution;\nPrepare the technical specification and related documents;\nEnsure to follow the coding standard and best practices;\nPerform and ensure the quality of unit tests and system integration tests;\nProvide ongoing application maintenance and program refinement; and\nSupport ad-hoc tasks on demand.\n\nRequirements:\n\nA Bachelor\u2019s Degree in Information Technology, Computer Science or related disciplines;\nAt least 2 years\u2019 working experience.\u00a0 Fresh graduates are welcome and may be considered as Software Developer;\nExperience in software development for backend, frontend, server-side, API web services, cloud based and mobile applications development, maintenance and support;\nHands-on programming skills in web development with PHP, Java, JavaScript, CSS, programming frameworks including Drupal, JASON, XML, WordPress & Microsoft .NET framework;\nKnowledge and/or Experience of Database programming and both SQL/T-SQL and NoSQL (MS-SQL, MySQL);\nExperience in preparing system integration, data migration, and rollout plan, providing IT security requirements and issues;\nExperience in performing the stress test and optimizing the system performance;\nExperience in managing vendors would be an advantage;\nExperience in using Apache, Tomcat, Git and/or TortoiseSVN, Jenkins development services or tools would be an advantage;\nMature, proactive, flexible, self-motivated and team oriented;\nPossesses analytical, problem solving and interpersonal skills;\nWilling to learn and improve skills;\nWilling to explore and study the new technologies applicable to new projects;\nGood communication and documentation skills; and\nProficiency in both written and spoken English and Chinese.\n\n\nPlease send full resume with expected salary and reference no. quoted to Haven of Hope Christian Service, Staff Engagement Department, 7 Haven of Hope Road, Tseung Kwan O, New Territories or via email by clicking \"Apply Now\", or via Whatsapp no. 6507 8148 (with reference no. quoted at the caption) on or before 5 February 2022. Only short-listed candidates will be notified.\nEnquiry: 2703 3227 (Phone); 6507 8148 (Whatsapp).\nFor details about our organization, please visit www.hohcs.org.hk.\nProspective employees are requested to undergo/submit Sexual Conviction Record Check for work relating to children or mentally incapacitated persons before employment. Data collected will be used for recruitment purpose only.\nThis advertisement should not be reproduced, in whole or in part, to other recruitment websites without our prior written permission.", "employment_types": ["Full Time"], "selling_points": [], "locations": ["Not Specified"], "categories": ["Information Technology (IT)", "IT Project Management / Team Lead", "Support", "Others"], "post_time": "2022-01-17T11:05:34Z", "salary": {"currency": null, "max": null, "min": null, "period": "monthly", "term": null}, "salary_visible": false, "title_keywords": ["officer"], "responsibilities": ["maintenance", "related documents", "analysis", "ad-hoc tasks", "quality", "implementation", "back office", "design", "coding", "architecture"], "requirements": {"degrees": ["degree", "bachelor"], "majors": ["related disciplines", "computer science", "information technology"], "languages": ["english", "chinese"], "language_level": ["proficiency"], "hard_skills": ["jenkins", "server", "java", "git", "no", "problem solving", "database programming", "integration", "web development", "t-sql", "sql", "wordpress", "javascript", "whatsapp", "documentation", "hope", "apache", "maintenance", "php", "mobile", "ms-sql", "programming", "css", "web services"], "soft_skills": ["flexible", "self-motivated", "willing to learn", "mature", "problem solving", "communication", "hands-on", "interpersonal skills", "proactive"], "languages_combined": [{"language": "english", "language_level": ["proficiency"]}, {"language": "chinese", "language_level": ["proficiency"]}]}, "experience_required": {"duration": ["at least 2 years"], "field": ["maintenance", "software development", "development", "sql", "it", "security", "programming", "database"]}}, {"job_id": "100003009051877", "location_code": "hk", "company": "LAWSGROUP", "job_title": "System Analyst", "description": "Office of the Chief Information Officer\n\nThe Office of the Chief Information Officer (OCIO) has a vision to be a world-class provider of information and communications technology services and solutions to support and enhance teaching, learning, research and administration of the University.\n\nThe OCIO provides quality services to support all central information systems in support of teaching, learning, research and administration. It places emphasis on staff\u2019s career/professional development. The Office is looking for quality professionals to fill the vacancy of Computer Officer\n\nThe appointee will be responsible for supervising a team of technical staff to provide quality IT support services, including on-site and telephone services; answering enquiries through the IT Help Desk email account; coordinating and conducting IT services orientation workshops for new students. He/she has to assist the IT Manager in planning, budgeting and tendering computing resources for all departments and teaching venues; as well as maintaining an accurate and up-to-date inventory record of computing equipment for the University.\n\nApplicants should have a recognized Bachelor\u2019s Degree in Computer Science/Information Technology or related disciplines, with at least 7 years of relevant full-time post-qualification working experience gained in a sizeable IT environment. They should have supervisory experience and in-depth knowledge in support of PC, Microsoft Windows and Macintosh systems. Applicants should have good problem-solving, analytical and interpersonal skills; and be proficient in both English and Chinese with good communication skills. They should also work proactively and independently; be able to handle multiple tasks simultaneously and be a good team player.\n\nSalary will be commensurate with qualifications and experience.\n\nInitial appointment will be made on a fixed-term contract.\u00a0Fringe benefits include contract-end gratuity, leave, medical and dental benefits.\n\nThe University only accepts and considers applications submitted online for this post.\u00a0 Applicants should complete the online application form and upload a full CV.\u00a0 Review of applications will start from 28 January 2022, and will continue until the post is filled.\u00a0 Applications which are incomplete or without the required documents may not be considered. \u00a0Personal data provided by applicants will be used for recruitment and other employment-related purposes. \u00a0For details of the Personal Information Collection Statement, please refer to http://www.eduhk.hk/jobsopp/index.php?glang=en.\n\nAll applications will be treated in strict confidence.\u00a0 Only those who are shortlisted will be contacted.\u00a0 The University reserves the right not to fill the position(s) advertised.\u00a0 \u00a0\u00a0\n\nFurther information about the University is available at http://www.eduhk.hk.\n\nEdUHK is an Equal Opportunities Employer.", "employment_types": ["Full Time", "Permanent"], "selling_points": ["Degree holder w 5 yrs exp in system development", "Solid experience in MySQL / Informix etc.", "Familiar with Angular front-end language"], "locations": ["Lai Chi Kok"], "categories": ["Information Technology (IT)", "IT Project Management / Team Lead", "Network & System", "Others"], "post_time": "2022-01-17T01:25:52Z", "salary": {"currency": null, "max": null, "min": null, "period": "monthly", "term": null}, "salary_visible": false, "title_keywords": ["system analyst"], "responsibilities": ["supervising", "maintaining", "budgeting", "support services", "systems", "quality", "tendering", "inventory record", "communication", "planning", "administration"], "requirements": {"degrees": ["degree", "bachelor"], "majors": ["related disciplines", "it", "computer science", "information technology"], "languages": ["english", "chinese"], "language_level": ["good", "proficient"], "hard_skills": ["workshops", "pc", "problem-solving"], "soft_skills": ["communication skills", "good team player", "independently", "responsible", "problem-solving", "handle multiple tasks", "learning", "interpersonal skills", "accurate", "world-class"], "languages_combined": [{"language": "english", "language_level": ["proficient", "good"]}, {"language": "chinese", "language_level": ["proficient", "good"]}]}, "experience_required": {"duration": ["at least 7 years"], "field": ["post-qualification", "related", "information technology", "it", "supervisory experience"]}}, {"job_id": "100003009051931", "location_code": "hk", "company": "Octopus Holdings Limited", "job_title": "Assistant Manager, Professional Services (Ref: OCL/OPS/2021-225)", "description": "UAT Tester (Business Innovation & FinTech) (Job ID 3045)\nResponsibilities\n\nTo be a team member of Business Innovation & FinTech Department\nAssist Test Manager to complete all UAT related activities\nRequirements\n\nUniversity graduate with 1-2 years\u2019 working experience in banking industry is preferable covering the following:\nPrepare UAT test cases according to the user requirement and UI design\nExecute UAT test cases in regular or ad-hoc release cycles\nReport defect/issue clearly with detail steps using the provided bug tracking tools\nGenerate daily test report for management\nSolid experience in performing UAT\nExperience with performance and/or security testing is a plus\nStrong communication and presentation skill is an advantage\nFamiliar with Excel, HPQC, JIRA\nProficient in of both spoken and written English and Chinese\nPlease apply online via the BEA Careers website at https://careers.hkbea.com/psp/hcmprd/EMPLOYEE/HRMS/c/HRS_HRAM.HRS_APP_SCHJOB.GBL?Page=HRS_APP_JBPST&Action=UFOCUS=Applicant&SiteId=1&JobOpeningId=3045&PostingSeq=1 or by clicking the \"Apply Now\" button below. Kindly note that if you are a new user, you have to first create your User Profile before you can apply.\nPersonal data provided by job applicants will be used for recruitment purposes only and will be treated in accordance with the Bank's Personal Information Collection (Employees) Statement and Privacy Policy Statement. Applicants who are not invited for interviews within six weeks may consider their applications unsuccessful and the personal data collected will be destroyed after six months.", "employment_types": ["Full Time", "Permanent"], "selling_points": ["Handle merchant complaints and liaise internally", "Bachelor degree holders in Information, Computer", "Minimum 7 years working experience"], "locations": ["Kowloon Bay"], "categories": ["Information Technology (IT)", "Network & System", "Technical / Functional Consulting", "Others"], "post_time": "2022-01-17T01:32:43Z", "salary": {"currency": null, "max": null, "min": null, "period": "monthly", "term": null}, "salary_visible": false, "title_keywords": ["assistant manager,"], "responsibilities": ["uat"], "requirements": {"degrees": ["university graduate"], "majors": [], "languages": ["english", "chinese"], "language_level": ["proficient"], "hard_skills": ["presentation skill", "excel", "plus", "c"], "soft_skills": ["communication", "presentation skill"], "languages_combined": [{"language": "english", "language_level": ["proficient"]}, {"language": "chinese", "language_level": ["proficient"]}]}, "experience_required": {"duration": ["1-2 years"], "field": ["banking industry", "security", "testing"]}}, {"job_id": "100003009051207", "location_code": "hk", "company": "\u5411\u85cd\u5929\u79d1\u6280\u6709\u9650\u516c\u53f8", "job_title": "Senior Frontend Software Developer (Flutter)", "description": "Responsibilities\n\n1. Responsible for full cycle of talent recruitment process from candidates sourcing, shortlisting, conducting interview, offering to on-boarding process\n2. Explore and manage all potential sourcing channels of talent, e.g. LinkedIn, online job posting, social media, campus recruitment, employee referrals and other active searching channels\n3. Work closely with Compensation & Benefit (C&B) team to organize and implement HR initiatives and projects\n4. Deliver induction program to new joiners, support and deliver learning & development initiatives and monitor training administration\n5. Assist in identifying and assessing future and current training needs through job analysis, career paths, annual performance appraisals and consultation\n6. Support and assist in organizing staff activities and events and ad hoc projects as assigned\n\nRequirements\n\n1. Bachelor Degree in Business Administration, Human Resources Management or equivalent\n2. Minimum 4-8 year\u2019s related working experience, preferably in IT industry\n3. Fluent in spoken and written English, Cantonese and Putonghua\n4. Proficient in MS Word, Excel, PowerPoint & Chinese Word Processing\n5. Well-versed in Hong Kong Employment Ordinance, related statutory regulations and HR general practice.\n6. Good interpersonal & communication skills, competence to interact and build relationships at all levels of the company independently\u00a0 \u00a0 \u00a0\n7. Knowledge of hiring overseas and mainland staff would be advantage; such as contract T&C, Immigration, Visa application, etc.", "employment_types": ["Full Time", "Permanent"], "selling_points": ["Fast Growing Technology Company", "Career Development and Good Team Culture", "Competitive compensation"], "locations": ["Yau Ma Tei"], "categories": ["Information Technology (IT)", "Application Specialist - Software", "Software Development", "Others"], "post_time": "2022-01-15T04:46:22Z", "salary": {"currency": null, "max": null, "min": null, "period": "monthly", "term": null}, "salary_visible": false, "title_keywords": ["developer"], "responsibilities": ["social media", "hr", "analysis", "monitor", "recruitment", "ad hoc projects", "recruitment process", "administration"], "requirements": {"degrees": ["degree", "bachelor"], "majors": ["business administration"], "languages": ["cantonese", "putonghua", "english", "chinese"], "language_level": ["proficient", "fluent"], "hard_skills": ["excel", "chinese word processing", "hong kong employment ordinance", "powerpoint", "ms word"], "soft_skills": ["communication skills", "independently", "interpersonal"], "languages_combined": [{"language": "cantonese", "language_level": ["fluent"]}, {"language": "putonghua", "language_level": ["fluent"]}, {"language": "english", "language_level": ["fluent"]}, {"language": "chinese", "language_level": ["proficient"]}]}, "experience_required": {"duration": ["minimum 4-8 year"], "field": ["related", "it"]}}, {"job_id": "100003009053989", "location_code": "hk", "company": "The Bank of East Asia, Limited", "job_title": "UAT Tester (Business Innovation & FinTech)", "description": "This position will provide high quality services and technical support to customers and partners for the products.\u00a0 Main responsibilities include:\n\nResponsibilities\n\nPerform user requirements collection, system design & configuration and report design\nParticipate in testing of customers\u2019 systems performance\nEvaluate alternative solutions and make recommendation on system improvement\nProvide remote or onsite access support on customers\u2019 system environments\nPerform trouble shooting and implement solution to complex technical issues\nSupervises and provides direction to software engineers. Daily interaction with clients and stakeholders\nDeliver customer presentations, internal & external customers training\n\n\u00a0Requirements\n\nBachelor\u2019s Degree in Computer Science, Electrical Engineering or related discipline\nMinimum 6 years\u2019 relevant experience covering an entire software lifecycle in a team environment\nKnowledgeable in SQL, .Net , C# or JavaScript. Expertise in database applications, particularly in Oracle and/or MS SQL Server a plus\nKnowledge and experience in maintaining Windows Server cluster (VMware ESXi) and network configuration (firewall rules and DMZ) is a plus.\nCustomer-oriented with excellent interpersonal and communication skills\nFluency in oral and written English and Chinese communication\n\n\u00a0 \u00a0 \u00a0Please visit our website www.sinowittech.com for more information about our CompanyPersonal data collected will be used for recruitment purposes only.", "employment_types": ["Full Time", "Permanent"], "selling_points": ["To be a team member of Business Innovation", "Assist Test Manager to complete all UAT related", "With 1-2 years\u2019 working experience in banking"], "locations": ["Not Specified"], "categories": ["Information Technology (IT)", "Testing / QA", "Others"], "post_time": "2022-01-17T07:56:47Z", "salary": {"currency": null, "max": null, "min": null, "period": "monthly", "term": null}, "salary_visible": false, "title_keywords": ["uat tester"], "responsibilities": ["make recommendation", "software", "configuration", "systems", "design", "testing", "evaluate", "presentations", "system design", "report"], "requirements": {"degrees": ["degree", "bachelor"], "majors": ["electrical engineering", "computer science"], "languages": ["english", "chinese"], "language_level": ["fluency"], "hard_skills": ["plus", "vmware", "ms sql server", "c#", "sql", "javascript", "firewall", "windows server", "oracle"], "soft_skills": ["communication skills", "oral", "communication", "customer-oriented", "interpersonal"], "languages_combined": [{"language": "english", "language_level": ["fluency"]}, {"language": "chinese", "language_level": ["fluency"]}]}, "experience_required": {"duration": ["minimum 6 years"], "field": ["relevant experience", "team"]}}, {"job_id": "100003009052080", "location_code": "hk", "company": "ADECCO", "job_title": "IT Helpdesk Administrator (General IT support, up to 22k)", "description": "Responsibilities:\n\nProvide technical/ desk side support including Windows, Mac, Smart Phone and Virtual Conferencing, for end users\nShare best practices to end users\nSupport and troubleshoot in IT operations issues including the operations of in-house systems\nAssist to handle any ad-hoc projects upon request by line manager\n\nRequirements:\n\nDiploma or above in Computer Science/Information Technology/ Information Systems or related disciplines\n1 year's relevant in IT support operations, Windows Server Administration, Systems/Network supports and troubleshooting\nKnowledge in SQL database language will be advantageous\nProactive with a \u2018can-do\u2019 attitude, willingness to learn, good communication skills, customer service oriented, and good problem-solving skills\nGood command in spoken and written English and Mandarin\n\n\nWe offer attractive remuneration package including work from home policy, 13-instalment salary, discretionary bonus,\u00a0life, medical, dental and eyecare insurances to the right candidate.\u00a0Interested\u00a0applicants\u00a0please send\u00a0your\u00a0detailed\u00a0resume with current and expected salary and the\u00a0availability to Human Resources Department by clicking \"APPLY NOW\"\u00a0or by post:\n\n\nHuman Resources Department\nCurrys Sourcing Limited\n31/F, AXA Tower, Landmark East\n100 How Ming Street, Kwun Tong\nKowloon\nPersonal Data collected will be used for recruitment purposes only. Applicants who are not invited within 2 months may consider their application unsuccessful. Personal data of unsuccessful applicants will be retained for a period of up to 6 months from the date of rejecting applicants and will then be destroyed.", "employment_types": ["Full Time", "Permanent"], "selling_points": [], "locations": ["Pok Fu Lam"], "categories": ["Information Technology (IT)", "Support", "Testing / QA", "Others"], "post_time": "2022-01-17T02:03:02Z", "salary": {"currency": null, "max": null, "min": null, "period": "monthly", "term": null}, "salary_visible": false, "title_keywords": ["administrator", "it support"], "responsibilities": ["operations", "ad-hoc projects", "systems", "troubleshoot"], "requirements": {"degrees": ["diploma or above"], "majors": ["related disciplines", "computer science", "information technology"], "languages": ["english", "mandarin"], "language_level": ["good command"], "hard_skills": ["sql", "problem-solving skills", "windows server"], "soft_skills": ["communication skills", "customer service oriented", "troubleshooting", "can-do", "problem-solving skills", "proactive", "detailed"], "languages_combined": [{"language": "english", "language_level": ["good command"]}, {"language": "mandarin", "language_level": ["good command"]}]}, "experience_required": {"duration": [], "field": []}}, {"job_id": "100003009050053", "location_code": "hk", "company": "Million Tech Development Ltd", "job_title": "Technical Support Engineer (5 Days Work)", "description": "Responsibilities:\n\nTo provide EUC day-to-day support, inclusive of Office IT systems, PC hardware / software / connectivity and BYOD users; and\nTo assist the VDI Project deployment includes user management, profile migration, data migration, troubleshooting and inventory management\n\n\u00a0Requirements:\n\nDiploma in IT or related discipline;\nMinimum 3 years working experience in EUC support;\nHands on experience in VDI (VMWare), Microsoft Office and Outlook Applications (troubleshooting & problem solving) and VPN\nFamiliar with PC / Laptop / Phone / Mobile phone / Thin Client;\nService to Senior Management experience is a plus\nGood analytical, PC / device trouble shooting, and problem solving skills;\nGood interpersonal skill and a good team player\nMature, dynamic, work independent and self-motivated\nGood spoken and written English and Cantonese, Mandarin a plus.\n\nWe offer competitive salary package and career development opportunity. \u00a0Free company coach is provided. Interested parties, please quote our reference number and apply with full resume,\u00a0present and expected salary, by clicking \"APPLY NOW\".\u00a0\n\u00a0\n\nWe are an equal opportunity employer and welcome applications from all qualified candidates. Information provided will be treated in strict confidence and only be used for consideration of your application for the relevant post within the HGC Global Communications Limited. Personal data provided by job applicants will be used strictly according to our Personal Information Collection Statement, a copy of which will be available upon written request. Information of unsuccessful candidates will be destroyed within six months.", "employment_types": ["Full Time", "Permanent"], "selling_points": ["Higher Diploma or above in Computer Science/ IT", "2 years working experience in IT Industry", "Holder of CCNA, MCP, MCSE is an advantage"], "locations": ["Lai Chi Kok"], "categories": ["Information Technology (IT)", "Support", "Network & System", "Others"], "post_time": "2022-01-14T10:01:09Z", "salary": {"currency": null, "max": null, "min": null, "period": "monthly", "term": null}, "salary_visible": false, "title_keywords": ["technical support engineer"], "responsibilities": ["management", "software", "data", "systems", "troubleshooting", "inventory management", "hardware", "migration"], "requirements": {"degrees": ["diploma"], "majors": ["it"], "languages": ["cantonese", "english", "mandarin"], "language_level": ["good"], "hard_skills": ["plus", "vmware", "microsoft office", "euc", "problem solving", "mobile", "dynamic", "outlook", "vpn", "pc", "problem solving skills"], "soft_skills": ["good team player", "self-motivated", "independent", "troubleshooting", "mature", "interpersonal skill", "problem solving", "hands on", "dynamic", "problem solving skills"], "languages_combined": [{"language": "cantonese", "language_level": ["good"]}, {"language": "english", "language_level": ["good"]}, {"language": "mandarin", "language_level": ["good"]}]}, "experience_required": {"duration": ["minimum 3 years"], "field": ["management", "troubleshooting"]}}, {"job_id": "100003009054429", "location_code": "hk", "company": "Currys Sourcing Limited", "job_title": "IT Support", "description": "Responsibilities:\n\nImplement network infrastructure installations and configurations\nParticipate in troubleshooting and support of network infrastructure and various client services\nDeliver technical documentation of infrastructure, control procedures, operation and review data network proposals\nDrive vendor for technology enhancement and manage the project delivery, product support and escalated issue management\n\nRequirements:\n\nHigher Diploma or above in Information Technology, Electrical Engineering or Computer Science\nAt least 3 year\u2019s experience in Network management such as: switches, routers, wi-fi, and load balancers.\nAt least 3 year\u2019s experience in one or more of the following: installing, troubleshooting, operating, testing, planning and configuring relevant technologies.\nAbility to perform advanced problem determination / resolution\nGood Command in written and communicate in English and Chinese\n\nPlease send your full resume with MS Word format to us\u00a0by email\u00a0or\u00a0fax: 3426 2763,\u00a0or you may click the\u00a0Apply Now\u00a0button below.\u00a0\n\nFor other vacancies, please visit our website www.swing-hk.com\n\nJoin us on facebook \u2013 www.facebook.com/swinghk\n\nAll information provided will be treated in strict confidence and used for recruitment purposes only.\u00a0", "employment_types": ["Full Time", "Permanent"], "selling_points": ["Attractive Remuneration Package", "Comprehensive Wellbeing Programme", "Work-life Balance"], "locations": ["Kwun Tong"], "categories": ["Information Technology (IT)", "Support", "Others"], "post_time": "2022-01-17T09:30:36Z", "salary": {"currency": null, "max": null, "min": null, "period": "monthly", "term": null}, "salary_visible": false, "title_keywords": ["it support"], "responsibilities": ["network infrastructure", "control", "management", "data", "infrastructure", "procedures", "troubleshooting", "review", "documentation"], "requirements": {"degrees": ["higher diploma or above"], "majors": ["electrical engineering", "computer science", "information technology"], "languages": ["english", "chinese"], "language_level": ["good command"], "hard_skills": ["ms word", "network management", "facebook", "wi-fi"], "soft_skills": ["advanced", "confidence", "troubleshooting"], "languages_combined": [{"language": "english", "language_level": ["good command"]}, {"language": "chinese", "language_level": ["good command"]}]}, "experience_required": {"duration": ["at least 3 year"], "field": ["management", "planning", "troubleshooting", "testing"]}}, {"job_id": "100003009049369", "location_code": "hk", "company": "HGC Global Communications Limited", "job_title": "End User Computing Support Engineer", "description": "About us:\n\nAutotoll is not just a toll collector for roads and tunnels!\nWe have diversified into Smart City solutions including Finance, Big Data, Artificial Intelligence, Machine Learning, Internet of Things, and much more\nWe work on projects from traffic control to smart property management with an IT team approaching 100\nWhat we do is unique, creative and at the forefront of innovative technology\nWe are constantly searching for the bright, the passionate, and the committed to join our quest to shape the future of our home\n\nAbout The Role:\n\n\nContinuous delivery for application / system on staging and production environments, include regression testing / health check, assist in user acceptance test, deployment, application monitoring and performance review\nHandle technical support cases that transfer from first-line support\nHandle and troubleshoot application/system issues encountered by users and monitoring system\nSetup application and performance monitoring\nReport bugs and performance issue to development team\n\n\u00a0\nAbout You:\n\n\nHigher Diploma or above in Computing or related discipline\nExperiencing in programming / scripting in C# / JAVA, HTML 5, Linux Shell Script, SQL\nPython / YAML / PowerShell in advantage but not a must\nDevOps experience will be an advantage but not a must\nAt least 2 year's working experience in application support / development\nFresh graduates will also be considered\n\n\nWhat you can get from us\n\n\nWork happier - Flexible working hour and five-day work week for better work-life balance\nWork healthier - Dental insurance, life insurance, and medical insurance\nInvest in your future - On-the-job training, learning and certification to build your career\nCorporate benefits - Executive workshops, interest class, corporate purchase discount offered by SHKP\nValuing your contribution - Competitive salary and annual leaves, and performance bonus\nWe are not that far away - Free shuttle bus to/from MTR\n\nInterested parties, please send full resume with\u00a0expected salary\u00a0and\u00a0available date\u00a0to Human Resources and Administration Department by e-mail or by fax 2111 9459.\n\n(Data collected will be used for recruitment purpose only.)", "employment_types": ["Full Time", "Permanent"], "selling_points": ["Internal IT service and operations support", "Vibrant team culture and atmosphere", "System enhancement exposure"], "locations": ["Tsing Yi"], "categories": ["Information Technology (IT)", "Hardware", "Support", "Others"], "post_time": "2022-01-14T08:31:44Z", "salary": {"currency": null, "max": null, "min": null, "period": "monthly", "term": null}, "salary_visible": false, "title_keywords": ["support engineer"], "responsibilities": ["control", "management", "technical support", "monitoring", "big data", "review", "testing", "troubleshoot", "insurance", "setup", "report"], "requirements": {"degrees": ["higher diploma or above"], "majors": [], "languages": [], "language_level": [], "hard_skills": ["linux", "java", "devops", "html", "sql", "deployment", "programming", "powershell", "python", "c#"], "soft_skills": ["passionate", "flexible", "unique", "innovative", "committed", "learning", "troubleshoot", "creative"], "languages_combined": []}, "experience_required": {"duration": ["at least 2 year"], "field": ["development", "devops"]}}, {"job_id": "100003009054797", "location_code": "hk", "company": "IKEA", "job_title": "IT Technical Specialist (infrastructure)", "description": "WHY YOU WILL LOVE US\n\nWe\u2019re a diverse group of down-to-earth, straightforward people with a passion for home furnishing. We come from all over the world, but we share an inspiring vision: \u201cto create a better everyday life for the many people\u201d. How we realize this vision is based on our shared humanistic values. These values guide our work and build our inclusive, open and honest culture. It\u2019s all based on a spirit of togetherness and enthusiasm. We work hard, but we have fun doing it. We\u2019re always looking for people who share our positive attitude and values.\n\nWHY WE WILL LOVE YOU\n\nYou have 2 years IT-related experience in the retail industry experience, either IKEA or Dairy Farm experience will be the plus\nYou have medium level knowledge of IT infrastructure and basic for Application\nYou have strong passion and comfort to perform daily operational support\nYou are a strong fit with the IKEA Culture and Values\nYou have strong communication and interpersonal skills\nYou are customer service oriented\nYou have logical and creative thinking\nYou have a good command of both written and spoken English\n\nWHAT YOU WILL BE DOING DAY TO DAY\n\nOffer the first tier support service of IT infrastructure to end-users and ensure the robust daily business operation in the stores, services office and warehouse. Infrastructure service scope to cover Store, Service Office and warehouse workplace management, Server operation, Network, Capacity, Basic database administration, IT Security Management, Facility management and appointed projects\nProactive monitor the daily infrastructure or application service and implement the preventive actions & solutions with IKEA IT, Dairy Farm Group IT, contractors or service providers in order to provide first-tier efficient service to store end users\nTo be the store, service office & warehouse focal point of first-tier help desk service, server, storage and network support, record, response or escalate users' incident log to teammates. Ensure the service level was secured and delivered. The purpose is to maintain the high-level service scarification of end-users\nParticipate the in-store, service office and warehouse IT infrastructure projects to assist the planned activities or appointed assignments from line manager\nResponsible for updating the documentation of infrastructure landscape\nAssist to conduct the necessary training to store end users. The purpose to increase the basic IT knowledge of users and reduce the number of incidents\nPerform all daily tasks according to set procedures, rules and guidelines to secure the availability of business application\nEngage with Risk Management for IT security policy to manage and secure the business information in the store. Also, engage with line manager\n\nTOGETHER AS A TEAM\n\nThe Technical Specialist will report to Technical Leader in the market. The key responsibility of this function is to offer excellent professional infrastructure knowledge and engage with practical business operation to fulfill end users requirements. Also, to act as the communication bridge between users and infrastructure service provider to ensure the agreed infrastructure requirement be converted to infrastructure solution for store, services office and warehouse\n\nSTAFF BENEFITS\n\nAnnual Fixed Bonus, 5-Day Work Week, 17 days Public Holiday, Paid Leave (Paid Annual Leave, 14 weeks Maternity Leave, 5 days Paternity Leave, 1 week Marriage Leave), Employee Medical Coverage, Non-Contributory Retirement Plan, Staff Purchase Discount, Birthday Coupon, Referral Bonus, Excellent Career Path\n\nPersonal data collected will be kept and handled confidentially by authorized personnel for recruitment purposes only. It might also be disclosed to our subsidiaries, associates and agencies authorized to process the information for appointment. The Company will retain the applications of candidates not selected for a maximum period of 24 months after the selection process is finalized. Our Personal Information Collection Statement (PICS) is available at our career site and can be provided upon request by contacting our Human Resources Department. Applicants not heard from us within six weeks may consider their applications filed for future reference.\n\nIssued by The Dairy Farm Company, Limited\n", "employment_types": ["Full Time", "Permanent"], "selling_points": ["First tier support service of IT infrastructure", "Monitor daily infrastructure or applications", "Participate in IT infrastructure projects"], "locations": ["Shatin Area"], "categories": ["Information Technology (IT)", "Support", "IT Management", "Others"], "post_time": "2022-01-17T11:08:03Z", "salary": {"currency": null, "max": null, "min": null, "period": "monthly", "term": null}, "salary_visible": false, "title_keywords": ["technical specialist"], "responsibilities": ["business operation", "management", "operational support", "it infrastructure", "guidelines", "infrastructure", "monitor", "procedures", "communication", "it security management", "customer service", "maintain", "database", "documentation", "report", "administration"], "requirements": {"degrees": [], "majors": [], "languages": ["english"], "language_level": ["good command"], "hard_skills": ["plus", "documentation", "basic", "security management", "fun", "focal", "basic it knowledge", "server"], "soft_skills": ["efficient", "proactive", "customer service oriented", "passion for", "responsible", "robust", "positive attitude", "diverse", "communication", "communication and interpersonal skills", "inspiring", "honest", "creative"], "languages_combined": [{"language": "english", "language_level": ["good command"]}]}, "experience_required": {"duration": ["2 years"], "field": ["related", "it", "retail industry"]}}, {"job_id": "100003009053210", "location_code": "hk", "company": "The Hong Kong Federation of Youth Groups", "job_title": "Head of Information Technology\uff08\u8cc7\u8a0a\u79d1\u6280\u7e3d\u76e3\uff09", "description": "A multinational law firm is now looking for an experienced Tier 1 & 2 IT support officer to join their information technology team. Selected Candidate will be responsible for providing helpdesk support to internal users and engaging in their regional IT projects.\n\nClient Details\n\nFounded in the United States, our client is one of the largest international law firms with their presence in more than 30 countries. To cope with their business needs, they are currently seeking an IT Support Analyst who will be responsible for providing IT support to internal users in the Hong Kong office.\n\nDescription\n\nProvide helpdesk support for users, such as O365 and windows\nIdentify and resolve user issues relating to applications, mobile devices, systems, & network\nSupport legal document management software (DMS)\nProvide Support for video conference, webinar events and remote conference tools\nPerform other duties and ad hoc projects as required\n\nProfile\n\nDegree holder in Computer Science and Information Systems or equivalent\nMinimum 2 years' hand-on experience providing helpdesk support\nKnowledge of the ITIL environment would be a great advantage\nExcellent verbal and written communication skills including English, Cantonese and Mandarin\nWide range of IT Knowledge on Windows, IOS, Android and Office suite\n\nJob Offer\n\nPermanent role\nAttractive performance bonus\nAnnual leave\nGreat career exposure\nMedical coverage\n\nTo apply online please click the 'Apply' button below. For a confidential discussion about this role please contact Ray Chanon +852 3602 2432.", "employment_types": ["Full Time", "Contract"], "selling_points": [], "locations": ["Quarry Bay"], "categories": ["Information Technology (IT)", "IT Project Management / Team Lead", "IT Management", "Others"], "post_time": "2022-01-17T07:22:51Z", "salary": {"currency": null, "max": null, "min": null, "period": "monthly", "term": null}, "salary_visible": false, "title_keywords": [], "responsibilities": ["provide support", "management", "perform other duties", "software", "systems", "communication", "ad hoc projects", "contact", "mobile devices"], "requirements": {"degrees": ["degree holder"], "majors": ["computer science"], "languages": ["cantonese", "english", "mandarin"], "language_level": ["excellent"], "hard_skills": ["itil", "o365", "it knowledge", "mobile", "android"], "soft_skills": ["communication skills", "responsible"], "languages_combined": [{"language": "cantonese", "language_level": ["excellent"]}, {"language": "english", "language_level": ["excellent"]}, {"language": "mandarin", "language_level": ["excellent"]}]}, "experience_required": {"duration": ["minimum 2 years"], "field": []}}, {"job_id": "100003009053567", "location_code": "hk", "company": "IT Consulting Solutions Limited", "job_title": "System/Network Engineer - Japan's Leading Financial Institution", "description": "Responsibilities:\n\nResponsible for all-round office administrative and clerical support;\nCommunicate\u00a0with\u00a0teammates and vendors and follow up procurement status in daily operations;\nMaintain stock and procurement of office supplies;\nAssist in ad-hoc duties assigned by supervisor\n\nRequirements:\n\nDiploma or above;\nExperience in IT industry is an advantage;\nA good team player, energetic and enthusiastic;\nWell-organised and detailed minded;\nProficient with MS Office applications;\nGood command in English and Cantonese;\nFresh graduates are welcome\nYou have a career opportunity in gaining knowledge and experience in serving one of the largest Data Center providers for local and international enterprises.\n\n\nAn attractive remuneration package and fringe benefits will be offered to the right candidate. Interested parties, we appreciate it if you\u00a0must send your resume stating with current and expected salary\u00a0to the Human Resources Department\u00a0by\u00a0clicking\u00a0Apply Now.\n\nFor more information, please visit our website at\u00a0http://www.oneas1a.com\nAll information collected will be kept strictly confidential and for recruitment purpose only.", "employment_types": ["Contract"], "selling_points": ["System/network focused", "Leading Japanese financial institution", "Work Location: Central"], "locations": ["Central"], "categories": ["Information Technology (IT)", "Support", "Network & System", "Others"], "post_time": "2022-01-17T07:10:07Z", "salary": {"currency": null, "max": null, "min": null, "period": "monthly", "term": null}, "salary_visible": false, "title_keywords": ["engineer"], "responsibilities": ["communicate with", "office supplies", "daily operations", "maintain", "administrative and clerical support", "ad-hoc duties"], "requirements": {"degrees": ["diploma or above"], "majors": [], "languages": ["cantonese", "english"], "language_level": ["good command"], "hard_skills": ["ms office"], "soft_skills": ["good team player", "enthusiastic", "well-organised", "energetic", "detailed"], "languages_combined": [{"language": "cantonese", "language_level": ["good command"]}, {"language": "english", "language_level": ["good command"]}]}, "experience_required": {"duration": [], "field": ["it"]}}, {"job_id": "100003009054828", "location_code": "hk", "company": "Ignite Recruitment Hong Kong Limited", "job_title": "IT Infrastructure & Support Specialist - Corporate & Investment Bank", "description": "Job Duties and Responsibilities:\nSet the technology vision and roadmap for innovation for the organization\nHead up a team and take the lead in driving IT changes to bring about digital transformation to the workplace and services\nCultivate business relationships with various parties, including but not limited to, vendors, funders, business partners; as well as staff\nDevise and implement innovative IT approaches to support the organization\u2019s strategic plans with its focus on digitalization transformation\nManage and execute major system change projects as part of the organization\u2019s digital transformation journey\nStay abreast of trends and advances in IT solutions, monitor changes in the market and apply them to the operations and services to drive change management in the organization\nEntry Requirements:\nStudy Fields\uff1a\nBachelor Degree, or above, in Computer Science, Information System Management or equivalent\nKnowledge, Skills and Abilities:\n15 years, or more, in the IT field with at least recent 8 years as IT Leader / Manager / Head in sizeable organizations\nExtensive IT work experience in managing and leading IT changes and digital transformation programmes\nPersonal Attributes:\nProven ability in leading project execution\nProven leadership, with problem solving, as well as, interpersonal and communication skills\nResourceful, with strong professional network in both private and public sectors, with abilities to build partnerships with key stakeholders\nAdditional Requirements:\nProfessionals who can provide service in flextime may be considered for the role of consultant.\nTo apply, please submit an online application at HKFYG Recruitment Portal https://erecruit.hkfyg.org.hk/ OR complete the application form (downloaded from erecruit.hkfyg.org.hk/ApplicationForm.doc) and email by clicking \"Apply now\" .\u00a0 Candidates may be required to undergo Sexual Conviction Record Check (SCRC) if job duties involve frequent contact with children.\u00a0 Only shortlisted candidates will be notified to attend a written test. hkfyg.org.hk. \u00a0", "employment_types": ["Full Time", "Permanent"], "selling_points": ["Stable Permanent Position", "Excellent Work-Life Balance", "Strong Financial Performance with Attractive Bonus"], "locations": ["Central & Western Area"], "categories": ["Information Technology (IT)", "Support", "Network & System", "Others"], "post_time": "2022-01-17T11:45:44Z", "salary": {"currency": "HKD", "max": 29999, "min": 20000, "period": "monthly", "term": null}, "salary_visible": true, "title_keywords": ["specialist"], "responsibilities": ["operations", "monitor", "strategic plans", "change management"], "requirements": {"degrees": ["degree", "bachelor"], "majors": ["computer science"], "languages": [], "language_level": [], "hard_skills": ["problem solving", "information system"], "soft_skills": ["communication skills", "resourceful", "problem solving", "leadership", "extensive", "interpersonal"], "languages_combined": []}, "experience_required": {"duration": [], "field": ["digital", "it"]}}, {"job_id": "100003009052321", "location_code": "hk", "company": "Hong Kong Aircraft Engineering Co Ltd", "job_title": "Assistant IT Manager, Infrastructure", "description": "At least 2-3 years of hands on experience in system/network setup and support/administration\nHands on experience in IT network environment\nTechnical knowledge in TCP/IP, HTTPS, LAN/WAN and other related areas\nHands on experience in Cisco enterprise grade products\nPerform first level troubleshooting, understand the escalated technical issues, identify the root cause and escalate to 2nd line support team\nProvide daily operational BAU support and system administration according to the company standard\nPerform computer installations and hardware/software configurations on desktop, laptop, and mobile devices, and day-to-day support covering end-user desktop & business applications\nPerform systems and network monitoring and routine hardware/software maintenance and other system administration tasks\nManage IT Inventory and support IT procurement and maintain proper records\nProvide VIP video conference setup and standby support\nProvide desktop/end-user training to users as required\nAssist other IT projects and provide non-office hour support as needed\n\nRequirements:\n\n\nDegree holder in information technology, computer science or other related disciplines\nWith at least 2-3 years of experience working in related positions\nIn depth experience in setting up and managing server platform and network appliances\nExperience in storage devices is preferred\nGood knowledge in Server, VMware, PC, and LAN / WAN and networking equipment\nGood understanding in Windows OS, Office 365, Microsoft Applications, Active Directory, Exchange, Skype for Business, Mobile Device Management Support, Patching software, MS Teams, etc.\nBe able to work independently with good team spirit\nQuick in response and reaction time\nPossess excellent communication skills in English and Chinese, Putonghua is an advantage", "employment_types": ["Full Time", "Permanent"], "selling_points": ["IT infrastructure development and support", "Degree holder in IT, Computing, Engineering", "8 years IT experience,5 years of IT Infrastructure"], "locations": ["Airport Area"], "categories": ["Information Technology (IT)", "IT Project Management / Team Lead", "IT Management", "Others"], "post_time": "2022-01-17T02:45:26Z", "salary": {"currency": null, "max": null, "min": null, "period": "monthly", "term": null}, "salary_visible": false, "title_keywords": ["it manager", "assistant"], "responsibilities": ["management", "software", "maintenance", "active directory", "systems", "monitoring", "troubleshooting", "teams", "communication", "hardware", "mobile devices", "maintain proper records", "it procurement", "it inventory", "setup", "administration"], "requirements": {"degrees": ["degree holder"], "majors": ["related disciplines", "computer science", "information technology"], "languages": ["putonghua", "english", "chinese"], "language_level": ["advantage", "excellent"], "hard_skills": ["office 365", "vmware", "maintenance", "tcp", "microsoft applications", "active directory", "ip", "mobile", "hardware", "os", "mobile device", "server", "pc", "wan", "exchange"], "soft_skills": ["communication skills", "work independently", "team spirit", "troubleshooting", "hands on", "active"], "languages_combined": [{"language": "putonghua", "language_level": ["advantage", "excellent"]}, {"language": "english", "language_level": ["excellent"]}, {"language": "chinese", "language_level": ["excellent"]}]}, "experience_required": {"duration": ["at least 2-3 years"], "field": ["related", "it", "administration"]}}, {"job_id": "100003009049416", "location_code": "hk", "company": "Shanghai Commercial Bank Ltd", "job_title": "System Administrator (MS Windows, Desktop & Operation Supports)", "description": "The Job\n\nResponsible for assisting the Product Owner to facilitate the digital product development and delivery, ensuring the digital assets across web and mobile app deliver a compelling and engaging user experience that meet the business objectives.\nResponsible for translating the digital journeys of the loyalty program into functional and non-functional requirement, developing test cases and performing UAT to ensure the product is fulfilling defined business goal and quality.\nAssists the Product Owner in gathering business requirements, developing user stories, defining acceptance criteria and managing the product backlog\nResponsible for documenting functional design of the digital platforms e.g. website and mobile apps\nCommunicates the business goal and acceptance criteria effectively with the scrum team or outsource partners to ensure the team has a comprehensive understanding of what to deliver in terms of functionality and quality\nHelps the Product Owner to inspect and evaluate the development and testing progress within sprint, and keep track the defect status\nDevelops \u201cDay-in-the-life\u201d test scripts for each of the user journeys\nConducts UAT to ensure the sprint deliverables are fulfilling defined acceptance criteria and well-functioned\nSupports the Product Owner on app usage analysis to identify UX improvements and business opportunities\nSupports the Product Owner on product release planning\n\nThe Person\n\nMinimum 3 years\u2019 experience as a Business Analyst with relevant industry experience\nDeep knowledge of Agile process and principles\nGood knowledge and experience of consumer facing digital solutions including websites and mobile apps\nStrong analytics and problem-solving skills\nStrong communication skills\nGood attention to detail with excellent organisational and time management skills", "employment_types": ["Full Time", "Permanent"], "selling_points": ["Windows end-point services", "Support IT Data Center Operations", "Windows based system, Linux/Unix shell script"], "locations": ["Kwai Hing"], "categories": ["Banking / Finance", "Others", "Information Technology (IT)", "Network & System", "Others"], "post_time": "2022-01-15T03:50:25Z", "salary": {"currency": null, "max": null, "min": null, "period": "monthly", "term": null}, "salary_visible": false, "title_keywords": ["system administrator"], "responsibilities": ["mobile app", "uat", "analysis", "business opportunities", "quality", "user experience", "developing", "design", "website", "evaluate", "testing", "planning"], "requirements": {"degrees": [], "majors": [], "languages": [], "language_level": [], "hard_skills": ["problem-solving skills", "mobile", "agile"], "soft_skills": ["communication skills", "agile", "time management skills", "deep", "attention to detail", "problem-solving skills"], "languages_combined": []}, "experience_required": {"duration": ["minimum 3 years"], "field": ["digital", "business"]}}, {"job_id": "100003009052149", "location_code": "hk", "company": "BDO", "job_title": "Group Assistant (Full time / Part time) - Assurance (Ref : AUD / JDB)", "description": "Our client is an expanding and well-established regional bank in Hong Kong. They are currently looking for an\u00a0IT Technical Support Specialist to solve & handle various IT issues to strengthen their operation capability in Hong Kong.\n\nResponsibilities\n\n\nTo solve IT problems and prepare for service upgrades related to HK government requirements\nTo help staffs to deal with issues in hardware and software\nTo manage server room, network facilities and IT assets\nTo manage administrative works related to IT in accordance with local and HQ guidelines\nTo cooperate with local maintenance services providers to meet HQ IT department\u2019s request\n\nRequirements\n\n\nPost secondary or above\n2 years + IT technical support experience\nWorking experience with sizable company is preferred\nFluency in written & spoken English would be an advantage\nCertificate holders related to IT services would be highly preferable\n\nTo apply online please click the 'Apply' button below. For a confidential discussion about this role & other openings please contact Alex CHEUNG at +852 2121 1418 .", "employment_types": ["Full Time", "Part Time", "Temporary", "Contract"], "selling_points": ["Assist in data processing and transformation", "Provide clerical support", "Full time / Part time"], "locations": ["Sheung Wan"], "categories": ["Accounting", "Others", "Admin & HR", "Clerical / Admin Staff", "Information Technology (IT)", "Others"], "post_time": "2022-01-17T02:16:29Z", "salary": {"currency": null, "max": null, "min": null, "period": "monthly", "term": null}, "salary_visible": false, "title_keywords": ["assistant"], "responsibilities": ["software", "upgrades", "guidelines", "hardware", "maintenance services", "cooperate with"], "requirements": {"degrees": ["certificate"], "majors": ["it"], "languages": ["english"], "language_level": ["fluency", "advantage"], "hard_skills": [], "soft_skills": [], "languages_combined": [{"language": "english", "language_level": ["fluency", "advantage"]}]}, "experience_required": {"duration": ["2 years +"], "field": ["it technical support"]}}, {"job_id": "100003009051870", "location_code": "hk", "company": "LAWSGROUP", "job_title": "Assistant IT Manager", "description": "Job Description:\nPrepare & review system documentation(s) on the developed systems and provide application support\nDesign & analyze user, business requirements on garment industry related system enhancement\nPerform system integration testing & support UAT to meet the users\u2019 requirement\nQuality assure deliverables are in good quality\nPerform ad hoc project as assigned by immediate supervisor\nJob Requirements:\nDegree or above in Computer Science, Information Technology, Management Information Systems or related discipline\nMinimum 5 years relevant experience in system development (with manufacturing industry background is an advantage)\nSolid experience in MySQL / Informix / Oracle and proficiency in SQL\nFamiliar with Angular front-end language and framework\nKnowledge in RPA / Qlikview is an advantage\nGood command in both spoken and written English and Chinese\nGood interpersonal communication and presentation skills\nExcellent problem solving, independently, able to work under pressure\nGood team player with self-initiative, open-minded and willing to learn\nWe\u00a0offer\u00a0attractive remuneration package to the right candidate. Interested parties please click the \"APPLY NOW\" button below and send your application together with a detailed resume including current & expected salary and availability to Human Resources Department.\nCompany website:\u00a0https://www.lawsgroup.com\n(Data collected will be treated in strict confidence and used for recruitment purpose only)", "employment_types": ["Full Time", "Permanent"], "selling_points": ["Minimum 5 years exprience in system support", "Degree or above in Computer Science", "Provide application support & troubleshooting"], "locations": ["Lai Chi Kok"], "categories": ["Information Technology (IT)", "IT Project Management / Team Lead", "Product Management / Business Analyst", "Others"], "post_time": "2022-01-17T01:25:48Z", "salary": {"currency": null, "max": null, "min": null, "period": "monthly", "term": null}, "salary_visible": false, "title_keywords": ["it manager", "assistant"], "responsibilities": ["ad hoc", "uat", "review", "systems", "quality", "design", "testing"], "requirements": {"degrees": ["degree or above"], "majors": ["computer science", "information technology"], "languages": ["english", "chinese"], "language_level": ["good command"], "hard_skills": ["qlikview", "informix", "sql", "rpa", "problem solving", "angular", "oracle"], "soft_skills": ["good team player", "independently", "open-minded", "willing to learn", "communication", "problem solving", "presentation skills", "self-initiative", "interpersonal", "work under pressure"], "languages_combined": [{"language": "english", "language_level": ["good command"]}, {"language": "chinese", "language_level": ["good command"]}]}, "experience_required": {"duration": ["minimum 5 years"], "field": ["sql", "relevant experience", "manufacturing industry", "system development"]}}, {"job_id": "100003009047988", "location_code": "hk", "company": "TSL Management Services Limited", "job_title": "Administration Associate (IT Department)", "description": "Position Overview\n\nThe Service Desk Analyst role at Marsh & McLennan affects colleagues of all levels, in all of our companies, in every region of the world.\n\nBeing the first point of contact on any technology-related process, application or device, you will be providing first-level technical phone support by diagnosing, reporting and resolving or correcting hardware and software problems.\n\nYou will manage all aspects of the installing, maintaining and troubleshooting hardware and software according to company standards \u2013 reconfiguring existing systems or performing system upgrades as required.\n\nThis will require monitoring and escalating issues until resolution, closure or handoff to a specialized support team.\n\nKey Responsibilities\n\n\nProvides Service Desk support by chat, phone and email, assisting users in diagnosing, reporting and resolving or correcting hardware and software problems.\nInstalls, maintains and troubleshoots hardware and software according to company standards \u2013 reconfigures existing systems and/or performs system upgrades as required.\nLogs all issues with appropriate documentation as requested.\nRoute calls to appropriate support teams as per described troubleshooting steps.\nMonitor and escalate issues until resolution, closure or the appropriate group has accepted.\nMaintain current knowledge of support knowledge provided through training and the Knowledge Base.\nExpected to resolve 75%+ of incoming incidents and attain 95%+ positive Customer Satisfaction feedback score, expected to handle a minimum of 40 incidents per day.\n\n\nSkills and Experience\n\n\nThis position will require the successful individual to provide technical support to our global colleague base, the shift pattern will be between Monday \u2013 Friday cover Bank Holidays. (Shift HK Time: 6:30am-3:30pm / 7:30am-4:30pm).\nBachelor\u2019s degree in computer science or equivalent is desired.\nMinimum 2-3 years\u2019 experience of working within a similar capacity for a Service Desk / Helpdesk/ Call Centre.\nTechnical Troubleshooting experience is a must.\nFamiliar with a variety of IT Service Desk concepts, practices, procedures and policies.\nMust have excellent verbal and written communication skills.\nEssential languages required: English, Cantonese. Also desired: Mandarin, Japanese, Korean.\nWe are an Equal Opportunity Employer. Visit us at\u00a0\u00a0www.marsh.com/hk\n\nAll information received will be kept in strict confidence and be used only for employment-related purposes.\n\n", "employment_types": ["Full Time", "Permanent"], "selling_points": ["Keep and maintain the IT Asset inventory", "Diploma holder or equivalent qualification", "2 years\u2019 experience in administrative role"], "locations": ["Hung Hom"], "categories": ["Admin & HR", "Clerical / Admin Staff", "Others", "Information Technology (IT)", "Others"], "post_time": "2022-01-14T04:25:36Z", "salary": {"currency": null, "max": null, "min": null, "period": null, "term": null}, "salary_visible": false, "title_keywords": ["associate"], "responsibilities": ["it service", "software", "troubleshooting", "communication", "maintain", "maintaining", "teams", "monitor", "resolution", "reporting", "upgrades", "monitoring", "procedures", "installing", "contact", "documentation", "technical support", "policies", "systems", "hardware"], "requirements": {"degrees": ["degree", "bachelor"], "majors": ["computer science"], "languages": ["cantonese", "english", "mandarin", "japanese", "korean"], "language_level": [], "hard_skills": ["documentation", "hardware", "system upgrades"], "soft_skills": ["communication skills", "confidence", "troubleshooting", "positive"], "languages_combined": [{"language": "cantonese", "language_level": []}, {"language": "english", "language_level": []}, {"language": "mandarin", "language_level": []}, {"language": "japanese", "language_level": []}, {"language": "korean", "language_level": []}]}, "experience_required": {"duration": ["minimum 2-3 years"], "field": ["troubleshooting"]}}, {"job_id": "100003009052776", "location_code": "hk", "company": "Hong Kong Sports Institute Ltd", "job_title": "INFORMATION TECHNOLOGY MANAGER", "description": "RESPONSIBILITIES\n\n- Handle enquiry via Helpdesk Hotline, in person or email and provide technical support to both\nour internal users and agency.\n- Provide 1st level supports on hardware & software troubleshooting\n- Provide PC installation and software deployment\n- Log all incident and request cases on the call logging system and follow up its status\n- Escalate incidents and problems to relevant second-level support team or external service providers\n- Relocation for desktop items and maintains the correct inventory record\n- Handle ad hoc IT support duties as assigned\n- Standby support during non-working hours when required\n\nREQUIREMENTS\n\n- Higher Diploma in Information Technology or related disciplines\n- 3+ years of IT support experience in Banking/Finance\n- Good communication skill in English & Chinese\n\nInterested parties, please click \"APPLY NOW\" or send your application to karis.chan@ambition.com.hk\n\nIf this job isn't quite right for you, but you know someone who would be great at this role, why not take advantage of our referral scheme? We offer HKD1000 in Apple gift cards for every referred candidate who we place in a role. Terms & Conditions Apply. https://www.ambition.com.hk/refer-a-friend", "employment_types": ["Full Time"], "selling_points": [], "locations": ["Shatin Area"], "categories": ["Information Technology (IT)", "IT Project Management / Team Lead", "IT Management", "Others"], "post_time": "2022-01-17T04:01:47Z", "salary": {"currency": null, "max": null, "min": null, "period": "monthly", "term": null}, "salary_visible": false, "title_keywords": ["technology manager"], "responsibilities": ["installation", "ad hoc", "software", "technical support", "handle enquiry", "troubleshooting", "inventory record", "hardware", "escalate incidents"], "requirements": {"degrees": ["diploma"], "majors": ["related disciplines", "information technology"], "languages": ["english", "chinese"], "language_level": ["good"], "hard_skills": [], "soft_skills": ["communication skill"], "languages_combined": [{"language": "english", "language_level": ["good"]}, {"language": "chinese", "language_level": ["good"]}]}, "experience_required": {"duration": ["3+ years"], "field": ["finance", "banking", "it support"]}}, {"job_id": "100003009054247", "location_code": "hk", "company": "CHOW TAI FOOK JEWELLERY CO LTD", "job_title": "Assistant Manager (IT Project Management Office PMO)", "description": "Job Responsibilities:\nFormulate solutions and service scope based on understanding of potential merchant (Service Provider) / System Integrator requirements\nFollow up complaints for merchants and performance management\nProvide review of Service Provider / System Integrator submissions and coordinate Type Approval Test\nAddress technical or operational issues within Service Provider\u2019s application\nCoordinate with different departments to respond to merchants\u2019 needs such as operational needs and system integration needs\nPrepare documents for Service Provider training including Operating Rules and training\u00a0 materials\nMonitor Service Provider accounts operation performance data and provide enhancement proposal to improvement system efficiency and productivity\nHandle merchant complaints and liaise internally to resolve the merchant complaints within the service level\nPrepare reports including incident report\nProvide support and service to internal partners and external merchants in non-office hours\nRequirements:\nBachelor degree holders in Information, Computer Engineering or related disciplines\nMinimum 7 years working experience in IT field and merchant serving field, of which includes at least 2 years working experience in managerial level\nProficient in spoken and written English and Chinese\nA fast learner with strong analytical skills\nGood communication, people management and project management skills\nGood knowledge in payment system for transportation, retail and self-service industries\nSelf-motivated, eager to learn and committed to self-development\nWe offer successful candidate an attractive remuneration package and excellent career prospects. Interested parties please send your resume, present and expected salary, contact details and quoting the reference number by clicking \"Apply Now\"\nVisit our web site: http://www.octopus.com.hk/\nThe personal data collected will be used for recruitment purposes only. If you are not contacted by us within six weeks, you may consider your application unsuccessful. Personal data with an unsuccessful applicant will be destroyed 12 months after rejection of the application. During this retention period, you have the right to request for correction or destruction of your personal data at any time. Any request for the correction or destruction of personal data should be addressed in writing to our Human Resources & Administration Department.\nWe are an equal opportunity employer and will ensure that every job applicant and staff has equal employment opportunities and will not be disadvantaged because of their sex, pregnancy, marital status, family status, disability or race.", "employment_types": ["Full Time", "Permanent"], "selling_points": ["IT Governance, Project Management, IT Compliance", "ServiceNow", "ScrumMaster, ITIL, PMP"], "locations": ["Kwai Hing"], "categories": ["Information Technology (IT)", "IT Auditing", "IT Project Management / Team Lead", "Others"], "post_time": "2022-01-17T08:56:58Z", "salary": {"currency": null, "max": null, "min": null, "period": "monthly", "term": null}, "salary_visible": false, "title_keywords": ["assistant manager"], "responsibilities": ["liaise", "management", "provide support", "data", "review", "coordinate with", "monitor", "coordinate", "prepare reports", "prepare documents", "report"], "requirements": {"degrees": ["degree", "bachelor"], "majors": ["related disciplines", "computer engineering"], "languages": ["english", "chinese"], "language_level": ["proficient"], "hard_skills": ["project management", "analytical skills"], "soft_skills": ["self-motivated", "project management skills", "analytical skills", "communication", "eager to learn", "committed", "fast learner"], "languages_combined": [{"language": "english", "language_level": ["proficient"]}, {"language": "chinese", "language_level": ["proficient"]}]}, "experience_required": {"duration": ["at least 2 years", "minimum 7 years"], "field": ["managerial", "it"]}}, {"job_id": "100003009052388", "location_code": "hk", "company": "Standard Chartered Bank (Hong Kong) Ltd", "job_title": "Frontend Engineer - Mox - (2200001037)", "description": "Reporting to the Senior Manager \u2013 Group Information Technology, the incumbent will be responsible for providing general clerical and administrative support to the Group IT Department.\n\nResponsibilities:\n\n\u2022 Keep and maintain the IT Asset inventory, such as computer parts, equipment, manuals and software license etc.;\n\u2022 Assist in procurement matters on IT equipment, including but not limited to prepare purchase order and cost comparison, follow up with vendors/suppliers on product information and quotations;\n\u2022 Provide finance and administrative support, such as payment requisition and expense handling, report preparation, meeting coordination/scheduling and business trip arrangement;\n\u2022 Provide general administrative support to the IT team;\n\u2022 Perform other ad hoc duties as assigned by superior;\n\nRequirements:\n\n\u2022 Diploma holder or equivalent qualification\n\u2022 2 years\u2019 experience in administrative role. Experienced in IT industry is an advantage\n\u2022 A team player with passion and good manner\n\u2022 Proactive, efficient and detail minded\n\u2022 Proficiency in MS Office, especially in MS Word, Excel & PowerPoint\n\u2022 Knowledge in Networking is preferable but not a must\n\u2022 Good communication and interpersonal skills\n\nCandidate with more experience would be considered as Assistant Officer.\n\nInterested parties please send your application with full resume, present and expected salary by clicking \"Apply Now\". (All information collected would be used for recruitment purposes only.)\n\n", "employment_types": ["Full Time"], "selling_points": ["Experience building and maintaining", "Deep understanding of ReactJS", "Exposure to native languages like Kotlin or Swift"], "locations": ["Not Specified"], "categories": ["Information Technology (IT)", "Application Specialist - Software", "Software Development", "Others"], "post_time": "2022-01-17T02:55:33Z", "salary": {"currency": null, "max": null, "min": null, "period": "monthly", "term": null}, "salary_visible": false, "title_keywords": ["engineer"], "responsibilities": ["ad hoc duties", "cost", "software", "administrative support", "general administrative support", "scheduling", "purchase", "asset inventory", "maintain", "payment", "coordination", "business trip", "it equipment", "report"], "requirements": {"degrees": ["diploma holder"], "majors": [], "languages": [], "language_level": [], "hard_skills": ["ms word", "excel", "powerpoint", "ms office"], "soft_skills": ["efficient", "team player", "proactive", "communication and interpersonal skills"], "languages_combined": []}, "experience_required": {"duration": ["2 years"], "field": ["administrative"]}}, {"job_id": "100003009048441", "location_code": "hk", "company": "Fortune Pharmacal Company Limited", "job_title": "IT Officer (Fresh graduate welcome)", "description": "Our client is a unique bilingual education in Hong Kong with an independent school offering a Chinese and English immersion education with a global perspective.\n\nResponsibilities\n\nServe as the first-line support to staff members, students and parents of the Academy\nProvide support to software, network, e-mail, office applications and educational software issues\nPerform administrative duties such as maintaining hardware and software inventory, setting up of event schedule calendar and keeping track of loaned equipment and laptops etc.\nAssist IT related daily activities\n\nExperience\n\nGood understanding on the use of computer systems, mobile devices and other technical products\nExcellent telephone manner and communication skills\nAbility to diagnose and resolve basic technical issues\nAbility to work independently\nBe a good team player\n\nEducation\n\nRelevant education background in either Information System, Information Technology or Computer Science disciplines\nGood command of both spoken and written English and Cantonese (including Mandarin)\n\n\n\nInterested parties, please\u00a0CLICK HERE\u00a0to apply online. (Ref:JDB/IT-TT)\n\nPlease note that only short-listed candidates will be notified. All information gathered will be treated in strict confidence and solely used for recruitment purposes", "employment_types": ["Full Time", "Permanent"], "selling_points": ["Provide frontline user support and troubleshooting", "Handle IT hardware and software upgrade", "1 year IT support exp., fresh graduate welcome"], "locations": ["Yuen Long"], "categories": ["Information Technology (IT)", "Support", "Network & System", "Others"], "post_time": "2022-01-14T06:35:07Z", "salary": {"currency": null, "max": null, "min": null, "period": "monthly", "term": null}, "salary_visible": false, "title_keywords": ["it officer"], "responsibilities": ["provide support", "software issues", "software", "maintaining", "inventory", "diagnose", "computer systems", "communication", "hardware", "administrative duties", "schedule", "mobile devices"], "requirements": {"degrees": [], "majors": [], "languages": ["cantonese", "english", "chinese", "mandarin"], "language_level": ["good command"], "hard_skills": ["basic", "computer systems", "office applications", "information system", "hardware", "mobile"], "soft_skills": ["communication skills", "work independently", "good team player", "independent", "unique", "telephone manner"], "languages_combined": [{"language": "cantonese", "language_level": ["good command"]}, {"language": "english", "language_level": ["good command"]}, {"language": "chinese", "language_level": []}, {"language": "mandarin", "language_level": ["good command"]}]}, "experience_required": {"duration": [], "field": []}}, {"job_id": "100003009054806", "location_code": "hk", "company": "The Education University of Hong Kong", "job_title": "Assistant Computer Officer / Programmer I (Ref: 2200025)", "description": "What You Will Own\n\nConduct project performance analysis and reporting to IT senior management\nHarmonize IT teams to engage and deliver project initiatives within budget and timeline\nProvide both verbal and written communications regarding project status, benefit, risks and issues\nMonitor the impacts and interdependencies between demands and resources to ensure project delivery efficiency\nCommunicate with business leaders to manage multiple demands, identify and resolve conflicting issues\nDevelop and introduce best practice project delivery approach\nDrive process improvements and project governance\nEnsure governance procedures are adhered for all projects throughout their project life cycle\nLead and assist with the deployment and use of IT Project Management tools, methodologies and standards within IT Division\nPerform other ad-hoc projects and tasks as assigned\nWho Will Thrive\nDegree holders with at least 5 to 8 years\u2019 work experience in PMO and IT governance\nProficient in SDLC project management execution and business analysis experience\nPrevious experience in setting up PMO is an advantage\nExperience on PM Tools (e.g. ServiceNow, JIRA) and Data Analytics tools (e.g. PowerBI, Qlik) is an advantage\nCustomer-oriented and self-motivated with excellent communication skill\nSelf-manage, proactive, independent, efficient, able to work under pressure in vague and fast growing environment\nCandidates with less experience will be considered as Officer (IT PMO)\nGood command of written and spoken English and Chinese as well as Putonghua\nHolder of PMP or ScrumMaster certification would be definitely an advantage\n\n\nBenefits\n\n5-day work\nCompetitive salary, staff meal, medical and dental insurance, life insurance\nVarious types of leave, e.g. Family-friendly leave, self-development leave,\u00a0Examination leave, marriage leave, birthday leave, volunteer service leave, etc\n\nWe offer excellent career opportunities, attractive remuneration package & benefits to the right candidate.\u00a0Interested parties please apply by clicking \"Apply Now\" with a full resume stating the latest and expected salary.\n\nAll information collected will be used for recruitment purposes only.", "employment_types": ["Full Time"], "selling_points": [], "locations": ["Not Specified"], "categories": ["Information Technology (IT)", "Support", "Software Development", "Others"], "post_time": "2022-01-17T11:12:12Z", "salary": {"currency": null, "max": null, "min": null, "period": "monthly", "term": null}, "salary_visible": false, "title_keywords": ["officer", "programmer", "assistant"], "responsibilities": ["communicate with", "reporting", "analytics tools", "ad-hoc projects", "data", "analysis", "budget", "teams", "monitor", "procedures", "develop", "communication", "project management", "business analysis", "senior management", "work under pressure"], "requirements": {"degrees": ["degree"], "majors": ["it"], "languages": ["putonghua", "english", "chinese"], "language_level": ["good command"], "hard_skills": ["data analytics", "analysis", "project management", "sdlc", "deployment", "pmp"], "soft_skills": ["efficient", "self-motivated", "independent", "communication skill", "project management", "customer-oriented", "proactive", "work under pressure"], "languages_combined": [{"language": "putonghua", "language_level": ["good command"]}, {"language": "english", "language_level": ["good command"]}, {"language": "chinese", "language_level": ["good command"]}]}, "experience_required": {"duration": ["at least 5 to 8 years"], "field": ["business analysis", "project management", "it governance", "it"]}}, {"job_id": "100003009055525", "location_code": "hk", "company": "Educational Publishing House, Limited", "job_title": "System Support Assistant (\u96fb\u8166\u6280\u8853\u54e1)", "description": "Responsibilities\n\nPerform troubleshooting and provide day-to-day support including hardware, software, end-user and helpdesk;\nPerform hardware installation, configuration or maintenance, including PC, notebook, Mac, server, printer and other computer peripheral devices;\nConduct software installation, configuration or maintenance including MS-Office, Outlook, Windows, Mac, Adobe products, AntiVirus and other office applications;\nProvide regular testing of IT equipment and monitoring of IT equipment status and ah hoc on site support;\n\nRequirements\n\nIVE/Diploma holder in Information System, Computer Science, Computer Engineering or related disciplines;\n1 year experience in IT technical / deskside support will be an advantage, fresh graduates are also welcomed;\nKnowledge in Windows;\nKnowledge in AD, DNS, FTP, TCP/IP, POP3, SMTP & SNMP;\nGood computer knowledge of MS-Word, Excel, PowerPoint;\nGood command of spoken and written English and Chinese\nImmediately available will be an advantage\n\nWe offer excellent career development opportunities to unleash your potential, competitive remuneration package including a 5-day work week, medical insurance & dental plan, discretionary bonus, staff training and staff purchasing discount etc.\n\n\nInterest parties, please simply click \"Apply now\" to submit your application with full resume stating current & expected salary and the availability for reporting duty.\u00a0\n\nYou are welcome to visit our website to know more about us:\u00a0www.popular.com.hk\u00a0or http://ephhk.popularworldhk.com.\n\n\nPersonal data provided by job applicants will be kept strictly confidential and will be used solely\u00a0for employment related purpose.\u00a0\u00a0Only short-listed candidates will be contacted.", "employment_types": ["Full Time", "Permanent"], "selling_points": ["5 days work, bonus, medical & dental", "Stable working environment", "IT hardware and software support"], "locations": ["Tsuen Wan Area"], "categories": ["Information Technology (IT)", "Hardware", "Support", "Others"], "post_time": "2022-01-18T02:40:47Z", "salary": {"currency": null, "max": null, "min": null, "period": "monthly", "term": null}, "salary_visible": false, "title_keywords": ["system support", "assistant"], "responsibilities": ["installation", "software", "maintenance", "configuration", "monitoring", "troubleshooting", "testing", "hardware", "it equipment"], "requirements": {"degrees": ["diploma holder"], "majors": ["related disciplines", "computer engineering", "computer science"], "languages": ["english", "chinese"], "language_level": ["good command"], "hard_skills": ["ms-word", "excel", "dns", "tcp", "information system", "powerpoint", "ip"], "soft_skills": [], "languages_combined": [{"language": "english", "language_level": ["good command"]}, {"language": "chinese", "language_level": ["good command"]}]}, "experience_required": {"duration": ["1 year"], "field": ["it"]}}, {"job_id": "100003009055176", "location_code": "hk", "company": "Win Hanverky Holdings Limited", "job_title": "IT Specialist", "description": "Responsibilities\n\n\nProvide technical support and troubleshooting to end users on hardware, software and computer services\u00a0\nPerform maintenance, configuration and monitoring of IT equipment\nPerform management of hardware and software inventory\nAssist in IT documentation, process improvement and equipment procurement\nAssist in project support and perform ad hoc duties as assigned\nRequirements:\n\n\nDegree in Information Technology, Computer Science or related disciplines\nCCNA/CCNP/MCSE certificate holder will be an advantage\n2 years experience in IT Support\nHands on experience in O365 (Teams/SharePoint Online), Win10, Active Directory, VMWare/Hyper-V\nKnowledge in TCP/IP, Wi-Fi, Firewall, network infrastructure and security technology\nA self-motivated and organized individual with good problem solving skills and strong sense of responsibility\nAbility to work independently, flexibly and positively\nGood command in both spoken and written English and Chinese (Cantonese and Mandarin)\u00a0\nApplicants with less experience will be considered as IT Officer.\u00a0 Fresh graduates is also welcomed\nInterested parties please send your resume with your\u00a0current and expected salary\u00a0to email:\u00a0hrd @ win-hanverky.com.hk\u00a0or click \"APPLY NOW\".\u00a0The closing date for application is 17 February 2022.\u00a0All information collected will be kept in strict confidence and will be used for recruitment purpose only.", "employment_types": ["Full Time", "Permanent"], "selling_points": [], "locations": ["Lai Chi Kok"], "categories": ["Information Technology (IT)", "Hardware", "Technical / Functional Consulting", "Others"], "post_time": "2022-01-18T01:38:51Z", "salary": {"currency": null, "max": null, "min": null, "period": "monthly", "term": null}, "salary_visible": false, "title_keywords": ["it specialist"], "responsibilities": ["ad hoc duties", "management", "software", "maintenance", "technical support", "configuration", "inventory", "computer services", "monitoring", "troubleshooting", "hardware", "documentation", "it equipment"], "requirements": {"degrees": ["certificate", "degree"], "majors": ["related disciplines", "computer science", "information technology"], "languages": ["cantonese", "english", "chinese", "mandarin"], "language_level": ["good command"], "hard_skills": ["mcse", "o365", "hyper-v", "vmware", "active directory", "tcp", "wi-fi", "ccnp", "ccna", "ip", "firewall", "problem solving skills"], "soft_skills": ["organized", "self-motivated", "work independently", "sense of responsibility", "hands on", "problem solving skills", "active"], "languages_combined": [{"language": "cantonese", "language_level": ["good command"]}, {"language": "english", "language_level": ["good command"]}, {"language": "chinese", "language_level": ["good command"]}, {"language": "mandarin", "language_level": ["good command"]}]}, "experience_required": {"duration": ["2 years"], "field": ["it", "it support"]}}, {"job_id": "100003009022237", "location_code": "hk", "company": "Resources Link Network Ltd", "job_title": "Human Resources Officer", "description": "Responsibilities\n\n1. Responsible for full cycle of talent recruitment process from candidates sourcing, shortlisting, conducting interview, offering to on-boarding process\n2. Explore and manage all potential sourcing channels of talent, e.g. LinkedIn, online job posting, social media, campus recruitment, employee referrals and other active searching channels\n3. Work closely with Compensation & Benefit (C&B) team to organize and implement HR initiatives and projects\n4. Deliver induction program to new joiners, support and deliver learning & development initiatives and monitor training administration\n5. Assist in identifying and assessing future and current training needs through job analysis, career paths, annual performance appraisals and consultation\n6. Support and assist in organizing staff activities and events and ad hoc projects as assigned\n\nRequirements\n\n1. Bachelor Degree in Business Administration, Human Resources Management or equivalent\n2. Minimum 4-8 year\u2019s related working experience, preferably in IT industry\n3. Fluent in spoken and written English, Cantonese and Putonghua\n4. Proficient in MS Word, Excel, PowerPoint & Chinese Word Processing\n5. Well-versed in Hong Kong Employment Ordinance, related statutory regulations and HR general practice.\n6. Good interpersonal & communication skills, competence to interact and build relationships at all levels of the company independently\u00a0 \u00a0 \u00a0\n7. Knowledge of hiring overseas and mainland staff would be advantage; such as contract T&C, Immigration, Visa application, etc.", "employment_types": ["Full Time"], "selling_points": ["Attractive Salary Package and Career Pathway", "Work-Life Balance, Five-day Work a Week", "World's Fortune 100 Group of Companies"], "locations": ["Wan Chai"], "categories": ["Admin & HR", "HR Director / Manager", "Information Technology (IT)", "Others"], "post_time": "2022-01-17T05:56:36Z", "salary": {"currency": null, "max": null, "min": null, "period": "monthly", "term": null}, "salary_visible": false, "title_keywords": ["human resources officer"], "responsibilities": ["social media", "hr", "analysis", "monitor", "recruitment", "ad hoc projects", "recruitment process", "administration"], "requirements": {"degrees": ["degree", "bachelor"], "majors": ["business administration"], "languages": ["cantonese", "putonghua", "english", "chinese"], "language_level": ["proficient", "fluent"], "hard_skills": ["excel", "chinese word processing", "hong kong employment ordinance", "powerpoint", "ms word"], "soft_skills": ["communication skills", "independently", "interpersonal"], "languages_combined": [{"language": "cantonese", "language_level": ["fluent"]}, {"language": "putonghua", "language_level": ["fluent"]}, {"language": "english", "language_level": ["fluent"]}, {"language": "chinese", "language_level": ["proficient"]}]}, "experience_required": {"duration": ["minimum 4-8 year"], "field": ["related", "it"]}}, {"job_id": "100003009056344", "location_code": "hk", "company": "Swing Consulting Limited", "job_title": "Network Engineer", "description": "Responsibilities:\n\nImplement network infrastructure installations and configurations\nParticipate in troubleshooting and support of network infrastructure and various client services\nDeliver technical documentation of infrastructure, control procedures, operation and review data network proposals\nDrive vendor for technology enhancement and manage the project delivery, product support and escalated issue management\n\nRequirements:\n\nHigher Diploma or above in Information Technology, Electrical Engineering or Computer Science\nAt least 3 year\u2019s experience in Network management such as: switches, routers, wi-fi, and load balancers.\nAt least 3 year\u2019s experience in one or more of the following: installing, troubleshooting, operating, testing, planning and configuring relevant technologies.\nAbility to perform advanced problem determination / resolution\nGood Command in written and communicate in English and Chinese\n\nPlease send your full resume with MS Word format to us\u00a0by email\u00a0or\u00a0fax: 3426 2763,\u00a0or you may click the\u00a0Apply Now\u00a0button below.\u00a0\n\nFor other vacancies, please visit our website www.swing-hk.com\n\nJoin us on facebook \u2013 www.facebook.com/swinghk\n\nAll information provided will be treated in strict confidence and used for recruitment purposes only.\u00a0", "employment_types": ["Full Time"], "selling_points": ["5 days work", "Exposure to sizeable company", "Attractive package and career progression"], "locations": ["Not Specified"], "categories": ["Information Technology (IT)", "Support", "Network & System", "Others"], "post_time": "2022-01-18T04:01:48Z", "salary": {"currency": null, "max": null, "min": null, "period": "monthly", "term": null}, "salary_visible": false, "title_keywords": ["engineer"], "responsibilities": ["network infrastructure", "control", "management", "data", "infrastructure", "procedures", "troubleshooting", "review", "documentation"], "requirements": {"degrees": ["higher diploma or above"], "majors": ["electrical engineering", "computer science", "information technology"], "languages": ["english", "chinese"], "language_level": ["good command"], "hard_skills": ["ms word", "network management", "facebook", "wi-fi"], "soft_skills": ["advanced", "confidence", "troubleshooting"], "languages_combined": [{"language": "english", "language_level": ["good command"]}, {"language": "chinese", "language_level": ["good command"]}]}, "experience_required": {"duration": ["at least 3 year"], "field": ["management", "planning", "troubleshooting", "testing"]}}, {"job_id": "100003009055098", "location_code": "hk", "company": "Autotoll Limited", "job_title": "Application Support", "description": "About us:\n\nAutotoll is not just a toll collector for roads and tunnels!\nWe have diversified into Smart City solutions including Finance, Big Data, Artificial Intelligence, Machine Learning, Internet of Things, and much more\nWe work on projects from traffic control to smart property management with an IT team approaching 100\nWhat we do is unique, creative and at the forefront of innovative technology\nWe are constantly searching for the bright, the passionate, and the committed to join our quest to shape the future of our home\n\nAbout The Role:\n\n\nContinuous delivery for application / system on staging and production environments, include regression testing / health check, assist in user acceptance test, deployment, application monitoring and performance review\nHandle technical support cases that transfer from first-line support\nHandle and troubleshoot application/system issues encountered by users and monitoring system\nSetup application and performance monitoring\nReport bugs and performance issue to development team\n\n\u00a0\nAbout You:\n\n\nHigher Diploma or above in Computing or related discipline\nExperiencing in programming / scripting in C# / JAVA, HTML 5, Linux Shell Script, SQL\nPython / YAML / PowerShell in advantage but not a must\nDevOps experience will be an advantage but not a must\nAt least 2 year's working experience in application support / development\nFresh graduates will also be considered\n\n\nWhat you can get from us\n\n\nWork happier - Flexible working hour and five-day work week for better work-life balance\nWork healthier - Dental insurance, life insurance, and medical insurance\nInvest in your future - On-the-job training, learning and certification to build your career\nCorporate benefits - Executive workshops, interest class, corporate purchase discount offered by SHKP\nValuing your contribution - Competitive salary and annual leaves, and performance bonus\nWe are not that far away - Free shuttle bus to/from MTR\n\nInterested parties, please send full resume with\u00a0expected salary\u00a0and\u00a0available date\u00a0to Human Resources and Administration Department by e-mail or by fax 2111 9459.\n\n(Data collected will be used for recruitment purpose only.)", "employment_types": ["Full Time", "Permanent"], "selling_points": ["2 years relevant IT programming experience", "Higher Diploma Computing Discipline", "Responsible for system maintenance and support"], "locations": ["Kowloon Bay"], "categories": ["Information Technology (IT)", "Support", "Network & System", "Others"], "post_time": "2022-01-18T01:15:11Z", "salary": {"currency": null, "max": null, "min": null, "period": "monthly", "term": null}, "salary_visible": false, "title_keywords": ["application support"], "responsibilities": ["control", "management", "technical support", "monitoring", "big data", "review", "testing", "troubleshoot", "insurance", "setup", "report"], "requirements": {"degrees": ["higher diploma or above"], "majors": [], "languages": [], "language_level": [], "hard_skills": ["linux", "java", "devops", "html", "sql", "deployment", "programming", "powershell", "python", "c#"], "soft_skills": ["passionate", "flexible", "unique", "innovative", "committed", "learning", "troubleshoot", "creative"], "languages_combined": []}, "experience_required": {"duration": ["at least 2 year"], "field": ["development", "devops"]}}, {"job_id": "100003009055872", "location_code": "hk", "company": "Page Personnel", "job_title": "IT Support Analyst - US Law Firm", "description": "A multinational law firm is now looking for an experienced Tier 1 & 2 IT support officer to join their information technology team. Selected Candidate will be responsible for providing helpdesk support to internal users and engaging in their regional IT projects.\n\nClient Details\n\nFounded in the United States, our client is one of the largest international law firms with their presence in more than 30 countries. To cope with their business needs, they are currently seeking an IT Support Analyst who will be responsible for providing IT support to internal users in the Hong Kong office.\n\nDescription\n\nProvide helpdesk support for users, such as O365 and windows\nIdentify and resolve user issues relating to applications, mobile devices, systems, & network\nSupport legal document management software (DMS)\nProvide Support for video conference, webinar events and remote conference tools\nPerform other duties and ad hoc projects as required\n\nProfile\n\nDegree holder in Computer Science and Information Systems or equivalent\nMinimum 2 years' hand-on experience providing helpdesk support\nKnowledge of the ITIL environment would be a great advantage\nExcellent verbal and written communication skills including English, Cantonese and Mandarin\nWide range of IT Knowledge on Windows, IOS, Android and Office suite\n\nJob Offer\n\nPermanent role\nAttractive performance bonus\nAnnual leave\nGreat career exposure\nMedical coverage\n\nTo apply online please click the 'Apply' button below. For a confidential discussion about this role please contact Ray Chanon +852 3602 2432.", "employment_types": ["Full Time", "Permanent"], "selling_points": ["Renowned law firm", "Strong track record of performance bonus", "Professional working environment"], "locations": ["Not Specified"], "categories": ["Information Technology (IT)", "Support", "Others"], "post_time": "2022-01-18T03:02:08Z", "salary": {"currency": null, "max": null, "min": null, "period": "monthly", "term": null}, "salary_visible": false, "title_keywords": ["analyst", "it support"], "responsibilities": ["provide support", "management", "perform other duties", "software", "systems", "communication", "ad hoc projects", "contact", "mobile devices"], "requirements": {"degrees": ["degree holder"], "majors": ["computer science"], "languages": ["cantonese", "english", "mandarin"], "language_level": ["excellent"], "hard_skills": ["itil", "o365", "it knowledge", "mobile", "android"], "soft_skills": ["communication skills", "responsible"], "languages_combined": [{"language": "cantonese", "language_level": ["excellent"]}, {"language": "english", "language_level": ["excellent"]}, {"language": "mandarin", "language_level": ["excellent"]}]}, "experience_required": {"duration": ["minimum 2 years"], "field": []}}, {"job_id": "100003009056203", "location_code": "hk", "company": "DFI Retail Group DFI\u96f6\u552e\u96c6\u5718", "job_title": "Analyst, Operations - yuu Rewards", "description": "The Job\n\nResponsible for assisting the Product Owner to facilitate the digital product development and delivery, ensuring the digital assets across web and mobile app deliver a compelling and engaging user experience that meet the business objectives.\nResponsible for translating the digital journeys of the loyalty program into functional and non-functional requirement, developing test cases and performing UAT to ensure the product is fulfilling defined business goal and quality.\nAssists the Product Owner in gathering business requirements, developing user stories, defining acceptance criteria and managing the product backlog\nResponsible for documenting functional design of the digital platforms e.g. website and mobile apps\nCommunicates the business goal and acceptance criteria effectively with the scrum team or outsource partners to ensure the team has a comprehensive understanding of what to deliver in terms of functionality and quality\nHelps the Product Owner to inspect and evaluate the development and testing progress within sprint, and keep track the defect status\nDevelops \u201cDay-in-the-life\u201d test scripts for each of the user journeys\nConducts UAT to ensure the sprint deliverables are fulfilling defined acceptance criteria and well-functioned\nSupports the Product Owner on app usage analysis to identify UX improvements and business opportunities\nSupports the Product Owner on product release planning\n\nThe Person\n\nMinimum 3 years\u2019 experience as a Business Analyst with relevant industry experience\nDeep knowledge of Agile process and principles\nGood knowledge and experience of consumer facing digital solutions including websites and mobile apps\nStrong analytics and problem-solving skills\nStrong communication skills\nGood attention to detail with excellent organisational and time management skills", "employment_types": ["Full Time"], "selling_points": ["Opportunity to work with high performing team", "Exciting career path", "One of the biggest loyalty program"], "locations": ["Tai Koo"], "categories": ["Information Technology (IT)", "Others"], "post_time": "2022-01-18T03:32:20Z", "salary": {"currency": null, "max": null, "min": null, "period": "monthly", "term": null}, "salary_visible": false, "title_keywords": ["analyst", "operations"], "responsibilities": ["mobile app", "uat", "analysis", "business opportunities", "quality", "user experience", "developing", "design", "website", "evaluate", "testing", "planning"], "requirements": {"degrees": [], "majors": [], "languages": [], "language_level": [], "hard_skills": ["problem-solving skills", "mobile", "agile"], "soft_skills": ["communication skills", "agile", "time management skills", "deep", "attention to detail", "problem-solving skills"], "languages_combined": []}, "experience_required": {"duration": ["minimum 3 years"], "field": ["digital", "business"]}}, {"job_id": "100003009052813", "location_code": "hk", "company": "Marsh (Hong Kong) Limited", "job_title": "Senior Service Desk Technical Support Analyst (1 year contract)", "description": "Position Overview\n\nThe Service Desk Analyst role at Marsh & McLennan affects colleagues of all levels, in all of our companies, in every region of the world.\n\nBeing the first point of contact on any technology-related process, application or device, you will be providing first-level technical phone support by diagnosing, reporting and resolving or correcting hardware and software problems.\n\nYou will manage all aspects of the installing, maintaining and troubleshooting hardware and software according to company standards \u2013 reconfiguring existing systems or performing system upgrades as required.\n\nThis will require monitoring and escalating issues until resolution, closure or handoff to a specialized support team.\n\nKey Responsibilities\n\n\nProvides Service Desk support by chat, phone and email, assisting users in diagnosing, reporting and resolving or correcting hardware and software problems.\nInstalls, maintains and troubleshoots hardware and software according to company standards \u2013 reconfigures existing systems and/or performs system upgrades as required.\nLogs all issues with appropriate documentation as requested.\nRoute calls to appropriate support teams as per described troubleshooting steps.\nMonitor and escalate issues until resolution, closure or the appropriate group has accepted.\nMaintain current knowledge of support knowledge provided through training and the Knowledge Base.\nExpected to resolve 75%+ of incoming incidents and attain 95%+ positive Customer Satisfaction feedback score, expected to handle a minimum of 40 incidents per day.\n\n\nSkills and Experience\n\n\nThis position will require the successful individual to provide technical support to our global colleague base, the shift pattern will be between Monday \u2013 Friday cover Bank Holidays. (Shift HK Time: 6:30am-3:30pm / 7:30am-4:30pm).\nBachelor\u2019s degree in computer science or equivalent is desired.\nMinimum 2-3 years\u2019 experience of working within a similar capacity for a Service Desk / Helpdesk/ Call Centre.\nTechnical Troubleshooting experience is a must.\nFamiliar with a variety of IT Service Desk concepts, practices, procedures and policies.\nMust have excellent verbal and written communication skills.\nEssential languages required: English, Cantonese. Also desired: Mandarin, Japanese, Korean.\nWe are an Equal Opportunity Employer. Visit us at\u00a0\u00a0www.marsh.com/hk\n\nAll information received will be kept in strict confidence and be used only for employment-related purposes.\n\n", "employment_types": ["Contract"], "selling_points": ["IT Desk Support", "Working with Regional Teams", "Technical Troubleshooting Experience"], "locations": ["Quarry Bay"], "categories": ["Information Technology (IT)", "Support", "Others"], "post_time": "2022-01-17T04:10:40Z", "salary": {"currency": null, "max": null, "min": null, "period": "monthly", "term": null}, "salary_visible": false, "title_keywords": ["technical support", "analyst"], "responsibilities": ["it service", "software", "troubleshooting", "communication", "maintain", "maintaining", "teams", "monitor", "resolution", "reporting", "upgrades", "monitoring", "procedures", "installing", "contact", "documentation", "technical support", "policies", "systems", "hardware"], "requirements": {"degrees": ["degree", "bachelor"], "majors": ["computer science"], "languages": ["cantonese", "english", "mandarin", "japanese", "korean"], "language_level": [], "hard_skills": ["documentation", "hardware", "system upgrades"], "soft_skills": ["communication skills", "confidence", "troubleshooting", "positive"], "languages_combined": [{"language": "cantonese", "language_level": []}, {"language": "english", "language_level": []}, {"language": "mandarin", "language_level": []}, {"language": "japanese", "language_level": []}, {"language": "korean", "language_level": []}]}, "experience_required": {"duration": ["minimum 2-3 years"], "field": ["troubleshooting"]}}, {"job_id": "100003009055831", "location_code": "hk", "company": "Ambition", "job_title": "IT Deskside Support (Contract)", "description": "RESPONSIBILITIES\n\n- Handle enquiry via Helpdesk Hotline, in person or email and provide technical support to both\nour internal users and agency.\n- Provide 1st level supports on hardware & software troubleshooting\n- Provide PC installation and software deployment\n- Log all incident and request cases on the call logging system and follow up its status\n- Escalate incidents and problems to relevant second-level support team or external service providers\n- Relocation for desktop items and maintains the correct inventory record\n- Handle ad hoc IT support duties as assigned\n- Standby support during non-working hours when required\n\nREQUIREMENTS\n\n- Higher Diploma in Information Technology or related disciplines\n- 3+ years of IT support experience in Banking/Finance\n- Good communication skill in English & Chinese\n\nInterested parties, please click \"APPLY NOW\" or send your application to karis.chan@ambition.com.hk\n\nIf this job isn't quite right for you, but you know someone who would be great at this role, why not take advantage of our referral scheme? We offer HKD1000 in Apple gift cards for every referred candidate who we place in a role. Terms & Conditions Apply. https://www.ambition.com.hk/refer-a-friend", "employment_types": ["Full Time", "Permanent"], "selling_points": ["Renewable contract", "Financial Services", "Deskside suppor"], "locations": ["Not Specified"], "categories": ["Information Technology (IT)", "Hardware", "Support", "Others"], "post_time": "2022-01-18T02:59:37Z", "salary": {"currency": null, "max": null, "min": null, "period": "monthly", "term": null}, "salary_visible": false, "title_keywords": [], "responsibilities": ["installation", "ad hoc", "software", "technical support", "handle enquiry", "troubleshooting", "inventory record", "hardware", "escalate incidents"], "requirements": {"degrees": ["diploma"], "majors": ["related disciplines", "information technology"], "languages": ["english", "chinese"], "language_level": ["good"], "hard_skills": [], "soft_skills": ["communication skill"], "languages_combined": [{"language": "english", "language_level": ["good"]}, {"language": "chinese", "language_level": ["good"]}]}, "experience_required": {"duration": ["3+ years"], "field": ["finance", "banking", "it support"]}}, {"job_id": "100003009055188", "location_code": "hk", "company": "Swire Coca-Cola HK Ltd", "job_title": "Business Analyst", "description": "Responsibilities:\n\n\nAssist with implementation of SAP and other technical and innovative projects\nEngage in all project stages relevant to an analyst position such as pre-project preparation, project scoping, requirement gathering, implementation, system testing, user acceptance testing and user training\nCoordinate any processes throughout the whole project for ensuring all the stages meet the project schedule\nAnalyze, identify and propose business process improvement based on business / system need\nPrepare requirement document, manage Quality Assurance and UAT, execute tests, provide test case and results\nConduct user training and lead the implementation to ensure new functionalities are implemented in accordance with specifications and match the users' needs\nPrepare and maintain knowledge base, systems related documentation, training materials and operation manuals\nRequirements:\n\nAt least 3 years of relevant experience, preferably in system implementation and system support\nBachelor\u2019s Degree or above in Information Technology or related discipline and equivalents\nBroad IT domain experience in three or more of the following areas IT areas: Applications Development, Project Management, Vendor Management, Quality Assurance, Infrastructure, Maintenance and Support\nStrong sense of responsibility and able to work independently\nGood analytical and problem-solving skills\nProject management and presentation skills\nAttention to detail and strong follow-through on deliverables\nExcellent interpersonal and communication skill\nGood in written and spoken English and Chinese\nSAP certification/ SAP HANA experience will be an advantage\nPlease apply with full resume,\u00a0current and expected salary and availability\u00a0to:\u00a0The Human Resources Manager, Swire Coca-Cola HK, 17-19 Yuen Shun Circuit, Siu Lek Yuen, Shatin, or by clicking 'Apply Now'.\u00a0\n\n\n*Personal data provided are treated in strictest confidence and for recruitment purposes only.\u00a0 All information will be destroyed after the process completed.*", "employment_types": ["Full Time", "Contract"], "selling_points": ["Degree or above in Information Technology/related", "3+ years exp in working with system implementation", "Business requirements for innovative projects"], "locations": ["Shatin Area"], "categories": ["Information Technology (IT)", "Product Management / Business Analyst", "Others"], "post_time": "2022-01-18T01:42:22Z", "salary": {"currency": null, "max": null, "min": null, "period": "monthly", "term": null}, "salary_visible": false, "title_keywords": ["business analyst"], "responsibilities": ["uat", "related documentation", "systems", "quality", "implementation", "testing", "coordinate", "business process", "specifications", "schedule", "maintain"], "requirements": {"degrees": ["degree or above", "bachelor"], "majors": ["information technology"], "languages": ["english", "chinese"], "language_level": ["good"], "hard_skills": ["maintenance", "sap", "vendor", "project management", "system implementation", "problem-solving skills"], "soft_skills": ["work independently", "confidence", "sense of responsibility", "communication skill", "project management", "presentation skills", "attention to detail", "problem-solving skills", "interpersonal"], "languages_combined": [{"language": "english", "language_level": ["good"]}, {"language": "chinese", "language_level": ["good"]}]}, "experience_required": {"duration": ["at least 3 years"], "field": ["management", "maintenance", "development", "system support", "infrastructure", "project management", "it", "relevant experience", "quality assurance"]}}, {"job_id": "100003009054253", "location_code": "hk", "company": "CHOW TAI FOOK JEWELLERY CO LTD", "job_title": "Business Intelligence Analyst", "description": "What You Do\n\n\nPerform ETL, Data modeling and Dashboard building\nWork closely with business analysis team and other stakeholders to develop end-to-end BI solutions and dashboards in order to facilitate business requirements that yield relevant business information\nMaintain, support and implement business intelligence platform\nTroubleshoot issues on BI reports & dashboards\nEnsure smooth data architecture and process for BI projects\nImprove data visualization by turning data into insights\nResponsible for data consolidation and ensure data quality is well maintained\nComplete jobs with good quality and within schedule\nProvide proper documentations, such as BRD and TDD\nPerform other ad-hoc management reports development as assigned\n\nWho Will Thrive\n\n\nBachelor Degree in Computer Science\u00a0/\u00a0Statistics /\u00a0Finance or other relevant quantitative disciplines\nAt least 3 years\u2019 solid working experiences in data analytics with exposure in business intelligence project\nFamiliar with Qlikview / Qlik Sense and\u00a0SQL Query or other data visualization tools\nCertified Qlik Data Architect is an advantage\nExperience in web development\u00a0is an\u00a0advantage but not essential\nExperience in\u00a0Supply\u00a0Chain\u00a0Management\u00a0/\u00a0jewelry industry is an advantage\nAble to work independently in\u00a0a\u00a0fast-paced environment with minimum supervision\nExcellent communication in English and Chinese\n\nBenefits\n\n5-day work\nCompetitive salary, staff meal, medical and dental insurance, life insurance\nVarious types of leave, e.g. Family-friendly leave, self-development leave,\u00a0Examination leave, marriage leave, birthday leave, volunteer service leave, etc\n\nWe offer excellent career opportunities, attractive remuneration package & benefits to the right candidate.\u00a0Interested parties please apply by clicking \"Apply Now\" with a full resume stating the latest and expected salary.\n\n\n\nAll information collected will be used for recruitment purposes only.", "employment_types": ["Full Time", "Contract"], "selling_points": ["Business Intelligence Analyst", "ETL, Data modeling and Dashboard building", "SQL Query / Qlikview / Qlik Sense / Python"], "locations": ["Kwai Hing"], "categories": ["Information Technology (IT)", "Software Development", "Technical Writing", "Others"], "post_time": "2022-01-17T08:58:11Z", "salary": {"currency": null, "max": null, "min": null, "period": "monthly", "term": null}, "salary_visible": false, "title_keywords": ["analyst"], "responsibilities": ["ad-hoc", "management", "visualization", "data", "quality", "develop", "communication", "management reports", "maintain", "reports", "troubleshoot", "schedule", "business analysis", "architecture"], "requirements": {"degrees": ["degree", "bachelor"], "majors": ["finance", "statistics", "computer science"], "languages": ["english", "chinese"], "language_level": ["excellent"], "hard_skills": ["qlikview", "web development", "bi", "data analytics", "analysis", "sql", "management reports", "data visualization", "business intelligence", "documentations"], "soft_skills": ["work independently", "responsible", "fast-paced environment", "communication", "troubleshoot", "smooth"], "languages_combined": [{"language": "english", "language_level": ["excellent"]}, {"language": "chinese", "language_level": ["excellent"]}]}, "experience_required": {"duration": ["at least 3 years"], "field": ["development", "management", "business", "supply chain"]}}, {"job_id": "100003009054040", "location_code": "hk", "company": "ADECCO", "job_title": "IT Officer / IT Support - HKD22K+ (Kowloon Bay)", "description": "Our client is a developing multiple corporation in Hong Kong, they are looking for a IT Officer with solid experience in daily IT operation support for their team.\n\n\nResponsibilities\nProvide IT support to users through phone-call, remote and on-site support\nInstallation and configuration of network, server, hardware, software, application systems, PC, printer and peripherals equipment\nAssist in performing any IT duties as assigned by the IT Manager\nNeed to cooperate with sales team to solve ad-hoc technical problem\nRequirements\nMinimum 1-year experience in IT Industry or relevant experience, fresh graduated will also be considered\nExperience in handle large scales corporation\nCandidate with less experience will be considered as assistant technical support technician\nA good team player and able to work independently\nLess experienced candidate will be considered IT Support\nImmediately available is preferred\nInterested parties, please\u00a0CLICK HERE\u00a0to apply the position via Adecco website with your CV.\u00a0Please note that only shortlisted candidates will be notified. All information gathered will be treated in strict confidence and solely used for recruitment purposes.", "employment_types": ["Full Time", "Permanent", "Contract"], "selling_points": [], "locations": ["Kowloon Bay"], "categories": ["Information Technology (IT)", "Support", "Network & System", "Others"], "post_time": "2022-01-17T08:10:49Z", "salary": {"currency": null, "max": null, "min": null, "period": "monthly", "term": null}, "salary_visible": false, "title_keywords": ["it officer", "it support"], "responsibilities": ["ad-hoc", "installation", "software", "configuration", "hardware", "sales team", "application systems", "cooperate with"], "requirements": {"degrees": [], "majors": [], "languages": [], "language_level": [], "hard_skills": [], "soft_skills": ["good team player", "work independently"], "languages_combined": []}, "experience_required": {"duration": ["minimum 1-year"], "field": ["it", "relevant experience"]}}, {"job_id": "100003009054823", "location_code": "hk", "company": "HALO Energy Limited, HKSTP Acceleration Programme", "job_title": "System Testing Engineer (Compliance)", "description": "Job Responsibilities:\nDesign and prepare test plan, test cases and test scenarios based on product requirement specification\nEstimate, prioritize, plan and coordinate testing activities\nPerform functional test and user test cases\nAutomation testing design implementation\nProvide testing report\nIssue tracking and management\nKnowledge of product quality assurance\nCollaborate with engineers and designers to ensure all products are completely compliant and no issues arise\nPrepare and present compliance reports with analysis of measurement, statistical, and other data\nDuties & Responsibilities:\nDesign and prepare test plan, test cases and test scenarios based on product requirement specification\nEstimate, prioritize, plan and coordinate testing activities\nPerform functional test and user test cases\nAutomation testing design implementation\nProvide testing report\nIssue tracking and management\nKnowledge of product quality assurance\nCollaborate with engineers and designers to ensure all products are completely compliant and no issues arise\nPrepare and present compliance reports with analysis of measurement, statistical, and other data\nBasic Qualifications:\nDegree in Electrical Engineering or related discipline required\nExperience in any one of the programming languages, python would be an advantage\nExperience in using auto-testing software would be an advantage\nExperience in mobile application testing distribution flow would be an advantage\nExperience in ISO27001 would be an advantage\nPreferred Qualifications:\nUnderstand the software development workflow\nWilling to learn new technologies\nSkilful on various software engineering tools\nGood analytical and problem-solving skill, results oriented attitude\nAble to communicate information in a clear & precise manner\nExcellent communication in both written and spoken English and Chinese (Mandarin an advantage)\nGood presentation skill", "employment_types": ["Full Time"], "selling_points": ["At least 5 years relevant working experience", "System testing in an innovation way", "5 days per week working hours, performance bonus"], "locations": ["Shatin Area"], "categories": ["Engineering", "Electrical / Electronics", "Information Technology (IT)", "Testing / QA", "Others"], "post_time": "2022-01-17T11:27:30Z", "salary": {"currency": null, "max": null, "min": null, "period": "monthly", "term": null}, "salary_visible": false, "title_keywords": ["engineer"], "responsibilities": ["tracking", "management", "collaborate with engineers", "software", "data", "analysis", "compliance", "quality", "implementation", "plan and coordinate", "testing", "testing activities", "design", "measurement", "communication", "reports", "plan", "report"], "requirements": {"degrees": ["degree"], "majors": ["electrical engineering"], "languages": ["english", "chinese", "mandarin"], "language_level": ["advantage", "excellent"], "hard_skills": ["presentation skill", "no", "basic", "analysis", "problem-solving", "mobile", "programming", "python"], "soft_skills": ["presentation skill", "problem-solving", "willing to learn", "prioritize", "clear", "communication", "precise"], "languages_combined": [{"language": "english", "language_level": ["excellent"]}, {"language": "chinese", "language_level": ["excellent"]}, {"language": "mandarin", "language_level": ["advantage", "excellent"]}]}, "experience_required": {"duration": [], "field": ["programming", "testing"]}}, {"job_id": "100003009055125", "location_code": "hk", "company": "Autotoll Limited", "job_title": "System Engineer", "description": "To cope with our expansion and continuous growth in the transportation and logistics related service, we are inviting talents to join our professional team.\n\nAbout the Role:\n\nSystem Infrastructure support and implement for Free Flow Tolling System (\"FFTS\") Hub\nProvide operation and maintenance supports\nMonitor and maintain system performance\nNetworking - Network setup and administration (firewall, VPN, VLAN, wireless AP, etc.)\nResponsible for the setup and administration for Backend Server\n\nAbout You:\n\nHigher Diploma or above in Computer Science or related disciplines\nHolder of CCNA, CISA, CISSP, CRISC, CSX-F, CSX-P qualification is preferable\nGood command of spoken and written English and Chinese\nAt least two years\u2019 work experience in server and network administration, computer technical support\nExperience in Windows 2019 servers, Cisco network/IP-Phone, Exchange, TCP/IP including Active Directory, DNS, DHCP, VPN and WINS operation\n\n\n\n\nWhat you can get from us:\n\nOn-the-job training, learning and development\u00a0provided\nExecutive workshops, interest class, corporate purchase discount offered by SHKP\nCompetitive salary and annual leaves\nFlexible working opportunities\n\nInterested parties, please send full resume with\u00a0expected salary\u00a0and\u00a0available date\u00a0to Human Resources and Administration Department by e-mail or by fax 2111 9459.\n\n(Data collected will be used for recruitment purpose only.)", "employment_types": ["Full Time", "Permanent"], "selling_points": ["Higher Diploma with at least 2 years exp.", "Provide operation and maintenance supports", "Monitor and maintain system performance"], "locations": ["Kwun Tong"], "categories": ["Information Technology (IT)", "Software Development", "Others"], "post_time": "2022-01-18T01:15:55Z", "salary": {"currency": null, "max": null, "min": null, "period": "monthly", "term": null}, "salary_visible": false, "title_keywords": ["system engineer"], "responsibilities": ["ap", "network administration", "dns", "maintenance", "active directory", "technical support", "infrastructure", "monitor", "purchase", "maintain", "logistics", "setup", "administration"], "requirements": {"degrees": ["higher diploma or above"], "majors": ["related disciplines", "computer science"], "languages": ["english", "chinese"], "language_level": ["good command"], "hard_skills": ["ap", "network administration", "workshops", "infrastructure support", "servers", "maintenance", "tcp", "active directory", "dns", "ccna", "ip", "vpn", "firewall", "server", "exchange"], "soft_skills": ["flexible", "active", "responsible", "learning"], "languages_combined": [{"language": "english", "language_level": ["good command"]}, {"language": "chinese", "language_level": ["good command"]}]}, "experience_required": {"duration": ["at least two years"], "field": ["network administration", "operation"]}}, {"job_id": "100003009053016", "location_code": "hk", "company": "JFE Consulting Limited", "job_title": "Systems Specialist (Unix/Linux)", "description": "\u00a0Our client, one of the leading IT companies, is looking for high calibres to join their winning team:-\n\nResponsibilities:\n\nPerform capacity planning for Linux/UNIX systems and services. Anticipates growth demands and responds with action plans accordingly\nParticipates with systems analysts, operations staff and IT staff in overall systems development direction from technical analysis to user acceptance testing. Prepares and reviews test data and executes detailed test plans\nPrepares and reviews assessments to include required tasks, estimated time frames and effort for any scope project\nParticipate in planning, designing, documenting, and implementing new technologies\nStaff supervision and Development \u2013 No\n\nReqirements:\n\n\n\n3 to 5 years\u2019 experience as a Linux/Unix system administrator in a virtualized environment such as VMWare (RHEL 6.x, 7.x, 8.x, AIX 6.1, 7.1)\nExperience installing, configuring and maintaining services such as SSSD, YUM, firewalld, Squid Proxy, Apache\nHolder of Unix, Red Hat Certified\u00a0Engineer (RHCE), LPI or SAN certification is preferred", "employment_types": ["Full Time", "Permanent"], "selling_points": ["Unix/Linux", "Holder of RHCE, LPI or SAN certification", "Technical project implementation"], "locations": ["Quarry Bay"], "categories": ["Information Technology (IT)", "Support", "Others", "UI/UX Designer"], "post_time": "2022-01-17T05:04:58Z", "salary": {"currency": null, "max": null, "min": null, "period": "monthly", "term": null}, "salary_visible": false, "title_keywords": ["specialist"], "responsibilities": ["data", "operations", "analysis", "systems", "testing", "designing", "plans", "planning"], "requirements": {"degrees": [], "majors": [], "languages": [], "language_level": [], "hard_skills": ["linux", "apache", "red hat", "vmware"], "soft_skills": [], "languages_combined": []}, "experience_required": {"duration": ["3 to 5 years"], "field": []}}, {"job_id": "100003009055126", "location_code": "hk", "company": "Autotoll Limited", "job_title": "System Support", "description": "About The Role:\n\nResponsible for system maintenance and support, including intelligent transport systems and smart city systems\nPerform daily application operation maintenance, including pre-opening health check, system monitoring, day-end operation, data backup and log management, etc\nAssist in project implementation, including system migration, UAT and other related ad-hoc project\nAssist in operation documentation\nShift duty required\n\nAbout You:\n\n\n1 year relevant IT support experience\n\n\nWhat you can get from us\n\nOn-the-job training, learning and development\u00a0provided\nExecutive workshops, interest class, corporate purchase discount offered by SHKP\nCompetitive salary and annual leaves\nFlexible working opportunities\n\nInterested parties, please send full resume with\u00a0expected salary\u00a0and\u00a0available date\u00a0to Human Resources and Administration Department by e-mail or by fax 2111 9459.\n\n(Data collected will be used for recruitment purpose only.)", "employment_types": ["Full Time", "Permanent"], "selling_points": ["1 year relevant IT support experience", "Responsible for system maintenance and support", "Perform daily application operation maintenance"], "locations": ["Kowloon Bay"], "categories": ["Information Technology (IT)", "Support", "Network & System", "Others"], "post_time": "2022-01-18T01:15:55Z", "salary": {"currency": null, "max": null, "min": null, "period": "monthly", "term": null}, "salary_visible": false, "title_keywords": ["system support"], "responsibilities": ["ad-hoc", "management", "uat", "maintenance", "data", "monitoring", "systems", "implementation", "purchase", "documentation", "migration"], "requirements": {"degrees": [], "majors": [], "languages": [], "language_level": [], "hard_skills": ["documentation", "workshops", "maintenance"], "soft_skills": ["flexible", "learning", "responsible"], "languages_combined": []}, "experience_required": {"duration": ["1 year"], "field": ["it support"]}}, {"job_id": "100003009054738", "location_code": "hk", "company": "Hong Kong Examinations and Assessment Authority", "job_title": "Programmers (Ref: IT/01/812)", "description": "Duties:\u00a0The appointees will be responsible for the development and support of core IT application systems.\n\nRequirements:\n\nA Bachelor\u2019s Degree / Associate Degree / Higher Diploma in Information Technology, Computer Science or related disciplines;\nAt least two years\u2019 working experience in application system development or support services;\nHands-on experience with web application development and PL/SQL programming;\nKnowledge in web-based system design and application security definitely an advantage;\nGood oral and written communication skills in both Chinese and English; and\nHigh-calibre fresh graduates are also welcome.\n\nEmployment Terms:\u00a0 The remuneration package will be commensurate with qualifications and experience.\u00a0 Appointment will be on a fixed-term contract with contract-end-gratuity, MPF benefits, medical and dental care.\u00a0 Future employment may be offered on renewable contracts subject to performance and staffing needs.\n\nDate for Application Review: 7 February 2022\n\nApplications would be considered until the post is filled.\n\nApplication forms can be obtained from the HKEAA office on 13/F., Southorn Centre, 130 Hennessy Road, Wan Chai, Hong Kong or downloaded from the HKEAA website (www.hkeaa.edu.hk/tc/Career/general.html).\u00a0 Completed application forms should be returned to the Manager \u2013 Human Resources at the above address. Due to the secrecy nature of HKEAA's job duties, applicants invited for interview may be required to make a declaration of any conflict of interests. Applicants not notified within 10 weeks from the application review date should consider their applications unsuccessful.\n\nThe HKEAA is an equal opportunities employer and welcomes applications from all qualified candidates. Information provided relating to employment will be kept confidential and used only for processing applications. For details, please refer to the Policy Statement on Equal Opportunities and the Personal Information Collection Statement on the HKEAA website (www.hkeaa.edu.hk).", "employment_types": ["Full Time", "Permanent"], "selling_points": [], "locations": ["Not Specified"], "categories": ["Information Technology (IT)", "Support", "Software Development", "Others"], "post_time": "2022-01-17T10:51:39Z", "salary": {"currency": null, "max": null, "min": null, "period": null, "term": null}, "salary_visible": false, "title_keywords": [], "responsibilities": ["application development", "support services", "application system", "communication", "system design", "application systems"], "requirements": {"degrees": ["associate degree", "diploma", "degree", "bachelor"], "majors": ["related disciplines", "computer science", "information technology"], "languages": ["english", "chinese"], "language_level": ["good"], "hard_skills": ["web application development", "web", "application system", "sql", "system design", "programming", "pl"], "soft_skills": ["communication skills", "hands-on", "oral", "responsible"], "languages_combined": [{"language": "english", "language_level": ["good"]}, {"language": "chinese", "language_level": ["good"]}]}, "experience_required": {"duration": ["at least two years"], "field": ["sql", "application development", "programming", "system development"]}}, {"job_id": "100003009054153", "location_code": "hk", "company": "CHOW TAI FOOK JEWELLERY CO LTD", "job_title": "Analyst Programmer", "description": "What You Do\n\nHands-on for SDLC including design, coding, testing, implementation and maintenance of in-house systems\nInterface internal systems with other outsourced modules\nWork closely with business analysts to produce application design\nConduct feasibility study and analysis based on users' requirements and provide technical advice\nEnsure flexibility, stability, scalability, sustainability and performance of systems\nProvide system support on more complex user enquiries, production problems and troubleshooting\nProvide technical investigation and quick fix in case of encountering critical incident\nComplete jobs with good quality and within schedule\nMaintain awareness of new technologies and best practices for adoption\nEnsure all deliverables are in good quality and meeting requirements\nProvide database maintenance and data housekeeping\nWork closely with data quality team to align with SDLC on data governance related compliance\nPrepare technical documentations and system specifications\n\nWho Will Thrive\n\nBachelor Degree in Computer Science, Information System or equivalent with experience in supply chain management, jewelry industry is an advantage\nAt least 3 years of experience in web-based application development in .NET platform\nFamiliar with the ASP.NET framework, SQL Server and design/architectural patterns (e.g. MVC)\nFamiliar with .NET languages (e.g. C#, VB.NET), javascript, Ajax, jQuery, JSON, HTML5/CSS3, MSSQL\nGood analytical, problem solving and interpersonal skills\nAble to work independently in fast paced environment with minimum supervision\nComplete jobs with good quality and within schedule\n\nBenefits\n\n\n5-day work\nCompetitive salary, staff meal,\u00a0medical and dental insurance, life insurance\nVarious types of leave, e.g.\u00a0Family-friendly leave, self-development leave,\u00a0Examination leave, marriage leave, birthday\u00a0leave, volunteer service leave, etc\n\nWe offer excellent career opportunities, attractive remuneration package & benefits to the right candidate.\u00a0Interested parties please apply by clicking \"Apply Now\" with a full resume stating the latest and expected salary.\n\n\n\nAll information collected will be used for recruitment purposes only.", "employment_types": ["Full Time", "Permanent"], "selling_points": ["Application development and testing", "Application management", ".NET / ASP.NET / RPA / Git"], "locations": ["Kwai Hing"], "categories": ["Information Technology (IT)", "Software Development", "Technical Writing", "Others"], "post_time": "2022-01-17T08:35:31Z", "salary": {"currency": null, "max": null, "min": null, "period": "monthly", "term": null}, "salary_visible": false, "title_keywords": ["analyst programmer"], "responsibilities": ["data", "technical advice", "quality", "troubleshooting", "coding", "design", "maintain", "database", "application development", "compliance", "implementation", "testing", "schedule", "internal systems", "management", "investigation", "specifications", "maintenance", "housekeeping", "analysis", "systems"], "requirements": {"degrees": ["degree", "bachelor"], "majors": ["computer science"], "languages": [], "language_level": [], "hard_skills": ["maintenance", "web", "analysis", "jquery", "information system", "mssql", "sql", "problem solving", "sdlc", "javascript", "ajax", "server", "documentations", "c#"], "soft_skills": ["work independently", "troubleshooting", "problem solving", "hands-on", "interpersonal skills"], "languages_combined": []}, "experience_required": {"duration": ["at least 3 years"], "field": ["supply chain", "management", "application development"]}}, {"job_id": "100003009053328", "location_code": "hk", "company": "ALBA Integrated Waste Solutions (Hong Kong) Limited", "job_title": "IT Support (Eco Park)", "description": "Responsibilities\n\nProvide technical support to end-users on office software applications;\nTroubleshoot e-mail, printer and facsimile, software, hardware, networking and all other computer related issues;\nManage company's software/hardware assets;\nAssist IT Administrator on server administration and maintenance tasks\nCoordinate with internal users and external vendors to tackle IT issues\n\nRequirements\n\nDiploma preferably related to IT discipline\nMinimum 1-2 years of work experience in IT technical support\nSolid knowledge of IT and new technology\nOrganized, willing to learn, independent, multi-tasking, and a great team player\nFluent in English and Cantonese\n\nWorking hours: Monday to Friday, alternate Saturdays\nBenefits: End of Year Payment, Annual Leave, Birthday Leave, Bank Holidays, Education Allowance, Medical & Dental Insurance, Free Shuttle Bus (Kowloon/ Tuen Mun/ Tin Shui Wai)\n\nPlease\u00a0send your CV with professional qualifications and expected salary to Human Resources Department by clicking \"Apply Now\".\nApplicants not invited for interview within 6 weeks may consider their application unsuccessful.\u00a0Unsuccessful applications will be kept for 12 months and then destroyed. Personal data collected will be used for recruitment purposes only.", "employment_types": ["Full Time"], "selling_points": ["IT infrastructure, server adm and networking", "Monday to Friday, alternate Saturdays", "Bank Holidays, Birthday Leave, Double pay, Medical"], "locations": ["Tuen Mun Area"], "categories": ["Information Technology (IT)", "Others"], "post_time": "2022-01-17T06:46:28Z", "salary": {"currency": null, "max": null, "min": null, "period": "monthly", "term": null}, "salary_visible": false, "title_keywords": ["it support"], "responsibilities": ["software", "technical support", "coordinate with", "maintenance tasks", "hardware", "troubleshoot", "administration"], "requirements": {"degrees": ["diploma"], "majors": ["it"], "languages": ["cantonese", "english"], "language_level": ["fluent"], "hard_skills": ["professional qualifications"], "soft_skills": ["organized", "independent", "willing to learn", "multi-tasking", "team player"], "languages_combined": [{"language": "cantonese", "language_level": ["fluent"]}, {"language": "english", "language_level": ["fluent"]}]}, "experience_required": {"duration": ["minimum 1-2 years"], "field": ["it technical support"]}}, {"job_id": "100003009053939", "location_code": "hk", "company": "Shopline Limited", "job_title": "IT Analyst", "description": "Job Description\n\nSHOPLINE is Asia\u2019s largest smart commerce platform. With our customers in mind, we strive to deliver scalable commerce solutions to merchants of all sizes. We\u2019re a full-featured platform with services including online store opening, O2O solution, retail POS systems, advertising placement, business strategy consultation, marketing, and more to empower merchants to succeed in omnichannel retailing and cross-border commerce.\n\n\n\nWHAT YOU\u2019LL BE DOING:\u00a0\n\nManage IT service desk for incident resolution and service;\nEnsure software licenses and IT asset inventory records are properly maintained;\nAssist team lead in the procurement of end user computing products and services;\nMaintain IT documentation on user computing standards, service desk operation procedures and guidelines;\nParticipate in various IT projects.\n\nWHO WE ARE LOOKING FOR:\n\n1-3+ years relevant experience preferably in IT field\nUniversity degree is prefer\nWith Jira Software and ITIL experience is a plus\nQuick learner, curious and passionate about learnings and e-commerce\nGood command of spoken and written Chinese, English and Mandarin\n\n\n\nWHY YOU SHOULD JOIN US:\n\nWe work in a fun, collaborative open space where we encourage creativity and ideas flow freely.\nYou\u2019ll be able to steer the future roadmap to improve our products, big or small, and see the results of your products reach our customers.\nGet to work with flexible working hours. Our priority is on getting the job done.\nFlat structure environment, you will be able to work independently and make your own choices.\nWe provide guidance and mentorship to polish your business skills and entrepreneurship mindset.\nWe are one of the standout tech startups in Hong Kong, targeting a huge opportunity in Asia.\nShopline is a part of the 500 Startups Accelerator and Incubated by Hong Kong Cyberport, giving us a massive network of advisors and resources globally", "employment_types": ["Full Time", "Permanent"], "selling_points": ["IT Helpdeck & Admin support", "With Jira Software and ITIL experience is a plus", "Attractive package and benefits"], "locations": ["Sheung Wan"], "categories": ["Information Technology (IT)", "Support", "Others"], "post_time": "2022-01-17T07:48:05Z", "salary": {"currency": null, "max": null, "min": null, "period": "monthly", "term": null}, "salary_visible": false, "title_keywords": ["it analyst"], "responsibilities": ["advertising", "it service", "software", "ideas", "guidelines", "systems", "procedures", "resolution", "asset inventory", "maintain", "documentation", "software licenses"], "requirements": {"degrees": ["university degree"], "majors": [], "languages": ["english", "chinese", "mandarin"], "language_level": ["good command"], "hard_skills": ["itil", "small", "plus", "pos", "e-commerce", "fun", "make", "documentation"], "soft_skills": ["flexible", "work independently", "collaborative", "quick learner", "passionate about"], "languages_combined": [{"language": "english", "language_level": ["good command"]}, {"language": "chinese", "language_level": ["good command"]}, {"language": "mandarin", "language_level": ["good command"]}]}, "experience_required": {"duration": ["3+ years"], "field": ["it", "relevant experience"]}}, {"job_id": "100003009051737", "location_code": "hk", "company": "Tat Ming Wallpaper Company Limited", "job_title": "\u96fb\u8166\u6280\u8853\u652f\u63f4\u54e1", "description": "\u8981\u6c42 :\n\n\n\u4e2d\u4e94\u7a0b\u5ea6; 1-2\u5e74\u6709\u95dc\u5de5\u4f5c\u7d93\u9a57; \u826f\u597d\u7cb5\u8a9e; \u61c2\u666e\u901a\u8a71\u53ca\u82f1\u8a9e\n\n\u5de5\u4f5c\u7bc4\u570d :\n\n\n\u4e00\u822c\u65e5\u5e38IT\u652f\u63f4\u670d\u52d9; \u6587\u66f8\u8655\u7406; \u7db2\u7d61\u53ca\u96fb\u8166\u7dad\u8b77 ;\n\n\u8fa6\u516c\u5ba4\u8a2d\u5099\u7dad\u4fee; \u53ef\u4ee5\u7368\u7acb\u5de5\u4f5c; \u6709\u8cac\u4efb\u5fc3,\u6a02\u65bc\u8207\u4eba\u6e9d\u901a;\n\n\u61c2\u4e00\u822c\u7db2\u9801\u88fd\u4f5c / \u6703\u8a08\u6982\u5ff5/ php\n\n\u5f85\u9047 :\n\n\u85aa\u512a + \u96d9\u7ce7 + \u5e74\u7d42\u82b1\u7d05\n\u9280\u884c\u5047\u671f\n\u91ab\u7642\u6d25\u8cbc\n\u54e1\u5de5\u8cfc\u7269\u512a\u60e0\n\n\u6709\u610f\u8005\u8acb\u96fb\u90f5\u5c65\u6b77\u8868\u81f3\"Apply Now\"\u6216\u50b3\u771f\u5230 2838-0805 \u4eba\u4e8b\u90e8\u6536\n\n\u7db2\u9801 : www.tatming.com", "employment_types": ["Full Time", "Permanent"], "selling_points": ["\u4e2d\u4e94\u7a0b\u5ea6; 1-2\u5e74\u6709\u95dc\u5de5\u4f5c\u7d93\u9a57", "\u4e00\u822c\u65e5\u5e38IT\u652f\u63f4\u670d\u52d9; \u6587\u66f8\u8655\u7406; \u7db2\u7d61\u53ca\u96fb\u8166\u7dad\u8b77", "\u85aa\u512a + \u96d9\u7ce7 + \u5e74\u7d42\u82b1\u7d05"], "locations": ["Not Specified"], "categories": ["Information Technology (IT)", "Support", "Network & System", "Others"], "post_time": "2022-01-16T21:51:18Z", "salary": {"currency": null, "max": null, "min": null, "period": "monthly", "term": null}, "salary_visible": false, "title_keywords": [], "responsibilities": [], "requirements": {"degrees": [], "majors": [], "languages": [], "language_level": [], "hard_skills": ["php"], "soft_skills": [], "languages_combined": []}, "experience_required": {"duration": [], "field": []}}, {"job_id": "100003009056128", "location_code": "hk", "company": "DHL EXPRESS (HONG KONG) LIMITED", "job_title": "Manager, Service Management", "description": "Responsibilities:\n\n\n\nPlanning and implementation of cyber security projects and IT infrastructural projects\nManage internal team and external party for supporting the daily operations, including the monitoring, trouble shooting and subsequent customization and configuration works\nManage the IT service operation to meet the corresponding service level agreement (SLA)\nSupport audit and disaster recovery activities across the service team, and provide technical advice\nDevelop and maintain operational procedures and performance statistics/reports\nManage service delivery to project in daily IT operation according to the ITIL Best Practice, promoting the Continual Service Improvement of service quality and user satisfaction\nResponsible for resources planning and utilization control\nPrepare IT budget\n\nRequirements:\n\n\n\nStrong/solid experience/knowledge in data network and infrastructure, administration & maintenance of Windows 2012/2016 servers,\nKnowledge in Microsoft Windows Active Directory, VMware vSphere Administration is preferred\nDemonstrated strong presentation skill with high degree of maturity & sense of responsibility\nGood analytical skill with objective thinking and strong willingness to initiate and drive changes across all levels\nAssertive and result-oriented; able to follow through tasks until completion independently\nBachelor Degree or above education, preferably in Computer Science or related disciplines\n8 years IS and business experience, preferably in logistics industry, with 5 years IS management experience\n\nBelow qualifications are preferred\n\n\n\nCertified Information Systems Security Professional (CISSP)\nCisco Certified Network Professional (CCNP) or Cisco Certified Network Associates (CCNA)\nMicrosoft Certified System Engineer (MCSE) or Microsoft Certified IT Professional (MCITP)\n\nPersonal Information Collection Statement pertaining to Recruitment\n\nDHL Express (Hong Kong) Limited / DHL Aviation (Hong Kong) Limited (\u201cDHL\u201d) is committed to protecting and respecting your privacy in accordance with the Personal Data (Privacy) Ordinance of Hong Kong (the \u201cOrdinance\u201d) and DHL\u2019s Personal Data Protection Policy (the \u201cPolicy\u201d) at\u00a0https://www.dhl.com/hk-en/home/footer/local-privacy-notice.html\n\nBy proceeding to respond to this recruitment advertisement, you consent that we may use, retain, process, transfer or otherwise handle the personal data that we collect from you for recruitment,\u00a0 application processing, assessment and communication purposes (including any other purposes directly related thereto) in accordance with the Policy.\n\nAll personal data of unsuccessful applicants will be retained for future recruitment purposes for a period of not more than two (2) years after which such data will be destroyed.\n\nYou have the right at any time to make a data access or correction request concerning your personal data held by us. In addition, you may request us to delete your personal data that is no longer required for the relevant purposes which you have given consent. Should you wish to exercise such rights or have any question in relation to your personal data or the Policy, please contact our Human Resources Division in writing.", "employment_types": ["Full Time"], "selling_points": ["Manage the IT service operation", "Bachelor Degree or above education", "8 years IS and business experience"], "locations": ["Lantau Island"], "categories": ["Admin & HR", "Administration / Operation Manager", "Transportation & Logistics", "Others", "Information Technology (IT)", "Others"], "post_time": "2022-01-18T03:21:48Z", "salary": {"currency": null, "max": null, "min": null, "period": "monthly", "term": null}, "salary_visible": false, "title_keywords": ["manager"], "responsibilities": ["service delivery", "control", "it service", "cyber security", "configuration", "technical advice", "monitoring", "quality", "implementation", "audit", "develop", "it budget", "daily operations", "maintain", "operational procedures", "reports", "planning"], "requirements": {"degrees": ["degree or above", "degree", "bachelor"], "majors": ["related disciplines", "computer science"], "languages": [], "language_level": [], "hard_skills": ["presentation skill", "mcse", "analytical skill", "no", "servers", "active directory", "maintenance", "vmware", "ccnp", "ccna", "html", "make", "processing", "data network"], "soft_skills": ["presentation skill", "analytical skill", "independently", "assertive", "sense of responsibility", "communication", "committed", "active", "result-oriented"], "languages_combined": []}, "experience_required": {"duration": ["5 years", "8 years"], "field": ["management", "maintenance", "infrastructure", "logistics industry", "business", "administration"]}}, {"job_id": "100003009048757", "location_code": "hk", "company": "United Asia Finance Limited", "job_title": "Senior Infrastructure Specialist (FinTech and Innovation Department)", "description": "Job Responsibilities:\nAssist to design and implement the network infrastructure\nPerform system administration on Firewall, Router, Switch, Server and Storage\nConduct network monitoring and maintenance to ensure the performance and stability of the data network\nProvide consultative, proactive and/or reactive support for Networking Services not only to users but also to project team\nParticipate in the preparation of technical specifications for the procurement of telecommunication and Cloud services, servers and network equipment\nJob Requirements:\nBachelor Degree in Computer Science or related disciplines\nOver 5 years working experience in network and server administration\nHands-on experience in managing firewall, VPN, router, switch, Storage / Backup, WAN and network support in large scale network\nWorking experience in VMWare, Linux, Microsoft WindowsServer, O365 and Azure\nExtensive knowledge in IP network and IT security\nKnowledge in ISO27001 and ITIL is preferred\nAble to work independently and self-motivated to deliver good results\nGood command of both spoken and written Chinese and English\nImmediate available or short notice period is highly desirable\nCandidate with less experience will be considered as Infrastructure Specialist\nWe offer attractive remuneration package which includes double pay and discretionary bonus. Interested parties please send your CV indicating your current salary, expected salary and availability to HR Department, by email via clicking \"Apply Now\".\n\n(Personal data collected will be treated in the strictest confidence and will be handled by authorized personnel for recruitment-related purposes only. Applicants who do not hear from us within 3 months may consider their application unsuccessful and their data will be destroyed within 24 months of receipt.)", "employment_types": ["Full Time", "Permanent"], "selling_points": ["Double pay and discretionary bonus", "Perform system administration on Firewall", "Bachelor Degree in Computer Science"], "locations": ["Wan Chai"], "categories": ["Information Technology (IT)", "Network & System", "Technical / Functional Consulting", "Others"], "post_time": "2022-01-14T07:13:26Z", "salary": {"currency": null, "max": null, "min": null, "period": "monthly", "term": null}, "salary_visible": false, "title_keywords": ["specialist"], "responsibilities": ["network infrastructure", "maintenance", "data", "monitoring", "design", "specifications", "administration"], "requirements": {"degrees": ["degree", "bachelor"], "majors": ["related disciplines", "computer science"], "languages": ["english", "chinese"], "language_level": ["good command"], "hard_skills": ["itil", "linux", "o365", "azure", "vmware", "server administration", "switch", "router", "ip", "vpn", "firewall", "wan"], "soft_skills": ["hands-on", "extensive", "work independently", "self-motivated"], "languages_combined": [{"language": "english", "language_level": ["good command"]}, {"language": "chinese", "language_level": ["good command"]}]}, "experience_required": {"duration": ["5 years"], "field": ["infrastructure", "server administration"]}}, {"job_id": "100003009054692", "location_code": "hk", "company": "Our Hong Kong Foundation Limited", "job_title": "Senior Officer, System Development", "description": "Responsibilities:\n\nTo develop and implement new digital solutions, modify and enhance current systems, integrate new features and improvements, all with the aim of improving business efficiency and productivity\nTo participate in all phases of software application development from requirement gathering to implementation, testing and system delivery\nTo develop e-form for event registration\nTo maintain system documentation\nTo liaise with vendor and assure the quality of deliverable\n\nRequirements:\n\n\nUniversity degree or equivalent, or higher education in Computer Science or related discipline\n2-5 years solid experience in web development\nHands-on experience in Java/PHP and its framework\nSolid experience in MySQL with MongoDB is a plus\n\u00a0Ability to effectively prioritize and execute multiple projects simultaneously\nGood communication, problem-solving & time management skills\nCandidates with less experience would be considered as officer\n\nInterested parties please send:\n\n\nFull resume;\nCover letter;\nCopies of academic transcripts (including public examination results if applicable);\nPresent and expected salary;\nAvailability\u00a0\n\nBy clicking 'Apply Now' or by post to: Our Hong Kong Foundation Limited, 19/F, Nan Fung Tower, 88 Connaught Road Central, Hong Kong. Applicants who are not invited to an interview within two months from the date of this advertisement should consider their applications unsuccessful.\u00a0\n\nAll information provided by applicants will be handled with strictest confidence and will be solely used for the purpose of recruitment.\n", "employment_types": ["Full Time", "Permanent"], "selling_points": ["Solid experience in web development", "Hands-on experience in Java / PHP", "Growing platform with development opportunities"], "locations": ["Wan Chai"], "categories": ["Information Technology (IT)", "Application Specialist - Software", "Software Development", "Others"], "post_time": "2022-01-17T10:36:05Z", "salary": {"currency": null, "max": null, "min": null, "period": "monthly", "term": null}, "salary_visible": false, "title_keywords": ["senior officer"], "responsibilities": ["software", "system documentation", "systems", "system delivery", "implementation", "quality", "develop", "testing", "maintain", "liaise with", "application development"], "requirements": {"degrees": ["university degree"], "majors": ["computer science"], "languages": [], "language_level": [], "hard_skills": ["web development", "plus", "java", "php", "problem-solving"], "soft_skills": ["time management skills", "problem-solving", "prioritize", "communication", "hands-on"], "languages_combined": []}, "experience_required": {"duration": ["2-5 years"], "field": ["development"]}}, {"job_id": "100003009055107", "location_code": "hk", "company": "Autotoll Limited", "job_title": "Senior Analyst Programmer/ Analyst Programmer", "description": "About The Role :\n\nDevelop systems/functions according to the requirements\nPerform project implementation including documentation, coding, testing, training, demonstration\nDocument application development, translating business and user requirements into system requirements\n\nAbout You:\n\nDegree holder in Computing or related discipline\nAt least 6 year's working experience in application / web / backend development\nExperiencing in Web Application / POS System / API Development / DevOps / Docker / Kubernetes / Message Broker will be an advantage but not a must\nCandidates with less experience will be considered as position of Analyst Programmer\n\nWe offer vacancy with below skill set\n\nDevelopment skills in C# (.NET Core and Blazor), HTML 5, CSS 3, Java Scripts, SQL language\nPython / PHP / Node.JS in advance but not a must\n\n\n\nWhat you can get from us\n\nOn-the-job training, learning and development\u00a0provided\nExecutive workshops, interest class, corporate purchase discount offered by SHKP\nCompetitive salary and annual leaves\nFlexible working opportunities\n\nInterested parties, please send full resume with\u00a0expected salary\u00a0and\u00a0available date\u00a0to Human Resources and Administration Department by e-mail or by fax 2111 9459.\n\n(Data collected will be used for recruitment purpose only.)", "employment_types": ["Full Time", "Permanent"], "selling_points": ["Flexible Working Hour", "12 days annual leave", "5 days work"], "locations": ["Kowloon Bay"], "categories": ["Information Technology (IT)", "Application Specialist - Software", "Software Development", "Others"], "post_time": "2022-01-18T01:15:14Z", "salary": {"currency": null, "max": null, "min": null, "period": "monthly", "term": null}, "salary_visible": false, "title_keywords": ["analyst programmer", "senior analyst programmer"], "responsibilities": ["systems", "implementation", "coding", "develop", "testing", "documentation", "application development"], "requirements": {"degrees": ["degree holder"], "majors": [], "languages": [], "language_level": [], "hard_skills": ["documentation", "devops", "pos system", "web"], "soft_skills": [], "languages_combined": []}, "experience_required": {"duration": ["at least 6 year"], "field": ["development"]}}, {"job_id": "100003009053925", "location_code": "hk", "company": "GrammyTech Ltd", "job_title": "System Analyst/ Analyst Programmer (Java/ C# )(up to 50k)", "description": "Our client\u00a0 is looking for System Analyst/ Analyst Programmer for their team (Perm or\u00a0 contract) .\n\nResponsibilities:\n\n\nAnalyse, design and implement multi-tier web application systems\nDevelop data conversion and migration plan and strategies\nConduct requirement and justification studies\n\nRequirements:\n\nBachelor\u2019s degree in Computer Science or related area of study\nMinimum 4 years' experience in project management\u00a0\nExperience in Java or C#.Net programming\u00a0\nExperience in mobile app devlopment will be a big advantage\nParticipate in application development and unit test\nPrepare proper documentation for record purpose and provide support on systems implementation\nGood team player, communication and interpersonal skills\nGood command of both written and spoken English and Chinese\u00a0\n\nInterested parties, please send your full resume in word format together with salary expectation to\u00a0garychoi @grammytech.com\n\n(All data collected would be used for recruitment purposes only)", "employment_types": ["Full Time", "Permanent"], "selling_points": ["Nice working environment", "Bachelor\u2019s degree in Computer Science", "Experience in Java or C#.Net programming"], "locations": ["Not Specified"], "categories": ["Information Technology (IT)", "Application Specialist - Software", "Software Development", "Others"], "post_time": "2022-01-17T07:47:18Z", "salary": {"currency": "HKD", "max": 44999, "min": 30000, "period": "monthly", "term": null}, "salary_visible": true, "title_keywords": ["analyst programmer", "system analyst"], "responsibilities": ["data", "design", "develop", "plan", "application systems", "migration", "analyse"], "requirements": {"degrees": ["degree", "bachelor"], "majors": ["computer science"], "languages": ["english", "chinese"], "language_level": ["good command"], "hard_skills": ["java", "project management", "mobile", "programming", "documentation", "c#"], "soft_skills": ["project management", "good team player", "communication and interpersonal skills"], "languages_combined": [{"language": "english", "language_level": ["good command"]}, {"language": "chinese", "language_level": ["good command"]}]}, "experience_required": {"duration": ["minimum 4 years"], "field": ["project management"]}}, {"job_id": "100003009049407", "location_code": "hk", "company": "Shanghai Commercial Bank Ltd", "job_title": "Programmer, IT System Development (Fresh graduate also welcome)", "description": "Responsibilities:\n\nDevelop programs and perform programming tasks according to the Bank\u2019s established standards\nTest program logic and coded programs, and prepare documentation for production\nTest thoroughly the operations of completed programs and the linkage to other programs\nHandle end-user queries, recurring errors and problems in cases of emergency in production environment\nEnhance development process and support services actively to increase distribution, speed of delivery, quality and service level\n\nRequirements:\n\nDegree holder in Information Technology or related disciplines\nProficiency in various programming languages and development frameworks / tools (Java, C++, Eclipse, Web Services, Oracle/DB2)\nKnowledge of COBOL/CICS and MQ an advantage\nGood understanding of the applications and proficiency in the diagnostics or trouble-shooting tools and procedures\nKeep abreast of the changes in business environment, technology and industry standards\nGood communication skill with logical thinking\nAble to work independently\nFresh graduate will also be considered\n\nAttractive remuneration package will be offered to the right candidates. Interested parties please click \"Apply Now\" to submit your full resume with current and expected salary to the Human Resources Division.\n\nPlease visit us at www.shacombank.com.hk for more information about our Bank.\n\nAll personal data collected will be used for recruitment related purposes strictly in accordance with the Bank's personal data policies, a copy of which will be provided immediately upon request by contacting our Personal Data Compliance Officer. Applicants who are not contacted within two months may consider their applications unsuccessful and the personal data collected from the applicants will be retained for no longer than two years from the date of rejection during which the applicants may be considered for other suitable positions within the Bank.", "employment_types": ["Full Time", "Permanent"], "selling_points": ["Develop programs and perform programming tasks", "Test program logic and coded programs", "Enhance development process and support services"], "locations": ["Kwai Hing"], "categories": ["Banking / Finance", "Others", "Information Technology (IT)", "Software Development", "Others"], "post_time": "2022-01-15T03:50:23Z", "salary": {"currency": null, "max": null, "min": null, "period": "monthly", "term": null}, "salary_visible": false, "title_keywords": ["programmer"], "responsibilities": ["end-user queries", "operations", "support services", "quality", "develop", "recurring errors and problems", "documentation"], "requirements": {"degrees": ["fresh graduate", "degree holder"], "majors": ["related disciplines", "information technology"], "languages": [], "language_level": [], "hard_skills": ["java", "c++", "cics", "programming", "cobol", "web services", "oracle"], "soft_skills": ["business environment", "work independently", "communication skill"], "languages_combined": []}, "experience_required": {"duration": [], "field": []}}, {"job_id": "100003009055941", "location_code": "hk", "company": "Asia Molecular Diagnostics Laboratory Limited", "job_title": "Bioinformatics Officer", "description": "About the positions\n\n\u00a0Asia Molecular Diagnostics Laboratory Limited (AMDL) is looking for a Bioinformatics Officer to join AMDL.\n\n\u00a0As the Bioinformatics Officer, they will perform data analysis and join R&D activities to develop new genetic tests by utilizing cutting-edge sequencing technologies. We aim to build and deploy advanced genetic test technologies to provide high quality testing services to general public in Hong Kong.\n\n\u00a0Candidate will have the opportunity to work in a rapidly growing start up environment and a passionate and mission-oriented group.\n\nJob Highlights\n\n\u00a0\u00a0\u00a0\u00a0\u00a0\u00a0\u00a0\u00a0 Master degree\n\u00a0\u00a0\u00a0\u00a0\u00a0\u00a0\u00a0\u00a0 Working in Unix/Linux environment\n\u00a0\u00a0\u00a0\u00a0\u00a0\u00a0\u00a0\u00a0 Bioinformatics analysis of data generated by Next-generation sequencing (NGS) or other cutting-edge technologies\n\u00a0\u00a0\u00a0\u00a0\u00a0\u00a0\u00a0\u00a0 Building new bioinformatics data analysis pipeline and server\n\nResponsibilities:\n\nConduct different research work at R&D and research collaboration projects\nAssist Bioinformatics Manager/Senior Bioinformatics officer to build and develop bioinformatics analysis pipelines for different NGS research tests\nAssist Bioinformatics Manager/Senior Bioinformatics officer to build new bioinformatics data analysis server (local server and cloud-based server)\nMaintain bioinformatics data analysis servers\nPerform data analysis and QC for all sequencing data\nPrepare summary for analyzed data of research work\nPrepare documents, e.g., SOP, manuals, R&D results summary, publication and etc\n\nRequirements:\n\n\u00a0\u00a0\u00a0\u00a0\u00a0\u00a0\u00a0\u00a0 Master degree in Genetics, Biology, Biochemistry, Biomedical Sciences, Bioinformatics, Computational Biology, Computer Science, Information systems or related field or\n\u00a0\u00a0\u00a0\u00a0\u00a0\u00a0\u00a0\u00a0 Bachelor degree in Genetics, Biology, Biochemistry, Biomedical Sciences, Bioinformatics, Computational Biology, Computer Science, Information systems or related field with 3 years\u2019 experience working in the bioinformatics field in industry or academic areas\n\u00a0\u00a0\u00a0\u00a0\u00a0\u00a0\u00a0\u00a0 Able to work in Unix/Linux environment\n\u00a0\u00a0\u00a0\u00a0\u00a0\u00a0\u00a0\u00a0 Able to use different programming languages: Python, R, Perl, or other languages\n\u00a0\u00a0\u00a0\u00a0\u00a0\u00a0\u00a0\u00a0 Hands-on experience with large-scale genomic data (e.g., WGS, WES, targeted sequencing, etc.) in High-performance computing system would be an advantage\n\u00a0\u00a0\u00a0\u00a0\u00a0\u00a0\u00a0\u00a0 Good interpersonal, presentation and communication skills, and teamwork\n\nOffice location: Hong Kong Science Park, Shatin", "employment_types": ["Full Time", "Permanent"], "selling_points": [], "locations": ["Shatin Area"], "categories": ["Information Technology (IT)", "Others", "Sciences, Lab, R&D", "Research & Development (R&D)"], "post_time": "2022-01-18T03:06:41Z", "salary": {"currency": null, "max": null, "min": null, "period": "monthly", "term": null}, "salary_visible": false, "title_keywords": ["officer"], "responsibilities": ["data", "analysis", "develop", "data analysis", "publication", "maintain", "prepare documents"], "requirements": {"degrees": ["degree", "bachelor", "master degree"], "majors": ["biology", "genetics", "computer science"], "languages": [], "language_level": [], "hard_skills": ["linux", "programming", "python", "r", "perl"], "soft_skills": ["communication skills", "teamwork", "hands-on", "interpersonal", "presentation"], "languages_combined": []}, "experience_required": {"duration": ["3 years"], "field": ["related"]}}, {"job_id": "100003009049280", "location_code": "hk", "company": "Systex Information (H.K.) Ltd", "job_title": "Account Manager / Senior Account Manager", "description": "Job Requirements\u00a0:\n\nHigh Diploma or above in any Disciplines\n2 Years relevant sales working experience in IT related career\n1 Year corporate sales experience with proven track record, preferably in IT industry\nEnergetic, outgoing, self-motivated, hardworking and willing to learn\nStrong Communication, presentation and consultative selling skills, Innovative with an analytical mind\nProficient in computer applications such as MS Word, MS Excel and Chinese word processing\nGood command in English and Chinese\nImmediately available is preferred\nCandidates with more experience can apply for Senior Account Manager\nJob Responsibilities :\n\n\u00a0Handling\u00a0corporate account management and development\nTo meet sales target set by department head and foster business growth\nResponsible for preparing quotations, proposals, negotiating T&Cs and winning customer's contracts\nTo promote a wide range of IT products, services & solutions to commercial and/or institutional customers in Hong Kong\nTo introduce Information Technology product and services / solutions by leveraging expertise from the company and technologies from major global IT vendors\nTo establish and maintain excellent relationship with potential & existing customers\nInterested parties can apply online via jobsDB or send your full resume with expected salary and availability to : 13/F., TAL Building, 49 Austin Road, Kowloon, Hong Kong. (Attn.: Talent Acquisition)", "employment_types": ["Full Time", "Permanent"], "selling_points": ["Account Manager", "Corporate account manager, IT Products & Services", "meet sales target"], "locations": ["Tsim Sha Tsui"], "categories": ["Information Technology (IT)", "Others", "Sales, CS & Business Devpt", "Account Servicing"], "post_time": "2022-01-14T08:22:17Z", "salary": {"currency": null, "max": null, "min": null, "period": "monthly", "term": null}, "salary_visible": false, "title_keywords": ["senior account manager", "account manager"], "responsibilities": ["sales target", "contracts", "management", "maintain"], "requirements": {"degrees": ["high diploma or above"], "majors": ["any disciplines"], "languages": ["english", "chinese"], "language_level": ["good command", "proficient"], "hard_skills": ["ms excel", "chinese word processing", "ms word"], "soft_skills": ["outgoing", "self-motivated", "willing to learn", "innovative", "communication", "analytical mind", "energetic", "presentation", "hardworking"], "languages_combined": [{"language": "english", "language_level": ["good command"]}, {"language": "chinese", "language_level": ["good command", "proficient"]}]}, "experience_required": {"duration": ["2 years", "1 year"], "field": ["related", "corporate sales", "it"]}}, {"job_id": "100003009049291", "location_code": "hk", "company": "Henderson Land Development Company Limited", "job_title": "ASSISTANT IT SYSTEMS SUPPORT OFFICER", "description": "Ref. No.: JDB/HLD20/AITSSO\n\nResponsibilities:\n\nProviding daily operation support of computer systems and administrative tasks\nMonitoring and maintaining computer systems in data centers\nPreparing periodic operation reports\nRepairing and replacing equipment as instructed\nParticipating in testing new systems / technology\nAssisting in ad hoc projects as assigned\n\nRequirements:\n\n\nHigher Diploma or above in IT, Computer Science or related disciplines\nMinimum 2 years\u2019 relevant experience is preferred\nProficiency in Microsoft Office\nKnowledge of MCSE and CCNA is an advantage\nA good team player with analytical and problem solving skills\nSelf-motivated and good interpersonal skills\nGood command of spoken and written English and Chinese\nFresh graduate will also be considered\nAttractive salary and fringe benefits will be offered to the successful candidates. Please apply with full resume by mail to\u00a0Human Resources Department, Henderson Land Development Co. Ltd., 71/F, Two International Finance Centre, 8 Finance Street, Central, Hong Kong\u00a0or by fax at\u00a02905 1855\u00a0or visit our homepage at\u00a0http://www.hld.com\u00a0or\u00a0by clicking \"Apply now\".\n\n(Please quote the ref. no. on letter)\u00a0\n\nPersonal data provided by job applicants will be used for recruitment purpose only.", "employment_types": ["Full Time"], "selling_points": ["Medical Allowance", "Education Allowance", "Free Lunch"], "locations": ["Central"], "categories": ["Information Technology (IT)", "Security", "Network & System", "Others"], "post_time": "2022-01-14T08:23:36Z", "salary": {"currency": null, "max": null, "min": null, "period": "monthly", "term": null}, "salary_visible": false, "title_keywords": ["officer", "assistant"], "responsibilities": ["maintaining", "data", "monitoring", "daily operation", "computer systems", "systems", "testing", "reports", "ad hoc projects", "administrative tasks", "replacing"], "requirements": {"degrees": ["higher diploma or above", "fresh graduate"], "majors": ["related disciplines", "it", "computer science"], "languages": ["english", "chinese"], "language_level": ["good command"], "hard_skills": ["mcse", "problem solving skills", "ccna", "microsoft office"], "soft_skills": ["analytical and problem solving skills", "good team player", "interpersonal skills", "self-motivated"], "languages_combined": [{"language": "english", "language_level": ["good command"]}, {"language": "chinese", "language_level": ["good command"]}]}, "experience_required": {"duration": ["minimum 2 years"], "field": ["relevant experience"]}}, {"job_id": "100003009051428", "location_code": "hk", "company": "J&C Employment Consultant", "job_title": "Scrum Master (JC012)", "description": "Responsibilities\n\nCoach\u00a0the team in self-organization and cross-functionality\nRemoving impediments to the team\u2019s progress\nFind techniques for effective Product Goal definition and Product Backlog management\nEnsuring that all Scrum events take place and are positive, productive, and kept within the timebox\nHelp\u00a0the Team understand the need for clear and concise Product Backlog items\nHelp\u00a0establish empirical product planning for a complex environment\nFacilitating stakeholder collaboration as requested or needed\nLeading, training, and coaching the organization in its Scrum adoption\nPlanning and advising Scrum implementations within the organization\n\nRequirements\n\nDegree in Computer Science or relevant disciplines\n6+ years\u2019\u00a0Information Technology related experience\n2 years\u2019 experience with agile development using Scrum\nScrum Master, should obtained scrum master certification (such as Profession Scrum Master I or above, or equivalent)\nSound experience in Lean-agile software and systems development at scale.\nAble to track and report progress to management with Agile Management tools and methodology\nImmediate available is a plus\n\n\u00a0If this is a role for you, please apply now by sending your resume (in MS WORD format) with your expected salary to us via our company email\u00a0:\u00a0info @ jncemployment.com\u00a0or click \"APPLY NOW\"\n**Due to the volume of applicants, only shortlisted candidates will be contacted.**\nThe information provided by applicants will be used for employment related purpose only. All applications will be treated in strict confidence and used exclusively for recruitment purposes.", "employment_types": ["Full Time", "Permanent"], "selling_points": ["scrum master certification", "agile development using Scrum", "Information Technology related experience"], "locations": ["Kwun Tong"], "categories": ["Information Technology (IT)", "IT Project Management / Team Lead", "IT Management", "Others"], "post_time": "2022-01-15T16:24:01Z", "salary": {"currency": null, "max": null, "min": null, "period": "monthly", "term": null}, "salary_visible": false, "title_keywords": [], "responsibilities": ["management", "planning"], "requirements": {"degrees": ["degree", "master"], "majors": ["computer science"], "languages": [], "language_level": [], "hard_skills": ["ms word", "lean", "agile", "plus"], "soft_skills": ["confidence", "agile"], "languages_combined": []}, "experience_required": {"duration": ["6+ years", "2 years"], "field": ["related", "development", "information technology"]}}, {"job_id": "100003009053044", "location_code": "hk", "company": "PeopleLink Services Limited", "job_title": "Operation Support Engineer / Network Operation Engineer (On Job training will be provided)", "description": "Job Description:\u00a0\n\nProvide operation support in Data Centre / Network Operation Center\nConducting routine system health check; producing performance reports\nTo inspect, test and troubleshooting for system or servers' issue\nFollow procedures, instructions and checklists to complete tasks with good quality\nEnsure all client requests and other ad-hoc duties are processed in an efficient and timely manner\n\nJob Requirement\u00a0\u00a0\n\nHKCEE/ DSE or above.\u00a0 IT-related qualification is an advantage\u00a0\u00a0\nKnowledge of Windows / Linux / Networking will be an advantage\nGood communication and interpersonal skills\nFresh\u00a0graduate are welcome to apply\n\nPlease submit your resume with current and expected salary. All applications will be treated strictly confidential for recruitment purpose only. Un-selected candidates will be considered for other vacancies.", "employment_types": ["Full Time", "Permanent", "Contract"], "selling_points": ["Data Center, Network Operation", "System and Network Monitoring", "Training provided"], "locations": ["Not Specified"], "categories": ["Information Technology (IT)", "Support", "Network & System", "Others"], "post_time": "2022-01-17T05:21:23Z", "salary": {"currency": null, "max": null, "min": null, "period": "monthly", "term": null}, "salary_visible": false, "title_keywords": ["engineer", "operation support"], "responsibilities": ["performance reports", "data", "quality", "procedures", "troubleshooting", "ad-hoc duties"], "requirements": {"degrees": ["fresh graduate", "dse"], "majors": [], "languages": [], "language_level": [], "hard_skills": ["linux"], "soft_skills": ["communication and interpersonal skills"], "languages_combined": []}, "experience_required": {"duration": [], "field": []}}, {"job_id": "100003009054635", "location_code": "hk", "company": "The Hong Kong University of Science and Technology", "job_title": "Assistant Officer (Kellogg-HKUST EMBA Program)(Job ID: 7069)", "description": "Job Title:\u00a0\u00a0\u00a0\u00a0\u00a0\u00a0\u00a0\u00a0\u00a0\u00a0Assistant Officer (Kellogg-HKUST EMBA Program)\nDepartment:\u00a0\u00a0\u00a0\u00a0School of Business and Management\nJob ID:\u00a0 \u00a0 \u00a0 \u00a0 \u00a0 \u00a0 \u00a07069\n\nJob Posting Details\n\nThe Kellogg-HKUST EMBA Program team is looking for an individual for the position of Assistant Officer.\u00a0 The appointee will render administrative support to the Kellogg-HKUST Executive MBA Program team.\u00a0 Duties include collating course materials; managing databases; preparing mailings; handling enquiries; managing classroom facilities; and performing other duties as assigned.\n\nApplicants should have a higher diploma or an associate degree with at least 1-2 years of work experience.\u00a0 Degree holders are also welcome to apply.\u00a0 Candidates should have good communication and interpersonal skills, and knowledge in Microsoft Office.\u00a0 The ability to perform multi-tasks is preferred.\u00a0 A good command of written and spoken English and fluency in Cantonese are required.\u00a0 Working outside normal office hours and during weekends will be expected. (Duration: 2 years, renewable)\n\nStarting salary will be commensurate with qualifications and experience. \u00a0Fringe benefits including annual leave, medical and dental benefits will be provided.\u00a0 A gratuity will be payable upon successful completion of contract.\n\nApplication Procedure\nIn support of a green work environment, we accept applications submitted online only.\u00a0 To apply, please complete an online application form through the HKUST Careers website (https://hkustcareers.ust.hk) and return it online to the Human Resources Office on or before Monday, 31 January 2022.\u00a0 Applicants will receive an acknowledgement by email upon successful submission.\u00a0 We thank applicants for their interest, but advise that only shortlisted candidates will be notified of the result of the application.\n\n(Information provided by applicants will be used for recruitment and other employment-related purposes only.)\n\nHKUST is an equal opportunities employer and is committed to our core values of\ninclusiveness, diversity, and respect.", "employment_types": ["Full Time"], "selling_points": ["collating course materials", "managing databases; preparing mailings", "handling enquiries; managing classroom facilities"], "locations": ["Sai Kung"], "categories": ["Admin & HR", "Clerical / Admin Staff", "Education", "Others", "Information Technology (IT)", "Others"], "post_time": "2022-01-17T10:21:05Z", "salary": {"currency": null, "max": null, "min": null, "period": "monthly", "term": null}, "salary_visible": false, "title_keywords": ["assistant officer"], "responsibilities": ["management", "other duties", "administrative support", "communication", "databases"], "requirements": {"degrees": ["associate degree", "diploma", "degree"], "majors": [], "languages": ["cantonese", "english"], "language_level": ["fluency", "good command"], "hard_skills": ["id", "databases", "microsoft office"], "soft_skills": ["communication and interpersonal skills", "multi-tasks"], "languages_combined": [{"language": "cantonese", "language_level": ["good command"]}, {"language": "english", "language_level": ["fluency", "good command"]}]}, "experience_required": {"duration": ["at least 1-2 years"], "field": []}}, {"job_id": "100003009053606", "location_code": "hk", "company": "PERSOLKELLY Hong Kong Limited", "job_title": "Java Developer (Banking)", "description": "Our client a one of the largest banks in Asia is looking for a\u00a0high caliber professional to join their team\n\nResponsibilities:\n\nResponsible for applications development, maintenance and production support\nPrepare for project requirement clarification and discussion with users\nIdentifying options for potential solutions and assessing them for both technical and business suitability\nKeen interest in Financial Products, Open-Source stack, Agile and Continuous Delivery\nExperience on Kotlin, Akka, Groovy will be advantageous.\nSQL/Database knowledge\nAny messaging knowledge [JMS, KAFKA]\nHTML5, Angular2, CSS, JavaScript [ES6] & Other Front-End Technologies\nResponsive Design, Cross-Platform [Web & Mobile], Cross-Browser Environment compatibility, Object-Oriented Design, Web Services (REST)\n\nRequired Experience:\n\nAt least 1 year experience in Java, Spring Boot, Knowledge in RDBMS (e.g. MariaDB), REST-Based APIs\nPreferable to have knowledge in Private Cloud platform (Openshift, Kubernetes, Docker)\nFamiliar with Agile practice\nEstablish DevOps with Continuous integration and Release automation\n\nTo apply for this position, please send your full resume to contract_hk @persolkelly.com in word format indicating the job title.\u00a0\n\nIf you are not contacted by our consultants within 2 weeks, please consider your application unsuccessful. All applications will be treated in strict confidence and used for recruitment purposes only in accordance with PERSOLKELLY Hong Kong Limited's Privacy Notice.", "employment_types": ["Full Time"], "selling_points": ["Bachelor Degree in Computer Science or related", "1 year experience in Java, Spring", "Familiar with Agile practice"], "locations": ["Central & Western Area"], "categories": ["Information Technology (IT)", "Application Specialist - Software", "Software Development", "Others"], "post_time": "2022-01-17T07:32:07Z", "salary": {"currency": null, "max": null, "min": null, "period": "monthly", "term": null}, "salary_visible": false, "title_keywords": ["developer"], "responsibilities": ["maintenance", "clarification", "design", "recruitment", "database"], "requirements": {"degrees": [], "majors": [], "languages": [], "language_level": [], "hard_skills": ["java", "groovy", "agile", "maintenance", "devops", "word", "sql", "web & mobile", "javascript", "spring", "integration", "css", "kotlin", "web services"], "soft_skills": ["confidence", "agile", "responsible", "keen", "responsive"], "languages_combined": []}, "experience_required": {"duration": ["at least 1 year"], "field": []}}, {"job_id": "100003009051051", "location_code": "hk", "company": "The Wharf Group", "job_title": "IT Support", "description": "Responsibilities\n\nPerform daily technical support on desktop, network, system, software and hardware\nSet up computers and install software for various applications and programs\nProvide helpdesk support and solutions to users\nHandle helpdesk documentation and reporting, liaise with relevant parties to troubleshoot and report on problems and incidents\nWork on staggered hours to provide proper user support\u00a0\nTimely respond and handle urgent business requests during normal and non-office hours with company-assigned facilities including phone and laptop\n\nRequirements\n\nDiploma or above in Computer Science or related disciplines with MCSE / CCNA qualification preferred\nAt least 1 year\u2019s experience in supporting MS Windows\u00a0and\u00a0Office applications and desktop hardware\nExperience in LAN, H3C and CISCO equipment support is preferred\nSelf-motivated,\u00a0hardworking with good interpersonal and task management skills\nWell organized and able to work independently\u00a0under pressure and tight deadlines\nGood command of spoken and written English and Chinese\n\n\nWe work 5 days per week.\n\nInterested parties, please click \"APPLY NOW\" and attach with your application letter and full resume.\u00a0\n\nFor further information of the Wharf Group, please visit our website: www.wharfholdings.com\u00a0\n", "employment_types": ["Full Time", "Permanent"], "selling_points": [], "locations": ["Tsim Sha Tsui"], "categories": ["Information Technology (IT)", "Support", "Network & System", "Others"], "post_time": "2022-01-15T19:11:47Z", "salary": {"currency": null, "max": null, "min": null, "period": null, "term": null}, "salary_visible": false, "title_keywords": ["it support"], "responsibilities": ["reporting", "software", "technical support", "hardware", "liaise with", "troubleshoot", "documentation", "report"], "requirements": {"degrees": ["diploma or above"], "majors": ["related disciplines", "computer science"], "languages": ["english", "chinese"], "language_level": ["good command"], "hard_skills": ["mcse", "ms windows", "ccna", "office applications", "hardware"], "soft_skills": ["self-motivated", "work independently", "under pressure", "well organized", "interpersonal", "hardworking"], "languages_combined": [{"language": "english", "language_level": ["good command"]}, {"language": "chinese", "language_level": ["good command"]}]}, "experience_required": {"duration": ["at least 1 year"], "field": []}}, {"job_id": "100003009055374", "location_code": "hk", "company": "Hong Kong Aircraft Engineering Co Ltd", "job_title": "Group IT Manager, Infrastructure & Architecture", "description": "Scope of Duties:\u00a0\n\nLead the development and regular review of the Group IT Policies.\nLead the development and implementation of the Group IT Infrastructure Strategy\nFormulate the IT Infrastructure and integration platform according to the business needs, taking into account scalability and security requirements of the Digital Solutions portfolio.\nEnsure systems availability and performance meets the agreed service levels.\nManage IT budgets\nStrategic Direction and Standards for IT \u2013 Contribute to the development of Group IT Infrastructure strategy. Lead the Group IT Policies development and align the architectural standards to achieve business benefits and cost effectiveness.\nIT Infrastructure Ownership \u2013 Maintain currency on new technologies and platforms. Provides direction on what emerging infrastructure & technologies should be introduced to the group.\nSolution Formulation and Delivery \u2013 Oversee the end-to-end IT Infrastructure solution delivery and subsequent solution support. Ensure solutions are fit for purpose leveraging existing capabilities where possible.\nIT Services Management - Ensure effective management of IT infrastructure facilities and IT supporting services in accordance with agreed service levels and schedules.\nTeam Leadership and Management \u2013 Build and manage a team with a core set of skills for installed and future technologies. Develop, motivate, coach staff to achieve performance excellence.\u00a0\nFinancial Management \u2013 Provide good quality information and analysis for the IT budgeting and planning process; control actual IT Costs to meet operating budgets.\n\nRequirements:\u00a0\n\nA minimum of 12 years of IT Infrastructure and systems integration experience with 6 years of management experience\nTertiary qualifications\nProven experience in managing a team of technology professionals (including in-house, external, off-shore resources) to run strategic IT projects and support IT systems\nAbility to listen and articulate ideas to a broad range of audiences\nStrong interpersonal skills; promoting healthy relationships and team dynamics\nWell-developed analytical, problem-solving, and decision-making skills\nFocus on customer\u2019s needs; ability to set expectations and understand end user behavior\nProven technical management experience of working in a complex IT Infrastructure environment\nDemonstrated leadership and relationship management experience and skills\nDemonstrated ability to lead and motivate staff and to apply skills and techniques to solve dynamic problems\nStrong teamwork and interpersonal skills at all management level\n\nHow to Apply:\n\nPlease send your resume with expected salary, quoting the employer's reference no., to: Human Resources Department - Talent & Partnership Team, Hong Kong Aircraft Engineering Company Limited, 80 South Perimeter Road, Hong Kong International Airport, Lantau, Hong Kong OR submit your application via\u00a0https://careers.haeco.com/hkg/job-openings/\n\nCandidates not contacted 4-6 weeks after submission of applications and/or interviews may consider their application unsuccessful.\n\nAll information provided by candidates will be treated in strict confidence and will be used for employment purpose only.", "employment_types": ["Full Time", "Permanent"], "selling_points": ["A minimum of 12 years of IT Infrastructure", "6 years of management experience", "Ability to listen and articulate ideas"], "locations": ["Airport Area"], "categories": ["Information Technology (IT)", "IT Management", "Network & System", "Others"], "post_time": "2022-01-18T02:24:29Z", "salary": {"currency": null, "max": null, "min": null, "period": "monthly", "term": null}, "salary_visible": false, "title_keywords": ["it manager"], "responsibilities": ["budgets", "it infrastructure", "systems", "implementation", "it policies", "regular review"], "requirements": {"degrees": [], "majors": [], "languages": [], "language_level": [], "hard_skills": [], "soft_skills": [], "languages_combined": []}, "experience_required": {"duration": [], "field": []}}, {"job_id": "100003009054752", "location_code": "hk", "company": "Public Finance Limited", "job_title": "Help Desk Support (Shift)", "description": "Responsibilities:\n\nPerform help desk support and computer operation duties such as trouble-shooting, PC operation, file backup, distribution of reports, etc.\n\nRequirements\n\nSecondary education with technical or vocational training\n1-2 year\u2019s relevant working experience preferred\nWilling to perform shift duties\nSelf-motivated, good communication and interpersonal skills\nAble to work independently\nBenefits\nDouble Pay\nDiscretionary Bonus\nInsurance Benefits\nStudy subsidy\n\nApplication Method:\n\nBy Whatsapp : 9309 2925\n\nBy E-mail via \"Apply Now\"\n\nPersonal data collected will be treated in the strictest confidence in accordance with our\u00a0Personal Information Collection Statement\u00a0and\u00a0Privacy Policy\u00a0and will be handled by authorized personnel for recruitment-related purposes only. All applications will be kept for a maximum period of one year as may be considered for other suitable positions within Public Finance Ltd. and its associated companies. For details, please visit the Company\u2019s website\u00a0http://www.publicfinance.com.hk", "employment_types": ["Full Time", "Permanent"], "selling_points": [], "locations": ["Not Specified"], "categories": ["Information Technology (IT)", "Support", "Network & System", "Others"], "post_time": "2022-01-17T10:53:51Z", "salary": {"currency": null, "max": null, "min": null, "period": "monthly", "term": null}, "salary_visible": false, "title_keywords": [], "responsibilities": ["reports"], "requirements": {"degrees": ["secondary education"], "majors": [], "languages": [], "language_level": [], "hard_skills": [], "soft_skills": ["self-motivated", "communication and interpersonal skills", "work independently"], "languages_combined": []}, "experience_required": {"duration": ["1-2 year"], "field": ["relevant working experience"]}}, {"job_id": "100003009054590", "location_code": "hk", "company": "Hong Kong Applied Science and Technology Research Institute Company Limited (ASTRI)", "job_title": "Senior Engineer (PI) / Engineer (PI), Automation", "description": "Reference #:\u00a02022/ARD/274/a-b\n\nJob Responsibilities\n\nAssist in ITF R&D project as assigned\nResearch and Evaluate State-of-the-Art Robotic Systems\nDevelop Mechanical Systems for Applications in Robotics and Automation\n\nRequirements\n\nGraduate in STEM-related discipline such as Mechanical Engineering, Mechanical and Automation Engineering, Aerospace Engineering or relevant disciplines\nA bachelor\u2019s degree, master\u2019s degree or a doctoral degree\u2019s holder is welcome to apply\nFor bachelor\u2019s degree holder, they will be considered for the position of Engineering Associate (PI)\nExperience in using AutoCAD, Solidworks, Matlab and Labview.\nExperience in programming using Java, C/C++ and Python.\nExperience in Mill, Lathe, 3D Printing, Laser Printing, Water Jet.\nExperience in Systems Development Life Cycle is a plus.\nApplication\n\nTo apply, by clicking 'APPLY NOW'\u00a0\u00a0with your resume, you must quote the\u00a0Job Ref\u00a0and include the following information:\n\nName of University\nDegree obtained/expecting and when\nHave you participated in ITF Research Talent Hub before? Yes/No\nIf you answer Yes in item 3, please state the period\nHave you been employed by ASTRI before? If yes, please state the period\n\nThe resume should\u00a0not\u00a0include any sensitive personal information such as HKID or passport number, photo, etc.\n\nThe application will be open until the position is filled. Only short-listed candidates will be notified. ASTRI reserves the right not to fill the position.\n\nASTRI is an Equal Opportunities Employer. Personal data provided by job applicants will be used\u00a0exclusively\u00a0for recruitment\u00a0only. For details, please refer to\u00a0Privacy - ASTRI - Hong Kong Applied Science and Technology Research Institute Company Limited,\u00a0in particular section 9.", "employment_types": ["Full Time"], "selling_points": ["Robotic Systems", "Automation", "Mechanical Engineering"], "locations": ["Shatin Area"], "categories": ["Information Technology (IT)", "Others"], "post_time": "2022-01-17T10:09:33Z", "salary": {"currency": null, "max": null, "min": null, "period": "monthly", "term": null}, "salary_visible": false, "title_keywords": ["senior engineer", "engineer"], "responsibilities": ["evaluate", "systems", "robotics", "develop"], "requirements": {"degrees": ["degree holder", "degree", "bachelor", "master"], "majors": ["engineering"], "languages": [], "language_level": [], "hard_skills": ["java", "plus", "no", "labview", "c++", "c", "programming", "matlab", "python", "solidworks", "autocad"], "soft_skills": ["sensitive"], "languages_combined": []}, "experience_required": {"duration": [], "field": ["development", "programming"]}}, {"job_id": "100003009054673", "location_code": "hk", "company": "IT Solutions Ltd.", "job_title": "Linux System Administrator - Government Department (T25 Contract)", "description": "Smart Manufacturing Division\nRef:\u00a0SMD409/21,\u00a04866/JDB/040122\nJob Description\nWho we are looking for:\nCreativity in new ideas and future focus vision.\u00a0\nCollaboration with colleagues and the community at large.\nWork Smart, Play Smart!\nWhat you'll do:\nTo provide industrial consultancy services and implement government-funded and consultancy projects on Industry 4.0 (i4.0), intelligent manufacturing and reindustrialization related smart enabling solutions adoption, such as Digital Lean, Machine Connectivity via IIoT, Human Machine interface (HMI), Smart Data Analytics, Cyber Physical Production System (CPPS), etc.\nTo formulate government project proposals on i4.0 enabling technology development, reindustrialization, manufacturing upgrading and industrial applications.\nTo conduct R&D work in development of i4.0 enabling technology solution such as Blockchain, Industrial Drone, Smart Logistics, Sensor applications\nOrganize and deliver training and marketing activities such as overseas study missions, international conferences, technical seminars, workshops, etc.\nTo travel over GBA on a regular basis for consultancy projects\nYou'll be a good fit if you have/are:\nBachelor Degree from engineering disciplines such as Industrial and System Engineering, Manufacturing Engineering, Data/Computer Science, or equivalent. Candidate with top up master degree on Information and Communication Technology preferred\nAt least two years\u2019 or more relevant experience in manufacturing operations, particularly in the technical area of digital manufacturing knowledge/solutions\nSounds knowledge on i4.0, intelligent manufacturing, reindustrialization, advanced digital tools and enabling technologies for digital manufacturing a definitely advantage\nStrong commitment to task outcome, mature, independent, self-initiated, proactive and good team player\nExcellent analytical, presentation, communication and interpersonal skills\nExcellent command of English, Cantonese and Putonghua\nNote:\nApplicant may be considered for other positions if not matching the requirements of the subject position.\nWhat we offer and What you\u2019ll like here:\nInnovative and energetic culture with smart outfits and sport shoes\nProfessional lab and latest technology to actualize your creative ideas\n5-day work week\u00a0\nPrime location with good public transport network\nMPF Top-up and dental benefit\nMedical benefits from Day-1 with extended coverage to dependent(s)\nProfessional training and career advancement opportunities\nApply now if you\u2019re ready to take the challenge! \u00a0Do not miss this opportunity to join us to Create Value and \u201cMAKE SMART SMARTER\u201d!\u00a0\u00a0\nHKPC will take into consideration both the quantitative and qualitative requirements of the position when selecting the suitable candidates.\u00a0 A competitive salary package commensurate with academic qualifications and experience will be offered.\u00a0\nApplicants are welcome to\u00a0submit application\u00a0at the HKPC e-Recruitment System (careers.hkpc.org) in 1\u00a0week\u00a0from the posting date.\u00a0 Recruitment will continue until the position is filled.\u00a0\u00a0\nPersonal data collected will be used for recruitment purpose only. Candidates not invited for interviews within 6 weeks may consider their applications unsuccessful and the applications will be disposed by HKPC within 12 months.", "employment_types": ["Full Time", "Contract"], "selling_points": ["Salary up to $45K", "Work on Large Enterprise Infrastructure", "Contract till: Jan 2023"], "locations": ["Not Specified"], "categories": ["Information Technology (IT)", "Support", "Network & System", "Others"], "post_time": "2022-01-17T10:30:13Z", "salary": {"currency": null, "max": null, "min": null, "period": "monthly", "term": null}, "salary_visible": false, "title_keywords": ["system administrator"], "responsibilities": ["ideas", "data", "operations", "communication", "conferences", "logistics"], "requirements": {"degrees": ["degree", "bachelor", "master degree"], "majors": ["system engineering", "manufacturing", "engineering", "computer science"], "languages": ["cantonese", "putonghua", "english"], "language_level": ["excellent"], "hard_skills": ["r&d", "blockchain", "lean", "data analytics", "workshops", "focus"], "soft_skills": ["good team player", "independent", "advanced", "mature", "communication", "communication and interpersonal skills", "work smart", "focus", "proactive", "presentation"], "languages_combined": [{"language": "cantonese", "language_level": ["excellent"]}, {"language": "putonghua", "language_level": ["excellent"]}, {"language": "english", "language_level": ["excellent"]}]}, "experience_required": {"duration": ["at least two years"], "field": ["digital", "manufacturing", "relevant experience"]}}, {"job_id": "100003009049615", "location_code": "hk", "company": "ESD Services Limited (ESDlife)", "job_title": "Cloud Engineer", "description": "You will:\n\n\nCapability to deploy and configue proposed architecture\nManage Cloud resources and services\nTroubleshoot operation issues and incidents\nCooperate with development team on Cloud integration and optimization\nFulfill DevOps flow of the team\nDocumentation / R&D / POC of services on Clouds\n\nYou should have/be:\n\n\nBachelor's degree or above in Computer Science or related disciplines\u2002\u2002\u2002\u2002\u2002\n2+ years of public / private / hybrid Cloud experience\nAny Cloud certification (i.e. AWS, Azure) is highly preferred\nExperience with container (i.e. ECS, AKS, OpenShift, K8S), auto-scaling, HA would be an advantage\nExperience with Cloud CI / CD automations (i.e. Terraform, GitFlow, pipeline) would be an advantage\nExperience in handling networking or security product is a plus\nSelf-motived and able to work under pressure\nWilling to learn\n\nIn addition, you will be able to:\u00a0\n\nAn attractive and competitive remuneration package;\nReceive training and development opportunities\n\nSalary and benefit will commensurate with qualifications and experience.\u00a0\u00a0Interested party, please send in your\u00a0full resume and expected salary\u00a0by clicking the button\u00a0\u2018APPLY NOW\u2019.\n\u00a0\nTo know more about us, please visit our website\nhttps://corporate.esdlife.com\nhttps://ds.esdlife.com/\n\n\nWe are an equal opportunity employer and welcome applications from all qualified candidates. The information provided will be treated in strict confidence and used only for consideration of application for relevant/similar post(s) within the Hutchison Group of Companies.\n\nApplicants not having heard from us within four weeks from the date of this advertisement may consider their application unsuccessful. All personal data of unsuccessful applicants will be destroyed after the recruitment exercise when no longer required.", "employment_types": ["Full Time", "Permanent"], "selling_points": [], "locations": ["Hung Hom"], "categories": ["Information Technology (IT)", "Support", "Network & System", "Others"], "post_time": "2022-01-14T08:58:20Z", "salary": {"currency": null, "max": null, "min": null, "period": "monthly", "term": null}, "salary_visible": false, "title_keywords": ["engineer"], "responsibilities": ["website", "recruitment", "troubleshoot", "deploy", "documentation", "personal data", "architecture", "cooperate with", "work under pressure"], "requirements": {"degrees": ["degree or above", "bachelor"], "majors": ["related disciplines", "computer science"], "languages": [], "language_level": [], "hard_skills": ["r&d", "plus", "documentation", "azure", "no", "devops", "aws", "container", "integration"], "soft_skills": ["confidence", "willing to learn", "troubleshoot", "work under pressure"], "languages_combined": []}, "experience_required": {"duration": ["2+ years"], "field": ["security"]}}, {"job_id": "100003009053060", "location_code": "hk", "company": "OCBC Wing Hang Bank Limited", "job_title": "Fintech Intern, Digital Projects (12 months contract from Jul 2022 to Jun 2023)", "description": "Responsibilities\n\u200bAssist business and IT teams to gather requirements and define project scope\nAssist to identify functional impacts to front-to-back systems due to the gathered business and regulatory requirements\nAssist to analyse the business requirements to determine technology needs\nAssist to document fact-findings and results, design new process for delighted customer experience (CX) and specify system changes\nRequirements\n\u200bPostgraduate or 3rd year in Computing Science or e-commerce or related subject\nExperience in digital solution is a plus\nKnowledge in online collaboration tools (e.g. Jira, confluence, inVision), UML, HTML5, Xcode, Android and Business Process Model and Notation (BPMN) would be an advantage\nGood command of written and spoken English\nSpeaking in Cantonese is preferred\nDigital initiatives solutioning (mobile, internet or other banking products)\nIndependent and self-initiative\nAttractive remuneration package will be offered to the right candidate.\u00a0 Please apply with full resume stating present & expected salary and contact phone number\u00a0to\u00a0The Human Resources Manager, 10/F, 161 Queen\u2019s Road Central, Hong Kong.\u00a0Please quote the reference.\n\n\nPersonal data collected will be used for recruitment purpose only.\u00a0 For more information, please visit our website:\u00a0http://www.ocbcwhhk.com.", "employment_types": ["Temporary", "Contract"], "selling_points": ["\u200bAssist business and IT teams", "Digital / e-Banking initiatives", "Knowledge in online collaboration tools"], "locations": ["Shau Kei Wan"], "categories": ["Information Technology (IT)", "Application Specialist - Software", "Application Specialist - Network", "Others"], "post_time": "2022-01-17T05:30:40Z", "salary": {"currency": null, "max": null, "min": null, "period": "monthly", "term": null}, "salary_visible": false, "title_keywords": ["intern"], "responsibilities": ["regulatory requirements", "systems", "teams", "design", "system changes", "analyse"], "requirements": {"degrees": [], "majors": [], "languages": ["cantonese", "english"], "language_level": ["good command"], "hard_skills": ["mobile", "plus", "android", "e-commerce"], "soft_skills": ["independent", "self-initiative"], "languages_combined": [{"language": "cantonese", "language_level": []}, {"language": "english", "language_level": ["good command"]}]}, "experience_required": {"duration": [], "field": ["digital"]}}, {"job_id": "100003009048591", "location_code": "hk", "company": "CITIC Telecom International Holdings Limited", "job_title": "IT Security Specialist", "description": "Responsibilities:\u00a0\n\n\nDevelop and maintain IT security policies and guideline\nMain focal point for all IT security related technical matters\nWork with IT and other departments on the practical application of information security and data privacy\nDrive and provide internal IT security guideline to ensure delivery of an effective information security and data privacy framework in a corporate level; enabling control of risks and network protection in an aligned manner\nMonitor news or feeds to proactively deploy policy and inform platform owners and users\nDevelop and validate baseline security configuration for operating system, application, networking and security equipment\nLead and manage various security related projects and handle ad hoc tasks as assigned by management\n\nRequirements:\u00a0\n\nBachelor Degree in Computer Science or related disciplines\nMinimum 5 years\u2019 related experience in information security or data privacy\nCertification in Information Security is preferable (e.g. CISM, CISA or CISSP)\nKnowledge of information security best practices, such as PCI DSS or Secure SDLC preferred\nSound track record of project management experience and proficient in IT risk management, IT risk auditing and compliance\nExperience in security incident management\nHands on experience in IT security solutions such as SIEM, DLP, IPS, end point security, patch management and hardening\nGood communication skill for delivering information security/data privacy message to both technical and non-technical audience, up to management level\nGood command in both spoken and written English and Chinese (Cantonese & Mandarin)\n\nFringe Benefits:\n\nOn-the-job training\nDouble pay\nAttractive performance bonus\nTransportation allowance\nMedical & dental insurance\nFree meals\nFree shuttle bus service\nTraining subsidies\nStaff discount\n\nWe offer competitive salary and benefit package including double pay, medical and dental benefits, 5-day work, 14 days paid annual leave and free shuttle bus service to the capable candidate. If you are interested, please immediately send your application stating\u00a0your current & expected salary and date availability with full resume\u00a0to\u00a0Human Resources Department\u00a0by email by clicking \"Apply Now\". Please clearly indicate the applied position and reference number on your application.\n\nAll personal data received will be treated strictly confidential and will be used for employment related purpose only.", "employment_types": ["Full Time", "Permanent"], "selling_points": ["Develop and maintain IT security policies", "Main focal point for IT security related matters", "Double Pay, Bonus, 5-day work, Medical & Dental"], "locations": ["Kwai Fong"], "categories": ["Information Technology (IT)", "IT Management", "Security", "Others"], "post_time": "2022-01-14T06:52:06Z", "salary": {"currency": null, "max": null, "min": null, "period": "monthly", "term": null}, "salary_visible": false, "title_keywords": ["specialist"], "responsibilities": ["control", "management", "information security", "data", "configuration", "policies", "monitor", "ad hoc tasks", "develop", "maintain", "deploy"], "requirements": {"degrees": ["degree", "bachelor"], "majors": ["related disciplines", "computer science"], "languages": ["cantonese", "english", "chinese", "mandarin"], "language_level": ["good command"], "hard_skills": ["project management", "sdlc"], "soft_skills": ["communication skill", "project management", "hands on"], "languages_combined": [{"language": "cantonese", "language_level": ["good command"]}, {"language": "english", "language_level": ["good command"]}, {"language": "chinese", "language_level": ["good command"]}, {"language": "mandarin", "language_level": ["good command"]}]}, "experience_required": {"duration": ["minimum 5 years"], "field": ["risk management", "management", "related", "compliance", "project management", "it", "security"]}}, {"job_id": "100003009054606", "location_code": "hk", "company": "Hong Kong Applied Science and Technology Research Institute Company Limited (ASTRI)", "job_title": "Senior Engineer (PI) / Engineer (PI), Software Development", "description": "Reference #:2022/ARD/274/c-d\n\nJob Responsibilities\n\nAssist in ITF R&D project as assigned\nResearch and Evaluate State-of-the-Art Robotic Systems\nDevelop Software Systems for Applications in Robotics and Automation\n\nRequirements\n\nGraduate in STEM-related discipline such in Computer Science, Computer Engineering, Electronic Engineering, Information Engineering, Systems Engineering or relevant disciplines\nA bachelor\u2019s degree, master\u2019s degree or a doctoral degree\u2019s holder is welcome to apply\nFor bachelor\u2019s degree holder, they will be considered for the position of Engineering Associate (PI)\nExperience in programming using Java, C/C++ and Python.\nExperience in Data Structure and Algorithms development.\nExperience in Linux and Docker application development.\nExperience in Systems Development Life Cycle is a plus.\nApplication\n\nTo apply, by clicking 'APPLY NOW'\u00a0\u00a0with your resume, you must quote the\u00a0Job Ref\u00a0and include the following information:\n\nName of University\nDegree obtained/expecting and when\nHave you participated in ITF Research Talent Hub before? Yes/No\nIf you answer Yes in item 3, please state the period\nHave you been employed by ASTRI before? If yes, please state the period\n\nThe resume should\u00a0not\u00a0include any sensitive personal information such as HKID or passport number, photo, etc.\n\nThe application will be open until the position is filled. Only short-listed candidates will be notified. ASTRI reserves the right not to fill the position.\n\nASTRI is an Equal Opportunities Employer. Personal data provided by job applicants will be used\u00a0exclusively\u00a0for recruitment\u00a0only. For details, please refer to\u00a0Privacy - ASTRI - Hong Kong Applied Science and Technology Research Institute Company Limited,\u00a0in particular section 9.", "employment_types": ["Full Time"], "selling_points": ["Software Development", "Robotic", "Automation"], "locations": ["Shatin Area"], "categories": ["Information Technology (IT)", "Others"], "post_time": "2022-01-17T10:13:33Z", "salary": {"currency": null, "max": null, "min": null, "period": "monthly", "term": null}, "salary_visible": false, "title_keywords": ["senior engineer", "engineer"], "responsibilities": ["robotics", "software", "systems", "develop", "evaluate"], "requirements": {"degrees": ["degree holder", "degree", "bachelor", "master"], "majors": ["engineering"], "languages": [], "language_level": [], "hard_skills": ["linux", "java", "plus", "no", "c++", "c", "programming", "python"], "soft_skills": ["sensitive"], "languages_combined": []}, "experience_required": {"duration": [], "field": ["development", "application development", "programming"]}}, {"job_id": "100003009055852", "location_code": "hk", "company": "NP Solution Limited", "job_title": "Project Administrator - Digital Projects", "description": "Job Overview:\nThe role of Project Administrator is to assist the Project Manager in driving Digital Projects delivery for our clients in an effective manner. This role is key in maintaining a close relationship with the clients by coordinating and delivering administrative support in a timely manner.\n\nResponsibilities:\n\nAssist Project Manager and the project team with project documentation and coordinate with client\nAssist Business Development team on issuing quotations and invoices\nHandling roster planning, leave records and administration task\nAssist in project coordination\nAssist in office administration\nAssist in ad-hoc assignments and tasks\nCandidates with more experience will be considered for the position of Project Officer.\n\nRequirements:\n\n2 years of solid working experience at administrative capacity\nEffective multitasking skills in a fast-paced IT environment\nExcellent organizational and administrative skills with the ability to work independently and in a team environment\nStrong attention to detail and accuracy\nGood working attitude and self-discipline\nTo apply for this position, please simply click on the \u201cAPPLY NOW\u201d bottom.\n\nAll information provided will be treated in strict confidence and used solely for recruitment purpose.\nFor more job opportunities, please visit our website: https://npsl.com.hk/\n\nFluent in written and spoken English and Cantonese\nComprehensive computer skills is a plus", "employment_types": ["Full Time", "Part Time", "Permanent"], "selling_points": ["remote work", "mobile and digital transform project", "Scrum & Agile"], "locations": ["Not Specified"], "categories": ["Information Technology (IT)", "IT - Webmaster / SEO", "Support", "Others"], "post_time": "2022-01-18T03:00:53Z", "salary": {"currency": null, "max": null, "min": null, "period": "monthly", "term": null}, "salary_visible": false, "title_keywords": ["project administrator"], "responsibilities": ["invoices", "project coordination", "office administration", "ad-hoc assignments", "coordinate with", "planning", "project documentation", "administration"], "requirements": {"degrees": [], "majors": [], "languages": ["cantonese", "english"], "language_level": ["fluent"], "hard_skills": ["plus", "computer skills"], "soft_skills": ["good working attitude", "work independently", "confidence", "organizational", "comprehensive", "attention to detail"], "languages_combined": [{"language": "cantonese", "language_level": ["fluent"]}, {"language": "english", "language_level": ["fluent"]}]}, "experience_required": {"duration": ["2 years"], "field": ["administrative"]}}, {"job_id": "100003009055134", "location_code": "hk", "company": "Seamatch Asia Limited", "job_title": "Project Manager / Business Analyst / PMO/ UAT officer / Project Trainee (Fresh ok)", "description": "Our client is a large\u00a0corporation, due to expansion, they need to\u00a0 \u00a0recruit many IT / project professionals to join their\u00a0IT team.\n\n(for either application and infrastructure team projects)\u00a0 \u00a0 \u00a0\u00a0\n\n\n\nProject Manager / (Senior) Project Specialist /\n\nPMO Support / (Senior) Business Analyst\n\nProject Officer / Project Trainee (with training)\u00a0 \u00a0\u00a0\n\n\u00a0 \u00a0\u00a0\nResponsibilities\n\nHandle user requirement collection, business analysis of\u00a0various\u00a0 \u00a0application, Project Management\nLiaise with business users on scope, testing plans\nPerform\u00a0Quality Assurance and provide User Acceptance Testing (UAT) and production support of the application\nPrepare System Specification and user documentation writing up\nProject coordination and management (application and / or infrastructure projects)\u00a0\nProper training will be provided to the junior / fresh\n\nRequirements\n\nDegree in Business, Finance, Computer Science or related disciplines\nMin 2 years relevant experience in project management /business analysis\nStrong communication skills\nProficiency in both English and Chinese\u00a0\nFresh graduate or less experience also considered and proper training will be provided\nMore experience will consider as Senior Business Analyst / Project Specialist\u00a0\nFocus on UAT / Quality Assurance experience will be consider as QA specialist\n7 year or above experience will be considered as Project Manager / Business Analyst Lead", "employment_types": ["Full Time", "Permanent", "Contract"], "selling_points": ["Business analyst, Project Manager, QA", "Project Management", "SDLC UAT User requirement collection"], "locations": ["Central & Western Area"], "categories": ["Information Technology (IT)", "IT Project Management / Team Lead", "Product Management / Business Analyst", "Others"], "post_time": "2022-01-18T01:21:48Z", "salary": {"currency": null, "max": null, "min": null, "period": "monthly", "term": null}, "salary_visible": false, "title_keywords": ["project manager", "business analyst", "officer", "trainee"], "responsibilities": ["user requirement", "management", "documentation", "uat", "project coordination", "infrastructure", "quality", "testing", "project management", "liaise with", "business analysis", "plans"], "requirements": {"degrees": ["degree", "fresh graduate"], "majors": ["related disciplines", "finance", "business", "computer science"], "languages": ["english", "chinese"], "language_level": ["proficiency"], "hard_skills": ["project management", "analysis", "focus"], "soft_skills": ["communication skills", "project management", "focus"], "languages_combined": [{"language": "english", "language_level": ["proficiency"]}, {"language": "chinese", "language_level": ["proficiency"]}]}, "experience_required": {"duration": ["min 2 years", "7 year"], "field": ["training", "qa", "project management", "business", "relevant experience", "business analysis", "quality assurance"]}}, {"job_id": "100003009053635", "location_code": "hk", "company": "Cargo Services Far East Ltd", "job_title": "Business / System Analyst", "description": "Responsibilities:\nPerform software development to the full SDLC\nWork with users to collect and confirm project requirements\nReview and analyze business requirements and technical requirements\nResponsible for system design and prepare related software engineering documents\nMonitor the performance of outsourced vendors\nPerform and coordinate on change, incident and problem management\nProvide support to application systems including trouble-shooting, bug fixing and ad-hoc queries\nRemote support after office hour may be required\nRequirements:\nDegree Holder in Computer Science, Computer Studies, Information Technology or related discipline\nAt least 5 years relevant IT experience (candidates with less experience will be considered for junior position)\nHands on experience in software development using Visual Studio, SQL Server Management Studio\nProficient in C#, VB.NET, ASP.NET, MVC, LINQ, SQL, XML, JQuery, JS and CSS/HTML5 programming\nKnowledge in warehouse management system is a plus.\nGood leadership and analytical skills\nAble to work independently and deal with tight project schedule\nGood spoken and written English and Mandarin\nBenefits:\nDouble Pay\nFive-day work week\nBirthday Leave\nMedical Insurance\nFree Shuttle Bus\nTraining Allowance\nAttractive remuneration package and excellent career development opportunities will be offered to the successful candidate.\u00a0 For Interested parties, please apply with a detailed resume stating present and stating present and expected salary by clicking \"Apply Now\".\u00a0 You are welcome to visit our website at http://www.cargofe.com.\nPersonal data collected will be used for recruitment purposes only and be treated in strict confidence.\u00a0 Cargo Services treats all applicants for employment in the same way, regardless of age, sex, marriage and civil partnership, race, disability, religion or belief.", "employment_types": ["Full Time", "Permanent"], "selling_points": ["~5 years exp or less exp for junior position", "Hands on experience in software development", "Double Pay; Five-day work week; Birthday Leave"], "locations": ["Kwai Tsing Area"], "categories": ["Information Technology (IT)", "Application Specialist - Software", "Product Management / Business Analyst", "Others"], "post_time": "2022-01-17T07:16:10Z", "salary": {"currency": null, "max": null, "min": null, "period": "monthly", "term": null}, "salary_visible": false, "title_keywords": ["system analyst"], "responsibilities": ["ad-hoc", "project requirements", "management", "provide support", "software", "review", "coordinate", "system design", "monitor the performance", "application systems"], "requirements": {"degrees": ["degree holder"], "majors": ["information technology", "computer science", "computer studies"], "languages": ["english", "mandarin"], "language_level": ["good"], "hard_skills": ["plus", "jquery", "analytical skills", "sql", "programming", "server", "css", "c#"], "soft_skills": ["work independently", "hands on", "leadership", "analytical skills"], "languages_combined": [{"language": "english", "language_level": ["good"]}, {"language": "mandarin", "language_level": ["good"]}]}, "experience_required": {"duration": ["at least 5 years"], "field": ["software development", "management", "sql", "it experience"]}}, {"job_id": "100003009047947", "location_code": "hk", "company": "Darwin Rhodes (Hong Kong) Company Limited", "job_title": "Software Engineer - Blockchain/Smart Contracts/Tokens/NFT", "description": "Job Description\nParticipate in various\u00a0blockchain projects related to Blockchain, Tokens & NFT\nDevelop blockchain applications and smart contracts\nConduct research on blockchain technologies\nTesting, Write documentation and technical specifications\nQualifications\nDegree in Information Technology, Computer Science, Business Information Technology or related discipline\nExperience in software development (Frontend & Backend)\nFamiliar with one or several programming languages: Solidity, Java, Node.js, Go, Python, C#\nExperience in one or several Blockchain technologies, e.g., Ethereum, Hyperledger Fabric, Corda\nKnowledge of Smart Contracts, Cryptocurrencies, Cryptography will be an advantage\nExperience with cloud computing, e.g., AWS, Azure, Google Cloud\nCreative in solving problems with programming\nHaving good interpersonal and communication skills\nBeing critical thinking, well organized and detail-minded", "employment_types": ["Full Time"], "selling_points": ["Cryptography", "Blockchain", "cloud computing"], "locations": ["Shatin Area"], "categories": ["Information Technology (IT)", "Others"], "post_time": "2022-01-14T04:21:18Z", "salary": {"currency": null, "max": null, "min": null, "period": "monthly", "term": null}, "salary_visible": false, "title_keywords": ["software engineer"], "responsibilities": ["software", "contracts", "testing", "develop", "communication", "specifications", "documentation", "conduct research"], "requirements": {"degrees": ["degree"], "majors": ["business", "computer science", "information technology"], "languages": [], "language_level": [], "hard_skills": ["blockchain", "java", "azure", "python", "aws", "programming", "documentation", "solidity", "go", "c#"], "soft_skills": ["detail-minded", "communication skills", "well organized", "creative", "interpersonal"], "languages_combined": []}, "experience_required": {"duration": [], "field": ["software development"]}}, {"job_id": "100003009050771", "location_code": "hk", "company": "The Hong Kong Polytechnic University", "job_title": "Specialist / Assistant Specialist (System Infrastructure) (three posts)", "description": "INFORMATION TECHNOLOGY SERVICES OFFICE\nSpecialist / Assistant Specialist (System Infrastructure) (three posts) (Ref. 22011410-E5)\nDuties\nThe appointees will work in the Systems Infrastructure Services Section and will be required to:\n(a)\u00a0\u00a0\u00a0\u00a0 support computer systems and facilities in Central Data Centres;\n(b)\u00a0\u00a0\u00a0\u00a0 support the University\u2019s cloud infrastructures;\n(c)\u00a0\u00a0\u00a0\u00a0 support service automation and streamlining of workflows;\n(d)\u00a0\u00a0\u00a0\u00a0 work outside normal office hours whenever necessary; and\n(e)\u00a0\u00a0\u00a0\u00a0 perform any other duties as assigned by the Director of the Office or his delegates.\nQualifications\nApplicants should:\n(a)\u00a0\u00a0\u00a0\u00a0 have a recognised degree or diploma\u00a0 in\u00a0 Computer\u00a0 Science, Information Technology or a related discipline;\n(b)\u00a0\u00a0\u00a0\u00a0 preferably have relevant working experience; and\n(c)\u00a0\u00a0\u00a0\u00a0 be able to communicate effectively in both written and spoken English and Chinese.\nApplicants with less experience or fresh graduates will also be considered.\nApplicants who have responded to the previous advertisements need not re-apply.\nRemuneration and Conditions of Service\nA highly competitive remuneration package will be offered.\u00a0 Initial appointment will be on a fixed-term gratuity-bearing contract.\u00a0 Re-engagement thereafter is subject to mutual agreement.\u00a0 Applicants should state their current and expected salary in the application.\nApplication\nPlease send a completed application form by post to Human Resources Office, 13/F, Li Ka Shing Tower, The Hong Kong Polytechnic University, Hung Hom, Kowloon, Hong Kong or via email by clicking \"Apply Now\".\u00a0 Application forms can be downloaded from https://www.polyu.edu.hk/hro/careers/guidelines_and_forms/forms.\u00a0 If\u00a0 a separate curriculum vitae is to be provided, please still complete the application form which will help speed up the recruitment process.\u00a0 The closing date for application is Monday, 14 February 2022.\u00a0 Applicants who are not invited to an interview within two months from the closing date should consider their applications unsuccessful.\u00a0 The University\u2019s Personal Information Collection Statement for recruitment can be found at https://www.polyu.edu.hk/hro/careers/guidelines_and_forms/pics_for_recruitment.\nPolyU is an equal opportunity employer committed to diversity and inclusivity.\u00a0 All qualified applicants will receive consideration for employment without regard to gender, ethnicity, nationality, family status or physical or mental disabilities.\u00a0\u00a0", "employment_types": ["Full Time"], "selling_points": [], "locations": ["Not Specified"], "categories": ["Information Technology (IT)", "Network & System", "Technical / Functional Consulting", "Others"], "post_time": "2022-01-14T11:21:41Z", "salary": {"currency": null, "max": null, "min": null, "period": "monthly", "term": null}, "salary_visible": false, "title_keywords": ["specialist", "assistant"], "responsibilities": ["any other duties", "systems infrastructure", "data", "advertisements", "infrastructure", "computer systems", "recruitment", "recruitment process"], "requirements": {"degrees": ["diploma", "degree"], "majors": ["science", "information technology"], "languages": ["english", "chinese"], "language_level": [], "hard_skills": ["c", "computer systems"], "soft_skills": ["committed"], "languages_combined": [{"language": "english", "language_level": []}, {"language": "chinese", "language_level": []}]}, "experience_required": {"duration": [], "field": ["relevant working experience"]}}, {"job_id": "100003009051871", "location_code": "hk", "company": "LAWSGROUP", "job_title": "Senior Analyst Programmer", "description": "Job Description:\nDevelop, maintain and enhance for internal system applications\nTroubleshoot software development problems\nPrepare system documentation(s) on the developed systems and provide application support\nProvide support on user acceptance tests and perform user support\nHandle ad hoc tasks as assigned by supervisor\nJob Requirements:\nDegree or above in Computer Science or related disciplines\nAt least 5 year working experience in software development\nWith hands on experience in Angular and JAVA Spring Boot is a MUST\nKnowledge in C#, Python, HTML5, Docker, Nginx and Android platform, AWS Services (Lambda, API Gateway, S3), WECOM API, Crystal Reports would be an advantage\nMobile development experience is preferable\nExcellent analytical, organizing & communication skills\nGood interpersonal communication and presentation skills\nGood command in both spoken and written English and Chinese\nGood team player with self-initiative, open-minded and willing to learn\nWe\u00a0offer\u00a0attractive remuneration package to the right candidate. Interested parties please click the \"APPLY NOW\" button below and send your application together with a detailed resume including current & expected salary and availability to Human Resources Department.\nCompany website:\u00a0https://www.lawsgroup.com\n(Data collected will be treated in strict confidence and used for recruitment purpose only)", "employment_types": ["Full Time", "Permanent"], "selling_points": ["Degree or above in Computer Science", "Min 5 yrs exp in software development", "Develop & maintain internal system applications"], "locations": ["Lai Chi Kok"], "categories": ["Information Technology (IT)", "IT Project Management / Team Lead", "Software Development", "Others"], "post_time": "2022-01-17T01:25:48Z", "salary": {"currency": null, "max": null, "min": null, "period": "monthly", "term": null}, "salary_visible": false, "title_keywords": ["senior analyst programmer"], "responsibilities": ["provide support", "software", "systems", "ad hoc tasks", "develop", "maintain", "troubleshoot"], "requirements": {"degrees": ["degree or above"], "majors": ["related disciplines", "computer science"], "languages": ["english", "chinese"], "language_level": ["good command"], "hard_skills": ["java", "aws", "mobile", "spring", "angular", "python", "s3", "android", "c#"], "soft_skills": ["communication skills", "good team player", "open-minded", "willing to learn", "communication", "presentation skills", "hands on", "self-initiative", "interpersonal"], "languages_combined": [{"language": "english", "language_level": ["good command"]}, {"language": "chinese", "language_level": ["good command"]}]}, "experience_required": {"duration": ["at least 5 year"], "field": ["development", "software development"]}}, {"job_id": "100003009044998", "location_code": "hk", "company": "CLP Power Hong Kong Limited", "job_title": "Team Lead \u2013 IT Operations", "description": "CLP has embarked on a journey to becoming a \u201cUtility of the Future\u201d which is customer-centric, agile and digitally-enabled. The company is launching strategic transformation initiatives across the business in which next generation technologies will play a pivotal role.\u00a0\n\nWe are looking for a passionate IT professional to join the Cloud Program and Infrastructure Transformation within the Information Technology Group of CLP Power Hong Kong Limited. The successful applicant will be responsible for the following duties:\n\nKey Responsibilities:\n\nExperience to lead and response the 7x24 IT Monitoring Centre/ IT Command Centre as a centralised focal point for all IT incident through continuous drive the IT service monitoring competency detection.\nExperience on Major Incident Commander role to drive major incident resolution.\nHands on experience on establish process and mechanism for effective monitoring of systems with a view to minimise unplanned system interruption (e.g., Identify leading indicator of system health issue, correlate multiple source of data for analysis) and timely identify system issue (e.g., active monitoring of website for service outage).\nResponsible for regular review and refine systems and services monitoring requirements with consideration of the changes in business needs (e.g., change in business criticality) and lesson learnt from prior incidents.\nMaintain, enforce and regularly review procedures and processes in associate with crisis management, IT service continuity management, disaster recovery and business continuity with consideration on the evolving technology landscape (e.g., Cloud based backup solution, cross-site availability) and service requirements; Fully leverage technology in optimising service provision.\nManage and conduct regular vulnerability and patch maintenance activities, server and system patches, disaster recovery drills and crisis management drills to ensure planned processes and procedures are effective.\nDrive internal improvement programs with other relevant teams on identified improvement areas for enhancing system reliability (e.g., optimal timing for firmware upgrade).\nDesign and implement sourcing strategy on IT operation services; Manage suppliers\u2019 performance through establishing proper governance processes and regular performance review.\nRequirements:\n\nA recognized University degree in Information Technology, Computer Science, or related disciplines. Master\u2019s degree in a related field is desirable.\nAt least 6-8 years\u2019 experience in providing IT infrastructure / operations services.\nProfessional credentials in ITIL, PMP, COBIT, ScrumMaster, DevOps, cloud certifications or relevant disciplines preferred\nProven track record of problem solving and analytical abilities\nStrong technical capability, vendor management, communication, and relationship management skills\nProactive, performance driven and results oriented\nPlease apply by clicking the button \u201cApply Now\u201d below for application on or before 28\u00a0January 2022.\n\nApplicants not invited for interview within 6 weeks from the closing date may assume their applications unsuccessful.\n\nInformation provided will be for recruitment purpose within the CLP Group and only short-listed candidates will be contacted. We comply with all applicable laws and regulations of HKSAR in handling applications. For details of the Personal Information Collection Statement, please visit our website: https://clp.to/engPICS\nFor further information on our company, please visit our website:\u00a0https://www.clpgroup.com/", "employment_types": ["Full Time"], "selling_points": [], "locations": ["Sham Shui Po"], "categories": ["Information Technology (IT)", "IT Project Management / Team Lead", "Others"], "post_time": "2022-01-13T18:55:05Z", "salary": {"currency": null, "max": null, "min": null, "period": "monthly", "term": null}, "salary_visible": false, "title_keywords": ["operations", "lead"], "responsibilities": ["business continuity", "management", "it service", "maintenance", "data", "analysis", "monitoring", "systems", "website", "review", "procedures", "resolution", "regular review", "teams", "maintain", "design", "crisis management"], "requirements": {"degrees": ["university degree", "degree", "master"], "majors": ["related disciplines", "computer science", "information technology"], "languages": [], "language_level": [], "hard_skills": ["itil", "devops", "vendor", "problem solving", "pmp"], "soft_skills": ["problem solving", "proactive", "driven", "communication"], "languages_combined": []}, "experience_required": {"duration": ["at least 6-8 years"], "field": ["infrastructure", "it"]}}, {"job_id": "100003009052578", "location_code": "hk", "company": "Ricoh Hong Kong Limited", "job_title": "Business Analyst", "description": "Job Description:\n\nThis position will be a member of the Process Excellence Team under Information Technology (IT), reporting to Process Excellence Manager.\u00a0 Besides business analysis, process design and engineering, he/she will also assist in enhancing contribution of IT to business efficiency.\n\nResponsibilities:\n\n\u00a0Plan and execute process excellence initiatives with alignment to business strategies\nCollect business requirements and to define clear and measurable project objectives. Create as-as and to-be process maps for process changes.\nPrepare functional design documents and work with IT Development Team or suppliers to develop systems with business analytic capabilities to ensure deliverables (system solutions and process designs) are aligned with requirements.\nParticipate in ERP replacement project and coordinate related process re-engineering tasks.\nCarry out testing of developed systems or IT tools to obtain user acceptance.\nAct as an internal IT process officer to ensure IT governance and standards are properly embedded into day-to-day IT operations and project management.\nResearch and review up-to-date business processes with new technology advancements to improve business efficiency and to consistently align with market trends.\nAssist supervisor in documentation, preparing budget plans and proposals for projects\nAny other duties assigned by supervisor\n\nRequirements:\n\nBachelor\u2019s degree or above in Industrial Engineering, Information Technology, or related discipline.\nMinimum 3 years process improvement experience with at least 1 year IT system / IT tool development project experience, e.g., ERP implementation or Power BI Applications.\nQualified lean practitioner or six sigma green belt.\nStrong process mapping capability to build process maps and workflow designs.\nSolid experience in project management, certified PMP or relevant qualification will be an added advantage but not a must.\nEffective verbal and written communication in English and Chinese.\nExcellent team player, able to work with multinational project members.\nWe offer 5-day work, attractive\u00a0remuneration\u00a0and benefits package to the right candidate.\nInterested parties please forward your full resume\u00a0(in Microsoft Word or PDF format)\u00a0with current and expect salary to the Human Resources & Facilities Services, Ricoh Hong Kong Limited,\u00a0by clicking \"Apply Now\".\nInformation provided will be treated in strict confidence and only be used for recruitment related purposes. All personal data of unsuccessful candidates will be destroyed on completion of the recruitment exercise.", "employment_types": ["Full Time", "Permanent"], "selling_points": ["Business analysis and process improvement", "Drive innovation and technology integration", "Exp in process engineering and system development"], "locations": ["Kowloon Bay"], "categories": ["Professional Services", "Business Analysis / Data Analysis", "Information Technology (IT)", "Product Management / Business Analyst", "Others"], "post_time": "2022-01-17T03:36:22Z", "salary": {"currency": null, "max": null, "min": null, "period": "monthly", "term": null}, "salary_visible": false, "title_keywords": ["business analyst"], "responsibilities": ["reporting", "any other duties", "documentation", "re-engineering", "operations", "systems", "review", "budget", "design", "develop", "coordinate", "testing", "project management", "plan", "business analysis", "plans", "collect business requirements"], "requirements": {"degrees": ["degree or above", "bachelor"], "majors": ["engineering", "information technology"], "languages": ["english", "chinese"], "language_level": [], "hard_skills": ["lean", "bi", "erp", "project management", "six sigma", "pmp"], "soft_skills": ["communication", "project management", "team player"], "languages_combined": [{"language": "english", "language_level": []}, {"language": "chinese", "language_level": []}]}, "experience_required": {"duration": ["at least 1 year", "minimum 3 years"], "field": ["development", "project management", "it"]}}, {"job_id": "100003009048507", "location_code": "hk", "company": "Dataplugs Limited", "job_title": "Data Centre Technical Support", "description": "Responsibilities:\n\nHandle phone-in, email, instant message of support enquiries in using our services\nTroubleshooting for various technical issues\nMaintain an accurate and up-to-date hardware inventory\nWork on Shift\n\nRequirements:\n\n\u00a0 Form 5 graduated or Diploma in Computer Studies or above.\n\u00a0 1 year or above experience in IT with solid experience in end-user is an advantage\n\u00a0 \u00a0Ability to communicate effectively with all customers at all levels\n\u00a0 Good command of spoken and written English and Chinese\n\u00a0 Fresh graduated will also be considered, training will be provided\n\n\u00a0Benefits:\n\n\u00a0\u00a0\u00a0\u00a0\u00a0\u00a0\u00a0\u00a0 5-day work or 4-day work\n\u00a0\u00a0\u00a0\u00a0\u00a0\u00a0\u00a0\u00a0 Friendly and Professional Working Environment\n\u00a0\u00a0\u00a0\u00a0\u00a0\u00a0\u00a0\u00a0 Medical insurance\n\u00a0\u00a0\u00a0\u00a0\u00a0\u00a0\u00a0\u00a0 Dental Insurance\n\u00a0\u00a0\u00a0\u00a0\u00a0\u00a0\u00a0\u00a0 Night shift allowance\n\u00a0\u00a0\u00a0\u00a0\u00a0\u00a0\u00a0\u00a0 Education allowance\n\u00a0\u00a0\u00a0\u00a0\u00a0\u00a0\u00a0\u00a0 Attractive remuneration\n\u00a0\u00a0\u00a0\u00a0\u00a0\u00a0\u00a0\u00a0 Year-end performance Bonus\n\u00a0\u00a0\u00a0\u00a0\u00a0\u00a0\u00a0\u00a0 On-the job training\n\nSalary Negotiable, depends on experience & qualifications.\n\n\n\nInterested candidate please send your updated CV with expected salary by clicking \"Apply Now\".\n\n\n\nAll applications will be treated in strict confidence and used solely for recruitment purpose.", "employment_types": ["Full Time", "Permanent"], "selling_points": ["5 days work or 4 days work, On job Training", "Performance Bonus, Medical & Dental Insurance", "Night shift Allowance,Education allowance"], "locations": ["Kwai Hing"], "categories": ["Information Technology (IT)", "Support", "Network & System", "Others"], "post_time": "2022-01-15T03:50:00Z", "salary": {"currency": null, "max": null, "min": null, "period": "monthly", "term": null}, "salary_visible": false, "title_keywords": ["technical support"], "responsibilities": ["hardware", "inventory", "maintain", "troubleshooting"], "requirements": {"degrees": ["form 5", "diploma"], "majors": ["computer studies"], "languages": ["english", "chinese"], "language_level": ["good command"], "hard_skills": [], "soft_skills": [], "languages_combined": [{"language": "english", "language_level": ["good command"]}, {"language": "chinese", "language_level": ["good command"]}]}, "experience_required": {"duration": ["1 year"], "field": ["it"]}}, {"job_id": "100003009049016", "location_code": "hk", "company": "Techbob Academy Limited", "job_title": "STEAM/Tech Course Instructor / Program Manager", "description": "\u00a0Responsibilities:\n\n- Teach, guide and engage students in STEAM courses including robotics, coding, IoT, drone, AR, AI etc. to enlighten their interests and shape their minds in learning tech and STEAM- Explain the course content in digestible, interesting and engaging ways- Develop curriculum, lesson plans and teaching notes independently-\u00a0Teaching by Cantonese and English\n\n- Train and supervise junior instructors (senior experienced instructors may be considered the position of Senior Instructor or Program Manager)\n\nRequirements:- Degree in Computer Science, Information Technology, Engineering, Science, Mathematics, Education or related disciplines- Basic knowledge in coding / app development / IoT / robotics / mechanics\u00a0/ AR / AI / 3D\u00a0printing\u00a0(experience in any above is a plus but not a must. On-job training is provided).\u00a0Eagar to learn new teaching curriculum and contents- Strong communication and presentation skills. Fluency and confidence to present often complex and abstract tech concepts in an easy-to-understand ways to young students is a must- Enthusaism and patience to teach. Teaching experience or formal education training is an advantage but not a must. Welcome current programmer and software engineer to apply.Benefits:- Competitive pay with high incentives and performance bonus- Faster career track.\u00a0 Potential promotion to be the Program Director and other management positions for good performers- 5 days work- 10 days annual leave- On-job training, opportunity to learn newest STEAM and tech curriculum- Staff's children free to take courses in centers- Staff discount on purchase", "employment_types": ["Full Time", "Part Time", "Permanent"], "selling_points": ["Competitive pay with high incentives & bonus", "Join the top STEAM education brand in HK", "Fast career track with high growth company"], "locations": ["Yau Tsim Mong Area"], "categories": ["Education", "Teacher", "Tutor / Instructor", "Information Technology (IT)", "Others"], "post_time": "2022-01-14T07:55:15Z", "salary": {"currency": null, "max": null, "min": null, "period": "monthly", "term": null}, "salary_visible": false, "title_keywords": ["manager"], "responsibilities": ["robotics", "ar", "software", "coding", "develop", "communication", "3d printing", "plans"], "requirements": {"degrees": ["degree"], "majors": ["mathematics", "science", "engineering", "information technology", "computer science"], "languages": ["cantonese", "english"], "language_level": [], "hard_skills": ["plus", "basic", "ar", "ai"], "soft_skills": ["confidence", "communication", "presentation skills", "learning", "patience"], "languages_combined": [{"language": "cantonese", "language_level": []}, {"language": "english", "language_level": []}]}, "experience_required": {"duration": [], "field": ["engineering", "training", "related", "development", "education", "information technology", "teaching"]}}, {"job_id": "100003009049418", "location_code": "hk", "company": "Shanghai Commercial Bank Ltd", "job_title": "Computer Operator", "description": "Responsibilities:\n\nProvide operation support in Data Centre, including batch processing, system monitoring, report distribution, data restoration and backup\nAssist in the monitoring of computer operation, logging and other activities\nDistribute output to the users and perform report distribution\nMonitor the hardware and software performance\nCarry out 24 hours on-site service in both production and backup site\n\nRequirements:\n\nDiploma or Higher Diploma in Computing Studies or related disciplines\nGood communication and interpersonal skills\nAbility to work independently and under pressure\nShift duty required with shift allowance\n\nAttractive remuneration package will be offered to the right candidates. Interested parties please click \"Apply Now\" to submit your full resume with current and expected salary to the Human Resources Division.\n\nPlease visit us at www.shacombank.com.hk for more information about our Bank.\n\nAll personal data collected will be used for recruitment related purposes strictly in accordance with the Bank's personal data policies, a copy of which will be provided immediately upon request by contacting our Personal Data Compliance Officer. Applicants who are not contacted within two months may consider their applications unsuccessful and the personal data collected from the applicants will be retained for no longer than two years from the date of rejection during which the applicants may be considered for other suitable positions within the Bank.", "employment_types": ["Full Time", "Permanent"], "selling_points": ["Provide operation support in Data Centre", "Assist in the monitoring of computer operation", "Monitor the hardware & software performance"], "locations": ["Kwai Hing"], "categories": ["Banking / Finance", "Others", "Information Technology (IT)", "Support", "Others"], "post_time": "2022-01-15T03:50:25Z", "salary": {"currency": null, "max": null, "min": null, "period": "monthly", "term": null}, "salary_visible": false, "title_keywords": ["operator"], "responsibilities": ["software", "data", "monitoring", "monitor", "hardware", "report"], "requirements": {"degrees": ["diploma"], "majors": ["related disciplines"], "languages": [], "language_level": [], "hard_skills": [], "soft_skills": ["work independently", "communication and interpersonal skills", "under pressure"], "languages_combined": []}, "experience_required": {"duration": [], "field": []}}, {"job_id": "100003009051260", "location_code": "hk", "company": "OnTheList Limited", "job_title": "IT Business Analyst", "description": "OnTheList is a pioneering\u00a0concept of Members-Only Flash Sales, offering its members authentic and quality products with the promise of being the best deal in town.\u00a0\n\nCurrently the IT team is expanding and we are looking for dynamic Business Analyst to join! He/ she will participate in different development projects, help to prepare documents, data required and set up the current systems to support daily operations.\n\nJOB SCOPE\n\nEngage in various web development & data warehouse projects\nParticipate in business requirement analysis and user requirement studies for new system design/enhancement\nLiaise with other departments to ensure the proposed solution design would meet business requirement\nCo-ordinate testing and/or trial runs with users to make sure new system/system enhancements will be functioning as expected\nExtract & prepare data required from our databases for other departments\nAssist in ad hoc analysis and other duties as required\nAssist in configuring systems to support sales events\n\nPOSITION QUALIFICATIONS\n\nDiploma or above in Business administration, Information Technology, or related disciplines\nGood knowledge in MS Office, in particular MS Excel\nKnowledge in SQL will be a big advantage\n3+ years of experience with BI tool suits, such as Power BI, QuickSight etc. is a plus\nWorking experience in IT related field is a plus\nStrong logical mindset and good communication skills\n\nWHAT DO WE OFFER\n\nInternational and dynamic environment\nDiverse career opportunities for the right candidate\nDiverse and challenging tasks to ensure professional development\nFlexible working environment with work from home arrangement\u00a0\nCommitment to a diversity, equity and inclusive work environment", "employment_types": ["Full Time", "Permanent"], "selling_points": [], "locations": ["Central"], "categories": ["Information Technology (IT)", "Support", "Software Development", "Others"], "post_time": "2022-01-16T21:50:26Z", "salary": {"currency": null, "max": null, "min": null, "period": "monthly", "term": null}, "salary_visible": false, "title_keywords": ["business analyst"], "responsibilities": ["user requirement", "ad hoc", "power bi", "other duties", "data", "analysis", "systems", "quality", "design", "testing", "communication", "daily operations", "system design", "configuring", "databases", "liaise with", "prepare documents", "administration"], "requirements": {"degrees": ["diploma or above"], "majors": ["related disciplines", "business administration", "information technology"], "languages": [], "language_level": [], "hard_skills": ["web development", "bi", "plus", "data warehouse", "analysis", "sql", "make", "ms excel", "dynamic", "system design", "flash", "databases", "ms office"], "soft_skills": ["communication skills", "dynamic", "logical mindset"], "languages_combined": []}, "experience_required": {"duration": ["3+ years"], "field": ["related", "it"]}}, {"job_id": "100003009049388", "location_code": "hk", "company": "Success Universe Group", "job_title": "I.T. Support", "description": "Responsibilities :\n\nProvide day-to-day IT technical support to business units and internal users;\nManage inventory of hardware, software and licenses of services, accounts and applications; and\nPerform end-user IT services including PC, LAN/WAN installation and trouble shooting.\n\nRequirements :\n\nMinimum 1 year relevant experience in I.T. support;\nIn-depth practical experience in PC, LAN/WAN installation, trouble shooting and administration;\nHands on experience in MS Office; and\nGood interpersonal and communication skills.\nWe offer 5 days week to the right candidate and you are welcome to visit our website at\u00a0http://www.successuniversegroup.com.\n\nInterested parties please send your resume with\u00a0current\u00a0and\u00a0expected salary\u00a0by clicking below \"APPLY NOW\".\n\n\n\n(Personal data collected will be treated in the strictly confidence and only be used for recruitment related purpose.)", "employment_types": ["Full Time", "Permanent"], "selling_points": [], "locations": ["Admiralty"], "categories": ["Information Technology (IT)", "Support", "Network & System", "Others"], "post_time": "2022-01-14T08:32:46Z", "salary": {"currency": null, "max": null, "min": null, "period": "monthly", "term": null}, "salary_visible": false, "title_keywords": [], "responsibilities": ["installation", "software", "it technical support", "inventory", "hardware"], "requirements": {"degrees": [], "majors": [], "languages": [], "language_level": [], "hard_skills": ["pc", "wan", "ms office"], "soft_skills": ["communication skills", "hands on", "interpersonal"], "languages_combined": []}, "experience_required": {"duration": ["minimum 1 year"], "field": ["installation", "relevant experience", "administration"]}}, {"job_id": "100003009053049", "location_code": "hk", "company": "JFE Consulting Limited", "job_title": "Network System Analyst", "description": "Our client, one of the leading IT companies, is looking for high calibres to join their winning team:-\n\nResponsiblities:\n\n\n\u00a0\u00a0Provide network support and perform troubleshoot to resolve various WAN/LAN connectivity issues.\nAssist various departments to maintain network security and configure remote routers and firewalls and provide engineering support.\nAnalyze and recommend solutions, upgrades services to streamline process and recommend improvements.\nMaintain hardware and software for network perform troubleshoot and assist in installation and upgrade workstations and Servers.\nInstall and maintain data and voice circuits through routers, switches, and Wide Area Network devices.\n\nRequirements:\n\n\nA degree or above in computer science or equivalent;\nAt least 6 years of post-qualification IT experience\n\u00a0At least 4 years of functional/specialty experience in design and/or implementation of network infrastructure(s);\nExperience in supporting network devices from different vendors: Routers, Switches, Multi-layer Switches, Firewalls, Local Server Load Balancers, IPSec VPN, SSL VPN, IPS/IDS, Web Application Firewall etc.;\nFamiliar with network configurations and changes, spanning-tree, dynamic routing protocols, VLANs, DHCP, NAT, ACL, QoS, Metro Network etc.", "employment_types": ["Full Time", "Permanent"], "selling_points": ["Network System Analyst", "Experienced in supporting network devices", "Attractive salary"], "locations": ["Quarry Bay"], "categories": ["Information Technology (IT)", "Application Specialist - Network", "Network & System", "Others"], "post_time": "2022-01-17T05:24:24Z", "salary": {"currency": null, "max": null, "min": null, "period": "monthly", "term": null}, "salary_visible": false, "title_keywords": ["system analyst"], "responsibilities": ["maintain network", "installation", "software", "upgrades", "hardware", "maintain", "troubleshoot", "maintain data"], "requirements": {"degrees": ["degree or above"], "majors": ["computer science"], "languages": [], "language_level": [], "hard_skills": ["server", "dynamic", "vpn", "web application firewall"], "soft_skills": ["dynamic"], "languages_combined": []}, "experience_required": {"duration": ["at least 6 years", "at least 4 years"], "field": ["post-qualification", "design", "it experience"]}}, {"job_id": "100003009055625", "location_code": "hk", "company": "Gravitas Recruitment Group", "job_title": "LEADING IBANK - Service desk anaylst", "description": "Opportunity to join a leading Bank!\n\nThe Service Desk Analyst provides support for basic incident resolution and requests reported to the regional service desk.\n\n\nResponsibilities:\n\n\nAct as a single point of contact and support internal staff via phone calls, emails, live chat and self-service tickets from internal staff regarding IT related issues and queries.\n1st line support: troubleshooting of IT related problems\nEscalate unresolved issues / requests to the corresponding helpdesk (L2/L3 support)\nTake ownership of users' problems, follow up the status of problems on behalf of the user and communicate the status to users in a timely manner\nUpdate all taken actions and information into ticketing system in a timely manner\nTo maintain a high degree of customer service for all support queries\nMaintain knowledge database to ensure all information is up-to-date\nDefine / Improve processes and workflows\nCapable to manage projects or tasks given by the manager\n\nProfile Required\n\nRequirements:\n\n\nFluent in English\nExcellent communication skills and telephone manner.\nEffective listening and attentiveness skills\nExcellent organizational skills\nWillingness to improve and to learn\nCustomer service orientation and/or prior customer service training\nTeam player\nBanking experience will be advantageous, but it is not mandatory", "employment_types": ["Full Time", "Permanent"], "selling_points": ["International environment", "Good work-life balance environment", "Great career development"], "locations": ["Not Specified"], "categories": ["Information Technology (IT)", "Hardware", "Support", "Others"], "post_time": "2022-01-18T02:48:37Z", "salary": {"currency": "HKD", "max": 34999, "min": 20000, "period": "monthly", "term": null}, "salary_visible": true, "title_keywords": [], "responsibilities": ["a timely manner", "troubleshooting", "maintain", "customer service", "contact", "database", "manage projects", "phone calls"], "requirements": {"degrees": [], "majors": [], "languages": ["english"], "language_level": ["fluent"], "hard_skills": [], "soft_skills": ["communication skills", "organizational skills", "customer service", "team player", "telephone manner"], "languages_combined": [{"language": "english", "language_level": ["fluent"]}]}, "experience_required": {"duration": [], "field": ["it", "banking experience"]}}, {"job_id": "100003009047369", "location_code": "hk", "company": "Ebroker Systems Ltd", "job_title": "IT Support Engineer-Fintech (Fresh Graduates are welcome)", "description": "Responsibilities:\n\n\nTo provide first level support to existing clients and to carry out daily health check of systems\nTo provide system and application support\nTo handle deployment of system modules\nProactively follow up technical issues and incidents\nTo assist clients to participate HKEx Market Rehearsal and to perform system tests\nTo carry mobile and handle non-office hours call\n\nRequirements:\n\nHigher Diploma or above in\u00a0Computer Science, Computer Engineering, Information Technology or related disciplines\u00a0\nKnowledge in MS SQL Server, MS Windows administrative and configuration\nKnowledge and experience in trading solutions, equity/futures trading rules of HK and China is preferable\nAnalytical, creative mind and able to work under pressure\nResponsible, good interpersonal skill and good team player\nGood command of both written and spoken Mandarin/English is preferable\nJoin us to work in a Hong Kong\u00a0listed leading Fintech company!\n\nFor application, please email your detailed resume and expected salary to us.\n\nAll applications will be treated in strict confidence and will be handled by authorized personnel only. Information provided will be used for the purpose of employment application to eBroker Systems Limited and will be destroyed within 6 months from the date of receipt.", "employment_types": ["Full Time"], "selling_points": ["Happy & friendly environment", "Great career exposure", "Provides on-the-job training, 5-day work week"], "locations": ["Tsim Sha Tsui"], "categories": ["Information Technology (IT)", "Support", "Others", "Others", "Student / Fresh Graduate / No Experience"], "post_time": "2022-01-14T02:55:51Z", "salary": {"currency": null, "max": null, "min": null, "period": "monthly", "term": null}, "salary_visible": false, "title_keywords": ["it support engineer"], "responsibilities": ["systems"], "requirements": {"degrees": ["higher diploma or above"], "majors": ["related disciplines", "computer engineering", "computer science", "information technology"], "languages": ["english", "mandarin"], "language_level": ["good command"], "hard_skills": ["ms sql server", "ms windows"], "soft_skills": ["good team player", "confidence", "responsible", "detailed", "interpersonal skill", "creative", "work under pressure"], "languages_combined": [{"language": "english", "language_level": ["good command"]}, {"language": "mandarin", "language_level": ["good command"]}]}, "experience_required": {"duration": [], "field": ["trading"]}}, {"job_id": "100003009056005", "location_code": "hk", "company": "Dyxnet Limited", "job_title": "Finance Manager", "description": "\u00a0Responsibilities\n\nLeading finance team in Hong Kong, monitoring daily accounting activities. including cash-flows, settlement, reconciliation, general ledger, schedules and reports.\nOverseeing accounts receivables and payables to ensure the timely collection and settlement of payments.\nPreparing various monthly management reports on a timely basis.\nCash flow management, interfacing with the bank in Hong Kong and Singapore for all financing requirements.\nManaging and complying with government reporting requirements and tax filings in Hong Kong and Singapore.\nAs a key role in SAP system implementation.\nConducting financial and business analysis.\nOverseeing all audit, compliance and internal control functions/operations.\nDeveloping and enforcing accounting policies to maintain and strengthen internal control.\nParticipating in ad hoc projects as assigned.\n\n\u00a0Job Requirements\n\n\nDegree or above in Accounting or Finance with CPA or qualified accreditation.\nMinimum 10 years relevant experience in which 5 years in managerial capacity.\nExperience in Telecommunication sector is an advantage\nSolid knowledge of Tax rules in Hong Kong and Singapore.\nThorough knowledge of accounting standards (IAS and USGAAP)\nExperience with ISO audit and SOX compliance.\nSolid knowledge of financial analysis and forecasting.\nInteract in a positive, proactive, customer-service manner with internal and external customers.\nStrong interpersonal and communication skills\nProficiency in SAP and Yonyou NC.\nStrong analytical, data mining and problem-solving skills. Familiar with Excel and sensitive with number and formulas.\nExcellent communication skills in English, Cantonese, and Mandarin.\nAttractive remuneration and compensation package, including year end bonus, medical scheme as well as career development opportunities will be offered.\u00a0\n\n\nInterested parties please send your resume with expected salary and availability to Human Resources Department, Dyxnet Group, 37/F, Tower 1, Metorplaza, 223 Hing Fong Road, Kwai Fong.\u00a0\n\nWelcome to visit our website:\u00a0http://www.dyxnet.com/\u00a0for further information of our company.\u00a0\n\nData collected will be used for recruitment purpose only.", "employment_types": ["Full Time", "Permanent"], "selling_points": ["Leading finance team in Hong Kong", "Overseeing accounts receivables and payables", "Five days work"], "locations": ["Kwai Fong"], "categories": ["Accounting", "Accountant", "Finance / Accounting Manager", "Information Technology (IT)", "Others"], "post_time": "2022-01-18T03:11:03Z", "salary": {"currency": null, "max": null, "min": null, "period": "monthly", "term": null}, "salary_visible": false, "title_keywords": ["finance manager"], "responsibilities": ["schedules", "general ledger", "operations", "audit", "accounting policies", "maintain", "internal control", "compliance", "implementation", "developing", "reports", "finance team", "reporting", "management", "monitoring", "cash flow", "tax", "management reports", "financial and business analysis", "payments", "ad hoc projects", "daily accounting"], "requirements": {"degrees": ["degree or above"], "majors": ["finance", "accounting"], "languages": ["cantonese", "english", "mandarin"], "language_level": ["excellent"], "hard_skills": ["excel", "sap", "scheme", "financial analysis", "cpa", "data mining", "problem-solving skills"], "soft_skills": ["communication skills", "thorough", "sensitive", "problem-solving skills", "proactive", "interpersonal", "positive"], "languages_combined": [{"language": "cantonese", "language_level": ["excellent"]}, {"language": "english", "language_level": ["excellent"]}, {"language": "mandarin", "language_level": ["excellent"]}]}, "experience_required": {"duration": ["5 years", "minimum 10 years"], "field": ["managerial", "compliance", "relevant experience", "audit"]}}, {"job_id": "100003009050066", "location_code": "hk", "company": "Fujitec (HK) Co Ltd", "job_title": "System Administration Officer (Ref: SAO)", "description": "Responsibilities:\n\nProviding daily IT operation service to in-house and service stations\nResponsible for hardware, software and network equipment installation, configuration and upgrade\nTroubleshooting of problems in software and hardware products\nCoordinate with vendors on hardware and software purchase/maintenance\nManage IT asset and server hardware inventory\nPerforming other duties as and when required\n\n\u00a0Requirements:\n\nHigher Diploma or above in Information Technology or related discipline\nMinimum 3 years relevant working experience including system & network support, project management, web programming and database design\nStrong support and troubleshooting skills in Microsoft Windows platform\nStrong infrastructure skills especially in MS Window Server and MS\u00a0SQL\u00a0Server\nProficiency in MS Office (Excel/ Word/ Access) and Chinese Word Processing and website development knowledge\nImmediate available is preferable\n\nWe offer attractive remuneration package and fringe benefits including performance bonus etc. to the right candidate.\n\nInterested parties please send your full resume with current and expected salary by clicking \u201cApply Now\u201d\u00a0button. Or you can send by post directly to Manager, Personnel Department, Fujitec (HK) Co. Ltd., 34/F., Hong Kong Plaza, 188 Connaught Road West, Hong Kong. Please state the Reference No. on the envelope for our reference.\n\nTo find out more about us, please visit our Website at\u00a0www.fujitec-hk.com.hk\n\nAll personal data of unsuccessful applicants will be destroyed after the recruitment exercise when no longer required.", "employment_types": ["Full Time", "Permanent"], "selling_points": ["MS Window Server and MS SQL Server", "Strong support and troubleshooting skills", "Higher Diploma or above in Information Technology"], "locations": ["Sai Wan"], "categories": ["Information Technology (IT)", "Support", "Network & System", "Others"], "post_time": "2022-01-14T09:43:13Z", "salary": {"currency": null, "max": null, "min": null, "period": "monthly", "term": null}, "salary_visible": false, "title_keywords": ["administration officer"], "responsibilities": ["installation", "software", "maintenance", "server hardware", "configuration", "other duties", "inventory", "coordinate with", "troubleshooting", "hardware", "purchase"], "requirements": {"degrees": ["higher diploma or above"], "majors": ["information technology"], "languages": ["chinese"], "language_level": ["proficiency"], "hard_skills": ["excel", "chinese word processing", "web", "ms sql server", "word", "project management", "programming", "server", "ms office"], "soft_skills": ["project management", "troubleshooting"], "languages_combined": [{"language": "chinese", "language_level": ["proficiency"]}]}, "experience_required": {"duration": ["minimum 3 years"], "field": ["relevant working experience", "design", "project management", "programming", "database"]}}, {"job_id": "100003009054701", "location_code": "hk", "company": "Cymballe Limited", "job_title": "Full Stack Developer / Software Engineer / Analyst Programmer (Fresh Graduate Welcome)", "description": "Responsibilities\n\nWorking closely with PM, Designers, Developers and Programmers\nUnderstand the client's requirements and generate technical solutions\nIdentify issues and implement solutions to complex problems\nPerform function enhancement, system deployment and testing\n\nRequirements\n\n\nHigher Diploma / Bachelor Degree in Computer Science, Information Technology, or any related disciplines;\n1 year or above experience in web or application development;\nExperience in PHP framework (e.g. Laravel, Codeigniter), MySql, MSSQL, RESTful API, HTML, CSS, JavaScript framework (e.g. React, bootstrap), Python will be an advantage;\nExperience in payment integration (e.g. Paypal / Stripe) will be an advantage;\nGood team player with strong analytical and problem-solving skills;\nSelf-motivated with can do attitude and timely delivery results\nWorking Location in Tsuen Wan\n\nNice to have\n\nExperience in cloud storage, deployment and computing. We use Azure / AWS but we're open to other platform experience\n", "employment_types": ["Full Time"], "selling_points": ["Award-winning creative digital agency", "Rapid advancement opportunity, dynamic culture", "Experience in web or application development"], "locations": ["Tsuen Wan Area"], "categories": ["Information Technology (IT)", "Application Specialist - Software", "Software Development", "Others"], "post_time": "2022-01-17T10:38:44Z", "salary": {"currency": null, "max": null, "min": null, "period": "monthly", "term": null}, "salary_visible": false, "title_keywords": ["software engineer", "developer", "analyst programmer"], "responsibilities": ["testing"], "requirements": {"degrees": ["diploma", "degree", "bachelor"], "majors": ["related disciplines", "computer science", "information technology"], "languages": [], "language_level": [], "hard_skills": ["restful api", "azure", "web", "php", "react", "integration", "problem-solving skills", "nice", "html", "python", "aws", "javascript", "deployment", "mssql", "css", "wan"], "soft_skills": ["problem-solving skills", "good team player", "timely", "self-motivated"], "languages_combined": []}, "experience_required": {"duration": ["1 year"], "field": ["application development"]}}, {"job_id": "100003009055952", "location_code": "hk", "company": "Asia Molecular Diagnostics Laboratory Limited", "job_title": "Bioinformatics Manager", "description": "About the positions\n\nAsia Molecular Diagnostics Laboratory Limited (AMDL) is looking for a Bioinformatics Manager to join AMDL.\n\nAs the Bioinformatics Manager, they will perform data analysis and join R&D activities to develop new genetic tests by utilizing cutting-edge sequencing technologies. We aim to build and deploy advanced genetic test technologies to provide high quality testing services to general public in Hong Kong.\n\nCandidate will have the opportunity to work in a rapidly growing startup environment and passionate and mission-oriented group.\n\nJob Highlights\n\nDoctoral degree\nWorking in Unix/Linux environment\nBioinformatics analysis of data generated by Next-generation sequencing (NGS) or other cutting-edge technologies\nBuilding new bioinformatics data analysis pipeline and server\n\nResponsibilities:\n\nConduct different research work at R&D and research collaboration projects\nBuild and develop bioinformatics analysis pipelines for different NGS research tests\nImplement new data analysis software and databases to current system\nOversee the design, maintenance, and implementation of data analysis server (local server and cloud-based server)\nCollaborate with IT team to adhere to policies and procedures related to data security\nBuild and develop system for test validation to fulfil accreditation (e.g. CAP) requirements\nArrangement for preparation of documents, e.g. SOP, manuals, R&D results summary, publication and etc\nProvide training to junior Bioinformatics staffs\n\nRequirements:\n\nDoctoral degree in Genetics, Biology, Biochemistry, Biomedical Sciences, Bioinformatics, Computational Biology, Computer Science, information systems or related field or\nMaster degree in Genetics, Biology, Biochemistry, Biomedical Sciences, Bioinformatics, Computational Biology, Computer Science, information systems or related field with at least 3years\u2019 experience working in the bioinformatics field in industry or academic areas\nProficiency in working in Unix/Linux environment\nHands-on experiences with large-scale genomic data (e.g., WGS, WES, targeted sequencing, etc.) in High-performance computing system is required\nAdvance experiences with different programming languages: Python, R, Perl, or other languages\nExperiences in the following areas: cancer risk, somatic cancer, rare diseases, cell-free DNA sequencing, and single-cell sequencing would be an advantage\nExperiences in setting up data analysis system (e.g. analysis pipeline) for cutting-edge sequencing technology would be an advantage\nGood interpersonal, presentation and communication skills, and teamwork\nGood spoken and written Chinese and English\n\nOffice location: Hong Kong Science Park, Shatin", "employment_types": ["Full Time", "Permanent"], "selling_points": [], "locations": ["Shatin Area"], "categories": ["Information Technology (IT)", "Others", "Sciences, Lab, R&D", "Research & Development (R&D)"], "post_time": "2022-01-18T03:07:34Z", "salary": {"currency": null, "max": null, "min": null, "period": "monthly", "term": null}, "salary_visible": false, "title_keywords": ["manager"], "responsibilities": ["collaborate with", "software", "maintenance", "data", "policies", "analysis", "procedures", "implementation", "design", "develop", "data analysis", "databases"], "requirements": {"degrees": ["degree", "master degree"], "majors": ["biology", "genetics", "computer science"], "languages": ["english", "chinese"], "language_level": ["good"], "hard_skills": ["r&d", "linux", "analysis", "programming", "python", "r", "perl"], "soft_skills": ["communication skills", "cutting-edge", "teamwork", "hands-on", "interpersonal", "presentation"], "languages_combined": [{"language": "english", "language_level": ["good"]}, {"language": "chinese", "language_level": ["good"]}]}, "experience_required": {"duration": [], "field": ["related", "data analysis", "programming"]}}, {"job_id": "100003009055124", "location_code": "hk", "company": "Autotoll Limited", "job_title": "Solutions Architect", "description": "Autotoll is Hong Kong's major Intelligent Transport and Smart City solution provider, as well as being a financial institution with Stored Value Facility License and a Faster Payment System Participant, providing the best solutions and efficient services to our corporate and consumer customers.\n\nWith the constant evolution of our innovative solutions, agility is an integral part of our development process.\u00a0 We are looking for a Solutions Architect as part of the team to assist in new projects and drive the transformation of existing systems.\u00a0 If you are interested in developing industry leading solutions, Autotoll is a great place to grow your career and be part of our winning team.\n\n\nAbout The Role:\n\nBe part of the dynamic team of developers and engineers building modern, robust, DevOps infrastructures;\nInvolve in the all aspects of Autotoll\u2019s Smart Solution strategy from solutions development, bid management, Smart City projects initiation and delivery;\nDevelop end-to-end technology solutions, system architectural design, solution planning, and feasibility study, create technical write ups, scope of work and presentations for proposals and provides input to contract and SLA;\nLead technical discussion with peer architects, developers and project managers to validate design and derive fit-for-purpose solution;\nLead the effort in new technology evaluation and onboarding, followed by establishing new standards, best practices and guidelines;\nAutomate everything in the application lifecycle from design, setup, test, release, update, support, and improve.\n\nAbout You\n\nPositive attitude and a strong commitment to delivering quality work;\nExperience in leading a team of subject matter expert and delivery management;\nSolid architecture experience in DevOps, CI/CD, process automation and application performance monitoring;\nSound knowledge with scalable infrastructure architecture including cloud solutions, operating systems, networking, security, backups and monitoring;\nBachelor's degree or above in Computing or related discipline;\nMinimum 5 years of experience in IT architecture design for large-scale enterprises.\n\nWhat you can get from us:\nOn-the-job training, learning and development\u00a0provided\nExecutive workshops, interest class, corporate purchase discount offered by SHKP\nCompetitive salary and annual leaves\nFlexible working opportunities\nInterested parties, please send full resume with\u00a0expected salary\u00a0and\u00a0available date\u00a0to Human Resources and Administration Department by e-mail or by fax 2111 9459.\n(Data collected will be used for recruitment purpose only.)", "employment_types": ["Full Time", "Permanent"], "selling_points": ["Attractive salary plus performance bonus;", "Good career development opportunities", "5-day work, bank holiday, AL & medical plan"], "locations": ["Kowloon Bay"], "categories": ["Information Technology (IT)", "Software Development", "Others"], "post_time": "2022-01-18T01:15:55Z", "salary": {"currency": null, "max": null, "min": null, "period": "monthly", "term": null}, "salary_visible": false, "title_keywords": ["solutions architect"], "responsibilities": ["quality", "design", "payment", "purchase", "evaluation", "infrastructure", "developing", "presentations", "develop", "architecture", "setup", "operating systems", "management", "monitoring", "backups", "guidelines", "systems", "subject matter expert", "planning"], "requirements": {"degrees": ["degree or above", "bachelor"], "majors": [], "languages": [], "language_level": [], "hard_skills": ["devops", "presentations", "sla", "dynamic", "workshops"], "soft_skills": ["efficient", "flexible", "interested in", "robust", "positive attitude", "dynamic", "learning", "innovative"], "languages_combined": []}, "experience_required": {"duration": ["minimum 5 years"], "field": ["management", "devops", "design", "it", "team"]}}, {"job_id": "100003009052973", "location_code": "hk", "company": "mapwithyou", "job_title": "Programmer / Programmer Trainee (5-day work)", "description": "Programmer / Programmer Trainee (5-day work)\nIT related Certificate, Diploma, High Diploma or Science related Degree\nInterested in IT field\nNo IT experience or fresh graduate will also be considered\u00a0\nExperienced in developing web application software is a plus\nCommitted and willing to learn\nTeam-player, self-motivated\n5 days work\nWe provide on-job training\n\nWe offer competitive remuneration packages and 5-day working week. Excellent potential for promotion. Interested parties please apply by e-mail with\u00a0full resume, expected salary and date of availability.\n\nFor more information, please visit our site at www.mapwithyou.com\n\nPersonal data collected will be used for recruitment purpose only\n", "employment_types": ["Full Time", "Permanent"], "selling_points": [], "locations": ["Tsuen Wan Area"], "categories": ["Information Technology (IT)", "Application Specialist - Software", "Software Development", "Others"], "post_time": "2022-01-17T04:48:08Z", "salary": {"currency": null, "max": null, "min": null, "period": "monthly", "term": null}, "salary_visible": false, "title_keywords": ["programmer", "trainee"], "responsibilities": ["developing", "software"], "requirements": {"degrees": ["high diploma", "fresh graduate", "certificate", "diploma", "degree"], "majors": ["science", "it"], "languages": [], "language_level": [], "hard_skills": ["no", "web", "plus"], "soft_skills": ["self-motivated", "team-player", "interested in", "willing to learn", "committed"], "languages_combined": []}, "experience_required": {"duration": [], "field": ["it experience"]}}, {"job_id": "100003009052736", "location_code": "hk", "company": "The Hong Kong Jockey Club", "job_title": "Assistant Customer Digital Experience Development Manager (UX lead)", "description": "The Job Scope\nYou will:\n\nSupport Customer Digital Experience Development Manager in delivering user centred digital application projects across the Club\u2019s range of digital channels, including mobile app, website, e-commerce and cross-media platforms.\nTransform business analysis, customer feedback and/or market research outcomes in to digital business insights and product requirement.\nResponsible for interaction design of various digital channels in the Club\u2019s\nExpert in user experience design from user\u2019s requirement analysis, through information architecture, wireframes, user flow, behavioural design and prototype for a variety of mobile/web products.\nHaving sophisticated experience in conducting agile research, including needs finding research, conceptual validation, usability testing etc.\nPassionate and skilful for translating research findings into tangible designs\nBe part of the scrum team, work closely with development team to maximize value of sprint deliveries\nDemonstrable experience with Agile methodologies such as Kanban, Scrum and tools such as Jira, Confluence and Slack.\n\nAbout You\nYou should have:\n\nA bachelor degree or above in interaction design, industrial design, computer science, psychology or other relevant disciplines.\nAt least 6 years of proven working experience in Consulting / Digital Solution / Technology project management\nSolid working experience within an agile team on digital products implementation\nStrong interpersonal skills with internal and external stakeholders. Easily understand people idea and turn it into action.\nExcellent written and verbal communication (English and Chinese).\nAn excellent working attitude, self-motivated and being a team player.\nProficiency in design and prototyping software (e.g. Adobe Creative Suite, Sketch, Axure) is a must\nKnowledge in Horse Racing and/or Football betting is a definite advantage\nUnderstanding in latest digital trend, including Gamification and Artificial Intelligence is a plus\nA portfolio demonstration during the interview.\nCandidate with less experience may consider as Senior Officer\n\n\nTerms of Employment\nThe level of appointment will be commensurate with qualifications and experience.\n\nHow to Apply\nPlease send your resume, complete with expected salary and job reference by clicking the Apply Now button\n\nWe are an equal opportunity employer. Personal data provided by job applicants will be used strictly in accordance with the Club's notice to employees and prospective employees relating to the Personal Data (Privacy) Ordinance. A copy of which will be provided immediately upon request.", "employment_types": ["Full Time"], "selling_points": ["Demonstrable experience with Agile methodologies", "6 yr of Consulting / Digital Solution / Technology", "A portfolio demonstration during interview"], "locations": ["Causeway Bay"], "categories": ["Design", "Others", "Information Technology (IT)", "Others", "UI/UX Designer"], "post_time": "2022-01-17T03:52:14Z", "salary": {"currency": null, "max": null, "min": null, "period": null, "term": null}, "salary_visible": false, "title_keywords": ["manager", "lead", "assistant"], "responsibilities": ["mobile app", "software", "consulting", "analysis", "website", "design", "market research", "user experience", "testing", "project management", "implementation", "communication", "business analysis", "personal data", "architecture"], "requirements": {"degrees": ["degree or above", "bachelor"], "majors": ["psychology", "computer science", "design"], "languages": ["english", "chinese"], "language_level": ["excellent"], "hard_skills": ["plus", "agile", "e-commerce", "analysis", "web products", "mobile", "project management", "adobe creative suite"], "soft_skills": ["sophisticated", "passionate", "self-motivated", "agile", "responsible", "communication", "project management", "interpersonal skills", "team player", "creative"], "languages_combined": [{"language": "english", "language_level": ["excellent"]}, {"language": "chinese", "language_level": ["excellent"]}]}, "experience_required": {"duration": ["at least 6 years"], "field": ["research", "consulting", "e-commerce", "development", "design", "testing", "project management", "digital", "media", "team"]}}, {"job_id": "100003009054230", "location_code": "hk", "company": "Linkers International Limited", "job_title": "Web Developer / Programmer (JavaScript)", "description": "RESPONSIBILITIES\u00a0\n\nAssist System Analyst to perform web development and testing\nWork with UI graphic designer, develop web application and perform integration test\nPerform initial feasibility study for web solution for minor enhancement\nLiaise with internal users for system and business application support\u00a0\n\nREQUIREMENTS\n\nHigher Diploma or above in Computer Science, Information Technology or other related discipline\n0-2 year working experience in software development, system solution consultancy or developing programmable documents\nHands-on skills in Vue.js, JavaScript, HTML5, CSS3 and SQL\nFamiliar with React.js, Angular.js, & Node.js is a highly preferable\nGood command of written and spoken English and Chinese (including Putonghua)\nSelf-motivated and positive attitude\u00a0\nGood communication and interpersonal skills\n\nTo apply online, \u00a0please click the Apply button below. For a confidential discussion about this role please contact us on +852 2391 2813.\n\nPersonal data collected will be used for recruitment purposes only.", "employment_types": ["Full Time", "Permanent"], "selling_points": ["Experience in web application development", "Hand-on  Vue.js, JavaScript, HTML5, CSS3, SQL", "In-house working enviorment. Perm with Bonus"], "locations": ["Not Specified"], "categories": ["Information Technology (IT)", "Application Specialist - Software", "Software Development", "Others"], "post_time": "2022-01-17T08:51:46Z", "salary": {"currency": null, "max": null, "min": null, "period": "monthly", "term": null}, "salary_visible": false, "title_keywords": ["developer", "programmer"], "responsibilities": ["liaise with", "develop", "ui", "testing"], "requirements": {"degrees": ["higher diploma or above"], "majors": ["computer science", "information technology"], "languages": ["putonghua", "english", "chinese"], "language_level": ["good command"], "hard_skills": ["sql", "javascript", "angular", "react"], "soft_skills": ["positive attitude", "hands-on", "communication and interpersonal skills", "self-motivated"], "languages_combined": [{"language": "putonghua", "language_level": ["good command"]}, {"language": "english", "language_level": ["good command"]}, {"language": "chinese", "language_level": ["good command"]}]}, "experience_required": {"duration": ["0-2 year"], "field": ["developing", "software development"]}}, {"job_id": "100003009045762", "location_code": "hk", "company": "Manpower Services (Hong Kong) Limited", "job_title": "IT Support (Up to 20k, Welcome IT Fresh Grads)", "description": "Our clients from Telecommunications Industry is now looking for IT Support to join their team.\n\nResponsibilities:\n\nTo provide EUC (End User Computing) day-to-day support, inclusive of Office IT systems, PC hardware / software / connectivity and BYOD users\nTo assist the VDI(VMWare) Project deployment includes user management, profile migration, data migration, troubleshooting and inventory management\n\nRequirements:\n\nHigh Diploma in IT or related discipline;\n1 - 2 years working experience in EUC support; Fresh Graduate with IT Support Intern/PT Exp. is welcomed.\nHands on experience in VDI (VMWare), Microsoft Office and Outlook Applications (troubleshooting & problem solving) and VPN\nFamiliar with PC / Laptop / Phone / Mobile phone / Thin Client;\nService to Senior Management experience is a plus\nGood analytical, PC / device trouble shooting, and problem solving skills;\nGood interpersonal skill and a good team player\nMature, dynamic, work independent and self-motivated\nGood spoken and written English and Cantonese, Mandarin a plus.\n\n**Location: Tsing Yi; Up to 20k + 2 Months Discretionary Bonus;\u00a0Mon. - Fri. / 0900 - 1800\n\nInterested parties please email a MS Word version resume and expected salary to luke.he@manpowergrc.hk and quote the job reference no..", "employment_types": ["Permanent"], "selling_points": ["Internal IT service and operations support", "2 Months Discretionary Bonus", "Fresh Graduate Welcome"], "locations": ["Tsing Yi"], "categories": ["Information Technology (IT)", "Application Specialist - Software", "Support", "Others"], "post_time": "2022-01-13T08:35:54Z", "salary": {"currency": null, "max": null, "min": null, "period": "monthly", "term": null}, "salary_visible": false, "title_keywords": ["it support"], "responsibilities": ["management", "software", "data", "systems", "troubleshooting", "inventory management", "hardware", "migration"], "requirements": {"degrees": ["high diploma", "fresh graduate"], "majors": ["it"], "languages": ["cantonese", "english", "mandarin"], "language_level": ["good"], "hard_skills": ["plus", "vmware", "microsoft office", "euc", "problem solving", "mobile", "dynamic", "outlook", "vpn", "pc", "problem solving skills"], "soft_skills": ["good team player", "self-motivated", "independent", "troubleshooting", "mature", "interpersonal skill", "problem solving", "hands on", "dynamic", "problem solving skills"], "languages_combined": [{"language": "cantonese", "language_level": ["good"]}, {"language": "english", "language_level": ["good"]}, {"language": "mandarin", "language_level": ["good"]}]}, "experience_required": {"duration": ["1 - 2 years"], "field": ["management", "troubleshooting"]}}, {"job_id": "100003009055592", "location_code": "hk", "company": "Randstad Hong Kong Limited", "job_title": "Unity Developer - AR/VR/Metaverse Project (25K - 35K + Bonus)", "description": "about the company.\n\nOur client is a fast growing business who combines creativity and storytelling with immersive digital, mobile, AR/VR, E-commerce and NFT technologies. To assist the existing and upcoming new product development, they are looking for a Developer who specialize in development using C# Unity for development and willing to pick up new technologies for building VR experience. Candidates from both gaming or agency background will also be considered.\n\nThis is a great opportunity to have a big impact on the direction of the business moving forward, you will have lots of autonomy and will be part of a passionate team.\n\nabout the job.\n\nResearch, design and develop the AR/VR applications using cutting-edge technology\nWork closely with other developers, designers, 3D artists and business partners to enhance and implement new features for the new projects to meet business requirements\nCollaborate with designers and business stakeholders to ensure the products with best user experience\nParticipation in new products/functions brainstorming\nIncorporating user feedback into tech solutions\n\nskills & experiences required.\n\nAssociate Degree/Diploma or above in Computer Science or relevant discipline\nMinimum 3+ years of relevant experience in development\nSolid experience in Unity Engine for C# development is a must\nExperience in Unity material, lighting systems and render settings etc.\nKnowledge of developing AR/VR experience for mobile application would be advantageous\nKnowledge of AR Foundation/ARCore Extensions or other 3rd party tools for Unity is a plus\nGood problem-solving skill, and able to pick up new technologies for VR experience such as A-frame/three.js\nCandidates who with less experience but have proven project experience and portfolio/gaming industry background will also be considered\n\nIf you're interested in this exciting opportunity please don't delay and click APPLY NOW or for more information you can reach out to Kelvin Chu on +852 2232-3411 or kelvin.chu@ randstad.com.hk", "employment_types": ["Full Time", "Permanent"], "selling_points": ["Permanent Headcount", "Cutting-edge Tech & Exciting Innovation Projects", "Result-Oriented with Flexible Working Hours"], "locations": ["Not Specified"], "categories": ["Information Technology (IT)", "Application Specialist - Software", "Software Development", "Others"], "post_time": "2022-01-18T02:46:21Z", "salary": {"currency": "HKD", "max": 34999, "min": 25000, "period": "monthly", "term": null}, "salary_visible": true, "title_keywords": ["developer"], "responsibilities": ["collaborate with", "ar", "systems", "design and develop", "user experience", "developing", "meet business requirements"], "requirements": {"degrees": ["associate degree", "diploma or above"], "majors": ["computer science"], "languages": [], "language_level": [], "hard_skills": ["plus", "ar", "e-commerce", "problem-solving", "mobile", "unity", "c#"], "soft_skills": ["passionate", "problem-solving", "interested in", "cutting-edge"], "languages_combined": []}, "experience_required": {"duration": ["minimum 3+ years"], "field": ["development", "developing", "business", "relevant experience", "developer", "product development"]}}, {"job_id": "100003009055276", "location_code": "hk", "company": "Seamatch Asia Limited", "job_title": "Data Analysts / Senior Data Analysts / Trainee Analysts x 10", "description": "\nOur client is one of the largest online shopping ecommerce platforms in Hong Kong. They are looking for new team members to join their data science teams.\u00a0\u00a0\n\nData Analysts / Senior Data Analysts / Trainee Analysts\n\n20K (entry levels) to around 60K (senior levels)\n\n\nResponsibilities:\n\nAgile team collaboration in continual development of Company's big data analytics platform and existing data governance frameworks\nData analysis, data discovery and metadata management for business intelligence (BI), quantitative modeling, machine learning and predictive analytics projects\nData warehousing, data mining and extract/transform/load (ETL) integration in cloud and on-premise environments\nData visualization, BI reporting, data dashboard design & development\nRequirements:\n\nDegree holder in IT and data sciences related subjects\nOver or around 3 years of technical experience in data analytics, business intelligence (BI), data warehousing, or related functional areas\nGood knowledge of major data programming languages and analytic tools such as Python, Hadoop, Tableau, MS SQL, Oracle RDBMS, PL SQL, Azure Cloud, Microsoft Power BI, Excel Power Query, Google\u00a0Analytics, Google Data Studio highly preferred\nFluent Chinese and English communication with local team members\nMore experience will be considered as Assistant Manager (Data Analysis)\nLess experience or Fresh will also consider for junior post\n\nCustomer Data Analyst (SAS)\n\nYour role:\n\nDevelop Dashboards to facilitate efficient data analysis for product performance, customer profiles and campaign effectiveness;\nConduct quantitative analysis and data mining to support management decisions and provide data-driven recommendations;\nOrganize and prepare regular\u00a0reports relating to business performance and service usage;\nConduct user acceptance test of in-house-developed applications.\n\nTo succeed in this role\n\nUniversity graduate in Computer Science, Information Technology, Data Science, Statistics or relevant discipline;\n1 \u2013 4 years\u2019 relevant experience, preferably in data analysis, database programming or database management\nProficient in SAS, SQL, Python or other data mining tools;\nPractical experience in data visualization tools (e.g. Qlik View/Sense, Power BI or Tableau);\nGood analytical and problem solving skills, able to work under tight timeline;\nSelf-motivated and able to accomplish multiple tasks with minimal supervision;\nGood\u00a0interpersonal and communication skills and\u00a0able to work with people at all levels;\nGood command in both spoken and written English;\nCandidate with more experience will be considered for the position of Senior Customer Data Analyst.\n\n\n", "employment_types": ["Full Time", "Permanent"], "selling_points": ["Data Analyst, Senior Data Analyst, Trainee Analyst", "Big data analysis, business intelligence (BI), SAS", "Data warehousing, data integration, data mining"], "locations": ["Tsim Sha Tsui"], "categories": ["Information Technology (IT)", "DBA", "Others", "Data Scientist"], "post_time": "2022-01-18T02:00:24Z", "salary": {"currency": null, "max": null, "min": null, "period": "monthly", "term": null}, "salary_visible": false, "title_keywords": ["trainee"], "responsibilities": ["warehousing", "management", "reporting", "visualization", "data", "big data", "design", "data analysis", "data mining"], "requirements": {"degrees": ["university graduate", "degree holder"], "majors": ["data science", "statistics", "information technology", "it", "computer science"], "languages": ["english", "chinese"], "language_level": ["good command", "fluent"], "hard_skills": ["excel", "bi", "azure", "business intelligence", "data mining", "tableau", "database programming", "ms sql", "sas", "data analytics", "sql", "python", "oracle", "google analytics", "analysis", "programming", "data visualization", "problem solving skills", "pl"], "soft_skills": ["efficient", "communication skills", "self-motivated", "multiple tasks", "communication", "analytical and problem solving skills", "interpersonal", "driven"], "languages_combined": [{"language": "english", "language_level": ["good command", "fluent"]}, {"language": "chinese", "language_level": ["fluent"]}]}, "experience_required": {"duration": ["3 years", "4 years"], "field": ["related", "data analysis", "business", "relevant experience", "database management", "database", "programming"]}}, {"job_id": "100003009049385", "location_code": "hk", "company": "Sontec Technology Company Ltd", "job_title": "Sales Manager (POS / HR Solution)", "description": "Responsibilities:\n\nResponsible for planning, executing, monitoring and directing sales performance\nDevelop sales activities for existing and potential customers to achieve sales targets\nResponsible for project management and provide pre-sales and pro-sales consultant services\nLiaise with customers to understand their needs and collect user requirements\nIdentify and develop new business opportunities to increase market share and revenue\n\nRequirements:\n\nDegree holder or above\nMinimum 5 years sales experience in IT industry, of which 2 years should be at supervisory level, preferably in application software\nStrong and proven sales track record with strong team building and leadership skills\nSelf-motivated, aggressive, independent, energetic with excellent interpersonal and presentation skills\nStrong problem resolution with good decision making and analytical skills\nGood command of written and spoken English, Cantonese and Mandarin\nFamiliarity with consultative / solution selling methodologies is preferred\nImmediate available is preferred\nThe working location is at Kwun Tong (King Yip Street).\n\nWe offer 5-day work week, career advancement opportunities and attractive remuneration package to the right candidate. Interested parties, please send the full resume & expected salary to Human Resources Department via Apply Now.\n\n(All information submitted will be used for recruitment purpose only and will be destroyed after completion of the process.)", "employment_types": ["Full Time", "Permanent"], "selling_points": [], "locations": ["Kwun Tong"], "categories": ["Information Technology (IT)", "IT Project Management / Team Lead", "Software Development", "Others"], "post_time": "2022-01-14T08:32:33Z", "salary": {"currency": null, "max": null, "min": null, "period": "monthly", "term": null}, "salary_visible": false, "title_keywords": ["hr", "sales manager"], "responsibilities": ["sales activities", "develop new business", "sales performance", "monitoring", "develop", "project management", "executing", "liaise with", "planning"], "requirements": {"degrees": ["degree holder"], "majors": [], "languages": ["cantonese", "english", "mandarin"], "language_level": ["good command"], "hard_skills": ["analytical skills"], "soft_skills": ["self-motivated", "independent", "leadership skills", "analytical skills", "presentation skills", "energetic", "interpersonal", "decision making"], "languages_combined": [{"language": "cantonese", "language_level": ["good command"]}, {"language": "english", "language_level": ["good command"]}, {"language": "mandarin", "language_level": ["good command"]}]}, "experience_required": {"duration": ["2 years", "minimum 5 years"], "field": ["supervisory level", "it"]}}, {"job_id": "100003009050712", "location_code": "hk", "company": "Hutchison Telecommunications (Hong Kong) Limited", "job_title": "IT Operation Officer", "description": "Responsibilities:\n\nManage Data Center, Operations and Service desk function of IT\u00a0\nCoordinate with internal and external parties on support system maintenance, system failover and annual drill\u00a0\nAssist in preparing, review and update various operations policies and procedures on regular basis\u00a0\nAssist in ad hoc tasks / projects as required\u00a0\n\nRequirements:\n\nAssociate degree or Higher Diploma holder\u00a0in\u00a0Information Technology/ Date Centre/ Telecommunications or related discipline\n3 years or above working experiences in IT operation\u00a0\nProficient in MS Office - Excel, knowledge of Linux, Windows and VMWare is advantage\u00a0\nIndependent, detail-minded and able to work under pressure\nGood command of written and spoken English and Chinese\n\nApart from competitive remuneration package and exciting opportunity for career development within the Group, we provide attractive employee benefits such as free company shuttle, free company SIM card and preferential SIM plan offers, comprehensive medical & insurance schemes, as well as full range of other employee well-being provisions.\u00a0\n\nInterested parties, please apply with full resume, present and expected salary, by clicking \u201cAPPLY NOW\u201d. Please quote the reference number on the e-mail subject.\n\nWe are an equal opportunity employer and welcome applications from all qualified candidates. Personal data collected will be treated in the strictest confidence and handled confidentially by authorised personnel for recruitment-related purposes only within the CK Hutchison Group of companies. The personal data of unsuccessful applicants will be destroyed after the recruitment exercise pursuant to the requirements of the Personal Data (Privacy) Ordinance in Hong Kong.", "employment_types": ["Full Time", "Permanent"], "selling_points": [], "locations": ["Tsing Yi"], "categories": ["Information Technology (IT)", "Support", "Others"], "post_time": "2022-01-14T11:13:29Z", "salary": {"currency": null, "max": null, "min": null, "period": "monthly", "term": null}, "salary_visible": false, "title_keywords": ["operation officer"], "responsibilities": ["maintenance", "data", "operations", "policies", "internal and external parties", "coordinate with", "review", "procedures", "ad hoc tasks"], "requirements": {"degrees": ["associate degree", "higher diploma holder"], "majors": ["information technology"], "languages": ["english", "chinese"], "language_level": ["good command"], "hard_skills": ["excel", "vmware", "linux", "ms office"], "soft_skills": ["detail-minded", "comprehensive", "independent", "work under pressure"], "languages_combined": [{"language": "english", "language_level": ["good command"]}, {"language": "chinese", "language_level": ["good command"]}]}, "experience_required": {"duration": ["3 years"], "field": ["operation", "it"]}}]