[{"job_id": "100003009054062", "location_code": "hk", "company": "EC Healthcare", "job_title": "Manager / Assistant Manager, Business Integration", "description": "Working closely with integration partners as well as internal cross function teams, this position is responsible for the smooth transition of post M&A business integration to achieve the set vision and synergy.\n\n\u00a0Job Responsibilities:\n\nLead discussion and drive execution on vision and strategy of the acquisition\nDevelop deep understanding of responsible pillar / discipline to drive value creation and synergy with group business\nAct as single point of contact for M&A partner\nDevelop and foster close working relationship with M&A partner and internal departments\nProject manage and coordinate with internal departments on integration tasks to ensure smooth integration of the M&A business\nLead business readiness planning and activities including communications, training etc. with relevant departments\nSetup governance structure and lead regular update on integration progress and escalate issues if required\nLead risks and issues management during and post M&A integration\nLead regular review of post M&A performance\n\nJob Requirements:\n\nDegree holder in Business, Communications or related discipline\nAt least 5 years of experience in business programme or project management\nExcellent communications, interpersonal, planning and organizing skills\nExperience in change management will be highly valued\nExperience in healthcare industry a definite advantage\nWilling to understand detail and possess a problem-solving mindset\nAbility to look at big picture and think strategically\nGood command of both spoken & written English and Chinese", "employment_types": ["Full Time"], "selling_points": ["Working closely with integration partners", "Smooth transition of post M&A business integration", "Discussion & drive execution on vision & strategy"], "locations": ["Mong Kok"], "categories": ["Information Technology (IT)", "IT Project Management / Team Lead", "IT Management", "Product Management / Business Analyst"], "post_time": "2022-01-17T08:15:57Z", "salary": {"currency": null, "max": null, "min": null, "period": "monthly", "term": null}, "salary_visible": false, "title_keywords": ["manager", "assistant manager,"], "responsibilities": ["management", "coordinate with", "develop", "regular review", "contact", "setup", "planning"], "requirements": {"degrees": ["degree holder"], "majors": ["business", "communications"], "languages": ["english", "chinese"], "language_level": ["good command"], "hard_skills": ["project management", "problem-solving"], "soft_skills": ["project management", "problem-solving", "interpersonal", "think strategically"], "languages_combined": [{"language": "english", "language_level": ["good command"]}, {"language": "chinese", "language_level": ["good command"]}]}, "experience_required": {"duration": ["at least 5 years"], "field": ["project management", "management", "business", "healthcare industry"]}}, {"job_id": "100003009054621", "location_code": "hk", "company": "CK Hutchison Holdings Limited", "job_title": "Senior Systems Analyst / Systems Analyst", "description": "CK Hutchison, head office of a diversified group of companies with over 18,000 employees in Hong Kong and an additional 279,300 employees worldwide, invites high calibre and self-motivated individuals to join our organisation.\n\n\nThe Group Information Services Department, located in Hunghom, strives to serve the system needs of Head Office and is responsible for coordinating the information technology related services within the CK Hutchison Group.\u00a0\nResponsibilities:\n\nPlay key role in system development life cycle from requirement study, system analysis and design, program development, testing, implementation to maintenance and support to internal Group companies and end-users\nParticipate or manage implementation or upgrade cloud application projects\nDepending on the applicant\u2019s background, s/he will responsible for system on Oracle E-Business Suite Financial, Human Resources, or other Oracle Cloud or on-premises application systems\nRequirements:\nUniversity graduate or equivalent in computing related disciplines\nSolid experience in Oracle E-Business Suite Applications, e.g. ERP or HRMS\nExperience in Oracle Fusion Cloud would be an advantage\nStrong technical skill on Oracle Forms & Reports, BI Publisher, RESTful API, SOAP, Linux scripting, PowerShell or VBA programming (MS Excel macros)\nKnowledge in Fusion Cloud or EPM Cloud would also be an advantage\nA team player with good interpersonal skills and \u201ccan-do\u201d attitude\nAdaptable in regards to learning and understanding new technologies\nAttentive to details and able to work on assigned tasks with minimum supervision\nProficiency in both written and spoken English and Chinese\n*Applicant with less experience will be considered as Analyst Programmer or Programmer\nSalary and benefits will commensurate with experience and competence. Please click the \u201cAPPLY NOW\u201d button and include a detailed resume with indication of expected salary.\u00a0\u00a0\nWe are an equal opportunity employer and welcome applications from all qualified candidates. Personal data collected will be treated in the strictest confidence and handled confidentially by authorised personnel for recruitment-related purposes only within the CK Hutchison Group of companies.\u00a0\nApplicants not having heard from us within six weeks of the date of application may consider their applications unsuccessful. The personal data of unsuccessful applicants will be destroyed after the recruitment exercise pursuant to the requirements of the Personal Data (Privacy) Ordinance in Hong Kong.\u00a0", "employment_types": ["Full Time"], "selling_points": ["Head Office", "Oracle E-Business Suite Applications (ERP or HRMS)", "Oracle Fusion Cloud"], "locations": ["Hung Hom"], "categories": ["Information Technology (IT)", "Application Specialist - Software", "Product Management / Business Analyst", "Software Development"], "post_time": "2022-01-17T10:18:36Z", "salary": {"currency": null, "max": null, "min": null, "period": "monthly", "term": null}, "salary_visible": false, "title_keywords": ["analyst"], "responsibilities": ["maintenance", "analysis", "implementation", "design", "testing", "application systems"], "requirements": {"degrees": ["university graduate"], "majors": ["related disciplines"], "languages": ["english", "chinese"], "language_level": ["proficiency"], "hard_skills": ["linux", "restful api", "bi", "vba", "erp", "ms excel", "powershell", "programming", "publisher", "oracle"], "soft_skills": ["attentive to details", "adaptable", "learning", "interpersonal skills", "can-do", "team player", "technical skill"], "languages_combined": [{"language": "english", "language_level": ["proficiency"]}, {"language": "chinese", "language_level": ["proficiency"]}]}, "experience_required": {"duration": [], "field": ["business"]}}, {"job_id": "100003009054520", "location_code": "hk", "company": "Fano Labs Limited", "job_title": "Business Analyst", "description": "Office location: Hong Kong Science Park\n\nResponsibilities:\n\nLearn and master product features and acts as application specialist to present our product\u00a0values\u00a0to clients\nGather user requirements and translate\u00a0them into actionable items for implementation\nPrepare project/ product document such as\u00a0User requirement document, Use cases, User Manual, UAT Test Plan etc\nReceive and manage clients\u2019 reported issues and provide initial investigation and response to the client\nTrouble shoot on issue by analysing error log and keep track of issue status and follow up in well manner\nWork across multiple internal teams and external partners\u00a0to ensure project success\nOffer professional user training and support to clients on our enterprise products\nKeen on learning, fast on picking up new technology and applying them in projects with practical\u00a0deliverables\n\nRequirements:\n\nBachelor degree in any relevant disciplines (Finance, Business Management, Project Management, Information System or Computer Science)\nMinimum 2+ years of experience as consultant/support role in application/software project delivery\nSound knowledge on SaaS product, cloud/ on-premise hosting, project management approach and web/ app application is an advantage\u00a0\nExcellent communication and presentation skills\nFluent in English, Cantonese and Mandarin\nFresh graduate with passion in the digital industry will also be considered\n\nPlus\n\nPrevious\u00a0project and account management\u00a0experience\u00a0is highly\u00a0preferred\nExperience with python programming, AI technology, micro-service architectures is an advantage (Docker, RESTful API...) is a plus\nHands-on experience in gathering business requirements or application trouble-shooting is an advantage", "employment_types": ["Full Time", "Permanent"], "selling_points": [], "locations": ["Shatin Area"], "categories": ["Information Technology (IT)", "IT Project Management / Team Lead", "Product Management / Business Analyst"], "post_time": "2022-01-17T09:51:26Z", "salary": {"currency": null, "max": null, "min": null, "period": "monthly", "term": null}, "salary_visible": false, "title_keywords": ["business analyst"], "responsibilities": ["user requirement", "uat", "teams", "implementation", "investigation", "plan"], "requirements": {"degrees": ["degree", "bachelor", "fresh graduate"], "majors": ["finance", "project management", "business", "computer science"], "languages": ["cantonese", "english", "mandarin"], "language_level": ["fluent"], "hard_skills": ["business management", "plus", "restful api", "web", "ai", "information system", "project management", "programming", "python"], "soft_skills": ["passion in", "communication", "project management", "presentation skills", "hands-on"], "languages_combined": [{"language": "cantonese", "language_level": ["fluent"]}, {"language": "english", "language_level": ["fluent"]}, {"language": "mandarin", "language_level": ["fluent"]}]}, "experience_required": {"duration": ["minimum 2+ years"], "field": ["business", "account management", "programming"]}}, {"job_id": "100003009055263", "location_code": "hk", "company": "Accenture Company Limited", "job_title": "Interactive \u2013 Digital Business Analyst", "description": "About Accenture\uff1a\n\nAccenture is a global professional services company with leading capabilities in digital, cloud and security. Combining unmatched experience and specialized skills across more than 40 industries, we offer Strategy and Consulting, Interactive, Technology and Operations services\u2014all powered by the world\u2019s largest network of Advanced Technology and Intelligent Operations centers. Our 506,000 people deliver on the promise of technology and human ingenuity every day, serving clients in more than 120 countries. We embrace the power of change to create value and shared success for our clients, people, shareholders, partners and communities.\n\nThe company has been operating in Greater China for over 30 years. Today, it has more than 17,000 people servicing clients across the region with offices in the cities including Beijing, Shanghai, Dalian, Chengdu, Guangzhou, Shenzhen, Hong Kong and Taipei. As a trusted Partner of Choice for digital transformation, Accenture is bringing more innovation to the business and technology ecosystems and helping Chinese enterprises and the government to embrace digitization and enhance global competitiveness to succeed in the new era.\n\nFor more information about Accenture, please visit its corporate homepage www.accenture.com and its Greater China homepage www.accenture.cn .\n\n\nAbout Accenture Interactive\uff1a\n\nAs one of the key services under Accenture, Accenture Interactive is in the business of Experience. We connect deep human and business insights with the possibilities of technology to define and deliver new realities. We're committed to helping clients design, build, communicate and run Experiences that make peoples' lives better, more productive and more meaningful. Visit http://www.accentureinteractive.com to find out more about us.\n\n\nKey Responsibilities\n\nWork in conjunction with different parties to conceptualize and propose solution approaches\u00a0\nDrive and challenge business units on their assumptions of how they will successfully execute the business plans\u00a0\nElicit requirements using interviews, document analysis, requirements workshops, surveys, business process descriptions, use cases, scenarios, and task and workflow analysis for major and minor projects\u00a0\nPlan and implement analytics to projects for different clients with tasks including but not limited to data tracking, tag management, data visualization, reporting & analysis and developing insights & recommendation\u00a0\nTransform data to insights for business development, strategies or optimization approaches\u00a0\nCreate high level and detailed level requirements specifications for major and minor projects\u00a0\nGenerate business\u00a0requirements\u00a0and use cases which documents business needs, rules and details\u00a0\nIdentify and document constraints, assumptions and risks associated with business requirements\u00a0\nDocument gaps in projects whilst providing potential solutions\u00a0\nPrepare business case\u00a0\nMaintain timely communications to business stakeholders throughout the project life cycle to ensure common understanding of the requirements and the impact to the business area\u00a0\n\nExperience, Attributes and Qualifications:\n\nDegree in\u00a0Information Management,\u00a0Computer Science, Information Technology, Business or related area\u00a0\n4-5+\u00a0years of relevant experience in Business Analyst and/or Digital Data Analytics\u00a0role, preferably in a consulting environment\nMinimum of 2 years of experience using, implementing, and / or customizing digital analytics and tag management solutions (e.g., Adobe, Google, Tealium, etc.)\nAgile experience and digital experience\u00a0preferred\u00a0(e.g. Digital Transformation,\u00a0eCommerce, Digital Marketing, O2O Digital Channels, etc.)\u00a0\nUnderstanding of design thinking\u00a0\nExperienced in executing implementation digital projects\u00a0\nStrong background in\u00a0digital\u00a0business analysis and/or system analysis\u00a0\nStrong analytical mind with excellent relationship management\u00a0\nExcellent verbal and written communication skills and the ability to interact professionally with diverse group of stakeholders\u00a0\nFluent Cantonese, English and Mandarin is a must\u00a0\nAble to legally work in\u00a0Hong Kong", "employment_types": ["Full Time", "Permanent"], "selling_points": ["4-5+ years of relevant experience", "Digital Transformation Projects", "IT Consulting"], "locations": ["Not Specified"], "categories": ["Information Technology (IT)", "IT Project Management / Team Lead", "Product Management / Business Analyst", "Technical / Functional Consulting"], "post_time": "2022-01-18T01:58:12Z", "salary": {"currency": null, "max": null, "min": null, "period": "monthly", "term": null}, "salary_visible": false, "title_keywords": ["business analyst"], "responsibilities": ["visualization", "consulting", "data", "operations", "business plans", "design", "communication", "business process", "maintain", "plan", "developing", "implementation", "reporting", "management", "specifications", "digital marketing", "executing", "tracking", "analysis", "business analysis"], "requirements": {"degrees": ["degree"], "majors": ["business", "computer science", "information technology"], "languages": ["cantonese", "english", "chinese", "mandarin"], "language_level": ["fluent"], "hard_skills": ["agile", "data analytics", "analysis", "make", "adobe", "data visualization", "workshops"], "soft_skills": ["productive", "communication skills", "advanced", "agile", "timely", "deep", "committed", "diverse", "analytical mind", "detailed"], "languages_combined": [{"language": "cantonese", "language_level": ["fluent"]}, {"language": "english", "language_level": []}, {"language": "chinese", "language_level": []}, {"language": "mandarin", "language_level": []}]}, "experience_required": {"duration": ["minimum of 2 years", "5+ years"], "field": ["management", "consulting", "design", "business", "relevant experience", "digital"]}}, {"job_id": "100003009053176", "location_code": "hk", "company": "Arup", "job_title": "Digital Business Analyst", "description": "A career at Arup offers you the chance to make a positive difference in the world. Independently owned and independently minded, we attract a diverse mix of people to work on ground-breaking global projects. We have an ambitious commitment to be the digital leader in the built environment and have digital teams and experts all over the world, who collaborate on world-leading software, data and technology projects and products. Being a global team means we value people with diverse experiences, backgrounds, specialisms and skills.\u00a0\nThe role\u00a0\nAs a business analyst, you will join a growing team that contribute to the digital delivery portfolio within Arup. Our technology projects underpin Arup\u2019s digital strategy, which is focused on data, products and automation. You will work with stakeholders and users across the organisation to identify opportunities, articulate and prioritise business needs, and propose or design deliverable solutions that help make the strategy a reality. We are not looking for someone to purely gather requirements or write up processes \u2013 the role is an opportunity to shape and contribute to our digital transformation. The role is based in our Hong Kong office and will be part of a geographically diverse, remote team.\nThis role will form part of a geographically distributed team of 8 staff, reporting into the lead business analyst based in London.\n\u201cWe are always challenging ourselves and the people around us to think differently so that we can understand our business problems better and develop creative solutions. No two projects are ever the same \u2013 each presents a unique set of challenges as well as opportunities to acquire new knowledge, learn new skills, and build new connections with colleagues from different disciplines across the globe.\u201d\nMariah, Sydney, Australia\nYou should apply if:\nYou are motivated by the potential of technology to transform a global business\nYou enjoy working with diverse stakeholders to build trusting relationships that leverage your interpersonal and communication skills\nYou are curious and relish the opportunity to deliver products and solutions that hit the sweet spot between competing or ambiguous demands \u00a0\nResponsibilities of the role include:\nConsult with business leaders to collaboratively articulate needs and identify opportunities\nFacilitate, influence, problem-solve and negotiate to agree requirements across diverse cross-functional stakeholder groups\nDesign and validate the user experience to ensure quality outcomes\nFormulate alternate solutions to business problems and conduct feasibility assessments\nProduct management of software products through the product delivery lifecycle\nWork closely with developers, quality assurance, business change and support teams to ensure product quality, and support effective business change and benefits realisation\nDrive continuous improvement and work for the overall success of the team and the firm\nRequirements and skills\nEssential\u00a0skills and knowledge:\nExperience of having worked on projects with highly satisfied sponsors and end users, having achieved tangible results and business outcomes, leading to value creation and benefits realisation\nCapable of articulating the value of business analysis when engaging with stakeholders, and calling upon a range of business analysis techniques when eliciting requirements\nExperience working with different delivery methodologies, with a focus on agile and iterative value creation in a user-centred design environment\nProven track record in software product development, data or automation projects in a cloud-oriented, secure, global landscape\nExperience working with diverse teams across several global locations, time zones or cultural backgrounds\nDesirable experience:\nSeveral years of experience in the Architecture, Engineering & Construction sector, or the technology department of a large global organisation, ideally as a business analyst\u00a0(or similar) delivering digital technology projects\nExperience with user experience design and information architecture\nFamiliarity with data, analytics, business intelligence, data science, or metrics and KPIs\nUnderstanding of policy and operating model development in an innovative stakeholder environment\nProficiency in Mandarin (both verbal and written) would be advantageous but not essential\nRequired behaviours:\nA passion for diversity,\u00a0recognising\u00a0the innovation and competitive edge that comes from a diverse highly skilled team where equal opportunities are truly valued\nTake accountability for delivery, being proactive and able to consider what else could be delivered to add value to customers\nExcellent relationship management and communication skills with both non-technical and technical audiences and building long-term collaborative connections\u00a0\nStrong business acumen and commercial\u00a0mindset\nAble to find common ground and accommodate different points of view\nAble to lead workshops and engage in collective problem-solving\nAble to influence others to consider your point of view and gain support and agreement for plans, changes and new approaches\nComfortable with ambiguity, seeking clarity from stakeholders, and being able to challenge the status quo with creative and innovative solutions\nSeveral members of our team have transferred into business analysis from roles outside of technology, or from project / scrum management, business architecture, or from other professions with analytical or collaborative backgrounds. Please\u202fdon\u2019t be discouraged if you don\u2019t meet every point above \u2013 if you meet\u202fmost and\u202fare strongly motivated by the role and willing to learn, we are still interested in hearing from you.\u00a0\n\nWe offer a competitive remuneration package commensurate with qualifications and experience to the right candidate including Global Profit Share scheme, additional fringe benefits of maternity / paternity leave and long-term career development opportunities.\n\nFor interested applicants, please click \u201cApply Now\u201d to submit your online application.\n\nPersonal data collected will be used for recruitment purpose only. Applicants not contacted within 8 weeks may consider their applications unsuccessful.", "employment_types": ["Full Time", "Permanent"], "selling_points": [], "locations": ["Kowloon City"], "categories": ["Information Technology (IT)", "Product Management / Business Analyst", "Others"], "post_time": "2022-01-17T06:18:21Z", "salary": {"currency": null, "max": null, "min": null, "period": null, "term": null}, "salary_visible": false, "title_keywords": ["business analyst"], "responsibilities": ["management", "software", "quality", "user experience", "design", "teams"], "requirements": {"degrees": [], "majors": [], "languages": ["mandarin"], "language_level": ["proficiency"], "hard_skills": ["agile", "analysis", "problem-solving", "scheme", "workshops", "focus", "business intelligence", "acumen"], "soft_skills": ["communication skills", "proactive", "capable", "agile", "passion for", "accountability", "creative", "problem-solving", "interested in", "willing to learn", "collaborative", "diverse", "motivated", "organisation", "business acumen", "focus", "innovative"], "languages_combined": [{"language": "mandarin", "language_level": ["proficiency"]}]}, "experience_required": {"duration": [], "field": ["engineering", "development", "design", "business", "digital", "construction"]}}, {"job_id": "100003009052121", "location_code": "hk", "company": "Optimum Solutions (Hong Kong) Limited", "job_title": "Senior Business Analyst - Insurance", "description": "Responsibilities:\n\nCollaborate with Product Owners and different business stakeholders to understand business challenges, identify user needs to deliver the product vision\nConduct analysis and drive workshops to define forward looking business requirements and assist in defining product roadmap\nWork closely with both business and technology stakeholders to identify problems, elicit key business needs and create a prioritized backlog of requirements based on business value.\nTranslate business, functional, and technical requirements into user stories and with clear acceptance criteria for development within agile teams.\nCollaborate with UX and UI teams to ensure the usability needs are met and requirements are reflected appropriately\nSupplement business requirements as needed with business process flows, data mapping and gap analysis\nVerify requirements for completeness, consistency, comprehensibility, feasibility, and conformity to standards\nWork closely with technical development teams to provide functional inputs for system impact analysis and clarify questions as needed\nWork closely within the Agile development teams to ensure development of the backlog items prioritized for the sprint.\nOwn a section of the backlog of requirements and act as the SME and bridge between business and technology.\nContribute as a functional expert in a defined Insurance domain/business area as part of business competency centre\nAssist in performing market analysis and benchmarking on key business areas to understand gap compared to competition on business focus areas\nAssist in user on-boarding to product with documentation and user training as needed\n\nExperience:\n\n\nUniversity Graduate and above\nMin 5 years of experience in Insurance industry with proven experience as Business, Functional SME or Product Owner or Business Analyst\n6+ years\u2019 experience in sizable IT projects or large organizations acting in the capacity of a Business Analyst\nExperience and knowledge of core insurance products, channels, customer behaviours and any related technologies\nAreas in Insurance such as PoS solutions or PAS, underwriting transformation, Product Configuration are necessary experiences.\nExperience in all phases of the software development lifecycle, and with a broad range of platforms, including transitioning from legacy systems to digital.\nExperience and capabilities in handling multiple projects at once would be very advantageous.\nExperience and skills within Business Analysis.\nBusiness Analysis Skills, Stakeholder Management Skills, Requirements Documentation Skills, and Facilitation skills are necessary skills\nExperience with Migration from Legacy to Digital will be very advantageous.\nExperience in Agile and Agile Toolsets (JIRA, Confluence) would be an advantage\nAbility to work in Waterfall, Hybrid or Agile approaches as per project needs\nAbility to speak in business and technology terms, as well as the ability to effectively communicate both internally and externally\nMust be able to break problems down, analyse data, drill into problem statements, ask the right questions to really understand root causes and then solution around issue to drive business value.\nAble to work in a complex environment with a mix of technologies and different levels of IT maturities across multiple business unit.\nMust possess good problem-solving skills for large complicated and broad issues and able to work independently, with keen attention to details\nExcellent communication, collaboration, and inter-personnel skills\nExcellent influencing and negotiation skills with stakeholders\nFluent in English\u00a0", "employment_types": ["Contract"], "selling_points": ["Agile Methodology", "Insurance", "English Fluency"], "locations": ["Tai Koo"], "categories": ["Information Technology (IT)", "Product Management / Business Analyst", "Software Development", "Insurance", "Others"], "post_time": "2022-01-17T02:08:39Z", "salary": {"currency": null, "max": null, "min": null, "period": "monthly", "term": null}, "salary_visible": false, "title_keywords": ["senior business analyst"], "responsibilities": ["collaborate with", "software", "data", "agile development", "communication", "business process", "sme", "configuration", "teams", "migration", "ui", "management", "market analysis", "documentation", "analysis", "systems", "business analysis", "multiple projects", "insurance", "analyse"], "requirements": {"degrees": ["university graduate"], "majors": [], "languages": ["english"], "language_level": ["fluent"], "hard_skills": ["documentation", "agile", "pos", "analysis", "gap", "workshops", "problem-solving skills", "focus"], "soft_skills": ["work independently", "agile", "keen", "clear", "communication", "negotiation skills", "attention to details", "problem-solving skills", "focus"], "languages_combined": [{"language": "english", "language_level": ["fluent"]}]}, "experience_required": {"duration": ["6+ years", "min 5 years"], "field": ["underwriting", "insurance products", "related", "insurance industry", "business", "it", "software development", "business analysis", "digital", "insurance"]}}, {"job_id": "100003009052578", "location_code": "hk", "company": "Ricoh Hong Kong Limited", "job_title": "Business Analyst", "description": "Responsibilities\n\nCoordinate and communicate with business users for production products\nAssist Business Analysts to ensure IT deliverables that would satisfy business requirements and would achieve anticipated business benefits\nWork with key project members e.g. project manager, developers, QA to help them understand business requirements and the processes, to ensure finished product complies with users and business specifications\n\nRequirements\n\nExcellent communication skills with possession of good problem-solving ability\nWilling to learn and work under pressure\nProactive, confident, can-do attitude\nAble to work effectively with business users and technical team\nExperience in Finance products / projects is a big plus!\nNative Cantonese Speaker\u00a0\nBenefits\n\nPassionate and Young Team\nMedical, Dental Insurance\n18 days AL\nOn-site Training\n5 days Work Week", "employment_types": ["Full Time", "Permanent"], "selling_points": ["Business analysis and process improvement", "Drive innovation and technology integration", "Exp in process engineering and system development"], "locations": ["Kowloon Bay"], "categories": ["Professional Services", "Business Analysis / Data Analysis", "Information Technology (IT)", "Product Management / Business Analyst", "Others"], "post_time": "2022-01-17T03:36:22Z", "salary": {"currency": null, "max": null, "min": null, "period": "monthly", "term": null}, "salary_visible": false, "title_keywords": ["business analyst"], "responsibilities": ["coordinate", "communicate with"], "requirements": {"degrees": [], "majors": [], "languages": [], "language_level": [], "hard_skills": [], "soft_skills": [], "languages_combined": []}, "experience_required": {"duration": [], "field": []}}, {"job_id": "100003009053512", "location_code": "hk", "company": "Bape Hong Kong Limited", "job_title": "Senior Business Analyst - Ecommerce", "description": "Accountabilities \u2013 Key Result Areas\n\n\n\nAct as the subject matter expert in digital and consumer applications (e.g., E-Commerce, CRM)\nParticipate in digital transformation projects in the areas of business requirements collection, process development, functional spec development, testing etc.\nManage both internal and external resources for system enhancements and projects\nManage business demands, analyze business requirements and ensure consistent communication to all stakeholders across all levels on project status, issues and risks\nWork with cross-functional teams to design, evaluate, and prioritize product features to shape the development roadmap of Company\u2019s digital transformation\nSupport the business to ensure smooth production systems operations\nApply ITIL methodology in problem, issue change and enhancement management\nExperience / Qualification Requirements\n\n\nDegree in Computer Science or a related technical field\n5 years\u2019 online product management or E-Commerce platform management experience\nExperience in e-Commerce platform e.g. Shopify, Web application, mobile APP, O2O, CRM and/or digital transformation, preferable in retail industry\nFamiliar with project management lifecycles\nStrong communicator, both verbal and written, proven ability to coordinate different teams of Vendors, Internal Developers and\u00a0Marketing\nFast learner for various online and offline retail business processes\nStrong written and verbal language efficiency in English, Cantonese, and Mandarin\n\nCompetitive remuneration and benefit package will be offered to the right candidate. Please submit your application by clicking \"Apply Now\" below.\n\n\n\nAll data collected is for recruitment purpose only.", "employment_types": ["Full Time"], "selling_points": ["5 years\u2019 e-Commerce platform management experience", "Participate in digital transformation projects", "Familiar with project management lifecycles"], "locations": ["Southern Area"], "categories": ["Information Technology (IT)", "Product Management / Business Analyst", "E-commerce", "Product Management / Business Analyst", "Software Development"], "post_time": "2022-01-17T07:04:31Z", "salary": {"currency": null, "max": null, "min": null, "period": "monthly", "term": null}, "salary_visible": false, "title_keywords": ["senior business analyst"], "responsibilities": ["management", "mobile app", "data", "operations", "systems", "teams", "subject matter expert", "design", "testing", "communication", "evaluate", "project management", "coordinate", "recruitment", "e-commerce platform", "cross-functional teams"], "requirements": {"degrees": ["degree"], "majors": ["computer science"], "languages": ["cantonese", "english", "mandarin"], "language_level": [], "hard_skills": ["itil", "web", "e-commerce", "shopify", "mobile", "project management"], "soft_skills": ["prioritize", "communication", "project management", "smooth", "communicator", "fast learner"], "languages_combined": [{"language": "cantonese", "language_level": []}, {"language": "english", "language_level": []}, {"language": "mandarin", "language_level": []}]}, "experience_required": {"duration": ["5 years"], "field": ["product management", "management", "e-commerce"]}}, {"job_id": "100003009055397", "location_code": "hk", "company": "Rise Associates Asia Limited", "job_title": "Junior Business Analyst", "description": "Our client is a list global manufacturer, with strong international presence and produces daily use consumers products. To cope with their regional ERP upgrade project, they are looking for a Junior Business Analyst to support the implementation and migration to Microsoft Dynamic 365.\n\nResponsibilities:\n\nWork with business users and vendors throughout the project cycle, to develop, implement and support ERP systems\nGather and analyze\u00a0requirements from business, prepare specification for development\nPrepare test cases and perform UAT testing\nProvide post-production application support to users\nProvide feedbacks to vendors for system enhancement\u00a0\n\nRequirements:\n\nHigher Diploma or above in IT, Computer Science or relevant disciplines\nWith 2+ years\u2019 work experience in IT\nTrack records of support ERP systems; practical experience in MS NAV/ D365 a plus\nGood command of Chinese and English language skills\nStrong interpersonal skills and highly motivated; with eagerness to learn", "employment_types": ["Full Time", "Permanent"], "selling_points": ["Listed global company", "MS D365 implementation", "$24k x 13 months + bonus"], "locations": ["Yau Tsim Mong Area"], "categories": ["Information Technology (IT)", "Support", "Product Management / Business Analyst", "Software Development"], "post_time": "2022-01-18T02:27:06Z", "salary": {"currency": null, "max": null, "min": null, "period": "monthly", "term": null}, "salary_visible": false, "title_keywords": ["business analyst", "junior"], "responsibilities": ["systems", "uat testing", "develop"], "requirements": {"degrees": ["higher diploma or above"], "majors": ["it", "computer science"], "languages": ["english", "chinese"], "language_level": ["good command"], "hard_skills": ["erp systems", "plus"], "soft_skills": ["motivated", "interpersonal skills"], "languages_combined": [{"language": "english", "language_level": ["good command"]}, {"language": "chinese", "language_level": ["good command"]}]}, "experience_required": {"duration": ["2+ years"], "field": ["it"]}}, {"job_id": "100003008977003", "location_code": "hk", "company": "IT Consulting Solutions Limited", "job_title": "IT Project Assistant / Administrator / Junior Business Analyst", "description": "Responsibilities:\u00a0\n\nProvide assistance and administrative support to IT projects\nCoordinate internal users and external vendors for project arrangement\nCoordinate and participate in team meetings, prepare and/or edit meeting minutes, presentations and reports\nEnsure coordination of the interfaces between clients and project / delivery team\nMinutes-taking, reporting and documentation\nPerform admin and ad hoc tasks as required\n\n\u00a0Requirements:\n\nAt least 2 years related working experience\nExcellent analytical, interpersonal and communication skills\nGood command in both spoken and written English and Chinese\nExperience working with Microsoft Office (Excel, Word and PowerPoint)\nIT knowledge is a plus", "employment_types": ["Contract"], "selling_points": ["World's leading insurance company", "Stable work hours: 9AM-6PM; MON-FRI", "Pathway to become a Business Analyst"], "locations": ["Aberdeen"], "categories": ["Admin & HR", "Administration / Operation Manager", "Information Technology (IT)", "IT Project Management / Team Lead", "Product Management / Business Analyst"], "post_time": "2022-01-17T14:38:52Z", "salary": {"currency": null, "max": null, "min": null, "period": "monthly", "term": null}, "salary_visible": false, "title_keywords": ["business analyst", "administrator", "junior", "project assistant"], "responsibilities": ["reporting", "administrative support", "ad hoc tasks", "presentations", "coordinate", "reports", "coordination", "documentation", "provide assistance"], "requirements": {"degrees": [], "majors": [], "languages": ["english", "chinese"], "language_level": ["good command"], "hard_skills": ["excel", "plus", "it knowledge", "microsoft office", "word", "powerpoint"], "soft_skills": ["communication skills", "interpersonal"], "languages_combined": [{"language": "english", "language_level": ["good command"]}, {"language": "chinese", "language_level": ["good command"]}]}, "experience_required": {"duration": ["at least 2 years"], "field": ["related"]}}, {"job_id": "100003009055188", "location_code": "hk", "company": "Swire Coca-Cola HK Ltd", "job_title": "Business Analyst", "description": "Responsibilities:\n\n\nAssist with implementation of SAP and other technical and innovative projects\nEngage in all project stages relevant to an analyst position such as pre-project preparation, project scoping, requirement gathering, implementation, system testing, user acceptance testing and user training\nCoordinate any processes throughout the whole project for ensuring all the stages meet the project schedule\nAnalyze, identify and propose business process improvement based on business / system need\nPrepare requirement document, manage Quality Assurance and UAT, execute tests, provide test case and results\nConduct user training and lead the implementation to ensure new functionalities are implemented in accordance with specifications and match the users' needs\nPrepare and maintain knowledge base, systems related documentation, training materials and operation manuals\nRequirements:\n\nAt least 3 years of relevant experience, preferably in system implementation and system support\nBachelor\u2019s Degree or above in Information Technology or related discipline and equivalents\nBroad IT domain experience in three or more of the following areas IT areas: Applications Development, Project Management, Vendor Management, Quality Assurance, Infrastructure, Maintenance and Support\nStrong sense of responsibility and able to work independently\nGood analytical and problem-solving skills\nProject management and presentation skills\nAttention to detail and strong follow-through on deliverables\nExcellent interpersonal and communication skill\nGood in written and spoken English and Chinese\nSAP certification/ SAP HANA experience will be an advantage\nPlease apply with full resume,\u00a0current and expected salary and availability\u00a0to:\u00a0The Human Resources Manager, Swire Coca-Cola HK, 17-19 Yuen Shun Circuit, Siu Lek Yuen, Shatin, or by clicking 'Apply Now'.\u00a0\n\n\n*Personal data provided are treated in strictest confidence and for recruitment purposes only.\u00a0 All information will be destroyed after the process completed.*", "employment_types": ["Full Time", "Contract"], "selling_points": ["Degree or above in Information Technology/related", "3+ years exp in working with system implementation", "Business requirements for innovative projects"], "locations": ["Shatin Area"], "categories": ["Information Technology (IT)", "Product Management / Business Analyst", "Others"], "post_time": "2022-01-18T01:42:22Z", "salary": {"currency": null, "max": null, "min": null, "period": "monthly", "term": null}, "salary_visible": false, "title_keywords": ["business analyst"], "responsibilities": ["uat", "related documentation", "systems", "quality", "implementation", "testing", "coordinate", "business process", "specifications", "schedule", "maintain"], "requirements": {"degrees": ["degree or above", "bachelor"], "majors": ["information technology"], "languages": ["english", "chinese"], "language_level": ["good"], "hard_skills": ["maintenance", "sap", "vendor", "project management", "system implementation", "problem-solving skills"], "soft_skills": ["work independently", "confidence", "sense of responsibility", "communication skill", "project management", "presentation skills", "attention to detail", "problem-solving skills", "interpersonal"], "languages_combined": [{"language": "english", "language_level": ["good"]}, {"language": "chinese", "language_level": ["good"]}]}, "experience_required": {"duration": ["at least 3 years"], "field": ["management", "maintenance", "development", "system support", "infrastructure", "project management", "it", "relevant experience", "quality assurance"]}}, {"job_id": "100003009055825", "location_code": "hk", "company": "Mattel Asia Pacific Sourcing Ltd", "job_title": "Business Analyst Specialist- IT, QMS", "description": "The Opportunity:\u00a0\n\nMattel is currently seeking a Business Analyst Specialist in our Global Technology Organization. This role will report directly to the Director, IT, responsible for delivering technology solutions across our Brands, Global Supply Chain and Corporate back office solutions.\n\nThis role will oversee QMS, Quality, Laboratory Management, Safety, Regulatory Compliance, and Sustainability platforms, which helps drive business drive quality, safety, and compliance.\u00a0\n\nResponsibilities:\n\nPartner with the business process owners to gain an in-depth knowledge for process improvement\nDevelop business requirement and business case documents, along with financial justification and ROI for all initiatives\nWork with business to identify issues, problems, and opportunities; compare data from different sources to draw conclusions; use effective approaches for developing appropriate actions and solutions\u00a0\nDevelop and sustain productive customer relationships\nLead User Acceptance testing, to ensure that the system addresses the business needs from the user\u2019s point of view\nManage multiple projects and personnel to coordinate all aspects of implementation and delivery of tasks\u00a0\nCoordinate Organization Change Management in alignment with the \u201cto be\u201d state\nMaintain effective knowledge of the Quality Management processes,\u00a0 thorough awareness and evaluation of trends and developments of emerging technologies\nEvaluate timing of software version upgrades and facilitate migrations\nPartner with GTO Client Services, to ensure timely and effective support/break/fix and add/change services\n\nRequirements:\n\n\nDegree holder with 5+ years of relevant experience working in IT in a global delivery function\nMust have working knowledge in 2 or more of the following domains: Product Lifecycle Management, Quality Management, or Sustainability\nExperience with managing a Quality Management System, with various modules that satisfy Quality, Safety, and Compliance requirements preferred.\nExperience with quality applications such as Polarion, STARLIMS, Chemical Management Database, Dexi \u2013 Data Scrapping Tool, and iCiX is preferred.\nExperience with PowerBI, Cognos, Tableau, and Google Data Lake is preferred.\u00a0Oracle Agile PLM, or Salesforce Service Cloud experiences a plus\nExperience in Consumer Packaged Goods or Fast Fashion industries preferred\nStrong analytical and reporting skills, able to create dashboards and establishing KPIs.\nAble to work with contractors and consultants to drive outcome and presenting to\u00a0business stakeholders on a regular basis\nExperience with compliance documentation management and support.\nOpen to travel as needed (approximately 10%)\n\nWho Should Join Us:\n\nWe are not only looking for the right experience and skill set, but also for attitude, potential & cultural fit.\n\nIf you are creative, energetic, passionate with a growth mindset and devoted to developing your future career in the world\u2019s leading toy company, you are welcome to be a part of our team and we will play & grow together!\u00a0\n\nWhat We Offer:\n\nAs a caring company, we are committed to providing engaging and work-life balance environment, competitive remuneration, comprehensive fringe benefits, and progressive career opportunities to our people.\u00a0 \u00a0\n\nOur benefits include:\n\n5-day work week; 2 Half-Day off every month\nFlexi Working Hours\n13th Month Salary and Performance Bonus\nAnnual Leave and Company Holidays\nGroup Medical, Dental and Life Insurance\nMPF/ Mattel Retirement Scheme (ORSO Scheme)\nTraining Sponsorship & Education Subsidy\nComprehensive Wellness Programs\nHow To Apply:\n\nInterested parties please click \u201cApply Now\u201d to send your full resume (in Microsoft Word or PDF format), current and expected salary to us for review.\n\nApplicants not invited for interview within 6 weeks may assume their application unsuccessful. All information will be treated in strictest confidence and used solely for recruitment purpose.", "employment_types": ["Full Time", "Permanent"], "selling_points": ["Degree holder in IT/  5+ years of relevant exp", "QMS Project Experience required", "Regional system project support"], "locations": ["Tsim Sha Tsui"], "categories": ["Information Technology (IT)", "IT Project Management / Team Lead", "Product Management / Business Analyst"], "post_time": "2022-01-18T02:59:18Z", "salary": {"currency": null, "max": null, "min": null, "period": "monthly", "term": null}, "salary_visible": false, "title_keywords": ["specialist", "business analyst"], "responsibilities": ["migrations", "management", "change management", "software", "data", "upgrades", "quality", "developing", "manage multiple projects", "testing", "develop", "coordinate", "implementation", "business process", "maintain", "evaluate", "evaluation"], "requirements": {"degrees": ["degree holder"], "majors": ["it"], "languages": [], "language_level": [], "hard_skills": ["plus", "salesforce", "agile", "tableau", "documentation", "oracle"], "soft_skills": ["passionate", "creative", "agile", "devoted", "energetic"], "languages_combined": []}, "experience_required": {"duration": ["5+ years"], "field": ["management", "compliance", "it", "relevant experience", "quality management", "database"]}}, {"job_id": "100003009053642", "location_code": "hk", "company": "eCargo Enterprise Limited", "job_title": "Business Analyst (e-Commerce)", "description": "Responsibilities:\nPerform application UAT/ SIT testing and work with testing teams for test case definition\nAnalyse and define user requirements to create the functional documentation\nWork with System Analysts to turn functional document into technical specification\nDocument the project into systems and processes for management review\nPrepare and update system documentation, operation guides and training materials etc.\nRequirements:\nDegree holder in eCommerce / computer science / software engineering or related disciplines\n2+ years relevant experience is advance\nFresh graduates will also be considered\nSolid experience in System Integration, Electronic Data Interchange\nGood communications with written/oral English, Cantonese and Mandarin\nBasic Knowledge in Software Development Life Cycle\u00a0\nPrevious experience in eBusiness mode is advance\nGood command of both spoken and written English, Chinese and Mandarin\nBenefits:\nDouble Pay\nFive-day work week\nBirthday Leave\nMedical Insurance\nFree Shuttle Bus\nTraining Allowance\nAttractive remuneration package and excellent career development opportunities will be offered to the successful candidate. \u00a0For Interested parties, please apply with a detailed resume stating present and stating present and expected salary by clicking \"Apply Now\".\u00a0 \u00a0\u00a0You are welcome to visit our website at http://www.ecargo.com.\n\nPersonal data collected will be used for recruitment purposes only and be treated in strict confidence.\u00a0 Cargo Services treats all applicants for employment in the same way, regardless of age, sex, marriage and civil partnership, race, disability, religion or belief.", "employment_types": ["Full Time", "Permanent"], "selling_points": ["Double Pay; Five-day work week; Birthday Leave", "IT Business Analyst role in e-Commerce", "1-3 years experiences or Fresh grad"], "locations": ["Kwai Tsing Area"], "categories": ["Information Technology (IT)", "Product Management / Business Analyst", "Software Development", "E-commerce", "Product Management / Business Analyst"], "post_time": "2022-01-17T07:16:35Z", "salary": {"currency": null, "max": null, "min": null, "period": "monthly", "term": null}, "salary_visible": false, "title_keywords": ["business analyst"], "responsibilities": ["uat", "system documentation", "systems", "teams", "testing", "documentation", "management review", "analyse"], "requirements": {"degrees": ["degree holder"], "majors": ["ecommerce", "related disciplines", "software engineering", "computer science"], "languages": ["cantonese", "english", "chinese", "mandarin"], "language_level": ["good command", "good"], "hard_skills": ["integration", "basic"], "soft_skills": ["oral"], "languages_combined": [{"language": "cantonese", "language_level": ["good"]}, {"language": "english", "language_level": ["good command", "good", "good"]}, {"language": "chinese", "language_level": ["good command", "good"]}, {"language": "mandarin", "language_level": ["good command", "good", "good"]}]}, "experience_required": {"duration": ["2+ years"], "field": ["relevant experience"]}}, {"job_id": "100003009054433", "location_code": "hk", "company": "Hong Kong Life Insurance Limited", "job_title": "Assistant Business Analyst / Business Analyst", "description": "Responsibilities\n\nParticipate in business and systems projects and ensure quality delivery of the systems\nCo-ordinate with users of different areas , investigate & resolve issues and concerns raised by users\nLead requirements gathering, analyze business processes, and prepare user requirement specifications in accordance with business needs\nManage requirements throughout project life cycles and prioritize initiatives based on business needs and requirements\nPrepare test plan and participate in quality assurance testing cycles\nMonitor deliverables, conduct SIT, support UAT, prepare user manual and conduct training\nAssist project team members with the development of project documentation\nRequirements:\n\nDegree holder with major in Computing\nAt least 3 years' practical work experience as a Business Analyst or in a related role; demonstrated experience in Life Insurance and IT is a definite asset\nKnowledge in SQL and Power BI is preferable\nExcellent analytical mind and problem solving skills\nExcellent interpersonal, verbal and written communication skills\nExcellent planning, organizational and time management skills\nFLMI qualification is an advantage\nLess experience will be considered as Assistant Business Analyst", "employment_types": ["Full Time", "Permanent"], "selling_points": ["At Least 3 years of exp. in BA role", "Excellent planning, time management skills", "Less exp. will be considered as Assistant BA"], "locations": ["Sheung Wan"], "categories": ["Information Technology (IT)", "Product Management / Business Analyst"], "post_time": "2022-01-17T09:31:33Z", "salary": {"currency": null, "max": null, "min": null, "period": "monthly", "term": null}, "salary_visible": false, "title_keywords": ["business analyst", "assistant"], "responsibilities": ["user requirement", "uat", "co-ordinate with", "systems", "quality", "monitor", "testing", "specifications", "plan", "project documentation"], "requirements": {"degrees": ["degree holder"], "majors": [], "languages": [], "language_level": [], "hard_skills": ["sql", "problem solving skills", "bi"], "soft_skills": ["communication skills", "time management skills", "organizational", "analytical mind", "problem solving skills", "interpersonal"], "languages_combined": []}, "experience_required": {"duration": ["at least 3 years"], "field": ["related", "business", "it", "insurance"]}}, {"job_id": "100003009051887", "location_code": "hk", "company": "Automated Systems (HK) Ltd", "job_title": "Business Analyst / Senior Business Analyst", "description": "Job Responsibilities:\nWork with clients to perform requirement analysis, prepare functional specification and support business testing;\nCommunicate between users and development team, and liaise with the team on resources allocation and task scheduling;\nPrepare test plans, conduct testing, coordinate UAT and provide user training;\nCo-ordinate, provide roll-out and post-implementation support;\nPrepare documentation update;\nPrepare project monthly report;\nPerform other ad-hoc projects and tasks as required\nJob Requirements:\nUniversity graduate or above in Computer Science/Business Administration or equivalent;\n1+ years of related experiences\u00a0\nExperiences in Scrum/Agile/Waterfall would be an advantage.\nGood problem solving skills, self-motivated, able to work independently\nGood communication and interpersonal skill;\nEffective verbal and written communication in English and Chinese\nImmediately available is highly preferred\nWe offer 5-day week, public holidays, medical benefits, excellent career opportunities, considerable remuneration to the right candidates.\n\n\u201cIf you have the desire for an exciting and rewarding career, please send us your resume, stating your notice period, present and expected salary to Human Resources Department by clicking \"Apply Now\".\n\nTo learn us more, please visit our website: www.asl.com.hk\n\n\nWe are an equal opportunity employer. All applications will be treated in strict confidence. We regret that only shortlisted candidates will be notified. All personal data will be destroyed within six months after the selection process.", "employment_types": ["Full Time", "Permanent", "Contract"], "selling_points": ["Listed IT solution company", "Various projects exposure and excellent career", "Attractive package"], "locations": ["Shatin Area"], "categories": ["Information Technology (IT)", "Application Specialist - Software", "IT Project Management / Team Lead", "Product Management / Business Analyst"], "post_time": "2022-01-17T01:27:12Z", "salary": {"currency": null, "max": null, "min": null, "period": "monthly", "term": null}, "salary_visible": false, "title_keywords": ["senior business analyst", "business analyst"], "responsibilities": ["documentation", "uat", "analysis", "implementation", "testing", "coordinate", "scheduling", "monthly report", "liaise with", "plans", "ad-hoc projects"], "requirements": {"degrees": ["university graduate or above"], "majors": ["business administration", "computer science"], "languages": ["english", "chinese"], "language_level": [], "hard_skills": ["problem solving skills", "agile"], "soft_skills": ["self-motivated", "work independently", "agile", "interpersonal skill", "communication", "problem solving skills"], "languages_combined": [{"language": "english", "language_level": []}, {"language": "chinese", "language_level": []}]}, "experience_required": {"duration": ["1+ years"], "field": ["related"]}}, {"job_id": "100003009055568", "location_code": "hk", "company": "PeopleLink Services Limited", "job_title": "Business Analyst / Senior Business Analyst | Up to HK$60k + Bonus", "description": "\u00a0Responsibilities:\n\nUnderstand business and user requirement and translate to project scope and work closely with Product Owner, Project Managers and Development Teams\nLiaise and communicate with project stakeholders to ensure project deliverable meet user expectations\nTest deliverables regularly to ensure project on track and prepare document report to management\nQualifications\n\u00a0\n\nBachelor's degree in Computer Science, Information Technology, Business Analytics or equivalent\n5+ years of experience in business analyst on medium-sized to large projects involving multiple stakeholders. Experience in systems revamp in insurance business is preferred.\nSolid work experience in collect user requirements, change management, UAT\nParticipated in full SDLC for at least one of the projects below:\nArtificial Intelligence / Machine Learning application development\nData Management / Data Warehousing\nCloud Infrastructure\nAbility to work effectively with all levels of personnel across the organization\nEffective interpersonal skills with a clear, concise and relevant communication style, including excellent presentation skills.\nExperience in using project tools such as Jira, Confluence\nFluent English and excellent report writing skills", "employment_types": ["Full Time", "Permanent"], "selling_points": ["5+ yrs experience as Business Analyst", "Participate in AI/ML, Data, Cloud projects", "Large scale project exposure, Perm, Great Benefits"], "locations": ["Not Specified"], "categories": ["Information Technology (IT)", "IT Project Management / Team Lead", "Product Management / Business Analyst", "Technical Writing"], "post_time": "2022-01-18T02:43:58Z", "salary": {"currency": "HKD", "max": 54999, "min": 45000, "period": "monthly", "term": null}, "salary_visible": true, "title_keywords": ["senior business analyst", "business analyst"], "responsibilities": ["liaise", "user requirement", "communicate with", "management", "revamp", "change management", "uat", "data", "warehousing", "systems", "teams", "infrastructure", "communication", "application development", "insurance", "report"], "requirements": {"degrees": ["degree", "bachelor"], "majors": ["business analytics", "computer science", "information technology"], "languages": ["english"], "language_level": ["excellent", "fluent"], "hard_skills": ["sdlc", "data management", "writing skills"], "soft_skills": ["work effectively", "writing skills", "communication", "clear", "presentation skills", "learning", "interpersonal skills"], "languages_combined": [{"language": "english", "language_level": ["fluent", "excellent"]}]}, "experience_required": {"duration": ["5+ years"], "field": ["management", "business", "insurance"]}}, {"job_id": "100003009053720", "location_code": "hk", "company": "Insight Information Technology Limited", "job_title": "Business Analyst / Senior Business Analyst", "description": "\"We develop innovative technologies to provide your business with the best solution\"\nWe are a company that helping our clients to enhance and develop their operational management and Ecommerce business efficiently by providing the latest technology and continuous technological development, such as tailor made web design, mobile application design , system construction, programming and technical support services all over the world.\n\nResponsibilities:\n\nCollect and analyze user requirement to prepare functional specifications\nLiaise with business users, vendor and internal IT team to ensure smooth delivery of the Project\nExecute user acceptance testing including test planning, execution and defect management\nConduct market research and analysis to identify business needs and opportunities\nManage resources planning and budget\nRequirements:\n\nDegree holder in Business, IT, Operations Management or related discipline s\nMinimum 2 years\u2019 experiences in business analysis or system analysis, preferably in Finance Services\nExperience in Product Development/ UAT is an advantage\nStrong business analysis skills on requirement gathering and documentation\nSolid experience in software testing (e.g. planning, execution and result document)\nStrong analytical and problem solving skills with the ability to work under dynamic environment and multi-tasking\nAddition Information:\n\nEmployment Type: Full Time\nLanguage: English Business fluency , Mandarin Business level or above\nLocation: Tsim Sha Tsui, Hong Kong\nTsim Sha Tsui\nStart Date: Immediate - Highly preferable\nWebsite: https://www.insightinfor.com/", "employment_types": ["Full Time"], "selling_points": ["Work Life Balance", "Career Growth Opportunities", "Minimum 2 years\u2019 experiences in business analysis"], "locations": ["Tsim Sha Tsui"], "categories": ["Information Technology (IT)", "Product Management / Business Analyst"], "post_time": "2022-01-17T07:24:11Z", "salary": {"currency": null, "max": null, "min": null, "period": "monthly", "term": null}, "salary_visible": false, "title_keywords": ["senior business analyst", "business analyst"], "responsibilities": ["user requirement", "management", "conduct market research", "analysis", "budget", "testing", "specifications", "liaise with", "planning"], "requirements": {"degrees": ["degree holder"], "majors": ["business", "it"], "languages": ["english", "mandarin"], "language_level": ["fluency"], "hard_skills": ["documentation", "analysis", "dynamic", "problem solving skills"], "soft_skills": ["analytical and problem solving skills", "dynamic environment", "multi-tasking"], "languages_combined": [{"language": "english", "language_level": ["fluency"]}, {"language": "mandarin", "language_level": []}]}, "experience_required": {"duration": ["minimum 2 years"], "field": ["business analysis", "finance", "product development", "testing"]}}, {"job_id": "100003009055095", "location_code": "hk", "company": "Autotoll Limited", "job_title": "Senior Business Analyst", "description": "Job Description:\n\nThis position will be a member of the Process Excellence Team under Information Technology (IT), reporting to Process Excellence Manager.\u00a0 Besides business analysis, process design and engineering, he/she will also assist in enhancing contribution of IT to business efficiency.\n\nResponsibilities:\n\n\u00a0Plan and execute process excellence initiatives with alignment to business strategies\nCollect business requirements and to define clear and measurable project objectives. Create as-as and to-be process maps for process changes.\nPrepare functional design documents and work with IT Development Team or suppliers to develop systems with business analytic capabilities to ensure deliverables (system solutions and process designs) are aligned with requirements.\nParticipate in ERP replacement project and coordinate related process re-engineering tasks.\nCarry out testing of developed systems or IT tools to obtain user acceptance.\nAct as an internal IT process officer to ensure IT governance and standards are properly embedded into day-to-day IT operations and project management.\nResearch and review up-to-date business processes with new technology advancements to improve business efficiency and to consistently align with market trends.\nAssist supervisor in documentation, preparing budget plans and proposals for projects\nAny other duties assigned by supervisor\n\nRequirements:\n\nBachelor\u2019s degree or above in Industrial Engineering, Information Technology, or related discipline.\nMinimum 3 years process improvement experience with at least 1 year IT system / IT tool development project experience, e.g., ERP implementation or Power BI Applications.\nQualified lean practitioner or six sigma green belt.\nStrong process mapping capability to build process maps and workflow designs.\nSolid experience in project management, certified PMP or relevant qualification will be an added advantage but not a must.\nEffective verbal and written communication in English and Chinese.\nExcellent team player, able to work with multinational project members.\nWe offer 5-day work, attractive\u00a0remuneration\u00a0and benefits package to the right candidate.\nInterested parties please forward your full resume\u00a0(in Microsoft Word or PDF format)\u00a0with current and expect salary to the Human Resources & Facilities Services, Ricoh Hong Kong Limited,\u00a0by clicking \"Apply Now\".\nInformation provided will be treated in strict confidence and only be used for recruitment related purposes. All personal data of unsuccessful candidates will be destroyed on completion of the recruitment exercise.", "employment_types": ["Full Time", "Permanent"], "selling_points": ["Degree in Computer Science", "5 years+ relevant IT System Development Experience", "5 days work"], "locations": ["Kowloon Bay"], "categories": ["Information Technology (IT)", "Application Specialist - Software", "Product Management / Business Analyst", "Data Scientist"], "post_time": "2022-01-18T01:15:10Z", "salary": {"currency": null, "max": null, "min": null, "period": "monthly", "term": null}, "salary_visible": false, "title_keywords": ["senior business analyst"], "responsibilities": ["reporting", "any other duties", "documentation", "re-engineering", "operations", "systems", "review", "budget", "design", "develop", "coordinate", "testing", "project management", "plan", "business analysis", "plans", "collect business requirements"], "requirements": {"degrees": ["degree or above", "bachelor"], "majors": ["engineering", "information technology"], "languages": ["english", "chinese"], "language_level": [], "hard_skills": ["lean", "bi", "erp", "project management", "six sigma", "pmp"], "soft_skills": ["communication", "project management", "team player"], "languages_combined": [{"language": "english", "language_level": []}, {"language": "chinese", "language_level": []}]}, "experience_required": {"duration": ["at least 1 year", "minimum 3 years"], "field": ["development", "project management", "it"]}}, {"job_id": "100003009049258", "location_code": "hk", "company": "SmarTone Telecommunications Limited", "job_title": "Business Analyst (IT Project)", "description": "About The Role:\n\n\nCommunicating with business users and project clients\nGathering user requirement\nTranslating business requirements and proposed solutions into functional development requirements\nDrafting user stories and workflows\nPreparation of technical documents for government project submission\nWorking closely with IT teams, project clients and vendors for development\u00a0\n\n\nAbout You:\n\n\n5 years project documentation experience, involvement in system analysis and design, good communication skill with end-users\n2-3 years working on government projects\n\n\nWhat you can get from us\n\nOn-the-job training, learning and development\u00a0provided\nExecutive workshops, interest class, corporate purchase discount offered by SHKP\nCompetitive salary and annual leaves\nFlexible working opportunities\n\nInterested parties, please send full resume with\u00a0expected salary\u00a0and\u00a0available date\u00a0to Human Resources and Administration Department by e-mail or by fax 2111 9459.\n\n(Data collected will be used for recruitment purpose only.)", "employment_types": ["Full Time", "Permanent"], "selling_points": ["Collect, validate and document business problems", "Liaise between stakeholders and technical teams", "Drive the delivery of IT projects"], "locations": ["Ngau Tau Kok"], "categories": ["Information Technology (IT)", "IT Project Management / Team Lead", "IT Management", "Product Management / Business Analyst"], "post_time": "2022-01-14T08:19:54Z", "salary": {"currency": null, "max": null, "min": null, "period": "monthly", "term": null}, "salary_visible": false, "title_keywords": ["business analyst"], "responsibilities": ["user requirement", "analysis", "teams", "design", "communication", "purchase", "communicating with", "project documentation"], "requirements": {"degrees": [], "majors": [], "languages": [], "language_level": [], "hard_skills": ["documentation", "workshops", "analysis"], "soft_skills": ["flexible", "communication skill", "learning"], "languages_combined": []}, "experience_required": {"duration": ["5 years"], "field": ["design"]}}, {"job_id": "100003009055306", "location_code": "hk", "company": "Wellesley Associates Limited", "job_title": "Business Analyst - Asset Management Firm/ MNC- Investment Accounting System - 50-60+K + Bonus", "description": "Responsibilities:\u00a0\n\n\nActing as a liaison between the business and IT teams\nDevelop a trusted advisor relationship with key stakeholders\nCollect, elicit, validate and document the business problems, requirements and processes\nDecompose business requirements into functional requirements for solution design\nWork closely with business users & IT to align the understanding of business goal, requirements and solution\nLiaise between stakeholders and technical teams to facilitate timely and successful delivery of solutions\n\nRequirements:\n\n\nDegree holder or above in Computer Science/Information System/Business Administration\nMinimum 5 years relevant experience, preferable in telecom industry.\u00a0\nExperience in Project Management / Process Analysis / Business Flow Design & Reengineering is required\nAbility to understand the as-is process, conduct gap analysis with new system features/functionality and come up with the to-be process\nStrong interpersonal skills\nGood written and verbal communication skills in English and Chinese\nMature, dynamic, self-motivated and able to work under pressure\n\nInterested parties please apply with full resume stating present and expected salary by clicking \"Apply Now\" or visiting our website:\u00a0www.smartone.com/tc/about_us/careers/\n\nSmarTone is an equal-opportunity employer. All data supplied will be kept in strict confidence and will be used for employment related purpose. We may transfer such data to any agent, contractor or third party who provides services to us with respect to matters relating to your application. Only short-listed candidates will be contacted.\n\n\nYou are welcome to visit our website : www.smartone.com\u00a0", "employment_types": ["Full Time"], "selling_points": ["Inhouse Asset Management Firm/ FS MNC", "Back-Office/ Investment Accounting System", "Business Analyst/ System Migration/Implementation"], "locations": ["Not Specified"], "categories": ["Banking / Finance", "Project Finance", "Information Technology (IT)", "IT Project Management / Team Lead", "Product Management / Business Analyst"], "post_time": "2022-01-18T02:07:14Z", "salary": {"currency": null, "max": null, "min": null, "period": "monthly", "term": null}, "salary_visible": false, "title_keywords": ["accounting", "business analyst", "asset management"], "responsibilities": ["liaise", "teams", "design", "develop"], "requirements": {"degrees": ["degree holder"], "majors": ["business administration", "computer science"], "languages": ["english", "chinese"], "language_level": ["good"], "hard_skills": ["analysis", "gap", "information system", "project management", "dynamic"], "soft_skills": ["communication skills", "self-motivated", "mature", "project management", "dynamic", "interpersonal skills", "work under pressure"], "languages_combined": [{"language": "english", "language_level": ["good"]}, {"language": "chinese", "language_level": ["good"]}]}, "experience_required": {"duration": ["minimum 5 years"], "field": ["project management", "business", "relevant experience", "design"]}}, {"job_id": "100003009056052", "location_code": "hk", "company": "Hays", "job_title": "Assistant Vice President, Business Analyst, 60k(Negotiable)", "description": "This role is to deliver business or systems analysis to support design of small/medium complexity projects\n\nThe Job:\n\nDo hands on business and systems analysis work\nEstablish and maintain good working relationship with other IT functional areas\nHave a solid understanding of the IT architecture and business processes in your area to be a trusted business advisor\nCoach and mentor junior members of staff in BA or SA tasks\nLiaise effectively with offshore development teams when required\nFollow and tune the Software Development Life Cycle to deliver good quality and lower cost solutions\nStrong Cost/Benefit focus to ensure effort is focused on true business value\n\nThe Person:\n\nA bachelor\u2019s degree in Business Information Systems or related field\nA minimum of 2 to 3 years\u2019 experience in business analysis or a related field\nExceptional analytical and conceptual thinking skills\nThe ability to influence stakeholders and work closely with them to determine acceptable solutions\nAdvanced technical and excellent documentation skills\nCompetency in Microsoft applications including Word, Excel, Outlook and Sharepoint\nExcellent in spoken and written English, Chinese and Mandarin\n\n\u201cDFI Retail Group is responsible for ensuring that all personal information collected from each Candidate presented to DFI Retail Group is used for recruitment purposes only and the data collection process is in accordance with all applicable laws and compliant with the Code of Practice on Human Resource Management.\n\nTo find out more about Our Businesses and Our People, please visit our website: https://www.DFIretailgroup.com\n\nWe are an equal opportunity employer. Personal data collected will be kept and handled confidentially by authorised personnel for recruitment purposes only. We will retain the applications of candidates not selected for a period of no more than 24 months. A copy of our Privacy Policy can be accessed by visiting our Company website.\u201d\n\nIssued by The Dairy Farm Company, Limited", "employment_types": ["Full Time", "Permanent"], "selling_points": ["High salary packages", "Flexible work location", "work with like minded professionals"], "locations": ["Not Specified"], "categories": ["Information Technology (IT)", "Product Management / Business Analyst"], "post_time": "2022-01-18T03:13:44Z", "salary": {"currency": null, "max": null, "min": null, "period": "monthly", "term": null}, "salary_visible": false, "title_keywords": ["business analyst", "assistant vice president"], "responsibilities": ["liaise", "cost", "software", "analysis", "systems", "teams", "quality", "maintain", "architecture"], "requirements": {"degrees": ["degree", "bachelor"], "majors": ["business"], "languages": ["english", "chinese", "mandarin"], "language_level": ["excellent"], "hard_skills": ["excel", "no", "microsoft applications", "analysis", "word", "outlook", "documentation", "code"], "soft_skills": ["advanced", "responsible"], "languages_combined": [{"language": "english", "language_level": ["excellent"]}, {"language": "chinese", "language_level": ["excellent"]}, {"language": "mandarin", "language_level": ["excellent"]}]}, "experience_required": {"duration": ["minimum of 2 to 3 years"], "field": ["business analysis", "related"]}}, {"job_id": "300003002512365", "location_code": "th", "company": "Transcendent Business Services Pte Ltd", "job_title": "Business Development Manager Travel Solutions", "description": "A Hong Kong based commercial bank is looking for Assistant Vice President ,Business Analyst\n\nYour new company\nThis is a local innovative commercial bank that truly transform people's lives and pride themselves on being a progressive and forward thinker. They have a number of exceptional financial services spanning wealth management, personal banking, wholesale banking as well as global markets and treasury solutions.\n\nYour new role\nYou'll be working closely with digital transformation project stakeholders under wealth management team, it is consisted of 5 professionals reporting directly to the head of wealth management transformation in IT department.\n\nWhat you'll need to succeed\n\nProject and stakeholder management, work closely with digital transformation project stakeholders (Business, IT, Compliance, Risk, Legal and Solution providers) to define business objective, document requirement, track risks & issues and manage communications on project updates.\nDrive and support the business transformation of PBG to a digital and e-savvy best-in-class business model\nCoordinate and perform detailed business analysis; develop functional/business and technical specifications\nEnsure that the product creates maximum value for its customers and users, and for the Bank\nMinimum 6 years of working experience as Digital Business Analyst or similar capacity preferably in the Banking/Finance sector\n\n\nWhat you'll get in return\n\nThe career development opportunities working in a fast-paced environment\nThe highest packages among local banks\nHumane work culture\n\n\n\nWhat you need to do now\nClick 'apply now' if you are interested in this role. For further details or a confidential discussion on other opportunities please contact Carrie Lin at Hays on 22307940 or email carrie.lin@hays.com.hk", "employment_types": ["Full Time", "Permanent"], "selling_points": ["Attractive salary and benefits", "Career advancement", "High commission"], "locations": ["Causeway Bay"], "categories": ["Sales, CS & Business Devpt", "Business Development", "Information Technology (IT)", "Product Management / Business Analyst", "Hospitality / F & B", "Tourism / Travel Agency"], "post_time": "2022-01-17T11:12:12Z", "salary": {"currency": "HKD", "max": 44999, "min": 25000, "period": "monthly", "term": null}, "salary_visible": true, "title_keywords": ["business development manager"], "responsibilities": ["management team", "management", "reporting", "compliance", "develop", "project updates", "coordinate", "specifications", "contact", "career development", "banking", "business analysis"], "requirements": {"degrees": [], "majors": [], "languages": [], "language_level": [], "hard_skills": ["analysis"], "soft_skills": ["fast-paced environment", "interested in", "progressive", "innovative", "detailed"], "languages_combined": []}, "experience_required": {"duration": ["minimum 6 years"], "field": ["finance", "digital", "business", "banking"]}}, {"job_id": "100003009054365", "location_code": "hk", "company": "Ricoh Hong Kong Limited", "job_title": "Data Analyst", "description": "Our client is a leading integrated express logistics service provider in China, aims to provide customers with one-stop integrated logistics solutions.\n\nResponsibilities\n\nUnderstand the business needs, balance the requirements amongst business stakeholders and recommend solutions\nAnalyze users \u2018 requirements and translate users\u2019 ideas and cases into functional specification\nWork closely with onshore/offshore development team and external vendors to ensure the system can be completed timely\nManage the project schedule from the high-level system design and analysis, system implementation/enhancement, UAT to system deployment\nPrepare and maintain function specification and training documentation\n\nExperience\n\n1 year plus the working experience in software development, system solution consultancy, or developing programmable documents, preferably in Logistics/Courier Industries or consultant companies\nPractical experience in understanding, analyzing, and verifying user requirements versus business processes to develop programmable documents\nGood presentation and communication skills\n\nEducation\n\nHigher Diploma or above in Computer Science, Business Analytics, Information Technology, Logistics or other related disciplines\nGood command of written and spoken English and Chinese (including Putonghua)\n\n\n\nInterested parties, please\u00a0CLICK HERE\u00a0to apply online. (Ref:JDB/IT-TT)\n\nPlease note that only short-listed candidates will be notified. All information gathered will be treated in strict confidence and solely used for recruitment purposes", "employment_types": ["Full Time", "Permanent"], "selling_points": ["Data analytic and business intelligence", "Reports and process improvement", "Exp in data analysis and development of data model"], "locations": ["Kowloon Bay"], "categories": ["Professional Services", "Business Analysis / Data Analysis", "Information Technology (IT)", "Product Management / Business Analyst", "Data Scientist"], "post_time": "2022-01-17T09:17:42Z", "salary": {"currency": null, "max": null, "min": null, "period": "monthly", "term": null}, "salary_visible": false, "title_keywords": ["data analyst"], "responsibilities": ["ideas", "uat", "software", "analysis", "implementation", "developing", "develop", "communication", "system design", "logistics", "schedule", "maintain", "documentation"], "requirements": {"degrees": ["higher diploma or above"], "majors": ["related disciplines", "business analytics", "computer science", "information technology"], "languages": ["putonghua", "english", "chinese"], "language_level": ["good command"], "hard_skills": ["plus", "documentation", "analysis", "system design", "deployment", "system implementation"], "soft_skills": ["communication skills", "timely", "presentation"], "languages_combined": [{"language": "putonghua", "language_level": ["good command"]}, {"language": "english", "language_level": ["good command"]}, {"language": "chinese", "language_level": ["good command"]}]}, "experience_required": {"duration": ["1 year"], "field": ["business", "logistics", "developing", "software development"]}}, {"job_id": "100003009055811", "location_code": "hk", "company": "Randstad Hong Kong Limited", "job_title": "Business Analyst Manager (Insurance)", "description": "Job Description\nOur client is one of the renowned Travel Technology company. It is\u00a0 seeking an experienced sales professionals to join the team in Hong Kong. You will be responsible for acquiring large multinational corporations to be their key clients in Hong Kong. Reporting to the Sales Leader, you will have the opportunity to be a key part of the team in the region. You will have the chance to develop your skills and work with entrepreneurial leaders across the world.\u00a0\nRequirements\nMinimum 5 years\u2019 solid track record of successful B2B development/sales (sales experience in the travel industry is a plus).\nExcellent command of\u00a0English\u00a0and Cantonese as you are required to communicate with clients that only speak Cantonese in Hong Kong region.\nA passion for travel and the travel industry.\nStrong communication and persuasion skills.\nSelf-motivated, independent with strong interpersonal skills and a hunger for success.\nProficiency in developing relationships at a strategic level.\nExperienced in presentations/product demonstrations in a confident/engaging manner.\nMulti-task and communicate effectively in a fast-paced environment.\nAbility to engage with various levels of staff and management.\nSound commercial knowledge, with the ability to analyse financial data and build a value-driven business case.\nProficient skills in Microsoft Office suite and experience in using CRM Salesforce.com\nKey duties and responsibilities\nAchieve defined monthly, quarterly and annual sales and total transaction value (TTV) targets.\nDevelop and execute a sales plan to target key prospective accounts.\nIdentify, evaluate and prioritise new business opportunities, using a variety of cold-calling, networking and other prospection methods.\nWrite value-driven customer proposals and create highly professional responses to RFPs to maximise win-rates.\nEffectively capture and communicate customer requirements internally, completing timely handovers of closed sales to the account management team\nCollaborate with other internal departments (finance, operations, product, HR) where necessary to resolve other client-related matters.\n\nFion Karis Woon Yun Shia\u00a0\nTranscendent Business Services Pte Ltd\nEA:R1110743/10C5505", "employment_types": ["Full Time", "Permanent"], "selling_points": ["Leading global insurance company", "Stakeholder management, change management", "At least 5 years relevant experience"], "locations": ["Not Specified"], "categories": ["Information Technology (IT)", "IT Project Management / Team Lead", "IT Management", "Product Management / Business Analyst"], "post_time": "2022-01-18T02:58:22Z", "salary": {"currency": "HKD", "max": 54999, "min": 35000, "period": "monthly", "term": null}, "salary_visible": true, "title_keywords": ["manager", "business analyst"], "responsibilities": ["reporting", "develop"], "requirements": {"degrees": [], "majors": [], "languages": ["cantonese", "english"], "language_level": ["excellent"], "hard_skills": ["microsoft office suite", "plus", "salesforce", "presentations"], "soft_skills": ["confident", "self-motivated", "independent", "multi-task", "ability to analyse", "passion for", "fast-paced environment", "timely", "prioritise", "communication", "interpersonal skills", "driven"], "languages_combined": [{"language": "cantonese", "language_level": ["excellent"]}, {"language": "english", "language_level": ["excellent"]}]}, "experience_required": {"duration": ["minimum 5 years"], "field": ["development"]}}, {"job_id": "100003009053635", "location_code": "hk", "company": "Cargo Services Far East Ltd", "job_title": "Business / System Analyst", "description": "Job Description:\nThis role is a key member of data analytic function in Process Excellence Team and report directly to Process Excellence Manager under Information Technology function. This role will also work closely with technical team in different business intelligence and data related activities.\u00a0\nResponsibilities:\nDesign data acquisition and provision methods that suit business needs\nManage BI reports and data pipeline and look for improvements\nDevelop business analytic model, reports and visualizations\nPerform quantitative and explorative data analysis to offer basis for business decisions and operations\nSupport data operations that ensure availability of business analytic solutions\nAssist to evangelize business analytics practices and techniques in RHK\nPromote and demonstrate fact-based decisions\nAny other duties assigned by supervisor\nRequirements:\nBachelor\u2019s degree or above in Data Science, Business Statistics, Information Technology, or related discipline.\nMinimum 3 years business data analytic experience with experience in data model construction and transformation\nProficiency in SQL, Python/R and Power BI\nExperienced in Data Dictionaries, Data Warehouses and MS D365 is preferable\nProject experience in AI applications and familiar with machine learning is a plus.\nGood understanding in statistics and its application in business problems\nStrong analytical,\u00a0presentation, interpersonal,\u00a0communication\u00a0and problem-solving skills\nWilling to explore new frontier and possibilities to excel in business analytics\nBeing a good team player while can work independently\nWe offer 5-day work, attractive\u00a0remuneration\u00a0and benefits package to the right candidate.\nInterested parties please forward your full resume\u00a0(in Microsoft Word or PDF format)\u00a0with current and expect salary to the Human Resources & Facilities Services, Ricoh Hong Kong Limited,\u00a0by clicking \"Apply Now\".\nInformation provided will be treated in strict confidence and only be used for recruitment related purposes. All personal data of unsuccessful candidates will be destroyed on completion of the recruitment exercise.", "employment_types": ["Full Time", "Permanent"], "selling_points": ["~5 years exp or less exp for junior position", "Hands on experience in software development", "Double Pay; Five-day work week; Birthday Leave"], "locations": ["Kwai Tsing Area"], "categories": ["Information Technology (IT)", "Application Specialist - Software", "Product Management / Business Analyst", "Others"], "post_time": "2022-01-17T07:16:10Z", "salary": {"currency": null, "max": null, "min": null, "period": "monthly", "term": null}, "salary_visible": false, "title_keywords": ["system analyst"], "responsibilities": ["any other duties", "data", "operations", "design", "develop", "data analysis", "reports", "report"], "requirements": {"degrees": ["degree or above", "bachelor"], "majors": ["data science", "business", "statistics", "information technology"], "languages": [], "language_level": [], "hard_skills": ["excel", "plus", "bi", "ai", "problem-solving skills", "sql", "python", "r"], "soft_skills": ["good team player", "work independently", "communication", "learning", "problem-solving skills", "interpersonal", "presentation"], "languages_combined": []}, "experience_required": {"duration": ["minimum 3 years"], "field": ["business", "construction"]}}, {"job_id": "100003009054276", "location_code": "hk", "company": "YKK Hong Kong Limited", "job_title": "Business Planning Officer", "description": "\nabout the company.\n\nA leading global insurer with presence in 54 markets and serving 105 million customers worldwide.\nabout the job.\nYou will provide business analysis supports on all projects under the Department\nResponsible for preparing business requirements and translate to IT specifications\nEnsure the specifications are align with the final system design and/or work flow\nTake lead on the change management activities e.g workshops, training to understand business concerns and manage user expectations\nWork with various stakeholders to deliver the best solution; including IT vendor, Internal departments, IT, Operations, Marketing, Product, Legal & Compliance, Finance\nLead, plan and execute user acceptance testings\nPrepare data tracking report to evaluate the implementation outcome\nskills & experiences required.\nBachelor degree or above in information technology, business administration, financial engineering related disciplines or other relevant qualifications\nAt least 5 years Project Management experience in insurance industry\nSolid Business analysis skills, stakeholder management skills, change management skills\nStrong presentation and problem solving skills; Multi-tasking skills is necessary\nShort notice will be a plus\n\nInterested parties, please click \"Apply Now\" or contact Cheryl Lau at cheryl.lau@randstad.com.hk", "employment_types": ["Full Time", "Permanent"], "selling_points": ["2 year work exp in data analysis, fresh grad ok", "Bachelor Degree in Statistics, Science", "5-day, 13-mth, discretionary bonus, extra leave"], "locations": ["Tsim Sha Tsui"], "categories": ["Professional Services", "Business Analysis / Data Analysis", "Information Technology (IT)", "Product Management / Business Analyst", "Translation"], "post_time": "2022-01-17T16:21:04Z", "salary": {"currency": null, "max": null, "min": null, "period": "monthly", "term": null}, "salary_visible": false, "title_keywords": ["officer"], "responsibilities": ["administration", "management", "change management", "data", "operations", "compliance", "implementation", "evaluate", "project management", "specifications", "system design", "plan", "business analysis", "report", "insurance", "tracking"], "requirements": {"degrees": ["degree or above", "bachelor"], "majors": ["related disciplines", "business administration", "engineering", "information technology"], "languages": [], "language_level": [], "hard_skills": ["plus", "analysis", "vendor", "project management", "system design", "workshops", "problem solving skills"], "soft_skills": ["responsible", "project management", "multi-tasking skills", "problem solving skills", "presentation"], "languages_combined": []}, "experience_required": {"duration": ["at least 5 years"], "field": ["project management", "insurance industry"]}}, {"job_id": "100003009052978", "location_code": "hk", "company": "JFE Consulting Limited", "job_title": "Project Manager - IT", "description": "Responsibilities:\nPerform software development to the full SDLC\nWork with users to collect and confirm project requirements\nReview and analyze business requirements and technical requirements\nResponsible for system design and prepare related software engineering documents\nMonitor the performance of outsourced vendors\nPerform and coordinate on change, incident and problem management\nProvide support to application systems including trouble-shooting, bug fixing and ad-hoc queries\nRemote support after office hour may be required\nRequirements:\nDegree Holder in Computer Science, Computer Studies, Information Technology or related discipline\nAt least 5 years relevant IT experience (candidates with less experience will be considered for junior position)\nHands on experience in software development using Visual Studio, SQL Server Management Studio\nProficient in C#, VB.NET, ASP.NET, MVC, LINQ, SQL, XML, JQuery, JS and CSS/HTML5 programming\nKnowledge in warehouse management system is a plus.\nGood leadership and analytical skills\nAble to work independently and deal with tight project schedule\nGood spoken and written English and Mandarin\nBenefits:\nDouble Pay\nFive-day work week\nBirthday Leave\nMedical Insurance\nFree Shuttle Bus\nTraining Allowance\nAttractive remuneration package and excellent career development opportunities will be offered to the successful candidate.\u00a0 For Interested parties, please apply with a detailed resume stating present and stating present and expected salary by clicking \"Apply Now\".\u00a0 You are welcome to visit our website at http://www.cargofe.com.\nPersonal data collected will be used for recruitment purposes only and be treated in strict confidence.\u00a0 Cargo Services treats all applicants for employment in the same way, regardless of age, sex, marriage and civil partnership, race, disability, religion or belief.", "employment_types": ["Full Time", "Permanent"], "selling_points": ["Project Management", "IT industry", "10+ years of experience, attractive salary"], "locations": ["Quarry Bay"], "categories": ["Information Technology (IT)", "IT Project Management / Team Lead", "IT Management", "Product Management / Business Analyst"], "post_time": "2022-01-17T04:48:24Z", "salary": {"currency": null, "max": null, "min": null, "period": "monthly", "term": null}, "salary_visible": false, "title_keywords": ["project manager"], "responsibilities": ["ad-hoc", "project requirements", "management", "provide support", "software", "review", "coordinate", "system design", "monitor the performance", "application systems"], "requirements": {"degrees": ["degree holder"], "majors": ["information technology", "computer science", "computer studies"], "languages": ["english", "mandarin"], "language_level": ["good"], "hard_skills": ["plus", "jquery", "analytical skills", "sql", "programming", "server", "css", "c#"], "soft_skills": ["work independently", "hands on", "leadership", "analytical skills"], "languages_combined": [{"language": "english", "language_level": ["good"]}, {"language": "mandarin", "language_level": ["good"]}]}, "experience_required": {"duration": ["at least 5 years"], "field": ["software development", "management", "sql", "it experience"]}}, {"job_id": "100003009054831", "location_code": "hk", "company": "Hong Kong Disneyland", "job_title": "Associate Manager, Program Management Office", "description": "Job Descriptions:\n\nSupport internal requests to prepare weekly and monthly reports of sales data, make weekly/ monthly reports, consolidate and analyze sales and research data;\n\nCreate the business yearly plan by using Excel Format;\nRegular updates and prepares internal database and distribute the summary of some specific items sales by month;\nPerform data extraction, collect and analyze the marketing information of HK & China for apparel business and generate reports for management's review;\nPrepare PowerPoint, presentation\u00a0materials and ad-hoc analysis or tasks for the Department or seniors;\nSupporting RPA & EDI arrangement as well as build and maintain digitalization of working processing;\nHandle enquiries from Japan HQ about business situation;\nAssist in ad-hoc duties if necessary.\nJob Requirements:\n\nBachelor Degree or above majoring in Statistics or Sciences or other business related subjects with 2 years working experience in data analysis, fresh graduates with also be considered;\nMUST be sensitive to figures / numbers with\u00a0analytical and organized thinking;\nMust be proficient in the following computer skills:-\nMS Office Excel\nAble to arrange a series of data with \"Pivot Table\"\nFamiliar with other functions such as \"VLOOKUP\", \"HLOOKUP\", \"AVERAGE\", etc.\nAccess\nWith basic knowledge of Access.\nVBA\nWith basic knowledge of VBA is a plus.\nProficient in MS Word, PowerPoint, Chinese Word Processing;\nGood command of both spoken and written Cantonese, English and Mandarin;\nCandidates with study (JPLT N2 or above) or working experience in Japan will be an advantage;\nFast learner and able to work under pressure;\nSelf-motivated, good writing and presentation skills.\n\nBenefits:\n\n5-day work (Staggered Work Hour System)\nDouble Pay\nDiscretionary bonus\nGroup medical\nOT pay\nStatutory Annual Leave with extra 7 days Company Annual Leave\nBank Holiday\nOther Special Leave i.e. Marriage Leave, etc.\n\nWe offer competitive remuneration and benefits, holidays, stable working environment to the right candidates. Interested parties please click \"Apply Now\" and send your full resume with expected salary in MS Word Format to us (Please quote Position Name & Reference No.)", "employment_types": ["Full Time", "Permanent"], "selling_points": ["Assist team head in preparing presentations", "Bachelor Degree", "7 years in in technology, planning"], "locations": ["Lantau Island"], "categories": ["Admin & HR", "Secretary", "Information Technology (IT)", "IT Project Management / Team Lead", "Product Management / Business Analyst"], "post_time": "2022-01-17T11:27:38Z", "salary": {"currency": null, "max": null, "min": null, "period": "monthly", "term": null}, "salary_visible": false, "title_keywords": ["associate manager"], "responsibilities": ["ad-hoc", "management", "ad-hoc duties", "monthly reports", "data", "analysis", "review", "handle enquiries", "maintain", "reports", "database", "plan", "weekly and monthly reports"], "requirements": {"degrees": ["degree or above", "bachelor"], "majors": ["business", "statistics"], "languages": ["cantonese", "english", "chinese", "mandarin"], "language_level": ["good command", "proficient"], "hard_skills": ["excel", "vba", "plus", "basic", "chinese word processing", "ms word", "analysis", "pivot table", "powerpoint", "vlookup", "ms office"], "soft_skills": ["organized", "self-motivated", "sensitive to figures", "presentation skills", "fast learner", "work under pressure"], "languages_combined": [{"language": "cantonese", "language_level": ["good command"]}, {"language": "english", "language_level": ["good command"]}, {"language": "chinese", "language_level": ["proficient"]}, {"language": "mandarin", "language_level": ["good command"]}]}, "experience_required": {"duration": ["2 years"], "field": ["related", "business", "statistics", "data analysis"]}}, {"job_id": "100003009050170", "location_code": "hk", "company": "Nanyang Commercial Bank, Limited", "job_title": "Information Technology Manager - Business Analyst", "description": "Our client, one of the leading IT companies, is looking for high calibres to join their winning team:-\n\nResponsiblities:\n\n\n\nAdvanced computer skills and in-depth knowledge of different operating systems, network administration and service desk administration\nProject management and leadership skills for managing projects and the teams involved with themStrong written and verbal communication skills to coordinate with team members and management and explain technical issues\nAnalytical and problem-solving skills to handle any issues that occur during project completion\n\nRequirements:\n\nBachelor Degree in Information Technology or equivalent.\n10 years of IT experience or above with 6 years or above experience of project management in web application implementation projects\nUnderstanding of MSP ticketing and Alert Management Systems.\nThorough understanding of project management fundamentals.\nUnderstanding of software development life cycle\nOutstanding leadership, organizational, and time management skills.\nOutstanding verbal and written communication skills.\nStrong people skills.", "employment_types": ["Full Time"], "selling_points": ["Information Technology", "System Integration", "Problem Solving"], "locations": ["Central"], "categories": ["Information Technology (IT)", "Product Management / Business Analyst"], "post_time": "2022-01-15T03:50:54Z", "salary": {"currency": null, "max": null, "min": null, "period": "monthly", "term": null}, "salary_visible": false, "title_keywords": ["business analyst", "technology manager"], "responsibilities": ["network administration", "management", "teams", "coordinate with", "communication", "project management", "operating systems", "administration"], "requirements": {"degrees": ["degree", "bachelor"], "majors": ["information technology"], "languages": [], "language_level": [], "hard_skills": ["project management", "web"], "soft_skills": ["communication skills", "time management skills", "organizational", "project management", "thorough", "leadership"], "languages_combined": []}, "experience_required": {"duration": ["6 years", "10 years"], "field": ["project management", "it experience"]}}, {"job_id": "100003009056166", "location_code": "hk", "company": "Osmium Consulting Group Limited", "job_title": "Business Coordinator / Business Analyst - 20K - 35K ( FinTech Company )", "description": "Responsibilities\n\nCoordinate and communicate with business users for production products\nAssist Business Analysts to ensure IT deliverables that would satisfy business requirements and would achieve anticipated business benefits\nWork with key project members e.g. project manager, developers, QA to help them understand business requirements and the processes, to ensure finished product complies with users and business specifications\n\nRequirements\n\nExcellent communication skills with possession of good problem-solving ability\nWilling to learn and work under pressure\nProactive, confident, can-do attitude\nAble to work effectively with business users and technical team\nExperience in Finance products / projects is a big plus!\nNative Cantonese Speaker\u00a0\nBenefits\n\nPassionate and Young Team\nMedical, Dental Insurance\n18 days AL\nOn-site Training\n5 days Work Week", "employment_types": ["Full Time", "Permanent"], "selling_points": ["FinTech inHouse / Global Vendor Company", "Young and Passionate Team !", "18 days AL !"], "locations": ["Wan Chai"], "categories": ["Information Technology (IT)", "IT Management", "Product Management / Business Analyst", "Software Development"], "post_time": "2022-01-18T03:27:41Z", "salary": {"currency": "HKD", "max": 34999, "min": 20000, "period": "monthly", "term": null}, "salary_visible": true, "title_keywords": ["coordinator", "business analyst"], "responsibilities": ["coordinate", "communicate with"], "requirements": {"degrees": [], "majors": [], "languages": [], "language_level": [], "hard_skills": [], "soft_skills": [], "languages_combined": []}, "experience_required": {"duration": [], "field": []}}, {"job_id": "100003009056077", "location_code": "hk", "company": "DFI Retail Group DFI\u96f6\u552e\u96c6\u5718", "job_title": "Business Systems Analyst", "description": "This role is to deliver business or systems analysis to support design of small/medium complexity projects\n\nThe Job:\n\nDo hands on business and systems analysis work\nEstablish and maintain good working relationship with other IT functional areas\nHave a solid understanding of the IT architecture and business processes in your area to be a trusted business advisor\nCoach and mentor junior members of staff in BA or SA tasks\nLiaise effectively with offshore development teams when required\nFollow and tune the Software Development Life Cycle to deliver good quality and lower cost solutions\nStrong Cost/Benefit focus to ensure effort is focused on true business value\n\nThe Person:\n\nA bachelor\u2019s degree in Business Information Systems or related field\nA minimum of 2 to 3 years\u2019 experience in business analysis or a related field\nExceptional analytical and conceptual thinking skills\nThe ability to influence stakeholders and work closely with them to determine acceptable solutions\nAdvanced technical and excellent documentation skills\nCompetency in Microsoft applications including Word, Excel, Outlook and Sharepoint\nExcellent in spoken and written English, Chinese and Mandarin\n\n\u201cDFI Retail Group is responsible for ensuring that all personal information collected from each Candidate presented to DFI Retail Group is used for recruitment purposes only and the data collection process is in accordance with all applicable laws and compliant with the Code of Practice on Human Resource Management.\n\nTo find out more about Our Businesses and Our People, please visit our website: https://www.DFIretailgroup.com\n\nWe are an equal opportunity employer. Personal data collected will be kept and handled confidentially by authorised personnel for recruitment purposes only. We will retain the applications of candidates not selected for a period of no more than 24 months. A copy of our Privacy Policy can be accessed by visiting our Company website.\u201d\n\nIssued by The Dairy Farm Company, Limited", "employment_types": ["Full Time"], "selling_points": [], "locations": ["Quarry Bay"], "categories": ["Information Technology (IT)", "Product Management / Business Analyst"], "post_time": "2022-01-18T03:15:04Z", "salary": {"currency": null, "max": null, "min": null, "period": "monthly", "term": null}, "salary_visible": false, "title_keywords": ["analyst"], "responsibilities": ["liaise", "cost", "software", "analysis", "systems", "teams", "quality", "maintain", "architecture"], "requirements": {"degrees": ["degree", "bachelor"], "majors": ["business"], "languages": ["english", "chinese", "mandarin"], "language_level": ["excellent"], "hard_skills": ["excel", "no", "microsoft applications", "analysis", "word", "outlook", "documentation", "code"], "soft_skills": ["advanced", "responsible"], "languages_combined": [{"language": "english", "language_level": ["excellent"]}, {"language": "chinese", "language_level": ["excellent"]}, {"language": "mandarin", "language_level": ["excellent"]}]}, "experience_required": {"duration": ["minimum of 2 to 3 years"], "field": ["business analysis", "related"]}}, {"job_id": "100003009051969", "location_code": "hk", "company": "ADECCO", "job_title": "(Senior) Business Analyst (UAT, Developer, Up to 40k)", "description": "Our client is a leading integrated express logistics service provider in China, aims to provide customers with one-stop integrated logistics solutions.\n\nResponsibilities\n\nUnderstand the business needs, balance the requirements amongst business stakeholders and recommend solutions\nAnalyze users \u2018 requirements and translate users\u2019 ideas and cases into functional specification\nWork closely with onshore/offshore development team and external vendors to ensure the system can be completed timely\nManage the project schedule from the high-level system design and analysis, system implementation/enhancement, UAT to system deployment\nPrepare and maintain function specification and training documentation\n\nExperience\n\n1 year plus the working experience in software development, system solution consultancy, or developing programmable documents, preferably in Logistics/Courier Industries or consultant companies\nPractical experience in understanding, analyzing, and verifying user requirements versus business processes to develop programmable documents\nGood presentation and communication skills\n\nEducation\n\nHigher Diploma or above in Computer Science, Business Analytics, Information Technology, Logistics or other related disciplines\nGood command of written and spoken English and Chinese (including Putonghua)\n\n\n\nInterested parties, please\u00a0CLICK HERE\u00a0to apply online. (Ref:JDB/IT-TT)\n\nPlease note that only short-listed candidates will be notified. All information gathered will be treated in strict confidence and solely used for recruitment purposes", "employment_types": ["Full Time", "Permanent"], "selling_points": ["Leading delivery and logistic company in HK", "Business Analyst role with developer background", "Stable job with attractive salary and bonus"], "locations": ["Tsing Yi"], "categories": ["Information Technology (IT)", "Product Management / Business Analyst", "Software Development", "Testing / QA"], "post_time": "2022-01-17T01:40:31Z", "salary": {"currency": null, "max": null, "min": null, "period": "monthly", "term": null}, "salary_visible": false, "title_keywords": ["developer", "business analyst"], "responsibilities": ["ideas", "uat", "software", "analysis", "implementation", "developing", "develop", "communication", "system design", "logistics", "schedule", "maintain", "documentation"], "requirements": {"degrees": ["higher diploma or above"], "majors": ["related disciplines", "business analytics", "computer science", "information technology"], "languages": ["putonghua", "english", "chinese"], "language_level": ["good command"], "hard_skills": ["plus", "documentation", "analysis", "system design", "deployment", "system implementation"], "soft_skills": ["communication skills", "timely", "presentation"], "languages_combined": [{"language": "putonghua", "language_level": ["good command"]}, {"language": "english", "language_level": ["good command"]}, {"language": "chinese", "language_level": ["good command"]}]}, "experience_required": {"duration": ["1 year"], "field": ["business", "logistics", "developing", "software development"]}}, {"job_id": "100003009056057", "location_code": "hk", "company": "Dyxnet Limited", "job_title": "Product Solution Manager", "description": "Job Responsibilities:\n\n\nSolid experience in network solution, such as MPLS VPN\u3001SD-WAN.\nSupport and contribution to the network solution project in Hong Kong and Taiwan. Assist and implement the project solutions plan.\nConduct the customer needs and responsible for in depth analysis for our customer and provide insights and recommendations for network solution.\nManage Price Book and Product P&L.\nKeep track on monitoring product/solution performance, including sales, GP, service level, customer satisfactions, in order to communicate with management and partner for better synergy with mutual benefits\n\nRequirements:\n\nBachelor\u2019s degree in Information Technology, Computer Science, or related disciplines.\n5 years\u2019 relevant experience in IT & Telecommunications industry is highly preferred.\nFamiliar with networking technologies (Such as SD-WAN, MPLS and VPN).\nExcellent presentation, communication, and interpersonal skills.\nKeep learning enthusiasm for new network products and new technologies.\nPositive attitude, fast-learning, energetic, able to perform in challenging environment.\nA good team player with analytical & problem-solving skills, self-motivation and good interpersonal skills, cost, and time conscious.\n\nAttractive remuneration and compensation package, including year end bonus, medical scheme, life insurance, as well as career development opportunities will be offered.\n\nInterested parties please send your resume with expected salary and availability to Human Resources Department, Dyxnet Group, 37/F, Tower 1, Metoplaza, 223 Hing Fong Road, Kwai Fong.\n\nWelcome to visit our website: http://www.dyxnet.com for further information of our company.\n\nData collected will be used for recruitment purpose only.", "employment_types": ["Full Time", "Permanent"], "selling_points": ["Experience in network solution", "5 years\u2019 relevant", "SD-WAN, MPLS and VPN"], "locations": ["Kwai Fong"], "categories": ["Information Technology (IT)", "Product Management / Business Analyst", "Network & System", "Sales, CS & Business Devpt", "Others"], "post_time": "2022-01-18T03:14:00Z", "salary": {"currency": null, "max": null, "min": null, "period": "monthly", "term": null}, "salary_visible": false, "title_keywords": ["manager"], "responsibilities": ["communicate with", "provide insights", "management", "analysis", "monitoring", "p&l", "plan"], "requirements": {"degrees": ["degree", "bachelor"], "majors": ["related disciplines", "computer science", "information technology"], "languages": [], "language_level": [], "hard_skills": ["problem-solving skills", "sd-wan", "vpn", "scheme"], "soft_skills": ["good team player", "fast-learning", "communication", "positive attitude", "learning", "interpersonal skills", "self-motivation", "problem-solving skills", "energetic", "presentation"], "languages_combined": []}, "experience_required": {"duration": ["5 years"], "field": ["telecommunications", "it", "relevant experience"]}}, {"job_id": "100003009052114", "location_code": "hk", "company": "Chesterton Consulting Co Limited", "job_title": "IT Business Analyst", "description": "Our Client is a long established local university in Hong Kong.\u00a0 A need has arisen to hire an IT Business Analyst to join its team.\u00a0\n\nThis is an excellent opportunity for individuals who enjoy working in a fast paced environment.\u00a0\u00a0\n\nContributing to and driving continuous process improvement initiatives to meet faculty needs\nWorking closely with multiple stakeholders to gather, analyse and define current business processes as well as requirements\nTranslating business requirements into detailed functional specifications.\nSupporting the Project Manager in delivering the project plan on-time and on-budget\nEnsuring requirements issues are tracked, reported and resolved in a timely manner\nEffectively communicating plan, status, risks and issues to the stakeholder in a precise and timely manner\nSupporting users' participation in deployments and implementation activities\nTo qualify, you should be a degree holder with at least 5 years of experience working as a business analyst in a large corporations setting.\u00a0 You should demonstrate high level of initative and with the ability to work with different stakeholders.\u00a0 Full fluency in English and Chinese is a must.\u00a0\u00a0", "employment_types": ["Full Time", "Permanent"], "selling_points": ["Excellent Career Opportunity", "Stable Enviornment", "Fast Paced"], "locations": ["Sai Ying Pun"], "categories": ["Information Technology (IT)", "Product Management / Business Analyst"], "post_time": "2022-01-17T02:07:43Z", "salary": {"currency": null, "max": null, "min": null, "period": "monthly", "term": null}, "salary_visible": false, "title_keywords": ["business analyst"], "responsibilities": ["budget", "a timely manner", "project plan", "implementation", "specifications", "plan", "analyse"], "requirements": {"degrees": ["degree holder"], "majors": ["business"], "languages": ["english", "chinese"], "language_level": ["fluency"], "hard_skills": [], "soft_skills": ["precise", "enjoy working", "timely", "detailed"], "languages_combined": [{"language": "english", "language_level": ["fluency"]}, {"language": "chinese", "language_level": ["fluency"]}]}, "experience_required": {"duration": ["at least 5 years"], "field": ["business"]}}, {"job_id": "100003009055833", "location_code": "hk", "company": "Ambition", "job_title": "Business Analyst - Commerce - Hong Kong", "description": "Business Analyst - Commerce - Hong Kong\n\nA MNC client on commerce side is now hiring a high calibre Business Analyst to join their team. The ideal candidate would have prior project experience around ERP system implementation/enhancement.\n\nResponsibilities:\n\nYou will support operations and functional teams to define problems or desired outcomes, determine required information, synthesize findings, and recommend action.\nYou will work closely with the IT application team throughout the system development life cycle to deliver product features and solutions.\nYou will also understand the business objectives and rationales behind high-level product features, analyse and translate them into detailed user project specifications and system configuration requirements.\n\nRequirements:\n\nExperienced in Agile/Scrum software development environment preferred\nExperienced in medium to large scale digital transformation and ERP implementation projects\nAnalytical thinking and strong communication skills\nExcellent communication skills in Cantonese and English\n\nPlease submit resume to jessie.rao@ambition.com.hk\n\nIf this job isn't quite right for you, but you know someone who would be great at this role, why not take advantage of our referral scheme? We offer HKD1000 in Apple gift cards for every referred candidate who we place in a role. Terms & Conditions Apply. https://www.ambition.com.hk/refer-a-friend", "employment_types": ["Full Time", "Permanent"], "selling_points": ["Business Analyst", "Commerce", "Based in Hong Kong"], "locations": ["Not Specified"], "categories": ["Information Technology (IT)", "Application Specialist - Software", "Product Management / Business Analyst", "Technical / Functional Consulting"], "post_time": "2022-01-18T02:59:42Z", "salary": {"currency": "HKD", "max": 29999, "min": 25000, "period": "monthly", "term": null}, "salary_visible": true, "title_keywords": ["business analyst"], "responsibilities": ["configuration", "operations", "teams", "specifications", "analyse"], "requirements": {"degrees": [], "majors": [], "languages": ["cantonese", "english"], "language_level": ["excellent"], "hard_skills": ["agile", "erp", "scheme"], "soft_skills": ["communication skills", "agile"], "languages_combined": [{"language": "cantonese", "language_level": ["excellent"]}, {"language": "english", "language_level": ["excellent"]}]}, "experience_required": {"duration": [], "field": []}}, {"job_id": "100003009056088", "location_code": "hk", "company": "Hays", "job_title": "Business Intelligence Officer", "description": "Perform data analysis and planning to generate business insights for the team\n\nYour new company\nThe expanding team is looking for a proactive and motivated team player with experiences in data analysis and data visualisation to support their thriving businesses.\n\nYour new role\n\nWork closely with different parties for the preparation of business analysis\nDesign dashboards for KPI reporting\nTranslate daily business observations by data analytical methods\nEnsure the accuracy of existing data\n\n\nWhat you'll need to succeed\n\nDegree holder in Statistics, Mathematics, or other related disciplines\nSavvy in financial reporting or statistical analysis\n3+ years of experience in data analysis and data visualisation\nProficient in using Power BI, Tableau, or other relevant data visualisation software\n\n\nWhat you need to do now\nIf you're interested in this role, click 'apply now' to forward an up-to-date copy of your CV, or reach out to our consultant Agnes Chow via phone 2101 0060 or agnes.chow@hays.com.hk now. If this job isn't quite right for you but you are looking for a new position, please contact us for a confidential discussion on your career.", "employment_types": ["Full Time", "Permanent"], "selling_points": ["Data visualisation", "Career progression", "Competitive package"], "locations": ["Not Specified"], "categories": ["Information Technology (IT)", "Product Management / Business Analyst"], "post_time": "2022-01-18T03:15:44Z", "salary": {"currency": null, "max": null, "min": null, "period": "monthly", "term": null}, "salary_visible": false, "title_keywords": ["officer"], "responsibilities": ["reporting", "power bi", "software", "data", "analysis", "design", "data analysis", "financial reporting", "contact", "business analysis", "planning"], "requirements": {"degrees": ["degree holder"], "majors": ["related disciplines", "mathematics", "statistics"], "languages": [], "language_level": [], "hard_skills": ["analysis", "bi", "statistical analysis", "tableau"], "soft_skills": ["motivated", "team player", "proactive", "interested in"], "languages_combined": []}, "experience_required": {"duration": ["3+ years"], "field": ["data analysis", "team"]}}, {"job_id": "100003009056209", "location_code": "hk", "company": "DFI Retail Group DFI\u96f6\u552e\u96c6\u5718", "job_title": "Analyst - yuu", "description": "yuu is Hong Kong\u2019s newest, biggest and best rewards club. Launched in July 2020, it has rapidly grown to a membership covering over 50% of the addressable population in Hong Kong. And we continue to grow! The yuu team is highly energetic and motivated to do the best for our members and partners and we\u2019re always looking out for like-minded individuals to join us on our exciting growth journey.\n\nReporting into the Analytics Manager, the purpose of this role is to provide high quality insights to loyalty program partners\u2019 trading and marketing teams and/or FMCG suppliers.\n\nThe job holder will use their high numerical aptitude to deliver high quality customer insight & expertise to their clients as part of a rapidly expanding analytics team.\n\n\nThe Job\n\nThe main day-to-day responsibilities are:\n\nPerform customer analysis and drive insights and recommendations from the results to address business questions\nSupport CRM activities through customer targeting, lists preparation and analysis\nConduct offer and campaign evaluations, recommend right tracking metrics, measure effectiveness and provide recommendations to improve future response/ ROI\nSupport ad hoc analytics projects e.g. customer segmentation, churn prediction, propensity on acquisition\nIdentify areas to improve efficiency and streamline process through automation\nKeep track on KPIs and regular reports on CRM and customer performance\n\n\nThe Person\n\nEducated to degree level in numerical field (e.g. Mathematics, Statistics, Economics)\nAt least 2 years experience in data analysis, customer segmentation, statistical modelling\nSolid experience in SQL\nKnowledge of Tableau, Python, R is a plus\nKnowledge of Microsoft Azure environment, Databricks is a plus\nConfident communicator of analytics to technical and non-technical audiences\nA natural curiosity to interrogate data and identify hidden patterns to support business needs\n\u00a0\n\nDFI Retail Group is responsible for ensuring that all personal information collected from each Candidate presented to DFI Retail Group is used for recruitment purposes only and the data collection process is in accordance with all applicable laws and compliant with the Code of Practice on Human Resource Management.\n\nTo find out more about Our Businesses and Our People, please visit our website:\u00a0www.DFIretailgroup.com\n\nWe are an equal opportunity employer. Personal data collected will be kept and handled confidentially by authorised personnel for recruitment purposes only. We will retain the applications of candidates not selected for a period of no more than 24 months. A copy of our Privacy Policy can be accessed by visiting our Company website.\n\nIssued by The Dairy Farm Company, Limited", "employment_types": ["Full Time"], "selling_points": ["One of the biggest loyalty programs in HK", "Degree level in Mathematics, Statistics, Economics", "2 years experience in data analysis"], "locations": ["Tai Koo"], "categories": ["Information Technology (IT)", "Product Management / Business Analyst"], "post_time": "2022-01-18T03:32:45Z", "salary": {"currency": null, "max": null, "min": null, "period": "monthly", "term": null}, "salary_visible": false, "title_keywords": ["analyst"], "responsibilities": ["ad hoc", "analysis", "provide recommendations", "reports", "kpis", "tracking"], "requirements": {"degrees": ["degree"], "majors": [], "languages": [], "language_level": [], "hard_skills": ["plus", "no", "azure", "analysis", "code", "tableau", "sql", "python", "r"], "soft_skills": ["confident", "communicator", "responsible"], "languages_combined": []}, "experience_required": {"duration": ["at least 2 years"], "field": ["data analysis", "sql"]}}, {"job_id": "100003009046736", "location_code": "hk", "company": "DCH Auriga (Hong Kong) Limited", "job_title": "Senior Business Analyst / Assistant Manager - IT", "description": "Job Descriptions:\n\nThe incumbent will be responsible for providing IT support services and implementing application systems and network integration. He/She will manage projects, collect business requirements, design, prepare system documentation & testing and provide support on logistic/trading business.\n\nRequirements:\n\nDegree in Information Technology or related disciplines\nat least 5 year's relevant experience, preferably in project management, system implementation and application support\nExposure in ERP, WMS and Supply Chain process\nProject Management experience is a bonus\nBasic understanding on IT Infrastructure\nGood communication, analytical and problem solving skills\nWilling to learn and can work independently\nGood in written and spoken English and Chinese; Mandarin is a plus\nCandidate with more experience will be considered as Assistant Manager\u00a0 \u00a0\nAll applications received will be used exclusively for recruitment purposes only. Applicants who are not contacted within 8 weeks should consider their application unsuccessful for the position advertised. Data supplied by applicants will be kept for 6 months.", "employment_types": ["Full Time", "Permanent"], "selling_points": [], "locations": ["Kwai Fong"], "categories": ["Information Technology (IT)", "Application Specialist - Software", "IT Project Management / Team Lead", "Product Management / Business Analyst"], "post_time": "2022-01-14T00:14:47Z", "salary": {"currency": null, "max": null, "min": null, "period": "monthly", "term": null}, "salary_visible": false, "title_keywords": ["assistant manager", "senior business analyst"], "responsibilities": ["provide support", "system documentation", "support services", "design", "testing", "manage projects", "application systems", "network integration", "collect business requirements"], "requirements": {"degrees": ["degree"], "majors": ["related disciplines", "information technology"], "languages": ["english", "chinese", "mandarin"], "language_level": ["good"], "hard_skills": ["plus", "basic", "erp", "project management", "system implementation", "problem solving skills"], "soft_skills": ["work independently", "willing to learn", "communication", "project management", "analytical and problem solving skills"], "languages_combined": [{"language": "english", "language_level": ["good"]}, {"language": "chinese", "language_level": ["good"]}, {"language": "mandarin", "language_level": []}]}, "experience_required": {"duration": ["at least 5 year"], "field": ["project management", "relevant experience"]}}, {"job_id": "100003009052466", "location_code": "hk", "company": "Xensetech Limited", "job_title": "Business Process Re-engineering Officer", "description": "Responsibilities\n\nWork with different internal teams to enhance business operations and process reengineering projects;\nDefine Business Process Reengineering scope and to-be process;\nDocumentation of process and workflows;\nAssist in\u00a0ad hoc tasks and other duties as required;\nPrepare training materials & documents and provide training to user department\n\nRequirements\n\nDegree or above in IT, CS and Computing Engineering or equivalent;\n3 years or above relevant experience in business analysis/project management role;\nWell-developed analytical and problem solving skills;\nExcellent interpersonal and communication skill;\nExcellent verbal and written skill in English and Chinese;\nDeep intellectual curiosity, detail-oriented and independently;\nExperience in SQL and programming skill will be an advantage;\nExperience in managing and delivering process improvement / re-engineering / project management;\nUnderstanding the operations in the Construction industry will be an advantage\n\nInterested parties please apply with a detailed resume stating expected salary and date of availability to the HR Manager through fax at 2833 5441 or e-mail by clicking \"APPLY NOW\".\n\nCompany Website:\u00a0https://xensetech.hk/\n\nAll personal data provided will be used strictly in accordance with our \u201cPersonal Information Collection Statement Pertaining to Recruitment\u201d, a copy of which is available upon written request to us by E-mail.", "employment_types": ["Full Time", "Permanent"], "selling_points": ["Degree or above in IT, CS & Computing Engineering", "Stable and professional team, friendly culture", "Competitive remuneration package"], "locations": ["Shatin Area"], "categories": ["Information Technology (IT)", "Application Specialist - Software", "Product Management / Business Analyst", "Technical / Functional Consulting"], "post_time": "2022-01-17T03:05:53Z", "salary": {"currency": null, "max": null, "min": null, "period": "monthly", "term": null}, "salary_visible": false, "title_keywords": ["officer"], "responsibilities": ["provide training", "other duties", "operations", "teams", "ad hoc tasks", "business process", "documentation"], "requirements": {"degrees": ["degree or above"], "majors": ["it", "engineering"], "languages": ["english", "chinese"], "language_level": ["excellent"], "hard_skills": ["analysis", "sql", "project management", "programming", "problem solving skills"], "soft_skills": ["independently", "communication skill", "deep", "detail-oriented", "project management", "analytical and problem solving skills", "interpersonal"], "languages_combined": [{"language": "english", "language_level": ["excellent"]}, {"language": "chinese", "language_level": ["excellent"]}]}, "experience_required": {"duration": ["3 years"], "field": ["engineering", "sql", "project management", "relevant experience", "programming", "business analysis"]}}, {"job_id": "100003009054993", "location_code": "hk", "company": "China Mobile Hong Kong \u4e2d\u570b\u79fb\u52d5\u9999\u6e2f", "job_title": "Product Manager, Smart Home Business", "description": "CHINA MOBILE HONG KONG COMPANY LIMITED\u00a0(\"CMHK\") is the wholly-owned subsidiary of China Mobile Limited (HKEx: 941) (NYSE: CHL), which ranks 65th on the Fortune Global 500.\n\nOur company strives to offer superior service experience and to become the preferable digital partner for customers. We are preserving an environment with trust, responsibility and caring. At CMHK, we commit to maximizing people\u2019s potential and paving the way toward success for every striver. We are now inviting high caliber professional to join us.\n\nDivision: Marketing\u00a0 / Smart Home Business Department\n\nIn this position, you will:\n\nResponsible for the design and delivery of household product solutions;\nPromote ecological cooperation and product expansion and cooperation; have practical experience in building a smart furniture ecosystem, have strong upstream terminal or application field customer resources, and be able to quickly build a product system based on the industrial chain;\nResponsible for the B2B2C product integration planning, and cooperate with the corporate sales department to participate in the project competition of real estate developers and industry customers, and formulate product plans;\nThe ability to understand the business goals and high-level requirements and effectively define a systematic solution;\nResponsible for technology solution of home service IT supporting system, smart home products, GPON/IP network enhancement.\nAs technical facial point, create quality deliverables and communicate with appropriate all level audiences;\nCandidate shall coordinate various projects which related to home service IT supporting system, new products release, network enhancement.\n\n\n\nTo be successful in this position, you should meet the following requirements:\n\nBachelor degree holder;\nCAPM/ITIL/PMP certification preferred;\nAt least 5 years of work experience;\nExcellent communication skills, presentation skills, leadership skills and good at teamwork;\nEnergetic, self-motivated, able to work under pressure and independently;\nGood computer skills in Microsoft Office;\nGood command of written and spoken English and Chinese/Putonghua.\nCandidate with\u00a0less experience may consider as Assistant Manager\n\nWhen you work:\n\n5\u00a0days work\n8 hours/day\n\nWhat you enjoy:\n\nDouble pay\nDiscretionary Performance bonus\nLife insurance\nMedical insurance\nEducation subsidies\nBirthday gift\nMarriage leave\nBirthday leave\nStaff discount\n\nCMHK is committed to be an equal opportunity employer. We offer exceptional benefits package and the opportunity to work in a challenging environment. Personal data provided by applicants will be treated strictly in accordance with our personal data policy and for recruitment purposes only.\n\n\n", "employment_types": ["Full Time", "Permanent"], "selling_points": ["18 AL, Double pay, Performance bonus", "5 days work week", "Staff SIM, Staff offer"], "locations": ["Kwai Hing"], "categories": ["Information Technology (IT)", "Product Management / Business Analyst", "Marketing / Public Relations", "Marketing - Brand / Product Management", "Marketing - General / Support"], "post_time": "2022-01-17T16:22:50Z", "salary": {"currency": null, "max": null, "min": null, "period": null, "term": null}, "salary_visible": false, "title_keywords": ["product manager"], "responsibilities": ["communicate with", "business goals", "work under pressure", "quality", "design", "coordinate", "communication", "plans", "insurance", "cooperate with", "planning"], "requirements": {"degrees": ["bachelor degree holder"], "majors": [], "languages": ["putonghua", "english", "chinese"], "language_level": ["good command"], "hard_skills": ["itil", "microsoft office", "mobile", "ip", "computer skills", "integration", "pmp"], "soft_skills": ["communication skills", "self-motivated", "independently", "responsible", "work under pressure", "leadership skills", "teamwork", "systematic", "committed", "presentation skills", "energetic", "superior"], "languages_combined": [{"language": "putonghua", "language_level": ["good command"]}, {"language": "english", "language_level": ["good command"]}, {"language": "chinese", "language_level": ["good command"]}]}, "experience_required": {"duration": ["at least 5 years"], "field": ["digital"]}}, {"job_id": "100003009052319", "location_code": "hk", "company": "Capgemini Hong Kong Limited", "job_title": "Business Analyst", "description": "Responsibilities\n\nWork with delivery manager and solution architect to coordinate the API/mico-service integration\nReview and analyze the API coverage\nUnderstand basic RESTful API specification (e.g. RAML, Swagger)\nDocumentation of technical specifications\nCloud project experience, e.g. AWS/CGP\nExperience of using Jira/Confluence or similar tools\n\nQualifications:\n\n5 years+ relevant experience\nStrong and proactive communication\nA willingness to dig into the details to understand issues\nAble to quickly adapt in new situations and build relationships\nSTEM degree holder preferred\nCantonese and English", "employment_types": ["Full Time", "Contract"], "selling_points": ["API/mico-service integration project", "Financial domain project", "Business analyst"], "locations": ["Yau Tsim Mong Area"], "categories": ["Information Technology (IT)", "Product Management / Business Analyst"], "post_time": "2022-01-17T02:45:22Z", "salary": {"currency": null, "max": null, "min": null, "period": "monthly", "term": null}, "salary_visible": false, "title_keywords": ["business analyst"], "responsibilities": ["review", "coordinate", "communication", "specifications", "documentation"], "requirements": {"degrees": ["degree holder"], "majors": [], "languages": ["cantonese", "english"], "language_level": [], "hard_skills": ["restful api", "documentation", "basic", "aws", "integration"], "soft_skills": ["communication", "proactive"], "languages_combined": [{"language": "cantonese", "language_level": []}, {"language": "english", "language_level": []}]}, "experience_required": {"duration": [], "field": ["relevant experience"]}}, {"job_id": "100003009051612", "location_code": "hk", "company": "Leadership Solutions Limited", "job_title": "Business Analyst", "description": "Our client is looking for high caliber candidates to join their technical team. Candidates will be exposed to sizable projects with reputable customers. The job offers excellent opportunity for candidates to develop his/her career in IT Industry.\n\nJob Responsibilities:\n\nParticipate in requirement gathering and analysis, design, testing and support of automatic fare collection systems\nPrepare test plan, test workbook and test data to ensure the test coverage\nConduct various system testing to ensure that systems operate accurately, effectively, efficiently and according to the requirement specifications\nEnsure on-time and quality delivery\nFulfill subsequent system changes and post-launch support duties\nRequirements:\n\nBachelor degree holder in Information Technology or a related discipline\nHolder of Business Analyst certification from HKITPC or IIBA would be an advance\nAt least 2 years of experience working as business analyst on large & complex projects involving multiple stakeholders and complex technologies across different geographical areas/regions\nSound knowledge of project management lifecycle and methodologies (e.g. Prince2, PMP, SDLC, Agile, etc.) and typical problems associated with the implementation of projects\nKnowledge and experience in any of the following would be an advantage SQL SOAPUI .NET\nGood team player and willing to learn new technologies\nStrong analytical, problem solving, interpersonal and organizational skills\nEffective communication skills in both verbal and written English\nExperienced candidate will be considered as Senior Business Analyst\u00a0\n\nInterested parties please send your full resume with current and expected salary, availability in\u00a0Word format\u00a0to us.\n\nAll personal information collected will be treated in strict confidential and be used solely for recruitment purpose", "employment_types": ["Full Time", "Permanent"], "selling_points": ["Business Analyst", "gather user requirement", "prepare test plan"], "locations": ["Not Specified"], "categories": ["Information Technology (IT)", "Product Management / Business Analyst"], "post_time": "2022-01-16T14:32:30Z", "salary": {"currency": null, "max": null, "min": null, "period": "monthly", "term": null}, "salary_visible": false, "title_keywords": ["business analyst"], "responsibilities": ["data", "analysis", "systems", "quality", "design", "testing", "specifications", "plan", "system changes"], "requirements": {"degrees": ["bachelor degree holder"], "majors": ["information technology"], "languages": ["english"], "language_level": [], "hard_skills": ["agile", "sql", "project management", "sdlc", "problem solving", "pmp"], "soft_skills": ["organizational skills", "good team player", "communication skills", "agile", "willing to learn", "problem solving", "project management", "interpersonal"], "languages_combined": [{"language": "english", "language_level": []}]}, "experience_required": {"duration": ["at least 2 years"], "field": ["sql", "business"]}}, {"job_id": "100003009055589", "location_code": "hk", "company": "Randstad Hong Kong Limited", "job_title": "Product Manager - Digital Transformation (60K - 70K + Bonus)", "description": "about the company.\n\nRandstad are currently working with a well established MNC who are currently looking for a Product Manager for their digital transformation projects based around their in-house platform. The right candidate will be responsible for heading up the product side and managing relationships with stakeholders/end-users in terms of what needs to be built and helping to land these into the organisation.\n\n\nabout the job.\n\nWork closely with IT development team and other business stakeholders to define and advocate product strategy, roadmap and user stories for the digital transformation projects\nOwn and drive the product backlogs and prioritise using appropriate techniques\nDefine the business value for each feature adds to the product by ROI analysis, and prepare acceptance criteria in conjunction with other teams and support delivery of these features\nGather requirements from senior stakeholders to determine the underlying business process required to support the user stories defined and the development of business cases to ensure that there is clarity on the benefits expected and these can be measured clearly\nBe obsessed with constant improvement, scalability, reusability, and operational excellence based on the feedbacks from end-users\nLead and coach the junior teammates in the team for the industry best practices\n\nskills & experiences required.\n\nBachelor Degree or above in Computer Science/Business Administration or relevant discipline\nMinimum 6+ years of experience as a senior level Business Analyst or Product Owner ideally with software development/digital transformation project experience\nProven experience in managing requirements, stakeholders, while developing and maintaining an impactful product roadmap and backlogs to support its delivery\nAbility for communicating clearly, concisely and confidently across all levels in the business especially influencing business stakeholders especially Director/C-level is a must\nSolid experience in using customer centric approaches to define user stories, acceptance criteria and delivery of these with both internal IT development team and 3rd party vendors\nPrevious experience in Agile methodology / Scrum environment\nProficient in spoken and written English\nPMP/CSM/Lean Six Sigma certification is a plus\n\nabout the benefits.\n\nPerformance Bonus (Average 1.5 - 2 Months Salary)\n18 Days Annual Leave\nMedical, Dental and Life Insurance\nPermanent Headcount\n5 Days Work\n\nIf you're interested in this exciting opportunity please don't delay and click APPLY NOW or for more information, you can reach out to Kelvin Chu at kelvin.chu@randstad.com.hk", "employment_types": ["Full Time", "Permanent"], "selling_points": ["Permanent Headcount", "Multinational Environment", "In-house Platform Digital Transformation"], "locations": ["Not Specified"], "categories": ["Information Technology (IT)", "IT Project Management / Team Lead", "Product Management / Business Analyst", "Software Development"], "post_time": "2022-01-18T02:46:11Z", "salary": {"currency": "HKD", "max": 69999, "min": 55000, "period": "monthly", "term": null}, "salary_visible": true, "title_keywords": ["product manager"], "responsibilities": ["3rd party vendors", "software", "maintaining", "analysis", "teams", "developing", "business process", "administration"], "requirements": {"degrees": ["degree or above", "bachelor"], "majors": ["business administration", "computer science"], "languages": ["english"], "language_level": ["proficient"], "hard_skills": ["lean", "plus", "agile", "analysis", "six sigma", "c", "pmp"], "soft_skills": ["prioritise", "agile", "organisation", "responsible"], "languages_combined": [{"language": "english", "language_level": ["proficient"]}]}, "experience_required": {"duration": ["minimum 6+ years"], "field": ["it development", "developing", "business", "software development", "digital", "team"]}}, {"job_id": "100003009048821", "location_code": "hk", "company": "Hong Kong Air Cargo Terminals Ltd", "job_title": "Junior Business Analyst (Information Services)", "description": "Duties\n\nParticipate in business / technical requirements gathering meetings to produce business process, functional requirements and related documentation\nCommunicate effectively with internal teams and external parties to ensure product/system delivery\nStudy and analyze business and system information to facilitate system improvement planning and design\nDesign solutions to meet user requirements either end-to-end from analysis, design, implementation and quality assurance\nAnalyze requirements to produce documentation related to product and technology design\nAssist product/system rollouts\n\nQualifications\n\nFresh graduate of High Diploma / Bachelor degree in Information Technology, Computer Engineering, Computer Science or related disciplines\nAbility to work independently and proactively in a flexible and dynamic environment\nGood analytical, problem solving, communication and presentation skills\nGood team player, strong self-initiative, and commitment to achieve high quality results\nGood communication and interpersonal skills\n\n\nWe offer 5-Day work week with a competitive and comprehensive remuneration package including Chinese New Year bonus, discretionary bonus, transport subsidy, employer topped-up MPF contributions, medical benefits (including family members), voluntary dental coverage (including family members), life insurance, birthday leave, extra annual leave, marriage leave, maternity leave, paternity leave, newborn baby gift, sports centre and free shuttle bus.\nWritten applications with full resume detailing experience, qualifications and expected salary should be sent either by post or click \u2018Apply Now\u2019.\nBy post: Human Resources, 6/F, North Office Block, SuperTerminal 1, Hong Kong International Airport, HK\nPlease quote the above reference in your application. To know more about our company, please visit our website\u00a0http://career.hactl.com.\nApplicants not invited for interview within four weeks should consider their applications unsuccessful. Applicants\u2019 personal data collected will only be used for the sole purpose of recruitment. The data of unsuccessful applicants will be destroyed within six months.", "employment_types": ["Full Time", "Permanent"], "selling_points": ["HD or Degree in IT or related disciplines", "Recent graduate will be considered", "5-Day work week"], "locations": ["Airport Area"], "categories": ["Information Technology (IT)", "Support", "Product Management / Business Analyst", "Others"], "post_time": "2022-01-14T07:21:53Z", "salary": {"currency": null, "max": null, "min": null, "period": null, "term": null}, "salary_visible": false, "title_keywords": ["business analyst", "junior"], "responsibilities": ["related documentation", "design solutions", "data", "external parties", "system delivery", "quality", "design", "website", "communication", "business process", "personal data", "teams", "implementation", "mpf", "documentation", "analysis", "recruitment", "insurance", "planning"], "requirements": {"degrees": ["high diploma", "degree", "bachelor", "fresh graduate"], "majors": ["related disciplines", "computer engineering", "computer science", "information technology"], "languages": ["chinese"], "language_level": [], "hard_skills": ["documentation", "analysis", "dynamic", "problem solving"], "soft_skills": ["flexible", "work independently", "dynamic environment", "good team player", "communication", "problem solving", "presentation skills", "communication and interpersonal skills", "self-initiative", "comprehensive"], "languages_combined": [{"language": "chinese", "language_level": []}]}, "experience_required": {"duration": [], "field": []}}, {"job_id": "100003009052942", "location_code": "hk", "company": "Haven of Hope Christian Service", "job_title": "Assistant Business Analyst (Ref: SSO/IT/ABA/JDB)", "description": "Responsibilities:\nCollect business requirement, analyze, formulate and document business flows and process\nConduct business and in-house user requirement analysis\nPerform feasibility study, solution design, system support and develop user manual\nCreate functional specifications for enhancement and new development\nDevelop test plan and conduct system UAT\nData analysis\nRequirements:\nDiploma or above in Computer Science, Information Systems, Statistics or related discipline\nFresh graduates are welcome\nExperience in project management, project lifecycle and direct interaction with end user\nProficiency in SQL, Power BI, SharePoint, Excel and Google Analytics\nKnowledge of data analysis\nCustomer-oriented, good analytical, presentation, communication, problem solving and project management skills\nProficiency in both written and spoken English and Chinese\nPlease send full resume with expected salary and reference no. quoted to Haven of Hope Christian Service, Staff Engagement Department, 7 Haven of Hope Road, Tseung Kwan O, New Territories or via email by clicking \"Apply Now\", or via Whatsapp no. 6507 8148 (with reference no. quoted at the caption) on or before 5 February 2022. Only short-listed candidates will be notified.\nEnquiry: 2703 3227 (Phone); 6507 8148 (Whatsapp).\nFor details about our organization, please visit www.hohcs.org.hk.\nProspective employees are requested to undergo/submit Sexual Conviction Record Check for work relating to children or mentally incapacitated persons before employment. Data collected will be used for recruitment purpose only.\nThis advertisement should not be reproduced, in whole or in part, to other recruitment websites without our prior written permission.", "employment_types": ["Full Time", "Permanent"], "selling_points": [], "locations": ["Tseung Kwan O"], "categories": ["Professional Services", "Business Analysis / Data Analysis", "Information Technology (IT)", "IT Project Management / Team Lead", "Product Management / Business Analyst"], "post_time": "2022-01-17T04:38:35Z", "salary": {"currency": null, "max": null, "min": null, "period": "monthly", "term": null}, "salary_visible": false, "title_keywords": ["business analyst", "assistant"], "responsibilities": ["user requirement", "uat", "analysis", "design", "develop", "data analysis", "specifications", "plan"], "requirements": {"degrees": ["diploma or above"], "majors": ["statistics", "computer science"], "languages": ["english", "chinese"], "language_level": ["proficiency"], "hard_skills": ["hope", "google analytics", "excel", "bi", "no", "analysis", "sql", "project management", "problem solving", "whatsapp"], "soft_skills": ["project management skills", "communication", "project management", "customer-oriented", "problem solving", "presentation"], "languages_combined": [{"language": "english", "language_level": ["proficiency"]}, {"language": "chinese", "language_level": ["proficiency"]}]}, "experience_required": {"duration": [], "field": ["project management"]}}, {"job_id": "100003009053020", "location_code": "hk", "company": "Darmax Limited", "job_title": "Product Manager", "description": "Our client is a global consumer electronics leader specializing in IoT Baby Monitors & Products. They are currently seeking for an experienced Product Manager to join their dynamic international team focused on innovative design technology.\n\nCore responsibilities:\n\nDevelop and manage the whole product life cycle, including product planning, benchmarking and feasibility studies, product definition, product development, project management, suppliers\u2019 management, and cost management.\nResponsible for defining system and mobile application features\nCollaborate with internal & external stakeholders to clarify user stories, research in user scenarios, and produce organized and succinct Product Requirements Documents (PRD)\nBe the interface between our product design, technical engineering, and software development teams\nProactively identify potential risks and issues throughout the development process\nDevelop innovative solution to remove any roadblocks that prevent or slow down product growth\n\n\u00a0Essential Skills & Experience:\n\n+5 years\u2019 solid experience in product management in consumer electronics products\nExperience in Baby Monitor products is highly advantageous\nDegree in Electronics Engineering or Mechanical Engineering\nTechnical Product Manager with good software knowledge to converse with Developers, Engineers, IT vendors \u2013 ability to communicate at that level & speak their tech language\nStrong communication skills in English and Chinese\nAutonomous, self-driven, innovative, open-minded", "employment_types": ["Full Time", "Permanent"], "selling_points": ["Product management in consumer electronics product", "Degree in Electronics/ Mechanical Engineering", "Strong communication skills in English and Chinese"], "locations": ["Kwun Tong Area"], "categories": ["Information Technology (IT)", "Product Management / Business Analyst", "Software Development", "Mobile / Wireless Communications"], "post_time": "2022-01-17T05:09:06Z", "salary": {"currency": null, "max": null, "min": null, "period": "monthly", "term": null}, "salary_visible": false, "title_keywords": ["product manager"], "responsibilities": ["collaborate with", "management", "cost", "software", "teams", "monitor", "design", "develop", "identify potential risks", "project management", "communication", "product design", "planning"], "requirements": {"degrees": ["degree"], "majors": ["engineering", "mechanical engineering"], "languages": ["english", "chinese"], "language_level": [], "hard_skills": ["project management", "dynamic", "mobile"], "soft_skills": ["organized", "communication skills", "responsible", "focused", "open-minded", "project management", "autonomous", "dynamic", "innovative", "driven"], "languages_combined": [{"language": "english", "language_level": []}, {"language": "chinese", "language_level": []}]}, "experience_required": {"duration": [], "field": ["product management"]}}, {"job_id": "100003009048572", "location_code": "hk", "company": "S.F. Express (Hong Kong) Limited", "job_title": "Senior Business Analyst (IT)", "description": "Responsibilities:\n\nUnderstand the business needs, balance the requirements amongst business stakeholders and recommend solutions\nAnalyze users \u2018 requirements and translate users\u2019 ideas and cases into functional specification\nWork closely with onshore/offshore development team and external vendors to ensure the system can be completed timely\nManage the project schedule from the high-level system design and analysis, system implementation/enhancement, UAT to system deployment\nPrepare and maintain function specification and training documentation\n\nRequirement:\n\nDegree holder of Computer Science, Business Analytics, Information Technology, Logistics or other related disciplines\n3 - 5 year plus working experience in software development, system solution consultancy, or developing programmable documents, preferably in Logistics/Courier Industries or consultant companies\nPractical experience in understanding, analyzing, and verifying user requirements versus business processes to develop programmable documents\nGood command of written and spoken English and Chinese (including Putonghua)\nSelf-motivated, positive, able to work under pressure with emphasis on deliverables\n\nWe offer attractive remuneration package and fringe benefits to suitable candidates. Interested parties, please submit your application to us. If you do not want to apply as JobsDB member, you may send your full resume with your availability, current and expected salaries to recruit01 at sf-express.com.\n\nYou are welcome to visit our website at\u00a0https://htm.sf-express.com/hk/tc/\u00a0for more information about us.\n\nCandidates who are not invited for an interview within 1-month may consider their applications unsuccessful.\n\nAll personal data provided by job applicants will be used only for recruitment purposes and will be treated strictly confidential. Unsuccessful applications will be retained for a maximum period of 24-month.", "employment_types": ["Full Time"], "selling_points": ["Free shuttle bus coverage", "2 months or above performance bonus", "Attractive basic salary"], "locations": ["Tsing Yi"], "categories": ["Information Technology (IT)", "IT Management", "Product Management / Business Analyst", "Data Scientist"], "post_time": "2022-01-14T06:49:42Z", "salary": {"currency": null, "max": null, "min": null, "period": "monthly", "term": null}, "salary_visible": false, "title_keywords": ["senior business analyst"], "responsibilities": ["ideas", "uat", "analysis", "implementation", "system design", "maintain", "schedule", "documentation"], "requirements": {"degrees": ["degree holder"], "majors": ["related disciplines", "business analytics", "computer science", "information technology"], "languages": ["putonghua", "english", "chinese"], "language_level": ["good command"], "hard_skills": ["plus"], "soft_skills": ["self-motivated", "positive", "work under pressure"], "languages_combined": [{"language": "putonghua", "language_level": ["good command"]}, {"language": "english", "language_level": ["good command"]}, {"language": "chinese", "language_level": ["good command"]}]}, "experience_required": {"duration": ["3 - 5 year"], "field": ["business", "logistics", "developing", "software development"]}}, {"job_id": "100003009053634", "location_code": "hk", "company": "China CITIC Bank International Limited", "job_title": "Project Analyst - UAT (Contract)", "description": "Responsibilities:\nParticipate in project discussion and work with various stakeholders to collect user requirements and formulate test plans\nParticipate in UAT planning, preparation and execution.\nSupport new initiatives and participate in product development and system / process enhancement projects\nSupport team operations and enquiries; and prepare relevant MIS reporting.\nRequirement:\n\nMinimum 2 years of experience in banking operations/implementation in retail banking is preferred.\u00a0\u00a0\nExperience in UAT execution\nExperience in preparing Test Case/ Scenario, Test Plan\nPrior experience in project management in retail banking products will be an advantage", "employment_types": ["Contract"], "selling_points": ["UAT planning and executive", "Retail banking experience", "System and process enhancement"], "locations": ["Quarry Bay"], "categories": ["Information Technology (IT)", "Product Management / Business Analyst", "Testing / QA", "Others"], "post_time": "2022-01-17T07:16:09Z", "salary": {"currency": null, "max": null, "min": null, "period": "monthly", "term": null}, "salary_visible": false, "title_keywords": ["analyst"], "responsibilities": ["reporting", "uat", "operations", "plans", "enhancement projects", "planning"], "requirements": {"degrees": [], "majors": [], "languages": [], "language_level": [], "hard_skills": ["project management"], "soft_skills": ["project management"], "languages_combined": []}, "experience_required": {"duration": ["minimum 2 years"], "field": ["project management", "retail banking", "banking"]}}, {"job_id": "100003009052970", "location_code": "hk", "company": "Air Logistics Limited", "job_title": "Data Analyst", "description": "Job description:\n\nAs part of the Global Business Intelligence team you will be responsible for management of our Microsoft Analysis Services (Microsoft Tabular Model) and related processes in the Microsoft Azure Datalake. Using your skillset to realize analyse and integrate the dataflows according to the end user requirements, assemble data from various sources and produce outputs in Power BI.\n\n\nKey Responsibilities:\n\n\nManaging the developments in the Microsoft Analysis Services (Tabular model)\nCommunicating with technical and operational teams to ensure data integrity, security and optimized performance at the report and database level\nIdentifying and resolving data quality issues, validating datasets to ensure data integrity\nDetermining business requirements for reports and business intelligence solutions\nAnalyse the different Data sources and give new insights to the Business Stakeholders\nBuilding and updating dynamic Power Bi reports and dashboards, performing data quality checks\nAssisting with other data related duties\n\n\u00a0Required Experience/Education:\n\nBachelor\u2019s Degree in Analytics, Information Technology, Computer Science, Statistics, Engineering, Logistics, Supply Chain or another analytical discipline from an accredited college or university or equivalent experience\n3+ years of Data Analysis experience would be preferred\n\nRequired Skill:\n\n\nMicrosoft Analysis Services (Tabular model) experience has the preference\nExperience in Power BI or Tableau is preferred\nExperience in Python, SQL or Databricks is an advantage\nGood knowledge of DAX language is an advantage\nGood understanding to analyse & visualize data\nStrong speaking and writing English skills\n\nWe offer 5 days work with medical plan. Interested parties please send resume with current & salary expected\u00a0 and available date.\u00a0 All information provided will be treated in strict confidential and used solely for recruitment purposes.", "employment_types": ["Full Time", "Permanent"], "selling_points": ["5-day work", "Mulit-national environment", "Ensure the accuracy and integrity of data"], "locations": ["Lai Chi Kok"], "categories": ["Information Technology (IT)", "Product Management / Business Analyst", "Data Scientist"], "post_time": "2022-01-17T04:45:15Z", "salary": {"currency": null, "max": null, "min": null, "period": "monthly", "term": null}, "salary_visible": false, "title_keywords": ["data analyst"], "responsibilities": ["management", "power bi", "data", "analysis", "teams", "quality", "data analysis", "communicating with", "reports", "logistics", "database", "report", "analyse"], "requirements": {"degrees": [], "majors": [], "languages": ["english"], "language_level": [], "hard_skills": ["bi", "analysis", "tableau", "sql", "python"], "soft_skills": [], "languages_combined": [{"language": "english", "language_level": []}]}, "experience_required": {"duration": [], "field": ["sql"]}}, {"job_id": "100003009048559", "location_code": "hk", "company": "S.F. Express (Hong Kong) Limited", "job_title": "Business Analyst (IT)", "description": "Responsibilities:\n\nUnderstand the business needs, balance the requirements amongst business stakeholders and recommend solutions\nAnalyze users \u2018 requirements and translate users\u2019 ideas and cases into functional specification\nWork closely with onshore/offshore development team and external vendors to ensure the system can be completed timely\nManage the project schedule from the high-level system design and analysis, system implementation/enhancement, UAT to system deployment\nPrepare and maintain function specification and training documentation\n\nRequirement:\n\nHigher Diploma or above in Computer Science, Business Analytics, Information Technology, Logistics or other related disciplines\n1 year plus the working experience in software development, system solution consultancy, or developing programmable documents, preferably in Logistics/Courier Industries or consultant companies\nPractical experience in understanding, analyzing, and verifying user requirements versus business processes to develop programmable documents\nGood command of written and spoken English and Chinese (including Putonghua)\nSelf-motivated, positive, able to work under pressure with emphasis on deliverables\n\nWe offer attractive remuneration package and fringe benefits to suitable candidates. Interested parties, please submit your application to us. If you do not want to apply as JobsDB member, you may send your full resume with your availability, current and expected salaries to recruit01 at sf-express.com.\n\nYou are welcome to visit our website at\u00a0https://htm.sf-express.com/hk/tc/\u00a0for more information about us.\n\nCandidates who are not invited for an interview within 1-month may consider their applications unsuccessful.\n\nAll personal data provided by job applicants will be used only for recruitment purposes and will be treated strictly confidential. Unsuccessful applications will be retained for a maximum period of 24-month.", "employment_types": ["Full Time", "Permanent"], "selling_points": ["Free shuttle bus coverage", "2 months or above performance bonus", "Attractive basic salary"], "locations": ["Tsing Yi"], "categories": ["Information Technology (IT)", "IT Management", "Product Management / Business Analyst", "Data Scientist"], "post_time": "2022-01-14T06:47:44Z", "salary": {"currency": null, "max": null, "min": null, "period": "monthly", "term": null}, "salary_visible": false, "title_keywords": ["business analyst"], "responsibilities": ["ideas", "uat", "analysis", "implementation", "system design", "maintain", "schedule", "documentation"], "requirements": {"degrees": ["higher diploma or above"], "majors": ["related disciplines", "business analytics", "computer science", "information technology"], "languages": ["putonghua", "english", "chinese"], "language_level": ["good command"], "hard_skills": ["plus"], "soft_skills": ["self-motivated", "positive", "work under pressure"], "languages_combined": [{"language": "putonghua", "language_level": ["good command"]}, {"language": "english", "language_level": ["good command"]}, {"language": "chinese", "language_level": ["good command"]}]}, "experience_required": {"duration": ["1 year"], "field": ["business", "logistics", "developing", "software development"]}}, {"job_id": "100003009053869", "location_code": "hk", "company": "iAsia Online Systems Limited", "job_title": "Project Officer (Project Management Office Team)", "description": "Responsibilities\n\nProvide administrative support to the Senior Project Manager\nMonitor deadline of multi-projects\nReview and manage all phases of the project including requirements gathering, development, User Acceptance Test (UAT) and deployment\nCoordinate with external vendors and in-house development team to ensure smooth and timely execution of projects\nAssist with provision of support and QA review process for all projects / enhancements\nCoordinate and perform UAT\nPrepare user manual, support call knowledge-base documents, and related documents\nDraft meeting minutes, progress reports and UAT status reports\nSupport to day-to-day activities\nArrange and coordinate project meetings\nPerform business data analytics through SQL and BI tools\nRegularly update IT team leader and management on project status\nPerform other ad-hoc projects and tasks as assigned\n\nRequirements\n\nHigher Diploma or above in Computer Science, Information Technology or related disciplines\nFresh graduate will also be considered\n1\u20132 year(s) experience in Project Coordination or Project Management of IT industry is preferable\nExperience in banking & financial sector is preferable\nFamiliar with project management\nGood command of spoken & written English\u00a0and\u00a0Chinese.\u00a0Mandarin\u00a0is an advantage\nSound knowledge in Java, .NET, MSSQL, MySQL is an advantage\nA good team player with analytical & problem-solving skills, self-motivation and good interpersonal skills\nAble to work under pressure and meet tight deadlines\nImmediately available is preferred\n\nWe Offer\n\nCareer advancement opportunities\nAttractive remuneration package\n5-day work week and bank holiday\nCompany medical insurance, life insurance and dental insurance\nYear End Discretionary Bonus\nOn job training and training allowance\nFriendly working environment\nStaff Activities & Events e.g. Happy Friday Gathering, Annual Dinner, Festival Gift, Christmas Party, etc\n\nInterested parties please apply by clicking \"Apply Now\" to send full resume with current & expected salary.\n\nFor more information of our company, please visit our website address: http://www.iasia.com.hk\n\n(Data collected would be used for recruitment purpose only)", "employment_types": ["Full Time", "Permanent"], "selling_points": ["Experience in Project Mgt or Project Coordination", "Fresh graduate will also be considered", "Immediately available is preferred"], "locations": ["Yau Tsim Mong Area"], "categories": ["Information Technology (IT)", "Support", "Product Management / Business Analyst", "Testing / QA"], "post_time": "2022-01-17T07:39:30Z", "salary": {"currency": null, "max": null, "min": null, "period": "monthly", "term": null}, "salary_visible": false, "title_keywords": ["project officer"], "responsibilities": ["management", "uat", "progress reports", "related documents", "data", "review", "monitor", "coordinate with", "coordinate", "reports", "provide administrative support", "ad-hoc projects"], "requirements": {"degrees": ["higher diploma or above", "fresh graduate"], "majors": ["related disciplines", "computer science", "information technology"], "languages": ["english", "chinese", "mandarin"], "language_level": ["advantage", "good command"], "hard_skills": ["mssql", "project management", "java", "problem-solving skills"], "soft_skills": ["good team player", "meet tight deadlines", "project management", "self-motivation", "interpersonal skills", "coordination", "problem-solving skills", "work under pressure"], "languages_combined": [{"language": "english", "language_level": ["good command"]}, {"language": "chinese", "language_level": ["good command"]}, {"language": "mandarin", "language_level": ["advantage"]}]}, "experience_required": {"duration": [], "field": ["project management", "it", "financial", "banking"]}}, {"job_id": "100003009053593", "location_code": "hk", "company": "Principal Trust Company (Asia) Limited", "job_title": "Senior Analyst, Pension Operations", "description": "As the Senior Analyst, Pension Operations, you will be acted as a user business analyst, to enable organization to effectively automates tasks, streamline workflow processes, increase employee productivity, and ultimately deliver satisfying customer experiences.\n\nYou will also analyze business processes, identify automation opportunities, reengineer workflow process for efficiency and to improve automation potential and recommend approach/strategy; and develop Business Requirement Document (BRD) and Solution Design Document (SDD).\n\nOther responsibilities include:\n\nWork closely with scrum and production teams in the identification of business requirements, process design, UAT, training, write up use cases, test plan, defining support procedures for PISYS / AWD / RPA\nWork with project managers, IT and vendors on assigned projects.\nBuild and enhance automated process with AWD / Workflow system and RPA platform(s)\nProvide daily production support on AWD / Workflow system, PISYS and RPA\nWork with IT to discuss and resolve issues as reported\nProvide UAT on other areas as assigned\n\nEssential Skills, Experience and Competencies\n\nTo succeed in this role, strong communication and interpersonal skills, and a driving entrepreneurial spirit will be essential to collaborate with business and technical stakeholders in uncovering pain points and opportunities to deliver new business value through automation.\n\nOther key skills required for the role:\n\nBachelor\u2019s Degree in Computer Science or related disciplines\n4+ years of experience as business analyst, experience in agile/scrum team is preferred\nExperience in using workflow system or RPA, has worked in both QA and application development roles\nExperience in coding, translating user requirements to technical teams\nExperience in using Uipath will be an advantage\nExperience in financial service, pension/MPF will be an advantage\nFluent in spoken and written English and Chinese (both Cantonese and Mandarin)\nBe curious to understand the fundamentals of retirement business and financial services in support our service and product offerings\nSelf-starter, team player and attentive to details\nAdaptable, able to cope with a rapidly changing environment \u00a0\nBe passionate in new technologies, test automation with quality mindset\nFamiliar with Macros, SQL\nFamiliar in using JIRA, Dev Ops\n\nWhat We Offer\n\nPrincipal offers employees a competitive package and a comprehensive range of benefits to help meeting your needs now and in the future, including:\n\n5-Day Work Week\nYear-end Payment\nDiscretionary Bonus\nBirthday Leave\nMedical Plan\nLife Insurance\nPension Scheme\nEmployee Stock Purchase Plan\nAnd Growth Opportunities!", "employment_types": ["Full Time", "Permanent"], "selling_points": ["User business analyst", "Process improvements and automation", "Competitive offer package and attractive benefits"], "locations": ["Kwun Tong"], "categories": ["Information Technology (IT)", "Product Management / Business Analyst"], "post_time": "2022-01-17T07:12:35Z", "salary": {"currency": null, "max": null, "min": null, "period": null, "term": null}, "salary_visible": false, "title_keywords": ["operations", "senior analyst"], "responsibilities": ["collaborate with", "uat", "procedures", "teams", "design", "communication", "plan"], "requirements": {"degrees": ["degree", "bachelor"], "majors": ["related disciplines", "computer science"], "languages": ["cantonese", "english", "chinese", "mandarin"], "language_level": ["fluent"], "hard_skills": ["rpa", "sql", "agile"], "soft_skills": ["passionate", "agile", "attentive to details", "adaptable", "team player"], "languages_combined": [{"language": "cantonese", "language_level": ["fluent"]}, {"language": "english", "language_level": ["fluent"]}, {"language": "chinese", "language_level": ["fluent"]}, {"language": "mandarin", "language_level": ["fluent"]}]}, "experience_required": {"duration": ["4+ years"], "field": ["mpf", "qa", "business", "team", "application development", "financial"]}}, {"job_id": "100003009055607", "location_code": "hk", "company": "AXA Hong Kong", "job_title": "Senior Manager, Core systems", "description": "Solution Delivery\n\n\nCoordinate with Release Management to plan systems deployment to production.\nManage a group of application specialists and consultants to perform application analysis, design, development (where applicable) and quality assurance activities of all IT projects assigned.\nManage and engage the vendors to build, integrate and deliver RLS.\nMonitor daily activities to ensure application solutions meet AXA's policies, standards and quality requirement.\n\nProject Management\n\n\nManage projects throughout the delivery life cycle aim at controlling the scope, schedule and cost for IT projects.\n\nPeople Management\n\n\nDevelop and manage the performance of the team to ensure knowledge retention for key platforms via proper resource planning and backup.\nDrive capability development of the team to build specialization in their responsible application domain area.\n\nVendor Management\n\n\nFacilitate discussions and help vendors understand business requirements and improve vendor performance.\nReview and approve deliverables to ensure quality assurance.\nOversee the delivery of trainings and knowledge transfer to the production support teams to ensure necessary knowledge is transferred.\nManage vendor resources to ensure a right mix of external vendors to support multiple IT projects running in parallel, achieve utilization goal and on/offshore work ratio target.\nDefine, monitor and track overall vendor and project performance against SLA and KPIs to ensure value achievement.\n\nPlanning and Budgeting\n\n\nWith strong business acumen, negotiate and liaise with business divisions to define project scope and planning during project initiation phases with clarity on business objectives and outcomes.\nDefine the project timeline for the implementation approaches.\nMonitor the project costs against the budget.\n\nBusiness Advisory\n\n\nHelp customers fully understand the value of the applications to the business. Provide inputs to business proposals to ensure technical contents are covered correctly.\n\nSolution Architecture\n\n\nReview, challenge and contribute to the Solution Architect's proposed solution architecture to ensure the architecture meets the demand of applications.\n\nExperience and qualifications:\n\n\nUniversity degree in Computer Science or related fields.\nMinimum 13 years' experience in IT solution delivery, with at least 5 years' experience in the insurance/financial services field.\n\nSkills\n\n\nExperience in managing teams of technical professionals to evaluate solution on technical suitability, especially implementation and future maintenance, according to business requirements.\nIn-depth understanding of Insurance solution delivery\nIn-depth formal system development experience, preferably in AS400 RPGILE system development, Individual Life products, operations, finance and actuarial functional knowledge.\nSolid experience in large scale project delivery involving multiple teams, applications from both AS400 and non-AS400 platforms, and transition of the application implementation and maintenance to Delivery Centre / Vendor.\nExcellent analytical and problem-solving skills.\nExcellent written and verbal English communication skills.\nWorking experience in Asia countries, with understandings of the country characteristics, cultures and work style, is an advantage", "employment_types": ["Full Time", "Permanent"], "selling_points": ["AS400", "Solution Delivery", "Project Management"], "locations": ["Not Specified"], "categories": ["Information Technology (IT)", "IT Project Management / Team Lead", "Product Management / Business Analyst", "Technical / Functional Consulting"], "post_time": "2022-01-18T02:47:16Z", "salary": {"currency": null, "max": null, "min": null, "period": "monthly", "term": null}, "salary_visible": false, "title_keywords": ["senior manager"], "responsibilities": ["budgeting", "operations", "budget", "quality", "design", "communication", "manage projects", "plan", "liaise with", "costs", "monitor", "teams", "implementation", "develop", "schedule", "kpis", "architecture", "management", "cost", "review", "coordinate with", "contents", "maintenance", "policies", "analysis", "systems", "evaluate", "project management", "insurance", "planning"], "requirements": {"degrees": ["university degree"], "majors": ["computer science"], "languages": ["english"], "language_level": ["excellent"], "hard_skills": ["maintenance", "analysis", "vendor", "project management", "goal", "sla", "deployment", "problem-solving skills", "acumen"], "soft_skills": ["communication skills", "responsible", "project management", "business acumen", "problem-solving skills"], "languages_combined": [{"language": "english", "language_level": ["excellent"]}]}, "experience_required": {"duration": ["minimum 13 years", "at least 5 years"], "field": ["maintenance", "finance", "system development", "business", "it", "financial services", "insurance"]}}, {"job_id": "100003009046684", "location_code": "hk", "company": "Cathay Pacific Airways Ltd", "job_title": "Business Analyst - 12 months contract", "description": "Reports to:\u00a0Operations Analytics Manager, Digital\nDepartment: Digital\n\nRole Introduction\n\n\nThis position will be responsible to:\n\nGenerate actionable insight to support the data driven culture in decision making processes\nProactively support business streams in applying and integrating the right set of metrics, analytics model and visualization into day-to-day processes\nEnhance analytics power with new data, derived insight, tools and training with proper testing and requirement sets\nEnsure quality & data governance policies and processes to uphold security, quality and value of the analytics assets\n\nKey Responsibilities\n\n\nProvide analytics support services to various business partners\nDesign with business streams to frame business questions, perform analysis, design visualization of results, and derive analytical models to meet business objectives\nDevelop integrated BI solutions including reports, scorecards and dashboards, leveraging data processing and visualisation tools\nProactive in bring in new data & insight, support data model design and data definitions to ensure proper integration of internal and external sources\nTrain and facilitate business streams to conduct analysis to facilitate day-to-day decision making\nManage data quality by implementing quality metrics & regular monitoring, working on incidents to maintain accessibility and consistency of data as well as readiness of related analytics capabilities\nEnforce data governance practices to uphold the value of the data access, within the company and external parties\n\nRequirements\n\n\nTertiary education in STEM subjects;\nMinimum 3 years of working experience relating to data & analytics with a good understanding of at least one of the following business areas: Cargo operations, Customer management, Service Delivery, Sales & Marketing or Finance management\nStrong analytical abilities, numerate and familiar with statistical algorithms\nExpert in using analytics & query tools e.g. Alteryx and data modelling techniques\nProficiency in data visualization tools, ideally QlikSense\nProficiency in scripting languages (Python / SQL)\nTeam player with strong communication & interpersonal skills, able to share effectively across different business streams\nCurious, meticulous, self-motivated and strong continuous improvement mindset\nWorking knowledge in project management / JIRA a plus\nApplication Deadline: 31 January 2022\n\nPersonal & Application Information\n\n\nCathay Pacific is an Equal Opportunities Employer. Personal data provided by job applicants will be used strictly in accordance with our personal data policy and for recruitment purposes only. Candidates not notified within eight weeks may consider their application unsuccessful. All related information will be kept in our file for up to 24 months. A copy of our Personal Information Collection Statement will be provided upon request by contacting our Data Protection Officer.\n\nPlease note that with effect from 1 December 2021, all employees must be vaccinated in order to access Cathay City and all other Cathay Group Company premises in Hong Kong. Consideration will be given to those who are unable to get vaccinated for valid medical reasons.", "employment_types": ["Full Time", "Contract"], "selling_points": ["Minimum 3 years of data & analytics experience", "Proactively support business streams", "5-days work, Travel Benefits, Medical Benefits"], "locations": ["Lantau Island"], "categories": ["Transportation & Logistics", "Aviation Services", "Information Technology (IT)", "Product Management / Business Analyst", "Others"], "post_time": "2022-01-13T18:54:19Z", "salary": {"currency": null, "max": null, "min": null, "period": "monthly", "term": null}, "salary_visible": false, "title_keywords": ["business analyst"], "responsibilities": ["visualization", "data", "analysis", "support services", "quality", "monitoring", "design", "develop", "data processing", "external parties", "maintain", "reports"], "requirements": {"degrees": [], "majors": [], "languages": [], "language_level": [], "hard_skills": ["plus", "alteryx", "sql", "project management", "data visualization", "python"], "soft_skills": ["meticulous", "self-motivated", "communication", "project management", "interpersonal skills", "team player"], "languages_combined": []}, "experience_required": {"duration": ["minimum 3 years"], "field": ["finance", "management", "business", "marketing"]}}, {"job_id": "100003009051911", "location_code": "hk", "company": "Neo Derm (HK) Ltd", "job_title": "Senior Project Executive / Project Executive, Digital Platform", "description": "About us:\nWith the trend towards\u00a0Industrial Revolution 4.0, our IT department, the strategic technology enabler with more than 70 staff,\u00a0has established a comprehensive personalized customer-centric platform (gratus) and operation management system, i.e. Customer Behavioral Tracking System, Recommendation Engine, Business Intelligence Dashboard and Campaign Monitoring System, to support the fast-changing business transformation needs across the Group.\n\nTo support the Group\u2019s continuous development, we are looking for high caliber talent who is enthusiastic in system development to join our strong & fast-growing IT team.\n\nResponsibilities:\nIdentify and close the gap between users and IT or vendor when evaluating the digital platform solutions and approach with system and business knowledge\nResponsible for day-to-day IT project management, including user requirements collection, user experience design, UAT, platform support\nCollaborate with UX team to create and review the UX/UI and GUI of the solutions\nConduct the UAT of the system\nProvide administrative support to the project manager, including task scheduling, presentation materials, documentation and projects\u2019 activities\nRequirements:\nBachelor\u2019s Degree in Business Administration, Management Information Systems, Computer Science or related disciplines\nA minimum of 3 years working experience\nSolid experience in IT & digital project management ( Website & Mobile APP Projects)\nGood analytical and problem solving skills, self-initiated, attentive to details and customer focused\nPossesses sense of ownership and responsibility\nEnjoy a dynamic and multi-tasking working environment\nDetail-oriented and organized person\nLess Experience will be considered as Project Executive\nBenefits:\n\nFive-day work week\nDiscretionary year-end bonus\nMedical insurance\nDental insurance\nStaff purchase discount\nFree shuttle bus\nExcellent career development\nWe offer competitive remuneration package and comprehensive fringe benefits including medical, dental and life insurance, staff discount, and different types of allowances to the right candidates. Interested parties, please submit your application by clicking Apply Now. For details, please visit our website: http://career.neoderm.com.hk/", "employment_types": ["Full Time", "Permanent"], "selling_points": ["3 yrs supporting e-commerce or digital projects", "fast-paced; Self-motivated & well-organized person", "Excellent communication & interpersonal skills"], "locations": ["Quarry Bay"], "categories": ["Information Technology (IT)", "IT Project Management / Team Lead", "Product Management / Business Analyst", "E-commerce", "Product Management / Business Analyst"], "post_time": "2022-01-17T01:30:11Z", "salary": {"currency": null, "max": null, "min": null, "period": "monthly", "term": null}, "salary_visible": false, "title_keywords": ["senior project executive", "project executive"], "responsibilities": ["collaborate with", "documentation", "uat", "review", "user experience", "digital platform", "design", "project management", "scheduling", "provide administrative support", "ui"], "requirements": {"degrees": ["degree", "bachelor"], "majors": ["related disciplines", "business administration", "computer science"], "languages": [], "language_level": [], "hard_skills": ["project management", "problem solving skills", "dynamic", "mobile"], "soft_skills": ["organized", "focused", "attentive to details", "detail-oriented", "project management", "analytical and problem solving skills", "dynamic", "multi-tasking"], "languages_combined": []}, "experience_required": {"duration": ["minimum of 3 years"], "field": ["digital", "project management", "it"]}}, {"job_id": "100003009052833", "location_code": "hk", "company": "Panasonic Hong Kong Co., Limited", "job_title": "Officer (Operation Planning)", "description": "Responsibilities:\n\nPrepare schedule and coordinate Electronic Data Interchange with users, business partners, IT Dept and monitor the overall performance\nPrepare monthly reports and ad-hoc management reports for management analysis purpose\nCoordinate Global Freight Cost and container space issue with GFC Team and Operation team\nSupport improvement projects in system, operation and logistics aspects\nSupport in-house system login management\nPerform in-house training within Division\nPerform other ad-hoc projects as assigned\n\nRequirements:\n\nBachelor Degree or above in Business, Supply Chain Management, Computer Science or related discipline\n3 years relevant experience in international trading\nProficient in MS Office (Word, Excel, PowerPoint)\nGood command of English and Mandarin. Japanese is preferable\nGood analytical skills on reporting\nGood communication skills, well organized\n\nRemuneration will be commensurate with qualification and experience. Interested parties, please send your application with detailed resume indicating both existing & expected salary and date of availability to us.\n\nWe are an equal opportunity employer. All information provided by applicants will be treated in strict confidence and used for recruitment purpose only.", "employment_types": ["Full Time", "Permanent"], "selling_points": ["Knowledge in System & Operation Planning", "3 yrs relevant exp. in international trading", "Stable MNC in-house environment"], "locations": ["Tsim Sha Tsui"], "categories": ["Information Technology (IT)", "Product Management / Business Analyst", "Transportation & Logistics", "Supply Chain", "Merchandising & Purchasing", "Procurement / Purchasing / Sourcing"], "post_time": "2022-01-17T04:13:26Z", "salary": {"currency": null, "max": null, "min": null, "period": "monthly", "term": null}, "salary_visible": false, "title_keywords": ["officer"], "responsibilities": ["ad-hoc", "management", "cost", "monthly reports", "data", "analysis", "monitor", "coordinate", "management reports", "logistics", "schedule", "ad-hoc projects"], "requirements": {"degrees": ["degree or above", "bachelor"], "majors": ["business", "computer science"], "languages": ["japanese", "english", "mandarin"], "language_level": ["good command"], "hard_skills": ["excel", "word", "powerpoint", "analytical skills", "ms office"], "soft_skills": ["communication skills", "well organized", "analytical skills"], "languages_combined": [{"language": "japanese", "language_level": []}, {"language": "english", "language_level": ["good command"]}, {"language": "mandarin", "language_level": ["good command"]}]}, "experience_required": {"duration": ["3 years"], "field": ["relevant experience", "trading"]}}, {"job_id": "100003009049856", "location_code": "hk", "company": "World Vision Hong Kong", "job_title": "Business Analyst (Project Based - 1 Year Contract)", "description": "Job Responsibilities:\u00a0\nResponsible for the overall planning, scoping, organizing, monitoring and leading the IT projects\nLiaise with stakeholders to develop business requirement & related proposals for process\nDefine the deliverables, resource requirements & work plan for projects\nManage project development and delivery\nConduct functional specification, prepare testing plan, coordinate UAT, conduct user training\nResponsible for vendor selection, perform business requirement analysis and system design with vendors\nResponsible for change management to facilitate acceptance by users of new systems\nEnsure quality documentation and work are delivered in accordance with the project scope and schedule\n\n\u00a0Job Requirements:\n\n\n\nDegree in Information Technology, Computer Science or related disciplines\nMinimum 3 years of IT experience in project management of IT development project\nSolid experience in project management and ability in project planning, budgetary control, effort estimation and scope & change management\nUnderstanding of the software development lifecycle is a must\nExperience related to market technology development is an advantage\nStrong communication skills, analytical & problem solving skills\nAbility to meet tight deadlines and work under pressure\n\nPlease apply online with your full resume, listing church affiliations (if any), current and expected salary.\n\nYou may also send your application to:\nHead of HR & Administration, World Vision Hong Kong, 2/F Mayfair Centre, 4 Anchor Street, Tai Kok Tsui, Kowloon\n\nTo find out more about our job opportunities, please visit our website\u00a0https://www.worldvision.org.hk/get-involved/vacancies\n\nWorld Vision Hong Kong is committed to safeguarding our children and adult beneficiaries from any risk of abuse, exploitation and harm. Candidates selected for interviews will be requested a self-declaration of previous records for any crimes against children or sexual offences, and may be requested to undergo Sexual Conviction Record Check by the HK Police.\n\nPersonal Data provided by job applicants will be used for recruitment purposes only and will be treated in accordance with the organization's personal data privacy policy. Applicants who are not invited for interviews within six weeks may consider their applications unsuccessful and the personal data collected will be destroyed within 12 months.", "employment_types": ["Full Time", "Temporary"], "selling_points": [], "locations": ["Mong Kok"], "categories": ["Information Technology (IT)", "IT Project Management / Team Lead", "Product Management / Business Analyst", "Network & System"], "post_time": "2022-01-14T09:19:27Z", "salary": {"currency": null, "max": null, "min": null, "period": "monthly", "term": null}, "salary_visible": false, "title_keywords": ["business analyst"], "responsibilities": ["documentation", "change management", "uat", "analysis", "monitoring", "systems", "quality", "develop", "testing", "coordinate", "system design", "schedule", "plan", "liaise with", "planning"], "requirements": {"degrees": ["degree"], "majors": ["related disciplines", "computer science", "information technology"], "languages": [], "language_level": [], "hard_skills": ["project management", "problem solving skills"], "soft_skills": ["communication skills", "meet tight deadlines", "project management", "committed", "problem solving skills", "work under pressure"], "languages_combined": []}, "experience_required": {"duration": ["minimum 3 years"], "field": ["management", "it development", "related", "development", "it experience", "project management", "planning"]}}, {"job_id": "100003009055253", "location_code": "hk", "company": "Accenture Company Limited", "job_title": "Strategy & Consulting - Insurance Consultant", "description": "Your Role:\nThere will never be a typical day at Accenture, but that\u2019s why people love it here. The opportunities to make a difference within exciting client initiatives are limitless in this ever-changing business landscape.\n\nKey Responsibilities:\n\nAnalyze opportunities and challenges our clients face in the areas of system, processes, operations, and enterprise performance management\nSupport the client in defining and modeling the key drivers of current and future enterprise value\nSupport clients\u2019 transformation in insurance products, process and core system\nDemonstrate strong analytical capabilities and apply knowledge of selected tools and techniques, drawing logical conclusions\nDevelop expertise in customer insight & growth experience practice areas to increase the breadth and depth of our knowledge base and capabilities\nDesign and deploy end-to-end insurance process and operating model\n\n\nExperience, Attributes and Qualifications:\n\nUniversity Degree from reputable university, MBA preferred.\nMinimum 3 years of working experience with insurance clients or insurance companies, experience in large-scale system integration/data migration project will be preferred\nKnowledge in Insurance Products/Process and Insurance Core System\nKnowledge in project management (Waterfall/Agile Scrum)\nExperience in end-to-end insurance or retirement process and operating model design\nStrong stakeholder management with business/IT stakeholders and subject matter experts, able to create and deliver high-impact communication to senior audiences (written and oral in English, Mandarin and Cantonese)", "employment_types": ["Full Time"], "selling_points": ["Management consulting", "Digital transformation", "Insurance core system"], "locations": ["Quarry Bay"], "categories": ["Professional Services", "Business Consultancy", "Information Technology (IT)", "Product Management / Business Analyst", "Insurance", "Others"], "post_time": "2022-01-18T01:55:31Z", "salary": {"currency": null, "max": null, "min": null, "period": "monthly", "term": null}, "salary_visible": false, "title_keywords": ["consultant"], "responsibilities": ["management", "data", "operations", "design", "develop", "communication", "migration", "project management", "support clients", "deploy", "insurance"], "requirements": {"degrees": ["university degree"], "majors": [], "languages": ["cantonese", "english", "mandarin"], "language_level": [], "hard_skills": ["integration", "make", "project management", "agile"], "soft_skills": ["communication", "project management", "oral", "agile"], "languages_combined": [{"language": "cantonese", "language_level": []}, {"language": "english", "language_level": []}, {"language": "mandarin", "language_level": []}]}, "experience_required": {"duration": ["minimum 3 years"], "field": ["insurance", "design"]}}, {"job_id": "100003009055822", "location_code": "hk", "company": "HKT Financial Services", "job_title": "Product Executive, HKT Financial Services", "description": "Responsibilities:\n\nCoordinate and formulate financial budget and KPI for the overall Personal Banking and corresponding business units, and optimizing the workflow\nReview financial and management reporting including financial performance analysis, peer comparison and financial forecast\nMonitor financial plan progress and budget performance and review corresponding reports and presentation materials\nFormulate/update the various business plan policies/implementation action plan/structure design and etc. in order to support business development\nCarry out ad-hoc tasks assigned by supervisors or management\n\nRequirement:\n\nDegree holder or above with major in Business Administration/Finance/ Economics/ Statistic/ Marketing or related disciplines\n7-10 years or above relevant experience in management reporting/financial planning and budgeting related experience in banking field preferred\nWith strong analytical skills and critical mindset, capable of examining and analyzing financial and management information with business acumen\nBe a good team player and self-motivated, energetic, and enthusiastic for new challenges under pressure\nExcellent communication and presentation skills with good command of spoken and written English and Chinese including Putonghua and Cantonese\nCompetent in MS office application (Word, Excel, PowerPoint and etc.) and Chinese & English input method\n\nWe offer competitive remuneration package and comprehensive fringe benefits including medical and life insurance, and different types of allowances to the right candidate. Interested parties, please submit your application online. For details, please visit our website\u00a0http://www.bochk.com\n\nData collected would be used for recruitment purposes only. It might also be disclosed to our subsidiaries or Associated Companies to process the information for appointment. Applicants who do not hear from us within 8 weeks may consider their application unsuccessful and their data will be destroyed within 12 months of receipt.\n\u00a0", "employment_types": ["Full Time"], "selling_points": [], "locations": ["Quarry Bay"], "categories": ["Information Technology (IT)", "IT Project Management / Team Lead", "Support", "Product Management / Business Analyst"], "post_time": "2022-01-18T02:59:07Z", "salary": {"currency": null, "max": null, "min": null, "period": "monthly", "term": null}, "salary_visible": false, "title_keywords": ["executive"], "responsibilities": ["management", "policies", "analysis", "review", "budget", "monitor", "implementation", "design", "coordinate", "ad-hoc tasks", "reports", "management reporting", "forecast", "banking", "plan", "business plan"], "requirements": {"degrees": ["degree holder"], "majors": ["business administration", "finance", "economics", "related disciplines", "marketing"], "languages": ["cantonese", "putonghua", "english", "chinese"], "language_level": ["excellent", "good command"], "hard_skills": ["excel", "word", "acumen", "analytical skills", "powerpoint", "ms office"], "soft_skills": ["good team player", "self-motivated", "under pressure", "capable", "competent", "analytical skills", "communication", "presentation skills", "comprehensive", "enthusiastic", "business acumen", "energetic"], "languages_combined": [{"language": "cantonese", "language_level": ["excellent", "good command"]}, {"language": "putonghua", "language_level": ["excellent", "good command"]}, {"language": "english", "language_level": ["excellent", "good command"]}, {"language": "chinese", "language_level": ["excellent", "good command"]}]}, "experience_required": {"duration": ["7-10 years"], "field": ["management", "financial", "related", "relevant experience", "banking", "planning"]}}, {"job_id": "100003009048923", "location_code": "hk", "company": "Heep Hong Society", "job_title": "Business Intelligence Data Analyst", "description": "Responsibilities:\nAssist and develop the bank\u2019s FX and general banking services (including Payment, Payroll & Safe Deposit Box etc.), and optimize the product structure in order to maximize the profitability\n\nImplement the measures for FX and general banking services, monitor business progress and complete business target.\n\nAnalysis on the needs and opportunities of different customers segment, cooperate with the latest market conditions to provide appropriate strategic advice to maximize the profitability\n\nMonitor and ensure the products are operated smoothly. Reflect to management as needed\n\nSupport in the formulation of product marketing plan and staff training etc. Cooperate with other relevant departments to carry out marketing activities\n\nFormulating and review the bank risk related policies, risk management policies and procedure in order to control the potential risks. Report to management timely and formulate measures to follow up.\n\nComplete personal performance management standard\n\nHandle ad hoc projects as assigned by management\n\nRequirements:\nDegree holder with major in Business Administration, Finance, Marketing, Statistics, Financial Management and Administration etc\n\nAt least 4 years\u2019 relevant experience (will be adjusted according to the level of application)\n\nCreative thinking, good project management ability and independent analytical mind\n\nExcellent communication and presentation skills\n\nGood command of spoken & written English and Chinese. Proficient in Word, Excel, PowerPoint and Access of MS office\n\nCandidate with more experience will be considered as Senior Manager\n\nWe offer competitive remuneration package and comprehensive fringe benefits including medical and life insurance, and different types of allowances to the right candidate. Interested parties, please submit your application online. For details, please visit our website http://www.bochk.com\n\n[via APPLY NOW]\u00a0\u00a0\n\nData collected would be used for recruitment purposes only. It might also be disclosed to our subsidiaries or Associated Companies to process the information for appointment. Applicants who do not hear from us within 8 weeks may consider their application unsuccessful and their data will be destroyed within 12 months of receipt.", "employment_types": ["Full Time"], "selling_points": ["Design, implement, deploy, problem diagnosis", "Data analytics, user req., solution design", "Comp. Sci, IT/Info System Degree; min. 3-5yrs' exp"], "locations": ["Ngau Tau Kok"], "categories": ["Information Technology (IT)", "DBA", "Product Management / Business Analyst", "Data Scientist"], "post_time": "2022-01-14T11:32:05Z", "salary": {"currency": null, "max": null, "min": null, "period": "monthly", "term": null}, "salary_visible": false, "title_keywords": ["data analyst"], "responsibilities": ["management", "control", "policies", "analysis", "review", "monitor", "develop", "marketing plan", "payment", "ad hoc projects", "banking", "payroll", "cooperate with", "report"], "requirements": {"degrees": ["degree holder"], "majors": ["finance", "statistics", "marketing", "business administration"], "languages": ["english", "chinese"], "language_level": ["good command"], "hard_skills": ["excel", "word", "powerpoint", "project management", "ms office"], "soft_skills": ["independent", "communication", "project management", "presentation skills", "analytical mind", "comprehensive", "creative"], "languages_combined": [{"language": "english", "language_level": ["good command"]}, {"language": "chinese", "language_level": ["good command"]}]}, "experience_required": {"duration": ["at least 4 years"], "field": ["relevant experience"]}}, {"job_id": "100003009047126", "location_code": "hk", "company": "ANGLO EAST GROUP LTD.", "job_title": "Programmer", "description": "Our client, a Public Listed Company, is looking for high-caliber person to fill the position.\n\nResponsibilities:-\n\nDevelop and maintain spatial data platforms\nDesign and analyze the development of large scale spatial data dissemination platform riding on cloud environment\nValidate data modeling, design data processing workflows, verify data conversion integrity and examine spatial data dissemination via API\nIdentify and rectify data issues during functional testing, system integration testing, and support useracceptance test\nReview, comment and revise technical project documents to enhance the quality of project deliverables\nPrepare documentation, project reports and specifications\n\nRequirements:-\n\nAt least 2 years' working experience in data modelling and management\nSolid knowledge and experience in data architecture design and modelling, implementing and development of data dissemination platform\nHands-on experience in working with spatial data modelling spatial data conversion is a plus\nExperience in Python, web programming or Java programming is an advantage\nPossess strong sense of analytical and problem solving skills\nGood command of both spoken and written Chinese and English", "employment_types": ["Full Time", "Permanent"], "selling_points": [], "locations": ["Hung Hom"], "categories": ["Information Technology (IT)", "IT Management", "Product Management / Business Analyst", "E-commerce", "Software Development"], "post_time": "2022-01-14T03:09:58Z", "salary": {"currency": null, "max": null, "min": null, "period": "monthly", "term": null}, "salary_visible": false, "title_keywords": ["programmer"], "responsibilities": ["data", "project deliverables", "review", "quality", "design", "data processing", "develop", "testing", "project documents", "maintain", "project reports", "specifications", "documentation"], "requirements": {"degrees": [], "majors": [], "languages": ["english", "chinese"], "language_level": ["good command"], "hard_skills": ["plus", "java", "web", "programming", "python", "problem solving skills"], "soft_skills": ["analytical and problem solving skills", "hands-on"], "languages_combined": [{"language": "english", "language_level": ["good command"]}, {"language": "chinese", "language_level": ["good command"]}]}, "experience_required": {"duration": ["at least 2 years"], "field": ["programming", "development", "management", "design"]}}, {"job_id": "100003009050192", "location_code": "hk", "company": "Meta Air Labs Limited", "job_title": "Senior Product Development Officer / Product Development Officer", "description": "Meta Air Labs Limited is an Enterprise-Grade Blockchain as a Solutions (BaaS) Service Provider based in Hong Kong. We are looking for talented candidates to join us . If you are passionate in blockchain technology and want a new fresh start for your career path, SEND US YOUR LATEST CV!\n\nYour role:\n\nResponsible for the e-wallet product, liaise with business users, vendor, and internal IT team to ensure smooth delivery of the project.\nGather\u00a0and\u00a0analyze user requirement into functional specifications\nExecute user acceptance testing including test planning, execution, and defect management\nConduct market research and analysis to identify business needs and opportunities\u00a0\n\nWe look for:\n\nDegree holder in Business Management, IT or related disciplines\n2 years or above in business analysis and/or system analysis experiences\nPrevious working in Fintech industry is preferred\nStrong business analysis skills on requirement gathering and documentation\nSolid experience in software testing including planning, execution, and result document\nStrong analytical and problem-solving skills with the ability to work under dynamic environment and multi-tasking\nProficiency in spoken and written English, Cantonese, and Mandarin\nImmediately available is highly preferred\n\u00a0#\u00a0Candidates with more experience will be considered as\u00a0Senior\u00a0Product Development Officer\n\n\nWe offer:\n\nAttractive remuneration package with performance bonus\nPrivilege insurance plan for group medical (covers clinical, hospitalization with supplementary major medical) & dental\n5-day work week, flexible working hours\nConvenient office location in Tsimshatsui\nWork with the young and energetic team\nOpportunities to participate in blockchain projects\nFree snacks, coffee, and tea\nFestival red packets and gifts\nEmployee referral bonus\nRegular staff activities\n\nIf you are interested in this position and want to get a new exposure in Fintech industry, please don\u2019t hesitate to apply with your full resume, present/expected salary and availability by click on the 'Apply Now' button.\u00a0\n\nAll personal data collected will be\u00a0treated in strict confidence\u00a0and used for recruitment purposes only.", "employment_types": ["Full Time", "Permanent"], "selling_points": ["E-wallet Product Development, project monitoring", "Requirement analytics, function verification", "Working independent, strong interpersonal skill"], "locations": ["Tsim Sha Tsui"], "categories": ["Information Technology (IT)", "IT Project Management / Team Lead", "Product Management / Business Analyst", "Testing / QA"], "post_time": "2022-01-14T09:58:41Z", "salary": {"currency": null, "max": null, "min": null, "period": "monthly", "term": null}, "salary_visible": false, "title_keywords": ["officer", "product development"], "responsibilities": ["user requirement", "management", "documentation", "business analysis", "software", "conduct market research", "analysis", "testing", "specifications", "liaise with", "planning"], "requirements": {"degrees": ["degree holder"], "majors": ["related disciplines", "business", "it"], "languages": ["cantonese", "english", "mandarin"], "language_level": ["proficiency"], "hard_skills": ["blockchain", "business management", "analysis", "vendor", "dynamic", "documentation", "problem-solving skills"], "soft_skills": ["passionate", "dynamic environment", "responsible", "multi-tasking", "smooth", "problem-solving skills"], "languages_combined": [{"language": "cantonese", "language_level": ["proficiency"]}, {"language": "english", "language_level": ["proficiency"]}, {"language": "mandarin", "language_level": ["proficiency"]}]}, "experience_required": {"duration": ["2 years"], "field": ["business analysis", "product development", "planning", "testing"]}}, {"job_id": "100003009046554", "location_code": "hk", "company": "Sun Hung Kai Properties Ltd", "job_title": "ASSISTANT MANAGER \u2013 DATA ANALYTICS", "description": "Requirements:\n\n\nBachelor\u2019s degree in Computer Science, Statistics or Information Management or related discipline\nMinimum 7 years\u2019 experience in data analytics, managing data warehouse, business intelligence of mobile app loyalty program, preferably with retail market exposure\nHands-on experience in ETL process, database management, data analysis with data visualization tools and Google Analytics\nProficiency in SQL programming (e.g. MySQL, MSSQL, etc) and Tableau is a must\nStrong business acumen, analytical skills and numerical sense, able to work independently\nWell-organized, self-motivated and a good team player\nEffective communication skills, both in oral presentation and report writing\nProven English proficiency\n\nResponsibilities:\n\n\nManage data warehouse, consolidate and integrate data from diversified data source including MySQL Database, Google Analytics, etc\nAnalyze consumer data of customer loyalty programs and identify insights for management on business development opportunities\nDevelop and built segmentation platform for performing the evaluation of segmentation used in different channels\nOrganize and prepare regular business analysis reports\nCommunicate and coordinate with internal and external parties to refine data management and analytics procedures, workflows and other best practices\nDevelop Business Intelligence tools / Dashboards to facilitate efficient cross-platform data analysis\nMaintain data integrity and conduct periodic quality assurance tracking of the Company\u2019s customer loyalty program\u2019s databases\n\n(Candidates with more experience will be considered for Manager \u2013 Data Analytics.)\n\nGood remuneration and attractive fringe benefits will be offered to the successful applicant. Interested parties please apply with full resume, present and expected salary, available date by clicking \u201cApply Now\u201d.\n\nFor further information, please visit our company website:\u00a0http://www.shkp.com/.\n\n\nWe are an equal opportunity employer and welcome applications from all qualified candidates. All personal data collected will be used for recruitment purpose only.\u00a0 Applicants not hearing from us within 3 months may consider their applications unsuccessful.\u00a0 All personal data collected will be destroyed within 24 months.", "employment_types": ["Full Time", "Permanent"], "selling_points": ["Manage data warehouse & integrate data", "Organize and prepare business analysis reports", "Develop Business Intelligence tools"], "locations": ["Wan Chai"], "categories": ["Professional Services", "Business Analysis / Data Analysis", "Information Technology (IT)", "Product Management / Business Analyst", "Data Scientist"], "post_time": "2022-01-13T13:52:27Z", "salary": {"currency": null, "max": null, "min": null, "period": null, "term": null}, "salary_visible": false, "title_keywords": ["assistant manager"], "responsibilities": ["management", "data", "internal and external parties", "coordinate with", "procedures", "quality", "develop", "business analysis reports", "data analysis", "database", "evaluation", "maintain data", "databases", "tracking"], "requirements": {"degrees": ["degree", "bachelor"], "majors": ["statistics", "computer science"], "languages": ["english"], "language_level": ["proficiency"], "hard_skills": ["google analytics", "data warehouse", "data analytics", "analysis", "tableau", "analytical skills", "sql", "mobile", "programming", "data visualization", "mssql", "business intelligence", "acumen"], "soft_skills": ["communication skills", "work independently", "self-motivated", "good team player", "oral", "well-organized", "analytical skills", "hands-on", "business acumen", "presentation"], "languages_combined": [{"language": "english", "language_level": ["proficiency"]}]}, "experience_required": {"duration": ["minimum 7 years"], "field": ["data analysis", "business", "database management", "retail"]}}, {"job_id": "100003009044889", "location_code": "hk", "company": "Harbour City Estates Ltd", "job_title": "SYSTEM ANALYST", "description": "Responsibilities:\n\n\nTake lead in planning and implementing IT projects for Wharf\u2019s investment properties in Hong Kong and China\n\nEnsure all phases of the projects are well planned and completed on time, within budget and to the specified high quality\nHandle the project full cycle include identifying user requirements, performing feasibility study, recommending and selecting potential vendors, allocating manpower and resources, carrying out user acceptance test as well as conducting post project evaluation\u00a0\n\nRequirements:\n\n\nDegree holder in Computer Science, Information Technology or related disciplines\nHolder of project management certificates (e.g. PMP/Prince 2), information audit/security certificates (e.g. CISA/CISM/CISSP) or relevant professional qualifications\nMinimum 6 years\u2019 solid experiences in project management, vendor management and system implementation\nProven knowledge of web and mobile app development, cloud computing, workflow system, property management system, HR system, database management or BI system will be highly preferred\nExperienced project leader with good interpersonal and communication skills\nGood command of written and spoken English and Chinese\n\nWe offer competitive remuneration package that commensurate with experience and qualifications. Interested parties are invited to send full resume stating contact telephone number, date available, present and expected salary to our recruitment email address.\u00a0\n\n(Personal data provided will be used strictly in accordance with the Company's personal data policy which is available upon request.)", "employment_types": ["Full Time", "Permanent"], "selling_points": ["Degree holder in Computer Science, IT", "Minimum 6 years\u2019 solid experiences", "Proven knowledge of web and mobile app development"], "locations": ["Tsim Sha Tsui"], "categories": ["Information Technology (IT)", "Application Specialist - Software", "IT Project Management / Team Lead", "Product Management / Business Analyst"], "post_time": "2022-01-15T03:49:22Z", "salary": {"currency": null, "max": null, "min": null, "period": null, "term": null}, "salary_visible": false, "title_keywords": ["system analyst"], "responsibilities": ["evaluation", "budget", "quality", "planning"], "requirements": {"degrees": ["degree holder"], "majors": ["related disciplines", "computer science", "information technology"], "languages": ["english", "chinese"], "language_level": ["good command"], "hard_skills": ["bi", "web", "professional qualifications", "vendor", "project management", "mobile", "system implementation", "pmp"], "soft_skills": ["communication skills", "project management", "interpersonal"], "languages_combined": [{"language": "english", "language_level": ["good command"]}, {"language": "chinese", "language_level": ["good command"]}]}, "experience_required": {"duration": ["minimum 6 years"], "field": ["project management", "management"]}}, {"job_id": "100003009051870", "location_code": "hk", "company": "LAWSGROUP", "job_title": "Assistant IT Manager", "description": "Job Description:\nProvide application support & troubleshooting including system / server configurations / data patching\nWork with overseas local IT team to provide user training /end user support\nPerform system testing & daily routine job\nHandle overseas IT Projects\nPerform system support to overseas factory\nPerform ad hoc project as assigned by immediate supervisor\nJob Requirements:\nDegree or above in Computer Science, Information Technology or related discipline\nMinimum 5 years relevant experience with proven project implement/ system support/ helpdesk experience\nHands on experience in Oracle / MSSQL / Informix DBMS administration, AD/ Windows server / VMWare / VSAN administration\nSolid programming experience in SQL\nKnowledge in RPA / QlikView is an advantage\nExcellent problem solving, independently, able to work under pressure\nGood interpersonal communication and presentation skills\nGood command in both spoken and written English and Chinese\nWilling to travel and support different overseas projects and travel among factories is required\nWe\u00a0offer\u00a0attractive remuneration package to the right candidate. Interested parties please click the \"APPLY NOW\" button below and send your application together with a detailed resume including current & expected salary and availability to Human Resources Department.\nCompany website:\u00a0https://www.lawsgroup.com\n(Data collected will be treated in strict confidence and used for recruitment purpose only)", "employment_types": ["Full Time", "Permanent"], "selling_points": ["Minimum 5 years exprience in system support", "Degree or above in Computer Science", "Provide application support & troubleshooting"], "locations": ["Lai Chi Kok"], "categories": ["Information Technology (IT)", "IT Project Management / Team Lead", "Product Management / Business Analyst", "Others"], "post_time": "2022-01-17T01:25:48Z", "salary": {"currency": null, "max": null, "min": null, "period": "monthly", "term": null}, "salary_visible": false, "title_keywords": ["it manager", "assistant"], "responsibilities": ["testing", "ad hoc", "troubleshooting", "data"], "requirements": {"degrees": ["degree or above"], "majors": ["computer science", "information technology"], "languages": ["english", "chinese"], "language_level": ["good command"], "hard_skills": ["qlikview", "informix", "vmware", "vsan", "dbms", "sql", "rpa", "problem solving", "programming", "mssql", "windows server", "oracle"], "soft_skills": ["independently", "problem solving", "communication", "presentation skills", "hands on", "interpersonal", "work under pressure"], "languages_combined": [{"language": "english", "language_level": ["good command"]}, {"language": "chinese", "language_level": ["good command"]}]}, "experience_required": {"duration": ["minimum 5 years"], "field": ["project implement", "system support", "helpdesk experience", "sql", "relevant experience", "programming", "administration"]}}, {"job_id": "100003009048817", "location_code": "hk", "company": "Hong Kong Air Cargo Terminals Ltd", "job_title": "Digital Solution Lead (Mobile Development)", "description": "Duties\n\nPerform technical analysis, design and development and formulate the best-fit solution, which meets the business requirement, architectural standards and other non-functional requirement\nPerform project management duties and work with other IT teams for system integration\nManage digital, innovation and collaboration solution delivery\nParticipate in vendor management, keep track of the progress of project implementation and monitor the performance of the service providers\nIn-charge of the software development lifecycle and deliver the solution with good quality\nIdentify and resolve the project and technical constraints/risks\nPrepare project documentation and provide operation support to ensure service stability and availability\n\nQualifications\n\nBachelor degree holders in Information Technology, Computer Engineering, Computer Science or related disciplines\nMinimum 6 years\u2019 experience in application development, mainly in digital solution delivery and 2 years\u2019 experience in project management\nStrong experience in digital, innovation and collaboration solutions and integration projects\nHands on experience in web and mobile development projects delivery\nAbility to work independently and proactively in a flexible and dynamic environment\nGood analytical, problem solving and presentation skills\nGood team player, strong self-initiative and commit to achieve high quality results\nGood command of spoken and written English\nCandidates with less relevant experience may be considered as Systems Analyst\nWe offer 5-Day work week with a competitive and comprehensive remuneration package including Chinese New Year bonus, discretionary bonus, transport subsidy, employer topped-up MPF contributions, medical benefits (including family members), voluntary dental coverage (including family members), life insurance, birthday leave, extra annual leave, marriage leave, maternity leave, paternity leave, newborn baby gift, sports centre and free shuttle bus.\nInterested parties please apply with full resume detailing experience, qualifications and expected salary by post, by e-mail or click \"Apply Now\".\nBy post: Human Resources, 6/F, North Office Block, SuperTerminal 1, Hong Kong International Airport, HK\nPlease quote the above reference in your application. To know more about our company, please visit our website https://careers.hactl.com/.\nApplicants not invited for interview within four weeks should consider their applications unsuccessful. Applicants\u2019 personal data collected will only be used for the sole purpose of recruitment. The data of unsuccessful applicants will be destroyed within six months.", "employment_types": ["Full Time", "Permanent"], "selling_points": ["Excellent career opportunity with attractive pay", "Guarantee 13th month pay & discretionary bonus", "Free Shuttle and Transport Subsidy"], "locations": ["Airport Area"], "categories": ["Information Technology (IT)", "Application Specialist - Software", "Product Management / Business Analyst", "Software Development"], "post_time": "2022-01-14T07:21:52Z", "salary": {"currency": null, "max": null, "min": null, "period": "monthly", "term": null}, "salary_visible": false, "title_keywords": ["lead"], "responsibilities": ["management", "software", "mpf", "analysis", "systems", "teams", "implementation", "design", "quality", "project management", "monitor the performance", "application development", "insurance", "project documentation"], "requirements": {"degrees": ["degree", "bachelor"], "majors": ["related disciplines", "computer engineering", "computer science", "information technology"], "languages": ["english", "chinese"], "language_level": ["good command"], "hard_skills": ["documentation", "web", "technical analysis", "vendor", "problem solving", "project management", "mobile", "dynamic", "integration", "operation support"], "soft_skills": ["flexible", "work independently", "dynamic environment", "good team player", "problem solving", "project management", "presentation skills", "hands on", "self-initiative", "comprehensive"], "languages_combined": [{"language": "english", "language_level": ["good command"]}, {"language": "chinese", "language_level": []}]}, "experience_required": {"duration": ["2 years", "minimum 6 years"], "field": ["project management", "relevant experience", "digital", "application development", "development projects"]}}, {"job_id": "100003009048900", "location_code": "hk", "company": "Ambitious People Group", "job_title": "Project Manager | E commerce", "description": "What are you going to do?\n\nAs a project manager, you are going to work on an E-commerce platform with the team. You will be a key member to improve the applications and processes that optimise logistics, operations, and user growth. Time management is the key and have to fully understand the e-commerce life-cycle. There will be room for you to thrive and come up with new solutions with the latest technologies. You will be working closely with the rest of the IT team, i.e. graphic designers, and UI/US designers. The tool they are using in this application: PHP,UI/US, Adobe Magento, SAP.\n\nWhat is offered to you?\n\nSalary between HKD 25,000 and HKD 45,000\nOpportunities to learn the latest technologies\nOpen-minded culture\nFlexible working hour\nProvide technical training\n\nWhat is expected of you?\n\nBachelor's degree in information systems or other related disciplines\n3-4 years of experience of project management\nExperienced in handle large scale of projects\nProficient in Magento\nFluency in English and Cantonese\n\nWhere are you going to work?\n\nYou are going to work in an E-commerce house that is helping more than 100 merchants market and sell their products online. Other than that, your company is also providing the logistics, operations, and warehousing of thousands of products every week. You are going to work under a flat company structure and a flexible environment.\n\nLearn more or apply directly?\n\nClick on the 'Apply' button if this sounds interesting to you. If you would like to discuss other opportunities, feel free to contact me via + 852 3511 6013 or mail me at inez.poon@ambitiouspeople.com. Looking forward to hearing from you!", "employment_types": ["Full Time", "Permanent"], "selling_points": ["Open-minded culture", "Flexible working hour", "Provide training"], "locations": ["Kwun Tong"], "categories": ["Information Technology (IT)", "Product Management / Business Analyst", "Others"], "post_time": "2022-01-14T07:39:01Z", "salary": {"currency": "HKD", "max": 44999, "min": 30000, "period": "monthly", "term": null}, "salary_visible": true, "title_keywords": ["project manager"], "responsibilities": ["warehousing", "management", "operations", "systems", "project management", "logistics", "contact", "e-commerce platform", "ui"], "requirements": {"degrees": ["degree", "bachelor"], "majors": ["related disciplines"], "languages": ["cantonese", "english"], "language_level": ["fluency"], "hard_skills": ["sap", "php", "e-commerce", "project management", "adobe"], "soft_skills": ["flexible", "open-minded", "project management", "time management"], "languages_combined": [{"language": "cantonese", "language_level": ["fluency"]}, {"language": "english", "language_level": ["fluency"]}]}, "experience_required": {"duration": ["3-4 years"], "field": ["project management"]}}, {"job_id": "100003009043170", "location_code": "hk", "company": "iFAST ePension Services Limited", "job_title": "Business Analyst (Frontend Pension Projects)", "description": "Responsibilities:\n\nWork closely with the IT application team throughout the system development life cycle to deliver product features and solutions;\nDrive and participate into projects related to digital-user adoption and commercialization of digital capabilities in pensions business;\nDesign the digitalization journey, and prepare business and functional requirements for the purpose of digitization process;\nWork closely with UI/UX Designer, IT and external vendors for digitalization initiatives;\nPerform end-to-end UAT and work closely with UI/UX, IT and BA as a team;\nProject and analyze users initiatives and recommend best solutions to achieve digitalization target.\n\nRequirements:\n\nBachelor degree in Computer Science, IT, Business Information Systems or related field;\nMinimum 1 year\u2019s related experience in project managements of digital solutions; preferably related experience in the financial industry;\nExperience working in an Agile/Scrum software development environment a plus;\nCapacity to multi-task, manage time effectively and work under pressure and to fixed deadlines with attention to detail in a fast-paced environment;\nStrong analytical, interpersonal and communication skills;\nExcellent command in spoken and written English and Chinese.\n\nOur Offer:\n\nAttractive remuneration;\nCareer development prospect;\n5-day working week;\n21+ days Annual Leave for all staff;\nPerformance bonus and company shares;\nMedical, Dental, Life Insurance;\nEducation allowance and monthly sports allowance.\n\nOur company is an equal opportunities employer and welcomes applications from all qualified candidates.\u00a0Information provided will be treated with strict confidentiality and be used for the purpose of selection only.\u00a0Applicants who are not invited for an interview within 10 weeks may consider their applications unsuccessful. Personal data of unsuccessful applicants will be destroyed within 12 months.", "employment_types": ["Full Time", "Permanent"], "selling_points": ["Digital pension platform and related applications", "Fresh graduates are welcome", "21 days+ annual leave and company shares (SGX:AIY)"], "locations": ["Tsim Sha Tsui"], "categories": ["Information Technology (IT)", "IT Project Management / Team Lead", "Product Management / Business Analyst", "Testing / QA"], "post_time": "2022-01-12T10:00:14Z", "salary": {"currency": null, "max": null, "min": null, "period": "monthly", "term": null}, "salary_visible": false, "title_keywords": ["business analyst"], "responsibilities": ["commercialization", "ui", "design", "uat"], "requirements": {"degrees": ["degree", "bachelor"], "majors": ["business", "it", "computer science"], "languages": ["english", "chinese"], "language_level": ["excellent"], "hard_skills": ["plus", "agile"], "soft_skills": ["communication skills", "multi-task", "agile", "fast-paced environment", "attention to detail", "interpersonal", "work under pressure"], "languages_combined": [{"language": "english", "language_level": ["excellent"]}, {"language": "chinese", "language_level": ["excellent"]}]}, "experience_required": {"duration": ["minimum 1 year"], "field": ["related", "digital", "financial industry", "software development"]}}, {"job_id": "100003009053174", "location_code": "hk", "company": "Okay Property Agency Limited", "job_title": "Senior Developer", "description": "OKAY.com \u5c4b\u4f01 is a disruptive prop-tech real estate agency using technology to change the Hong Kong real estate market. The company is also a Founding Member of Forbes Global Properties, an elite invitation-only consortium of the top real estate agencies worldwide, connecting buyers and sellers to the highest caliber of property experts and luxury properties around the globe. We are the exclusive member in Hong Kong and sole Founding Member in Asia.\n\nWe are seeking an outstanding senior architect/developer to join a high-performance team responsible for the development and operation of the company\u2019s technology platforms. This person is highly motivated, combines deep technology expertise across multiple successful implementations and relishes the prospect of taking responsibility across various projects and disciplines.\n\nThis is a terrific opportunity to contribute to the growth of a business where technology and innovation are key enablers to success.\n\nReporting directly to the IT Director, your responsibilities will include:\n\n\nContributing to the strategy, roadmap and architecture of OKAY.com\u2019s technology platforms\nMapping requirements to technical designs, articulating solution risks and barriers, recommending project approaches\nPrototyping and evaluating new technologies and tools\nDeveloping, testing and implementing solutions across multiple technical tiers (front-end, back-end, interfaces, analytics)\nDirecting and supporting resources to develop new functionality and features\nLiaising with digital marketing teams to enhance SEO and our web presence\nPreparing and enabling our users through training\nDiagnosing issues, researching solutions and taking the necessary actions to resolve them\nYou have:\n\nAn advanced university degree and a keen interest in technology\nAt least 7 years professional experience designing, developing and implementing n-tier architectures across:\nC#, ASP.NET, .Net Core, WebApi\nHTML, CSS, Javascript, JSON, REST\nSql Server, EF, TSQL\nExperience in information architecture design and implementation across traditional database technologies as well as modern document databases\nExperience with modern software development processes including continuous build/test/release cycles (DevOps)\nThe tenacity to quickly comprehend complex problems / opportunities and create innovative solutions\nThe people skills required to work across users, designers, developers and business managers\nA strong desire for fun on the job as well as deep commitment to personal development", "employment_types": ["Full Time", "Permanent"], "selling_points": ["Senior Developer", "Tech Company", "Friendly & Collaborative Work Environment"], "locations": ["Central"], "categories": ["Information Technology (IT)", "Application Specialist - Software", "Product Management / Business Analyst", "Software Development"], "post_time": "2022-01-17T06:16:14Z", "salary": {"currency": null, "max": null, "min": null, "period": "monthly", "term": null}, "salary_visible": false, "title_keywords": ["developer"], "responsibilities": ["reporting", "seo", "software", "teams", "developing", "liaising with", "develop", "testing", "design", "implementation", "digital marketing", "database", "designing", "databases", "architecture"], "requirements": {"degrees": ["university degree"], "majors": [], "languages": [], "language_level": [], "hard_skills": ["seo", "fun", "devops", "html", "sql", "javascript", "databases", "server", "css", "web presence", "c#"], "soft_skills": ["advanced", "responsible", "keen", "deep", "motivated", "innovative"], "languages_combined": []}, "experience_required": {"duration": ["at least 7 years"], "field": ["devops", "developing", "design", "database", "software development"]}}, {"job_id": "100003009045871", "location_code": "hk", "company": "DKSH Hong Kong Limited", "job_title": "System Analyst (Business Intelligence)", "description": "Job Responsibilities:\n\nIdentify opportunities to optimize enterprise database architectures as a part of Business Intelligence initiatives\nProvide solutions, perform implementation and monitor validation processes to ensure data integrity and optimal performance\nDesign, implement and monitor source-to-target systems to ensure availability, as well as providing support, problem determination and resolution of business intelligence reporting / technical issues within service level expectations\nParticipate in infrastructure design and installations that suit different business operations\nPerform all phases of the ETL process to ensure compliance with standard operating procedures and global templates\nMaintain internal processes and quality standards documentation to ensure process controls and audits are up to date and aligned to DKSH IT standards\nAssist and support Business Objects application / SQL databases within various project / implementations, including global / country support processes\nConduct knowledge transfer, training and best practice sharing to local Country IT or other internal stakeholders to ensure knowledge availability / continuity\nNegotiate solutions with business stakeholders and users\nEnsure adherence to agreed service/operational level agreements as well as user satisfaction\n\nJob Requirements:\n\nDiploma or above in Computing / Information Technology or equivalent\nAt least 1 year of relevant experience, solid experience in the implementation of business intelligence tools (e.g. SAP Business Warehouse, Business Warehouse on HANA, QlikView, Lumira, Business Objects and SQL) and performance-tuning of business intelligence systems\nProven visual design skills used to create information-dense and easy-to-understand reports/dashboards\nAbility to demonstrate relational database and star schema design and implementation skills\nProficiencies in office productivity tools (e.g. Excel, Word and PowerPoint\nGood command in both written and spoken English and Chinese\nCandidate with more experience will be considered as Senior role\nWorking Location: Wong Chuk Hang\n\n\n\nWe offer 5-day work week, performance bonus and attractive benefits including medical insurance.\u00a0Please apply with full particulars, contact number and current/ expected salary to Human Resources Department, DKSH Hong Kong Limited, 23rd Floor, Tower A, Southmark, 11 Yip Hing Street, Wong Chuk Hang, Hong Kong or fax:2895 9711.\n\nAll personal data collected will be used for recruitment purpose only.\u00a0Candidates will be contacted within 2 weeks if the background and experience are closely relevant to the job requirement.\n\nDrive Growth. Be the Difference. Join DKSH.\n\nDKSH\u2019s strength lies in our great diversity of services, industries, clients, products, regions, and employees from various cultures. We are proud of our people: they are the best in the industry and the reason for our business success. They are passionate, energetic, and purposeful, positively touching millions of lives through the products and services we provide. Join us today if you are ready to \u201cDrive Growth. Be the Difference.\u201d With DKSH, you will experience a world of learning and development, own your career and take business responsibility, and have a positive impact that touches people\u2019s lives.", "employment_types": ["Full Time", "Permanent"], "selling_points": ["Diploma or above in Computing / Information Tech", "Implementation of business intelligence tools", "Optimize enterprise database architectures"], "locations": ["Aberdeen"], "categories": ["Information Technology (IT)", "Support", "Product Management / Business Analyst", "Data Scientist"], "post_time": "2022-01-13T08:59:31Z", "salary": {"currency": null, "max": null, "min": null, "period": "monthly", "term": null}, "salary_visible": false, "title_keywords": ["system analyst"], "responsibilities": ["data", "operations", "ensure adherence", "quality", "design", "maintain", "database", "infrastructure", "monitor", "implementation", "resolution", "reporting", "procedures", "provide solutions", "providing support", "audits", "documentation", "systems", "ensure compliance", "databases"], "requirements": {"degrees": ["diploma or above"], "majors": ["information technology"], "languages": ["english", "chinese"], "language_level": ["good command"], "hard_skills": ["qlikview", "excel", "sap", "word", "powerpoint", "sql", "visual design", "business intelligence"], "soft_skills": [], "languages_combined": [{"language": "english", "language_level": ["good command"]}, {"language": "chinese", "language_level": ["good command"]}]}, "experience_required": {"duration": ["at least 1 year"], "field": ["business", "relevant experience"]}}, {"job_id": "100003009045978", "location_code": "hk", "company": "PressLogic Limited", "job_title": "Product Manager / Project Manager (NFT marketplace)", "description": "We are looking for candidates who are familiar with the Blockchain & NFT market, its operation and products. Responsible for the overall planning and management of a project or product and translate them into executable plans. You should be experienced and be able to analyze the situation independently for possible solutions and driving the project forward.\u00a0\n\n\n\n\nBy driving the project or product from 0 to 1. This requires good communication skills with strong passion in driving for success and excellence by cooperating with different internal and external stakeholders. You will take lead in project planning, resourcing, progress reporting, project team management, timeframe, troubleshooting and the continuing maintenance of good relations with all stakeholders.\n\n\n\n\nResponsibilities:\n\nCoordinate with our partners to manage the delivery of blockchain applications, and connected applications or websites\nDevelop a holistic executive level milestone plan for the business spanning technical delivery and business activities\nDefine project scope and communicate effectively to cross functional team\nBe responsible for product planning, design guiding and execution with internal cross team communication\nResearch and provide business insight, knowledge on blockchain technologies and gaming independently upon products launched\u00a0\nPresent ideas and proposals with confidence in lobbying and negotiation\nIdentify areas for improvement to sharpen product ecosystem, continuously enhance the product features and development\n\nRequirements:\n\nMinimum 6 years relevant project management experience with demonstrated entrepreneurial capability\nAll-round project management skills; proven track record of project success is preferred\nStrong interest in blockchain and NFTs industries\nStrong conceptual and logical thinking with great design sense\nExcellent written and verbal communication skills\nProactive with excellent negotiation and presentation skills\nGood understanding of the game development and/or website development\nAbility to communicate, coordinate, and actively liaise across different departments and external parties (Engineers, artists, QA, and marketing)\nFamiliar with live operations, as well as CS and social and community management", "employment_types": ["Full Time"], "selling_points": ["NFT & Social Media", "Blockchain & Crypto project management", "Company start-up ownership opportunity"], "locations": ["Lai Chi Kok"], "categories": ["Information Technology (IT)", "IT Project Management / Team Lead", "Product Management / Business Analyst", "Others"], "post_time": "2022-01-13T09:18:46Z", "salary": {"currency": null, "max": null, "min": null, "period": "monthly", "term": null}, "salary_visible": false, "title_keywords": ["project manager", "product manager"], "responsibilities": ["ideas", "coordinate with", "design", "develop", "communication", "plan", "business activities", "planning"], "requirements": {"degrees": [], "majors": [], "languages": [], "language_level": [], "hard_skills": ["blockchain", "project management"], "soft_skills": ["communication skills", "negotiation", "project management skills", "project management", "presentation skills", "proactive"], "languages_combined": []}, "experience_required": {"duration": ["minimum 6 years"], "field": ["project management"]}}, {"job_id": "100003008998684", "location_code": "hk", "company": "SEEK Asia (JobsDB)", "job_title": "Senior Business Analyst (Mobile)", "description": "The Role\nThe Senior Business Analyst is responsible for analysing, forming requirements, writing agile stories, spring iteration, sprint planning, sprint tracking and team reporting for Seek Asia Apps. This is an individual contributor who has the ability to understand mobile applications, break down complex problems and to help drive the success of the team.\nKey responsibilities include:\nCreating, planning, estimating and maintaining the agile stories for Seek Asia mobile apps.\nBreak down complex requirements into clear stories.\nEnsuring the teams agile rituals operate smoothly.\nPrioritisation of stories with the product managers and engineering manager.\nCreation of clear reports showing team velocity,\u00a0 team health, and risks for delivery.\nEnsuring clear communication between the key stakeholders and other teams.\nAct as a facilitator for the team, who follow agile practices.\nHelp with knowledge sharing within the organisation.\nSo, what we are looking for?\nWorking in a test-driven and agile software development environment.\nWorking with Jira, Miro, Slack, Microsoft Office.\nHands-on experience in requirements gathering, analysis, estimating and planning.\nPrevious experience in mobile apps.\nInvolved in collaboration with stakeholders to understand business challenges and customer needs, remove bottlenecks, and help identify new opportunities for growth.\nKnowledge and experience with industry best practices, regulations and compliance (GDPR, PDPI), and quality assurance techniques.\nExperience working with geo-distributed teams and external consultants.\nPositive attitude and a clear sense of initiative.\nUses data to help drive decision making.\nInfluences and motivates others.\nHas a growth mindset - flexible, open, and actively seeking opportunities to improve.\nContinuously learn and understand the business requirements, customer, and end-user feedback to further improve the products.\nManage own time well, being able to support the key stakeholders and be critical on inefficiencies. \u200b\nHighly self-motivated team player with good analytical and conceptual thinking, results-driven and customer focus.\nAbility to define requirements to improve customer experience.\nAbility to share new knowledge and new tools to cultivate constructive conversations and improve team capabilities.\nOpen minded collaborator and clear communicator who can manage stakeholders' expectations.\nDesired Values\nBelieved in aiming high to deliver world-class results and yet, not forgetting to care for others\nThe Team\nSeek Asia Apps provides products and services to candidates in job markets across the Asia region. We operate under the 3 brands of JobStreet, JobsDB and SEEK to help over 150 million candidates find employment.\nAdditional information\n\nAt SEEK, the health and safety of our people is our highest priority. For this reason, SEEK has introduced a policy requiring all employees and visitors to be fully vaccinated for COVID-19 within our offices, unless a formal medical exemption applies. In addition, all employees attending in-person work related meetings or events outside the office will also need to be fully vaccinated.\u00a0 We have chosen to share this information early in our hiring process, so that candidates can make an informed choice. On this basis, as part of the application process you will be asked to confirm that you have read and understood this policy, and would like to continue with the hiring process.\u00a0 Further details about this policy will be shared during the hiring process, as required.", "employment_types": ["Full Time", "Permanent"], "selling_points": ["Our motto: Improving Lives through Better Careers", "Company Values: We Care, We Aim High, We Deliver", "Customized career development opportunities"], "locations": ["Quarry Bay"], "categories": ["Information Technology (IT)", "Product Management / Business Analyst"], "post_time": "2022-01-13T18:48:24Z", "salary": {"currency": null, "max": null, "min": null, "period": "monthly", "term": null}, "salary_visible": false, "title_keywords": ["senior business analyst"], "responsibilities": ["regulations", "reporting", "software", "maintaining", "data", "analysis", "compliance", "teams", "quality", "communication", "planning", "reports", "tracking"], "requirements": {"degrees": [], "majors": [], "languages": [], "language_level": [], "hard_skills": ["agile", "microsoft office", "analysis", "reason", "mobile", "make", "spring", "focus"], "soft_skills": ["flexible", "self-motivated", "agile", "responsible", "communicator", "world-class", "clear", "communication", "hands-on", "positive attitude", "open minded", "organisation", "customer focus", "constructive", "team player", "initiative", "driven", "decision making"], "languages_combined": []}, "experience_required": {"duration": [], "field": ["quality assurance", "compliance", "planning"]}}, {"job_id": "100003009038526", "location_code": "hk", "company": "MSIG Insurance (Hong Kong) Limited", "job_title": "Senior Business Analyst, Information Technology", "description": "Job Responsibilities:\n\nDrive business requirement discussions and collaborations with key business users to conduct feasibility analysis and determine cost, benefits and scope of potential IT solutions\nPerform business process analysis, document existing processes to recommend areas of operational improvements as well as contribute to business growth\nLiaise closely with business users, IT teams and vendors to ensure effective delivery of IT solutions and timely resolution or escalation of critical production business growth\nPlan, coordinate, and conduct all project activities, IT integration and user acceptance test, users training, production deployment, problem diagnosis and reporting\nTransform business requirements into test cases to establish traceability linkage across the entire software development life cycle\nProduce relevant documentation in each stage of the implementation cycle and ensure its continuous up-to-date\nComply with corporate IT governance policy and standards, and the company policy on information and cyber security\n\nJob Requirements:\n\nBachelor degree holder or equivalent in information technology or related business disciplines\nMinimum 5 years\u2019 experiences of business analyst and project management in client server or web application development for the insurance or financial industry\nExperience in IT development skills (e.g. Scrum Development methodology, data warehousing, system testing methodology) and software quality assurance disciplines\nBusiness domain knowledge in General Insurance will be an advantage\nGood team player, self-motivated and independent\nGood analytical, interpersonal, communication and problem-solving skills\nExcellent command of written & spoken English\n\n\n\nFor interested parties, please send full resume with\u00a0expected and current salary\u00a0by clicking the \"Apply Now\" button below.\u00a0You may visit our company website\u00a0www.msig.com.hk\u00a0for more background information.\n\nPersonal data collected will be used for recruitment purpose only and all applications will be treated in strict confidential. Unsuccessful applications will be destroyed after 12 months.", "employment_types": ["Full Time", "Permanent"], "selling_points": ["Perform business process analysis", "Ensure effective delivery of IT solutions", "Double pay, 5-days work, medical, training subsidy"], "locations": ["Tai Koo"], "categories": ["Information Technology (IT)", "Product Management / Business Analyst", "Insurance", "Others"], "post_time": "2022-01-11T07:14:26Z", "salary": {"currency": null, "max": null, "min": null, "period": "monthly", "term": null}, "salary_visible": false, "title_keywords": ["senior business analyst"], "responsibilities": ["liaise", "reporting", "cost", "software", "cyber security", "analysis", "teams", "implementation", "resolution", "coordinate", "business process", "plan", "documentation"], "requirements": {"degrees": ["bachelor degree holder"], "majors": ["business", "information technology"], "languages": ["english"], "language_level": ["excellent"], "hard_skills": ["server", "project management", "problem-solving skills", "web application development"], "soft_skills": ["good team player", "self-motivated", "independent", "communication", "project management", "problem-solving skills", "interpersonal"], "languages_combined": [{"language": "english", "language_level": ["excellent"]}]}, "experience_required": {"duration": ["minimum 5 years"], "field": ["it development", "financial industry", "project management", "business", "application development", "insurance"]}}, {"job_id": "100003009046074", "location_code": "hk", "company": "St. James' Settlement", "job_title": "Business Analyst (PO I) (Contract)\u3008Ref: RS/05322\u3009", "description": "Requirement:\n\nBachelor degree or above in Management Information System or related disciplines\n3 years relevant experience in preferred\nExcellent knowledge in IT security, application software and hardware devices\nGood analytical, problem solving, communication and interpersonal skills\nGood commend of spoken and written in English and Chinese\nJob Duties:\n\nAnalyze work procedures and needs in our operation, perform feasibility study to establish computerized information systems and propose solutions to the management\nResponsible for the whole system development project, including but not limited to identify users\u2019requirements, system design, vendor management, and system implementation\nEnsure smooth transformation to the new system, perform system maintenance and support to ensure system reliability, and identify potential risks and set up Business Continuity Plan to reduce adverse effects\nProvide hardware and software support in our operations\nIdentify and propose new tech products/solutions to enhance our operations, work safety, members\u2019physical mobility and/or mental development\nSupervisor subordinates\nWork as a member of the central support team to perform administrative support to Rehabilitation Services\n\nInterested persons please apply with full resume via \u201cAPPLY NOW\u201d\u00a0or\u00a0mail to 6/F, 85 Stone Nullah Lane, Wanchai, Hong Kong\u00a0on or before 26/01/2022.", "employment_types": ["Full Time", "Contract"], "selling_points": ["Bachelor degree in Management Information System", "3 years relevant experience in preferred", "Excellent knowledge in IT security"], "locations": ["Wan Chai"], "categories": ["Information Technology (IT)", "Product Management / Business Analyst", "Public / Civil", "Social Services - Community / Non-profit Organization"], "post_time": "2022-01-13T09:32:22Z", "salary": {"currency": null, "max": null, "min": null, "period": "monthly", "term": null}, "salary_visible": false, "title_keywords": ["business analyst"], "responsibilities": ["business continuity", "management", "rehabilitation", "software", "maintenance", "administrative support", "operations", "systems", "procedures", "implementation", "identify potential risks", "hardware", "system design", "plan"], "requirements": {"degrees": ["degree or above", "bachelor"], "majors": ["related disciplines"], "languages": ["english", "chinese"], "language_level": ["good"], "hard_skills": ["problem solving", "hardware", "information system"], "soft_skills": ["problem solving", "communication and interpersonal skills"], "languages_combined": [{"language": "english", "language_level": ["good"]}, {"language": "chinese", "language_level": ["good"]}]}, "experience_required": {"duration": ["3 years"], "field": ["relevant experience"]}}, {"job_id": "100003009044112", "location_code": "hk", "company": "3PL-Total Technology (HK) Limited", "job_title": "Business Analyst / Application Specialist", "description": "Responsibilities:\nUnderstand and keep learning among company\u2019s software / SaaS product and solutions, in both business, industrial and technical aspects\nWork closely with business teams / regional partners to provide effective support in the full path of solution engagement, includes requirement discovery, solution demonstration and recommendation, up to implementations and post-sale reviews\nMaintain a set of training / demonstration environments and to provide effective demonstrations & trainings in flexible ways\nConvert and translate solution recommendations into detail technical document and specifications for DevOps teams\nWork simultaneously with multiple projects in different stages\nProactively share product, process, solution and lesson-learns to technical and business teams\nAssist business teams to deliver sophisticated and effective business material, in different formats and levels of detail\u00a0\nRequirements:\nUniversity degree in Computer Science or relevant preferred;\u00a0 Candidates from other disciplines with sufficient IT knowledge is also considered.\n2-4 years of working experience in software industry\nHighly communicative, well organized and able to work efficiently in tight timeline\nHighly responsible, quick learning and self-motivated are essential\nSmooth communication skills with people from different cultures and working levels are must\nGood language commands in English and Cantonese is a must;\u00a0 such in Mandarin are preferred\nWilling to travel to different regions frequently\nExperience in software pre-sales or application specialist will be an advantage\nSoftware development experience will be an advantage\nProject management experience will be an advantage\nKnowledge or experience in logistic / supply chain / auto-ID industries is an advantage\nCapable candidate with less experience will be considered as Application Specialist Trainee\n\u00a0Career Path:\nContinual internal product training and business know-how training\nExcellent opportunity for development of a profession that balances technical and people skills, in the scopes of Internet business.\nWith 2+ year in-house experience, capable staffs at post of Application Specialist are considered to be promoted to Assistant Solution Manager or Project Manager or other applicable positions.\nBenefits:\nFriendly and complaisant working environment, various allowances & bonus plus career growth supports such as education subsides.\nOpportunity to explore pioneering technology, innovative solutions and arising business trends, such as eCommercing, Demand-driven supply chain \u2026 etc\nRewarding and flexible company cultures and career paths\nCompany Business Milestone Bonuses (Several times in a year)\nInterested candidates please submit cover letter and resume,\u00a0stating present & expected Salary\u00a0to hr@3pltotal .com or click APPLY NOW.\u00a0Any inquiry please contact\u00a0+852 2699 9920\n", "employment_types": ["Full Time", "Permanent"], "selling_points": ["Misc. allowances & business milestone bonuses", "1-4 yr. exp. in software industry", "SaaS software for logistics industries"], "locations": ["Wong Tai Sin Area"], "categories": ["Information Technology (IT)", "Application Specialist - Software", "IT Project Management / Team Lead", "Product Management / Business Analyst"], "post_time": "2022-01-13T03:06:06Z", "salary": {"currency": null, "max": null, "min": null, "period": "monthly", "term": null}, "salary_visible": false, "title_keywords": ["business analyst", "application specialist"], "responsibilities": ["software", "teams", "specifications", "maintain", "multiple projects"], "requirements": {"degrees": ["university degree"], "majors": ["computer science"], "languages": ["cantonese", "english", "mandarin"], "language_level": ["good"], "hard_skills": ["project management", "it knowledge"], "soft_skills": ["communication skills", "self-motivated", "capable", "responsible", "well organized", "project management", "learning", "smooth"], "languages_combined": [{"language": "cantonese", "language_level": ["good"]}, {"language": "english", "language_level": ["good"]}, {"language": "mandarin", "language_level": []}]}, "experience_required": {"duration": ["2-4 years", "2+ year"], "field": ["project management", "supply chain", "software development"]}}, {"job_id": "100003009044859", "location_code": "hk", "company": "Mad Mobile Application Development Limited", "job_title": "IT Project Manager", "description": "The Role\n\nWork with all stake holders, regional partners and customer to complete project within defined schedule and achieve set targets.\nPrepare documents for the whole project implementation.\nDrive internal and third-party service review meetings covering performance, service improvements, quality and processes.\nCoordinate with various parties for service launch.\nLead & control the project related risk management process & ad-hoc tasks as assigned.\n\nTo Qualify\n\nDegree holder in Information Technology or related disciplines.\nAt least 5 years of working experience in IT with at least 3 years project management experience.\nAble to work independently and meet project deadlines.\nA good team player that is self-motivated, detail-oriented and able to work under pressure.\nGood command of spoken and written English and Chinese (Cantonese and Mandarin).\n\n(Candidate with less experience will be considered as Senior Project Coordinator)\n\nWe Offer\n\nMAD MAD offers the right candidate 5-day work week, competitive salary package and fringe benefits, discretionary bonus, and a friendly and wonderful working environment.\n\nTo Apply\n\nThis is definitely a golden opportunity to gain valuable experience in an excellent company.\n\nDue to the high volume of applicants, only shortlisted candidates will be notified. All personal data collected will be used for recruitment purpose only.", "employment_types": ["Full Time"], "selling_points": [], "locations": ["Tsuen Wan Area"], "categories": ["Information Technology (IT)", "IT Project Management / Team Lead", "IT Management", "Product Management / Business Analyst"], "post_time": "2022-01-13T06:28:21Z", "salary": {"currency": null, "max": null, "min": null, "period": "monthly", "term": null}, "salary_visible": false, "title_keywords": ["it project manager"], "responsibilities": ["control", "management", "ad-hoc tasks", "review", "quality", "implementation", "coordinate with", "project management", "schedule", "prepare documents", "work under pressure"], "requirements": {"degrees": ["degree holder"], "majors": ["related disciplines", "information technology"], "languages": ["cantonese", "english", "chinese", "mandarin"], "language_level": ["good command"], "hard_skills": ["project management"], "soft_skills": ["work independently", "self-motivated", "good team player", "detail-oriented", "project management", "work under pressure"], "languages_combined": [{"language": "cantonese", "language_level": ["good command"]}, {"language": "english", "language_level": ["good command"]}, {"language": "chinese", "language_level": ["good command"]}, {"language": "mandarin", "language_level": ["good command"]}]}, "experience_required": {"duration": ["at least 3 years", "at least 5 years"], "field": ["project management", "it"]}}, {"job_id": "100003009045780", "location_code": "hk", "company": "Kepro Solutions Limited", "job_title": "Consultant/Associate Consultant \u2013 Business Intelligence", "description": "Dashboard implementation project\nBI systems support and maintenance\n\nRequirements\n\nDegree in Computer Sciences / Information Technology / Data management but not a must or related discipline.\nExperience in using Business Intelligence (BI) / Data Visualization tools such as Tableau, PowerBI, Qlikview etc.\nExperience in SQL, Python programming is an advantage.\nETL project experience is an advantage.\nAbility to provide efficient, timely, and reliable service to customers.\nGood command of both written and spoken English and Chinese.\nFresh graduates would also be considered.\n\nWe offer a competitive remuneration package to the right candidate. Interested parties please send your full resume with\u00a0present and expected salary to us by\u00a0clicking 'Apply Now'.\n\nCompany Address: 9/F, The Whitney, 183 Wai Yip Street, Kwun Tong, Hong Kong\n\nKepro Solutions Website:\u00a0https://intranet.karingroup.com/IntranetApp/Default.aspx\n\n\n(We are an Equal Opportunity Employer and personal data collected would be used for recruitment purpose only.)", "employment_types": ["Full Time", "Permanent"], "selling_points": ["Fresh graduates are welcome; 5-day work", "BI and Data Analytics", "Big data projects exposure and Steady career path"], "locations": ["Kwun Tong"], "categories": ["Professional Services", "Business Analysis / Data Analysis", "Information Technology (IT)", "Product Management / Business Analyst", "Data Scientist"], "post_time": "2022-01-15T03:49:32Z", "salary": {"currency": null, "max": null, "min": null, "period": "monthly", "term": null}, "salary_visible": false, "title_keywords": ["associate", "consultant"], "responsibilities": ["management", "visualization", "maintenance", "data", "systems", "implementation"], "requirements": {"degrees": ["degree"], "majors": ["information technology"], "languages": ["english", "chinese"], "language_level": ["good command"], "hard_skills": ["qlikview", "bi", "data management", "maintenance", "tableau", "sql", "programming", "data visualization", "python", "business intelligence"], "soft_skills": ["efficient", "timely", "reliable"], "languages_combined": [{"language": "english", "language_level": ["good command"]}, {"language": "chinese", "language_level": ["good command"]}]}, "experience_required": {"duration": [], "field": ["sql", "business", "programming"]}}, {"job_id": "100003009049458", "location_code": "hk", "company": "Standard Chartered Bank (Hong Kong) Ltd", "job_title": "Enterprise Agile Coach - Mox - (2200000356)", "description": "About Standard Chartered\u00a0\nWe are a leading international bank focused on helping people and companies prosper across Asia, Africa and the Middle East.\u00a0\n\nTo us, good performance is about much more than turning a profit.\u00a0 It's about showing how you embody our valued behaviours - do the right thing, better together and never settle - as well as our brand promise, Here for good.\n\nWe're committed to promoting equality in the workplace and creating an inclusive and flexible culture - one where everyone can realise their full potential and make a positive contribution to our organisation. This in turn helps us to provide better support to our broad client base.\n\nAbout Mox\nAs one of the biggest banks in market, we are rapidly expanding by growing a new virtual banking business in Hong Kong. We see ourselves as a fast growing start-up company where you will enjoy autonomy and teamwork at the same time, solving new and exciting problems in a nimble and agile way. Join us and be part of history making for future banking experience!\n\nThe Role Responsibilities\n\nCoordinate the stream (ie a project) and apply the programme methodology and governance to ensure deliveries are made on time and within the budget allocated\nIdentify all the required activities to delivery and build the plan accordingly\nCarefully manage the plan as well as the risks and issues and translate the plan into tangible timelines and milestones; suggest solid mitigation options when required\nIdentify and monitor the key external dependencies that could affect the delivery\nAct as a first escalation point: Remove any blocker preventing the delivery; able to escalate in a timely way to senior management when required\nWork out an effective communication to report regularly to management and key stakeholders the progress on the project as well as potential issues/decisions needed\nProvide visibility to the project stream leads on the overall progress and their contribution to the overall deliverables\nApply a structured methodology to ensure the project deliverables.\u202fIt should cover the following:\nDesign the mode and facilitate the communications within the wider project team, as well as to senior stakeholders; identify and manage areas of potential resistance\nSuggest metrics and KPIs to measure and monitor the progress\nMaintain close interactions with the work stream leaders to keep abreast of the progress, make adjustment to the project plan if necessary\nSupport program level governance work when required\n\nOur Ideal Candidate\n\nUniversity graduate with at least 5 years solid experience in the banking industry, exposure of key positions in Operations Development, Business Process Management, Change Management and/or Management Consulting; with at least 3 years in a project management role or equivalent capacity\nProven track record in delivery of large projects in a sizable organization\nProject management certification (PMP, SCRUM, PRINCE etc) with focus on Agile methodology required\nExpertise in software development methodologies (SDLC, Waterfall, Agile) including being seasoned Jira and Confluence user is a must\nResults oriented, able to work in high pressure environment\nStrong sense of ownership for the project and demonstrate commitment to driving project objectives\nDemonstrated ability to work with different cultures, and with proven negotiation and leadership skills; strong coordination skills and capability to drive the contributors and stakeholders who have different priorities; ability to influence and facilitate executive level decisions\nAbility to identify project risks and to recommend mitigation actions\nPro-active and forward thinker: able to anticipate and to take action accordingly\nAble to be comfortable at the deepest level of details and to be able to articulate a clear summary to senior stakeholders when required (covering both technical and business aspects)\nThinks critically about project delivery, challenges the status quo to identify opportunities to enhance processes and services\nDemonstrate strong moral principles to do what is right for the customers, employees and partners; have the courage to speak the mind and not afraid to push boundaries\nApply now to join the Bank for those with big career ambitions.\n", "employment_types": ["Full Time"], "selling_points": ["University graduate", "At least 5 years solid experience", "Proven track record in delivery of large projects"], "locations": ["Not Specified"], "categories": ["Information Technology (IT)", "IT Project Management / Team Lead", "Product Management / Business Analyst", "Others"], "post_time": "2022-01-14T08:42:41Z", "salary": {"currency": null, "max": null, "min": null, "period": "monthly", "term": null}, "salary_visible": false, "title_keywords": [], "responsibilities": ["software", "consulting", "operations", "budget", "design", "communication", "maintain", "business process", "plan", "senior management", "monitor", "client base", "banking", "kpis", "report", "management", "change management", "project deliverables", "project plan", "coordinate", "project management", "coordination"], "requirements": {"degrees": ["university graduate"], "majors": ["business"], "languages": [], "language_level": [], "hard_skills": ["agile", "pmp", "make", "project management", "sdlc", "focus"], "soft_skills": ["agile", "focused", "coordination skills", "leadership skills", "communication", "articulate", "focus", "moral", "clear", "committed", "ideal", "negotiation", "pro-active", "positive", "flexible", "timely", "teamwork", "project management", "organisation", "structured"], "languages_combined": []}, "experience_required": {"duration": ["at least 5 years"], "field": ["banking industry", "management", "banking experience", "consulting", "development", "business"]}}, {"job_id": "100003009044255", "location_code": "hk", "company": "Up Recruitment Limited", "job_title": "Business Analyst", "description": "The client:\n\nA well-known conglomerate in HK\n\nWhat can the client offer?\n\nValuable working experience in a market leading company\nFriendly working environment, down-to-earth management culture\n\nWhat are your responsibilities?\n\nLiaising with various business units and functional departments on business requirements\nPerforming requirement analysis, feasibility study and producing requirement and functional specifications\nWork closely with the IT team and vendors to deliver quality solution to users\nDeliver IT solution and advise, and support to end-user and on IT projects\nMonitor project progress and co-ordinate with various stakeholders for necessary resources\n\nWhat skills/qualification will you need?\n\nDegree in computer science, IT, information system, BBA or related disciplines\n3+ years of experience in IT system, App, Web project management\nExperiences in using O365 with TEAMS, word, excel, PowerPoint\nKnowledge and experience in application development and software tools would be an advantage\nGood command in English and Chinese\nCandidate with more experience will be considered as senior Business Analyst\n\nWho would be suitable for the position?\n\nStrong problem-solving techniques, interested in applying up-to-date IT solution to business operation\nAble to work under pressure and meet tight deadlines", "employment_types": ["Full Time", "Permanent"], "selling_points": ["Degree Holder in BBA or IT", "3+ years of experience", "Fluent in English and Chinese"], "locations": ["Central & Western Area"], "categories": ["Information Technology (IT)", "IT Project Management / Team Lead", "Product Management / Business Analyst"], "post_time": "2022-01-13T03:34:16Z", "salary": {"currency": null, "max": null, "min": null, "period": "monthly", "term": null}, "salary_visible": false, "title_keywords": ["business analyst"], "responsibilities": ["business operation", "management", "monitor project progress", "software", "co-ordinate with", "analysis", "quality", "liaising with", "teams", "project management", "specifications", "application development", "work under pressure"], "requirements": {"degrees": ["degree"], "majors": ["related disciplines", "bba", "it", "computer science"], "languages": ["english", "chinese"], "language_level": ["good command"], "hard_skills": ["o365", "excel", "analysis", "problem-solving", "word", "information system", "powerpoint", "web project management"], "soft_skills": ["meet tight deadlines", "problem-solving", "interested in", "project management", "friendly", "work under pressure"], "languages_combined": [{"language": "english", "language_level": ["good command"]}, {"language": "chinese", "language_level": ["good command"]}]}, "experience_required": {"duration": ["3+ years"], "field": ["business", "project management", "application development", "it"]}}, {"job_id": "100003009049042", "location_code": "hk", "company": "HKT Consumer Group", "job_title": "Product Assistant / Executive, eSmartHealth (Product Development)", "description": "Your Role\n\nAs a member in Product Development & Management team, you are required to assist the Product Managers in performing product development and management roles of our eSmartHealth products and services.\n\nYou will work closely with developers, technical consultants, customer service, sales and marketing teams in product strategies formulation, project planning and control, on-going enhancements of product logistics and supporting systems, training and feasibility studies.\n\nYou are also required to work with external business partners to carry out demonstrations, service installation and maintenance, system and user acceptance testing on products, services and features.\n\nTo Succeed in This Role\n\nDegree holder in Information Technology, Computer Science, Engineering, or related disciplines\n1-2 years relevant experience in product development / project management\nKnowledge of e-Health products and IoT technologies is an advantage\nCreative, self-motivated, analytical with good business sense\nA good team player with excellent presentation and interpersonal skills\nGood command of written and spoken English and Chinese, Mandarin is an advantage", "employment_types": ["Full Time"], "selling_points": [], "locations": ["Quarry Bay"], "categories": ["Information Technology (IT)", "Support", "Product Management / Business Analyst", "Technical / Functional Consulting"], "post_time": "2022-01-14T07:57:53Z", "salary": {"currency": null, "max": null, "min": null, "period": "monthly", "term": null}, "salary_visible": false, "title_keywords": ["product assistant", "product development", "executive"], "responsibilities": ["management team", "management", "project planning", "control", "installation", "maintenance", "systems", "teams", "testing", "project management", "customer service", "logistics"], "requirements": {"degrees": ["degree holder"], "majors": ["related disciplines", "engineering", "computer science", "information technology"], "languages": ["english", "chinese", "mandarin"], "language_level": ["advantage", "good command"], "hard_skills": ["project management", "maintenance"], "soft_skills": ["self-motivated", "good team player", "business sense", "project management", "customer service", "interpersonal skills", "creative", "presentation"], "languages_combined": [{"language": "english", "language_level": ["advantage", "good command"]}, {"language": "chinese", "language_level": ["advantage", "good command"]}, {"language": "mandarin", "language_level": ["advantage", "good command"]}]}, "experience_required": {"duration": ["1-2 years"], "field": ["project management", "product development", "relevant experience"]}}, {"job_id": "100003009047908", "location_code": "hk", "company": "Macroview Telecom Limited", "job_title": "Product Development Manager", "description": "Description\n\nTo develop product life cycle - idea generation, market research, building a market strategy, product development, create business cases, workflow development, market launch, and regular review process\nTo manage the business for selected ranges of products and implement product marketing program to capture incremental revenues\nAchieves assigned quota for company\u2019s assigned products\nTo help in nurturing and managing the Company\u2019s partnering relationship with vendors of selected products, and design and implement joint promotion events\nTo help in the management of the Company\u2019s overall product/solution portfolio\n\nRequirements\n\nShould be a degree holder with 8 years\u2019 experience in sales and/or product marketing in the ICT / Telecom / IT industry\nExcellent in both spoken and written Chinese and English, ability to speak in Putonghua will be an advantage\nAbility to work independently\nInterest in new technologies and self-motivated\nExperience in professional service or SOC selling would be preferred\nProficiency with power-point and Excel\nStrong people and communication skills\nCreative brainstorming, ambitious; self-starter; proactive and aggressive\nPassionate and knowledgeable about IT Security is preferred\nCandidates with less experience will be considered as Assistant Product Manager or Product Executive", "employment_types": ["Full Time", "Permanent"], "selling_points": ["Develop product life cycle", "Passionate and knowledgeable about IT Security", "8+ years\u2019 experience"], "locations": ["Quarry Bay"], "categories": ["Information Technology (IT)", "Product Management / Business Analyst", "Marketing / Public Relations", "Marketing - Brand / Product Management"], "post_time": "2022-01-14T04:12:45Z", "salary": {"currency": null, "max": null, "min": null, "period": "monthly", "term": null}, "salary_visible": false, "title_keywords": ["product development manager"], "responsibilities": ["management", "market research", "design", "develop", "regular review"], "requirements": {"degrees": ["degree holder"], "majors": ["marketing", "it"], "languages": ["putonghua", "english", "chinese"], "language_level": ["advantage", "excellent"], "hard_skills": ["excel"], "soft_skills": ["passionate", "communication skills", "work independently", "proactive", "self-motivated", "creative"], "languages_combined": [{"language": "putonghua", "language_level": ["advantage", "excellent"]}, {"language": "english", "language_level": ["advantage", "excellent"]}, {"language": "chinese", "language_level": ["advantage", "excellent"]}]}, "experience_required": {"duration": ["8 years"], "field": ["marketing", "it"]}}, {"job_id": "100003009047725", "location_code": "hk", "company": "Public Bank (Hong Kong) Ltd", "job_title": "Data Analyst (Ref: JD-DA)", "description": "Manage and participate data warehousing and data analytic project initiatives, including but not limited to data schema design, extract/transform/load (ETL) design, data presentation and visualization\nAcquire data from primary or secondary data sources and maintain databases/data systems\nWork with IT, user department and product owner to build and manage a wide variety of data sets\nTranslate business pain-points and solve by formulating action plans with analytical techniques and mathematical modeling\u00a0\nHelp planning and executing the development of analytical/machine learning solutions from initial design to model development, model validation, implementation, prototyping and testing\nPresent key findings and actionable recommendations to supervisors and other stakeholders\nMaintain good knowledge of data analytics trends and propose the use of latest data tools\nDegree holder in Computer Science or Engineering or related discipline\n3-5 years of experience in relevant business intelligence and data analytics, experience in banking industry is preferred\nExperience in analyzing business / data requirements, data gathering, cleansing & preparation.\nStrong SQL skills and experience working with relational databases.\nStrong data analytical skill and data sense.\nFamiliarity with visualization tools, e.g. Tableau, Qlikview\nSelf-directed with high motivation and demonstrated capability to manage time & projects and to innovate and explore new techniques\nStrong communication and interpersonal skills\nExperience in banking industry preferred, but not a strict requirement.\n\n\n\nTo apply, interested parties please follow the application methods available in the Bank\u2019s career website https://www.publicbank.com.hk/en/aboutus/careeropportunities. You can send us your resume quoting our job reference number together with present & expected salary (a must) to the Human Resources Department by email or fax at 2815 3157 or by post to Human Resources Department, 12/F, Public Bank Centre, 120 Des Voeux Road Central, Hong Kong. You may also visit our career website for other career opportunities available within our Group.\n\nPersonal data collected will be used for recruitment purpose only and will be treated in accordance with the Bank\u2019s Personal Information Collection Statement, a copy of which has been available in the Bank\u2019s career website.", "employment_types": ["Full Time", "Permanent"], "selling_points": [], "locations": ["Not Specified"], "categories": ["Banking / Finance", "Others", "Information Technology (IT)", "DBA", "Product Management / Business Analyst"], "post_time": "2022-01-15T03:49:00Z", "salary": {"currency": null, "max": null, "min": null, "period": null, "term": null}, "salary_visible": false, "title_keywords": ["data analyst"], "responsibilities": ["warehousing", "visualization", "data", "cleansing", "systems", "implementation", "design", "testing", "communication", "maintain", "executing", "databases", "banking", "plans", "planning"], "requirements": {"degrees": ["degree holder"], "majors": ["engineering", "computer science"], "languages": [], "language_level": [], "hard_skills": ["qlikview", "analytical skill", "data analytics", "tableau", "sql", "databases", "business intelligence"], "soft_skills": ["analytical skill", "learning", "presentation", "communication and interpersonal skills"], "languages_combined": []}, "experience_required": {"duration": ["3-5 years"], "field": ["sql", "banking industry", "business"]}}, {"job_id": "100003009043066", "location_code": "hk", "company": "Pinpoint Asia Limited", "job_title": "Digital IT Business Analyst - Wealth Management", "description": "Our client, a leading bank, is looking for a Digital IT Business Analyst to drive their strategic project and business analysis functions particularly for their wealth management business. The selected candidate will be leading the next-generation wealth management solutions for the bank.\n\nResponsibilities:\n\nWork with the business partners including technology, operations, and legal to collect user requirements and perform business analysis.\nBuild product requirement specifications in maximizing the values and create the best customer value.\nDefine business requirements with the stakeholders. Perform business analysis, user story, and define the workflow. Provide recommendations on process enhancements and systems upgrades.\nManage end-to-end project business analysis including feasibility study, requirement analysis, UAT, and implementation support.\nBuild a strong relationship with business leaders and decision-makers. Establish user cases and solution plans in achieving the business objectives.\nManage system testing, UAT, implementations, and post-implementation evaluation.\nRequirements:\n\nUniversity graduate with a Bachelors Degree preferably in Business, Finance, IT or other related disciplines\nProven experience in participating in digital-related projects in the banking and finance space.\nExperience in managing end-to-end business analysis with business stakeholders.\nPrivate / Retail Banking or Wealth Asset Management experience is preferred.\nGreat knowledge of the business process and change management.\nExperience in data analytics software, Jira, Confluence, and Tableau is a big plus\nStrong interpersonal skills with different senior stakeholders.\nExcellent communication and interpersonal skills.\nFluency in verbal and written Chinese and English communications is essential.\n\nIf this outstanding opportunity sounds like your next career move, please send your resume in Word format to Danny Kwan at resume(at)pinpointasia(dot)com and put Digital IT Business Analyst - Wealth Management in the subject header.\n\nData provided is for recruitment purposes only.", "employment_types": ["Full Time"], "selling_points": ["Major Bank", "Private Banking Wealth Biz", "Fast growing firm"], "locations": ["Not Specified"], "categories": ["Banking / Finance", "Private Banking", "Information Technology (IT)", "Product Management / Business Analyst", "Technical / Functional Consulting"], "post_time": "2022-01-12T10:02:59Z", "salary": {"currency": "HKD", "max": 69999, "min": 45000, "period": "monthly", "term": null}, "salary_visible": true, "title_keywords": ["wealth management", "business analyst"], "responsibilities": ["uat", "upgrades", "operations", "analysis", "systems", "implementation", "testing", "specifications", "provide recommendations", "evaluation", "business analysis", "plans"], "requirements": {"degrees": ["university graduate", "degree"], "majors": ["related disciplines", "finance", "business", "it"], "languages": ["english", "chinese"], "language_level": ["fluency"], "hard_skills": ["plus", "data analytics", "analysis", "word", "tableau"], "soft_skills": ["communication and interpersonal skills", "interpersonal skills"], "languages_combined": [{"language": "english", "language_level": ["fluency"]}, {"language": "chinese", "language_level": ["fluency"]}]}, "experience_required": {"duration": [], "field": ["related", "finance", "retail banking", "business", "banking", "business analysis", "digital", "asset management"]}}, {"job_id": "100003009051070", "location_code": "hk", "company": "IT Solutions Ltd.", "job_title": "IT Business Analyst / Senior Business Analyst (Life Insurance) - Major Bank", "description": "We are searching on behalf of a major bank for\u00a0IT Business Analyst/ Senior Business Analyst\u00a0to work on\u00a0Life Insurance System Projects\u00a0in a\u00a0Major Bank.\n\nResponsibilities:\n\nPerform business analysis and user requirement studies for various banking systems\nAct as the key interface between business users and technical developers\nGuide technical developers to provide a business solution\nFormulate Test Plans and conduct User Acceptance Test\nPrepare system documentation such as requirements specifications\nManage IT project implementation and testing\u00a0\n\nRequirements:\n\n\nDegree in Computer Science, Actuarial Science, Finance or Accounting or IT related discipline\nSolid working experience in Insurance Company or Banking Industry\nGood knowledge in Life Insurance Products\nGood communication skill with business users\nBenefits:\nAttractive remuneration will be offered to the successful candidates.\nExcellent opportunity to further develop your professional skills in working on a major Financial Banking Project in a\u00a0major bank.\n\nIf you are interested, please send your resume in MS Word format, specifying your availability, current and expected salaries to:\n\njobs @itsolutions.com.hk\n\nor\n\nPlease click the Apply Now button and attach your cv in MS Word Format, specifying your availability, current and expected salaries.\n\nPersonal data collected will be used for recruitment purposes only.\n\nIT Solutions Ltd.\nSuite 2102, 21st Floor\nLucky Building\n39 Wellington Street\nCentral, Hong Kong\n\n(P.S.\u00a0 We do not process applications from overseas for this position)", "employment_types": ["Full Time"], "selling_points": ["Business Analysis + Project Management", "Various Insurance System Project Exposure", "Good Career Prospect in Major Bank"], "locations": ["Tai Koo"], "categories": ["Banking / Finance", "Corporate Banking", "Information Technology (IT)", "IT Project Management / Team Lead", "Product Management / Business Analyst"], "post_time": "2022-01-15T01:44:49Z", "salary": {"currency": "HKD", "max": 54999, "min": 20000, "period": "monthly", "term": null}, "salary_visible": true, "title_keywords": ["senior business analyst", "business analyst"], "responsibilities": ["user requirement", "system documentation", "systems", "testing", "specifications", "banking", "business analysis", "plans", "it project implementation"], "requirements": {"degrees": ["degree"], "majors": ["actuarial science", "finance", "it", "computer science", "accounting"], "languages": [], "language_level": [], "hard_skills": [], "soft_skills": ["communication skill"], "languages_combined": []}, "experience_required": {"duration": [], "field": ["banking industry", "insurance"]}}, {"job_id": "100003009028589", "location_code": "hk", "company": "Legislative Council Secretariat", "job_title": "Information Technology Officer \u8cc7\u8a0a\u79d1\u6280\u4e3b\u4efb", "description": "Main duties\n\nThe main duties of an Information Technology Officer include:\n\n(a) managing the daily operation and helpdesk support of various information systems and electronic systems including email system / file and print system / computer workstation / IT security system / network infrastructure;\u00a0\n(b)\u00a0carrying out information system development with tasks including system analysis, design, programming, implementation, integration, deployment, testing, procurement, technology research, documentation and user training;\n(c) assisting in the preparation of funding and budget proposals;\n(d) maintaining information systems and electronic systems; and\n(e) monitoring the quality of services and the performance of outsourced vendors.\nThe appointee will be required to work irregular hours subject to operational needs.\n\nEntry requirements\n\nCandidates should:\n\n(a) have a recognized university degree in electronic engineering / computer engineering / computer science, or equivalent;\n(b) have at least six years\u2019\u00a0relevant and hands-on work experience in planning, design,\u00a0application\u00a0development, programming, implementation, installation, integration, testing, maintenance and operation of electronic systems / information systems\u00a0Note 1\u00a0;\n(c) have excellent command of written and spoken Chinese and English; and\n(d) possess very strong analytical, communication, negotiation and supervisory skills, and be able to lead junior team members to deliver timely and quality services for electronic systems / information systems.\n\nNote 1\u00a0\u00a0e.g. Microsoft Windows Server 2016/2019, software development technologies such as Microsoft SQL Servers 2016/2019 databases, JavaScript, React, C#, Web API, ASP.NET, HTML5 and CSS3.\n\nPreference will be given to those who possess the following information technology professional certifications: MCSD/MCSE/MCSA.\n\nThe Secretariat may devise further criteria to shortlist applicants.\n\nRemuneration\n\nThe starting salary is $58,635 per month, increasing by five annual increments to $73,775.\u00a0 There is also a monthly cash allowance for the rank of Information Technology Officer (the current rate is $1,110 per month).\u00a0 The successful candidate will be appointed on three-year agreement terms subject to renewal upon satisfactory completion of service, at which the appointee will be eligible for an end-of-agreement gratuity.\u00a0 The gratuity, when added to the employer\u2019s contribution to a Mandatory Provident Fund Scheme, is equal to 15% of the total basic salary drawn during the agreement period.\u00a0 Fringe benefits include paid leave as well as medical and dental benefits.\n\nApplication\u00a0\n\nApplications should be sent directly to Human Resources Office, Legislative Council Secretariat, Legislative Council Complex, 1 Legislative Council Road, Central, Hong Kong on or before 31 January 2022.Note 2\u00a0 The position\u00a0applied for should be indicated on the envelope, and an email address should also be provided in your application.\u00a0 Shortlisted applicants will be notified by email or by phone.\u00a0 All personal data provided will be treated in strict confidence.\u00a0 Applicants not invited for interview within eight weeks from the closing date may assume their applications unsuccessful.\n(A standard application form may be downloaded from the LegCo Website (http://www.legco.gov.hk))\n\nAs an Equal Opportunities Employer, The Legislative Council Commission is committed to ensuring that there is no discrimination in employment with the Secretariat.\u00a0 The post advertised is open to all applicants meeting the basic entry requirements irrespective of their disability, sex, marital status, pregnancy, age, family status, sexual orientation and race.\n\nNote 2\u00a0Please note that the Secretariat has not authorized any employment agencies or third-party organizations to receive applications on behalf of the Secretariat.\n\n\u4e3b\u8981\u8077\u8cac\n\n\u8cc7\u8a0a\u79d1\u6280\u4e3b\u4efb\u7684\u4e3b\u8981\u8077\u8cac\u5305\u62ec\uff1a\n\n(a) \u7ba1\u7406\u5404\u7a2e\u8cc7\u8a0a\u7cfb\u7d71\u548c\u96fb\u5b50\u7cfb\u7d71(\u5305\u62ec\u96fb\u90f5\u7cfb\u7d71 / \u6a94\u6848\u53ca\u5217\u5370\u7cfb\u7d71 / \u96fb\u8166\u5de5\u4f5c\u7ad9 / \u8cc7\u8a0a\u79d1\u6280\u4fdd\u5b89\u7cfb\u7d71 / \u7db2\u7d61\u57fa\u790e\u8a2d\u65bd)\u7684\u65e5\u5e38\u904b\u4f5c\u548c\u6551\u52a9\u53f0\u652f\u63f4\uff1b\n(b) \u958b\u767c\u8cc7\u8a0a\u7cfb\u7d71\uff0c\u5de5\u4f5c\u5305\u62ec\u7cfb\u7d71\u5206\u6790\u3001\u8a2d\u8a08\u3001\u7de8\u7a0b\u3001\u63a8\u884c\u3001\u6574\u5408\u3001\u8abf\u914d\u3001\u6e2c\u8a66\u3001\u63a1\u8cfc\u3001\u6280\u8853\u7814\u7a76\u3001\u6587\u4ef6\u7de8\u88fd\u548c\u7528\u6236\u57f9\u8a13\uff1b\n(c) \u5354\u52a9\u64ec\u5099\u7533\u8acb\u64a5\u6b3e\u548c\u9810\u7b97\u5efa\u8b70\uff1b\n(d) \u7dad\u6301\u8cc7\u8a0a\u7cfb\u7d71\u548c\u96fb\u5b50\u7cfb\u7d71\uff1b\u53ca\n(e) \u76e3\u5bdf\u5916\u5224\u7522\u54c1\u548c\u670d\u52d9\u63d0\u4f9b\u8005\u7684\u670d\u52d9\u8cea\u7d20\u548c\u8868\u73fe\u3002\n\n\u53d7\u8058\u4eba\u5c07\u9808\u56e0\u61c9\u904b\u4f5c\u9700\u8981\u800c\u4e0d\u5b9a\u6642\u5de5\u4f5c\u3002\n\n\u5165\u8077\u689d\u4ef6\n\n\u61c9\u5fb5\u8005\u61c9\uff1a\n\n(a) \u6301\u6709\u96fb\u5b50\u5de5\u7a0b / \u96fb\u8166\u5de5\u7a0b / \u96fb\u8166\u79d1\u5b78\u7684\u8a8d\u53ef\u5927\u5b78\u5b78\u4f4d\uff0c\u6216\u5177\u5099\u540c\u7b49\u5b78\u6b77\uff1b\n(b) \u5177\u5099\u6700\u5c116\u5e74\u76f8\u95dc\u53ca\u5be6\u969b\u9032\u884c\u4e0b\u8ff0\u5de5\u4f5c\u7684\u7d93\u9a57\uff1a\u7b56\u5283\u3001\u8a2d\u8a08\u3001\u61c9\u7528\u7a0b\u5f0f\u958b\u767c\u3001\u7de8\u7a0b\u3001\u63a8\u884c\u3001\u5b89\u88dd\u3001\u6574\u5408\u3001\u6e2c\u8a66\u3001\u7dad\u6301\u53ca\u64cd\u4f5c\u96fb\u5b50\u7cfb\u7d71 / \u8cc7\u8a0a\u7cfb\u7d71\u200d\u00a0\u8a3b1\uff1b\n(c) \u5177\u5099\u6975\u4f73\u7684\u4e2d\u3001\u82f1\u6587\u8b1b\u5beb\u80fd\u529b\uff1b\u53ca\n(d) \u5177\u5099\u975e\u5e38\u826f\u597d\u7684\u5206\u6790\u3001\u6e9d\u901a\u3001\u5546\u8ac7\u548c\u7763\u5c0e\u6280\u5de7\uff0c\u4e26\u80fd\u9818\u5c0e\u5718\u968a\u521d\u7d1a\u6210\u54e1\u63d0\u4f9b\u9069\u6642\u53ca\u512a\u8cea\u7684\u96fb\u5b50\u7cfb\u7d71 / \u8cc7\u8a0a\u7cfb\u7d71\u670d\u52d9\u3002\n\n\u00a0\u8a3b1\u00a0 \u4f8b\u5982Microsoft\u00a0Windows Server 2016/2019\u3001\u8edf\u4ef6\u958b\u767c\u6280\u8853(\u5982Microsoft SQL Servers 2016/2019 \u6578\u64da\u5eab\u3001 JavaScript\u3001React\u3001 C# \u3001Web API\u3001ASP.NET\u3001HTML5\u53caCSS3)\u3002\n\n\u5177\u5099\u4e0b\u8ff0\u8cc7\u8a0a\u79d1\u6280\u5c08\u696d\u8b49\u66f8\u7684\u4eba\u58eb\u6703\u7372\u512a\u5148\u8003\u616e\uff1aMCSD/MCSE/MCSA.\n\n\u79d8\u66f8\u8655\u53ef\u5236\u8a02\u9032\u4e00\u6b65\u7684\u6e96\u5247\uff0c\u4ee5\u9078\u51fa\u521d\u6b65\u5165\u9078\u7684\u7533\u8acb\u4eba\u3002\n\n\u85aa\u916c\n\n\u5165\u8077\u85aa\u916c\u70ba\u6bcf\u670858,635\u5143\uff0c\u4e26\u63095\u500b\u6309\u5e74\u589e\u85aa\u984d\u589e\u81f373,775\u5143\uff0c\u53e6\u6709\u70ba\u8cc7\u8a0a\u79d1\u6280\u4e3b\u4efb\u8077\u7d1a\u800c\u8a2d\u7684\u6bcf\u6708\u73fe\u91d1\u6d25\u8cbc(\u73fe\u6642\u7684\u6d25\u8cbc\u984d\u70ba\u6bcf\u67081,110\u5143)\u3002\u6210\u529f\u53d7\u8058\u4eba\u58eb\u6703\u6309\u5408\u7d04\u689d\u6b3e\u53d7\u8058\uff0c\u70ba\u671f3\u5e74\uff0c\u5018\u5b8c\u6210\u670d\u52d9\u671f\u800c\u5de5\u4f5c\u8868\u73fe\u826f\u597d\uff0c\u53ef\u7372\u7e8c\u7d04\uff0c\u4e26\u6703\u7372\u5f97\u4e00\u7b46\u7d04\u6eff\u916c\u91d1\uff0c\u5176\u6b3e\u984d\u52a0\u4e0a\u50f1\u4e3b\u5728\u5f37\u5236\u6027\u516c\u7a4d\u91d1\u8a08\u5283\u4e0b\u6240\u4f5c\u7684\u4f9b\u6b3e\uff0c\u76f8\u7b49\u65bc\u5408\u7d04\u671f\u5167\u6240\u5f97\u5e95\u85aa\u7e3d\u984d\u768415%\u3002\u9644\u5e36\u798f\u5229\u5305\u62ec\u6709\u85aa\u5047\u671f\u3001\u91ab\u7642\u53ca\u7259\u79d1\u798f\u5229\u3002\n\n\u7533\u8acb\n\n\u8acb\u65bc2022\u5e741\u670831\u65e5\u6216\u8a72\u65e5\u524d\uff0c\u5c07\u7533\u8acb\u76f4\u63a5\u5bc4\u9054\u9999\u6e2f\u4e2d\u5340\u7acb\u6cd5\u6703\u90531\u865f\u7acb\u6cd5\u6703\u7d9c\u5408\u5927\u6a13\u7acb\u6cd5\u6703\u79d8\u66f8\u8655\u4eba\u529b\u8cc7\u6e90\u7d44\u3002\u8a3b2\u00a0\u7533\u8acb\u4eba\u61c9\u5728\u4fe1\u5c01\u9762\u8a3b\u660e\u7533\u8acb\u8077\u4f4d\u7684\u540d\u7a31\uff0c\u4e26\u5728\u7533\u8acb\u6587\u4ef6\u4e2d\u63d0\u4f9b\u96fb\u90f5\u5730\u5740\u3002\u79d8\u66f8\u8655\u5c07\u4ee5\u96fb\u90f5\u6216\u96fb\u8a71\u65b9\u5f0f\u901a\u77e5\u521d\u6b65\u5165\u9078\u7684\u7533\u8acb\u4eba\u3002\u7533\u8acb\u4eba\u63d0\u4f9b\u7684\u6240\u6709\u500b\u4eba\u8cc7\u6599\u5747\u6703\u56b4\u52a0\u4fdd\u5bc6\u3002\u7533\u8acb\u4eba\u5982\u65bc\u622a\u6b62\u65e5\u671f\u5f8c8\u661f\u671f\u5167\u672a\u7372\u9080\u53c3\u52a0\u9762\u8a66\uff0c\u53ef\u7576\u4f5c\u5176\u7533\u8acb\u4e0d\u6210\u529f\u3002\n(\u6a19\u6e96\u7533\u8acb\u8868\u683c\u53ef\u65bc\u7acb\u6cd5\u6703\u7db2\u7ad9(http://www.legco.gov.hk)\u4e0b\u8f09)\n\n\u7acb\u6cd5\u6703\u884c\u653f\u7ba1\u7406\u59d4\u54e1\u6703\u70ba\u5e73\u7b49\u6a5f\u6703\u50f1\u4e3b\uff0c\u81f4\u529b\u78ba\u4fdd\u79d8\u66f8\u8655\u6c92\u6709\u5c31\u696d\u65b9\u9762\u7684\u6b67\u8996\u3002\u6240\u6709\u7b26\u5408\u57fa\u672c\u5165\u8077\u689d\u4ef6\u7684\u4eba\u58eb\uff0c\u4e0d\u8ad6\u5176\u6b98\u75be\u3001\u6027\u5225\u3001\u5a5a\u59fb\u72c0\u6cc1\u3001\u61f7\u5b55\u8207\u5426\u3001\u5e74\u9f61\u3001\u5bb6\u5ead\u5d17\u4f4d\u3001\u6027\u50be\u5411\u53ca\u7a2e\u65cf\uff0c\u5747\u53ef\u7533\u8acb\u6b64\u8077\u4f4d\u3002\n\n\u8a3b2\u00a0\u00a0\u8acb\u6ce8\u610f\uff0c\u79d8\u66f8\u8655\u4e26\u7121\u6388\u6b0a\u4efb\u4f55\u8077\u696d\u4ecb\u7d39\u6240\u6216\u7b2c\u4e09\u65b9\u6a5f\u69cb\u4ee3\u8868\u672c\u8655\u63a5\u6536\u7533\u8acb\u3002\n", "employment_types": ["Full Time", "Contract"], "selling_points": [], "locations": ["Admiralty"], "categories": ["Information Technology (IT)", "Product Management / Business Analyst", "Software Development", "Network & System"], "post_time": "2022-01-14T03:04:23Z", "salary": {"currency": null, "max": null, "min": null, "period": "monthly", "term": null}, "salary_visible": false, "title_keywords": ["information technology officer"], "responsibilities": ["network infrastructure", "maintaining", "analysis", "systems", "daily operation", "implementation", "design", "testing", "budget", "monitoring", "quality", "documentation"], "requirements": {"degrees": ["university degree"], "majors": ["computer engineering", "engineering", "computer science"], "languages": ["english", "chinese"], "language_level": ["excellent"], "hard_skills": ["mcse", "basic", "servers", "maintenance", "react", "mcsa", "scheme", "sql", "c", "javascript", "web api", "programming", "databases", "integration", "windows server", "c#"], "soft_skills": ["communication", "hands-on", "negotiation", "timely"], "languages_combined": [{"language": "english", "language_level": ["excellent"]}, {"language": "chinese", "language_level": ["excellent"]}]}, "experience_required": {"duration": ["at least six years"], "field": ["installation", "maintenance", "design", "testing", "operation", "programming", "application development", "planning"]}}, {"job_id": "100003009038414", "location_code": "hk", "company": "Sompo Insurance (Hong Kong) Company Limited", "job_title": "Application Support / Business Analyst (IT)", "description": "Responsibilities\n\n\nResponsible for application system requirements analysis, design and planning, development management and implementation.\nCollaborate with external development resources to deliver application software platforms in highest quality and stability.\nCollaborate with other team members and stakeholders.\nConduct systems testing to ensure the developed applications are in good quality.\nProvide on-going application systems support.\nUndertake Ad hoc tasks as assigned\n\nRequirements\n\n\nDegree holder in Business, Information Systems, Computer Science or equivalent\nWith strong analytical skills and able to liaise with users at different levels effectively\nBasic knowledge of General insurance operation is preferable\n3 year's relevant experience in supporting is an added advantage\nExposure to technical skill, e.g. SQL query, Windows scripting, WAMP, Web-based application development is an advantage\nExperience in dealing with end users and system vendors, problem solving and troubleshooting production system issue is preferable\nResponsible, reliable, strong interpersonal and communication skills\nGood command of written and spoken English and Cantonese\n\nWe offer 5-day week and competitive remuneration package commensurate with qualification and experience.\u00a0 Please send full resume with details of current and expected salary to HR Department by clicking \"Apply Now\".\n\nPersonal data will be used for recruitment purpose only.", "employment_types": ["Full Time", "Permanent"], "selling_points": ["Provide on-going application systems support", "Relevant experience in supporting is an advantage", "Challenging work environment"], "locations": ["Quarry Bay"], "categories": ["Professional Services", "Business Analysis / Data Analysis", "Information Technology (IT)", "Application Specialist - Software", "Product Management / Business Analyst"], "post_time": "2022-01-11T16:01:44Z", "salary": {"currency": null, "max": null, "min": null, "period": "monthly", "term": null}, "salary_visible": false, "title_keywords": ["application support", "business analyst"], "responsibilities": ["collaborate with", "management", "software", "analysis", "systems", "quality", "implementation", "application system", "design", "testing", "ad hoc tasks", "application systems", "planning"], "requirements": {"degrees": ["degree holder"], "majors": ["business", "computer science"], "languages": ["cantonese", "english"], "language_level": ["good command"], "hard_skills": ["basic", "web", "analytical skills", "sql", "problem solving"], "soft_skills": ["communication skills", "responsible", "troubleshooting", "analytical skills", "problem solving", "reliable", "technical skill", "interpersonal"], "languages_combined": [{"language": "cantonese", "language_level": ["good command"]}, {"language": "english", "language_level": ["good command"]}]}, "experience_required": {"duration": ["3 year"], "field": ["relevant experience", "troubleshooting"]}}, {"job_id": "100003009038008", "location_code": "hk", "company": "Lane Crawford (Hong Kong) Limited", "job_title": "Business Analyst", "description": "\u201cTo Own the Global Asian Luxury Customer\u201d\nFounded in 1850, Lane Crawford is an iconic, luxury department store offering a seamless shopping experience in stores and online.\nAs the most talked-about lifestyle destination in Asia, Lane Crawford presents a unique global edit of more than 800 coveted international brands across Womenswear, Menswear, Shoes and Accessories, Cosmetics, Fine Jewellery and Home and Lifestyle. LaneCrawford.com and each store is an inspiring space to spend time and be immersed in the world of fashion, art, design and culture.\nProviding market leading services, Lane Crawford offers an unparalleled luxury lifestyle experience. Across creative programmes and award-winning visual merchandising, every customer experience is unique, including personalised services such as Concierge, Personal Styling, Cosmetics Concierge, and online order collection and returns in store.\n____________________________________________________________\n\n\n\nJob Purpose:\u00a0 \u00a0\u00a0\u00a0\u00a0\u00a0\u00a0\u00a0\u00a0\u00a0\u00a0\n\u201cTo gather and understand the business objective for all projects. And support strategic and operation optimization thinking with business process knowledge, and other methodologies to quantitatively analyse issues and drive technology solution to transform our business and process.\u201d\nKey Accountabilities:\nIn addition to following Lane Crawford\u2019s policies and procedures, key accountabilities include, but are not limited to:\nResponsibilities:\nUnderstand, validate, and support business group\u2019s objectives, change requests and issues\nPerform business process analysis in documenting AS-IS and TO-BE process\nConduct testing and feasibility studies to suggest enhancement approaches\nHighlight any potential issues or incompatibility of proposed designs with existing systems, and suggest alternative approaches to align current and future solutions\nDocument business and solution requirements in the TO-BE processes to allow development teams with understanding of the requirements and expected behaviour, acting as the first point-of-contact for clarification\nProvide Delivery Support in aligning on delivery priority, deployment schedule with development team, prepare release note or training materials to business, and to ensure seamless knowledge and support transfer to Service Desk team\nProvide Post-Implementation support by responsible for incoming questions or issues raised after project deployment\nRequirements:\nDegree in Information System or related disciplines\n2-3 years relevant experience, preferably in Retail or Supply Chain related industry\nExperience in ERP solutions or related\nGood understanding in POS and Digital\nExperience in process improvement and solution design\nSound understanding on Project management process/governance, IT application development life-cycle, good practices, quality management techniques\nGood in analysis and problem solving\nSelf-motivated, independent, responsible and detail-oriented\nWell Team-player and work well under pressure\nGood communication and relationship building\nStrong command of spoken and written skills in English, Cantonese and Mandarin\nA competitive remuneration package with career advancement opportunity will be offered to the right candidate. If you desire an exciting and rewarding career, please send your cover letter and full resume with\u00a0current and expected salary\u00a0via \"Apply Now\"\n\nAll information provided will be treated in strict confidence and used for recruitment purposes only.", "employment_types": ["Full Time", "Permanent"], "selling_points": ["Degree in Information System", "Experience in ERP solutions", "Good understanding in POS and Digital"], "locations": ["Southern Area"], "categories": ["Information Technology (IT)", "IT Project Management / Team Lead", "Product Management / Business Analyst", "Others"], "post_time": "2022-01-11T04:33:43Z", "salary": {"currency": null, "max": null, "min": null, "period": null, "term": null}, "salary_visible": false, "title_keywords": ["business analyst"], "responsibilities": ["analysis", "systems", "teams", "clarification", "implementation", "testing", "business process", "contact", "schedule"], "requirements": {"degrees": ["degree"], "majors": ["related disciplines"], "languages": ["cantonese", "english", "mandarin"], "language_level": [], "hard_skills": ["pos", "analysis", "information system", "erp", "problem solving", "project management"], "soft_skills": ["self-motivated", "confidence", "independent", "under pressure", "responsible", "team-player", "detail-oriented", "problem solving", "project management", "communication"], "languages_combined": [{"language": "cantonese", "language_level": []}, {"language": "english", "language_level": []}, {"language": "mandarin", "language_level": []}]}, "experience_required": {"duration": ["2-3 years"], "field": ["related", "supply chain", "design", "relevant experience", "retail"]}}, {"job_id": "100003009042517", "location_code": "hk", "company": "ALS International Limited", "job_title": "Senior Business Analyst", "description": "Summary\nOur client is a European fashion company with Hong Kong being their sourcing office. Reporting to the Application Lead, this role will liaise with users to carry out business analysis duties, conduct data analysis and provide project support.\u00a0\n\nResponsibilities\n\nOversee and assist in various tasks of project management for local & global IT projects\nLiaise with users to gather requirement and draft specification\nMonitor project progress as well as control budget and schedule\nCreate and maintain documentation\nProvide systems support to users on demand\nConduct UAT and provide users training\n\nRequirements\n\nHolder of Higher Diploma in Computer Science, Information Management, Supply Chain Management or relevant discipline\u00a0\nMinimum 3 years of working experience with relevant track record handling business analysis duties\u00a0\u00a0\nKnowledge of data analysis using SQL and MS Office applications\u00a0\nFluent communication, both written and spoken, in English and Chinese\u00a0\n\n\nInterested candidates should send their resume in Word file, please click \"APPLY NOW\" below to contact Kelvin Lau\u00a0for further information.", "employment_types": ["Full Time"], "selling_points": [], "locations": ["Central"], "categories": ["Information Technology (IT)", "Support", "Product Management / Business Analyst", "Technical / Functional Consulting"], "post_time": "2022-01-12T07:50:56Z", "salary": {"currency": null, "max": null, "min": null, "period": "monthly", "term": null}, "salary_visible": false, "title_keywords": ["senior business analyst"], "responsibilities": ["control", "monitor project progress", "maintain documentation", "uat", "budget", "systems", "project management", "schedule", "liaise with"], "requirements": {"degrees": ["diploma"], "majors": ["computer science"], "languages": ["english", "chinese"], "language_level": ["fluent"], "hard_skills": ["sql", "analysis", "ms office"], "soft_skills": ["communication"], "languages_combined": [{"language": "english", "language_level": ["fluent"]}, {"language": "chinese", "language_level": ["fluent"]}]}, "experience_required": {"duration": ["minimum 3 years"], "field": ["business analysis"]}}, {"job_id": "100003009044860", "location_code": "hk", "company": "Wellesley Associates Limited", "job_title": "IT Project Specialist - Premium MNC (European Brand) - ERP/SQL - Perm - 35K + Bonus", "description": "Background: My client is one of the Europe\u2019s leading premium brand and is now looking for an IT Project Specialist to join the APAC team.\u00a0\n\nJob Duties:\u00a0\n\nAssist the Regional IT manager to support the implementation of projects, and day to day business tasks within the region\nInsure the application of global guidelines.\nSupport day to day business requirement\nTake the responsibility of key ERP software, and in close coordination with the Supply Chain department.\nManage the B2B software and ensure its setup maintenance\nIn coordination with the central team, support user with the wholesale application.\nSupport the front office domain via ERP and become the key person to provide user training, assist day to day usage, and respect of best practices.\nMaintain Finance interface, using SQL language.\nLook after e-commerce and proximity warehouse interfaces and liaise with vendors to support\u00a0\nRequirements:\u00a0\n\nDegree holder in computer science or other relevant discipline\n5 years of experience working as an IT Project Specialist/Coordinator/Business Analyst under a multi-regions environment\nPossess good SQL database, and SQL query knowledge\nGood to have experience in Retail/ Warehouse ERP Software implementation & supporting experience\nPossess analytical and structured mindset with excellent problem-solving skills\u00a0\nExcellent communication and management skills to interact with users\nGood inter-personal relationship skills\nAbility to work in a fast-paced and highly dynamic environment with a strong sense of urgency and results-orientation\nSpeaks fluent English and Chinese\n\nCandidates who are interested in this opportunity, please apply directly by submitting your latest CV including current and expecting salary. Please note that only shortlisted candidates will be notified.\u00a0", "employment_types": ["Full Time"], "selling_points": ["IT Project Specialist", "ERP Software/ SQL Database/ SQL Query", "Retail MNC/ Western Culture"], "locations": ["Not Specified"], "categories": ["Information Technology (IT)", "IT Project Management / Team Lead", "Support", "Product Management / Business Analyst"], "post_time": "2022-01-13T06:28:18Z", "salary": {"currency": null, "max": null, "min": null, "period": "monthly", "term": null}, "salary_visible": false, "title_keywords": ["specialist"], "responsibilities": ["guidelines", "implementation of projects"], "requirements": {"degrees": ["degree holder"], "majors": ["computer science"], "languages": ["english", "chinese"], "language_level": ["fluent"], "hard_skills": ["maintenance", "e-commerce", "erp", "sql", "dynamic", "problem-solving skills"], "soft_skills": ["dynamic environment", "inter-personal", "urgency", "interested in", "communication", "coordination", "problem-solving skills", "structured"], "languages_combined": [{"language": "english", "language_level": ["fluent"]}, {"language": "chinese", "language_level": ["fluent"]}]}, "experience_required": {"duration": ["5 years"], "field": ["business", "it", "retail"]}}, {"job_id": "100003009040258", "location_code": "hk", "company": "iFAST Financial (HK) Limited", "job_title": "Business Analyst", "description": "Responsibilities:\n\nWork closely with the IT application team throughout the system development life cycle to deliver product features and solutions;\nUnderstand the business objectives and rationales behind high-level product features, analyze and translate them into detailed user specifications of projects;\nCoordinate with users in integration and testing of new enhancements;\nWork closely with the business/ product owners to influence and understand the product vision, strategic product direction, and product roadmap;\nAct as the key interface between the IT application team, relevant departments, and external vendors;\nKeep abreast of the market, suggest and propose new business initiatives.\n\n\u00a0Requirements:\n\nBachelor degree in Computer Science, IT, Business Information Systems or related field;\n1-2 years of relevant working experience is required, preferably in the financial industry;\u00a0\nExperience working in an Agile/Scrum software development environment a plus;\nKnowledge of SQL / automated testing tools is added advantage;\nPassionate about supporting development of IT systems and applications;\nStrong interpersonal skills and ability to work in a team;\nAbility to multi-task and manage in a fast-paced, dynamic environment;\nGood command of written and spoken English, Cantonese and Mandarin.\n\n\u00a0Our offer:\u00a0\n\nAttractive remuneration;\nCareer development prospect;\n5-day working week;\n21+ days Annual Leave for all staff;\nPerformance bonus and company shares;\nMedical, dental, life insurance;\nStaff discount on securities tranactions;\nTraining allowance and monthly sports allowance.\n\nInterested parties please send your full resume by clicking \"APPLY NOW\".\nOur company is an equal opportunities employer and welcome application from all qualified candidates.\u00a0Information provided will be treated with strict confidential and be used for the purpose of selection only.\u00a0Applicants who are not invited for interview within 10 weeks may consider their applications unsuccessful. Personal data of unsuccessful applicants will be destroyed within 12 months.", "employment_types": ["Full Time", "Permanent"], "selling_points": ["Exposure to new business implementation", "Regional exposure on Fintech platform development", "21+ days Annual Leave for all staff"], "locations": ["Central"], "categories": ["Information Technology (IT)", "IT Project Management / Team Lead", "Product Management / Business Analyst", "Testing / QA"], "post_time": "2022-01-12T02:02:09Z", "salary": {"currency": null, "max": null, "min": null, "period": "monthly", "term": null}, "salary_visible": false, "title_keywords": ["business analyst"], "responsibilities": ["business initiatives", "specifications", "coordinate with", "testing"], "requirements": {"degrees": ["degree", "bachelor"], "majors": ["business", "it", "computer science"], "languages": ["cantonese", "english", "mandarin"], "language_level": ["good command"], "hard_skills": ["sql", "plus", "dynamic", "agile"], "soft_skills": ["dynamic environment", "multi-task", "agile", "interpersonal skills", "passionate about"], "languages_combined": [{"language": "cantonese", "language_level": ["good command"]}, {"language": "english", "language_level": ["good command"]}, {"language": "mandarin", "language_level": ["good command"]}]}, "experience_required": {"duration": ["1-2 years"], "field": ["financial industry", "relevant working experience", "software development"]}}, {"job_id": "100003009051271", "location_code": "hk", "company": "China Mobile International Limited", "job_title": "Assistant Product Manager, Data Center (Ref:CMIJD-0115-PMIDCHK)", "description": "Responsibilities:\n\nPrepare and manage product planning, strategies and development\nSupport existing and new product life-cycle,and all related management work, such as preparing product portfolios, P&L models, business forecasts, budget formulation, service improvement plan, contractual SLA details, MSA and sales order documentation, product workflow, etc.\nFormulate and implement pricing/promotion offer strategies and policies\nManage global partners, vendors and suppliers programs\nConduct market researches, prepare productstatus analysis reports and recommendations for management review, e.g. monthly P&L reports as well as provide product training and assist marketing events, etc.\nSupport important Sales activities, such as preparing Sales collateral materials and pre-sales solution\n\nRequirements:\n\nBachelor's degree or above in related disciplines\nMinimum 6 years of experience in Telecom and/or IDC industries\nSolid experience on product development and management\nExcellent teamwork skills, hardworking, self-motived and able to work under pressure\nProficiency in MS\u00a0 Office applications and Chinese Word Processing\nGood command of spoken and written Chinese and English, proficiency in Putonghua is an advantage\n\nCandidate with less experience will be considered as Senior Product Specialist.\n\nInterested parties please send your full resume with current & expected salary\u00a0by e-mail to\u00a0hr @ cmi.chinamobile.com.\u00a0 Please indicate the reference in the subject line.\n\nAll personal data provided will be used for consideration of your job application only.", "employment_types": ["Full Time", "Permanent"], "selling_points": ["IDC Sales and Presales", "Product Management", "Global deployments solution"], "locations": ["Tseung Kwan O"], "categories": ["Engineering", "Electrical / Electronics", "Telecommunication / Wireless / Radio", "Information Technology (IT)", "Product Management / Business Analyst"], "post_time": "2022-01-15T07:02:05Z", "salary": {"currency": null, "max": null, "min": null, "period": "monthly", "term": null}, "salary_visible": false, "title_keywords": ["assistant product manager"], "responsibilities": ["marketing events", "management", "sales activities", "analysis reports", "policies", "budget", "p&l", "reports", "plan", "documentation", "management review", "planning"], "requirements": {"degrees": ["degree or above", "bachelor"], "majors": ["related disciplines"], "languages": ["putonghua", "english", "chinese"], "language_level": ["advantage", "proficiency", "good command"], "hard_skills": ["chinese word processing", "office applications"], "soft_skills": ["teamwork", "hardworking", "work under pressure"], "languages_combined": [{"language": "putonghua", "language_level": ["proficiency", "advantage", "good command"]}, {"language": "english", "language_level": ["advantage", "good command"]}, {"language": "chinese", "language_level": ["proficiency", "advantage", "good command"]}]}, "experience_required": {"duration": ["minimum 6 years"], "field": ["product development", "management"]}}, {"job_id": "100003009038028", "location_code": "hk", "company": "Manulife (International) Limited", "job_title": "IT Business Analyst", "description": "Are you looking for a supportive, collaborative workplace with great teams and inspiring leaders? You\u2019ve come to the right place. We\u2019re looking for ambitious people who share our values and want to make every day better for people around the world. If this sounds like you, and the career below sounds exciting, we\u2019d like to hear from you.\nJob Description\nIT Business Analyst\nHong Kong\nThe Opportunity\nManulife HK is seeking a self-motivated IT Business Analyst, who is obsessed with delivering value, is forward-thinking, and improves business analysis process.\nWhat motivates you?\n\nYou obsess about customers, listen, engage and act for their benefit\u00a0\n\nYou think big, with curiosity to discover ways to use your agile mindset and enable business outcomes\u00a0\n\nYou thrive in teams, and enjoy getting things done together\n\nYou take ownership and build solutions, focusing on what matters\u00a0\n\nYou do what is right, work with integrity and speak up\n\nYou share your humanity, helping us build a diverse and inclusive work environment for everyone\u00a0\n\nWe are looking for someone with:\u00a0\n\nReview and analyze requests from various departments and value streams\n\nProduce user requirement documents and specifications, and mock-ups for proposed solution\n\nBuild consensus and facilitate discussion with related stakeholders, business partners and IT development teams\n\nParticipate in project planning from project initiation to closure and responsible for tracking requirement and testing progress\n\nAct as an internal business system area expert and champion\n\nProvide quality system training to business users\n\nDefine test strategy, construct test plan and manage testing team on test execution to ensure the end product meets the business objectives\n\nOwn, investigate and resolve system and project issues\n\nPlan and develop various reports to meet different business/regulatory needs, perform data analysis and integrity check\u00a0\n\nOn the job you will:\u00a0\n\nThorough understanding of individual insurance products, operations and processes\n\nExperience in life insurance policy admin system enhancement\n\nWell organized and attentive to details, flexible with working hours\n\nGood analytical and problem solving skills, and disciplined with project scheduling\n\nSelf initiated and have a strong drive to learn\n\nStrong PC skills including MS Word, Excel and good understanding of SQL\n\nAble to clearly articulate business processes and ideas verbally and in written English\n\nExperience and knowledge in complicate testing execution and support\n\nMinimum 5 years' work experience with insurance\n\nOur commitment to you\n\nOur mission; to be a part of making Decisions Easier and Lives Better\n\nA leadership team dedicated to your growth and success\u00a0\n\nA bold ambition and set of goals to be a leader in driving transformation in our industry\u00a0\n\nOur best. Every day.\u00a0\n\nLearn more about opportunities with us at www.manulife.com/en/careers/why-join-us.html\nEvery career at Manulife/John Hancock provides the opportunity to learn new skills and move your career forward. Ready to make an impact somewhere? What are you waiting for? Apply today.", "employment_types": ["Full Time", "Permanent"], "selling_points": ["Review and analyze requests from various", "Experience in life insurance policy", "Self initiated and have a strong drive to learn"], "locations": ["Not Specified"], "categories": ["Information Technology (IT)", "Product Management / Business Analyst", "Others"], "post_time": "2022-01-11T04:38:55Z", "salary": {"currency": null, "max": null, "min": null, "period": "monthly", "term": null}, "salary_visible": false, "title_keywords": ["business analyst"], "responsibilities": ["user requirement", "project planning", "ideas", "operations", "review", "teams", "mock-ups", "quality", "testing", "develop", "data analysis", "specifications", "reports", "project scheduling", "plan", "business analysis", "insurance", "tracking"], "requirements": {"degrees": [], "majors": [], "languages": ["english"], "language_level": [], "hard_skills": ["excel", "agile", "analysis", "html", "sql", "make", "problem solving skills", "pc skills", "ms word"], "soft_skills": ["flexible", "supportive", "self-motivated", "agile", "responsible", "attentive to details", "integrity", "collaborative", "well organized", "bold", "diverse", "analytical and problem solving skills", "inspiring", "thorough", "articulate", "leadership"], "languages_combined": [{"language": "english", "language_level": []}]}, "experience_required": {"duration": ["minimum 5 years"], "field": ["admin", "insurance", "testing"]}}, {"job_id": "100003009043098", "location_code": "hk", "company": "Captiare", "job_title": "Manager / Business Analyst - supply chain/ sourcing", "description": "In house regional role\nSupply chain/ sourcing system/ PLM/ ERP\nBusiness analysis and system integration\n\nOur client is a well-known company with strong presence in APAC region. Due to their additional headcount, they are now looking for the captioned position to join their team.\n\nYou will be responsible for getting user requirement, handling system integration for supply chain system, sourcing and PLM system. You will have to involve in ERP project delivery and roll out. You will have to communicate with various stakeholder across APAC.\n\nRequirements:\n\n\nBachelor degree of Information Technology or any related disciplines\nWith around 8-10 years of work experience, gained from MNC company, with regional exposure is a plus, gained from retail or apparel industry is a plus\nExperience in supply chain and sourcing system, with ERP project delivery and system integration experience are preferred\nGood command of Chinese and English\nGood communication skill and interpersonal skill", "employment_types": ["Full Time", "Permanent"], "selling_points": ["In house regional role", "Supply chain/ sourcing/ PLM/ ERP", "Business analysis and system integration"], "locations": ["Not Specified"], "categories": ["Information Technology (IT)", "IT Project Management / Team Lead", "Product Management / Business Analyst"], "post_time": "2022-01-12T09:48:43Z", "salary": {"currency": null, "max": null, "min": null, "period": "monthly", "term": null}, "salary_visible": false, "title_keywords": ["manager", "business analyst"], "responsibilities": ["business analysis", "user requirement", "communication", "communicate with"], "requirements": {"degrees": ["degree", "bachelor"], "majors": ["related disciplines", "information technology"], "languages": ["english", "chinese"], "language_level": ["good command"], "hard_skills": ["integration", "analysis", "erp", "plus"], "soft_skills": ["communication skill", "responsible", "interpersonal skill"], "languages_combined": [{"language": "english", "language_level": ["good command"]}, {"language": "chinese", "language_level": ["good command"]}]}, "experience_required": {"duration": ["8-10 years"], "field": ["supply chain", "retail"]}}, {"job_id": "100003009048001", "location_code": "hk", "company": "Fiducia Limited", "job_title": "ERP Functional Consultant (China, Hong Kong or Singapore)", "description": "We are looking for a high calibre professional to join our operation team!\n\nPrimary role purpose:\n\nThe ERP Team is responsible for the Microsoft Dynamics 365 Business Central platform at Fiducia Management Consultants. Business Central is used to run business processes across accounting, corporate and trade services, consulting and recruiting. Our talented team is experienced, collaborative, innovative and lots of fun to work with. Our mission is to enable our clients to get the most out of our applications.\n\nOur ERP-Team is accountable for the strategy, implementation & operation of our ERP technologies and journeys. Working with service managers and clients, they provide customer-centric solutions to evolving processes. Our services are at the heart of how Fiducia Management Consultants run the Finance and Accounting services as well as a critical enabler for the supply chain operations of our clients in Mainland China and APAC.\n\nThis is an exciting time to join our team. We are also about to embark on a major ERP Strategy to further grow our services. This will revolutionise ERP for our clients and internal users. Therefore, we are looking to augment our team of outstanding Functional Consultants who will be pivotal to delivering ambitious solutions within the current platform and contributing to shaping the new-direction ERP. It is a great opportunity to play a major role in this programme and develop the depth & breath of your experience. If you are a proactive and detail-oriented consultant with strong ability to communicate with our clients and have the capability to think both tactically & strategically, we would love to speak to you.\n\nYour focus will be the delivery of End to End Microsoft Dynamics 365 business solutions, that meet the business requirements and add business value. As a Functional Consultant in the ERP-team,\u00a0 you will use your expertise, experience, Dynamics365 skills and business process knowledge to design, develop, integrate, test and deploy solutions to help our business achieve its objectives.\n\nJob Description:\n\nAs a key member of the ERP Team you will ensure the design and realisation of functional solutions are fit for purpose and delivered against stated business requirements. You will collaborate with cross functional teams & business stakeholders to implement and oversee operational excellence in maintaining processes by the service units within Fiducia Management Consultants. Be able to identify & assess available technologies and recommend solution options according to the business requirements & drivers. You are expected to collaborate with clients, team members and service managers to clearly understand business journeys and requirements and how they can be simplified and optimised. You may serve as team member in some projects or Functional Team Lead on others; as such, you will work well in partnership with the team and be equally able to work independently. You will be able to do, teach & evangelise all things in the field of ERP and bring colleagues and stakeholders on the journey to best-of-class solutions.\n\n\n\nYour responsibilities:\n\nAbility to perform the role of Functional Consultant on Microsoft Dynamics365 Business Central, Enhancements and Projects including the facilitation of requirement gathering sessions.\nAbility to drive excellence in the delivery of support in this domain, partnering with our internal team and external partners, including successful knowledge transfer to this team and mentoring of partner colleagues.\nAbility to communicate effectively at all levels within the organisation, our implementation partners and pool of freelancers\nDesign and implement best practice business / Dynamics365 Business Central solutions appropriate to the requirements, business needs and strategic direction of the client and the organization\nManage and own enhancements and incidents through to completion adhering to Fiducia Management Consultants standards.\nTo keep up to date with Microsoft Dynamics 365 Business Central capabilities within the whole solution offering\nDelivery of complex integrated solutions\nPreparation of specifications, estimates and solution documentation to support work completed\nFostering and maintaining good relationships with clients and colleagues to meet expected customer service quality\nMay be required to coach and manage the other members within the team\nManaging third party suppliers and delivery of contracted work\nTaking ownership of continuous improvement within the ERP solution\n\nWho are we looking for:\n\nExperience of multiple, full lifecycle project implementations.\nExcellent experience in Microsoft Dynamics 365 Business Central functional configuration and technical support.\nExtensive experience in designing Dynamics 365 Business Central and integrated solutions.\nDeep knowledge & experience in integrating with other applications.\nA creative and innovative mindset to your work and stakeholders while ensuring the highest quality work delivered on time.\nDesire for self-improvement, results and growth oriented mind together with a strong work ethic.\nCertifications in Microsoft Dynamics 365 Business Central or a related field is a plus\nExcellent communication skills & command of English, preferably also Mandarin\n\nPlease refer to our Company Website:\u00a0http://www.fiducia-china.com. Please submit your full CV with expected salary, plus availability to us. If you do not hear from us within four weeks, you can assume that your application is unsuccessful.", "employment_types": ["Full Time", "Permanent"], "selling_points": ["ERP strategy, implementation & operation", "Minimum 3 years related experience", "12-mth Salaries +2 Behavioural Goals Bonuses"], "locations": ["Wan Chai"], "categories": ["Accounting", "Consulting", "Professional Services", "Business Consultancy", "Information Technology (IT)", "Product Management / Business Analyst"], "post_time": "2022-01-14T04:28:03Z", "salary": {"currency": null, "max": null, "min": null, "period": "monthly", "term": null}, "salary_visible": false, "title_keywords": ["consultant"], "responsibilities": ["collaborate with", "consulting", "operations", "microsoft dynamics", "quality", "design", "communication", "business process", "customer service", "deploy", "designing", "maintaining", "configuration", "teams", "implementation", "develop", "company website", "management", "specifications", "documentation", "third party", "communicate with", "technical support"], "requirements": {"degrees": [], "majors": [], "languages": ["english", "mandarin"], "language_level": ["excellent"], "hard_skills": ["plus", "fun", "erp", "documentation", "focus"], "soft_skills": ["communication skills", "work independently", "creative", "responsible", "deep", "accountable", "collaborative", "innovative", "detail-oriented", "team member", "customer service", "organisation", "work ethic", "focus", "proactive", "extensive"], "languages_combined": [{"language": "english", "language_level": ["excellent"]}, {"language": "mandarin", "language_level": ["excellent"]}]}, "experience_required": {"duration": [], "field": ["business", "it", "design", "team"]}}, {"job_id": "100003009046850", "location_code": "hk", "company": "Hang Seng Bank Ltd", "job_title": "Assistant Digital Product Manager \u2013 Credit Card / Card Lending", "description": "Digital Banking\n\n\nAs one of the leading banks in Hong Kong, we provide extensive digital services on both online and mobile platforms. Facing an ever-growing need for innovative digital solutions, services and platforms, our digital banking capabilities offer an extensive range of products and services that serve over half the adult population in Hong Kong.\n\nWe are currently seeking high caliber professionals to join our department as\u00a0Assistant Digital Product Manager \u2013 Credit Card / Card Lending.\n\nPrincipal responsibilities\n\nAccountable for business requirements preparation for respective digital product's (credit card, card lending, etc.) project delivery\nPreparing user stories and grooming product backlog\nSupporting Team Head on deployment of commercial business strategy that positions Digital as an increasing driver of revenue and business improvement\nActing as a key team member in managing development of digital products under respective business disciplines so as to drive digital conversion / sales via transactional platform according to prioritization\nEnsuring digital deliverables can meet expected business requirements and are fit for purpose to release to customers by supporting in-sprint, pre-release UAT and live test\nFacilitating collaboration with specialists such as UX Design, Engineering, Solution Architecture and Quality Assurance across sprints\nProducing and optimising content of specific product across Mobile, Internet Banking, Public Website and Digital Messaging to improve online experiences and generate income\nAssisting Team Head to continuously enhance user experience of digital platforms and collaborate closely with business stakeholders, IT and project team\nApplying data, metrics and test results from customer reactions to tailor design, content, digital marketing and customer interactions to improve customer response thus business conversion\nRequirements\nStrong analytical and problem solving skills, attention to detail and able to comprehend complicated business dynamics\nUniversity degree, relevant qualifications in Technology, Finance, ecommerce etc. is preferred\nAt least 2 years of relevant experience in driving online sales and/or digital project delivery, preferably with exposure to digital banking or related financial sector experience\nStrong communication skills, both written and verbal, to explain complex or technical issues\nGood understanding of User Centred Design and Agile project methodology, frameworks and best practices\nOpen-minded and self-motivated with good project management, interpersonal, collaboration skill and strong sense of responsibility\nProficiency in both English and Chinese\u00a0\nExperience of project management tools such as JIRA, Confluence for day-to-day communications within the team\nExperience of analytic tools like Adobe Analytics, Google Analytics, etc. is preferred\nGreat sense of ownership and servicing mind-set to ensure efficient and effective customer service delivery\u00a0\n\u00a0\n\nIf you would like to explore other opportunities at Hang Seng Hong Kong, please visit\u00a0www.hangseng.com/careers/\u00a0for details.\n\nThe health and safety of our employees and candidates is very important to us. Due to the current situation related to the Novel Coronavirus (2019-nCoV), we\u2019re leveraging our digital capabilities to ensure we can continue to recruit top talent at the HSBC Group.\u00a0 As your application progresses, you may be asked to use one of our digital tools to help you through your recruitment journey.\u00a0 If so, one of our\u00a0 Resourcing colleagues will explain how our video-interviewing technology will be used throughout the recruitment process and will be on hand to answer any questions you might have.\n\nAll information provided by applicants will be used only for recruitment purposes and will be used strictly in accordance with the Bank's personal data policies, a copy of which may be obtained by the applicant upon request. Unless otherwise instructed in writing by the applicant concerned, applicants may be considered for other suitable positions within the Bank and its related companies. The personal data of unsuccessful job applicants may be retained for a maximum of two years from the date when the job application is rejected and such data may be retained for a longer period if there is a subsisting reason that obliges the Bank to do so, after which the personal data will be destroyed.", "employment_types": ["Full Time", "Permanent"], "selling_points": [], "locations": ["Not Specified"], "categories": ["Banking / Finance", "Financial Services", "Project Finance", "Information Technology (IT)", "Product Management / Business Analyst"], "post_time": "2022-01-14T01:28:24Z", "salary": {"currency": null, "max": null, "min": null, "period": "monthly", "term": null}, "salary_visible": false, "title_keywords": ["product manager", "assistant"], "responsibilities": [], "requirements": {"degrees": [], "majors": [], "languages": [], "language_level": [], "hard_skills": [], "soft_skills": [], "languages_combined": []}, "experience_required": {"duration": [], "field": []}}, {"job_id": "100003009048448", "location_code": "hk", "company": "S.F. Express (Hong Kong) Limited", "job_title": "Senior Data Scientist", "description": "Responsibilities:\n\nEngage with different business units to understand the challenges and identify possible solutions.\nBuilding, training, evaluation models such as retention, risk, fraud, etc.\nKnowledge & statistics sharing and mentoring direct reports\nCollect data from different sources to enhance understanding of data trends.\nInvestigate tools for real-time analysis, time series trends, etc.\nProduction environment machine learning and AI is a plus\n\n\u00a0Technical Skills:\n\nExperience in interactive data exploration and data-driven storytelling\nUnderstanding and application of Big Data and distributed computing principles (Hadoop and MapReduce).\nStrong analytical and statistical knowledge with an understanding of the latest machine learning algorithms for both unstructured and structured data\n\nRequirement:\n\nDegree holder in Computer Science, Business Analytics, Information Technology, or other related disciplines.\nExperience using other statistical programming languages such as Python, SQL, and Hive.\nAt least 3 years of professional experience with analytic projects.\nStrong analytical, critical thinking, and creative problem-solving skills.\nOperates with little supervision in a complex, dynamic, matrixed environment. Able to handle multiple tasks at one time.\nUnderstanding current industry challenges and trends at the level needed to identify business needs and opportunities proactively.\nProven track record and ability to mentor and supervise junior resources on a project assignment basis\n\n\n\nWe offer attractive remuneration package and fringe benefits to the suitable candidates. Interested parties, please submit your application to us. If you do not want to apply as a JobsDB member, you may send your full resume with your availability, current and expected salaries to recruit01 at sf-express.com.\n\nYou are welcome to visit our website at\u00a0https://htm.sf-express.com/hk/tc/\u00a0for more information about us.\n\nCandidates who are not invited for an interview within 1-month may consider their applications unsuccessful.\n\nAll personal data provided by job applicants will be used only for recruitment purposes and will be treated strictly confidential. Unsuccessful applications will be retained for a maximum period of 24-month.", "employment_types": ["Full Time", "Permanent"], "selling_points": ["Free shuttle bus coverage", "2 months or above performance bonus", "Attractive basic salary"], "locations": ["Tsing Yi"], "categories": ["Information Technology (IT)", "IT Project Management / Team Lead", "Product Management / Business Analyst", "Data Scientist"], "post_time": "2022-01-14T06:36:17Z", "salary": {"currency": null, "max": null, "min": null, "period": "monthly", "term": null}, "salary_visible": false, "title_keywords": ["data scientist"], "responsibilities": ["data", "analysis", "big data", "reports", "evaluation"], "requirements": {"degrees": ["degree holder"], "majors": ["related disciplines", "business analytics", "computer science", "information technology"], "languages": [], "language_level": [], "hard_skills": ["sql", "dynamic", "programming", "python", "problem-solving skills"], "soft_skills": ["handle multiple tasks", "problem-solving skills", "dynamic", "creative"], "languages_combined": []}, "experience_required": {"duration": ["at least 3 years"], "field": ["sql", "programming"]}}, {"job_id": "100003009035674", "location_code": "hk", "company": "Cathay Pacific Airways Ltd", "job_title": "Business Analyst (15-months Contract) - Commercial Analytics", "description": "Reports to: Analytics Manager\nDepartment: Digital (DGT)\n\nRole Introduction\nThis position will be responsible to:\n\nGenerate actionable quantitative insight to support the data & insight driven culture in decision making processes\nProactively support business streams in applying and integrating the right set of metrics, analytics model and visualization into day-to-day processes\nEnhance analytics power with new data, derived insight, tools and training with proper testing and requirement sets\nEnsure quality & data governance policies and processes to uphold security, quality and value of the analytics assets.\nKey responsibilities\n\nProvide analytics support services to various business partners.\nDesign with business streams to frame business questions, perform analysis, design visualization of results, and derive analytical models to meet business objectives\nCoordinate with IMT and BU on UAT testing, including specifications review, testing approach design, UAT scoping and execution\nDevelop integrated BI solutions including reports, scorecards and dashboards, leveraging data processing and visualisation tools\nProactive in bring in new data & insight, support data model design and data definitions to ensure proper integration of internal and external sources\nManage enhancements on tools to advance the analytical power, including analytics requirement, testing, prepare training material and delivery\nTrain and facilitate business streams to conduct analysis to facilitate day-to-day decision making\nManage Data Quality by implementing quality metrics & regular monitoring, working on incidents to maintain accessibility and consistency of data as well as readiness of related analytics capabilities\nRequirements\n\nTertiary education in Actuarial Science, Mathematics, Statistics, Information Management, Operations Research or related disciplines;\nMinimum 3 years of working experience relating to data & analytics with a good understanding of at least one of the following business areas: Revenue Management, Sales & Marketing, Finance Management, Operations, Customer management or Service Delivery,\nStrong analytical abilities, numerate and familiar with statistical algorithms, ideally with exposure in developing optimization models\nExpert in using analytics & query tools e.g. Alteryx and data modelling techniques\nProficiency in data visualization tools, ideally Qlikview, Qliksense, PowerBI\nProficiency in scripting languages e.g. Python, SQL\nTeam player with strong communication & interpersonal skills, able to share effectively across different business streams\nCurious, meticulous, self-motivated and strong continuous improvement mindset\nWorking knowledge in managing vendors and suppliers and project management a plus\nApplication deadline: 24 January 2022\n\n\n\nCathay Pacific is an Equal Opportunities Employer. Personal data provided by job applicants will be used strictly in accordance with our personal data policy and for recruitment purposes only. Candidates not notified within eight weeks may consider their application unsuccessful. All related information will be kept in our file for up to 24 months. A copy of our Personal Information Collection Statement will be provided upon request by contacting our Data Protection Officer.\n\nPlease note that with effect from 1 December 2021, all employees must be vaccinated in order to access Cathay City and all other Cathay Group Company premises in Hong Kong. Consideration will be given to those who are unable to get vaccinated for valid medical reasons.", "employment_types": ["Full Time", "Contract"], "selling_points": ["Minimum 3 years of working experience", "Expert in using analytics & query tools", "Travel Benefits, 5-day work, Medical Benefits"], "locations": ["Lantau Island"], "categories": ["Information Technology (IT)", "Product Management / Business Analyst", "Others", "E-commerce", "Product Management / Business Analyst"], "post_time": "2022-01-10T08:07:18Z", "salary": {"currency": null, "max": null, "min": null, "period": "monthly", "term": null}, "salary_visible": false, "title_keywords": ["business analyst"], "responsibilities": ["visualization", "uat", "data", "analysis", "support services", "coordinate with", "uat testing", "design", "review", "testing", "develop", "data processing", "specifications", "reports", "quality", "monitoring", "maintain"], "requirements": {"degrees": [], "majors": [], "languages": [], "language_level": [], "hard_skills": ["qlikview", "plus", "alteryx", "sql", "project management", "data visualization", "python"], "soft_skills": ["meticulous", "self-motivated", "communication", "project management", "interpersonal skills", "team player"], "languages_combined": []}, "experience_required": {"duration": ["minimum 3 years"], "field": ["finance", "management", "business", "marketing"]}}, {"job_id": "100003009044666", "location_code": "hk", "company": "Morgan McKinley", "job_title": "Sourcing Lead, Global Bank", "description": "Responsibilities\n\nProject Management for integration activities.\nSupport the implementation of Third Party Program Management operations\nSupport all Sourcing activities for the China business.\nDay-to-day involvement in contractual and commercial matters and issues\nSupport on tender preparation, bid analysis, contract preparation and award, contract negotiation and administration, vendor management etc\nIdentify operational and cost savings to benefit the Firm\nWorking closely with business partners to develop sourcing strategies\n\nRequirements\n\n5-7 years' experience in strategic sourcing, third party risk, contract negotiation\nRelevant sourcing experience in China\nExcellent verbal, written communications skills in Mandarin and English\nStrong analytical, writing and critical thinking skills; successful candidate must be able to analyze offers, business cases (including financial reports), processes and present a summary quantifying differences in a clear concise manner\nEffective communication to lead/influence a diverse group of people\nSound knowledge of industry and sourcing experience in the key Asia Pac locations\nAbility to work in a fast-paced environment where priorities can change quickly\nGeneral understanding of regulatory and tax requirements within China", "employment_types": ["Full Time", "Permanent"], "selling_points": ["Top-Tier US Bank", "Exposure to China project", "Third Party Program Management"], "locations": ["Not Specified"], "categories": ["Information Technology (IT)", "Product Management / Business Analyst", "Transportation & Logistics", "Supply Chain", "Merchandising & Purchasing", "Procurement / Purchasing / Sourcing"], "post_time": "2022-01-13T05:08:51Z", "salary": {"currency": null, "max": null, "min": null, "period": "monthly", "term": null}, "salary_visible": false, "title_keywords": ["lead"], "responsibilities": ["management", "cost", "operations", "analysis", "implementation", "develop", "project management", "tender preparation", "third party", "administration"], "requirements": {"degrees": [], "majors": [], "languages": ["english", "mandarin"], "language_level": ["excellent"], "hard_skills": [], "soft_skills": ["negotiation", "fast-paced environment", "clear", "diverse", "communication"], "languages_combined": [{"language": "english", "language_level": ["excellent"]}, {"language": "mandarin", "language_level": ["excellent"]}]}, "experience_required": {"duration": ["5-7 years"], "field": []}}, {"job_id": "100003009047329", "location_code": "hk", "company": "Techtronic Industries Co Ltd", "job_title": "APAC Digital Marketing Manager", "description": "Responsibilities:\n\n\n\nWork with internal teams to formulate and execute growth strategy in digital channel for e-commerce and lead-generation across 8+ APAC countries\nManage end-to-end digital marketing across the customer lifecycle (awareness, conversion, retention and referral)\nClosely work with CRM team to develop retention and loyalty strategy, including building-out communication touchpoints across multiple channels (email, SMS, ad etc.)\nImplement marketing automation with Salesforce Marketing Cloud\nDefine measurements of success (KPIs) for campaigns, develop testing framework, and analyze data\nClosely monitor key performance indicators (such as conversion rate, abandoned cart rate & e-commerce metric) and perform A/B testing on website\nRecommend digital marketing opportunities to improve ROI\nWork with external agencies to optimize go-to-market strategy and sustain growth for across regions\nPerform other ad-hoc projects as assigned\n\n\u00a0Requirements:\n\n\nBachelor\u2019s Degree in Marketing, Business Management or related fields\nAt least 5 years relevant experience\nComputer literate in MAC OSX and proficiency in MS Office\nExperience in Google Analytics and comfortable with data visualization tool such as\u00a0PowerBI\nKnowledge of the latest growth practices including paid acquisition, SEO, SEM, etc.\nUnderstand on local SEM and SEO for Naver and Japan Yahoo Ad will be an advantage\nPrevious experience in Google Tag Manager and Tag management including tag implementation plan and data layer is preferred\nCommunicate with IT & Web team in Martech terminology\nPrevious experience in Salesforce Marketing Cloud or other email marketing/marketing automation platform\n\u00a0A highly motivated self-starter and good project management skill\nAble to work independently, under tight schedule and a fast-paced environment\nOutstanding and positive team player\nProficiency in both spoken and written English and Chinese\n\n\u00a0We offer 5-day week, competitive remuneration package and good career prospects to the right candidate. Interested parties please send your resume with expected salary\u00a0by clicking APPLY NOW.\n\n(All personal data collected would be used for recruitment purpose only)", "employment_types": ["Full Time", "Permanent"], "selling_points": ["Manage & support APAC digital marketing", "Project management skill", "Excellent communication skill"], "locations": ["Kwai Hing"], "categories": ["Information Technology (IT)", "Product Management / Business Analyst", "Marketing / Public Relations", "Marketing - Brand / Product Management", "Digital Marketing"], "post_time": "2022-01-14T02:50:24Z", "salary": {"currency": null, "max": null, "min": null, "period": "monthly", "term": null}, "salary_visible": false, "title_keywords": ["digital marketing manager"], "responsibilities": ["teams", "monitor", "website", "develop", "communication", "testing", "digital marketing", "analyze data", "kpis", "ad-hoc projects"], "requirements": {"degrees": ["degree", "bachelor"], "majors": ["business", "marketing"], "languages": ["english", "chinese"], "language_level": ["proficiency"], "hard_skills": ["business management", "google analytics", "seo", "salesforce", "web", "project management", "sem", "data visualization", "ms office"], "soft_skills": ["work independently", "fast-paced environment", "motivated", "project management skill", "team player", "positive"], "languages_combined": [{"language": "english", "language_level": ["proficiency"]}, {"language": "chinese", "language_level": ["proficiency"]}]}, "experience_required": {"duration": ["at least 5 years"], "field": ["management", "marketing", "relevant experience"]}}, {"job_id": "100003009043021", "location_code": "hk", "company": "Wellesley Associates Limited", "job_title": "Business Analyst - Asset Management Firm/ MNC- Investment Accounting System - 40-50+K + Bonus", "description": "Background: My client is one of Asia\u2019s largest independent asset management firms offering world-class investment services and products for institutional and individual clients globally. They are now looking for a Business Analyst to work on their Back-Office/Investment Accounting System Migration and Implementation project.\u00a0\n\nHighlights:\u00a0\nBusiness Analyst\nBuy-Side Firm\u00a0\nBack-Office/Investment Accounting System - Implementation/ Migration\u00a0\u00a0\n\nResponsibilities:\n\nWork with Project Manager and business users to understand their requirements\nLiaise with different teams, but not limited to, front office and data team, for redesigning key process flows.\nCollect effective requirements to facilitate a smooth process flow\u00a0\nMaintain client relationships and manage client expectations.\nDevelopment of project strategies and expected results with users to ensure the applications are meeting expected deliverables.\n\nTechnical Requirements:\n\nImplementation/ System Migration experience of back-office system within the Buy-Side\u00a0 /Financial industry is highly preferred\u00a0\nPossess domain in Back Office Investment Accounting System such as FIS, Sungard, SAP, or other relevant solutions\nExcellent vendor management skills and project management experience on implementation of packaged solutions.\nOwning Process Re-engineering experience is a definite plus.\nStrong interpersonal skills, communications and presentation skills, positive, can-do attitude, meticulous are essential.\nFluent in English and Chinese\nCandidates with less years of experience will also be considered\nCandidates who are interested in this position, please apply directly with your latest CV including current and expecting salary. Please note that only shortlisted candidates will be notified", "employment_types": ["Full Time"], "selling_points": ["Inhouse Asset Management Firm/ FS MNC", "Back-Office/ Investment Accounting System", "Business Analyst/ System Migration/Implementation"], "locations": ["Not Specified"], "categories": ["Banking / Finance", "Project Finance", "Information Technology (IT)", "IT Project Management / Team Lead", "Product Management / Business Analyst"], "post_time": "2022-01-12T09:33:04Z", "salary": {"currency": null, "max": null, "min": null, "period": "monthly", "term": null}, "salary_visible": false, "title_keywords": ["accounting", "business analyst", "asset management"], "responsibilities": ["liaise with", "maintain", "teams", "data"], "requirements": {"degrees": [], "majors": [], "languages": ["english", "chinese"], "language_level": ["fluent"], "hard_skills": ["plus", "sap", "vendor", "project management", "accounting system"], "soft_skills": ["meticulous", "can-do attitude", "interested in", "project management", "presentation skills", "interpersonal skills", "positive"], "languages_combined": [{"language": "english", "language_level": ["fluent"]}, {"language": "chinese", "language_level": ["fluent"]}]}, "experience_required": {"duration": [], "field": ["project management", "management", "financial industry", "engineering"]}}]