[{"job_id": "100003009052769", "location_code": "hk", "company": "Konew Financial Express Ltd", "job_title": "Information Security Manager", "description": "Main Duties & Responsibilities:\n\n\nMonitor and support the information security and IT governance based on international IT security standards including but not limited to ISO 27001\nDevelop, maintain and enforce information security policy, procedure and guideline according to industry standard, company policy and regulatory requirements\nPerform regular cybersecurity assessment for company systems and operation process\nReview and provide professional advice on application logical access and identity management, hardening, security monitoring and vulnerability management\nIntroduce the latest information security technology and policy to the organization\nConduct security incident management, investigation and reporting\nWork closely with project teams and vendors to ensure the development cycle and deliverables comply with all necessary security policies and standards.\nOrganize security training and motivate security awareness among the group\nWork closely with internal and external IT Auditors\n\nRequirements:\n\n\nBachelor\u2019s Degree holder in IT or related disciplines\nAt least 5-10 years of relevant experience in IT security, preferably in FSI\nGood knowledge and experience with security infrastructure (e.g.: Privileges ID management, Endpoint security)\nProblem-solving aptitude, well-organized, self-motivated and able to work under pressure\nExcellent communication, interpersonal skills\nProficiency in Chinese and English, both written and verbal communications\n\nWe offer:\n\n\u00a0\u00a0\u00a0\u00a0\u00a0\u00a0\u00a0 Discretionary bonus\n\u00a0\u00a0\u00a0\u00a0\u00a0\u00a0\u00a0 Medical insurance\n\u00a0\u00a0\u00a0\u00a0\u00a0\u00a0\u00a0 Dental insurance\n\u00a0\u00a0\u00a0\u00a0\u00a0\u00a0\u00a0 Hardship allowance\n\u00a0\u00a0\u00a0\u00a0\u00a0\u00a0\u00a0 Competitive annual leave days\n\u00a0\u00a0\u00a0\u00a0\u00a0\u00a0\u00a0 Birthday leave\n\u00a0\u00a0\u00a0\u00a0\u00a0\u00a0\u00a0 Anniversary leave\n\u00a0\u00a0\u00a0\u00a0\u00a0\u00a0\u00a0 Study leave\n\u00a0\u00a0\u00a0\u00a0\u00a0\u00a0\u00a0 Marriage leave\n\u00a0\u00a0\u00a0\u00a0\u00a0\u00a0\u00a0 Compassionate leave\n\nHow to apply:\n\nInterested parties, please send your resume stating your expected salary to Human Capital Department\u00a0by clicking \"APPLY NOW\".\n\n(We are an equal opportunity employer.\u00a0 Personal data collected will be used for recruitment purpose only.\u00a0 The unsuccessful applications will be destroyed after 6 months.)", "employment_types": ["Full Time"], "selling_points": ["Protect company asset from cybersecurity risk", "Drive cybersecurity enhancement program", "Comply with all necessary security policies"], "locations": ["Central"], "categories": ["Information Technology (IT)", "IT Management", "Security", "Network & System"], "post_time": "2022-01-17T03:59:26Z", "salary": {"currency": null, "max": null, "min": null, "period": "monthly", "term": null}, "salary_visible": false, "title_keywords": ["information security manager"], "responsibilities": ["reporting", "management", "information security", "regulatory requirements", "policies", "systems", "monitor", "review", "monitoring", "develop", "investigation", "teams", "maintain", "vulnerability management"], "requirements": {"degrees": ["bachelor", "degree holder"], "majors": ["related disciplines", "it"], "languages": ["english", "chinese"], "language_level": ["proficiency"], "hard_skills": ["id", "problem-solving"], "soft_skills": ["self-motivated", "problem-solving", "well-organized", "communication", "interpersonal skills", "work under pressure"], "languages_combined": [{"language": "english", "language_level": ["proficiency"]}, {"language": "chinese", "language_level": ["proficiency"]}]}, "experience_required": {"duration": ["at least 5-10 years"], "field": ["infrastructure", "it", "relevant experience", "security"]}}, {"job_id": "100003009053196", "location_code": "hk", "company": "Alpacian Limited", "job_title": "Associate Consultant (Information Security & Audit)", "description": "Responsibilities\n\nOversee the safety and security\u2019s facilities for the company\nEvaluate and review the internal security and safety procedures\nConduct regular security inspections, audits and drill\nMonitor the security operations, access control, alarm system, CCTV system and other security related issues\nCheck the CCTV system logs and review the recorded images\nRepair and maintain the CCTV network and equipment\nPrepare documents and quotations for security system projects \u00a0\nLiaise and supervise the security system vendors\nCommunicate with alarm companies regarding the 7x24\u00a0intruder alarm monitoring system\nMonitor and maintain the vaults system\u00a0 \u00a0 \u00a0 \u00a0 \u00a0\u00a0\n\nRequirements\n\nMinimum 2-3 years of working experiences\nReliable, Proactive and able to work under pressure\nMust be careful, detail-minded & tactful\nQuick response with strong sense of responsibility\nAble to work independently as well as being a team player\nFamiliar with computer applications\nKnowledge for Security System is an advantage\nGood interpersonal and communication skills\nProficiency in spoken and written English and Chinese\nWith driving license preferred\nWorking location at Kwai Chung\nImmediately available is preferred\nWe offer attractive remuneration package fringe benefits including\u00a0Banking Holidays,\u00a0Annual Leave,\u00a0Discretionary Bonus\u00a0&\u00a0Medical Insurance. If you have the desire to join us, please send us your resume immediately with your present and expected salary by clicking \"Apply Now\".\n\n(The information provided will be used for employment related purpose only. All information of unsuccessful applicants will be destroyed within six months.)", "employment_types": ["Full Time", "Permanent"], "selling_points": ["Flexible Working Hours", "Dental and Medical Insurance", "Education Allowance"], "locations": ["Quarry Bay"], "categories": ["Professional Services", "Business Consultancy", "Information Technology (IT)", "Security", "Technical / Functional Consulting"], "post_time": "2022-01-17T06:24:12Z", "salary": {"currency": null, "max": null, "min": null, "period": "monthly", "term": null}, "salary_visible": false, "title_keywords": ["associate", "consultant"], "responsibilities": ["liaise", "communicate with", "operations", "review", "monitor", "procedures", "monitoring", "evaluate", "repair", "maintain", "audits", "access control", "prepare documents"], "requirements": {"degrees": [], "majors": [], "languages": ["english", "chinese"], "language_level": ["proficiency"], "hard_skills": [], "soft_skills": ["detail-minded", "communication skills", "work independently", "proactive", "careful", "sense of responsibility", "team player", "reliable", "tactful", "interpersonal", "work under pressure"], "languages_combined": [{"language": "english", "language_level": ["proficiency"]}, {"language": "chinese", "language_level": ["proficiency"]}]}, "experience_required": {"duration": ["minimum 2-3 years"], "field": []}}, {"job_id": "100003009052105", "location_code": "hk", "company": "BUPA Asia Limited", "job_title": "Information Security Manager", "description": "\u8077\u8cac :\u8ca0\u8cac\u62bc\u904b\u91d1\u9322\u53ca\u8cb4\u91cd\u8ca8\u7269\n\u8cc7\u6b77 :\u6c92\u6709\u5b78\u6b77\u8981\u6c42; \u4e00\u822c\u7cb5\u8a9e; \u4e00\u822c\u82f1\u8a9e; \u7565\u61c2\u8b80\u5beb\u4e2d\u6587; \u7565\u61c2\u8b80\u5beb\u82f1\u6587; \u6301\u6709\u4fdd\u5b89\u57f9\u8a13\u8ab2\u7a0b\u8b49\u66f8(QAS); \u6301\u6709\u4fdd\u5b89\u4eba\u54e1\u8a31\u53ef\u8b49; \u9762\u8a66\u6642\u9593\uff1a\u661f\u671f\u4e00\u81f3\u4e94 (\u516c\u773e\u5047\u671f\u5916)\uff0c0900-1300 \u53ca 1400-1800; \u8acb\u5e36\u5099\uff1a\u5de5\u4f5c\u53ca\u5b78\u6b77\u8b49\u660e;\u4fdd\u5b89\u8b49\u53caQAS\u8b49\u66f8\n\u5f85\u9047 :\u6bcf\u5c0f\u6642$70.00 - $85.00, \u4e0a\u53488\u6642\u81f3\u4e0b\u53488\u6642, \u6bcf\u9031\u5de5\u4f5c6\u5929,\u8f2a\u4f11, \u5de5\u4f5c\u671f\u7531 01/01/2022 \u81f3 10/02/2022, \u6bcf\u5929\u5de5\u4f5c 9 - 12 \u5c0f\u6642\n\u7533\u8acb\u9808\u77e5 :\u6c42\u8077\u8005\u8acb\u6309 APPLY NOW\u7533\u8acb\u6216\u89aa\u81e8\u65b0\u754c\u8475\u6d8c\u8208\u82b3\u8def223\u865f\u65b0\u90fd\u6703\u5ee3\u57f8\u4e8c\u5ea7\u8fa6\u516c\u5ba4\u5927\u6a1320\u6a132001\u5ba4\u5e03\u6797\u514b\u91d1\u878d\u7269\u6d41(\u9999\u6e2f)\u6709\u9650\u516c\u53f8\u9762\u8a66\u3002\u67e5\u8a62\u8acb\u81f4\u96fb28216882\u8207\u9673\u5c0f\u59d0\u806f\u7d61\u3002", "employment_types": ["Full Time", "Permanent"], "selling_points": ["Min. 7  years experience", "Excellent career development & working environment", "Competitive benefits package"], "locations": ["Not Specified"], "categories": ["Information Technology (IT)", "IT Management", "Security", "Insurance", "Others"], "post_time": "2022-01-17T02:05:55Z", "salary": {"currency": null, "max": null, "min": null, "period": "monthly", "term": null}, "salary_visible": false, "title_keywords": ["information security manager"], "responsibilities": [], "requirements": {"degrees": [], "majors": [], "languages": [], "language_level": [], "hard_skills": [], "soft_skills": [], "languages_combined": []}, "experience_required": {"duration": [], "field": []}}, {"job_id": "100003009052963", "location_code": "hk", "company": "NexLen International Limited", "job_title": "Technical Consultant / Pre-Sales Consultant (Network and Cybersecurity)", "description": "\u8077\u8cac :\u4e00\u822c\u901f\u905e\u54e1\u5de5\u4f5c, \u9700\u5916\u52e4\u5de5\u4f5c, \u8ca0\u8cac\u6d3e\u9001\u6587\u4ef6\n\u8cc7\u6b77 :\u6c92\u6709\u5b78\u6b77\u8981\u6c42; \u4e00\u822c\u7cb5\u8a9e; \u7565\u61c2\u8b80\u5beb\u4e2d\u6587; \u61c2\u95b1\u8b80\u82f1\u6587; \u6301\u6709\u4fdd\u5b89\u57f9\u8a13\u8ab2\u7a0b\u8b49\u66f8(QAS); \u6301\u6709\u4fdd\u5b89\u4eba\u54e1\u8a31\u53ef\u8b49\n\u5f85\u9047 :\u6bcf\u6708$13,100 - $15,600, \u6709\u8d85\u6642\u5de5\u4f5c\u6d25\u8cbc, \u914c\u60c5\u6027\u82b1\u7d05, \u8868\u73fe\u734e\u91d1, \u91ab\u7642\u798f\u5229, \u5728\u8077\u57f9\u8a13 \u53ca\u6649\u5347\u6a5f\u6703, \u661f\u671f\u4e00\u81f3\u4e94: \u4e0a\u53488\u6642\u81f3\u4e0b\u53487\u6642\u53ca\u661f\u671f\u516d: \u4e0a\u53488\u6642\u81f3\u4e0b\u53482\u6642, \u6bcf\u9031\u5de5\u4f5c6\u5929, \u6bcf\u5929\u5de5\u4f5c 9 - 11 \u5c0f\u6642\n\u7533\u8acb\u9808\u77e5 :\u6c42\u8077\u8005\u8acb\u89aa\u81e8\u8475\u82b3\u65b0\u90fd\u6703\u5ee3\u58342\u671f20\u6a132001\u5ba4\u5e03\u6797\u514b\u91d1\u878d\u7269\u6d41(\u9999\u6e2f)\u6709\u9650\u516c\u53f8\u9762\u8a66\u3002\u67e5\u8a62\u8acb\u81f4\u96fb28216882\u8207\u9673 \u5c0f\u59d0\u806f\u7d61\u3002\n\u5099\u8a3b :** \u50f1\u4e3b\u53ef\u5c31\u6b64\u8077\u4f4d\u7a7a\u7f3a\u7533\u8acb\u53c3\u52a0\u300c\u4e2d\u9ad8\u9f61\u5c31\u696d\u8a08\u5283\u300d\uff0c\u6b61\u8fce\u4e2d\u9ad8\u9f61\u6c42\u8077\u4eba\u58eb\u61c9\u5fb5\u3002", "employment_types": ["Full Time"], "selling_points": ["Attractive salary package", "Customer orientated, provide network and cybersecu", "Provide network and cybersecurity consultancy"], "locations": ["Kwun Tong"], "categories": ["Information Technology (IT)", "Product Management / Business Analyst", "Application Specialist - Network", "Security"], "post_time": "2022-01-17T04:42:32Z", "salary": {"currency": null, "max": null, "min": null, "period": "monthly", "term": null}, "salary_visible": false, "title_keywords": ["sales consultant", "consultant"], "responsibilities": [], "requirements": {"degrees": [], "majors": [], "languages": [], "language_level": [], "hard_skills": [], "soft_skills": [], "languages_combined": []}, "experience_required": {"duration": [], "field": []}}, {"job_id": "100003009048591", "location_code": "hk", "company": "CITIC Telecom International Holdings Limited", "job_title": "IT Security Specialist", "description": "\u8077\u8cac :\u8ca0\u8cac\u9ede\u7b97\u73fe\u91d1\n\u8cc7\u6b77 :\u6c92\u6709\u5b78\u6b77\u8981\u6c42; \u4e00\u822c\u7cb5\u8a9e; \u7565\u61c2\u8b80\u5beb\u4e2d\u6587; \u7565\u61c2\u8b80\u5beb\u82f1\u6587; \u6301\u6709\u4fdd\u5b89\u57f9\u8a13\u8ab2\u7a0b\u8b49\u66f8(QAS); \u6301\u6709\u4fdd\u5b89\u4eba\u54e1\u8a31\u53ef\u8b49\n\u5f85\u9047 :\u6bcf\u6708$16,100, \u6709\u8d85\u6642\u5de5\u4f5c\u6d25\u8cbc, \u914c\u60c5\u6027\u82b1\u7d05, \u8868\u73fe\u734e\u91d1, \u91ab\u7642\u798f\u5229, \u5728\u8077\u57f9\u8a13 \u53ca\u6649\u5347\u6a5f\u6703, \u4e2d\u534812\u6642\u81f3\u51cc\u666812\u6642, \u6bcf\u9031\u5de5\u4f5c6\u5929,\u8f2a\u4f11, \u6bcf\u5929\u5de5\u4f5c 9 - 12 \u5c0f\u6642\n\u7533\u8acb\u9808\u77e5 :\u6c42\u8077\u8005\u8acb\u89aa\u81e8\u8475\u82b3\u65b0\u90fd\u6703\u5ee3\u58342\u671f20\u6a132001\u5ba4\u5e03\u6797\u514b\u91d1\u878d\u7269\u6d41(\u9999\u6e2f)\u6709\u9650\u516c\u53f8\u9762\u8a66\u3002\u67e5\u8a62\u8acb\u81f4\u96fb28216882\u8207\u9673 \u5c0f\u59d0\u806f\u7d61\u3002\n\u5099\u8a3b :** \u50f1\u4e3b\u53ef\u5c31\u6b64\u8077\u4f4d\u7a7a\u7f3a\u7533\u8acb\u53c3\u52a0\u300c\u4e2d\u9ad8\u9f61\u5c31\u696d\u8a08\u5283\u300d\uff0c\u6b61\u8fce\u4e2d\u9ad8\u9f61\u6c42\u8077\u4eba\u58eb\u61c9\u5fb5\u3002", "employment_types": ["Full Time", "Permanent"], "selling_points": ["Develop and maintain IT security policies", "Main focal point for IT security related matters", "Double Pay, Bonus, 5-day work, Medical & Dental"], "locations": ["Kwai Fong"], "categories": ["Information Technology (IT)", "IT Management", "Security", "Others"], "post_time": "2022-01-14T06:52:06Z", "salary": {"currency": null, "max": null, "min": null, "period": "monthly", "term": null}, "salary_visible": false, "title_keywords": ["specialist"], "responsibilities": [], "requirements": {"degrees": [], "majors": [], "languages": [], "language_level": [], "hard_skills": [], "soft_skills": [], "languages_combined": []}, "experience_required": {"duration": [], "field": []}}, {"job_id": "100003009053171", "location_code": "hk", "company": "Johnson Electric Industrial Manufactory Limited", "job_title": "Cyber Security Manager", "description": "\u8077\u8cac :\u8ca0\u8cac\u99d5\u99db\u8eca\u8f1b\u3001\u62bc\u904b\u91d1\u9322\u53ca\u8cb4\u91cd\u8ca8\u7269 (\u9577\u6c99\u7063\u53d6\u8eca)\n\u8cc7\u6b77 :\u6c92\u6709\u5b78\u6b77\u8981\u6c42; \u4e00\u822c\u7cb5\u8a9e; \u7565\u61c2\u8b80\u5beb\u4e2d\u6587; \u61c2\u95b1\u8b80\u82f1\u6587; \u6301\u6709\u4fdd\u5b89\u57f9\u8a13\u8ab2\u7a0b\u8b49\u66f8(QAS); \u6301\u6709\u4fdd\u5b89\u4eba\u54e1\u8a31\u53ef\u8b49; \u6301\u6709\u8f15\u578b\u8ca8\u8eca\u99d5\u99db\u57f7\u7167; \u6301\u6709\u79c1\u5bb6\u8eca\u99d5\u99db\u57f7\u7167\n\u5f85\u9047 :\u6bcf\u6708$21,700, \u6709\u8d85\u6642\u5de5\u4f5c\u6d25\u8cbc, \u914c\u60c5\u6027\u82b1\u7d05, \u8868\u73fe\u734e\u91d1, \u91ab\u7642\u798f\u5229, \u5728\u8077\u57f9\u8a13 \u53ca\u6649\u5347\u6a5f\u6703, \u4e0a\u53488\u6642\u81f3\u4e0b\u53488\u6642\u6216\u4e0a\u53487\u6642\u81f3\u4e0b\u53487\u6642, \u6bcf\u9031\u5de5\u4f5c6\u5929,\u8f2a\u4f11, \u6bcf\u5929\u5de5\u4f5c 9 - 12 \u5c0f\u6642\n\u7533\u8acb\u9808\u77e5 :\u6c42\u8077\u8005\u8acb\u89aa\u81e8\u8475\u82b3\u65b0\u90fd\u6703\u5ee3\u58342\u671f20\u6a132001\u5ba4\u5e03\u6797\u514b\u91d1\u878d\u7269\u6d41(\u9999\u6e2f)\u6709\u9650\u516c\u53f8\u9762\u8a66\u3002\u67e5\u8a62\u8acb\u81f4\u96fb28216882\u8207\u9673 \u5c0f\u59d0\u806f\u7d61\u3002\n\u5099\u8a3b :** \u50f1\u4e3b\u53ef\u5c31\u6b64\u8077\u4f4d\u7a7a\u7f3a\u7533\u8acb\u53c3\u52a0\u300c\u4e2d\u9ad8\u9f61\u5c31\u696d\u8a08\u5283\u300d\uff0c\u6b61\u8fce\u4e2d\u9ad8\u9f61\u6c42\u8077\u4eba\u58eb\u61c9\u5fb5\u3002", "employment_types": ["Full Time", "Permanent"], "selling_points": ["Globally Leading Motor Manufacturer", "Innovative Team Environment", "Attractive Salary Remuneration Package"], "locations": ["Tai Po Area"], "categories": ["Information Technology (IT)", "IT Project Management / Team Lead", "Security", "Network & System"], "post_time": "2022-01-17T06:14:52Z", "salary": {"currency": null, "max": null, "min": null, "period": "monthly", "term": null}, "salary_visible": false, "title_keywords": ["manager"], "responsibilities": [], "requirements": {"degrees": [], "majors": [], "languages": [], "language_level": [], "hard_skills": [], "soft_skills": [], "languages_combined": []}, "experience_required": {"duration": [], "field": []}}, {"job_id": "100003009054770", "location_code": "hk", "company": "Public Finance Limited", "job_title": "System Security Officer", "description": "\u8077\u8cac :\u8ca0\u8cac\u8655\u7406\u51fa\u5165\u8ca8, \u9ede\u7b97\u53ca\u8a18\u9304\u5009\u5eab\u5b58\u8ca8; \u56fa\u5b9a\u591c\u73ed, \u5ba4\u5167\u51b7\u6c23\u74b0\u5883\u5de5\u4f5c\n\u8cc7\u6b77 :\u6c92\u6709\u5b78\u6b77\u8981\u6c42; \u4e00\u822c\u7cb5\u8a9e; \u7565\u61c2\u8b80\u5beb\u4e2d\u6587; \u6301\u6709\u4fdd\u5b89\u4eba\u54e1\u8a31\u53ef\u8b49\n\u5f85\u9047 :\u6bcf\u6708$20,200, \u6709\u8d85\u6642\u5de5\u4f5c\u6d25\u8cbc, \u914c\u60c5\u6027\u82b1\u7d05, \u8868\u73fe\u734e\u91d1, \u91ab\u7642\u798f\u5229, \u5728\u8077\u57f9\u8a13 \u53ca\u6649\u5347\u6a5f\u6703, \u4e0b\u53487\u6642\u81f3\u4e0a\u53487\u6642, \u6bcf\u9031\u5de5\u4f5c6\u5929,\u8f2a\u4f11, \u6bcf\u5929\u5de5\u4f5c 12 \u5c0f\u6642\n\u7533\u8acb\u9808\u77e5 :\u6c42\u8077\u8005\u8acb\u89aa\u81e8\u8475\u82b3\u65b0\u90fd\u6703\u5ee3\u58342\u671f20\u6a132001\u5ba4\u5e03\u6797\u514b\u91d1\u878d\u7269\u6d41(\u9999\u6e2f)\u6709\u9650\u516c\u53f8\u9762\u8a66\u3002\u67e5\u8a62\u8acb\u81f4\u96fb28216882\u8207\u9673 \u5c0f\u59d0\u806f\u7d61\u3002\n\u5099\u8a3b :** \u50f1\u4e3b\u53ef\u5c31\u6b64\u8077\u4f4d\u7a7a\u7f3a\u7533\u8acb\u53c3\u52a0\u300c\u4e2d\u9ad8\u9f61\u5c31\u696d\u8a08\u5283\u300d\uff0c\u6b61\u8fce\u4e2d\u9ad8\u9f61\u6c42\u8077\u4eba\u58eb\u61c9\u5fb5\u3002", "employment_types": ["Full Time", "Permanent"], "selling_points": [], "locations": ["Not Specified"], "categories": ["Information Technology (IT)", "Hardware", "Security", "Network & System"], "post_time": "2022-01-17T11:01:16Z", "salary": {"currency": null, "max": null, "min": null, "period": "monthly", "term": null}, "salary_visible": false, "title_keywords": ["officer"], "responsibilities": [], "requirements": {"degrees": [], "majors": [], "languages": [], "language_level": [], "hard_skills": [], "soft_skills": [], "languages_combined": []}, "experience_required": {"duration": [], "field": []}}, {"job_id": "100003009053302", "location_code": "hk", "company": "SmarTone Telecommunications Limited", "job_title": "Consultant, Cyber Risk & Security Practice", "description": "\u8077\u8cac :\u8ca0\u8cac\u62bc\u904b\u91d1\u9322\u53ca\u8cb4\u91cd\u8ca8\u7269\n\u8cc7\u6b77 :\u6c92\u6709\u5b78\u6b77\u8981\u6c42; \u4e00\u822c\u7cb5\u8a9e; \u7565\u61c2\u8b80\u5beb\u4e2d\u6587; \u7565\u61c2\u8b80\u5beb\u82f1\u6587; \u6301\u6709\u4fdd\u5b89\u57f9\u8a13\u8ab2\u7a0b\u8b49\u66f8(QAS); \u6301\u6709\u4fdd\u5b89\u4eba\u54e1\u8a31\u53ef\u8b49\n\u5f85\u9047 :\u6bcf\u6708$18,900, \u6709\u8d85\u6642\u5de5\u4f5c\u6d25\u8cbc, \u8868\u73fe\u734e\u91d1, \u914c\u60c5\u6027\u82b1\u7d05, \u91ab\u7642\u798f\u5229, \u5728\u8077\u57f9\u8a13 \u53ca\u6649\u5347\u6a5f\u6703, \u4e0a\u53488\u6642\u81f3\u4e0b\u53488\u6642\u6216\u4e0a\u53487\u6642\u81f3\u4e0b\u53487\u6642, \u6bcf\u9031\u5de5\u4f5c6\u5929,\u8f2a\u4f11, \u6bcf\u5929\u5de5\u4f5c 9 - 12 \u5c0f\u6642\n\u7533\u8acb\u9808\u77e5 :\u6c42\u8077\u8005\u8acb\u89aa\u81e8\u8475\u82b3\u65b0\u90fd\u6703\u5ee3\u58342\u671f20\u6a132001\u5ba4\u5e03\u6797\u514b\u91d1\u878d\u7269\u6d41(\u9999\u6e2f)\u6709\u9650\u516c\u53f8\u9762\u8a66\u3002\u67e5\u8a62\u8acb\u81f4\u96fb28216882\u8207\u9673 \u5c0f\u59d0\u806f\u7d61\u3002\n\u5099\u8a3b :** \u50f1\u4e3b\u53ef\u5c31\u6b64\u8077\u4f4d\u7a7a\u7f3a\u7533\u8acb\u53c3\u52a0\u300c\u4e2d\u9ad8\u9f61\u5c31\u696d\u8a08\u5283\u300d\uff0c\u6b61\u8fce\u4e2d\u9ad8\u9f61\u6c42\u8077\u4eba\u58eb\u61c9\u5fb5\u3002", "employment_types": ["Full Time", "Permanent"], "selling_points": ["Security & networking application & solutions", "Support pre-sales activities", "Passionate about Cybersecurity"], "locations": ["Ngau Tau Kok"], "categories": ["Information Technology (IT)", "Security", "Network & System", "Technical / Functional Consulting"], "post_time": "2022-01-17T06:43:34Z", "salary": {"currency": null, "max": null, "min": null, "period": "monthly", "term": null}, "salary_visible": false, "title_keywords": ["consultant"], "responsibilities": [], "requirements": {"degrees": [], "majors": [], "languages": [], "language_level": [], "hard_skills": [], "soft_skills": [], "languages_combined": []}, "experience_required": {"duration": [], "field": []}}, {"job_id": "100003009052043", "location_code": "hk", "company": "Chesterton Consulting Co Limited", "job_title": "IT Infrastructure and Security Manager", "description": "\u8077\u8cac :\u8ca0\u8cac\u642c\u904b\u9322\u7bb1\u53ca\u9ede\u7b97\u73fe\u91d1\n\u8cc7\u6b77 :\u6c92\u6709\u5b78\u6b77\u8981\u6c42; \u4e00\u822c\u7cb5\u8a9e; \u7565\u61c2\u8b80\u5beb\u4e2d\u6587; \u7565\u61c2\u8b80\u5beb\u82f1\u6587; \u6301\u6709\u4fdd\u5b89\u4eba\u54e1\u8a31\u53ef\u8b49\n\u5f85\u9047 :\u6bcf\u6708$18,600, \u6709\u8d85\u6642\u5de5\u4f5c\u6d25\u8cbc, \u914c\u60c5\u6027\u82b1\u7d05, \u91ab\u7642\u798f\u5229, \u8868\u73fe\u734e\u91d1, \u5728\u8077\u57f9\u8a13 \u53ca\u6649\u5347\u6a5f\u6703, \u4e0a\u53487\u6642\u81f3\u4e0b\u53487\u6642, \u6bcf\u9031\u5de5\u4f5c6\u5929,\u8f2a\u4f11, \u6bcf\u5929\u5de5\u4f5c 9 - 12 \u5c0f\u6642\n\u7533\u8acb\u9808\u77e5 :\u6c42\u8077\u8005\u8acb\u89aa\u81e8\u8475\u82b3\u65b0\u90fd\u6703\u5ee3\u58342\u671f20\u6a132001\u5ba4\u5e03\u6797\u514b\u91d1\u878d\u7269\u6d41(\u9999\u6e2f)\u6709\u9650\u516c\u53f8\u9762\u8a66\u3002\u67e5\u8a62\u8acb\u81f4\u96fb28216882\u8207\u9673 \u5c0f\u59d0\u806f\u7d61\u3002\n\u5099\u8a3b :** \u50f1\u4e3b\u53ef\u5c31\u6b64\u8077\u4f4d\u7a7a\u7f3a\u7533\u8acb\u53c3\u52a0\u300c\u4e2d\u9ad8\u9f61\u5c31\u696d\u8a08\u5283\u300d\uff0c\u6b61\u8fce\u4e2d\u9ad8\u9f61\u6c42\u8077\u4eba\u58eb\u61c9\u5fb5\u3002", "employment_types": ["Full Time", "Permanent"], "selling_points": ["Fast Paced", "Excellent Career Opportunity", "Job Security"], "locations": ["Sai Ying Pun"], "categories": ["Information Technology (IT)", "IT Management", "Security"], "post_time": "2022-01-17T01:55:46Z", "salary": {"currency": null, "max": null, "min": null, "period": "monthly", "term": null}, "salary_visible": false, "title_keywords": ["manager"], "responsibilities": [], "requirements": {"degrees": [], "majors": [], "languages": [], "language_level": [], "hard_skills": [], "soft_skills": [], "languages_combined": []}, "experience_required": {"duration": [], "field": []}}, {"job_id": "100003009051751", "location_code": "hk", "company": "Pinpoint Asia Limited", "job_title": "SOC Security Operations Manager - Enterprise Security Hub", "description": "Our client, a leading large enterprise with a large CyberSecurity Center and SOC in Hong Kong, is looking for a SOC Manager to comply with their increasing Cyber Security defense need. Great exposure and scale to work with one of the most prominent financial institutions in the region.\n\nResponsibilities:\n\nLead the SOC Operations in Hong Kong to monitor potential risks, threats, and attacks.\nReview and manage security systems including security log, user behavior analytics, vulnerability scanning, security playbook automation.\nMonitor suspicious cloud-based user activities, potential hazardous actions, malware, etc.\nWork with the IT and security teams in performing system and network vulnerability scanning. Advice development teams and technology product owners on security to withstand known attack vectors and prevalent threats.\nWork with the development and operations team on integrating security control policies and instructions into the CASB architecture.\nWork with the business stakeholders for user requirements and enable CASH security controls on business SaaS.\n\nRequirements:\n\nAt least 10 years of hands-on technical experience in the Information Security and/or Cyber Security area.\nExperience with vulnerability assessments, environment scanning, security controls, etc.\nExperience with Security Data Analytics technology in SIEM, UEBA, ELK, and SOAR.\nExperience in building secure network infrastructure including Anti-DDoS, NG Firewall, IDS/IPS, WAF, Secure MTA, Load Balancer, Internet Proxy, DNS hosting, etc.\nExperience in performing malware analysis and using the sandbox for detailed investigation.\nHands-on experience on endpoint whitelisting, web isolation, and or MSS handling.\nFamiliar with network and infrastructure design to adopt security controls.\nSecurity Certificates in CISSP, CISM, CISA, or equivalent.\nExcellent communication skills in English.\nBachelor's Degree in Computer Science or related field from a reputable University.\n\nIf this outstanding opportunity sounds like your next career move, please send your resume in Word format to Danny Kwan at resume(at)pinpointasia(dot)com and put SOC Security Operations Manager - Enterprise Security Hub\u00a0in the subject header.\n\nData provided is for recruitment purposes only.", "employment_types": ["Full Time", "Permanent"], "selling_points": ["Large Security Center", "Sophisticated Technology", "SOC Operations"], "locations": ["Not Specified"], "categories": ["Information Technology (IT)", "IT Management", "Security", "Technical / Functional Consulting"], "post_time": "2022-01-17T00:14:13Z", "salary": {"currency": "HKD", "max": 89999, "min": 70000, "period": "monthly", "term": null}, "salary_visible": true, "title_keywords": ["operations manager"], "responsibilities": ["scanning", "control", "operations", "policies", "review", "monitor", "systems", "teams", "architecture"], "requirements": {"degrees": ["degree", "bachelor"], "majors": ["computer science"], "languages": ["english"], "language_level": ["excellent"], "hard_skills": ["dns", "web", "cyber security", "data analytics", "analysis", "word", "firewall"], "soft_skills": ["communication skills", "hands-on", "detailed"], "languages_combined": [{"language": "english", "language_level": ["excellent"]}]}, "experience_required": {"duration": ["at least 10 years"], "field": ["infrastructure", "security"]}}, {"job_id": "100003009051264", "location_code": "hk", "company": "Crossings Executive Search", "job_title": "IT Security Manager (Ref: ITSM/SL)", "description": "Our client is a reputable life insurance company, actively and successfully expanding its business and IT team recently.\u00a0 They are now looking for an all-rounded IT Security Manager to join their IT Security team, reporting directly to the Chief IT Security Architect with all-rounded IT security duty and responsibility.\nThe position is required to oversees all aspects of IT security systems, including application and infrastructure, and responsible for performing information security analysis, implementation and consultation, as well as to assist information security architecture, define and implement security policies and measurements. For ad-hoc activities, the position is required to assist security incident response (IR) process and working together with other teams or managing external vendors for solutions.\nRequirements:\nDegree holder majoring in Computer Science or equivalent\nMinimum seven (7) years of IT experience, of which five (5) years in information security preferably in financial service industry\nHands on experience in managing information security projects and solutions\nGood experience in dealing with business partner and managing external vendors\nProfessional qualification in Information Security such as CISSP, CISA or CISM\nKnowledge of industrial practices such as ISO27001, COBIT and NIST CSF would be a plus\n\nFor all applications, kindly send us your updated CV quoting reference ITSM/SL", "employment_types": ["Full Time"], "selling_points": ["IT Security Manager", "Hands-on information security experience", "Financial service or insurance company"], "locations": ["Ngau Tau Kok"], "categories": ["Information Technology (IT)", "IT Management", "Security"], "post_time": "2022-01-15T06:40:39Z", "salary": {"currency": null, "max": null, "min": null, "period": "monthly", "term": null}, "salary_visible": false, "title_keywords": ["manager"], "responsibilities": ["ad-hoc", "reporting", "information security", "policies", "analysis", "infrastructure", "systems", "implementation", "teams", "insurance", "architecture"], "requirements": {"degrees": ["degree holder"], "majors": ["computer science"], "languages": [], "language_level": [], "hard_skills": ["analysis", "plus"], "soft_skills": ["hands on", "responsible"], "languages_combined": []}, "experience_required": {"duration": [], "field": ["service industry", "business partner", "it experience", "security", "financial"]}}, {"job_id": "100003009052948", "location_code": "hk", "company": "Edvance Technology (Hong Kong) Limited", "job_title": "Technical Engineer", "description": "Working in one of our three core cybersecurity disciplines, you will be working with senior members of the team to deliver services and support services. We ask junior members to pick up skills along the way and to contribute positively to the success of the team.\n\nJob Responsibilities\n\nWork with senior staff on project delivery and support tasks\nPick up cybersecurity skillsets and contribute to team efforts\nFocus on one of three primary domains:\nNetwork Security\nApplication & Data Security\nIdentity & Access Management\n\nJob Requirements\n\nKeen interest to broaden skills in IT and Cybersecurity\nDegree in Information Technology / Computer Science / Engineering or equivalent\nOpen-minded and innovative, think outside-the-box!\nGood communication skills and a positive can-do attitude is!\n\n\n\nWe Offer:\n\nGenerous Remuneration\nFixed and Discretionary Bonus\nAnnual Leave + Other Paid Leaves\nAdditional Monthly Allowance\nGroup Medical\nStaff Award", "employment_types": ["Full Time", "Permanent"], "selling_points": ["Suitable for fresh graduate/up to 3 yrs exp in IT", "Enthusiasm in securing technologies(cybersecurity)", "Attractive Remuneration"], "locations": ["Ngau Tau Kok"], "categories": ["Information Technology (IT)", "Security"], "post_time": "2022-01-17T04:39:37Z", "salary": {"currency": null, "max": null, "min": null, "period": "monthly", "term": null}, "salary_visible": false, "title_keywords": ["technical engineer"], "responsibilities": ["management", "data"], "requirements": {"degrees": ["degree"], "majors": ["engineering", "computer science", "information technology"], "languages": [], "language_level": [], "hard_skills": [], "soft_skills": ["communication skills", "can-do attitude", "open-minded", "keen", "innovative", "positive"], "languages_combined": []}, "experience_required": {"duration": [], "field": []}}, {"job_id": "100003009052265", "location_code": "hk", "company": "Vanke Holdings (Hong Kong) Company Limited", "job_title": "Senior Officer / Officer (IT Support)", "description": "Responsibilities:\n\nRespond to user requests in office and personal visits to remote locations, for assistance with system-related concerns\nProvide system support on Office 365, VMware, Veeam, Windows AD, Windows Server, website and mobile application management\nProvide first level user applications support\nMonitor all backup activities by following the well-defined backup procedure\nProvide network support on firewalls, switches and VPNs\nProvide PC/Server installation, configuration and administration\nWork with vendor to perform IT support activities\nManage small to medium sized projects according to agreed-upon budgets and schedules\nProvide on-site support at all locations during business hours and otherwise where problems dictate\nPerform ad hoc assignments and responsibilities requested by supervisor\nAdminister IT asset inventories, ensuring records are in an accurate and kept up to date\nEnsure application availability, perform regular capacity planning, housekeeping to maintain system healthiness and disaster recovery planning\n\nRequirements:\n\nDiploma in Information Technology, Computer Science related disciplines or above\nMinimum 3 years relevant experience in technical support\nSolid experience in user, server and network support\nExperience in Microsoft Windows Configuration, VMware, Cloud and desktop environment\nGood knowledge of Network Infrastructure & Cyber Security\nHolder of MCSA, MCSE, CCNA / Experience in IT security audit or compliance (such as security risk assessment) is preferable\nGood communication, problem-solving & time management skills\nGood command of spoken and written English & Chinese\nIndependent, self-motivated, quick learner, good team player, strong sense of responsibility and able to work under pressure\nCandidate with more experience will be considered as Senior Officer\nWe offer an attractive remuneration package. Interested parties please send your resume stating your present and expected salaries, together with your cover letter by clicking \"APPLY NOW\".\u00a0\n\nPlease read carefully the following Privacy Statement before applying: \"The personal data of unsuccessful candidates collected\u00a0for this\u00a0recruitment exercise will be kept no more than 2 years from its completion for future recruitment use and therefore destroyed.\u00a0 Information provided will be used for recruitment and appointment related purpose only.\u00a0 The Company will handle all personal data confidentially in accordance with the Personal Data (Privacy) Ordinance.\"\u00a0\u00a0\u00a0\n\nCandidates have a\u00a0right to make a data access, correction or destroy request concerning\u00a0the personal data by applying to the Human\u00a0Resources Department.\u00a0\u00a0", "employment_types": ["Full Time", "Permanent"], "selling_points": ["System and network administration/ support", "Good knowledge of Network Infrastructure", "Good knowledge of Cyber Security"], "locations": ["Central"], "categories": ["Information Technology (IT)", "Support", "Security", "Network & System"], "post_time": "2022-01-17T02:36:37Z", "salary": {"currency": null, "max": null, "min": null, "period": "monthly", "term": null}, "salary_visible": false, "title_keywords": ["senior officer", "officer", "it support"], "responsibilities": ["installation", "management", "budgets", "recovery planning", "configuration", "schedules", "housekeeping", "monitor", "website", "it asset inventories", "maintain system healthiness", "ad hoc assignments", "application availability", "regular capacity planning", "administration"], "requirements": {"degrees": ["diploma"], "majors": ["related disciplines", "computer science", "information technology"], "languages": ["english", "chinese"], "language_level": ["good command"], "hard_skills": ["mcse", "vmware", "cyber security", "problem-solving", "ccna", "mcsa", "server"], "soft_skills": ["self-motivated", "good team player", "independent", "sense of responsibility", "time management skills", "problem-solving", "quick learner", "communication", "work under pressure"], "languages_combined": [{"language": "english", "language_level": ["good command"]}, {"language": "chinese", "language_level": ["good command"]}]}, "experience_required": {"duration": ["minimum 3 years"], "field": ["compliance", "audit", "it", "relevant experience", "security"]}}, {"job_id": "100003009055044", "location_code": "hk", "company": "Generali Life (Hong Kong) Limited", "job_title": "Cloud (AWS) Engineer / Assistant Manager", "description": "Job Description\nWith ever-increasing growth and expansion, we are looking for a new technical Cloud (AWS) Engineer to join our enterprise infrastructure team. Ideally, this technical hand-on Cloud (AWS) Engineer has extensive experience implementing cloud (AWS) and other related security and infrastructure enterprise projects. In addition to this, this Engineer would be providing ongoing technical internal support.\n\nResponsibilities:\n\nCloud, infrastructure and security project implementation, which includes working with the respective vendors.\nPerform and oversee software installation, upgrades and maintenance, remediate vulnerabilities and keep patch updates to systems\nDevice configuration of switch, server, firewall, Email support systems, anti-spam etc.\nL2 technical IT helpdesk support\n\nMinimum Requirements:\n\n3-5 years of technical cloud(AWS) implementation experience\n3-5 years experience in Infrastructure management, network administration, and network security related experience\nStrong team player with a proactive and willingness to learn attitude\nProfessional certification in Cisco Certified Network Associate (CCNA), Microsoft Certificated System Engineer (MCSE), System Administrator (MCSA) or equivalent\nUniversity degree in Computer Science, Information Systems or other technology-related disciplines\nFluent in both spoken and written English and Chinese\n\nHighly Preferred:\n\nExperience with Microsoft 365 (Office 365)\nKnowledge on Cybersecurity market standards like CISSP (Certified Information Systems Security Professional)\nEnterprise financial institution exposure (insurance or banking)\n\nFor strong candidates with less experience, they will be considered for a Cloud Engineer position.", "employment_types": ["Full Time", "Permanent"], "selling_points": [], "locations": ["Tai Koo"], "categories": ["Information Technology (IT)", "IT Management", "Security", "Network & System"], "post_time": "2022-01-18T00:49:18Z", "salary": {"currency": null, "max": null, "min": null, "period": "monthly", "term": null}, "salary_visible": false, "title_keywords": ["assistant manager", "engineer"], "responsibilities": ["installation", "software", "maintenance", "upgrades", "configuration", "infrastructure", "systems", "implementation"], "requirements": {"degrees": ["university degree"], "majors": ["related disciplines", "computer science"], "languages": ["english", "chinese"], "language_level": ["fluent"], "hard_skills": ["network administration", "mcse", "office 365", "ccna", "mcsa", "cisco certified network associate"], "soft_skills": ["team player", "proactive"], "languages_combined": [{"language": "english", "language_level": ["fluent"]}, {"language": "chinese", "language_level": ["fluent"]}]}, "experience_required": {"duration": ["3-5 years"], "field": ["network administration", "management", "related", "infrastructure", "security"]}}, {"job_id": "100003009055131", "location_code": "hk", "company": "Meyer Aluminium Ltd", "job_title": "TECHNICAL ANALYST", "description": "The appointee will report to the\u00a0System Engineering Services Manager\u00a0and is responsible for network infrastructure\u00a0planning, implementation, administration\u00a0monitoring and trouble shooting. \u00a0Your prerequisite attributes are:\n\nUniversity/Tertiary\u00a0graduate in related disciplines;\nAt least 3\u00a0years\u2019\u00a0experience in Windows Server and network configuration and administration;\nIn-depth network knowledge and solid hands-on experience in firewall, routers and switches;\nExperience in VCP is an advantage.\n\nWe offer competitive remuneration plus comprehensive fringe benefits. \u00a0Interested parties, please send full resume and salary expected to Senior Human Resources Officer, Meyer Aluminium Ltd, 5 Dai Li Street, Tai Po Industrial Estate, Tai Po, New Territories. \u00a0or clicking \"Apply Now'. \u00a0All applications will be treated in strictly confidential.", "employment_types": ["Full Time"], "selling_points": [], "locations": ["Tai Po Area"], "categories": ["Information Technology (IT)", "Application Specialist - Network", "Security", "Network & System"], "post_time": "2022-01-18T01:20:25Z", "salary": {"currency": null, "max": null, "min": null, "period": "monthly", "term": null}, "salary_visible": false, "title_keywords": ["analyst"], "responsibilities": ["network infrastructure", "configuration", "monitoring", "implementation", "planning", "report", "administration"], "requirements": {"degrees": [], "majors": [], "languages": [], "language_level": [], "hard_skills": ["windows server", "firewall"], "soft_skills": ["hands-on", "responsible"], "languages_combined": []}, "experience_required": {"duration": ["at least 3 years"], "field": ["administration"]}}, {"job_id": "100003009055995", "location_code": "hk", "company": "Roctec Technology Ltd", "job_title": "Senior Network Engineer / Network Engineer", "description": "WHAT YOU\u2019LL BE DOING\n\nProvide technical supports on network and/or security projects\nProvide technical designs, implementations, and troubleshooting of network and/or security projects co-operating with internal parties, vendors and partners to customers.\n\nWHO WE\u2019RE LOOKING FOR\n\nDiploma or Degree holders in Computer or Information Engineering or related subjects\n2-5 years of relevant experience\nWith technical support experience on LAN, WAN, switches, routers and firewall\nHands on experience in H3C switches, FortiGate firewalls or Aruba wireless equipment\nHolding one or more of the following certificates is an advantage (e.g. H3CSE, CCNP, CCIE, NSE7, NSE8 etc.)\nGood Command in English and Cantonese\nGood communication and interpersonal skills\nProactive and can work independently or as a team\nCandidates with less experience will be considered as Network Engineer or Assistant Network Engineer\n\nRoctec Technology Ltd\u00a0offers you a bank holiday, medical benefits, 11 days\u2019 annual leave, special allowance, performance bonus, study sponsorship scheme. Special leaves for Birthday, Marriage, Paternity, etc. excellent career prospects & attractive remuneration to the right candidate.\u00a0\n\nYou will enjoy our work atmosphere with friendly work environment, casual dress code, free fruits, free drink and birthday party for you.\n\nInterested applicants, please apply by sending full resume with availability, present and expected salary, contact no. to us.\n\nPersonal data collected will be used for recruitment purposed only", "employment_types": ["Full Time", "Permanent"], "selling_points": ["Technical support on network / security projects", "Diploma holder in Computer / related disciplines", "2+ years of working experience"], "locations": ["North Point"], "categories": ["Information Technology (IT)", "IT Project Management / Team Lead", "Security", "Network & System"], "post_time": "2022-01-18T03:10:24Z", "salary": {"currency": null, "max": null, "min": null, "period": "monthly", "term": null}, "salary_visible": false, "title_keywords": ["engineer"], "responsibilities": ["technical supports", "technical support", "troubleshooting", "communication", "recruitment", "contact", "personal data", "internal parties"], "requirements": {"degrees": ["diploma", "degree"], "majors": ["engineering"], "languages": ["cantonese", "english"], "language_level": ["good command"], "hard_skills": ["no", "ccnp", "scheme", "firewall", "code", "wan"], "soft_skills": ["work independently", "troubleshooting", "hands on", "communication and interpersonal skills", "friendly", "proactive"], "languages_combined": [{"language": "cantonese", "language_level": ["good command"]}, {"language": "english", "language_level": ["good command"]}]}, "experience_required": {"duration": ["2-5 years"], "field": ["relevant experience"]}}, {"job_id": "100003009055929", "location_code": "hk", "company": "API Lab Testing Limited", "job_title": "System Support Engineer", "description": "Job Overview:\n\nWe seek a System Support Engineer to join Group IT to support our Hong Kong and global users.\n\nEssential Duties and Responsibilities:\n\nProvide remote and on-site IT support, software installation\u2019s, Upgrade, hardware replacement etc.\nSupport on Microsoft 365 related products and services\nProvide analysis of security log data from security devices\nAnalyze security incidents and formulate incident reports\nDesign technical solutions on multiple clouds that address clients\u2019 scalability, reliability, security, and performance requirements.\nEstablish and refine daily IT security operations tasks.\nSupport and maintain telephone resource management, firewall security and IT asset management.\nTroubleshoot the hardware and software in Windows / Mac, networking types of equipment, mobile (Android / iPhone), Printer, Projector, NAS\nSupport Copier and Audio & Video Conference\nWork closely with the Global IT team on systems\u2019 implementation and maintenance\n\nExperience & Competencies Required:\n\nGraduate or diploma or above in Information Technology, Computer Science, or related disciplines\nAt least 4 years of working experience in network/server administration and IT support and troubleshooting.\nFamiliar with network infrastructure, Firewall, Router, VPN, Endpoint Security.\nProficient in Windows Server, Backup solutions, Data Security, Office 365 Environments, Active Directory & Hybrid Exchange configuration and setup\nKnowledge of enterprise standards including logging, monitoring, access limitation, sensitive data handling\nGood team player but also can work on individual tasks without supervision.\nMust have a customer service-oriented attitude and good communication skills.\nGood command of spoken and written English and Chinese\n\nEducation and Qualifications Required:\n\nGraduate or diploma or above in Information Technology , Computer Science or related disciplines.\nAt least 4\u00a0 years of working experience in network / server administration and IT support and troubleshooting.", "employment_types": ["Full Time"], "selling_points": ["Group IT to support HK & Global, IT helpdesk", "Analysis of security, Multiple clouds solutions", "Office equipment maintenance, Microsoft 365"], "locations": ["Kowloon City"], "categories": ["Information Technology (IT)", "Support", "Security", "Network & System"], "post_time": "2022-01-18T03:06:01Z", "salary": {"currency": "HKD", "max": 34999, "min": 30000, "period": "monthly", "term": null}, "salary_visible": true, "title_keywords": ["system support", "engineer"], "responsibilities": ["software", "active directory", "data", "operations", "troubleshooting", "design", "communication", "maintain", "customer service", "troubleshoot", "administration", "configuration", "implementation", "reports", "audio", "setup", "network infrastructure", "installation", "management", "monitoring", "maintenance", "analysis", "systems", "hardware", "asset management"], "requirements": {"degrees": ["diploma or above"], "majors": ["related disciplines", "computer science", "information technology"], "languages": ["english", "chinese"], "language_level": ["good command"], "hard_skills": ["office 365", "maintenance", "server administration", "active directory", "analysis", "router", "hardware", "mobile", "vpn", "firewall", "nas", "windows server", "android", "exchange"], "soft_skills": ["communication skills", "good team player", "service-oriented", "troubleshooting", "troubleshoot", "sensitive", "active"], "languages_combined": [{"language": "english", "language_level": ["good command"]}, {"language": "chinese", "language_level": ["good command"]}]}, "experience_required": {"duration": ["at least 4 years"], "field": ["it support", "troubleshooting", "server administration"]}}, {"job_id": "100003009053156", "location_code": "hk", "company": "Arup", "job_title": "Identity Access Management Engineer", "description": "A career at Arup offers you the chance to make a positive difference in the world. Independently owned and independently minded, we attract a diverse mix of people to work on ground-breaking global projects. We have an ambitious commitment to be the digital leader in the built environment and have digital teams and experts all over the world, who collaborate on world-leading software, data and technology projects and products. Being a global team means we value people with diverse experiences, backgrounds,\u00a0specialisms\u00a0and skills.\u00a0\n\nThe role\u00a0\n\nWe currently have an opportunity for an\u00a0identity access management engineer to join our global team. You will be implementing multiple business to consumer services for Arup and our subsidiaries while also playing a major role in the team that looks after authentication and authorisation for the firm.\u00a0\n\nIt is an exciting time to join the\u00a0Identity Access Management (IAM) team which\u00a0has responsibility for organisational wide, fit-for-purpose,\u00a0identity platforms and services.\u00a0\u00a0We\u2019ve recently launched an industry first business to business automated authentication service.\n\nThe role reports to\u00a0the head of identity access management who is based in Newcastle, UK.\u00a0\u00a0\n\n\u201cOne of the best parts of our culture is the diversity - it allows us to be more effective, productive, tolerant and most importantly welcoming. I really enjoy working in a team that is doing really interesting and innovative work.\u201d\n\nAdrian, Toronto\n\n\nYou should apply if:\u00a0\n\nYou\u00a0would relish a working culture that will support your skills and career development\u00a0\nYou have strong interpersonal and communication skills, and enjoy working with diverse stakeholders\u00a0\nYou\u00a0are\u00a0motivated by the potential of technology to transform a global business\u00a0\n\nResponsibilities of the role\u00a0include:\u00a0\n\nManaging Arup\u2019s directory services (Active Directory, Azure Active Directory, Azure Active Directory Connect)\nDelivering privileged identity management and its applications to groups/roles\nManaging conditional access policy, including business and user impact\nManaging other Azure AD identity and security technologies and services such as identity risk, device management and enterprise applications\nManaging sync services such as AAD Connect, FIM, MIM and ADFS service\nBringing a culture of implementing Identity lifecycle management to all aspects of the role\nImplementing report and audit capabilities into solution designs, as well as utilising role-based access control implementation as a foundation of new design\nKeeping up to date with new authentication mechanisms and their possible benefits throughout the business\nRepresenting IAM as a service and promoting cyber standards to our stakeholders and end users\n\nRequirements and skills\n\nEssential skills and knowledge:\n\nPrevious experience of implementing an Azure B2C tenant and associated management activities\nSignificant experience of providing identity related services to customers, including identity lifecycle management\nSolid understanding and implementation experience of IAM governance\nExcellent understanding of cyber security concepts and how identity governance supports cyber security goals\nPrevious experience of developing identity and access related policies and standards\nExtensive knowledge of AD, Azure AD, ADFS, FIM, MIM, AD Connect, B2B and B2C\nExposure to identity related security technologies in Azure \u2013 SSPR, PIM, conditional access, multifactor authentication\nExcellent understanding of authentication mechanisms and standards\nExperience of developing and implementing role and attribute-based access control models\n\nDesirable skills and knowledge:\u00a0\n\nKnowledge of IT service processes (ITIL) and best practices can manage risk\nStrong communication and reporting skills\n\nRequired behaviours:\u00a0\n\nProfessional, with attention to detail - always seeking quality and excellence in their work\u00a0\nCollaborative approach and willingness to work as an integral part of the team\u00a0\u00a0\nExcellent consulting and stakeholder management skills, ability to challenge and influence, as well as being an agent for change\u00a0\nStrong influencing and negotiation skills working with multiple stakeholders (at all levels and across regions/virtually) with differing or complex views- with an ability to assess a situation and confidently influence and define the best approach to achieve the desired outcome\u00a0\nA problem-solver, always seeking the best solution for the right outcome\u00a0\nFriendly manner, with a willingness to adapt style and approach to achieve quality results\u00a0\nSelf-motivated, results-focussed, pragmatic with the ability to manage conflicting deadlines and prioritise\u00a0\nRapid, enthusiastic learner who quickly becomes a leading authority on new capabilities and tools and take others on the journey\u00a0\nEnjoys engaging and collaborating with others in different culture,\u00a0countries\u00a0and time zones on a day-to-day basis with some\u00a0adhoc\u00a0travel anticipated\u00a0\n\nPlease don\u2019t be discouraged if you don\u2019t meet every point above \u2013 if you\u202fmeet most, and are strongly motivated by the role, and willing to learn, we are still interested in hearing from you.\u202f\u00a0\n\nQualifications\u00a0\n\nEducated to degree level, or equivalent experience\u00a0is desirable\nProfessional technical accreditations such as MCP, MCSE, VCP, NCIE\u00a0is desirable\nCyber security or IAM related certification is desirable\n\nWe offer a competitive remuneration package commensurate with qualifications and experience to the right candidate including Global Profit Share scheme, additional fringe benefits of maternity / paternity leave and long-term career development opportunities.\n\nFor interested applicants, please click \u201cApply Now\u201d to submit your online application.\n\nPersonal data collected will be used for recruitment purpose only. Applicants not contacted within 8 weeks may consider their applications unsuccessful.", "employment_types": ["Full Time", "Permanent"], "selling_points": [], "locations": ["Kowloon City"], "categories": ["Information Technology (IT)", "Security", "Network & System", "Others"], "post_time": "2022-01-17T06:09:41Z", "salary": {"currency": null, "max": null, "min": null, "period": null, "term": null}, "salary_visible": false, "title_keywords": ["engineer"], "responsibilities": ["management", "active directory", "audit", "implementation", "design", "access control", "report"], "requirements": {"degrees": [], "majors": [], "languages": [], "language_level": [], "hard_skills": [], "soft_skills": [], "languages_combined": []}, "experience_required": {"duration": [], "field": []}}, {"job_id": "100003009054218", "location_code": "hk", "company": "Easy Great Technology Limited", "job_title": "Network Engineer / Senior Network Engineer", "description": "Rewards you deserve:\n\nGenerous remuneration\nDiscretionary Bonus / Performance Bonus\n5 Days Work Week,\n13 days or above AL, Marriage Leave\nMedical + Dental insurance\nBirthday coupon\nWork-Life Balance\nOn job training\n\nJob Responsibilities:\n\nPerform network infrastructure deployment & maintenance\u00a0\nProvide technical support solutions and consultation on solving clients\u2019 technical issues\nSupport Server and Network System installation and configuration\nProvide technical solution in solving clients' technical issues\n\nJob Requirements:\n\nDiploma /Degree holder in\u00a0Engineer,Computer Science\u00a0or related disciplines\nA minimum of\u00a03\u00a0years\u00a0network infrastructure\u00a0experience\nHands-on experience in different network and security product (i.e. F5, Impreva, Palo Alto, Cisco, Juniper, SIEM etc.)\nCertification in CCNP, CISA, CISSP or equivalent will be advantageous\nFresh graduates will be considered as Assistant Engineer", "employment_types": ["Full Time"], "selling_points": ["Network operation and support", "Excellent Career Path", "Competitive Salary, 5-day work"], "locations": ["Tsim Sha Tsui"], "categories": ["Information Technology (IT)", "Security", "Network & System", "Others"], "post_time": "2022-01-17T08:50:19Z", "salary": {"currency": null, "max": null, "min": null, "period": "monthly", "term": null}, "salary_visible": false, "title_keywords": ["engineer"], "responsibilities": ["network infrastructure", "installation", "maintenance", "configuration", "technical support"], "requirements": {"degrees": ["diploma", "degree holder"], "majors": ["related disciplines", "computer science"], "languages": [], "language_level": [], "hard_skills": ["ccnp"], "soft_skills": ["hands-on"], "languages_combined": []}, "experience_required": {"duration": ["minimum of 3 years"], "field": ["infrastructure", "security"]}}, {"job_id": "100003009048858", "location_code": "hk", "company": "Gravitas Recruitment Group", "job_title": "IT Security Engineer", "description": "Job Summary:\n\nThe IT Security Engineer leads the design, installation, and management of the security infrastructure and security procedures, serves as the functional lead for cybersecurity investigations and incident response.\n\nResponsibilities:\n\nInfrastructure Security and Cyber Security\n\n\u25cf Administer the firewall working closely with other IT team members.\n\n\u25cf Manage the implementation of a Security Incident and Event Management (SIEM) system and security projects by working closely with other IT team members.\n\n\u25cf Build and administer the business continuity infrastructure.\n\n\u25cf Work together with other IT Infrastructure team members in implementing a secure IT Infrastructure.\n\n\u25cf Lead the investigation and incident response.\n\n\u25cf Implement, maintain and operate information security solutions according to IT security strategy.\n\n\u25cf Support asset deployments, upgrades, and maintenance, including servers, databases, network assets, and wireless intrusion detection LAN security\n\nEXPERIENCE AND QUALIFICATIONS\n\n\u25cf University graduate with a degree in Information Security, Computer Science, or other related disciplines preferred.\n\n\u25cf Holder of security certificates such as SANS/GIAC, CEH, CISSP, CISM, CISA, ISO27000/27001 is preferred.\n\n\u25cf Holder of certificates such as CCNA, CCNP is preferred.\n\n\u25cf Minimum 4 years working experience with at least three years in IT security preferred.\n\n\u25cf Knowledge of operating systems (Windows, Unix, Linux, and Macintosh), backups, virtualization technologies\n\n\u25cf Experience with vulnerability assessments and penetration methods\n\n\u25cf Familiar with advanced routing, switching, remote access, multilayer switching, CISCO IOS security, VPN security, and troubleshooting.\n\n\u25cf Knowledge of cyber security or security products such as firewall, IDS/IPS, web proxy, EDR/XDR, IAM, Sandbox, SIEM is preferred.\n\n\u25cf Familiar with Cybersecurity frameworks, such as MITRE ATT&CK, OWASP, NIST, is preferred.\n\n\u25cf Experience with working in a network security environment highly preferred, such as Security Operations Center (SOC), Computer Emergency Response Team (CERT), Computer Incident Response Team (CIRT), Computer Incident Response Center (CIRC), or Cyber Security Incident Response Center (CSIRC) preferred.", "employment_types": ["Full Time", "Permanent"], "selling_points": ["International environment", "Good work-life balance environment", "Internal flexibility in job functions"], "locations": ["Not Specified"], "categories": ["Information Technology (IT)", "Security", "Network & System", "Others"], "post_time": "2022-01-14T07:29:00Z", "salary": {"currency": "HKD", "max": 54999, "min": 35000, "period": "monthly", "term": null}, "salary_visible": true, "title_keywords": ["engineer"], "responsibilities": ["business continuity", "information security", "cyber security", "operations", "troubleshooting", "design", "maintain", "proxy", "it infrastructure", "infrastructure", "implementation", "operating systems", "installation", "management", "upgrades", "procedures", "investigation", "backups", "maintenance", "databases"], "requirements": {"degrees": ["university graduate", "degree"], "majors": ["related disciplines", "computer science"], "languages": [], "language_level": [], "hard_skills": ["linux", "servers", "maintenance", "cyber security", "web", "ccnp", "ccna", "databases", "firewall", "vpn"], "soft_skills": ["troubleshooting", "advanced"], "languages_combined": []}, "experience_required": {"duration": ["minimum 4 years", "at least three years"], "field": ["it", "security", "team"]}}, {"job_id": "100003009044739", "location_code": "hk", "company": "Mizuho Bank, Ltd", "job_title": "Senior Vice President, Cybersecurity, Systems Planning & Development Section", "description": "Company Overview\n\nMizuho has a long-term commitment to the Hong Kong market. With strong ties to Mizuho\u2019s global network and a workforce of over 600 staff in Hong Kong, we are able to help corporations in Hong Kong to expand their business worldwide. Our clients primarily comprise Japanese and non-Japanese corporations (including those domiciled in the PRC), financial institutions, and government and quasi-government organizations. We provide a full spectrum of corporate banking services to our customers including syndicated loans, treasury, transaction banking, financial advisory, project finance, merger and acquisition, leveraged finance, and structured finance.\n\nWhy Mizuho\n\nAt Mizuho, we provide the stability of an international industry leader with the career trajectory of a growing business. Our steady, strategic growth gives our people at all levels rewarding degrees of responsibility and a richer work experience than a boutique firm or an established giant could offer alone.\n\nIt is the local expertise of our employees that makes our global network so powerful. By collaborating with colleagues and clients who have your same ambition and drive, you can amplify your sphere of influence and base of knowledge as part of one of the largest\u2014and growing\u2014banks in the world.\n\nAbout the Team\n\nSystems Planning & Development Section (SPD) is responsible for overall system planning of Hong Kong office, EUC/RPA development, PoC for new system solution, and security control. System Security Control Team is mainly responsible for conducting user ID and access authority control, system security monitoring, software license control, database management, firewall management, penetration test and follow up, coordinate assessment for regulatory requirement, support Head office and local system projects and follow up the revision of system security policy, guideline and let related staff to understand them.\n\nRole requirements\n\nTo assume a team lead position to manage all-round Cybersecurity function for the Bank\nTo identify potential threats of and report on security violations and control weaknesses in cybersecurity by determining causes, possible solutions and remedial actions required for ensuring data security;\nTo recommend and implement changes to procedures and systems designed to enhance systems security;\nTo develop and conduct IT security awareness training programs for all units within the Bank and ensure IT security/risk compliance within the bank;\nTo develop and maintain the system security procedures to cope with policy and standard established by Head Office, and to follow up the revision of System Security Policies and Guidelines;\nDesign, develop and update IT risk management framework, policies and controls taking into consideration the bank\u2019s strategy, current/future regulatory requirements and emerging risk scenario; Communicate IT risk management standards, policies and procedures to stakeholders of bank;\nAssess the potential cybersecurity impact of emerging technologies and innovations, and include known risk and issues;\nTo delegate the assignments and supervise subordinates in overall daily security control operations of all systems.\n\nEssential Functions\n\nPerform assigned tasks in a correct and timely manner;\nAlways observe compliance of policies and procedures;\nMonitor and make recommendations for process improvement;\nProvide covers all activities related to System Security Control team members.\n\nCompetencies\n\nWe are looking for an individual who sets challenging individual or Team targets to contributes to our customer, organization and Section, and has strong motivation to achieve the targets;\nEnhances internal and external network and acquires knowledge for executing deals and tasks;\nNurtures the performance and potential of juniors by providing regular feedback/guidance.\n\nWork experience, education and skills\n\nBachelor degree in computer science or IT;\nMinimum 5 years related experience in Cybersecurity;\nSupervisory experience is essential;\nFamiliar with Windows Serve installation and security administration, Windows Active Directory, Domain Group Policy, DBMS administration (MSSQL, Oracle, etc), networking device and firewall configuration and administration and practical experience for those setting and monitoring;\nProficiency in English and Cantonese;\nHolding professional level qualification that are specified in HKMA Enhanced Competency Framework on Cybersecurity (ECF-C).\n\nApplication\n\nPlease indicate your\u00a0current and expected salary\u00a0on CV for the application.\n\n\u00a0Mizuho Bank, Limited\n\nMizuho Bank, Ltd. in Hong Kong is an integral part of the Japan-based Mizuho Financial Group, Inc. (NYSE: MFG). The Mizuho group is a global financial services leader with offices in nearly 40 countries, approximately 60,000 employees, and assets of almost USD 2 trillion. Mizuho provides expertise in retail banking, corporate finance, investment banking, asset management, capital markets, and sales and trading, to help businesses develop and find new opportunities for growth. To learn more: www.mizuhogroup.com\n\nPersonal data collected will be kept in strict confidence, and will be used for recruitment purpose only.", "employment_types": ["Full Time", "Permanent"], "selling_points": ["Bachelor degree in computer science or IT", "Min. 5 years' related experience in Cybersecurity", "Supervisory experience is essential"], "locations": ["Tsim Sha Tsui"], "categories": ["Information Technology (IT)", "Security", "Testing / QA", "Network & System"], "post_time": "2022-01-13T06:01:48Z", "salary": {"currency": null, "max": null, "min": null, "period": "monthly", "term": null}, "salary_visible": false, "title_keywords": ["vice president"], "responsibilities": ["banking"], "requirements": {"degrees": [], "majors": [], "languages": ["japanese"], "language_level": [], "hard_skills": [], "soft_skills": ["structured"], "languages_combined": [{"language": "japanese", "language_level": []}]}, "experience_required": {"duration": [], "field": []}}, {"job_id": "100003009049717", "location_code": "hk", "company": "Drake Overload Ltd", "job_title": "Cyber Security Manager", "description": "Cyber Security Manager\n\nOur client is a publicly listed company with international businesses in properties, hospitality, logistics. They are currently looking for a Cyber Security Manager in group level to join their IT team in Hong Kong.\n\n\nResponsibilities\n\nTo strengthen 24/7 security operations capabilities, especially on incident response\nEnforce good cyber hygiene and conduct cyber security awareness program\nConduct cyber security reviews and risk assessments on new technologies, IT systems and digitization solutions\nDefine and implement cyber security improvement projects to counter latest cyber threats\nDevelop and maintain cyber security policy, standards and guidelines\nOversee IT Disaster Recovery (DR) capability and conduct regular ITDR drills\nPlan and manage cyber security budget and measure its effectiveness\nAutomate security operations and upkeep the technical capabilities of the team\nParticipate in deployment and maintenance of enterprise security documents\n\nRequirements\n\nBachelor Degree in Computer Science, Engineering, information security, related disciplines\n8 years of experience in cyber security, with at least 3 years in management role\nExperience in supporting endpoint security solutions, McAfee, Symantec, Carbon Black, FireEye HX etc.\nGood understanding of common cyber-threats, penetration/intrusion techniques and attack vectors\nUnderstanding of CVSS, CVE, CWE, CPE, CCE, CWE, OVAL, SCAP and/or other standards\nKnowledge in SIEM solutions (Splunk, QRadar, ArcSight, AlienVault, etc.),\u00a0Azure, AWS\nFamiliar with IT protocols, security products, cyber security and data protection standards\nExcellent interpersonal and presentation skills\nFluency in written and spoken English & Cantonese\nHolder of CISA, CISM, CISSP or CCSP\n\nWhat does it mean for you\n\nThis is an excellent opportunity to join a reputable and growing company. The position is ideal for professional in IT security to take a permanent role and seek for career progression in a global enterprise.\n\nTo Apply\n\nIf you feel your experience and professionalism can make an impact with this firm, please click the Apply now button.\n\nDue to a\u00a0high volume of applicants,\u00a0only\u00a0shortlisted candidates will be contacted.\n\nPersonal data provided by job applicants will be used strictly in accordance with the employer's personal data policies and for recruitment services purposes only.", "employment_types": ["Full Time", "Permanent"], "selling_points": ["Listed company, properties, hospitality, logistics", "Management level role, report to Group IT Director", "Holder of CISA, CISM, CISSP or CCSP"], "locations": ["Central & Western Area"], "categories": ["Information Technology (IT)", "IT Auditing", "Security", "Network & System"], "post_time": "2022-01-14T09:09:23Z", "salary": {"currency": "HKD", "max": 119999, "min": 70000, "period": "monthly", "term": null}, "salary_visible": true, "title_keywords": ["manager"], "responsibilities": ["maintenance", "cyber security", "guidelines", "operations", "systems", "budget", "develop", "hygiene", "maintain", "plan"], "requirements": {"degrees": ["degree", "bachelor"], "majors": ["related disciplines", "engineering", "computer science"], "languages": ["cantonese", "english"], "language_level": ["fluency"], "hard_skills": ["make", "aws", "azure", "cyber security"], "soft_skills": ["presentation skills", "interpersonal", "ideal"], "languages_combined": [{"language": "cantonese", "language_level": ["fluency"]}, {"language": "english", "language_level": ["fluency"]}]}, "experience_required": {"duration": ["at least 3 years", "8 years"], "field": ["management", "security"]}}, {"job_id": "100003009055419", "location_code": "hk", "company": "Shangri-La International Hotel Management Limited", "job_title": "System Administrator", "description": "We are currently looking for a System Administrator to\u00a0provide\u00a0technical support and maintenance of technology infrastructure\u00a0of the Group.\n\nAs a System Administrator, we will rely on you to:\n\nProvide technical support for all aspects of the back end IT infrastructure including:\n- Windows Active Directory\n- Virtualized servers (VMWare / Hyper-V)\n- Storage Area Network\n- Office 365 / Azure Platform\n- Network firewalls, switches\n- Connectivity infrastructure\nPerform performance management and capacity planning\nEvaluate, analyze, design and implement new projects in IT infrastructure\nManagement of disaster recovery planning and ensure smooth cutover during outages\nCo-ordinate with IT vendors to deploy appropriate hardware, network devices and software solutions\nParticipate in an after-hours, rotating support duty roster to remotely provide technical support during critical system outages\n\nWe are looking for someone who has:\n\nBachelor\u2019s Degree in Information Technology or relevant discipline\nMinimum 3\u00a0years of experience in IT infrastructure technical design and support\nCertification in\u00a0\u00a0VCP5 (VMware Certified Professional), MCSA (Microsoft Certified Solutions Associate), MCSE (Microsoft Certified Solutions Expert) and CISSP (Certified Information Systems Security Professional)\u00a0is preferred\nExperience in using VMware vCenter for virtualization management\nTechnical support experience in SAN (HP 3Par, NetApp and HDS)\u00a0\nStrong analytical and problem solving skills\nProficiency in both written and spoken English, Cantonese and Mandarin", "employment_types": ["Full Time", "Permanent"], "selling_points": ["Corporate IT Infrastructure", "Based in Global Headquarter", "Exp. in IT Infrastructure Design & Support"], "locations": ["Quarry Bay"], "categories": ["Information Technology (IT)", "Support", "Security", "Network & System"], "post_time": "2022-01-18T02:31:17Z", "salary": {"currency": null, "max": null, "min": null, "period": "monthly", "term": null}, "salary_visible": false, "title_keywords": ["system administrator"], "responsibilities": ["management", "it infrastructure", "active directory", "maintenance", "technical support", "recovery planning", "outages", "infrastructure", "co-ordinate with", "software", "design", "systems", "evaluate", "hardware", "deploy", "planning"], "requirements": {"degrees": ["degree", "bachelor"], "majors": ["information technology"], "languages": ["cantonese", "english", "mandarin"], "language_level": ["proficiency"], "hard_skills": ["hyper-v", "office 365", "mcse", "azure", "servers", "active directory", "maintenance", "vmware", "hardware", "mcsa", "problem solving skills"], "soft_skills": ["analytical and problem solving skills", "active", "smooth"], "languages_combined": [{"language": "cantonese", "language_level": ["proficiency"]}, {"language": "english", "language_level": ["proficiency"]}, {"language": "mandarin", "language_level": ["proficiency"]}]}, "experience_required": {"duration": ["minimum 3 years"], "field": ["infrastructure", "management", "it", "design"]}}, {"job_id": "100003009043864", "location_code": "hk", "company": "Advanced Assembly Materials International Limited", "job_title": "IT Security Administrator", "description": "Responsibilities:\n\nDeveloping and implementing sufficient measures to detect cyber threats\nImplement IT security policies\nMaintaining IT system integrity\nDetermine potential risks and vulnerabilities inside the system\nRecognize problems within systems by identifying uncharacteristic activity\nAssess current situations with the network security and carry out audits\n\nRequirements:\n\nDegree in IT Security / Computer Science / Information Technology / Information System or relevant disciplines\nMinimum 3 years\u2019 working experience in IT security area\nHands-on experience in firewall, antivirus software and web proxy management administration\nCISA, CISSP holder preferred\nFrequent business travels to Asian countries and day trip to Mainland China are required", "employment_types": ["Full Time", "Permanent"], "selling_points": ["5-day work", "Flexible working hours", "Competitive remuneration package"], "locations": ["Shatin Area"], "categories": ["Information Technology (IT)", "IT Auditing", "Security", "Network & System"], "post_time": "2022-01-13T02:14:02Z", "salary": {"currency": null, "max": null, "min": null, "period": "monthly", "term": null}, "salary_visible": false, "title_keywords": ["administrator"], "responsibilities": ["maintaining", "policies", "systems", "developing", "audits"], "requirements": {"degrees": ["degree"], "majors": ["it", "computer science", "information technology"], "languages": [], "language_level": [], "hard_skills": ["web", "information system", "antivirus", "firewall"], "soft_skills": ["hands-on"], "languages_combined": []}, "experience_required": {"duration": ["minimum 3 years"], "field": ["management", "it", "security", "administration"]}}, {"job_id": "100003009053067", "location_code": "hk", "company": "Orient Overseas Container Line Ltd (OOCL)", "job_title": "Senior Technical Analyst / Technical Analyst - Networking", "description": "\u00a0Accelerate your career\n\nExperience the latest technologies in global network infrastructure, software-defined network, hybrid cloud and cyber security\nGain exposure in running a global data, voice network and hybrid multi-cloud network infrastructure\u00a0\n\nYour role\n\nTechnology driver on Software-Defined Network, Hybrid Cloud, Network Security and Unified Communications\nArchitectural design and Implementation on Global Network Infrastructure projects\nProvide second tier support on global network, IP telephony and Contact Centre for global offices\nResearch and evaluate new technologies on networking, cloud and cyber security\u00a0\n\nWho we are looking for\n\nUniversity graduate in Computer Science, Computer Engineering or related discipline\nMinimum 3 years\u2019 working experience in Software-Defined Network, Next-Generation firewall, Hybrid Cloud, Unified Communication or Cyber Security\nSelf-motivated, analytical, with curious mindset\nEager to learn in a fast-paced and dynamic environment\nHolder of CCNA / CCNP is preferable\nDemonstrate a good learning track record with excellent interpersonal and communication skills\nGood command of spoken and written English, Mandarin is an advantage\nHigh quality candidate with less experience will also be considered for a junior position\nInterested parties please send your application letter with detailed resume and expected salary by clicking \"Apply Now\" .\n\n(Data collected will be used for recruitment purpose only.)", "employment_types": ["Full Time", "Permanent"], "selling_points": ["Software-Defined Network, Network Security", "Global Network Infrastructure projects", "5-day work, Double Pay, Discretionary Bonus"], "locations": ["Shatin Area"], "categories": ["Information Technology (IT)", "Application Specialist - Network", "Security", "Network & System"], "post_time": "2022-01-17T05:33:52Z", "salary": {"currency": null, "max": null, "min": null, "period": "monthly", "term": null}, "salary_visible": false, "title_keywords": ["analyst"], "responsibilities": ["network infrastructure", "software", "data", "cyber security", "quality", "implementation", "design", "evaluate", "communication", "contact"], "requirements": {"degrees": ["university graduate"], "majors": ["computer engineering", "computer science"], "languages": ["english", "mandarin"], "language_level": ["advantage", "good command"], "hard_skills": ["cyber security", "ccnp", "ccna", "ip", "unified communication", "dynamic", "firewall"], "soft_skills": ["communication skills", "self-motivated", "dynamic environment", "communication", "eager to learn", "learning", "interpersonal"], "languages_combined": [{"language": "english", "language_level": ["advantage", "good command"]}, {"language": "mandarin", "language_level": ["advantage", "good command"]}]}, "experience_required": {"duration": ["minimum 3 years"], "field": ["infrastructure", "security"]}}, {"job_id": "100003009049152", "location_code": "hk", "company": "Hong Kong Interbank Clearing Ltd", "job_title": "Specialist I (Information Security)", "description": "Major Responsibilities\n\n\nParticipate in the development and maintenance of corporate-wide information security framework, policy, guideline, standard, and operation procedures with reference to ISO27001 standard and applicable best practices;\nPerform day-to-day security administration and operation including but not limited to management of end users and privileged accounts, keys and certificates, review of security logs, performance of technical vulnerability assessment and penetration testing as well as handling of security incidents, etc.;\nAssess and recommend information security control measures, as well as monitor the implementation for major projects;\nParticipate in the implementation of security solutions and infrastructure collaborating with internal teams and external service providers;\nMonitor and analyse security events for detection, investigation and response to potential security issue;\nMaintain and monitor appropriate computer and network access controls, data, and physical security to ensure no security exposure;\nParticipate in cyber threat intelligence analysis when required\nAssist to define information security risk indicators; collect, analyse and interpret the corresponding statistics for assisting senior management in overseeing information security risk;\nIdentify control gaps, review the residual risk level and make recommendation for risk treatment;\nInterpret security key risk statistics for reporting to senior management on regular basis\nPromote security awareness and ensure compliance with applicable security standards\nReview and make recommendation on using of Open Source Software (OSS) and freeware\nExecute security operation procedures in accordance with the corporate information security policy and guidelines when required\nKeep abreast of technological knowledge in managed area of responsibility, and provide recommendations for adaptation of new security technologies and standard with reference to prevailing industry best practices\nPerform other job duties as assigned by the supervisors\n\nRequirements\n\nUniversity degree preferably in information technology, information security or related discipline\nMinimum 4 years of experience in information security or related field\nKnowledge in security practices and standards commonly adopted by the banking/financial industry such as the Cyber Resilience Assessment Framework (C-RAF), SWIFT Customer Security Controls Framework (CSCF), ISO27001 standard, etc. is an advantage;\nTeam player with sound interpersonal, communication and presentation skills as well as excellent problem solving and analytical skills;\nHolder of security certificates - CRISC, CISA, CISM, CISSP or other equivalent certificates is an advantage\nExperience and knowledge in the area of public and/or private cloud security is an advantage\nPractical experience and knowledge in risk management framework and methodology is desirable\nExperience in working for major financial institutions is preferred but not a must\nGood command of written and spoken English and Chinese\nWilling to work shift duty (evening shift normally from 12:30 to 21:30 with shift duty allowance)\nCandidate from non-financial industries will also be considered\nCandidate with less experience may be considered for appointment as Specialist II (Information Security)", "employment_types": ["Full Time", "Permanent"], "selling_points": [], "locations": ["Ngau Tau Kok"], "categories": ["Information Technology (IT)", "Security"], "post_time": "2022-01-14T08:11:01Z", "salary": {"currency": null, "max": null, "min": null, "period": null, "term": null}, "salary_visible": false, "title_keywords": ["specialist"], "responsibilities": ["software", "information security", "data", "maintain", "penetration testing", "senior management", "administration", "control", "infrastructure", "monitor", "implementation", "teams", "reporting", "management", "make recommendation", "review", "procedures", "investigation", "security operation", "provide recommendations", "maintenance", "guidelines", "analysis", "ensure compliance", "analyse"], "requirements": {"degrees": ["university degree"], "majors": ["information technology"], "languages": ["english", "chinese"], "language_level": ["good command"], "hard_skills": ["swift", "c", "problem solving", "analytical skills"], "soft_skills": ["communication", "problem solving and analytical skills", "presentation skills", "team player", "interpersonal"], "languages_combined": [{"language": "english", "language_level": ["good command"]}, {"language": "chinese", "language_level": ["good command"]}]}, "experience_required": {"duration": ["minimum 4 years"], "field": ["related", "risk management", "financial institutions", "security"]}}, {"job_id": "100003009051914", "location_code": "hk", "company": "Dah Sing Financial Group", "job_title": "Systems Analyst (General Insurance)", "description": "Job Purpose:\n\nResponsible for analyzing & designing, developing and maintaining application software.\nLead the development team for applications implementation.\nCo-ordinate\u00a0 with internal teams, users and external vendors to ensure deliverables are meeting the requirement.\nLarge scale project in general insurance industry with good exposure on new Agile methodology, core systems (B2B & B2C system) and new InsurTech.\n\nMain Responsibilities:\u00a0\n\nResponsible for application software development to deliver values according to customer needs.\nResponsible for defining system requirement to ensure business requirements and problems are addressed.\nLead the development team to deliver on time and with good quality.\nPerform code review to ensure code quality and standard are met\nConduct system test and escalate issues and recommend solution & workaround for discussion and decision.\nParticipate in Agile environment and ensure development team follows standard and practice properly.\nCo-ordinate with internal teams, users and external vendors to ensure deliverables are meeting the requirement.\nResponsible for smooth production rollout.\nHandle user queries and production support including bug fixes and enhancements.\nStay up-to-date on technologies and experience to perform more complex requirement analysis and technical design of large scale project.\nProvide guidance and coaching to the subordinates &/or team members.\nPerform ad hoc projects as assigned by supervisor.\n\nIncumbent Requirements:\n\n\u00a0a. \u00a0 \u00a0 Academic & Professional Qualifications\n\nUniversity graduate in Information Technology, Computer Science or equivalent.\n\n\u00a0b.\u00a0\u00a0\u00a0\u00a0 Experience\n\nAt least 9-11 years relevant experience in software development.\nStrong experience in Web application and Database development.\nExperience in General Insurance application system is preferred.\nExperience in Agile methodology is preferred.\n\n\u00a0c. \u00a0 \u00a0 Knowledge & Skill Required\n\nAble to work independently, excellent Analytical, problem solving and organizing skills, and a fast learner.\nGood leader and team player, strong writing and communication skills.\n\nd.\u00a0\u00a0\u00a0\u00a0 Sound technical knowledge\n\nJava J2EE multi-tier architecture\nAngular JS, HTML, CSS, XML, JSON\nRestful API\nApache, JBoss Server 7\nEclipse, Maven\nGIT, JMeter\nSQL Queries , MS SQL Server, Oracle DB\n\u00a0\n\nPlease note that only shortlisted candidates will be notified.\n\n\n", "employment_types": ["Permanent"], "selling_points": ["Responsible for analyzing & designing, developing", "Responsible for application software development", "University graduate in Information Technology"], "locations": ["North Point"], "categories": ["Information Technology (IT)", "Security", "Network & System", "Others"], "post_time": "2022-01-17T01:31:31Z", "salary": {"currency": null, "max": null, "min": null, "period": "monthly", "term": null}, "salary_visible": false, "title_keywords": ["analyst"], "responsibilities": ["software", "co-ordinate with", "analysis", "review", "teams", "quality", "design", "ad hoc projects", "provide guidance"], "requirements": {"degrees": ["university graduate"], "majors": ["computer science", "information technology"], "languages": [], "language_level": [], "hard_skills": ["java", "restful api", "apache", "agile", "web", "professional qualifications", "git", "ms sql server", "application system", "html", "problem solving", "sql", "c", "angular", "server", "css", "oracle"], "soft_skills": ["communication skills", "work independently", "agile", "problem solving", "team player", "fast learner"], "languages_combined": []}, "experience_required": {"duration": ["at least 9-11 years"], "field": ["general insurance", "development", "relevant experience", "database", "software development"]}}, {"job_id": "100003009045703", "location_code": "hk", "company": "Computer Recruitment Consultants Ltd", "job_title": "Security Engineer / Senior Security Engineer", "description": "One of our clients, a major bank is currently seeking a suitable candidate to join their elite team.\n\nResponsibilities:\n\nCoordinate, prioritize, filter and fulfill various Security related requests initiated by various BU / SU with regard to DLP Controls (Email, USB, Web) and folder permissions.\nExecute the Bank-wide revalidation processes such as Data Loss Prevention Controls (Email, USB), LAN Account, VPN Token, Folder Permissions and etc. in accordance to Bank Security Policies.\nTest and deploy application whitelisting security controls.\u00a0 Troubleshoot the quarantined during the detection stage.\u00a0\u00a0\u00a0\u00a0\nAssist in the preparation of Security Awareness Training material and conducting debrief sessions.\nPerform administration, consolidation and analysis of Security Deviations or Weakness and report the implementation or rectification status to immediate supervisor.\nConsolidate the Cybersecurity status figures and report to the Immediate Supervisor or IT management.\nPerform any other ad-hoc tasks as per requests.\n\nRequirements:\n\nDegree / Diploma in Computer Science or related discipline\n2 - 7 years working experience in IT Security\nCertified in CISSP, CISA, CISM or other recognized certificate is preferred\nBasic knowledge on Security Project administration and coordination.\nFamiliar with Information Security requirement of Banking industry and related regulatory guidelines issued from HKMA on Customer Data Protection.\nWorking experiences from Banking / Financial institutions are more preferred.\n\nInterested parties, please forward your resume in WORD FORMAT to us by clicking here Computer Recruitment Consultants Ltd or fax to 2528-9091.\u00a0\u00a0 The information provided by candidates will be treated in strict CONFIDENTIAL and will only be used for recruitment purpose\u00a0", "employment_types": ["Full Time"], "selling_points": ["2 - 7 years working experience in IT Security", "Fulfill Security request", "Execute the Bank-wide revalidation processes"], "locations": ["Quarry Bay"], "categories": ["Information Technology (IT)", "Security"], "post_time": "2022-01-14T04:31:57Z", "salary": {"currency": null, "max": null, "min": null, "period": "monthly", "term": null}, "salary_visible": false, "title_keywords": ["engineer"], "responsibilities": ["data", "policies", "analysis", "rectification", "ad-hoc tasks", "implementation", "coordinate", "it management", "troubleshoot", "deploy", "report", "administration"], "requirements": {"degrees": ["certificate", "diploma", "degree"], "majors": ["computer science"], "languages": [], "language_level": [], "hard_skills": ["hkma", "basic"], "soft_skills": ["coordination"], "languages_combined": []}, "experience_required": {"duration": ["2 - 7 years"], "field": ["financial institutions", "it", "security", "banking"]}}, {"job_id": "100003009046746", "location_code": "hk", "company": "VTECH Corporate Services Ltd", "job_title": "Information Security Engineer (VCO204/J10)", "description": "Responsibilities:\n\nSupport and maintain security solutions, including antivirus, next generation firewall, web application firewall, endpoint encryption, log analysis tools\u00a0\nWork with IT operation to monitor and identify security issues\nConduct regular security assessment on IT systems\nCreate and maintain security standards and guidelines for technical platforms, including OS, web application platform and network devices\nKeep tabs on latest security threats, attacks and updates\nAssist the Information Security Manager on the following tasks\nInformation security incident response\nAdministration of security awareness training program\nConduct research and study on security solutions\nIdentify and manage security risks of business functions and processes\n\nRequirements:\n\n\nDegree in Computer Science or the equivalent with minimum 3 years of relevant experience in IT, cybersecurity and risk management\nHolder of security certifications, e.g. CISSP, CISA, CCSP, CCSK, CEH, ComTIA, is preferred\nProficiency in security configuration for Windows, Linux and network devices\nGood knowledge in TCP/IP, network security, OWASP Top 10 for web application security\nGood Analytical skills\nExperience with IT audits, cloud computing, IT/security frameworks (e.g. ISO27001) is an advantage\n\n", "employment_types": ["Full Time", "Permanent"], "selling_points": ["IT, cybersecurity and risk management", "Proficiency in security configuration", "5-day work, flexible working hour, double pay"], "locations": ["Tai Po Area"], "categories": ["Information Technology (IT)", "Security"], "post_time": "2022-01-14T00:39:50Z", "salary": {"currency": null, "max": null, "min": null, "period": "monthly", "term": null}, "salary_visible": false, "title_keywords": ["engineer"], "responsibilities": ["information security", "guidelines", "analysis", "systems", "monitor", "maintain", "conduct research", "administration"], "requirements": {"degrees": ["degree"], "majors": ["risk management", "it", "computer science"], "languages": [], "language_level": [], "hard_skills": ["linux", "web application security", "tcp", "analytical skills", "ip"], "soft_skills": ["analytical skills"], "languages_combined": []}, "experience_required": {"duration": ["minimum 3 years"], "field": ["risk management", "it", "relevant experience", "security"]}}, {"job_id": "100003009045760", "location_code": "hk", "company": "Karin Technology Holdings Ltd.", "job_title": "Network and Security Expert", "description": "Responsible for post-sales support to resellers and customers\nParticipate in Demo &\u00a0POC setup and testing\nParticipate the project implementation of large-scale/Enterprise network\n\nRequirements:\n\n\nDiploma / Degree holder in relevant discipline or equivalent\nSolid IT networking and security knowledge\nUnderstanding of LAN / WAN, TCP/IP networking, DNS, VPN, firewall router and switch\nAt least of 3 years relevant working experiences in implement and support network and security solutions\nHolder of IT certification such as CCNA, CCNP, CISSP, PCNSA, PCNSE or equivalent will be advantage but not a must\nA good team player with strong communication and interpersonal skills\nCapable to work under pressure with self-motivation, and able to work independently\nGood communication in both written and spoken Cantonese and English\nCandidate with less experience would be considered as Network and Security Engineer.\n\nWe offer a competitive remuneration package to the right candidate. Interested parties please send your full resume with\u00a0present and expected salary\u00a0by email to recruitment\u00aekarin.com.hk\u00a0or\u00a0clicking 'Apply Now'.\n\nCompany Address: 9/F, The Whitney, 183 Wai Yip Street, Kwun Tong, Hong Kong\n\n(We are an Equal Opportunity Employer and personal data collected would be used for recruitment purpose only.)", "employment_types": ["Full Time", "Permanent"], "selling_points": ["Participate in Demo & POC setup and testing", "Implementation of large-scale/Enterprise network", "3 years relevant working experiences"], "locations": ["Kwun Tong"], "categories": ["Information Technology (IT)", "Support", "Security", "Network & System"], "post_time": "2022-01-15T03:49:31Z", "salary": {"currency": null, "max": null, "min": null, "period": "monthly", "term": null}, "salary_visible": false, "title_keywords": [], "responsibilities": ["dns", "implementation", "testing", "communication", "setup", "work under pressure"], "requirements": {"degrees": ["diploma", "degree holder"], "majors": [], "languages": ["cantonese", "english"], "language_level": ["good"], "hard_skills": ["sales support", "dns", "tcp", "switch", "ccnp", "ccna", "router", "ip", "vpn", "firewall", "wan"], "soft_skills": ["good team player", "work independently", "capable", "responsible", "communication", "communication and interpersonal skills", "self-motivation", "work under pressure"], "languages_combined": [{"language": "cantonese", "language_level": ["good"]}, {"language": "english", "language_level": ["good"]}]}, "experience_required": {"duration": ["of 3 years"], "field": ["security"]}}, {"job_id": "100003009054060", "location_code": "hk", "company": "eCloudvalley Technology (HK) Limited", "job_title": "Cloud Engineer/Cloud Developer", "description": "Do you like helping enterprise clients implement innovative cloud solutions and solve technical problems? Do you want to be the leader and demonstrate how the emerging technologies (such as A.I., Big Data, Cloud, DevOps) can be applied to businesses? With business growth and global expansion opportunities, we are looking for a highly motivated\u00a0Cloud Engineer/Cloud Developer to help accelerate our growing technical team. This is an excellent opportunity to join a world class technical team, working with some of the best and brightest engineers and account managers while also developing your skills and furthering your career within one of the most innovative and progressive technology young companies in Hong Kong.\n\nResponsibilities includes but is not limited to:\n\n\u00b7 Understanding clients\u2019 requirements and design technical solutions on AWS that address clients\u2019 requirements for scalability, reliability, security, and performance.\n\n\u00b7 Work closely and support sales team from technical perspective.\n\n\u00b7 Work closely with a team of architects and engineers to create technical documents and proposals.\n\n\u00b7 Conduct proof-of-concept demonstrations, technical presentations, and sharing.\n\n\u00b7 Respond to technical issues in a professional and timely manner.\n\n\u00b7 Maintain technical skills and knowledge of market trends and competitive insights; collaborate and share with the technical community.\n\nRequirements:\n\n\u00b7 Bachelor's degree in Computer Science, Computer Engineering, Information Technology or relevant field.\n\n\u00b7 2-4+ years' experience designing, executing and supporting IT cloud solutions.\n\n\u00b7 Experience architecting, designing and programming applications in an AWS Cloud environment.\n\n\u00b7 Hands-on experience with cloud computing technologies in AWS preferred\n\n\u00b7 Current AWS Certified Solutions Architect \u2013 Professional preferred\n\n\u00b7 Knowledge of cloud computing technologies on AWS and current computing trends.\n\n\u00b7 Architectural knowledge of data center infrastructure including networking, servers, storage infrastructure and virtualization.\n\n\u00b7 Positive attitude and a strong commitment to delivering quality work.\n\n\u00b7 Effective communication skills (written and verbal)\n\n\u00b7 Putonghua and English are mandatory", "employment_types": ["Full Time", "Permanent"], "selling_points": [], "locations": ["Wan Chai"], "categories": ["Information Technology (IT)", "Support", "IT Management", "Security"], "post_time": "2022-01-17T08:15:51Z", "salary": {"currency": null, "max": null, "min": null, "period": "monthly", "term": null}, "salary_visible": false, "title_keywords": ["developer", "engineer"], "responsibilities": ["collaborate", "presentations", "design", "maintain", "sales team"], "requirements": {"degrees": ["degree", "bachelor"], "majors": ["computer engineering", "computer science", "information technology"], "languages": ["putonghua", "english"], "language_level": [], "hard_skills": ["servers", "computing technologies", "aws", "programming", "cloud environment"], "soft_skills": ["positive attitude", "communication skills", "hands-on"], "languages_combined": [{"language": "putonghua", "language_level": []}, {"language": "english", "language_level": []}]}, "experience_required": {"duration": ["4+ years"], "field": ["it", "programming"]}}, {"job_id": "100003009049421", "location_code": "hk", "company": "Shanghai Commercial Bank Ltd", "job_title": "Assistant Manager / Officer, Information Security", "description": "Responsibilities:\n\nPerform vulnerability scanning, penetration test and security assessments\nReview security log and system configuration for IT technical infrastructure\nDevelop and maintain information security system products and tools\nAssist to develop and implement IT control process\nSetup and maintain IT security systems covering SIEM, AV, IPS\u00a0\n\nRequirements:\n\nDegree or Diploma holder in Computer Science or related disciplinesProfessional qualifications of CISA, CISSP or equivalent\nMinimum 3 years of experience in IT security\nProficiency in Windows/Unix/Linux Operating Systems, TCP/IP networking and security products\nGood knowledge in SIEM, AV, IPS, Web Gateway and Firewall preferred\n\nAttractive remuneration package will be offered to the right candidates. Interested parties please click \"Apply Now\" to submit your full resume with current and expected salary to the Human Resources Division or by post to G.P.O. Box 139, Hong Kong.\n\nPlease visit us at www.shacombank.com.hk for more information about our Bank.\n\nAll personal data collected will be used for recruitment related purposes strictly in accordance with the Bank's personal data policies, a copy of which will be provided immediately upon request by contacting our Personal Data Compliance Officer. Applicants who are not contacted within two months may consider their applications unsuccessful and the personal data collected from the applicants will be retained for no longer than two years from the date of rejection during which the applicants may be considered for other suitable positions within the Bank.", "employment_types": ["Full Time", "Permanent"], "selling_points": ["Perform vulnerability scanning & penetration test", "Review security log and system configuration", "Develop and maintain information security system"], "locations": ["Kwai Hing"], "categories": ["Banking / Finance", "Others", "Information Technology (IT)", "Security", "Others"], "post_time": "2022-01-15T03:50:26Z", "salary": {"currency": null, "max": null, "min": null, "period": "monthly", "term": null}, "salary_visible": false, "title_keywords": ["assistant manager", "officer"], "responsibilities": ["scanning", "control", "information security", "configuration", "infrastructure", "review", "systems", "develop", "maintain", "setup"], "requirements": {"degrees": ["diploma holder", "degree"], "majors": ["computer science"], "languages": [], "language_level": [], "hard_skills": ["linux", "web", "tcp", "ip", "firewall"], "soft_skills": [], "languages_combined": []}, "experience_required": {"duration": ["minimum 3 years"], "field": ["it", "security"]}}, {"job_id": "100003009053069", "location_code": "hk", "company": "Orient Overseas Container Line Ltd (OOCL)", "job_title": "Technical Analyst - Office Intelligence Solution / Infrastructure", "description": "Accelerate your career\n\nExperience the latest technology on cloud and infrastructure services\nLearn and apply the latest technologies in building enterprise office intelligence solution and infrastructure services\nGain global exposure on office intelligence solution management\u00a0\n\nYour role\n\nParticipate in enterprise office intelligence solution design, solution and software development\nResearch and evaluate new technologies on different office intelligence solutions\nInteract directly with users through user centered design techniques including observational research, interviews, and concept testing to uncover needs, learn about user behavior and explore design concepts.\nTranslate visionary ideas or requirements into thoughtful and compelling design concepts and work with team members to muck up both low and high-fidelity prototypes and implement solution for different business users globally\nParticipate in server and desktop solution research and development\nParticipate in architectural design and implementation of infrastructure services\n2nd tier technical support of infrastructure servers platform\u00a0\n\nWho we are looking for\n\nBachelor\u2019s degree in Computer Engineering, Computer Science or IT related disciplines\nEager to learn in a fast-paced and dynamic environment\nPassionate in pursuing IT professionalism\nAt least 2 years of IT infrastructure support and administration in an enterprise environment\nProficient in Microsoft Windows Server and desktop operating environment and network (Windows 2016 Server, Active Directory, DNS, Windows 10 Desktop)\nKnowledge on cloud product like Azure, AWS and O365\nGood command of spoken and written English, Mandarin is an advantage\u00a0\n\nPlease send your application letter with detailed resume and expected salary by clicking \"Apply Now\" and quote the reference number on the subject\u00a0\n\n(Data collected will be used for recruitment purpose only.)", "employment_types": ["Full Time", "Permanent"], "selling_points": ["5 day work week + Benefits", "Opportunities to explore to new technologies", "Good team player; Strong communication skills"], "locations": ["Shatin Area"], "categories": ["Information Technology (IT)", "Hardware", "Application Specialist - Network", "Security"], "post_time": "2022-01-17T05:33:53Z", "salary": {"currency": null, "max": null, "min": null, "period": "monthly", "term": null}, "salary_visible": false, "title_keywords": ["analyst"], "responsibilities": ["design concepts", "management", "ideas", "software", "it infrastructure", "active directory", "technical support", "dns", "data", "infrastructure", "implementation", "design", "testing", "evaluate", "recruitment", "administration"], "requirements": {"degrees": ["degree", "bachelor"], "majors": ["related disciplines", "it", "computer engineering", "computer science"], "languages": ["english", "mandarin"], "language_level": ["advantage", "good command"], "hard_skills": ["o365", "infrastructure support", "azure", "servers", "active directory", "dns", "aws", "windows 10", "dynamic", "server", "windows server"], "soft_skills": ["passionate", "dynamic environment", "eager to learn", "visionary", "active", "detailed"], "languages_combined": [{"language": "english", "language_level": ["advantage", "good command"]}, {"language": "mandarin", "language_level": ["advantage", "good command"]}]}, "experience_required": {"duration": [], "field": ["infrastructure"]}}, {"job_id": "100003009050556", "location_code": "hk", "company": "Ambition", "job_title": "Information Security Manager - Financial Services - Hong Kong", "description": "Information Security Manager - Financial Services - Hong Kong\n\nOur client is a leading financial services group, and they are now looking for a high calibre Information Security Manager to join their fast-growing team.\n\nResponsibilities:\n\nYou will develop a security governance function including facilitation of Information Security Committee.\nYou will lead refresh of annual Policies, Standards, Information Security Strategy and Roadmaps.\nYou will develop and manage Information Security compliance function.\nYou will maintain Information Security policies and controls, based on industry standards and best practices which incorporate all applicable legislative and regulatory requirements.\nYou will develop and maintain an Information Security dashboard andmetrics that provide an accurate representation of the information security risk profile and relevant cyber threats.\nYou will coordinate and oversee timely completion of internal and external audits and control assurance findings.\nYou will ensure Information and Cyber Security risks are logged, identified and reported regularly to Information Security Committee and Group Technology Risk Management.\nYou will build a security culture within IT by providing guidance, awareness and advocacy of Information Security.\nYou will work closely with Risk, Legal and Compliance team to handle high profile breaches and incidents.\n\nRequirements:\n\nRelevant University degree in Computer Science, Information Management, or related field, or equivalent experience.\nRelevant experience with information security and governance, risk and compliance methods.\nExperience working with financial institutions and critical national infrastructure.\nExperience with industry best-practice approaches to the governance, operation and management of IT systems (e.g., NIST, ISO 27000, SANS Critical Controls, ITIL,COBIT).\nStrong business acumen and technology knowledge can work effectively with Senior Management.\nStrong written communication skills, experienced with writing board-level papers and verbal presentations to senior management.\n\nPlease send your cv to Jessie.Rao@ambition.com.hk\n\nIf this job isn't quite right for you, but you know someone who would be great at this role, why not take advantage of our referral scheme? We offer HKD1000 in Apple gift cards for every referred candidate who we place in a role. Terms & Conditions Apply. https://www.ambition.com.hk/refer-a-friend", "employment_types": ["Full Time", "Permanent"], "selling_points": ["Information Security Manager", "Financial Services", "Based in Hong Kong"], "locations": ["Not Specified"], "categories": ["Information Technology (IT)", "IT Management", "Security", "Technical / Functional Consulting"], "post_time": "2022-01-14T10:44:03Z", "salary": {"currency": "HKD", "max": 69999, "min": 55000, "period": "monthly", "term": null}, "salary_visible": true, "title_keywords": ["information security manager"], "responsibilities": ["guidance", "control", "management", "information security", "cyber security", "policies", "regulatory requirements", "compliance", "internal and external audits", "develop", "coordinate", "maintain"], "requirements": {"degrees": ["relevant university degree"], "majors": ["computer science"], "languages": [], "language_level": [], "hard_skills": ["itil", "scheme", "presentations", "acumen"], "soft_skills": ["business acumen", "communication skills", "work effectively"], "languages_combined": []}, "experience_required": {"duration": [], "field": ["management", "related", "compliance", "infrastructure", "operation", "relevant experience", "security", "it", "financial institutions"]}}, {"job_id": "100003009045582", "location_code": "hk", "company": "Resources Link Network Ltd", "job_title": "IT Security Consultant", "description": "Responsibilities\n\nParticipate in our customers\u2019 security project, external & internal compliance audit support, security operation including training, security incident and response, core system user account review, vulnerability lifecycle management\nAssists to drive cybersecurity-related projects including scope definition, vendor coordination, scheduling, and technical implementation.\nProvide IT security advisory services to our customers on security standards, the architecture of new products, applications, and systems, and implementing security controls in existing systems and applications\nConduct security risk assessment for application projects, infrastructure, and adoption of new technologies\nDesign security solutions in security measures to implement security tools for projects\nDevelop and maintain security architecture (e.g. reference architectures, principles, models, templates, standards, and procedures)\nAssists to develop Security Operation Center (SOC) and establish KPI to formalize the measurement of the degree of attack and our defense ability\u00a0\n\n\n\nRequirements\n\nDegree holder or above in Computer Science or IT related disciplines\nAt least 5 years with Information Technology Risk and Security experience, and/or experience as IT Security Auditor/Consultant\nHolder of Industry certifications such as CISSP, CISM, CISA, CRISC. CEH, ISO Lead Auditor preferred\nProven track record of project management experience and proficient in IT risk management, IT risk auditing, and compliance\nFamiliar with security technologies such as SIEM, SOAR, UEBA, DLP, Antivirus, EDR, WAF, IPS/IDS, Anti-DDoS Services, Forensic Tools and Vulnerability Scanners\nKnowledgeable with Anti-bot solutions, Network and Application Layer Firewalls, Cryptography, Authentication, PCI DSS requirements, web application architecture, vulnerability assessment, and application penetration testing, endpoint security, patch management, and hardening\nA good team player with strong communication and interpersonal skills\nSelf-initiative and high sense of responsibility with a can-do attitude\nGood command of Cantonese, Mandarin, and English", "employment_types": ["Full Time"], "selling_points": ["Attractive Salary Package and Career Pathway", "Work-Life Balance, 5-Days Work a Week", "Consulting and Implementation Work for Government"], "locations": ["Wan Chai"], "categories": ["Information Technology (IT)", "Security", "Technical / Functional Consulting"], "post_time": "2022-01-13T08:08:04Z", "salary": {"currency": null, "max": null, "min": null, "period": "monthly", "term": null}, "salary_visible": false, "title_keywords": ["consultant"], "responsibilities": ["management", "measurement", "review", "compliance", "audit", "implementation", "systems", "infrastructure", "scheduling", "security operation", "design", "develop", "maintain", "coordination", "architecture", "procedures"], "requirements": {"degrees": ["degree holder"], "majors": ["related disciplines", "it", "computer science"], "languages": ["cantonese", "english", "mandarin"], "language_level": ["good command"], "hard_skills": ["project management", "web", "antivirus"], "soft_skills": ["good team player", "can-do attitude", "high sense of responsibility", "project management", "communication and interpersonal skills", "self-initiative"], "languages_combined": [{"language": "cantonese", "language_level": ["good command"]}, {"language": "english", "language_level": ["good command"]}, {"language": "mandarin", "language_level": ["good command"]}]}, "experience_required": {"duration": ["at least 5 years"], "field": ["risk management", "compliance", "information technology", "project management", "it", "security"]}}, {"job_id": "100003009045891", "location_code": "hk", "company": "Kinetix Systems Ltd", "job_title": "Security Consultant", "description": "Job Description\n\nProvide IT security consultancy services for clients\nConduct security assessment and audit for clients' IT systems\nDevelop / evaluate new security products / services\nProvide implementation services for security systems\n\nRequirements\n\nBachelor' degree or above in Computer Science or IT related disciplines\nCertification of CISA / CISM / CISSP is a must\nMinimum 4 years of IT experience with at least 2 years in IT security\nExperience in IT audit, IT risk advisory or related aspects\nGood understanding of IT system platforms and IT security services\nExperience in government's SRAA projects is an advantage\nExperiences in vulnerability scanning on web and mobile applications and code review is an advantage\nIf you enjoy working in a friendly and challenging working environment, please send your full resume with your availability, last/current and expected salary by clicking \u201cApply Now\u201d.\n\n*All information collected will be used for recruitment purpose only and will be kept strictly confidential*", "employment_types": ["Full Time", "Permanent"], "selling_points": ["CISA / CISM / CISSP is a must", "Exposure on different projects and clients", "Comprehensive remuneration package"], "locations": ["Kwun Tong"], "categories": ["Information Technology (IT)", "IT Auditing", "IT Management", "Security"], "post_time": "2022-01-13T09:02:41Z", "salary": {"currency": null, "max": null, "min": null, "period": "monthly", "term": null}, "salary_visible": false, "title_keywords": ["consultant"], "responsibilities": ["systems", "audit", "implementation", "develop", "evaluate"], "requirements": {"degrees": ["degree or above", "bachelor"], "majors": ["related disciplines", "it", "computer science"], "languages": [], "language_level": [], "hard_skills": ["mobile", "code", "web"], "soft_skills": ["enjoy working", "friendly"], "languages_combined": []}, "experience_required": {"duration": ["minimum 4 years", "at least 2 years"], "field": ["related", "audit", "it experience", "it", "security"]}}, {"job_id": "100003009045045", "location_code": "hk", "company": "China Mobile Hong Kong \u4e2d\u570b\u79fb\u52d5\u9999\u6e2f", "job_title": "Senior Information Security Officer", "description": "CHINA MOBILE HONG KONG COMPANY LIMITED (\"CMHK\") is the wholly-owned subsidiary of China Mobile Limited (HKEx: 941) (NYSE: CHL), which ranks 47th on the Fortune Global 500.\n\nOur company strives to offer superior service experience and to become the preferable digital partner for customers. We are preserving an environment with trust, responsibility and caring. At CMHK, we commit to maximizing people\u2019s potential and paving the way toward success for every striver. We are now inviting high caliber professional to join us.\n\nDepartment: System Operation & Maintenance \u00a0\n\nIn this position, you will :\n\nParticipate in security project, external & internal compliance audit support, security operation including training, security incident and response, core system user account review, vulnerability lifecycle management\nEstablish, maintain and update documentation on the policies, processes, guidelines and security reports\nEstablish, maintain, and operationalize the process for Change and Release Management to ensure the production environment with standardized process and procedures are used for efficient handling of changes to minimize incidents due to change & release\nLead the Change and Release Management process activities across various IT functions within the organization including coordination, monitoring and reporting as a continuous service improvement cycle.\nAct as a focal point for all escalation and communication activities related to users and IT teams to ensure effective and efficient execution of change activities. Highlight and escalate risk & issues to management.\nDefine and measure success metrics and monitor Change and Release progresses\nOther task and responsibility assigned by Team Lead and Department Manager\n\nTo be successful in this position, you should meet the following requirements:\n\nDegree or above in Information Technology, Computer Science or related disciplines\n5+ years\u2019 with Information Security and IT Service Management\nITIL v4 and CISSP or Cyber Security equivalent certification is a MUST\nExperience with international compliance standard : ISO 27001 and ISO 20000 & \u00a0ITIL Framework and SOX\nUnderstanding DevOps and ITIL complementary\nExcellent technical knowledge of mainstream operating system, networking, security technology\nProven track record in Change and Release Management\nWorking knowledge of IT security, especially Data Security domain is an advantage\nExcellent communication skills to facilitate cross team collaboration and different departments\nSelf-initiative and high sense of responsibility with can-do attitude\nStrong sense and passion for information security\nGood command of Cantonese, Mandarin and English\nHigh sense of urgency and ability to multitask and work well under pressure among ad-hoc, project, and management\u2019s request concurrently\u00a0\nLess experience candidates will be consider as IT Security Officer\n\nCMHK is committed to be an equal opportunity employer. We offer exceptional benefits package and the opportunity to work in a challenging environment. Personal data provided by applicants will be treated strictly in accordance with our personal data policy and for recruitment purposes only.\n\nPlease submit your application to us by clicking the\u00a0Apply Now\u00a0\u00a0button and completing the on-line application process.", "employment_types": ["Full Time", "Permanent"], "selling_points": ["Degree in Information Technology/Computer Science", "5+ years\u2019 with Information Security and IT Service", "ITIL v4 and CISSP/Cyber Security certification"], "locations": ["Kwai Hing"], "categories": ["Information Technology (IT)", "IT Management", "Security", "Network & System"], "post_time": "2022-01-13T07:00:31Z", "salary": {"currency": null, "max": null, "min": null, "period": null, "term": null}, "salary_visible": false, "title_keywords": ["senior information security officer"], "responsibilities": ["ad-hoc", "it service", "information security", "cyber security", "data", "audit", "communication", "maintain", "compliance", "teams", "monitor", "reports", "reporting", "management", "review", "procedures", "monitoring", "security operation", "documentation", "maintenance", "guidelines", "policies", "coordination"], "requirements": {"degrees": ["degree or above"], "majors": ["related disciplines", "computer science", "information technology"], "languages": ["cantonese", "english", "mandarin"], "language_level": ["good command"], "hard_skills": ["itil", "focal", "maintenance", "cyber security", "devops", "mobile", "documentation"], "soft_skills": ["efficient", "communication skills", "under pressure", "can-do attitude", "passion for", "urgency", "high sense of responsibility", "communication", "committed", "self-initiative", "coordination", "ability to multitask", "superior"], "languages_combined": [{"language": "cantonese", "language_level": ["good command"]}, {"language": "english", "language_level": ["good command"]}, {"language": "mandarin", "language_level": ["good command"]}]}, "experience_required": {"duration": [], "field": ["digital", "compliance", "it", "security"]}}, {"job_id": "100003009050585", "location_code": "hk", "company": "Ambition", "job_title": "Information Security Engineer - Financial Services - Hong Kong", "description": "Information Security Engineer - Financial Services - Hong Kong\n\nOur client is a leading financial services group, and they are now looking for a high calibre Information Security Engineer to join their fast-growing team.\n\nResponsibilities:\n\nYou will identify and define system security requirements\nYou will design computer security architecture and develop detailed cyber security designs\nYou will prepare and document standard operating procedures and protocols\nYou will configure and troubleshoot security systems and infrastructure devices\nYou will develop technical solutions and new security tools to help mitigate security vulnerabilities and automate repeatable tasks\nYou will work with product vendors and suppliers to maintain and enhance existing security tooling and products\nYou will write comprehensive reports including assessment-based findings, outcomes and propositions for further system security enhancement\n\nRequirements:\n\nRelevant University degree in Computer Science, Information Management, or related field, or equivalent experience\nStrong experience in building, maintaining and operating security systems and platforms\nExperience in firewalls ,intrusion detection systems, anti-virus software, authentication systems, log management, content filtering, data loss prevention systems, etc\nExperience with network security and networking technologies and with system, security, and network monitoring tools\nStrong information security technology knowledge/concepts and can effectively communicate with senior management\nFamiliar with web related technologies and of network/web related protocols\nFamiliar with cloud security technologies (AWS or Azure is preferred)\nFamiliar with risk / control frameworks, such as Mitre ATT&CK, D3FEND, OWASP, NIST Cybersecurity Framework\n\nPlease send your cv to Jessie.Rao@ambition.com.hk\n\nIf this job isn't quite right for you, but you know someone who would be great at this role, why not take advantage of our referral scheme? We offer HKD1000 in Apple gift cards for every referred candidate who we place in a role. Terms & Conditions Apply. https://www.ambition.com.hk/refer-a-friend", "employment_types": ["Full Time", "Permanent"], "selling_points": ["Information Security Engineer", "Financial Services", "Based in Hong Kong"], "locations": ["Not Specified"], "categories": ["Information Technology (IT)", "Support", "Security", "Network & System"], "post_time": "2022-01-14T10:50:03Z", "salary": {"currency": "HKD", "max": 69999, "min": 55000, "period": "monthly", "term": null}, "salary_visible": true, "title_keywords": ["engineer"], "responsibilities": ["cyber security", "systems", "procedures", "infrastructure", "design", "develop", "system security", "maintain", "troubleshoot", "reports", "architecture"], "requirements": {"degrees": ["relevant university degree"], "majors": ["computer science"], "languages": [], "language_level": [], "hard_skills": ["azure", "scheme", "web", "aws"], "soft_skills": [], "languages_combined": []}, "experience_required": {"duration": [], "field": ["related", "management", "security"]}}, {"job_id": "100003009044660", "location_code": "hk", "company": "Komsearch Talent", "job_title": "(Senior) Cyber Security Officer", "description": "Responsibilities:\n\nConduct IT technical or audit consultancy assignments (including general IT controls, application reviews and cyber security assessments)\nIdentify control weaknesses, analyse evidential information and suggest practical recommendations for risk mitigation and process improvement\nLiaise with group's companies to formulate action plans and assist in drafting and presenting audit reports to senior management\nSupport financial and operational audits (e.g., revenue assurance and data governance) and ad-hoc projects (e.g., fraud investigations) with IT expertise (e.g., data analytics and CAAT programs)\n\nRequirements:\n\nDegree holder in Computing or related fields with relevant professional qualifications (e.g., CISA, CISSP and CPA)\nExperience relevant to IT cyber security / consultancy / programming\nKnowledge in IT infrastructure (e.g., firewall, virtual machines and IaaS), database query languages (e.g., MySQL), common web development languages (e.g., JavaScript and PHP) and cyber kill chain\u00a0\nHands-on experience on vulnerability scanning tools (e.g., Burp and Qualys) and knowledge on IT-related regulations and standards (e.g., ISO 27001, NIST and GDPR)\nGood command of Cantonese, English and Putonghua", "employment_types": ["Full Time", "Permanent"], "selling_points": ["Cyber Security", "Auditing", "Programming"], "locations": ["Tsuen Wan Area"], "categories": ["Information Technology (IT)", "Security"], "post_time": "2022-01-13T05:05:49Z", "salary": {"currency": null, "max": null, "min": null, "period": "monthly", "term": null}, "salary_visible": false, "title_keywords": ["officer"], "responsibilities": ["control", "ad-hoc projects", "cyber security", "data", "audit", "audits", "reports", "liaise with", "plans", "senior management", "analyse"], "requirements": {"degrees": ["degree holder"], "majors": [], "languages": ["cantonese", "putonghua", "english"], "language_level": ["good command"], "hard_skills": ["web development", "cyber security", "professional qualifications", "php", "cpa", "javascript", "programming", "firewall"], "soft_skills": ["hands-on"], "languages_combined": [{"language": "cantonese", "language_level": ["good command"]}, {"language": "putonghua", "language_level": ["good command"]}, {"language": "english", "language_level": ["good command"]}]}, "experience_required": {"duration": [], "field": ["it", "security", "programming"]}}, {"job_id": "100003009046496", "location_code": "hk", "company": "Bank of China Group Insurance Company Limited", "job_title": "IT Security Manager", "description": "Job Description\n\nResponsible for routine security threats discover, detection, mitigation and report following requirement from Bank of China HQ and HK Insurance Authority;\nResponsible for IT security assessment, vulnerability management and risk management;\nManage IT security related policy, guideline and ensure the policies are followed by all staffs;\nResponsible for IT security operational support with IT teams and external vendor.\nJob Requirement\n\nDegree or above in Computer Science, Information Technology or related fields;\u00a0\nMinimum 5 years' professional experience in information security or related fields;\nSound knowledge in IT security and compliance concepts, architecture and controls;\nQualification in CISA / CISM / CISSP or equivalent security certification will be advantage;\nGood understanding and experience of technologies related to cyber security, like patch management, firewall, SIEM, web application security, vulnerability scanning, data protection, security hardening etc.;\nGood interpersonal and communication skill with a good command of spoken and written Chinese and English.", "employment_types": ["Full Time", "Permanent"], "selling_points": [], "locations": ["Central"], "categories": ["Information Technology (IT)", "Security"], "post_time": "2022-01-13T12:14:57Z", "salary": {"currency": "HKD", "max": 54999, "min": 30000, "period": "monthly", "term": null}, "salary_visible": true, "title_keywords": ["manager"], "responsibilities": ["management", "operational support", "policies", "teams", "vulnerability management", "insurance", "report"], "requirements": {"degrees": ["degree or above"], "majors": ["computer science", "information technology"], "languages": ["english", "chinese"], "language_level": ["good command", "good"], "hard_skills": ["firewall", "web application security", "cyber security"], "soft_skills": ["communication skill", "interpersonal"], "languages_combined": [{"language": "english", "language_level": ["good command", "good"]}, {"language": "chinese", "language_level": ["good command", "good"]}]}, "experience_required": {"duration": ["minimum 5 years"], "field": ["related", "management", "security"]}}, {"job_id": "100003009055581", "location_code": "hk", "company": "Ambitious People Group", "job_title": "Senior DevOps Engineer - Blockchain Company (Defi)", "description": "What will you do as a DevOps Developer?\n\nAs a devOps engineer, you will work in a well-known blockchain company. You will be responsible for the transformation of the cloud platform. implement CI/CD pipeline on development and deployment. A part from that, you will invovle in the system design including API and data flow. You will also deliver the implementation with DevOps and automation tool. In addition, you will support the security team to build a reliable system on AWS.\n\nWhat is offered to you?\n\nA competitive salary range up to 25000 to 50000 HKD per month:\n\n* Guarantee 13 months;\n* Medical and dental;\n* 15 AL;\n* Internal career growth plan;\n\nWhat is expected of you?\n\n* 3 years of development experience;\n* Experience in CI/CD workflow and container services, eg. AWS, Docker;\n* Experience in GitHub and New Relic will be a plus;\n* Good communication in English;\n\nWhere are you going to work?\n\nThe office is located at Tsim Sha Tsui. This blockchain company has developed a application that connect people to digital assets, mobile payments, and DeFi services. You can also find their token on the well-known crypto currency plateform. The team you will be working in is a heavily scrum oriented team with daily stand-ups to share their and your progress. All your colleagues are smart and energetic.\n\nLearn more or apply directly?\n\nDoes the job suit you well and do you want to start a new challenging job? If you want to apply directly, click on the 'Apply' button. Not sure if the vacancy fits your experience and wishes? Feel free to contact me for more information about this vacancy and/or other possibilities, you can contact me via + 852 3511 6201 or mail me at cheryl.ng@ambitiouspeople.com.", "employment_types": ["Full Time", "Permanent"], "selling_points": ["Monthly salary HKD 25,000 to HKD 50,000 per month", "Gurantee 13 months", "Good communication in English"], "locations": ["Not Specified"], "categories": ["Information Technology (IT)", "Support", "Software Development", "Security"], "post_time": "2022-01-18T02:45:22Z", "salary": {"currency": "HKD", "max": 54999, "min": 25000, "period": "monthly", "term": null}, "salary_visible": true, "title_keywords": ["engineer"], "responsibilities": ["data", "implementation", "communication", "system design", "payments", "contact", "plan"], "requirements": {"degrees": [], "majors": [], "languages": ["english"], "language_level": ["good"], "hard_skills": ["blockchain", "plus", "crypto currency", "devops", "aws", "mobile", "system design", "container", "deployment"], "soft_skills": ["communication", "energetic", "reliable", "responsible"], "languages_combined": [{"language": "english", "language_level": ["good"]}]}, "experience_required": {"duration": ["3 years"], "field": ["development"]}}, {"job_id": "100003009052488", "location_code": "hk", "company": "GrammyTech Ltd", "job_title": "System Analyst", "description": "Job Responsibilities:\n\nResponsible for system analysis and application development\nMonitor the system and provide maintenance support for current systems\nResponsible for system rollout, deployment and operation support\u00a0\nConduct SIT, UAT, system and software testing\n\nJob Requirements:\n\nDegree holder in Computer Science, Engineering or equivalent\nProficient in C#.NET is preferred\nExperience with using enterprise DMS/EDMS package is preferred;\nImmediate available is an advantage.\n\n\n\nInterested parties, please send your full resume in word format together with salary expectation to katherineli @grammytech.com\n\n(All data collected would be used for recruitment purposes only)", "employment_types": ["Full Time"], "selling_points": ["IT Project", "System Analysis", "Good Career Progression"], "locations": ["Kwun Tong Area"], "categories": ["Information Technology (IT)", "Application Specialist - Network", "Security", "Network & System"], "post_time": "2022-01-17T03:10:29Z", "salary": {"currency": null, "max": null, "min": null, "period": "monthly", "term": null}, "salary_visible": false, "title_keywords": ["system analyst"], "responsibilities": ["uat", "software", "maintenance support", "analysis", "systems", "monitor", "testing", "application development"], "requirements": {"degrees": ["degree holder"], "majors": ["engineering", "computer science"], "languages": [], "language_level": [], "hard_skills": ["c#"], "soft_skills": [], "languages_combined": []}, "experience_required": {"duration": [], "field": []}}, {"job_id": "100003009044515", "location_code": "hk", "company": "Pinpoint Asia Limited", "job_title": "Data Security Technology Manager - Enterprise Security Office", "description": "Our client, a leading enterprise, is looking for a Data Security Technology Manager in their large Security Technology office in Hong Kong.\u00a0 The successful candidate will be the key person in providing Information Security advisory for their strategic project. Interesting project exposure.\n\nResponsibilities:\n\nManage the IT Security Solutions design, development, and integrations particularly for Data Lake, Data Warehouse, and Analytics. Evaluate the security controls, technical capabilities, and timeline of such technology integrations.\nManage the technical implementation, security solution development across the project development lifecycle working with IT Governance and Technical teams.\nMake decisions and solve technical problems to provide an efficient technical environment for solutions implementation.\nProvide technical support in the security log, feeds, and raw source into SIEM for data security analytics.\nEnable dashboards for monitoring security information for the management and Cyber SOC team, to be able to provide various degrees of visibility in both real-time and past periods of the security events.\n\nRequired:\n\nAround 8 years of technology experience in technology security ideally in a large enterprise environment.\u00a0\nHands-on experience in enterprise security infrastructure and risk assessment.\nBackground and certifications in Information Security and Risk (CISSP, CEH, GIAC, etc)\nWorking experience in information security or IT Audit with consulting firm background is a great plus.\nDeep understanding of database encryption technologies, database proxies, and secure protocols, etc.\nDeep understanding of security threats with respect to SQL injection attacks, virtual private databases and database auditing, searchable encryption.\nAble to implement security solutions such as Demisto, Splunk, ELK, Carbon Black, Darktrace, ALSID, and/or Tufin.\nGood knowledge and experience of Database Security, Data Protection, Database Encryption technologies, Data Flow Mapping etc.\nGood design and solution knowledge of Certificate Authority and PKI infrastructure and operations.\nExperience in managing secure network infrastructure, Anti-DDoS, NG Firewall, IDS/IPS, WAF, Secure MTA, Load Balancer, Internet Proxy, as well as DNS hosting.\nStrong project management and stakeholders management skills.\nExcellent Communications Skills in English.\nBachelor's Degree from a reputable University.\n\nIf this outstanding opportunity sounds like your next career move, please send your resume in Word format to Danny Kwan at resume(at)pinpointasia(dot)com and put Data Security Technology Manager - Enterprise Security Office in the subject header.\n\nData provided is for recruitment purposes only.", "employment_types": ["Full Time", "Permanent"], "selling_points": ["Data Specific Security", "1LOD Blue Team", "Large Enterprise Environment"], "locations": ["Others - Macau"], "categories": ["Information Technology (IT)", "IT Auditing", "IT Management", "Security"], "post_time": "2022-01-13T04:25:10Z", "salary": {"currency": null, "max": null, "min": null, "period": "monthly", "term": null}, "salary_visible": false, "title_keywords": ["technology manager"], "responsibilities": ["information security", "data", "consulting", "operations", "audit", "design", "database", "proxy", "infrastructure", "teams", "implementation", "network infrastructure", "management", "monitoring", "solve technical problems", "dns", "technical support", "evaluate", "project management", "recruitment", "databases", "auditing"], "requirements": {"degrees": ["certificate", "degree", "bachelor"], "majors": ["design"], "languages": ["english"], "language_level": ["excellent"], "hard_skills": ["plus", "dns", "data warehouse", "word", "sql", "make", "project management", "databases", "firewall"], "soft_skills": ["efficient", "project management", "hands-on", "deep"], "languages_combined": [{"language": "english", "language_level": ["excellent"]}]}, "experience_required": {"duration": ["8 years"], "field": ["consulting", "infrastructure", "audit", "it", "security", "database"]}}, {"job_id": "100003009047649", "location_code": "hk", "company": "Moore Associates Limited", "job_title": "Senior Associate / Associate (IT Audit)", "description": "Responsibilities:\n\n\nInvolve in IT governance reviews and technical assessments to evaluate system security and control effectiveness\nCarry out IT audit engagements, including but not limited to IT general control review, application controls and CAATs\nPlan and deliver IT security compliance, based on international IT security standards including but not limited ISO, NIST, COBIT etc.\nCarry out IT security review and auditing services, and perform on-going consultancy work\nAssist in preparing reports with audit findings and recommendations\nTake up other ad-hoc projects as required\u00a0\n\nRequirements:\n\n\nBachelor degree in Information Technology, Computer Science or related discipline\nExperience in IT audit, IT risk advisory, IT security, or related areas\nGood business acumen with knowledge of technology risk, cyber security, and information security\nProfessional qualification such as CISA, CISM, CISSP, CRISC, CIA, CEH holder is a plus but not a must\nCreative, innovative and well-organised personnel with strong communication and interpersonal skills\nSelf-motivated, independent, diligent and able to work under pressure\nExcellent command of written and spoken English and Chinese\nFresh graduate with IT background is also welcomed\n\nCompetitive package will be offered to the right candidate(s), including 5 day work week, paid examination & study leave, birthday leave & medical insurance coverage. Interested parties please send full resume with working experience, academic and professional qualifications, including present & expected salary by clicking the \"Apply Now\" button.\u00a0 Personal data collected will be used for recruitment purposes only.\n\nSimply click the \u201cApply Now\u201d button\n\nPlease visit our website at\u00a0www.moore.hk\u00a0to know more about us.", "employment_types": ["Full Time", "Permanent"], "selling_points": ["IT audit engagements", "IT security compliance", "Vulnerability assessment"], "locations": ["Tsim Sha Tsui"], "categories": ["Banking / Finance", "Financial Services", "Information Technology (IT)", "IT Auditing", "Security"], "post_time": "2022-01-15T03:49:47Z", "salary": {"currency": null, "max": null, "min": null, "period": "monthly", "term": null}, "salary_visible": false, "title_keywords": ["senior associate", "associate"], "responsibilities": ["control", "review", "compliance", "audit", "evaluate", "system security", "plan", "preparing reports", "ad-hoc projects", "auditing"], "requirements": {"degrees": ["degree", "bachelor", "fresh graduate"], "majors": ["it", "computer science", "information technology"], "languages": ["english", "chinese"], "language_level": ["excellent"], "hard_skills": ["cyber security", "plus", "acumen"], "soft_skills": ["self-motivated", "independent", "well-organised", "diligent", "innovative", "communication and interpersonal skills", "business acumen", "creative", "work under pressure"], "languages_combined": [{"language": "english", "language_level": ["excellent"]}, {"language": "chinese", "language_level": ["excellent"]}]}, "experience_required": {"duration": [], "field": ["related", "it", "security", "audit"]}}, {"job_id": "100003009045468", "location_code": "hk", "company": "Michael Page", "job_title": "Information Security Officer / AM (Regional role)", "description": "Planning, implementing, monitoring and optimising the Information Security Management System in global scale.\n\nClient Details\n\nOur client is a global reputable company which is seeking for a high calibre IT professional to take up the global role in Hong Kong.\n\nDescription\n\nDevelop and maintain security policies and guidelines;\nTo maintain and enforce the information security management system and framework;\nTo provide support and advice from security perspective on architecture design, system setup, risk assessment and risk mitigation;\nCoordinate and conduct regularly vulnerability scanning and life cycle management;\nLead teams on IT security related projects\n\nProfile\n\nDegree holder in Computer Science or related disciplines\nMin. 3 years of experience in IT Security\nHolder of information security certification such as CISSP, CISA, CISM, GIAC, ISO27001 are highly preferred\nExperience in Vulnerability Management and Privileged Access Management solution is an advantage\nGood command of written and spoken English and Chinese (Mandarin) languages\n\nJob Offer\n\nAttractive remuneration package\n\nTo apply online please click the 'Apply' button below. For a confidential discussion about this role please contact Connie Mo on +852 2848 9540.", "employment_types": ["Full Time", "Permanent"], "selling_points": ["Global role, NA and APAC", "3-5 years of experience in IT security", "Lead teams for network security projects"], "locations": ["Not Specified"], "categories": ["Information Technology (IT)", "IT Auditing", "Security", "Network & System"], "post_time": "2022-01-13T07:54:50Z", "salary": {"currency": "HKD", "max": 54999, "min": 30000, "period": "monthly", "term": null}, "salary_visible": true, "title_keywords": ["officer"], "responsibilities": ["scanning", "management", "provide support", "information security", "guidelines", "policies", "monitoring", "teams", "design", "develop", "coordinate", "maintain", "contact", "vulnerability management", "architecture", "setup", "planning"], "requirements": {"degrees": ["degree holder"], "majors": ["related disciplines", "computer science"], "languages": ["english", "chinese", "mandarin"], "language_level": ["good command"], "hard_skills": ["security management"], "soft_skills": [], "languages_combined": [{"language": "english", "language_level": ["good command"]}, {"language": "chinese", "language_level": ["good command"]}, {"language": "mandarin", "language_level": ["good command"]}]}, "experience_required": {"duration": ["3 years"], "field": ["management", "it", "security"]}}, {"job_id": "100003009044364", "location_code": "hk", "company": "Pinpoint Asia Limited", "job_title": "Security Architecture Lead - Enterprise Technology Platform", "description": "Scope of Duties:\u00a0\n\nWorking with Finance Manager to oversee the implementation process of new financial consolidation system\nLeading project team to ensure a smooth migration from the existing financial consolidation system to the new one\nAssisting in user acceptance test, data migration and reviewing forms & reports\nDesigning and documenting procedures and control measures of the new financial consolidation system\nProviding coordination between finance team users (of Group level and local levels) and IT / product support team after the system goes live\nAssistance in reviewing accounting system / process to drive automation and efficiency\n\nRequirements:\u00a0\n\nRecognised degree in Accounting or related disciplines\nA qualified member of HKICPA (or equivalent) with a minimum 3 years of experience in financial system analysis, implementation & support related role\nStrong business and financial consolidation system knowledge\nKnowledge in Tagetik or SAP BPC system will be an advantage\nExperience in project and vendor management will be an advantage\nAbility to work closely with finance users & IT vendors\nProficiency in MS Excel manipulation and formulae\nProficient spoken and written English (and a working proficiency in Putonghua being a plus)\n\nHow to Apply:\n\nPlease send your resume with expected salary, quoting the employer's reference no., to: Human Resources Department - Talent & Partnership Team, Hong Kong Aircraft Engineering Company Limited, 80 South Perimeter Road, Hong Kong International Airport, Lantau, Hong Kong OR submit your application via\u00a0https://careers.haeco.com/hkg/job-openings/\n\nCandidates not contacted 4-6 weeks after submission of applications and/or interviews may consider their application unsuccessful.\n\nAll information provided by candidates will be treated in strict confidence and will be used for employment purpose only.", "employment_types": ["Full Time"], "selling_points": ["Lead Security Architecture", "Leadership Position", "Security on Application, Infra & Cloud"], "locations": ["Not Specified"], "categories": ["Information Technology (IT)", "IT Management", "Software Development", "Security"], "post_time": "2022-01-13T03:51:37Z", "salary": {"currency": "HKD", "max": 159999, "min": 90000, "period": "monthly", "term": null}, "salary_visible": true, "title_keywords": ["lead"], "responsibilities": ["control", "data", "procedures", "implementation", "reports", "finance team", "coordination", "designing", "migration"], "requirements": {"degrees": ["degree"], "majors": ["related disciplines", "accounting"], "languages": ["putonghua", "english"], "language_level": ["proficiency", "proficient"], "hard_skills": ["plus", "no", "sap", "aircraft", "analysis", "vendor", "ms excel", "hkicpa"], "soft_skills": ["confidence"], "languages_combined": [{"language": "putonghua", "language_level": ["proficient"]}, {"language": "english", "language_level": ["proficiency", "proficient"]}]}, "experience_required": {"duration": ["minimum 3 years"], "field": ["related", "management", "financial"]}}, {"job_id": "100003009041111", "location_code": "hk", "company": "Retail Technology (Hong Kong) Limited", "job_title": "Cyber Security Analyst", "description": "Scope of Duties:\u00a0\n\nActs as the key buyer and subject matter expert for responsible categories, including but not limited to, vendor selection, proposal evaluation, developing and negotiating contract terms & conditions. Additionally, this position manages the contract execution process, resolving problems, mitigating delays, mediating disputes and escalating issues\nMonitor the performance of the agreements and the overall relationships with the vendors\nHandling daily procurement duties, executing projects and leading tender exercises and contract development\nProvision/Input and execution of mid to long-term strategy\nUnderstanding supply base and market trend\nProviding constructive feedback to supplier for future development\nConducting product development and analysis\nCollaborating with teams and Influence relevant stakeholders effectively\nInitiating and leading projects at both local & group levels; such as market research, benchmarking exercises, information analysis and contract development\nTaking lead in assigned taskforces/working teams for procurement related studies and/or process improvement\n\nRequirements:\u00a0\n\nRecognized degree in any disciplines, business / management related an advantage\nProfessional qualification in procurement & supply is preferred\nMinimum of 5 years of procurement experience\nProduct and market knowledge in related category of purchases is an advantage\nExcellent command of English and Chinese, both spoken and written\nTo lead projects and facilitate the team with high quality of work and implementation of good procurement practices & control\nTo resolve operation problems, enhance cross team communication and review key supplier performance\nTo lead the projects or being contract manager for those purchase recommendation & decision with a longer term and higher financial impact to the company and the group\nTo carry out strategic analysis on data for development of cost saving opportunities and execution of proper risk management\nTo be actively involved in staff engagement initiatives and process improvement projects\n\nHow to Apply:\n\nPlease send your resume with expected salary, quoting the employer's reference no., to: Human Resources Department - Talent & Partnership Team, Hong Kong Aircraft Engineering Company Limited, 80 South Perimeter Road, Hong Kong International Airport, Lantau, Hong Kong OR submit your application via\u00a0https://careers.haeco.com/hkg/job-openings/\n\nCandidates not contacted 4-6 weeks after submission of applications and/or interviews may consider their application unsuccessful.", "employment_types": ["Full Time"], "selling_points": ["3 years of experinece in IT security", "Experience in SOC", "Retail, Ecommerce and Supply Chain industry"], "locations": ["Tai Koo"], "categories": ["Information Technology (IT)", "IT Project Management / Team Lead", "Security", "Network & System"], "post_time": "2022-01-12T03:27:56Z", "salary": {"currency": null, "max": null, "min": null, "period": "monthly", "term": null}, "salary_visible": false, "title_keywords": ["analyst"], "responsibilities": ["analysis", "teams", "developing", "subject matter expert", "market research", "executing", "monitor the performance", "tender", "evaluation"], "requirements": {"degrees": ["degree"], "majors": ["business", "any disciplines"], "languages": ["english", "chinese"], "language_level": ["excellent"], "hard_skills": ["no", "analysis", "aircraft"], "soft_skills": ["communication"], "languages_combined": [{"language": "english", "language_level": ["excellent"]}, {"language": "chinese", "language_level": ["excellent"]}]}, "experience_required": {"duration": ["minimum of 5 years"], "field": ["procurement"]}}, {"job_id": "100003009038723", "location_code": "hk", "company": "Telecommunications & Technology Asia Ltd", "job_title": "IT Sales \u2013 Cybersecurity", "description": "Scope of Duties:\u00a0\n\nWork collaboratively and in strong partnership with Learning and Development Manager/ Line Managers/ Local HR to drive HAECO Group talent management initiatives, e.g. succession planning;\nLead and manage the talent management team;\nManage and support the development and delivery of talent initiatives;\nNurture the High Flyers within the relevant business area and use existing talent frameworks to support their growth;\nLeverage data from SuccessFactors to provide insights and help inform decisions;\nIdentify and develop competency assessment models for talent development;\nPerform other relevant duties as assigned\n\nRequirements:\u00a0\n\nDegree in Training & Development, Human Resources Management or related discipline;\n5 years of relevant experience in a sizable organization;\nAdvanced project management skills, data savvy, and strong systems thinking and understanding;\nProficiency in MS Office applications e.g. PowerPoint, Excel, and Chinese Word Processing\nStrong supervisory skills and analytical abilities;\nGood team player and people skills to develop rapport with line managers and all levels of employees;\nPositive attitude and able to deal with multi-tasks effectively;\nExcellent command of English and Chinese, both spoken and written. Fluency in Putonghua\n\nHow to Apply:\n\nPlease send your resume with expected salary, quoting the employer's reference no., to: Human Resources Department - Resourcing Team, Hong Kong Aircraft Engineering Company Limited, 80 South Perimeter Road, Hong Kong International Airport, Lantau, Hong Kong OR submit your application via\u00a0https://careers.haeco.com/hkg/job-openings/\n\nCandidates not contacted 4-6 weeks after submission of applications and/or interviews may consider their application unsuccessful.\n\nAll information provided by candidates will be treated in strict confidence and will be used for employment purpose only.", "employment_types": ["Full Time", "Contract"], "selling_points": ["Challenging and high commission job", "Flexible hours and can work from home", "Sales of revolutionary Zero Trust Security product"], "locations": ["Eastern Area"], "categories": ["Information Technology (IT)", "Security", "Sales, CS & Business Devpt", "Technical Sales / Sales Engineer"], "post_time": "2022-01-11T07:41:19Z", "salary": {"currency": null, "max": null, "min": null, "period": "monthly", "term": null}, "salary_visible": false, "title_keywords": ["sales"], "responsibilities": ["management team", "management", "provide insights", "data", "hr", "develop", "planning"], "requirements": {"degrees": ["degree"], "majors": [], "languages": ["putonghua", "english", "chinese"], "language_level": ["fluency", "excellent"], "hard_skills": ["excel", "no", "chinese word processing", "aircraft", "powerpoint", "project management", "ms office"], "soft_skills": ["good team player", "confidence", "advanced", "multi-tasks", "project management skills", "positive attitude"], "languages_combined": [{"language": "putonghua", "language_level": ["fluency"]}, {"language": "english", "language_level": ["excellent"]}, {"language": "chinese", "language_level": ["excellent"]}]}, "experience_required": {"duration": ["5 years"], "field": ["sizable organization", "relevant experience"]}}, {"job_id": "100003009050332", "location_code": "hk", "company": "Connexe Search Limited", "job_title": "Technology Risk Manager", "description": "Scope of Duties:\u00a0\n\n\u00a0Group Cybersecurity Improvement program\nParticipate the Group Cybersecurity Improvement program to coordinate with Group companies\u2019 IT and report the status to the group management\n\u00a0Group Cybersecurity Incident Management\nManage Cybersecurity incident and participate to the Cybersecurity crisis drill in order to minimize the damage/loss due to the cybersecurity attacks. Formulate the cybersecurity response plan with group companies IT\n\u00a0Manage the Cybersecurity Operations\nOversee the \u00a0Cybersecurity Operations to leverage security platforms (i.e Malware, SIEM, Network ATP, etc) for the identification of security events\n\u00a0Business engagement on Cybersecurity\nDeploy the cybersecurity training program to uplift business cybersecurity awareness, facilitate the cybersecurity risk assessment with group companies\u2019 IT and act as the backup of cybersecurity focal contact point with business owners and Swire Group\n\nRequirements:\u00a0\n\nDegree holder in IT, Computing, Engineering or related disciplines\nOver 6 years of experience in IT project or technical risk management and project deliverables\nWorking experience in information security risk management and cybersecurity technologies such as malware, firewall, network ATP, SIEM, DLP, etc. protection\nHolder of IT Security certifications such as CISSP/CISA/CISM/CISP-HK is an advantage\nPossess strong vendor and stakeholders\u2019 management skills\nAssist in developing, maintaining and reviewing IT security and IT risk management policy\nKeep up-to-date Knowledge in Cloud infrastructure and cyber security\nWell-developed analytical, problem solving, and decision-making skills\nFluent in Mandarin, Cantonese and English\n\nHow to Apply:\n\nPlease send your resume with expected salary, quoting the employer's reference no., to: Human Resources Department - Talent & Partnership Team, Hong Kong Aircraft Engineering Company Limited, 80 South Perimeter Road, Hong Kong International Airport, Lantau, Hong Kong OR submit your application via\u00a0https://careers.haeco.com/hkg/job-openings/\n\nCandidates not contacted 4-6 weeks after submission of applications and/or interviews may consider their application unsuccessful.\n\nAll information provided by candidates will be treated in strict confidence and will be used for employment purpose only.", "employment_types": ["Full Time", "Part Time"], "selling_points": ["Technology Risk, Op Risk, Cyber Security", "Knowledge of HKMA regulatory requirements", "Good career prospects"], "locations": ["Not Specified"], "categories": ["Information Technology (IT)", "Security", "Banking / Finance", "Risk Management"], "post_time": "2022-01-14T10:08:20Z", "salary": {"currency": null, "max": null, "min": null, "period": "monthly", "term": null}, "salary_visible": false, "title_keywords": ["manager"], "responsibilities": ["management", "operations", "coordinate with", "contact", "plan", "deploy", "report"], "requirements": {"degrees": ["degree holder"], "majors": ["related disciplines", "it", "engineering"], "languages": ["cantonese", "english", "mandarin"], "language_level": ["fluent"], "hard_skills": ["no", "aircraft", "cyber security", "vendor", "problem solving", "firewall"], "soft_skills": ["problem solving", "confidence"], "languages_combined": [{"language": "cantonese", "language_level": ["fluent"]}, {"language": "english", "language_level": ["fluent"]}, {"language": "mandarin", "language_level": ["fluent"]}]}, "experience_required": {"duration": ["6 years"], "field": ["risk management", "it", "security"]}}, {"job_id": "100003009050423", "location_code": "hk", "company": "SmarTone Telecommunications Limited", "job_title": "Senior Engineer, Cloud Virtualization", "description": "Scope of Duties \u5de5\u4f5c\u7bc4\u570d:\u00a0\n\nProvide general transportation services for internal staff and external VIPs\n\u8ca0\u8cac\u99d5\u99db\u516c\u53f8\u8eca\u8f1b\u63a5\u9001\u8077\u54e1\u53ca\u8cb4\u8cd3\n\n\nRequirements \u7533\u8acb\u689d\u4ef6:\u00a0\n\nCompletion of HKCEE / HKDSE (or equivalent)\n\u5b8c\u6210\u9999\u6e2f\u6703\u8003/\u9999\u6e2f\u4e2d\u5b78\u6587\u6191\u8a66 (\u6216\u540c\u7b49\u5b78\u6b77)\nAt least 2 years driving experience\n\u6700\u5c11\u5169\u5e74\u6216\u4ee5\u4e0a\u99d5\u99db\u7d93\u9a57\nPossess valid Hong Kong driving licence (Cat. 1 ,2 & 4)\n\u9808\u6301\u6709\u6548\u9999\u6e2f\u99d5\u99db\u57f7\u7167(\u7b2c1\u30012\u53ca4\u985e\u5225)\nGood driving record\n\u5177\u826f\u597d\u99d5\u99db\u8a18\u9304\nWilling to work overtime\n\u9700\u52a0\u73ed\u53ca\u8f2a\u73ed\u5de5\u4f5c\n\nHow to Apply:\n\nPlease send your resume with expected salary, quoting the employer's reference no., to: Human Resources Department - Talent & Partnership Team, Hong Kong Aircraft Engineering Company Limited, 80 South Perimeter Road, Hong Kong International Airport, Lantau, Hong Kong OR submit your application via\u00a0https://careers.haeco.com/hkg/job-openings/\n\nCandidates not contacted 4-6 weeks after submission of applications and/or interviews may consider their application unsuccessful.\n\nAll information provided by candidates will be treated in strict confidence and will be used for employment purpose only.", "employment_types": ["Full Time", "Permanent"], "selling_points": ["Cloud Infrastructure engineering in Core Netowork", "Network & capacity planning & system dimensioning", "IP networking, Virtualization, SDN topology"], "locations": ["Kowloon Bay"], "categories": ["Information Technology (IT)", "Security", "Network & System", "Mobile / Wireless Communications"], "post_time": "2022-01-14T10:22:49Z", "salary": {"currency": null, "max": null, "min": null, "period": "monthly", "term": null}, "salary_visible": false, "title_keywords": ["senior engineer"], "responsibilities": [], "requirements": {"degrees": ["hkdse"], "majors": [], "languages": [], "language_level": [], "hard_skills": ["no", "hong kong driving licence", "aircraft"], "soft_skills": ["work overtime", "confidence"], "languages_combined": []}, "experience_required": {"duration": ["at least 2 years"], "field": []}}, {"job_id": "100003009049684", "location_code": "hk", "company": "Hong Kong Internet Registration Corporation Limited", "job_title": "Senior System Engineer", "description": "Scope of Duties:\u00a0\n\nDevelop and implement processes and procedures to assure compliance to regulatory requirements and company / customer procedures\nPlan and execute processes and procedures to assure compliance to quality and safety standard of the workplace\nPlan, structure and organize the warehouse functions to meet business and development requirements\nWork closely with internal / external customers to deliver solutions that meet their needs\nMotivate and encourage teamwork within the workforce to ensure productivity targets are met or exceeded\nConduct continuous review, plan and evaluate warehouse activities, work flow, cost effectiveness, KPI achievement, staff performance and development\nMonitor the execution and effectiveness of corrective and preventive action plan in response to quality audit findings, customer complaints, IOR\u2019s and MOR\u2019s\nAssure proper capture and billing of Storage cost to customer per contractual requirements\nManage annual budget exercise, monitor budget adherence, investigate variance and develop improvement action plan\nDrive cross sections and cross departments process improvement projects\nInitiate, lead, prepare and present progress report of ad hoc / process improvement projects\n\nRequirements:\u00a0\n\nDegree in Supply Chain Management, Logistics or relevant disciplines\nMinimum of 9 years relevant experience, preferably in aviation industry\nIn-depth knowledge in supply chain operations\nStrong command of spoken and written English and Chinese\nStrong communication, supervisory and interpersonal skills\nExcellent leadership and negotiation skills\nExcellent analytical skills\nGood in Microsoft Office applications\nKnowledge in Lean / Six Sigma / 5S an advantage\n\nHow to Apply:\n\nPlease send your resume with expected salary, quoting the employer's reference no., to: Human Resources Department - Talent & Partnership Team, Hong Kong Aircraft Engineering Company Limited, 80 South Perimeter Road, Hong Kong International Airport, Lantau, Hong Kong OR submit your application via\u00a0https://careers.haeco.com/hkg/job-openings/\n\nCandidates not contacted 4-6 weeks after submission of applications and/or interviews may consider their application unsuccessful.\n\nAll information provided by candidates will be treated in strict confidence and will be used for employment purpose only.", "employment_types": ["Full Time", "Permanent"], "selling_points": [], "locations": ["Pok Fu Lam"], "categories": ["Information Technology (IT)", "Security", "Network & System", "Technical / Functional Consulting"], "post_time": "2022-01-14T09:04:51Z", "salary": {"currency": null, "max": null, "min": null, "period": "monthly", "term": null}, "salary_visible": false, "title_keywords": ["senior system engineer"], "responsibilities": ["cost", "ad hoc", "customer complaints", "regulatory requirements", "compliance", "procedures", "quality", "review", "develop", "evaluate", "monitor", "audit", "budget", "plan", "report"], "requirements": {"degrees": ["degree"], "majors": [], "languages": ["english", "chinese"], "language_level": [], "hard_skills": ["lean", "no", "aircraft", "microsoft office", "analytical skills", "six sigma"], "soft_skills": ["confidence", "analytical skills", "communication", "negotiation skills", "interpersonal skills", "leadership"], "languages_combined": [{"language": "english", "language_level": []}, {"language": "chinese", "language_level": []}]}, "experience_required": {"duration": ["minimum of 9 years"], "field": ["relevant experience"]}}, {"job_id": "100003009045457", "location_code": "hk", "company": "Edvance Technology (Hong Kong) Limited", "job_title": "Technical Engineer (Graduate)", "description": "Scope of Duties:\u00a0\n\nPerform defect analysis on each captured defect\nPerform defect next task (work instruction)\nIdentify required spare for rectification and preloading\nIdentify required tools/equipment for rectification\nEstimate TRT/MH for each defect and set planning attributes\nReview power plant defects and structural defects with CX-TS\nEvaluate defect qualify CFI procedure\nReview restrictive defect and perform technical follow up action\n\nRequirements:\u00a0\n\nHolder of valid HKCAD B1.1 basic license or any NAA B1 basic licence\nA minimum of 5 years of LM or BM working experience, preferably hold B1 approval with type aircraft of B747-400, B748, B777, A350, A330, A320 or attended full type course and passed exam\nKnowledge of OEM trouble shooting aids and maintenance documentations\nAnalytical, results-oriented, customer focus and good project management skills\nA good team player with strong supervisory skills and communication skills\nSound knowledge in using MS Office application e.g. Word, Excel, Access\nExcellent command of English and Chinese, both spoken and written\n\nHow to Apply:\n\nPlease send your resume with expected salary, quoting the employer's reference no., to: Human Resources Department - Talent & Partnership Team, Hong Kong Aircraft Engineering Company Limited, 80 South Perimeter Road, Hong Kong International Airport, Lantau, Hong Kong OR submit your application via\u00a0https://careers.haeco.com/hkg/job-openings/\n\nCandidates not contacted 4-6 weeks after submission of applications and/or interviews may consider their application unsuccessful.\n\nAll information provided by candidates will be treated in strict confidence and will be used for employment purpose only.", "employment_types": ["Full Time", "Permanent"], "selling_points": ["For fresh grad to gain knowledge in cybersesurity", "Rotation through three primary domains", "Attractive Remuneration and great prospect"], "locations": ["Ngau Tau Kok"], "categories": ["Information Technology (IT)", "Support", "Security", "Others", "Student / Fresh Graduate / No Experience"], "post_time": "2022-01-13T07:53:37Z", "salary": {"currency": null, "max": null, "min": null, "period": "monthly", "term": null}, "salary_visible": false, "title_keywords": ["technical engineer"], "responsibilities": ["analysis", "review", "rectification", "evaluate", "planning"], "requirements": {"degrees": [], "majors": [], "languages": ["english", "chinese"], "language_level": ["excellent"], "hard_skills": ["excel", "no", "basic", "maintenance", "aircraft", "word", "project management", "focus", "documentations", "ms office"], "soft_skills": ["communication skills", "good team player", "confidence", "project management skills", "customer focus"], "languages_combined": [{"language": "english", "language_level": ["excellent"]}, {"language": "chinese", "language_level": ["excellent"]}]}, "experience_required": {"duration": ["minimum of 5 years"], "field": []}}, {"job_id": "100003009048950", "location_code": "hk", "company": "Heep Hong Society", "job_title": "Manager, Project Management Office", "description": "Scope of Duties:\u00a0\n\nWork closely with Assistant Manager, Group Talent Management;\u00a0\u00a0\nEngage in talent review, succession planning and performance management exercises across all HAECO Group entities;\u00a0\nManage the talent management programmes for the Group;\u00a0\u00a0\nAdminister and maintain the Performance Management and Succession Planning systems;\u00a0\nProvide regular tracking reports and relevant analysis.\u00a0\nLiaise and negotiate with internal and external parties on talent development related activities;\u00a0\u00a0\nPerform other relevant duties as assigned\u00a0\n\nRequirements:\u00a0\n\nHolder of recognised degree in Human Resources or related disciplines;\u00a0\u00a0\n3 years of solid experience in talent management or human resources functions at sizable organisations;\u00a0\u00a0\nAttention to details, action-oriented and a good team player;\u00a0\u00a0\nExcellent communication and interpersonal skills;\u00a0\u00a0\nHands-on experience in SAP/ HR systems is preferred;\u00a0\nProficiency in MS Office applications e.g. Word, PowerPoint and Excel\u00a0\nExcellent command of English and Chinese, both spoken and written, fluency in Putonghua will be an advantage\u00a0\n\nHow to Apply:\n\nPlease send your resume with expected salary, quoting the employer's reference no., to: Human Resources Department - Talent & Partnership Team, Hong Kong Aircraft Engineering Company Limited, 80 South Perimeter Road, Hong Kong International Airport, Lantau, Hong Kong OR submit your application via\u00a0https://careers.haeco.com/hkg/job-openings/\n\nCandidates not contacted 4-6 weeks after submission of applications and/or interviews may consider their application unsuccessful.\n\nAll information provided by candidates will be treated in strict confidence and will be used for employment purpose only.", "employment_types": ["Full Time"], "selling_points": ["Analyse & manage proj. priorities, strategy, risk", "Deg. in Computer Science, IT/Information System", "Min. 10+ yrs' exp. in project & vendor management"], "locations": ["Ngau Tau Kok"], "categories": ["Information Technology (IT)", "IT Project Management / Team Lead", "IT Management", "Security"], "post_time": "2022-01-14T11:33:15Z", "salary": {"currency": null, "max": null, "min": null, "period": "monthly", "term": null}, "salary_visible": false, "title_keywords": ["manager"], "responsibilities": ["liaise", "management", "tracking", "analysis", "review", "systems", "internal and external parties", "maintain", "reports", "planning"], "requirements": {"degrees": ["degree"], "majors": ["related disciplines"], "languages": ["putonghua", "english", "chinese"], "language_level": ["fluency", "advantage", "excellent"], "hard_skills": ["excel", "no", "sap", "aircraft", "word", "powerpoint", "ms office"], "soft_skills": ["good team player", "confidence", "hands-on", "communication and interpersonal skills", "attention to details"], "languages_combined": [{"language": "putonghua", "language_level": ["fluency", "advantage", "excellent"]}, {"language": "english", "language_level": ["advantage", "excellent"]}, {"language": "chinese", "language_level": ["advantage", "excellent"]}]}, "experience_required": {"duration": ["3 years"], "field": ["hr", "management", "human resources"]}}, {"job_id": "100003009041371", "location_code": "hk", "company": "CK Life Sciences Limited", "job_title": "Assistant Systems Engineer (Listed Company, 5-day workweek)", "description": "Scope of Duties:\u00a0\n\n\nCommunicate and collaborate with business uses to understand business processes and system requirements\nPerform user requirement collection and system analysis\nEnsure the system design reflects business requirements\nConduct code development or code review, Unit Testing (UT), System Integration Testing (SIT) and coordinate User Acceptance Testing (UAT), where necessary\nCoordinate with external technology vendors throughout the system development lifecycle\nDocument project artifacts and deliverables, e.g. functional and technical specifications, test cases, and test results, where applicable\nExplore latest technologies and evaluate capabilities of new products and services where necessary. Liaises with service providers to select the products or services that best meet business goals\n\nRequirements:\u00a0\n\nDegree holder in Computer Science, Engineering, or related disciplines\nPreferably with relevant experience in below areas:\nIntegration technologies and mechanisms such as API management and cloud computing. Experience in VB, SQL, Power BI, MS Azure, REST API will be an advantage.\u00a0 Able to apply different technologies and tools in various business scenarios\nEnd-to-end system development lifecycle (SDLC) including requirements analysis, development, testing, deployment, and maintenance will be a plus\nProficient in Office products (Word, Excel, PowerPoint, SharePoint, etc) and exposure to Microsoft 365 suite of apps\nStrong analytical and problem-solving skills, able to work with challenges and adapt quickly to ambiguity and changing priorities in fast-changing environment\nStrong communication and interpersonal skills with good command of written and spoken English and Chinese (Putonghua and Cantonese), and the ability to interact professionally with diverse group of stakeholders\n\nHow to Apply:\n\nPlease send your resume with expected salary, quoting the employer's reference no., to: Human Resources Department - Talent & PartnershipTeam, Hong Kong Aircraft Engineering Company Limited, 80 South Perimeter Road, Hong Kong International Airport, Lantau, Hong Kong OR submit your application via\u00a0https://careers.haeco.com/hkg/job-openings/\n\nCandidates not contacted 4-6 weeks after submission of applications and/or interviews may consider their application unsuccessful.\n\nAll information provided by candidates will be treated in strict confidence and will be used for employment purpose only.", "employment_types": ["Full Time", "Permanent"], "selling_points": ["Diploma in Computer Science, IT / Engineering", "3 years of experience in technical support", "1st tier desktop support,server/network technology"], "locations": ["Tai Po Area"], "categories": ["Information Technology (IT)", "Support", "Security", "Network & System"], "post_time": "2022-01-12T03:50:12Z", "salary": {"currency": null, "max": null, "min": null, "period": "monthly", "term": null}, "salary_visible": false, "title_keywords": ["systems engineer", "assistant"], "responsibilities": ["collaborate with", "user requirement", "business goals", "uat", "analysis", "review", "coordinate with", "testing", "coordinate", "evaluate", "system design", "specifications"], "requirements": {"degrees": ["degree holder"], "majors": ["related disciplines", "engineering", "computer science"], "languages": ["cantonese", "putonghua", "english", "chinese"], "language_level": ["good command"], "hard_skills": ["excel", "plus", "bi", "azure", "no", "maintenance", "aircraft", "analysis", "word", "powerpoint", "sql", "sdlc", "deployment", "integration", "problem-solving skills"], "soft_skills": ["problem-solving skills", "communication and interpersonal skills", "confidence", "diverse"], "languages_combined": [{"language": "cantonese", "language_level": ["good command"]}, {"language": "putonghua", "language_level": ["good command"]}, {"language": "english", "language_level": ["good command"]}, {"language": "chinese", "language_level": ["good command"]}]}, "experience_required": {"duration": [], "field": ["sql", "relevant experience"]}}, {"job_id": "100003009048758", "location_code": "hk", "company": "United Asia Finance Limited", "job_title": "Application Architect (FinTech and Innovation Department)", "description": "Scope of Duties:\u00a0\n\nManage, coordinate and optimize daily operations of tool rooms\nAssure compliance to regulatory requirements and company / customer procedures\nStructure and organize the tool handling functions such as tool inspection, tool loan, tool return, tool repair and calibration to support the aircraft maintenance\nConduct continuous review, plan and evaluate tool room activities, work flow, cost effectiveness, KPI achievement, staff performance and development\nWork closely with internal / external customers to deliver solutions that meet their needs\nPerform occurrence analysis and investigation of related quality audit findings, customer complaints, IOR\u2019s and MOR\u2019s and propose corrective and preventive action plan.\u00a0 Liaise with internal and external parties for case follow up\nMonitor and assure quality and safety standard of the workplace\nMonitor the progress of the calibration / repair / load test and expedite the outstanding orders\nInitiate, lead, prepare and present progress report of ad hoc / process improvement projects\nProvide coaching and mentoring to staff\nPerform supervisory duties\nPerform ad hoc duties as assigned\n\nRequirements:\u00a0\n\nMinimum 4 years relevant experience for Degree holder in relevant disciplines or equivalent\nGood command of spoken and written English and Chinese\nStrong communication, supervisory and interpersonal skills\nStrong leadership and negotiation skills\nGood analytical skills\nGood in Microsoft Office applications\nEngineering / aviation background is preferred\n\nHow to Apply:\n\nPlease send your resume with expected salary, quoting the employer's reference no., to: Human Resources Department - Resourcing Team, Hong Kong Aircraft Engineering Company Limited, 80 South Perimeter Road, Hong Kong International Airport, Lantau, Hong Kong OR submit your application via\u00a0https://careers.haeco.com/hkg/job-openings/\n\nCandidates not contacted 4-6 weeks after submission of applications and/or interviews may consider their application unsuccessful.\n\nAll information provided by candidates will be treated in strict confidence and will be used for employment purpose only.", "employment_types": ["Full Time", "Permanent"], "selling_points": ["Double pay and discretionary bonus", "Drive system/ software architecture design", "Degree or above in Computer Science, IT"], "locations": ["Wan Chai"], "categories": ["Information Technology (IT)", "Software Development", "Security", "Network & System"], "post_time": "2022-01-14T07:13:26Z", "salary": {"currency": null, "max": null, "min": null, "period": "monthly", "term": null}, "salary_visible": false, "title_keywords": [], "responsibilities": ["regulatory requirements", "internal and external parties", "quality", "audit", "plan", "liaise with", "ad hoc duties", "ad hoc", "compliance", "monitor", "report", "cost", "customer complaints", "review", "procedures", "investigation", "inspection", "daily operations", "maintenance", "analysis", "coordinate", "evaluate", "repair"], "requirements": {"degrees": ["degree holder"], "majors": [], "languages": ["english", "chinese"], "language_level": ["good command"], "hard_skills": ["microsoft office", "no", "aircraft", "analytical skills"], "soft_skills": ["confidence", "analytical skills", "communication", "negotiation skills", "interpersonal skills", "leadership"], "languages_combined": [{"language": "english", "language_level": ["good command"]}, {"language": "chinese", "language_level": ["good command"]}]}, "experience_required": {"duration": ["minimum 4 years"], "field": ["relevant experience"]}}, {"job_id": "100003009041780", "location_code": "hk", "company": "Reda Technology Limited", "job_title": "IT / Technical Support", "description": "Scope of Duties:\u00a0\n\nSecurity Operations (e.g. malware detection and eradication, incident responses, SOC, etc.)\nBusiness engagement and awareness training on cybersecurity\nReview and update cybersecurity policies, guidelines, and procedures\nPropose and lead the project to implement the new security solutions e.g. EDR, WAF, etc.\nManage vulnerability/penetration tests for risks detection and mitigation\nAssess the security design and make security recommendation for the new applications or services\nFocal contact point for the security assessments, e.g. NIST Cybersecurity Framework assessment\nAssist in developing, maintaining and reviewing IT security and IT risk management policy\nKeep up-to-date knowledge in Cloud infrastructure and cyber security\nLiaise with other group entities for joint cybersecurity initiatives\n\nRequirements:\u00a0\n\nDegree holder in IT, Computing, Engineering or related disciplines\nOver 8 years of experience in IT project or technical risk management and project deliverables\nWorking experience in information security risk management and cybersecurity technologies such as malware, firewall, network ATP, SIEM, DLP, etc. protection\nHolder of IT Security certifications such as CISSP/CISA/CISM/CISP-HK is an advantage\nPossess strong vendor and stakeholders\u2019 management skills\nWell-developed analytical, problem solving, and decision-making skills\nFluent in Mandarin, Cantonese and English\nGood understanding of technology concepts, trends and capabilities\nEffective verbal and written communication skill\nAbility to interact professionally with diverse groups of stakeholders\nSelf-motivation and ability to work under pressure\n\nHow to Apply:\n\nPlease send your resume with expected salary, quoting the employer's reference no., to: Human Resources Department - Talent & Partnership Team, Hong Kong Aircraft Engineering Company Limited, 80 South Perimeter Road, Hong Kong International Airport, Lantau, Hong Kong OR submit your application via\u00a0https://careers.haeco.com/hkg/job-openings/\n\nCandidates not contacted 4-6 weeks after submission of applications and/or interviews may consider their application unsuccessful.\n\nAll information provided by candidates will be treated in strict confidence and will be used for employment purpose only.", "employment_types": ["Full Time"], "selling_points": ["Salary negotiable", "Knowledge on computer server hardware and systems", "Fresh Graduate Welcome"], "locations": ["Not Specified"], "categories": ["Information Technology (IT)", "Support", "Security", "Network & System"], "post_time": "2022-01-12T23:26:12Z", "salary": {"currency": null, "max": null, "min": null, "period": "monthly", "term": null}, "salary_visible": false, "title_keywords": ["technical support"], "responsibilities": ["management", "maintaining", "cyber security", "guidelines", "operations", "policies", "review", "procedures", "developing", "design", "infrastructure", "contact", "liaise with"], "requirements": {"degrees": ["degree holder"], "majors": ["related disciplines", "it", "engineering"], "languages": ["cantonese", "english", "mandarin"], "language_level": ["fluent"], "hard_skills": ["no", "aircraft", "vendor", "problem solving", "firewall"], "soft_skills": ["confidence", "communication skill", "problem solving", "diverse", "self-motivation", "work under pressure"], "languages_combined": [{"language": "cantonese", "language_level": ["fluent"]}, {"language": "english", "language_level": ["fluent"]}, {"language": "mandarin", "language_level": ["fluent"]}]}, "experience_required": {"duration": ["8 years"], "field": ["risk management", "it", "security"]}}, {"job_id": "100003009049983", "location_code": "hk", "company": "Golden Siv Technology Limited", "job_title": "Senior Software Engineer - Blockchain / Back-end development / Java", "description": "Scope of Duties:\u00a0\n\nSolicit and analyze business requirements and then assess detailed solution options\nManage and deliver IT solution project for business departments\nLead cross-team members to deliver solution designs for IT systems\nWork with the external vendors and in-house teams on project delivery as well as system support\nCompile and review specifications for both functional and non-functional requirements\nSupport business process change\nOversee all solution components ensuring that they comply with all relevant company standards\nHands on technical implementation and code reviews\nConstruct and devise adoption guidelines and best practice of solution components.\n\nRequirements:\u00a0\n\nDegree holder in Computer Science, IT or related disciplines\n8 years of solid IT solution delivery experience, including at least 6 years in solution design and implementation work of various size\nExperience in data analytics is preferable\nGood understanding of technology concepts, trends and capabilities\nStrong analytical, problem solving and decision making skills\nEffective verbal and written communication skill\nAbility to interact professionally with diverse groups of stakeholders\nExcellent vendor and people management\nSelf-motivation and ability to work under pressure\n\nHow to Apply:\n\nPlease send your resume with expected salary, quoting the employer's reference no., to: Human Resources Department - Resourcing Team, Hong Kong Aircraft Engineering Company Limited, 80 South Perimeter Road, Hong Kong International Airport, Lantau, Hong Kong OR submit your application via\u00a0https://careers.haeco.com/hkg/job-openings/\n\nCandidates not contacted 4-6 weeks after submission of applications and/or interviews may consider their application unsuccessful.\n\nAll information provided by candidates will be treated in strict confidence and will be used for employment purpose only.", "employment_types": ["Full Time"], "selling_points": ["Experienced in MySQL", "Experienced in Java", "Experienced as Software Engineer"], "locations": ["Wan Chai"], "categories": ["Information Technology (IT)", "Application Specialist - Software", "Security", "Data Scientist"], "post_time": "2022-01-14T09:35:39Z", "salary": {"currency": null, "max": null, "min": null, "period": "monthly", "term": null}, "salary_visible": false, "title_keywords": ["senior software engineer"], "responsibilities": ["review specifications", "guidelines", "systems", "teams", "implementation", "business process"], "requirements": {"degrees": ["degree holder"], "majors": ["related disciplines", "it", "computer science"], "languages": [], "language_level": [], "hard_skills": ["no", "aircraft", "data analytics", "vendor", "problem solving"], "soft_skills": ["decision making skills", "confidence", "communication skill", "problem solving", "diverse", "self-motivation", "work under pressure"], "languages_combined": []}, "experience_required": {"duration": ["at least 6 years", "8 years"], "field": ["it", "design"]}}, {"job_id": "100003009037856", "location_code": "hk", "company": "China Construction Bank (Asia) Corporation Limited", "job_title": "Information Security Risk Management Professional", "description": "HAECO ITM Limited is a joint venture between HAECO (Hong Kong Aircraft Engineering Co. Ltd) and Cathay Pacific, providing inventory technical management services to different airline customers in Hong Kong and around the world. Customers anticipate to benefit saving from the ITM services through synergy of component pooling, sound technical know-how of component engineering, repair and supplier management.\n\nHXITM is now looking for candidates who are interested in this business for the position of\u00a0Engineer (Component Engineering).\n\nScope of Duties:\u00a0\n\nBe the specialist of the assigned ATA chapters and perform in depth technical investigation, with the objective to improve component reliability in a cost-effective way\nPerform NFF and Low Time Removals investigations to determine drivers and implement cost-effective improvements.\nPerform repair quotation vetting and justify repair workscope from both technical and commercial aspects.\nDetermine the best maintenance practices (i.e. softlife workscope) with the goal to optimize component reliability and shop visit cost.\nEvaluate and provide disposition for technical documents (i.e. AD, VSB, VSIL etc) and perform cost and benefit analysis and recommend implementation programs to justify the return of investment on component modification/upgrade.\nReview component technical requirements (from OEMs or from customers) and assess impact on pool and provide recommendation.\nLiaise with aircraft manufacturers and/or component OEMs to progress on technical issues.\nDevelop and improve the current workflow by utilizing new processes and new technologies (like real time A/C monitoring, predictive maintenance etc)\nEvaluate and provide recommendations on claims and warranty.\nFollow company quality standard and perform investigation on quality issues.\nPerform other duties and undertake other projects as assigned.\n\nRequirements:\u00a0\n\nA recognized Degree in Engineering (Aeronautical Engineering is an advantage) or other related disciplines\nA minimum of 4 years of experience in aircraft engineering or material services\nExcellent analytical, problem-solving, interpersonal, and presentation/communication skills\nProactive mindset, customer-focused, and forward thinking\nExcellent technical knowledge in aircraft systems and/or component in various aircraft types\nAble to manage, corelate, and draw conclusion from different and large datasets\nGood negotiation skills and supplier management skills; able to understand basic contractual language\nAble to identify opportunities for continuous improvements and cost saving, and adapt to new changes quickly\nConversant with aircraft and component repair manuals, technical publications and documentation control procedures\nComputer literacy with advanced data analysis and predictive maintenance tools, and proficiency in preparing presentations with MS Office applications\nExcellent command of English, both spoken and written\n\nHow to Apply:\n\nPlease send your resume with expected salary, quoting the employer's reference no., to: Human Resources Department - Talent & Partnership Team, Hong Kong Aircraft Engineering Company Limited, 80 South Perimeter Road, Hong Kong International Airport, Lantau, Hong Kong OR submit your application via\u00a0https://careers.haeco.com/hkg/job-opening-itm/\u00a0\n\nCandidates not contacted 4-6 weeks after submission of applications and/or interviews may consider their application unsuccessful.\n\nAll information provided by candidates will be treated in strict confidence and will be used for employment purpose only.", "employment_types": ["Full Time", "Permanent"], "selling_points": ["Information Security", "Risk Management", "IT compliance"], "locations": ["Kowloon Bay"], "categories": ["Information Technology (IT)", "IT Auditing", "Security"], "post_time": "2022-01-11T04:03:50Z", "salary": {"currency": null, "max": null, "min": null, "period": "monthly", "term": null}, "salary_visible": false, "title_keywords": [], "responsibilities": ["cost", "perform other duties", "maintenance", "analysis", "quotation", "review", "implementation", "investigation", "develop", "evaluate", "provide recommendation", "repair", "monitoring", "provide recommendations", "quality", "liaise with"], "requirements": {"degrees": ["degree"], "majors": ["related disciplines", "engineering"], "languages": ["english"], "language_level": ["excellent"], "hard_skills": ["aircraft systems", "no", "basic", "aircraft", "maintenance", "problem-solving", "analysis", "presentations", "documentation", "ms office"], "soft_skills": ["communication skills", "proactive", "customer-focused", "advanced", "confidence", "problem-solving", "computer literacy", "negotiation skills", "interpersonal", "presentation"], "languages_combined": [{"language": "english", "language_level": ["excellent"]}]}, "experience_required": {"duration": ["minimum of 4 years"], "field": ["engineering"]}}, {"job_id": "100003009050302", "location_code": "hk", "company": "Max Founder Technology Limited", "job_title": "Senior Network Engineers/Assistant System Manager/System Engineers (HK$25K-60K)", "description": "HAECO leads a broad range of aviation products and services that enable our customers to build and operate their aircraft, engines and components safely and efficiently and, in doing so, we seek to deliver sustainable value to all our stakeholders. HAECO Global Engine Support provides global round-the-clock on-wing and off-wing engine support from its strategic locations in Hong Kong, Dallas in the U.S. and Amsterdam in the Netherlands, and we are now expanding our business in the UK.\n\nHAECO Global Engine Support Limited are searching for a leader to take the business forward to meet the strategic goals of the company in On Wing and Off Wing Maintenance. Sitting on the Board of Directors and being the Part 145 Accountable Manager, the Head of HAECO Global Engine Support Limited will be responsible for providing business and technical leadership of all activities of the company, ensuring the highest levels of safety, operational performance and regulatory compliance whilst maintaining a strong focus on product & process improvement, cost control, productivity and team building. \u00a0In additional, the candidate will also oversee the operations of the company in Europe and the Middle East.\u00a0\n\nWhat You\u2019ll Do\n\nAssume the responsibilities of Accountable Manager for the company to the UK CAA and EASA\nManage and support the Integration of the London facility and the team into HAECO Global Engine Support Limited, as part of the HAECO Group\nDevelop and execute business strategy and plan through direct leadership of the management team and staff\nBe responsible for budgetary compliance and cost\nAlign and implement HAECO Health, Safety, and Environment policies\nImplement and deliver Lean / CI programs that deliver benefits at local and network level\nProvide leadership and direction including labour workforce to maximize productivity and output in accordance with collective bargaining agreements where applicable whilst ensuring necessary resources are available\nDeliver performance goals and objectives aligning with the company goals\nInterface with regulatory authorities and local governments, including International locations, to ensure regulatory compliance of technical operations activities on a global basis\u00a0\n\nWhat You Need\n\nTechnical Experience\n\nIn charge of an engine workshop at least for 5 years, with EASA and UK CAA requirement is an advantage.\n10 years in a leadership role within an aviation maintenance organization\nA proven successful track record in managing medium scale maintenance operations, with multiple locations is a plus\nStrong background and technical knowledge on engines and maintenance programs\n\n\u00a0Leadership Competencies\n\nDrive for Result: Displays a strong commitment to achieve ambitious goals and a determination to drive performance improvements through changes\nBusiness Acumen: Good understanding of MRO markets and engine maintenance industry\nCustomer Focus: Understands and responds fast to the need of internal and external customers\nCollaborating & Influencing: Builds collaborative work relationships with stakeholders and leads without authority to get things done\nDeveloping Self/Others: Motivates, empowers and inspires self/others to realise high performance and achieve business, team and individual goals. Build and manager a diverse and inclusive team on a global basis\nContinuous Improvement & Innovation:Proactively seeks new ways of doing things and constantly challenges the status quo.\u00a0\n\nOther Qualifications:\n\nUniversity Degree education, or equivalent, prefer engineering related disciplines\nExcellent command of English\u00a0\n\nBuild your career with us, to deliver sustainable value to the community and our stakeholders.", "employment_types": ["Full Time", "Permanent"], "selling_points": ["Technical expertise in Linux System Automation", "Strong troubleshooting skills", "5 day, overtime pay, double pay, education subsidy"], "locations": ["Hung Hom"], "categories": ["Information Technology (IT)", "Support", "Security", "Network & System"], "post_time": "2022-01-14T10:05:01Z", "salary": {"currency": null, "max": null, "min": null, "period": "monthly", "term": null}, "salary_visible": false, "title_keywords": ["system manager", "assistant"], "responsibilities": ["management team", "cost", "maintaining", "maintenance", "operations", "policies", "compliance", "develop", "cost control", "plan"], "requirements": {"degrees": [], "majors": [], "languages": [], "language_level": [], "hard_skills": ["integration", "maintenance", "focus", "aircraft"], "soft_skills": ["focus", "leadership", "accountable", "responsible"], "languages_combined": []}, "experience_required": {"duration": [], "field": []}}, {"job_id": "100003009045463", "location_code": "hk", "company": "Edvance Technology (Hong Kong) Limited", "job_title": "Cloud Application Developer(s)", "description": "Scope of Duties:\u00a0\n\n\nHandling all administrative works in relation to the issue of Long Term TRA Permit for HAECO and Contractors\u2019 staff\nCollect TRA and ARA permits and contractors\u2019 staff on their last working day prior to departure\nProcessing the application and renewal of ARA Permit, Visitor Pass and AA Driving Endorsement Examination and updating of these records\nTake all necessary actions in accordance with the instruction of Assistant Security and Fire Services Officer\nMaintain job-related statistical record and registers\nRelieve Permit Office personnel when necessary\nCoordinate with procurement, accounting department to handle purchase request and billing process\nAssist Security and Fire Services Manager, Head of Section (Security) and Security and Fire Services Officer in all administrative works\n\nRequirements:\u00a0\n\nForm 5 or above\nMinimum 2 years\u2019 relevant experience\nCandidate with aviation industry exposure would be advantage\nGood command of spoken and written English and Chinese\nProficient in the use of MS Excel and MS Word\nAble to handle multi-tasking independently and details oriented\nIndependent, well organized, proactive, good communication and interpersonal skills\nSelf-motivated with strong sense of responsibility, capable to meet tight deadlines\n\nHow to Apply:\n\nPlease send your resume with expected salary, quoting the employer's reference no., to: Human Resources Department - Talent & PartnershipTeam, Hong Kong Aircraft Engineering Company Limited, 80 South Perimeter Road, Hong Kong International Airport, Lantau, Hong Kong OR submit your application via\u00a0https://careers.haeco.com/hkg/job-openings/\n\nCandidates not contacted 4-6 weeks after submission of applications and/or interviews may consider their application unsuccessful.\n\nAll information provided by candidates will be treated in strict confidence and will be used for employment purpose only.", "employment_types": ["Full Time", "Permanent"], "selling_points": ["Cloud innovation projects", "Constant career growth opportunities", "Fresh Graduates are Welcome!"], "locations": ["Ngau Tau Kok"], "categories": ["Information Technology (IT)", "Application Specialist - Software", "Software Development", "Security"], "post_time": "2022-01-13T07:54:07Z", "salary": {"currency": null, "max": null, "min": null, "period": "monthly", "term": null}, "salary_visible": false, "title_keywords": [], "responsibilities": ["purchase", "maintain", "coordinate with", "billing process"], "requirements": {"degrees": ["form 5 or above"], "majors": [], "languages": ["english", "chinese"], "language_level": ["good command"], "hard_skills": ["no", "ms excel", "aircraft", "ms word"], "soft_skills": ["self-motivated", "independently", "independent", "capable", "meet tight deadlines", "sense of responsibility", "confidence", "well organized", "multi-tasking", "communication and interpersonal skills", "proactive"], "languages_combined": [{"language": "english", "language_level": ["good command"]}, {"language": "chinese", "language_level": ["good command"]}]}, "experience_required": {"duration": ["minimum 2 years"], "field": ["relevant experience"]}}, {"job_id": "100003009041029", "location_code": "hk", "company": "Retail Technology (Hong Kong) Limited", "job_title": "Product Security Engineer", "description": "The Job\n\nMaintain product security specification and requirements\nMaintain security architecture blueprints\nReview static and dynamic code scanning results and remediation status\nImplement and maintain security products, Infrastructure, and technologies\nProvide security implementation advice\nResponsible for security technologies & products life cycle management\n\nThe Person\n\nBachelor\u2019s degree or above in Computer Science, Information Technology, Information Security and Cyber Security or equivalent discipline\nAt least 3 years working experience in IT security with 1 years of hands-on experience in security requirement definition, security architecture design, and implementation of security technologies.\nFamiliar with various security detection and protection technologies and controls such as Firewalls, IPS, WAF, EDR, SIEM, SOAR, IAM, DLP, Application control, DDoS Mitigation, Network access control, Email security, Anti-phishing, and Anti-Malware\nKnowledge in Secure SDLC, DevSecOps, SAST and DAST\nKnowledge in securing containerized applications, virtual Infrastructure in Microsoft Azure and other cloud technologies\nKnowledge in network, operating systems, and database security\nKnowledge in ISO27001 and 27002, ISO 27017, ISO 27018, PCIDSS, GDPR, PDPO, NIST CSF, CIS Critical Control, OWASP, CIS Hardening Benchmark and Cyber Security Laws\nKnowledge in project and vendor management\nGood EQ and ability to handle high pressure situation with key stake holder\nGood attention to details\nSelf-motivated and can work independently\nInnovative, open minded and adopt quickly to change\nGood analytical, problem solving and inter-personal skills\nGood communication skills. Can communicate effectively in English, Cantonese, and Mandarin\n\n", "employment_types": ["Full Time"], "selling_points": ["3 years of product security experience", "Knowledge in secure SDLC, DevSecOps, SAST, DAST", "Guarantee 13 months, performance bonus"], "locations": ["Tai Koo"], "categories": ["Information Technology (IT)", "IT Project Management / Team Lead", "Security", "Technical / Functional Consulting"], "post_time": "2022-01-12T03:21:11Z", "salary": {"currency": null, "max": null, "min": null, "period": "monthly", "term": null}, "salary_visible": false, "title_keywords": ["engineer"], "responsibilities": ["scanning", "management", "infrastructure", "review", "implementation", "maintain", "architecture"], "requirements": {"degrees": ["degree or above", "bachelor"], "majors": ["computer science", "information technology"], "languages": ["cantonese", "english", "mandarin"], "language_level": [], "hard_skills": ["azure", "cyber security", "vendor", "problem solving", "sdlc", "anti-phishing"], "soft_skills": ["communication skills", "self-motivated", "work independently", "inter-personal skills", "problem solving", "hands-on", "open minded", "attention to details", "innovative"], "languages_combined": [{"language": "cantonese", "language_level": []}, {"language": "english", "language_level": []}, {"language": "mandarin", "language_level": []}]}, "experience_required": {"duration": ["at least 3 years", "1 years"], "field": ["it", "security", "design"]}}, {"job_id": "100003009039763", "location_code": "hk", "company": "Captiare", "job_title": "Senior/ IT Manager - security", "description": "In house perm role\nWork under CISO\nInformation security and risk\n\nOur client is a well-known organization in FI sector. Due to their additional headcount, they are now looking for the captioned position to join their team.\n\nReport to the CISO, you will be responsible on assisting the line manager on cyber risk control and governance related matters. You will focus on assisting the CISO on IT security programme and security projects. You have to analyze and assess the current and future threat landscape, provide the overview of risks and threats.\n\nRequirements:\n\n\nBachelor degree of Information Technology or any related disciplines, certificate holder of CISSP, CISM, CISA, ISO27001 is a plus\nWith around 10 years of experience in cyber security/ control, information security and operational risk, access management, vulnerability management, endpoint security, threat detection & response, systems security\nExperience in formulating best practice and review risk management and control framework\nStrong knowledge of regulations such as TM-E-1, TM-G-1, SA-2 and CRAF would be preferred\nGood command of Chinese and English\nGood communication skill and interpersonal skill\n\nInterested parties please apply online with your latest cv or send Feel free to call Jade Lo +852 3905 1195 for discussion.\n", "employment_types": ["Full Time", "Permanent"], "selling_points": ["In house perm role", "Work under CISO", "Information Security and Risk"], "locations": ["Not Specified"], "categories": ["Information Technology (IT)", "IT Project Management / Team Lead", "IT Management", "Security"], "post_time": "2022-01-11T11:00:29Z", "salary": {"currency": null, "max": null, "min": null, "period": "monthly", "term": null}, "salary_visible": false, "title_keywords": ["it manager"], "responsibilities": ["regulations", "control", "management", "information security", "cyber security", "systems", "review", "communication", "vulnerability management", "report"], "requirements": {"degrees": ["certificate", "degree", "bachelor"], "majors": ["related disciplines", "information technology"], "languages": ["english", "chinese"], "language_level": ["good command"], "hard_skills": ["cyber security", "focus", "plus"], "soft_skills": ["focus", "communication skill", "responsible", "interpersonal skill"], "languages_combined": [{"language": "english", "language_level": ["good command"]}, {"language": "chinese", "language_level": ["good command"]}]}, "experience_required": {"duration": ["10 years"], "field": ["risk management", "management", "security"]}}, {"job_id": "100003009042695", "location_code": "hk", "company": "CKC Solutions Limited", "job_title": "Head of Tech Risk / IT Senior Security Manager - up to 80K+ & Attractive Bonus", "description": "Responsibilities:\n\nDrive strategic and ad-hoc information security and risk analyses, risk papers and risk reports with fact finding, researching and documenting activities;\nLeading the development and maintenance of Group Information Security & Risk Management Strategy, Framework, Policies, Minimum Standards;\nParticipating in, challenging and periodically reporting upon the risks of key IT or TRBCM strategic programs and projects;\nLeading risk assessments (including Data Classification, IT Risk assessments or Business Impact Assessments) on Information Security/Risk and TBCM projects and programs;\nPerforming scheduled/ad-hoc checks for verifying the effectiveness of the controls implemented on various technology areas;\nSupporting the identification of the technology impact of and the coordination of responses to law and regulatory changes, internal & external audit reports, etc. And monitoring the follow-up on the regulatory issue solving related to technology areas;\nMeasuring and reporting the implementation of Information (Technology) security framework throughout the Group;\nPerforming and assisting in other information risk activities where the requirements arise.\n\nRequirements:\n\nUniversity BSc Degree or equivalent, preferably in IT field;\nOver 10\u00a0years\u2019\u00a0experience in Financial Industry with experience on IT Audit, Risk Management or Business Continuity Management areas (Senior title will be offered with more experience)\nSound knowledge of international information security standards and regulations (e.g., SFC IT related regulations, COBIT, ISO 27001, PDPO(HK), GDPR, China Cyber Security Law)\nKnowledge of retail business and/or securities trading business, and associated laws & regulations would be considered a plus;\nGood analytical skills and sound judgment;\nCollaboration skills and ability to work across multiple functional line and geographical locations;\nExperience in Business Continuity Management & having professional education and/or multiple international certifications for Information (Technology) Security (e.g. ISC2, ISACA accreditations) would be considered a plus.\n\nThis is a great opportunity to be part of the team and get more new exposure. If you are interested in this role please send us your CV or call us on +852 2885 8318 for a further discussion.", "employment_types": ["Full Time", "Permanent"], "selling_points": ["Permanent role", "Awesome chance and Career path", "Good prospect, Attractive salary"], "locations": ["Not Specified"], "categories": ["Information Technology (IT)", "IT Project Management / Team Lead", "Security", "Others"], "post_time": "2022-01-12T08:25:43Z", "salary": {"currency": null, "max": null, "min": null, "period": "monthly", "term": null}, "salary_visible": false, "title_keywords": ["manager"], "responsibilities": ["ad-hoc", "reporting", "management", "maintenance", "information security", "data", "policies", "monitoring", "audit", "implementation", "reports", "coordination"], "requirements": {"degrees": ["degree", "bsc"], "majors": ["it"], "languages": [], "language_level": [], "hard_skills": ["plus", "analytical skills", "cyber security"], "soft_skills": ["interested in", "analytical skills"], "languages_combined": []}, "experience_required": {"duration": ["10 years"], "field": ["risk management", "management", "financial industry", "audit", "education", "business", "it", "security"]}}, {"job_id": "100003009038291", "location_code": "hk", "company": "FWD Life Insurance Company (Bermuda) Limited", "job_title": "Senior Analyst (IT Security Assurance), Information Technology", "description": "Established in Asia in 2013 with a trailblazer mentality, FWD is the primary insurance business of investment group, Pacific Century Group (PCG), with minority shareholders Swiss Re Group, GIC Ventures, RRJ Capital and Hopu Investments.\n\nFWD spans 10 markets in Asia including Hong Kong SAR & Macau SAR, Thailand, Indonesia, the Philippines, Singapore, Vietnam, Japan, Malaysia and Cambodia. In Hong Kong, FWD offers life and medical insurance, general insurance, employee benefits, and financial planning. We focus on creating fresh customer experiences and making the insurance journey simpler, faster and smoother, with innovative propositions and easy-to-understand products, supported by digital technology. Through this customer-led approach, FWD aims to be a leading pan-Asian insurer by changing the way people feel about insurance.\n\nIf you are looking for a company where can fuel your inspiration and cultivate your expertise, join us on our exciting journey.\n\nThe Job\n\nWork with Group IT Security and local Information Risk Management for the implementation of security initiatives to ensure the compliance with company\u2019s information security policies and compliance standards\nInvolve in new systems and projects under development as an independent advisor to IT teams and business operations throughout the project life cycle to safeguard the confidentiality, integrity, and availability of company information asset\nDesign and provide solutions and associated compensating controls based on the technical risk assessment results\nAssess relevant policies, procedures, standards, and controls are embedded into BAU IT processes by performing thematic reviews\nPerform risk assessment and trend analysis to ensure that IT risks are identified, measured, recorded and reported, monitored, and remediated timely and within the Company\u2019s risk appetite\nPrepare materials communicating IT security related messages and supporting management reporting\n\nThe Person\n\nDegree in Computer Science, Information Technology, or related disciplines is preferred\nAt least 6 years of relevant experience in IT, preferably in information security or security operation center environment\nHolder of relevant professional certifications (e.g. CISA, CISM, CISSP, CEH)\nExperience in the banking/insurance industry is preferred, big four advisory experience would be an advantage\nAble to work on various platforms and operating systems (such as Windows and Linux) is preferred\nExperience with various scripting tools languages (such as PowerShell, Bash and Python) is preferred\nFamiliar with security technologies (such as SIEM, DLP, Antivirus, EDR, WAF, IPS/IDS, Anti-DDoS Services and Vulnerability Scanners)\nKnowledge of IT security processes, such as patch and vulnerability management, penetration testing and privileged ID management\nKnowledge and experience in security incident detection and incident response\nAble to articulate IT risk in relation to the business\nCommitted, proactive, assertive and positive with a can-do attitude\nAble to articulate IT risk in relation to the business\nStrong interpersonal and communication skills, able to communicate effectively at all levels\nFluent in both spoken and written English and Chinese\n\nWe offer 5-day work, 20-22 days annual leaves, excellent learning & development opportunities and an attractive package to the right candidate.\n\nInformation collected will be treated in strict confidence and used solely for recruitment purpose. The company will retain all applications no longer than 24 months of which will be destroyed thereafter. When there are vacancies in any of our subsidiaries, holding companies, associated or affiliated companies of, or companies controlled by, or under common control with the Company during that period, we may transfer your application to them for consideration of employment. We are an equal opportunity employer. We do not discriminate on the basis of race, sex, disability or family status in employment process.", "employment_types": ["Full Time"], "selling_points": ["Implementation of security initiatives", "Perform risk assessment", "Prepare materials communicating IT security"], "locations": ["Kwun Tong"], "categories": ["Accounting", "Finance / Accounting Manager", "Information Technology (IT)", "Security"], "post_time": "2022-01-11T06:26:36Z", "salary": {"currency": null, "max": null, "min": null, "period": "monthly", "term": null}, "salary_visible": false, "title_keywords": ["senior analyst"], "responsibilities": [], "requirements": {"degrees": [], "majors": [], "languages": [], "language_level": [], "hard_skills": [], "soft_skills": [], "languages_combined": []}, "experience_required": {"duration": [], "field": []}}, {"job_id": "100003009039438", "location_code": "hk", "company": "Guotai Junan International Holdings Limited", "job_title": "Information Security Officer/ Assistant Manager", "description": "Job Description:\n\nAssist in implement remediation security controls based on IT initiatives on technology risk perspective.\nAssist the team to oversight external parties to perform information security assessment including but not limited to; vulnerability scanning, penentration test, technical security assessment and etc.\nAssist the team to conduct periodic review and technical assessment when needed including phishing attack simulation, penetration test, vulnerability scanning and etc\u2026\n\nRequirements:\n\nPassionate in InfoSec and Cybersecurity area\nHolder of Bachelors Degree or above in IT/Computer Science \u00a0related disciplines, other discipline with knowledge in IT are also welcome.\n2+ years' working experience in InfoSec/Cybersecurity/TRM. No experience but with strong cybersecurity knowledge will also consider for a lower title\nWith previous working experience in technology consulting firm or Big 4 is a plus\nCertified in professional certfications is a plus but not necessary, e.g.: CISSP, CISA, CRISC, CEH, etc\u2026\nProficiency in spoken English and Chinese, fluency in Putonghua is a must.\nFresh graduates are welcomed.\n\n\nWe offer an attractive remuneration package to the right candidate. Interested parties please forward your full resume with availability, expected salary by pressing \"Apply now\" or send it to 27/F., Low Block, Grand Millennium Plaza, 181 Queen\u2019s Road, Central, Hong Kong.\n\n(Data collected will be kept strictly confidential and used for recruitment purpose only.)", "employment_types": ["Full Time", "Permanent"], "selling_points": ["Assist in implement remediation security controls", "Assist the team to conduct periodic review", "Oversight external parties to perform assessments"], "locations": ["Central & Western Area"], "categories": ["Information Technology (IT)", "Security", "Others", "Banking / Finance", "Risk Management"], "post_time": "2022-01-11T09:46:31Z", "salary": {"currency": null, "max": null, "min": null, "period": "monthly", "term": null}, "salary_visible": false, "title_keywords": ["officer", "assistant manager"], "responsibilities": ["scanning", "review", "external parties", "information security"], "requirements": {"degrees": ["degree or above"], "majors": ["related disciplines", "it", "computer science"], "languages": ["putonghua", "english", "chinese"], "language_level": ["fluency", "proficiency"], "hard_skills": ["no", "plus"], "soft_skills": ["passionate"], "languages_combined": [{"language": "putonghua", "language_level": ["fluency", "proficiency"]}, {"language": "english", "language_level": ["fluency", "proficiency"]}, {"language": "chinese", "language_level": ["fluency", "proficiency"]}]}, "experience_required": {"duration": ["2+ years"], "field": ["big 4", "consulting"]}}, {"job_id": "100003009050625", "location_code": "hk", "company": "Walters People (HK)", "job_title": "Network Engineer - Finance", "description": "The role is responsible to implement and contribute to Network strategies, standards, policies and planning to enable the best solution.\n\nResponsibilities:\n\nResponsible for network related project implementation.\nExperience on Checkpoint, Palo Alto, and Fortinet; set up the Data Center and Main Office.\nMaximize network performance by monitoring performance, troubleshooting network problems and outages, scheduling upgrades and collaborating with network architects on network optimization\nProvide support for daily network operation and maintenance.\nConfiguring and installing various network devices and services (e.g., routers, switches, firewalls, load balancers, wireless, VPN, QoS)\nUpgrade data network equipment to the latest stable firmware releases.\nWork within established configuration and change management policies to ensure awareness, approval and success of changes made to the network infrastructure\nSelect and implement security tools, policies, and procedures in conjunction with the company's security team\nLiaise with vendors and other IT personnel for problem resolution\n\nJOB REQUIREMENTS:\n\nDegree holder in Information Technology, Computer Science, Electronic Engineering, Computer Engineering, or similar discipline\nStrong previous work experience on Cisco, Palo Alto, and Fortinet.\nDeep understanding of networking protocols (e.g., IPSEC, HSRP, BGP, OSPF, 802.11, QoS).\nCCNA or CCNP\nGood team player and self-starter to work with minimum supervision.\nGood problem solving, systematic work approach and communication skills in English are required.\nFamiliar with managing external vendors, IT support operations, and able to communicate with users across all levels.\nProven ability to work under stressful conditions, such as business-related crises.\nStrong oral communication and written communication skills.\nGood command of written and spoken English and Chinese.", "employment_types": ["Full Time", "Permanent"], "selling_points": ["CCNA/CCNP", "Router/Switching/Firewall", "DC Network"], "locations": ["Not Specified"], "categories": ["Information Technology (IT)", "Hardware", "Security", "Network & System"], "post_time": "2022-01-14T11:00:09Z", "salary": {"currency": "HKD", "max": 69999, "min": 45000, "period": "monthly", "term": null}, "salary_visible": true, "title_keywords": ["engineer"], "responsibilities": ["network infrastructure", "provide support", "change management", "maintenance", "data", "outages", "upgrades", "configuration", "monitoring", "policies", "troubleshooting", "implementation", "procedures", "resolution", "scheduling", "configuring", "installing", "liaise with"], "requirements": {"degrees": ["degree holder"], "majors": ["computer engineering", "engineering", "computer science", "information technology"], "languages": ["english", "chinese"], "language_level": ["good command", "good"], "hard_skills": ["problem solving", "ccnp", "ccna"], "soft_skills": ["communication skills", "good team player", "oral", "deep", "systematic", "problem solving", "communication"], "languages_combined": [{"language": "english", "language_level": ["good command", "good", "good"]}, {"language": "chinese", "language_level": ["good command", "good"]}]}, "experience_required": {"duration": [], "field": []}}, {"job_id": "100003009051097", "location_code": "hk", "company": "Pinpoint Asia Limited", "job_title": "IT Audit Manager - Leading Bank", "description": "Our client, a leading bank, is looking for an experienced IT Audit Manager to join their Audit 3LOD team. The successful candidate will be bringing IT audits especially for their Cyber Security and new digital banking initiatives.\u00a0\n\nResponsibilities:\n\nLead the IT Audit across audit plans, and methods across various IT areas including Cyber Security, Digital, Banking Procedures and IT Controls.\nConduct risk assessment, audit planning, audit testings, control evaluation, etc. Provide audits finding reports, follow-up, and verifications.\nDevelop and monitor cybersecurity development initiatives, through design and perform of continuous risk assessment methodology\nPerform Investigation on technology-related frauds and incidents.\nWork closely with the management through tracking and reporting function, to ensure a timely response to executives, board, and regulators.\nStay up-to-date with evolving industry and regulatory change requirements which may impact the business and technology team.\nUpdate and maintain Audit systems and provide suggestions on efficiency and effectiveness improvement.\u00a0\n\n\u00a0Required Skills/Experience:\n\nAt least 4 years of experience in the IT Audit area, ideally with exposure to the banking / financial services industry.\nUnderstanding regulatory requirements including HKMA is highly preferable.\nUnderstanding of banking information security and information technology governance and assessment.\nOutstanding communication and interpersonal skills. Ability to work effectively with all levels of the organization.\nStrong analytical skills required to enable independent research and accurate assessments of risk management process effectiveness and adherence to regulatory requirements.\nCISA, CISM, CISSP, or equivalent industry certification is preferred.\n\nIf this outstanding opportunity sounds like your next career move, please send your resume in Word format to Danny Kwan at resume(at)pinpointasia(dot)com and put IT Audit Manager - Leading Bank in the subject header.\n\nData provided is for recruitment purposes only.", "employment_types": ["Full Time", "Permanent"], "selling_points": ["IT Audit", "Cybersecurity", "Leading Well-known Bank"], "locations": ["Not Specified"], "categories": ["Information Technology (IT)", "IT Auditing", "Security", "Technical / Functional Consulting"], "post_time": "2022-01-15T02:10:20Z", "salary": {"currency": "HKD", "max": 69999, "min": 45000, "period": "monthly", "term": null}, "salary_visible": true, "title_keywords": ["manager"], "responsibilities": ["information security", "cyber security", "data", "regulatory requirements", "audit", "design", "communication", "maintain", "evaluation", "plans", "control", "monitor", "develop", "reports", "banking", "reporting", "management", "procedures", "investigation", "audits", "tracking", "systems", "recruitment", "planning"], "requirements": {"degrees": [], "majors": [], "languages": [], "language_level": [], "hard_skills": ["hkma", "word", "analytical skills", "cyber security"], "soft_skills": ["work effectively", "independent", "timely", "analytical skills", "communication and interpersonal skills", "accurate"], "languages_combined": []}, "experience_required": {"duration": ["at least 4 years"], "field": ["financial services industry", "it", "audit", "banking"]}}, {"job_id": "100003009037837", "location_code": "hk", "company": "Dah Sing Financial Group", "job_title": "Manager, Technology Risk and Information Security", "description": "Job Purpose:\nSupport the Head of Technology Risk to provide 1st line technology risk management services for ITD division.\nKey Role and Responsibilities:\nSupport the Head of Technology Risk to oversee technology risk management programmes\nDesign, develop and maintain Information Security Polices, Standards and Guidelines\nProvide technical guidance to application development and infrastructure tam regarding security designs and configurations\nAssist in communicating risk management standards, policies and procedures to relevant stakeholders\nConduct regular security assessment on internal system, network and infrastructure\nFacilitate risk management committee meeting for enhancing risk governance and oversight\nDesign and apply operational control process to ensure IT operational and control risks are within acceptable risk appetite\nDesign and monitor Key Risk Indicators.\u00a0 Proficiency in risk reporting to facilitate effective management oversight on technology risk and cybersecurity matters\nPlay a governance role on IT outsourcing.\u00a0 Perform regular security assessment on 3rd party IT service provider\nParticipate in developing, tuning and implementing threat detection analytics\nAct as focal point to support internal, external and regulatory audits\nPrepare and conduct security awareness training for internal IT and non-IT users\nJob Requirements:\nMinimum 5 years of relevant work experience in technology risk, information security and cybersecurity\nUniversity graduate in Computer Science / Information Technology or equivalent\nPossess one or more professional certificates listed below:\nISC2 Certified Information Security Professional (CISSP)\nISACA Certified Information System Auditor (CISA)\nISACA Certified Information Security Manager (CISM)\nISC2 Certified Cloud Security Professional (CCSP)\nSolid experience in vulnerability management, penetration test and technology risk assessment\nSound knowledge in Public Key Infrastructure (PKI), Internet vulnerability, cybersecurity, firewalls, Intrusion Detection/Prevention System\u00a0 and application security of finance/banking systems\nSound experience in performing vulnerability scanning, penetration test and technology risk assessment\nSolid experience in regulators\u2019 requirement on technology risk management including the Supervisory Policy Manuals of HKMA, Cyber Resilience Assessment Framework (CRAF), Personal Data Privacy Ordinance, PCI Data Security Standard, SFC guidelines and Customer Security Controls Framework of SWIFT\nBanking experience is an advantage\nStrong communication skill, both in Chinese and English\nMature, independent and able to deliver quality results under tight schedule\nGood communication and interpersonal skills\nPlease note that only shortlisted candidates will be notified.", "employment_types": ["Permanent"], "selling_points": ["Assist in communicating risk management standards", "Minimum 5 years of relevant work experience", "University graduate in Computer Science / I.T"], "locations": ["North Point"], "categories": ["Information Technology (IT)", "IT Management", "Security", "Network & System"], "post_time": "2022-01-11T04:01:46Z", "salary": {"currency": null, "max": null, "min": null, "period": "monthly", "term": null}, "salary_visible": false, "title_keywords": ["manager"], "responsibilities": ["guidance", "management", "control", "reporting", "it service", "information security", "guidelines", "policies", "infrastructure", "procedures", "monitor", "design", "develop", "developing", "maintain", "audits", "application development"], "requirements": {"degrees": ["university graduate"], "majors": ["computer science", "information technology"], "languages": ["english", "chinese"], "language_level": [], "hard_skills": ["hkma", "swift", "information system"], "soft_skills": ["communication and interpersonal skills", "communication skill", "independent", "mature"], "languages_combined": [{"language": "english", "language_level": []}, {"language": "chinese", "language_level": []}]}, "experience_required": {"duration": ["minimum 5 years"], "field": ["risk management", "management", "supervisory", "banking experience", "security"]}}, {"job_id": "100003009037999", "location_code": "hk", "company": "Ensign Infosecurity (East Asia) Limited", "job_title": "Service Delivery Manager (Cyber Security)", "description": "Job Overview\n\nCyber Security Manager performs deployment of internally developed security products or third party security products for projects, and also provide technical pre-sales support to the assigned accounts\n\nDuties and Responsibilities\n\nTake over the services during transition from the project phase to operational phase in order to deliver contracted service commitments.\nWork with the Ensign Account Manager and Ensign Delivery Teams to ensures the baseline documents for the services provided to client are up to date.\nManage service delivery and Service Level Agreements (SLAs) for assigned customer(s) to ensure that Ensign\u2019s obligations are met.\nSDM oversees stakeholders in different stages of the delivery process, even though they may not be their direct line manager. The service delivery manager holds all operating units accountable for carrying out the required processes and tasks and providing great customer service.\nProvide and present service performance reports to client with reference to agreed format and period of reporting.\nWork with the internal stakeholders to provide incident report to customer.\nWork with the Ensign and Customer Change Management team to ensure Service Request(s) and Change Request(s) are reviewed and tracked base on the approved processes.\nWork with the Account Manager on client\u2019s feedback for continual service improvement.\nSDMs to assess customers\u2019 feedback and improving procedures accordingly to ensure that great customer service is provided at all times. SDMs to evaluate a customer\u2019s experience against a set of customer satisfaction goals and criteria. When scores fall below these thresholds, service delivery managers conduct additional research. And develop/execute service improvement.\nWork with internal and external stakeholders to identify, select, plan and deliver initiatives with a focus on improving the customer experience, process efficiency and effectiveness, service quality, and profitability\nPerform other duties as required by the management\n\nRequirements\n\nRequirements include, but not exhaustive:\n\nDegree / Diploma in Information Technology / Information Systems / Computer Science, Business IT or other relevant disciplines.\nAt least Six (6) years of IT Service Outsourcing experience with proven ability to work with internal and external parties.\nExcellent interpersonal skills both in written and presentation.\nGood business acumen and customer focus.\nDemonstrate the drive to excel and achieve goals.\nSelf-motivating and pro-active in heading off problems and in identifying new opportunities on the account for Ensign.\nStrong analytical and problem-solving skills combined with the ability to provide quick resolution to problems.\nLooking for people who have a passion for providing excellent customer service, who possess strong interpersonal and leadership skills, and who enjoy working as part of a team\nBenefit Offer\u00a0\n\n\nExcellent career prospects will be offered to the right candidates.\u00a0 Salary will be commensurate with qualifications and experience.\u00a0 Attractive remuneration package includes:\nAllowance\nMedical Insurance (includes dependents)\n18 - 21 working days\u2019 annual leave\nDiscretionary bonus\nStudy and Continuous Learning Sponsorship\nOn-the-job training\nGuidance from experienced mentor\nApplications\nAn attractive remuneration package will be offered to the right candidates.\nInterested parties please submit your application to the following URL link:\n\nhttps://ensigninfosecurity.wd3.myworkdayjobs.com/Ensign_Careers/job/Hong-Kong/Manager--Managed-Security-Services--EnSOC---HK-_JOBREQ-0001303\n\n", "employment_types": ["Full Time", "Permanent"], "selling_points": ["Degree in Information Technology or related", "Manage service delivery and SLA", "Assess customers\u2019 feedback and improving procedure"], "locations": ["Kwun Tong"], "categories": ["Information Technology (IT)", "IT Project Management / Team Lead", "Security", "Network & System"], "post_time": "2022-01-11T04:30:51Z", "salary": {"currency": null, "max": null, "min": null, "period": "monthly", "term": null}, "salary_visible": false, "title_keywords": ["manager"], "responsibilities": ["service delivery", "reporting", "perform other duties", "management", "change management", "performance reports", "teams", "procedures", "quality", "develop", "evaluate", "customer service", "plan", "report"], "requirements": {"degrees": ["diploma", "degree"], "majors": ["business", "it", "computer science", "information technology"], "languages": [], "language_level": [], "hard_skills": ["problem-solving skills", "excel", "focus", "acumen"], "soft_skills": ["exhaustive", "passion for", "interpersonal", "enjoy working", "leadership skills", "customer service", "interpersonal skills", "learning", "pro-active", "business acumen", "problem-solving skills", "customer focus", "presentation"], "languages_combined": []}, "experience_required": {"duration": [], "field": ["it"]}}, {"job_id": "100003009039720", "location_code": "hk", "company": "Morgan Half International (Hong Kong) Limited", "job_title": "IT Manager - Cloud Security (Microsoft 365, Aliyun/Azure/AWS)", "description": "Client Details:\n\nOur client is a reputable company. They are looking for a Cloud Security IT Manager. In this role you will accountable to develop the cloud security design framework.\n\nResponsibilities:\n\n\nAccountable for development of the Cloud Security Design framework for new technology solutions\nResponsible for embedding best practice security through the setup and maintenance of Cloud Landing Zones\nDevelop security hardening standard for AWS, Azure and Aliyun cloud platforms\nResponsible for leading cloud security project to automate cloud hardening compliance checking and remediation\nDevelop cloud security alert handling SOP for SOC to follow\nPerform security risk assessment on Cloud applications/IT systems to identify security weaknesses and non-compliance with IT Reference Architecture and IT security control matrix\nImplement RPA/automation to improve team efficiency\n\nRequirements:\n\nDegree holder/or above with IT related discipline\n5+ years of IT security experience\u00a0\nHolder of cloud security certification such as CCSP, Aliyun ACP, AWS Certified Security Specialty, Azure security certification\nManagerial grade experience with cyber and cloud security knowledge\nStrong knowledge of IT general controls, cybersecurity risks, technology risks (including infrastructure, cloud and application security)\nHand-on security assessment/implementation experience on Microsoft 365, Aliyun/Azure/AWS public cloud platforms.\nHand-on experience on cloud landing zone design and maintenance\nPractical skill on cloud configuration compliance checking automation\nA strong team player with good analytical and problem-solving skill\nProject management experience is preferred\nGood communication skill\nGood English and Chinese (including Mandarin) Language skill (both written & verbal)\n\nTo apply online, please press \"Apply Now\" button below. For any inquiries, please email info @morganhalf.com", "employment_types": ["Full Time"], "selling_points": ["CCSP, Aliyun ACP, AWS Certified Security Specialty", "Listed company, Cyber Security Team", "13 months salary plus bonus, stable environment"], "locations": ["Not Specified"], "categories": ["Information Technology (IT)", "Security", "Technical / Functional Consulting", "Technical Writing"], "post_time": "2022-01-11T10:40:42Z", "salary": {"currency": null, "max": null, "min": null, "period": "monthly", "term": null}, "salary_visible": false, "title_keywords": ["it manager"], "responsibilities": ["control", "maintenance", "compliance", "systems", "checking", "design", "develop", "architecture", "setup"], "requirements": {"degrees": ["degree holder"], "majors": ["it"], "languages": ["english", "chinese", "mandarin"], "language_level": ["good"], "hard_skills": ["azure", "maintenance", "problem-solving", "aws", "project management", "public cloud platforms"], "soft_skills": ["problem-solving", "project management", "team player", "communication skill"], "languages_combined": [{"language": "english", "language_level": ["good"]}, {"language": "chinese", "language_level": ["good"]}, {"language": "mandarin", "language_level": []}]}, "experience_required": {"duration": ["5+ years"], "field": ["managerial", "maintenance", "design", "project management", "it", "security"]}}, {"job_id": "100003009046624", "location_code": "hk", "company": "Reasonable Software House Limited", "job_title": "IT Trainee - Network Engineer/ Programmer/ Business Analyst (Fresh graduates are welcome)", "description": "Web/Mobile Developer\n\nResponsibilities:\n\nResponsible for on-going in-house Web applications\u00a0and Mobile Apps developments and enhancements\nEither experience\u00a0 Java or C#, .NET programming are welcome\nInvolve in coding, testing, UAT\nProvide business applications support for the programming system\n\n\u00a0Requirements:\n\nDegree in Computer Science/Engineering, Information Engineering or equivalent\nPassionate about programming\nCoding is requirement\nInternship or school project on coding is advantage\nFresh graduates are welcome\n\nInformation Security Specialist\n\nResponsibilities\n\nMonitor firewall, OS, log for security alert\nConduct Regular\u00a0Vulnerability scan\nPrepare user manual and conduct training\nFollow ISO27001 standard\nNetwork abuse helpdesk\nSet up security including firewall etc.\n\nRequirements:\n\nDegree holder with major in Computing, Computer Science/Engineering, Information Engineering or equivalent is an advantage\nExcellent interpersonal, verbal and written communication skills\n\nBusiness Analyst\n\nResponsibilities\n\nParticipate in business and systems projects and ensure quality delivery of the systems\nLead requirements gathering, analysis and prepare user requirement specifications in accordance with business needs\nManage requirements throughout project life cycles\nPrepare test plan and participate in quality assurance testing cycles\nConduct SIT to ensure the enhanced systems meet the requirement specifications\nSupport UAT, prepare user manual and conduct training\nAssist project team members with the development of project documentation\nAnalyze business processes, identify problem areas of systems and recommend solutions\nCo-ordinate with users of different areas , investigate & resolve issues and concerns raised by users\nPrioritizing initiatives based on business needs and requirements\nMonitoring deliverables and ensuring timely completion of projects\n\nRequirements:\n\nDegree holder with major in Computing, Computer Science/Engineering, Information Engineering or equivalent\nExcellent interpersonal, verbal and written communication skills\n\n\nFor a confidential discussion, please contact Alan at 35906853\n\nTo apply, email resume and application letter to hr[at]reasonable.hk", "employment_types": ["Full Time", "Permanent", "Contract"], "selling_points": ["IT trainee", ".net Programming", "project manager"], "locations": ["Lai Chi Kok"], "categories": ["Information Technology (IT)", "IT Management", "Software Development", "Security"], "post_time": "2022-01-13T17:06:38Z", "salary": {"currency": "HKD", "max": 24999, "min": 20000, "period": "monthly", "term": null}, "salary_visible": true, "title_keywords": ["programmer", "engineer", "trainee", "business analyst"], "responsibilities": ["uat", "coding", "testing"], "requirements": {"degrees": ["degree", "degree holder"], "majors": ["engineering", "computer science"], "languages": [], "language_level": [], "hard_skills": ["analysis", "os", "programming", "firewall", "documentation"], "soft_skills": ["communication skills", "passionate about", "timely", "interpersonal", "prioritizing"], "languages_combined": []}, "experience_required": {"duration": [], "field": []}}, {"job_id": "100003009037449", "location_code": "hk", "company": "Thales Transport & Security (Hong Kong) Limited", "job_title": "CSOC Analyst (Cyber Security)", "description": "Responsibilities\n\n\nBuild the initial service for the customer\nAdministrate and Monitor tools\nProcess and feedback definition\nMonitor contracts initialization\nDeep client environment knowledge\nTechnological watch\nContinuously improve the service with the customer once the build is over\nProvide standby service responding to security incident after office hour\n\nRequirements\n\n\n1-2 years of relevant work experience\nProfessional in security domain\nKnowledge of log parsing and management, correlation and incident management\nKnowledge in networking like firewall, switches, VLAN, MPLS, VPN, HA proxy, etc\nKnowledge in system administration like Linux & Windows OS, LDAP, DNS, DHCP, SMTP, anti-virus, backup, etc\nKnowledge in storage administration like SAN and DAS\nBasic knowledge in Relational Databases (mysql, Oracle, MongoDB) and Big Data (ElasticSearch)\nKnowledge in monitoring of IT infrastructure\nKnowledge in software like Kibana, Kafka, Storn, Punchlet, Java, Apache, Ruby, etc\nBasic knowledge on NetForensic correlation", "employment_types": ["Full Time", "Permanent"], "selling_points": ["Shift duty is not required", "Certificates allowance", "Fresh graduates are welcome"], "locations": ["Mong Kok"], "categories": ["Information Technology (IT)", "Security"], "post_time": "2022-01-11T02:54:29Z", "salary": {"currency": null, "max": null, "min": null, "period": "monthly", "term": null}, "salary_visible": false, "title_keywords": ["analyst"], "responsibilities": ["contracts", "monitor"], "requirements": {"degrees": [], "majors": [], "languages": [], "language_level": [], "hard_skills": ["linux", "java", "apache", "basic", "dns", "ruby", "os", "vpn", "firewall", "databases", "oracle"], "soft_skills": [], "languages_combined": []}, "experience_required": {"duration": ["1-2 years"], "field": []}}, {"job_id": "100003009050808", "location_code": "hk", "company": "Ztore HK Limited", "job_title": "Analyst Programmer (Java)", "description": "We are expanding our team and looking for a number of passionate and talented IT professionals to join us and support our business to grow innovatively.\n\nAs a Java Analyst Programmer, you will work closely with internal Development Team to design, develop, test, and implement a Middleware software project that support the business growth.\n\n\nResponsibilities:\n\n\nCommunicating with internal development team and use cases into functional applications\nParticipate in full development life cycle from system design, coding, development, testing, debug, document and implement\nEnsure the best possible performance, quality, and responsiveness of the applications\nIdentify bottlenecks and bugs, and devise solutions to these problems\nHelp maintain code quality, organisation, and automatization\nUnderstanding the business domain deeply and working closely with business stakeholders\n\nRequirement:\n\n\nMinimum 6 Year of web development experience working with Java, Spring Boot, Spring MVC, Spring Cloud and MySQL in Microservices architecture\nProficient in Java 8, familiar with OOP, Java multi-threading, high concurrency, IO / NIO, network communication, etc\nFamiliar with commonly used design patterns, with experience in design and development of large-scale distributed, high concurrency, high load, high availability systems \u2022 Strong understanding of TDD development approaches\nExperienced in Docker and Kubernetes will be an added advantage\nKnowledge on Kafka, MQ and AWS Cloud is a plus\nAbility to quickly grasp any new technologies\nGood communication skill in both Chinese & English\n\nWhat you will learn:\n\n\nAuto CI/CD\nVersioning tools, such as Git\nContainerized Application (Docker, AWS Fargate, Kubernetes)\nAWS Cloud Services\nHow to solve a business problem\nHow to manage a project\nExperienced in a well-planned software development cycle", "employment_types": ["Full Time"], "selling_points": ["Java, Spring Boot, Microservices Architecture", "Docker, Kubernetes, MQ, AWS Cloud", "Test Driven Development"], "locations": ["Lai Chi Kok"], "categories": ["Information Technology (IT)", "IT - Webmaster / SEO", "Software Development", "Security"], "post_time": "2022-01-14T11:26:50Z", "salary": {"currency": null, "max": null, "min": null, "period": "monthly", "term": null}, "salary_visible": false, "title_keywords": ["analyst programmer"], "responsibilities": ["quality", "coding", "testing", "communicating with", "system design", "maintain"], "requirements": {"degrees": [], "majors": [], "languages": ["english", "chinese"], "language_level": ["good"], "hard_skills": ["web development", "java", "plus", "io", "git", "microservices", "aws", "spring"], "soft_skills": ["communication", "communication skill"], "languages_combined": [{"language": "english", "language_level": ["good"]}, {"language": "chinese", "language_level": ["good"]}]}, "experience_required": {"duration": ["minimum 6 year"], "field": ["development", "design"]}}, {"job_id": "100003009035767", "location_code": "hk", "company": "Macroview Telecom Limited", "job_title": "Systems Engineer Trainee - CyberSecurity", "description": "How you will contribute:\n\n- Assist in the implementation of security-related projects by working closely with internal team and customers\n\n- Assist to conduct Cybersecurity research\n\n- Provide 1st tier technical support and maintenance of security platform\n\n- Assist in the preparation of technical documents to customers\n\nWho are we looking for:\n\n- Interested in Cybersecurity\n\n- Diploma or above in Computer Science or IT related disciplines\n\n- Have a strong sense of responsibility and an eagerness to learn\n\n- Have good interpersonal and communication skills\n\nWe offer attractive remuneration package, medical benefits and marriage leave to the right candidate. Interested parties please send full resume with expected salary by clicking 'Apply Now'.\nAll information collected will be used for recruitment purpose only.\nTo know more about Macroview, please visit:\u00a0http://www.macroview.com\n\u200b", "employment_types": ["Full Time", "Permanent"], "selling_points": ["Fresh graduates will be considered", "CyberSecurity role", "Technical Support"], "locations": ["Quarry Bay"], "categories": ["Information Technology (IT)", "Security", "Network & System", "Others", "Student / Fresh Graduate / No Experience"], "post_time": "2022-01-10T08:24:56Z", "salary": {"currency": null, "max": null, "min": null, "period": "monthly", "term": null}, "salary_visible": false, "title_keywords": ["systems engineer", "trainee"], "responsibilities": ["technical support", "communication", "implementation", "maintenance"], "requirements": {"degrees": ["diploma or above"], "majors": ["related disciplines", "it", "computer science"], "languages": [], "language_level": [], "hard_skills": ["maintenance"], "soft_skills": ["communication skills", "interested in", "interpersonal", "sense of responsibility"], "languages_combined": []}, "experience_required": {"duration": [], "field": []}}, {"job_id": "100003009036000", "location_code": "hk", "company": "Hashkey Digital Asset Group Limited", "job_title": "Senior Cyber Security Manager", "description": "Job Description:\n\n\nWorking with Corporate IT team closely to support Cybersecurity matters and tackling with regulatory requirements with SFC and MAS timely\nImplementing information security controls and ensure the efficiency of the controls in HK office\nWorking as key contact person and coordinator between SH security team and different stakeholders in HK office\nDevelop security awareness program and promote security culture across the organization in partnership with internal stakeholders\n\nRequirements:\n\n\nA University degree with a major in economics, mathematics, computer science, physics or similar and at least 8 years of experience in the Audit, Risk & Compliance or Cyber Security field\nSolid knowledge in information security principles and practices\nProven hands-on expertise in the following areas\nPolicy Making\nPhysical Security\nSecurity Compliance\nSecurity Audits\nSecurity Risk Management\nBusiness Level Communication\nIT Architecture\nIndustry recognized training and certification (e.g., CISSP, CISA, CRISC, CISM, CGEIT etc.) is a plus\nExcellent command in both spoken and written Chinese (Cantonese and Mandarin) and English\n\nJoin us in our mission to make a lasting contribution to the digital asset community!", "employment_types": ["Full Time"], "selling_points": ["Min. 8 yrs of experience in Audit, Cyber Security", "Solid knowledge in information security principles", "Support Cybersecurity matters"], "locations": ["Pok Fu Lam"], "categories": ["Banking / Finance", "Financial Services", "Information Technology (IT)", "Security"], "post_time": "2022-01-10T09:02:33Z", "salary": {"currency": null, "max": null, "min": null, "period": "monthly", "term": null}, "salary_visible": false, "title_keywords": ["manager"], "responsibilities": ["regulatory requirements", "contact", "information security", "develop"], "requirements": {"degrees": ["university degree"], "majors": ["mathematics", "economics", "computer science", "physics"], "languages": ["cantonese", "english", "chinese", "mandarin"], "language_level": ["excellent"], "hard_skills": ["make", "plus", "cyber security"], "soft_skills": ["communication", "hands-on"], "languages_combined": [{"language": "cantonese", "language_level": ["excellent"]}, {"language": "english", "language_level": ["excellent"]}, {"language": "chinese", "language_level": ["excellent"]}, {"language": "mandarin", "language_level": ["excellent"]}]}, "experience_required": {"duration": ["at least 8 years"], "field": ["compliance", "security", "audit"]}}, {"job_id": "100003009047103", "location_code": "hk", "company": "Fortune Technologies International Ltd", "job_title": "Senior IT Technical Engineer", "description": "Responsibilities\n\nProvide technical support to end user, either on-site or by phone.\nHandle technical issues and inquiries related to networking, security, operation system and VMware infrastructure.\nDaily check system health, backup issue.\nMaintain\u00a0inventory records, and prepare project report.\nEnsure outstanding incidents and requests are escalated properly and monitored\nEstablish and maintain appropriate and effective communication with users, technical teams and vendors.\n\nRequirements\n\nHigher Diploma or above in Computer Studies or equivalent\nAt least 3 years of hands-on experience\nCandidates with less experience will also be considered\nGood communication skill, good time management\nMature and independent, self-motivated and willing to take initiative to keep updates on IT knowledge\nGood command of written and spoken English and Chinese", "employment_types": ["Full Time", "Permanent"], "selling_points": [], "locations": ["Wan Chai Area"], "categories": ["Information Technology (IT)", "Hardware", "Security", "Network & System"], "post_time": "2022-01-14T02:19:49Z", "salary": {"currency": null, "max": null, "min": null, "period": "monthly", "term": null}, "salary_visible": false, "title_keywords": ["technical engineer"], "responsibilities": ["technical support", "inventory", "infrastructure", "teams", "communication", "maintain", "report"], "requirements": {"degrees": ["higher diploma or above"], "majors": ["computer studies"], "languages": ["english", "chinese"], "language_level": ["good command"], "hard_skills": ["it knowledge"], "soft_skills": ["self-motivated", "independent", "communication skill", "mature", "hands-on", "time management", "initiative"], "languages_combined": [{"language": "english", "language_level": ["good command"]}, {"language": "chinese", "language_level": ["good command"]}]}, "experience_required": {"duration": ["at least 3 years"], "field": []}}, {"job_id": "100003009042861", "location_code": "hk", "company": "Ingram Micro (China) Ltd", "job_title": "System Engineer, Cloud", "description": "Main Duties and Responsibilities\n\nIdentify sales leads with peers, present Cloud portfolio to new clients and maintain a good working relationship with different stakeholders\nDriving subscription and services revenue on Hybrid/Multi-Cloud products through prospects for potential new partners\nStep up and work with other internal colleagues to enable Partners in up-selling Cloud product\nBuild, manage and maintain a substantial pipeline of qualified opportunities to underpin target achievement with internal sales team and channel partners\nPresent new products and services and enhance existing relationships\nUsing knowledge of the market and competitors, identify and develop the company\u2019s unique selling propositions and differentiators\nExperience to architect the framework and may need to deliver project(s) with stakeholders\n\nSkills and Attributes Requirements\n\nKnowledge and experience in Microsoft Azure and cloud synergy solution (storage / backup / DR / workspace / big data)\nProfessional Certificate in Azure and/or AWS Cloud Certification is a plus\nGood communication and past project-handling skills is recommended\n\n\u00a0Academic and Language Requirement\n\nUniversity Degree in Information Technology or related discipline\nHigh Proficiency in spoken and written English and Cantonese\n\nBenefits\n\n12 \u2013 18 Days Annual Leave\nBank Holidays\nMedical and Life insurance\n5-day work per week\nEducation subsidies\nGlobal exposure\nWork from home arrangement\nEmployee referral bonuses\n10 mins walk from MTR\n\nInterested parties please submit full resume with current/last salary, expected salary, and available date by clicking 'Apply Now' below.\n\nIngram Micro is an equal opportunity employer and welcomes applications from all qualified candidates. Information provided will be treated in strict confidence and will only be used for recruitment-related purposes.", "employment_types": ["Full Time", "Permanent"], "selling_points": ["Fresh graduate is welcome", "Medical and Life insurance; 5-day work per week", "Work from Home Arrangement"], "locations": ["Kwun Tong Area"], "categories": ["Information Technology (IT)", "IT Management", "Security", "Network & System"], "post_time": "2022-01-12T09:02:12Z", "salary": {"currency": null, "max": null, "min": null, "period": "monthly", "term": null}, "salary_visible": false, "title_keywords": ["system engineer"], "responsibilities": ["maintain", "sales team", "develop"], "requirements": {"degrees": ["certificate", "university degree"], "majors": ["information technology"], "languages": ["cantonese", "english"], "language_level": ["proficiency"], "hard_skills": ["plus", "azure", "aws"], "soft_skills": ["communication"], "languages_combined": [{"language": "cantonese", "language_level": ["proficiency"]}, {"language": "english", "language_level": ["proficiency"]}]}, "experience_required": {"duration": [], "field": []}}, {"job_id": "100003009036213", "location_code": "hk", "company": "Newrecs Consultancy Limited", "job_title": "Information Security Assistant Manager / Security Manager- Leading Banks", "description": "Our client is a leading bank in Hong Kong, they are now expanding and looking for\u00a0Assistant Manager\u00a0/ Security Manager to join their dynamic and professional team.\u00a0\n\n\nResponsibilities:\n\nAssist to formulate and maintain information security policies / BCP plan / manuals and procedures\nSupport security administration on application logical access\u00a0and\u00a0identity management, hardening, security monitoring and vulnerability management\nSupport security setup, design access control matrix, and control reviews\nConduct IT security risk assessment / outsourcing service provider reviews\nImplement and support IT security systems and projects\nAssist to perform operational risk and compliance activities\nCoordinate with external / internal auditors on audit matters and follow up audit findings.\nConduct Security incident handling, investigation and reporting\nProvide security awareness training to staffs and consultation on information security area\n\n\n\nRequirements:\n\nUniversity degree or above in Computer Science or related discipline\nMinimum 2 years experience in information security in banking sector\nStrong knowledge in information security / risk management principles\nStrong knowledge of banking regulation on technology risk management and cyber security\nTechnical knowledge in network / server / OS / Databases / security / banking applications\nSolid experience in security solution implementation, server and network administration, and incident management\nCan work independently and a good team player\nGood command of written and spoken in English and Chinese (preferably fluent in Mandarin)\n\n\n\nIf you are interested to this role, please quick apply or send your resume with your expected salary to us Internal @ newrecs.com.hk.\u00a0", "employment_types": ["Full Time", "Permanent"], "selling_points": ["Around 3 years of exp in banking sector", "CISA, CISSP, CISM is prefered", "In-house perm role with fruitful bonus"], "locations": ["Central"], "categories": ["Information Technology (IT)", "Security", "Network & System", "Others"], "post_time": "2022-01-10T09:40:13Z", "salary": {"currency": null, "max": null, "min": null, "period": "monthly", "term": null}, "salary_visible": false, "title_keywords": ["assistant manager", "manager"], "responsibilities": ["information security", "audit", "design", "maintain", "plan", "administration", "control", "compliance", "vulnerability management", "setup", "reporting", "management", "monitoring", "procedures", "coordinate with", "investigation", "policies", "systems", "access control"], "requirements": {"degrees": ["degree or above"], "majors": ["computer science"], "languages": ["english", "chinese", "mandarin"], "language_level": ["good command", "fluent"], "hard_skills": ["network administration", "cyber security", "os", "databases", "server"], "soft_skills": ["good team player", "work independently"], "languages_combined": [{"language": "english", "language_level": ["fluent", "good command"]}, {"language": "chinese", "language_level": ["fluent", "good command"]}, {"language": "mandarin", "language_level": ["fluent", "good command"]}]}, "experience_required": {"duration": ["minimum 2 years"], "field": ["network administration", "management", "banking sector", "security"]}}, {"job_id": "100003009043511", "location_code": "hk", "company": "HKT Enterprise Solutions", "job_title": "Network Engineer", "description": "To help our customers thrive in today\u2019s dynamic business environment, HKT Commercial Group is empowering enterprises to accelerate their business transformation with end-to-end integrated solutions employing emerging technologies such as 5G, cloud computing, managed security service (MSS), Internet of Things (IoT), artificial intelligence (AI) and smart applications.\n\nIn the era of digital transformation, technology is a forceful enabler, while people and culture are the core and irreplaceable change makers.\u00a0 To cope with our business expansion, we are currently seeking high-caliber candidates with a keen interest in Technology to join our team.\n\nYour role\n\nProvide project implementation and post-sales maintenance on networking products\nProvide pre-sales support and analyze customer requirements to provide low level network design\nPerform emergency call out to customers\nPrepare documentation, test plan and customer configuration to the projects\nConduct operational training and briefing to customers\n\nTo succeed in this role\n\nDegree / Higher Diploma in Electronic Engineering, Computer, Information Engineering or equivalent\n2 years relevant experience in networking implementation and maintenance support\nSolid experience in handling\u00a0Cisco networking or security products,\u00a0Huawei,\u00a0H3C or Juniper\u00a0networking products\nHolder of CCNA, CCNP, HCIA, HCIP or equivalent\nExcellent interpersonal and presentation skill\nMature, responsible and self-motivated\nGood customer services skill and able to work under pressure\nProficiency in spoken and written in both Chinese and English\n\nLearn more about HKT Commercial Group business portfolios:\n\u00a0\n\nHKT Enterprise Solutions:\u00a0\u00a0https://www.hkt-enterprise.com/\n\n1O1O Corporate Solutions:\u00a0\u00a0https://www.1010corporate.com/\n\nHKT is an equal opportunity employer and welcomes applications from all qualified candidates. Information provided will be treated in strict confidence and will only be used for recruitment-related purposes. Personal data provided by job applicants will be used strictly in accordance with the employer's privacy statement (http://www.hkt.com/privacy-statement), a copy of which will be provided immediately upon request.", "employment_types": ["Full Time"], "selling_points": [], "locations": ["Mong Kok"], "categories": ["Information Technology (IT)", "Support", "Security", "Network & System"], "post_time": "2022-01-12T14:56:50Z", "salary": {"currency": null, "max": null, "min": null, "period": "monthly", "term": null}, "salary_visible": false, "title_keywords": ["engineer"], "responsibilities": ["maintenance", "configuration", "maintenance support", "implementation", "design", "customer services", "recruitment", "plan", "documentation", "personal data", "work under pressure"], "requirements": {"degrees": ["diploma", "degree"], "majors": ["engineering"], "languages": ["english", "chinese"], "language_level": ["proficiency"], "hard_skills": ["presentation skill", "sales support", "maintenance", "ai", "ccnp", "ccna", "dynamic", "documentation"], "soft_skills": ["presentation skill", "self-motivated", "confidence", "customer services skill", "responsible", "keen", "mature", "dynamic", "business environment", "interpersonal", "work under pressure"], "languages_combined": [{"language": "english", "language_level": ["proficiency"]}, {"language": "chinese", "language_level": ["proficiency"]}]}, "experience_required": {"duration": ["2 years"], "field": ["relevant experience", "security", "maintenance"]}}, {"job_id": "100003009047336", "location_code": "hk", "company": "JPMorgan Chase Bank, N.A.", "job_title": "CIB Chief Data Office Controls - Data Controls Regional Lead- APAC - Executive Director", "description": "Background\n\nThe CIB Controls Office partners with CIB and Firmwide business executives to provide accountability for the end to end controls environment responsible for operational risk assessment, controls design & evaluation, subject matter expertise and program management of controls related initiatives as well as lead ongoing control related activities on behalf of the business. Amongst the responsibilities we; assist in designing appropriate controls through expert understanding of operational risk within business processes, policy and standards, regulatory requirements (including legal obligations), and existing controls, provide ongoing monitoring and assessment of operational risk and the control environment to proactively identify & assess existing and emerging operational risks and issues; Lead efficient and streamlined governance of operational risk and control environments across the LOB / Function including global, regional, and sub-LOB controls committees / forums\n\nThe CIB Chief Data Office (CDO) Controls function is a newly formed team created to support the CIB CDO, delivering on the Data Controls Strategy for the CIB inclusive of a robust governance framework underpinned by metrics & reporting.\n\nOverview\n\nReporting to the CIB CDO Controls Manager, accountable to the Asia Regional Control Manager and Asia CDO Governance Lead, the successful candidate will assume regional responsibility for the delivery of the data controls agenda in region across four pillars; Risk Identification & Assessment, Control Design & Evaluation, Issues & Control Deficiencies, and Control Governance & Reporting. Supporting the CDO Governance Office in region, this role will require interaction and collaboration with Process Owners and Data Control Officers to identify data related risks relative to the business as well as perform ongoing monitoring of the Data related Operational Risk and Control environment across the CIB.\n\nThis role is ideal for a highly motivated individual with advanced skills in strategy, problem solving and transformation as well as strong influencing, interpersonal and communication skills. The successful candidate will have a commercial mindset and a strong background and proven ability to deliver coordinated analysis of issues and determination of business impact.\n\nResponsibilities\n\nAssess the effectiveness of data governance relative to programs, business processes and the direction the firm is taking relative data\nPartner with APAC Compliance to review regulatory change, industry patterns, external events, incumbent policies & standards, etc. to proactively identify existing and emerging operational risks and issues at country and legal entity level\nPartner with APAC Compliance to advise on local implementation; ensuring that local data management implementations in support of regulatory data-related requirements at country and legal entity level are consistent with CIB-wide data management practices and tools\nDevelop a deep understanding of Asia-specific business and regulatory nuances and related data requirements; feeding back Asia specific requirements into the development/refinement of global CIB CDO strategy and tools\nAssess data related risks and translate into business impact, informing broader CM organisation on how to disposition\nDesign operational data controls in partnership with the Business Executive, including determining how to measure control effectiveness (e.g. metrics), providing control implementation support and performing control validation\nSupport design of application data controls, facilitating business representation at the CDA level and partnership with ISMs\nProvide control related subject matter expertise for relevant projects driven outside of the organization\nContribute to the CIB CDO Control Forum and participate as Control lead in the relevant CIB controls / data governance forums in APAC\nCompile metrics and thresholds with the CIB CDO and Business Executives to inform on health of data related operational risk and controls\nWork Experience/ Skills\n\nAt least 10 years' experience in financial services, preferably in Audit, internal control or operational risk functions\nPrevious experience in strategic and tactical initiatives: Ability to identify problems and propose solutions\nExceptional critical thinking, project management and analytical skills\nSolid organizational skills including attention to detail and multi-tasking skills\nAbility to directly address conflicts and escalate issues where appropriate\nStrong communication skills - verbal, written and technical (e.g., PowerPoint). Ability to present concise, direct and timely communications to executives, management and key partners; strong presentation skills are essential\nDetail oriented and strong organizational skills: Take ownership and accountability for area of responsibility\nProactive approach to problem solving, owning the issues and having the determination to follow tasks/issues through\nExcellent prioritization and time management\nWork independently as well as part of a team\nAbsorb and present complex ideas quickly and accurately\nAbility to shift perspective from high level 'big picture' to low-level detail\nPartnership and relationship management: must have ability to develop and maintain strong partnerships with numerous teams and key stakeholders\nAbility to be flexible and follow tight deadlines; provide clear and concise solutions constrained by tight deadlines\nAdvanced proficiency with Microsoft Office (e.g., Excel, Word, PowerPoint, Visio, Project) preferred\nInterested parties please click \u201cApply Now\u201d to apply job.\n\nAll applications applied through our system will be delivered directly to the advertiser and privacy of personal data of the applicant will be ensured with security.", "employment_types": ["Full Time"], "selling_points": [], "locations": ["Not Specified"], "categories": ["Information Technology (IT)", "Security", "Others", "Management", "Top Executives (CEO, CFO, CTO, GM, MD etc.)"], "post_time": "2022-01-14T02:51:00Z", "salary": {"currency": null, "max": null, "min": null, "period": "monthly", "term": null}, "salary_visible": false, "title_keywords": ["executive director", "lead"], "responsibilities": ["ideas", "data", "regulatory requirements", "audit", "design", "communication", "maintain", "evaluation", "designing", "internal control", "control", "compliance", "teams", "implementation", "develop", "reporting", "management", "monitoring", "review", "policies", "analysis", "project management"], "requirements": {"degrees": [], "majors": [], "languages": [], "language_level": [], "hard_skills": ["excel", "inform", "data management", "microsoft office", "analysis", "word", "powerpoint", "analytical skills", "problem solving", "project management", "internal control"], "soft_skills": ["organizational skills", "time management", "efficient", "robust", "problem solving", "clear", "interpersonal", "ideal", "communication skills", "work independently", "detail oriented", "analytical skills", "motivated individual", "attention to detail", "multi-tasking skills", "driven", "flexible", "advanced", "accountability", "responsible", "timely", "deep", "accountable", "project management", "presentation skills", "organisation", "proactive"], "languages_combined": []}, "experience_required": {"duration": ["at least 10 years"], "field": ["financial services", "audit"]}}, {"job_id": "100003009040247", "location_code": "hk", "company": "CKC Solutions Limited", "job_title": "Information Security Analyst (IT) - Financial Service - Up to HKD55k + Bonus", "description": "Job Description\n\n\nResponsible for full spectrum of cyber security function in accordance with the established policies, guidelines and process\nWill be involved in new system and projects as an advisor to IT teams and business operations throughout the project life cycle to safeguard the business, systems and data\nWill be conducted security incident handling, investigation and reporting\nProvide IT compliance advice and coordinate with internal and external auditors to perform information system audit\nDevelop and enhance the security operation and monitoring\n\nRequirements\u00a0\n\nDegree in Computer Science or IT related fields\u00a0\n4-5 years of IT security and risk management experience\u00a0\nHolder of CISA / CISSP / CISM/ CEHis preferred\nFamiliar with industry frameworks, ISO27001, NIST, ITIL, PCI\nExperience in running SOC is a plus\nExcellent interpersonal and communication skills in English and Chinese (including Putonghua)\u00a0\n\nThis is a great opportunity to\u00a0be part of the team and get more new exposure. If you are interested in this role please send us your CV or call us on +852 2885 8318 for a further discussion.", "employment_types": ["Full Time", "Permanent"], "selling_points": ["Permanent role", "Good Career Path", "Attractive package and benefits"], "locations": ["Not Specified"], "categories": ["Information Technology (IT)", "Application Specialist - Network", "Security", "Others"], "post_time": "2022-01-12T02:00:04Z", "salary": {"currency": null, "max": null, "min": null, "period": "monthly", "term": null}, "salary_visible": false, "title_keywords": ["analyst"], "responsibilities": ["reporting", "cyber security", "guidelines", "policies", "operations", "systems", "teams", "data", "investigation", "compliance", "coordinate with", "audit", "develop", "security operation", "monitoring", "external auditors"], "requirements": {"degrees": ["degree"], "majors": ["it", "computer science"], "languages": ["putonghua", "english", "chinese"], "language_level": ["excellent"], "hard_skills": ["itil", "plus"], "soft_skills": ["communication skills", "interested in", "interpersonal"], "languages_combined": [{"language": "putonghua", "language_level": ["excellent"]}, {"language": "english", "language_level": ["excellent"]}, {"language": "chinese", "language_level": ["excellent"]}]}, "experience_required": {"duration": ["4-5 years"], "field": ["risk management", "it", "security"]}}, {"job_id": "100003009039540", "location_code": "hk", "company": "Cornerstone Global Partners", "job_title": "IT Security Analyst (Manager / AVP Grade)", "description": "Responsibilities\u00a0\nEvaluate IT systems, the security policies of the bank, requirements of regulators and user departments to establish IT risk and security framework together with the policies and procedures necessary to ensure system security is in place\nDevelop and oversee implementation plans of the policies and procedures\nConduct system vulnerabilities scan and recommend remediation\nProvide training and awareness update on technology risk and security\nConduct security risk assessment of IT systems, assess effectiveness of IT security measures and carry out improvement work\nMonitor security risk, handle security incidents and carry out investigation\nEvaluate, recommend and procure security solutions and tools\u00a0\nCoordinate with head office, regulator, risk management, compliance and audit on technology risk and security matters\nCarry out ad-hoc tasks as required by management\nRequirements:\nMinimum 3 years working experience in management of technology risk, IT compliance and security in banking sector\nHolder of CISSP / CISA certification is required\nDegree holder in information technology or related disciplines\nFamiliar with technology risk and security management in banking industry\nSound knowledge in Hong Kong Monetary Authority's requirements in technology related areas e.g. CRAF, TMG, TME, etc.\nGood understanding of banking IT architecture and development process\nPossess project management skills, including analysis, determination and communication\nPrior experience in technology risk management of banking is an added advantage\nHigh proficiency in spoken and written Putonghua, English and Cantonese\nPossess good communication and coordination skills\nDedicated to work, well conducted\nResponsible, attentive to details, a good team player and professional", "employment_types": ["Full Time"], "selling_points": ["Banking Industry", "CISSP / CISA certification is required", "Evaluate IT systems and security policies"], "locations": ["Central"], "categories": ["Information Technology (IT)", "Security"], "post_time": "2022-01-11T10:02:06Z", "salary": {"currency": null, "max": null, "min": null, "period": "monthly", "term": null}, "salary_visible": false, "title_keywords": ["analyst", "manager"], "responsibilities": ["provide training", "management", "policies", "ad-hoc tasks", "systems", "procedures", "implementation", "monitor", "develop", "evaluate", "investigation", "coordinate with", "system security", "compliance", "audit", "plans"], "requirements": {"degrees": ["degree holder"], "majors": ["related disciplines", "information technology"], "languages": ["cantonese", "putonghua", "english"], "language_level": ["proficiency"], "hard_skills": ["project management", "analysis", "security management", "tmg"], "soft_skills": ["good team player", "coordination skills", "attentive to details", "responsible", "project management skills", "communication"], "languages_combined": [{"language": "cantonese", "language_level": ["proficiency"]}, {"language": "putonghua", "language_level": ["proficiency"]}, {"language": "english", "language_level": ["proficiency"]}]}, "experience_required": {"duration": ["minimum 3 years"], "field": ["risk management", "management", "compliance", "it", "banking sector", "security", "banking"]}}, {"job_id": "100003009034538", "location_code": "hk", "company": "Shangri-La International Hotel Management Limited", "job_title": "Senior Analyst, Information Security", "description": "As a Senior Analyst, Information Security, we will rely on you to:\nPerform PCI-DSS compliance for the Group and hotels (Annual PCI-DSS certification, hotel compliance issues and documents submissions)\nConduct security awareness training and phishing test\nMaintain and ensure policies are compliant with regulatory requirements\nProvide project advisory to guide and certify all company projects for internal and external information security and compliance requirements\nMonitor, investigate and document security incidents detected; perform security incident response and root cause analysis, which includes after office hours support\nWork closely with managed security provider, vendors, information system owners or representatives and infrastructure technical staff on security incidents to perform incident handling and provide remedial actions\nHandle change requests, regular upgrades and provide support on issues relating to all supported security solutions (e.g. endpoint security solutions, logging solution, web proxy, and advanced threat detection systems)\nDeploy security solutions and perform vulnerability assessment to IT assets.\nPerform regular governance review on sensitive administrative activities\nPrepare and deliver monthly and ad-hoc security reports.\n\nWe are looking for someone who has:\n\n\nDegree in Computer Science or Information System\nMinimum 3 years of relevant work experience in IT security operations environment\nKnowledgeable in PCI-DSS, IT Security incident handling, log management, IT security software and tools\nStrong technical knowledge in operating system, network and security technologies.\nProfessional security related qualification (e.g. GCIH, CISSP, CISA etc.) will be an advantage.\nGood communication and analytic skills with sound technical and security control process knowledge\nAble to work under pressure\nGood command in both spoken and written English & Chinese\nAble to perform multi-tasking, organized work independently and good team player", "employment_types": ["Full Time"], "selling_points": ["Handle IT Security Incidents and Log Management", "Knowledgeable in PCI-DSS", "3 years' experience in IT Security Operations"], "locations": ["Quarry Bay"], "categories": ["Information Technology (IT)", "Security"], "post_time": "2022-01-10T03:37:10Z", "salary": {"currency": null, "max": null, "min": null, "period": "monthly", "term": null}, "salary_visible": false, "title_keywords": ["senior analyst"], "responsibilities": ["ad-hoc", "software", "information security", "regulatory requirements", "operations", "communication", "maintain", "deploy", "proxy", "work under pressure", "control", "compliance", "monitor", "infrastructure", "reports", "provide support", "management", "upgrades", "review", "administrative activities", "policies", "analysis", "systems"], "requirements": {"degrees": ["degree"], "majors": ["computer science"], "languages": ["english", "chinese"], "language_level": ["good command"], "hard_skills": ["analytic skills", "analysis", "information system", "web"], "soft_skills": ["organized", "work independently", "good team player", "advanced", "communication", "multi-tasking", "sensitive", "work under pressure"], "languages_combined": [{"language": "english", "language_level": ["good command"]}, {"language": "chinese", "language_level": ["good command"]}]}, "experience_required": {"duration": ["minimum 3 years"], "field": ["it", "security"]}}, {"job_id": "100003009028527", "location_code": "hk", "company": "Konica Minolta Business Solutions (HK) Limited", "job_title": "IT Deskside Engineer", "description": "Responsibilities:\n\nProvide technical support and troubleshooting to end user on both hardware, software, and other related computer services.\nPerform monitoring of IT equipment status.\nPerform management of hardware and software inventory.\nCoordinate with level 2 support team and vendors to resolve the technical issue.\n\nRequirements:\n\nHigher Diploma in IT, Computer Science or related disciplines\nPrior experience in deskside / helpdesk support will be an advantage\nWilling to learn and work as a team\nOn the job training and job rotation will be provided\nFresh graduate will also be considered\n\nBenefits:\n\n5-Day Work\u00a0\nDouble Pay and Discretionary Bonus\nMedical Insurance\nBirthday Leave\nStaff Recreational Activity", "employment_types": ["Full Time", "Permanent"], "selling_points": ["IT deskside / helpdesk support", "Work as a team", "5 Day Work, Double Pay, Bonus"], "locations": ["Not Specified"], "categories": ["Information Technology (IT)", "Support", "Security", "Network & System"], "post_time": "2022-01-11T08:58:41Z", "salary": {"currency": null, "max": null, "min": null, "period": "monthly", "term": null}, "salary_visible": false, "title_keywords": ["engineer"], "responsibilities": ["management", "software", "technical support", "inventory", "computer services", "monitoring", "troubleshooting", "coordinate with", "hardware", "it equipment"], "requirements": {"degrees": ["diploma", "fresh graduate"], "majors": ["related disciplines", "it", "computer science"], "languages": [], "language_level": [], "hard_skills": [], "soft_skills": ["willing to learn", "work as a team"], "languages_combined": []}, "experience_required": {"duration": [], "field": []}}, {"job_id": "100003009035768", "location_code": "hk", "company": "Macroview Telecom Limited", "job_title": "Systems Engineer - CyberSecurity", "description": "How you will contribute:\n\n- Design, plan and manage the implementation of SIEM , SOAR and security projects by working closely with internal teams and customers\n\n- Provide technical support and troubleshooting for cybersecurity platform\n\n- Conduct research and identify nowadays cybersecurity threats and vulnerabilities\n\n- Analyze security event data from multiple security platforms\n\n- Develop and finetune cybersecurity analytics use cases\n\n- Work with operation team to provide professional service to customers\n\n- Monitor project status, quality, material procurement and progress in a right track\n\nWho are we looking for:\n\n\u200b- Higher Diploma or above in Computer Science or IT related disciplines\n\n- 2 Year experience on infrastructure setup, technical support and troubleshooting on Windows Server and Linux Server\n\n- Knowledge of operating systems, servers, backups , virtualization technologies\n\n- Knowledge of cybersecurity or security products such as firewall, proxy, EDR , IAM ,Sandbox\n\n- Knowledge of SIEM platform is an advantage\n\n- Familiar with Cybersecurity frameworks, such as MITRE ATT&CK, OWASP, NIST\n\n- Have a strong sense of responsibility and an eagerness to learn\n\n- Have good interpersonal and communication skills\n\n- Independent, proactive, innovative and able to work under pressure\n\nWe offer attractive remuneration package, medical benefits and marriage leave to the right candidate. Interested parties please send full resume with expected salary by clicking 'Apply Now'.\nAll information collected will be used for recruitment purpose only.\nTo know more about Macroview, please visit:\u00a0http://www.macroview.com\n\u200b", "employment_types": ["Full Time", "Permanent"], "selling_points": ["Implementation of SIEM and security projects", "Cybersecurity, cloud, network security products", "Security analytics use cases development"], "locations": ["Quarry Bay"], "categories": ["Information Technology (IT)", "Security", "Network & System", "Others", "Student / Fresh Graduate / No Experience"], "post_time": "2022-01-10T08:24:56Z", "salary": {"currency": null, "max": null, "min": null, "period": "monthly", "term": null}, "salary_visible": false, "title_keywords": ["systems engineer"], "responsibilities": ["data", "technical support", "work under pressure", "infrastructure", "teams", "implementation", "design", "troubleshooting", "develop", "monitor", "quality", "communication", "plan", "backups", "proxy", "conduct research", "setup", "operating systems"], "requirements": {"degrees": ["higher diploma or above"], "majors": ["related disciplines", "it", "computer science"], "languages": [], "language_level": [], "hard_skills": ["linux", "servers", "firewall", "server", "windows server"], "soft_skills": ["communication skills", "independent", "sense of responsibility", "troubleshooting", "innovative", "proactive", "interpersonal", "work under pressure"], "languages_combined": []}, "experience_required": {"duration": ["2 year"], "field": ["infrastructure", "troubleshooting"]}}, {"job_id": "100003009032992", "location_code": "hk", "company": "Pernod Ricard Hong Kong Ltd", "job_title": "Cybersecurity Specialist", "description": "Reference #:\u00a02021/ART/328CP/c-d\n\u00a0\nJob Responsibilities\nResearch and Development in machine learning, computer vision and image processing algorithm\nDevelop modelling and simulation software for cutting-edge DNN accelerator/AI chip\nDevelop tool chain for DNN Accelerator/AI chip including quantizer and compiler\nParticipating in AI system design and implementation for commercialization\nRequirements\nGraduate in STEM-related discipline such as Computer Science, Electronic Engineering, Information Engineering and Mathematics or relevant discipline\nA bachelor\u2019s degree, master\u2019s degree or a doctoral degree\u2019s holder is welcome to apply\nFor bachelor\u2019s degree holder, they will be considered for the position of Engineering Associate (PI)\nStrong programming skills of at least one of the following languages: Python, C, C++\nTeam player with good analytical and strong communication skills\nGood command of both written and spoken English and/or Chinese\nApplication\n\nTo apply, by clicking 'APPLY NOW'\u00a0\u00a0with your resume, you must quote the\u00a0Job Ref\u00a0and include the following information:\n\nName of University\nDegree obtained/expecting and when\nHave you participated in ITF Research Talent Hub before? Yes/No\nIf you answer Yes in item 3, please state the period\nHave you been employed by ASTRI before? If yes, please state the period\n\nThe resume should\u00a0not\u00a0include any sensitive personal information such as HKID or passport number, photo, etc.\n\nThe application will be open until the position is filled. Only short-listed candidates will be notified. ASTRI reserves the right not to fill the position.\n\nASTRI is an Equal Opportunities Employer. Personal data provided by job applicants will be used\u00a0exclusively\u00a0for recruitment\u00a0only. For details, please refer to\u00a0Privacy - ASTRI - Hong Kong Applied Science and Technology Research Institute Company Limited,\u00a0in particular section 9.", "employment_types": ["Full Time"], "selling_points": ["Cyber Security APAC", "Attractive package; MNC; Wine & Spirit Industry", "5+ years experience; IT Security, Safety, Risk"], "locations": ["Tsim Sha Tsui"], "categories": ["Information Technology (IT)", "IT Management", "Security", "Others"], "post_time": "2022-01-08T05:24:56Z", "salary": {"currency": null, "max": null, "min": null, "period": "monthly", "term": null}, "salary_visible": false, "title_keywords": ["specialist"], "responsibilities": ["software", "implementation", "develop", "commercialization", "system design"], "requirements": {"degrees": ["degree holder", "degree", "bachelor", "master"], "majors": ["engineering"], "languages": ["english", "chinese"], "language_level": ["good command"], "hard_skills": ["no", "c++", "c", "programming", "python"], "soft_skills": ["communication skills", "team player", "sensitive"], "languages_combined": [{"language": "english", "language_level": ["good command"]}, {"language": "chinese", "language_level": ["good command"]}]}, "experience_required": {"duration": [], "field": []}}, {"job_id": "100003009033440", "location_code": "hk", "company": "MTR Corporation Limited", "job_title": "\u4f01\u696d\u4fdd\u5b89\u8b66\u885b (\u7de8\u865f:2200000I)", "description": "Reference #:\u00a0CTO/CCT/04\n\nJob Responsibilities\nWork with the technical team in algorithm, hardware architecture design and development.\nWork with the technical team to implement RISC-V SoC on FPGA\nWork with Software engineers to boot up RISC-V processor\nAssist in R&D project\u2019s planning and management\nConduct research in RISC-V architecture and Trusted Execution Environment\nProvide training and to develop team members\nRequirements\nPh.D. or Master holder in Computer Science, Electronic Engineering, Electrical Engineering, Information Engineering, IC Design or relevant disciplines with a minimum of 6 years of related experience\nExperience in HDL coding is highly preferred\nHands-on experience in IC design and verification is highly preferred\nExperience in processor integration and development is an advantage\nKnowledge on Trusted Execution Environment is an advantage\nExperience in FPGA prototyping and debugging is an advantage\nExcellent analytical and troubleshooting skills is highly preferred\nPassionate about new technology\nLive the ASTRI values\nApplication\n\n\nThe appointment will be on renewable contract terms with a competitive salary and performance-linked variable pay. Fringe benefits include paid leave, medical and dental benefits, insurance coverage and contribution to MPF. The incumbent will normally work\u00a0a five-day week.\n\nInterested candidates, please send an application (quoting Ref. No.) with a detailed resume, current and expected salary to\u00a0Talent Acquisition by clicking \"APPLY NOW\".\u00a0The resume should\u00a0not\u00a0include any sensitive personal information such as HKID or passport number, photo, etc.\u00a0Application open until this position is filled.\n\nPosition offer is subject to the applicant\u2019s experience and academic qualification. The application will be open until the position is filled. Only short-listed candidates will be notified. ASTRI reserves the right not to fill the position.\n\nASTRI is an Equal Opportunities Employer. Personal data provided by job applicants will be used\u00a0exclusively\u00a0for recruitment\u00a0only. For details, please refer to\u00a0Privacy - ASTRI - Hong Kong Applied Science and Technology Research Institute Company Limited, in particular section 9.", "employment_types": ["Full Time"], "selling_points": ["\u8ca0\u8cac\u6e2f\u9435\u8eca\u5ee0\u3001\u4e3b\u8981\u8fa6\u516c\u5927\u6a13\u3001\u904e\u5883\u8eca\u7ad9\u6216\u5176\u4ed6\u76f8\u95dc\u5730\u65b9\u7684\u4fdd\u5b89\u3001\u5de1\u908f\u53ca\u9632\u706b\u5de5\u4f5c", "\u53c3\u8207\u76f8\u95dc\u91cd\u5927\u4e8b\u6545\u7684\u4fdd\u5b89\u5de5\u4f5c", "\u6548\u7532\u985e\u53ca\u4e59\u985e\u300c\u4fdd\u5b89\u4eba\u54e1\u8a31\u53ef\u8a3c\u300d\u53ca\u8cea\u7d20\u4fdd\u8b49\u7cfb\u7d71\u6240\u8a8d\u53ef\u8ab2\u7a0b\u8b49\u66f8"], "locations": ["Kowloon Bay"], "categories": ["Information Technology (IT)", "Security", "Others", "Security / Safety Control"], "post_time": "2022-01-09T16:25:07Z", "salary": {"currency": null, "max": null, "min": null, "period": "monthly", "term": null}, "salary_visible": false, "title_keywords": ["\u4f01\u696d\u4fdd\u5b89\u8b66\u885b"], "responsibilities": ["provide training", "management", "software", "conduct research", "design", "develop", "hardware", "architecture", "planning"], "requirements": {"degrees": ["master"], "majors": ["design", "engineering", "computer science", "electrical engineering"], "languages": [], "language_level": [], "hard_skills": ["integration"], "soft_skills": ["hands-on", "troubleshooting", "passionate about"], "languages_combined": []}, "experience_required": {"duration": ["minimum of 6 years"], "field": ["related", "development", "engineering", "design"]}}, {"job_id": "100003009042566", "location_code": "hk", "company": "Captiare", "job_title": "Network manager x 2", "description": "Reference #:\u00a02021/ART/328CP/a-b\n\u00a0\n\nJob Responsibilities\nCarry out logic design, module-level or top-level verification to implement AI algorithms on FPGA/ASIC\nWork with Algorithm team to come up with an optimized hardware architecture\nCompile technical documents for the project deliverables, including hardware micro-architecture, test plans, test reports, etc.\nParticipating in AI system design and implementation for commercialization\nRequirements\nGraduate in STEM-related discipline such as Computer Science, Electronic Engineering, Information Engineering and Mathematics or relevant discipline\nA bachelor\u2019s degree, master\u2019s degree or a doctoral degree\u2019s holder is welcome to apply\nFor bachelor\u2019s degree holder, they will be considered for the position of Engineering Associate (PI)\nStrong hardware programming skills of at least one of the following languages: VHDL, Verilog, System Verilog, UVM\nTeam player with good analytical and strong communication skills\nGood command of both written and spoken English and/or Chinese\nApplication\n\nTo apply, by clicking 'APPLY NOW'\u00a0\u00a0with your resume, you must quote the\u00a0Job Ref\u00a0and include the following information:\n\nName of University\nDegree obtained/expecting and when\nHave you participated in ITF Research Talent Hub before? Yes/No\nIf you answer Yes in item 3, please state the period\nHave you been employed by ASTRI before? If yes, please state the period\n\nThe resume should\u00a0not\u00a0include any sensitive personal information such as HKID or passport number, photo, etc.\n\nThe application will be open until the position is filled. Only short-listed candidates will be notified. ASTRI reserves the right not to fill the position.\n\nASTRI is an Equal Opportunities Employer. Personal data provided by job applicants will be used\u00a0exclusively\u00a0for recruitment\u00a0only. For details, please refer to\u00a0Privacy - ASTRI - Hong Kong Applied Science and Technology Research Institute Company Limited,\u00a0in particular section 9.", "employment_types": ["Full Time", "Permanent"], "selling_points": ["Network infrastructure", "Firewall/ wifi/ security", "Great career prospect"], "locations": ["Not Specified"], "categories": ["Information Technology (IT)", "IT Management", "Security", "Network & System"], "post_time": "2022-01-12T07:59:38Z", "salary": {"currency": null, "max": null, "min": null, "period": "monthly", "term": null}, "salary_visible": false, "title_keywords": ["manager"], "responsibilities": ["project deliverables", "implementation", "design", "hardware", "commercialization", "system design", "reports", "plans", "architecture"], "requirements": {"degrees": ["degree holder", "degree", "bachelor", "master"], "majors": ["engineering"], "languages": ["english", "chinese"], "language_level": ["good command"], "hard_skills": ["no", "verilog", "hardware", "vhdl", "programming"], "soft_skills": ["communication skills", "team player", "sensitive"], "languages_combined": [{"language": "english", "language_level": ["good command"]}, {"language": "chinese", "language_level": ["good command"]}]}, "experience_required": {"duration": [], "field": []}}, {"job_id": "100003009033517", "location_code": "hk", "company": "Pinpoint Asia Limited", "job_title": "Security Operations Engineer - FinTech Group", "description": "Ref No:\u00a0CTO/CCT/14\n\nJob Responsibilities\nDevelopment of device drivers for hardware devices\nDevelopment of firmware for embedded system\nWork with hardware engineers in firmware development\nPortation of software to new CPU architecture\nResponsible for the complete cycle of development including design, coding, debugging, and documentation\nRequirements\nPhD or Master degree holder in Computer Science/Computer Engineering/Information Engineering or relevant disciplines with a minimum of 3 years experience. Candidates with fewer experience may also be considered.\nExperience in C and assembly programming for embedded system is a plus\nExperience in Linux device driver development is a plus\nExperience in Real Time Operating System programming is a plus\nExperience in RISC-V architecture and programming will be an advantage\nExperience in Linux and GIT version control will be an advantage\nLive ASTRI value\nApplication\n\nThe appointment will be on renewable contract terms with a competitive salary and performance-linked variable pay. Fringe benefits include paid leave, medical and dental benefits, insurance coverage and contribution to MPF. The incumbent will normally work\u00a0a five-day week.\n\nInterested candidates, please send an application (quoting Ref. No.) with a detailed resume, current and expected salary to\u00a0Talent Acquisition by clicking \"APPLY NOW\".\u00a0The resume should\u00a0not\u00a0include any sensitive personal information such as HKID or passport number, photo, etc.\u00a0\n\nPosition offer is subject to the applicant\u2019s experience and academic qualification. The application will be open until the position is filled. Only short-listed candidates will be notified. ASTRI reserves the right not to fill the position.\n\nASTRI is an Equal Opportunities Employer. Personal data provided by job applicants will be used\u00a0exclusively\u00a0for recruitment\u00a0only. For details, please refer to\u00a0Privacy - ASTRI - Hong Kong Applied Science and Technology Research Institute Company Limited, in particular section 9.", "employment_types": ["Full Time"], "selling_points": ["1LOD SecOps", "Fast Growing Environment", "International Environment"], "locations": ["Not Specified"], "categories": ["Information Technology (IT)", "IT Auditing", "Security", "Network & System"], "post_time": "2022-01-10T00:08:25Z", "salary": {"currency": "HKD", "max": 54999, "min": 35000, "period": "monthly", "term": null}, "salary_visible": true, "title_keywords": ["operations", "engineer"], "responsibilities": ["software", "coding", "design", "hardware", "documentation", "architecture"], "requirements": {"degrees": ["master degree"], "majors": ["computer engineering", "engineering", "computer science"], "languages": [], "language_level": [], "hard_skills": ["linux", "plus", "git", "c", "programming"], "soft_skills": [], "languages_combined": []}, "experience_required": {"duration": ["minimum of 3 years"], "field": ["development", "engineering", "programming"]}}, {"job_id": "100003009037876", "location_code": "hk", "company": "China Construction Bank (Asia) Corporation Limited", "job_title": "Parameter and User Access Management Professional", "description": "Reference #:\u00a0CTO/ICS/02\n\nOpening: 6\nJob Responsibilities\nResponsible for schematics and layout design of digital, RF, analog, mixed signal, or power IC, including all facets of the design flow, from schematics to layout, from initial floor-planning to final verification\nDevelop algorithms, building blocks, firmwares, SoC, or testing solutions for various smart city and industry 4.0 related applications\nWork with marketing and technology transfer team to prepare engineering prototypes and conduct on-site tests\nRequirements\nDegree holders (Bachelor/Master/Ph.D.) in Electronic Engineering or related fields with minimum of 3 years related experience\nExtensive experiences in digital, RF, analog, mixed signal, or power IC design. Familiar with EDA Tools (e.g., Cadence/ Mentor/ Synopsys). Rich programming knowledge such as C/C++, Python, Matlab, Verilog, Skill, or TCL is preferred.\nGood communication and interpersonal skills, a good team player\nProficiency in written and spoken English\nLives ASTRI values\n\nApplication\n\nThe appointment will be on renewable contract terms with a competitive salary and performance-linked variable pay. Fringe benefits include paid leave, medical and dental benefits, insurance coverage and contribution to MPF. The incumbent will normally work\u00a0a five-day week.\n\nInterested candidates, please send an application (quoting Ref. No.) with a detailed resume, current and expected salary to\u00a0Talent Acquisition by clicking \"APPLY NOW\".\u00a0The resume should\u00a0not\u00a0include any sensitive personal information such as HKID or passport number, photo, etc.\u00a0\n\nPosition offer is subject to the applicant\u2019s experience and academic qualification. The application will be open until the position is filled. Only short-listed candidates will be notified. ASTRI reserves the right not to fill the position.\n\nASTRI is an Equal Opportunities Employer. Personal data provided by job applicants will be used\u00a0exclusively\u00a0for recruitment\u00a0only. For details, please refer to\u00a0Privacy - ASTRI - Hong Kong Applied Science and Technology Research Institute Company Limited, in particular section 9.", "employment_types": ["Full Time", "Permanent"], "selling_points": ["parameter maintenance", "User Access Management", "IT security"], "locations": ["Kowloon Bay"], "categories": ["Information Technology (IT)", "Security", "Network & System"], "post_time": "2022-01-11T04:06:49Z", "salary": {"currency": null, "max": null, "min": null, "period": "monthly", "term": null}, "salary_visible": false, "title_keywords": [], "responsibilities": ["layout design", "design", "develop", "testing", "planning"], "requirements": {"degrees": ["degree", "bachelor", "master"], "majors": [], "languages": ["english"], "language_level": ["proficiency"], "hard_skills": ["c++", "verilog", "tcl", "c", "programming", "matlab", "python", "signal"], "soft_skills": ["good team player", "communication and interpersonal skills", "extensive"], "languages_combined": [{"language": "english", "language_level": ["proficiency"]}]}, "experience_required": {"duration": ["minimum of 3 years"], "field": ["related", "digital", "engineering", "design"]}}, {"job_id": "100003009033572", "location_code": "hk", "company": "The University of Hong Kong", "job_title": "Security Specialist (at the rank of IT Officer)", "description": "Reference #:\u00a0\u00a0CTO/IOTSEN/05\nJob Responsibilities\nDevelop the software and firmware, for process control, data collection and analysis of portable device with the optoelectronics module, optical sensing module, and acoustic sensing module\nWorking closely with the optoelectronics hardware team members to optimize the operation procedure of the device and to streamline the process flow for automations with computer aids\nWorking closely with the chemical sensing team members to construct customized databases for jewelry, food, environment, and health applications\nConstruction, evaluation, and interactive demonstration for the software development of the prototypes\nLiaison with external software suppliers and sub-contractors\nRequirements\nPh.D. holder or Master\u2019s degree in Physics, Mechanics, Electronics, Chemistry, Science, Engineering or relevant disciplines with a minimum of 3 years of related experience in the industry of Opto-electronics / Opto-mechatronics. Candidate with fewer experience may also be considered.\nFamiliar with R&D methodologies, design concepts and principles for the development of optical sensing device comprising optoelectronics modules\nFamiliar with computer programming languages, e.g., Python, C, C++, C#, Labview, etc. for both device control and data processing\nHands-on experience in constructing the software and firmware of the portable device with the optoelectronics modules\nPractical knowledge in the development of portable optoelectronics devices for food, environment, and health applications\nKnowledge in simulation tools, e.g., Matlab, COMSOL, AutoCAD, L-edit, Chem3D, is a plus\nFluent in English and be able to work as part of a team\nLive the ASTRI values\nApplication\n\nThe appointment will be on renewable contract terms with a competitive salary and performance-linked variable pay. Fringe benefits include paid leave, medical and dental benefits, insurance coverage and contribution to MPF. The incumbent will normally work\u00a0a five-day week.\n\nInterested candidates, please send an application (quoting Ref. No.) with a detailed resume, current and expected salary to\u00a0Talent Acquisition by clicking \"APPLY NOW\".\u00a0The resume should\u00a0not\u00a0include any sensitive personal information such as HKID or passport number, photo, etc.\u00a0\n\nPosition offer is subject to the applicant\u2019s experience and academic qualification. The application will be open until the position is filled. Only short-listed candidates will be notified. ASTRI reserves the right not to fill the position.\n\nASTRI is an Equal Opportunities Employer. Personal data provided by job applicants will be used\u00a0exclusively\u00a0for recruitment\u00a0only. For details, please refer to\u00a0Privacy - ASTRI - Hong Kong Applied Science and Technology Research Institute Company Limited, in particular section 9.", "employment_types": ["Contract"], "selling_points": ["a Bachelor\u2019s degree or above in Computer", "4 years\u2019 experience in network infrastructure", "annual leave and medical benefits"], "locations": ["Pok Fu Lam"], "categories": ["Information Technology (IT)", "Security"], "post_time": "2022-01-10T01:07:23Z", "salary": {"currency": null, "max": null, "min": null, "period": "monthly", "term": null}, "salary_visible": false, "title_keywords": ["specialist", "it officer"], "responsibilities": ["control", "evaluation", "software", "analysis", "develop", "hardware", "data collection", "databases"], "requirements": {"degrees": ["degree", "master"], "majors": ["science", "chemistry", "engineering", "physics"], "languages": ["english"], "language_level": ["fluent"], "hard_skills": ["r&d", "plus", "c++", "portable", "c", "autocad", "programming", "matlab", "python", "processing", "labview", "c#"], "soft_skills": ["hands-on"], "languages_combined": [{"language": "english", "language_level": ["fluent"]}]}, "experience_required": {"duration": ["minimum of 3 years"], "field": ["related", "engineering"]}}, {"job_id": "100003009035167", "location_code": "hk", "company": "PeopleLink Services Limited", "job_title": "System Engineer /  Security Engineer (Salary range 25K-50K) (Financial & Insurance Industry)", "description": "Reference #:2021/ART/333CP/b\n\u00a0\nJob Responsibilities\n\nAssist in ITF R&D project as assigned\nHands on firmware development\nCooperation with the software team to implement AI, algorithm accelerator and controlling logics into embedded system\nPrepare testing data for the deliverables, write reports documenting detail methods and results\nRequirements\n\nGraduate in EE-related discipline such as Electronic Engineering, Information Engineering, Computer Science, or relevant discipline\nA bachelor\u2019s degree, master\u2019s degree or a doctoral degree\u2019s holder is welcome to apply\nFor bachelor\u2019s degree holder, they will be considered for the position of Engineering Associate (PI)\nExperiences in firmware development including DSP/MCU programming with different interface protocol, coding and verification\nStrong programming skills in C/C++, experience in Python, TCL, cross-platform programming and Linux environment is highly preferred\nKnowledge in circuit schematic and layout, FPGA HDL (Verilog or VHDL) is a plus\nGood command of written and spoken English or Chinese\nApplication\n\nTo apply, by clicking 'APPLY NOW'\u00a0\u00a0with your resume, you must quote the\u00a0Job Ref\u00a0and include the following information:\n\nName of University\nDegree obtained/expecting and when\nHave you participated in ITF Research Talent Hub before? Yes/No\nIf you answer Yes in item 3, please state the period\nHave you been employed by ASTRI before? If yes, please state the period\n\nThe resume should\u00a0not\u00a0include any sensitive personal information such as HKID or passport number, photo, etc.\n\nThe application will be open until the position is filled. Only short-listed candidates will be notified. ASTRI reserves the right not to fill the position.\n\nASTRI is an Equal Opportunities Employer. Personal data provided by job applicants will be used\u00a0exclusively\u00a0for recruitment\u00a0only. For details, please refer to\u00a0Privacy - ASTRI - Hong Kong Applied Science and Technology Research Institute Company Limited,\u00a0in particular section 9.", "employment_types": ["Full Time", "Permanent", "Contract"], "selling_points": ["System & Networking", "Familiar with IT Infra", "Knowledge in IT Security & Audit"], "locations": ["Not Specified"], "categories": ["Information Technology (IT)", "Security", "Network & System", "Others"], "post_time": "2022-01-10T06:17:04Z", "salary": {"currency": null, "max": null, "min": null, "period": "monthly", "term": null}, "salary_visible": false, "title_keywords": ["system engineer", "engineer"], "responsibilities": ["data", "software", "reports", "testing"], "requirements": {"degrees": ["degree holder", "degree", "bachelor", "master"], "majors": ["engineering"], "languages": ["english", "chinese"], "language_level": ["good command"], "hard_skills": ["linux", "plus", "no", "c++", "verilog", "tcl", "c", "programming", "vhdl", "python"], "soft_skills": ["sensitive"], "languages_combined": [{"language": "english", "language_level": ["good command"]}, {"language": "chinese", "language_level": ["good command"]}]}, "experience_required": {"duration": [], "field": ["development", "programming"]}}, {"job_id": "100003009031492", "location_code": "hk", "company": "CITIC Telecom International CPC Limited", "job_title": "Security Engineer (on-shift duty) (fresh graduate welcome)", "description": "Reference #:\u00a0CTO/IOTSEN/09\n\nJob Responsibilities\n\nContribute, provide guidance and lead in software design, development and testing including requirement analysis, software architecture design, user interface development, module development and improvement.\nResearch and design computer vision systems both independently and as part of collaborative teams for 2D and 3D industrial applications\nPrepare documents and invention disclosures\nWork closely with Optical, Electronic/Electrical and Mechanical engineers to develop prototypes.\nProvide excellent communication with customers, partners and teammates.\nTake business trips to other cities for onsite support occasionally\nPerform other related duties and responsibilities, on occasion, as assigned.\nRequirements\nPh.D. holder or Master\u2019s degree in Computer Science, Electronic/Electrical Engineering, Information Engineering, Mathematics, Statistics, Physics or relevant disciplines with a minimum of 3 years of related experiences. Candidate with less experiences may also be considered.\nFamiliarity with source code management workflows\nExposure to C++, Python, C, CUDA and SQL programming.\nExperience with computer vision, image processing and OpenCV\nExperience with GUI development tools such as Qt and MFC is a plus\nExperience with Deep Learning frameworks such as TensorFlow, PyTorch and others is a plus\nFamiliarity with maintenance of workstations and clusters for Machine Learning/Deep Learning is a plus\nStrong teamwork and good analytical thinking skills\nGood verbal and written communication skills in English\nLive ASTRI values\nApplication\n\nThe appointment will be on renewable contract terms with a competitive salary and performance-linked variable pay. Fringe benefits include paid leave, medical and dental benefits, insurance coverage and contribution to MPF. The incumbent will normally work\u00a0a five-day week.\n\nInterested candidates, please send an application (quoting Ref. No.) with a detailed resume, current and expected salary to\u00a0Talent Acquisition by clicking \"APPLY NOW\".\u00a0The resume should\u00a0not\u00a0include any sensitive personal information such as HKID or passport number, photo, etc.\u00a0\n\nPosition offer is subject to the applicant\u2019s experience and academic qualification. The application will be open until the position is filled. Only short-listed candidates will be notified. ASTRI reserves the right not to fill the position.\n\nASTRI is an Equal Opportunities Employer. Personal data provided by job applicants will be used\u00a0exclusively\u00a0for recruitment\u00a0only. For details, please refer to\u00a0Privacy - ASTRI - Hong Kong Applied Science and Technology Research Institute Company Limited, in particular section 9.", "employment_types": ["Full Time", "Permanent"], "selling_points": ["Perform daily log analysis in SOC", "Assist in dectection & resolution of problems", "Fresh graduate welcome, shift duty"], "locations": ["Kwai Tsing Area"], "categories": ["Information Technology (IT)", "Support", "Security", "Network & System"], "post_time": "2022-01-07T09:22:38Z", "salary": {"currency": null, "max": null, "min": null, "period": "monthly", "term": null}, "salary_visible": false, "title_keywords": ["engineer"], "responsibilities": ["software", "analysis", "systems", "teams", "design", "testing", "develop", "user interface", "communication", "provide guidance", "architecture", "prepare documents"], "requirements": {"degrees": ["degree", "master"], "majors": ["mathematics", "engineering", "electrical engineering", "statistics", "physics", "computer science"], "languages": ["english"], "language_level": ["good"], "hard_skills": ["plus", "c++", "maintenance", "cuda", "sql", "c", "programming", "python", "code", "processing"], "soft_skills": ["teamwork", "communication skills", "deep", "learning"], "languages_combined": [{"language": "english", "language_level": ["good"]}]}, "experience_required": {"duration": ["minimum of 3 years"], "field": ["related", "development", "statistics", "engineering"]}}, {"job_id": "100003009035769", "location_code": "hk", "company": "Macroview Telecom Limited", "job_title": "Service Engineer / Service Consultant - Professional Services (Pre-Sales, Fresh Graduate Welcome)", "description": "Reference #:\u00a0CTO/CCT/02\nJob Responsibilities\nAssist in R&D project development\nConduct research in RISC-V architecture and Trusted Execution Environment\nCarry out logic design, module-level or top-level verification\nWork with the technical team to implement RISC-V SoC on FPGA\nCarry out firmware design to support ASIC/FPGA development\nWork with Software engineers to boot up RISC-V processor\n\u00a0\nRequirements\nPh.D. or Master holder in Computer Science, Electronic Engineering, Electrical Engineering, Information Engineering, IC Design or relevant disciplines with a minimum of 3 years of related experience\nExperience in HDL coding is highly preferred\nHands-on experience in IC design and verification is highly preferred\nExperience in processor integration and development is an advantage\nKnowledge on Trusted Execution Environment is an advantage\nExperience in FPGA prototyping and debugging is an advantage\nExcellent analytical and troubleshooting skills is highly preferred\nPassionate about new technology\nLive the ASTRI values\nApplication\n\n\nThe appointment will be on renewable contract terms with a competitive salary and performance-linked variable pay. Fringe benefits include paid leave, medical and dental benefits, insurance coverage and contribution to MPF. The incumbent will normally work\u00a0a five-day week.\n\nInterested candidates, please send an application (quoting Ref. No.) with a detailed resume, current and expected salary to\u00a0Talent Acquisition by clicking \"APPLY NOW\".\u00a0The resume should\u00a0not\u00a0include any sensitive personal information such as HKID or passport number, photo, etc.\u00a0\n\nPosition offer is subject to the applicant\u2019s experience and academic qualification. The application will be open until the position is filled. Only short-listed candidates will be notified. ASTRI reserves the right not to fill the position.\n\nASTRI is an Equal Opportunities Employer. Personal data provided by job applicants will be used\u00a0exclusively\u00a0for recruitment\u00a0only. For details, please refer to\u00a0Privacy - ASTRI - Hong Kong Applied Science and Technology Research Institute Company Limited, in particular section 9.", "employment_types": ["Full Time", "Permanent"], "selling_points": ["Degree in IT/ Computer Science / Engineering", "Address customers' ICT and digitalization needs", "Fresh graduates with passion will be considered"], "locations": ["Quarry Bay"], "categories": ["Information Technology (IT)", "IT Management", "Security", "Technical / Functional Consulting"], "post_time": "2022-01-10T08:24:57Z", "salary": {"currency": null, "max": null, "min": null, "period": "monthly", "term": null}, "salary_visible": false, "title_keywords": ["service engineer", "consultant", "sales"], "responsibilities": ["conduct research", "software", "architecture", "design"], "requirements": {"degrees": ["master"], "majors": ["design", "engineering", "computer science", "electrical engineering"], "languages": [], "language_level": [], "hard_skills": ["integration"], "soft_skills": ["hands-on", "troubleshooting", "passionate about"], "languages_combined": []}, "experience_required": {"duration": ["minimum of 3 years"], "field": ["related", "development", "engineering", "design"]}}, {"job_id": "100003009034650", "location_code": "hk", "company": "Wellesley Associates Limited", "job_title": "Senior Manager/Associate Director (Information Security) - 1-1.5 Line - IAM/ HKMA - Bank/FSI - Perm", "description": "Reference #:\u00a0CTO/IOTSEN/10\n\n\nJob Responsibilities\n\n\nPropose, review, and execute projects advancing the practical state-of-the-art in machine learning (ML) and deep learning (DL)\nResearch and implement ML and DL technologies both independently and as part of collaborative teams to solve industrial vision-related problems\nDevelop and prototype ML/DL algorithms and software\nWork with hardware engineers to integrate a software into a well-tested and robust system\nProvide excellent communication with customers, partners, and teammates\nTake business trips to other cities for onsite support occasionally\nPerform other related duties and responsibilities, on occasion, as assigned\nRequirements\nPhD holder or Master\u2019s degree in Computer Science, Electronic/Electrical Engineering, Information Engineering, Mathematics, Statistics, Physics or relevant disciplines with minimum 3 years of related experience. Candidates with less experience may also be considered.\nExposure to Python or C++ programming\nExperience with DL frameworks such as TensorFlow, PyTorch and others.\nExposure to C, C# or CUDA programming is a plus\nFamiliar with maintenance of workstations and clusters for ML/DL is a plus\nStrong teamwork and good analytical thinking skills\nGood verbal and written communication skills in English\nLive ASTRI values\nApplication\n\nThe appointment will be on renewable contract terms with a competitive salary and performance-linked variable pay. Fringe benefits include paid leave, medical and dental benefits, insurance coverage and contribution to MPF. The incumbent will normally work\u00a0a five-day week.\n\nInterested candidates, please send an application (quoting Ref. No.) with a detailed resume, current and expected salary to\u00a0Talent Acquisition by clicking \"APPLY NOW\".\u00a0The resume should\u00a0not\u00a0include any sensitive personal information such as HKID or passport number, photo, etc.\u00a0\n\nPosition offer is subject to the applicant\u2019s experience and academic qualification. The application will be open until the position is filled. Only short-listed candidates will be notified. ASTRI reserves the right not to fill the position.\n\nASTRI is an Equal Opportunities Employer. Personal data provided by job applicants will be used\u00a0exclusively\u00a0for recruitment\u00a0only. For details, please refer to\u00a0Privacy - ASTRI - Hong Kong Applied Science and Technology Research Institute Company Limited, in particular section 9.", "employment_types": ["Full Time"], "selling_points": ["Information Security Manager - 1st/1.5 Line", "Banking/Financial Services", "Permanent Headcount"], "locations": ["Not Specified"], "categories": ["Information Technology (IT)", "IT Management", "Security", "Network & System"], "post_time": "2022-01-10T03:52:31Z", "salary": {"currency": null, "max": null, "min": null, "period": "monthly", "term": null}, "salary_visible": false, "title_keywords": ["senior manager", "associate director"], "responsibilities": ["software", "review", "teams", "develop", "communication", "hardware"], "requirements": {"degrees": ["degree", "master"], "majors": ["mathematics", "engineering", "electrical engineering", "statistics", "physics", "computer science"], "languages": ["english"], "language_level": ["good"], "hard_skills": ["plus", "c++", "maintenance", "cuda", "ml", "c", "programming", "python", "c#"], "soft_skills": ["communication skills", "teamwork"], "languages_combined": [{"language": "english", "language_level": ["good"]}]}, "experience_required": {"duration": ["minimum 3 years"], "field": ["related", "statistics", "engineering"]}}, {"job_id": "100003009040332", "location_code": "hk", "company": "Orient Overseas Container Line Ltd (OOCL)", "job_title": "Senior Technical Analyst - Oracle, MongoDB Database Administrator", "description": "Reference #:\u00a0CTO/CCT/12\n\n\nJob Responsibilities\nDesign and develop software systems for FinTech applications\nParticipate in the cycle of software development: design, testing, deployment, documentation and support.\nConduct software quality control\nDocument all implementation and testing with peer review.\nDeploy software systems at production sites\nRequirements\nPh.D. or Master\u2019s degree holder in Computer Science, Mathematics, Data Science or relevant disciplines with minimum 3 years of related experience\nFamiliarity with JavaScript frameworks such as Vue, React\nProficiency with server side languages such as Node.js, Go, Python, Java\nFamiliarity with database technology such as PostgreSQL and MongoDB\nExperience in practicing DevOps is a plus\nStrong teamwork and good analytical thinking skills\nLive ASTRI values\nApplication\n\n\nThe appointment will be on renewable contract terms with a competitive salary and performance-linked variable pay. Fringe benefits include paid leave, medical and dental benefits, insurance coverage and contribution to MPF. The incumbent will normally work\u00a0a five-day week.\n\nInterested candidates, please send an application (quoting Ref. No.) with a detailed resume, current and expected salary to\u00a0Talent Acquisition by clicking \"APPLY NOW\".\u00a0The resume should\u00a0not\u00a0include any sensitive personal information such as HKID or passport number, photo, etc.\u00a0Application open until this position is filled.\u00a0\n\nPosition offer is subject to the applicant\u2019s experience and academic qualification. The application will be open until the position is filled. Only short-listed candidates will be notified. ASTRI reserves the right not to fill the position.\n\nASTRI is an Equal Opportunities Employer. Personal data provided by job applicants will be used\u00a0exclusively\u00a0for recruitment\u00a0only. For details, please refer to\u00a0Privacy - ASTRI - Hong Kong Applied Science and Technology Research Institute Company Limited, in particular section 9.", "employment_types": ["Full Time", "Permanent"], "selling_points": ["Knowledge in Oracle DB, MongoDB, MYSQL", "Exposure to Oracle technology e.g. Oracle DB 10g", "Welcome open sources tools and new technologies"], "locations": ["Shatin Area"], "categories": ["Information Technology (IT)", "DBA", "Security", "Testing / QA"], "post_time": "2022-01-12T02:18:36Z", "salary": {"currency": null, "max": null, "min": null, "period": "monthly", "term": null}, "salary_visible": false, "title_keywords": ["analyst", "administrator"], "responsibilities": ["software", "systems", "design and develop", "implementation", "design", "testing", "review", "quality control", "deploy", "documentation"], "requirements": {"degrees": ["degree holder", "master"], "majors": ["mathematics", "data science", "computer science"], "languages": [], "language_level": [], "hard_skills": ["java", "plus", "react", "devops", "python", "javascript", "server", "go"], "soft_skills": ["teamwork"], "languages_combined": []}, "experience_required": {"duration": ["minimum 3 years"], "field": ["related", "devops"]}}, {"job_id": "100003009035803", "location_code": "hk", "company": "Macroview Telecom Limited", "job_title": "SOC Manager", "description": "Reference #:2021/ART/317CP/a-d\n\u00a0\nJob Responsibilities\n\nAssist in ITF R&D project as assigned\nDevelop, implement, and deploy deep-learning-based software for machine vision related manufacturing applications, such as image classification, object detection and semantic segmentation\nEvaluate state-of-the-art deep learning and automated machine learning algorithms\nIndependently write reports documenting detail methods and results\nRequirements\n\nGraduate in STEM-related discipline such as Computer Science, Electronic Engineering, Information Engineering and Mathematics or relevant discipline\nA bachelor\u2019s degree, master\u2019s degree or a doctoral degree\u2019s holder is welcome to apply\nFor bachelor\u2019s degree holder, they will be considered for the position of Engineering Associate (PI)\nProficiency in Python or C++ programming\nExperience with deep learning frameworks such as TensorFlow, PyTorch and others\nExposure to C, C#, CUDA or SQL programming is a plus\nExperience with GUI development tools such as Qt, MFC, Dash, Flask or Django is a plus\nStrong teamwork and good analytical thinking skills\nGood verbal and written communication skills in English\nApplication\n\nTo apply, by clicking 'APPLY NOW'\u00a0\u00a0with your resume, you must quote the\u00a0Job Ref\u00a0and include the following information:\n\nName of University\nDegree obtained/expecting and when\nHave you participated in ITF Research Talent Hub before? Yes/No\nIf you answer Yes in item 3, please state the period\nHave you been employed by ASTRI before? If yes, please state the period\n\nThe resume should\u00a0not\u00a0include any sensitive personal information such as HKID or passport number, photo, etc.\n\nThe application will be open until the position is filled. Only short-listed candidates will be notified. ASTRI reserves the right not to fill the position.\n\nASTRI is an Equal Opportunities Employer. Personal data provided by job applicants will be used\u00a0exclusively\u00a0for recruitment\u00a0only. For details, please refer to\u00a0Privacy - ASTRI - Hong Kong Applied Science and Technology Research Institute Company Limited,\u00a0in particular section 9.", "employment_types": ["Full Time", "Permanent"], "selling_points": ["Cyber Security Managed Services", "Conduct Project / Incident management", "6+ years experience in Information Security"], "locations": ["Quarry Bay"], "categories": ["Information Technology (IT)", "IT Project Management / Team Lead", "Security", "Technical / Functional Consulting"], "post_time": "2022-01-10T08:27:06Z", "salary": {"currency": null, "max": null, "min": null, "period": "monthly", "term": null}, "salary_visible": false, "title_keywords": ["manager"], "responsibilities": ["software", "develop", "evaluate", "reports", "deploy"], "requirements": {"degrees": ["degree holder", "degree", "bachelor", "master"], "majors": ["engineering"], "languages": ["english"], "language_level": ["good"], "hard_skills": ["plus", "no", "c++", "cuda", "sql", "c", "programming", "python", "c#"], "soft_skills": ["communication skills", "teamwork", "deep", "learning", "sensitive"], "languages_combined": [{"language": "english", "language_level": ["good"]}]}, "experience_required": {"duration": [], "field": ["development"]}}, {"job_id": "100003009037081", "location_code": "hk", "company": "Canon Hongkong Company Limited", "job_title": "(Senior) System Administrator / IT Support", "description": "Reference #:2021/ART/333CP/c-d\n\u00a0\nJob Responsibilities\n\nFor the research and development of advanced optical system design and prototyping, including imaging/non-imaging optical design for machine vision, nano-optics, 3D reconstruction and medical imaging\nDefine optical specifications, design analyses, risk analysis with contingency plans, design reviews, manufacturability assessments, verification of design durability and Reliability, vendor survey, schedule control and prototype verification\nEvaluating and implementing customer requirements in an optical engineering environment\nRequirements\n\nDegree holder in Optical Engineering, Nano Optics, Bio-optics or relevant disciplines\nA bachelor\u2019s degree, master\u2019s degree or a doctoral degree\u2019s holder is welcome to apply\nFor bachelor\u2019s degree holder, they will be considered for the position of Engineering Associate (PI)\nExperience of both imaging optical system and non-imaging optical system design and production\nFamiliar with optical design software tools such as Zemax, CodeV, LightTools , TracePro, FTDT etc\nFamiliar with optical design for machine vision application, Nano Optics, 3D reconstruction, medical imaging, confocal optical design, OCT, etc\nGood command of written and spoken English, self-motivated and good communication skills\nApplication\n\nTo apply, by clicking 'APPLY NOW'\u00a0\u00a0with your resume, you must quote the\u00a0Job Ref\u00a0and include the following information:\n\nName of University\nDegree obtained/expecting and when\nHave you participated in ITF Research Talent Hub before? Yes/No\nIf you answer Yes in item 3, please state the period\nHave you been employed by ASTRI before? If yes, please state the period\n\nThe resume should\u00a0not\u00a0include any sensitive personal information such as HKID or passport number, photo, etc.\n\nThe application will be open until the position is filled. Only short-listed candidates will be notified. ASTRI reserves the right not to fill the position.\n\nASTRI is an Equal Opportunities Employer. Personal data provided by job applicants will be used\u00a0exclusively\u00a0for recruitment\u00a0only. For details, please refer to\u00a0Privacy - ASTRI - Hong Kong Applied Science and Technology Research Institute Company Limited,\u00a0in particular section 9.", "employment_types": ["Full Time", "Permanent"], "selling_points": ["IT operations and support under DevOps model", "Infrastructure and cloud services, ITIL/ITSM, SDLC", "Asset management, vendor management, procurement"], "locations": ["Hung Hom"], "categories": ["Information Technology (IT)", "Support", "Security", "Network & System"], "post_time": "2022-01-11T01:39:17Z", "salary": {"currency": null, "max": null, "min": null, "period": "monthly", "term": null}, "salary_visible": false, "title_keywords": ["system administrator", "it support"], "responsibilities": ["control", "design", "specifications", "system design", "risk analysis", "schedule", "plans"], "requirements": {"degrees": ["master", "degree", "bachelor", "degree holder"], "majors": ["engineering"], "languages": ["english"], "language_level": ["good command", "good"], "hard_skills": ["no", "system design"], "soft_skills": ["communication skills", "self-motivated", "sensitive"], "languages_combined": [{"language": "english", "language_level": ["good", "good command"]}]}, "experience_required": {"duration": [], "field": ["system design"]}}, {"job_id": "100003009039044", "location_code": "hk", "company": "Recolo Limited", "job_title": "IT Specialist - HKD $25K (16612)", "description": "Reference #:\u00a0CTO/CCT/08\n\n\nJob Responsibilities\nDesign and develop software systems for FinTech applications\nParticipate in the cycle of software development: design, testing, deployment, documentation and support.\nConduct software quality control\nDocument all implementation and testing with peer review\nDeploy software systems at production sites\nRequirements\nPhD or Master\u2019s degree holder in Computer Science, Mathematics, Data Science or relevant disciplines with minimum 3 years of related experience\nKnowledge of Software development in Python\nExperience in developing data analytics and machine learning models\nFamiliarity with the tools for data and AI modeling\nExperience and/or knowledge in privacy enhancing technologies such as federated learning, homomorphic encryption, and secure multi-party computation is a plus\nStrong communication skills and good teamwork\nLive ASTRI values\nApplication\n\n\nThe appointment will be on renewable contract terms with a competitive salary and performance-linked variable pay. Fringe benefits include paid leave, medical and dental benefits, insurance coverage and contribution to MPF. The incumbent will normally work\u00a0a five-day week.\n\nInterested candidates, please send an application (quoting Ref. No.) with a detailed resume, current and expected salary to\u00a0Talent Acquisition by clicking \"APPLY NOW\".\u00a0The resume should\u00a0not\u00a0include any sensitive personal information such as HKID or passport number, photo, etc.\u00a0\n\nPosition offer is subject to the applicant\u2019s experience and academic qualification. The application will be open until the position is filled. Only short-listed candidates will be notified. ASTRI reserves the right not to fill the position.\n\nASTRI is an Equal Opportunities Employer. Personal data provided by job applicants will be used\u00a0exclusively\u00a0for recruitment\u00a0only. For details, please refer to\u00a0Privacy - ASTRI - Hong Kong Applied Science and Technology Research Institute Company Limited, in particular section 9.", "employment_types": ["Full Time", "Permanent"], "selling_points": ["Global Law Firm", "Technical Support", "MCSE / CCNA; Azure,Office 365"], "locations": ["Central & Western Area"], "categories": ["Information Technology (IT)", "Hardware", "Support", "Security"], "post_time": "2022-01-11T08:29:13Z", "salary": {"currency": null, "max": null, "min": null, "period": "monthly", "term": null}, "salary_visible": false, "title_keywords": ["it specialist"], "responsibilities": ["software", "systems", "design and develop", "implementation", "design", "testing", "review", "quality control", "deploy", "documentation"], "requirements": {"degrees": ["degree holder", "master"], "majors": ["mathematics", "data science", "computer science"], "languages": [], "language_level": [], "hard_skills": ["python", "data analytics", "plus", "ai"], "soft_skills": ["communication skills", "learning", "teamwork"], "languages_combined": []}, "experience_required": {"duration": ["minimum 3 years"], "field": ["related", "developing"]}}, {"job_id": "100003009039129", "location_code": "hk", "company": "PERSOLKELLY Hong Kong Limited", "job_title": "Presales/Senior Presales manager/ICT Consultant/Solution Consultant - Telco", "description": "Reference #:\u00a0CTO/ICS/03\n\nOpening: 2\n\u00a0\nJob Responsibilities\nResponsible for the product designs of advanced semiconductor (including Si, SiC, GaN) based power modules, power systems, or energy storage systems, including all facets of the design flow, from schematics to layout, from component selection to final verification\nDevelop leading-edge electric, electronics, thermal, mechanical, or materials solutions for different kinds of power modules, power systems, or energy storage systems for various smart city and industry 4.0 related applications\nWork with marketing and technology transfer team to prepare engineering prototypes and conduct on-site tests\n\u00a0\nRequirements\nDegree holders (Bachelor/Master/Ph.D.) in Electrical Engineering, Electronics Engineering, Computer Science, Mechanical Engineering, or related fields with minimum of 3 years related experience\nExperiences in the package/module designs (e.g., electric, electronics, thermal, mechanical, or materials), power electronics products (e.g., DC/DC converters, AC/DC converters), or energy storage systems (e.g., battery module, pack, AGV)\nGood communication and interpersonal skills, a good team player\nProficiency in written and spoken English\nLives ASTRI values\nApplication\n\nThe appointment will be on renewable contract terms with a competitive salary and performance-linked variable pay. Fringe benefits include paid leave, medical and dental benefits, insurance coverage and contribution to MPF. The incumbent will normally work\u00a0a five-day week.\n\nInterested candidates, please send an application (quoting Ref. No.) with a detailed resume, current and expected salary to\u00a0Talent Acquisition by clicking \"APPLY NOW\".\u00a0The resume should\u00a0not\u00a0include any sensitive personal information such as HKID or passport number, photo, etc.\u00a0\n\nPosition offer is subject to the applicant\u2019s experience and academic qualification. The application will be open until the position is filled. Only short-listed candidates will be notified. ASTRI reserves the right not to fill the position.\n\nASTRI is an Equal Opportunities Employer. Personal data provided by job applicants will be used\u00a0exclusively\u00a0for recruitment\u00a0only. For details, please refer to\u00a0Privacy - ASTRI - Hong Kong Applied Science and Technology Research Institute Company Limited, in particular section 9.", "employment_types": ["Full Time", "Permanent"], "selling_points": ["ICT/ Cloud/ IoT/ Data Center/ Net work /Security", "Telco/ Telecommunications", "Presale / consultant / solution consultant"], "locations": ["Not Specified"], "categories": ["Information Technology (IT)", "Security", "Network & System", "Technical / Functional Consulting"], "post_time": "2022-01-11T08:46:52Z", "salary": {"currency": null, "max": null, "min": null, "period": "monthly", "term": null}, "salary_visible": false, "title_keywords": ["manager", "consultant"], "responsibilities": ["systems", "design", "develop"], "requirements": {"degrees": ["degree", "bachelor", "master"], "majors": [], "languages": ["english"], "language_level": ["proficiency"], "hard_skills": ["dc"], "soft_skills": ["good team player", "communication and interpersonal skills"], "languages_combined": [{"language": "english", "language_level": ["proficiency"]}]}, "experience_required": {"duration": ["minimum of 3 years"], "field": ["related", "engineering"]}}]