[{"job_id": "100003009050497", "location_code": "hk", "company": "LABS Group Limited", "job_title": "Game Editor/\u904a\u6232\u6e2c\u8a66\u54e1 (English and Chinese)", "description": "\u00a0Motto: Are you a hardcore Gamer? Into Blockchain? Come and talk to us!\n\n\u00a0Responsibilities include:\n\nReview Gamefi / NFT / Blockchain Projects for content quality based on company requirements..\nAble to provide data & reports through analysis on market trends for Gamefi / NFTs.\nThoroughly check ad content with quality and accuracy.\nAnalyze data and evaluate trends/ patterns.\nRecommend generic marketing patterns / buying insight\nEscalating questions/issues from the team regarding the process and cascading updates to the team.\nPreparing weekly process reports & sending out to the concerned people.\nBecome a key personality within the team to potentially become a crypto influencer.\n\n\u00a0Requirements:\n\nMinimum 1 years of experience in\u00a0game QA testing,\u00a0developing test plans and test cases\nAim to choose crypto as long-term career pathStrong sense of art or degen in NFT discord channels is a plus\nHeavy game player is a strong bonusFull-time analyst\u00a0\nStrong communication\u00a0and\u00a0analytical skills\nFamiliar with the popular games released in past 5 years\n\nApplication Requirement:\n\nA writing sample that introduce you as a hardcore mobile gamer and why you're a good fit for us\n\n\n\nWhat We Offer:\n\nAttractive remuneration package that includes 5-day work\nPrivilege insurance plan for group medical (covers clinical, hospitalization with supplementary major medical) & dental\nConvenient office location in TsimShaTsui\nWork with the young and energetic team\nFree snacks, coffee, and tea\nFestival cash and gifts\nRegular staff activities\n\nPlease send your full resume in English, stating present and expected salary by clicking APPLY NOW.\n\nWe are an equal opportunity employer and welcome applications from all qualified candidates.\u00a0 Personal data collected will be treated in strictest confidence and handled confidentially by authorized personnel for recruitment-related purposes within the Group.", "employment_types": ["Full Time", "Permanent"], "selling_points": ["Joyful working environment with free snacks/drinks", "Young & friendly working environment", "5 days work medical and Dental Insurance"], "locations": ["Tsim Sha Tsui"], "categories": ["Media & Advertising", "Editorial / Journalism", "Information Technology (IT)", "Software Development", "Testing / QA"], "post_time": "2022-01-17T10:52:26Z", "salary": {"currency": null, "max": null, "min": null, "period": "monthly", "term": null}, "salary_visible": false, "title_keywords": ["editor"], "responsibilities": ["data", "analysis", "review", "quality", "evaluate", "reports", "analyze data"], "requirements": {"degrees": [], "majors": [], "languages": [], "language_level": [], "hard_skills": ["mobile", "plus", "crypto", "analytical skills"], "soft_skills": ["communication", "analytical skills"], "languages_combined": []}, "experience_required": {"duration": ["minimum 1 years"], "field": ["developing", "qa", "testing"]}}, {"job_id": "100003009054299", "location_code": "hk", "company": "K. Wah International Holdings Ltd", "job_title": "System Analyst", "description": "Job Responsibilities\n\nResponsible for mobile platforms (iOS / Android) and web application software development\nConduct detailed system analysis, problem diagnosis, purpose, develop and implement IT solutions\nPrepare requirement specifications of IT solutions\nMonitor service provision and prepare cases for testing IT solutions\nMaintain system documentation and reports of IT solutions\n\nJob Requirements\n\nDegree / Higher Diploma / Diploma in Computer Science, Computer Engineering or related disciplines\n5 years of working experience, with at least 2 years of hands-on experience in mobile (IOS/Android) and web application programming\nKnowledge of mobile development Java-Android SDK, Objective-C / SwiftUI\nKnowledge of web development WAMP, HTML JavaScript, CSS, JSON and PHP\nKnowledge of mobile cross-platform development VueJS, React or Flutter is in advance\nPassionate about mobile & web application development, cloud platforms (e.g. AWS, GC) and new technologies\nGood analytical and problem-solving skills\nWell organized, disciplined and responsible with a good work ethic\nAble to work independently and be self-driven to meet project schedules\nA self-motivated team player with good interpersonal and communication skills\nA good team player\nInterested parties please send resume with salary expectation and availability to\u00a0Human Resources Department, K. Wah International Holdings Limited, 29/F, K. Wah Centre, 191 Java Rd., North Point, H.K.\u00a0or by clicking\u00a0Apply Now\u00a0.\n\nAll Personal data collected will be used for recruitment purpose only. All applications will be retained for a maximum period of 2 years and may be considered for other suitable positions within the Group.\n\n", "employment_types": ["Full Time", "Permanent"], "selling_points": ["Web application programming", "Mobile platforms (iOS / Android)", "Cross-platform development"], "locations": ["North Point"], "categories": ["Information Technology (IT)", "Application Specialist - Software", "Software Development", "Mobile / Wireless Communications"], "post_time": "2022-01-17T09:05:23Z", "salary": {"currency": null, "max": null, "min": null, "period": "monthly", "term": null}, "salary_visible": false, "title_keywords": ["system analyst"], "responsibilities": ["software", "system documentation", "analysis", "monitor", "develop", "testing", "specifications", "maintain", "reports"], "requirements": {"degrees": ["diploma", "degree"], "majors": ["related disciplines", "computer engineering", "computer science"], "languages": [], "language_level": [], "hard_skills": ["java", "web development", "web application development", "web", "android sdk", "php", "react", "problem-solving skills", "html", "objective-c", "aws", "mobile", "javascript", "programming", "css", "android"], "soft_skills": ["communication skills", "work independently", "self-motivated", "good team player", "responsible", "well organized", "hands-on", "work ethic", "problem-solving skills", "team player", "interpersonal", "driven", "passionate about"], "languages_combined": []}, "experience_required": {"duration": ["5 years", "at least 2 years"], "field": ["programming"]}}, {"job_id": "100003009054621", "location_code": "hk", "company": "CK Hutchison Holdings Limited", "job_title": "Senior Systems Analyst / Systems Analyst", "description": "Description/ Responsibility:\n\nResponsible for full-stack development of web, IoT and cloud applications\nInteract with customers and project leaders to understand requirement\nWhat we offer\u00a0:\n\nFriendly culture\nHarmony working environment\nAnnual leave and banking holidays\nPerformance bonus\nRequirements:\n\nHigher Diploma or above in related discipline\n1 year+ relevant working experience in software development\nGood knowledge in NodeJS, HTML5, CSS3, JavaScript, PHP, and Perl\nGood knowledge in RDBMS database\nFresh graduates will also be considered\n\nWe offer relevant training, attractive remuneration and promotion path to successful candidates. Final position offer is subject to candidate\u2019s experiences. For interested party, please email your CV with your expected salary by clicking \u201cApply Now\u201d\n\nPersonal data collected will be used for recruitment purpose only.\n", "employment_types": ["Full Time"], "selling_points": ["Head Office", "Oracle E-Business Suite Applications (ERP or HRMS)", "Oracle Fusion Cloud"], "locations": ["Hung Hom"], "categories": ["Information Technology (IT)", "Application Specialist - Software", "Product Management / Business Analyst", "Software Development"], "post_time": "2022-01-17T10:18:36Z", "salary": {"currency": null, "max": null, "min": null, "period": "monthly", "term": null}, "salary_visible": false, "title_keywords": ["analyst"], "responsibilities": [], "requirements": {"degrees": [], "majors": [], "languages": [], "language_level": [], "hard_skills": [], "soft_skills": [], "languages_combined": []}, "experience_required": {"duration": [], "field": []}}, {"job_id": "100003009054402", "location_code": "hk", "company": "Huacomm Telecommunications Engineering (HK) Ltd", "job_title": "Software Developer / Full Stack Developer/ Programmer (5-day Work)", "description": "Job Description and Responsibilities\n\nDesign and Develop corporate training platforms for corporate in Hong Kong;\nPerform AI-related research for applying AI-related functions to e-learning systems.\u00a0\n\n\u00a0Job Openings\n\n2+\n\n\u00a0Job Requirements\n\nAt least 1 year of working experience (Fresh graduate will also be considered)\nExperience in e-learning platform development is a plus\nFamiliar with at least one of the following areas\nWeb Programming (HTML, CSS, JavaScript, PHP, MySQL) + Laravel (PHP Framework)\nSystem administration or Database administration (e.g. linux-based server, cloud based servers, MySQL administration, etc.)\niOS Programming (Objective-C / Swift)\nAndroid Programming (Java)\nFull-time working mode (5-day work)\n\n\u00a0Monthly Salary & Bonus:\n\nSalary will be offered based on experience, skills and education level\nRanged from 18,000 to 28,000 per month\nPerformance-based bonus will be considered at the end of the year\n\n\u00a0Team's Focus:\n\nCorporate Training Platform Development\nMobile Learning Platforms (Apps & Web)\nSoftware Product Development\n\n\u00a0Products and Services Highlight\n\niTrain - Self-learning corporate training platform\n\nA self-learning corporate training platform developed for MNC. Over 100,000 users have been enrolled to our system.", "employment_types": ["Full Time", "Permanent"], "selling_points": ["Perform program development and maintain systems", "1 yr+ working experience. Welcome Fresh graduates", "Stable working hour and good career path"], "locations": ["Admiralty"], "categories": ["Information Technology (IT)", "Application Specialist - Software", "Software Development"], "post_time": "2022-01-18T01:41:35Z", "salary": {"currency": null, "max": null, "min": null, "period": "monthly", "term": null}, "salary_visible": false, "title_keywords": ["developer", "programmer"], "responsibilities": ["systems", "design and develop"], "requirements": {"degrees": ["fresh graduate"], "majors": [], "languages": [], "language_level": [], "hard_skills": ["linux", "plus", "java", "servers", "web", "php", "swift", "html", "objective-c", "mobile", "javascript", "programming", "server", "css", "focus", "android"], "soft_skills": ["focus", "learning"], "languages_combined": []}, "experience_required": {"duration": ["at least 1 year"], "field": ["development", "education"]}}, {"job_id": "100003009054511", "location_code": "hk", "company": "Hong Kong Education City Limited", "job_title": "Software Engineer / Analyst Programmer / Web Application Developer", "description": "Responsibilities:\n-To develop web applications using PHP, React, Laravel, MySQL,\u00a0Redis and other APIs\n-To follow up customer for system requirements and feedbacks\n\nRequirements:\n- Minimum 1 year of relevant experience in web programming with past job reference\n- Proven knowledge\u00a0 in PHP, API, SQL, JavaScript, CSS are essentials.\n- Proven knowledge in development tools of Git, PhpUnit\u00a0are essentials.\n- Familiar with Shell Scripts / Linux (CentOS)Server knowledge\u00a0will be a plus.\n- Familiar with docker, CD/CI knowledge\u00a0will be a plus.\n- Good command of written Chinese, English\n- Self-motivated, responsible, able to work independently under tight deadline and willing to work under pressure\n- Experienced/Outstanding candidates will be considered as Analyst Developer\n- Immediately available preferred\n\nWe Offer:\n- Attractive remuneration package (Basic + Bonus)\n- Bank Holiday\n\nWant to know more about us, please visit http://www.sunnyvision.com\n\n9:00am-6:00pm, 5 days week, Mon-Fri (3 months probation)\n\nInterest party, please send your full resume with CURRENT & EXPECTED SALARY by email to jobs at sunnyvision.com\u00a0for an interview.\n\nAll applications will be treated in the strictest confidence. We regret that only shortlisted candidates will be notified. Data collected will be used for recruitment purpose only.\u00a0", "employment_types": ["Full Time"], "selling_points": ["5-day workweek and happy & friendly environment", "14-21 days AL, medical, dental & life insurance", "Competitive pay, Incentive Pay & MPFVC"], "locations": ["Shatin Area"], "categories": ["Information Technology (IT)", "Application Specialist - Software", "Software Development", "Mobile / Wireless Communications"], "post_time": "2022-01-17T09:50:03Z", "salary": {"currency": null, "max": null, "min": null, "period": "monthly", "term": null}, "salary_visible": false, "title_keywords": ["software engineer", "developer", "analyst programmer"], "responsibilities": ["develop"], "requirements": {"degrees": [], "majors": [], "languages": ["english", "chinese"], "language_level": ["good command"], "hard_skills": ["linux", "plus", "git", "web", "php", "sql", "javascript", "programming", "css"], "soft_skills": ["self-motivated", "work independently", "responsible", "work under pressure"], "languages_combined": [{"language": "english", "language_level": ["good command"]}, {"language": "chinese", "language_level": ["good command"]}]}, "experience_required": {"duration": ["minimum 1 year"], "field": ["relevant experience", "programming"]}}, {"job_id": "100003009054930", "location_code": "hk", "company": "SunnyVision Limited", "job_title": "Web Developer", "description": "Responsibilities\n\nWorking closely with PM, Designers, Developers and Programmers\nUnderstand the client's requirements and generate technical solutions\nIdentify issues and implement solutions to complex problems\nPerform function enhancement, system deployment and testing\n\nRequirements\n\n\nHigher Diploma / Bachelor Degree in Computer Science, Information Technology, or any related disciplines;\n1 year or above experience in web or application development;\nExperience in PHP framework (e.g. Laravel, Codeigniter), MySql, MSSQL, RESTful API, HTML, CSS, JavaScript framework (e.g. React, bootstrap), Python will be an advantage;\nExperience in payment integration (e.g. Paypal / Stripe) will be an advantage;\nGood team player with strong analytical and problem-solving skills;\nSelf-motivated with can do attitude and timely delivery results\nWorking Location in Tsuen Wan\n\nNice to have\n\nExperience in cloud storage, deployment and computing. We use Azure / AWS but we're open to other platform experience\n", "employment_types": ["Full Time", "Permanent"], "selling_points": ["Develop web applications using PHP, MySQL, Redis", "Proven knowledge in PHP, React, Laravel, MySQL", "Familiar with Linux, CD/CI, Docker will be a plus"], "locations": ["Wong Tai Sin Area"], "categories": ["Information Technology (IT)", "Application Specialist - Software", "IT - Webmaster / SEO", "Software Development"], "post_time": "2022-01-17T14:20:31Z", "salary": {"currency": null, "max": null, "min": null, "period": "monthly", "term": null}, "salary_visible": false, "title_keywords": ["developer"], "responsibilities": ["testing"], "requirements": {"degrees": ["diploma", "degree", "bachelor"], "majors": ["related disciplines", "computer science", "information technology"], "languages": [], "language_level": [], "hard_skills": ["restful api", "azure", "web", "php", "react", "integration", "problem-solving skills", "nice", "html", "python", "aws", "javascript", "deployment", "mssql", "css", "wan"], "soft_skills": ["problem-solving skills", "good team player", "timely", "self-motivated"], "languages_combined": []}, "experience_required": {"duration": ["1 year"], "field": ["application development"]}}, {"job_id": "100003009054701", "location_code": "hk", "company": "Cymballe Limited", "job_title": "Full Stack Developer / Software Engineer / Analyst Programmer (Fresh Graduate Welcome)", "description": "About us\n\nWe are a small start-up looking for founding engineers to grow with us.\nWe are young founders with technical, marketing and capital management backgrounds.\nOur own flagship product is a user-generated Augmented Reality content app, currently under development.\u00a0Other projects include a recycling app,\u00a0facial authentication system, catalogue system,\u00a0etc.\n\n\nOther Job Highlights\n\nWork in Wan Chai or remotely from home\u00a0\nNo fixed working hours, performance based daily work flow\u00a0\nSmall, close team\u00a0\nYou can contribute ideas in any areas and shape the future development of company\nGrow along side the company\u00a0\nExcellent salary which is flexible based on experience\u00a0\nStock options after 12 months\u00a0\n\nResponsibilities\n\nReact Native app development\nParticipate in system design, development, testing and implementation of mobile apps\nWork with UI/UX designer and backend engineer for a user centric design\u00a0\n(\u548c UI/UX \u8a2d\u8a08\u5e2b\u53ca\u5f8c\u7aef\u5de5\u7a0b\u5e2b\u5bc6\u5207\u5408\u4f5c)\u00a0\nAnalyze/refactor current system, design new functions\u00a0\n(\u8ca0\u8cac\u8edf\u9ad4\u4e4b\u5206\u6790\u3001\u8a2d\u8a08\u4ee5\u53ca\u7a0b\u5f0f\u64b0\u5beb)\u00a0\nInvestigate and reproduce steps of bugs from user reports\u00a0\n(\u9032\u884c\u8edf\u9ad4\u4e4b\u6e2c\u8a66\u8207\u4fee\u6539)\u00a0\nContribute your great ideas to innovate and energize team members\u00a0\n(\u5354\u52a9\u7814\u767c\u8edf\u9ad4\u65b0\u6280\u8853\u8207\u65b0\u5de5\u5177)\u00a0\n\nRequirements\n\nHigh diploma, degree in Computer Science or related disciplines is NOT A MUST, candidates with any experience or fresh graduates are welcome\nProficiency in React Native Expo, React Components, Props, State, and Flexbox\u00a0\n(\u719f\u6089 React Native Expo\uff0c\u6703\u4ee5 React Component \u908f\u8f2f\u5207\u7248\u3001\u5efa\u69cb\u9801\u9762)\u00a0\nProficiency in Redux\u00a0\n(\u719f\u6089 Redux \u8cc7\u6599\u6d41\u63a7\u7ba1)\u00a0\nProficiency in React Hooks\n(\u719f\u6089 React Hooks)\u00a0\nFamiliar with Git and Github\n(\u719f\u6089 Git \u8edf\u9ad4\u7248\u672c\u63a7\u7ba1)\u00a0\nA simple portfolio of created apps\u00a0\nPassionate in multicultural trends is a plus\u00a0\n\nFor junior applicants, there are new learning pathways for your development:\n\nLearn API to access data and interact with external software components\u00a0\nLearn Swift to create native iOS and Kotlin to create Android apps, and native bridging in React Native\nLearn UI frameworks such as React Native Element, NativeBase\u00a0\nLearn NodeJS\u00a0\nLearn Database: DynamoDB, Neo4j, etc.\u00a0\nLearn AWS Cloud\n\n\n\nWe offer a competitive remuneration package and fringe benefits to the right candidates. If you are interested please send us your\u00a0motivation,\u00a0expected salary\u00a0&\u00a0available date\u00a0together with your detailed resume\u00a0and\u00a0portfolio\u00a0(if any) by clicking \"Apply Now\".\n\nWe are an equal opportunity employer and welcome applications from all qualified candidates. All information provided will be treated in strict confidence and used for recruitment purposes only.", "employment_types": ["Full Time"], "selling_points": ["Award-winning creative digital agency", "Rapid advancement opportunity, dynamic culture", "Experience in web or application development"], "locations": ["Tsuen Wan Area"], "categories": ["Information Technology (IT)", "Application Specialist - Software", "Software Development", "Others"], "post_time": "2022-01-17T10:38:44Z", "salary": {"currency": null, "max": null, "min": null, "period": "monthly", "term": null}, "salary_visible": false, "title_keywords": ["software engineer", "developer", "analyst programmer"], "responsibilities": ["ideas", "implementation", "design", "testing", "system design", "reports", "ui"], "requirements": {"degrees": ["high diploma", "degree"], "majors": ["related disciplines", "computer science"], "languages": [], "language_level": [], "hard_skills": ["simple", "plus", "git", "react", "aws", "react native", "swift", "kotlin", "android"], "soft_skills": ["passionate", "learning"], "languages_combined": []}, "experience_required": {"duration": [], "field": ["related"]}}, {"job_id": "100003009053948", "location_code": "hk", "company": "Nnenu Limited", "job_title": "Frontend Developer (JavaScript/Swift/Kotlin)", "description": "Responsibilities\n\nMobile app development,\u00a0testing,\u00a0implementation and enhancement\n\nRequirements\n\nChristian preferred\nExcellent communication skill and willing to learn new technologies\nBe a good team player and able to work as a group\nInnovative and analytical problem solving mind set\nAt least 1 year solid hands-on development experience in\u00a0React Native\nSolid Experience with GIT\nProficiency with REST-based APIs\nKnowledge in Big Data analysis, AI, Android Native (JAVA) or Kotlin is a plus\nDiploma or degree holder in Computer Science,\u00a0Software Engineering or related disciplines\nFresh graduates with proven experience will also be considered\nFamiliar with Smartphone operation\nPerform ad-hoc assignment as required\u00a0\nImmediate available preferred", "employment_types": ["Full Time", "Permanent"], "selling_points": [], "locations": ["Wan Chai"], "categories": ["Information Technology (IT)", "Software Development"], "post_time": "2022-01-17T07:49:32Z", "salary": {"currency": "HKD", "max": 34999, "min": 20000, "period": "monthly", "term": null}, "salary_visible": true, "title_keywords": ["developer"], "responsibilities": ["mobile app", "implementation", "testing"], "requirements": {"degrees": ["diploma", "degree holder"], "majors": ["related disciplines", "software engineering", "computer science"], "languages": [], "language_level": [], "hard_skills": ["java", "git", "plus", "ai", "analysis", "problem solving", "react native", "kotlin", "android"], "soft_skills": ["good team player", "communication skill", "willing to learn", "problem solving", "hands-on", "innovative"], "languages_combined": []}, "experience_required": {"duration": ["at least 1 year"], "field": ["development"]}}, {"job_id": "100003009053395", "location_code": "hk", "company": "Evergreat Creative (Hong Kong) Limited", "job_title": "App Developer (React Native)", "description": "We are a small-medium HK listed company seeking a Frontend Developer, a strong technical skillset and hands-on doer responsible for developing the planning, execution and control of multiple complex, high-visibility programs for the IT project, from inception through implementation.\n\nThe successful candidate will be one of the core members of a FinTech project which will become the principal business of the company in the upcoming phase of business development.\n\nOur company has an open-minded and proactive culture in which we place a high priority of communication, recognition and collaboration and welcome the candidate who is aligned with our value to join us.\n\n\n\nJob Description:\n\nWork with product owners and other development teams to help scope and spec requirements;\nPerform code reviews and facilitate peer reviews;\nAdapt appropriate development processes to improve quality of work and efficiency;\nProduce quality code for stability, security, and maintainability;\nParticipate in R&D and proof-of-concepts of new technologies and platforms; and\nOwn, research and recommend new solutions to meet project defined business and technical requirements.\nJob Requirements:\n\nBachelor degree or above in computer science or equivalent discipline;\n3-5 years' experience in Application development;\nStrong knowledge of abilities and limitations for mobile and web platforms\nFamiliarity or proficiency in some of the following technologies: NodeJS / ReactJS / Python / Kotlin / Go / Kubernetes / Docker.\nOffers:\n\n5-day work week\nBank holidays + Annual Leave\nGuaranteed Double pay\u00a0\nMedical insurance\nBirthday Red Packet\nFree snacks, coffee, and tea\nFestival gifts\nRegular staff activities\nConvenient office location in Sheung Wan\nWork with the young and energetic team which value opinions and efforts", "employment_types": ["Full Time", "Part Time", "Temporary", "Contract", "Freelance"], "selling_points": ["Fresh grad welcomed, system programmer", "5 days works with flexible work hours", "Year end bonus based on performance"], "locations": ["Lai Chi Kok"], "categories": ["Information Technology (IT)", "Software Development", "Mobile / Wireless Communications"], "post_time": "2022-01-17T07:00:10Z", "salary": {"currency": null, "max": null, "min": null, "period": "monthly", "term": null}, "salary_visible": false, "title_keywords": ["developer"], "responsibilities": ["quality", "teams"], "requirements": {"degrees": ["degree or above", "bachelor"], "majors": ["computer science"], "languages": [], "language_level": [], "hard_skills": ["tea", "web", "wan", "mobile", "red", "python", "kotlin", "go"], "soft_skills": ["energetic"], "languages_combined": []}, "experience_required": {"duration": ["3-5 years"], "field": ["application development"]}}, {"job_id": "100003009053155", "location_code": "hk", "company": "Top Vast Finance Limited", "job_title": "Frontend Developer", "description": "Job Description:\u00a0\nSystems development, enhancement and maintenance;\nPerform unit tests;\nPrepare program specification;\nPerform any other duties assigned.\u00a0\nJob Requirements:\u00a0\n\nDegree holder in Computer Science or related disciplines;\nAt least 2 years related working experience for analyst programmer;\nKnowledge in Java, SQL is required;\nKnowledge in any of Spring, Javascript/Typescript, React, React Native, MQ is a plus;\nGood analytical skill, commitment to work, good problem-solving skill;\nCandidate with less experience or fresh graduate will also be considered as Programmer.", "employment_types": ["Full Time", "Permanent"], "selling_points": ["Developers want to exposure in Fintech industry", "New headcount & stable company", "Coached by senior developers"], "locations": ["Sheung Wan"], "categories": ["Information Technology (IT)", "Application Specialist - Software", "Software Development", "Network & System"], "post_time": "2022-01-17T06:09:16Z", "salary": {"currency": null, "max": null, "min": null, "period": "monthly", "term": null}, "salary_visible": false, "title_keywords": ["developer"], "responsibilities": ["any other duties", "systems", "maintenance"], "requirements": {"degrees": ["fresh graduate", "degree holder"], "majors": ["related disciplines", "computer science"], "languages": [], "language_level": [], "hard_skills": ["java", "plus", "analytical skill", "react", "problem-solving", "sql", "javascript", "typescript", "react native", "spring"], "soft_skills": ["problem-solving", "analytical skill"], "languages_combined": []}, "experience_required": {"duration": ["at least 2 years"], "field": ["related"]}}, {"job_id": "100003009053169", "location_code": "hk", "company": "Softcube Systems Limited", "job_title": "Programmer (5 days work)", "description": "Open Creative is looking for highly motivated and hands-on candidates, ready to take on the challenge of building large, scalable web and mobile solutions that real people use everyday!\n\nWhat we're looking for:\n\nFull stack web development for new web projects.\nMaintain, develop & support existing big & small web projects.\nGather client user requirements & perform analysis of the requirements.\nProvide daily client technical troubleshooting.\nSolid experience in Linux servers administration is needed.\nKey skills & requirements:\n\nDegree in Computer Science or equivalent.\nAt least 2.0 years of solid hands-on programming experience.\nExpert in HTML5, CSS3, Javascript, React.js is a must.\nExcellent working experience in PHP programming environment is a must.\nExperience in Node.js developing server-side & Github/Redux for secure networking application deployment is a big advantage.\nWorking experience with AWS / Azure Linux builds a big advantage.\nExperience in implementing responsive UI & UX for web & mobile apps using Bootstrap is a bonus.\nStrong knowledge of cross-platform compatibility, new web technologies & e-commerce best practices.\nSound logic-problem solving, self-motivated & good time-management.\nGood communication in spoken & written English & Chinese.\nDoes this sound like you? Then send us your current resume, expected salary & a brief cover letter about yourself via email to jobs at opencreative.com. All personal information collected will be used for recruitment purposes only.", "employment_types": ["Full Time"], "selling_points": ["5-days work week", "Vibrant, Friendly and Diversify environment", "Performance bonus"], "locations": ["Ngau Tau Kok"], "categories": ["Information Technology (IT)", "Software Development", "Technical Writing", "Others"], "post_time": "2022-01-17T06:13:36Z", "salary": {"currency": null, "max": null, "min": null, "period": "monthly", "term": null}, "salary_visible": false, "title_keywords": ["programmer"], "responsibilities": ["management", "analysis", "troubleshooting", "developing", "develop", "communication", "maintain", "recruitment", "ui", "administration"], "requirements": {"degrees": ["degree"], "majors": ["computer science"], "languages": ["english", "chinese"], "language_level": ["good"], "hard_skills": ["azure", "web", "e-commerce", "server", "web projects", "servers", "problem solving", "web technologies", "small", "web development", "aws", "web & mobile", "javascript", "linux", "react", "php", "analysis", "mobile", "deployment", "programming"], "soft_skills": ["self-motivated", "troubleshooting", "problem solving", "communication", "hands-on", "motivated", "creative", "responsive"], "languages_combined": [{"language": "english", "language_level": ["good"]}, {"language": "chinese", "language_level": ["good"]}]}, "experience_required": {"duration": ["0 years"], "field": ["programming", "administration"]}}, {"job_id": "100003009053653", "location_code": "hk", "company": "International Transport Information Systems Limited", "job_title": "Analyst Programmer / Programmer", "description": "CK Hutchison, head office of a diversified group of companies with over 18,000 employees in Hong Kong and an additional 279,300 employees worldwide, invites high calibre and self-motivated individuals to join our organisation.\n\n\nThe Group Information Services Department, located in Hunghom, strives to serve the system needs of Head Office and is responsible for coordinating the information technology related services within the CK Hutchison Group.\u00a0\nResponsibilities:\n\nPlay key role in system development life cycle from requirement study, system analysis and design, program development, testing, implementation to maintenance and support to internal Group companies and end-users\nParticipate or manage implementation or upgrade cloud application projects\nDepending on the applicant\u2019s background, s/he will responsible for system on Oracle E-Business Suite Financial, Human Resources, or other Oracle Cloud or on-premises application systems\nRequirements:\nUniversity graduate or equivalent in computing related disciplines\nSolid experience in Oracle E-Business Suite Applications, e.g. ERP or HRMS\nExperience in Oracle Fusion Cloud would be an advantage\nStrong technical skill on Oracle Forms & Reports, BI Publisher, RESTful API, SOAP, Linux scripting, PowerShell or VBA programming (MS Excel macros)\nKnowledge in Fusion Cloud or EPM Cloud would also be an advantage\nA team player with good interpersonal skills and \u201ccan-do\u201d attitude\nAdaptable in regards to learning and understanding new technologies\nAttentive to details and able to work on assigned tasks with minimum supervision\nProficiency in both written and spoken English and Chinese\n*Applicant with less experience will be considered as Analyst Programmer or Programmer\nSalary and benefits will commensurate with experience and competence. Please click the \u201cAPPLY NOW\u201d button and include a detailed resume with indication of expected salary.\u00a0\u00a0\nWe are an equal opportunity employer and welcome applications from all qualified candidates. Personal data collected will be treated in the strictest confidence and handled confidentially by authorised personnel for recruitment-related purposes only within the CK Hutchison Group of companies.\u00a0\nApplicants not having heard from us within six weeks of the date of application may consider their applications unsuccessful. The personal data of unsuccessful applicants will be destroyed after the recruitment exercise pursuant to the requirements of the Personal Data (Privacy) Ordinance in Hong Kong.\u00a0", "employment_types": ["Full Time"], "selling_points": [], "locations": ["Kowloon Bay"], "categories": ["Information Technology (IT)", "Software Development"], "post_time": "2022-01-17T07:17:50Z", "salary": {"currency": null, "max": null, "min": null, "period": "monthly", "term": null}, "salary_visible": false, "title_keywords": ["analyst programmer", "programmer"], "responsibilities": ["maintenance", "analysis", "implementation", "design", "testing", "application systems"], "requirements": {"degrees": ["university graduate"], "majors": ["related disciplines"], "languages": ["english", "chinese"], "language_level": ["proficiency"], "hard_skills": ["linux", "restful api", "bi", "vba", "erp", "ms excel", "powershell", "programming", "publisher", "oracle"], "soft_skills": ["attentive to details", "adaptable", "learning", "interpersonal skills", "can-do", "team player", "technical skill"], "languages_combined": [{"language": "english", "language_level": ["proficiency"]}, {"language": "chinese", "language_level": ["proficiency"]}]}, "experience_required": {"duration": [], "field": ["business"]}}, {"job_id": "100003009054494", "location_code": "hk", "company": "Open Creative Limited", "job_title": "Full Stack Web Developers", "description": "\u8077\u8cac\uff1a\n\n\n\u8ca0\u8cac\u7db2\u7ad9\u958b\u767c\u548c\u7dad\u8b77\n\u8ca0\u8cac\u7522\u54c1\u7814\u7a76\u548c\u898f\u5283\uff0c\u5305\u62ec\u9700\u6c42\u7814\u7a76\u3001\u7cfb\u7d71\u5206\u6790\u3001\u6d41\u7a0b\u63a7\u5236\u3001\u5b89\u5168\u63a7\u5236\n\u53c3\u8207\u6280\u8853\u898f\u683c\u3001\u6d41\u7a0b\u3001\u898f\u5247\u3001\u6e2c\u8a66\u6587\u6a94\u64b0\u5beb\n\u53c3\u8207\u5916\u5305\u65b9\u5c0d\u63a5\uff0c\u63a8\u9032\u6280\u8853\u5c0d\u63a5\u548c\u9032\u5ea6\u66f4\u65b0\n\n\u8981\u6c42\uff1a\n\n\n3\u5e74\u4ee5\u4e0aPHP\u958b\u767c\u7d93\u9a57\uff0c2\u5e74\u4ee5\u4e0aLaravel\u6846\u67b6\u4f7f\u7528\u7d93\u9a57\n\u638c\u63e1MySQL\u3001NoSQL,\u968a\u5217\u7b49\u77e5\u8b58\u53ca\u61c9\u7528\n\u719f\u6089\u96f2\u670d\u52d9\u7684\u76f8\u95dc\u61c9\u7528\uff08\u963f\u91cc\u96f2\u3001AWS\uff09\n\u719f\u6089HTML5\u3001CSS3\u3001JS\uff0c\u6709\u97ff\u61c9\u5f0f\u7db2\u7ad9\u6216\u79fb\u52d5\u61c9\u7528\u7a0b\u5f0f\u958b\u767c\u7d93\u9a57\n\n\u6709\u4ee5\u4e0b\u7d93\u9a57\u8005\u512a\u5148\uff1a\n\n\n\u719f\u6089Node.js, vue\nAPI\u8a2d\u8a08\u7d93\u9a57\n\u719f\u6089Linux\u7cfb\u7d71\uff0c\u719f\u6089\u4f3a\u670d\u5668\u914d\u7f6e\u3001\u512a\u5316\u3001\u5b89\u5168\n\u6709\u610f\u8005\u8acb\u9023\u540c\u5c65\u6b77\u53ca\u85aa\u91d1\u8981\u6c42\uff0c\u6309\u201dApply Now\u201d\u6309\u9215\u7533\u8acb\uff0c\u6216\u90f5\u5bc4\u81f3\u672c\u516c\u53f8\u4eba\u529b\u8cc7\u6e90\u90e8\uff0c\u5730\u5740:\u4e5d\u9f8d\u8354\u679d\u89d2\u9577\u9806\u88577\u865f \u897f\u9813\u4e2d\u5fc33305-7\u5ba4\uff0c\u4fe1\u5c01\u9762\u8acb\u8a3b\u660e\u300c\u61c9\u5fb5\u9ad8\u7d1aPHP\u958b\u767c\u4eba\u54e1\u300d\u3002", "employment_types": ["Full Time", "Permanent"], "selling_points": ["HTML5, CSS, JavaScript, React.js, Bootstrap, Linux", "Develop & support stack-based PHP & Node.js builds", "Good spoken & written English & Chinese"], "locations": ["Sheung Wan"], "categories": ["Information Technology (IT)", "Application Specialist - Software", "IT - Webmaster / SEO", "Software Development"], "post_time": "2022-01-17T09:46:43Z", "salary": {"currency": "HKD", "max": 34999, "min": 30000, "period": "monthly", "term": null}, "salary_visible": true, "title_keywords": [], "responsibilities": [], "requirements": {"degrees": [], "majors": [], "languages": [], "language_level": [], "hard_skills": [], "soft_skills": [], "languages_combined": []}, "experience_required": {"duration": [], "field": []}}, {"job_id": "100003009053157", "location_code": "hk", "company": "\u5708\u50b3\u5a92\u6709\u9650\u516c\u53f8", "job_title": "\u9ad8\u7d1aPHP\u958b\u767c\u4eba\u54e1 (Senior PHP programmer) - 5 days", "description": "Duties and responsibilities\n\nSoftware development for backend applications\nSystem architecture design\nDeployment & maintenance of applications\nPerform coding, testing and debugging in different stages\nAdopt cloud infrastructure and technologies\nConduct research and evaluate emerging software technologies\n\nRequirements\n\nDegree in Computer Science / IT or related field\nMinimum 2 years of professional experience with Software Engineering related field\nExperienced in Firebase Cloud Service\nExperienced in Node.js, Typescript, Rxjs\nKnowledge in React, Python, AWS, GraphQL is a plus\nUnderstanding of Google BigQuery is an advantage\nHands-on expertise in data analytic tools (e.g. Google Analytic / Firebase Analytic etc) development\nAble to work independently to meet project deadlines\nAble to understand business requirements and set up the required analytics and exports from those analytic tools is an advantage\nGood interpersonal, strong organization and communication skills\nEager to make things better and to take up challenges", "employment_types": ["Full Time"], "selling_points": [], "locations": ["Lai Chi Kok"], "categories": ["Information Technology (IT)", "Application Specialist - Software", "Software Development", "Network & System"], "post_time": "2022-01-17T06:09:26Z", "salary": {"currency": null, "max": null, "min": null, "period": "monthly", "term": null}, "salary_visible": false, "title_keywords": ["programmer"], "responsibilities": ["software", "maintenance", "infrastructure", "conduct research", "coding", "design", "testing", "evaluate", "architecture"], "requirements": {"degrees": ["degree"], "majors": ["it", "computer science"], "languages": [], "language_level": [], "hard_skills": ["plus", "react", "aws", "make", "typescript", "python"], "soft_skills": ["communication skills", "hands-on", "interpersonal", "work independently"], "languages_combined": []}, "experience_required": {"duration": ["minimum 2 years"], "field": ["related", "engineering"]}}, {"job_id": "100003009054716", "location_code": "hk", "company": "GOFA", "job_title": "Backend Developer (Cloud Engineer)", "description": "Programmer / Programmer Trainee (5-day work)\nIT related Certificate, Diploma, High Diploma or Science related Degree\nInterested in IT field\nNo IT experience or fresh graduate will also be considered\u00a0\nExperienced in developing web application software is a plus\nCommitted and willing to learn\nTeam-player, self-motivated\n5 days work\nWe provide on-job training\n\nWe offer competitive remuneration packages and 5-day working week. Excellent potential for promotion. Interested parties please apply by e-mail with\u00a0full resume, expected salary and date of availability.\n\nFor more information, please visit our site at www.mapwithyou.com\n\nPersonal data collected will be used for recruitment purpose only\n", "employment_types": ["Full Time"], "selling_points": ["2 years+ experience with Software Engineering", "Firebase Cloud Service", "High degree of autonomy"], "locations": ["Central"], "categories": ["Information Technology (IT)", "Application Specialist - Software", "Software Development"], "post_time": "2022-01-17T10:46:57Z", "salary": {"currency": null, "max": null, "min": null, "period": "monthly", "term": null}, "salary_visible": false, "title_keywords": ["developer", "engineer"], "responsibilities": ["developing", "software"], "requirements": {"degrees": ["high diploma", "fresh graduate", "certificate", "diploma", "degree"], "majors": ["science", "it"], "languages": [], "language_level": [], "hard_skills": ["no", "web", "plus"], "soft_skills": ["self-motivated", "team-player", "interested in", "willing to learn", "committed"], "languages_combined": []}, "experience_required": {"duration": [], "field": ["it experience"]}}, {"job_id": "100003009052430", "location_code": "hk", "company": "FEIYANG METAVRSE TECHNOLOGY LIMITED", "job_title": "Java programmer", "description": "You will be trained to be our ICT technology or management professional by rotations through a wide range of innovation and technology initiatives.\n\nYour Role\n\nWorking as a software engineer with a focus on Java / Web application projects\nWork with System Analyst / Team Leader in requirement study, system analysis and design\nUnderstand user requirement, design specification and carry out design and programming\nConduct software development based on specification\nPrepare technical / Operational documentation for reference and reporting\nTroubleshoot, debug and upgrade existing software\nDeploy and verify programs and systems\n\nTo succeed in this role\n\nBachelor degree in Computer Science, Information Technology, Software Engineering, Data Science or related disciplines\n1 year of working experience in software development in either one of the following areas,\nWeb Frontend (JavaScript, Angular, React, CSS, Springboot, HTML, etc.)\nBackend application programming (Java, PHP, JSON, RESTful or Python, etc.)\nMobile apps (Android or iOS native, hybid framework)\nRelevant internship experience would be considered as an advantage\nKnowledge or experience in Linux environment, TCP/IP networking, source code control (git, SVN) and CI/CD tools (Gradle, Maven, Jenkins, Docker) will be an advantage\nProficiency in database such as Oracle, MySQL or Postgre is a plus\nStrong business sense, good analytical skills, problem solving skills and innovative\nGood team player and able to work independently and cross-functionally in a dynamic business environment\nGood command in written and spoken English and Chinese\nCandidate with more experience will be considered as Application Developer\nFresh Graduate will also be considered\n\nAs Hong Kong\u2019s leading ICT service provider, HKT has in recent years transformed into a technology innovator and provider of smart, digital services and solutions for consumers and businesses.\n\nHKT is the first in Hong Kong to provide true 5G services, complete with applications and content to afford our customers a unique and truly differentiated experience.\n\nHKT is Hong Kong\u2019s largest broadband service provider with a territory-wide fiber network covering 88% of homes. Our services go beyond connectivity to make the daily lives of customers smarter and more convenient.\n\nFor enterprises, HKT delivers end-to-end solutions employing emerging technologies to accelerate their digital transformation, contributing to Hong Kong\u2019s development into a smart city.\n\nOur global connectivity network has 125 points of presence across 76 cities and encompasses over 60 cable systems worldwide. PCCW Global maintains regional centers in 11 countries worldwide.\n\nThe Club is HKT\u2019s loyalty program and one of the largest of its kind in Hong Kong. With more than 800 merchants as coalition and redemption partners, it offers privileges and benefits to enrich the lifestyle of members. Club Travel is a travel service for consumers and corporate customers. Club Like is an online shopping platform for customers to make purchases with Clubpoints and in cash. These represent a new digital ecosystem using data analytics to connect consumers and merchants.\n\nHKT also offers financial services such as mobile payment, smart mobile POS solutions, digital financing, and insurance. We are a member in a joint venture offering virtual bank services in Hong Kong.\n\nEmploying over 16,200 staff, HKT is headquartered in Hong Kong and maintains a presence in mainland China and other parts of the world.\n\nThe share stapled units of the HKT Trust and HKT Limited are listed on The Stock Exchange of Hong Kong Limited (SEHK: 6823).\n\nHKT Limited is a company incorporated in the Cayman Islands with limited liability.\n\nHKT is an equal opportunity employer and welcomes applications from all qualified candidates. Information provided will be treated in strict confidence and will only be used for recruitment-related purposes. Personal data provided by job applicants will be used strictly in accordance with the employer's personal data policies (www.hkt/privacy-statement), a copy of which will be provided immediately upon request.", "employment_types": ["Full Time"], "selling_points": [], "locations": ["Wan Chai"], "categories": ["Information Technology (IT)", "Software Development"], "post_time": "2022-01-17T03:00:37Z", "salary": {"currency": null, "max": null, "min": null, "period": "monthly", "term": null}, "salary_visible": false, "title_keywords": ["programmer"], "responsibilities": ["user requirement", "management", "reporting", "control", "software", "data", "analysis", "systems", "design", "troubleshoot", "database", "deploy", "documentation"], "requirements": {"degrees": ["degree", "bachelor", "fresh graduate"], "majors": ["data science", "software engineering", "information technology", "related disciplines", "computer science"], "languages": ["english", "chinese"], "language_level": ["good command"], "hard_skills": ["plus", "jenkins", "web", "focus", "java", "git", "tcp", "css", "make", "html", "analytical skills", "javascript", "dynamic", "angular", "python", "documentation", "go", "oracle", "linux", "react", "php", "analysis", "mobile", "ip", "programming", "code", "problem solving skills", "android"], "soft_skills": ["good team player", "work independently", "business sense", "unique", "analytical skills", "problem solving skills", "dynamic", "troubleshoot", "business environment", "focus", "innovative"], "languages_combined": [{"language": "english", "language_level": ["good command"]}, {"language": "chinese", "language_level": ["good command"]}]}, "experience_required": {"duration": ["1 year"], "field": ["developer", "software development"]}}, {"job_id": "100003009055152", "location_code": "hk", "company": "FunTown Hong Kong Limited", "job_title": "Technical Support Engineer (Game) (5-day work)", "description": "Job Description\nBe part of the delivery team to implement modules and applications\nWork closely with the creative design team on delivery\u00a0high-quality web application projects\nResponsible for hands-on development with Java web and server-side programming\nMaintain and provide system support of the existing in-house systems\nWork as a coordinator with teams and users\n\n\u00a0Requirement\n\nproficiency in\u00a0Java 8+\u00a0and Declarative/Functional Programming\nExperienced in\u00a0Spring Framework, Hibernate or OGM Tools\nExperience in Web, JS, Node.js,\u00a0Kotlin, Golang would be advantage\nExperience in MQ, Document / Graph DB would be advantage\nExperience in Public/Private Cloud, Containerization and Scalable Architecture would be advantage\nExcellent communication and interpersonal skills\nDemonstrate a positive and can-do attitude, also a strong team player\nPassionate to new technologies\nCandidate with more experience will be considered as\u00a0Senior Software Engineer\nFresh Graduate\u00a0are also Welcome!", "employment_types": ["Full Time"], "selling_points": [], "locations": ["Mong Kok"], "categories": ["Information Technology (IT)", "Software Development"], "post_time": "2022-01-18T01:29:24Z", "salary": {"currency": "HKD", "max": 29999, "min": 20000, "period": "monthly", "term": null}, "salary_visible": true, "title_keywords": ["technical support engineer"], "responsibilities": ["systems", "teams", "quality", "design", "maintain"], "requirements": {"degrees": ["fresh graduate"], "majors": [], "languages": [], "language_level": [], "hard_skills": ["java", "hibernate", "web", "spring", "programming", "kotlin"], "soft_skills": ["passionate", "can-do attitude", "communication and interpersonal skills", "team player", "positive"], "languages_combined": []}, "experience_required": {"duration": [], "field": []}}, {"job_id": "100003009055272", "location_code": "hk", "company": "Infocast Limited", "job_title": "Analyst Programmer", "description": "Responsibilities\n\nResponsible for financial application development and enhancement (Visual Studio .Net and Oracle Database)\nPerform UAT to ensure deliverables and meet requirements\nAssist in various project implementation\nWork closely in team-environment and meet project schedules\n\nRequirements\n\nDegree in Computer Science or related disciplines\nAt least 2 years experience in software development is preferred\nKnowledge in Visual Studio.Net / Javawill be an advantage\nKnowledge in Visual Basic / C++ will be an advantage\nWorking experience in RDBMS such as Oracle\nExperience in developing equities and financial software will be a definite advantage\nGood communication skills in both English and Chinese\nGood team player\nAble to work under pressure and within tight schedule\n\nWe Offer\n\n5-day work week\nDiscretionary Bonus\nMedical Insurance\nVariety of Leaves (e.g. Birthday, Marriage Leave etc.)\nVariety of company activities and training\n\nTo Apply:\nWe offer attractive package including medical insurance scheme and good career prospects to the right candidate. Interested parties please send your application via \"Apply Now\" button.\n\nFor more Company information, please feel free to visit our website at www.infocast.com.hk.\n\nAll information received will be kept in strict confidential and only for employment-related purposes.", "employment_types": ["Full Time", "Permanent"], "selling_points": ["Financial application development and enhancement", "Perform UAT", "2yrs exp. in software development"], "locations": ["Hung Hom"], "categories": ["Information Technology (IT)", "Application Specialist - Software", "Software Development"], "post_time": "2022-01-18T01:59:47Z", "salary": {"currency": null, "max": null, "min": null, "period": "monthly", "term": null}, "salary_visible": false, "title_keywords": ["analyst programmer"], "responsibilities": ["uat", "schedules", "implementation", "database", "visual", "application development"], "requirements": {"degrees": ["degree"], "majors": ["related disciplines", "computer science"], "languages": ["english", "chinese"], "language_level": ["good"], "hard_skills": ["visual basic", "c++", "oracle"], "soft_skills": ["communication skills", "good team player", "work under pressure"], "languages_combined": [{"language": "english", "language_level": ["good"]}, {"language": "chinese", "language_level": ["good"]}]}, "experience_required": {"duration": ["at least 2 years"], "field": ["developing", "financial", "software development"]}}, {"job_id": "100003009053943", "location_code": "hk", "company": "Nnenu Limited", "job_title": "AWS Solution Architect / DevOps", "description": "About us\n\nWe are a small start-up looking for founding engineers to grow with us.\nWe are youngfounders with technical, marketing and capital management backgrounds.\nOur own flagship product is a user-generated Augmented Reality content app, currently under development.\u00a0Other projects include a recycling app,\u00a0facial authentication system, catalogue system,\u00a0etc.\n\nOther Job Highlights\n\nWork in Wan Chai or remotely from home\u00a0\nNo fixed working hours, performance based daily work flow\u00a0\nSmall, close team\u00a0\nYou can contribute ideas in any areas and shape the future development of company\nGrow along side the company\u00a0\nExcellent salary which is flexible based on experience\u00a0\nStock options after 12 months\u00a0\n\nResponsibilities\n\nTransform business needs into high quality cloud architecture to support front-end application development\nCloud infrastructure provisioning, maintenance and cost monitoring\nDesign, implement and build APIs and microservices in a hybrid Cloud environment\nDesign, develop and review tools for cloud operations and maintenance\u00a0\nDesign and maintain CI/CD pipelines for cloud application deployment\u00a0\nProvide immediate assistance on incidents reported. Troubleshoot the root cause and provide solutions\nWrite and maintain deployment and operation documentation\u00a0\nContribute your great ideas to shape and form the team\u2019s development directions\n\nRequirements\n\nHigh diploma, degree in Computer Science or related disciplines\u00a0\nExperience with Private and/or Public Cloud environments like AWS\u00a0\nProficiency in Node.js\u00a0\nKnowledgeable in database design would be an advantage\u00a0\nProficiency in DevOps and CI/CD would be an advantage\u00a0\nProficiency in DynamoDB or Cognito or IAM or Lambda or API Gateway would be an advantage\nProficiency in Serverless Architecture would be an advantage\u00a0\nProficiency in Neo4j would be an advantage\u00a0\nPassionate in multicultural trends is a plus\u00a0\nCandidates with less experience but interested in becoming a DevOps Engineer or Solution Architect are also welcome\n\nWe offer a competitive remuneration package and fringe benefits to the right candidates. If you are interested please send us your\u00a0motivation,\u00a0expected salary\u00a0&\u00a0available date\u00a0together with your detailed resume\u00a0and\u00a0portfolio\u00a0(if any) by clicking \"Apply Now\".\n\nWe are an equal opportunity employer and welcome applications from all qualified candidates. All information provided will be treated in strict confidence and used for recruitment purposes only.", "employment_types": ["Full Time", "Permanent"], "selling_points": [], "locations": ["Wan Chai"], "categories": ["Information Technology (IT)", "Software Development"], "post_time": "2022-01-17T07:48:58Z", "salary": {"currency": "HKD", "max": 69999, "min": 25000, "period": "monthly", "term": null}, "salary_visible": true, "title_keywords": [], "responsibilities": ["cost", "ideas", "maintenance", "operations", "infrastructure", "quality", "monitoring", "design", "develop", "review", "provide solutions", "maintain", "troubleshoot", "documentation", "application development", "architecture"], "requirements": {"degrees": ["high diploma", "degree"], "majors": ["related disciplines", "computer science"], "languages": [], "language_level": [], "hard_skills": ["devops", "plus", "aws"], "soft_skills": ["passionate", "interested in"], "languages_combined": []}, "experience_required": {"duration": [], "field": ["devops", "solution architect"]}}, {"job_id": "100003009055031", "location_code": "hk", "company": "FCC Analytics Limited", "job_title": "Software Engineer / Software Developer / Full Stack Developer", "description": "We are looking for a Software Engineer / Software Developer / Full Stack Developer to develop software for the financial industry. The ideal candidate will be involved in a full application development cycle of an enterprise-level application.\n\n\u00a0Responsibilities\n\nResponsible for software development, ensure delivery quality, perform unit test and system integration test.\u00a0\nDevelop and support software including applications, database integration, interfaces, ETL processes.\nCompile documentation of specifications on technical and functional design.\nFull SDLC involvement.\nJob Requirements\n\n\u00a0Higher Diploma/Degree Holder of Computer Science or other related disciplines\nExperience in Java, Java Script, Python, SQL, JSON\nExperience in DevOps, JS Framework (e.g. Angular), Scala, Golang, Cloud Platform, Kubernetes, Shell Script will be an advantage\nGood team player, positive attitude, able to work independently\nGood command of written and spoken English and Cantonese\nLess experienced candidates will be considered for a junior position", "employment_types": ["Full Time"], "selling_points": [], "locations": ["Kwai Fong"], "categories": ["Information Technology (IT)", "Application Specialist - Software", "Software Development"], "post_time": "2022-01-17T23:54:26Z", "salary": {"currency": null, "max": null, "min": null, "period": "monthly", "term": null}, "salary_visible": false, "title_keywords": ["software engineer", "developer"], "responsibilities": ["software", "quality", "design", "develop", "specifications", "database", "documentation"], "requirements": {"degrees": ["diploma", "degree holder"], "majors": ["related disciplines", "computer science"], "languages": ["cantonese", "english"], "language_level": ["good command"], "hard_skills": ["java script", "java", "devops", "sql", "scala", "angular", "python"], "soft_skills": ["positive attitude", "good team player", "work independently"], "languages_combined": [{"language": "cantonese", "language_level": ["good command"]}, {"language": "english", "language_level": ["good command"]}]}, "experience_required": {"duration": [], "field": ["sql", "devops"]}}, {"job_id": "100003009052817", "location_code": "hk", "company": "ELM Computer Technologies Ltd", "job_title": "Analyst Programmer", "description": "Responsibilities:\n\nInvolved in the entire system development life cycle (SDLC), including collection of user requirements, system analysis and design and system development and testing\nPerforming coding and system test\nPrepare technical documentation and provide user training\n\n\u00a0Requirements:\u00a0\n\nDiploma or above in IT related disciplines\nMinimum 2 years relevant working experience\nProficiency in Java and RDBMS\nWith knowledge in development frameworks, such as Spring Boot, Angular and Hibernate and system integration\nSelf-motivated, a team player, hardworking and able to work independently\nFresh graduate and candidate with less experience will be considered as Programmer", "employment_types": ["Temporary", "Contract"], "selling_points": ["Minimum 2 years relevant working experience", "Proficiency in Java and RDBMS", "Less experience will be considered as Programmer"], "locations": ["Shatin Area"], "categories": ["Information Technology (IT)", "Application Specialist - Software", "Software Development", "Technical Writing"], "post_time": "2022-01-17T04:09:39Z", "salary": {"currency": null, "max": null, "min": null, "period": "monthly", "term": null}, "salary_visible": false, "title_keywords": ["analyst programmer"], "responsibilities": ["analysis", "coding", "design", "testing", "documentation"], "requirements": {"degrees": ["fresh graduate", "diploma or above"], "majors": ["related disciplines", "it"], "languages": [], "language_level": [], "hard_skills": ["java", "hibernate", "angular", "spring", "integration"], "soft_skills": ["self-motivated", "team player", "work independently", "hardworking"], "languages_combined": []}, "experience_required": {"duration": ["minimum 2 years"], "field": ["relevant working experience"]}}, {"job_id": "100003009053718", "location_code": "hk", "company": "Insight Information Technology Limited", "job_title": "Analyst Programmer (Java)", "description": "Responsibilities:\n\nArchitect and build website, web applications and/or prototypes.\nPrepare system documentations.\n\nRequirements:\n\nAt least 2 years working experience\nExperience in development on AWS/GCP/Azure/other Cloud computing platform. (experience in Google API is a plus)\nExperience in Any Backend Development(e.g. Go, Node.js, Java)\nExperience in Java and Web API development (Java EE, Spring, Hibernate) is a plus\nExperience in SQL and NoSQL Database\nExperience in automation tools and frameworks (e.g. git, Jenkins, JMeter, ApacheBench)\nCollaborate with team members to improve the company\u2019s engineering tools, systems and procedures, and data security.\nConduct systems tests for security, performance, and availability.\nDevelop and maintain design and troubleshooting documentation.", "employment_types": ["Full Time"], "selling_points": ["Java/Spring boot/SQL database", "Perm/ in-house", "2-4 years\u2019 relevant working experience"], "locations": ["Tsim Sha Tsui"], "categories": ["Information Technology (IT)", "Software Development"], "post_time": "2022-01-17T07:24:11Z", "salary": {"currency": null, "max": null, "min": null, "period": "monthly", "term": null}, "salary_visible": false, "title_keywords": ["analyst programmer"], "responsibilities": ["website"], "requirements": {"degrees": [], "majors": [], "languages": [], "language_level": [], "hard_skills": ["java", "plus", "azure", "hibernate", "git", "jenkins", "aws", "sql", "web api", "spring", "documentation", "go"], "soft_skills": ["troubleshooting"], "languages_combined": []}, "experience_required": {"duration": ["at least 2 years"], "field": ["sql", "development", "database"]}}, {"job_id": "100003009054919", "location_code": "hk", "company": "Oslo Environmental Innovation Limited", "job_title": "Programmer (Web and Mobile Application)", "description": "We are undergoing Digital Transformation and is actively looking for talented people to join our team which is expanding rapidly. The successful candidate will be exposed to a wide range of innovative technology initiatives and chance to work with talents and industry experts worldwide.\n\nWhat you\u2019ll get from us\n\nExposure to technology including but not limited to:\nHTML5 & JavaScript or TypeScript\nC# / Java / Node.js\nWeb APIs development\u00a0\nAny RDBMS (e.g. T-SQL, MySQL)\nCurrent Version Control Systems (Git)\nAngular / React / Vue\nCI/CD\nNoSQL database\nCloud technologies and platforms\nNice, reasonable and open-minded teammates\nWork-life balance team culture\nLarge corporation working experience\nLeverages corporate resources, you\u2019ll have the chance to experience numerous current architecture (e.g. Microservices, Micro-Frontend) / platforms (e.g. Salesforce) while we\u2019re undergoing Digital Transformation\nGain experience and knowledge in large-scale projects with a wide range of systems and solutions, from internal systems to public-facing systems\n\nYour Role\n\nWork as a software programmer that mainly focuses on web apps, both front-ends and back-ends included\nWork with System Analyst / Team Leader in requirement study, system analysis and design\nAdapt to new technologies or languages when required\nUnderstand user requirements, design specifications etc. and carry out programming accordingly\n\nTo succeed in this role\n\nBachelor degree in Computer Science, Information Technology, Software Engineering or related disciplines\n1-4 years of hands-on software development experience\nEagerness to learn and adapt to new technologies / concepts is crucial\nGood analytical and problem-solving skills, critical thinking is crucial\nWork well with a team, able to collaborate nicely and proactively\nQuality-oriented\nProficient in both written and English, Chinese and Cantonese\n\nCandidate with\u00a0less experience will be considered as a\u00a0Applciation Developer\n\nAs Hong Kong\u2019s leading ICT service provider, HKT has in recent years transformed into a technology innovator and provider of smart, digital services and solutions for consumers and businesses.\n\nHKT is the first in Hong Kong to provide true 5G services, complete with applications and content to afford our customers a unique and truly differentiated experience.\n\nHKT is Hong Kong\u2019s largest broadband service provider with a territory-wide fiber network covering 88% of homes. Our services go beyond connectivity to make the daily lives of customers smarter and more convenient.\n\nFor enterprises, HKT delivers end-to-end solutions employing emerging technologies to accelerate their digital transformation, contributing to Hong Kong\u2019s development into a smart city.\n\nOur global connectivity network has 125 points of presence across 76 cities and encompasses over 60 cable systems worldwide. PCCW Global maintains regional centers in 11 countries worldwide.\n\nThe Club is HKT\u2019s loyalty program and one of the largest of its kind in Hong Kong. With more than 800 merchants as coalition and redemption partners, it offers privileges and benefits to enrich the lifestyle of members. Club Travel is a travel service for consumers and corporate customers. Club Like is an online shopping platform for customers to make purchases with Clubpoints and in cash. These represent a new digital ecosystem using data analytics to connect consumers and merchants.\n\nHKT also offers financial services such as mobile payment, smart mobile POS solutions, digital financing, and insurance. We are a member in a joint venture offering virtual bank services in Hong Kong.\n\nEmploying over 16,200 staff, HKT is headquartered in Hong Kong and maintains a presence in mainland China and other parts of the world.\n\nThe share stapled units of the HKT Trust and HKT Limited are listed on The Stock Exchange of Hong Kong Limited (SEHK: 6823).\n\nHKT Limited is a company incorporated in the Cayman Islands with limited liability.\n\nHKT is an equal opportunity employer and welcomes applications from all qualified candidates. Information provided will be treated in strict confidence and will only be used for recruitment-related purposes. Personal data provided by job applicants will be used strictly in accordance with the employer's personal data policies (www.hkt/privacy-statement), a copy of which will be provided immediately upon request.", "employment_types": ["Full Time", "Part Time", "Permanent", "Internship"], "selling_points": ["5-day work", "Support digital business", "Fresh grad also welcome"], "locations": ["Tuen Mun Area"], "categories": ["Information Technology (IT)", "Application Specialist - Software", "Software Development", "UI/UX Designer"], "post_time": "2022-01-17T13:51:39Z", "salary": {"currency": null, "max": null, "min": null, "period": "monthly", "term": null}, "salary_visible": false, "title_keywords": ["programmer"], "responsibilities": ["collaborate", "control", "software", "analysis", "systems", "quality", "design", "design specifications", "database", "architecture", "internal systems"], "requirements": {"degrees": ["degree", "bachelor"], "majors": ["related disciplines", "software engineering", "computer science", "information technology"], "languages": ["cantonese", "english", "chinese"], "language_level": ["proficient"], "hard_skills": ["java", "git", "salesforce", "web", "react", "nice", "t-sql", "web apps", "microservices", "analysis", "make", "typescript", "javascript", "angular", "programming", "problem-solving skills", "go", "c#"], "soft_skills": ["open-minded", "unique", "hands-on", "problem-solving skills", "innovative"], "languages_combined": [{"language": "cantonese", "language_level": ["proficient"]}, {"language": "english", "language_level": ["proficient"]}, {"language": "chinese", "language_level": ["proficient"]}]}, "experience_required": {"duration": ["1-4 years"], "field": ["developer", "software development"]}}, {"job_id": "100003009054007", "location_code": "hk", "company": "Impacts Technology Limited", "job_title": "Web / Mobile Developer", "description": "Job Description and Responsibilities\n\nDesign and Develop corporate training platforms for corporate in Hong Kong;\nPerform AI-related research for applying AI-related functions to e-learning systems.\u00a0\n\n\u00a0Job Openings\n\n2+\n\n\u00a0Job Requirements\n\nAt least 1 year of working experience (Fresh graduate will also be considered)\nExperience in e-learning platform development is a plus\nFamiliar with at least one of the following areas\nWeb Programming (HTML, CSS, JavaScript, PHP, MySQL) + Laravel (PHP Framework)\nSystem administration or Database administration (e.g. linux-based server, cloud based servers, MySQL administration, etc.)\niOS Programming (Objective-C / Swift)\nAndroid Programming (Java)\nFull-time working mode (5-day work)\n\n\u00a0Monthly Salary & Bonus:\n\nSalary will be offered based on experience, skills and education level\nRanged from 18,000 to 28,000 per month\nPerformance-based bonus will be considered at the end of the year\n\n\u00a0Team's Focus:\n\nCorporate Training Platform Development\nMobile Learning Platforms (Apps & Web)\nSoftware Product Development\n\n\u00a0Products and Services Highlight\n\niTrain - Self-learning corporate training platform\n\nA self-learning corporate training platform developed for MNC. Over 100,000 users have been enrolled to our system.", "employment_types": ["Full Time"], "selling_points": [], "locations": ["Pok Fu Lam"], "categories": ["Engineering", "Others", "Information Technology (IT)", "IT Management", "Software Development"], "post_time": "2022-01-17T16:21:02Z", "salary": {"currency": null, "max": null, "min": null, "period": "monthly", "term": null}, "salary_visible": false, "title_keywords": ["developer"], "responsibilities": ["systems", "design and develop"], "requirements": {"degrees": ["fresh graduate"], "majors": [], "languages": [], "language_level": [], "hard_skills": ["linux", "plus", "java", "servers", "web", "php", "swift", "html", "objective-c", "mobile", "javascript", "programming", "server", "css", "focus", "android"], "soft_skills": ["focus", "learning"], "languages_combined": []}, "experience_required": {"duration": ["at least 1 year"], "field": ["development", "education"]}}, {"job_id": "100003009052973", "location_code": "hk", "company": "mapwithyou", "job_title": "Programmer / Programmer Trainee (5-day work)", "description": "Programmer / Programmer Trainee (5-day work)\nIT related Certificate, Diploma, High Diploma or Science related Degree\nInterested in IT field\nNo IT experience or fresh graduate will also be considered\u00a0\nExperienced in developing web application software is a plus\nCommitted and willing to learn\nTeam-player, self-motivated\n5 days work\nWe provide on-job training\n\nWe offer competitive remuneration packages and 5-day working week. Excellent potential for promotion. Interested parties please apply by e-mail with\u00a0full resume, expected salary and date of availability.\n\nFor more information, please visit our site at www.mapwithyou.com\n\nPersonal data collected will be used for recruitment purpose only\n", "employment_types": ["Full Time", "Permanent"], "selling_points": [], "locations": ["Tsuen Wan Area"], "categories": ["Information Technology (IT)", "Application Specialist - Software", "Software Development", "Others"], "post_time": "2022-01-17T04:48:08Z", "salary": {"currency": null, "max": null, "min": null, "period": "monthly", "term": null}, "salary_visible": false, "title_keywords": ["programmer", "trainee"], "responsibilities": ["developing", "software"], "requirements": {"degrees": ["high diploma", "fresh graduate", "certificate", "diploma", "degree"], "majors": ["science", "it"], "languages": [], "language_level": [], "hard_skills": ["no", "web", "plus"], "soft_skills": ["self-motivated", "team-player", "interested in", "willing to learn", "committed"], "languages_combined": []}, "experience_required": {"duration": [], "field": ["it experience"]}}, {"job_id": "100003009055987", "location_code": "hk", "company": "HKT", "job_title": "Application Developer", "description": "You will be trained to be our ICT technology or management professional by rotations through a wide range of innovation and technology initiatives.\n\nYour Role\n\nWorking as a software engineer with a focus on Java / Web application projects\nWork with System Analyst / Team Leader in requirement study, system analysis and design\nUnderstand user requirement, design specification and carry out design and programming\nConduct software development based on specification\nPrepare technical / Operational documentation for reference and reporting\nTroubleshoot, debug and upgrade existing software\nDeploy and verify programs and systems\n\nTo succeed in this role\n\nBachelor degree in Computer Science, Information Technology, Software Engineering, Data Science or related disciplines\n1 year of working experience in software development in either one of the following areas,\nWeb Frontend (JavaScript, Angular, React, CSS, Springboot, HTML, etc.)\nBackend application programming (Java, PHP, JSON, RESTful or Python, etc.)\nMobile apps (Android or iOS native, hybid framework)\nRelevant internship experience would be considered as an advantage\nKnowledge or experience in Linux environment, TCP/IP networking, source code control (git, SVN) and CI/CD tools (Gradle, Maven, Jenkins, Docker) will be an advantage\nProficiency in database such as Oracle, MySQL or Postgre is a plus\nStrong business sense, good analytical skills, problem solving skills and innovative\nGood team player and able to work independently and cross-functionally in a dynamic business environment\nGood command in written and spoken English and Chinese\nCandidate with more experience will be considered as Application Developer\nFresh Graduate will also be considered\n\nAs Hong Kong\u2019s leading ICT service provider, HKT has in recent years transformed into a technology innovator and provider of smart, digital services and solutions for consumers and businesses.\n\nHKT is the first in Hong Kong to provide true 5G services, complete with applications and content to afford our customers a unique and truly differentiated experience.\n\nHKT is Hong Kong\u2019s largest broadband service provider with a territory-wide fiber network covering 88% of homes. Our services go beyond connectivity to make the daily lives of customers smarter and more convenient.\n\nFor enterprises, HKT delivers end-to-end solutions employing emerging technologies to accelerate their digital transformation, contributing to Hong Kong\u2019s development into a smart city.\n\nOur global connectivity network has 125 points of presence across 76 cities and encompasses over 60 cable systems worldwide. PCCW Global maintains regional centers in 11 countries worldwide.\n\nThe Club is HKT\u2019s loyalty program and one of the largest of its kind in Hong Kong. With more than 800 merchants as coalition and redemption partners, it offers privileges and benefits to enrich the lifestyle of members. Club Travel is a travel service for consumers and corporate customers. Club Like is an online shopping platform for customers to make purchases with Clubpoints and in cash. These represent a new digital ecosystem using data analytics to connect consumers and merchants.\n\nHKT also offers financial services such as mobile payment, smart mobile POS solutions, digital financing, and insurance. We are a member in a joint venture offering virtual bank services in Hong Kong.\n\nEmploying over 16,200 staff, HKT is headquartered in Hong Kong and maintains a presence in mainland China and other parts of the world.\n\nThe share stapled units of the HKT Trust and HKT Limited are listed on The Stock Exchange of Hong Kong Limited (SEHK: 6823).\n\nHKT Limited is a company incorporated in the Cayman Islands with limited liability.\n\nHKT is an equal opportunity employer and welcomes applications from all qualified candidates. Information provided will be treated in strict confidence and will only be used for recruitment-related purposes. Personal data provided by job applicants will be used strictly in accordance with the employer's personal data policies (www.hkt/privacy-statement), a copy of which will be provided immediately upon request.", "employment_types": ["Full Time"], "selling_points": [], "locations": ["Wan Chai"], "categories": ["Information Technology (IT)", "Application Specialist - Software", "Software Development"], "post_time": "2022-01-18T03:09:49Z", "salary": {"currency": null, "max": null, "min": null, "period": "monthly", "term": null}, "salary_visible": false, "title_keywords": ["developer"], "responsibilities": ["user requirement", "management", "reporting", "control", "software", "data", "analysis", "systems", "design", "troubleshoot", "database", "deploy", "documentation"], "requirements": {"degrees": ["degree", "bachelor", "fresh graduate"], "majors": ["data science", "software engineering", "information technology", "related disciplines", "computer science"], "languages": ["english", "chinese"], "language_level": ["good command"], "hard_skills": ["plus", "jenkins", "web", "focus", "java", "git", "tcp", "css", "make", "html", "analytical skills", "javascript", "dynamic", "angular", "python", "documentation", "go", "oracle", "linux", "react", "php", "analysis", "mobile", "ip", "programming", "code", "problem solving skills", "android"], "soft_skills": ["good team player", "work independently", "business sense", "unique", "analytical skills", "problem solving skills", "dynamic", "troubleshoot", "business environment", "focus", "innovative"], "languages_combined": [{"language": "english", "language_level": ["good command"]}, {"language": "chinese", "language_level": ["good command"]}]}, "experience_required": {"duration": ["1 year"], "field": ["developer", "software development"]}}, {"job_id": "100003009056056", "location_code": "hk", "company": "HKT Consumer Group", "job_title": "Programmer", "description": "Your Role:\n\nTo participate in requirement gathering, design and development covering the entire System Development Life Cycle (SDLC)\nTo provide UAT and production support on the systems\nTo perform bug-fixing, system testing and troubleshooting on the systems\nTo provide technical support to end-users\n\nTo succeed in this role:\n\nHigher Diploma or above in Computer Science or equivalent\nRelevant experience in software engineering and software design\nKnowledge in using C#, Visual Basic, CSS and Javascript and relevant web programming languages\nExperience in Microsoft SQL and ASP/ASP.Net\nGood problem solving and communication skills\nStrong analytical skills, self-motivated and able to work under pressure\nCandidates with more experience will be considered as Analyst Programmer", "employment_types": ["Full Time"], "selling_points": [], "locations": ["Lai Chi Kok"], "categories": ["Information Technology (IT)", "Application Specialist - Software", "Software Development", "Network & System"], "post_time": "2022-01-18T03:13:54Z", "salary": {"currency": null, "max": null, "min": null, "period": "monthly", "term": null}, "salary_visible": false, "title_keywords": ["programmer"], "responsibilities": ["uat", "software", "technical support", "systems", "troubleshooting", "design", "testing", "communication", "visual", "work under pressure"], "requirements": {"degrees": ["higher diploma or above"], "majors": ["computer science"], "languages": [], "language_level": [], "hard_skills": ["web", "analytical skills", "sql", "problem solving", "sdlc", "javascript", "visual basic", "programming", "css", "c#"], "soft_skills": ["communication skills", "self-motivated", "troubleshooting", "analytical skills", "problem solving", "work under pressure"], "languages_combined": []}, "experience_required": {"duration": [], "field": ["sql", "software design", "relevant experience", "engineering"]}}, {"job_id": "100003009056163", "location_code": "hk", "company": "Osmium Consulting Group Limited", "job_title": "Software Engineer ( Java Spring ) - $20K - $45K", "description": "Job Description\nBe part of the delivery team to implement modules and applications\nWork closely with the creative design team on delivery\u00a0high-quality web application projects\nResponsible for hands-on development with Java web and server-side programming\nMaintain and provide system support of the existing in-house systems\nWork as a coordinator with teams and users\n\n\u00a0Requirement\n\nproficiency in\u00a0Java 8+\u00a0and Declarative/Functional Programming\nExperienced in\u00a0Spring Framework, Hibernate or OGM Tools\nExperience in Web, JS, Node.js,\u00a0Kotlin, Golang would be advantage\nExperience in MQ, Document / Graph DB would be advantage\nExperience in Public/Private Cloud, Containerization and Scalable Architecture would be advantage\nExcellent communication and interpersonal skills\nDemonstrate a positive and can-do attitude, also a strong team player\nPassionate to new technologies\nCandidate with more experience will be considered as\u00a0Senior Software Engineer\nFresh Graduate\u00a0are also Welcome!", "employment_types": ["Full Time", "Permanent"], "selling_points": ["Java Developers ( Back-end )", "Fresh Graduates are Welcome", "In-house Development, No OT!"], "locations": ["Yau Tsim Mong Area"], "categories": ["Information Technology (IT)", "Application Specialist - Software", "Software Development", "Network & System"], "post_time": "2022-01-18T03:27:25Z", "salary": {"currency": "HKD", "max": 44999, "min": 25000, "period": "monthly", "term": null}, "salary_visible": true, "title_keywords": ["software engineer"], "responsibilities": ["systems", "teams", "quality", "design", "maintain"], "requirements": {"degrees": ["fresh graduate"], "majors": [], "languages": [], "language_level": [], "hard_skills": ["java", "hibernate", "web", "spring", "programming", "kotlin"], "soft_skills": ["passionate", "can-do attitude", "communication and interpersonal skills", "team player", "positive"], "languages_combined": []}, "experience_required": {"duration": [], "field": []}}, {"job_id": "100003009054707", "location_code": "hk", "company": "Tab Next Limited", "job_title": "Web Developer (Junior/ Fresh Graduate)", "description": "To apply for the job:\n\nPlease fill-in the pre-interview form:\u00a0http://hr.tabnext.asia/developer\nAnd click \"apply\" in jobsdb to send us latest CV\u00a0\n\nJob descriptions:\n\nDevelop web applications for professional healthcare sector\nOur clients are all large healthcare service providers\nWork closely with system analyst, account manager and project manager\nBe patient, logical, and attention to details\nAccountability, be a good learner and team player\nChinese or Local, with Fluent Cantonese speaker only\n\nRequirement:\u00a0\n\nTertiary education (Ive or above) in Computer Science or related discipline or relevant working experience\nSkill set: PHP + MySQL or ASP.NET + MS SQL\nExperience in programming framework is a plus\nExperience in healthcare sector is a plus\nGood communication in both verbal and written Chinese and English\nCandidate with less experience shall be considered as junior web programmer\nChinese or Local, with Fluent Cantonese speaker only\nFresh graduates are also welcomed\n\nBenefits\n\n5-day(s) work week\nFlexible working hour\nWork from home even under normal circumstance\nCareer coaching and development\nPerformance bonus\nComfortable studio working environment\nFree games, free drinks and free snacks\n\nFor better understanding of our company, you can visit our Website.\nhttps://www.tabnext.asia\n\nTo apply for the job:\n\nPlease fill-in the pre-interview form: http://hr.tabnext.asia/developer\nAnd click \"apply\" in jobsdb to send us latest CV\u00a0\n\nWe are not interested in any recruitment service from agency. If you are NOT applicant, please stay out of this page.", "employment_types": ["Full Time", "Part Time", "Contract"], "selling_points": ["IT programming for professional medical area", "Healthcare private sector; Worldwide career path", "Lai Chi Kok office or Tai Wai office"], "locations": ["Lai Chi Kok"], "categories": ["Information Technology (IT)", "Software Development"], "post_time": "2022-01-17T10:39:28Z", "salary": {"currency": null, "max": null, "min": null, "period": "monthly", "term": null}, "salary_visible": false, "title_keywords": ["developer", "junior"], "responsibilities": ["hr", "develop"], "requirements": {"degrees": [], "majors": [], "languages": ["cantonese", "english", "chinese"], "language_level": ["fluent", "good"], "hard_skills": ["plus", "web", "php", "programming", "ms sql"], "soft_skills": ["communication"], "languages_combined": [{"language": "cantonese", "language_level": ["fluent", "fluent"]}, {"language": "english", "language_level": ["good"]}, {"language": "chinese", "language_level": ["fluent", "fluent", "good"]}]}, "experience_required": {"duration": [], "field": ["healthcare", "related", "relevant working experience", "education", "programming"]}}, {"job_id": "100003009055080", "location_code": "hk", "company": "Newtech Management Services Ltd", "job_title": "System Programmer / Assistant Programmer", "description": "Responsibilities:\n\nDevelop BMS / DCIM systems used by Data Centers, Carriers, ISP or MNC corporations.\nParticipate in full software development life cycle, from design, coding, testing to implementation.\nAssist system analysts on requirement analysis, prototyping, coding and testing.\nProvide quality software development.\nPrepare technical documentation and user manuals.\nParticipate in new projects and adopt new tools and technologies.\nProvide on-site technical assistance in project / maintenance works if necessary.\u00a0 \u00a0\n\n\u00a0Requirements:\n\n\nHigher Diploma / Certificate or above in Computer Science, Information Technology, Multimedia design or other related disciplines.\n3 years of software development experience.\nAbility to learn new coding languages and technologies quickly.\nExperience in HTML programming framework (e.g. Vue.js, Reat or Angular), Nodejs, PostgreSQL/MSSQL.\nCandidates with solid experience in Linux and Windows OS operation and configuration will be an advantage.\nFresh graduate or candidate with less experience will be considered as Assistant Programmer.\nAn attractive remuneration package and fringe benefits will be offered to the right candidate. Interested parties, we appreciate it if you\u00a0must send your resume with a cover letter, stating current and expected salary\u00a0to the Human Resources Department\u00a0by\u00a0clicking\u00a0Apply Now.\n\nFor more information, please visit the corporate website at\u00a0www.newtechapac.com\u00a0\n\nAll information collected will be kept strictly confidential and for recruitment purpose only.", "employment_types": ["Full Time", "Permanent"], "selling_points": [], "locations": ["Kowloon Bay"], "categories": ["Information Technology (IT)", "Application Specialist - Software", "Software Development", "Others"], "post_time": "2022-01-18T01:11:09Z", "salary": {"currency": null, "max": null, "min": null, "period": "monthly", "term": null}, "salary_visible": false, "title_keywords": ["programmer", "assistant"], "responsibilities": ["software", "maintenance", "data", "analysis", "systems", "quality", "implementation", "design", "develop", "coding", "testing", "documentation", "technical assistance"], "requirements": {"degrees": ["certificate", "diploma", "fresh graduate"], "majors": ["multimedia design", "related disciplines", "computer science", "information technology"], "languages": [], "language_level": [], "hard_skills": ["linux", "html", "os", "multimedia", "programming", "angular", "mssql"], "soft_skills": [], "languages_combined": []}, "experience_required": {"duration": ["3 years"], "field": ["operation", "programming", "software development"]}}, {"job_id": "100003009051207", "location_code": "hk", "company": "\u5411\u85cd\u5929\u79d1\u6280\u6709\u9650\u516c\u53f8", "job_title": "Senior Frontend Software Developer (Flutter)", "description": "We are looking for a senior frontend software developer preferably with 2 \u2013 4 years of experience to participate in the development of our software platform, integrating data and user centric design to achieve sustainability performances for our users.\n\nKey to the role successes is having the technical software knowledge, teamwork and programming skills. You will be part of the software team and be fully supported by the rest of the Blue Sky team to develop our product.\n\n\u00a0Responsibilities:\n\nDevelop frontend applications for the web and the mobile platform\nProduct owner of the frontend applications\nProvide guidance to junior team members\nCoordinate with the business development team\u00a0\n\nRequirements:\n\nBachelor or above in Computer Science, Computer Engineering or related discipline\nExperience in Flutter\nExperience in 3rd party API integration\nExperience in mobile applications deployment preferred\nFamiliar with other frontend web frameworks such as React Native will be advantageous\nKnowledge of OOP, database, version control, electronics circuits will be advantageous\n\nOffers:\n\n5-day work week\nBank holidays + Annual Leave\nPerformance incentives\nOngoing learning fund\nMedical insurance\n\nFor more information about Blue Sky Energy Technology,\u00a0 please visit us at www.blueskyenergy.co.\n\nPlease send us your CV together with your current & expected salary and available start date via email OR apply here.", "employment_types": ["Full Time", "Permanent"], "selling_points": ["Fast Growing Technology Company", "Career Development and Good Team Culture", "Competitive compensation"], "locations": ["Yau Ma Tei"], "categories": ["Information Technology (IT)", "Application Specialist - Software", "Software Development", "Others"], "post_time": "2022-01-15T04:46:22Z", "salary": {"currency": null, "max": null, "min": null, "period": "monthly", "term": null}, "salary_visible": false, "title_keywords": ["developer"], "responsibilities": ["provide guidance", "coordinate with", "develop"], "requirements": {"degrees": ["bachelor"], "majors": ["computer engineering", "computer science"], "languages": [], "language_level": [], "hard_skills": ["web", "mobile", "react native", "deployment", "integration"], "soft_skills": ["learning"], "languages_combined": []}, "experience_required": {"duration": [], "field": []}}, {"job_id": "100003009056194", "location_code": "hk", "company": "Marco Technology Limited", "job_title": "Web Backend Developer", "description": "Responsibilities:\n\nArchitect and build website, web applications and/or prototypes.\nPrepare system documentations.\n\nRequirements:\n\nAt least 2 years working experience\nExperience in development on AWS/GCP/Azure/other Cloud computing platform. (experience in Google API is a plus)\nExperience in Any Backend Development(e.g. Go, Node.js, Java)\nExperience in Java and Web API development (Java EE, Spring, Hibernate) is a plus\nExperience in SQL and NoSQL Database\nExperience in automation tools and frameworks (e.g. git, Jenkins, JMeter, ApacheBench)\nCollaborate with team members to improve the company\u2019s engineering tools, systems and procedures, and data security.\nConduct systems tests for security, performance, and availability.\nDevelop and maintain design and troubleshooting documentation.", "employment_types": ["Full Time", "Permanent"], "selling_points": [], "locations": ["Lai Chi Kok"], "categories": ["Information Technology (IT)", "Software Development"], "post_time": "2022-01-18T03:31:08Z", "salary": {"currency": null, "max": null, "min": null, "period": "monthly", "term": null}, "salary_visible": false, "title_keywords": ["developer"], "responsibilities": ["website"], "requirements": {"degrees": [], "majors": [], "languages": [], "language_level": [], "hard_skills": ["java", "plus", "azure", "hibernate", "git", "jenkins", "aws", "sql", "web api", "spring", "documentation", "go"], "soft_skills": ["troubleshooting"], "languages_combined": []}, "experience_required": {"duration": ["at least 2 years"], "field": ["sql", "development", "database"]}}, {"job_id": "100003009055982", "location_code": "hk", "company": "HKT", "job_title": "Senior Application Developer II", "description": "We are undergoing Digital Transformation and is actively looking for talented people to join our team which is expanding rapidly. The successful candidate will be exposed to a wide range of innovative technology initiatives and chance to work with talents and industry experts worldwide.\n\nWhat you\u2019ll get from us\n\nExposure to technology including but not limited to:\nHTML5 & JavaScript or TypeScript\nC# / Java / Node.js\nWeb APIs development\u00a0\nAny RDBMS (e.g. T-SQL, MySQL)\nCurrent Version Control Systems (Git)\nAngular / React / Vue\nCI/CD\nNoSQL database\nCloud technologies and platforms\nNice, reasonable and open-minded teammates\nWork-life balance team culture\nLarge corporation working experience\nLeverages corporate resources, you\u2019ll have the chance to experience numerous current architecture (e.g. Microservices, Micro-Frontend) / platforms (e.g. Salesforce) while we\u2019re undergoing Digital Transformation\nGain experience and knowledge in large-scale projects with a wide range of systems and solutions, from internal systems to public-facing systems\n\nYour Role\n\nWork as a software programmer that mainly focuses on web apps, both front-ends and back-ends included\nWork with System Analyst / Team Leader in requirement study, system analysis and design\nAdapt to new technologies or languages when required\nUnderstand user requirements, design specifications etc. and carry out programming accordingly\n\nTo succeed in this role\n\nBachelor degree in Computer Science, Information Technology, Software Engineering or related disciplines\n1-4 years of hands-on software development experience\nEagerness to learn and adapt to new technologies / concepts is crucial\nGood analytical and problem-solving skills, critical thinking is crucial\nWork well with a team, able to collaborate nicely and proactively\nQuality-oriented\nProficient in both written and English, Chinese and Cantonese\n\nCandidate with\u00a0less experience will be considered as a\u00a0Applciation Developer\n\nAs Hong Kong\u2019s leading ICT service provider, HKT has in recent years transformed into a technology innovator and provider of smart, digital services and solutions for consumers and businesses.\n\nHKT is the first in Hong Kong to provide true 5G services, complete with applications and content to afford our customers a unique and truly differentiated experience.\n\nHKT is Hong Kong\u2019s largest broadband service provider with a territory-wide fiber network covering 88% of homes. Our services go beyond connectivity to make the daily lives of customers smarter and more convenient.\n\nFor enterprises, HKT delivers end-to-end solutions employing emerging technologies to accelerate their digital transformation, contributing to Hong Kong\u2019s development into a smart city.\n\nOur global connectivity network has 125 points of presence across 76 cities and encompasses over 60 cable systems worldwide. PCCW Global maintains regional centers in 11 countries worldwide.\n\nThe Club is HKT\u2019s loyalty program and one of the largest of its kind in Hong Kong. With more than 800 merchants as coalition and redemption partners, it offers privileges and benefits to enrich the lifestyle of members. Club Travel is a travel service for consumers and corporate customers. Club Like is an online shopping platform for customers to make purchases with Clubpoints and in cash. These represent a new digital ecosystem using data analytics to connect consumers and merchants.\n\nHKT also offers financial services such as mobile payment, smart mobile POS solutions, digital financing, and insurance. We are a member in a joint venture offering virtual bank services in Hong Kong.\n\nEmploying over 16,200 staff, HKT is headquartered in Hong Kong and maintains a presence in mainland China and other parts of the world.\n\nThe share stapled units of the HKT Trust and HKT Limited are listed on The Stock Exchange of Hong Kong Limited (SEHK: 6823).\n\nHKT Limited is a company incorporated in the Cayman Islands with limited liability.\n\nHKT is an equal opportunity employer and welcomes applications from all qualified candidates. Information provided will be treated in strict confidence and will only be used for recruitment-related purposes. Personal data provided by job applicants will be used strictly in accordance with the employer's personal data policies (www.hkt/privacy-statement), a copy of which will be provided immediately upon request.", "employment_types": ["Full Time"], "selling_points": [], "locations": ["Wan Chai"], "categories": ["Information Technology (IT)", "Application Specialist - Software", "Software Development"], "post_time": "2022-01-18T03:09:28Z", "salary": {"currency": null, "max": null, "min": null, "period": "monthly", "term": null}, "salary_visible": false, "title_keywords": ["developer"], "responsibilities": ["collaborate", "control", "software", "analysis", "systems", "quality", "design", "design specifications", "database", "architecture", "internal systems"], "requirements": {"degrees": ["degree", "bachelor"], "majors": ["related disciplines", "software engineering", "computer science", "information technology"], "languages": ["cantonese", "english", "chinese"], "language_level": ["proficient"], "hard_skills": ["java", "git", "salesforce", "web", "react", "nice", "t-sql", "web apps", "microservices", "analysis", "make", "typescript", "javascript", "angular", "programming", "problem-solving skills", "go", "c#"], "soft_skills": ["open-minded", "unique", "hands-on", "problem-solving skills", "innovative"], "languages_combined": [{"language": "cantonese", "language_level": ["proficient"]}, {"language": "english", "language_level": ["proficient"]}, {"language": "chinese", "language_level": ["proficient"]}]}, "experience_required": {"duration": ["1-4 years"], "field": ["developer", "software development"]}}, {"job_id": "100003009054153", "location_code": "hk", "company": "CHOW TAI FOOK JEWELLERY CO LTD", "job_title": "Analyst Programmer", "description": "What You Do\n\nHands-on for SDLC including design, coding, testing, implementation and maintenance of in-house systems\nInterface internal systems with other outsourced modules\nWork closely with business analysts to produce application design\nConduct feasibility study and analysis based on users' requirements and provide technical advice\nEnsure flexibility, stability, scalability, sustainability and performance of systems\nProvide system support on more complex user enquiries, production problems and troubleshooting\nProvide technical investigation and quick fix in case of encountering critical incident\nComplete jobs with good quality and within schedule\nMaintain awareness of new technologies and best practices for adoption\nEnsure all deliverables are in good quality and meeting requirements\nProvide database maintenance and data housekeeping\nWork closely with data quality team to align with SDLC on data governance related compliance\nPrepare technical documentations and system specifications\n\nWho Will Thrive\n\nBachelor Degree in Computer Science, Information System or equivalent with experience in supply chain management, jewelry industry is an advantage\nAt least 3 years of experience in web-based application development in .NET platform\nFamiliar with the ASP.NET framework, SQL Server and design/architectural patterns (e.g. MVC)\nFamiliar with .NET languages (e.g. C#, VB.NET), javascript, Ajax, jQuery, JSON, HTML5/CSS3, MSSQL\nGood analytical, problem solving and interpersonal skills\nAble to work independently in fast paced environment with minimum supervision\nComplete jobs with good quality and within schedule\n\nBenefits\n\n\n5-day work\nCompetitive salary, staff meal,\u00a0medical and dental insurance, life insurance\nVarious types of leave, e.g.\u00a0Family-friendly leave, self-development leave,\u00a0Examination leave, marriage leave, birthday\u00a0leave, volunteer service leave, etc\n\nWe offer excellent career opportunities, attractive remuneration package & benefits to the right candidate.\u00a0Interested parties please apply by clicking \"Apply Now\" with a full resume stating the latest and expected salary.\n\n\n\nAll information collected will be used for recruitment purposes only.", "employment_types": ["Full Time", "Permanent"], "selling_points": ["Application development and testing", "Application management", ".NET / ASP.NET / RPA / Git"], "locations": ["Kwai Hing"], "categories": ["Information Technology (IT)", "Software Development", "Technical Writing", "Others"], "post_time": "2022-01-17T08:35:31Z", "salary": {"currency": null, "max": null, "min": null, "period": "monthly", "term": null}, "salary_visible": false, "title_keywords": ["analyst programmer"], "responsibilities": ["data", "technical advice", "quality", "troubleshooting", "coding", "design", "maintain", "database", "application development", "compliance", "implementation", "testing", "schedule", "internal systems", "management", "investigation", "specifications", "maintenance", "housekeeping", "analysis", "systems"], "requirements": {"degrees": ["degree", "bachelor"], "majors": ["computer science"], "languages": [], "language_level": [], "hard_skills": ["maintenance", "web", "analysis", "jquery", "information system", "mssql", "sql", "problem solving", "sdlc", "javascript", "ajax", "server", "documentations", "c#"], "soft_skills": ["work independently", "troubleshooting", "problem solving", "hands-on", "interpersonal skills"], "languages_combined": []}, "experience_required": {"duration": ["at least 3 years"], "field": ["supply chain", "management", "application development"]}}, {"job_id": "100003009052465", "location_code": "hk", "company": "Xensetech Limited", "job_title": "Advanced Technology Engineer (Developers)", "description": "Job details:\n\nResponsible for the system design, development and maintenance of\u00a0in-house developed Java applications\nAssist in collecting user requirements and transforming into functional requirements and technical specifications\nLiaise with and support users for system implementation, bug fixing, user acceptance test, deployment, training and related documentation\nCreate database tunneling via SQL\n\nRequirements:\n\nBachelor degree in Computer Science or a related discipline\nMinimum 3 years working experience in similar position\nSolid experience n Java,\u00a0Struts (Apache) and SQL\nGood command of spoken and written English and Chinese\n\nFor more job opportunity, please visit our website: www.clts.com\n\nThe personal information is collected strictly for recruitment purpose only.", "employment_types": ["Full Time", "Permanent"], "selling_points": ["Degree or above in IT, CS & Computing Engineering", "Stable and professional team, friendly culture", "Competitive remuneration package"], "locations": ["Shatin Area"], "categories": ["Information Technology (IT)", "Application Specialist - Software", "Software Development", "Technical / Functional Consulting"], "post_time": "2022-01-17T03:05:53Z", "salary": {"currency": null, "max": null, "min": null, "period": "monthly", "term": null}, "salary_visible": false, "title_keywords": ["engineer"], "responsibilities": ["related documentation", "maintenance", "implementation", "specifications", "system design", "database", "liaise with"], "requirements": {"degrees": ["degree", "bachelor"], "majors": ["computer science"], "languages": ["english", "chinese"], "language_level": ["good command"], "hard_skills": ["sql", "java", "apache", "struts"], "soft_skills": [], "languages_combined": [{"language": "english", "language_level": ["good command"]}, {"language": "chinese", "language_level": ["good command"]}]}, "experience_required": {"duration": ["minimum 3 years"], "field": ["sql"]}}, {"job_id": "100003009054399", "location_code": "hk", "company": "Global eSolutions (HK) Limited", "job_title": "System Analyst", "description": "We build incredible signage and Adtech solutions. Create endpoints that is used an viewed by millions!\u00a0\n\nAura Labs is a the leading signage solutions provider in Hong Kong, Our deployments are some of the largest in the local market. Our company build interactive solutions for shopping malls and other properties. Join us, we offer a fast pace and fun environment.\n\nThe ideal candidate is a self-motivated, multi-tasker, and demonstrated team player. You will be a senior software engineer responsible for the core development of all new software products and enhancements to existing products.\u00a0Join and grow with a multi-disciplinary team, gain the opportunity to work on software and hardware\n\n\u00a0Whom we are looking for\n\nAn individual with a recognised degree or diploma in Computer Science or equivalent technology and development related fields\n2+ years of experience in software development\u00a0\nExpertise in PHP Laravel preferred\nBeing familiar with Node.js and other backend languages would be an advantage\nSome experience with frontend development in JS (e.g. React, Angular)\nFamiliar with the web development constructs, e.g. GitHub, XML, HTML/XHTML, CSS, AJAX, JSON\nKnowledge of SQL\u00a0\nExperience in DevOps (Jenkins, Docker, Ansible) will be an advantage\u00a0\nTeam player with good communication skills\u00a0\u00a0\nStrong programming practice and able to prepare technical documents\u00a0\nAccountability and ability to work under pressure\u00a0\nAvailability prioritised\n\nJob Nature and Responsibilities\n\nBe involved in all aspects of the software development-cycle. From synthesising requirements, analysis of existing systems, design and implementation, to production rollout and subsequent support\u00a0\nProvide development leadership and expertise for the company\u00a0\nWriting clean, high-quality, high-performance, maintainable code\u00a0\nDevelop and support software including applications, database integration, interfaces, and new functionality enhancements\nCompile documentation of specifications on technical and functional design\u00a0\nDevelop systems according to business requirements and technical specifications\nDevelop, enhance, and maintain software applications for various solutions, including coding, debugging, testing of the system\nWork closely with technical leadership to deliver exceptional solutions and products to our clients\nWe offer an attractive salary and benefits package,\u00a0a long-term career prospect to the right talents. Interested individuals should prepare a Resume in MS Word or PDF format, including personal particulars, employment history, project reference, expected salary and contact phone number. Hope to see you soon.", "employment_types": ["Full Time", "Permanent"], "selling_points": ["Java, Spring, SQL", "Development", "5 Days, Medical Allowance"], "locations": ["Kwun Tong"], "categories": ["Information Technology (IT)", "IT Project Management / Team Lead", "Software Development", "Technical Writing"], "post_time": "2022-01-17T09:22:35Z", "salary": {"currency": null, "max": null, "min": null, "period": "monthly", "term": null}, "salary_visible": false, "title_keywords": ["system analyst"], "responsibilities": [], "requirements": {"degrees": [], "majors": [], "languages": [], "language_level": [], "hard_skills": [], "soft_skills": [], "languages_combined": []}, "experience_required": {"duration": [], "field": []}}, {"job_id": "100003009053197", "location_code": "hk", "company": "Kwonnie Electrical Products Ltd", "job_title": "Software Engineer", "description": "Responsibilities:\n\nDevelop new mobile apps (iOS / Android / React Native)\nMaintain and enhance existing apps\nTroubleshoot and debug\nCollaborate with project managers, UX designers, backend developers and quality assurance to deliver client projects\n\nRequirements:\n\n\nTo qualify for the role you must have:\n\nHigher Diploma or Degree in Computer Science / IT or related disciplines\nGood communication and interpersonal skills\nResponsible and able to work under pressure\nProficiency in Objective-C / Swift / Java / Kotlin\nSolid experience in iOS / Android development\nKnowledge on cross platform development is an advantage\n1 - 2 year experience in mobile app development (Fresh graduates are also welcome)\n\nWhat working at EY offers:\n\nSupport, coaching and feedback from some of the most engaging colleagues around\nOpportunities to develop new skills and progress your career\nThe freedom and flexibility to handle your role in a way that\u2019s right for you\n\nIf you can confidently demonstrate that you meet the criteria above, please contact us as soon as possible.\n\nJoin us in building a better working world.\n\nApply now.", "employment_types": ["Full Time", "Permanent"], "selling_points": [], "locations": ["Kwun Tong"], "categories": ["Engineering", "Electrical / Electronics", "Information Technology (IT)", "Software Development"], "post_time": "2022-01-17T06:24:43Z", "salary": {"currency": null, "max": null, "min": null, "period": "monthly", "term": null}, "salary_visible": false, "title_keywords": ["software engineer"], "responsibilities": ["collaborate with", "quality", "develop", "maintain", "troubleshoot"], "requirements": {"degrees": ["diploma", "degree"], "majors": ["related disciplines", "it", "computer science"], "languages": [], "language_level": [], "hard_skills": ["android development", "java", "objective-c", "mobile", "swift", "kotlin"], "soft_skills": ["communication and interpersonal skills", "responsible", "work under pressure"], "languages_combined": []}, "experience_required": {"duration": ["1 - 2 year"], "field": ["development"]}}, {"job_id": "100003009054327", "location_code": "hk", "company": "MIT Technology System Limited", "job_title": "Analyst Programmer (AP)", "description": "Responsibilities:\n\n- Analyze, design, develop, implement for real-time, low-latency mobile applications;\n- Conduct program testing, system testing and develop test cases to support user acceptance test;\n- Assist team leader in requirement study, documentation and co-ordination;\n- Provide ongoing user and application support;\n\nRequirements:\n\n- University Degree in Computer Science, Information Technology, Electronic Engineering or equivalent;\n- 2+ yrs experiences in Flutter/React Native application development;\n- Solid knowledge in React Native libraries, frameworks\n- Experience in Objective-C/Swift (for iOS) or Java/Kotlin (for Android) or JavaScript, ReactJS is a plus;\n- Extremely enthusiastic in programming and learning new technologies\n- Willing to learn, responsible, a good team player with good communication skills;\n- Self-motivated, work independently, good analytical and problem solving skill;\n- Experience in Agile/Scrum development is a plus.", "employment_types": ["Full Time"], "selling_points": ["Familiar with Python and related technologies", "Degree holder with exp. in Java 1.5  development", "Attractive salary w/bonus, 5-day week, 12 days AL"], "locations": ["Not Specified"], "categories": ["Information Technology (IT)", "Support", "Software Development", "Others"], "post_time": "2022-01-17T09:10:19Z", "salary": {"currency": null, "max": null, "min": null, "period": "monthly", "term": null}, "salary_visible": false, "title_keywords": ["analyst programmer"], "responsibilities": ["documentation", "testing", "design", "develop"], "requirements": {"degrees": ["university degree"], "majors": ["engineering", "computer science", "information technology"], "languages": [], "language_level": [], "hard_skills": ["java", "plus", "agile", "objective-c", "problem solving", "javascript", "react native", "programming", "swift", "kotlin", "android"], "soft_skills": ["communication skills", "good team player", "self-motivated", "work independently", "agile", "responsible", "analytical and problem solving skill", "willing to learn", "learning", "enthusiastic"], "languages_combined": []}, "experience_required": {"duration": [], "field": ["development", "application development"]}}, {"job_id": "100003009051988", "location_code": "hk", "company": "Eclipse Trading", "job_title": "Front End Platform Engineer", "description": "We are working on large projects with well known property management cooperation.\nShe/He will join a new project to build a A.I. related project.\n\nResponsibilities:\n\nAnalyze, design, program, test, document and maintain IT systems or applications\nGather systems requirements from users\nAnalyze requests for enhancements / changes and write amendment / program specification\nDevelop test cases, conduct load test and tune the performance of systems\n\nRequirements:\n\nDegree/Higher Diploma in Computer Science / Information Technology or equivalent\nExperience in Python or Java or .Net\nKnowledge of Mobile development will be advantage\nSelf-motivated, able to work independently and willing to learn", "employment_types": ["Full Time", "Permanent"], "selling_points": ["Experience in C# software development", "Experience in JavaScript/TypeScript", "Attractive benefits package"], "locations": ["Causeway Bay"], "categories": ["Information Technology (IT)", "Application Specialist - Software", "Software Development", "UI/UX Designer"], "post_time": "2022-01-17T01:45:51Z", "salary": {"currency": null, "max": null, "min": null, "period": "monthly", "term": null}, "salary_visible": false, "title_keywords": ["engineer"], "responsibilities": ["maintain", "design", "systems"], "requirements": {"degrees": ["diploma", "degree"], "majors": ["computer science", "information technology"], "languages": [], "language_level": [], "hard_skills": ["python", "mobile", "java"], "soft_skills": ["self-motivated", "willing to learn", "work independently"], "languages_combined": []}, "experience_required": {"duration": [], "field": []}}, {"job_id": "100003009052436", "location_code": "hk", "company": "Sky 88 Technology Limited", "job_title": "System Analyst / Analyst Programmer", "description": "Main Duties & Responsibilities:\n\nResponsible for development of latest FinTech systems and enhancement of existing IT systems\nTo participate in the entire System Development Life Cycle (SDLC) for successful project delivery\nTo assist manager in requirement study, analysis, design, documentation and co-ordination with users and operations teams\nProvide support to end users on various business systems\nExplore new technologies and drive for innovation, especially new development tools, new algorithmic code, bring better solution for existing environment\nActive participation on latest company FinTech initiatives\n\nRequirements:\u00a0\n\nDiploma or above in Computer Studies / Computer Science / Information Technology (I.T.) or related disciplines\nMinimum 5 years relevant experience with at least 2 years in system analyst role\nGood experience in MS SQL Server, SQL Server Stored Procedure and C#.NET\nAble to demonstrate systematic and logical reasoning\nWith interest to learn new technologies, including AI, big data, DLT technology, mobile, cloud, etc.\nEnergetic, self-motivated, teamwork, dynamic and with passion for FinTech innovation\nWork experience in banking industry will be an added advantage\n\nWe offer:\n\nDiscretionary bonus\nMedical insurance\nDental insurance\nHardship allowance\nCompetitive annual leave days\nBirthday leave\nAnniversary leave\nPerformance reward days\nStudy leave\nMarriage leave\nCompassionate leave\n\nHow to apply:\n\nInterested parties, please send your resume stating your expected salary to Human Capital Department\u00a0by clicking \"APPLY NOW\".\n\n(We are an equal opportunity employer.\u00a0 Personal data collected will be used for recruitment purpose only.\u00a0 The unsuccessful applications will be destroyed after 6 months.)", "employment_types": ["Full Time", "Permanent"], "selling_points": ["Key role in our programming team", "5 yrs of solid hands-on programming experiences", "NodeJS, SQL, MYSQL, C#, AWS, ReactJS, C++"], "locations": ["Ngau Tau Kok"], "categories": ["Information Technology (IT)", "Application Specialist - Software", "Software Development"], "post_time": "2022-01-17T03:01:45Z", "salary": {"currency": "HKD", "max": 69999, "min": 35000, "period": "monthly", "term": null}, "salary_visible": true, "title_keywords": ["analyst programmer", "system analyst"], "responsibilities": ["provide support", "operations", "analysis", "systems", "teams", "design", "documentation"], "requirements": {"degrees": ["diploma or above"], "majors": ["information technology", "computer science", "computer studies"], "languages": [], "language_level": [], "hard_skills": ["ai", "ms sql server", "sql", "mobile", "dynamic", "server", "c#"], "soft_skills": ["self-motivated", "passion for", "teamwork", "systematic", "dynamic", "energetic"], "languages_combined": []}, "experience_required": {"duration": ["at least 2 years", "minimum 5 years"], "field": ["sql", "banking industry", "system analyst", "relevant experience"]}}, {"job_id": "100003009054769", "location_code": "hk", "company": "Public Finance Limited", "job_title": "Programmer", "description": "Responsibilities:\u00a0\n\nDevelopment and implementation of Web applications\nSystems integration and implementation of Web applications\nExplore and recommend new technology to improve existing products and services\nRequirements:\n\nDegree / Diploma in Computer Science, Information Technology or related disciplines\n2 years or above experience in Java/J2EE\nObject oriented design and basic knowledge of software and networking\nExperience in Java, J2EE, JSF, Tomcat and RDBMS e.g. Oracle, MySQL\nKnowledge in Spring Frameworks, Hibernate Frameworks, PHP, mobile applications will be an advantage\nPro-active, initiative and able to complete job assignments independently with minimum supervision\nWilling to work in competent, challenging and team-working environment\n(Those with less experience or fresh graduate will be considered as\u00a0Web Developer (Backend Programmer)\n\n\n\n\n\u00a0Application Method\n\nWe offer 5-day work week, free shuttle bus, free parking and fringe benefits including medical scheme, discretionary bonus, public holidays together with career growth opportunities to the right candidate. \u00a0Interested parties, please send full resume with expected salary to ORIENTAL\u00a0HUMAN RESOURCES LIMITED\u00a0by\u00a0clicking \"Apply now\" ;\u00a0or fax to 3600 1900 ( Please quote reference on the application letter )\n\nPersonal Information Collection Statement\n\nPersonal data collected will be treated in accordance with our Personal Data Policy and handled in strict confidence by authorized personnel for recruitment related purpose only.\n\non.cc", "employment_types": ["Full Time", "Permanent"], "selling_points": [], "locations": ["Not Specified"], "categories": ["Information Technology (IT)", "Application Specialist - Software", "Support", "Software Development"], "post_time": "2022-01-17T11:00:08Z", "salary": {"currency": null, "max": null, "min": null, "period": "monthly", "term": null}, "salary_visible": false, "title_keywords": ["programmer"], "responsibilities": ["systems", "implementation"], "requirements": {"degrees": ["diploma", "degree", "fresh graduate"], "majors": ["related disciplines", "computer science", "information technology"], "languages": [], "language_level": [], "hard_skills": ["java", "hibernate", "basic", "web", "php", "jsf", "scheme", "mobile", "spring", "oracle"], "soft_skills": ["independently", "initiative", "competent", "pro-active"], "languages_combined": []}, "experience_required": {"duration": ["2 years"], "field": ["developer"]}}, {"job_id": "100003009042519", "location_code": "hk", "company": "IT Channel (Asia) Limited", "job_title": "System Analyst \u2013 Application Services (5 days work week)", "description": "Duties:\n\nParticipate in application design and implementation, system enhancements, testing, and end-user training\nDevelopment of web-based management systems\nDaily system maintenance and troubleshooting and routinely software deployment\n\nRequirements:\n\nUniversity Graduate in Computer Science or related subject\n5-10 years experience\u00a0in coding and development using\u00a0Java, Spring Framework, SQL\nExperienced in DevOps, Git\nGood analytical and problem-solving skills, and capable of preparing technical and programming documentation\nPositive attitude\nSalary range depends on the\u00a0capability of the candidates\n\nWe offer 5-day work, public holidays, medical benefits, excellent career opportunities, considerable remuneration to the right candidates.\n\nInterested parties please send an email of a full resume and/or application letter, with current and expected salary to us.", "employment_types": ["Full Time", "Permanent"], "selling_points": ["Work life balance, Birthday Leave", "Minimum 3 years exp in software development", "Lead and work with developer team"], "locations": ["Tsim Sha Tsui"], "categories": ["Information Technology (IT)", "Application Specialist - Software", "Software Development", "Others"], "post_time": "2022-01-16T21:50:14Z", "salary": {"currency": null, "max": null, "min": null, "period": "monthly", "term": null}, "salary_visible": false, "title_keywords": ["system analyst"], "responsibilities": ["management", "software", "maintenance", "systems", "implementation", "design", "testing", "troubleshooting"], "requirements": {"degrees": ["university graduate"], "majors": ["computer science"], "languages": [], "language_level": [], "hard_skills": ["java", "git", "devops", "sql", "spring", "programming", "documentation", "problem-solving skills"], "soft_skills": ["positive attitude", "problem-solving skills", "capable"], "languages_combined": []}, "experience_required": {"duration": ["5-10 years"], "field": ["sql", "development"]}}, {"job_id": "100003009054653", "location_code": "hk", "company": "Asendia Hong Kong Limited", "job_title": "IT Programmer (JAVA)", "description": "Job Description:\n\nAnalyze existing IT system and develop IT solution for new enhancements;\nProvide daily support to operational and ad-hoc issues;\nAssist teams with smaller related projects related to primary application system.\nRequirement:\n\nDegree holder in Information Technology or other related disciplines;\n2 years of Java (Spring) and Javascript Development experience;\nGood knowledge of SQL and writing Stored Procedures (Preferably SQL Server);\nSelf-motivated, strong sense of responsibility, good analytical, problem solving skills and attention to details.\n\nInterested parties please send full resume with employment history and\u00a0expected salary\u00a0to HRA Division, Yusen Logistics Global Management Limited at Level 31, Tower 1, Kowloon Commerce Centre, 51 Kwai Cheong Road, Kwai Chung, N.T. or by email to\u00a0hr.ylhk @ hk.yusen-logistics.com\u00a0 \u00a0 \u00a0\n\nYusen Logistics Global Management Limited is an equal opportunity employer. All information collected will be used for recruitment purpose only.", "employment_types": ["Full Time", "Permanent"], "selling_points": ["3 years relevant working experience", "5-day work, Double Pay, Discretionary Bonus", "Attractive remuneration"], "locations": ["Tsuen Wan Area"], "categories": ["Information Technology (IT)", "Application Specialist - Software", "Software Development"], "post_time": "2022-01-17T10:25:04Z", "salary": {"currency": null, "max": null, "min": null, "period": "monthly", "term": null}, "salary_visible": false, "title_keywords": ["it programmer"], "responsibilities": ["ad-hoc", "teams", "application system", "develop"], "requirements": {"degrees": ["degree holder"], "majors": ["related disciplines", "information technology"], "languages": [], "language_level": [], "hard_skills": ["java", "sql", "javascript", "spring", "server", "problem solving skills"], "soft_skills": ["self-motivated", "attention to details", "problem solving skills", "sense of responsibility"], "languages_combined": []}, "experience_required": {"duration": ["2 years"], "field": ["development"]}}, {"job_id": "100003009052405", "location_code": "hk", "company": "TEKsystems", "job_title": "Data Engineer - The Fintech Financial", "description": "Responsibilities:\n\nResponsible for handling software development in 4/8/16 bit Microcontroller including debugging, performance testing and project follow-up of electronic products.\nResponsible for software design and testing plan documentation\n\nRequirements:\n\nBachelor degree in Electronic Engineering, Computer Engineering/Computer Science or related disciplines\nAt least 2 years\u2019 experience in MCU software development. Good knowledge and practical experience in Microcontroller application and C programming\nGood coding practice and source code control and management\nFamiliar with various communication protocol include UART, I2C, SPI\nReading schematic diagram and understanding circuit operation is a plus.\nKnowledge in embedded OS development (RTOS or embedded Linux) is a plus.\nExperience in assembly language programming, circuit design and PCB layout is a plus.\nGood command of English, Mandarin and Cantonese\nOccasionally travel to China\u00a0\nInterested parties, please send your full resume stating your expected salary and date of availability to the Human Resources Department\u00a0for application.\u00a0 We offer successful candidates an attractive remuneration packages (Basic salary + Bonus + Medical Scheme) and the opportunity to work in a dynamic and exciting environment.\u00a0 (Data collected will be used for recruitment purpose only)", "employment_types": ["Full Time"], "selling_points": ["Data Engineer", "Fintech", "Cloud"], "locations": ["Yau Tsim Mong Area"], "categories": ["Information Technology (IT)", "Application Specialist - Software", "Software Development", "Data Scientist"], "post_time": "2022-01-17T02:58:00Z", "salary": {"currency": null, "max": null, "min": null, "period": "monthly", "term": null}, "salary_visible": false, "title_keywords": ["data engineer"], "responsibilities": ["software", "performance testing", "design", "testing", "plan", "documentation"], "requirements": {"degrees": ["degree", "bachelor"], "majors": ["related disciplines", "computer engineering", "engineering", "computer science"], "languages": ["cantonese", "english", "mandarin"], "language_level": ["good command"], "hard_skills": ["linux", "plus", "assembly language", "c", "os", "programming", "code"], "soft_skills": ["communication"], "languages_combined": [{"language": "cantonese", "language_level": ["good command"]}, {"language": "english", "language_level": ["good command"]}, {"language": "mandarin", "language_level": ["good command"]}]}, "experience_required": {"duration": ["at least 2 years"], "field": ["design", "programming", "software development"]}}, {"job_id": "100003009053415", "location_code": "hk", "company": "Kazoo Technology (Hong Kong) Limited", "job_title": "\u8cc7\u8a0a\u79d1\u6280\u9805\u76ee\u7d93\u7406", "description": "Key Responsibilities:\n\nDevelop, implement, test, and maintain Java cryto applications.\nDesign overall architecture of the backend application.\nMaintain quality and ensure the responsiveness of applications.", "employment_types": ["Full Time"], "selling_points": [], "locations": ["Shatin Area"], "categories": ["Information Technology (IT)", "IT Project Management / Team Lead", "Product Management / Business Analyst", "Software Development"], "post_time": "2022-01-17T06:57:27Z", "salary": {"currency": null, "max": null, "min": null, "period": "monthly", "term": null}, "salary_visible": false, "title_keywords": [], "responsibilities": ["maintain quality", "design", "develop", "maintain", "architecture"], "requirements": {"degrees": [], "majors": [], "languages": [], "language_level": [], "hard_skills": ["java"], "soft_skills": [], "languages_combined": []}, "experience_required": {"duration": [], "field": []}}, {"job_id": "100003009054457", "location_code": "hk", "company": "I-Access Group Limited", "job_title": "Programmer / Junior Programmer", "description": "Responsibilities :\n\nWork closely with Project Lead to develop application for users\nMaintain and support the application for production and usage\nWeb development\u00a0\n\nRequirements :\n\nDegree holder in Computer Science or related disciplines\nExperience in PHP\u00a0\nWelcome Fresh graduates", "employment_types": ["Full Time", "Permanent"], "selling_points": ["5-Day work week", "Exposure in financial industry", "Fresh graduates will also be considered"], "locations": ["Causeway Bay"], "categories": ["Information Technology (IT)", "Software Development", "Banking / Finance", "Order Processing & Operation / Settlement", "Others", "Student / Fresh Graduate / No Experience"], "post_time": "2022-01-17T09:37:31Z", "salary": {"currency": null, "max": null, "min": null, "period": "monthly", "term": null}, "salary_visible": false, "title_keywords": ["programmer", "junior"], "responsibilities": ["maintain", "develop"], "requirements": {"degrees": ["degree holder"], "majors": ["related disciplines", "computer science"], "languages": [], "language_level": [], "hard_skills": ["php"], "soft_skills": [], "languages_combined": []}, "experience_required": {"duration": [], "field": []}}, {"job_id": "100003009047584", "location_code": "hk", "company": "theOrigo Ltd.", "job_title": "Analyst Programmer / Senior Web Programmer", "description": "Your Role\n\nTo develop applications on mobile platforms (Flutter / iOS / Android / React Native)\nTo be responsible for design, development, testing, implementation, enhancement and maintenance\nTo implement systems to meet dynamic business needs riding on the latest and proven technology;\nTo assist in the company\u2019s digital transformation initiatives and build related common and re-usable components;\nTo cultivate and train development team members to fast-track with mobile app development technique;\nTo appreciate latest technological development and adapt for application development productivity\n\nTo succeed in this role\n\nDegree / Higher Diploma in Computer Science, Information Engineering or equivalent;\nMinimum of 2-3 years\u2019 software development experience, in which at least 1 year on mobile application development;\nHands-on experience on HTML, XML, Json, JSP, Shell scripts, Git;\nWorking knowledge of Objective-C/Swift and JAVA/Kotlin-Android;\nKnowledge of Java / Spring, Flutter/React, Cloud (AWS) technology is an advantages;\nPossess solid organizational and technical skills to effectively manage multiple priorities;\nSelf-motivated, good customer-oriented attitude and ability to work under pressure;\nEager to learn new technology;\nSound knowledge of Development / Ops practice;\nGood command of both written and spoken English and Chinese", "employment_types": ["Full Time", "Permanent"], "selling_points": ["2+ years of experiences in PHP, Java", "Backend development for websites and apps", "Excellent promotion opportunities"], "locations": ["Central"], "categories": ["Information Technology (IT)", "Application Specialist - Software", "IT Project Management / Team Lead", "Software Development"], "post_time": "2022-01-16T21:50:19Z", "salary": {"currency": null, "max": null, "min": null, "period": "monthly", "term": null}, "salary_visible": false, "title_keywords": ["analyst programmer", "web programmer"], "responsibilities": ["mobile app", "software", "maintenance", "systems", "implementation", "design", "testing", "develop", "application development", "work under pressure"], "requirements": {"degrees": ["diploma", "degree"], "majors": ["engineering", "computer science"], "languages": ["english", "chinese"], "language_level": ["good command"], "hard_skills": ["java", "git", "maintenance", "react", "html", "objective-c", "aws", "mobile", "dynamic", "react native", "spring", "swift", "kotlin", "android"], "soft_skills": ["self-motivated", "responsible", "organizational", "eager to learn", "hands-on", "dynamic", "customer-oriented", "technical skills", "work under pressure"], "languages_combined": [{"language": "english", "language_level": ["good command"]}, {"language": "chinese", "language_level": ["good command"]}]}, "experience_required": {"duration": ["at least 1 year", "minimum of 2-3 years"], "field": ["application development", "software development"]}}, {"job_id": "100003009052213", "location_code": "hk", "company": "Newtimes Human Resources Limited", "job_title": "Business Analyst", "description": "Responsibilities\nTo be responsible for development, enhancement and maintenance if our internal applications\nTo prepare detail documentations\nTo assure the program quality, conduct UAT and user training, perform user support and project coordination, etc\nRequirements\nUniversity degree in Computer Science or related disciplines\nMinimum 1 year experience in application development with good database management concept\nKnowledge of any of the followings is a plus: VB.NET, ASP.NET, Crystal Report, Visual Basic\nGood command in both spoken and written English\nBenefits\nDouble Pay\nDiscretionary Bonus\nInsurance Benefits\nStudy subsidy\nApplication Method:\nBy Whatsapp : 9309 2925By E-mail via \"Apply Now\"\nPersonal data collected will be treated in the strictest confidence in accordance with our\u00a0Personal Information Collection Statement\u00a0and\u00a0Privacy Policy\u00a0and will be handled by authorized personnel for recruitment-related purposes only. All applications will be kept for a maximum period of one year as may be considered for other suitable positions within Public Finance Ltd. and its associated companies. For details, please visit the Company\u2019s website\u00a0http://www.publicfinance.com.hk", "employment_types": ["Full Time"], "selling_points": ["Immediate availability is highly preferred", "hands on experience in software application", "Less experiences is also considered"], "locations": ["Lai Chi Kok"], "categories": ["Information Technology (IT)", "Application Specialist - Software", "Support", "Software Development"], "post_time": "2022-01-17T02:30:20Z", "salary": {"currency": null, "max": null, "min": null, "period": "monthly", "term": null}, "salary_visible": false, "title_keywords": ["business analyst"], "responsibilities": ["quality", "uat", "maintenance", "project coordination"], "requirements": {"degrees": ["university degree"], "majors": ["related disciplines", "computer science"], "languages": ["english"], "language_level": ["good command"], "hard_skills": ["plus", "visual basic"], "soft_skills": [], "languages_combined": [{"language": "english", "language_level": ["good command"]}]}, "experience_required": {"duration": ["minimum 1 year"], "field": ["application development", "database management"]}}, {"job_id": "100003009053963", "location_code": "hk", "company": "Nissin Foods (HK) Management Co Ltd", "job_title": "Analyst Programmer", "description": "Responsibilities:\n\nResponsible for back end system development, testing and bug fixing\nWork closely with team members to develop and test application systems according to system design documentations\nAssist in project implementation\nPerform ad hoc projects as required\n\nRequirement:\n\nDegree / Diploma in Information Technology / Computer Science or related disciplines\nProficient in Java, Spring Framework, Play Framework, JQuery, Database design and MySQL or Oracle SQL\nGood analytical and troubleshooting skills\nMinimum 3 years working experience\nFluent with Mandarin, Cantonese and English; Good communications skills\n\nWe offer competitive remuneration package and fringe benefits to the right candidate. Interest parties please send full resume stating your availability, present and expected salary to Human Resources Manager by clicking\u00a0APPLY NOW.\n\nAll personal data collected will be used for recruitment related purposes and treated in strictest confidentiality.\u00a0 Applicants not hearing from us within 2 months may consider their applications unsuccessful.\u00a0 All personal data supplied will be destroyed after completion of the recruitment process.\n", "employment_types": ["Full Time", "Permanent"], "selling_points": [], "locations": ["Tai Po Area"], "categories": ["Information Technology (IT)", "Application Specialist - Software", "Software Development", "Network & System"], "post_time": "2022-01-17T07:51:33Z", "salary": {"currency": null, "max": null, "min": null, "period": "monthly", "term": null}, "salary_visible": false, "title_keywords": ["analyst programmer"], "responsibilities": ["implementation", "develop", "testing", "system design", "ad hoc projects", "application systems"], "requirements": {"degrees": ["diploma", "degree"], "majors": ["related disciplines", "computer science", "information technology"], "languages": ["cantonese", "english", "mandarin"], "language_level": ["fluent"], "hard_skills": ["java", "jquery", "sql", "spring", "oracle"], "soft_skills": ["troubleshooting"], "languages_combined": [{"language": "cantonese", "language_level": ["fluent"]}, {"language": "english", "language_level": ["fluent"]}, {"language": "mandarin", "language_level": ["fluent"]}]}, "experience_required": {"duration": ["minimum 3 years"], "field": []}}, {"job_id": "100003009053936", "location_code": "hk", "company": "SHOPLINE", "job_title": "Software Engineer (Fresh Grads Welcome)", "description": "Responsibilities\n\nContribute to the development of desktop applications using .NET programming language\nImplement and maintain features and enhancements on application requirements\n\nRequirements\n\nExperience in C#.NET\nExperience in Windows application development\nExperience in C++ would be in advantage\nExperience with high quality, customer facing UI development\nFresh graduate welcome\n\nWhat we provide\n\nAttractive remuneration and package\n5-day work\nPerformance bonus\n14 days annual leave plus birthday leave\nMedical insurance\nCheerful, friendly & energetic environment\nIndoor golf and entertainment facilities!", "employment_types": ["Full Time"], "selling_points": ["Practical training to know industry best practices", "Attractive package and benefits e.g.Birthday leave", "Develop technical knowledge and skill"], "locations": ["Sheung Wan"], "categories": ["Information Technology (IT)", "Software Development"], "post_time": "2022-01-17T07:48:05Z", "salary": {"currency": null, "max": null, "min": null, "period": "monthly", "term": null}, "salary_visible": false, "title_keywords": ["software engineer"], "responsibilities": ["maintain"], "requirements": {"degrees": ["fresh graduate"], "majors": [], "languages": [], "language_level": [], "hard_skills": ["c++", "c#"], "soft_skills": [], "languages_combined": []}, "experience_required": {"duration": [], "field": ["development", "application development"]}}, {"job_id": "100003009053925", "location_code": "hk", "company": "GrammyTech Ltd", "job_title": "System Analyst/ Analyst Programmer (Java/ C# )(up to 50k)", "description": "Responsibilities\n\nDevelop various financial services systems\nAssist in project implementation, system testing & documentation\nProvide technical support to end users\n\nRequirements\n\nDegree holder in Computer Science or related disciplines\nAround 1 year relevant experience in programming\nProficiency in C++, Java,\u00a0SQL,\u00a0HTML and JavaScript is an advantage\nInterested in Securities Industry and Financial Market is a plus\nFresh university graduates will be considered as junior programmers\n\nWe offer attractive remuneration package, 5-day work and stable working environment. Interested persons please send resume indicating current and expected salary by clicking \"Apply Now\" or by fax 39960112\n\n(Personal data collected will be used for recruitment purpose only)", "employment_types": ["Full Time", "Permanent"], "selling_points": ["Nice working environment", "Bachelor\u2019s degree in Computer Science", "Experience in Java or C#.Net programming"], "locations": ["Not Specified"], "categories": ["Information Technology (IT)", "Application Specialist - Software", "Software Development", "Others"], "post_time": "2022-01-17T07:47:18Z", "salary": {"currency": "HKD", "max": 44999, "min": 30000, "period": "monthly", "term": null}, "salary_visible": true, "title_keywords": ["analyst programmer", "system analyst"], "responsibilities": ["technical support", "systems", "implementation", "testing", "develop", "documentation"], "requirements": {"degrees": ["degree holder"], "majors": ["related disciplines", "computer science"], "languages": [], "language_level": [], "hard_skills": ["java", "plus", "c++", "html", "sql", "javascript", "programming"], "soft_skills": ["interested in"], "languages_combined": []}, "experience_required": {"duration": ["1 year"], "field": ["relevant experience", "programming"]}}, {"job_id": "100003009053318", "location_code": "hk", "company": "Neo Derm (HK) Ltd", "job_title": "Analyst Programmer / Programmer \u2013 Website Support", "description": "Background\n\nYou will be responsible for back-end development for large scale high-quality websites and apps development. Join us to work with our professional and creative teams to accomplish and share the success and growth of the company.\u00a0\n\nResponsibilities\nCreating larger, scalable and transactional websites and applications\nPropose technical solution options to a specific user requirement\nMaintain well-documented, reusable, and transferrable code\nParticipate in thoughtful code reviews\nEnsure smooth implementation and delivery of the projects\nTroubleshoot issues for production applications\nKeep up to date with advances in technology and promote the related best practices at theOrigo\nHelp strengthen our team by passing on your craftsmanship through close collaboration, knowledge shares, and mentorship\nBe innovative on creating outstanding websites and features\nRequirements\nDegree or High Diploma in computer science, IT, engineering or relevant fields of study\nAt least 2 years of hands-on experience in web development or backend development\nFluency with one or more server-side languages, such as PHP, Node.js, or Java to develop websites, applications, and APIs\nExpert knowledge of Git and related branching strategies\nFamiliarity with working in Linux and docker/container environments\nSolid grasp of the principles, patterns, and practice of software design\nWorking knowledge of testing tools for load test and security testing\nAttentive to detail and committed to quality\nClear and concise written and oral communication, both internally and with our clients\nGood organizational skills, problem solving ability\nGood command in interpersonal/communication skills\nApplicants with less experience will also be considered\nBenefits\nYou will be working with a high-performing and energetic team with excellent career progression.\nAttractive remuneration and package\n5-day work\u00a0\nPerformance bonus\nBirthday Leave, Caring Leave and Anniversary Leave\u00a0\nMedical insurance benefits\nTravel allowance\nFree good coffee!\n\nA competitive remuneration package and excellent career prospects will be offered to the right candidate. Interested parties please send a full resume with salary expectation and availability through JobsDB.\n\nAll applications will be treated in strict confidence and used solely for recruitment purposes. Only shortlisted candidates will be notified for the interview.\n\ntheOrigo is an equal opportunity employer and all employment decisions are made on the basis of valid job qualifications regardless of race, color, creed, sex, age, national origin, ancestry, religion, medical condition, sexual orientation, marital status, physical handicap, or veteran status.", "employment_types": ["Full Time", "Permanent"], "selling_points": ["Full stack on JavaScript, CSS & Bootstrap", "MS SQL Server, MySQL 8 & MongoDB", "Fresh graduate are welcome"], "locations": ["Tai Koo"], "categories": ["Information Technology (IT)", "Application Specialist - Software", "Software Development"], "post_time": "2022-01-17T06:45:08Z", "salary": {"currency": null, "max": null, "min": null, "period": "monthly", "term": null}, "salary_visible": false, "title_keywords": ["analyst programmer", "programmer"], "responsibilities": ["user requirement", "maintain", "implementation", "troubleshoot"], "requirements": {"degrees": ["high diploma", "degree"], "majors": ["it", "engineering", "computer science"], "languages": [], "language_level": [], "hard_skills": ["linux", "web development", "git", "java", "php", "problem solving", "container", "server"], "soft_skills": ["organizational skills", "oral", "communication skills", "attentive to detail", "clear", "committed", "hands-on", "communication", "problem solving", "interpersonal"], "languages_combined": []}, "experience_required": {"duration": ["at least 2 years"], "field": ["development"]}}, {"job_id": "100003009054038", "location_code": "hk", "company": "Yusen Logistics Global Management Limited", "job_title": "System Analyst (ETL/ELT)", "description": "Responsibilities:\n\nSupport ongoing operation of ERP system, Microsoft Dynamics Navision, including end user support, configuration, problem solving and enhancement.\nAssist with the analysis of user requests and design of technical solutions based on those requests.\nCarry out in-house development, including integration and/or implementation of interface with other applications. Coordinate with external vendors to execute development tasks in needs.\nDocuments and demonstrates solutions by developing documentation, flowcharts, layouts, diagrams, charts, code comments and clear code.\nImproves operations by conducting systems analysis; recommending changes in policies and procedures.\nDevelops software solutions by studying information needs, conferring with users studying systems flow, data usage, and work processes investigating problem areas following the software development lifecycle.\nSupport coming ERP system upgrade\nOpportunity to involve different type of development project such as CRM, Business Intelligence, RPA, cloud ERP\nRequirements:\n\nDiploma in Computer Science, Information Technology or equivalent\u00a0 \u00a0 \u00a0 certifications\n1-3 years of experience with Microsoft Dynamics.\nGood knowledge in NAV functionality, implementation experience in EDI and BI tool is desirable.\nUnderstanding and demonstrable experience with SQL\nDesigning, coding and debugging applications in various software languages.\nDemonstrated ability to thrive in a collaborative environment, working with people from all departments in the company who have varying degrees of computer/technology knowledge and to produce work in a timely, budgeted, scheduled and profitable manner for the Company.\nApplicant please email detailed resume with present and expected salary to Human Resources Dept.\n(All personal data collected will be kept confidential and used for recruitment purpose only)", "employment_types": ["Full Time"], "selling_points": ["Experience in Power BI ETL and visualization.", "Experience with Alteryx and MS SQL", "Good analytics and problem solving skills"], "locations": ["Kwai Hing"], "categories": ["Information Technology (IT)", "Application Specialist - Software", "Support", "Software Development"], "post_time": "2022-01-17T08:09:30Z", "salary": {"currency": null, "max": null, "min": null, "period": "monthly", "term": null}, "salary_visible": false, "title_keywords": ["system analyst"], "responsibilities": ["software", "data", "configuration", "operations", "analysis", "comments", "microsoft dynamics", "implementation", "design", "coordinate with", "developing", "systems", "policies", "procedures", "documentation"], "requirements": {"degrees": ["diploma"], "majors": ["computer science", "information technology"], "languages": [], "language_level": [], "hard_skills": ["sql", "bi"], "soft_skills": ["timely", "collaborative", "detailed"], "languages_combined": []}, "experience_required": {"duration": ["1-3 years"], "field": ["sql"]}}, {"job_id": "100003009053835", "location_code": "hk", "company": "Konew Financial Express Ltd", "job_title": "Quality Assurance Analyst", "description": "SHOPLINE is Asia\u2019s largest smart commerce platform. With our customers in mind, we strive to deliver scalable commerce solutions to merchants of all sizes. We\u2019re a full-featured platform with services including online store opening, O2O solution, retail POS systems, advertising placement, business strategy consultation, marketing, and more to empower merchants to succeed in omnichannel retailing and cross-border commerce.\n\nYou\u2019ll be a part of an engineering team that is dedicated to developing a reliable and robust e-commerce platform for merchants in Asia.\n\nWHAT YOU'LL BE DOING:\n\nDeveloping, and maintaining high quality, scalable applications.\nThis includes writing well-crafted, well-tested, readable, maintainable code.\nDevise new, innovative ways of development for both web and mobile platforms.\nThis role goes beyond just coding. You will be making an immediate impact on the design, development and overall direction of our products.\nWe\u2019ll leverage you to explore emerging technologies and techniques to make recommendations on how we could use them to advance goals.\n\nWHO WE ARE LOOKING FOR:\n\nUniversity / Diploma Degree in Computer Science, Computer Engineering, Electronic Engineering, Information Engineering or related fields;\nExperience with one or more of the following program languages: JavaScript (React.js, Node.js), Ruby, Python.\nFresh graduates are welcome. More experienced engineers will be considered for the Senior Software Engineer position.\nWillingness to take ownership of tasks and features assigned.\nAble to figure out what should be done and get it done. (this requires thoughtfulness with a bias towards taking action and assuming responsibility)\nExperience with object-oriented programming and MVC Frameworks.\nAgile development and SCRUM experience is a plus.\nLife long learner and quick learner to new technologies\n\nGood to haves\n\nExperience working for a fast-paced startup\nKnowledge on building or maintaining e-commerce platforms\n\nWHY YOU SHOULD JOIN US:\n\nWe provide training for newcomers to understand industry best practices.\nWe have check points to keep newcomers motivated and learn various skills.\nWe work in a fun, collaborative open space where we encourage creativity and ideas flow freely.\u00a0\nYou\u2019ll be able to steer the future roadmap to improve our products, big or small, and see the results of your products reach our customers.\nGet to work with flexible working hours. Our priority is on getting the job done.\nBirthday leave, marriage leave etc\u00a0\nFlat structure environment, you will be able to work independently and make your own choices.\nWe provide guidance and mentorship to polish your business skills and entrepreneurship mindset.\nWe are one of the standout tech startups in Hong Kong, targeting a huge opportunity in Asia.\nShopline is a part of the 500 Startups Accelerator and Incubated by Hong Kong Cyberport, giving us a massive network of advisors and resources globally.", "employment_types": ["Full Time", "Permanent"], "selling_points": ["Design and execute functional test plans", "Prepare Project Test Strategy/Plan", "At least 5 years of relevant testing experience"], "locations": ["Central"], "categories": ["Information Technology (IT)", "IT Management", "Software Development", "Testing / QA"], "post_time": "2022-01-17T07:36:08Z", "salary": {"currency": null, "max": null, "min": null, "period": "monthly", "term": null}, "salary_visible": false, "title_keywords": ["quality assurance analyst"], "responsibilities": ["make recommendations", "advertising", "software", "maintaining", "systems", "quality", "developing", "coding", "design", "agile development", "e-commerce platforms", "e-commerce platform"], "requirements": {"degrees": ["diploma", "degree"], "majors": ["computer engineering", "engineering", "computer science"], "languages": [], "language_level": [], "hard_skills": ["plus", "agile", "web", "pos", "e-commerce", "react", "ruby", "mobile", "make", "javascript", "programming", "python", "code"], "soft_skills": ["make recommendations", "agile", "robust", "innovative", "quick learner", "reliable"], "languages_combined": []}, "experience_required": {"duration": [], "field": ["development", "programming"]}}, {"job_id": "100003009054253", "location_code": "hk", "company": "CHOW TAI FOOK JEWELLERY CO LTD", "job_title": "Business Intelligence Analyst", "description": "Roles and responsibilities:\n\n-\u00a0\u00a0\u00a0\u00a0\u00a0\u00a0\u00a0\u00a0\u00a0 Developing innovative Websites, Digital Applications based on the supplied design;\n-\u00a0\u00a0\u00a0\u00a0\u00a0\u00a0\u00a0\u00a0\u00a0 Exploring on new technology to meet different project requirements;\n-\u00a0\u00a0\u00a0\u00a0\u00a0\u00a0\u00a0\u00a0\u00a0 Work closely with all colleagues in creative, development team and clients to ensure requirements and schedule are met.\n\n\u00a0Requirements:\n\n3 years+ working experience in related industry;\nSolid knowledge and experience in PHP / MySQL\u00a0/ Javascript\u00a0;\nFamiliar with different web CMS system would be a Big Advantage;\nBasic knowledge in\u00a0HTML / CSS\u00a0is needed;\nExperience with any Frameworks is an added bonus;\nProven experience and understanding of responsive design;\nEfficient, self-motivated and able to work independently to meet multiple project deadlines;\n\nBenefits:\n-\u00a0\u00a0\u00a0\u00a0\u00a0\u00a0\u00a0\u00a0\u00a0 5 days work\n-\u00a0\u00a0\u00a0\u00a0\u00a0\u00a0\u00a0\u00a0\u00a0 Competitive salary\n-\u00a0\u00a0\u00a0\u00a0\u00a0\u00a0\u00a0\u00a0\u00a0 Medical Insurance\n-\u00a0\u00a0\u00a0\u00a0\u00a0\u00a0\u00a0\u00a0\u00a0 Performance Bonus\n-\u00a0 \u00a0 \u00a0 \u00a0 \u00a0 Free Snacks\n-\u00a0\u00a0\u00a0\u00a0\u00a0\u00a0\u00a0\u00a0\u00a0 Casual attire\n\nFor interested parties, please email full resume with\u00a0proven portfolio and expected salary to us through \"Apply Now\" button.\n\nPersonal data collected will be used for recruitment purpose only.", "employment_types": ["Full Time", "Contract"], "selling_points": ["Business Intelligence Analyst", "ETL, Data modeling and Dashboard building", "SQL Query / Qlikview / Qlik Sense / Python"], "locations": ["Kwai Hing"], "categories": ["Information Technology (IT)", "Software Development", "Technical Writing", "Others"], "post_time": "2022-01-17T08:58:11Z", "salary": {"currency": null, "max": null, "min": null, "period": "monthly", "term": null}, "salary_visible": false, "title_keywords": ["analyst"], "responsibilities": ["project requirements", "developing", "design", "schedule"], "requirements": {"degrees": [], "majors": [], "languages": [], "language_level": [], "hard_skills": ["basic", "web", "php", "html", "javascript", "css"], "soft_skills": ["efficient", "self-motivated", "responsive", "work independently"], "languages_combined": []}, "experience_required": {"duration": [], "field": ["related", "design"]}}, {"job_id": "100003009001342", "location_code": "hk", "company": "Lik On Technology Limited", "job_title": "C# Web Programmer", "description": "Reporting to the Enterprise Information Solutions Director, your main responsibilities will be to:\n\nSupport on the operation and development of Management Report\nDesign and develop both web-based and client-based applications\nMaintain and manage existing application systems\nPerform ad-hoc projects as assigned\n\n\n\nThe successful candidate will be:\n\nHigher Diploma / Degree holder in Computer Science or related discipline\nWell-versed in JavaScript, VB.Net, C#.Net, VBA and SQL\nAt least 1 year related experience\nKnowledge in SAP will be an advantage\nWilling to work overtime, face new challenges and able to meet deadline\nGood team player with strong interpersonal & communication skill\nSelf-starter and problem-solver\nGood command of both spoken and written English & Chinese\n\nCandidates who fit this profile will enjoy an attractive remuneration package and benefits with 5-day work week. Interested parties, please\u00a0submit your application\u00a0by\u00a0Apply Now.\n\nYou are also welcome to visit our website: www.kao.com/hk for more details about our company.\n\n(All information collected will be used for recruitment purpose only).", "employment_types": ["Full Time", "Permanent"], "selling_points": ["Higher diploma or above in Computer Studies/Inform", "Minimum 1 year's relevant experience", "Experienced working with remote data"], "locations": ["Cheung Sha Wan"], "categories": ["Information Technology (IT)", "Software Development", "Network & System", "Mobile / Wireless Communications"], "post_time": "2022-01-16T21:50:07Z", "salary": {"currency": null, "max": null, "min": null, "period": "monthly", "term": null}, "salary_visible": false, "title_keywords": ["web programmer"], "responsibilities": ["reporting", "ad-hoc projects", "design and develop", "communication", "maintain", "application systems", "management report"], "requirements": {"degrees": ["diploma", "degree holder"], "majors": ["computer science"], "languages": ["english", "chinese"], "language_level": ["good command"], "hard_skills": ["vba", "web", "sap", "sql", "javascript", "c#"], "soft_skills": ["good team player", "work overtime", "communication skill", "interpersonal"], "languages_combined": [{"language": "english", "language_level": ["good command"]}, {"language": "chinese", "language_level": ["good command"]}]}, "experience_required": {"duration": ["at least 1 year"], "field": ["related"]}}, {"job_id": "100003009054043", "location_code": "hk", "company": "Konica Minolta Business Solutions (HK) Limited", "job_title": "System Analyst", "description": "Your role:\n\nSupport senior members in system platform setup and support.\nFacilitate service rollout with our Development and Operations team.\nKeen sense of technology trends and participate in product evaluation.\n2nd tier technical support on production platforms.\n\nTo succeed in this role:\n\nHigher Certificate/Diploma in Computer Science, Information Technology or related disciplines with 1-2 years relevant experience. (Fresh Graduate will also be considered)\nEntry-level experience in at least 2 of the following areas:\nLinux OS administration & troubleshooting.\nVMware (or other hypervisor) setup, administration & troubleshooting\nNetwork concepts and equipment setup, administration.\nStorage (SAN/NAS) administration.\nPassionate about computers and internet technology.\nGood analytical and problem-solving skills.\nSelf-motivated team player and ready to learn.\nAwareness of contemporary Open Source Cloud Platforms and Deployment Methodology.\nEntry-level accreditations holders preferred (e.g. RHCSA, CCNA).", "employment_types": ["Full Time", "Permanent"], "selling_points": ["Use State-of-the-Art development platform and tech", "Wide exposure for various customers and business", "Development and new technology"], "locations": ["Tai Koo"], "categories": ["Information Technology (IT)", "Application Specialist - Software", "Software Development", "Data Scientist"], "post_time": "2022-01-17T08:11:15Z", "salary": {"currency": null, "max": null, "min": null, "period": "monthly", "term": null}, "salary_visible": false, "title_keywords": ["system analyst"], "responsibilities": ["technical support", "operations", "troubleshooting", "evaluation", "setup", "administration"], "requirements": {"degrees": ["diploma", "higher certificate", "fresh graduate"], "majors": ["related disciplines", "computer science", "information technology"], "languages": [], "language_level": [], "hard_skills": ["linux", "vmware", "ccna", "os", "deployment", "nas", "problem-solving skills"], "soft_skills": ["self-motivated", "keen", "troubleshooting", "problem-solving skills", "team player", "passionate about"], "languages_combined": []}, "experience_required": {"duration": ["1-2 years"], "field": ["related", "relevant experience", "information technology"]}}, {"job_id": "100003009051919", "location_code": "hk", "company": "Octopus Holdings Limited", "job_title": "System Engineer / Senior System Engineer (Back End)", "description": "Main Duties & Responsibilities:\n\n\nResponsible for development of latest FinTech systems and enhancement of existing IT systems\nTo participate in the entire System Development Life Cycle (SDLC) for successful project delivery\nTo assist IT Manager in requirement study, analysis, design, documentation and co-ordination with users and operations teams\nProvide support to end users on various business systems\nExplore new technologies and drive for innovation, especially new development tools, new algorithmic code, bring better solution for existing environment\nActive participation on latest company FinTech initiatives\n\nRequirements:\n\n\nDiploma or above in Computer Studies / Computer Science / Information Technology (I.T.) or related disciplines\nProficiency in at least one modern object-oriented programming language\nFast learner and willing to pick up new technology and skill\nHave knowledge in cloud development is an advantage\nAble to work in fast paced environment\nEnergetic, self-motivated, teamwork, dynamic and out of the box thinking\nFresh graduate is welcome. Less experience will be considered as software developer\n\nWe offer:\n\nDiscretionary bonus\nMedical insurance\nDental insurance\nHardship allowance\nCompetitive annual leave days\nBirthday leave\nAnniversary leave\nStudy leave\nMarriage leave\nCompassionate leave\n\nHow to apply:\n\nInterested parties, please send your resume stating your expected salary to Human Capital Department\u00a0by clicking \"APPLY NOW\".\n\n(We are an equal opportunity employer.\u00a0 Personal data collected will be used for recruitment purpose only.\u00a0 The unsuccessful applications will be destroyed after 6 months.)", "employment_types": ["Full Time", "Permanent"], "selling_points": ["Perform requirement analysis, design & development", "Prepare quality technical specifications", "Minimum 2 years of relevant experience"], "locations": ["Kowloon Bay"], "categories": ["Information Technology (IT)", "Software Development"], "post_time": "2022-01-17T01:32:38Z", "salary": {"currency": null, "max": null, "min": null, "period": null, "term": null}, "salary_visible": false, "title_keywords": ["system engineer", "senior system engineer"], "responsibilities": ["provide support", "operations", "analysis", "systems", "teams", "design", "documentation"], "requirements": {"degrees": ["fresh graduate", "diploma or above"], "majors": ["information technology", "computer science", "computer studies"], "languages": [], "language_level": [], "hard_skills": ["dynamic", "programming"], "soft_skills": ["self-motivated", "teamwork", "dynamic", "energetic", "fast learner"], "languages_combined": []}, "experience_required": {"duration": [], "field": ["developer"]}}, {"job_id": "100003009054843", "location_code": "hk", "company": "Cathay United Bank Company, Limited", "job_title": "Full Stack Developer, Treasury Solutions", "description": "Our client\u00a0 is looking for System Analyst/ Analyst Programmer for their team (Perm or\u00a0 contract) .\n\nResponsibilities:\n\n\nAnalyse, design and implement multi-tier web application systems\nDevelop data conversion and migration plan and strategies\nConduct requirement and justification studies\n\nRequirements:\n\nBachelor\u2019s degree in Computer Science or related area of study\nMinimum 4 years' experience in project management\u00a0\nExperience in Java or C#.Net programming\u00a0\nExperience in mobile app devlopment will be a big advantage\nParticipate in application development and unit test\nPrepare proper documentation for record purpose and provide support on systems implementation\nGood team player, communication and interpersonal skills\nGood command of both written and spoken English and Chinese\u00a0\n\nInterested parties, please send your full resume in word format together with salary expectation to\u00a0garychoi @grammytech.com\n\n(All data collected would be used for recruitment purposes only)", "employment_types": ["Full Time", "Permanent"], "selling_points": ["Bachelor\u2019s degree or above", "At least 5 years\u2019 relevant work experience", "Solid skill in Java development"], "locations": ["Causeway Bay"], "categories": ["Information Technology (IT)", "Software Development", "Others"], "post_time": "2022-01-17T11:40:13Z", "salary": {"currency": null, "max": null, "min": null, "period": "monthly", "term": null}, "salary_visible": false, "title_keywords": ["developer"], "responsibilities": ["data", "design", "develop", "plan", "application systems", "migration", "analyse"], "requirements": {"degrees": ["degree", "bachelor"], "majors": ["computer science"], "languages": ["english", "chinese"], "language_level": ["good command"], "hard_skills": ["java", "project management", "mobile", "programming", "documentation", "c#"], "soft_skills": ["project management", "good team player", "communication and interpersonal skills"], "languages_combined": [{"language": "english", "language_level": ["good command"]}, {"language": "chinese", "language_level": ["good command"]}]}, "experience_required": {"duration": ["minimum 4 years"], "field": ["project management"]}}, {"job_id": "100003009053642", "location_code": "hk", "company": "eCargo Enterprise Limited", "job_title": "Business Analyst (e-Commerce)", "description": "Duties:\n\nDevelop, configure and implement system applications and external system interfaces in accordance to user requirements\nPerform unit testing, system integration testing and project implementation with knowledge of methodologies and procedures for application testing and quality assurance\nInvestigate into defects, research for problem resolution and implementation problem rectification\nPlan and assist in User Acceptance Testing\nAssist with application training for users\nParticipate in implementation roll-out\nProvide operational support and ongoing maintenance and enhancement after implementation, including troubleshooting of production issues\n\nRequirements:\n\nHigher Diploma or above in Computer Science / Information Technology or equivalent\nAt least 2 years solid experience in application development\nProficient in .NET framework and Angular\nStrong understanding of object-oriented programming\nCreating database schemas that represent and support business processes\nAble to work independently to meet project deadlines with minimum supervision, and a good team player\nGood interpersonal and communication skills\n\nFor more job opportunity, please visit our website: www.clts.com\n\nThe personal information collected is strictly for recruitment purpose only.", "employment_types": ["Full Time", "Permanent"], "selling_points": ["Double Pay; Five-day work week; Birthday Leave", "IT Business Analyst role in e-Commerce", "1-3 years experiences or Fresh grad"], "locations": ["Kwai Tsing Area"], "categories": ["Information Technology (IT)", "Product Management / Business Analyst", "Software Development", "E-commerce", "Product Management / Business Analyst"], "post_time": "2022-01-17T07:16:35Z", "salary": {"currency": null, "max": null, "min": null, "period": "monthly", "term": null}, "salary_visible": false, "title_keywords": ["business analyst"], "responsibilities": ["operational support", "maintenance", "rectification", "procedures", "implementation", "quality", "testing", "develop", "resolution", "troubleshooting", "plan"], "requirements": {"degrees": ["higher diploma or above"], "majors": ["computer science", "information technology"], "languages": [], "language_level": [], "hard_skills": ["programming", "angular"], "soft_skills": ["communication skills", "good team player", "work independently", "interpersonal"], "languages_combined": []}, "experience_required": {"duration": ["at least 2 years"], "field": ["application development"]}}, {"job_id": "100003009054045", "location_code": "hk", "company": "NEC Hong Kong Limited", "job_title": "Senior System Analyst  / System Analyst - C#, JAVA", "description": "Responsibilities:\n\nPrepare proposal and tender documents in response to clients\u2019 requirements;\nDevelopment of data conversion and migration plan and strategies;\nConducting requirement and justification studies;\nAnalysis, design and implementation of multi-tier web application systems;\nEnsuring conformance of software packages against user requirement ; and\nLead a team of programmer for application development and project implementation.\n\nRequirements:\u00a0\n\nDegree holder in computer science, computer engineering, information technology and or related disciplines;\nWith at least of 5 years\u2019 experience in system analysis and design, reporting solutions and or other web application development projects;\nMust have specialty experience relating to the implementation of data warehouse, business intelligence and data analysis system;\nMust be proficient in Windows and Unix Platform;\nSolid experience in .Net, C#, JAVA and JavaScript is highly preferred;\nGood writing skills for documentation;\nExcellent communication and interpersonal skills; and\nGood command of both spoken and written English.\n\n\nPlease send your full detailed resume with expected salary and date available to The Human Resources Manager, NEC Hong Kong Limited, 25th Floor, The Metropolis Tower, 10 Metropolis Drive, Hunghom, Kowloon or by e-mail.\n\nPersonal data provided by job applicant will be used strictly in accordance with employer's personal data policy, a copy of which will be provided immediately upon request.", "employment_types": ["Full Time", "Permanent"], "selling_points": ["Lead a technical team on system design and coding", "With at least 5 yrs. relevant experience", "Knowledge in .Net, C#, JAVA  and JavaScript"], "locations": ["Hung Hom"], "categories": ["Information Technology (IT)", "Application Specialist - Software", "IT Project Management / Team Lead", "Software Development"], "post_time": "2022-01-17T08:11:37Z", "salary": {"currency": null, "max": null, "min": null, "period": "monthly", "term": null}, "salary_visible": false, "title_keywords": ["system analyst"], "responsibilities": ["user requirement", "software", "data", "tender documents", "application development", "analysis", "implementation", "design", "lead a team", "plan", "application systems", "migration"], "requirements": {"degrees": ["degree holder"], "majors": ["related disciplines", "computer engineering", "computer science", "information technology"], "languages": ["english"], "language_level": ["good command"], "hard_skills": ["java", "web application development", "data warehouse", "analysis", "writing skills", "javascript", "documentation", "business intelligence", "c#"], "soft_skills": ["communication and interpersonal skills", "writing skills", "detailed"], "languages_combined": [{"language": "english", "language_level": ["good command"]}]}, "experience_required": {"duration": ["of 5 years"], "field": ["data analysis", "application development", "business", "design"]}}, {"job_id": "100003009051469", "location_code": "hk", "company": "Joy Aether Limited", "job_title": "Mobile App Developer (Android / React Native)", "description": "Job description\n\nResponsibilities\n\nThe right individual will:\n\nPerform design, development, implementation of\u00a0 Android and React Native mobile\u00a0applications\nResearch and implement new technologies for PoCs and production (e.g. chatbots, AI / NLP)\nCommunicate closely with customers to conduct business requirements\u00a0analysis\nFunctional Verification Testing and defect fixing Work on delivering great\u00a0results to our top-tier customers\n\nRequirements:\n\nDegree in Computer Science or equivalent\n1+ years of programming experience\nExperience in React Native or Android\nCan apply Object Oriented concepts and Design Patterns to mobile\u00a0programming\nGenuine interest in programming and likes to play new technology", "employment_types": ["Full Time", "Permanent"], "selling_points": ["Fresh graduate welcome", "Experience in React Native or Android", "5-day work, flexible working hours"], "locations": ["Shatin Area"], "categories": ["Information Technology (IT)", "Application Specialist - Software", "Software Development"], "post_time": "2022-01-16T03:26:31Z", "salary": {"currency": null, "max": null, "min": null, "period": "monthly", "term": null}, "salary_visible": false, "title_keywords": ["developer"], "responsibilities": ["analysis", "implementation", "design", "testing"], "requirements": {"degrees": ["degree"], "majors": ["computer science"], "languages": [], "language_level": [], "hard_skills": ["android", "react native", "mobile", "programming"], "soft_skills": ["genuine"], "languages_combined": []}, "experience_required": {"duration": ["1+ years"], "field": ["programming"]}}, {"job_id": "100003009053782", "location_code": "hk", "company": "Hysan Development Co Ltd", "job_title": "Senior Application Analyst", "description": "Job Purpose\nThis role is responsible for development and maintenance of ERP system, and other business\u00a0applications\u00a0in both support activities and department projects to support the company fast-growing development.\n\nKey Responsibilities\n\n\nProvide application support and troubleshoot for various internal application systems\u00a0\nParticipate in business process transformational initiatives\nParticipate in technical analysis, design, application development and system integration\nWork closely with business users, review business needs and drive business process improvement with IT solution\nCoordinate with vendors and infrastructure team to deliver solution to business users\nBe responsible for system analysis, design, development and implementation Assist in ad hoc projects when required\nDeliver project documentation and training materials in professional standard\nAssist in system audit\n\n\u00a0\u00a0\nSkills, Qualifications and Experience Requirements\n\nUniversity graduate in Information Technology/Computer Science or related disciplines\n6 years or above in system development with at least 3 years in system analysis and development in SAP areas\nExperience in SAP ABAP programming and Basis is preferrable\u00a0\nSAP hands-on experience or certification in one or more of the following modules including FI/CO, REFX, MM, BW, BO, HCM\nProven experience in system integration and components including application-to-application integrations and services, internal and external API, file transfer, and EDI / SQL queries\nKnowledge and experience in other business applications is advantage Ideal with project management skills\nExperience in managing 3rd party vendors Good team player with strong interpersonal and communication skills\nDemonstrated commitment working under pressure independently\nCandidate with Finance background will be a plus\nGood command of written and spoken English and Cantonese\n\nAn attractive remuneration package will be offered to the right candidate. Interested parties please press \"Apply now\".\n\nHysan is an equal opportunity employer.\u00a0 All information collected will be kept in strict confidence and used solely for recruitment related purposes within the Hysan Group Companies.\n\nYou may get to know more about us through www.hysan.com.hk", "employment_types": ["Full Time", "Permanent"], "selling_points": ["Development and maintenance of ERP system", "Degree holder with 6+ years relevant experience", "5-day work, 14-day AL, Dental, Double Pay + Bonus"], "locations": ["Causeway Bay"], "categories": ["Information Technology (IT)", "Application Specialist - Software", "IT Auditing", "Software Development"], "post_time": "2022-01-17T07:30:49Z", "salary": {"currency": null, "max": null, "min": null, "period": "monthly", "term": null}, "salary_visible": false, "title_keywords": ["application analyst"], "responsibilities": ["3rd party vendors", "maintenance", "application development", "analysis", "review", "coordinate with", "infrastructure", "design", "implementation", "audit", "project management", "communication", "business process", "ad hoc projects", "troubleshoot", "application systems", "project documentation"], "requirements": {"degrees": ["university graduate"], "majors": ["related disciplines", "computer science", "information technology"], "languages": ["cantonese", "english"], "language_level": ["good command"], "hard_skills": ["abap", "documentation", "plus", "maintenance", "sap", "analysis", "technical analysis", "sql", "project management", "erp system", "programming", "integration"], "soft_skills": ["communication skills", "good team player", "independently", "under pressure", "responsible", "project management skills", "hands-on", "troubleshoot", "interpersonal", "ideal"], "languages_combined": [{"language": "cantonese", "language_level": ["good command"]}, {"language": "english", "language_level": ["good command"]}]}, "experience_required": {"duration": [], "field": ["sql", "project management", "business", "programming", "team"]}}, {"job_id": "100003009051260", "location_code": "hk", "company": "OnTheList Limited", "job_title": "IT Business Analyst", "description": "OnTheList is a pioneering\u00a0concept of Members-Only Flash Sales, offering its members authentic and quality products with the promise of being the best deal in town.\u00a0\n\nCurrently the IT team is expanding and we are looking for dynamic Business Analyst to join! He/ she will participate in different development projects, help to prepare documents, data required and set up the current systems to support daily operations.\n\nJOB SCOPE\n\nEngage in various web development & data warehouse projects\nParticipate in business requirement analysis and user requirement studies for new system design/enhancement\nLiaise with other departments to ensure the proposed solution design would meet business requirement\nCo-ordinate testing and/or trial runs with users to make sure new system/system enhancements will be functioning as expected\nExtract & prepare data required from our databases for other departments\nAssist in ad hoc analysis and other duties as required\nAssist in configuring systems to support sales events\n\nPOSITION QUALIFICATIONS\n\nDiploma or above in Business administration, Information Technology, or related disciplines\nGood knowledge in MS Office, in particular MS Excel\nKnowledge in SQL will be a big advantage\n3+ years of experience with BI tool suits, such as Power BI, QuickSight etc. is a plus\nWorking experience in IT related field is a plus\nStrong logical mindset and good communication skills\n\nWHAT DO WE OFFER\n\nInternational and dynamic environment\nDiverse career opportunities for the right candidate\nDiverse and challenging tasks to ensure professional development\nFlexible working environment with work from home arrangement\u00a0\nCommitment to a diversity, equity and inclusive work environment", "employment_types": ["Full Time", "Permanent"], "selling_points": [], "locations": ["Central"], "categories": ["Information Technology (IT)", "Support", "Software Development", "Others"], "post_time": "2022-01-16T21:50:26Z", "salary": {"currency": null, "max": null, "min": null, "period": "monthly", "term": null}, "salary_visible": false, "title_keywords": ["business analyst"], "responsibilities": ["user requirement", "ad hoc", "power bi", "other duties", "data", "analysis", "systems", "quality", "design", "testing", "communication", "daily operations", "system design", "configuring", "databases", "liaise with", "prepare documents", "administration"], "requirements": {"degrees": ["diploma or above"], "majors": ["related disciplines", "business administration", "information technology"], "languages": [], "language_level": [], "hard_skills": ["web development", "bi", "plus", "data warehouse", "analysis", "sql", "make", "ms excel", "dynamic", "system design", "flash", "databases", "ms office"], "soft_skills": ["communication skills", "dynamic", "logical mindset"], "languages_combined": []}, "experience_required": {"duration": ["3+ years"], "field": ["related", "it"]}}, {"job_id": "100003009054832", "location_code": "hk", "company": "Hong Kong Disneyland", "job_title": "Systems Analyst I / II (Digital Product Management)", "description": "Job Summary:\n\nCareer with a Difference\nHong Kong Disneyland delivers world-class service and lifetime memories for our Guests. As a Cast Member, you will be an important part of the Disney Show. Working at Hong Kong Disneyland offers you the opportunity to participate in comprehensive training and experience excellent career development opportunities. Interested in a career with a difference? Join us now!\n\n\nResponsibilities:\nEngage directly with the line of businesses in order to capture application demand, provide guidance on the strategic initiatives and assist with prioritization\nAssist to formulate Customer 360 and data strategy\nDevelop Business Intelligence tools / Dashboards to facilitate efficient cross-platform data analysis\nParticipate in projects of customer data model and data flow amongst integrated systems\nCoordinate between Technology and Digital teams and end users as second line support with vendors to handle daily support and enhancement activities on data warehouse and various applications including problem management\nCollaborate with internal control, security & compliance team and external auditor to ensure systems meet compliance standard and policies\nBasic Qualifications:\nBachelor\u2019s degree or above in Computer Science, Information Systems or equivalent with minimum 5 years of relevant experience\nHand on experience on enterprise database environment and complex data warehouse project\nSolid experience in database design, BI tool, ETL and data warehousing\nProficiency in data analytics, CRM, Salesforce and cloud solutions\nWell-organized, self-motivated and a good team player\nAble to manage multiple tasks, anticipate project needs, prioritize work and meet deadlines\nGood communication skills for both verbal and written in English and Chinese\nAdditional Information:\nSUBMITTING YOUR APPLICATION\nAfter clicking \u201cApply for this job\u201d below, the employment application will open in a new window. Please complete ALL pages of the application in ENGLISH by clicking \u201cNext\u201d on each page, then \u201cSubmit\u201d on the final page.\n#LI-GN1 HKProfessional", "employment_types": ["Full Time", "Permanent"], "selling_points": ["Assist to formulate Customer 360 and data strategy", "Participate in projects of customer data model", "Minimum 5 years of relevant experience"], "locations": ["Lantau Island"], "categories": ["Information Technology (IT)", "IT Project Management / Team Lead", "Software Development", "Data Scientist"], "post_time": "2022-01-17T11:27:38Z", "salary": {"currency": null, "max": null, "min": null, "period": "monthly", "term": null}, "salary_visible": false, "title_keywords": ["analyst"], "responsibilities": ["collaborate with", "warehousing", "management", "data", "policies", "systems", "teams", "customer data", "compliance", "develop", "data analysis", "coordinate", "design", "communication", "database", "career development", "provide guidance", "internal control"], "requirements": {"degrees": ["degree or above", "bachelor"], "majors": ["computer science"], "languages": ["english", "chinese"], "language_level": ["good"], "hard_skills": ["bi", "basic", "salesforce", "data warehouse", "data analytics", "analysis", "business intelligence", "internal control"], "soft_skills": ["efficient", "communication skills", "self-motivated", "good team player", "multiple tasks", "interested in", "well-organized", "prioritize", "comprehensive", "meet deadlines", "world-class"], "languages_combined": [{"language": "english", "language_level": ["good"]}, {"language": "chinese", "language_level": ["good"]}]}, "experience_required": {"duration": ["minimum 5 years"], "field": ["training", "development", "design", "relevant experience", "database"]}}, {"job_id": "100003009054738", "location_code": "hk", "company": "Hong Kong Examinations and Assessment Authority", "job_title": "Programmers (Ref: IT/01/812)", "description": "Duties:\u00a0The appointees will be responsible for the development and support of core IT application systems.\n\nRequirements:\n\nA Bachelor\u2019s Degree / Associate Degree / Higher Diploma in Information Technology, Computer Science or related disciplines;\nAt least two years\u2019 working experience in application system development or support services;\nHands-on experience with web application development and PL/SQL programming;\nKnowledge in web-based system design and application security definitely an advantage;\nGood oral and written communication skills in both Chinese and English; and\nHigh-calibre fresh graduates are also welcome.\n\nEmployment Terms:\u00a0 The remuneration package will be commensurate with qualifications and experience.\u00a0 Appointment will be on a fixed-term contract with contract-end-gratuity, MPF benefits, medical and dental care.\u00a0 Future employment may be offered on renewable contracts subject to performance and staffing needs.\n\nDate for Application Review: 7 February 2022\n\nApplications would be considered until the post is filled.\n\nApplication forms can be obtained from the HKEAA office on 13/F., Southorn Centre, 130 Hennessy Road, Wan Chai, Hong Kong or downloaded from the HKEAA website (www.hkeaa.edu.hk/tc/Career/general.html).\u00a0 Completed application forms should be returned to the Manager \u2013 Human Resources at the above address. Due to the secrecy nature of HKEAA's job duties, applicants invited for interview may be required to make a declaration of any conflict of interests. Applicants not notified within 10 weeks from the application review date should consider their applications unsuccessful.\n\nThe HKEAA is an equal opportunities employer and welcomes applications from all qualified candidates. Information provided relating to employment will be kept confidential and used only for processing applications. For details, please refer to the Policy Statement on Equal Opportunities and the Personal Information Collection Statement on the HKEAA website (www.hkeaa.edu.hk).", "employment_types": ["Full Time", "Permanent"], "selling_points": [], "locations": ["Not Specified"], "categories": ["Information Technology (IT)", "Support", "Software Development", "Others"], "post_time": "2022-01-17T10:51:39Z", "salary": {"currency": null, "max": null, "min": null, "period": null, "term": null}, "salary_visible": false, "title_keywords": [], "responsibilities": ["application development", "support services", "application system", "communication", "system design", "application systems"], "requirements": {"degrees": ["associate degree", "diploma", "degree", "bachelor"], "majors": ["related disciplines", "computer science", "information technology"], "languages": ["english", "chinese"], "language_level": ["good"], "hard_skills": ["web application development", "web", "application system", "sql", "system design", "programming", "pl"], "soft_skills": ["communication skills", "hands-on", "oral", "responsible"], "languages_combined": [{"language": "english", "language_level": ["good"]}, {"language": "chinese", "language_level": ["good"]}]}, "experience_required": {"duration": ["at least two years"], "field": ["sql", "application development", "programming", "system development"]}}, {"job_id": "100003009052562", "location_code": "hk", "company": "LinkedU Overseas Education Limited", "job_title": "Wordpress Developer (Part-Time / Freelance)", "description": "\n\nHandle new development & maintenance to the company's WordPress website and service portals\nImplement appropriate and tidy codes and test them in various environments, enhance and/or modify them if necessary\nCarry out testing, bug fixing and troubleshooting\nConduct WordPress performance test and tuning\nCustom WordPress theme and plugins\nMonitor the performance of the website\nJob Requirements:\n\nDegree holder in Web design, web development or related technical disciplines\nProficient in web development on WordPress with minimum 2 years hands-on experience\nProven experience and understanding of responsive design\nKnowledge of front-end technologies including CSS3, JavaScript, HTML5, and jQuery\nKnowledge of back-end integration such as database, JSON API integration\nFamiliar with SEO tracking code installation (eg. GTM, GA, Facebook Pixel, etc.) will be a plus\nGood command of written Chinese and English", "employment_types": ["Part Time", "Temporary"], "selling_points": ["Proficient in Front-End & Back-End Web Programming", "Familiar with SEO is a plus", "fast-growing overseas education industry"], "locations": ["Central"], "categories": ["Education", "Others", "Information Technology (IT)", "IT - Webmaster / SEO", "Software Development"], "post_time": "2022-01-17T03:25:18Z", "salary": {"currency": null, "max": null, "min": null, "period": "hourly", "term": null}, "salary_visible": false, "title_keywords": ["developer"], "responsibilities": ["installation", "seo", "maintenance", "troubleshooting", "website", "testing", "design", "monitor the performance", "database", "facebook", "tracking"], "requirements": {"degrees": ["degree holder"], "majors": ["web design"], "languages": ["english", "chinese"], "language_level": ["good command"], "hard_skills": ["web design", "web development", "plus", "seo", "maintenance", "jquery", "wordpress", "javascript", "integration", "code", "facebook", "codes"], "soft_skills": ["hands-on", "responsive", "troubleshooting"], "languages_combined": [{"language": "english", "language_level": ["good command"]}, {"language": "chinese", "language_level": ["good command"]}]}, "experience_required": {"duration": ["minimum 2 years"], "field": ["development", "design"]}}, {"job_id": "100003009052422", "location_code": "hk", "company": "Sky 88 Technology Limited", "job_title": "Software Engineer (Web and Game Development)", "description": "1) Software Engineer (Web Development)\n\nRoles:\u00a0\nDevelopment of web applications.\nRectify reports issues,\u00a0Problem solver & Solutions Provider.\nCooperate with other development and operation teams\nRequirements:\n\nDegree / Diploma in Computer Science or related disciplines\nProgramming with React.js, Javascript, MySQL, C#\nExperience/Knowledge in responsive web development using React, AWS, Node.js\nAble to work independently and under pressure\nSelf-motivated, good command of English and Chinese\n\n2) Software Engineer (Game Development)\n\nRoles:\u00a0\nPlay a key role in game development throughout the whole development cycle\nRectify issues reported\n\nResearch new technology\nCooperate with other development and operation teams\nRequirements:\n\nDegree / Diploma in Computer Science or related disciplines\nWorking experience in using Unity3D and C#\nKnowledge in AWS / NoSQL / C++ / Python / 3D Modeling / Photoshop is an advantage\nAble to work independently and under pressure\nSelf-motivated, good command of English and Chinese\n\n\n\n(Candidate with more experience will be considered for senior positions including Analyst Programmer / System Analyst)\n\n\nBenefits:\n\n14 days Paid Annual Leave\nBirthday leave and special holiday leave.\n5-day work and bank holidays\n\nPlease send your cover letter, personal portfolio\u00a0(if any and provide share drive link to download instead of attachment, attachment larger than 1MB may be dropped), and\u00a0resume with last and expected salary to us \u00a0 andy.chan @sky88tech.com or apply\u00a0via Jobsdb.com\n\n", "employment_types": ["Full Time", "Permanent"], "selling_points": ["Key role in our programming team", "1-3 yrs or above hands-on programming experience", "ReactJS, NodeJS, AWS, Unity3D, C#, C++"], "locations": ["Ngau Tau Kok"], "categories": ["Information Technology (IT)", "Application Specialist - Software", "Software Development"], "post_time": "2022-01-17T03:00:07Z", "salary": {"currency": null, "max": null, "min": null, "period": "monthly", "term": null}, "salary_visible": false, "title_keywords": ["software engineer"], "responsibilities": ["teams", "reports", "software", "cooperate with"], "requirements": {"degrees": ["diploma", "degree"], "majors": ["related disciplines", "computer science"], "languages": ["english", "chinese"], "language_level": ["good command"], "hard_skills": ["web development", "web applications", "c++", "react", "aws", "javascript", "photoshop", "programming", "python", "c#"], "soft_skills": ["work independently", "self-motivated", "under pressure", "problem solver", "responsive"], "languages_combined": [{"language": "english", "language_level": ["good command", "good command"]}, {"language": "chinese", "language_level": ["good command", "good command"]}]}, "experience_required": {"duration": [], "field": ["development", "system analyst"]}}, {"job_id": "100003009053598", "location_code": "hk", "company": "Toray Industries (South China) Co Ltd", "job_title": "Application Support (ERP)", "description": "Responsibilities:\n\n\nWork closely with the Team Leader and users to develop, support and rollout of application systems\nPlay a key role in the System Development Life Cycle, from requirement study, system analysis and design, system development and testing, implementation to maintenance and support\nMonitor and maintain application system, including trouble-shooting, bug fixing and ad-hoc queries\nEnsure proper process on testing planning, execution and documentation of all test results\nHandle any ad-hoc projects as assigned\n\nRequirements:\n\n\nDegree in Information Technology, Computer Science or related disciplines\nExperience in the implementation and support of ERP software and reporting tools will be an advantage\nFresh graduates are welcome\nAble to work under pressure and meet tight deadlines\nSelf-motivated, responsible, well-organized, detail-oriented and willing to learn\nExcellent interpersonal and communication skills\nProficiency in both written and spoken English, Cantonese and Mandarin\nBusiness travel to PRC is occasionally required\nImmediate available is highly preferred\n\nWe offer attractive remuneration package including 5-day work, 15-day annual leave & medical insurance to successful candidate.\u00a0 Please send your full resume stating your availability, current and expected salary, contact details by clicking \"Apply Now\"\n\n(All data collected will be treated as strictly confidential and will be used for recruitment purpose only)", "employment_types": ["Full Time", "Permanent"], "selling_points": [], "locations": ["Tsim Sha Tsui"], "categories": ["Information Technology (IT)", "Application Specialist - Software", "Software Development", "E-commerce", "Software Development"], "post_time": "2022-01-17T07:12:55Z", "salary": {"currency": null, "max": null, "min": null, "period": "monthly", "term": null}, "salary_visible": false, "title_keywords": ["application support"], "responsibilities": ["ad-hoc", "ad-hoc projects", "maintenance", "analysis", "monitor", "implementation", "design", "testing", "develop", "application system", "maintain", "documentation", "application systems", "planning"], "requirements": {"degrees": ["degree"], "majors": ["related disciplines", "computer science", "information technology"], "languages": ["cantonese", "english", "mandarin"], "language_level": ["proficiency"], "hard_skills": ["erp"], "soft_skills": ["communication skills", "meet tight deadlines", "self-motivated", "responsible", "well-organized", "willing to learn", "detail-oriented", "interpersonal", "work under pressure"], "languages_combined": [{"language": "cantonese", "language_level": ["proficiency"]}, {"language": "english", "language_level": ["proficiency"]}, {"language": "mandarin", "language_level": ["proficiency"]}]}, "experience_required": {"duration": [], "field": []}}, {"job_id": "100003009054064", "location_code": "hk", "company": "Accenture Technology Solutions (HK) Ltd", "job_title": "Technology \u2013 SAP Hybris Lead", "description": "Let there be CHANGE\n\nReady to fast-track your career? Ready to solve complex problems? Advance your skills? Deliver next-generation technology solutions? Join Accenture and help transform leading organizations and communities around the world. Working in highly collaborative teams for world-leading clients, we\u2019ll nurture your talent in an inclusive\n\nYour career is about what you want to be and who you want to be. It\u2019s about bringing your skills, your curiosity and your best true self to your work.\n\nHere, you\u2019ll match your ingenuity with the latest technology to make incredible things.\nLet\u2019s create something together.\n\nYou can enjoy:\n\nComprehensive Medical (24-hour worldwide) coverage, including your spouse/ life partner and children!\nDental insurance, Life insurance, Total and perm disability, accidental death & dismemberment insurance!\nVision care benefits, Health check, Housing benefits!\nPurchase of Accenture stocks at attractive discount!\nReimbursement of Professional Membership costs\nProfessional training and career advancement opportunities!\nValuable project exposure for different technologies and industry domains!\n\nWhen you work with us, change becomes the most dynamic, powerful source of progress you have!\n\n\n\nJob duties of this Role:\n\nTake part in developing eCommerce platforms and omni-channel solutions for our enterprise clients\nWork closely with onshore and offshore team to ensure smooth implementation and project delivery\u00a0\nEnsure smooth roll out of the project with maintenance afterwards, in close collaboration with the project management team\n\n\u00a0Come JOIN US if you have:\n\nStrong in Java and experience with Spring\nHands-on experience in developing SAP Hybris platform\u00a0\nExperience with B2C and/or B2B Hybris accelerator\nKnowledge on Hybris ORM, WCMS, Backoffice, Cockpits\nWith team leading experience is a huge plus", "employment_types": ["Full Time", "Permanent"], "selling_points": ["Assistant Manager / Manager grade", "eCommerce platforms and omni-channel solutions", "Tech stack: SAP Hybris, Java, Spring"], "locations": ["Not Specified"], "categories": ["Information Technology (IT)", "Application Specialist - Software", "IT Project Management / Team Lead", "Software Development"], "post_time": "2022-01-17T08:16:42Z", "salary": {"currency": null, "max": null, "min": null, "period": "monthly", "term": null}, "salary_visible": false, "title_keywords": ["lead"], "responsibilities": ["insurance", "teams"], "requirements": {"degrees": [], "majors": [], "languages": [], "language_level": [], "hard_skills": ["make"], "soft_skills": ["comprehensive", "collaborative"], "languages_combined": []}, "experience_required": {"duration": [], "field": []}}, {"job_id": "100003009051523", "location_code": "hk", "company": "MPower Technologies Limited", "job_title": "FULL STACK SOFTWARE ENGINEER", "description": "Enterprise Software Development Team\nThis team will design and build out next\u00a0generation\u00a0enterprise technology for our enterprise customers and help us manage our expanding array of products and bring the MPower brand to more people.\u00a0 A role in this team involves a dynamic work environment, supporting product development with loads of creativity and exciting hands-on day-to-day work with local and international retail brands. Our ideal team player will have a genuine passion for product development, and a strong interest in MPower\u2019s future of work mission and the ability to work with our team in a collaborative environment. We\u2019re looking for experienced startup-to-growth stage veterans who have built and led scalable teams who have delivered SaaS products to enterprise clients. We\u2019re lean and nimble, where everyone plays a key role and is experienced enough to understand the right balance of process and getting stuff done. We participate, delegate, and accomplish. If you share our entrepreneurial spirit or you know someone else who would fit the bill perfectly then we look forward to hearing from you!\n\nFULL STACK SOFTWARE ENGINEER\nDetails on the role and specific requirements below\n\nJob Description:\n\nListen, synthesize and reimagine customer use cases and develop system requirements\nDesign, develop, test, maintain and scale enterprise software platform aligned with short and long-term revenue targets\nStay ahead of developments in the competitive landscape\nTrack and optimize for customer success\nMobile/Web application development under agile development framework\nPrepare test cases and support user acceptance tests and production rollout\nPrepare system documentation\nRequirements:\nPassion for enterprise software and driving positive change\nStrategic thinker with an ability to put high-level ideas into practice\nDynamic, creative, digital native and a self-starter\n2-4 years of experience in software development\nOrganized, details-oriented, strong ability to problem-solve, follow-through and work together with teammates\nDegree or Diploma in Computer Science or related discipline a plus\nFamiliar with JavaScript, Node.js, JSON, REST API\nProficiency in both iOS and Android application development\nProficiency in Web and App UI development\nExperience in AWA, Google Cloud (BigQuery, Data Studio) and other Cloud service\nExperience in SaaS product development is preferable\nProficiency in both English and Chinese\nHOW TO APPLY\nplease email to us\u00a0with your\n\nresume/ curriculum vitae\nsalary expectations\nwhy you would like to work at MPower\ninclude two enterprise SaaS solutions your think we can learn from\n\nPersonal data collected will be used for recruitment purposes only and will be treated in strict confidence.\u00a0 Applicants not invited for interview within\u00a04 months\u00a0may consider their applications unsuccessful.\n\n\u00a0", "employment_types": ["Full Time", "Permanent"], "selling_points": ["Full Stack Software Engineer, software development", "Familiar with Javascript, Node.js, JSON, REST AP", "AWS, Google Cloud (BigQuery, Data Studio), SaaS"], "locations": ["Tin Hau"], "categories": ["Information Technology (IT)", "Application Specialist - Software", "Software Development", "Mobile / Wireless Communications"], "post_time": "2022-01-16T08:01:21Z", "salary": {"currency": null, "max": null, "min": null, "period": null, "term": null}, "salary_visible": false, "title_keywords": ["software engineer"], "responsibilities": ["software", "system documentation", "agile development", "design", "develop", "maintain", "application development"], "requirements": {"degrees": ["diploma", "degree"], "majors": ["computer science"], "languages": ["english", "chinese"], "language_level": ["proficiency"], "hard_skills": ["plus", "web", "dynamic", "javascript", "android"], "soft_skills": ["organized", "confidence", "passion for", "dynamic", "creative", "positive"], "languages_combined": [{"language": "english", "language_level": ["proficiency"]}, {"language": "chinese", "language_level": ["proficiency"]}]}, "experience_required": {"duration": ["2-4 years"], "field": ["product development", "software development"]}}, {"job_id": "100003009056072", "location_code": "hk", "company": "Tata Consultancy Services Limited", "job_title": "Senior Solution\u202fArchitect - Digital", "description": "Principal responsibilities:\n\n\nWork with technical leads,\u00a0engineers\u00a0and other Solution/domain architects to define architecture solution design for digital products and services, which meets the business needs and is cost effective\u00a0\n\nConvert requirements into actionable product/service requirements that feed Technology solutions development & influence service direction.\u00a0\n\nResponsible for ensuring solutions are aligned with the platform architecture and roadmap, group standards and policies and the overall enterprise architecture for their function.\u00a0\n\nAccountable for overall design & integrity of set of systems/apps to support specific products, services & customer journeys.\u00a0\n\nAccountable for the architecture governance and design authority for the development of the products and services in line with the published roadmap.\u00a0\n\nResponsible for engaging and leading the enterprise architecture and design practice at the\u00a0DevSecOps\u00a0team level.\u00a0\n\nWork with the Service Quality Manager and control functions to ensure that architecture solutions are \"fit for purpose\" and \"fit for use\".\u00a0\n\nWork with Ops Engineers to ensure operational issues (performance, operator intervention, alerting, design defect related issues,\u00a0etc) are resolved and that any design related issues are addressed in a timely manner.\u00a0\n\n\nRequirements:\u00a0\n\n\n\nDegree or above in a technology,\u00a0engineering\u00a0or science related disciplines.\u00a0\n\nMinimum 10 years solution architect experience in digital transformation especially banking applications.\u00a0\n\nIn-depth knowledge in one or more technology domains: digital, mobile, conversational platform, CRM, data analytic, Blockchain/DLT, API / Microservices and cloud platforms such as Azure, AWS, and GCP.\u00a0\n\nTOGAF certificate would be an advantage.\u00a0\n\nExcellent communication and interpersonal skills, with strong oral, written and presentation skills.\u00a0\n\nStrong analytical, problem solving, negotiation, influencing skills and possess logical and critical thinking in architecture.\u00a0\n\nExpert level of relevant IT architecture,\u00a0strategy\u00a0or solution design experience in delivery role in financial services environment.\u00a0\n\nEnd to end application architecture knowledge with focus on non-functional requirements that are critical in financial service applications.\u00a0\n\nProficiency in both English and Chinese, Putonghua speaking is an advantage\u00a0\n\n\n", "employment_types": ["Permanent"], "selling_points": ["Minimum 10 years solution architect experience.", "Expert level of relevant IT architecture, strategy", "Proficiency in both English and Chinese."], "locations": ["Others"], "categories": ["Information Technology (IT)", "Software Development"], "post_time": "2022-01-18T03:14:51Z", "salary": {"currency": null, "max": null, "min": null, "period": "monthly", "term": null}, "salary_visible": false, "title_keywords": [], "responsibilities": ["cost", "control", "policies", "systems", "quality", "a timely manner", "design", "architecture"], "requirements": {"degrees": ["certificate", "degree or above"], "majors": ["related disciplines", "science", "engineering"], "languages": ["putonghua", "english", "chinese"], "language_level": ["advantage", "proficiency"], "hard_skills": ["blockchain", "azure", "microservices", "aws", "problem solving", "mobile", "focus"], "soft_skills": ["oral", "negotiation", "problem solving", "presentation skills", "communication and interpersonal skills", "focus"], "languages_combined": [{"language": "putonghua", "language_level": ["proficiency"]}, {"language": "english", "language_level": ["advantage", "proficiency"]}, {"language": "chinese", "language_level": ["advantage", "proficiency"]}]}, "experience_required": {"duration": ["minimum 10 years"], "field": ["design", "solution architect", "it", "financial services", "banking", "digital"]}}, {"job_id": "100003009051394", "location_code": "hk", "company": "Meta Air Labs Limited", "job_title": "Analyst Programmer / Frontend, Web Developer (Vue.Js / React.Js) - Expansion", "description": "Meta Air Labs Limited is an Enterprise-Grade Blockchain as a Solutions (BaaS) Service Provider based in Hong Kong. We are looking for talented candidates to join us. If you are passionate about blockchain technology and want a new fresh start for your career path, LET US KNOW YOU!\n\nYour role:\n\n\u00a0\u00a0\u00a0\u00a0\u00a0\u00a0Gather end-user\u2019s requirement\n\u00a0\u00a0\u00a0\u00a0\u00a0\u00a0Develop crypto wallet Front-end application\n\u00a0\u00a0\u00a0\u00a0\u00a0\u00a0Coding and testing technical solutions from scratch\n\u00a0\u00a0\u00a0\u00a0\u00a0\u00a0Work in Tsimshatsui\u00a0\n\nWe look for:\n\n\u00a0\u00a0\u00a0\u00a0\u00a0\u00a01 year or above web application development experiences with using React.Js or Vue.Js, fresh graduates are also welcome\n\u00a0\u00a0\u00a0\u00a0\u00a0\u00a0High Diploma or above in computer science, software engineering, or other related disciplines\n\u00a0\u00a0\u00a0\u00a0\u00a0\u00a0Well knowledge in web technologies such as WebSocket, HTTPS, HTML5 & CSS\n\u00a0\u00a0\u00a0\u00a0\u00a0\u00a0Related experience working on browser extensions (chrome manifest v2/v3, web extensions, etc) is a huge advantage\n\u00a0\u00a0\u00a0\u00a0\u00a0\u00a0Previous working in Fintech, or Financial Service industries are preferable\n\u00a0\u00a0\u00a0\u00a0\u00a0\u00a0Strong passion for cryptocurrency space and blockchain technology\u00a0\n\u00a0\u00a0\u00a0\u00a0\u00a0\u00a0Desire to learn, diligent, passionate, responsible, and good team player\n\u00a0\u00a0\u00a0\u00a0\u00a0\u00a0Proficiency in spoken and written English, Cantonese, and Mandarin\n\nWe offer:\n\n\u00a0\u00a0\u00a0\u00a0\u00a0\u00a0Attractive remuneration package with performance bonus\n\u00a0\u00a0\u00a0\u00a0\u00a0\u00a0Privilege insurance plan for group medical (covers clinical, hospitalization with supplementary major medical) & dental\n\u00a0\u00a0\u00a0\u00a0\u00a0\u00a05-day work week, flexible working hours\n\u00a0\u00a0\u00a0\u00a0\u00a0\u00a0Convenient office location in Tsimshatsui\n\u00a0\u00a0\u00a0\u00a0\u00a0\u00a0Work with the young and energetic team which value opinions and efforts\n\u00a0\u00a0\u00a0\u00a0\u00a0\u00a0Opportunities to participate in blockchain projects\n\u00a0\u00a0\u00a0\u00a0\u00a0\u00a0Free snacks, coffee, and tea\n\u00a0\u00a0\u00a0\u00a0\u00a0\u00a0Festival red packets and gifts\n\u00a0\u00a0\u00a0\u00a0\u00a0\u00a0Employee referral bonus\n\u00a0\u00a0\u00a0\u00a0\u00a0\u00a0Regular staff activities\n\nIf you are interested in this position and want to get new exposure in the Fintech industry, please don\u2019t hesitate to apply with your full resume, present/expected salary, and availability by clicking on the 'Apply Now' button.\u00a0\n\nAll personal data collected will be\u00a0treated in strict confidence\u00a0and used for recruitment purposes only.", "employment_types": ["Full Time", "Permanent"], "selling_points": ["Blockchain Crypto e-wallet project Vue.Js React.Js", "Passionate Diligent Responsible Good team sprit", "An energetic team that value efforts and opinions"], "locations": ["Tsim Sha Tsui"], "categories": ["Banking / Finance", "Financial Services", "Information Technology (IT)", "Application Specialist - Software", "Software Development"], "post_time": "2022-01-15T13:59:50Z", "salary": {"currency": null, "max": null, "min": null, "period": "monthly", "term": null}, "salary_visible": false, "title_keywords": ["analyst programmer", "developer"], "responsibilities": ["software", "coding", "testing", "develop", "application development"], "requirements": {"degrees": ["high diploma or above"], "majors": ["related disciplines", "software engineering", "computer science"], "languages": ["cantonese", "english", "mandarin"], "language_level": ["proficiency"], "hard_skills": ["blockchain", "web application development", "crypto", "web", "react", "web technologies", "cryptocurrency", "css", "scratch"], "soft_skills": ["passionate", "good team player", "responsible", "passion for", "diligent", "passionate about"], "languages_combined": [{"language": "cantonese", "language_level": ["proficiency"]}, {"language": "english", "language_level": ["proficiency"]}, {"language": "mandarin", "language_level": ["proficiency"]}]}, "experience_required": {"duration": ["1 year"], "field": ["related", "application development"]}}, {"job_id": "100003009053068", "location_code": "hk", "company": "Orient Overseas Container Line Ltd (OOCL)", "job_title": "Technical Analyst - Software Development", "description": "Responsibilities:\n\nAnalyze user requirements, perform feasibility studies and impact analysis\nPerform technical design, development, unit testing and development integration testing to deliver high performance, scalable, flexible and reliable software systems\nWork with project teams from oversea to perform system integration, testing and production environment setup, deployment and release\nProduce high quality deliverables based on thorough understanding of business requirements\nProvide technical supports during system development and production roll-out\u00a0\n\nRequirements (Java):\n\nUniversity graduate in Information Technology or related disciplines\nAt least 2 year of Java and JavaEE application development project experience\nSolid experience in programming Rich Internet Application (JavaScript, JSON, CSS, SOAP/RESTful web services)\nSolid understanding of object-oriented programming principles and design\nKnowledge of Software Development Life Cycles, requirement study, design walk-through and release control process\nGood command of spoken and written English, Putonghua is an advantage\n\nCandidate with more experience will be considered as Senior Technical Analyst\n\nRequirements (Cloud Native):\n\nUniversity graduate with major in Information Technology or related disciplines\u00a0\nAt least 2 years\u2019 experience in application development using Spring Boot with Spring Cloud framework on Kubernetes\u00a0\nSolid experience in developing micro-services / event-driven architecture application\u00a0\nHands on experience on ReactJS / Vue.js\u00a0\nHands on experience on MySQL / MongoDB / Redis\u00a0\nHands on experience on low-code application platform and RPA is a big advantage\u00a0\nInnovative and strong analytical skill\u00a0\nDesire to research and use new technology\u00a0\nGood command of spoken and written English, Putonghua is an advantage\u00a0\nCandidate with more experience will be considered as Senior Technical Analyst\n\nPlease send your application letter with detailed resume and expected salary by clicking \"Apply Now\" and quote the reference number on the subject\n\n(Data collected will be used for recruitment purpose only)\u00a0", "employment_types": ["Full Time", "Permanent"], "selling_points": ["Exposure to full development life cycle", "Team player; Initiative; Proactive", "5-day work week + Benefits"], "locations": ["Shatin Area"], "categories": ["Information Technology (IT)", "Application Specialist - Software", "Support", "Software Development"], "post_time": "2022-01-17T05:33:52Z", "salary": {"currency": null, "max": null, "min": null, "period": "monthly", "term": null}, "salary_visible": false, "title_keywords": ["analyst"], "responsibilities": ["technical supports", "software", "analysis", "systems", "teams", "quality", "design", "testing", "setup"], "requirements": {"degrees": ["university graduate"], "majors": ["related disciplines", "information technology"], "languages": ["putonghua", "english"], "language_level": ["advantage", "good command"], "hard_skills": ["java", "analytical skill", "code", "rpa", "javascript", "programming", "spring", "css", "web services"], "soft_skills": ["analytical skill", "hands on", "innovative", "driven", "detailed"], "languages_combined": [{"language": "putonghua", "language_level": ["advantage", "advantage", "good command", "good command"]}, {"language": "english", "language_level": ["good command", "good command"]}]}, "experience_required": {"duration": ["at least 2 years", "at least 2 year"], "field": ["application development", "developing", "programming"]}}, {"job_id": "100003009053030", "location_code": "hk", "company": "Moov", "job_title": "iOS Developer, Hong Kong", "description": "Your New Role\n\nResponsible for implementation, maintenance, and release of our iOS music service applications\nImplement app functionalities based on product requirements under iteration cycles and participate in R&D and prototyping\nEnsure that architectural design and solution can balance business needs and technical/security standards\n\nWhat makes you succeed\n\nUniversity Graduate or High Diploma in Computer Science or related discipline\nMinimum 2+ years of relevant experience\nStrong knowledge and hands-on experience in both Swift and Objective C\nSolid understanding of the full mobile development life cycle\nGood problem solving and analytical skills\nOrganized, self-motivated and teamwork oriented\nCandidate with more experience will be considered as senior position", "employment_types": ["Full Time"], "selling_points": [], "locations": ["Kowloon Bay"], "categories": ["Information Technology (IT)", "Application Specialist - Software", "Software Development", "Technical / Functional Consulting"], "post_time": "2022-01-17T05:13:27Z", "salary": {"currency": null, "max": null, "min": null, "period": null, "term": null}, "salary_visible": false, "title_keywords": ["developer"], "responsibilities": ["implementation", "maintenance", "design"], "requirements": {"degrees": ["high diploma", "university graduate"], "majors": ["computer science"], "languages": [], "language_level": [], "hard_skills": ["r&d", "maintenance", "analytical skills", "problem solving", "mobile", "c", "swift"], "soft_skills": ["organized", "self-motivated", "responsible", "teamwork", "problem solving and analytical skills", "hands-on"], "languages_combined": []}, "experience_required": {"duration": ["minimum 2+ years"], "field": ["relevant experience"]}}, {"job_id": "100003009053055", "location_code": "hk", "company": "Pathos Consultancy Limited", "job_title": ".NET Analyst Programmer- PERM role Fresh Graduates are welcome", "description": "The Company\nOur client\u00a0is providing professional financial services in Hong Kong. They are currently looking for an experienced .NET candidate to join their development team.\u00a0\n\nThe Role\n\n\nResponsible for system development and deployment\nWork closely with business users to prepare business requirements\nPrepare test plans and conduct system tests\nContributes to systems and applications specifications\nProvide post-implementation & production support to business users\nDiscusses system requirements with user departments and develops the necessary IT support required\nAble to analyst, prepare technical specification and identify possible problems and solution during project cycles\u00a0 \u00a0 \u00a0 \u00a0 \u00a0\n\nYour Profile\n\n\nDegree in Computer Science, Information Technology\u00a0or related disciplines\u00a0\nAt least one year of IT experience in .NET programming preferably in Finance services industry\nProgramming experience in .NET framework is a must, e.g. C# and ASP.Net etc.\nHighly result-oriented and focused on delivering value and benefits for the business\nIndependent, proactive, innovative and able to work under pressure\u00a0\nStrong sense of responsibility, eager to learn and a good team player\u00a0\u00a0\n\nApply Today\nTo apply online (Word attachment only), please click the 'Apply' button. Interested parties please apply with the most updated CV with expected salary and available date via JobsDB. Applicants who do not hear from us within 2 weeks may consider their applications unsuccessful.\u00a0\n\nAbout Pathos\nWe are Pathos Consultancy Limited, a boutique recruitment firm based in Hong Kong strategically placing our candidates across all levels in permanent, temporary and contract roles.\u00a0 We specialize in IT and finance roles for banking, financial services and listed MNC sectors.", "employment_types": ["Full Time", "Permanent"], "selling_points": [".NET programming experience", "Renowned company background", "Great team culture"], "locations": ["Central"], "categories": ["Information Technology (IT)", "Application Specialist - Software", "Software Development", "Network & System"], "post_time": "2022-01-17T05:27:54Z", "salary": {"currency": null, "max": null, "min": null, "period": "monthly", "term": null}, "salary_visible": false, "title_keywords": ["analyst programmer"], "responsibilities": ["plans", "specifications", "systems", "implementation"], "requirements": {"degrees": ["degree"], "majors": ["related disciplines", "computer science", "information technology"], "languages": [], "language_level": [], "hard_skills": ["deployment", "programming", "c#"], "soft_skills": ["responsible"], "languages_combined": []}, "experience_required": {"duration": ["at least one year"], "field": ["programming", "it experience"]}}, {"job_id": "100003009053077", "location_code": "hk", "company": "Solvians (Asia) Limited", "job_title": "Tech Lead/ System Analyst/ Application Development Manager | Java, Spring", "description": "Solvians is a Germany-based Fintech Company executing high quality, demanding projects for the world's leading investment banks. Our focus is on data management and the conception, design and marketing of websites developed to give investors access to financial markets information.\u00a0We are looking for personalities who believe in high commitment to their work and see success as team result.\u00a0\n\n\nYour profile\n\nYou are an experienced, passionate and enthusiastic Java master\nYou love elegant and highly effective code and prefer to find an easy solution for complex problems\nReactive Programming principles challenge you\nYou have experiences in TDD and are ready to implement your knowledge and share it with the teammates\nYou know how Mongo DB work, and have fun becoming a proper expert in that\nYou are familiar with Docker containerization\nYou like to work in a team and are willing to drive it to success\n\nWe are looking forward to welcoming you to our team! Please apply now, send us your CV and certificates mentioning your starting date and your salary expectations!\n\nYou will enjoy\n\nA permanent and challenging employment as Java Developer in our Hong Kong office\nA well-established IT company with designated clients\nOpportunity to have a real impact in the shaping of our products\nUse of new technologies\nAn established IT-company with designated clients\nAn exciting job with almost no travel activities\n100% fun to work in an international, motivated and pleasant team\nFlat hierarchy and friendly you-culture\nWork-Life Balance\nContinuous professional training\nMany extras like beverages for free and team events\n\nYour challenge\n\nTogether with a team of highly qualified and dedicated Java Developers, you will realize and implement complex and sophisticated projects using Java 8-11. You will be encouraged to apply TDD. You will participate actively in our conceptual and agile development process and take over the responsibility for our high code quality and in-time and bug-free completion of our software projects. Using the current web standards and latest technologies is part of your success.\n\nYou may find further information about Solvians on our website www.solvians.com.\u00a0", "employment_types": ["Full Time", "Permanent"], "selling_points": ["5-Day work, Agile team, International Fintech co.", "Work-Life Balance, Training Budget, Great Benefit", "Java/ TDD/ Spring/ JEE/ Jenkins/ Docker/ k8s"], "locations": ["Central & Western Area"], "categories": ["Banking / Finance", "Others", "Information Technology (IT)", "Application Specialist - Software", "Software Development"], "post_time": "2022-01-17T16:20:59Z", "salary": {"currency": null, "max": null, "min": null, "period": "monthly", "term": null}, "salary_visible": false, "title_keywords": ["system analyst", "manager", "lead"], "responsibilities": ["management", "software", "data", "quality", "agile development", "design", "website", "executing"], "requirements": {"degrees": ["master"], "majors": [], "languages": [], "language_level": [], "hard_skills": ["java", "no", "data management", "agile", "fun", "web standards", "programming", "code", "focus"], "soft_skills": ["passionate", "sophisticated", "agile", "pleasant", "motivated", "friendly", "enthusiastic", "focus"], "languages_combined": []}, "experience_required": {"duration": [], "field": ["it"]}}, {"job_id": "100003009056170", "location_code": "hk", "company": "Osmium Consulting Group Limited", "job_title": "Senior/Mobile Developer ( iOS/ Android/Flutter/React Native ) | FinTech", "description": "Responsibilities\n\nDevelopment of iOS/ Android mobile application\nTechnical system design, development and UAT\nRequirement analysis and documentation\nCoordinate with offshore team on system development and implementation\nWork closely with internal & external parties to collect and analyze their requirements\n\nRequirements\n\nHigher Diploma or above in Technology, Computer Science, Engineering or related disciplines\nSolid experience in mobile software development on iOS or Android platform\nExperience in Kotlin, Java - Android / Swift - iOS platform / Flutter, React Native - Hybrid\nFresh graduates with programming background and strong motivation to learn will be considered\nExperienced candidates will be considered for a senior position\nFamiliar with Agile development methodology is a definite advantage\n\nWhat we can provide\n\nDouble Pay\nDiscretionary Performance Bonus\nLife Insurance\nMedical insurance\nFree Snacks and Drinks", "employment_types": ["Full Time", "Permanent"], "selling_points": ["FinTech/Crypto industry", "Fully work form home plan", "New Tech & Technical"], "locations": ["Tsim Sha Tsui"], "categories": ["Information Technology (IT)", "Application Specialist - Software", "Software Development", "UI/UX Designer"], "post_time": "2022-01-18T03:28:29Z", "salary": {"currency": "HKD", "max": 54999, "min": 30000, "period": "monthly", "term": null}, "salary_visible": true, "title_keywords": ["developer"], "responsibilities": ["system design", "uat"], "requirements": {"degrees": ["higher diploma or above"], "majors": ["related disciplines", "engineering", "computer science"], "languages": [], "language_level": [], "hard_skills": ["java", "agile", "analysis", "swift", "mobile", "react native", "programming", "documentation", "kotlin", "android"], "soft_skills": ["agile"], "languages_combined": []}, "experience_required": {"duration": [], "field": ["software development"]}}, {"job_id": "100003009055750", "location_code": "hk", "company": "PCCW Solutions", "job_title": "Tech Talent - ICT Associate", "description": "The Job\n\nAcquire IT solutions knowledge and soft skills through on-the-job training in different high value and large scale IT projects\nBe exposed to the areas of cloud computing, digital solutions, loT, big data, enterprise applications (SAP / Oracle), software systems application, IT infrastructure operations and applications support\nExciting opportunity to gain exposure in the trending area of Data Analytics, Business Analyst, IoT, Customer Experience Journey and Block Chain\nDevelop a rewarding career in an advanced, fast-paced and multicultural environment.\n\nThe Person\n\nBachelor / Master degree in Computer Science, IT, Electronic Electrical Engineering or related disciplines with less than 2 years of full-time working experience\nGood presentation, interpersonal and communication skills\nA team player with good analytical and problem-solving skills and who relishes challenges\nGood command of spoken and written English and Chinese", "employment_types": ["Full Time"], "selling_points": [], "locations": ["Mong Kok"], "categories": ["Information Technology (IT)", "Application Specialist - Software", "Software Development", "Application Specialist - Network"], "post_time": "2022-01-18T02:55:12Z", "salary": {"currency": null, "max": null, "min": null, "period": "monthly", "term": null}, "salary_visible": false, "title_keywords": ["associate"], "responsibilities": ["software", "it infrastructure", "data", "operations", "systems", "big data", "develop"], "requirements": {"degrees": ["bachelor", "master degree"], "majors": ["related disciplines", "it", "electrical engineering", "computer science"], "languages": ["english", "chinese"], "language_level": ["good command"], "hard_skills": ["problem-solving skills"], "soft_skills": ["communication skills", "presentation", "problem-solving skills", "team player", "interpersonal"], "languages_combined": [{"language": "english", "language_level": ["good command"]}, {"language": "chinese", "language_level": ["good command"]}]}, "experience_required": {"duration": ["2 years"], "field": ["related", "it", "engineering"]}}, {"job_id": "100003009051528", "location_code": "hk", "company": "Ma Belle Jewellery Co Ltd", "job_title": "Senior Programmer / Programmer", "description": "Senior Programmer / Programmer\n\nSupport the Head of Application and Development, you will be a part of the team members in supporting and developing various application and systems with ample opportunities to work with various business projects.\n\nThe Job\n\nDefine and build systems and Apps in relation to various business channels\nEnsure quality system development is executed including system application development, maintenance, implementation and deployment\u00a0\nConduct feasibility study, system design, application development and UAT for assigned projects and system enhancement\n\nWork closely with in house experts as well as vendors to ensure quality technical integration\u00a0\n\nThe Person\n\nDegree holder in Computer, Information Technology or other related disciplines\nMinimum 2 years of system development experience\nSolid in JavaScript, MS SQL Server, SQL Server Stroed Procedure\nGood at HTML, C#.NET, ASP or PHP, MVC and BI development with good understanding of API design\nStrong analytical and problem solving skills, flexible and be able to communicate with end users and deliver projects under a tight schedule\nExperience in QlikView is an advantage but not a must\nSavvy in current web technology trend\nProficiency in spoken and written Chinese and English\nCandidates with less experience or fresh graduate will also be considered\n\nWe offer 5-day week, attractive remuneration, career advancement opportunity, medical benefit, discretionary bonus, staff purchase privileges to the right candidate. Interested parties, please\u00a0send us your full resume with current and expected salary.\n\nPersonal data collected will be used for recruitment purposes only and will be treated in strict confidence.\u00a0 Applicants not invited for interview within\u00a04 months\u00a0may consider their applications unsuccessful.", "employment_types": ["Full Time", "Permanent"], "selling_points": ["Perform system design, development & testing", "Various Project Exposure", "Fresh Graduates are welcome"], "locations": ["Tin Hau"], "categories": ["Information Technology (IT)", "Application Specialist - Software", "Software Development", "Data Scientist"], "post_time": "2022-01-16T08:05:52Z", "salary": {"currency": null, "max": null, "min": null, "period": "monthly", "term": null}, "salary_visible": false, "title_keywords": ["programmer", "senior programmer"], "responsibilities": ["uat", "maintenance", "systems", "quality", "implementation", "system design", "application development"], "requirements": {"degrees": ["fresh graduate", "degree holder"], "majors": ["related disciplines", "information technology"], "languages": ["english", "chinese"], "language_level": ["proficiency"], "hard_skills": ["qlikview", "bi", "web", "php", "ms sql server", "html", "sql", "javascript", "server", "problem solving skills", "c#"], "soft_skills": ["flexible", "analytical and problem solving skills"], "languages_combined": [{"language": "english", "language_level": ["proficiency"]}, {"language": "chinese", "language_level": ["proficiency"]}]}, "experience_required": {"duration": ["minimum 2 years"], "field": ["system development"]}}, {"job_id": "100003009051492", "location_code": "hk", "company": "Asia Airfreight Terminal Co., Ltd.", "job_title": "Programmer - Fresh graduates are welcome", "description": "Duties\n\nParticipate in the design, development, implementation and maintenance of enterprise applications\nParticipate in the project implementation and support services\nSupervise vendors to perform system development duties\n\nRequirements\n\nBachelor Degree in Computer Science or related discipline\u00a0\nKnowledge in J2EE and RDBMS (Oracle, Microsoft SQL), C#, .NET, Business Intelligence and mobile development would be an added advantage\nAbility to work independently\nGood communication, presentation, documentation and demonstrated people/vendor management skills\n\nWe offer the right incumbent attractive remuneration package including 12 days annual leave, 5-day week, double pay, performance bonus, medical scheme, life insurance, travel allowance and education subsidy.\u00a0\n\nInterested parties please send your full resume with reference no., recent and expected salary to:\u00a0Human Resources Department, Asia Airfreight Terminal Co. Ltd., 10 Chun Ping Road, Hong Kong International Airport, Lantau, Hong Kong\u00a0OR Fax to\u00a02286 0374\u00a0OR\u00a0Please click \u201cApply Now\u201d to submit your application.\n\nTo know more about AAT, please visit http://www.aat.com.hk/\n\nWe are an equal opportunity employer and welcome applications from all qualified candidates. We will not be responsible for any disclosure or the loss of personal data during transmission. All personal data collected will be used for recruitment only. Information of unsuccessful candidates will be destroyed after 3 months from the date of application.", "employment_types": ["Full Time", "Permanent"], "selling_points": ["5-day week, double pay, performance bonus", "Bachelor Degree in Computer Science", "Fresh graduates are welcome"], "locations": ["Airport Area"], "categories": ["Information Technology (IT)", "IT Project Management / Team Lead", "Software Development", "Others", "Student / Fresh Graduate / No Experience"], "post_time": "2022-01-16T04:38:40Z", "salary": {"currency": null, "max": null, "min": null, "period": "monthly", "term": null}, "salary_visible": false, "title_keywords": ["programmer"], "responsibilities": ["maintenance", "support services", "implementation", "design"], "requirements": {"degrees": ["degree", "bachelor"], "majors": ["computer science"], "languages": [], "language_level": [], "hard_skills": ["oracle", "vendor", "scheme", "sql", "mobile", "documentation", "business intelligence", "c#"], "soft_skills": ["communication", "work independently", "presentation"], "languages_combined": []}, "experience_required": {"duration": [], "field": []}}, {"job_id": "100003009053029", "location_code": "hk", "company": "PCCW Media", "job_title": "System Engineer / Cloud Engineer / DevOps Engineer (MOOV), Hong Kong", "description": "Your New Role\n\nYou will have the opportunities to manage various projects and work closely with the team to facilitate new initiatives.\n\nWork closely with internal teams to build and maintain infrastructure & best practice\nDesign and maintain hybrid cloud infrastructure in highly scalable, reliable, and cost-effective ways\nDesign and maintain CI/CD pipelines to maximize SDLC efficiency\nCreate and maintain DevOps guidelines & documentations\n\nWhat makes you succeed\n\nUniversity Graduate or High Diploma in Computer Science or related discipline\nMinimum 2+ years of relevant experience\nExperience in VM server management (VMWare, Linux, etc.)\nExperience in designing and implementing solution on AWS cloud\nKnowledge in containerization (i.e. Kubernetes, Docker)\nKnowledge in CI/CD using Jenkins and infrastructure as code\nKnowledge in network & infrastructure of on-premises is highly recommended\nKnowledge in programming and involving in SDLC is an advantage\u00a0\u00a0\u00a0\u00a0\u00a0\u00a0\u00a0\u00a0\nPassionate in learning and using new technologies\nCandidate with more experience will be considered as senior position\n\n\n\nWe offer attractive and competitive salary and benefits, an exciting work environment and excellent career development opportunities.\u00a0If you have the desire for an exciting and rewarding career, please send us your resume,\u00a0stating your present and expected salary to Human Resources Department by post, fax or clicking \"Apply Now\":\n\nPost:\u00a0\u00a0 \u00a0\u00a06/F, Goldin Financial Global Centre, 17 Kai Cheung Road, Kowloon Bay\u00a0\nFax:\u00a0\u00a0\u00a0\u00a0 (852) 2827 8322\u00a0\u00a0\n\nFor more information on other job opportunities of PCCW, please visit our website at <http://www.pccw.com/Careers/Job+Opportunities+&+Application/Current+Opportunities?language=en_US>\n\nPCCW is an equal opportunity employer and welcomes applications from all qualified candidates. Information provided will be treated in strict confidence and will only be used for recruitment-related purposes. Personal data provided by job applicants will be used strictly in accordance with the employer\u2019s privacy statement\u00a0(www.pccw.com/privacy-statement/index.page), a copy of which will be provided immediately upon request.", "employment_types": ["Full Time"], "selling_points": [], "locations": ["Kowloon Bay"], "categories": ["Information Technology (IT)", "Application Specialist - Software", "Software Development", "Technical / Functional Consulting"], "post_time": "2022-01-17T05:12:49Z", "salary": {"currency": null, "max": null, "min": null, "period": null, "term": null}, "salary_visible": false, "title_keywords": ["system engineer", "engineer"], "responsibilities": ["cost", "management", "guidelines", "infrastructure", "teams", "design", "maintain", "designing"], "requirements": {"degrees": ["high diploma", "university graduate"], "majors": ["computer science"], "languages": [], "language_level": [], "hard_skills": ["linux", "vmware", "jenkins", "pipelines", "devops", "aws", "sdlc", "programming", "server", "code", "documentations"], "soft_skills": ["passionate", "reliable", "learning"], "languages_combined": []}, "experience_required": {"duration": ["minimum 2+ years"], "field": ["management", "relevant experience"]}}, {"job_id": "100003009051404", "location_code": "hk", "company": "Mindcluster Limited", "job_title": "Frontend Software Developer", "description": "Want to work in a venture studio with boundless opportunities and future-crafting projects? Join Us!\u00a0\n\nHere we have a cluster of passionate and goal-oriented talents who strive for the acceleration of economies in the decentralized future. With extensive business networks, profound market insights and comprehensive capabilities in Digital Assets, Blockchain, Fintech and AI, we are inviting you to join our ambitious team to embark your bespoke venture journey and make a real impact with your expertise.\n\n\nWho will love this job? Someone who:\n\n\nIs willing to challenge themselves in a fast-paced environment\nHappy to work in a flexible and dynamic team with strong bonding\nIs not afraid of failure, and love to explore different possibilities\nHas great communication skills, knows how to cooperate with different team members and between different teams\nWants to work on exciting Blockchain / FinTech / AI products and projects\n\nYour responsibilities\u00a0\n\n\nDevelop and test business applications and work across full stack through the entire software development lifecycle\nCode and build high quality software and compiles to specifications and standards\nTranslates user requirements into software requirements\nApplies creative problem solving which puts software designs to life\nEnsure completion of any required documentation required such as deployment, maintenance, support and business needs\nJob Requirement\u00a0\n\nDegree holder in computer science\u00a0/ computer engineering\u00a0or other relevant disciplines\nHave experience in developing applications\nExperience with React, JavaScript, HTML, and CSS\nDeep understanding of underlying design philosophy and implementation of common web frameworks\nWrites clear, readable and maintainable code, takes ownership of the usability and quality of codes\nGood to Have:\nBasic backend knowledge and RESTful API\nBasic knowledge of cloud services (e.g. AWS)", "employment_types": ["Full Time"], "selling_points": ["Step ahead and work on future-crafting projects", "Boundless opportunities & Fast-tracked career path", "Grow with us & Embark your bespoke venture journey"], "locations": ["Kwun Tong"], "categories": ["Information Technology (IT)", "Software Development"], "post_time": "2022-01-15T14:37:51Z", "salary": {"currency": null, "max": null, "min": null, "period": "monthly", "term": null}, "salary_visible": false, "title_keywords": ["developer"], "responsibilities": ["software", "maintenance", "quality", "develop", "specifications", "documentation"], "requirements": {"degrees": ["degree holder"], "majors": ["computer engineering", "computer science"], "languages": [], "language_level": [], "hard_skills": ["restful api", "basic", "web", "react", "code", "html", "aws", "javascript", "css", "codes"], "soft_skills": ["clear", "deep"], "languages_combined": []}, "experience_required": {"duration": [], "field": ["developing"]}}, {"job_id": "100003009052285", "location_code": "hk", "company": "Ricoh Hong Kong Limited", "job_title": "System Analyst / Senior Analyst Programmer", "description": "The Job:\n\nBe a project leader to manage and deliver quality systems\u00a0\nParticipates in all stages of\u00a0Software Development Life Cycle from project Proposal to System Roll Out\nCoach the team members to\u00a0accomplish projects\u00a0\nAssists team head to monitor and control the projects\nLiaise with business users and vendors on project implementation\nProvides technical analysis and hands-on development per business needs\n\nThe Person:\n\nDegree holder in Information Systems, Computer Science or IT related disciplines\n4 \u2013 9 years solid experiences in commercial applications development with at least 5 years experiences in C#/RESTful APIs development/AJAX/JSON/XML\nWith hand-on experiences in project management and team management is highly preferred\nKnowledge in\u00a0CRM / ERP / D365 / SAP is an advantage\nFamiliar with Cloud / Agile Development and DevOps\nOrganized, self-motivated and work independently with good analytical skills\nGood command of English and Chinese\nCandidate with less experiences would be considered as\u00a0Senior Analyst Programmer\u00a0\n\nInterested parties please forward your full resume (in Microsoft Word or PDF format) with current and expect salary to the Human Resources and Administration Division, Ricoh Hong Kong Limited, by clicking \"Apply Now\" or by fax 2833 7891.\n\nInformation provided will be treated in strict confidence and only be used for recruitment related purposes. All personal data of unsuccessful candidates will be destroyed on completion of the recruitment exercise.", "employment_types": ["Full Time", "Permanent"], "selling_points": ["Be a project leader to deliver quality systems", "Participates in all stages of SDLC", "6-9yrs exps in commercial applications development"], "locations": ["Kowloon Bay"], "categories": ["Information Technology (IT)", "Application Specialist - Software", "Software Development", "Network & System"], "post_time": "2022-01-17T02:39:03Z", "salary": {"currency": null, "max": null, "min": null, "period": "monthly", "term": null}, "salary_visible": false, "title_keywords": ["system analyst", "senior analyst programmer"], "responsibilities": ["control", "software", "analysis", "systems", "monitor", "quality", "implementation", "liaise with"], "requirements": {"degrees": ["degree holder"], "majors": ["related disciplines", "it", "computer science"], "languages": ["english", "chinese"], "language_level": ["good command"], "hard_skills": ["agile", "sap", "devops", "erp", "analytical skills", "project management", "ajax", "c#"], "soft_skills": ["organized", "self-motivated", "work independently", "agile", "analytical skills", "project management"], "languages_combined": [{"language": "english", "language_level": ["good command"]}, {"language": "chinese", "language_level": ["good command"]}]}, "experience_required": {"duration": ["at least 5 years", "9 years"], "field": ["management", "development", "commercial", "project management", "team"]}}, {"job_id": "100003009051708", "location_code": "hk", "company": "ASM Technology Hong Kong Limited", "job_title": "Senior Software Engineer", "description": "Job description\nAct as a technical lead to oversee the full development lifecycle\nWork with the team to develop system enhancements / new features\nCoordinate with stakeholders to organize project expectations and liaise closely with stakeholders and build good rapport\nManage user requirements and implementation of the defined features\nProvide detailed business process and technical documentation\nDrive code quality improvement and enhance system security at code level\nSupport development projects by enforcing the practice of SCRUM methodology\nJob requirements\nDegree in Software Engineering or other IT disciplines\nAt least 3 years of experience in Software development using C# and ASP.net\nVery competent in software system analysis and design\nStrong communication skills with good command in English\nExperienced in software development project management using Agile and SCRUM framework\nWorking knowledge of engineering processes and operations will be an added advantage\nWorking knowledge in PLM/Teamcenter will be an asset\nSelf-motivated with the ability to prioritize tasks, manage requirement changes and meet schedules\nA good team-player\n\nAttractive salary and fringe benefits package will be offered to the right candidates.\n\nInterested parties please submit your application with cover letter, resume, certificate and transcripts.\n\nData collected will be used for recruitment purpose only. Suitable candidates may be referred to other vacancies within our company.", "employment_types": ["Full Time", "Permanent"], "selling_points": ["Degree in Software Engineering", "At least 3 years of experience in Software develop", "Act as a technical lead to oversee full develop"], "locations": ["Tsing Yi"], "categories": ["Information Technology (IT)", "Software Development", "Others"], "post_time": "2022-01-16T21:50:59Z", "salary": {"currency": null, "max": null, "min": null, "period": "monthly", "term": null}, "salary_visible": false, "title_keywords": ["senior software engineer"], "responsibilities": ["liaise", "quality", "implementation", "develop", "business process", "system security", "coordinate with stakeholders", "documentation"], "requirements": {"degrees": ["degree"], "majors": ["it", "software engineering"], "languages": ["english"], "language_level": ["good command"], "hard_skills": ["agile", "analysis", "project management", "scrum framework", "c#"], "soft_skills": ["communication skills", "self-motivated", "agile", "competent", "team-player", "prioritize", "project management"], "languages_combined": [{"language": "english", "language_level": ["good command"]}]}, "experience_required": {"duration": ["at least 3 years"], "field": ["software development"]}}, {"job_id": "100003008993884", "location_code": "hk", "company": "Tranthink Technology Service Limited", "job_title": "Analyst Programmer / System Analyst (Java & Server-oriented)", "description": "Design and implement server-side systems.\nEnhance existing components\nWilling to learn new technologies\nGuide junior programmers and do code reviews\nSkills & Requirements\nStrong in JAVA\nStrong in Spring stack, Mybatis or Hibernate\nMust have experiences in version control tools (GIT/SVN)\nFamiliar with RDBMS solutions (Oracle/MSSQL/PostgreSQL)\nExperienced in building tools (Gradle/Maven) and building systems (Jenkins/Hudson/Gitlab CI)\nReliable and cooperative personalities\nPriority considers:\nExperienced in High concurrency programming\nExperienced in Java performance tuning\nFamiliar with Microservices, NoSQL, Big Data and MQ\n3 years or above experiences\nInterested parties, please click \"Apply Now\" for application.\n\nPersonal data collected will be used for recruitment purpose only.\n\n#JAVA #SQL #Spring #Dubbo #Microservices\n", "employment_types": ["Full Time", "Permanent"], "selling_points": ["5 Days Work, Double Pay, Medical Insurance", "Flexible working hours, Free snack", "Must have exp in version control tools (GIT/SVN)"], "locations": ["Lai Chi Kok"], "categories": ["Information Technology (IT)", "Software Development", "Network & System", "Others"], "post_time": "2022-01-16T21:50:02Z", "salary": {"currency": null, "max": null, "min": null, "period": "monthly", "term": null}, "salary_visible": false, "title_keywords": ["analyst programmer", "server", "system analyst"], "responsibilities": ["control", "systems", "big data", "design"], "requirements": {"degrees": [], "majors": [], "languages": [], "language_level": [], "hard_skills": ["java", "hibernate", "git", "jenkins", "microservices", "mssql", "spring", "programming", "server", "code", "oracle"], "soft_skills": ["cooperative", "reliable", "willing to learn"], "languages_combined": []}, "experience_required": {"duration": ["3 years"], "field": []}}, {"job_id": "100003009055878", "location_code": "hk", "company": "Links International", "job_title": "Analyst Programmer", "description": "Responsibilities\n\nDevelop and maintain system and applications\nParticipate in the core banking system development and implementation\nPerform coding, testing, and debugging in different stages\nConduct system implementation, configuration and deployment\nPerform ad hoc assignments as required\n\nRequirements\n\nDegree holder or above in Computer Science, Information Technology, or relevant discipline\nMinimum 2 years hands-on application development experience\nExperience in banking/financial projects is highly preferred\nExperience working for core banking projects is an advantage\nHands-on experience in Java and database such as SQL Server, Oracle, etc.\nKnowledge in VB.net and UNIX shell script programming are added advantages\nStrong communication skills, proactive and able to work under pressure\nFluency in spoken and written Cantonese and English", "employment_types": ["Full Time", "Permanent"], "selling_points": ["2 yrs hands on Java development", "Exp. in BFS projects is an advantage", "Familiar with Agile practice"], "locations": ["Not Specified"], "categories": ["Information Technology (IT)", "Application Specialist - Software", "IT Project Management / Team Lead", "Software Development"], "post_time": "2022-01-18T03:02:43Z", "salary": {"currency": "HKD", "max": 34999, "min": 30000, "period": "monthly", "term": null}, "salary_visible": true, "title_keywords": ["analyst programmer"], "responsibilities": ["configuration", "implementation", "coding", "develop", "testing", "maintain", "ad hoc assignments", "banking"], "requirements": {"degrees": ["degree holder"], "majors": ["computer science", "information technology"], "languages": ["cantonese", "english"], "language_level": ["fluency"], "hard_skills": ["java", "sql", "programming", "server", "unix shell", "oracle"], "soft_skills": ["communication skills", "hands-on", "proactive", "work under pressure"], "languages_combined": [{"language": "cantonese", "language_level": ["fluency"]}, {"language": "english", "language_level": ["fluency"]}]}, "experience_required": {"duration": ["minimum 2 years"], "field": ["sql", "database", "banking", "application development", "financial"]}}, {"job_id": "100003009056073", "location_code": "hk", "company": "Tata Consultancy Services Limited", "job_title": "Senior Solution\u202fArchitect \u2013 Cloud & Innovation", "description": "Principal responsibilities:\u00a0\n\u00a0\n\n\nWork with technical leads,\u00a0engineers\u00a0and other Solution/domain architects to define architecture solution design for digital products and services, which meets the business needs and is cost effective.\u00a0\n\nConvert requirements into actionable product/service requirements that feed Technology solutions development & influence service direction.\u00a0\n\nResponsible for ensuring solutions are aligned with the platform architecture and roadmap, group standards and policies and the overall enterprise architecture for their function.\u00a0\n\nAccountable for overall design & integrity of set of systems/apps to support specific products, services & customer journeys.\u00a0\n\nAccountable for the architecture governance and design authority for the development of the products and services in line with the published roadmap.\u00a0\n\nResponsible for engaging and leading the enterprise architecture and design practice at the\u00a0DevSecOps\u00a0team level.\u00a0\n\nWork with the Service Quality Manager and control functions to ensure that architecture solutions are \"fit for purpose\" and \"fit for use\".\u00a0\n\nWork with Ops Engineers to ensure operational issues (performance, operator intervention, alerting, design defect related issues,\u00a0etc) are resolved and that any design related issues are addressed in a timely manner.\u00a0\n\nQualifications\u00a0\n\nRequirements:\u00a0\n\n\nDegree or above in a technology,\u00a0engineering\u00a0or science related disciplines.\u00a0\nMinimum 10 years solution architect experience in digital transformation especially banking applications.\u00a0\n\nIn-depth knowledge in one or more technology domains: digital, mobile, data, analytic, API and Cloud Computing.\u00a0\n\nTOGAF certificate would be an advantage.\u00a0\n\nExcellent communication and interpersonal skills, with strong oral, written and presentation skills.\u00a0\n\nStrong analytical, problem solving, negotiation, influencing skills and possess logical and critical thinking in architecture.\u00a0\n\nExpert level of relevant IT architecture,\u00a0strategy\u00a0or solution design experience in delivery role in financial services environment.\u00a0\n\nEnd to end application architecture knowledge with focus on non-functional requirements that are critical in financial service applications.\u00a0\nProficiency in both English and Chinese, Putonghua speaking is an advantage.\u00a0", "employment_types": ["Permanent"], "selling_points": ["Minimum 10 years solution architect experience.", "digital, mobile, data, analytic, API and Cloud.", "Proficiency in both English and Chinese"], "locations": ["Others"], "categories": ["Information Technology (IT)", "Software Development"], "post_time": "2022-01-18T03:14:52Z", "salary": {"currency": null, "max": null, "min": null, "period": "monthly", "term": null}, "salary_visible": false, "title_keywords": [], "responsibilities": ["cost", "control", "policies", "systems", "quality", "a timely manner", "design", "architecture"], "requirements": {"degrees": ["certificate", "degree or above"], "majors": ["related disciplines", "science", "engineering"], "languages": ["putonghua", "english", "chinese"], "language_level": ["advantage", "proficiency"], "hard_skills": ["problem solving", "mobile", "focus"], "soft_skills": ["oral", "negotiation", "problem solving", "presentation skills", "communication and interpersonal skills", "focus"], "languages_combined": [{"language": "putonghua", "language_level": ["proficiency"]}, {"language": "english", "language_level": ["advantage", "proficiency"]}, {"language": "chinese", "language_level": ["advantage", "proficiency"]}]}, "experience_required": {"duration": ["minimum 10 years"], "field": ["design", "solution architect", "it", "financial services", "banking", "digital"]}}, {"job_id": "100003009052975", "location_code": "hk", "company": "Recruit Logic Limited", "job_title": "Java Developer - MNC - 30-35K", "description": "Job Purpose:\nResponsible for developing and maintaining application software\nParticipate in user requirement analysis, design, build, documentation, rollout and support.\nLarge scale project in general insurance industry with good exposure on new Agile methodology and core policy, front end and business process management systems.\nMain Responsibilities:\u00a0\nApply IT knowledge on application software development to deliver values according to customer needs.\nParticipate in Agile environment and ensure development standard and practice followed properly.\nCo-ordinate\u00a0 with internal teams, users and external vendors to ensure deliverables are meeting the requirement.\nEnsure smooth production rollout.\nHandle user queries and production support including bug fixes and enhancements.\nGain up-to-date on technologies and experience to perform more complex requirement analysis and technical design.\nActs as backup to supervisor.\nPerform ad hoc projects as assigned by supervisor\nIncumbent Requirements:\na. \u00a0 \u00a0 Academic & Professional Qualifications\nUniversity graduate in Information Technology, Computer Science or equivalent.\n\u00a0b. \u00a0 \u00a0Experience\nRelevant experience in software development is preferred\n\u00a0c. \u00a0 \u00a0Knowledge & Skill Required\nGood analytical, problem solving and organizing skills.\nGood team player, strong writing and communication skills.\nMature, independent, work with minimal supervisions and able to deliver quality results\nd. \u00a0 \u00a0 Sound technical knowledge\nSQL Queries , MS SQL Server, Oracle DB\nJava J2EE multi-tier architecture\nAngular JS, HTML, CSS, XML, JSON\nRestful API\nApache, JBoss Server 7\nEclipse, Maven\nGIT, JMeter\n\u00a0\n\nPlease note that only shortlisted candidates will be notified.", "employment_types": ["Full Time", "Permanent"], "selling_points": ["Java Developer - Business/FinTech firm", "Java, C/C++, NodeJS", "Minimum 1 year of experience"], "locations": ["Sheung Wan"], "categories": ["Information Technology (IT)", "DBA", "Support", "Software Development"], "post_time": "2022-01-17T04:47:07Z", "salary": {"currency": "HKD", "max": 44999, "min": 30000, "period": "monthly", "term": null}, "salary_visible": true, "title_keywords": ["developer"], "responsibilities": ["software", "analysis", "teams", "design", "ad hoc projects"], "requirements": {"degrees": ["university graduate"], "majors": ["computer science", "information technology"], "languages": [], "language_level": [], "hard_skills": ["java", "restful api", "apache", "git", "professional qualifications", "ms sql server", "html", "problem solving", "sql", "c", "angular", "server", "css", "oracle"], "soft_skills": ["communication skills", "good team player", "independent", "mature", "problem solving"], "languages_combined": []}, "experience_required": {"duration": [], "field": ["relevant experience", "software development"]}}, {"job_id": "100003009050189", "location_code": "hk", "company": "ICO Limited", "job_title": "Java Programmer", "description": "Development of web and server applications.\nRectify reports issues,\u00a0Problem solver & Solutions Provider.\nCooperate with other development and operation teams\nRequirements:\n\nDegree / Diploma in Computer Science or related disciplines\n5+ yrs or above solid working experience in using NodeJS, Javascript, MySQL, C#, AWS\nExperience/Knowledge in responsive web development using ReactJS\nAble to work independently and under pressure\nSelf-motivated, good command of English and Chinese\n\n(Those with more experience will be considered for senior position)\n\n\nBenefits:\n\n14 days Paid Annual Leave\nBirthday leave and special holiday leave.\n5-day work and bank holidays\n\nPlease send your cover letter, personal portfolio\u00a0(if any and provide share drive link to download instead of attachment, attachment larger than 1MB may be dropped), and\u00a0resume with last and expected salary to us \u00a0 andy.chan @sky88tech.com or apply\u00a0via Jobsdb.com\n\n", "employment_types": ["Full Time"], "selling_points": ["Project exposure in bank and commerical projects", "13 months salary", "1 year of Java, JavaScript, SQL development"], "locations": ["Wan Chai Area"], "categories": ["Information Technology (IT)", "Application Specialist - Software", "Support", "Software Development"], "post_time": "2022-01-15T19:11:41Z", "salary": {"currency": null, "max": null, "min": null, "period": "monthly", "term": null}, "salary_visible": false, "title_keywords": ["programmer"], "responsibilities": ["teams", "reports", "cooperate with"], "requirements": {"degrees": ["diploma", "degree"], "majors": ["related disciplines", "computer science"], "languages": ["english", "chinese"], "language_level": ["good command"], "hard_skills": ["web development", "web", "aws", "javascript", "server", "c#"], "soft_skills": ["work independently", "self-motivated", "under pressure", "problem solver", "responsive"], "languages_combined": [{"language": "english", "language_level": ["good command"]}, {"language": "chinese", "language_level": ["good command"]}]}, "experience_required": {"duration": [], "field": ["development"]}}, {"job_id": "100003009052441", "location_code": "hk", "company": "Haitong International Securities Group Limited", "job_title": "Quantitative Analyst (VP to SVP) - Trading (Ref. no.: JDB/TRD/QA/VP_SVP)", "description": "Responsible for server systems development, testing and bug fixing\nWilling to learn new technologies (ELK, Dubbo, Docker..)\nMay perform other duties as assigned\nSkills & Requirements\nFoundation level in JAVA and SQL\nExperienced in version control tools (GIT/SVN)\nReliable and cooperative personalities\nWilling to learn and work with new technologies\nFresh Graduate will also be considered\nPriority considers:\nExperienced in Spring stack\nFoundation level in Microservices, Cache, Big Data and MQ\nPlease click \"Apply Now\" to submit your application.\n\nPersonal data collected will be used for recruitment purpose only.\n\n#JAVA #SQL #Spring #Dubbo #Microservices", "employment_types": ["Full Time", "Permanent"], "selling_points": [], "locations": ["Central"], "categories": ["Banking / Finance", "Financial Services", "Information Technology (IT)", "Support", "Software Development"], "post_time": "2022-01-17T03:02:17Z", "salary": {"currency": null, "max": null, "min": null, "period": null, "term": null}, "salary_visible": false, "title_keywords": ["analyst"], "responsibilities": ["perform other duties", "control", "systems", "big data", "testing", "recruitment", "personal data"], "requirements": {"degrees": ["fresh graduate"], "majors": [], "languages": [], "language_level": [], "hard_skills": ["java", "git", "microservices", "sql", "spring", "server"], "soft_skills": ["cooperative", "reliable", "willing to learn", "responsible"], "languages_combined": []}, "experience_required": {"duration": [], "field": []}}, {"job_id": "100003009052580", "location_code": "hk", "company": "Sun Life Hong Kong Ltd", "job_title": "Senior Manager, Data Management", "description": "Job Description:\nDevelop, maintain and enhance for internal system applications\nTroubleshoot software development problems\nPrepare system documentation(s) on the developed systems and provide application support\nProvide support on user acceptance tests and perform user support\nHandle ad hoc tasks as assigned by supervisor\nJob Requirements:\nDegree or above in Computer Science or related disciplines\nAt least 5 year working experience in software development\nWith hands on experience in Angular and JAVA Spring Boot is a MUST\nKnowledge in C#, Python, HTML5, Docker, Nginx and Android platform, AWS Services (Lambda, API Gateway, S3), WECOM API, Crystal Reports would be an advantage\nMobile development experience is preferable\nExcellent analytical, organizing & communication skills\nGood interpersonal communication and presentation skills\nGood command in both spoken and written English and Chinese\nGood team player with self-initiative, open-minded and willing to learn\nWe\u00a0offer\u00a0attractive remuneration package to the right candidate. Interested parties please click the \"APPLY NOW\" button below and send your application together with a detailed resume including current & expected salary and availability to Human Resources Department.\nCompany website:\u00a0https://www.lawsgroup.com\n(Data collected will be treated in strict confidence and used for recruitment purpose only)", "employment_types": ["Full Time", "Permanent"], "selling_points": ["Data Governance experiences", "Experience in designing data structure", "Machine Learning and AI"], "locations": ["Hung Hom"], "categories": ["Information Technology (IT)", "Software Development", "Others", "Data Scientist"], "post_time": "2022-01-17T03:28:11Z", "salary": {"currency": null, "max": null, "min": null, "period": "monthly", "term": null}, "salary_visible": false, "title_keywords": ["senior manager"], "responsibilities": ["provide support", "software", "systems", "ad hoc tasks", "develop", "maintain", "troubleshoot"], "requirements": {"degrees": ["degree or above"], "majors": ["related disciplines", "computer science"], "languages": ["english", "chinese"], "language_level": ["good command"], "hard_skills": ["java", "aws", "mobile", "spring", "angular", "python", "s3", "android", "c#"], "soft_skills": ["communication skills", "good team player", "open-minded", "willing to learn", "communication", "presentation skills", "hands on", "self-initiative", "interpersonal"], "languages_combined": [{"language": "english", "language_level": ["good command"]}, {"language": "chinese", "language_level": ["good command"]}]}, "experience_required": {"duration": ["at least 5 year"], "field": ["development", "software development"]}}, {"job_id": "100003009054641", "location_code": "hk", "company": "China Mobile Hong Kong \u4e2d\u570b\u79fb\u52d5\u9999\u6e2f", "job_title": "Business Analyst/Senior Business Analyst", "description": "Responsibilities\n\nParticipate in system design, development, testing, and implementation of financial system\nSupport projects and mainteance of internal system applications\nWork closely with end-users/stakeholders to collect user requirements\n\nRequirements\n\nDiploma or above in Computer Science, Information Technology or relevant disciplines\n1-2 years experience in system development\nExperience in banking/finance project is a plus\nProficient in Oracle SQL, PL/SQL\nKnowledge in Oracle APEX\nGood communication and interpersonal skills\nCapability to work under pressure and working in a team/independently\nFluency in Cantonese and English", "employment_types": ["Full Time", "Permanent"], "selling_points": ["3 years related working experience", "Bachelor Degree in IT/Business Analyst", "Excellent career development with good benefit"], "locations": ["Kwai Hing"], "categories": ["Information Technology (IT)", "IT Management", "Software Development", "Network & System"], "post_time": "2022-01-17T10:23:16Z", "salary": {"currency": null, "max": null, "min": null, "period": null, "term": null}, "salary_visible": false, "title_keywords": ["senior business analyst", "business analyst"], "responsibilities": ["support projects", "financial system", "implementation", "testing", "system design"], "requirements": {"degrees": ["diploma or above"], "majors": ["computer science", "information technology"], "languages": ["cantonese", "english"], "language_level": ["fluency"], "hard_skills": ["plus", "apex", "sql", "pl", "oracle"], "soft_skills": ["independently", "communication and interpersonal skills", "work under pressure"], "languages_combined": [{"language": "cantonese", "language_level": ["fluency"]}, {"language": "english", "language_level": ["fluency"]}]}, "experience_required": {"duration": ["1-2 years"], "field": ["finance", "banking", "system development"]}}, {"job_id": "100003009051270", "location_code": "hk", "company": "Letlink Technology Limited", "job_title": "Full Set Magento2 Developer", "description": "Executive Summary:\nGlobal firm with footprint across North America and Europe with Headquarter in HK\nPublicly Listed company - Annual global sales turnover at 6 Billion USD\nEstablished for 30 years with solid stable work culture and puts people first\nAround 600 staffs in Hong Kong office and IT team around 50 staffs.\nStable work culture for longer term career development\nGrade A office \u2013 5 mins from MTR\nMajor Responsibilities:\nDevelop interactive and modern user interfaces using the frontend technologies such as React, Angular, Vue.JS with the digital communication team\nIntegrate internal and third-party APIs using provided documentation\nWrite solid, tested, and well-documented code that is easy to read, scalable and easy to share with other developers\nUse component-based approach to analyze design handover files and follow that structure when building the web applications\nBuild restful API\u2019s using Drupal 9+ and maintain an information-rich API documentation\nUse version control (git) to push and track code changes in a timely manner and use branch strategies to collaborate with other developers\nProactively monitor infrastructure to ensure web applications are in good performance\nKey Requirements\nHigher Diploma holder in Computer Science, Information Systems or related disciplines\nAt least 2-5 years\u2019 experience in HTML, CSS, Javascript working on production level projects\nExperience with PHP frameworks and Drupal is desirable\nFamiliar with oAuth2 authentication method, implementation in the backend and exploitation on the frontend\nFamiliar with React.js, hooks, Restful APIs and handling JSON format data\nExcellent understanding of modern Javascript\nKnowledge on mobile app development (native or hybrid), Wordpress would be a plus\nStrong project management, analytical, technical, and problem-solving skills with critical thinking\nGood command of written and spoken English\nTo apply, please send your CV in word document to Gloria(a)endeavourasia.com or call 3956-1829 for a confidential discussion.", "employment_types": ["Full Time"], "selling_points": [], "locations": ["Shatin Area"], "categories": ["Information Technology (IT)", "Software Development", "Network & System", "Technical Writing"], "post_time": "2022-01-15T07:00:57Z", "salary": {"currency": null, "max": null, "min": null, "period": "monthly", "term": null}, "salary_visible": false, "title_keywords": ["developer"], "responsibilities": ["collaborate with", "control", "infrastructure", "a timely manner", "monitor", "design", "develop", "communication", "maintain", "documentation"], "requirements": {"degrees": ["higher diploma holder"], "majors": ["related disciplines", "computer science"], "languages": ["english"], "language_level": ["good command"], "hard_skills": ["plus", "react", "php", "problem-solving skills", "word", "html", "mobile", "wordpress", "javascript", "project management", "css"], "soft_skills": ["problem-solving skills", "project management"], "languages_combined": [{"language": "english", "language_level": ["good command"]}]}, "experience_required": {"duration": ["at least 2-5 years"], "field": []}}, {"job_id": "100003009052965", "location_code": "hk", "company": "David James Recruitment Limited", "job_title": "Automation QA Engineer \u2013 Crypto/FX Trading Platforms \u2013 HKD$30k-60k", "description": "Our client is an international Fintech Company that owns millions of customer data.\u00a0\n\nIt strives to transform into a data-driven organization and is investing a lot in expanding their technology team and\u00a0using cutting edge technologies including Azure/GCP/AWS, AI, NLP, Tableau and Power BI.\n\nThis role will provide the candidate opportunity for extensive\u00a0data engineering and analysis experience with a large set of customer data. If you are interested to develop you career path in Big Data/ Data Engineer domain to bring business value and further expand the organization footprint regionally, this is the opportunity for you:\n\nResponsibility:\n\u2022 build data pipelines on Cloud Platform(Data engineer focus)\u00a0\n\u2022 Construct data flow to transform unstructured data to structured data from multiple data source\u00a0\n\u2022 Be responsible for\u00a0\u00a0Internal communications with technical and non-technical parties for business requirements and technical enquiries.\n\u2022 Deploy projects by using CI / CD on Cloud Devops\n\u2022 Support and manage data requests from business stakeholders \u2013 can understand business change needs and assess the impact of those changes\n\u2022 Able to do ETL and build data pipeline to feed data into data lake, data factory\u00a0\n\u2022 Collaborate closely with\u00a0development and product teams in a fast-paced delivery environment\n\u2022 AI projects\u00a0\n\nRequirement:\n\u2022 2+ years of experience with data engineer\u00a0\n\u2022 7+ years of exp would be Data Lead\u00a0\n\u2022 1 year + of experience with Azure/GCP/AWS (for junior role, cloud is not the must)\n\u2022 Experience with data warehouse, data lake, data pipelines design and building\n\u2022 Self-starter, Self-organized, Problem solver, deliver projects from scratch\n\u2022 English, Cantonese and Mandarin", "employment_types": ["Full Time"], "selling_points": ["3-6 years in Automation QA", "Young and Energetic Working Environment", "Exposure to crypto exchange platform"], "locations": ["Not Specified"], "categories": ["Information Technology (IT)", "Application Specialist - Software", "Software Development", "Testing / QA"], "post_time": "2022-01-17T04:43:14Z", "salary": {"currency": null, "max": null, "min": null, "period": "monthly", "term": null}, "salary_visible": false, "title_keywords": ["engineer"], "responsibilities": ["collaborate", "communications with", "data", "teams", "deploy"], "requirements": {"degrees": [], "majors": [], "languages": ["cantonese", "english", "mandarin"], "language_level": [], "hard_skills": ["azure", "data warehouse", "pipelines", "aws", "scratch"], "soft_skills": ["organized", "problem solver"], "languages_combined": [{"language": "cantonese", "language_level": []}, {"language": "english", "language_level": []}, {"language": "mandarin", "language_level": []}]}, "experience_required": {"duration": ["2+ years", "1 year +"], "field": ["design"]}}, {"job_id": "100003009051888", "location_code": "hk", "company": "Automated Systems (HK) Ltd", "job_title": "Mobile App Developer / Senior Mobile App Developer", "description": "Responsibilities & Duties\n\nBuild and maintain web applications for a yacht rental, travel and leisure booking platform\nDevelop and enhance current backend system based on the features defined by product owners\nPerform user acceptance test (UAT) for various systems and websites\nOptimize website functionality and spot out bugs to ensure platform\u2019s functionality\nExecute day-to-day website function enhancement and maintenance\nImplement any new APIs and optimization of existing APIs\nBuild UI based on design by writing clean front-end code\nUnderstand requirements to build a user friendly application with extendable functionalities\n\nRequirements\n\nAt least 2 years of experience in overall software development\nDegree or above in Computer Science / Information Technology or related disciplines\nHands-on experience in web back-end and/or front-end development\nExperience in Laravel and Vue.js, JavaScript, HTML, CSS\nStrong knowledge in API and website tracker implementation\nAble to develop clean and maintainable code, that is highly performant and secure by design\nStrong project management, analytical, technical and problem-solving skills with critical thinking\nPerformance bonus will be vested based on milestones reached", "employment_types": ["Full Time", "Contract"], "selling_points": ["Opportunities for your career promotion every year", "Have opportunities to try different projects", "Become part of our talented and core team members"], "locations": ["Not Specified"], "categories": ["Information Technology (IT)", "Application Specialist - Software", "Software Development", "Mobile / Wireless Communications"], "post_time": "2022-01-17T01:27:12Z", "salary": {"currency": null, "max": null, "min": null, "period": "monthly", "term": null}, "salary_visible": false, "title_keywords": ["developer"], "responsibilities": ["uat", "maintenance", "systems", "website", "design", "develop", "maintain", "booking", "ui"], "requirements": {"degrees": ["degree or above"], "majors": ["related disciplines", "computer science", "information technology"], "languages": [], "language_level": [], "hard_skills": ["clean", "web", "problem-solving skills", "code", "html", "project management", "javascript", "css"], "soft_skills": ["problem-solving skills", "project management", "hands-on"], "languages_combined": []}, "experience_required": {"duration": ["at least 2 years"], "field": ["development", "software development"]}}, {"job_id": "100003009051910", "location_code": "hk", "company": "Neo Derm (HK) Ltd", "job_title": "Technical Lead", "description": "What are you going to do as a (Senior) Backend Developer?\n\nAs a (Senior) Backend Developer, you will work in a finance company located in Kowloon. You will also be responsible in whole software development cycle, design and develop systems to connect business clients through marketing analytics tools, mobile payment, and credit card networks to boost business for them. You will work closely with R&D team to bring out new ideas for the system as well. On top of that, you will use the latest IoT technology that generates a unique algorithm, detects users' emotions, and carries out performance predictions. Techniques: PHP, Laravel, Javascript, nodejs, expressjs, reactjs, MySQL, Restful APIs,\n\nWhat is offered to you?\n\n* Monthly Salary from HKD30K - 50k up\n\n* working hour 10am - 6pm\n\n* Medical and dental allowance\n\n* Year-End Bonus\n\n* 15 annual leave\n\nWhat is expected of you?\n\n* Higher Diploma or Degree in Computer Science, IT, Engineering or equivalent\n\n* Hands-on experience with PHP Laravel/ Javascript nodejs\n\n* Minimum 3 years of experience in System development\n\n* Good command of written and verbal English and Chinese\n\nWhere are you going to work?\n\nYou are going to work in a well-established payment solution company that has been in the market for more than ten years that provides B2B secured payment platform. Your company focuses on developing modern infrastructure to connect different merchants through mobile payment, card network tools to boost business growth. They have overseas offices in Asia: Shanghai, Bangkok, Tokyo, etc. Right now they are actively extending their business to western Europe and northern America for further development. You will be working in a young and fun environment with a flat structure.\n\nLearn more or apply directly?\n\nHow do you feel about this Job? Are you ready for the challenges in this Company? You can apply directly, click on the 'Apply' button. For more information about this vacancy or other opportunities, you can contact me at cheryl.ng@ambitiouspeople.com or call me on 3511 6201.", "employment_types": ["Full Time", "Permanent"], "selling_points": ["5yr system development + 3yr team lead experience", "Hands-on MySQL, MongoDB, SQL Server", "Vue.js,React.js,Angular.js,Node.js,JavaScript"], "locations": ["Tai Koo"], "categories": ["Information Technology (IT)", "Application Specialist - Software", "IT Management", "Software Development"], "post_time": "2022-01-17T01:30:10Z", "salary": {"currency": null, "max": null, "min": null, "period": "monthly", "term": null}, "salary_visible": false, "title_keywords": ["lead"], "responsibilities": ["analytics tools", "year-end", "ideas", "software", "systems", "design and develop", "developing", "infrastructure", "payment", "contact"], "requirements": {"degrees": ["diploma", "degree"], "majors": ["it", "engineering", "computer science"], "languages": ["english", "chinese"], "language_level": ["good command"], "hard_skills": ["r&d", "analytics tools", "fun", "php", "mobile", "javascript"], "soft_skills": ["unique", "hands-on", "responsible"], "languages_combined": [{"language": "english", "language_level": ["good command"]}, {"language": "chinese", "language_level": ["good command"]}]}, "experience_required": {"duration": ["minimum 3 years"], "field": ["system development"]}}, {"job_id": "100003009047018", "location_code": "hk", "company": "iASPEC Services Limited", "job_title": "Software Engineer", "description": "Participate in development life cycle\nJoin team meetings and come up with plans based on user requirements\nDesign and implement according to the defined plans\nCollaborate with teammates to ensure requirement fulfilment\nTroubleshoot the problems users face\n\nThe Successful Applicant\n\n\nDegree holder in Computer Science or related disciplines\nProficient in JavaScript ES6+, Node.js, MySQL/MariaDB/MongoDB\nHands-on experience in AWS, React\nIn-depth knowledge and troubleshooting of Linux/Unix is a plus\nExperience in Ansible, Elasticsearch, Kafka is a plus\nGood attention in details\nGood team player with excellent communication skills\nSelf-motivated with positive and proactive mindset\nFast learner with passion in modern technologies\nInterested parties please send your\u00a0full resume with expected salary\u00a0and\u00a0your availability\u00a0to us.\n\n\nAll personal data collected will be treated strictly confidential and used for recruitment purposes only.", "employment_types": ["Full Time"], "selling_points": [], "locations": ["Shatin Area"], "categories": ["Information Technology (IT)", "Software Development"], "post_time": "2022-01-14T02:02:44Z", "salary": {"currency": null, "max": null, "min": null, "period": "monthly", "term": null}, "salary_visible": false, "title_keywords": ["software engineer"], "responsibilities": ["collaborate with", "troubleshooting", "design", "communication", "troubleshoot", "plans"], "requirements": {"degrees": ["degree holder"], "majors": ["related disciplines", "computer science"], "languages": [], "language_level": [], "hard_skills": ["linux", "plus", "react", "aws", "ansible", "javascript"], "soft_skills": ["communication skills", "good team player", "self-motivated", "passion in", "troubleshooting", "hands-on", "troubleshoot", "proactive", "fast learner", "positive"], "languages_combined": []}, "experience_required": {"duration": [], "field": []}}, {"job_id": "100003009047556", "location_code": "hk", "company": "Quantr Limited", "job_title": "Programmer (Fresh Graduates are welcome)", "description": "Responsibilities\nAssist the Department Head to oversee the Applications Development team for performing functions such as application development, database design and support, etc.\nSupervise the team members in analyzing user requirements, conducting system design and programming, implementing system enhancements, and preparing system documentations\nLead and manage various projects\nRequirements\nUniversity degree or above in Computer Science or related disciplines\nAt least 8 years experience in applications development of which minimum 3 years in managerial role preferably gained in banking and finance industry\nBe proficient in database design and project management\nResult-oriented, self-motivated, strong leadership, good communication and interpersonal skills\nAble to work independently and well under pressure\nBenefits\nDouble Pay\nDiscretionary Bonus\nInsurance Benefits\nStudy Subsidy\nApplication Method:\nBy E-mail via \"Apply Now\"", "employment_types": ["Full Time", "Contract"], "selling_points": [], "locations": ["Lai Chi Kok"], "categories": ["Information Technology (IT)", "Application Specialist - Software", "Software Development"], "post_time": "2022-01-14T03:27:08Z", "salary": {"currency": null, "max": null, "min": null, "period": "monthly", "term": null}, "salary_visible": false, "title_keywords": ["programmer"], "responsibilities": ["application development", "system design", "database", "design"], "requirements": {"degrees": ["degree or above"], "majors": ["related disciplines", "computer science"], "languages": [], "language_level": [], "hard_skills": ["project management"], "soft_skills": ["self-motivated", "work independently", "under pressure", "project management", "communication and interpersonal skills", "leadership", "result-oriented"], "languages_combined": []}, "experience_required": {"duration": ["at least 8 years", "minimum 3 years"], "field": ["development", "managerial", "finance industry", "banking"]}}, {"job_id": "100003009051393", "location_code": "hk", "company": "Meta Air Labs Limited", "job_title": "System Analyst / Analyst Programmer (Backend - Blockchain) - Expansion", "description": "Key Responsibilities:\u00a0\n\n\nResponsible for the analysis, design, documentation, development, unit testing, and support of database ETL and report development for software applications\u00a0\n\nDesign, develop, test, tune, and implement ETL processes, SSRS Reports, SQL\u00a0queries, stored procedures\u00a0\n\nMaintain good working knowledge of industry trends, products, relevant laws and regulations.\u00a0\n\nJob Requirements:\u00a0\u00a0\n\nDegree holder in Computer science, information technology or related discipline\u00a0\n\nProven experience in system analysis and design\u00a0\n\nStrong Knowledge of Data Warehousing methodologies and concepts\u00a0\n\nRelevant experience in a report development and business intelligence.\u00a0\n\nProficient in\u00a0SQL Server Integration Service (SSIS),\u00a0SQL Server Reporting Services (SSRS)\u00a0\u00a0\n\nPossession of banking business knowledge, Temenos T24 Core Banking Solution,\u00a0Temenos Analytics,\u00a0PowerBI\u00a0is an advantage\u00a0\n\nSolid analytical and problem-solving skills\u00a0\n\nGood communication in English and Chinese\u00a0", "employment_types": ["Full Time", "Permanent"], "selling_points": ["Blockchain crypto e-wallet project, Golang", "Passionate Deligent Responsible Good team sprit", "An energetic team that value efforts and opinions"], "locations": ["Tsim Sha Tsui"], "categories": ["Banking / Finance", "Financial Services", "Information Technology (IT)", "Application Specialist - Software", "Software Development"], "post_time": "2022-01-15T13:57:42Z", "salary": {"currency": null, "max": null, "min": null, "period": "monthly", "term": null}, "salary_visible": false, "title_keywords": ["analyst programmer", "system analyst"], "responsibilities": ["regulations", "software", "analysis", "procedures", "design", "testing", "develop", "maintain", "reports", "database", "documentation", "report"], "requirements": {"degrees": ["degree holder"], "majors": ["computer science", "information technology"], "languages": ["english", "chinese"], "language_level": ["good"], "hard_skills": ["integration", "analysis", "sql", "server", "problem-solving skills", "business intelligence"], "soft_skills": ["communication", "problem-solving skills"], "languages_combined": [{"language": "english", "language_level": ["good"]}, {"language": "chinese", "language_level": ["good"]}]}, "experience_required": {"duration": [], "field": ["development", "business", "relevant experience", "design"]}}]