[{"job_id": "100003009053469", "location_code": "hk", "company": "Info-Tech Systems Integrators (HK) Limited", "job_title": "Customer Service Consultant", "description": "Responsibilities:\n\nProvide technical/ desk side support including Windows, Mac, Smart Phone and Virtual Conferencing, for end users\nShare best practices to end users\nSupport and troubleshoot in IT operations issues including the operations of in-house systems\nAssist to handle any ad-hoc projects upon request by line manager\n\nRequirements:\n\nDiploma or above in Computer Science/Information Technology/ Information Systems or related disciplines\n1 year's relevant in IT support operations, Windows Server Administration, Systems/Network supports and troubleshooting\nKnowledge in SQL database language will be advantageous\nProactive with a \u2018can-do\u2019 attitude, willingness to learn, good communication skills, customer service oriented, and good problem-solving skills\nGood command in spoken and written English and Mandarin\n\n\nWe offer attractive remuneration package including work from home policy, 13-instalment salary, discretionary bonus,\u00a0life, medical, dental and eyecare insurances to the right candidate.\u00a0Interested\u00a0applicants\u00a0please send\u00a0your\u00a0detailed\u00a0resume with current and expected salary and the\u00a0availability to Human Resources Department by clicking \"APPLY NOW\"\u00a0or by post:\n\n\nHuman Resources Department\nCurrys Sourcing Limited\n31/F, AXA Tower, Landmark East\n100 How Ming Street, Kwun Tong\nKowloon\nPersonal Data collected will be used for recruitment purposes only. Applicants who are not invited within 2 months may consider their application unsuccessful. Personal data of unsuccessful applicants will be retained for a period of up to 6 months from the date of rejecting applicants and will then be destroyed.", "employment_types": ["Full Time", "Permanent"], "selling_points": ["5-day work", "Yearly performance bonus", "2-3 years' of IT Support/ Helpdesk experience"], "locations": ["Lai Chi Kok"], "categories": ["Information Technology (IT)", "Support"], "post_time": "2022-01-17T07:01:25Z", "salary": {"currency": null, "max": null, "min": null, "period": "monthly", "term": null}, "salary_visible": false, "title_keywords": ["customer service", "consultant"], "responsibilities": ["operations", "ad-hoc projects", "systems", "troubleshoot"], "requirements": {"degrees": ["diploma or above"], "majors": ["related disciplines", "computer science", "information technology"], "languages": ["english", "mandarin"], "language_level": ["good command"], "hard_skills": ["sql", "problem-solving skills", "windows server"], "soft_skills": ["communication skills", "customer service oriented", "troubleshooting", "can-do", "problem-solving skills", "proactive", "detailed"], "languages_combined": [{"language": "english", "language_level": ["good command"]}, {"language": "mandarin", "language_level": ["good command"]}]}, "experience_required": {"duration": [], "field": []}}, {"job_id": "100003009054429", "location_code": "hk", "company": "Currys Sourcing Limited", "job_title": "IT Support", "description": "Responsibilities:\n\nProvide technical/ desk side support including Windows, Mac, Smart Phone and Virtual Conferencing, for end users\nShare best practices to end users\nSupport and troubleshoot in IT operations issues including the operations of in-house systems\nAssist to handle any ad-hoc projects upon request by line manager\n\nRequirements:\n\nDiploma or above in Computer Science/Information Technology/ Information Systems or related disciplines\n1 year's relevant in IT support operations, Windows Server Administration, Systems/Network supports and troubleshooting\nKnowledge in SQL database language will be advantageous\nProactive with a \u2018can-do\u2019 attitude, willingness to learn, good communication skills, customer service oriented, and good problem-solving skills\nGood command in spoken and written English and Mandarin\n\n\nWe offer attractive remuneration package including work from home policy, 13-instalment salary, discretionary bonus,\u00a0life, medical, dental and eyecare insurances to the right candidate.\u00a0Interested\u00a0applicants\u00a0please send\u00a0your\u00a0detailed\u00a0resume with current and expected salary and the\u00a0availability to Human Resources Department by clicking \"APPLY NOW\"\u00a0or by post:\n\n\nHuman Resources Department\nCurrys Sourcing Limited\n31/F, AXA Tower, Landmark East\n100 How Ming Street, Kwun Tong\nKowloon\nPersonal Data collected will be used for recruitment purposes only. Applicants who are not invited within 2 months may consider their application unsuccessful. Personal data of unsuccessful applicants will be retained for a period of up to 6 months from the date of rejecting applicants and will then be destroyed.", "employment_types": ["Full Time", "Permanent"], "selling_points": ["Attractive Remuneration Package", "Comprehensive Wellbeing Programme", "Work-life Balance"], "locations": ["Kwun Tong"], "categories": ["Information Technology (IT)", "Support", "Others"], "post_time": "2022-01-17T09:30:36Z", "salary": {"currency": null, "max": null, "min": null, "period": "monthly", "term": null}, "salary_visible": false, "title_keywords": ["it support"], "responsibilities": ["operations", "ad-hoc projects", "systems", "troubleshoot"], "requirements": {"degrees": ["diploma or above"], "majors": ["related disciplines", "computer science", "information technology"], "languages": ["english", "mandarin"], "language_level": ["good command"], "hard_skills": ["sql", "problem-solving skills", "windows server"], "soft_skills": ["communication skills", "customer service oriented", "troubleshooting", "can-do", "problem-solving skills", "proactive", "detailed"], "languages_combined": [{"language": "english", "language_level": ["good command"]}, {"language": "mandarin", "language_level": ["good command"]}]}, "experience_required": {"duration": [], "field": []}}, {"job_id": "100003009054658", "location_code": "hk", "company": "OPM Systems Company Limited", "job_title": "IT Helpdesk Support / Engineer", "description": "Job Description\n\u2022Accountable for the sales of products & services, strong commitment in achieving monthly sales target with the team.\n\u2022Develop and maintain strong relationship with new and existing partners and channels\n\u2022Plan and executive Partner strategies to achieve revenue, profit and growth targets\n\u2022Initiate and drive the development of new partners\n\u2022Perform product demonstration/presentation\n\n\nJob Requirements\n\u2022Candidate must possess at least Diploma or relevant professional qualifications.\n\u2022At least 3 Year(s) of working experience in Sales, Business development. Preferably in Payroll / HR Software or any other software systems\n\u2022Strong Enterprise and Channel Sales Experience\n\u2022Independent and self driven\n\u2022Confident, high EQ, with excellent communication and sales skills\n\u2022Ability to communicate with all level of staff internally and externally\n\u2022Attractive salary package (Basic + Sales Commission + Transport allowance)\n\u2022Yearly performance bonus, appraisal, promotion & increment\n\u2022Career advancement opportunities both locally and overseas", "employment_types": ["Full Time", "Permanent"], "selling_points": ["IT Support", "Shift duties required", "Immediate available preferred"], "locations": ["Tung Chung"], "categories": ["Information Technology (IT)", "Hardware", "Support", "Technical / Functional Consulting"], "post_time": "2022-01-17T10:26:29Z", "salary": {"currency": null, "max": null, "min": null, "period": "monthly", "term": null}, "salary_visible": false, "title_keywords": ["engineer"], "responsibilities": ["sales target", "maintain"], "requirements": {"degrees": ["diploma"], "majors": [], "languages": [], "language_level": [], "hard_skills": ["basic", "professional qualifications"], "soft_skills": ["communication", "driven"], "languages_combined": []}, "experience_required": {"duration": [], "field": ["business development"]}}, {"job_id": "100003009052019", "location_code": "hk", "company": "Multisoft Limited", "job_title": "Helpdesk Engineer (IT Support Team)", "description": "Responsibilities:\n\n\nProvide technical assistance and support\nTroubleshoot desktop computers and applications\nCommunicate with hardware and software vendors to ensure the provision of effective work orders\n\nRequirements:\n\n\nHigher Diploma or above in\u00a0Information Technology, Computer Engineering, Computer Science, or related disciplines\nBasic Knowledge in Server, PC, and LAN / WAN and networking equipment\nSelf-motivated, quick learner, and strong sense of responsibility\nEffective team player and excellent interpersonal skills\nCantonese and English communication skill\nFresh Graduates with good attitude will be also considered\n\nJoin us, sketch the future with digitalization!\n\n\u00a0Interested parties please send us your detailed resume with\u00a0current and\u00a0expected salary\u00a0by clicking the link\u00a0\"APPLY NOW\".\n\nAll information provided by applicants will be used for recruitment-related purposes and handled in strict confidence by authorized personnel. The personal data collected will be destroyed after three months.\n\nFor more information about Multisoft, please visit http://www.multisoft.com.hk/ or follow us on:\u00a0\nFacebook:\u00a0https://www.facebook.com/MultisoftLimited/\nYoutube:\u00a0https://www.youtube.com/user/MultisoftLimited\nLinkedin:\u00a0https://www.linkedin.com/company/multisoft-limited/", "employment_types": ["Full Time", "Permanent"], "selling_points": ["Fresh graduate welcome", "Good advancement opportunities", "On-the-job training will be provided"], "locations": ["Kwun Tong"], "categories": ["Information Technology (IT)", "Support", "Network & System", "Technical / Functional Consulting"], "post_time": "2022-01-17T01:51:46Z", "salary": {"currency": null, "max": null, "min": null, "period": "monthly", "term": null}, "salary_visible": false, "title_keywords": ["engineer", "it support"], "responsibilities": ["communicate with", "software", "hardware", "troubleshoot", "technical assistance"], "requirements": {"degrees": ["higher diploma or above"], "majors": ["related disciplines", "computer engineering", "computer science", "information technology"], "languages": ["cantonese", "english"], "language_level": [], "hard_skills": ["server", "pc", "wan", "basic"], "soft_skills": ["self-motivated", "sense of responsibility", "communication skill", "quick learner", "interpersonal skills", "team player"], "languages_combined": [{"language": "cantonese", "language_level": []}, {"language": "english", "language_level": []}]}, "experience_required": {"duration": [], "field": []}}, {"job_id": "100003009051816", "location_code": "hk", "company": "John Swire & Sons (HK) Limited", "job_title": "Technical Support Engineer", "description": "Responsibilities:\n\nResponsible for system operations and administration of OSSs and NMSs that supports SmarTone's 2G/3G, LTE and IMS mobile network surveillance and operations\nAssist in system administration activities and in-house programming development\nTrouble-shooting on hardware / software and hands-on problem diagnosis for end users.\nParticipate OSS major upgrade/ migrations project execution\nLiaise with vendor for all sorts of system hardware/software troubleshooting and system recovery actions.\nProvide after office hours on-call emergency support services upon request.\n\nRequirements:\u00a0\n\nDegree in Electronic Engineering, Computer Science, Information Technology or related disciplines\n2 years\u2019 relevant experience in system administration is preferred, fresh graduates will also be considered as junior position\nSolid experience in computer operating systems such as HP Blade platform, Oracle Solaris, Linux and Window platform\nKnowledge in Shell, Perl, PHP, SQL, Python and Java Programming\nExperience in telecommunication network management systems or operations support systems is preferred\nGood interpersonal and analytical skills\nAble to work independently and under pressure\n\nInterested parties please apply with full resume stating present and expected salary by clicking \"Apply Now\" or visiting our Website:\u00a0www.smartone.com/tc/about_us/careers/\n\nSmarTone is an equal-opportunity employer. All data supplied will be kept in strict confidence and will be used for employment related purpose. We may transfer such data to any agent, contractor or third party who provides services to us with respect to matters relating to your application. Only short-listed candidates will be contacted.\n\n\nYou are welcome to visit our website :\u00a0www.smartone.com\u00a0\u00a0", "employment_types": ["Full Time"], "selling_points": ["Deliver end user support", "IT ambassador", "High diploma or above"], "locations": ["Quarry Bay"], "categories": ["Information Technology (IT)", "Support", "Network & System"], "post_time": "2022-01-17T01:16:23Z", "salary": {"currency": null, "max": null, "min": null, "period": null, "term": null}, "salary_visible": false, "title_keywords": ["technical support engineer"], "responsibilities": ["migrations", "software", "operations", "support services", "troubleshooting", "hardware", "liaise with", "administration"], "requirements": {"degrees": ["degree"], "majors": ["related disciplines", "engineering", "computer science", "information technology"], "languages": [], "language_level": [], "hard_skills": ["linux", "oracle", "java", "network management", "php", "analytical skills", "sql", "programming", "python", "perl"], "soft_skills": ["work independently", "under pressure", "interpersonal", "analytical skills"], "languages_combined": []}, "experience_required": {"duration": ["2 years"], "field": ["management", "relevant experience", "administration"]}}, {"job_id": "100003009055904", "location_code": "hk", "company": "Manpower Services (Hong Kong) Limited", "job_title": "IT Support / System Administrator (15K-50K) (URGENT)", "description": "Responsibilities\u00a0\n\nBe the subject matter expert to drive eCommerce marketing, online retention business performance and end-to-end operationfor the company.\n\u00a0Lead an eCommerce team\nto manage, plan and implement digital strategies for online retention campaigns of mobile and broadband services and day-to-day eCommerce campaigns to meet different business targets\nto ensure seamless operations from customer service, vendors to back-end logistic in order to deliver a top-notch digital customer experience\nWork closely with other digital team members to enhance UI/UX, introduce effective customer features and streamline the ecommerce and online retention journey to optimize funnel and improve conversion ratios\nPlay a key role in planning and executing digital transformation projects, along with different stakeholders within the company, to increase operation efficiency, improve customer\u00a0engagement and expand the scope of online business for the company.\n\n\u00a0Requirements\n\n\nDegree in eCommerce or related disciplines with 8 years+ experience in eCommerce industry.\nHands-on experience in operating a full-functioned online shop for a B2C brand is a must.\nExperience in subscription based services would be a definite advantage.\nPassionate towards new digital trend, internet technology and social media savvy, highly analytical and data-driven decisioning are essential.\nProven track record of content collaboration with renowned agencies, content producers and influencers would be ideal.\nWell-versed in Google Marketing Platforms, Facebook Ads Manager, Google Analytics, Salesforce Marketing Cloud, Cognos BI, Tableau are highly preferred.\nProblem solver with strong project management skills to meet tight deadlines.\nExcellent written and spoken English and Chinese.\n\nSmarTone is an equal-opportunity employer. All data supplied will be kept in strict confidence and will be used for employment related purpose. We may transfer such data to any agent, contractor or third party who provides services to us with respect to matters relating to your application. Only short-listed candidates will be contacted.\n\n\nYou are welcome to visit our website :\u00a0www.smartone.com\u00a0", "employment_types": ["Contract"], "selling_points": ["0-6 years + experience", "Public Sector, stable career", "5-day work"], "locations": ["Aberdeen"], "categories": ["Information Technology (IT)", "Support"], "post_time": "2022-01-18T03:04:23Z", "salary": {"currency": null, "max": null, "min": null, "period": "monthly", "term": null}, "salary_visible": false, "title_keywords": ["system administrator", "it support"], "responsibilities": ["operations", "subject matter expert", "customer service", "executing", "plan", "digital strategies", "ui", "planning"], "requirements": {"degrees": ["degree"], "majors": ["ecommerce", "related disciplines"], "languages": ["english", "chinese"], "language_level": ["excellent"], "hard_skills": ["google analytics", "bi", "salesforce", "tableau", "project management", "facebook"], "soft_skills": ["passionate", "meet tight deadlines", "confidence", "problem solver", "project management skills", "hands-on", "driven", "ideal"], "languages_combined": [{"language": "english", "language_level": ["excellent"]}, {"language": "chinese", "language_level": ["excellent"]}]}, "experience_required": {"duration": [], "field": ["ecommerce", "brand", "related"]}}, {"job_id": "100003009054037", "location_code": "hk", "company": "NEC Hong Kong Limited", "job_title": "System Engineer", "description": "Responsibilities:\n\n\nResponsible for full project lifecycle with vendor management\nDefine project scope and communicate effectively to cross functional team\nDevelop, track and update project status using appropriate project management techniques and tools (e.g. meetings, status tracking tools)\nIdentify project issues and risk and develop projects scopes, plans, schedules and budget\nManage resources and risks, escalate potential issues to management\nFacilitate onsite construction co-ordination, meetings and supervision works\nProactively drive solutions to problems while involving key stakeholders\nObtain appropriate information necessary for the proper carrying out and completion of the project in accordance with the contract conditions\nIdentify gaps in the contract and support VO discussion with Sales\n\nRequirements:\n\n\nHD holders or above in in Mechanical/ Electrical Engineering/ Building Service\nAt least 5 years practical experience in E&M design and co-ordination, prefer in client or consultant side\nKnowledge of building and interior fitting-out works is required\nPC and AutoCAD knowledge\nExperience for luxury residential development and house is an advantage\nGood leadership and communication skills, able to works with people at all levels, strong in coordination with contractor\nClose attention to details and ability to handle multi-tasks\nExperience in IoT and network cabling structure is a plus\nWith valid Construction Industry Safety Training Certificate (commonly known as \"Green Card\") would be advantage or obtain a certificate within 1 month\nComplete Safety Supervisor certificate by an authorized institution within 3 months\nGood command of written and spoken English and Cantonese\n\nInterested parties please apply with full resume stating our reference code, present and expected salary by clicking \"Apply Now\"\u00a0via JobsDB\n\nYou are welcome to visit our website :\u00a0www.smartone.com\u00a0\n\nSmarTone is an equal-opportunity employer. All data supplied will be kept in strict confidence and will be used for employment related purpose. We may transfer such data to any agent, contractor or third party who provides services to us with respect to matters relating to your application. Only short-listed candidates will be contacted.", "employment_types": ["Full Time", "Permanent"], "selling_points": ["Servers/SAN/desktop configuration & troubleshoot", "Network Infrastructure design & support is a plus", "Knowledge in systems configuration and VMware"], "locations": ["Not Specified"], "categories": ["Engineering", "Engineering Project Management", "Information Technology (IT)", "Support", "Network & System"], "post_time": "2022-01-17T08:09:12Z", "salary": {"currency": null, "max": null, "min": null, "period": "monthly", "term": null}, "salary_visible": false, "title_keywords": ["system engineer"], "responsibilities": ["management", "schedules", "budget", "develop", "project management", "plans", "tracking"], "requirements": {"degrees": ["certificate"], "majors": [], "languages": ["cantonese", "english"], "language_level": ["good command"], "hard_skills": ["pc", "plus", "green card", "autocad"], "soft_skills": ["communication skills", "multi-tasks", "attention to details", "coordination", "leadership"], "languages_combined": [{"language": "cantonese", "language_level": ["good command"]}, {"language": "english", "language_level": ["good command"]}]}, "experience_required": {"duration": ["at least 5 years"], "field": ["development", "design"]}}, {"job_id": "100003009054797", "location_code": "hk", "company": "IKEA", "job_title": "IT Technical Specialist (infrastructure)", "description": "Responsibilities:\n\nLead the small team to provide onsite/remote technical support\nResponsible for support, configure, testing the IoT, 5G router, AI camera, etc.\nLearn new technologies and provide training to internal users and customers\n\n\u00a0Requirements:\n\n\nDegree holder in Computer Science or related discipline is preferable\n5+ years working experience, with 2 years\u2019 experience in Linux platform\n3 years\u2019 experience in network support (e.g. Router, VPN configuration, Trouble shooting)\nExperience in application servers configuration, e.g. Apache, Tomcat, NGINX\nGood in problem solving and communication skills\nSelf-initiative, teamwork and passionate working attitude\n\nInterested parties please apply with full resume stating present and expected salary by clicking \"Apply Now\" or visiting our Website:\u00a0www.smartone.com/tc/about_us/careers/\n\nSmarTone is an equal-opportunity employer. All data supplied will be kept in strict confidence and will be used for employment related purpose. We may transfer such data to any agent, contractor or third party who provides services to us with respect to matters relating to your application. Only short-listed candidates will be contacted.\n\n\nYou are welcome to visit our website :\u00a0www.smartone.com\u00a0\u00a0", "employment_types": ["Full Time", "Permanent"], "selling_points": ["First tier support service of IT infrastructure", "Monitor daily infrastructure or applications", "Participate in IT infrastructure projects"], "locations": ["Shatin Area"], "categories": ["Information Technology (IT)", "Support", "IT Management", "Others"], "post_time": "2022-01-17T11:08:03Z", "salary": {"currency": null, "max": null, "min": null, "period": "monthly", "term": null}, "salary_visible": false, "title_keywords": ["technical specialist"], "responsibilities": ["technical support", "provide training", "testing"], "requirements": {"degrees": ["degree holder"], "majors": ["computer science"], "languages": [], "language_level": [], "hard_skills": ["linux", "apache", "servers", "router", "problem solving", "vpn"], "soft_skills": ["passionate", "communication skills", "teamwork", "problem solving", "self-initiative"], "languages_combined": []}, "experience_required": {"duration": ["3 years", "2 years", "5+ years"], "field": []}}, {"job_id": "100003009047135", "location_code": "hk", "company": "ShinePlus Technology (Hong Kong) Limited", "job_title": "IT Support Engineer", "description": "Responsibilities:\n\nAssist supervisor to conduct system development, support of intelligent bandwidth management and AAA/\u00a0Radius\u00a0platforms\nAssure high system availability with proactive performance monitoring\nConduct system evaluation and testing for new applications or new features\nProvide 7x24 emergency support for fast system fault resolutions\nHandle fault or compliant analysis in related to service enabling systems\nProvide technical support to business marketing on corporate solution\n\n\u00a0Requirements:\n\nDegree, Higher Diploma or equivalent in Electronic Engineering, Computer Science or Telecommunications\nKnowledge in Router, Ethernet Switch, Load Balancer, Firewall, Security, Internet Protocols, Network Management tools\nHands-on experience in Unix/Linux environment and shell script programming will be an advantage\nGood problem solving skill, self-motivated, proactive to learn and able to work independently\nGood communications skill in both English and Cantonese\nWilling to perform work or support outside office hour\nFresh graduates will also be considered", "employment_types": ["Full Time", "Permanent"], "selling_points": ["1 to 3 years\u2019 experience and above in IT projects", "5 days work/week, Medical insurance, Bonus, WFH", "Good verbal & writing skill in Cant./Mandarin/Eng."], "locations": ["Tin Hau"], "categories": ["Information Technology (IT)", "Support", "Network & System"], "post_time": "2022-01-15T19:11:33Z", "salary": {"currency": null, "max": null, "min": null, "period": "monthly", "term": null}, "salary_visible": false, "title_keywords": ["it support engineer"], "responsibilities": ["management", "technical support", "analysis", "monitoring", "systems", "testing", "evaluation"], "requirements": {"degrees": ["diploma", "degree"], "majors": ["engineering", "computer science"], "languages": ["cantonese", "english"], "language_level": ["good"], "hard_skills": ["network management", "linux", "switch", "router", "problem solving", "programming", "firewall"], "soft_skills": ["work independently", "self-motivated", "hands-on", "problem solving skill", "proactive"], "languages_combined": [{"language": "cantonese", "language_level": ["good"]}, {"language": "english", "language_level": ["good"]}]}, "experience_required": {"duration": [], "field": ["programming"]}}, {"job_id": "100003009052512", "location_code": "hk", "company": "China Mobile Hong Kong \u4e2d\u570b\u79fb\u52d5\u9999\u6e2f", "job_title": "Assistant IT System Manager", "description": "Responsibilities\n\nUnderstand research users\u2019 business questions and translate into a valid research study with clear research objectives\nPerform both quantitative and qualitative customer analyses with innovative and actionable solutions\nProvide customer segmentation analysis and identify threats and opportunities for each customer group\nGenerate insights from vast volume internal customer data, match with market research to provide a holistic view on the whole customer journey\nWork closely with research users, vendors and other key stakeholders on project coordination, evaluation of performance and brainstorm action plans\n\n\u00a0Requirements\n\nUniversity graduates of marketing or related disciplines with minimum 1 year\u2019s relevant experience in research and data analysis.\nStrong project management skill and experience in research execution including quality assurance\nStrong in PC skills (excel, powerpoint)\nKnowledge in statistical tools (COGNOS, SPSS, R) or data visualization tool (Tableau) will be an advantage\nProficient in both Chinese and English writing\nGood team player, outgoing, self-motivated, flexible and independent", "employment_types": ["Full Time", "Permanent"], "selling_points": ["Degree in Information Technology/Computer Science", "7+ years experience with IT Infrastructure", "Competitive pay, Good fringe benefits"], "locations": ["Kwai Hing"], "categories": ["Information Technology (IT)", "Support", "IT Management", "Network & System"], "post_time": "2022-01-17T03:17:34Z", "salary": {"currency": null, "max": null, "min": null, "period": null, "term": null}, "salary_visible": false, "title_keywords": ["system manager", "assistant"], "responsibilities": ["project coordination", "analysis", "market research", "customer data", "evaluation", "plans"], "requirements": {"degrees": [], "majors": [], "languages": ["english", "chinese"], "language_level": ["proficient"], "hard_skills": ["excel", "analysis", "powerpoint", "tableau", "project management", "data visualization", "r", "pc skills"], "soft_skills": ["outgoing", "flexible", "good team player", "self-motivated", "independent", "project management skill"], "languages_combined": [{"language": "english", "language_level": ["proficient"]}, {"language": "chinese", "language_level": ["proficient"]}]}, "experience_required": {"duration": ["minimum 1 year"], "field": ["research", "related", "data analysis", "project management", "marketing", "relevant experience", "quality assurance"]}}, {"job_id": "100003009054534", "location_code": "hk", "company": "Asia Airfreight Terminal Co., Ltd.", "job_title": "System Support Officer - Fresh graduates are welcome", "description": "Responsibilities:\nAssist in formulating product and service strategies, marketing offers, and implement new service launch\nIdentify and develop new business opportunities\nResponsible on day-to-day operations, including data mining and analysis, sales operational support and monitoring, etc\nExpand and manage outreach channels of existing customers\nClosely work with various internal departments for marketing materials to support the launch\nMonitor competitors and customer analysis; keep track on the market trend\nMonitor and evaluate business performance against target. Study customer profiles and usage pattern, and to draw insights on business development\n\u00a0\u00a0Requirements:\nDegree holder, major in Marketing, Business Studies, or relevant disciplines\nMinimum 5 years\u2019 relevant experience, preferably gained in telecommunication / technology industry\nExcellent command of written and spoken Chinese (Cantonese) / English\nPossess strong ownership, entrepreneurial working style\nCreative, confident, outgoing with initiatives and self-motivated\nStrong project management and negotiation skills. Ability to multi-task and prioritize the tasks in a fast-paced market situation\nCandidate with less experience will be considered as Marketing Executive\n\n\nInterested parties please apply with full resume stating present and expected salary by clicking \"Apply Now\" or visiting our website:\u00a0www.smartone.com/tc/about_us/careers/\n\n\nSmarTone is an equal-opportunity employer.\u00a0 All data supplied will be kept in strict confidence and will be used for employment related purpose.\u00a0 We may transfer such data to any agent, contractor or third party who provides services to us with respect to matters relating to your application. Only short-listed candidates will be contacted.\n\nYou are welcome to visit our website :\u00a0smartone.com\u00a0", "employment_types": ["Full Time", "Permanent"], "selling_points": ["5-day week, 12 days annual leave, double pay", "Fresh graduates are welcome", "Shift duty is required"], "locations": ["Airport Area"], "categories": ["Information Technology (IT)", "Support", "Network & System", "Technical / Functional Consulting"], "post_time": "2022-01-17T09:54:44Z", "salary": {"currency": null, "max": null, "min": null, "period": "monthly", "term": null}, "salary_visible": false, "title_keywords": ["officer", "system support"], "responsibilities": ["marketing materials", "develop new business", "operational support", "analysis", "monitoring", "day-to-day operations", "monitor", "evaluate", "data mining"], "requirements": {"degrees": ["degree holder"], "majors": ["business", "marketing"], "languages": ["cantonese", "english", "chinese"], "language_level": ["excellent"], "hard_skills": ["project management"], "soft_skills": ["confident", "outgoing", "self-motivated", "multi-task", "prioritize", "project management", "negotiation skills", "creative"], "languages_combined": [{"language": "cantonese", "language_level": ["excellent"]}, {"language": "english", "language_level": ["excellent"]}, {"language": "chinese", "language_level": ["excellent"]}]}, "experience_required": {"duration": ["minimum 5 years"], "field": ["marketing", "relevant experience"]}}, {"job_id": "100003009055885", "location_code": "hk", "company": "HKT Enterprise Solutions", "job_title": "System Support / Engineer", "description": "Responsibilities:\n\nResponsible for full project lifecycle with vendor management\nDefine project scope and communicate effectively to cross functional team.\nDevelop, track and update project status using appropriate project management techniques and tools (e.g. meetings, status tracking tools)\nIdentify project issues and risk, and develop projects scopes, plans, schedules and budget\nManage resources and risks, escalate potential issues to management\nProactively drive solutions to problems while involving key stakeholders\nAssist to design future process model and to build business and system requirements\nWork closely with various stakeholders to provide professional advices and recommendations on development and deployment of solutions\nTo obtain appropriate information necessary for the proper carrying out and completion of the project in accordance with the contract conditions\n\nRequirements:\n\n\nDegree holders or above in Computer Science, IT or related disciplines\nOver 3 years' experience in customer project management\nSound knowledge in network, enterprise and IoT solution with customization experience\nExcellent communications and interpersonal skills\nClose attention to details and ability to handle multi-tasks\nSelf-starter/highly motivated team player\nGood command of written and spoken Chinese and English\nPMP Certified\nCertificate Holders of CCNA / CCNP / MCSE or cloud services would be advantage\nExperience in building services or construction field is a plus\n\nInterested parties please apply with full resume stating our reference code, present and expected salary by clicking \"Apply Now\"\u00a0via JobsDB\n\nYou are welcome to visit our website :\u00a0www.smartone.com\u00a0\n\nSmarTone is an equal-opportunity employer. All data supplied will be kept in strict confidence and will be used for employment related purpose. We may transfer such data to any agent, contractor or third party who provides services to us with respect to matters relating to your application. Only short-listed candidates will be contacted.", "employment_types": ["Full Time"], "selling_points": [], "locations": ["Wan Chai"], "categories": ["Information Technology (IT)", "Support", "Network & System"], "post_time": "2022-01-18T03:03:08Z", "salary": {"currency": null, "max": null, "min": null, "period": "monthly", "term": null}, "salary_visible": false, "title_keywords": ["system support", "engineer"], "responsibilities": ["management", "schedules", "budget", "design", "develop", "project management", "plans", "tracking"], "requirements": {"degrees": ["certificate", "degree"], "majors": ["related disciplines", "it", "computer science"], "languages": ["english", "chinese"], "language_level": ["good command"], "hard_skills": ["mcse", "plus", "ccnp", "ccna", "project management", "pmp"], "soft_skills": ["multi-tasks", "project management", "motivated", "interpersonal skills", "attention to details", "team player"], "languages_combined": [{"language": "english", "language_level": ["good command"]}, {"language": "chinese", "language_level": ["good command"]}]}, "experience_required": {"duration": ["3 years"], "field": ["project management", "building services", "construction"]}}, {"job_id": "100003009055294", "location_code": "hk", "company": "Wellesley Associates Limited", "job_title": "IT System Administrator/ System Engineer \u2013 Financial Services - 25-40K + Bonus", "description": "Responsibilities:\n\n\nConduct pre-sales and consultative activities\nDrive\u00a0Information and Communication Technologies (ICT) solution sales to meet departmental target via professional consultancy\nUnderstand and translate business & functional requirements into solution proposals, presentations and scope of work\nProduce technical drawing and documentation based on industry standard\nWork closely with internal departments to deliver benchmark pre-sales and post-sales support to business clients\nKeep abreast of the industries focused\u00a0ICT\u00a0development and sensibly integrate them into sales pitches and eventually a solution offer\nManage joint activities with external hardware and software vendors for ICT solution\n\nRequirements:\u00a0\u00a0\n\nUniversity graduate in Information Technology or other related disciplines\n3 years' solid working experience in either ICT Solution Pre-sales Consultancy or Project Management\nHands on experience in ICT project management with different hardware and software vendors, system integrators (SI), etc\nKnowledge and experience in IoT Solution and/or\u00a0Cyber Security Practices is an absolute advantage\nExcellent\u00a0analytical and presentation skills\nGood\u00a0command of\u00a0written and spoken English and Chinese\u00a0\n\nInterested parties please apply with full resume stating our reference code, present and expected salary by clicking \"Apply Now\"\u00a0via JobsDB or\u00a0visiting our website:\u00a0www.smartone.com/tc/about_us/careers/.\n\n\nYou are welcome to visit our website :\u00a0www.smartone.com\u00a0\n\n\nSmarTone is an equal-opportunity employer. All data supplied will be kept in strict confidence and will be used for employment related purpose. We may transfer such data to any agent, contractor or third party who provides services to us with respect to matters relating to your application. Only short-listed candidates will be contacted.", "employment_types": ["Full Time"], "selling_points": ["System Administrator", "25-40K + Bonus", "Financial Services/ Good Working Culture"], "locations": ["Not Specified"], "categories": ["Information Technology (IT)", "Hardware", "Support", "Network & System"], "post_time": "2022-01-18T02:05:14Z", "salary": {"currency": null, "max": null, "min": null, "period": "monthly", "term": null}, "salary_visible": false, "title_keywords": ["system engineer", "system administrator"], "responsibilities": ["software", "presentations", "communication", "hardware", "documentation", "technical drawing"], "requirements": {"degrees": ["university graduate"], "majors": ["related disciplines", "information technology"], "languages": ["english", "chinese"], "language_level": ["good command"], "hard_skills": ["project management", "hardware", "cyber security"], "soft_skills": ["project management", "presentation skills", "hands on"], "languages_combined": [{"language": "english", "language_level": ["good command"]}, {"language": "chinese", "language_level": ["good command"]}]}, "experience_required": {"duration": ["3 years"], "field": ["project management", "security"]}}, {"job_id": "100003009054539", "location_code": "hk", "company": "PERSOLKELLY Hong Kong Limited", "job_title": "Helpdesk Support Specialist (VIP Support)", "description": "\u00a0Responsibilities:\n\nPromote\u00a0Mobile, Fixed and Information and Communication Technologies (ICT) Solutions to corporate clients\nExplore and develop enterprise solutions to fit the business needs of corporate clients\nDevelop sales leads, identify customer requirements and establish long term relationships with corporate accounts\nAchieve\u00a0assigned sales targets and objectives in\u00a0order to increase\u00a0the market share and\u00a0Company's revenue\u00a0\n\nRequirements:\u00a0\n\nTertiary education or above\n2 years of experience\u00a0in corporate sales or account servicing\nWith\u00a0ICT knowledge will be an advantage\nGood interpersonal and communication skills\nEnergetic, aggressive, pro-active and hardworking\nProficiency in written\u00a0and spoken English and Chinese;\u00a0knowledge in Mandarin is preferred\u00a0\n\nInterested parties please apply with full resume stating our reference code, present and expected salary by clicking \"Apply Now\" via JobsDB\n\n\nYou are welcome to visit our website :\u00a0www.smartone.com\u00a0\n\nSmarTone is an equal-opportunity employer. All data supplied will be kept in strict confidence and will be used for employment related purpose. We may transfer such data to any agent, contractor or third party who provides services to us with respect to matters relating to your application. Only short-listed candidates will be contacted.\n", "employment_types": ["Full Time"], "selling_points": ["VIP Helpdesk Support", "E-Commerce", "Competitive Package"], "locations": ["Central & Western Area"], "categories": ["Information Technology (IT)", "Support", "Application Specialist - Network", "Network & System"], "post_time": "2022-01-17T09:55:02Z", "salary": {"currency": null, "max": null, "min": null, "period": "monthly", "term": null}, "salary_visible": false, "title_keywords": ["specialist"], "responsibilities": ["communication", "develop"], "requirements": {"degrees": [], "majors": [], "languages": ["english", "chinese", "mandarin"], "language_level": ["proficiency"], "hard_skills": [], "soft_skills": ["communication skills", "pro-active", "energetic", "interpersonal", "hardworking"], "languages_combined": [{"language": "english", "language_level": ["proficiency"]}, {"language": "chinese", "language_level": ["proficiency"]}, {"language": "mandarin", "language_level": []}]}, "experience_required": {"duration": ["2 years"], "field": ["corporate sales", "account servicing"]}}, {"job_id": "100003009054283", "location_code": "hk", "company": "FUJIFILM Data Management Solutions Asia Limited", "job_title": "Project Manager / Assistant Project Manager", "description": "Responsibilities:\u00a0\n\nPerform month-end closing\nReview daily operational work in revenue aspect\nAssist in streamline accounting process and workflow to improve efficiency\nPerform other duties and ad hoc assignments as required\u00a0\n\n\u00a0Requirements:\n\nDegree holder in Accountancy or Finance with full qualification/student\u00a0member\u00a0in professional accounting body (HKICPA or equivalent)\nMinimum\u00a03 years\u2019 relevant work experience,\u00a0preferably with experience in audit firms\nKnowledge in HRFRS15 will be a prominent advantage\nPrevious experience in telecommunication in revenue operation is preferred\nIndependent, detailed oriented, analytical, good time management, strong communication and interpersonal skills.\nProficient in MS Office applications, particularly in MS Excel\nPrior experience in Oracle accounting system will be an advantage\nCandidates with\u00a0less experience will be considered as\u00a0\u00a0Senior Accounting Officer\n\nInterested parties please apply with full resume stating present and expected salary by clicking \"Apply Now\"\n\nSmarTone is an equal-opportunity employer. All data supplied will be kept in strict confidence and will be used for employment related purpose. We may transfer such data to any agent, contractor or third party who provides services to us with respect to matters relating to your application. Only short-listed candidates will be contacted.\n\nYou are welcome to visit our website :\u00a0www.smartone.com\u00a0", "employment_types": ["Full Time", "Permanent"], "selling_points": ["With 5-7 years\u2019 customer servicing experience", "Monitor the projects' progress and outcomes", "5-day work, 9:00am - 5:30pm"], "locations": ["Chai Wan"], "categories": ["Information Technology (IT)", "IT Project Management / Team Lead", "Support", "IT Management"], "post_time": "2022-01-17T09:02:30Z", "salary": {"currency": null, "max": null, "min": null, "period": "monthly", "term": null}, "salary_visible": false, "title_keywords": ["project manager", "assistant project manager"], "responsibilities": ["review", "month-end closing", "perform other duties", "ad hoc assignments"], "requirements": {"degrees": ["degree holder"], "majors": ["finance", "accounting", "accountancy"], "languages": [], "language_level": [], "hard_skills": ["oracle", "hkicpa", "ms excel", "accounting system", "ms office"], "soft_skills": ["communication and interpersonal skills", "time management", "independent", "detailed oriented"], "languages_combined": []}, "experience_required": {"duration": ["minimum 3 years"], "field": ["operation", "audit", "accounting"]}}, {"job_id": "100003009054099", "location_code": "hk", "company": "Data World Computer & Communication Ltd", "job_title": "System / Network Engineer", "description": "Responsibilities:\n\n\nResponsible for direct marketing campaign such as MMS, SMS and eDM by data management, data mining, segmentation and profiling analysis\nMaintain and operate SAS program to facilitate the customer filtering\nConduct analysis with Google Analytics and support on dimension, metrics, goals and funnels setup\nWork closely with internal parties to conduct effective direct marketing campaign and ensure accurate performance tracking\nSupport data consolidation and analysis from various internal parties in order to provide insights of in-depth customer behavior\nCoordinate and perform user acceptance tests to ensure system and data integrity\nPrepare regular statistical report to evaluate the performance of direct marketing campaign\n\nRequirements:\n\nDegree holder in Information Management, Marketing or other business disciplines with a minimum of 2 years\u2019 relevant experience\nFamiliar with CRM data extraction and marketing data analysis is a plus\nKnowledge of basic programming languages (such as SQL) and Google Analytics is preferred. Experience in Marketing Cloud and Cognos would be an advantage\nOrganised, analytical, attentive to details and possess good project management skills\nSelf motivated, able to work independently with capability in priority setting and meeting tight deadlines\nA good team player with communication and inter-personal skills\nProficient in Chinese and English with good command of PC skills in MS Office and Chinese WP\nCandidate with more experience will be considered as Senior Marketing Executive\n\nInterested parties please apply with full resume stating present and expected salary by clicking \"Apply Now\" or visiting our website:\u00a0www.smartone.com/tc/about_us/careers/\n\nSmarTone is an equal-opportunity employer.\u00a0 All data supplied will be kept in strict confidence and will be used for employment related purpose.\u00a0 We may transfer such data to any agent, contractor or third party who provides services to us with respect to matters relating to your application. Only short-listed candidates will be contacted.", "employment_types": ["Full Time", "Permanent"], "selling_points": ["Networking and cybersecurity product support", "Junior to senior positions available", "1-5 years relevant working experience"], "locations": ["Kwai Hing"], "categories": ["Information Technology (IT)", "Support", "Security", "Network & System"], "post_time": "2022-01-17T08:23:00Z", "salary": {"currency": null, "max": null, "min": null, "period": "monthly", "term": null}, "salary_visible": false, "title_keywords": ["engineer"], "responsibilities": ["provide insights", "management", "data", "edm", "analysis", "coordinate", "evaluate", "maintain", "internal parties", "data mining", "report", "setup", "tracking"], "requirements": {"degrees": ["degree holder"], "majors": ["business", "marketing"], "languages": ["english", "chinese"], "language_level": ["good command", "proficient"], "hard_skills": ["google analytics", "plus", "basic", "chinese wp", "analysis", "sql", "project management", "programming", "pc skills", "ms office"], "soft_skills": ["work independently", "good team player", "meeting tight deadlines", "attentive to details", "project management skills", "inter-personal skills", "self motivated", "communication", "organised"], "languages_combined": [{"language": "english", "language_level": ["good command", "proficient"]}, {"language": "chinese", "language_level": ["good command", "proficient"]}]}, "experience_required": {"duration": ["minimum of 2 years"], "field": ["business", "management", "marketing", "relevant experience"]}}, {"job_id": "100003009054738", "location_code": "hk", "company": "Hong Kong Examinations and Assessment Authority", "job_title": "Programmers (Ref: IT/01/812)", "description": "Responsibilities:\n\nAssist the Marketing Manager to formulate product and service strategies, marketing offers, and implement new service/tariff launch\nResponsible on day-to-day operations, including data mining and analysis, sales operational support and monitoring, etc\nAssist in monitoring market developments, business performance and analyse customer usage and market opportunities to develop appropriate marketing programs\nFollow through sales and marketing initiatives and help to achieve business objectives\nManage the proposition life cycle from inception to launch and beyond\n\nRequirements:\n\nDegree in business disciplines, preferably in Marketing\nMinimum\u00a02 years\u2019 relevant working experience, preferably in telecom industry\nCreative, confident, outgoing with initiatives and self-motivated\nAttentive to details\nStrong in handling numbers, strong analytical skills and out-going\nHands-on data analysis experience; strong in handling numbers,\u00a0analytics\nExcellent command of written and spoken English & Chinese\nGood PC skill (MS Word, Excel, Access, PowerPoint & Chinese WP)\nCandidates may need to work on weekend occasionally\n\n\u00a0Interested parties please apply with full resume stating present and expected salary.\n\nSmarTone is an equal-opportunity employer.\u00a0 All data supplied will be kept in strict confidence and will be used for employment related purpose.\u00a0 We may transfer such data to any agent, contractor or third party who provides services to us with respect to matters relating to your application. Only short-listed candidates will be contacted. All data supplied will be kept in strict confidence and used for employment related purpose. Only short-listed candidates will be contacted.\n\nYou are welcome to visit our website :\u00a0http://www.smartone.com/\u00a0", "employment_types": ["Full Time", "Permanent"], "selling_points": [], "locations": ["Not Specified"], "categories": ["Information Technology (IT)", "Support", "Software Development", "Others"], "post_time": "2022-01-17T10:51:39Z", "salary": {"currency": null, "max": null, "min": null, "period": null, "term": null}, "salary_visible": false, "title_keywords": [], "responsibilities": ["operational support", "analysis", "monitoring", "day-to-day operations", "develop", "data mining", "analyse"], "requirements": {"degrees": ["degree"], "majors": ["business", "marketing"], "languages": ["english", "chinese"], "language_level": ["excellent", "good"], "hard_skills": ["excel", "chinese wp", "analysis", "pc skill", "analytical skills", "powerpoint", "ms word"], "soft_skills": ["confident", "outgoing", "self-motivated", "attentive to details", "analytical skills", "hands-on", "creative"], "languages_combined": [{"language": "english", "language_level": ["excellent"]}, {"language": "chinese", "language_level": ["excellent", "good"]}]}, "experience_required": {"duration": ["minimum 2 years"], "field": ["data analysis", "relevant working experience"]}}, {"job_id": "100003009054241", "location_code": "hk", "company": "", "job_title": "IT Infrastructure Analyst", "description": "Responsibilities:\nPlan, implement and manage the execution of mobile product and service development and enhancement by working closely with cross-functional departments\nIdentify segment needs and develop marketing programs and communications to drive product and service subscription\u00a0and retention with segmentation approach\nAnalyze CRM data to understand customer profiles and usage patterns, and draw insights to support business growth\nKeep regular tracking and prepare reports on business performance to ensure targets are met\nPrepare program evaluation for each campaign and measure campaign effectiveness & ROI performance\nMonitor MI and evaluate market trend to identify mobile service development and enhancement opportunities\n\u00a0Requirements:\nDegree holder with minimum 2 years\u2019 relevant working experience\nSolid analytical and project\u00a0management skills\nDynamic, proactive, independent and result-driven\nGood communication and interpersonal skills\nAttention to details and able to work under pressure\nProficient in spoken and\u00a0written English and Chinese\nInterested parties please apply with full resume stating present and expected salary by clicking \"Apply Now\" or visiting our website:\u00a0www.smartone.com/tc/about_us/careers/\u00a0 \u00a0\u00a0\nSmarTone is an equal-opportunity employer.\u00a0 All data supplied will be kept in strict confidence and will be used for employment related purpose.\u00a0 We may transfer such data to any agent, contractor or third party who provides services to us with respect to matters relating to your application. Only short-listed candidates will be contacted.\u00a0\u00a0\n\u00a0You are welcome to visit our website:\u00a0http://www.smartone.com/\u00a0", "employment_types": ["Full Time", "Permanent"], "selling_points": ["5 years or above in-house IT support", "Software/Hardware/Networking", "Good communication"], "locations": ["Kowloon Bay"], "categories": ["Information Technology (IT)", "Hardware", "Support", "Application Specialist - Network"], "post_time": "2022-01-17T08:54:57Z", "salary": {"currency": null, "max": null, "min": null, "period": null, "term": null}, "salary_visible": false, "title_keywords": ["analyst"], "responsibilities": ["data", "monitor", "develop", "evaluate", "plan", "evaluation", "prepare reports", "tracking"], "requirements": {"degrees": ["degree holder"], "majors": [], "languages": ["english", "chinese"], "language_level": ["proficient"], "hard_skills": ["project management", "dynamic"], "soft_skills": ["independent", "project management skills", "dynamic", "communication and interpersonal skills", "attention to details", "proactive", "driven", "work under pressure"], "languages_combined": [{"language": "english", "language_level": ["proficient"]}, {"language": "chinese", "language_level": ["proficient"]}]}, "experience_required": {"duration": ["minimum 2 years"], "field": ["relevant working experience"]}}, {"job_id": "100003009056024", "location_code": "hk", "company": "Dyxnet Limited", "job_title": "Assistance Network Support Engineer", "description": "Responsibilities:\n\nHandle customer feedback & complaints in written/verbal format\nResponsible for case investigation\nEstablish good customer relationship by providing professional customer care services\nHandle ad hoc assignments and other duties as required\n\nRequirements:\n\nMatriculated or above with\u00a0at least 2 years' customer service experience in telecommunication industry\nCustomer oriented\nExcellent interpersonal, communication and problem solving skills\nPleasant, mature, independent and able to work under pressure\nGood PC skills (MS Word, Excel & Chinese Word Processing)\nExcellent command of both spoken and written English & Chinese\nGood spoken Putonghua is an advantage\n\nInterested parties please apply with full resume stating present and expected salary by clicking \"Apply Now\" or visiting our website: www.smartone.com/tc/about_us/careers/\u00a0\n\nSmarTone is an equal-opportunity employer.\u00a0 All data supplied will be kept in strict confidence and will be used for employment related purpose.\u00a0 We may transfer such data to any agent, contractor or third party who provides services to us with respect to matters relating to your application. Only short-listed candidates will be contacted.\n\nYou are welcome to visit our website : www.smartone.com\u00a0", "employment_types": ["Full Time", "Permanent"], "selling_points": ["Onsite deliver networking services", "Fresh Graduate will also be considered", "Five days work"], "locations": ["Kwai Fong"], "categories": ["Engineering", "Telecommunication / Wireless / Radio", "Information Technology (IT)", "Support", "Network & System"], "post_time": "2022-01-18T03:12:02Z", "salary": {"currency": null, "max": null, "min": null, "period": "monthly", "term": null}, "salary_visible": false, "title_keywords": ["support engineer", "assistance"], "responsibilities": ["other duties", "ad hoc assignments", "investigation"], "requirements": {"degrees": [], "majors": [], "languages": ["putonghua", "english", "chinese"], "language_level": ["advantage", "excellent", "good"], "hard_skills": ["excel", "chinese word processing", "problem solving skills", "pc skills", "ms word"], "soft_skills": ["independent", "mature", "pleasant", "communication", "customer service", "problem solving skills", "interpersonal", "work under pressure"], "languages_combined": [{"language": "putonghua", "language_level": ["good", "advantage"]}, {"language": "english", "language_level": ["excellent"]}, {"language": "chinese", "language_level": ["excellent"]}]}, "experience_required": {"duration": ["at least 2 years"], "field": ["customer service"]}}, {"job_id": "100003009055367", "location_code": "hk", "company": "DXC Technology Hong Kong Limited", "job_title": "Data center Operator", "description": "JR\n\n- perform system healthiness monitoring and verification\n- perform daily housekeeping tasks\n- provide helpdesk support ; and\n- provide first line problem solving and escalation.\n\nJD\n\nAt least 2 years of experience in networking or Internet technology, and 1 year of experience in data centre operation.", "employment_types": ["Full Time"], "selling_points": ["Helpdesk support", "Experience in networking or Internet technology", "Experience on data centre operation"], "locations": ["Admiralty"], "categories": ["Information Technology (IT)", "Support", "Network & System"], "post_time": "2022-01-18T02:20:38Z", "salary": {"currency": "HKD", "max": 24999, "min": 17000, "period": "monthly", "term": null}, "salary_visible": true, "title_keywords": ["operator"], "responsibilities": ["housekeeping", "monitoring", "system healthiness", "data"], "requirements": {"degrees": [], "majors": [], "languages": [], "language_level": [], "hard_skills": ["problem solving"], "soft_skills": ["problem solving"], "languages_combined": []}, "experience_required": {"duration": ["at least 2 years", "1 year"], "field": ["operation"]}}, {"job_id": "100003009054034", "location_code": "hk", "company": "NEC Hong Kong Limited", "job_title": "Project Engineer", "description": "Responsibilities:\u00a0\n\n\nAssist in project implementation, testing & commissioning, quality assurance and documentation;\u00a0\nProvide first line maintenance service to network and LED display panels;\nAssist in installation and configuration of network and computer systems;\nManage contractors\u2019 work progress to fulfill the project requirement; and\nHandle ad hoc tasks as assigned.\nRequirements:\n\nHigher Diploma or above in Electronic Engineering or IT-related\u00a0disciplines;\nAt least 3 years' relevant experiences in IT and or ELV equipment installation, maintenance and trouble shooting;\n\nKnowledge in network switches, PC/Server setup and configuration;\nHands-on knowledge of AutoCAD is highly preferable;\nSelf-motivated and able to work independently under tight deadline with minimum supervision;\nGood command of spoken English, Cantonese and Mandarin.\n\nPlease send your full detailed resume with expected salary and date available to The Human Resources Manager, NEC Hong Kong Limited, 25th Floor, The Metropolis Tower, 10 Metropolis Drive, Hunghom, Kowloon or by e-mail.\n\nPersonal data provided by job applicant will be used strictly in accordance with employer's personal data policy, a copy of which will be provided immediately upon request.", "employment_types": ["Full Time", "Permanent"], "selling_points": ["3 yrs in project implementation", "knowledge in network switches, server & PC setup", "experience in using AutoCAD preferred"], "locations": ["Not Specified"], "categories": ["Engineering", "Engineering Project Management", "Information Technology (IT)", "Support", "Network & System"], "post_time": "2022-01-17T08:08:53Z", "salary": {"currency": null, "max": null, "min": null, "period": "monthly", "term": null}, "salary_visible": false, "title_keywords": ["project engineer"], "responsibilities": ["installation", "commissioning", "maintenance", "configuration", "quality", "implementation", "computer systems", "testing", "ad hoc tasks", "documentation"], "requirements": {"degrees": ["higher diploma or above"], "majors": ["related disciplines", "it", "engineering"], "languages": ["cantonese", "english", "mandarin"], "language_level": ["good command"], "hard_skills": ["server", "pc", "maintenance", "autocad"], "soft_skills": ["hands-on", "work independently", "self-motivated", "detailed"], "languages_combined": [{"language": "cantonese", "language_level": ["good command"]}, {"language": "english", "language_level": ["good command"]}, {"language": "mandarin", "language_level": ["good command"]}]}, "experience_required": {"duration": ["at least 3 years"], "field": ["installation", "it", "maintenance"]}}, {"job_id": "100003009053273", "location_code": "hk", "company": "Sa Sa Cosmetic Company Limited", "job_title": "HRIS - Specialist", "description": "Responsibilities:\n\nResponsible to prepare advanced and predictive analysis, people metrics and HR reports on a periodic basis\nDrive HRIS initiatives and projects including liaison with vendors, team members, process management and operation review.\nMonitor HR information needs and design new or modify existing systems to meet changing requirements\nKeep abreast of local legislations\u2019 updates and ensure HR policies and practices are compliant with local legislation\nAssist a team to manage monthly payroll and benefits operation, while ensuring all payroll and tax calculations are well handled and executed effectively and efficiency\n\nRequirements:\n\nBachelor degree in HR/Business, or related disciplines, Computer Science is a definite advantage\n5 years or above solid HRIS experience preferably in sizable Company, retail, or FMCG\nStrong interpersonal skills with the ability to drive changes and communicate with different section leaders\nSelf-motivated & strong analytical skills, multi-tasking, meticulous, organized and able to meet tight deadlines\nPositive, detail-minded, well-organized and flexible\nGood command in both written and spoken English and Chinese proficiency\nimmediately available is preferred\n\n\u00a0We offer\n\n5 - day work week\nMedical Benefits\nPerformance Bonus\nStaff Purchase Discounts\nStaff Recreation Activity\nShuttle Bus Service\u00a0\n\nInterested parties please send a\u00a0full resume\u00a0with current and expected salary\u00a0by clicking APPLY NOW:\n\nHuman Resources Department\n\nSa Sa Cosmetic Co Ltd\n14/F, Block B, MP Industrial Centre\u00a0\n18 Ka Yip Street\u00a0\nChai Wan\u00a0\nHong Kong\n\nEmail:\u00a0recruitment_mgt @sasa.com\nFax: 2898 0864\n\nPlease visit our corporate website\u00a0at\u00a0http://corp.sasa.com/en/home\u00a0to know more about us.\u00a0\n\n(Sa Sa is an Equal Opportunity Employer and all qualified applicants will receive consideration for employment. Personal data collected will be kept confidential and used for recruitment purpose only)", "employment_types": ["Full Time"], "selling_points": ["HRIS experience is a must", "Manage data integrity in the HR system.", "Perform C&B support on Payroll"], "locations": ["Siu Sai Wan"], "categories": ["Admin & HR", "Administration / Operation Manager", "Compensation & Benefits", "Information Technology (IT)", "Support"], "post_time": "2022-01-17T06:38:34Z", "salary": {"currency": null, "max": null, "min": null, "period": null, "term": null}, "salary_visible": false, "title_keywords": ["specialist"], "responsibilities": ["tax", "management", "policies", "analysis", "review", "monitor", "hr reports", "hr", "design", "systems", "payroll", "legislations"], "requirements": {"degrees": ["degree", "bachelor"], "majors": ["related disciplines", "business", "computer science"], "languages": ["english", "chinese"], "language_level": ["proficiency", "good command"], "hard_skills": ["analytical skills"], "soft_skills": ["detail-minded", "meticulous", "self-motivated", "organized", "meet tight deadlines", "flexible", "well-organized", "analytical skills", "multi-tasking", "interpersonal skills", "positive"], "languages_combined": [{"language": "english", "language_level": ["proficiency", "good command"]}, {"language": "chinese", "language_level": ["proficiency", "good command"]}]}, "experience_required": {"duration": ["5 years"], "field": ["retail", "fmcg"]}}, {"job_id": "100003009052080", "location_code": "hk", "company": "ADECCO", "job_title": "IT Helpdesk Administrator (General IT support, up to 22k)", "description": "Our client is a unique bilingual education in Hong Kong with an independent school offering a Chinese and English immersion education with a global perspective.\n\nResponsibilities\n\nServe as the first-line support to staff members, students and parents of the Academy\nProvide support to software, network, e-mail, office applications and educational software issues\nPerform administrative duties such as maintaining hardware and software inventory, setting up of event schedule calendar and keeping track of loaned equipment and laptops etc.\nAssist IT related daily activities\n\nExperience\n\nGood understanding on the use of computer systems, mobile devices and other technical products\nExcellent telephone manner and communication skills\nAbility to diagnose and resolve basic technical issues\nAbility to work independently\nBe a good team player\n\nEducation\n\nRelevant education background in either Information System, Information Technology or Computer Science disciplines\nGood command of both spoken and written English and Cantonese (including Mandarin)\n\n\n\nInterested parties, please\u00a0CLICK HERE\u00a0to apply online. (Ref:JDB/IT-TT)\n\nPlease note that only short-listed candidates will be notified. All information gathered will be treated in strict confidence and solely used for recruitment purposes", "employment_types": ["Full Time", "Permanent"], "selling_points": [], "locations": ["Pok Fu Lam"], "categories": ["Information Technology (IT)", "Support", "Testing / QA", "Others"], "post_time": "2022-01-17T02:03:02Z", "salary": {"currency": null, "max": null, "min": null, "period": "monthly", "term": null}, "salary_visible": false, "title_keywords": ["administrator", "it support"], "responsibilities": ["provide support", "software issues", "software", "maintaining", "inventory", "diagnose", "computer systems", "communication", "hardware", "administrative duties", "schedule", "mobile devices"], "requirements": {"degrees": [], "majors": [], "languages": ["cantonese", "english", "chinese", "mandarin"], "language_level": ["good command"], "hard_skills": ["basic", "computer systems", "office applications", "information system", "hardware", "mobile"], "soft_skills": ["communication skills", "work independently", "good team player", "independent", "unique", "telephone manner"], "languages_combined": [{"language": "cantonese", "language_level": ["good command"]}, {"language": "english", "language_level": ["good command"]}, {"language": "chinese", "language_level": []}, {"language": "mandarin", "language_level": ["good command"]}]}, "experience_required": {"duration": [], "field": []}}, {"job_id": "100003009054484", "location_code": "hk", "company": "Waion Solutions Limited", "job_title": "Server Support Engineer (Ref. 11893) - Working Location: Cyberport", "description": "Responsibilities:\n\nRegular windows servers patching activities; patch operation execution through patch management tool Lumension Patchlink\nPatch execution and support during non-office hour\u00a0\nServers monitoring and alert handling; perform daily health check to server systems\n7x24 servers alert monitoring\nDaily ticket and windows server incident handling\nVMware operation\nHands-on troubleshooting and installation with windows servers, VMware.\n\nRequirements:\n\n1+ year experience and exposure to similar enterprise server operation\nExperience with windows servers patching exercise\nExperience with server hardware such as IBM xSeries, Cisco UCS, HP and Dell\u00a0\nHands-on experience with windows servers troubleshooting.\nExperience with ITIL/ISO type incident and change ticket handling\nExperience with vSphere 4.x, 5.x will be an added advantage\nMicrosoft, VMWare or ITIL certification is preferred\nExperience/certification with Microsoft System Centre (Operation Manager) will be an added advantage\nWorking Location:\u00a0Cyberport, Hong Kong", "employment_types": ["Contract"], "selling_points": ["Server support", "VMware, ITIL", "IT-related position"], "locations": ["Southern Area"], "categories": ["Information Technology (IT)", "Support", "Network & System"], "post_time": "2022-01-17T09:44:53Z", "salary": {"currency": null, "max": null, "min": null, "period": "monthly", "term": null}, "salary_visible": false, "title_keywords": ["server", "support engineer"], "responsibilities": ["installation", "monitoring", "systems", "troubleshooting", "patch management"], "requirements": {"degrees": [], "majors": [], "languages": [], "language_level": [], "hard_skills": ["itil", "servers", "vmware", "hardware", "server"], "soft_skills": ["hands-on", "troubleshooting"], "languages_combined": []}, "experience_required": {"duration": ["1+ year"], "field": ["operation", "troubleshooting"]}}, {"job_id": "100003009049367", "location_code": "hk", "company": "HGC Global Communications Limited", "job_title": "(Senior) Support Officer", "description": "Responsibilities:\n\nAttend to helpdesk phone calls and call registration into helpdesk system;\nCreate and maintain Helpdesk analysis report and records;\nPerform daily system operations \u2013 include batch job submission, data backup, etc.;\nProvide technical support services to internal users and external customers;\nAdminister / monitor system (data centre facilities, networks, IT systems, etc.);\nAssist Data Centre Supervisor and System/Network Engineer with problem diagnosis;\nCo-ordinate with internal team / vendor to follow up and fix problem, including internal / external incident and problem escalation\n\nRequirements:\u00a0 \u00a0 \u00a0\n\n1 year working experience in computer and data network operations\nExperience in hotline / data centre operations and support; in telecommunication industry, Data Centre or Helpdesk are definite advantage\nCandidates are required to work in shift, good phone manner and attitude is essential\n\nWe offer competitive salary package and career development opportunity. \u00a0Interested parties, please apply with full resume, present and expected salary, by clicking \u201cAPPLY NOW\u201d.\u00a0\u00a0Please quote the reference number on the e-mail subject.\n\nWe are an equal opportunity employer and welcome applications from all qualified candidates. Information provided will be treated in strict confidence and only be used for consideration of your application for the relevant post within HGC Global Communications Limited. Personal data provided by job applicants will be used strictly according to our Personal Information Collection Statement, a copy of which will be available upon written request. Information of unsuccessful candidates will be destroyed within six months.", "employment_types": ["Full Time"], "selling_points": ["Flexible working hours", "Helpdesk Support", "Strong supporting team"], "locations": ["Shatin Area"], "categories": ["Information Technology (IT)", "Support"], "post_time": "2022-01-14T08:31:44Z", "salary": {"currency": null, "max": null, "min": null, "period": "monthly", "term": null}, "salary_visible": false, "title_keywords": ["officer"], "responsibilities": ["data", "analysis report", "operations", "technical support", "systems", "monitor", "co-ordinate with", "maintain", "phone calls"], "requirements": {"degrees": [], "majors": [], "languages": [], "language_level": [], "hard_skills": ["data network"], "soft_skills": [], "languages_combined": []}, "experience_required": {"duration": ["1 year"], "field": []}}, {"job_id": "100003009051196", "location_code": "hk", "company": "Kingvisions Consultants Limited", "job_title": "IT Support (Welcome Fresh Grad!)", "description": "Job Description:\n\nProvide helpdesk support for hardware & software, computer installation & setup, Email setup & support for computer or mobile device, basic printer setup & support (Windows 10, MS Office, OTP)\nProvide first-tier networking support, video conference equipment health check & setup, basic telephone system support and assist computer related procurement.\nSetup of new computers, OS and software installation.\nTroubleshooting and Problem Solving for both IT Hardware and Applications in a timely manner. Escalate issue and involve experts whenever required in order to resolve issues as quickly as possible.\nPerform daily preventive checking.\nReceive and log IT service requests and incidents into ticketing system, case monitoring to ensure supporting team close out the cases.\n\nRequirement:\n\nDiploma/High Diploma or Degree in Computer Science or Information Technology related disciplines.\n0-1 years\u2019 experience on end user IT support.\nExperience in supporting Microsoft product like outlook, SharePoint, etc.\nGood level of knowledge on LAN, WAN and Desktop OS/application support.\nExperience on IT project coordination is plus.\nGood written and verbal communications and soft skill is required.\nBasic English and Mandarin communication are required.", "employment_types": ["Full Time", "Temporary", "Contract"], "selling_points": ["will be working in Large Enterprise", "Joinin Bonus Provided!!!!!!!!!!!!!!!", "Helpdesk support (remote, on-site)"], "locations": ["Tsim Sha Tsui"], "categories": ["Information Technology (IT)", "Support", "Others", "Student / Fresh Graduate / No Experience"], "post_time": "2022-01-15T04:34:41Z", "salary": {"currency": "HKD", "max": 29999, "min": 17000, "period": "monthly", "term": null}, "salary_visible": true, "title_keywords": ["it support"], "responsibilities": ["installation", "it service", "software", "video conference equipment", "telephone system", "a timely manner", "troubleshooting", "checking", "monitoring", "hardware", "setup"], "requirements": {"degrees": ["high diploma", "diploma", "degree"], "majors": ["related disciplines", "computer science", "information technology"], "languages": ["english", "mandarin"], "language_level": ["basic"], "hard_skills": ["plus", "basic", "os", "outlook", "wan"], "soft_skills": ["communication", "coordination"], "languages_combined": [{"language": "english", "language_level": ["basic"]}, {"language": "mandarin", "language_level": ["basic"]}]}, "experience_required": {"duration": ["0-1 years"], "field": ["it", "it support"]}}, {"job_id": "100003009052416", "location_code": "hk", "company": "Ebroker Systems Ltd", "job_title": "IT Support Engineer-Fintech (Fresh Graduates are welcome)", "description": "Responsibilities:\n\n\nTo provide first level support to existing clients and to carry out daily health check of systems\nTo provide system and application support\nTo handle deployment of system modules\nProactively follow up technical issues and incidents\nTo assist clients to participate HKEx Market Rehearsal and to perform system tests\u00a0\nTo carry mobile and handle non-office hours call\n\nRequirements:\n\nHigher Diploma or above in\u00a0Computer Science, Computer Engineering, Information Technology or related disciplines\u00a0\nKnowledge in MS SQL Server, MS Windows administrative and configuration\nKnowledge and experience in trading solutions, equity/futures trading rules of HK and China is preferable\nAnalytical, creative mind and able to work under pressure\nResponsible, good interpersonal skill and good team player\nGood command of both written and spoken Mandarin/English is preferable\nJoin us to work in a Hong Kong\u00a0listed leading Fintech company!\n\nFor application, please email your detailed resume and expected salary to us.\n\nAll applications will be treated in strict confidence and will be handled by authorized personnel only. Information provided will be used for the purpose of employment application to eBroker Systems Limited and will be destroyed within 6 months from the date of receipt.", "employment_types": ["Full Time"], "selling_points": ["Happy & friendly environment", "Great career exposure", "Provides on-the-job training, 5-day work week"], "locations": ["Tsim Sha Tsui"], "categories": ["Information Technology (IT)", "Support", "Others", "Others", "Student / Fresh Graduate / No Experience"], "post_time": "2022-01-17T03:05:23Z", "salary": {"currency": null, "max": null, "min": null, "period": "monthly", "term": null}, "salary_visible": false, "title_keywords": ["it support engineer"], "responsibilities": ["systems"], "requirements": {"degrees": ["higher diploma or above"], "majors": ["related disciplines", "computer engineering", "computer science", "information technology"], "languages": ["english", "mandarin"], "language_level": ["good command"], "hard_skills": ["ms sql server", "ms windows"], "soft_skills": ["good team player", "confidence", "responsible", "detailed", "interpersonal skill", "creative", "work under pressure"], "languages_combined": [{"language": "english", "language_level": ["good command"]}, {"language": "mandarin", "language_level": ["good command"]}]}, "experience_required": {"duration": [], "field": ["trading"]}}, {"job_id": "100003009051423", "location_code": "hk", "company": "Jardine Restaurant Group", "job_title": "IT Officer - (POS & CMS)", "description": "Responsibilities:\n\nPerform timely POS and CMS System menu update, and testing\nProvide daily technical support and handle requests from key users\nSupport new implementation promotion campaign and technical issues\nWork with external service vendors to ensure vendor deployments and deliverables are in quality standard\nAssist in ad-hoc projects as assigned\n\nRequirements:\n\n\nHigher Diploma or above in Computer Science or related discipline\n3 years working experience in IT user support, experience in QSR is preferred\nMCP, MCSE or CCNA holder would be an advantage\n\nKnowledge, Skills & Abilities Required:\n\nSolid experience in helpdesk support, virus and spam control, PC disaster recovery and data migration\nHands-on experience in supporting Windows, MS Active Directory, Office 365, Sophos, POS and other Microsoft applications\nSelf-motivated, strong problem solving and analytical skills\nCan do attitude and willing to work under pressure and overtime\nCustomer focused attitude and dedicated to problem resolution\nAble to work shift duty in weekend and on public holidays (5-day work per week)\nMore experiences will be considered as Senior Officer", "employment_types": ["Full Time"], "selling_points": ["POS & CMS", "Technical Support", "Vendors Deployments"], "locations": ["Hung Hom"], "categories": ["Information Technology (IT)", "Support", "Network & System", "Technical / Functional Consulting"], "post_time": "2022-01-15T15:43:31Z", "salary": {"currency": null, "max": null, "min": null, "period": "monthly", "term": null}, "salary_visible": false, "title_keywords": ["it officer"], "responsibilities": ["technical support", "quality", "implementation", "testing", "ad-hoc projects"], "requirements": {"degrees": ["higher diploma or above"], "majors": ["computer science"], "languages": [], "language_level": [], "hard_skills": ["mcse", "office 365", "active directory", "pos", "microsoft applications", "ccna", "analytical skills", "problem solving", "pc"], "soft_skills": ["self-motivated", "focused", "problem solving and analytical skills", "hands-on", "active", "work under pressure"], "languages_combined": []}, "experience_required": {"duration": ["3 years"], "field": ["it", "disaster recovery"]}}, {"job_id": "100003009054752", "location_code": "hk", "company": "Public Finance Limited", "job_title": "Help Desk Support (Shift)", "description": "Responsibilities:\n\nPerform help desk support and computer operation duties such as trouble-shooting, PC operation, file backup, distribution of reports, etc.\n\nRequirements\n\nSecondary education with technical or vocational training\n1-2 year\u2019s relevant working experience preferred\nWilling to perform shift duties\nSelf-motivated, good communication and interpersonal skills\nAble to work independently\nBenefits\nDouble Pay\nDiscretionary Bonus\nInsurance Benefits\nStudy subsidy\n\nApplication Method:\n\nBy Whatsapp : 9309 2925\n\nBy E-mail via \"Apply Now\"\n\nPersonal data collected will be treated in the strictest confidence in accordance with our\u00a0Personal Information Collection Statement\u00a0and\u00a0Privacy Policy\u00a0and will be handled by authorized personnel for recruitment-related purposes only. All applications will be kept for a maximum period of one year as may be considered for other suitable positions within Public Finance Ltd. and its associated companies. For details, please visit the Company\u2019s website\u00a0http://www.publicfinance.com.hk", "employment_types": ["Full Time", "Permanent"], "selling_points": [], "locations": ["Not Specified"], "categories": ["Information Technology (IT)", "Support", "Network & System", "Others"], "post_time": "2022-01-17T10:53:51Z", "salary": {"currency": null, "max": null, "min": null, "period": "monthly", "term": null}, "salary_visible": false, "title_keywords": [], "responsibilities": ["reports"], "requirements": {"degrees": ["secondary education"], "majors": [], "languages": [], "language_level": [], "hard_skills": [], "soft_skills": ["self-motivated", "communication and interpersonal skills", "work independently"], "languages_combined": []}, "experience_required": {"duration": ["1-2 year"], "field": ["relevant working experience"]}}, {"job_id": "100003009052691", "location_code": "hk", "company": "Global Logistics System (HK) Co Ltd", "job_title": "OPERATIONS SUPPORT SPECIALIST", "description": "Job Responsibilities:\n\nProvide on-call support including hardware, software and applications\nSupport local on-site hardware and software installation and provide user training\nProvide trouble-shooting and problem-solving to ensure total customer satisfaction\nSupport and respond to worldwide customer enquiries through email and phone call\nMaintain and update user manual\nBusiness travel when required\nShift duty is required\n\nJob Requirements:\n\n\nHigher certificate, diploma or above in Computer / software engineering related disciplines is an advantage but not a must.\nWorking experience in customer service or application support preferred.\nWilling to acquire new knowledge, sense of responsibility and with customer-centric mindset is a must.\nFluent in Cantonese, English and Mandarin.\nTeam player and able to communicate effectively within the team and to customers.\nHighly independent with an analytical mind and good problem-solving skills.\n\n\u00a0* Candidate does not meet all the requirements may be considered for an Assistant position.\n\nWe offer 5-day work, work from home for night shift\u00a0and attractive remuneration, medical and dental insurance, provident fund and other fringe benefits\u00a0including\u00a0discounted air tickets\u00a0on Cathay Pacific Airways,\u00a0recreation subsidy,\u00a0birthday leave,\u00a0Airport Express discount\u00a0and\u00a0shuttle bus\u00a0to the right candidate and his/her dependents etc.\u00a0 Interested parties, please submit your detailed CV, stating your present and\u00a0expected salary\u00a0and\u00a0availability\u00a0to us.\n\nWe are an equal opportunity Employer. All CVs and personal data collected are for recruitment purposes and the information will be kept confidential.", "employment_types": ["Full Time", "Permanent"], "selling_points": ["Provide on-call support and user training", "Provide trouble-shooting and problem solving", "Business travel and shift duty are required"], "locations": ["Airport Area"], "categories": ["Sales, CS & Business Devpt", "Customer Service - Supervisor / Officer", "Information Technology (IT)", "Application Specialist - Software", "Support"], "post_time": "2022-01-17T03:42:53Z", "salary": {"currency": null, "max": null, "min": null, "period": "monthly", "term": null}, "salary_visible": false, "title_keywords": ["specialist", "operations"], "responsibilities": ["installation", "software", "customer enquiries", "hardware", "maintain"], "requirements": {"degrees": ["higher certificate", "diploma or above"], "majors": ["related disciplines", "software engineering"], "languages": ["cantonese", "english", "mandarin"], "language_level": ["fluent"], "hard_skills": ["problem-solving skills"], "soft_skills": ["highly independent", "sense of responsibility", "customer service", "analytical mind", "problem-solving skills", "team player"], "languages_combined": [{"language": "cantonese", "language_level": ["fluent"]}, {"language": "english", "language_level": ["fluent"]}, {"language": "mandarin", "language_level": ["fluent"]}]}, "experience_required": {"duration": [], "field": ["customer service"]}}, {"job_id": "100003009049789", "location_code": "hk", "company": "ESD Services Limited (ESDlife)", "job_title": "IT Support Engineer", "description": "You will:\n\n\nResponsible for daily backup of various systems, reports generation and distribution\nIT support to end users\nConduct daily operation tasks such as support call handling, network equipment monitoring, banner upload, batch processing and emergency support as assigned by superior\nAssist in the installation of PC and front end software\n\nYou should have/be:\n\n\nHigher Diploma or above in Information Technology or related disciplines\nMinimum 1 year experience in IT technical support role\nExperience in Microsoft and Linux platform, PC setup, email system and mobile support, helpdesk support / back office operations\nKnowledge of Server and Desktop Virtualization platform (VMware, Citrix), Storage System (NAS, SAN) & inter-networking (switch & firewall) is preferred\nExcellent customer service attitude and good communication & inter-personal skill\nCo-operative, good sense of responsibility\n\nIn addition, you will be able to:\u00a0\n\nAn attractive and competitive remuneration package;\nReceive training and development opportunities\n\nSalary and benefit will commensurate with qualifications and experience.\u00a0\u00a0Interested party, please send in your\u00a0full resume and expected salary\u00a0by clicking the button\u00a0\u2018APPLY NOW\u2019.\n\u00a0\nTo know more about us, please visit our website\nhttps://corporate.esdlife.com\nhttps://ds.esdlife.com/\n\n\nWe are an equal opportunity employer and welcome applications from all qualified candidates. The information provided will be treated in strict confidence and used only for consideration of application for relevant/similar post(s) within the Hutchison Group of Companies.\n\nApplicants not having heard from us within four weeks from the date of this advertisement may consider their application unsuccessful. All personal data of unsuccessful applicants will be destroyed after the recruitment exercise when no longer required.", "employment_types": ["Full Time", "Permanent"], "selling_points": [], "locations": ["Hung Hom"], "categories": ["Information Technology (IT)", "Support", "Network & System", "Others"], "post_time": "2022-01-14T09:14:34Z", "salary": {"currency": null, "max": null, "min": null, "period": "monthly", "term": null}, "salary_visible": false, "title_keywords": ["it support engineer"], "responsibilities": ["installation", "software", "it technical support", "operations", "monitoring", "daily operation", "systems", "back office", "website", "communication", "customer service", "reports", "recruitment", "personal data", "setup"], "requirements": {"degrees": ["higher diploma or above"], "majors": ["related disciplines", "information technology"], "languages": [], "language_level": [], "hard_skills": ["linux", "no", "vmware", "nas", "switch", "mobile", "batch", "citrix", "firewall", "server", "pc", "processing"], "soft_skills": ["confidence", "responsible", "sense of responsibility", "communication", "customer service", "inter-personal skill", "superior"], "languages_combined": []}, "experience_required": {"duration": ["minimum 1 year"], "field": ["it technical support"]}}, {"job_id": "100003009044472", "location_code": "hk", "company": "Kai Shing Management Services Ltd", "job_title": "Assistant IT Officer (Assistant IT Support Engineer)", "description": "What will you do?\n\nResponsible for IT/IOT project implementation\nWork closely with the Solution Architect and other Software Engineers for the software development a various project\nConduct the on-site testing and commissioning\nLiaise with site to better understanding their needs and requirements\nStrong sense of responsibility and able to meet project deadlines\n\nDo you have a right profile?\n\nHigher Diploma or above in Computer & Information Sciences\n1-3 years of relevant experiences in IT/IOT project\nKnowledge of Windows Servers, workstations and Linux is an advantage\nKnowledge and experience of Chatbot, AI, BI and IOT solution is an advantage\nHaving a good conception of Cloud, including AWS and Azure, is highly preferred\nGood analytical, inter-personal and problem solving skills\nGood team player, positive attitude, innovative, self-initiating, eager to learn new technology and share with other team members, hardworking, able to work under pressure and work independently\nProficient in both English and Mandarin Chinese\u00a0\n\nWhat do we offer?\n\nAttractive remuneration package\nGreat promotion ladder\nReferral reward\nMedical benefit\nPaid marriage leave, birthday leave, well-being leave and annual leave\nEducation subsidy\nChildren scholarship\nCompany trip\n\nHow to apply?\n\nInterested parties, please apply once with application quoting job reference number, detailed resume, contact telephone number and expected salary by:\n\nClicking the \u201cApply Now\u201d button\nMail to: Human Resources Department, Unit 301-303, 3/F, Apec Plaza, 49 Hoi Yuen Road, Kwun Tong, Hong Kong\nFax to:\u00a0 (852) 2827 8608\nCall: (852)\u00a03703 5460\n\n(Attached resume should be in MS Word for Windows)\n\n(Data collected would be used for recruitment purpose only)", "employment_types": ["Full Time", "Permanent"], "selling_points": ["Projects", "Learn new technology", "1-3 years relevant experiences in IT/IOT projects"], "locations": ["Not Specified"], "categories": ["Information Technology (IT)", "Support", "Software Development", "Property / Real Estate", "Property Management"], "post_time": "2022-01-15T03:49:17Z", "salary": {"currency": null, "max": null, "min": null, "period": "monthly", "term": null}, "salary_visible": false, "title_keywords": ["assistant it officer", "it support engineer", "assistant"], "responsibilities": ["commissioning", "software", "implementation", "testing", "liaise with", "work under pressure"], "requirements": {"degrees": ["higher diploma or above"], "majors": ["information sciences"], "languages": ["mandarin chinese", "english"], "language_level": ["proficient"], "hard_skills": ["linux", "bi", "azure", "servers", "ai", "aws", "problem solving skills"], "soft_skills": ["good team player", "work independently", "responsible", "inter-personal", "sense of responsibility", "positive attitude", "eager to learn", "problem solving skills", "innovative", "hardworking", "work under pressure"], "languages_combined": [{"language": "mandarin chinese", "language_level": ["proficient"]}, {"language": "english", "language_level": ["proficient"]}]}, "experience_required": {"duration": ["1-3 years"], "field": ["it"]}}, {"job_id": "100003009048441", "location_code": "hk", "company": "Fortune Pharmacal Company Limited", "job_title": "IT Officer (Fresh graduate welcome)", "description": "Job Duties:\nPerform frontline IT technical support for end users\nManage and provide IT infrastructure support such as Microsoft AD, system and data backup, network and IP telephony, etc\nHandle IT hardware and software upgrade and system patch deployment\nCarry out daily maintenance work on PC configuration and troubleshooting\nPractice good IT asset management\nCoordinate and assist BCP/DR drill test\nHandle other ad-hoc tasks as required\nJob Requirements:\nDegree/diploma in Computer Science or related disciplines\n1 year IT support experience, fresh graduate is also welcomed\nHands-on experience on MS Windows server, networking, firewall and VC equipment\nFamiliar with Microsoft AD and multi-domain GPO administration\nExperienced in handling IT infrastructure implementation and migration project\nCertified MCP/ITIL-F is an advantage\nGood team player, self-motivated, good time management and communication skills\nWork location: Yuen Long\nShuttle bus pick up point: Quarry Bay / Lam Tin / Kowloon Tong / University Station / Long Ping Station\n\nAll information collected will be used for recruitment purpose only.\nWe are an equal opportunity employer.", "employment_types": ["Full Time", "Permanent"], "selling_points": ["Provide frontline user support and troubleshooting", "Handle IT hardware and software upgrade", "1 year IT support exp., fresh graduate welcome"], "locations": ["Yuen Long"], "categories": ["Information Technology (IT)", "Support", "Network & System", "Others"], "post_time": "2022-01-14T06:35:07Z", "salary": {"currency": null, "max": null, "min": null, "period": "monthly", "term": null}, "salary_visible": false, "title_keywords": ["it officer"], "responsibilities": ["software", "it infrastructure", "it technical support", "data", "maintenance", "ad-hoc tasks", "troubleshooting", "coordinate", "hardware", "pc configuration", "asset management"], "requirements": {"degrees": ["diploma", "degree", "fresh graduate"], "majors": ["related disciplines", "it", "computer science"], "languages": [], "language_level": [], "hard_skills": ["itil", "vc", "ms windows", "firewall", "server", "gpo"], "soft_skills": ["communication skills", "good team player", "self-motivated", "hands-on", "time management"], "languages_combined": []}, "experience_required": {"duration": ["1 year"], "field": ["it support"]}}, {"job_id": "100003009053368", "location_code": "hk", "company": "Automated Systems (HK) Ltd", "job_title": "Technical Service Supervisor", "description": "Responsibilities:\nProvide IT deskside and helpdesk support to customer through various channels\nLead a team to deliver IT support service to customer\nPerform operation support including data backup, data center management, IT facilities administration, installation and configuration of network, server, desktop PC, printer and peripherals\nMaintain hardware and software inventory, prepare inventory reports as required\nAssign work tasks to team members for follow up\nProvide service report and update service performance to management regularly\nHandle ad-hoc assignments / projects as required\nRequirements:\nHigher Diploma or above in computer science or related disciplines\nMore than 5 years IT helpdesk / deskside support experience with at least 1 year in team lead role\nProfessional certificate(s) holder is preferable such as ITIL / MCITP / MCSE / CCNA / CCNP\nHands-on experience in PC support operation, TCP/IP and server infrastructure are essential\nMature, positive thinking and active person are desired\nGood communication skill in both English and Cantonese\nImmediate available is preferred\nPlease click \"Apply Now\" to submit your application.\nPersonal data collected will be used for recruitment purpose only.", "employment_types": ["Full Time", "Permanent"], "selling_points": ["Lead a team to deliver IT support service", "Higher Diploma or above in computer science", "5 years IT helpdesk / deskside support"], "locations": ["Tin Hau"], "categories": ["Information Technology (IT)", "Hardware", "Support", "Network & System"], "post_time": "2022-01-17T06:52:13Z", "salary": {"currency": null, "max": null, "min": null, "period": "monthly", "term": null}, "salary_visible": false, "title_keywords": ["supervisor"], "responsibilities": ["installation", "management", "software", "data", "configuration", "ad-hoc assignments", "inventory", "lead a team", "hardware", "maintain", "reports", "report", "administration"], "requirements": {"degrees": ["higher diploma or above"], "majors": ["related disciplines", "computer science"], "languages": ["cantonese", "english"], "language_level": ["good"], "hard_skills": ["itil", "mcse", "tcp", "ccnp", "ccna", "ip", "server", "pc"], "soft_skills": ["communication skill", "positive thinking", "mature", "hands-on", "active"], "languages_combined": [{"language": "cantonese", "language_level": ["good"]}, {"language": "english", "language_level": ["good"]}]}, "experience_required": {"duration": ["5 years", "at least 1 year"], "field": ["infrastructure", "it helpdesk", "operation", "team"]}}, {"job_id": "100003009048028", "location_code": "hk", "company": "The Hong Kong Medical Association", "job_title": "IT Officer", "description": "Job Responsibilities:\n\nHandle internal users\u2019 technical requests\nProvide technical support and troubleshooting on network, system, hardware and software\nPerform IT equipment administration\nManage and liaise with outsource vendors to meet development projects quality and schedule\nUndertake ad-hoc IT related tasks as required\nRequirements:\n\nDiploma or above in Computer Science/Information Technology or related disciplines\n1 year of work experience in IT support, fresh graduates are welcomed\nMature, independent and team player\nGood command of English and Chinese, both spoken and written\nApplication letters in\u00a0BOTH\u00a0Chinese and English with full resume, present and expected salary and date available should be sent to Human Resources Team of the Hong Kong Medical Association.\u00a0\u00a0\n\n(Personal data collected for recruitment purpose only)\n\n", "employment_types": ["Full Time", "Contract"], "selling_points": [], "locations": ["Wan Chai"], "categories": ["Information Technology (IT)", "Support", "Network & System"], "post_time": "2022-01-14T04:41:49Z", "salary": {"currency": null, "max": null, "min": null, "period": "monthly", "term": null}, "salary_visible": false, "title_keywords": ["it officer"], "responsibilities": ["ad-hoc", "software", "technical support", "quality", "troubleshooting", "hardware", "schedule", "liaise with", "it equipment", "administration"], "requirements": {"degrees": ["diploma or above"], "majors": ["related disciplines", "computer science", "information technology"], "languages": ["english", "chinese"], "language_level": ["good command"], "hard_skills": [], "soft_skills": ["team player", "independent", "mature"], "languages_combined": [{"language": "english", "language_level": ["good command"]}, {"language": "chinese", "language_level": ["good command"]}]}, "experience_required": {"duration": ["1 year"], "field": ["it support"]}}, {"job_id": "100003009051483", "location_code": "hk", "company": "Tech Advance Consultancy Limited", "job_title": "Helpdesk / Deskside Support Engineer (Kwun Tong and Central)", "description": "Responsibilities:\n\nProvide helpdesk and technical support for internal users on: \u00a0Desktop hardware, , Software, MS Windows, Office, Outlook and networking\nSetup and configure desktop or networking devices and provide technical support\nSkills on supporting tablet or smartphones, conference room's AV equipments or video conference tools.\nTroubleshoot I.T related issues and report to line manager or supervisor on the issues.\n\nRequirements:\n\nHigher Diploma in Computer Studies or above\n2 years working experience in I.T related field and have solid helpdesk or deskside support background\nKnowledge of Windows XP, 7 and Windows based applications.\nNetworking and firewall knowledge\nGood communication and interpersonal skills\u00a0\nAble to work independently\nCandidate will ITIL will be advantage", "employment_types": ["Full Time", "Contract"], "selling_points": ["Work in Large scale companies", "With travel allowance and performance bonus", "Attractive salary packages"], "locations": ["Ngau Tau Kok"], "categories": ["Information Technology (IT)", "Support"], "post_time": "2022-01-16T04:12:36Z", "salary": {"currency": "HKD", "max": 24999, "min": 17000, "period": "monthly", "term": null}, "salary_visible": true, "title_keywords": ["support engineer"], "responsibilities": ["software", "technical support", "hardware", "troubleshoot", "setup", "report"], "requirements": {"degrees": ["diploma"], "majors": ["computer studies"], "languages": [], "language_level": [], "hard_skills": ["itil", "firewall"], "soft_skills": ["work independently", "communication and interpersonal skills"], "languages_combined": []}, "experience_required": {"duration": ["2 years"], "field": []}}, {"job_id": "100003009053567", "location_code": "hk", "company": "IT Consulting Solutions Limited", "job_title": "System/Network Engineer - Japan's Leading Financial Institution", "description": "At least 2-3 years of hands on experience in system/network setup and support/administration\nHands on experience in IT network environment\nTechnical knowledge in TCP/IP, HTTPS, LAN/WAN and other related areas\nHands on experience in Cisco enterprise grade products\nPerform first level troubleshooting, understand the escalated technical issues, identify the root cause and escalate to 2nd line support team\nProvide daily operational BAU support and system administration according to the company standard\nPerform computer installations and hardware/software configurations on desktop, laptop, and mobile devices, and day-to-day support covering end-user desktop & business applications\nPerform systems and network monitoring and routine hardware/software maintenance and other system administration tasks\nManage IT Inventory and support IT procurement and maintain proper records\nProvide VIP video conference setup and standby support\nProvide desktop/end-user training to users as required\nAssist other IT projects and provide non-office hour support as needed\n\nRequirements:\n\n\nDegree holder in information technology, computer science or other related disciplines\nWith at least 2-3 years of experience working in related positions\nIn depth experience in setting up and managing server platform and network appliances\nExperience in storage devices is preferred\nGood knowledge in Server, VMware, PC, and LAN / WAN and networking equipment\nGood understanding in Windows OS, Office 365, Microsoft Applications, Active Directory, Exchange, Skype for Business, Mobile Device Management Support, Patching software, MS Teams, etc.\nBe able to work independently with good team spirit\nQuick in response and reaction time\nPossess excellent communication skills in English and Chinese, Putonghua is an advantage", "employment_types": ["Contract"], "selling_points": ["System/network focused", "Leading Japanese financial institution", "Work Location: Central"], "locations": ["Central"], "categories": ["Information Technology (IT)", "Support", "Network & System", "Others"], "post_time": "2022-01-17T07:10:07Z", "salary": {"currency": null, "max": null, "min": null, "period": "monthly", "term": null}, "salary_visible": false, "title_keywords": ["engineer"], "responsibilities": ["management", "software", "maintenance", "active directory", "systems", "monitoring", "troubleshooting", "teams", "communication", "hardware", "mobile devices", "maintain proper records", "it procurement", "it inventory", "setup", "administration"], "requirements": {"degrees": ["degree holder"], "majors": ["related disciplines", "computer science", "information technology"], "languages": ["putonghua", "english", "chinese"], "language_level": ["advantage", "excellent"], "hard_skills": ["office 365", "vmware", "maintenance", "tcp", "microsoft applications", "active directory", "ip", "mobile", "hardware", "os", "mobile device", "server", "pc", "wan", "exchange"], "soft_skills": ["communication skills", "work independently", "team spirit", "troubleshooting", "hands on", "active"], "languages_combined": [{"language": "putonghua", "language_level": ["advantage", "excellent"]}, {"language": "english", "language_level": ["excellent"]}, {"language": "chinese", "language_level": ["excellent"]}]}, "experience_required": {"duration": ["at least 2-3 years"], "field": ["related", "it", "administration"]}}, {"job_id": "100003009052813", "location_code": "hk", "company": "Marsh (Hong Kong) Limited", "job_title": "Senior Service Desk Technical Support Analyst (1 year contract)", "description": "Position Overview\n\nThe Service Desk Analyst role at Marsh & McLennan affects colleagues of all levels, in all of our companies, in every region of the world.\n\nBeing the first point of contact on any technology-related process, application or device, you will be providing first-level technical phone support by diagnosing, reporting and resolving or correcting hardware and software problems.\n\nYou will manage all aspects of the installing, maintaining and troubleshooting hardware and software according to company standards \u2013 reconfiguring existing systems or performing system upgrades as required.\n\nThis will require monitoring and escalating issues until resolution, closure or handoff to a specialized support team.\n\nKey Responsibilities\n\n\nProvides Service Desk support by chat, phone and email, assisting users in diagnosing, reporting and resolving or correcting hardware and software problems.\nInstalls, maintains and troubleshoots hardware and software according to company standards \u2013 reconfigures existing systems and/or performs system upgrades as required.\nLogs all issues with appropriate documentation as requested.\nRoute calls to appropriate support teams as per described troubleshooting steps.\nMonitor and escalate issues until resolution, closure or the appropriate group has accepted.\nMaintain current knowledge of support knowledge provided through training and the Knowledge Base.\nExpected to resolve 75%+ of incoming incidents and attain 95%+ positive Customer Satisfaction feedback score, expected to handle a minimum of 40 incidents per day.\n\n\nSkills and Experience\n\n\nThis position will require the successful individual to provide technical support to our global colleague base, the shift pattern will be between Monday \u2013 Friday cover Bank Holidays. (Shift HK Time: 6:30am-3:30pm / 7:30am-4:30pm).\nBachelor\u2019s degree in computer science or equivalent is desired.\nMinimum 2-3 years\u2019 experience of working within a similar capacity for a Service Desk / Helpdesk/ Call Centre.\nTechnical Troubleshooting experience is a must.\nFamiliar with a variety of IT Service Desk concepts, practices, procedures and policies.\nMust have excellent verbal and written communication skills.\nEssential languages required: English, Cantonese. Also desired: Mandarin, Japanese, Korean.\nWe are an Equal Opportunity Employer. Visit us at\u00a0\u00a0www.marsh.com/hk\n\nAll information received will be kept in strict confidence and be used only for employment-related purposes.\n\n", "employment_types": ["Contract"], "selling_points": ["IT Desk Support", "Working with Regional Teams", "Technical Troubleshooting Experience"], "locations": ["Quarry Bay"], "categories": ["Information Technology (IT)", "Support", "Others"], "post_time": "2022-01-17T04:10:40Z", "salary": {"currency": null, "max": null, "min": null, "period": "monthly", "term": null}, "salary_visible": false, "title_keywords": ["technical support", "analyst"], "responsibilities": ["it service", "software", "troubleshooting", "communication", "maintain", "maintaining", "teams", "monitor", "resolution", "reporting", "upgrades", "monitoring", "procedures", "installing", "contact", "documentation", "technical support", "policies", "systems", "hardware"], "requirements": {"degrees": ["degree", "bachelor"], "majors": ["computer science"], "languages": ["cantonese", "english", "mandarin", "japanese", "korean"], "language_level": [], "hard_skills": ["documentation", "hardware", "system upgrades"], "soft_skills": ["communication skills", "confidence", "troubleshooting", "positive"], "languages_combined": [{"language": "cantonese", "language_level": []}, {"language": "english", "language_level": []}, {"language": "mandarin", "language_level": []}, {"language": "japanese", "language_level": []}, {"language": "korean", "language_level": []}]}, "experience_required": {"duration": ["minimum 2-3 years"], "field": ["troubleshooting"]}}, {"job_id": "100003009049134", "location_code": "hk", "company": "Shama Management Limited", "job_title": "Coordinator, Information Technology (IT Support)", "description": "Main Duties & Responsibilities\n\nHelpdesk implementation and management\nEnd user communications of networking, server or other service changes or interruptions\nMonitor and troubleshoot network performance problems\nMaintain high level of technical competence; assist staff in resolving complex technical problems and work with guests to ensure solutions are satisfactory\nProvide reports and communication progress to Manager\nPerform related work appropriate to the classification as assigned\n\nRequirements\n\nHolder of Diploma / Degree in Computer Science or related disciplines\nMinimum 1 year of relevant experience in IT operations support\nExperience in MS Windows Servers, LAN/WAN Infrastructure of the organization\nKnowledge in hotel system would be a definite advantage\nKnowledge in VM environment would be a definite advantage\nWell-organized, independent and customer-oriented\nGood analytical and problem solving skills\nGood in both spoken and written English and Chinese", "employment_types": ["Full Time", "Permanent"], "selling_points": ["1 years of experience required", "Experience in MS Windows Servers, LAN/WAN", "Holder of Diploma / Degree in Computer Science"], "locations": ["Wan Chai"], "categories": ["Information Technology (IT)", "Support"], "post_time": "2022-01-14T08:10:14Z", "salary": {"currency": null, "max": null, "min": null, "period": "monthly", "term": null}, "salary_visible": false, "title_keywords": ["coordinator", "it support"], "responsibilities": ["management", "monitor", "implementation", "provide reports", "communication", "maintain", "troubleshoot"], "requirements": {"degrees": ["diploma", "degree"], "majors": ["related disciplines", "computer science"], "languages": ["english", "chinese"], "language_level": ["good"], "hard_skills": ["problem solving skills", "wan", "servers", "ms windows"], "soft_skills": ["analytical and problem solving skills", "independent", "customer-oriented", "well-organized"], "languages_combined": [{"language": "english", "language_level": ["good"]}, {"language": "chinese", "language_level": ["good"]}]}, "experience_required": {"duration": ["minimum 1 year"], "field": ["infrastructure", "relevant experience", "it operations"]}}, {"job_id": "100003009052752", "location_code": "hk", "company": "Lung Fung Pharmaceutical (Group) Limited", "job_title": "Senior IT Specialist / IT Specialist", "description": "Job Duties:\n\nSupport the implementation of infrastructure projects\nResponsible for the system maintenance, server backup and all related I.T. infrastructure\nPerform software / hardware installation, configuration, and support\nPrepare user guidelines for system operations and maintenance\nResearch and evaluate the latest information technologies and standards to identify areas of improvement and/or future tech-related needs\nAssist in any ad-hoc projects assigned\n\nRequirements:\n\nCertificate / Diploma / Associated Degree or above in I.T. or related discipline\n1 year or above work experience in I.T.\nHands-on experience in daily I.T. support at desktop level to the company internal or function users\nGood interpersonal, communication and problem-solving skills\nFresh graduates will be considered\n\nInterested parties, please submit your detailed resume, expected salary & available date by clicking \u201cAPPLY NOW\u201d.\n\nAll personal information submitted by job applicants will be used for recruitment purposes and we reserve the rights to consider the applications for other positions in our Group.", "employment_types": ["Full Time", "Permanent"], "selling_points": ["Projects follow up", "System maintenance", "$3000 cash incentive for new joiner"], "locations": ["Fanling"], "categories": ["Information Technology (IT)", "Support", "Network & System"], "post_time": "2022-01-17T03:55:55Z", "salary": {"currency": null, "max": null, "min": null, "period": "monthly", "term": null}, "salary_visible": false, "title_keywords": ["it specialist"], "responsibilities": ["installation", "software", "maintenance", "configuration", "guidelines", "operations", "infrastructure", "implementation", "evaluate", "hardware", "ad-hoc projects"], "requirements": {"degrees": ["certificate", "diploma", "degree or above"], "majors": [], "languages": [], "language_level": [], "hard_skills": ["problem-solving skills"], "soft_skills": ["communication", "problem-solving skills", "hands-on", "interpersonal"], "languages_combined": []}, "experience_required": {"duration": ["1 year"], "field": []}}, {"job_id": "100003009055884", "location_code": "hk", "company": "HKT", "job_title": "Senior Technical Officer", "description": "Your Role\n\nExperience in Linux (Oracle & Redhat), Virtualization technologies (VMware, Oracle & RedHat), Monitoring/Operational intelligence products (SolarWinds) and Backup products (Veeam)\nProvide technical support and conduct troubleshooting on AD, On-premises Exchange server and O365 cloud services.\nManage the IT inventory for hardware & software, and other IT-related services.\n\nTo succeed in this role\n\nDegree or Higher Diploma holder in Computer Science or Information Technology or related disciplines.\nAt least 3 years of system administration experience.\nHands-on experience in (Windows & Linux Server), O365, VMWare ESXi, and data recovery solutions.\nGood communication skills, hard-working and can work independently.\nGood attitude and team working", "employment_types": ["Full Time"], "selling_points": [], "locations": ["Wan Chai"], "categories": ["Information Technology (IT)", "DBA", "Support", "Network & System"], "post_time": "2022-01-18T03:03:03Z", "salary": {"currency": null, "max": null, "min": null, "period": "monthly", "term": null}, "salary_visible": false, "title_keywords": ["senior technical officer"], "responsibilities": ["software", "data", "technical support", "monitoring", "troubleshooting", "communication", "hardware", "it inventory", "administration"], "requirements": {"degrees": ["degree", "higher diploma holder"], "majors": ["related disciplines", "computer science", "information technology"], "languages": [], "language_level": [], "hard_skills": ["linux", "oracle", "o365", "vmware", "hardware", "server", "exchange"], "soft_skills": ["communication skills", "work independently", "troubleshooting", "hands-on", "hard-working", "team working"], "languages_combined": []}, "experience_required": {"duration": ["at least 3 years"], "field": ["administration"]}}, {"job_id": "100003009054863", "location_code": "hk", "company": "The Hong Kong Polytechnic University", "job_title": "Technical Assistant (two posts)", "description": "DEPARTMENT OF REHABILITATION SCIENCES\nTechnical Assistant (two posts) (Ref. 22011717)\n[Appointment period: each for twelve months]\nDuties\nThe appointees will be required to:\n(a) provide support for teaching, research and service to the Department;\n(b) provide information update and maintenance of accounts for e-learning system;\n(c) perform housekeeping in classrooms and laboratories;\n(d) assist in the setting up, operation and maintenance of the computing, audio-visual and other teaching equipment; and\n(e) perform any other duties as assigned by the Head of Department or his delegates.\nThe appointees may be required to work outside normal office hours and on Saturdays and Sundays.\nQualifications\nApplicants should have:\n(a) five passes in HKCEE including English Language (at least Grade C if Syllabus A; Level 2 if results are obtained from 2007 onwards), Chinese Language (Level 2 if results are obtained from 2007 onwards) and Mathematics; or a combination of results in five HKDSE subjects of Level 2\u00a0in New Senior Secondary subjects / \"Attained\" in Applied Learning subjects / Grade E in Other Language subjects, and the five subjects must include English Language, Chinese Language and Mathematics;\n(b) good computer knowledge and experience in using application software such as MS Office, photo/video editing software and e-learning system, etc.; and\n(c) good interpersonal and communication skills.\nRemuneration\nA highly competitive remuneration package will be offered. Applicants should state their current and expected salary in the application.\nApplication\nPlease send a completed application form by post to Human Resources Office, 13/F, Li Ka Shing Tower, The Hong Kong Polytechnic University, Hung Hom, Kowloon, Hong Kong or via email by clicking \"Apply Now\".\u00a0 Application forms can be downloaded from https://www.polyu.edu.hk/hro/careers/guidelines_and_forms/forms.\u00a0 If\u00a0 a separate curriculum vitae is to be provided, please still complete the application form which will help speed up the recruitment process.\u00a0 Consideration of applications will commence on 30 January 2022 until the positions are filled. \u00a0The University\u2019s Personal Information Collection Statement for recruitment can be found at https://www.polyu.edu.hk/hro/careers/guidelines_and_forms/pics_for_recruitment.\nPolyU is an equal opportunity employer committed to diversity and inclusivity.\u00a0 All qualified applicants will receive consideration for employment without regard to gender, ethnicity, nationality, family status or physical or mental disabilities.", "employment_types": ["Full Time"], "selling_points": [], "locations": ["Not Specified"], "categories": ["Education", "Others", "Information Technology (IT)", "Support", "Others"], "post_time": "2022-01-17T12:06:45Z", "salary": {"currency": null, "max": null, "min": null, "period": null, "term": null}, "salary_visible": false, "title_keywords": ["technical assistant"], "responsibilities": ["any other duties", "rehabilitation", "provide support", "software", "maintenance", "housekeeping", "video editing", "communication", "recruitment", "visual", "recruitment process", "audio"], "requirements": {"degrees": ["hkdse"], "majors": ["mathematics"], "languages": ["english", "chinese"], "language_level": [], "hard_skills": ["video editing", "c", "maintenance", "ms office"], "soft_skills": ["communication skills", "learning", "interpersonal", "committed"], "languages_combined": [{"language": "english", "language_level": []}, {"language": "chinese", "language_level": []}]}, "experience_required": {"duration": [], "field": ["editing", "photo", "video"]}}, {"job_id": "100003009049409", "location_code": "hk", "company": "Shanghai Commercial Bank Ltd", "job_title": "IT Operations Support", "description": "Responsibilities\n\nPlan and control IT operations job flow and execution\nAdminister and maintain user access rights to application systems\nPerform ad hoc data updates and parameter changes of application systems in production environment\nProvide administrative support on program version controls\n\nRequirements\n\nHigher Diploma holder in Information Technology or related disciplines\nMinimum 1 year of relevant experience in computer operations and support, preferably with experience in operating AIX, LINUX, Windows system platforms.\nKnowledge in job schedule tools, shell script programming, IBM Mainframe (Z/OS, JCL, CLIST, TSO)\n\nIndependent with logical thinking\nGood communication and interpersonal skills\n\nAttractive remuneration package will be offered to the right candidates. Interested parties please click \"Apply Now\" to submit your full resume with current and expected salary to the Human Resources Division.\n\n\nPlease visit us at www.shacombank.com.hk for more information about our Bank.\n\nAll personal data collected will be used for recruitment related purposes strictly in accordance with the Bank's personal data policies, a copy of which will be provided immediately upon request by contacting our Personal Data Compliance Officer. Applicants who are not contacted within two months may consider their applications unsuccessful and the personal data collected from the applicants will be retained for no longer than two years from the date of rejection during which the applicants may be considered for other suitable positions within the Bank.", "employment_types": ["Full Time", "Permanent"], "selling_points": ["Plan & control IT operations job flow & execution", "Administer and maintain user access rights", "Perform ad hoc data updates"], "locations": ["Kwai Hing"], "categories": ["Banking / Finance", "Others", "Information Technology (IT)", "Support", "Others"], "post_time": "2022-01-15T03:50:24Z", "salary": {"currency": null, "max": null, "min": null, "period": "monthly", "term": null}, "salary_visible": false, "title_keywords": ["operations"], "responsibilities": ["control", "ad hoc", "data", "operations", "maintain", "plan", "provide administrative support", "application systems"], "requirements": {"degrees": ["higher diploma holder"], "majors": ["related disciplines", "information technology"], "languages": [], "language_level": [], "hard_skills": ["linux", "jcl", "clist", "os", "programming"], "soft_skills": ["communication and interpersonal skills", "independent"], "languages_combined": []}, "experience_required": {"duration": ["minimum 1 year"], "field": ["relevant experience"]}}, {"job_id": "100003009051051", "location_code": "hk", "company": "The Wharf Group", "job_title": "IT Support", "description": "Responsibilities\n\nPerform daily technical support on desktop, network, system, software and hardware\nSet up computers and install software for various applications and programs\nProvide helpdesk support and solutions to users\nHandle helpdesk documentation and reporting, liaise with relevant parties to troubleshoot and report on problems and incidents\nWork on staggered hours to provide proper user support\u00a0\nTimely respond and handle urgent business requests during normal and non-office hours with company-assigned facilities including phone and laptop\n\nRequirements\n\nDiploma or above in Computer Science or related disciplines with MCSE / CCNA qualification preferred\nAt least 1 year\u2019s experience in supporting MS Windows\u00a0and\u00a0Office applications and desktop hardware\nExperience in LAN, H3C and CISCO equipment support is preferred\nSelf-motivated,\u00a0hardworking with good interpersonal and task management skills\nWell organized and able to work independently\u00a0under pressure and tight deadlines\nGood command of spoken and written English and Chinese\n\n\nWe work 5 days per week.\n\nInterested parties, please click \"APPLY NOW\" and attach with your application letter and full resume.\u00a0\n\nFor further information of the Wharf Group, please visit our website: www.wharfholdings.com\u00a0\n", "employment_types": ["Full Time", "Permanent"], "selling_points": [], "locations": ["Tsim Sha Tsui"], "categories": ["Information Technology (IT)", "Support", "Network & System", "Others"], "post_time": "2022-01-15T19:11:47Z", "salary": {"currency": null, "max": null, "min": null, "period": null, "term": null}, "salary_visible": false, "title_keywords": ["it support"], "responsibilities": ["reporting", "software", "technical support", "hardware", "liaise with", "troubleshoot", "documentation", "report"], "requirements": {"degrees": ["diploma or above"], "majors": ["related disciplines", "computer science"], "languages": ["english", "chinese"], "language_level": ["good command"], "hard_skills": ["mcse", "ms windows", "ccna", "office applications", "hardware"], "soft_skills": ["self-motivated", "work independently", "under pressure", "well organized", "interpersonal", "hardworking"], "languages_combined": [{"language": "english", "language_level": ["good command"]}, {"language": "chinese", "language_level": ["good command"]}]}, "experience_required": {"duration": ["at least 1 year"], "field": []}}, {"job_id": "100003009053848", "location_code": "hk", "company": "Konew Financial Express Ltd", "job_title": "Systems and Operations Manager", "description": "Main Duties & Responsibilities:\n\nLead the System Operation and Infrastructure team\nManage the overall system operations and long term direction for network infrastructure and application/database server support functions\nPerform system implementation, monitoring, trouble- shooting and documentation across platform and application domains\nCoordinate with Information Security team on performing security incident management including detection and response\nDevelop and implement IT operation and maintenance work plans according to the requirements of the company\nProactively review and identify potential changes and system improvements for consideration\nManage system related projects to ensure reliable system availability for application development and production and provide regular/timely/accurate status reporting\nManage the complete process of projects, deployments, system changes from preparation, implementation and testing\nHandle ad hoc tasks as assigned from time to time\n\nRequirements:\n\nBachelor\u2019s Degree holder in Computer Science, Information System or related disciplines\nAt least 10 years of relevant working experience in system operation and infrastructure, preferably with management exposure\nFamiliar with infrastructure support and experienced in system implementation\nProblem- solving aptitude, well- organized, self- motivated and able to work under pressure\nStrong leadership, coaching, communication and interpersonal skills\nExcellent command of spoken and written Chinese and English\nWe offer:\n\n\u00a0\u00a0\u00a0\u00a0\u00a0\u00a0\u00a0 Discretionary bonus\n\u00a0\u00a0\u00a0\u00a0\u00a0\u00a0\u00a0 Medical insurance\n\u00a0\u00a0\u00a0\u00a0\u00a0\u00a0\u00a0 Dental insurance\n\u00a0\u00a0\u00a0\u00a0\u00a0\u00a0\u00a0 Hardship allowance\n\u00a0\u00a0\u00a0\u00a0\u00a0\u00a0\u00a0 Competitive annual leave days\n\u00a0\u00a0\u00a0\u00a0\u00a0\u00a0\u00a0 Birthday leave\n\u00a0\u00a0\u00a0\u00a0\u00a0\u00a0\u00a0 Anniversary leave\n\u00a0\u00a0\u00a0\u00a0\u00a0\u00a0\u00a0 Study leave\n\u00a0\u00a0\u00a0\u00a0\u00a0\u00a0\u00a0 Marriage leave\n\u00a0\u00a0\u00a0\u00a0\u00a0\u00a0\u00a0 Compassionate leave\n\nHow to apply:\n\nInterested parties, please send your resume stating your expected salary to Human Capital Department\u00a0by clicking \"APPLY NOW\".\n\n(We are an equal opportunity employer.\u00a0 Personal data collected will be used for recruitment purpose only.\u00a0 The unsuccessful applications will be destroyed after 6 months.)", "employment_types": ["Full Time"], "selling_points": ["Lead the System Operation and Infrastructure team", "Implement IT operation and maintenance work plans", "Identify potential changes and system improvement"], "locations": ["Central"], "categories": ["Information Technology (IT)", "Support", "IT Management", "Network & System"], "post_time": "2022-01-17T07:37:02Z", "salary": {"currency": null, "max": null, "min": null, "period": "monthly", "term": null}, "salary_visible": false, "title_keywords": ["operations manager"], "responsibilities": ["information security", "operations", "database", "plans", "application development", "infrastructure", "implementation", "develop", "testing", "network infrastructure", "reporting", "management", "monitoring", "coordinate with", "review", "ad hoc tasks", "documentation", "system changes", "maintenance", "system improvements"], "requirements": {"degrees": ["bachelor", "degree holder"], "majors": ["related disciplines", "computer science"], "languages": ["english", "chinese"], "language_level": ["excellent"], "hard_skills": ["system implementation", "infrastructure support", "information system"], "soft_skills": ["organized", "motivated", "communication and interpersonal skills", "leadership", "work under pressure"], "languages_combined": [{"language": "english", "language_level": ["excellent"]}, {"language": "chinese", "language_level": ["excellent"]}]}, "experience_required": {"duration": ["at least 10 years"], "field": ["infrastructure", "management", "operation", "relevant working experience"]}}, {"job_id": "100003009049303", "location_code": "hk", "company": "Commercial Radio Productions Ltd", "job_title": "IT Support Engineer (Kowloon Tong)", "description": "Commercial Radio Interactive, a division of Commercial Radio Productions Limited and the digital arm of Commercial Radio, are looking for a passionate and energetic\u00a0System Engineer to join our IT team and develop his/her career under the guidance of our experienced senior staff.\n\n\n\nJob Duties\n\nProvide IT Helpdesk services for in-house end-users\nSetup and provide IT support for Live streaming event\nInstall, configure, and maintain internal systems/services\nPerform Linux/Windows system administration\nCreate and maintain technical documentation\nJob Requirements\n\n\nHigher Diploma or Degree holder in Computer Science or related disciplines of Tertiary Education\nMinimum 1 year solid experiences in system administration and technical support\u00a0\nHands-on experience in Linux/Windows is a MUST\nHolder of RHCT/RHCE, LPI, MCSA, MCSE is an advantage\nHands-on experience in VMWare is an advantage\nGood problem solving skills , pay attention to details and good communication skills\nResponsible, self motivated, work independently, and process tasks without supervision\nWilling to work at non office hour for urgent production service support & maintenance.\nFresh graduates are also welcome\n\nOffice location: Kowloon Tong\n\nApplication Procedure:\n\nWe offer attractive remuneration package, competitive salary, medical scheme and life insurance to the right candidate. Interested candidates, please submit application letter with full resume, present and expected salary by clicking \u201cApply Now\u201d (Please quote the job reference number on the e-mail subject line).\n\nAll information received will be kept in strict confidence and only for employment-related purpose. Only short listed candidates will be invited for interview.", "employment_types": ["Full Time", "Permanent"], "selling_points": ["Provide IT Helpdesk services for in-house end-user", "Setup and provide IT support for Live stream event", "Hands-on experience in Linux/Windows is a MUST"], "locations": ["Not Specified"], "categories": ["Information Technology (IT)", "Support", "Network & System", "Media & Advertising", "Broadcasting - TV / Radio"], "post_time": "2022-01-14T08:24:37Z", "salary": {"currency": null, "max": null, "min": null, "period": "monthly", "term": null}, "salary_visible": false, "title_keywords": ["it support engineer"], "responsibilities": ["maintain", "documentation", "internal systems", "setup", "administration"], "requirements": {"degrees": ["diploma", "degree holder"], "majors": ["related disciplines", "computer science"], "languages": [], "language_level": [], "hard_skills": ["linux", "mcse", "vmware", "maintenance", "mcsa", "problem solving skills"], "soft_skills": ["communication skills", "work independently", "responsible", "self motivated", "hands-on", "attention to details", "problem solving skills"], "languages_combined": []}, "experience_required": {"duration": ["minimum 1 year"], "field": ["administration"]}}, {"job_id": "100003009055872", "location_code": "hk", "company": "Page Personnel", "job_title": "IT Support Analyst - US Law Firm", "description": "A multinational law firm is now looking for an experienced Tier 1 & 2 IT support officer to join their information technology team. Selected Candidate will be responsible for providing helpdesk support to internal users and engaging in their regional IT projects.\n\nClient Details\n\nFounded in the United States, our client is one of the largest international law firms with their presence in more than 30 countries. To cope with their business needs, they are currently seeking an IT Support Analyst who will be responsible for providing IT support to internal users in the Hong Kong office.\n\nDescription\n\nProvide helpdesk support for users, such as O365 and windows\nIdentify and resolve user issues relating to applications, mobile devices, systems, & network\nSupport legal document management software (DMS)\nProvide Support for video conference, webinar events and remote conference tools\nPerform other duties and ad hoc projects as required\n\nProfile\n\nDegree holder in Computer Science and Information Systems or equivalent\nMinimum 2 years' hand-on experience providing helpdesk support\nKnowledge of the ITIL environment would be a great advantage\nExcellent verbal and written communication skills including English, Cantonese and Mandarin\nWide range of IT Knowledge on Windows, IOS, Android and Office suite\n\nJob Offer\n\nPermanent role\nAttractive performance bonus\nAnnual leave\nGreat career exposure\nMedical coverage\n\nTo apply online please click the 'Apply' button below. For a confidential discussion about this role please contact Ray Chanon +852 3602 2432.", "employment_types": ["Full Time", "Permanent"], "selling_points": ["Renowned law firm", "Strong track record of performance bonus", "Professional working environment"], "locations": ["Not Specified"], "categories": ["Information Technology (IT)", "Support", "Others"], "post_time": "2022-01-18T03:02:08Z", "salary": {"currency": null, "max": null, "min": null, "period": "monthly", "term": null}, "salary_visible": false, "title_keywords": ["analyst", "it support"], "responsibilities": ["provide support", "management", "perform other duties", "software", "systems", "communication", "ad hoc projects", "contact", "mobile devices"], "requirements": {"degrees": ["degree holder"], "majors": ["computer science"], "languages": ["cantonese", "english", "mandarin"], "language_level": ["excellent"], "hard_skills": ["itil", "o365", "it knowledge", "mobile", "android"], "soft_skills": ["communication skills", "responsible"], "languages_combined": [{"language": "cantonese", "language_level": ["excellent"]}, {"language": "english", "language_level": ["excellent"]}, {"language": "mandarin", "language_level": ["excellent"]}]}, "experience_required": {"duration": ["minimum 2 years"], "field": []}}, {"job_id": "100003009052035", "location_code": "hk", "company": "Entrust Asia Pacific Limited", "job_title": "Technical Support Specialist", "description": "Responsibilities:\nImprove Asia Pacific customer\u2019s satisfaction level\nEnhance communication between Customer, Partners, and\u00a0 Internal\nDeliver high quality emergency maintenance services on Entrust equipment\nDiagnose and understand equipment problems\nWork with a high degree of autonomy with the ability to test, diagnose and resolve issues\nPerform system/equipment calibration services to support regional business.\nProvide product supports and act as a technical Backup for channel partners in the region especially on \u00a0Entrust equipment issues.\nQuality control/monitoring for all Entrust products especially on the card issuance solutions\nDeliver product training to build up regional expertise in all technical aspects (Internally and Partners and Customers)\nSupport other functions and responsibilities within Entrust Services\nBasic Qualifications:\n\u00a0Associates degree or diploma in Electrical or Electronics;\nMinimum of 3 years of electromechanical technician experience;\nProficient problem solving and troubleshooting skills for complex mechanical assemblies;\nDemonstrated communication skills (verbal and written) in (English, Chinese (including Mandarin) and the ability to communicate effectively with external and internal customers", "employment_types": ["Permanent"], "selling_points": ["Career in Payments, Identity, Digital Technology", "Flexible Working", "Best team in Security"], "locations": ["Kwun Tong"], "categories": ["Engineering", "Electrical / Electronics", "Mechanical", "Information Technology (IT)", "Support"], "post_time": "2022-01-17T01:53:26Z", "salary": {"currency": null, "max": null, "min": null, "period": "monthly", "term": null}, "salary_visible": false, "title_keywords": ["technical support specialist"], "responsibilities": ["monitoring", "diagnose", "quality", "troubleshooting", "communication", "quality control", "maintenance services"], "requirements": {"degrees": ["diploma", "degree"], "majors": [], "languages": ["english", "chinese", "mandarin"], "language_level": [], "hard_skills": ["problem solving", "basic", "maintenance"], "soft_skills": ["communication", "communication skills", "troubleshooting", "problem solving"], "languages_combined": [{"language": "english", "language_level": []}, {"language": "chinese", "language_level": []}, {"language": "mandarin", "language_level": []}]}, "experience_required": {"duration": ["minimum of 3 years"], "field": []}}, {"job_id": "100003009055252", "location_code": "hk", "company": "iCON Business Systems Ltd", "job_title": "Post-Sales Engineer / Consultant - Storage, Virtualization & HCI Solutions", "description": "Responsibilities:\n\nReports to Technical Manager\nBe assigned to complete technical tasks including Post-sales and Project implementation\nProvides professional services on planning and design, deployment and integration services to fulfill customer's\u00a0Requirements\nBe responsible for proposal writing and preparing project documentation\n\nRequirements:\n\nAttains Degree in IT or related disciplines\nAttains At least TWO YEAR technical experience and solid skillset in storage and virtualization solutions\nBe Certified of Storage, VMware and HCI Solutions\nBe capable of effective communication with different customers\nBe Willing to learn and be aggressive\nCan work independently\nBe self-motivated with clear company and self objectives\nSenior System Engineer with similar experience and skillset will be considered\n\nWe offer comprehensive remuneration and benefits, and excellent career opportunities to the right candidates. Interested parties please state clearly the position you are applying to with reference no. if any in the subject line and email us a full resume with CURRENT & EXPECTED SALARY.\n\nAll applications will be treated in the strictest confidence. We regret that only shortlisted candidates will be notified. Data collected will be used for recruitment purpose only.", "employment_types": ["Full Time", "Permanent"], "selling_points": ["Post-Sales Engineer", "Infrastructure, HCI, Virtualization Technologies", "Fresh Graduate welcome"], "locations": ["Cheung Sha Wan"], "categories": ["Information Technology (IT)", "Support", "Network & System", "Technical / Functional Consulting"], "post_time": "2022-01-18T01:55:30Z", "salary": {"currency": null, "max": null, "min": null, "period": "monthly", "term": null}, "salary_visible": false, "title_keywords": ["consultant", "sales engineer"], "responsibilities": ["implementation", "design", "planning", "reports", "project documentation"], "requirements": {"degrees": ["degree"], "majors": ["related disciplines", "it"], "languages": [], "language_level": [], "hard_skills": ["vmware"], "soft_skills": ["work independently", "self-motivated", "capable", "willing to learn", "communication", "clear"], "languages_combined": []}, "experience_required": {"duration": ["at least two year"], "field": []}}, {"job_id": "100003009051737", "location_code": "hk", "company": "Tat Ming Wallpaper Company Limited", "job_title": "\u96fb\u8166\u6280\u8853\u652f\u63f4\u54e1", "description": "\u8981\u6c42 :\n\n\n\u4e2d\u4e94\u7a0b\u5ea6; 1-2\u5e74\u6709\u95dc\u5de5\u4f5c\u7d93\u9a57; \u826f\u597d\u7cb5\u8a9e; \u61c2\u666e\u901a\u8a71\u53ca\u82f1\u8a9e\n\n\u5de5\u4f5c\u7bc4\u570d :\n\n\n\u4e00\u822c\u65e5\u5e38IT\u652f\u63f4\u670d\u52d9; \u6587\u66f8\u8655\u7406; \u7db2\u7d61\u53ca\u96fb\u8166\u7dad\u8b77 ;\n\n\u8fa6\u516c\u5ba4\u8a2d\u5099\u7dad\u4fee; \u53ef\u4ee5\u7368\u7acb\u5de5\u4f5c; \u6709\u8cac\u4efb\u5fc3,\u6a02\u65bc\u8207\u4eba\u6e9d\u901a;\n\n\u61c2\u4e00\u822c\u7db2\u9801\u88fd\u4f5c / \u6703\u8a08\u6982\u5ff5/ php\n\n\u5f85\u9047 :\n\n\u85aa\u512a + \u96d9\u7ce7 + \u5e74\u7d42\u82b1\u7d05\n\u9280\u884c\u5047\u671f\n\u91ab\u7642\u6d25\u8cbc\n\u54e1\u5de5\u8cfc\u7269\u512a\u60e0\n\n\u6709\u610f\u8005\u8acb\u96fb\u90f5\u5c65\u6b77\u8868\u81f3\"Apply Now\"\u6216\u50b3\u771f\u5230 2838-0805 \u4eba\u4e8b\u90e8\u6536\n\n\u7db2\u9801 : www.tatming.com", "employment_types": ["Full Time", "Permanent"], "selling_points": ["\u4e2d\u4e94\u7a0b\u5ea6; 1-2\u5e74\u6709\u95dc\u5de5\u4f5c\u7d93\u9a57", "\u4e00\u822c\u65e5\u5e38IT\u652f\u63f4\u670d\u52d9; \u6587\u66f8\u8655\u7406; \u7db2\u7d61\u53ca\u96fb\u8166\u7dad\u8b77", "\u85aa\u512a + \u96d9\u7ce7 + \u5e74\u7d42\u82b1\u7d05"], "locations": ["Not Specified"], "categories": ["Information Technology (IT)", "Support", "Network & System", "Others"], "post_time": "2022-01-16T21:51:18Z", "salary": {"currency": null, "max": null, "min": null, "period": "monthly", "term": null}, "salary_visible": false, "title_keywords": [], "responsibilities": [], "requirements": {"degrees": [], "majors": [], "languages": [], "language_level": [], "hard_skills": ["php"], "soft_skills": [], "languages_combined": []}, "experience_required": {"duration": [], "field": []}}, {"job_id": "100003009054546", "location_code": "hk", "company": "Toppan Forms (Hong Kong) Limited", "job_title": "System & Network Administrator", "description": "Responsibilities:\n\n\nManage daily operations for MIS administration & security, Firewall, help-desk, installations for Windows, MS Office, Anti-Virus and software applications supports\nKnowledge of setting Windows Active Directory, VMware, Hyper-V, Veeam, SAN storage, Exchange Server, File Servers, Web Servers, Database Servers, DNS, FTP, on Windows platforms\nNetwork provisioning, monitoring and trouble shoot\nProvide planning and implementation of new technology and manage change and implement and communicate effectively\nEnsure the IT infrastructure is secure and protected and there is an approved and operational plan for disaster recovery and business continuity\n\nRequirements:\n\n\n\nDiploma or above in computer science or other related subjects\nCCNA, CCNP, MCSE or equivalent\nHands on experience on Networking, VPN, Microsoft Active Directory & Exchange Server\nKnowledge in at least 1 or more below products\n- Cisco Switches configuration\n- Sophos Firewall or Cisco Firewall\n- Huawei Switches or other Enterprise grade switch\nAt least 3 years of relevant experience in network & system administration\nKnowledge in .NET development, SQL Server and SharePoint server is a merit\nExcellent analytical and problem-solving skills\nA good team player, self-motivated and multitasking\nGood interpersonal & communication skills\nGood command in both English and Chinese including Mandarin\n\nWe offer excellent compensation package, promotion prospects and job satisfaction. Interested parties, please\u00a0email\u00a0your detailed resume with current and expected salary by click \u201cApply Now\u201d.\n\nWe are an Equal Opportunities Employer. Personal data collected will be\u00a0used strictly in accordance with the employer's personal data policy, a copy of which will be provided upon request.\u00a0Candidates who do not notified within 8 weeks after submitting your application may consider the application unsuccessful and the application will be retained up to 24 months.\n\nDisclaimer: The above position description has been designed to indicate the general nature and level of work performed by employees within this classification. It is not designed to contain or be interpreted as a comprehensive list of all duties, responsibilities, and qualifications required of employees assigned to the position.\n\nToppan Forms does not accept unsolicited referrals and/or resumes from employment businesses and/or employment agencies. Any resumes submitted in the absence of a signed agreement will become the property of Toppan Forms and no fee shall be due.\n\nFor the details of Company Information, please visit\u00a0www.toppanforms.com\u00a0", "employment_types": ["Full Time", "Permanent"], "selling_points": [], "locations": ["Kowloon Bay"], "categories": ["Information Technology (IT)", "Support", "Network & System"], "post_time": "2022-01-17T09:57:12Z", "salary": {"currency": null, "max": null, "min": null, "period": "monthly", "term": null}, "salary_visible": false, "title_keywords": ["administrator"], "responsibilities": ["business continuity", "software", "active directory", "dns", "it infrastructure", "monitoring", "implementation", "planning", "database", "plan", "manage daily operations", "administration"], "requirements": {"degrees": ["diploma or above"], "majors": ["computer science"], "languages": ["english", "chinese", "mandarin"], "language_level": ["good command"], "hard_skills": ["mcse", "active directory", "ccnp", "switch", "ccna", "sql", "vpn", "firewall", "server", "problem-solving skills", "exchange"], "soft_skills": ["communication skills", "self-motivated", "good team player", "hands on", "problem-solving skills", "active", "interpersonal"], "languages_combined": [{"language": "english", "language_level": ["good command"]}, {"language": "chinese", "language_level": ["good command"]}, {"language": "mandarin", "language_level": ["good command"]}]}, "experience_required": {"duration": ["at least 3 years"], "field": ["relevant experience", "administration"]}}, {"job_id": "100003009056164", "location_code": "hk", "company": "The Chinese University of Hong Kong", "job_title": "Full-time / Part-time Computer Technician II", "description": "Full-time / Part-time Computer Technician II (carrying the job title of \u2018Application Developer, SCS\u2019)\n\nThe appointee will be responsible for (a) developing and maintaining online admission and application portal; (b) providing technical and end-user support to in-house applications and office automation; (c) providing assistance in system design and documentation/reporting; and (d) participating in assigned projects.\n\nApplicants should have (i) a Diploma/Higher Diploma in Information Technology or a related discipline from a recognised university or technical institute, preferably with a Bachelor\u2019s degree in Computer Science or Software Engineering; (ii) at least 1 year\u2019s relevant experience in building web application development using one or more skills in Java / JavaScript / PHP / JPA; (iii) experience with database systems, such as MySQL; and (iv) self-motivation, good analytical and problem-solving skills, and the ability to work as a good team member. Knowledge of Moodle or any learning management systems will be advantageous. Shortlisted candidates will be required to sit for written and/or computer skill tests.\n\nAppointment will initially be made on contract basis for up to 2 years (with contract-end gratuity for a 2-year contract), renewable subject to good performance and mutual agreement.\n\nApplication Procedure\n\nThe University only accepts and considers applications submitted online for the post above. For more information and to apply online, please visit http://career.cuhk.edu.hk.", "employment_types": ["Full Time", "Part Time"], "selling_points": ["Developing and maintaining online admission", "Providing technical and end-user support", "Participating in assigned projects"], "locations": ["Not Specified"], "categories": ["Information Technology (IT)", "Support", "Others", "Technician"], "post_time": "2022-01-18T03:27:30Z", "salary": {"currency": null, "max": null, "min": null, "period": "monthly", "term": null}, "salary_visible": false, "title_keywords": ["technician"], "responsibilities": ["reporting", "management", "software", "maintaining", "systems", "developing", "providing assistance", "system design", "database", "documentation", "application development"], "requirements": {"degrees": ["diploma", "degree", "bachelor"], "majors": ["software engineering", "computer science", "information technology"], "languages": [], "language_level": [], "hard_skills": ["java", "web application development", "php", "c", "system design", "javascript", "computer skill", "documentation", "problem-solving skills"], "soft_skills": ["responsible", "self-motivation", "learning", "problem-solving skills", "team member"], "languages_combined": []}, "experience_required": {"duration": ["at least 1 year"], "field": ["application development", "relevant experience", "database"]}}, {"job_id": "100003009055864", "location_code": "hk", "company": "Peoplebank Hong Kong Ltd", "job_title": "Data Center Engineer (1-year renewable contract)", "description": "Duties & Responsibilities\n\nPerform daily IT operations at IT Monitoring Centre\nServices/system monitoring and 1st tier troubleshooting\nDaily scheduled task execution such as system jobs processing, system health check, preparing regular reports, etc\nProvides support to Data Centre facilities operations\nPerform ad-hoc tasks as assigned by supervisor\n7x24 shift works is required\n\n\n\nQualification and Experience\n\nDiploma or above in Computer Science, Electrical Engineering or related disciplines\n2+ years of experience in IT industry\nWork independent, analytical, good problem-solving skills\nIT professional certification (MCSE, CCNA, \u2026etc) is an advantage.\nExposure to cloud and virtualization technologies\nWilling to learn & good sense of responsibilities\nGood command of written and spoken English and Chinese\nLess expereinced / Fresh graduate with internship experience will be considered for junior role\n\nInterested parties please send your resume by Apply Now.", "employment_types": ["Full Time", "Contract"], "selling_points": ["Renewable contract", "With cloud and advance tech exposure", "Shift duty is required"], "locations": ["Sham Shui Po"], "categories": ["Information Technology (IT)", "Hardware", "Support", "Network & System"], "post_time": "2022-01-18T03:01:28Z", "salary": {"currency": null, "max": null, "min": null, "period": "monthly", "term": null}, "salary_visible": false, "title_keywords": ["engineer"], "responsibilities": ["data", "operations", "ad-hoc tasks", "monitoring", "troubleshooting", "reports"], "requirements": {"degrees": ["fresh graduate", "diploma or above"], "majors": ["related disciplines", "electrical engineering", "computer science"], "languages": ["english", "chinese"], "language_level": ["good command"], "hard_skills": ["problem-solving skills", "processing", "ccna", "mcse"], "soft_skills": ["independent", "willing to learn", "troubleshooting", "problem-solving skills", "sense of responsibilities"], "languages_combined": [{"language": "english", "language_level": ["good command"]}, {"language": "chinese", "language_level": ["good command"]}]}, "experience_required": {"duration": ["2+ years"], "field": ["it"]}}, {"job_id": "100003009043047", "location_code": "hk", "company": "OT&P Healthcare", "job_title": "IT Technical Support / IT Officer", "description": "Job Responsibilities:\n\n\nResponsible for IT infrastructure, helpdesk, hardware and application support for offices and clinics\nPerform PC troubleshooting, software and hardware installation\nProvide basic end-user training\nAdministrate hardware and software procurement and inventory\nMonitor servers, systems health and routine system operations\nMaintain administrative records, perform analysis and troubleshooting of system servers, including review server event log for system problems, use active directory to setup / change user accounts\nAssist with covers, audits and any other duties as assigned by Management\nJob Requirements:\n\n\nHigher Diploma or above in Computer Studies or related discipline;\n2 years relevant working experience in IT support\nHands on experience in Active Directory, O365 VMware, FortiGate administration\nKnowledge of network technologies, TCP/IP, network and cyber security\nHolder of MCSE / CCNA is an advantage\nCustomer focus, good problem-solving skill, self-initiative and responsible\nGood command of spoken and written English and Chinese\nFresh graduate will also be considered\n\nPlease apply in confidence with full resume, expected salary and availability to the Human Resources Department, OT&P by emailing us via\u00a0 projob@ otandp.com\u00a0or\u00a0 by clicking \u201cApply Now\u201d button.\n\nThe information provided will be used for selection purpose only. All information of unsuccessful applicants will be destroyed within six months.", "employment_types": ["Full Time", "Permanent"], "selling_points": ["IT infrastructure, helpdesk, hardware support", "2 years relevant working experience in IT support", "Monitor servers, systems health and routine system"], "locations": ["Sheung Wan"], "categories": ["Information Technology (IT)", "Hardware", "Support", "Network & System"], "post_time": "2022-01-12T09:37:50Z", "salary": {"currency": null, "max": null, "min": null, "period": "monthly", "term": null}, "salary_visible": false, "title_keywords": ["technical support", "it officer"], "responsibilities": ["installation", "any other duties", "management", "it infrastructure", "software", "active directory", "operations", "inventory", "systems", "monitor", "troubleshooting", "analysis", "review", "hardware", "hardware and software procurement", "maintain", "audits", "setup"], "requirements": {"degrees": ["higher diploma or above", "fresh graduate"], "majors": ["computer studies"], "languages": ["english", "chinese"], "language_level": ["good command"], "hard_skills": ["o365", "mcse", "vmware", "active directory", "tcp", "cyber security", "problem-solving", "ccna", "ip", "focus"], "soft_skills": ["confidence", "responsible", "problem-solving", "hands on", "self-initiative", "customer focus", "active"], "languages_combined": [{"language": "english", "language_level": ["good command"]}, {"language": "chinese", "language_level": ["good command"]}]}, "experience_required": {"duration": ["2 years"], "field": ["administration", "relevant working experience", "it support"]}}, {"job_id": "100003009049892", "location_code": "hk", "company": "Safilo Far East Ltd", "job_title": "IT Infrastructure and Support Specialist", "description": "Based in our Hong Kong Regional Headquarters, the\u00a0IT Infrastructure and Support Specialist will be responsible for effective provisioning, installation/ configuration, operation, and maintenance of systems hardware, software and network infrastructure, tracking and troubleshooting support issues, and completing other tasks as assigned by IT Director.\n\nJob Responsibilities:\n\nManaging day to day network and IT issues, applications and databases.\nMust be able to perform diagnosis on both hardware and software issues and implement solutions and resolve issues.\nAnalyze problem tickets to identify permanent solutions, user training needs, Help Desk process improvement, and ideas to eliminate business interruptions.\nProvide remote support to users across the region for hardware and software issues.\nWorking with our European Headquarters to standardize and streamline processes.\n\nRequirements:\n\nDegree Holder in Computer Studies or equivalent.\nMinimum 4 years of experience in related field.\nPossess a strong technical background in system administration and operation skills.\nGood understanding of how to support/troubleshoot/repair: Windows, Microsoft Active Directory, LAN and WAN network management, watchguard firewall, PC Hardware, mobile device management.\nExperience with applications such as Office365, Azure, Veeam, Teamviewer, Hyper-V, would be highly regarded.\nPrevious exposure to ERP, inventory management, CRM, B2B, SFA systems would be an advantage.\nThe ability to maintain and troubleshoot databases such as MS SQL Server and Oracle would be an advantage.\nMust be self-motivated and have the independence, initiative and desire to achieve.\nStrong time management skills with the ability to respond to service and trouble calls quickly and efficiently, while adjusting priorities.\nStrong English proficiency.\nInterested parties please send your applications together with your availability, latest and expected package to us.\n\nAll information collected will be used for recruitment purpose only.", "employment_types": ["Full Time"], "selling_points": [], "locations": ["Lai Chi Kok"], "categories": ["Information Technology (IT)", "Support", "Network & System"], "post_time": "2022-01-14T09:24:29Z", "salary": {"currency": null, "max": null, "min": null, "period": "monthly", "term": null}, "salary_visible": false, "title_keywords": ["specialist"], "responsibilities": ["ideas", "hardware and software issues", "databases"], "requirements": {"degrees": ["degree holder"], "majors": ["computer studies"], "languages": ["english"], "language_level": ["proficiency"], "hard_skills": ["network management", "hyper-v", "azure", "active directory", "mobile device", "ms sql server", "erp", "hardware", "databases", "firewall", "pc", "wan", "oracle"], "soft_skills": ["self-motivated", "time management skills", "troubleshoot", "active", "initiative"], "languages_combined": [{"language": "english", "language_level": ["proficiency"]}]}, "experience_required": {"duration": ["minimum 4 years"], "field": ["related"]}}, {"job_id": "100003009033907", "location_code": "hk", "company": "Primetech Technology Limited", "job_title": "IT Support Officer (Financial Institution)", "description": "Job Description:\n\nProvide technical support service for internal users\u00a0\nInstall, configure and upgrade variety of IT services including network printing, directory structures, user access and file services.\nAnticipate communication and networking problems and implement preventive measures\nTechnical Support for Desktop PCs \u2013 both Software and Hardware.\nMonitor and report on the progress of all support calls as well as maintain inventory update\nWork with internal and external parties to resolve technical issues\n\nJob Requirement:\n\nHigher Diploma\u00a0in\u00a0Information Technology\u00a0or equivalent\nAt least 1\u00a0year of IT support experience;\nGood command of spoken & written English and\u00a0Chinese", "employment_types": ["Full Time", "Contract"], "selling_points": ["5-day work", "Great career exposure", "Attractive remuneration"], "locations": ["Not Specified"], "categories": ["Information Technology (IT)", "Support", "IT Management", "Network & System"], "post_time": "2022-01-15T03:49:12Z", "salary": {"currency": null, "max": null, "min": null, "period": "monthly", "term": null}, "salary_visible": false, "title_keywords": ["it support officer"], "responsibilities": ["software", "technical support", "inventory", "pcs", "monitor", "internal and external parties", "communication", "hardware", "maintain", "report"], "requirements": {"degrees": ["diploma"], "majors": ["information technology"], "languages": ["english", "chinese"], "language_level": ["good command"], "hard_skills": [], "soft_skills": [], "languages_combined": [{"language": "english", "language_level": ["good command"]}, {"language": "chinese", "language_level": ["good command"]}]}, "experience_required": {"duration": ["at least 1 year"], "field": ["it support"]}}, {"job_id": "100003009053044", "location_code": "hk", "company": "PeopleLink Services Limited", "job_title": "Operation Support Engineer / Network Operation Engineer (On Job training will be provided)", "description": "Job Description:\u00a0\n\nProvide operation support in Data Centre / Network Operation Center\nConducting routine system health check; producing performance reports\nTo inspect, test and troubleshooting for system or servers' issue\nFollow procedures, instructions and checklists to complete tasks with good quality\nEnsure all client requests and other ad-hoc duties are processed in an efficient and timely manner\n\nJob Requirement\u00a0\u00a0\n\nHKCEE/ DSE or above.\u00a0 IT-related qualification is an advantage\u00a0\u00a0\nKnowledge of Windows / Linux / Networking will be an advantage\nGood communication and interpersonal skills\nFresh\u00a0graduate are welcome to apply\n\nPlease submit your resume with current and expected salary. All applications will be treated strictly confidential for recruitment purpose only. Un-selected candidates will be considered for other vacancies.", "employment_types": ["Full Time", "Permanent", "Contract"], "selling_points": ["Data Center, Network Operation", "System and Network Monitoring", "Training provided"], "locations": ["Not Specified"], "categories": ["Information Technology (IT)", "Support", "Network & System", "Others"], "post_time": "2022-01-17T05:21:23Z", "salary": {"currency": null, "max": null, "min": null, "period": "monthly", "term": null}, "salary_visible": false, "title_keywords": ["engineer", "operation support"], "responsibilities": ["performance reports", "data", "quality", "procedures", "troubleshooting", "ad-hoc duties"], "requirements": {"degrees": ["fresh graduate", "dse"], "majors": [], "languages": [], "language_level": [], "hard_skills": ["linux"], "soft_skills": ["communication and interpersonal skills"], "languages_combined": []}, "experience_required": {"duration": [], "field": []}}, {"job_id": "100003009048272", "location_code": "hk", "company": "Media-Go Engineering Ltd", "job_title": "System Support Engineer", "description": "Job responsibilities\n\n\nTechnical support, maintenance and project implementation for various IT projects\nDocumentation management of PC/network equipment inventory and etc.\nProvide in-house technical support\nEstablish and maintain technical standards and best practices in compliance with organization\u2019s policies and standards\n\nJob requirements\n\n\nDegree or Diploma holder in computer or information technology or equivalent\nHands-on experience in workstation, server and network equipment setup and management\nFamiliar with Windows & Linux server operation, Windows & Mac desktop application (MS office or etc.) and Cisco network device with strong troubleshooting skill\nGood interpersonal and communication skills in English & Chinese (including Mandarin)\nCandidate with less experience will be considered as Assistant System Support Engineer\nImmediate available preferred\n\nWe offer competitive remuneration package and good prospects to the right candidates. Interested parties please send your full resume, current and expected salary to us by clicking\u00a0\u201cAPPLY NOW\u201d, or post to\u00a025/F, Westin Centre, 26 Hung To Road, Kwun Tong, Kowloon,\u00a0Hong Kong, or fax to\u00a0+852-3101-2614.\u00a0(Please quote the job reference number and job title on the subject).\n\nFor more information, please visit our website:\u00a0www.mediago-group.com\n\nData collected will be kept confidential and used for recruitment purposes only.", "employment_types": ["Full Time"], "selling_points": [], "locations": ["Kwun Tong"], "categories": ["Information Technology (IT)", "Support", "IT Management", "Network & System"], "post_time": "2022-01-15T03:49:54Z", "salary": {"currency": null, "max": null, "min": null, "period": "monthly", "term": null}, "salary_visible": false, "title_keywords": ["system support", "engineer"], "responsibilities": ["management", "maintenance", "technical support", "policies", "inventory", "compliance", "implementation", "maintain", "documentation"], "requirements": {"degrees": ["diploma holder", "degree"], "majors": ["information technology"], "languages": ["english", "chinese", "mandarin"], "language_level": ["good"], "hard_skills": ["server", "linux", "ms office"], "soft_skills": ["communication skills", "hands-on", "interpersonal", "troubleshooting"], "languages_combined": [{"language": "english", "language_level": ["good"]}, {"language": "chinese", "language_level": ["good"]}, {"language": "mandarin", "language_level": ["good"]}]}, "experience_required": {"duration": [], "field": ["management", "system support"]}}, {"job_id": "100003009053652", "location_code": "hk", "company": "International Transport Information Systems Limited", "job_title": "Customer Service", "description": "Job Description:\n\nSupport service through hot line and email;\nGather preliminary information and pass to second line support;\nUnderstand customer requirement, provide solution through usage of ITIS software package;\nWrite up of customer requirement;\nConduct system testing;\nProvide user training;\nPrepare and maintain user documentation, such as user manual, training manual, etc.\n\nJob Requirement:\n\nWith 2 year or above relevant experience;\nDiploma or equivalent is a plus;\nKnowledge in logistics, freight forwarding, and transportation is a plus;\nExperience in using ERP systems of any kind is a plus;\nResponsive, good communication/interpersonal skills, and open to new tasks/ exposure;\nAble to listen to customers and understand their key concerns in order to achieve better services and solutions (with analytical mindset);\nPatient, helpful, eager to help customer resolving issues relating to services offered;\nGood command of spoken & written English and/or Chinese.\n\nEmployees with good performance will be promoted.\n\n\n\nWe are equal opportunity employer and welcome applications from all qualified candidates.\n\n", "employment_types": ["Full Time", "Permanent"], "selling_points": [], "locations": ["Kowloon Bay"], "categories": ["Sales, CS & Business Devpt", "Customer Service - Supervisor / Officer", "Information Technology (IT)", "Support"], "post_time": "2022-01-17T07:17:50Z", "salary": {"currency": null, "max": null, "min": null, "period": "monthly", "term": null}, "salary_visible": false, "title_keywords": ["customer service"], "responsibilities": ["software"], "requirements": {"degrees": ["diploma"], "majors": [], "languages": ["english", "chinese"], "language_level": ["good command"], "hard_skills": ["documentation", "erp systems", "plus"], "soft_skills": ["communication", "patient", "responsive", "interpersonal skills"], "languages_combined": [{"language": "english", "language_level": ["good command"]}, {"language": "chinese", "language_level": ["good command"]}]}, "experience_required": {"duration": ["2 year"], "field": ["relevant experience"]}}, {"job_id": "100003009055795", "location_code": "hk", "company": "Page Personnel", "job_title": "Sales Support Specialist - Health Care Solution", "description": "A leading health care solution company is now seeking for a Sales Support to join their winning team. The chosen candidate will be responsible for providing sales support service to the team.\n\nClient Details\n\nOur client is one of the leading healthcare solution companies based in Europe with nearly 10 years of experience. They are well-known for their excellent experience in clinical support. They are currently seeking for a talent to join their vibrant team now.\n\nDescription\n\nResponsible for order processing and sales support\nBackup for sales team\nPrepare and follow up sales orders\nProvide after-sales service\nCoordinate with suppliers on quotation\nAssist with ad-hoc projects\n\nProfile\n\nDiploma holder or above\n3+ years in sales administrative experience\nSales support experience in healthcare devices or IT solution is highly preferable\nAbility to handle multiple tasks at the same time\nCommand on Thai, Bahasa Indonesian/ Malay, Vietnamese or other SEA region languages is an advantage\nFluent in spoken and written English, Mandarin and Cantonese\n\nJob Offer\n\nMedical Allowance\nOn-the-job training\nCareer progression\nAttractive salary package\nPerformance bonus\n\nTo apply online please click the 'Apply' button below. For a confidential discussion about this role please contact Coco Ng on +852 3602 2446.", "employment_types": ["Full Time", "Permanent"], "selling_points": ["3+ years in sales administrative experience", "MNC, Global Exposure", "Immediately available"], "locations": ["Not Specified"], "categories": ["Information Technology (IT)", "Support", "Medical Services", "Medical Services Technician", "Sales, CS & Business Devpt", "Sales Administration"], "post_time": "2022-01-18T02:57:22Z", "salary": {"currency": "HKD", "max": 29999, "min": 25000, "period": "monthly", "term": null}, "salary_visible": true, "title_keywords": ["specialist", "sales"], "responsibilities": ["quotation", "coordinate with", "after-sales service", "sales team", "contact", "order processing", "clinical support", "ad-hoc projects"], "requirements": {"degrees": ["diploma holder"], "majors": [], "languages": ["cantonese", "english", "mandarin", "thai", "vietnamese", "indonesian", "malay"], "language_level": ["advantage", "fluent"], "hard_skills": ["sales support", "order processing"], "soft_skills": ["handle multiple tasks", "responsible"], "languages_combined": [{"language": "cantonese", "language_level": ["fluent"]}, {"language": "english", "language_level": ["fluent"]}, {"language": "mandarin", "language_level": ["fluent"]}, {"language": "thai", "language_level": ["advantage"]}, {"language": "vietnamese", "language_level": ["advantage"]}, {"language": "indonesian", "language_level": ["advantage"]}, {"language": "malay", "language_level": ["advantage"]}]}, "experience_required": {"duration": ["10 years", "3+ years"], "field": ["healthcare", "sales support", "administrative", "it", "clinical"]}}, {"job_id": "100003009053416", "location_code": "hk", "company": "HKBN Jos Limited", "job_title": "Senior Technical Consultant", "description": "You\u00a0will create impact via\u2026\n\n\nAct as a contact point for ticket escalation\nAssist Service Manager to ensure all Service Level Agreements have been met\nManage incident & change according to ITIL standard\nImprove & drive operational efficiency\nProvide documentation for standard procedures\nWrite simple scripts for task automation to enhance monitoring/ reporting/ troubleshooting/ health check procedures\nThe follow attributes will be valued\u2026\n\nUniversity Graduate / Higher Diploma holder in Computer Science or Information Technology, or relate discipline\nMore than 3 years' relevant technical experience in Deskside Support\nExperience in Server/ Network/ Cloud is an advantage\nExcellent verbal and written communication and teamwork skills to effectively connect with both business and technical IT teams\n\nJoin Us Today!\n\nAll information provided by applicants will be treated in strict confidence and used for consideration in relation to the relevant post within the company.\n\nAll personal data of unsuccessful applicants will be destroyed within one year. Applicants who are not invited for an interview within 3 weeks may consider their application unsuccessful.", "employment_types": ["Full Time", "Permanent"], "selling_points": ["Manage ticket escalation", "Assist Service Manager to ensure all SLAs are met", "Fix incident & change according to ITIL standard"], "locations": ["Not Specified"], "categories": ["Information Technology (IT)", "Hardware", "Support", "Network & System"], "post_time": "2022-01-17T06:57:11Z", "salary": {"currency": null, "max": null, "min": null, "period": "monthly", "term": null}, "salary_visible": false, "title_keywords": ["consultant"], "responsibilities": ["reporting", "monitoring", "procedures", "troubleshooting", "deskside support", "teams", "communication", "contact", "documentation", "personal data"], "requirements": {"degrees": ["university graduate", "higher diploma holder"], "majors": ["computer science", "information technology"], "languages": [], "language_level": [], "hard_skills": ["itil", "server", "documentation", "simple"], "soft_skills": ["communication", "confidence", "teamwork", "troubleshooting"], "languages_combined": []}, "experience_required": {"duration": ["3 years"], "field": []}}, {"job_id": "100003009055822", "location_code": "hk", "company": "HKT Financial Services", "job_title": "Product Executive, HKT Financial Services", "description": "Your role\n\nDesign and develop a cutting-edge mobile payment wallet application on iOS / Android platform\nIdentify business pain points and propose solutions; Summarize valuable results of industry research, business analysis\nIllustrate UX / UI design ideas, present process flow and user journey via wireframes and mockups. Identify and troubleshoot UX problems\nCommunicate with various lines of business within HKT as well as external business partners to define system requirement and user journey\nCoordinate with internal IT, external vendors and Card Schemes to define business processes, product features and functions\nPerform ad-hoc assignments\n\nTo succeed in this role\n\nDegree holder in Computer Science, Information Technology, Electronic Engineering or related discipline\nAt least 3 years of working experience of product management (or equivalent) in Internet or related industries\nSolid experience in developing digital products (App or Web) from scratch. Proven successful track record would be a huge plus\nExperience in UI/UX design with usability principles\nExperience in E-commerce related, digital tool products development and management would be nice\nPassionate, creative and knowledgeable in web and mobile technologies\nGood communication and presentation skills in Cantonese, Mandarin and English\n\nWe offer attractive & competitive salary and benefits, an exciting work environment and excellent career development opportunities. If you have the desire for an exciting and rewarding career, please send us your resume (please put our ref no. on the application subject), stating your present and expected salary to Human Resources Department by sending Email to career-fintech@pccw.com\n\nHKT is an equal opportunity employer and welcomes applications from all qualified candidates. Information provided will be treated in strict confidence and will only be used for recruitment-related purposes. Personal data provided by job applicants will be used strictly in accordance with the employer's\u00a0privacy statement\u00a0(http://www.hkt.com/privacy-statement), a copy of which will be provided immediately upon request.", "employment_types": ["Full Time"], "selling_points": [], "locations": ["Quarry Bay"], "categories": ["Information Technology (IT)", "IT Project Management / Team Lead", "Support", "Product Management / Business Analyst"], "post_time": "2022-01-18T02:59:07Z", "salary": {"currency": null, "max": null, "min": null, "period": "monthly", "term": null}, "salary_visible": false, "title_keywords": ["executive"], "responsibilities": ["communicate with", "management", "ideas", "ad-hoc assignments", "design and develop", "coordinate with", "design", "developing", "communication", "payment", "troubleshoot", "business analysis", "ui"], "requirements": {"degrees": ["degree holder"], "majors": ["engineering", "computer science", "information technology"], "languages": ["cantonese", "english", "mandarin"], "language_level": ["good"], "hard_skills": ["plus", "web", "e-commerce", "analysis", "nice", "mobile", "scratch", "android"], "soft_skills": ["passionate", "cutting-edge", "communication", "presentation skills", "troubleshoot", "creative"], "languages_combined": [{"language": "cantonese", "language_level": ["good"]}, {"language": "english", "language_level": ["good"]}, {"language": "mandarin", "language_level": ["good"]}]}, "experience_required": {"duration": ["at least 3 years"], "field": ["management", "e-commerce", "related", "development", "developing", "design", "product management", "digital"]}}, {"job_id": "100003009049369", "location_code": "hk", "company": "HGC Global Communications Limited", "job_title": "End User Computing Support Engineer", "description": "Responsibilities:\n\nTo provide EUC day-to-day support, inclusive of Office IT systems, PC hardware / software / connectivity and BYOD users; and\nTo assist the VDI Project deployment includes user management, profile migration, data migration, troubleshooting and inventory management\n\n\u00a0Requirements:\n\nDiploma in IT or related discipline;\nMinimum 3 years working experience in EUC support;\nHands on experience in VDI (VMWare), Microsoft Office and Outlook Applications (troubleshooting & problem solving) and VPN\nFamiliar with PC / Laptop / Phone / Mobile phone / Thin Client;\nService to Senior Management experience is a plus\nGood analytical, PC / device trouble shooting, and problem solving skills;\nGood interpersonal skill and a good team player\nMature, dynamic, work independent and self-motivated\nGood spoken and written English and Cantonese, Mandarin a plus.\n\nWe offer competitive salary package and career development opportunity. \u00a0Free company coach is provided. Interested parties, please quote our reference number and apply with full resume,\u00a0present and expected salary, by clicking \"APPLY NOW\".\u00a0\n\u00a0\n\nWe are an equal opportunity employer and welcome applications from all qualified candidates. Information provided will be treated in strict confidence and only be used for consideration of your application for the relevant post within the HGC Global Communications Limited. Personal data provided by job applicants will be used strictly according to our Personal Information Collection Statement, a copy of which will be available upon written request. Information of unsuccessful candidates will be destroyed within six months.", "employment_types": ["Full Time", "Permanent"], "selling_points": ["Internal IT service and operations support", "Vibrant team culture and atmosphere", "System enhancement exposure"], "locations": ["Tsing Yi"], "categories": ["Information Technology (IT)", "Hardware", "Support", "Others"], "post_time": "2022-01-14T08:31:44Z", "salary": {"currency": null, "max": null, "min": null, "period": "monthly", "term": null}, "salary_visible": false, "title_keywords": ["support engineer"], "responsibilities": ["management", "software", "data", "systems", "troubleshooting", "inventory management", "hardware", "migration"], "requirements": {"degrees": ["diploma"], "majors": ["it"], "languages": ["cantonese", "english", "mandarin"], "language_level": ["good"], "hard_skills": ["plus", "vmware", "microsoft office", "euc", "problem solving", "mobile", "dynamic", "outlook", "vpn", "pc", "problem solving skills"], "soft_skills": ["good team player", "self-motivated", "independent", "troubleshooting", "mature", "interpersonal skill", "problem solving", "hands on", "dynamic", "problem solving skills"], "languages_combined": [{"language": "cantonese", "language_level": ["good"]}, {"language": "english", "language_level": ["good"]}, {"language": "mandarin", "language_level": ["good"]}]}, "experience_required": {"duration": ["minimum 3 years"], "field": ["management", "troubleshooting"]}}, {"job_id": "100003009051484", "location_code": "hk", "company": "Tech Advance Consultancy Limited", "job_title": "Network Support Administrator", "description": "Responsibilities:\n\nProvide network support and troubleshoot for internal teams.\nDeploy, support and maintain the local\u00a0and wide area of network infrastructure.\nNetwork equipment configurations, and take part in technical planning, development and deployment\nWork in line with business requirements with fulfill the security guidelines, and provide constant support and troubleshooting service to the users by partner with the vendor / supplier\nIdentify and resolve high priority incidents which are business impacting as quickly as possible with minimum business impact and provide solutions\nAssist in\u00a0daily IT Network related administration\n\n\u00a0\u00a0Requirements:\n\nDiploma or above in Information Technology, Computer Science or\u00a0related disciplines\nAt 3-5 years work experience related to Networking - Router, Switch, AP and Firewall technologies.\nFamiliar with level 2-3 in network and router included:\u00a0 TCP/IP, STP, VLAN, OSPF, EIGRP, BGP.\nAbility of supporting difference level of users within an organization\nGood communication skills in Mandarin.\nCandidate who have experienced on Cisco, Juniper, Huawei, F5, wireless is an advantage.\nCertification holder of CCNA / CCNP / CCIE would be an advance\nCandidate who have less experience will be consider as Junior Network Support Engineer.", "employment_types": ["Full Time", "Contract"], "selling_points": ["Opportunity to work in large-scale company", "Work 5 days per week", "With good salary package"], "locations": ["Ngau Tau Kok"], "categories": ["Information Technology (IT)", "Support", "Network & System", "Mobile / Wireless Communications"], "post_time": "2022-01-16T04:12:36Z", "salary": {"currency": "HKD", "max": 29999, "min": 25000, "period": "monthly", "term": null}, "salary_visible": true, "title_keywords": ["administrator"], "responsibilities": ["network infrastructure", "administration", "guidelines", "teams", "troubleshooting", "provide solutions", "maintain", "troubleshoot", "deploy", "planning"], "requirements": {"degrees": ["diploma or above"], "majors": ["related disciplines", "computer science", "information technology"], "languages": ["mandarin"], "language_level": ["good"], "hard_skills": ["ap", "tcp", "switch", "ccnp", "ccna", "router", "ip", "firewall"], "soft_skills": ["communication skills"], "languages_combined": [{"language": "mandarin", "language_level": ["good"]}]}, "experience_required": {"duration": ["at 3-5 years"], "field": ["related"]}}, {"job_id": "100003009054036", "location_code": "hk", "company": "Automated Systems (HK) Ltd", "job_title": "Graduate Trainee Program 2022", "description": "The Automated Systems (H.K.) Limited (ASL) Graduate Trainee Program is a 2-year intensive and comprehensive journey. Young talents receive various opportunities to develop the most advance IT skills and professional expertise which are critical in becoming an IT expert.\n\nYou may participate in one of 4 divisions:\u00a0 Solution, Infrastructure, Security & Network and Sales. Each path will enable your career and personal development and pave the way for your future success.\n\nThe Program also provides a platform for fresh or recent graduates to:\n\nTransition from university into the business environment\nGain exposure in all aspects of IT industry\nBe coached and mentored by mentors and senior managers\nCultivate career interest and aspiration\n\nBesides the latest IT technologies, trainees will acquire the following knowledge with well-structured trainings:\n\nBusiness Knowledge, Project & People Management Skill\nCommunication, Presentation and other Soft Skills\nAttachment to different job scopes / clients / projects to enrich and specialize skillsets\n\n\n\nStart your career journey with ASL!\n\n\n\n1) Solution Division\n\n(e.g. Android / iOS Development, Java / .NET Development, Mobile Application Development, Data Analysis, QA Testing, UX / UI Design, etc.)\n\nObjectives of the role\n\nUndergo fundamental trainings and job rotations within teams to gain knowledge on web applications or system developments as well as support and testing roles.\u00a0\nExperience customized job attachments according to individual\u2019s academic background, interests and strengths in order to cope with project(s) and business needs.\u00a0\nWork on a variety of\u00a0projects, enrich career experience and skills techniques.\n\nExpectations and Educational Background\n\nFinal year students / Recent graduates from University with degree in Computer Science, Information Technology or related disciplines.\u00a0\nBasic knowledge in coding, e.g. Java / .NET / Angular JS/React JS/NodeJS, HTML/HTML5, CSS, JavaScript, XML, SQL, will be an advantage.\nExperience with online community video production will be an advantage.\nPositive thinking, proactive, analytical and responsible.\nGood communication & organizational skill.\n\n2) Infrastructure Division / 3) Security & Network Division\n\n\u00a0(e.g. Cloud Solutions, Data Centre operation, Network and Security, IT Support services, Servers, Storages, Backup/Recovery, etc.)\n\nObjectives of the role\n\nUndergo fundamental trainings and job rotations across different teams to enrich experience on infrastructure, system and network support as well as security matters.\u00a0\nEngage in one or two specific project(s) to implement particular tasks in order to let them grasp the business reality.\nUpon successful completion of the program, trainees will be offered a position which matches their interests and competence.\n\n\n\nExpectations and Educational Background\n\nFinal year students / Recent graduates from University with degree in Electronic, Electrical Engineering, Engineering, Information Technology or related disciplines.\u00a0\nGraduate with electives in the above disciplines as a second major will also be considered.\nBasic knowledge of general IT support among both system and network matters.\n\n4) Sales Division (e.g. Business Support, Sales and Marketing, Product Development, etc.)\n\nObjectives of the role (Sales Team)\n\nAssist Sales Managers to develop and expand the customer base.\nSupport Sales Managers to handle all sales functions, including business proposals, tenders, customer enquirers, production orders and quotation preparations, etc.\nSell and promote professional IT solutions.\nMaintain positive customer relation & interface with customers on time.\n\nExpectations and Educational Background\n\nFinal year students / Recent graduates from University with degree in Business Administration, Marketing or related disciplines who are mature, energetic and customer-oriented are welcomed.\nProficient in computer skills and willing to take challenges.\n\nObjectives of the role (Pre-sales Team)\n\nAssist Sales team in technical manner during sales & tender cycle.\u00a0\u00a0\nAssist in tender preparation by proposal write-up, technical diagram design, BOM generation, presentation etc.\u00a0\u00a0\nAssist in customer meeting by scope crafting, technical Q&A, customer\u2019s requirement analysing\u00a0\nUpon completion of the program, trainees will be offered a specific industrial & technical consultant position in which matches their ability & competence.\n\nExpectations and Educational Background\n\nFinal year students / Recent graduates from University with degree in Computer Science, Information Technology or related disciplines.\u00a0\u00a0\nGraduates with electives in the above disciplines as a second major will also be considered.\nBasic knowledge of general IT support among both system and network matters.\n\nAre you ready for a challenging journey within a positive working environment?\n\nPlease apply via http://www1.asl.com.hk/us/people-asl/graduate-trainee-program/on or before 31 March 2022.\n\nIf a self-introduction video is available, you are welcomed to provide a hyperlink to us (highly recommended if you are interested in social media marketing and have experience in video production). Applicants with high-quality video submissions may be eligible to skip the initial interview and enter subsequent rounds directly.\n\nYou may visit our corporate web site for details: http://www1.asl.com.hk/\n\nWe are an equal opportunity employer. All applications will be treated in strict confidence and used for recruitment purposes only. Regretfully only shortlisted candidates will be notified. Personal Information Collection Statement pertaining to Recruitment", "employment_types": ["Full Time"], "selling_points": ["2-year Graduate Program", "Gain exposure in all aspects of IT industry", "Start your career journey with ASL!"], "locations": ["Shatin Area"], "categories": ["Information Technology (IT)", "Support", "Network & System", "Others", "Student / Fresh Graduate / No Experience"], "post_time": "2022-01-17T08:09:08Z", "salary": {"currency": null, "max": null, "min": null, "period": "monthly", "term": null}, "salary_visible": false, "title_keywords": ["graduate trainee"], "responsibilities": ["data", "quotation", "quality", "design", "coding", "communication", "maintain", "application development", "administration", "video production", "infrastructure", "teams", "develop", "testing", "tender", "tender preparation", "ui", "social media", "management", "data analysis", "systems", "support services", "sales team", "recruitment"], "requirements": {"degrees": ["degree"], "majors": ["business administration", "engineering", "electrical engineering", "information technology", "related disciplines", "marketing", "computer science"], "languages": [], "language_level": [], "hard_skills": ["java", "web applications", "basic", "servers", "react", "web", "it technologies", "analysis", "html", "sql", "mobile", "javascript", "computer skills", "angular", "css", "android"], "soft_skills": ["proactive", "organizational skill", "confidence", "responsible", "interested in", "positive thinking", "mature", "communication", "energetic", "comprehensive", "customer-oriented", "business environment", "structured", "presentation", "positive"], "languages_combined": []}, "experience_required": {"duration": [], "field": ["social media", "video", "video production", "infrastructure", "business", "marketing", "security"]}}, {"job_id": "100003009054806", "location_code": "hk", "company": "The Education University of Hong Kong", "job_title": "Assistant Computer Officer / Programmer I (Ref: 2200025)", "description": "Office of the Chief Information Officer\n\nThe Office of the Chief Information Officer (OCIO) has a vision to be a world-class provider of information and communications technology services and solutions to support and enhance teaching, learning, research and administration of the University.\n\nThe OCIO provides quality services to support all central information systems in support of teaching, learning, research and administration. It places emphasis on staff\u2019s career/professional development. The Office is looking for quality professionals to fill the vacancy of Assistant Computer Officer / Programmer I.\n\nThe appointee will be assigned to the Network Services Team. He/She will mainly be responsible for the eLearning support and exploration of data analytics technologies for learning and teaching.\u00a0 The appointee will also be required to work shifts on Saturdays.\n\nApplicants should have a recognized Bachelor\u2019s Degree in Information Technology or related disciplines with at least one year of relevant full-time post-qualification working experience gained in a sizeable IT environment. Fresh graduates with good potential or those having an associate degree or a higher diploma in Information Technology or related disciplines with at least 2 years of working experience may be considered for the post of Programmer I.\n\nApplicants are expected to have solid experience and knowledge in HTML, MySQL and Java/PHP. They should have good problem-solving, analytical and interpersonal skills; and be proficient in both English and Chinese with good communication skills. They should also work proactively and independently; be able to handle multiple tasks simultaneously and be a good team player.\n\nSalary will be commensurate with qualifications and experience.\n\nInitial appointment will be made on a fixed-term contract. \u00a0Fringe benefits include contract-end gratuity, leave, medical and dental benefits.\n\nThe University only accepts and considers applications submitted online for this post.\u00a0 Applicants should complete the online application form and upload a full CV.\u00a0 Review of applications will start from 28 January 2022, and will continue until the post is filled.\u00a0 Applications which are incomplete or without the required documents may not be considered. \u00a0Personal data provided by applicants will be used for recruitment and other employment-related purposes. \u00a0For details of the Personal Information Collection Statement, please refer to http://www.eduhk.hk/jobsopp/index.php?glang=en.\n\nAll applications will be treated in strict confidence.\u00a0 Only those who are shortlisted will be contacted.\u00a0 The University reserves the right not to fill the position(s) advertised.\u00a0\u00a0\n\n\n\n\nFurther information about the University is available at http://www.eduhk.hk.\n\nEdUHK is an Equal Opportunities Employer.", "employment_types": ["Full Time"], "selling_points": [], "locations": ["Not Specified"], "categories": ["Information Technology (IT)", "Support", "Software Development", "Others"], "post_time": "2022-01-17T11:12:12Z", "salary": {"currency": null, "max": null, "min": null, "period": "monthly", "term": null}, "salary_visible": false, "title_keywords": ["officer", "programmer", "assistant"], "responsibilities": ["data", "systems", "quality", "communication", "administration"], "requirements": {"degrees": ["associate degree", "diploma", "degree", "bachelor"], "majors": ["related disciplines", "it", "information technology"], "languages": ["english", "chinese"], "language_level": ["good", "proficient"], "hard_skills": ["java", "php", "data analytics", "problem-solving", "html"], "soft_skills": ["communication skills", "good team player", "independently", "responsible", "problem-solving", "handle multiple tasks", "learning", "interpersonal skills", "world-class"], "languages_combined": [{"language": "english", "language_level": ["proficient", "good"]}, {"language": "chinese", "language_level": ["proficient", "good"]}]}, "experience_required": {"duration": ["at least 2 years", "at least one year"], "field": ["related", "it", "post-qualification", "information technology"]}}, {"job_id": "100003009050712", "location_code": "hk", "company": "Hutchison Telecommunications (Hong Kong) Limited", "job_title": "IT Operation Officer", "description": "Responsibilities:\n\nManage Data Center, Operations and Service desk function of IT\u00a0\nCoordinate with internal and external parties on support system maintenance, system failover and annual drill\u00a0\nAssist in preparing, review and update various operations policies and procedures on regular basis\u00a0\nAssist in ad hoc tasks / projects as required\u00a0\n\nRequirements:\n\nAssociate degree or Higher Diploma holder\u00a0in\u00a0Information Technology/ Date Centre/ Telecommunications or related discipline\n3 years or above working experiences in IT operation\u00a0\nProficient in MS Office - Excel, knowledge of Linux, Windows and VMWare is advantage\u00a0\nIndependent, detail-minded and able to work under pressure\nGood command of written and spoken English and Chinese\n\nApart from competitive remuneration package and exciting opportunity for career development within the Group, we provide attractive employee benefits such as free company shuttle, free company SIM card and preferential SIM plan offers, comprehensive medical & insurance schemes, as well as full range of other employee well-being provisions.\u00a0\n\nInterested parties, please apply with full resume, present and expected salary, by clicking \u201cAPPLY NOW\u201d. Please quote the reference number on the e-mail subject.\n\nWe are an equal opportunity employer and welcome applications from all qualified candidates. Personal data collected will be treated in the strictest confidence and handled confidentially by authorised personnel for recruitment-related purposes only within the CK Hutchison Group of companies. The personal data of unsuccessful applicants will be destroyed after the recruitment exercise pursuant to the requirements of the Personal Data (Privacy) Ordinance in Hong Kong.", "employment_types": ["Full Time", "Permanent"], "selling_points": [], "locations": ["Tsing Yi"], "categories": ["Information Technology (IT)", "Support", "Others"], "post_time": "2022-01-14T11:13:29Z", "salary": {"currency": null, "max": null, "min": null, "period": "monthly", "term": null}, "salary_visible": false, "title_keywords": ["operation officer"], "responsibilities": ["maintenance", "data", "operations", "policies", "internal and external parties", "coordinate with", "review", "procedures", "ad hoc tasks"], "requirements": {"degrees": ["associate degree", "higher diploma holder"], "majors": ["information technology"], "languages": ["english", "chinese"], "language_level": ["good command"], "hard_skills": ["excel", "vmware", "linux", "ms office"], "soft_skills": ["detail-minded", "comprehensive", "independent", "work under pressure"], "languages_combined": [{"language": "english", "language_level": ["good command"]}, {"language": "chinese", "language_level": ["good command"]}]}, "experience_required": {"duration": ["3 years"], "field": ["operation", "it"]}}, {"job_id": "100003009056272", "location_code": "hk", "company": "Swing Consulting Limited", "job_title": "Data Centre Operator", "description": "Responsibilities:\n\nResponsible for day-to-day support in 7x24 Data Centre\nProvide technical support including Data Centre operations, equipment maintenance and service provisioning\nPerform monitoring of Data Centre network and system\nMaintain accurate records, document problems, and prepare reports\nHandle incident, technical problem and escalate to upper tier\n\nRequirements:\n\nMinimum 1-year of working experience in computer and operation or related role\nBasic knowledge in Data Centre domain\nGood command of spoken and written English and Chinese\nShift duty is required\nNo experience in IT industry also welcome\n\nPlease send your full resume with MS Word format to us\u00a0by email\u00a0or\u00a0fax: 3426 2763,\u00a0or you may click the\u00a0Apply Now\u00a0button below.\u00a0\n\nFor other vacancies, please visit our website www.swing-hk.com\n\nJoin us on facebook \u2013 www.facebook.com/swinghk\n\nAll information provided will be treated in strict confidence and used for recruitment purposes only.\u00a0", "employment_types": ["Full Time"], "selling_points": ["5 days work", "Exposure to sizeable company", "Attractive package and career progression"], "locations": ["Not Specified"], "categories": ["Information Technology (IT)", "Support", "Network & System", "Others", "Student / Fresh Graduate / No Experience"], "post_time": "2022-01-18T03:46:49Z", "salary": {"currency": null, "max": null, "min": null, "period": "monthly", "term": null}, "salary_visible": false, "title_keywords": ["data centre operator"], "responsibilities": ["maintenance", "data", "technical support", "operations", "monitoring", "maintain", "prepare reports"], "requirements": {"degrees": [], "majors": [], "languages": ["english", "chinese"], "language_level": ["good command"], "hard_skills": ["facebook", "no", "basic", "ms word"], "soft_skills": ["confidence"], "languages_combined": [{"language": "english", "language_level": ["good command"]}, {"language": "chinese", "language_level": ["good command"]}]}, "experience_required": {"duration": ["minimum 1-year"], "field": ["related", "operation", "it"]}}, {"job_id": "100003009054135", "location_code": "hk", "company": "Prister Corporation Limited", "job_title": "STEM/ CODING  Specialist", "description": "Responsibilities:\n\n\u00a0\u00a0\u00a0\u00a0\u00a0\u00a0To create a series of creative contents to inspire young individual\u00a0\n\u00a0\u00a0\u00a0\u00a0\u00a0\u00a0To train, facilitate and assist trainers\n\u00a0\u00a0\u00a0\u00a0\u00a0\u00a0To\u00a0facilitate the student with the fun learning objective\u00a0\n\nRequirements:\n\n\u00a0\u00a0\u00a0\u00a0\u00a0\u00a0University or above in Computer Science or related\u00a0discipline\u00a0\n\u00a0\u00a0\u00a0\u00a0\u00a0\u00a0Minimum 1 year of work experience in STEM/ Coding/ AIoT related\n\u00a0 \u00a0 \u00a0 LOVE and PASSIONATE with Technology, Robotic, Toy\n\u00a0\u00a0\u00a0\u00a0\u00a0\u00a0Creative, Energetic, Passionate to work in Education Industry\n\u00a0\u00a0\u00a0\u00a0\u00a0\u00a0Good Communication, Good Presentation and Inter-personal skills\n\u00a0\u00a0\u00a0\u00a0\u00a0\u00a0Good command of written and spoken English and Chinese\u00a0\n\u00a0\u00a0\u00a0\u00a0\u00a0\u00a0Self-Motivated , Result-Oriented and Good team payer", "employment_types": ["Full Time", "Permanent"], "selling_points": [], "locations": ["Ngau Tau Kok"], "categories": ["Education", "Tutor / Instructor", "Information Technology (IT)", "Support", "Others", "Student / Fresh Graduate / No Experience"], "post_time": "2022-01-17T08:40:30Z", "salary": {"currency": null, "max": null, "min": null, "period": "monthly", "term": null}, "salary_visible": false, "title_keywords": ["specialist"], "responsibilities": ["contents"], "requirements": {"degrees": [], "majors": [], "languages": ["english", "chinese"], "language_level": ["good command"], "hard_skills": [], "soft_skills": ["passionate", "result-oriented", "self-motivated", "creative", "inter-personal skills", "communication", "energetic", "presentation"], "languages_combined": [{"language": "english", "language_level": ["good command"]}, {"language": "chinese", "language_level": ["good command"]}]}, "experience_required": {"duration": ["minimum 1 year"], "field": ["related"]}}, {"job_id": "100003009045292", "location_code": "hk", "company": "CITIC Telecom International CPC Limited", "job_title": "Senior System Administrator - Infrastructure", "description": "The Challenge We Pose to You:\u00a0\n\n\nSupport & maintain Server pools in windows, Linux platform\nSystem administration of VMware\nProvide End User Computing support\nManage enterprise wide LAN / WAN networks\nSecurity management of internal & external networks\nSupervise data & system backup & recovery operation\nProvide regional office IT environment support\nNegotiate with Vendor on Hardware and Software\nHandle ad hoc projects as assigned\n\nWhat You Bring to Us:\n\n\nDegree in Computer Science or related discipline\nMinimum 5 years relevant experience in sizeable organizations\nExperience in supporting and administrating Windows & Linux Server, providing end-user support & remote assistance\nExperience in supporting/implementing LAN/SAN/WAN including load-balancer, firewall, router, switch etc\nKnowledge in Security Product, such as FortiGate, FortiSandbox and FortiMail\nKnowledge in virtualization technologies, such as VMWare\nExperience in the management of Active Directory\u00a0\nExperience n leading junior teammate will be an advantage\u00a0\nGood interpersonal, communication & problem-solving skills\nGood command of spoken and written English, Chinese & Mandarin\nAble to work independently and under pressure\nProvide regional office support\u00a0\n\n\n\nOur Offer:\u00a0\n\n5-day work, 14 days annual leave, a competitive remuneration package, comprehensive medical plan, local and regional training and rewarding career opportunities\n\nPlease send your complete resume, inclusive of\u00a0your available date, current and expected salary\u00a0by clicking \"Apply now\"\u00a0or by mail\u00a0to:\u00a0Human Resources and Administration Department, CITIC Telecom International CPC Limited, 20/F, Lincoln House, Taikoo Place, 979 King's Road, Quarry Bay, Hong Kong.\n\nWebsite:\u00a0\u00a0www.citictel-cpc.com\n\nAll information received will be kept strictly confidential and for employment-related purpose only.", "employment_types": ["Full Time", "Permanent"], "selling_points": ["Support server, database, network, security&email", "Min 5 years of system admin experience", "14 AL, 5 day work, medical and dental insurance"], "locations": ["Kwun Tong"], "categories": ["Information Technology (IT)", "Support", "IT Management", "Network & System"], "post_time": "2022-01-16T21:50:14Z", "salary": {"currency": null, "max": null, "min": null, "period": "monthly", "term": null}, "salary_visible": false, "title_keywords": ["senior system administrator"], "responsibilities": ["management", "software", "active directory", "data", "office support", "website", "communication", "hardware", "ad hoc projects", "plan", "maintain server", "administration"], "requirements": {"degrees": ["degree"], "majors": ["computer science"], "languages": ["english", "chinese", "mandarin"], "language_level": ["good command"], "hard_skills": ["linux", "security management", "vmware", "active directory", "switch", "vendor", "router", "hardware", "firewall", "server", "problem-solving skills", "wan"], "soft_skills": ["work independently", "under pressure", "communication", "comprehensive", "problem-solving skills", "active", "interpersonal"], "languages_combined": [{"language": "english", "language_level": ["good command"]}, {"language": "chinese", "language_level": ["good command"]}, {"language": "mandarin", "language_level": ["good command"]}]}, "experience_required": {"duration": ["minimum 5 years"], "field": ["administrating", "management", "relevant experience"]}}, {"job_id": "100003009046997", "location_code": "hk", "company": "The Specialists Surgery and Endoscopy Centre", "job_title": "IT Officer / Senior IT Officer", "description": "Responsibilities:\n\n\nProvide IT help-desk support for internal parties, inclusive of software installation and update, hardware replacement etc.\nMonitor and maintain computer systems and networks.\nPerform network enhancement, performance and health status monitoring, troubleshooting network related issues and problem.\nPrepare and maintain system documentation and reports related to IT.\nPerform any other duties as assigned by supervisor(s).\n\nRequirement:\n\nHigher Diploma or Degree in Computer Science, Information Technology or related disciplines.\nWith at least 2 years of working experience in IT infrastructure or user support.\nProficiency in Microsoft Windows, Microsoft Office, and similar applications.\nFamiliar with TCP/IP, network equipment, internet, network security and email.\nGood command of spoken and written in English and Cantonese.\n\nPreferred Attributes:\n\nRelevant experience in healthcare industry.\nStrong knowledge in networking and security is a big plus.\nSelf-motivated and able to work independently under pressure.\nImmediate availability is highly preferred.\nCandidates with more experience will be considered as Senior IT Officer.\n\n\n\nWe offer\u00a0competitive pay\u00a0and fringe benefits. Interested parties please send your full resume with\u00a0current salary and expected salary to\u00a0Human Resources Department, The Specialist\u00a0by clicking 'Apply Now\".\n\nIf you would like to know more about our service or detail, please visit our website\u00a0https://www.specialists.hk/\n\nThe information provided will only be used for recruitment related purposes. All personal information on unsuccessful candidates will be destroyed within 6 months.", "employment_types": ["Full Time"], "selling_points": ["Healthcare Industry", "Help-desk support", "5 days work"], "locations": ["Mong Kok"], "categories": ["Information Technology (IT)", "Support"], "post_time": "2022-01-14T01:59:11Z", "salary": {"currency": null, "max": null, "min": null, "period": "monthly", "term": null}, "salary_visible": false, "title_keywords": ["senior it officer", "it officer"], "responsibilities": ["installation", "any other duties", "software", "system documentation", "monitoring", "monitor", "computer systems", "troubleshooting", "hardware", "maintain", "reports", "internal parties"], "requirements": {"degrees": ["diploma", "degree"], "majors": ["related disciplines", "computer science", "information technology"], "languages": ["cantonese", "english"], "language_level": ["good command"], "hard_skills": ["ip", "plus", "tcp", "microsoft office"], "soft_skills": ["self-motivated", "under pressure", "work independently"], "languages_combined": [{"language": "cantonese", "language_level": ["good command"]}, {"language": "english", "language_level": ["good command"]}]}, "experience_required": {"duration": ["at least 2 years"], "field": ["infrastructure", "healthcare industry", "it", "relevant experience"]}}, {"job_id": "100003009047191", "location_code": "hk", "company": "Vanguard Business Services Limited", "job_title": "IT Support Engineer", "description": "Our client is seeking an IT Support Engineer to join their expanding team:\n\n\u00a0 \u00a0 \u00a0 \u00a0 \u00a0 \u00a0 \u00a0Role & Responsibility:\n\nOnsite at customer site to perform daily IT Support service\nPatience and well support with users request\nFamiliar knowledge with window server domain & AD\nGood network knowledge for troubleshooting within network environment\nExperience in IT support service such as printer setup /Window installation / dairy tape swap etc..\nWellness with working third party vendor like Dell & provide onsite escort\nCarry out hardware Service activities\nOnsite parts inventory management\nCalls logging and reporting\nRequirements and Qualification:\u00a0\nHigh Diploma, IVE graduate in Electronic /Electrical / Mechanical Engineering\n3 year relevant working experience\nGood command of both spoken and written Chinese and English\nGood PC skills\nExcellent interpersonal and customer service skills with pleasant and outgoing personality\nSelf-initiative, good sense of responsibility and able to work independently\n\n\n", "employment_types": ["Full Time", "Contract"], "selling_points": ["Excellent chance to work in a dynamic environment", "One month Gratuity after 1 year service", "Experience working as IT Support"], "locations": ["Quarry Bay"], "categories": ["Information Technology (IT)", "Hardware", "Support"], "post_time": "2022-01-14T02:32:35Z", "salary": {"currency": null, "max": null, "min": null, "period": "monthly", "term": null}, "salary_visible": false, "title_keywords": ["it support engineer"], "responsibilities": ["installation", "reporting", "daily it support", "troubleshooting", "inventory management", "hardware", "third party", "setup"], "requirements": {"degrees": ["high diploma"], "majors": ["mechanical engineering"], "languages": ["english", "chinese"], "language_level": ["good command"], "hard_skills": ["pc skills"], "soft_skills": ["outgoing personality", "customer service skills", "work independently", "sense of responsibility", "pleasant", "self-initiative", "interpersonal"], "languages_combined": [{"language": "english", "language_level": ["good command"]}, {"language": "chinese", "language_level": ["good command"]}]}, "experience_required": {"duration": ["3 year"], "field": ["relevant working experience"]}}, {"job_id": "100003009048865", "location_code": "hk", "company": "Brother Machinery (Asia) Limited", "job_title": "IT Specialist / System Engineer / IT Support / RPA developer", "description": "Responsibilities\n\n\nProvide IT network security support & related infrastructure technical solutions\nProvide Server, PC, Networking and other IT related support services to internal users and clients\nDeveloping RPA for internal use\nDeliver timely, reliable and quality IT solutions to meet different internal project needs\nPlan, coordinate and implement IT security measures in order to protect data, software and hardware\nWork with different teams, suppliers, vendors and users to deliver assigned tasks on schedule and to run daily operations smoothly\n\nTraining & Development\nProvide in house E-learning platform and study subsidy for job related topics\n\nOur Ideal Candidate\n\n\nDiploma or above in Information Technology or related disciplines\n3 years\u2019 experience in end-user support and IT project deployment\nExperience in deploying, managing and supporting of network infrastructure, Window servers and VMWare\nExcel VBA knowledge\nHolder of MCSE, CCNA, CCNP is preferred\nSAP and RPA Knowledge is an advantage\nA good team player, detail-oriented, good problem-solving skills, self-motivated with good communication and interpersonal skills\nGood command in both English and Chinese\n\nStaff Benefits\n\n5 days work\nBank Holiday\nFlexible Working Hours\nWork From Home\nTransportation Allowance\nMedical & Dental Insurance\nBody check\nInterested?\nIf you are interested please send your\u00a0full resume,\u00a0current\u00a0and\u00a0expected salary\u00a0and\u00a0availability\u00a0by clicking \"APPLY NOW\".\n\n*Personal data provided are treated in strictest confidence and for recruitment purposes only.\u00a0 All information will be destroyed after the process completed.*", "employment_types": ["Full Time", "Permanent"], "selling_points": [], "locations": ["Tsuen Wan Area"], "categories": ["Information Technology (IT)", "Support", "Software Development", "Network & System"], "post_time": "2022-01-15T03:50:04Z", "salary": {"currency": null, "max": null, "min": null, "period": "monthly", "term": null}, "salary_visible": false, "title_keywords": ["developer", "it specialist", "system engineer", "it support"], "responsibilities": ["network infrastructure", "software", "data", "infrastructure", "quality", "support services", "developing", "teams", "coordinate", "hardware", "daily operations", "communication", "schedule", "plan"], "requirements": {"degrees": ["diploma or above"], "majors": ["related disciplines", "information technology"], "languages": ["english", "chinese"], "language_level": ["good command"], "hard_skills": ["excel", "vba", "mcse", "servers", "vmware", "sap", "problem-solving skills", "ccnp", "ccna", "rpa", "hardware", "deployment", "server", "pc"], "soft_skills": ["good team player", "self-motivated", "timely", "detail-oriented", "learning", "communication and interpersonal skills", "problem-solving skills", "reliable", "ideal"], "languages_combined": [{"language": "english", "language_level": ["good command"]}, {"language": "chinese", "language_level": ["good command"]}]}, "experience_required": {"duration": ["3 years"], "field": ["infrastructure", "it"]}}, {"job_id": "100003009050233", "location_code": "hk", "company": "CLP Power Hong Kong Limited", "job_title": "System Administrator (2-Year Contract) [Ref: CLPP-PSBG-TSD-MB-SA]", "description": "Applications are invited for the above vacancy in Metering Branch of Technical Services Department. Reporting to the engineer, the appointee will be required to:\n\n\nManage work schedules to ensure timeliness of meter data collection for all CLP customers\nPerform daily operations on various meter reading management systems, e.g., Customer Care & Marketing System (CCMS), Meter Data Management System (MDMS), Strategic Metering Platform (SMP), Meter Reading Handheld System (MRHS), etc.\nHandle and resolve exceptions triggered from metering systems\nMaintain metering operation performance to ensure compliance with established service standards\nAnalyze data and initiate projects to improve operation efficiency\nDesign and conduct user acceptance tests for system upgrade\nDevelop and produce procedures, guidelines and training materials to support operations\nPerform any other duties assigned by supervisor as and when required.\n\nRequirements:\n\nHigher Certificate / Higher Diploma in Electronic / Electrical Engineering / Computer Science or Professional Diploma in Power Engineering or equivalent plus minimum 2 years\u2019 relevant experience\nKnowledge in data analytic and cyber security management is preferable\nKnowledge and experience in metering operations and SAP is an advantage\nGood verbal and written communication skills\nBe mindful and has good safety awareness\nGood team player and be flexible to work on ad-hoc tasks\nCandidates who do not fully meet the requirements but have demonstrated positive attitude and good potential for further development will be considered for junior position.\n\nPlease apply by clicking the button \u201cApply Now\u201d below for application on or before 25 January 2022.\n\nApplicants not invited for interview within 6 weeks from the closing date may assume their applications unsuccessful.\n\nInformation provided will be for recruitment purpose within the CLP Group and only short-listed candidates will be contacted. We comply with all applicable laws and regulations of HKSAR in handling applications. For details of the Personal Information Collection Statement, please visit our website: http://clp.to/engPICS\n\nFor further information on our company, please visit our website: https://www.clpgroup.com/", "employment_types": ["Full Time", "Contract"], "selling_points": [], "locations": ["Not Specified"], "categories": ["Engineering", "Electrical / Electronics", "Information Technology (IT)", "Support"], "post_time": "2022-01-17T16:20:56Z", "salary": {"currency": null, "max": null, "min": null, "period": "monthly", "term": null}, "salary_visible": false, "title_keywords": ["system administrator"], "responsibilities": ["regulations", "any other duties", "data", "schedules", "operations", "cyber security", "website", "design", "communication", "service standards", "maintain", "develop", "analyze data", "reporting", "management", "procedures", "daily operations", "data collection", "guidelines", "ad-hoc tasks", "systems", "ensure compliance", "recruitment"], "requirements": {"degrees": ["diploma", "higher certificate"], "majors": ["engineering", "electrical engineering", "computer science"], "languages": [], "language_level": [], "hard_skills": ["plus", "data management", "sap", "cyber security"], "soft_skills": ["flexible", "communication skills", "good team player", "mindful", "positive attitude"], "languages_combined": []}, "experience_required": {"duration": ["minimum 2 years"], "field": ["relevant experience", "engineering"]}}, {"job_id": "100003009046424", "location_code": "hk", "company": "Reckitt Benckiser Hong Kong Limited", "job_title": "Junior IT Analyst", "description": "Role & Responsibilities:\n\nDrive the IT & digital team\u2019s vision: To design simple processes (WoW employee experience) & make analytics integral to business decision making in Hong Kong & Taiwan\nBe the first line of contact to support assigned application systems with agreed SLA, which includes but not limited to system job monitoring, data uploading, data update, system template generation, system or data or operation problem resolution, etc.\nProvide first line application production support to ensure good service is in place to support business result. Manage and continuously enhance the service level of vendor support; work with the business owner to enhance the business key user network\nClosely work with business analyst, business owner and users to identify the improvement opportunities, analyse and assess the business requirement, develop and align the system solution, and deliver it to realize the business value preposition\nImplement & conduct regular business user activity monitoring for the given applications, to make sure that active access is legitimate, with appropriate rights and in line with the application access right process validated by the Business\nProactively learn the industry leading solutions & IT trend in the respective business areas and develop the solution roadmap in the following 1-3 years\nUnderstand, support and execute the global IT strategy where applied. Ensure all IT infrastructure and systems in HK/TW are in line with RB information security standard\nProactively develops project management skills to manage timely delivery of business requests and small- medium scale projects\nSupport the Workplace Service team for Infrastructure/PC related deliverables\nQualification & Skills:\n\nBachelor's degree in IT or other related business major.\n1-2 years\u2019 experience of working as application support analyst or similar roles.\nProven success & experience in supporting IT application system in a fast-paced business environment to support business growth, improve productivity or solve a business problem\nIn-depth knowledge in more than one key business areas such as ERP, CRM/CDP, SFA/MFA, TPM/TPO, TM1, NewsPage knowledge is a plus\nFMCG experience is a preferred.\nStrong vendor management experience to achieve win-win partnership.\nStrong service management skills. ITIL certificate is a plus.\nAbility to communicate in both technical and business language, both written & verbal.\nFluency in spoken and written Cantonese, Mandarin and English.\nAbility to multitask and prioritize.\nQuickly learn and understand process knowledge.\nBe capable to answer how to question and continue to improve users\u2019 adoption / optimal support.\nBe agile to learn new technical from other markets or global team to adopt and enhance support service.\nEnthusiastic about learning new areas of technology & problem-solving using technology\nEnthusiastic about working in Entrepreneurial settings: can work in small teams, and can collaborate with business leaders\n\n", "employment_types": ["Full Time"], "selling_points": ["Bachelor's degree in IT", "Experience in supporting IT application system", "Fluency in spoken and written Cantonese, English"], "locations": ["Causeway Bay"], "categories": ["Information Technology (IT)", "Support"], "post_time": "2022-01-13T11:01:42Z", "salary": {"currency": null, "max": null, "min": null, "period": "monthly", "term": null}, "salary_visible": false, "title_keywords": ["it analyst", "junior"], "responsibilities": ["collaborate with", "management", "it infrastructure", "information security", "data", "monitoring", "systems", "infrastructure", "design", "develop", "resolution", "project management", "application system", "teams", "contact", "application systems", "analyse"], "requirements": {"degrees": ["certificate", "degree", "bachelor"], "majors": ["business", "it"], "languages": ["cantonese", "english", "mandarin"], "language_level": ["fluency"], "hard_skills": ["simple", "itil", "plus", "small", "agile", "problem-solving", "vendor", "application system", "erp", "make", "sla", "project management", "pc"], "soft_skills": ["capable", "agile", "project management skills", "timely", "problem-solving", "prioritize", "learning", "enthusiastic", "business environment", "ability to multitask", "active", "decision making"], "languages_combined": [{"language": "cantonese", "language_level": ["fluency"]}, {"language": "english", "language_level": ["fluency"]}, {"language": "mandarin", "language_level": ["fluency"]}]}, "experience_required": {"duration": ["1-2 years"], "field": ["management", "fmcg", "design", "business", "it", "digital", "team"]}}, {"job_id": "100003009055320", "location_code": "hk", "company": "CL Technical Services Ltd.", "job_title": "System Engineer (In-house, Windows)", "description": "Job Duties:\n\nAssist in the preparation of system design and technical specification\nLiaise with users and vendors for requirement study, implementation and testing\nPrepare test plan and conduct acceptance test\nAssist in the update of technical documents and the preparation of operation manual\n\nRequirement Details:\n\nHigh Diploma in Computer Science or equivalent\nAt least 2 years working experience in IT technical support\nAt least 1 year working experience in Windows 08/12 and Linux System administration\nGood knowledge in VM and Oracle database administration is preferable\nKnowledge in SAN and Veritas Backup Exec administration is preferable\nProficient in both spoken and written English and Cantonese\nHK Permanent Resident is required\n\nFor more job opportunity, please visit our website: www.clts.com\n\nThe personal information collected is strictly for recruitment purpose only.", "employment_types": ["Full Time"], "selling_points": ["Listed company", "5 days work", "Stable working environment"], "locations": ["Central & Western Area"], "categories": ["Information Technology (IT)", "Support", "Network & System"], "post_time": "2022-01-18T02:10:45Z", "salary": {"currency": null, "max": null, "min": null, "period": "monthly", "term": null}, "salary_visible": false, "title_keywords": ["system engineer"], "responsibilities": ["implementation", "testing", "system design", "plan", "liaise with"], "requirements": {"degrees": ["high diploma"], "majors": ["computer science"], "languages": ["cantonese", "english"], "language_level": ["proficient"], "hard_skills": ["exec", "linux", "oracle"], "soft_skills": [], "languages_combined": [{"language": "cantonese", "language_level": ["proficient"]}, {"language": "english", "language_level": ["proficient"]}]}, "experience_required": {"duration": ["at least 2 years", "at least 1 year"], "field": ["it technical support", "administration"]}}, {"job_id": "100003009051089", "location_code": "hk", "company": "ORIX Asia Limited", "job_title": "IT Administrative Assistant, Technology & Information", "description": "Job\n\nProvide administrative support for the IT Dept; provide info & assistance to office\nAssist in the IT documentation for hardware & software, and other IT related services\nProvide the daily support of IT systems to end users\nProvide general administrative support, such as purchasing, filing and staff record\nAssist in the procurement of office equipment and inventory keeping\nAssist in handling of maintenance and service contracts\nEstablish partnership with stakeholders for their understanding & evolving business needs\nParticipate in Project Implementation and various stages across System Development Life-Cycle alignment\n\nRequirements\n\nHKCEE /DSE or above\nMin. 1 to 3 years administrative experience in Banking, Finance or related\u00a0\u00a0\nProven experience as administrative / virtual / office assistant\nKnowledge of office management systems and procedures\nWorking knowledge of office equipment eg. printer, fax machine, etc\nProficiency in MS Office (MS Excel, PowerPoint, etc)\nGood time management skills and ability to prioritize work\nGood analytical problem solving, communication and presentation skills\nGood command of English and Chinese (Putonghua is a plus)\n\n\n\nWe offer attractive remuneration and benefits, comprehensive career development opportunities and 5-day week to the qualified candidate.\n\nInterested parties please send detailed resume including current salary and expected salary to:\u00a0HR Dept, 25/F, Two Exchange Square, 8 Connaught Place, Central, HK\n\nAll personal information provided by applicants will be treated in strict confidence and used solely for recruitment purpose. All information of unsuccessful candidates will be destroyed within 12 months from the date of this advertisement.", "employment_types": ["Full Time", "Permanent"], "selling_points": [], "locations": ["Central"], "categories": ["Information Technology (IT)", "Support"], "post_time": "2022-01-15T02:06:10Z", "salary": {"currency": null, "max": null, "min": null, "period": "monthly", "term": null}, "salary_visible": false, "title_keywords": ["administrative assistant"], "responsibilities": ["management", "documentation", "service contracts", "software", "maintenance", "inventory", "systems", "general administrative support", "implementation", "procedures", "communication", "hardware", "banking", "provide administrative support"], "requirements": {"degrees": ["dse"], "majors": [], "languages": ["putonghua", "english", "chinese"], "language_level": ["good command"], "hard_skills": ["plus", "maintenance", "powerpoint", "problem solving", "hardware", "ms excel", "documentation", "ms office"], "soft_skills": ["time management skills", "prioritize", "problem solving", "communication", "presentation skills"], "languages_combined": [{"language": "putonghua", "language_level": ["good command"]}, {"language": "english", "language_level": ["good command"]}, {"language": "chinese", "language_level": ["good command"]}]}, "experience_required": {"duration": ["1 to 3 years"], "field": ["related", "finance", "administrative", "banking"]}}, {"job_id": "100003009051329", "location_code": "hk", "company": "Maxim's Caterers Ltd", "job_title": "Officer - Store Deskside Service", "description": "Responsibilities\nCoordinate with internal IT functional teams and external vendor for technical support and trouble-shooting including incident and problem escalation\nBe responsible for system installation and rollout\nProvide support on configuration of both software and hardware equipment (POS, laptop, printer, mobile devices, etc.)\nPrepare technical design, documentation and user manual\nLiaise with vendor/supplier to setup IT infrastructure\nRecord and manage all incidents and requests in Ticket-Tracking System\nAssist in other ad hoc projects as assigned\nRequirements\nHigher Diploma or above in Computer Studies, Information Technology or related discipline\nAt least 5 years relevant working experience in services technical support role\nExperience in F&B and retail industry is a plus\nProficient in Windows client OS platforms and Microsoft Office software\nHolder of MCSE / MCITP / ITIL are desirable\nGood communication and problem solving skill\nGood command of written and spoken English and Chinese\nInterested parties please apply with full resume, state current and expected salaries by clicking \"Apply Now\". All applications and data collected will be treated in strict confidence and used exclusively for recruitment purposes.\u00a0 Only short listed candidates will be invited for interview. The company will retain the applications for a maximum period of 24 months and may refer suitable candidates to other vacancies within the Group.", "employment_types": ["Full Time", "Permanent"], "selling_points": ["Technical support and trouble-shooting", "System installation and rollout", "Prepare technical design, doc. and user manual"], "locations": ["Lai Chi Kok"], "categories": ["Information Technology (IT)", "Hardware", "Support"], "post_time": "2022-01-15T09:27:52Z", "salary": {"currency": null, "max": null, "min": null, "period": null, "term": null}, "salary_visible": false, "title_keywords": ["officer"], "responsibilities": ["installation", "provide support", "software", "it infrastructure", "technical support", "configuration", "teams", "coordinate with", "design", "hardware", "liaise with", "ad hoc projects", "mobile devices", "documentation", "setup", "tracking"], "requirements": {"degrees": ["higher diploma or above"], "majors": ["information technology", "computer studies"], "languages": ["english", "chinese"], "language_level": ["good command"], "hard_skills": ["itil", "mcse", "plus", "problem solving", "os", "microsoft office software"], "soft_skills": ["communication", "problem solving skill"], "languages_combined": [{"language": "english", "language_level": ["good command"]}, {"language": "chinese", "language_level": ["good command"]}]}, "experience_required": {"duration": ["at least 5 years"], "field": ["retail industry", "f&b", "relevant working experience"]}}, {"job_id": "100003009042739", "location_code": "hk", "company": "Promise (Hong Kong) Co., Limited", "job_title": "IT Officer/Senior Officer (Software Quality Assurance)", "description": "Job Duties:\n\nPerform unit test, integration test and system test on various systems, including Internal Loan System, Web Applications and Mobile Apps, etc.\nAnalyze test results and report to the development team\nWork with the development team to correct bugs and errors\nAssist in UAT\nProvide end-user support\nParticipate in IT Projects implementation as assigned\n\nRequirements:\n\nHigher Diploma holder in Information Technology, Computer Science or related disciplines\n2 years' working experience in software quality assurance or program development life cycle area\nKnowledge in SQL and programming\nAn excellent team player with good communication skill\nGood command of written and spoken English and Chinese\nFresh graduates would also be considered\n\n\nCompetitive remuneration package and fringe benefits will be offered to successful candidates. Please send your resume with present and expected salary to\u00a0The Human Resources\u00a0Department, Promise (Hong Kong) Co., Limited, 14/F., Luk Kwok Centre, No. 72 Gloucester Road, Wanchai, Hong Kong or click \"Apply Now\" to submit your application.\n\nPromise (Hong Kong) Co., Limited is an equal opportunity employer, all the qualified candidates are welcome\u00a0to apply for the position.\n\nAll the data collected will be treated as strictly confidential and will\u00a0be used on employment related purpose only.", "employment_types": ["Full Time", "Permanent"], "selling_points": ["Perform unit test and integration test", "Assist in UAT", "Provide end-user support"], "locations": ["Wan Chai"], "categories": ["Information Technology (IT)", "Support", "Testing / QA", "Others"], "post_time": "2022-01-15T03:49:15Z", "salary": {"currency": null, "max": null, "min": null, "period": "monthly", "term": null}, "salary_visible": false, "title_keywords": ["senior officer", "it officer"], "responsibilities": ["systems", "uat", "implementation", "report"], "requirements": {"degrees": ["higher diploma holder"], "majors": ["related disciplines", "computer science", "information technology"], "languages": ["english", "chinese"], "language_level": ["good command"], "hard_skills": ["sql", "programming"], "soft_skills": ["team player", "communication skill"], "languages_combined": [{"language": "english", "language_level": ["good command"]}, {"language": "chinese", "language_level": ["good command"]}]}, "experience_required": {"duration": ["2 years"], "field": ["development", "quality assurance"]}}, {"job_id": "100003009046573", "location_code": "hk", "company": "", "job_title": "IT Support", "description": "Job description\nWindows/Linux system maintenance/administration.\nIT assistance to staff and team members.\nResolve errors in a timely manner.\nMonitor hardware, CCTV, software, and system performance metrics.\nUpdate computer software. as well as upgrading hardware and systems.\nMaintain databases and ensuring system security.\nProgramming knowledge\nIT Support Requirements:\n\nDegree in computer science, information technology is preferable\n3-5 years of experience as an IT role\nAbility to provide technical support and resolve queries.\nIn-depth knowledge of computer hardware, software, and networks.\nExperience in documenting processes and monitoring performance metrics.\nInterested candidates, please contact us at 64688556 for company details before applying.", "employment_types": ["Full Time", "Part Time", "Permanent"], "selling_points": ["Linux", "Network infrastucture", "Azure"], "locations": ["Aberdeen"], "categories": ["Information Technology (IT)", "Hardware", "Support", "Network & System"], "post_time": "2022-01-13T14:49:52Z", "salary": {"currency": null, "max": null, "min": null, "period": "monthly", "term": null}, "salary_visible": false, "title_keywords": ["it support"], "responsibilities": ["software", "maintenance", "systems", "monitor", "a timely manner", "performance metrics", "hardware", "maintain", "system security", "databases", "administration"], "requirements": {"degrees": ["degree"], "majors": ["computer science", "information technology"], "languages": [], "language_level": [], "hard_skills": ["hardware"], "soft_skills": [], "languages_combined": []}, "experience_required": {"duration": ["3-5 years"], "field": ["it"]}}, {"job_id": "100003009049062", "location_code": "hk", "company": "Protiviti Hong Kong", "job_title": "Deskside Support Analyst - Insurance - 26k - Contract", "description": "Protiviti are looking for skilled candidates for the following role:\n\nThe Company\n\nProtiviti is a global consulting firm that delivers deep expertise, objective insights, a tailored approach and unparalleled collaboration to help leaders confidently face the future. As a Protiviti consultant, you will not only work on interesting business issues with world-class companies, but you will also have access to training and networking opportunities to accelerate your expertise. Our client is an instantly recognizable firm with a very strong reputation and brand within finance sector globally.\n\nThe Role\n\nProvide 1st level service desk and desktop support to all internal users\nPreform troubleshooting PC hardware and software issues\nSupport conference calls set up\nFollow the escalation process to ensure professional IT support service.\n\nYour Profile\n\nAt least two years of relevant experience on IT support\nGood hardware, video conferencing and networking knowledge.\nExperience in projects such as Windows upgrade and office relocation\nUniversity graduate in Computer Science or related disciplines\nGood spoken and written English and Chinese.\n\nApply Today\n\nTo apply online (Word attachment only), please click the 'Apply' button. Please note that only short-listed candidates will be contacted.\n\nAbout Protiviti\n\nProtiviti is a global consulting firm that delivers deep expertise, objective insights, a tailored approach and unparalleled collaboration to help leaders confidently face the future. Through our network of more than 70 offices in over 20 countries, Protiviti and its independently owned Member Firms provide clients with consulting solutions in finance, technology, operations, data, analytics, business performance improvement, risk and internal audit.\n\nAs a Protiviti consultant, you will not only work on interesting business issues with world-class companies, but you will also have access to training and networking opportunities to accelerate your expertise.", "employment_types": ["Full Time", "Contract"], "selling_points": ["Deskside support", "Insurance exposure", "Stable working hours"], "locations": ["Central & Western Area"], "categories": ["Information Technology (IT)", "Hardware", "Support", "Network & System"], "post_time": "2022-01-14T08:01:03Z", "salary": {"currency": "HKD", "max": 24999, "min": 20000, "period": "monthly", "term": null}, "salary_visible": true, "title_keywords": ["analyst"], "responsibilities": ["consulting", "data", "internal audit", "operations", "troubleshooting", "hardware", "hardware and software issues"], "requirements": {"degrees": ["university graduate"], "majors": ["related disciplines", "computer science"], "languages": ["english", "chinese"], "language_level": ["good"], "hard_skills": ["pc", "hardware", "word"], "soft_skills": ["independently", "deep", "troubleshooting", "world-class"], "languages_combined": [{"language": "english", "language_level": ["good"]}, {"language": "chinese", "language_level": ["good"]}]}, "experience_required": {"duration": ["at least two years"], "field": ["relevant experience", "it support"]}}, {"job_id": "100003009050631", "location_code": "hk", "company": "The Independent Schools Foundation Academy Ltd", "job_title": "IT Helpdesk Administrator (Ref: ITO/HA/20211129_ jdb)", "description": "Job Responsibilities:\nServe as the first-line support to staff members, students and parents of the Academy;\nProvide support to software, network, e-mail, office applications and educational software issues;\nResponsible for the opening, assignment, monitoring and closing of IT service tickets via the ticketing system;\nPerform administrative duties such as maintaining hardware and software inventory, setting up of event schedule calendar and keeping track of loaned equipment and laptops etc.; and\nAssist IT related daily activities.\nRequirements:\nRelevant education background in either Information System, Information Technology or Computer Science disciplines;\nGood understanding on the use of computer systems, mobile devices and other technical products;\nExcellent telephone manner and communication skills;\nGood command of both spoken and written English and Cantonese (including Mandarin);\nAbility to diagnose and resolve basic technical issues;\nAbility to work independently; and\nBe a good team player.\nThe ISF Foundation, Academy & Pre-School are committed to ensuring safety and well-being of our students. We hold high standards of recruitment practices with specific attention to child protection. All applicants must be willing to undergo relevant background checks and screenings.\nFree Shuttle Bus travelling to and from The ISF Academy will be provided:\nRoute: North Point > Admiralty Centre > Causeway Bay > Aberdeen > The ISF Academy\nApplication Deadline: 28 January 2022\n\nRemuneration will commensurate with qualifications and experience. We will offer an attractive benefits package including medical, life insurance, and opportunities for professional development and continuing education to the right candidate. Please submit your application by completing the Application Form, Reference Check Statement which could be downloaded from our website: www.isf.edu.hk together with full Curriculum Vitae and Covering Letter.Please quote with our \u201cRef: no.\u201d by email via \"Apply Now\"\n\n\nPersonal data is collected for employment purposes only.", "employment_types": ["Full Time", "Permanent"], "selling_points": ["Support to staff members, students and parents", "Perform administrative duties", "Relevant educ. background in either Information"], "locations": ["Pok Fu Lam"], "categories": ["Information Technology (IT)", "Support", "Software Development", "Network & System"], "post_time": "2022-01-14T11:01:24Z", "salary": {"currency": null, "max": null, "min": null, "period": "monthly", "term": null}, "salary_visible": false, "title_keywords": ["administrator"], "responsibilities": ["provide support", "software issues", "it service", "software", "maintaining", "inventory", "monitoring", "hardware", "administrative duties", "schedule"], "requirements": {"degrees": [], "majors": [], "languages": ["cantonese", "english", "mandarin"], "language_level": ["good command"], "hard_skills": ["no", "basic", "computer systems", "information system", "mobile"], "soft_skills": ["communication skills", "work independently", "good team player", "committed", "telephone manner"], "languages_combined": [{"language": "cantonese", "language_level": ["good command"]}, {"language": "english", "language_level": ["good command"]}, {"language": "mandarin", "language_level": ["good command"]}]}, "experience_required": {"duration": [], "field": []}}, {"job_id": "100003009052112", "location_code": "hk", "company": "Taylor Coulter", "job_title": "Government project------- Data center operator (5 days work)", "description": "We are seeking a data center operator in our government\u00a0Project.\n\nJob Description:\n\n-To assist in the operation and maintenance of the data centre systems by following the guidelines and instruction established in various policy and procedures.\n-To update system logs and report system fault if necessary;\n-To monitor the availability of data centre systems including network appliances, server equipment and environmental control systems;\n-To maintain the physical security of data centre;\n- To ensure the operation of data centre complying with established procedures;\n- To assist various departments in deploying systems in the data centre; and\n-To undertake any other duties as assigned by supervisors.\n\n\nJob Requirements:\n\n-Higher Diploma or above in Computer Studies or equivalent\n-at least 2 years of hands-on experience\n-Good communication in Cantonese and English\n-Candidates with less experience will also be considered for junior position", "employment_types": ["Full Time", "Permanent", "Contract"], "selling_points": ["deliver daily operations for systems in Data Cente", "Carry out data center monitoring", "Perform physical hardware health check annually"], "locations": ["North Point"], "categories": ["Information Technology (IT)", "Hardware", "Support", "Network & System"], "post_time": "2022-01-17T02:07:34Z", "salary": {"currency": "HKD", "max": 19999, "min": 17000, "period": "monthly", "term": null}, "salary_visible": true, "title_keywords": ["operator"], "responsibilities": ["any other duties", "control", "maintenance", "data", "guidelines", "systems", "procedures", "monitor", "maintain", "report"], "requirements": {"degrees": ["diploma or above"], "majors": ["computer studies"], "languages": ["cantonese", "english"], "language_level": [], "hard_skills": [], "soft_skills": ["communication", "hands-on"], "languages_combined": [{"language": "cantonese", "language_level": []}, {"language": "english", "language_level": []}]}, "experience_required": {"duration": ["least 2 years"], "field": []}}, {"job_id": "100003009052031", "location_code": "hk", "company": "Entrust Asia Pacific Limited", "job_title": "Senior Systems Engineer", "description": "Responsibilities:\n\nLead & develop day-to-day support & operation activities for Infrastructure services within backup, server, directory services, and storage platforms as well on-site desktop support:\n\nProvide proximity support to APAC users and revolve any deskside / applications / access requests or trouble shooting generated from business teams & user\nProvide life cycle management & support of enduser devices\nProvide support of onsite office equipment (Visual displays, projectors, printers)\nHands & eyes on support for onsite Network equipment (Switches, Firewalls\nPlatform ownership of Veeam backup environments\nSupport & management of server hardware on Intel x86_64 platforms\nPerform standard server Operating System administration duties\nPerform Threat & vulnerability remediation\u2019s\nDay-to-day support & operation activities for VMware Environment\nManage and support Active Directory, DHCP servers and scopes & internal DNS\nResponsible for remote server management\nCollaborate with Infrastructure DevOps subject matter expert to implement and manage Infrastructure\nExecute on strategic projects as assigned from end-to-end \u00a0\nBreak-Fix incident resolution, root cause analysis and problem management.\nParticipate in the service on-call rotation providing 24/7 incident response in accordance with published Service Level Agreements\nRespond to and fulfill customer Service Request tickets\nCreate and update operational and procedural documentation\nEstablish standards and repeatable processes for managing change across environments, and bringing in new and innovative technologies, where applicable\nIdentifies and tracks risks and opportunities of his/her domain of activities.\nEnsures the right implementation of all IT solutions and systems compliance to group IT and IT Security standards & policies\nActing as core team of global IT resource and support global infrastructure projects\nRequirements:\n\n5+ years of experience in IT infrastructure support & operations\nBachelor\u2019s Degree in Computer Science, Information Systems, or equivalent technical degree and/or work experience\nExperience with Veeam backup, and VMware Site Recovery Manager (SRM) Disaster Recovery SW \u00a0\nDeep experience in System Administration including extensive knowledge in server operating systems: Microsoft Server 2012R2/2016/2019\nPlatform management and administration experience\nGood understanding of IT systems development process\nExcellence communication skills and customer service mindset\nSome travel may be required", "employment_types": ["Full Time", "Permanent"], "selling_points": ["Worlds' leading Digital Security Company", "Career opportunities", "Working with best talent in the industry"], "locations": ["Kwun Tong"], "categories": ["Information Technology (IT)", "Support", "Network & System"], "post_time": "2022-01-17T01:53:05Z", "salary": {"currency": null, "max": null, "min": null, "period": "monthly", "term": null}, "salary_visible": false, "title_keywords": ["systems engineer"], "responsibilities": ["collaborate with", "active directory", "customer service", "administration", "server hardware", "infrastructure", "teams", "implementation", "compliance", "develop", "resolution", "visual", "management", "provide support", "documentation", "dns", "policies", "analysis", "systems", "subject matter expert"], "requirements": {"degrees": ["degree", "bachelor"], "majors": ["computer science"], "languages": [], "language_level": [], "hard_skills": ["server", "infrastructure support", "vmware"], "soft_skills": ["communication skills", "customer service", "deep", "extensive"], "languages_combined": []}, "experience_required": {"duration": ["5+ years"], "field": ["management", "infrastructure", "disaster recovery", "it", "administration"]}}, {"job_id": "100003009051073", "location_code": "hk", "company": "Lenovo Group Limited", "job_title": "Technical Account Manager", "description": "Day-To-Day Responsibilities:\n\nRelationship:\n\nAble to maximize the value of the customer\u2019s investment in Lenovo products and services throughout the end to end customer lifecycle. The TAM manages customer escalations and acts as the customer\u2019s advocate.\nEffective ownership, communication, coordination, and facilitation of support service activities between the Customer and support teams, account teams, field service personnel, and customers.\n\nEscalation management:\n\nActs as a single point of contact for customer escalations and owns the coordination and oversight to problem solving efforts between customers, Support engineers, field service personnel, software support, investigation and analysis of product problems.\nDevelops and delivers post incident reports on all critical support incidents, adheres to customer support plans and relationships.\nUses complex analytical skills to recognize trends and improve performance.\n\nPrevention:\n\nRequires a general understanding of and technical competence in PC technologies.\nDevelops and coordinates proactive maintenance initiatives based on industry best practices and statistical data trends.\n\nOptimization:\n\nIdentifies and leads continuous improvement activities in support of customer or internal business processes.\n\nSupport:\n\nLeads complex service delivery processes, develops creative resolutions to complex problems and ensures contractual support service deliverables are understood and managed effectively.\n\nCollaboration:\n\nCompiles, analyzes and interprets statistical data and trends relating to service level and operational effectiveness.\n\nIn this role, you will be reporting to a Premier TAM Manager.\n\nKey Competencies Needed:\n\nSuperior knowledge of PC technology, market trends, vendor competition. Strong understanding of sales strategies and management principles.\nAbility to effectively interact and communicate with different levels of people.\nExcellent presentation, communications and interpersonal skills.\nProficient in Microsoft Office programs and PC technologies.\nExcellent organization skills, must be a self-starter who has experience in managing multiple initiatives simultaneously in a demanding and changing environment.\nAbility to build effective virtual teams and drive results through others in a complex cross-functional organization required.", "employment_types": ["Full Time"], "selling_points": ["An exciting client facing role", "Robust, fast-growing organization", "Take ownership of working with your stakeholders"], "locations": ["Quarry Bay"], "categories": ["Information Technology (IT)", "IT Project Management / Team Lead", "Support", "IT Management"], "post_time": "2022-01-15T01:50:26Z", "salary": {"currency": null, "max": null, "min": null, "period": "monthly", "term": null}, "salary_visible": false, "title_keywords": ["account manager"], "responsibilities": ["service delivery", "reporting", "management", "communicate with", "software", "maintenance", "data", "analysis", "teams", "investigation", "communication", "reports", "contact", "coordination", "plans"], "requirements": {"degrees": [], "majors": [], "languages": [], "language_level": [], "hard_skills": ["maintenance", "microsoft office", "analysis", "vendor", "analytical skills", "problem solving", "pc"], "soft_skills": ["creative", "analytical skills", "communication", "problem solving", "interpersonal skills", "coordination", "organization skills", "proactive", "presentation", "superior"], "languages_combined": []}, "experience_required": {"duration": [], "field": []}}, {"job_id": "100003009055625", "location_code": "hk", "company": "Gravitas Recruitment Group", "job_title": "LEADING IBANK - Service desk anaylst", "description": "Opportunity to join a leading Bank!\n\nThe Service Desk Analyst provides support for basic incident resolution and requests reported to the regional service desk.\n\n\nResponsibilities:\n\n\nAct as a single point of contact and support internal staff via phone calls, emails, live chat and self-service tickets from internal staff regarding IT related issues and queries.\n1st line support: troubleshooting of IT related problems\nEscalate unresolved issues / requests to the corresponding helpdesk (L2/L3 support)\nTake ownership of users' problems, follow up the status of problems on behalf of the user and communicate the status to users in a timely manner\nUpdate all taken actions and information into ticketing system in a timely manner\nTo maintain a high degree of customer service for all support queries\nMaintain knowledge database to ensure all information is up-to-date\nDefine / Improve processes and workflows\nCapable to manage projects or tasks given by the manager\n\nProfile Required\n\nRequirements:\n\n\nFluent in English\nExcellent communication skills and telephone manner.\nEffective listening and attentiveness skills\nExcellent organizational skills\nWillingness to improve and to learn\nCustomer service orientation and/or prior customer service training\nTeam player\nBanking experience will be advantageous, but it is not mandatory", "employment_types": ["Full Time", "Permanent"], "selling_points": ["International environment", "Good work-life balance environment", "Great career development"], "locations": ["Not Specified"], "categories": ["Information Technology (IT)", "Hardware", "Support", "Others"], "post_time": "2022-01-18T02:48:37Z", "salary": {"currency": "HKD", "max": 34999, "min": 20000, "period": "monthly", "term": null}, "salary_visible": true, "title_keywords": [], "responsibilities": ["a timely manner", "troubleshooting", "maintain", "customer service", "contact", "database", "manage projects", "phone calls"], "requirements": {"degrees": [], "majors": [], "languages": ["english"], "language_level": ["fluent"], "hard_skills": [], "soft_skills": ["communication skills", "organizational skills", "customer service", "team player", "telephone manner"], "languages_combined": [{"language": "english", "language_level": ["fluent"]}]}, "experience_required": {"duration": [], "field": ["it", "banking experience"]}}, {"job_id": "100003009050833", "location_code": "hk", "company": "Bank of Communications Trustee Limited", "job_title": "System Support Engineer", "description": "Responsibilities\nPerform system support and maintain application servers\nAssist in project management, software installation and ad-hoc technical problems solving\nImplement Windows patches and upgrade server operating system\nPerform other administrative and emergency support\nPerform ad-hoc assignments as required\nRequirements\nDegree in computer science, information technology or equivalent\nAt least 3 years working experience in system server support and management experience\nExperience in Windows / Linux server / network / firewall configuration and software installation\nSolid experience on Windows/ Linux scripting, Citrix, Microsoft Exchange, VMWare and Veem backup solution\nIndependent, patient with good problem diagnosis and solving skills\nProficient in both spoken and written English and Chinese, Putonghua a plus\nCandidate with more experience will be considered with senior position\nImmediately available is highly preferred\nPlease click \"Apply Now\" to submit your application.\nPersonal data collected will be used for recruitment purpose only.", "employment_types": ["Full Time", "Permanent"], "selling_points": ["Perform system support", "Maintain application servers", "At least 3 years working experience"], "locations": ["Not Specified"], "categories": ["Information Technology (IT)", "Support", "Application Specialist - Network", "Network & System"], "post_time": "2022-01-14T11:31:03Z", "salary": {"currency": null, "max": null, "min": null, "period": "monthly", "term": null}, "salary_visible": false, "title_keywords": ["system support", "engineer"], "responsibilities": ["ad-hoc", "installation", "problems solving", "software", "ad-hoc assignments", "project management", "maintain"], "requirements": {"degrees": ["degree"], "majors": ["computer science", "information technology"], "languages": ["putonghua", "english", "chinese"], "language_level": ["proficient"], "hard_skills": ["linux", "plus", "vmware", "citrix", "firewall", "server", "microsoft exchange"], "soft_skills": ["patient", "independent"], "languages_combined": [{"language": "putonghua", "language_level": ["proficient"]}, {"language": "english", "language_level": ["proficient"]}, {"language": "chinese", "language_level": ["proficient"]}]}, "experience_required": {"duration": ["at least 3 years"], "field": ["installation", "management"]}}, {"job_id": "100003009042025", "location_code": "hk", "company": "EC Healthcare", "job_title": "IT Application Support Specialist", "description": "Job Responsibilities:\u00a0\n\nProvide 1st-level application support to system users over WhatsApp, email and phone;\nDispatch support ticket to 2nd-level support when necessary;\nPerform application testing;\nDocument support workflow and create operation manuals;\nMonitor the performance and operation of production systems, response to system alert and incident; and\n\u00a0Work closely with development teams, business analysts to enhance existing systems.\n\nRequirements:\u00a0\n\nDiploma or above in any discipline;\nMajor in Information Technology or Computer related disciplines\u00a0is an advantage;\n1 year of experience in\u00a0helpdesk related work in supporting business applications;\nStrong business application workflow mindset;\nExperience in writing technical document or IT Policy is an advantage;\nGood command in Cantonese and English, Putonghua is an advantage;\nWilling to learn, self-initiative and work independently; and\nGood interpersonal skill, telephone manner and service attitude.", "employment_types": ["Full Time", "Permanent"], "selling_points": ["Helpdesk in supporting business applications", "Documentations of workflows/ manuals", "Work closely with application development team"], "locations": ["Mong Kok"], "categories": ["Information Technology (IT)", "Application Specialist - Software", "Support", "Network & System"], "post_time": "2022-01-12T05:23:51Z", "salary": {"currency": null, "max": null, "min": null, "period": "monthly", "term": null}, "salary_visible": false, "title_keywords": ["specialist", "application support"], "responsibilities": ["systems", "teams", "monitor the performance", "testing"], "requirements": {"degrees": ["diploma or above"], "majors": [], "languages": ["cantonese", "putonghua", "english"], "language_level": ["advantage", "good command"], "hard_skills": [], "soft_skills": ["work independently", "willing to learn", "interpersonal skill", "self-initiative", "telephone manner"], "languages_combined": [{"language": "cantonese", "language_level": ["good command"]}, {"language": "putonghua", "language_level": ["advantage", "good command"]}, {"language": "english", "language_level": ["good command"]}]}, "experience_required": {"duration": ["1 year"], "field": ["related", "business", "it", "writing"]}}, {"job_id": "100003009049252", "location_code": "hk", "company": "Pacific Textiles Ltd", "job_title": "Technical Support", "description": "Job Description\n\nWe are looking for a bright Technical Support to provide enterprise level technical support for our colleagues. This technician will provide support via phone, email, chat, in person, and other channels as required. This technician will also be responsible for installing and maintaining server and network hardware. A background in engineering or IT support is required.\n\nResponsibilities\n\n\u00a0\u00a0\u00a0\u00a0\u00a0\u00a0\u00a0\u00a0 Take ownership of customer issues reported and see problems through to resolution\n\u00a0\u00a0\u00a0\u00a0\u00a0\u00a0\u00a0\u00a0 Research, diagnose, troubleshoot and identify solutions to resolve issues\n\u00a0\u00a0\u00a0\u00a0\u00a0\u00a0\u00a0\u00a0 Follow standard procedures for proper escalation of unresolved issues to the appropriate internal teams\n\u00a0\u00a0\u00a0\u00a0\u00a0\u00a0\u00a0\u00a0 Ensure proper recording and closure of all issues; report status regularly\n\u00a0\u00a0\u00a0\u00a0\u00a0\u00a0\u00a0\u00a0 Document knowledge in the form of knowledge base tech notes and articles\n\u00a0\u00a0\u00a0\u00a0\u00a0\u00a0\u00a0\u00a0 Provision/decommission hardware in/out of data center facilities\n\u00a0\u00a0\u00a0\u00a0\u00a0\u00a0\u00a0\u00a0 Diagnose and resolve hardware issues\n\u00a0\u00a0\u00a0\u00a0\u00a0\u00a0\u00a0\u00a0 Assist in ad hoc projects when required\n\nRequirements\n\n\u00a0\u00a0\u00a0\u00a0\u00a0\u00a0\u00a0\u00a0 BS degree in Information Technology, Computer Science or equivalent\n\u00a0\u00a0\u00a0\u00a0\u00a0\u00a0\u00a0\u00a0 Fresh graduation is welcome\n\u00a0\u00a0\u00a0\u00a0\u00a0\u00a0\u00a0\u00a0 Experience in Networking and Microsoft AD is preferred\n\u00a0\u00a0\u00a0\u00a0\u00a0\u00a0\u00a0\u00a0 Basic knowledge of Windows, Linux, networking, utilities and scripting\n\u00a0\u00a0\u00a0\u00a0\u00a0\u00a0\u00a0\u00a0 Strong problem-solving skills\n\u00a0\u00a0\u00a0\u00a0\u00a0\u00a0\u00a0\u00a0 Able to work under pressure with self-motivation.\n\u00a0\u00a0\u00a0\u00a0\u00a0\u00a0\u00a0\u00a0 Excellent written and verbal communication skills in Chinese and English\n\u00a0\u00a0\u00a0\u00a0\u00a0\u00a0\u00a0\u00a0 Immediate available is highly preferred\n\nInterested parties please send your full resume with expected salary and availability by clicking \"Apply Now\".\u00a0\n\nPersonal date provided by job applicants will be used strictly for recruitment related purpose. Those applications do not receive any response from us in 4 weeks may be considered as unsuccessful and their personal data will be destroyed in one month after the vacancy is filled up.", "employment_types": ["Full Time", "Permanent"], "selling_points": [], "locations": ["Kwai Hing"], "categories": ["Information Technology (IT)", "Hardware", "Support", "Others", "Student / Fresh Graduate / No Experience"], "post_time": "2022-01-14T08:19:29Z", "salary": {"currency": null, "max": null, "min": null, "period": "monthly", "term": null}, "salary_visible": false, "title_keywords": ["technical support"], "responsibilities": ["provide support", "maintaining", "data", "technical support", "diagnose", "procedures", "teams", "resolution", "hardware", "installing", "ad hoc projects", "troubleshoot", "customer issues", "hardware issues", "report"], "requirements": {"degrees": ["degree"], "majors": ["computer science", "information technology"], "languages": ["english", "chinese"], "language_level": ["excellent"], "hard_skills": ["problem-solving skills", "linux", "basic"], "soft_skills": ["communication skills", "problem-solving skills", "self-motivation", "work under pressure"], "languages_combined": [{"language": "english", "language_level": ["excellent"]}, {"language": "chinese", "language_level": ["excellent"]}]}, "experience_required": {"duration": [], "field": []}}, {"job_id": "100003009050053", "location_code": "hk", "company": "Million Tech Development Ltd", "job_title": "Technical Support Engineer (5 Days Work)", "description": "Responsibilities:\n\nProvide support and maintenance of customer PC, POS, CCTV (NVR and IP Cams), IT infrastructure and etc\nProvide end-user support on hardware, software and networking related issues\nProvide IT system design, test and configuration\nHardware and software evaluation and procurement, liaise with vendors to resolve technical issues\nProvide professional technical advices to sales team and customers\nExplore new technologies and business opportunities\nAssist in other duties as assigned\n\nRequirements:\n\nHigher Diploma or above in Computer Science/ Information Technology or equivalent\nAt least 2 years working experience in IT Industry is preferred\nProficient in IT infrastructure, system admin, VM, Windows and Linux\nHolder of CCNA, MCP, MCSE is an advantage\nSelf-motivated and resourceful\nGood communication, interpersonal and organization skills\nGood command of spoken and written English and Chinese\nFresh graduate will be considered\nImmediate available is preferred\n\nWe offer 5 days work, 12 days annual leave, medical scheme, health incentive program, attractive remuneration package & bonus scheme.\u00a0 Interested parties please quote Employer Ref. No. and send detailed resume with\u00a0CURRENT & EXPECTED SALARIES\u00a0and\u00a0AVAILABLE DATE\u00a0by clicking the \"APPLY NOW\" button.\n\nFor company information, please visit our website :\u00a0www.milliontech.com\u00a0or take a look to our\u00a0Company Profile Video :\u00a0\u00a0\n\nhttps://youtu.be/lPsQnpP6saU\n\nAll information is collected for recruitment purpose only.", "employment_types": ["Full Time", "Permanent"], "selling_points": ["Higher Diploma or above in Computer Science/ IT", "2 years working experience in IT Industry", "Holder of CCNA, MCP, MCSE is an advantage"], "locations": ["Lai Chi Kok"], "categories": ["Information Technology (IT)", "Support", "Network & System", "Others"], "post_time": "2022-01-14T10:01:09Z", "salary": {"currency": null, "max": null, "min": null, "period": "monthly", "term": null}, "salary_visible": false, "title_keywords": ["technical support engineer"], "responsibilities": ["provide support", "it infrastructure", "maintenance", "software", "configuration", "other duties", "business opportunities", "hardware", "system design", "sales team", "evaluation", "liaise with"], "requirements": {"degrees": ["higher diploma or above", "fresh graduate"], "majors": ["computer science", "information technology"], "languages": ["english", "chinese"], "language_level": ["good command"], "hard_skills": ["linux", "ccna", "mcse"], "soft_skills": ["self-motivated", "resourceful", "communication", "organization skills", "interpersonal"], "languages_combined": [{"language": "english", "language_level": ["good command"]}, {"language": "chinese", "language_level": ["good command"]}]}, "experience_required": {"duration": ["at least 2 years"], "field": ["it"]}}, {"job_id": "100003009048436", "location_code": "hk", "company": "S.F. Express (Hong Kong) Limited", "job_title": "\u96fb\u8166\u652f\u63f4\u6280\u8853\u54e1 - IT Support (\u8f2a\u73ed)", "description": "\u5de5\u4f5c\u5167\u5bb9 :\n\n\u8ca0\u8cac\u96fb\u8166\u5b89\u88dd\u53ca\u652f\u63f4\u670d\u52d9\n\u63d0\u4f9b\u6280\u8853\u652f\u63f4\u53ca\u4e00\u822c\u7dad\u8b77\u5de5\u4f5c\n\u6bcf\u9031\u5de5\u4f5c3 - 4\u5929\uff0c\u6bcf\u661f\u671f\u5e73\u5747\u5de5\u4f5c40\u5c0f\u6642\n\u5de5\u4f5c\u6642\u9593:\n- \u65e9\u4e0a7\u6642\u81f3\u665a\u4e0a7\u6642\u00a0\n- \u665a\u4e0a7\u6642\u81f3\u65e9\u4e0a7\u6642 (\u4e00\u500b\u6708\u4e00\u9031)\n\u5de5\u4f5c\u8981\u6c42 :\n\n\u4e2d\u4e94 / DSE\u540c\u7b49\u6216\u4ee5\u4e0a\u5b78\u6b77\n1\u5e74\u6216\u4ee5\u4e0a\u76f8\u95dc\u5de5\u4f5c\u7d93\u9a57\n\u826f\u597d\u7cb5\u8a9e\uff0c\u4e00\u822c\u666e\u901a\u8a71\u53ca\u82f1\u8a9e\n\u6709\u8cac\u4efb\u611f\u53ca\u5177\u7368\u7acb\u5de5\u4f5c\u80fd\u529b\n\nWe offer attractive remuneration package and fringe benefits to the right candidates. Interested parties please submit your application to us. If you do not want to apply as JobsDB member, you may send your full resume with your availability, current and expected salaries to recruit01 at sf-express.com.\n\nYou are welcome to visit our website at\u00a0https://htm.sf-express.com/hk/tc/\u00a0for more information about us.\n\nCandidates who are not invited for interview within 1-month may consider their applications unsuccessful.\n\nAll personal data provided by job applicants will be used only for recruitment purposes and will be treated strictly confidential. Unsuccessful applications will be retained for a maximum period of 24-month.", "employment_types": ["Full Time", "Permanent"], "selling_points": ["\u591a\u5340\u514d\u8cbb\u516c\u53f8\u63a5\u99c1\u5df4\u58eb\u63a5\u9001", "\u63d0\u4f9b2\u500b\u6708\u6216\u4ee5\u4e0a\u8868\u73fe\u82b1\u7d05", "\u4e00\u500b\u6708\u4e00\u9031\u591c\u66f4\u5de5\u4f5c"], "locations": ["Tsing Yi"], "categories": ["Information Technology (IT)", "Hardware", "Support", "Network & System"], "post_time": "2022-01-14T06:35:01Z", "salary": {"currency": null, "max": null, "min": null, "period": "monthly", "term": null}, "salary_visible": false, "title_keywords": ["it support"], "responsibilities": [], "requirements": {"degrees": [], "majors": [], "languages": [], "language_level": [], "hard_skills": [], "soft_skills": [], "languages_combined": []}, "experience_required": {"duration": [], "field": []}}, {"job_id": "100003009050506", "location_code": "hk", "company": "CL Technical Services Ltd.", "job_title": "IT Support Engineer (Perm, up to $19K, Shatin)", "description": "Job Duties:\n\nProvides end-user support and problem-solving support on hardware, software & package installation and maintenance for servers & PCs\nPerforms IT audit & complete group IT checklists & surveys\nLiaisons with internal & external vendors on network, email, application system (SBO), IT contracts and other related issues\nSet up presentation and conference equipment\nStudies and supports on IT security control software\nMaintains company Intranet website\nConducts fixed asset stock take with A/C Dept.\nAd Hoc projects\n\nJob Requirements:\n\nHigher Diploma or above in information technology, computer technology, or a similar field.\nAt least two years' experience as an IT support or related role.\nExperience working with Microsoft Office 2016, 2019, or Office 365.\nStrong troubleshooting, analytical, and problem-solving skills.\nGood interpersonal skills and the ability to work with technical and non-technical personnel.", "employment_types": ["Full Time"], "selling_points": ["Discretionary bonus", "5 days work", "Shatin"], "locations": ["Shatin Area"], "categories": ["Information Technology (IT)", "Support", "Application Specialist - Network", "Network & System"], "post_time": "2022-01-14T10:34:29Z", "salary": {"currency": null, "max": null, "min": null, "period": "monthly", "term": null}, "salary_visible": false, "title_keywords": ["it support engineer"], "responsibilities": ["installation", "control", "software", "maintenance", "contracts", "pcs", "audit", "application system", "website", "stock take", "hardware", "ad hoc projects"], "requirements": {"degrees": ["higher diploma or above"], "majors": ["information technology"], "languages": [], "language_level": [], "hard_skills": ["problem-solving skills", "office 365", "microsoft office"], "soft_skills": ["problem-solving skills", "interpersonal skills", "troubleshooting"], "languages_combined": []}, "experience_required": {"duration": ["at least two years"], "field": ["related", "it support"]}}, {"job_id": "100003009048607", "location_code": "hk", "company": "CITIC Telecom International Holdings Limited", "job_title": "System Support Engineer (Business Support Systems)", "description": "Responsibilities:\n\nSystem deployment, maintenance and support for Telecom Business Support Systems (BSS)\nDevOps tools introduction, development and integration\nDefine systems\u2019 O&M requirements, optimize systems\u2019 architecture and deploy innovative O&M technique\n\nRequirements:\n\nBachelor degree or above in Computer Science or related disciplines\nMinimum 3 years\u2019 experience in IT system development, testing or maintenance\nFamiliar with the functions and architectures of business support IT systems: Billing, CRM and Order system etc.\nFamiliar with\u00a0popular IT maintenance techniques\u00a0e.g. Docker, K8s, Prometheus, ELK, Jenkins, etc.\u00a0\nGood coding/database skills\u00a0in at least two of below areas: Java, PL/SQL, Python, Oracle, MySQL, etc.\nExperience in Oracle/MySQL DBA would be an advantage\nExperience in\u00a0Big Data, K8s development and maintenance would be an advantage\nGood command in both spoken and written English and Chinese (Cantonese & Mandarin)\nGood team player with a strong sense of integrity\nWilling to learn and able to work independently with minimum supervision\u00a0 \u00a0\n\nFringe Benefits:\n\nOn-the-job training\nDouble pay\nAttractive performance bonus\nTransportation allowance\nMedical & dental insurance\nFree meals\nFree shuttle bus service\nTraining subsidies\nStaff discount\n\nWe offer competitive salary and benefit package including double pay, medical and dental benefits, 5-day work, 14 days paid annual leave and free shuttle bus service to the capable candidate. If you are interested, please immediately send your application stating\u00a0your current & expected salary and date availability with full resume\u00a0to\u00a0Human Resources Department\u00a0by email by clicking \"Apply Now\". Please clearly indicate the applied position and reference number on your application.\n\nAll personal data received will be treated strictly confidential and will be used for employment related purpose only.", "employment_types": ["Full Time", "Permanent"], "selling_points": ["Business Support Systems support and maintenance", "IT position in Telecom Industry", "Double Pay, Bonus, 5-day work, Medical & Dental"], "locations": ["Kwai Fong"], "categories": ["Information Technology (IT)", "DBA", "Support", "IT Management"], "post_time": "2022-01-14T06:54:06Z", "salary": {"currency": null, "max": null, "min": null, "period": "monthly", "term": null}, "salary_visible": false, "title_keywords": ["system support", "engineer"], "responsibilities": ["systems", "architecture", "maintenance", "deploy"], "requirements": {"degrees": ["degree or above", "bachelor"], "majors": ["related disciplines", "computer science"], "languages": ["cantonese", "english", "chinese", "mandarin"], "language_level": ["good command"], "hard_skills": ["java", "jenkins", "maintenance", "sql", "python", "pl", "oracle"], "soft_skills": ["good team player", "willing to learn", "integrity", "work independently"], "languages_combined": [{"language": "cantonese", "language_level": ["good command"]}, {"language": "english", "language_level": ["good command"]}, {"language": "chinese", "language_level": ["good command"]}, {"language": "mandarin", "language_level": ["good command"]}]}, "experience_required": {"duration": ["minimum 3 years"], "field": ["development", "it system development", "maintenance", "testing"]}}, {"job_id": "100003009051260", "location_code": "hk", "company": "OnTheList Limited", "job_title": "IT Business Analyst", "description": "OnTheList is a pioneering\u00a0concept of Members-Only Flash Sales, offering its members authentic and quality products with the promise of being the best deal in town.\u00a0\n\nCurrently the IT team is expanding and we are looking for dynamic Business Analyst to join! He/ she will participate in different development projects, help to prepare documents, data required and set up the current systems to support daily operations.\n\nJOB SCOPE\n\nEngage in various web development & data warehouse projects\nParticipate in business requirement analysis and user requirement studies for new system design/enhancement\nLiaise with other departments to ensure the proposed solution design would meet business requirement\nCo-ordinate testing and/or trial runs with users to make sure new system/system enhancements will be functioning as expected\nExtract & prepare data required from our databases for other departments\nAssist in ad hoc analysis and other duties as required\nAssist in configuring systems to support sales events\n\nPOSITION QUALIFICATIONS\n\nDiploma or above in Business administration, Information Technology, or related disciplines\nGood knowledge in MS Office, in particular MS Excel\nKnowledge in SQL will be a big advantage\n3+ years of experience with BI tool suits, such as Power BI, QuickSight etc. is a plus\nWorking experience in IT related field is a plus\nStrong logical mindset and good communication skills\n\nWHAT DO WE OFFER\n\nInternational and dynamic environment\nDiverse career opportunities for the right candidate\nDiverse and challenging tasks to ensure professional development\nFlexible working environment with work from home arrangement\u00a0\nCommitment to a diversity, equity and inclusive work environment", "employment_types": ["Full Time", "Permanent"], "selling_points": [], "locations": ["Central"], "categories": ["Information Technology (IT)", "Support", "Software Development", "Others"], "post_time": "2022-01-16T21:50:26Z", "salary": {"currency": null, "max": null, "min": null, "period": "monthly", "term": null}, "salary_visible": false, "title_keywords": ["business analyst"], "responsibilities": ["user requirement", "ad hoc", "power bi", "other duties", "data", "analysis", "systems", "quality", "design", "testing", "communication", "daily operations", "system design", "configuring", "databases", "liaise with", "prepare documents", "administration"], "requirements": {"degrees": ["diploma or above"], "majors": ["related disciplines", "business administration", "information technology"], "languages": [], "language_level": [], "hard_skills": ["web development", "bi", "plus", "data warehouse", "analysis", "sql", "make", "ms excel", "dynamic", "system design", "flash", "databases", "ms office"], "soft_skills": ["communication skills", "dynamic", "logical mindset"], "languages_combined": []}, "experience_required": {"duration": ["3+ years"], "field": ["related", "it"]}}, {"job_id": "100003009049026", "location_code": "hk", "company": "Pok Oi Hospital", "job_title": "Temporary Information Technology Officer (1-year contract) (Ref.: BOD/ITO/Temp)", "description": "Requirements:\nHigher Diploma or above in Computer Science, Information System or related disciplines\nAt least 3 years\u2019 working experience in IT projects and IT technical support. Prior experience in non-governmental organization (NGO), welfare or medical sector will be an added advantage\nSolid experiences in information technologies support, ICT, VC (e.g. Zoom, Teams, Google Meet) support, Windows administration, networking troubleshooting, WIFI, firewalls and IT security issues handling\nProficient in Microsoft Windows technologies, Office applications and O365\nAttention to details with sound knowledge of technical implementation and documentation\nGood communication skills, time management, able to manage and prioritize tasks effectively\nGood team player with strong interpersonal, organizing and problem solving ability\nGood command of both written and spoken Chinese and English\nResponsibilities:\nProvide IT technical support in software and hardware, VC (e.g. Zoom, Teams, Google Meet), and desktops troubleshooting, installation and configuration, IT security issues; and provide technical support in different service units of Pok Oi Hospital\nProvide daily IT administrative support, documentation and procurement assistance to IT team including upkeeping project documentation, technical and user manuals etc.\nAssist in project support including requirements collection from different stakeholders and consolidation of user requirements, and project implementation\nCoordinate with users, external vendors to ensure quality job and project tasks delivery\nResponsible for system testing including user acceptance testing (UAT) and help in production rollouts including end-user training\nWork as a team proactively and constantly to look for potential system improvement opportunities\nAssist in ad hoc projects and IT related tasks as assigned\nCandidate with less experiences will be considered as Assistant IT Officer\nThe appointment will be made on a fixed-term contract basis. Interested candidates are invited to apply by sending full resume with current salary, expected salary and date available to Human Resources Department, Pok Oi Hospital Board, UG/F., Pok Oi Hospital Jockey Club Care & Attention Home Building, Au Tau, Yuen Long or by email via \"Apply Now\"\u00a0on or before 26 January 2022.\u00a0 For more details of Pok Oi Hospital, please visit our website http://www.pokoi.org.hk.\n\u00a0(All personal data collected from applicants will be kept confidential and used for employment-related purpose only. \u00a0The Board is an equal opportunity employer.)", "employment_types": ["Contract"], "selling_points": ["Higher Diploma or above in Computer Science", "At least 3 years\u2019 working experience in IT project", "Provide IT technical support in software/hardware"], "locations": ["Not Specified"], "categories": ["Information Technology (IT)", "IT Project Management / Team Lead", "Support", "Security"], "post_time": "2022-01-14T07:59:18Z", "salary": {"currency": null, "max": null, "min": null, "period": "monthly", "term": null}, "salary_visible": false, "title_keywords": ["information technology officer"], "responsibilities": ["installation", "software", "it technical support", "uat", "configuration", "technical support", "teams", "troubleshooting", "implementation", "it administrative support", "coordinate with", "hardware", "quality", "testing", "ad hoc projects", "documentation", "project documentation"], "requirements": {"degrees": ["higher diploma or above"], "majors": ["related disciplines", "computer science"], "languages": ["english", "chinese"], "language_level": ["good command"], "hard_skills": ["o365", "vc", "office applications", "information system", "problem solving", "documentation"], "soft_skills": ["communication skills", "good team player", "troubleshooting", "prioritize", "problem solving", "attention to details", "time management", "interpersonal"], "languages_combined": [{"language": "english", "language_level": ["good command"]}, {"language": "chinese", "language_level": ["good command"]}]}, "experience_required": {"duration": ["at least 3 years"], "field": ["it", "it technical support", "medical"]}}, {"job_id": "100003008304967", "location_code": "hk", "company": "Acton Consulting Limited", "job_title": "(Senior) System Engineer / Administrator - Servers", "description": "A leading sizable organization, due to their rapid growth of the company, they are now looking for talented individuals to join the professional team.\n\nYour Role\n\nResponsible for Unix or Linux or Wintel Server and OS administration, installation, configuration, maintenance and troubleshooting\nAssist in Network and infrastructure setup and support\n\nYour Profile\n\nDiploma / Degree holder in Computer Studies, Information Technology or related discipline\n1+ years' experience in\u00a0Infrastructure / Server Administration or configurations\nTechnical experience in Unix or Wintel or\u00a0Linux Server support\nSupport experience in AD, E-mail, DNS, Wins /OR Proxy is a plus\nTechnical knowledge in\u00a0Network OR Storage will be an advantage BUT not essential\n\nInterested parties please send full resume in MS WORD format stating current salary, expected salary and availability to us OR call 2792 9960 to discuss further.\n\nWebSite: www.ActonCL.com\n\nAll information received will be kept in strict confidence and only for employment-related purposes.", "employment_types": ["Full Time", "Permanent", "Contract"], "selling_points": ["Wintel / Unix/ Linux", "Infrastructure or System Administration", "Storage, Network or Router"], "locations": ["Not Specified"], "categories": ["Information Technology (IT)", "Support", "Network & System", "Technical / Functional Consulting"], "post_time": "2022-01-17T12:51:07Z", "salary": {"currency": null, "max": null, "min": null, "period": "monthly", "term": null}, "salary_visible": false, "title_keywords": ["administrator", "system engineer"], "responsibilities": ["installation", "dns", "maintenance", "configuration", "infrastructure", "troubleshooting", "proxy", "setup", "administration"], "requirements": {"degrees": ["diploma", "degree holder"], "majors": ["information technology", "computer studies"], "languages": [], "language_level": [], "hard_skills": ["linux", "plus", "dns", "maintenance", "server administration", "os", "rapid", "server"], "soft_skills": ["troubleshooting", "responsible"], "languages_combined": []}, "experience_required": {"duration": ["1+ years"], "field": ["infrastructure", "server administration"]}}, {"job_id": "100003009054060", "location_code": "hk", "company": "eCloudvalley Technology (HK) Limited", "job_title": "Cloud Engineer/Cloud Developer", "description": "Do you like helping enterprise clients implement innovative cloud solutions and solve technical problems? Do you want to be the leader and demonstrate how the emerging technologies (such as A.I., Big Data, Cloud, DevOps) can be applied to businesses? With business growth and global expansion opportunities, we are looking for a highly motivated\u00a0Cloud Engineer/Cloud Developer to help accelerate our growing technical team. This is an excellent opportunity to join a world class technical team, working with some of the best and brightest engineers and account managers while also developing your skills and furthering your career within one of the most innovative and progressive technology young companies in Hong Kong.\n\nResponsibilities includes but is not limited to:\n\n\u00b7 Understanding clients\u2019 requirements and design technical solutions on AWS that address clients\u2019 requirements for scalability, reliability, security, and performance.\n\n\u00b7 Work closely and support sales team from technical perspective.\n\n\u00b7 Work closely with a team of architects and engineers to create technical documents and proposals.\n\n\u00b7 Conduct proof-of-concept demonstrations, technical presentations, and sharing.\n\n\u00b7 Respond to technical issues in a professional and timely manner.\n\n\u00b7 Maintain technical skills and knowledge of market trends and competitive insights; collaborate and share with the technical community.\n\nRequirements:\n\n\u00b7 Bachelor's degree in Computer Science, Computer Engineering, Information Technology or relevant field.\n\n\u00b7 2-4+ years' experience designing, executing and supporting IT cloud solutions.\n\n\u00b7 Experience architecting, designing and programming applications in an AWS Cloud environment.\n\n\u00b7 Hands-on experience with cloud computing technologies in AWS preferred\n\n\u00b7 Current AWS Certified Solutions Architect \u2013 Professional preferred\n\n\u00b7 Knowledge of cloud computing technologies on AWS and current computing trends.\n\n\u00b7 Architectural knowledge of data center infrastructure including networking, servers, storage infrastructure and virtualization.\n\n\u00b7 Positive attitude and a strong commitment to delivering quality work.\n\n\u00b7 Effective communication skills (written and verbal)\n\n\u00b7 Putonghua and English are mandatory", "employment_types": ["Full Time", "Permanent"], "selling_points": [], "locations": ["Wan Chai"], "categories": ["Information Technology (IT)", "Support", "IT Management", "Security"], "post_time": "2022-01-17T08:15:51Z", "salary": {"currency": null, "max": null, "min": null, "period": "monthly", "term": null}, "salary_visible": false, "title_keywords": ["developer", "engineer"], "responsibilities": ["collaborate", "presentations", "design", "maintain", "sales team"], "requirements": {"degrees": ["degree", "bachelor"], "majors": ["computer engineering", "computer science", "information technology"], "languages": ["putonghua", "english"], "language_level": [], "hard_skills": ["servers", "computing technologies", "aws", "programming", "cloud environment"], "soft_skills": ["positive attitude", "communication skills", "hands-on"], "languages_combined": [{"language": "putonghua", "language_level": []}, {"language": "english", "language_level": []}]}, "experience_required": {"duration": ["4+ years"], "field": ["it", "programming"]}}, {"job_id": "100003009049468", "location_code": "hk", "company": "ISS Facility Services Limited", "job_title": "IT Helpdesk Support (Job Ref: ADV/22/013)", "description": "Responsibilities\n\nProvide day-to-day support on troubleshooting, maintenance, network infrastructure, mobile applications, web services, end-user, Microsoft 365, and helpdesk support\nAssist to monitor all network, security, and computer systems to meet the organization's business needs and future development\nAssist to maintain the organization's LAN / WAN / WiFi environment and server systems\nIdentify, analyze, resolve network problems, performance issues and computer resources allocation\nHandle installation of hardware and software as well as maintain software / hardware inventory, process renewal, maintenance, and subscription\nPerform ad hoc duties as assigned\n\nRequirements\n\nDiploma holder in Computer Science, Information Technology, or related disciplines\nMinimum 1-2 years\u2019 experience in networking administration / Microsoft 365, Systems support and LAN / WAN / WiFi management\nExperience of monitoring datacenter / Windows domain server / VMWare perform / IT security or site management is preferred\nSound knowledge in TCP/IP, DNS, DHCP, Cloud service and VPN networks\nCertification in ITIL is preferred but not a must\nProactive, detail-minded, problem solving skills and sensitive to business priorities\nGood command of both spoken & written English & Chinese\nExcellent interpersonal and communication skills to work with both internal stakeholders & external vendors\nImmediately available is an advantage\nFresh graduates are welcomed\n\nWe offer professional development opportunities, attractive remuneration and fringe benefits to the right candidate.\u00a0 Interested parties please send a detailed resume, current/expected salary, contact number and the job reference no \u201cADV/22/013\u201d via \"Apply Now\".\n\nInformation provided by applicants will only be used for recruitment related purposes and will be handled confidentially by authorized personnel.\u00a0 All personal data of unsuccessful candidates will be destroyed after three months from the date of applications.", "employment_types": ["Full Time"], "selling_points": ["Provide day-to-day helpdesk support", "Identify, analyze, resolve network problems", "Fresh graduates are welcomed"], "locations": ["Not Specified"], "categories": ["Information Technology (IT)", "Support", "Application Specialist - Network", "Network & System"], "post_time": "2022-01-14T08:44:33Z", "salary": {"currency": null, "max": null, "min": null, "period": "monthly", "term": null}, "salary_visible": false, "title_keywords": [], "responsibilities": ["network infrastructure", "installation", "ad hoc duties", "software", "maintenance", "inventory", "systems", "monitor", "computer systems", "troubleshooting", "hardware", "maintain"], "requirements": {"degrees": ["diploma holder"], "majors": ["related disciplines", "computer science", "information technology"], "languages": ["english", "chinese"], "language_level": ["good command"], "hard_skills": ["itil", "vmware", "dns", "tcp", "ip", "vpn", "server", "problem solving skills", "wan"], "soft_skills": ["detail-minded", "communication skills", "sensitive to", "problem solving skills", "proactive", "interpersonal"], "languages_combined": [{"language": "english", "language_level": ["good command"]}, {"language": "chinese", "language_level": ["good command"]}]}, "experience_required": {"duration": ["minimum 1-2 years"], "field": ["management", "it", "security", "administration"]}}, {"job_id": "100003009055615", "location_code": "hk", "company": "Michael Page", "job_title": "IT Manager", "description": "One man band role to manage and oversee the efficient operation of all Information Technology related functions and processes. In charge of strategic planning, development and management of the IT systems.\n\nClient Details\n\nOur client is a reputable international professional organisation.\n\nDescription\n\nResponsibilties:\n\nManage self imposed action plans for daily operations, whilst still retaining a flexible approach to assisting individuals as and when needed, bearing in mind the IT Manager is the single IT person for the office.\nDefine and discuss priorities, including service level expectations, with Regional IT Manager and with Global IT team where relevant.\nEnsure that all meeting room IT facilities are properly maintained and managed, and assist users where necessary in their operation\nDevelop and monitor budgets for area of responsibility.\nDevelop business case justifications and cost/benefit analyses for proposed areas of spending and initiatives. Includes researching potential technology solutions and implementations in support of new initiatives, opportunities, and procurement efforts.\nKey Operational areas:\n- Customer Support\n- Networking and Communications\n- Messaging\n- Telephony\n- Enterprise Applications\n- Software Deployment and Packaging\n- Development\n- Training\n\nProfile\n\nOne man band experience in sizeable company experience\nMinimum Bachelor's Degree in Computer science or related\nGood understanding of policy/procedure development, standards and frameworks eg ISO 27001 processes and procedures\nExperience Managing desktop and supporting enterprise software application environments and databases\nHands-on experience with computer networks, network administration and network installation\nStrong communication, interpersonal, problem solving and supervisory skills\nGood written and verbal English communication is a must.\n\nJob Offer\n\nCompetitive package\n\nTo apply online please click the 'Apply' button below. For a confidential discussion about this role please contact Connie Mo on +852 2848 9540.", "employment_types": ["Full Time", "Permanent"], "selling_points": ["One man band role", "Global Professional firm", "HK$ 40 - 55k/ month"], "locations": ["Not Specified"], "categories": ["Information Technology (IT)", "Support", "IT Management", "Network & System"], "post_time": "2022-01-18T02:47:51Z", "salary": {"currency": "HKD", "max": 54999, "min": 35000, "period": "monthly", "term": null}, "salary_visible": true, "title_keywords": ["it manager"], "responsibilities": ["network administration", "budgets", "management", "cost", "installation", "strategic planning", "software", "systems", "monitor", "procedures", "develop", "communication", "daily operations", "contact", "databases", "plans"], "requirements": {"degrees": ["degree", "bachelor"], "majors": ["computer science"], "languages": ["english"], "language_level": ["good"], "hard_skills": ["network administration", "problem solving", "deployment", "databases"], "soft_skills": ["efficient", "flexible", "communication", "problem solving", "hands-on", "organisation", "interpersonal"], "languages_combined": [{"language": "english", "language_level": ["good"]}]}, "experience_required": {"duration": [], "field": ["network administration", "installation"]}}, {"job_id": "100003008305711", "location_code": "hk", "company": "Johnson Electric Industrial Manufactory Limited", "job_title": "Cyber Security Analyst", "description": "Position Summary:\n\nJohnson Electric's 24x7 Global Security Operations Center (SOC) is dedicated to detect, analyze and respond to incidents with strong set of processes and technical solutions. This newly created role is critical to this SOC covering its operations in Asia and supporting our users/premises in Europe and Americas.\u00a0\nYou will be based in Hong Kong and directly reporting to Manager of Security Operations Center.\n\nResponsibilities:\n\n\nAccess technical controls and identify areas of improvement\nManage and operate the centralized security infrastructure and products globally\nDetect, escalate and assist in remediation of critical information security incidents\nRespond to emergency and inquiry calls from internal users\nEnhance the security operations control and processes\nKeep current on the IT threat landscape and upcoming trends in security\n\nRequirements:\n\n\nBachelor Degree in IT related disciplines\nCertificates from EC-Council, GIAC, (ISC)\u00b2 are preferred\n4 to 6 years of relevant experience in network security operations, product security and/or information technology; experience in a sizable company is preferred\nFamiliar with information security tools (Firewall, Anti-Virus system, Web filtering system, E-mail filtering system, etc.)\nHighly self-motivated, detail-minded and result-oriented characters\nGood team player\nGood communication and interpersonal skills", "employment_types": ["Full Time", "Permanent"], "selling_points": ["Global Leader of Motor Manufacturer", "Global SOC team", "Attractive Salary Package"], "locations": ["Tai Po Area"], "categories": ["Information Technology (IT)", "Support", "Security", "Network & System"], "post_time": "2022-01-18T03:49:10Z", "salary": {"currency": null, "max": null, "min": null, "period": "monthly", "term": null}, "salary_visible": false, "title_keywords": ["analyst"], "responsibilities": ["operations", "control", "infrastructure", "information security"], "requirements": {"degrees": ["degree", "bachelor"], "majors": ["related disciplines", "it"], "languages": [], "language_level": [], "hard_skills": ["web", "firewall"], "soft_skills": ["detail-minded", "good team player", "self-motivated", "communication and interpersonal skills", "result-oriented"], "languages_combined": []}, "experience_required": {"duration": ["4 to 6 years"], "field": ["relevant experience", "security", "information technology"]}}]