[{"job_id": "100003009053350", "location_code": "hk", "company": "iCON Business Systems Ltd", "job_title": "Post-Sales Engineer / Consultant - Storage, Virtualization & HCI Solutions", "description": "Our client, a Japanese\u00a0network services company, is looking for a suitable candidate to join their company:\n\n<Job Responsibilities>\n\n\u2022 Analyze client's requirements and applications to design a solution for meeting customers\u2019 objectives\n\u2022 Provide solution proposals and presentations, proof of concept, and technical documentation\n\u2022 Ensure good and timely communication among customers, implementation, and sales teams\n\u2022 Project management work such as project scheduling, tracking, and reporting, technical documents including system documentation, network diagrams, etc\n\u2022 Installation, configuration, system migration, and maintenance support of Routers / Switches, Firewall, Server and PC\n\u2022 Finish project on time with quality and cost control\n\n<Necessary Skill / Experience >\n\n\u2022 Degree holder in IT or related disciplines with a minimum of 3 years working experience in technical pre-sales or consultation support\n\u2022 Solid project management experience\n\u2022 Good command of spoken and written English and Cantonese. Knowledge of Mandarin or Japanese would be a plus\n\u2022 Hands-on experience with network equipment such as Router, LAN switch, and security appliances/products such as Firewall, IDS, IPS\n\u2022 Strong Microsoft Skills. Including Word, Excel, and Powerpoint\n\u2022 Knowledge and hands-on experience of Windows Server, VMware, Citrix virtualization technology, RPA technology, Public Cloud services are preferable.\n\nInterested parties please send us your resume in MS Word/PDF format in English.\u00a0All information received will be kept in strict confidential and only for recruitment purpose.", "employment_types": ["Full Time", "Permanent"], "selling_points": ["Post-Sales Engineer", "Infrastructure, HCI, Virtualization Technologies", "Fresh Graduate welcome"], "locations": ["Cheung Sha Wan"], "categories": ["Information Technology (IT)", "Support", "Network & System", "Technical / Functional Consulting"], "post_time": "2022-01-17T06:49:18Z", "salary": {"currency": null, "max": null, "min": null, "period": "monthly", "term": null}, "salary_visible": false, "title_keywords": ["consultant", "sales engineer"], "responsibilities": ["reporting", "installation", "system documentation", "configuration", "maintenance support", "teams", "implementation", "presentations", "design", "communication", "project management", "quality", "project scheduling", "cost control", "documentation", "migration", "tracking"], "requirements": {"degrees": ["degree holder"], "majors": ["related disciplines", "it"], "languages": ["cantonese", "japanese", "english", "mandarin"], "language_level": ["good command"], "hard_skills": ["server", "plus", "excel", "virtualization technology", "vmware", "maintenance", "switch", "word", "presentations", "router", "powerpoint", "project management", "rpa", "citrix", "firewall", "documentation", "pc", "windows server"], "soft_skills": ["communication", "project management", "timely", "hands-on"], "languages_combined": [{"language": "cantonese", "language_level": ["good command"]}, {"language": "japanese", "language_level": []}, {"language": "english", "language_level": ["good command"]}, {"language": "mandarin", "language_level": []}]}, "experience_required": {"duration": ["minimum of 3 years"], "field": ["related", "project management", "it", "security"]}}, {"job_id": "100003009053946", "location_code": "hk", "company": "Geek Plus International Company Limited", "job_title": "Assistant Manager, Customer Care (Overnight Shift Required)", "description": "Responsibilities:\n\nReports to Technical Manager\nBe assigned to complete technical tasks including Post-sales and Project implementation\nProvides professional services on planning and design, deployment and integration services to fulfill customer's\u00a0Requirements\nBe responsible for proposal writing and preparing project documentation\n\nRequirements:\n\nAttains Degree in IT or related disciplines\nAttains At least TWO YEAR technical experience and solid skillset in storage and virtualization solutions\nBe Certified of Storage, VMware and HCI Solutions\nBe capable of effective communication with different customers\nBe Willing to learn and be aggressive\nCan work independently\nBe self-motivated with clear company and self objectives\nSenior System Engineer with similar experience and skillset will be considered\n\nWe offer comprehensive remuneration and benefits, and excellent career opportunities to the right candidates. Interested parties please state clearly the position you are applying to with reference no. if any in the subject line and email us a full resume with CURRENT & EXPECTED SALARY.\n\nAll applications will be treated in the strictest confidence. We regret that only shortlisted candidates will be notified. Data collected will be used for recruitment purpose only.", "employment_types": ["Full Time", "Permanent"], "selling_points": ["Exp in technical support and customer services", "Strong communication, independently and flexible", "Overnight shift is required, with allowance"], "locations": ["Kwai Hing"], "categories": ["Sales, CS & Business Devpt", "Customer Service - Supervisor / Officer", "Engineering", "Engineering Project Management", "Information Technology (IT)", "Technical / Functional Consulting"], "post_time": "2022-01-17T07:48:56Z", "salary": {"currency": null, "max": null, "min": null, "period": "monthly", "term": null}, "salary_visible": false, "title_keywords": ["assistant manager,"], "responsibilities": ["implementation", "design", "planning", "reports", "project documentation"], "requirements": {"degrees": ["degree"], "majors": ["related disciplines", "it"], "languages": [], "language_level": [], "hard_skills": ["vmware"], "soft_skills": ["work independently", "self-motivated", "capable", "willing to learn", "communication", "clear"], "languages_combined": []}, "experience_required": {"duration": ["at least two year"], "field": []}}, {"job_id": "100003009052466", "location_code": "hk", "company": "Xensetech Limited", "job_title": "Business Process Re-engineering Officer", "description": "About Geek+\nGeek+ leads the technology revolution, by applying advanced robotics and AI technologies to realize high-flexibility and intelligent logistics automation solution. We are always looking for people who can bring new perspectives and life experiences to our company. We understand the value of our people and we strive to constantly satisfy their needs.\n\nWe are looking for a\u00a0Assistant Manager, Customer Care\u00a0to join our team. Are you someone who is driven by curiosity, craves a good challenge? Join us and be part of this exciting adventure!\n\nAbout the role:\n\nProactively liaise with different levels and functional teams to ensure operation runs smoothly\nAct as key escalation point in case of high severity incidents and push for resolution\nInvestigate and resolve customer complaints and queries, divert cases to related functional teams\nContinuously monitor the KPI of the team, speed of response / efficiency in dealing with customer enquiries\nTake ownership of any tasks set and ensure all deadlines are met by being organised\nReview the current operation and working with the manager to set up new processes to streamline and improve the customer experience\nProvide direction to the teammates to ensure that all issues are resolved quickly\nEnsure constant clear communication within the team to uphold complete transparency with new processes, issues, general updates etc\nRequirements:\n\nDegree in any business-related discipline, IT related is preferred\n5 years of working experience in customer service, logistics/IT solutions background would be an absolute advantageMust be fluent in both written and verbal English, Mandarin and Cantonese\nStrong planning and organizational skills as well as attention to detail\nProven experience to manage huge size corporation customers would be a plus\nWilling to learn, detail-oriented and open-minded\u00a0\nSelf-motivated,\u00a0hard-working\u00a0and\u00a0independent\nWhat We Offer:\n\nFive-day work week\nOvernight shift allowance\nYoung and energetic work culture with regional exposure\nCozy office environment with\u00a0light refreshments\nDouble pay & attractive performance bonus\nMedical and dental benefits and insurance\n14 to 21 days Annual Leave\nConvenient work location: KCC\nIf your qualifications, experience, and aspirations match our requirements, please send your resume with your current and expected salary to us.\n\nAll information and materials submitted to Geek+ will remain strictly confidential and be treated for recruitment purposes only. Only short-listed candidates will be notified.", "employment_types": ["Full Time", "Permanent"], "selling_points": ["Degree or above in IT, CS & Computing Engineering", "Stable and professional team, friendly culture", "Competitive remuneration package"], "locations": ["Shatin Area"], "categories": ["Information Technology (IT)", "Application Specialist - Software", "Product Management / Business Analyst", "Technical / Functional Consulting"], "post_time": "2022-01-17T03:05:53Z", "salary": {"currency": null, "max": null, "min": null, "period": "monthly", "term": null}, "salary_visible": false, "title_keywords": ["officer"], "responsibilities": ["robotics", "resolve customer complaints", "provide direction", "customer enquiries", "review", "teams", "monitor", "resolution", "communication", "customer service", "logistics", "liaise with", "planning"], "requirements": {"degrees": ["degree"], "majors": ["business", "it"], "languages": ["cantonese", "english", "mandarin"], "language_level": ["fluent"], "hard_skills": ["plus", "ai"], "soft_skills": ["organizational skills", "self-motivated", "independent", "advanced", "open-minded", "willing to learn", "detail-oriented", "clear", "communication", "customer service", "hard-working", "attention to detail", "organised", "driven"], "languages_combined": [{"language": "cantonese", "language_level": ["fluent"]}, {"language": "english", "language_level": ["fluent"]}, {"language": "mandarin", "language_level": ["fluent"]}]}, "experience_required": {"duration": ["5 years"], "field": ["logistics", "operation", "customer service", "it"]}}, {"job_id": "100003009054194", "location_code": "hk", "company": "HKBN Enterprise Solutions HK Limited", "job_title": "Senior / Cloud Engineer", "description": "You\u00a0will create impact via\u2026\n\n\n\nDesign & architect the implementation of cloud solution using AWS, Alibaba Cloud, Microsoft Azure, advise customers on various cloud solution options & recommend a solution that aligns with business customer needs\nEngage in the AWS Services Configuration Management, Cloud Automation and Design for the AWS platform and applications\nResponsible to build Cloud infrastructure as a code (CDK, Terraform, Ansible) capability by planning and implementation of the cloud platform\nArchitect level of AWS cloud, Alibaba Cloud, Azure is a plus\nPerform system and network, design, implementation, monitoring, capacity management, security operations, and support in AWS, Alibaba Cloud, Microsoft Azure environment\nWork with the business and technical stakeholders on explaining the technical solutions\nThe follow attributes will be valued\u2026\n\n\nBachelor\u2019s degree in IT-related, Computer Science discipline\u00a0\n2+ years of experience in Cloud computing technologies, concepts, and Cloud consulting, in the areas of Public Cloud , Private Cloud, Hybrid Cloud, Global Cloud technologies in AWS, Alibaba Cloud and Azure Cloud\nAcquired AWS Solution Architect Professional Certificate, specialty certificate in security and network is a plus\nCertificate in Alibaba Cloud, Azure and Google Cloud is a plus\nExperience with Cloud Automation & configuration management\nExperience with Cloud platform operations including system, network, and security monitoring\u00a0\nGood Communications skills in English\u00a0\nTalents with more experience will be considered Senior Cloud Engineer\n\nWhat you get in return\u2026\n\nApart from competitive salary package and benefits, in HKBN, you will work flexibly under our\u00a0Talent-first culture\u00a0and we uphold\u00a0Life-Work Priority. Examples of our flexible initiatives:\n\nFive-day work week\u00a0\nHalf Day Off Friday once a month (compensation leave for Talents who work on shift)\nHalf Day Off on Festival Eve (compensation leave for Talents who work on shift)\nUnique leaves arrangement: Family-care leave, Anniversary leave, Bonus leave, Volunteer leave, Sabbatical leave, etc.\nComprehensive medical and life insurance coverage\nUpgraded maternity leave and paternity leave\nDiscounted Talent plan offers including broadband and mobile plans and other promoted products\nEducation subsidies and Examination leave\nYear-end discretionary bonus\n\nJoin Us Today!\n\nAll information provided by applicants will be treated in strict confidence and used for consideration in relation to the relevant post within the company.\n\nAll personal data of unsuccessful applicants will be destroyed within one year. Applicants who are not invited for an interview within 3 weeks may consider their application unsuccessful.", "employment_types": ["Full Time", "Permanent"], "selling_points": ["AWS/Azure/AliCloud Service Configure Management", "1+ year on the cloud computing platform", "5 days work, Talent-first Culture"], "locations": ["Kowloon Bay"], "categories": ["Information Technology (IT)", "Support", "Network & System", "Technical / Functional Consulting"], "post_time": "2022-01-17T08:45:38Z", "salary": {"currency": null, "max": null, "min": null, "period": "monthly", "term": null}, "salary_visible": false, "title_keywords": ["engineer"], "responsibilities": ["management", "consulting", "configuration", "operations", "infrastructure", "monitoring", "implementation", "design", "planning"], "requirements": {"degrees": ["certificate", "degree", "bachelor"], "majors": ["it", "computer science"], "languages": ["english"], "language_level": ["good"], "hard_skills": ["plus", "azure", "computing technologies", "aws", "ansible", "code"], "soft_skills": ["responsible"], "languages_combined": [{"language": "english", "language_level": ["good"]}]}, "experience_required": {"duration": ["2+ years"], "field": ["management", "security", "consulting"]}}, {"job_id": "100003009052340", "location_code": "hk", "company": "Hong Kong Broadband Network Limited", "job_title": "Engineer ( Data Center Facility Management )", "description": "Job Description\n\nResponsibilities:\n\n\u2022\u00a0Manage Information Technology\u00a0team in Hong Kong, including all offices and warehouses, and provide IT support to corporate users;\n\u2022\u00a0Enhance system serviceability, online stability, provide solutions and troubleshoot hardware and software issues;\n\u2022\u00a0Ensure the development and operation of IT infrastructure are in compliance with the technical, system security and project management standards;\n\u2022\u00a0Liaise with IT service providers / vendors and other third-parties;\n\u2022\u00a0Oversee and determine time frames for major IT projects including system updates, upgrades, migrations and outages;\n\u2022\u00a0Communicate and arrange awareness training for business users;\n\u2022\u00a0Manage, train, and mentor IT staff;\n\u2022\u00a0Prepare IT proposal, budget, technical documentation and system specification;\n\u2022\u00a0Formulating IT policies and procedures;\n\u2022\u00a0Hands on experience in Oracle / MSSQL / AD / Windows server / VMWare / VSAN, Firewall administration, Systems Tools, Local Systems Infra / application Team and WMS system;\n\u2022\u00a0Responsible for System HA / DR infrastructure design, implementation and maintenance;\n\u2022\u00a0Perform system administration, monitoring and capacity management; and\n\u2022\u00a0Understand and satisfy Cyber Security requirements.\n\n\u00a0Requirements:\u00a0 \u00a0 \u00a0 \u00a0 \u00a0 \u00a0 \u00a0 \u00a0 \u00a0\n\n\u2022\u00a0Degree holder in Computer Science or Information System;\n\u2022\u00a0Current holder\u00a0of MCSE, CCNA, and\u00a0ITIL\u00a04\u00a0Foundation;\n\u2022\u00a0A minimum of 10 years\u2019 experience in multiple areas of technology, including systems infrastructure and application;\n\u2022\u00a0With strong and broad understanding in multiple technical domains including but not limited to: Business Applications, Microsoft O365, Microsoft Exchange, Sharepoint, Azure, Network and Firewalls etc;\n\u2022\u00a0A good team player with analytical & problem-solving skills, self-motivation, positive attitude, fast-learning, energetic, able to perform in challenging environment;\n\u2022\u00a0Good knowledge in developing Windows network, Linux and PC infrastructure;\n\u2022\u00a0Strong leadership and management skills, proven ability to manage IT team to achieve timelines and objectives;\n\u2022\u00a0Proficiency in both written and spoken English, Chinese and Mandarin; and\n\u2022\u00a0Can work under pressure and fast-paced working environment.", "employment_types": ["Full Time", "Permanent"], "selling_points": ["Talent-first Culture & LIFE-work priority", "Execute improvement projects for E&M facility", "Monitor E&M facility performance"], "locations": ["Kwai Hing"], "categories": ["Engineering", "Telecommunication / Wireless / Radio", "Information Technology (IT)", "Network & System", "Technical / Functional Consulting"], "post_time": "2022-01-17T02:48:21Z", "salary": {"currency": null, "max": null, "min": null, "period": "monthly", "term": null}, "salary_visible": false, "title_keywords": ["engineer"], "responsibilities": ["it service", "cyber security", "budget", "design", "troubleshoot", "wms", "liaise with", "administration", "compliance", "project management standards", "infrastructure", "implementation", "major it projects", "hardware and software issues", "migrations", "development and operation of it infrastructure", "management", "upgrades", "monitoring", "procedures", "it policies", "provide solutions", "documentation", "system serviceability", "online stability", "maintenance", "system updates", "outages", "systems", "system security"], "requirements": {"degrees": ["degree holder"], "majors": ["computer science"], "languages": ["english", "chinese", "mandarin"], "language_level": ["proficiency"], "hard_skills": ["itil", "mcse", "o365", "linux", "azure", "ccna", "information system", "pc", "problem-solving skills", "microsoft exchange"], "soft_skills": ["good team player", "fast-learning", "positive attitude", "self-motivation", "problem-solving skills", "energetic", "leadership", "work under pressure"], "languages_combined": [{"language": "english", "language_level": ["proficiency"]}, {"language": "chinese", "language_level": ["proficiency"]}, {"language": "mandarin", "language_level": ["proficiency"]}]}, "experience_required": {"duration": ["minimum of 10 years"], "field": ["infrastructure"]}}, {"job_id": "100003009054558", "location_code": "hk", "company": "Janco Global Logistics Limited", "job_title": "IT Manager", "description": "Our client, a Japanese\u00a0network services company, is looking for a suitable candidate to join their company:\n\n<Job Responsibilities>\n\n\u2022 Pre-sales support\n\u2022 Project scheduling, tracking, and reporting;\n\u2022 Project management work such as technical documents including system documentation, network diagrams, etc.;\n\u2022 Installation, configuration, maintenance, and operation support of routers/ switches, firewall, Server, and PC equipment;\n\u2022 Development of new IT solution product/service;\n\u2022 Finish project on time with quality and cost control\n\n<Necessary Skill / Experience >\n\n\u2022 University graduate in Computer Science or related disciplines.\n\u2022 At least 5 years of relevant working experience. Preferably in the telecommunications field in a global/regional carrier or vendor environment.\n\u2022 Fluent in Japanese and English, Chinese ability is an advantage\n\u2022 System administration experience on MS and Linux platforms is essential\n\u2022 Knowledge and hands-on experience of VMware, Citrix virtualization technology preferred\n\u2022 Vendor certification at professional or above level is preferred, e.g. CCNP/CCDP/MCSE\n\u2022 Knowledge of firewall configuration and network security technologies, e.g. Fotigate/SRX/SSG.\n\u2022 Solid understandings of networking protocols such as routing (BGP, OSPF), VLAN (STP, 802.1P, 802.1Q, etc.), IP-based audio \\video (SIP, H.323), etc.\n\nInterested parties please send us your resume in MS Word/PDF format in English.\u00a0All information received will be kept in strict confidential and only for recruitment purpose.", "employment_types": ["Full Time"], "selling_points": ["Provide IT support to corporate users", "Ensure develop & operation of IT infrastructure", "Hands on experience in WMS system"], "locations": ["Kwun Tong"], "categories": ["Information Technology (IT)", "Support", "Network & System", "Technical / Functional Consulting"], "post_time": "2022-01-17T09:59:07Z", "salary": {"currency": null, "max": null, "min": null, "period": "monthly", "term": null}, "salary_visible": false, "title_keywords": ["it manager"], "responsibilities": ["administration", "reporting", "installation", "system documentation", "maintenance", "configuration", "quality", "project management", "project scheduling", "cost control", "audio", "tracking"], "requirements": {"degrees": ["university graduate"], "majors": ["related disciplines", "computer science"], "languages": ["japanese", "english", "chinese"], "language_level": ["advantage", "fluent"], "hard_skills": ["server", "virtualization technology", "mcse", "sales support", "vmware", "maintenance", "linux platforms", "ccnp", "vendor", "project management", "ip", "citrix", "firewall", "documentation", "pc", "operation support"], "soft_skills": ["project management", "hands-on"], "languages_combined": [{"language": "japanese", "language_level": ["advantage", "fluent"]}, {"language": "english", "language_level": ["advantage", "fluent"]}, {"language": "chinese", "language_level": ["fluent"]}]}, "experience_required": {"duration": ["at least 5 years"], "field": ["relevant working experience", "administration"]}}, {"job_id": "100003009054592", "location_code": "hk", "company": "RGF HR Agent Hong Kong Limited", "job_title": "Japanese Speaking Pre/Post Sales Engineer  - Japanese Network Service Company", "description": "Who are we?\nDavid James Recruitment is a leader in IT recruitment, with directors who have a long track record and great success in our field. Our goal is to be outstanding - for service, knowledge, network, and quality delivery to our candidates and clients.\u00a0 Our team combines IT recruitment experience from major global cities across APAC and Europe, coupled with excellent knowledge in the HK and Asia markets.\nAt David James we are regard ourselves as \u201cold school\u201d \u2013we are keen on training and building consultants from trainee level so that we are consistent with our methods, as well as encouraging loyalty, teamwork and promoting a positive company culture with a real sense of fun and humour.\nWith Directors that are hands on and having many years of genuine end to end recruitment experience, we will provide an in depth insight of the industry in a short time, helping you to learn and pick things up quickly. We want to encourage and support people into bigger roles and more money. There is no hire/fire mentality here - consultants are given fair chances to learn, try hard, and make it happen, with senior staff supporting you every step of the way.\nWe have a particularly strong emphasis on quality service, end to end recruitment, work hard play hard mentality, fairness, loyalty and teamwork.\nThe right candidate will be:\u00a0\n\n\nNaturally sales driven and customer driven\nFearless and outgoing\nPositive and passionate\nHave a great sense of humour\nAble to think outside the box\nBe a fantastic communicator\nFocused and disciplined\nFluent in English and preferably Chinese (Cantonese or Mandarin)\nAmbitious and impatient for success\nYou will not need knowledge of IT, with all training provided, and hard work and application, you will be able to pick things up quickly\nContact us now if you are keen to have an informal chat to hear more at +852 3619 9860 or send us your CV for our reference.", "employment_types": ["Full Time", "Permanent"], "selling_points": ["Japanese Speaking Pre/Post Sales Engineer", "5 yrs + related exp /JLPT N2 ( fluent JP)", "HK Island/ DP / Up to 30K"], "locations": ["Others"], "categories": ["Sales, CS & Business Devpt", "Business Development", "Information Technology (IT)", "IT Project Management / Team Lead", "Technical / Functional Consulting"], "post_time": "2022-01-17T10:10:20Z", "salary": {"currency": null, "max": null, "min": null, "period": "monthly", "term": null}, "salary_visible": false, "title_keywords": ["sales engineer"], "responsibilities": [], "requirements": {"degrees": [], "majors": [], "languages": [], "language_level": [], "hard_skills": [], "soft_skills": [], "languages_combined": []}, "experience_required": {"duration": [], "field": []}}, {"job_id": "100003009054586", "location_code": "hk", "company": "David James Recruitment Limited", "job_title": "Recruitment Consultants - Experienced IT Desk \u2013 Fresh Graduates Welcome", "description": "About Accenture\uff1a\n\nAccenture is a global professional services company with leading capabilities in digital, cloud and security. Combining unmatched experience and specialized skills across more than 40 industries, we offer Strategy and Consulting, Interactive, Technology and Operations services\u2014all powered by the world\u2019s largest network of Advanced Technology and Intelligent Operations centers. Our 506,000 people deliver on the promise of technology and human ingenuity every day, serving clients in more than 120 countries. We embrace the power of change to create value and shared success for our clients, people, shareholders, partners and communities.\n\nThe company has been operating in Greater China for over 30 years. Today, it has more than 17,000 people servicing clients across the region with offices in the cities including Beijing, Shanghai, Dalian, Chengdu, Guangzhou, Shenzhen, Hong Kong and Taipei. As a trusted Partner of Choice for digital transformation, Accenture is bringing more innovation to the business and technology ecosystems and helping Chinese enterprises and the government to embrace digitization and enhance global competitiveness to succeed in the new era.\n\nFor more information about Accenture, please visit its corporate homepage www.accenture.com and its Greater China homepage www.accenture.cn .\n\n\nAbout Accenture Interactive\uff1a\n\nAs one of the key services under Accenture, Accenture Interactive is in the business of Experience. We connect deep human and business insights with the possibilities of technology to define and deliver new realities. We're committed to helping clients design, build, communicate and run Experiences that make peoples' lives better, more productive and more meaningful. Visit http://www.accentureinteractive.com to find out more about us.\n\n\nKey Responsibilities\n\nWork in conjunction with different parties to conceptualize and propose solution approaches\u00a0\nDrive and challenge business units on their assumptions of how they will successfully execute the business plans\u00a0\nElicit requirements using interviews, document analysis, requirements workshops, surveys, business process descriptions, use cases, scenarios, and task and workflow analysis for major and minor projects\u00a0\nPlan and implement analytics to projects for different clients with tasks including but not limited to data tracking, tag management, data visualization, reporting & analysis and developing insights & recommendation\u00a0\nTransform data to insights for business development, strategies or optimization approaches\u00a0\nCreate high level and detailed level requirements specifications for major and minor projects\u00a0\nGenerate business\u00a0requirements\u00a0and use cases which documents business needs, rules and details\u00a0\nIdentify and document constraints, assumptions and risks associated with business requirements\u00a0\nDocument gaps in projects whilst providing potential solutions\u00a0\nPrepare business case\u00a0\nMaintain timely communications to business stakeholders throughout the project life cycle to ensure common understanding of the requirements and the impact to the business area\u00a0\n\nExperience, Attributes and Qualifications:\n\nDegree in\u00a0Information Management,\u00a0Computer Science, Information Technology, Business or related area\u00a0\n4-5+\u00a0years of relevant experience in Business Analyst and/or Digital Data Analytics\u00a0role, preferably in a consulting environment\nMinimum of 2 years of experience using, implementing, and / or customizing digital analytics and tag management solutions (e.g., Adobe, Google, Tealium, etc.)\nAgile experience and digital experience\u00a0preferred\u00a0(e.g. Digital Transformation,\u00a0eCommerce, Digital Marketing, O2O Digital Channels, etc.)\u00a0\nUnderstanding of design thinking\u00a0\nExperienced in executing implementation digital projects\u00a0\nStrong background in\u00a0digital\u00a0business analysis and/or system analysis\u00a0\nStrong analytical mind with excellent relationship management\u00a0\nExcellent verbal and written communication skills and the ability to interact professionally with diverse group of stakeholders\u00a0\nFluent Cantonese, English and Mandarin is a must\u00a0\nAble to legally work in\u00a0Hong Kong", "employment_types": ["Full Time", "Permanent"], "selling_points": ["Fresh Graduates / Experienced Hires Welcome", "On The Job Training Provided", "Competitive Basic Salary & Commission Scheme"], "locations": ["Sheung Wan"], "categories": ["Admin & HR", "Recruitment / Executive Search", "Information Technology (IT)", "Technical / Functional Consulting", "Management", "Management Trainee"], "post_time": "2022-01-17T10:07:32Z", "salary": {"currency": null, "max": null, "min": null, "period": "monthly", "term": null}, "salary_visible": false, "title_keywords": ["consultants"], "responsibilities": ["visualization", "consulting", "data", "operations", "business plans", "design", "communication", "business process", "maintain", "plan", "developing", "implementation", "reporting", "management", "specifications", "digital marketing", "executing", "tracking", "analysis", "business analysis"], "requirements": {"degrees": ["degree"], "majors": ["business", "computer science", "information technology"], "languages": ["cantonese", "english", "chinese", "mandarin"], "language_level": ["fluent"], "hard_skills": ["agile", "data analytics", "analysis", "make", "adobe", "data visualization", "workshops"], "soft_skills": ["productive", "communication skills", "advanced", "agile", "timely", "deep", "committed", "diverse", "analytical mind", "detailed"], "languages_combined": [{"language": "cantonese", "language_level": ["fluent"]}, {"language": "english", "language_level": []}, {"language": "chinese", "language_level": []}, {"language": "mandarin", "language_level": []}]}, "experience_required": {"duration": ["minimum of 2 years", "5+ years"], "field": ["management", "consulting", "design", "business", "relevant experience", "digital"]}}, {"job_id": "100003009054658", "location_code": "hk", "company": "OPM Systems Company Limited", "job_title": "IT Helpdesk Support / Engineer", "description": "DEAR TALENT, YOUR MOVE!\n\nBeing the new rising airline since 2013, we are the Hong Kong\u2019s only Low Cost Carrier (LCC) offering you safe and flexible service options to Hong Kong and beyond.\n\nWe\u2019re on a mission to inspire you to be different, to shake things up, to inspire the spirit of adventure by bringing you to fascinating destinations that few others serve.\n\nSpread your wings and fly with us!\n\nWhat will you do?\u00a0\n\nLead a small team to maintain daily IT Infrastructure operation to support internal users within SLA under ITIL standard;\nSupport Security team to handle security events in IT infrastructure environment;\nSupport internal audit to assess different IT areas;\nDevelop and maintain formal guidelines, policies, and procedures to ensure the smooth operation;\nManage external vendor to provide technical support on corporate IT Infrastructure with emphasis on the internal network, servers, Microsoft office365 environment and cloud infrastructure;\nManage external vendor to provide technical support on Airport IT Infrastructure with emphasis on Express IP, AviNet, ACARS and EDI about Cargo / Crew / Passenger Information Filing;\nPlan, setup, lead and manage the IT Infrastructure and End-user Technology Strategy including disaster recovery planning;\nResearch on new technology, identify technology gaps, develop and deploy Infrastructure solutions;\nRemediate Risk & Vulnerability for Infrastructure and End-user computing;\nDrive the continuous improvement to all IT Infrastructure related services;\nDetermine how to leverage enabling technologies to implement innovative IT infrastructure solutions to support the business\nCoach and mentor team members;\nTravel occasionally for new station setup/support;\u00a0\nSupport ad-hoc duties as assigned.\n\nWe are a perfect match, if you are:\n\nUniversity graduate in Computer Technology or related discipline;\nMinimum 6 years of related working experiences in IT security with 2 years of supervisor post;\nStrong technical knowledge in all aspects of IT Infrastructure especially in Microsoft Office365, Fortinet, Azure/Alibaba cloud and End-user computing;\nSound Knowledgeable on SOC, DLP and SIEM;\nCertification on networking (such as CCNA, CCNP, CCIE);\nITILv3 Foundation Certification is a must;\nBasic knowledge of common information security management frameworks, such as ISO 27001, CobiT, ITIL, PCI DSS.\n\nYour Future Work Life?\n\nWork flexibly with staggered working hours and flexible workplace\nDress Casual and Smart everyday\nWork in a newly-designed office with open seating, stylish breakout areas, game room, gym and free coffee\u2026\nWork with a group of energetic and multicultural professionals (up to 50 nationalities!)\nHave great fun in Snack Friday, New Year Market, Fly with your Kids Day, Basketball Team\u2026\nHave your voice heard through Townhalls, Crew forums, CEO live sessions etc.\n\nWhat will you enjoy?\n\nFly anywhere we fly for free plus taxes during leisure with your friends and family\nSpecial privileges to buy duty free products\nCareer Express\n\n\nYou will be inspired by our core values.\nYou will be inspired by our vibrant, efficient and entrepreneurial spirit. Join our fun, collaborative and reliable team to ignite your dream!\n\n\nInterested? It\u2019s time to have YOUR MOVE!\nIf you're ready to embark your adventure, start by clicking the \u2018Apply now\u2019 and get on the plane to fly with HK Express!\u00a0", "employment_types": ["Full Time", "Permanent"], "selling_points": ["IT Support", "Shift duties required", "Immediate available preferred"], "locations": ["Tung Chung"], "categories": ["Information Technology (IT)", "Hardware", "Support", "Technical / Functional Consulting"], "post_time": "2022-01-17T10:26:29Z", "salary": {"currency": null, "max": null, "min": null, "period": "monthly", "term": null}, "salary_visible": false, "title_keywords": ["engineer"], "responsibilities": ["cost", "information security", "management", "it infrastructure", "internal audit", "recovery planning", "guidelines", "policies", "lead a small team", "technical support", "procedures", "infrastructure", "ad-hoc duties", "develop", "maintain", "plan", "deploy", "setup"], "requirements": {"degrees": ["university graduate"], "majors": [], "languages": [], "language_level": [], "hard_skills": ["small", "itil", "plus", "azure", "servers", "basic", "security management", "fun", "ccnp", "ccna", "airline", "vendor", "sla", "safe", "ip", "lcc"], "soft_skills": ["flexible", "efficient", "collaborative", "innovative", "smooth", "reliable", "ad-hoc duties", "energetic"], "languages_combined": []}, "experience_required": {"duration": ["2 years", "minimum 6 years"], "field": ["related", "it", "security"]}}, {"job_id": "100003009051931", "location_code": "hk", "company": "Octopus Holdings Limited", "job_title": "Assistant Manager, Professional Services (Ref: OCL/OPS/2021-225)", "description": "Job Highlights\n\ntechnical writer,project management\ncomfortable working environment\nWell-organized, mature, highly responsible\u2028\n\nJob Description\nJob Requirements\n\nWell-organized, mature, highly responsible and independent\nGood in spoken and writing English, Cantonese and Mandarin\nInterested in IT industry\u00a0\nWilling to build up and keep a good relationship with our clients and vendors\nDetailed-minded\nWilling to learn\nProactive with good communication skills\nHave basic understanding of retail/F&B businesses operation is a\u00a0plus\n\n\nJob Duties:\n\nReports to Project Manager\nCo-ordinate with development team to achieve project deliverables\nOperate and set up Omnitech system to cater for clients\u2019 operations, campaigns and promotions\napp testing and develop standardised test plans\nTroubleshoot for clients\u2019 technical problems\n\nWe offer you\n\nFlexible working hours\nComfortable working environment\nFree drinks and snacks\nChance to learn the coolest things in IT industryYou can find more in our website:\u00a0https://www.tofugear.com\n\nIf you are interested, please click apply now\u00a0with attached CV with expected salary\nAll personal information submitted by job applicants will be used for recruitment purposes and we reserve the rights to consider the applications for other positions in our\u00a0Group.", "employment_types": ["Full Time", "Permanent"], "selling_points": ["Handle merchant complaints and liaise internally", "Bachelor degree holders in Information, Computer", "Minimum 7 years working experience"], "locations": ["Kowloon Bay"], "categories": ["Information Technology (IT)", "Network & System", "Technical / Functional Consulting", "Others"], "post_time": "2022-01-17T01:32:43Z", "salary": {"currency": null, "max": null, "min": null, "period": "monthly", "term": null}, "salary_visible": false, "title_keywords": ["assistant manager,"], "responsibilities": [], "requirements": {"degrees": [], "majors": [], "languages": ["cantonese", "english", "mandarin"], "language_level": ["good"], "hard_skills": ["plus", "basic"], "soft_skills": ["communication skills", "independent", "responsible", "interested in", "well-organized", "willing to learn", "mature", "troubleshoot", "proactive", "detailed"], "languages_combined": [{"language": "cantonese", "language_level": ["good"]}, {"language": "english", "language_level": ["good"]}, {"language": "mandarin", "language_level": ["good"]}]}, "experience_required": {"duration": [], "field": []}}, {"job_id": "100003009054534", "location_code": "hk", "company": "Asia Airfreight Terminal Co., Ltd.", "job_title": "System Support Officer - Fresh graduates are welcome", "description": "Job Responsibilities:\n\nProvide end-user software applications and computer hardware support and troubleshooting in a professional manner.\nKeep\u00a0 record of daily data communication transactions, problems and remedial action taken\nHandle the user requests according to the IT standards/procedures/guidelines\nResponsible to work according to the shift duty assigned and support roster for 24/7 technical support to End users\nReport to Line manager or Supervisor and finish the duties with proper time management\nShift duty required (Public transportation available at their on-duty and off-duty time)\nShift duty on Sunday and Hong Kong Public Holiday required\n\nJob Requirements:\n\nDiploma or above in Information Technology or Computer related disciplines\nHands-on experience in IT Helpdesk and End-User support\nFlexible and able to work both in team and independently\nI.T. Certificates holder is an advantage\nGood command in Cantonese and English, Putonghua is an advantage\nWilling to learn, self-initiative and work independent.\nGood interpersonal skill, telephone manner and service attitude\nMonthly salary HK$17,000-20,000\u00a0\n\nWe offer competitive remuneration package and generous benefits including medical coverage.\u00a0\n\nPersonal data collected will be used for recruitment purpose only.", "employment_types": ["Full Time", "Permanent"], "selling_points": ["5-day week, 12 days annual leave, double pay", "Fresh graduates are welcome", "Shift duty is required"], "locations": ["Airport Area"], "categories": ["Information Technology (IT)", "Support", "Network & System", "Technical / Functional Consulting"], "post_time": "2022-01-17T09:54:44Z", "salary": {"currency": null, "max": null, "min": null, "period": "monthly", "term": null}, "salary_visible": false, "title_keywords": ["officer", "system support"], "responsibilities": ["management", "software", "data", "guidelines", "technical support", "professional manner", "troubleshooting", "transactions", "procedures", "communication", "hardware", "report"], "requirements": {"degrees": ["diploma or above"], "majors": ["computer related", "information technology"], "languages": ["cantonese", "putonghua", "english"], "language_level": ["advantage", "good command"], "hard_skills": [], "soft_skills": ["flexible", "independently", "independent", "willing to learn", "interpersonal skill", "hands-on", "self-initiative", "telephone manner"], "languages_combined": [{"language": "cantonese", "language_level": ["good command"]}, {"language": "putonghua", "language_level": ["advantage", "good command"]}, {"language": "english", "language_level": ["good command"]}]}, "experience_required": {"duration": [], "field": ["it helpdesk"]}}, {"job_id": "100003009052464", "location_code": "hk", "company": "Xensetech Limited", "job_title": "Senior / Advanced Technology Analyst", "description": "Duties\n\nProvide IT technical support to end-users, eg, outlook email client, file & print, end point protection, desktop application and mobile device\nPerform trouble-shooting for the computer and networking (including but not limited to WAN, Firewall, Routers, Switches, WIFI) related problems\nSupport software and hardware installation to users\nHelp to increase users satisfaction by responding to service calls from staff\n\n\u00a0Requirements\n\nDiploma holder or above in IT, Computer Science or related disciplines\n2 years\u2019 relevant experience of system support in MS Windows 7 and 10 PC including, Microsoft Outlook and Microsoft Office applications\nSolid experience and knowledge in PC and Microsoft products support\nPossess good sense of responsibilities, independent work, strong problem-solving and good communication skills\nShift duty is required\n\nWe offer the right incumbent attractive remuneration package including 12 days annual leave, 5-day week, double pay, performance bonus, medical scheme, life insurance, travel allowance and education subsidy.\n\nInterested parties please send your full resume with reference no., recent and expected salary to: Human Resources Department, Asia Airfreight Terminal Co. Ltd., 10 Chun Ping Road, Hong Kong International Airport, Lantau, Hong Kong OR Fax to 2286 0374 OR Please click \u201cApply Now\u201d to submit your application.\n\nTo know more about AAT, please visit http://www.aat.com.hk\n\nWe are an equal opportunity employer and welcome applications from all qualified candidates. We will not be responsible for any disclosure or the loss of personal data during transmission. All personal data collected will be used for recruitment only. Information of unsuccessful candidates will be destroyed after 3 months from the date of application.", "employment_types": ["Full Time", "Permanent"], "selling_points": ["Degree or above in IT, CS & Computing Engineering", "Stable and professional team, friendly culture", "Competitive remuneration package"], "locations": ["Shatin Area"], "categories": ["Information Technology (IT)", "Application Specialist - Software", "Product Management / Business Analyst", "Technical / Functional Consulting"], "post_time": "2022-01-17T03:05:53Z", "salary": {"currency": null, "max": null, "min": null, "period": "monthly", "term": null}, "salary_visible": false, "title_keywords": ["analyst"], "responsibilities": ["hardware", "installation", "software", "it technical support"], "requirements": {"degrees": ["diploma holder"], "majors": ["related disciplines", "it", "computer science"], "languages": [], "language_level": [], "hard_skills": ["ms windows", "microsoft office", "problem-solving", "scheme", "outlook", "pc"], "soft_skills": ["communication skills", "problem-solving", "independent", "sense of responsibilities"], "languages_combined": []}, "experience_required": {"duration": ["2 years"], "field": ["system support", "relevant experience"]}}, {"job_id": "100003009052284", "location_code": "hk", "company": "RICOH HONG KONG LIMITED", "job_title": "Solutions Consultant, Business Process Automation", "description": "Responsible for defining, developing & supporting the sales process for technology and solutions with account teams. Engages in account transactions based on technical expertise required in specific deals/programs leveraging specialized knowledge base across multiple accounts. Focuses on area of technical expertise, e.g., specific products/areas within company\u2019s global business units. Responsible for technical consulting work with customers in selling and supporting company products, services and systems, or software. Provides technical support in sales presentations, product demonstrations, and customer training.\nThese jobs focus on selling to customers, typically through work that occurs outside HPE offices.\n\nManagement Level Definition:\n\nApplies\u00a0developed\u00a0subject matter knowledge to solve common and complex business issues within established guidelines and recommends appropriate alternatives. Works on problems of diverse complexity and scope. May act as a team or project leader providing direction to team activities and facilitates information validation and team decision making process. Exercises independent judgment within generally defined policies and practices to identify and select a solution. Ability to handle most unique situations. May seek advice in order to make decisions on complex business issues.\n\nResponsibilities\n\nParticipates in deep-dive discussions and gathers information about customer technical needs and assesses customer's current IT infrastructure and translates the technical view into the implementation view to architect an overall technical solution.\u00a0 Additionally, defines technical alternatives and possible shortcomings to the proposed solution.\nCollaborates with account teams and other company organizations in developing and communicating key value propositions and negotiation points for a specific product set and technology.\nDelivers compelling and convincing presentations addressing specific requirements and expectations; effectively links the technical features and functions of company\u00b4s solutions with tangible business benefits that meet customer challenges.\nProtects and expands HPE's footprint with the customer by leveraging new technologies, upgrades, and refreshes to the company's installed base.\u00a0 Develops strategies to counter likely competitive threats.\nResponsible for pipeline information to be updated and accurately reflect the area of responsibility to ensure nurturing of all deals and constant movement of opportunities to close.\nFacilitates smooth transition from sales to implementation by orienting the appropriate teams to the technical solution design and identifying related training needs.\n\nEducation and Experience\n\nBachelor\u2019s degree in engineering or from technical university.\n5-8 years of experience in technology industry with focus on technical consulting and solution selling.Knowledge and Skills\nDemonstrates deep technical skills in assigned area of specialization.\nGood knowledge of the company offerings, strategic initiatives, current trends, competitor products and strategies within area of responsibility.\nExcellent written and verbal communication skills and mastery over English and local languages\nDemonstrates excellent consultative selling techniques, including active listening, framing, white boarding, storytelling etc.\nKnowledge of company business, technical tools, and standard CRM systems and tools.\nWorking knowledge and usage of social media, blogging, and related information sharing technologies\nSolid knowledge of partner\u00b4s offerings and how to effectively access, engage, and collaborate with them\nKnowledge-based and experienced-based industry certifications strongly preferred\nSolid project management skills or experience, with excellent analytical and problem solving skills, including appropriate due diligence.\nStrong business and financial acumen, with an understanding of functional responsibilities of various customer business roles\nExperience participating in solution configurations and the creation of PoCs to meet customer requirements.", "employment_types": ["Full Time", "Permanent"], "selling_points": ["3 years solid experience on pre-sales", "Exp in Enterprise Content Management Solutions", "Provide technical support to sales team"], "locations": ["Kowloon Bay"], "categories": ["Information Technology (IT)", "Application Specialist - Software", "Product Management / Business Analyst", "Technical / Functional Consulting"], "post_time": "2022-01-17T02:39:02Z", "salary": {"currency": null, "max": null, "min": null, "period": "monthly", "term": null}, "salary_visible": false, "title_keywords": ["consultant"], "responsibilities": ["management", "software", "consulting", "it infrastructure", "technical support", "guidelines", "policies", "systems", "teams", "developing", "transactions", "presentations", "implementation", "providing direction"], "requirements": {"degrees": [], "majors": [], "languages": [], "language_level": [], "hard_skills": ["make", "focus", "presentations"], "soft_skills": ["independent", "negotiation", "responsible", "deep", "unique", "diverse", "focus", "decision making"], "languages_combined": []}, "experience_required": {"duration": [], "field": []}}, {"job_id": "100003009054960", "location_code": "hk", "company": "Hewlett-Packard HK SAR Limited", "job_title": "Presales Consultant, Technology Architect", "description": "Responsibilities\n\n\nProvide technical support and troubleshooting to end users on hardware, software and computer services\u00a0\nPerform maintenance, configuration and monitoring of IT equipment\nPerform management of hardware and software inventory\nAssist in IT documentation, process improvement and equipment procurement\nAssist in project support and perform ad hoc duties as assigned\nRequirements:\n\n\nDegree in Information Technology, Computer Science or related disciplines\nCCNA/CCNP/MCSE certificate holder will be an advantage\n2 years experience in IT Support\nHands on experience in O365 (Teams/SharePoint Online), Win10, Active Directory, VMWare/Hyper-V\nKnowledge in TCP/IP, Wi-Fi, Firewall, network infrastructure and security technology\nA self-motivated and organized individual with good problem solving skills and strong sense of responsibility\nAbility to work independently, flexibly and positively\nGood command in both spoken and written English and Chinese (Cantonese and Mandarin)\u00a0\nApplicants with less experience will be considered as IT Officer.\u00a0 Fresh graduates is also welcomed\nInterested parties please send your resume with your\u00a0current and expected salary\u00a0to email:\u00a0hrd @ win-hanverky.com.hk\u00a0or click \"APPLY NOW\".\u00a0The closing date for application is 17 February 2022.\u00a0All information collected will be kept in strict confidence and will be used for recruitment purpose only.", "employment_types": ["Full Time"], "selling_points": ["Fast-Growing Industry", "MNC Working Environment", "Fast-track Career Opportunity"], "locations": ["Tai Koo"], "categories": ["Information Technology (IT)", "Technical / Functional Consulting"], "post_time": "2022-01-17T15:16:32Z", "salary": {"currency": null, "max": null, "min": null, "period": "monthly", "term": null}, "salary_visible": false, "title_keywords": ["consultant"], "responsibilities": ["ad hoc duties", "management", "software", "maintenance", "technical support", "configuration", "inventory", "computer services", "monitoring", "troubleshooting", "hardware", "documentation", "it equipment"], "requirements": {"degrees": ["certificate", "degree"], "majors": ["related disciplines", "computer science", "information technology"], "languages": ["cantonese", "english", "chinese", "mandarin"], "language_level": ["good command"], "hard_skills": ["mcse", "o365", "hyper-v", "vmware", "active directory", "tcp", "wi-fi", "ccnp", "ccna", "ip", "firewall", "problem solving skills"], "soft_skills": ["organized", "self-motivated", "work independently", "sense of responsibility", "hands on", "problem solving skills", "active"], "languages_combined": [{"language": "cantonese", "language_level": ["good command"]}, {"language": "english", "language_level": ["good command"]}, {"language": "chinese", "language_level": ["good command"]}, {"language": "mandarin", "language_level": ["good command"]}]}, "experience_required": {"duration": ["2 years"], "field": ["it", "it support"]}}, {"job_id": "100003009054383", "location_code": "hk", "company": "Wellesley Associates Limited", "job_title": "Software Product Manager  - IoT / Smart Home - MNC", "description": "Our client is a start-up company of IoT/Smart Home. Currently they are expanding in Hong Kong and seeking for a high calibre to be responsible to oversee their product team.\u00a0The ideal candidate will be responsible for whole product development process including, pricing, go-to-market planning and strategies. You will collaborate with internal and external parties to develop our strategy for product launches and product positioning.\u00a0\n\nResponsibilities\n\nDrive internet services and solutions decisions through industry/technology trend, performance tracking and analysis of vertical and horizontal enterprise solutions\nDesign & execute product strategy to achieve product growth\nDevelop and execute go-to-market planning and strategies, identify key target customers for different solutions and derive and develop solutions messaging and positioning\nUnderstand customer needs and liaise with sales and products teams to solve challenges of enterprises and penetrate solutions into the market\nDesign customer experience from consultancy, onboarding, delivery and post-sales stages\nBuild and develop the partner relationship management\nConduct product briefing/training session to support sales team & pre-sales consultant team\n\nQualifications\n\nBachelor's degree in computer science, Engineering/IT\n5+ years' experience in IoT, Smart Home or wearables\u00a0\nHands-on experience the formulation and implementation of product plan is a MUST\nKnowledge and hands-on working experience of Agile, Scrum and Kanban or related project management frameworks\u00a0\nStrong understanding in cloud service, embedded systems or mobile app development is preferred\u00a0\nExcellent communication and organizational skills with great attention to detail.\nGood command of spoken and written English, Cantonese and Mandarin\u00a0\nIf you would like to apply for this role or find out more, please contact\u00a0Boris LAW\u00a0on 2847 9960 or apply online with your latest CV in word format with expected salary, quoting the job role \u2013 Product Manager. Kindly note that only shortlisted candidates will be notified.", "employment_types": ["Full Time"], "selling_points": ["MNC", "IoT, Smart Home or wearables", "Agile and Scrum"], "locations": ["Not Specified"], "categories": ["Information Technology (IT)", "IT Project Management / Team Lead", "Product Management / Business Analyst", "Technical / Functional Consulting"], "post_time": "2022-01-17T09:19:29Z", "salary": {"currency": null, "max": null, "min": null, "period": "monthly", "term": null}, "salary_visible": false, "title_keywords": ["product manager"], "responsibilities": ["collaborate with", "understand customer needs", "internal and external parties", "design", "communication", "plan", "liaise with", "mobile app", "internet services", "teams", "implementation", "develop", "management", "contact", "tracking", "analysis", "systems", "project management", "sales team", "planning"], "requirements": {"degrees": ["degree", "bachelor"], "majors": ["it", "engineering", "computer science"], "languages": ["cantonese", "english", "mandarin"], "language_level": ["good command"], "hard_skills": ["agile", "analysis", "word", "project management", "mobile", "go"], "soft_skills": ["organizational skills", "agile", "responsible", "communication", "project management", "hands-on", "attention to detail", "ideal"], "languages_combined": [{"language": "cantonese", "language_level": ["good command"]}, {"language": "english", "language_level": ["good command"]}, {"language": "mandarin", "language_level": ["good command"]}]}, "experience_required": {"duration": ["5+ years"], "field": ["related", "project management", "design"]}}, {"job_id": "100003009054904", "location_code": "hk", "company": "Geek Plus International Company Limited", "job_title": "Korean Speaking Customer Care Executive (Overnight Shift Required)", "description": "About Geek+\nGeek+ leads the technology revolution, by applying advanced robotics and AI technologies to realize high-flexibility and intelligent logistics automation solution. We are always looking for people who can bring new perspectives and life experiences to our company. We understand the value of our people and we strive to constantly satisfy their needs.\n\nWe are looking for a\u00a0Customer Care Executive\u00a0to join our team. Are you someone who is driven by curiosity, craves a good challenge? Join us and be part of this exciting adventure!\n\nAbout the role:\n\nHandle Korea clients enquiries and complaints via various channels\nIdentify client needs and gather relervant information as much as possible\nCommunicate with internal departments for technical support\nMaintain high standard of customer services, keep records and prepare reports\nProvide status updates for all related parties in a timely manner\nRequirements:\n\nHigher Diploma with experience in technical support or customer services\nKorea speaking is a must\nNative in Cantonese, good written and spoken in English and Mandarin\nStrong communication and interpersonal skills, patient and detail-minded\nOvernight shift is required (with overnight allowance)\nWhat We Offer:\n\nFive-day work week\nOvernight shift allowance\nYoung and energetic work culture with regional exposure\nCozy office environment with\u00a0light refreshments\nDouble pay & attractive performance bonus\nMedical and dental benefits and insurance\n14 to 21 days Annual Leave\nConvenient work location: KCC\nIf your qualifications, experience, and aspirations match our requirements, please send your resume with your current and expected salary to us.\n\nAll information and materials submitted to Geek+ will remain strictly confidential and be treated for recruitment purposes only. Only short-listed candidates will be notified.", "employment_types": ["Full Time", "Permanent"], "selling_points": ["Exp in technical support and customer services", "Korean speaking is a must", "Overnight shift is required, with allowance"], "locations": ["Kwai Hing"], "categories": ["Sales, CS & Business Devpt", "Customer Service - Supervisor / Officer", "Engineering", "Engineering Project Management", "Information Technology (IT)", "Technical / Functional Consulting"], "post_time": "2022-01-17T13:23:36Z", "salary": {"currency": null, "max": null, "min": null, "period": "monthly", "term": null}, "salary_visible": false, "title_keywords": ["executive"], "responsibilities": ["communicate with", "robotics", "technical support", "a timely manner", "customer services", "communication", "maintain", "logistics", "prepare reports"], "requirements": {"degrees": ["diploma"], "majors": [], "languages": ["cantonese", "english", "mandarin"], "language_level": ["native", "good"], "hard_skills": ["ai"], "soft_skills": ["detail-minded", "advanced", "timely", "communication and interpersonal skills", "patient", "driven"], "languages_combined": [{"language": "cantonese", "language_level": ["native", "good"]}, {"language": "english", "language_level": ["good"]}, {"language": "mandarin", "language_level": ["good"]}]}, "experience_required": {"duration": [], "field": ["customer services"]}}, {"job_id": "100003009053507", "location_code": "hk", "company": "The French Chamber of Commerce and Industry in HK", "job_title": "Functional Consultant", "description": "Business Analyst - Commerce - Hong Kong\n\nA MNC client on commerce side is now hiring a high calibre Business Analyst to join their team. The ideal candidate would have prior project experience around ERP system implementation/enhancement.\n\nResponsibilities:\n\nYou will support operations and functional teams to define problems or desired outcomes, determine required information, synthesize findings, and recommend action.\nYou will work closely with the IT application team throughout the system development life cycle to deliver product features and solutions.\nYou will also understand the business objectives and rationales behind high-level product features, analyse and translate them into detailed user project specifications and system configuration requirements.\n\nRequirements:\n\nExperienced in Agile/Scrum software development environment preferred\nExperienced in medium to large scale digital transformation and ERP implementation projects\nAnalytical thinking and strong communication skills\nExcellent communication skills in Cantonese and English\n\nPlease submit resume to jessie.rao@ambition.com.hk\n\nIf this job isn't quite right for you, but you know someone who would be great at this role, why not take advantage of our referral scheme? We offer HKD1000 in Apple gift cards for every referred candidate who we place in a role. Terms & Conditions Apply. https://www.ambition.com.hk/refer-a-friend", "employment_types": ["Full Time", "Permanent"], "selling_points": ["Logistics solution platform", "Customer Service", "Friendly working environment"], "locations": ["Central"], "categories": ["Information Technology (IT)", "Technical / Functional Consulting", "Transportation & Logistics", "Freight Forwarding", "Supply Chain"], "post_time": "2022-01-17T07:04:28Z", "salary": {"currency": null, "max": null, "min": null, "period": "monthly", "term": null}, "salary_visible": false, "title_keywords": ["consultant"], "responsibilities": ["configuration", "operations", "teams", "specifications", "analyse"], "requirements": {"degrees": [], "majors": [], "languages": ["cantonese", "english"], "language_level": ["excellent"], "hard_skills": ["agile", "erp", "scheme"], "soft_skills": ["communication skills", "agile"], "languages_combined": [{"language": "cantonese", "language_level": ["excellent"]}, {"language": "english", "language_level": ["excellent"]}]}, "experience_required": {"duration": [], "field": []}}, {"job_id": "100003009052004", "location_code": "hk", "company": "Giesecke & Devrient Asia Pacific Ltd", "job_title": "System Engineer / Software Support Engineer", "description": "Our client is a\u00a0software and collaborative platform provider, European leader in transportation management and global sourcing solutions.\u00a0You will work within the Customer Service team which is in charge of:\u00a0\n\nFunctional consulting:\n\nHandling software deployment projects for new and existing clients\n\nResearch, elaborate and provide functional / technical solutions regarding the customer needs\n\nAnimate analysis workshops with the customers\n\nAnalyze set-up and development requests\n\nWrite detailed functional specifications and associated test scenarios\n\nTest developments and fixes\n\nTrain key-users / end-users\n\nProvide product demonstrations, enquiries and RFQ follow-up\n\nProvide consulting service for potential customers\n\nProvide functional support and insights to the commercial team\n\nSupport the Product team to ensure the quality of the standard released versions of our applications\n\nCustomer support\n\n\nContribute to functional user support\n\nAnalyze and process enquiries of the active clients\n\nManaging the relationship with the active clients through a Web-based Hotline ticketing system\nRequirements:\n\n\nUniversity degree in Information Technology or Logistics\n\nAt least 2 years\u2019 experience in customer support / deployment of information system, ideally in the international logistics / supply chain field.\n\nExperience in working with retail and / or logistics customers in an international environment\n\nOracle knowledge and SQL mastery are a plus\n\nGood interpersonal and communication skills in both oral and written\u00a0English\n\nStrong analytical, problem solving and synthesis skills\n\nGood organization skills: ability to manage priorities and to take initiative\n\nFluent in English and Cantonese", "employment_types": ["Full Time", "Permanent"], "selling_points": ["Support and troubleshoot on products and solutions", "Communicate with software users and customer IT", "Software system deployment and configuration"], "locations": ["Causeway Bay"], "categories": ["Information Technology (IT)", "Application Specialist - Software", "Support", "Technical / Functional Consulting"], "post_time": "2022-01-17T01:48:38Z", "salary": {"currency": null, "max": null, "min": null, "period": "monthly", "term": null}, "salary_visible": false, "title_keywords": ["system engineer", "support engineer"], "responsibilities": ["management", "software", "consulting", "analysis", "quality", "communication", "customer service", "specifications", "logistics"], "requirements": {"degrees": ["university degree"], "majors": ["information technology"], "languages": ["cantonese", "english"], "language_level": ["fluent", "good"], "hard_skills": ["plus", "web", "animate", "analysis", "information system", "sql", "problem solving", "deployment", "workshops", "oracle"], "soft_skills": ["initiative", "communication skills", "oral", "collaborative", "problem solving", "customer service", "organization skills", "active", "interpersonal", "detailed"], "languages_combined": [{"language": "cantonese", "language_level": ["fluent"]}, {"language": "english", "language_level": ["fluent", "good"]}]}, "experience_required": {"duration": ["at least 2 years"], "field": ["supply chain", "retail", "logistics"]}}, {"job_id": "100003009051194", "location_code": "hk", "company": "Kingvisions Consultants Limited", "job_title": "Pre-sales Engineer/ Solution Consultant (Networking & Security)", "description": "Responsibilities\n\nWork with different internal teams to enhance business operations and process reengineering projects;\nDefine Business Process Reengineering scope and to-be process;\nDocumentation of process and workflows;\nAssist in\u00a0ad hoc tasks and other duties as required;\nPrepare training materials & documents and provide training to user department\n\nRequirements\n\nDegree or above in IT, CS and Computing Engineering or equivalent;\n3 years or above relevant experience in business analysis/project management role;\nWell-developed analytical and problem solving skills;\nExcellent interpersonal and communication skill;\nExcellent verbal and written skill in English and Chinese;\nDeep intellectual curiosity, detail-oriented and independently;\nExperience in SQL and programming skill will be an advantage;\nExperience in managing and delivering process improvement / re-engineering / project management;\nUnderstanding the operations in the Construction industry will be an advantage\n\nInterested parties please apply with a detailed resume stating expected salary and date of availability to the HR Manager through fax at 2833 5441 or e-mail by clicking \"APPLY NOW\".\n\nCompany Website:\u00a0https://xensetech.hk/\n\nAll personal data provided will be used strictly in accordance with our \u201cPersonal Information Collection Statement Pertaining to Recruitment\u201d, a copy of which is available upon written request to us by E-mail.", "employment_types": ["Full Time", "Permanent"], "selling_points": ["Join-in bonus provided!! Same as yr end bonus!!", "1-3 yrs in solution briefing, deploying & support", "Engineer experience also welcome!"], "locations": ["Wan Chai Area"], "categories": ["Information Technology (IT)", "Application Specialist - Network", "Network & System", "Technical / Functional Consulting"], "post_time": "2022-01-15T04:34:40Z", "salary": {"currency": "HKD", "max": 54999, "min": 25000, "period": "monthly", "term": null}, "salary_visible": true, "title_keywords": ["consultant", "sales engineer"], "responsibilities": ["provide training", "other duties", "operations", "teams", "ad hoc tasks", "business process", "documentation"], "requirements": {"degrees": ["degree or above"], "majors": ["it", "engineering"], "languages": ["english", "chinese"], "language_level": ["excellent"], "hard_skills": ["analysis", "sql", "project management", "programming", "problem solving skills"], "soft_skills": ["independently", "communication skill", "deep", "detail-oriented", "project management", "analytical and problem solving skills", "interpersonal"], "languages_combined": [{"language": "english", "language_level": ["excellent"]}, {"language": "chinese", "language_level": ["excellent"]}]}, "experience_required": {"duration": ["3 years"], "field": ["engineering", "sql", "project management", "relevant experience", "programming", "business analysis"]}}, {"job_id": "100003009052019", "location_code": "hk", "company": "Multisoft Limited", "job_title": "Helpdesk Engineer (IT Support Team)", "description": "Responsibilities\n\n\u00a0\u00a0\u00a0\u00a0\u00a0\u00a0\u00a0 Present and demonstrate IT solutions of leading brands to partners and users\n\u00a0\u00a0\u00a0\u00a0\u00a0\u00a0\u00a0 Partner with Sales team to develop business opportunities majority in enterprise network infrastructure solutions and manage presales cases closely\n\u00a0\u00a0\u00a0\u00a0\u00a0\u00a0\u00a0 Understand, analyze customer requirements by solution base selling approach to achieve business outcome\n\u00a0\u00a0\u00a0\u00a0\u00a0\u00a0\u00a0 Responsible for quality deliverables including technical proposal, solutions presentation and demonstration, proof of concept test (POC) and test report\n\u00a0\u00a0\u00a0\u00a0\u00a0\u00a0\u00a0 Good customer, vendor handling skills\n\u00a0\u00a0\u00a0\u00a0\u00a0\u00a0\u00a0 Provide deliverables for win-case with task list and high-level design as solution assurance for project implementation\n\n\u00a0Requirements\n\n\u00a0\u00a0\u00a0\u00a0\u00a0\u00a0\u00a0 Degree holder in Computer Science, Electronics, Information Engineering or related disciplines\n\u00a0\u00a0\u00a0\u00a0\u00a0\u00a0\u00a0 Cisco CCIE / CCNP / CCNA certified or equivalent.\n\u00a0\u00a0\u00a0\u00a0\u00a0\u00a0\u00a0 Have 2-3 years of experience in solution deploying and support in\u00a0Infrastructure and Networking\n\u00a0\u00a0\u00a0\u00a0\u00a0\u00a0\u00a0 Passionate in ICT technology and enthusiastic to serve as pioneer in learning advanced technology\n\u00a0\u00a0\u00a0\u00a0\u00a0\u00a0\u00a0 Good communication, interpersonal skills & team player.\n\u00a0\u00a0\u00a0\u00a0\u00a0\u00a0\u00a0 Good command of written and spoken English & Chinese.\n\u00a0\u00a0\u00a0\u00a0\u00a0\u00a0\u00a0 Self-motivated and interested to explore new technologies and solutions.", "employment_types": ["Full Time", "Permanent"], "selling_points": ["Fresh graduate welcome", "Good advancement opportunities", "On-the-job training will be provided"], "locations": ["Kwun Tong"], "categories": ["Information Technology (IT)", "Support", "Network & System", "Technical / Functional Consulting"], "post_time": "2022-01-17T01:51:46Z", "salary": {"currency": null, "max": null, "min": null, "period": "monthly", "term": null}, "salary_visible": false, "title_keywords": ["engineer", "it support"], "responsibilities": ["network infrastructure", "business opportunities", "quality", "implementation", "design", "develop", "sales team", "report"], "requirements": {"degrees": ["degree holder"], "majors": ["related disciplines", "engineering", "computer science"], "languages": ["english", "chinese"], "language_level": ["good command"], "hard_skills": ["ccnp", "ccna"], "soft_skills": ["passionate", "self-motivated", "advanced", "communication", "learning", "interpersonal skills", "enthusiastic", "team player"], "languages_combined": [{"language": "english", "language_level": ["good command"]}, {"language": "chinese", "language_level": ["good command"]}]}, "experience_required": {"duration": ["2-3 years"], "field": ["infrastructure"]}}, {"job_id": "100003009051561", "location_code": "hk", "company": "KOS International Limited", "job_title": "Account Manager (IT Solutions) - Microsoft Products focusing", "description": "The Job\n\nResponsible for Presales consultancy,\nDesign infrastructure and create technical specifications to fulfil client requirements, specializing in Cloud Service, Server & Storage (Nutanix, Inspur, Netapp) , HCI and Backup solution (NetApp),\nConduct system operation training for system administrator and users,\nWork closely with sales team at presenting solutions to customer,\n\u00a0Analyze users\u2019 requirements and develop detailed solutions,\nPresent new products and services to enhance current customer relationship,\nCollaborate with end users, vendors and internal management team to process new solutions.\n\nThe Person\n\nDegree holder of Computer Science, Computer Engineering or related disciplines,\nAt least 2 years\u2019 working experience in infrastructure or system design,\nHolder of Professional Certificates such as NetApp, Commvault, AWS, Nutanix or VMware is an advantage,\n\u00a0Project experience on public cloud, SaaS or Backup solution is preferable,\n\u00a0Excellent communication and negotiation skills,\n\u00a0Proficient in both spoken and written English and Chinese,\n\u00a0Self-motivated and strong analytical skills.\n\nApplicant please send us your full resume, stating the date of availability, present and expected salary.\n\nYour application and personal information will be treated as strictly confidential and used only for purposes of recruitment and selection.\n\nApplicants who are not invited to interview within 8 weeks may consider their applications unsuccessful. All personal data of unsuccessful candidates will be destroyed after 6 months.", "employment_types": ["Full Time", "Permanent"], "selling_points": ["International Working Environment", "5+ years of relevant experience", "Attractive Package, Microsoft Products Focusing"], "locations": ["Central & Western Area"], "categories": ["Information Technology (IT)", "Technical / Functional Consulting", "Sales, CS & Business Devpt", "Account Servicing", "Technical Sales / Sales Engineer"], "post_time": "2022-01-16T10:35:24Z", "salary": {"currency": null, "max": null, "min": null, "period": "monthly", "term": null}, "salary_visible": false, "title_keywords": ["account manager"], "responsibilities": ["collaborate with", "management team", "infrastructure", "design", "develop", "specifications", "sales team"], "requirements": {"degrees": ["degree holder"], "majors": ["related disciplines", "computer engineering", "computer science"], "languages": ["english", "chinese"], "language_level": ["proficient"], "hard_skills": ["system design", "vmware", "analytical skills", "aws"], "soft_skills": ["communication", "negotiation skills", "self-motivated", "analytical skills"], "languages_combined": [{"language": "english", "language_level": ["proficient"]}, {"language": "chinese", "language_level": ["proficient"]}]}, "experience_required": {"duration": ["at least 2 years"], "field": ["infrastructure", "system design"]}}, {"job_id": "100003009045759", "location_code": "hk", "company": "Kepro Solutions Limited", "job_title": "Consultant (IT Infrastructure)", "description": "About our client\n\nOur client is an international IT solution provider, specialized in Microsoft products, and they are looking for an Account Manager(IT Solution) with good knowledge of Microsoft products & solutions.\n\nAbout the role\n\nResponsible for maintaining relationships with clients and business development potential clients\nCommunicating and liaising with clients to identify and gather user's requirements\nManage business sales process by effective promotion, presentation, negotiation\nResponsible for negotiation and deal closing with clients\nWorking closely with IT teams(e.g., developers and presales ) to develop technical solutions\nReporting on pipeline and putting forward solutions on improving team and sales performance\n\nRequirements\n\nBachelor degree holder in Computer Science, Information Technology, Business Administration or related discipline\nMinimum 5 years working experience in IT sales, IT service delivery, IT consulting or relative sector\nPractical experience in key account management, consulting or solution sales to sizable organizations\nFamiliar with Microsoft products is a plus\nWith a track record on sales achievement or target fulfillment is a plus\nStrong in communication, negotiation, and interpersonal skills\nMotived, customer-orient person with good team spirit\nGood command of English and Chinese(Cantonese & Mandarin)\n\nClick \"Apply Now\" to apply for this position or call Harry Yau at +852 3180 4936 for a confidential discussion. All information collected will be kept in strict confidence and will be used for recruitment purposes only.", "employment_types": ["Full Time", "Permanent"], "selling_points": ["Pre-sales role in proposing high-value IT services", "Solid experience in infrastructure solution design", "Competitive remuneration package"], "locations": ["Kwun Tong"], "categories": ["Information Technology (IT)", "Hardware", "Application Specialist - Network", "Technical / Functional Consulting"], "post_time": "2022-01-15T03:49:31Z", "salary": {"currency": null, "max": null, "min": null, "period": "monthly", "term": null}, "salary_visible": false, "title_keywords": ["consultant"], "responsibilities": ["reporting", "management", "it service", "maintaining", "consulting", "sales performance", "fulfillment", "liaising with", "develop", "communication", "recruitment", "administration"], "requirements": {"degrees": ["bachelor degree holder"], "majors": ["business administration", "computer science", "information technology"], "languages": ["english", "mandarin"], "language_level": ["good command"], "hard_skills": ["plus"], "soft_skills": ["team spirit", "confidence", "negotiation", "responsible", "communication", "interpersonal skills", "presentation"], "languages_combined": [{"language": "english", "language_level": ["good command"]}, {"language": "mandarin", "language_level": ["good command"]}]}, "experience_required": {"duration": ["minimum 5 years"], "field": ["it sales", "it", "account management", "consulting"]}}, {"job_id": "100003009045757", "location_code": "hk", "company": "Karin Technology Holdings Limited", "job_title": "Pre-sales Technical Consultant", "description": "Relationship Account Manager, HKT Premier\n\nYour role\n\nPromote and provide one-stop shop quadplay products and services to HKT\u2019s Premier customers\nUnderstand customer needs and promote customized home automation solutions to VIP residential projects through face-to-face consultations in Hong Kong, provide the highest level of personalized customer care service to develop and maintain relationship with potential and existing premium customers\nLiaise with external parties on potential partnership and identify business; Work closely with top tier architects, interior designers, contractors and IT managers and other internal & external professions to ensure project completion\nProject management in project schedule, cost, cash flow and profitability\nShift duty is required\n\nTo succeed in this role\n\nDiploma or above\nAt least 5 years related business development experience in consultancies, design & building firms, and contractors. Knowledge of design and maintenance of automation control systems is a must.\nExperience of High-end Home Theatre & Hi-Fi System business is a plus\nKnowledge of networking is preferable\nStrong network and contacts in residential projects\nPositive and customer oriented manner\nGood communication, negotiation and interpersonal skill\n\nWe offer you\n\nORSO/MPF retirement scheme\n16\u00a0days annual leave\nMedical and hospitalization insurance with dependent\nFull-paid sick leave\nExclusive staff discount plan and sales offer(i.e. CSL,1010,Now TV, nevigator and more)\nPre-sales on new product / service\nMarriage and compassionate leave\nSponsorship of external study\n\nApplication method\u00a0\n\nI want to make an interview appointment:\u00a06029 4292\u00a0\u00a0https://bit.ly/3tidcUa\u00a0\n\nEnquiry hotline:\u00a02888 1129\u00a0\n\nEmail:\u00a0career-consumer@pccw.com\u00a0", "employment_types": ["Full Time", "Permanent"], "selling_points": ["Provide technical support to channel partners", "Create internal design configuration documentation", "Pre-sales experience in ICT Infrastructure product"], "locations": ["Kwun Tong"], "categories": ["Information Technology (IT)", "Support", "Network & System", "Technical / Functional Consulting"], "post_time": "2022-01-15T03:49:30Z", "salary": {"currency": null, "max": null, "min": null, "period": "monthly", "term": null}, "salary_visible": false, "title_keywords": ["consultant", "sales"], "responsibilities": ["understand customer needs", "cost", "control", "maintenance", "external parties", "systems", "design", "develop", "communication", "project management", "cash flow", "maintain", "schedule", "liaise with"], "requirements": {"degrees": ["diploma or above"], "majors": [], "languages": [], "language_level": [], "hard_skills": ["project management", "plus", "maintenance"], "soft_skills": ["negotiation", "interpersonal skill", "communication", "project management", "positive"], "languages_combined": []}, "experience_required": {"duration": ["at least 5 years"], "field": ["related", "business development", "design", "business"]}}, {"job_id": "100003009055000", "location_code": "hk", "company": "Smarthing Technology Co., Limited", "job_title": "Senior Technical Support Engineer", "description": "Responsibilities:\n\nImplementation of ERP, provide training, UAT, Report Design with Business Intelligence Tools\nCollect user requirements, analysis and preparation in related documents\nSupport customers on using the system and work with the team to troubleshoot the problem\nAssist in the system development life cycle\nHandle any ad-hoc projects as assigned\n\nRequirements:\n\nDegree holder in Information Systems, Computing Science, Finance, Business Management or related disciplines\nFamiliar with ERP development or vendor experience is a definite advantage\nKnowledge in the financial systems, reporting tools, project management, database management or VBA will be an advantage\nExcellent communication, interpersonal skills and detail-minded\nProficient in both spoken and written English and Chinese (Cantonese & Mandarin are included)\nFresh graduates will be also considered\n\nInterested parties please apply with full resume stating availability, current and expected salaries by clicking \"APPLY NOW\".\n\nWe are an equal opportunity employer and welcome applications from qualified candidates.\u00a0 All information provided will be treated in strict confidence by authorized personnel and will be used only for recruitment related purpose.\u00a0 Applicants who do not hear from us within 6 weeks may consider their application unsuccessful.\u00a0 All personal data of unsuccessful applications will be destroyed after 6 months.\u00a0", "employment_types": ["Full Time"], "selling_points": ["At least 3-years or more technical support working", "Degree in Telecom, Computer Science/", "Telecom technologies"], "locations": ["Wan Chai"], "categories": ["Information Technology (IT)", "Support", "Network & System", "Technical / Functional Consulting"], "post_time": "2022-01-17T16:22:54Z", "salary": {"currency": null, "max": null, "min": null, "period": "monthly", "term": null}, "salary_visible": false, "title_keywords": ["technical support engineer"], "responsibilities": ["provide training", "uat", "related documents", "analysis", "implementation", "design", "troubleshoot", "ad-hoc projects", "report"], "requirements": {"degrees": ["degree holder"], "majors": ["finance", "science", "related disciplines", "business"], "languages": ["cantonese", "english", "chinese", "mandarin"], "language_level": ["proficient"], "hard_skills": ["business management", "vba", "vendor", "erp", "project management"], "soft_skills": ["communication", "project management", "detail-minded", "interpersonal skills"], "languages_combined": [{"language": "cantonese", "language_level": ["proficient"]}, {"language": "english", "language_level": ["proficient"]}, {"language": "chinese", "language_level": ["proficient"]}, {"language": "mandarin", "language_level": ["proficient"]}]}, "experience_required": {"duration": [], "field": ["development"]}}, {"job_id": "100003009052366", "location_code": "hk", "company": "Cartrack Technologies (China) Limited", "job_title": "\u8cc7\u8a0a\u79d1\u6280\u652f\u63f4\u6280\u8853\u54e1 IT Support (\u6b61\u8fce\u525b\u7562\u696d\u751f\u7533\u8acb)", "description": "Working Location: Ngau Tau Kok\nReporting to Senior Manager, Customer Facing IT, you will be responsible for managing Global / Regional customer integration and other customer solutions programs or projects implemented in Hong Kong.\nResponsibilities:\nPlan, formulate and execute the implementation of various customer IT programs\nUnderstand thoroughly from IT perspective of customer needs (including networking and infrastructure requirements) and work out feasible information system (IS) or system integration solutions\nWork closely with customers and stakeholders to manage deployment of agreed IT integration solutions in timely and quality manner\nWork closely with Sales Team on pre-sales support of IS costing estimation, customer requirements as well as post- sales support of technical issues resolution, performance monitoring and recommendation on continuous improvement\nCoordinate and work with global/regional or related internal stakeholders to offer and deploy appropriate IT solutions and e-tools to satisfy customer needs, including participation of UAT of new initiatives\nManage and liaise with external suppliers, but not limited to selection of vendors, contract negotiation, establishment of service levels, and performance monitoring, etc.\nLeverage digitalization to cope with business challenges as well as to enhance customer experience\nRequirements:\nDegree holder in Information Technology or related disciplines\nAt\u00a0least 5 years\u2019 customer facing IT experience, preferably in logistics/ transportation industry or multinational companies\nStrong\u00a0technical background in electronic data interchange (EDI) and Application Interface (API) technology\nExcellent communications skills and good knowledge on market trends of IT Technology\nCustomer focused and good influencing skills\nStrong project management and analytical skills\nEmbrace Design Thinking mindset that enable digital transformation\nProven track record of leading and managing digitalization projects\nGood command of spoken and written English and Chinese (Cantonese and Mandarin)\nProficient PC skills in software and applications\nApplication:\nClick \"Apply Now\". Indicate your current and expected salary, and availability.\u00a0 For more job opportunities, please visit our website at https://www.dpdhl.jobs/\n\n\n\nPersonal Information Collection Statement pertaining to Recruitment\n\nDHL Express (Hong Kong) Limited / DHL Aviation (Hong Kong) Limited (\u201cDHL\u201d) is committed to protecting and respecting your privacy in accordance with the Personal Data (Privacy) Ordinance of Hong Kong (the \u201cOrdinance\u201d) and DHL\u2019s Personal Data Protection Policy (the \u201cPolicy\u201d) at\u00a0https://www.dhl.com/hk-en/home/footer/local-privacy-notice.html\n\nBy proceeding to respond to this recruitment advertisement, you consent that we may use, retain, process, transfer or otherwise handle the personal data that we collect from you for recruitment,\u00a0 application processing, assessment and communication purposes (including any other purposes directly related thereto) in accordance with the Policy.\n\nAll personal data of unsuccessful applicants will be retained for future recruitment purposes for a period of not more than two (2) years after which such data will be destroyed.\n\nYou have the right at any time to make a data access or correction request concerning your personal data held by us. In addition, you may request us to delete your personal data that is no longer required for the relevant purposes which you have given consent. Should you wish to exercise such rights or have any question in relation to your personal data or the Policy, please contact our Human Resources Division in writing.", "employment_types": ["Full Time"], "selling_points": ["IT Support", "5 day work week / Bank Holiday", "Development opportunities"], "locations": ["Kowloon City Area"], "categories": ["Information Technology (IT)", "Technical / Functional Consulting"], "post_time": "2022-01-17T02:52:22Z", "salary": {"currency": null, "max": null, "min": null, "period": "monthly", "term": null}, "salary_visible": false, "title_keywords": ["it support"], "responsibilities": ["uat", "infrastructure", "quality", "implementation", "monitoring", "resolution", "coordinate", "sales team", "plan", "deploy", "liaise with"], "requirements": {"degrees": ["degree holder"], "majors": ["related disciplines", "information technology"], "languages": ["cantonese", "english", "chinese", "mandarin"], "language_level": ["good command"], "hard_skills": ["pc skills", "no", "html", "analytical skills", "project management", "make", "processing"], "soft_skills": ["focused", "analytical skills", "communication", "project management", "committed"], "languages_combined": [{"language": "cantonese", "language_level": ["good command"]}, {"language": "english", "language_level": ["good command"]}, {"language": "chinese", "language_level": ["good command"]}, {"language": "mandarin", "language_level": ["good command"]}]}, "experience_required": {"duration": ["at least 5 years"], "field": ["logistics", "it experience"]}}, {"job_id": "100003009053196", "location_code": "hk", "company": "Alpacian Limited", "job_title": "Associate Consultant (Information Security & Audit)", "description": "Candidate is invited to join our dynamic on-site support team in HK. He/She is expected take-up following supporting roles:\n\n\u00a0 \u00a0Responsibilities:\n\nTo be knowledgeable about the products and technologies.\nTo provide technical support to the corporate customer.\nProvide on-site support at the customer\u2019s premises for project installation and troubleshooting services.\n\nRequirements:\n\nAt least 3-years or more technical support working experience.\nDegree in Telecom, Computer Science/Computer Engineering or related engineering discipline.\nGood command of English; Fluent in both Cantonese and Mandarin\nDeep understanding of Cloud, Networking and Telecom technologies.\nWilling to learn new technologies\nGood troubleshooting skills, mature, responsible and self-motivated, be able to work independently.\nBe a good leader and mentor to teammates.", "employment_types": ["Full Time", "Permanent"], "selling_points": ["Flexible Working Hours", "Dental and Medical Insurance", "Education Allowance"], "locations": ["Quarry Bay"], "categories": ["Professional Services", "Business Consultancy", "Information Technology (IT)", "Security", "Technical / Functional Consulting"], "post_time": "2022-01-17T06:24:12Z", "salary": {"currency": null, "max": null, "min": null, "period": "monthly", "term": null}, "salary_visible": false, "title_keywords": ["associate", "consultant"], "responsibilities": ["technical support", "installation", "troubleshooting"], "requirements": {"degrees": ["degree"], "majors": ["computer engineering", "engineering", "computer science"], "languages": ["cantonese", "english", "mandarin"], "language_level": ["good command", "fluent"], "hard_skills": [], "soft_skills": ["self-motivated", "work independently", "responsible", "deep", "willing to learn", "troubleshooting", "mature"], "languages_combined": [{"language": "cantonese", "language_level": ["fluent"]}, {"language": "english", "language_level": ["good command"]}, {"language": "mandarin", "language_level": ["fluent"]}]}, "experience_required": {"duration": [], "field": []}}, {"job_id": "100003008304967", "location_code": "hk", "company": "Acton Consulting Limited", "job_title": "(Senior) System Engineer / Administrator - Servers", "description": "About our client\n\nOur client is an international IT solution provider, specialized in Microsoft products, and they are looking for an Account Manager(IT Solution) with good knowledge of Microsoft products & solutions.\n\nAbout the role\n\n\nResponsible for maintaining relationships with clients and business development potential clients\n\nCommunicating and liaising with clients to identify and gather user's requirements\n\nManage business sales process by effective promotion, presentation, negotiation\n\nResponsible for negotiation and deal closing with clients\n\nWorking closely with IT teams(e.g., developers and presales ) to develop technical solutions\n\nReporting on pipeline and putting forward solutions on improving team and sales performance\n\n\n\n\nRequirements\n\n\nBachelor degree holder in Computer Science, Information Technology, Business Administration or related discipline\n\nMinimum 5 years working experience in IT sales, IT service delivery, IT consulting or relative sector\n\nPractical experience in key account management, consulting or solution sales to sizable organizations\n\nFamiliar with Microsoft products is a plus\n\nWith a track record on sales achievement or target fulfillment is a plus\n\nStrong in communication, negotiation, and interpersonal skills\n\nMotived, customer-orient person with good team spirit\n\nGood command of English and Chinese(Cantonese & Mandarin)\n\n\nClick \"Apply Now\" to apply for this position or call Harry Yau at +852 3180 4936 for a confidential discussion. All information collected will be kept in strict confidence and will be used for recruitment purpose only.", "employment_types": ["Full Time", "Permanent", "Contract"], "selling_points": ["Wintel / Unix/ Linux", "Infrastructure or System Administration", "Storage, Network or Router"], "locations": ["Not Specified"], "categories": ["Information Technology (IT)", "Support", "Network & System", "Technical / Functional Consulting"], "post_time": "2022-01-17T12:51:07Z", "salary": {"currency": null, "max": null, "min": null, "period": "monthly", "term": null}, "salary_visible": false, "title_keywords": ["administrator", "system engineer"], "responsibilities": ["reporting", "management", "it service", "maintaining", "consulting", "sales performance", "fulfillment", "liaising with", "develop", "communication", "recruitment", "administration"], "requirements": {"degrees": ["bachelor degree holder"], "majors": ["business administration", "computer science", "information technology"], "languages": ["english", "mandarin"], "language_level": ["good command"], "hard_skills": ["plus"], "soft_skills": ["team spirit", "confidence", "negotiation", "responsible", "communication", "interpersonal skills", "presentation"], "languages_combined": [{"language": "english", "language_level": ["good command"]}, {"language": "mandarin", "language_level": ["good command"]}]}, "experience_required": {"duration": ["minimum 5 years"], "field": ["it sales", "it", "account management", "consulting"]}}, {"job_id": "100003009051970", "location_code": "hk", "company": "Aon Services Hong Kong Limited \u6021\u5b89\u670d\u52d9\u9999\u6e2f\u6709\u9650\u516c\u53f8", "job_title": "Senior Analyst, Business Platform Services", "description": "Our client is a\u00a0global software company providing innovative property management solutions and services in every real estate market. They are focused on providing our customers with superior products and outstanding customer service.\n\nResponsibilities\n\n\nPerform complex system and business process reviews and other service reviews to identify inefficient processes and make sound recommendations for client productivity gains\nUse your strong teaching skills to effectively train clients, manage software integrations, maintenance and updates in collaboration in clients\nResearch, analyze and resolve software functionality and reporting problems for clients\nCollaborate with management and peers to address complex client requests and resolve issues\nPerform data mapping, conversions and provide other support aligned to successful software deployment\nFocus on best practices and provide recommendations to clients regarding ancillary products and services that align with our client\u2019s business and operational needs and goals\n\n\nRequirement\n\n\nBachelor\u2019s degree in Business, Finance, Math, or Computer Science or other equivalent degree or experience in the property management industry\n3-5 years of experience in software or business process consulting, or equivalent consulting experience interacting with customers\n3-5 years of experience managing projects on accounting, business process, property management, or real estate software\nPrior experience working with ERP systems\nAwesome written and verbal communication skills\nConfidence and the ability to positively influence clients, peers and management\n\n\u00a0*Aberdeen,\u00a0Real Estate/Financial Industry, up to 35K\n\nif you are interested in this position or any other IT related opportunities, please send your CV to luke.he@manpowergrc.hk for more information.\u00a0", "employment_types": ["Full Time", "Permanent"], "selling_points": [], "locations": ["Quarry Bay"], "categories": ["Information Technology (IT)", "Product Management / Business Analyst", "Network & System", "Technical / Functional Consulting"], "post_time": "2022-01-17T01:52:55Z", "salary": {"currency": null, "max": null, "min": null, "period": "monthly", "term": null}, "salary_visible": false, "title_keywords": ["senior analyst"], "responsibilities": ["collaborate with", "reporting", "management", "software", "maintenance", "data", "business process", "provide recommendations"], "requirements": {"degrees": ["degree", "bachelor"], "majors": ["finance", "business", "computer science", "math"], "languages": [], "language_level": [], "hard_skills": ["erp systems", "math"], "soft_skills": ["interested in", "communication skills", "confidence"], "languages_combined": []}, "experience_required": {"duration": ["3-5 years"], "field": ["management", "consulting", "finance", "business", "accounting"]}}, {"job_id": "100003009054618", "location_code": "hk", "company": "RGF HR Agent Hong Kong Limited", "job_title": "ICT Solution Engineer  - Japanese Network Service Company", "description": "Our client, a Japanese\u00a0network services company, is looking for a suitable candidate to join their company:\n\n<Job Responsibilities>\n\n\u2022 Analyze client's requirements and applications to design a solution for meeting customers\u2019 objectives\n\u2022 Provide solution proposals and presentations, proof of concept, and technical documentation\n\u2022 Ensure good and timely communication among customers, implementation, and sales teams\n\u2022 Project management work such as project scheduling, tracking, and reporting, technical documents including system documentation, network diagrams, etc\n\u2022 Installation, configuration, system migration, and maintenance support of Routers / Switches, Firewall, Server and PC\n\u2022 Finish project on time with quality and cost control\n\n<Necessary Skill / Experience >\n\n\u2022 Degree holder in IT or related disciplines with a minimum of 3 years working experience in technical pre-sales or consultation support\n\u2022 Solid project management experience\n\u2022 Good command of spoken and written English and Cantonese. Knowledge of Mandarin or Japanese would be a plus\n\u2022 Hands-on experience with network equipment such as Router, LAN switch, and security appliances/products such as Firewall, IDS, IPS\n\u2022 Strong Microsoft Skills. Including Word, Excel, and Powerpoint\n\u2022 Knowledge and hands-on experience of Windows Server, VMware, Citrix virtualization technology, RPA technology, Public Cloud services are preferable.\n\nInterested parties please send us your resume in MS Word/PDF format in English.\u00a0All information received will be kept in strict confidential and only for recruitment purpose.", "employment_types": ["Full Time", "Permanent"], "selling_points": ["ICT Solution Engineer", "3 yrs+ related exp/Bachelor in IT/ related fields", "HK Island/ DP / Up to 35K"], "locations": ["Others"], "categories": ["Information Technology (IT)", "IT Project Management / Team Lead", "Support", "Technical / Functional Consulting"], "post_time": "2022-01-17T10:16:45Z", "salary": {"currency": null, "max": null, "min": null, "period": "monthly", "term": null}, "salary_visible": false, "title_keywords": ["engineer"], "responsibilities": ["reporting", "installation", "system documentation", "configuration", "maintenance support", "teams", "implementation", "presentations", "design", "communication", "project management", "quality", "project scheduling", "cost control", "documentation", "migration", "tracking"], "requirements": {"degrees": ["degree holder"], "majors": ["related disciplines", "it"], "languages": ["cantonese", "japanese", "english", "mandarin"], "language_level": ["good command"], "hard_skills": ["server", "plus", "excel", "virtualization technology", "vmware", "maintenance", "switch", "word", "presentations", "router", "powerpoint", "project management", "rpa", "citrix", "firewall", "documentation", "pc", "windows server"], "soft_skills": ["communication", "project management", "timely", "hands-on"], "languages_combined": [{"language": "cantonese", "language_level": ["good command"]}, {"language": "japanese", "language_level": []}, {"language": "english", "language_level": ["good command"]}, {"language": "mandarin", "language_level": []}]}, "experience_required": {"duration": ["minimum of 3 years"], "field": ["related", "project management", "it", "security"]}}, {"job_id": "100003009055312", "location_code": "hk", "company": "Valentino Hong Kong Limited", "job_title": "IT ASSISTANT", "description": "Responsibilities:\n\nPerform daily IT operation tasks, e.g. computer equipment installation, user account creation/deletion, problem handling, update IT inventory record, etc\nWork as a team member of IT helpdesk, provide IT support to end users across different countries in APAC region\nManage IT projects, set up IT systems in offices and retail stores across Asia\nCoordinate with internal parties and external vendors during IT projects and daily IT operations\nCreate IT tools training material to employees\n\nRequirements:\n\nUniversity graduate in computer related discipline\n1 year or above experience in managing IT projects and providing IT support to end users\nCandidates with experience in supporting IT infrastructure in retail stores are preferable\nGood communication skill, business oriented, flexible and enthusiastic in achieving excellence\nStrong documentation skill\nAbility to communicate effectively in English, Cantonese and Putonghua\n\nInterested parties please send your full resume with current & expected salary, date of availability to the Human Resources Department by clicking\u00a0\"APPLY NOW\"\n\n\nData collected will be used for recruitment purpose only.", "employment_types": ["Full Time", "Permanent"], "selling_points": ["Perform daily IT operation tasks", "Manage IT projects, set up IT systems", "University graduate, 1 year experience"], "locations": ["Aberdeen"], "categories": ["Information Technology (IT)", "Support", "Network & System", "Technical / Functional Consulting"], "post_time": "2022-01-18T02:08:45Z", "salary": {"currency": null, "max": null, "min": null, "period": "monthly", "term": null}, "salary_visible": false, "title_keywords": ["assistant"], "responsibilities": ["installation", "operations", "systems", "coordinate with", "it inventory", "internal parties"], "requirements": {"degrees": ["university graduate"], "majors": ["computer related"], "languages": ["cantonese", "putonghua", "english"], "language_level": [], "hard_skills": ["documentation"], "soft_skills": ["flexible", "communication skill", "enthusiastic"], "languages_combined": [{"language": "cantonese", "language_level": []}, {"language": "putonghua", "language_level": []}, {"language": "english", "language_level": []}]}, "experience_required": {"duration": ["1 year"], "field": ["infrastructure", "it", "retail", "it support"]}}, {"job_id": "100003009055252", "location_code": "hk", "company": "iCON Business Systems Ltd", "job_title": "Post-Sales Engineer / Consultant - Storage, Virtualization & HCI Solutions", "description": "Responsibilities:\n\nReports to Technical Manager\nBe assigned to complete technical tasks including Post-sales and Project implementation\nProvides professional services on planning and design, deployment and integration services to fulfill customer's\u00a0Requirements\nBe responsible for proposal writing and preparing project documentation\n\nRequirements:\n\nAttains Degree in IT or related disciplines\nAttains At least TWO YEAR technical experience and solid skillset in storage and virtualization solutions\nBe Certified of Storage, VMware and HCI Solutions\nBe capable of effective communication with different customers\nBe Willing to learn and be aggressive\nCan work independently\nBe self-motivated with clear company and self objectives\nSenior System Engineer with similar experience and skillset will be considered\n\nWe offer comprehensive remuneration and benefits, and excellent career opportunities to the right candidates. Interested parties please state clearly the position you are applying to with reference no. if any in the subject line and email us a full resume with CURRENT & EXPECTED SALARY.\n\nAll applications will be treated in the strictest confidence. We regret that only shortlisted candidates will be notified. Data collected will be used for recruitment purpose only.", "employment_types": ["Full Time", "Permanent"], "selling_points": ["Post-Sales Engineer", "Infrastructure, HCI, Virtualization Technologies", "Fresh Graduate welcome"], "locations": ["Cheung Sha Wan"], "categories": ["Information Technology (IT)", "Support", "Network & System", "Technical / Functional Consulting"], "post_time": "2022-01-18T01:55:30Z", "salary": {"currency": null, "max": null, "min": null, "period": "monthly", "term": null}, "salary_visible": false, "title_keywords": ["consultant", "sales engineer"], "responsibilities": ["implementation", "design", "planning", "reports", "project documentation"], "requirements": {"degrees": ["degree"], "majors": ["related disciplines", "it"], "languages": [], "language_level": [], "hard_skills": ["vmware"], "soft_skills": ["work independently", "self-motivated", "capable", "willing to learn", "communication", "clear"], "languages_combined": []}, "experience_required": {"duration": ["at least two year"], "field": []}}, {"job_id": "100003009055263", "location_code": "hk", "company": "Accenture Company Limited", "job_title": "Interactive \u2013 Digital Business Analyst", "description": "About Accenture\uff1a\n\nAccenture is a global professional services company with leading capabilities in digital, cloud and security. Combining unmatched experience and specialized skills across more than 40 industries, we offer Strategy and Consulting, Interactive, Technology and Operations services\u2014all powered by the world\u2019s largest network of Advanced Technology and Intelligent Operations centers. Our 506,000 people deliver on the promise of technology and human ingenuity every day, serving clients in more than 120 countries. We embrace the power of change to create value and shared success for our clients, people, shareholders, partners and communities.\n\nThe company has been operating in Greater China for over 30 years. Today, it has more than 17,000 people servicing clients across the region with offices in the cities including Beijing, Shanghai, Dalian, Chengdu, Guangzhou, Shenzhen, Hong Kong and Taipei. As a trusted Partner of Choice for digital transformation, Accenture is bringing more innovation to the business and technology ecosystems and helping Chinese enterprises and the government to embrace digitization and enhance global competitiveness to succeed in the new era.\n\nFor more information about Accenture, please visit its corporate homepage www.accenture.com and its Greater China homepage www.accenture.cn .\n\n\nAbout Accenture Interactive\uff1a\n\nAs one of the key services under Accenture, Accenture Interactive is in the business of Experience. We connect deep human and business insights with the possibilities of technology to define and deliver new realities. We're committed to helping clients design, build, communicate and run Experiences that make peoples' lives better, more productive and more meaningful. Visit http://www.accentureinteractive.com to find out more about us.\n\n\nKey Responsibilities\n\nWork in conjunction with different parties to conceptualize and propose solution approaches\u00a0\nDrive and challenge business units on their assumptions of how they will successfully execute the business plans\u00a0\nElicit requirements using interviews, document analysis, requirements workshops, surveys, business process descriptions, use cases, scenarios, and task and workflow analysis for major and minor projects\u00a0\nPlan and implement analytics to projects for different clients with tasks including but not limited to data tracking, tag management, data visualization, reporting & analysis and developing insights & recommendation\u00a0\nTransform data to insights for business development, strategies or optimization approaches\u00a0\nCreate high level and detailed level requirements specifications for major and minor projects\u00a0\nGenerate business\u00a0requirements\u00a0and use cases which documents business needs, rules and details\u00a0\nIdentify and document constraints, assumptions and risks associated with business requirements\u00a0\nDocument gaps in projects whilst providing potential solutions\u00a0\nPrepare business case\u00a0\nMaintain timely communications to business stakeholders throughout the project life cycle to ensure common understanding of the requirements and the impact to the business area\u00a0\n\nExperience, Attributes and Qualifications:\n\nDegree in\u00a0Information Management,\u00a0Computer Science, Information Technology, Business or related area\u00a0\n4-5+\u00a0years of relevant experience in Business Analyst and/or Digital Data Analytics\u00a0role, preferably in a consulting environment\nMinimum of 2 years of experience using, implementing, and / or customizing digital analytics and tag management solutions (e.g., Adobe, Google, Tealium, etc.)\nAgile experience and digital experience\u00a0preferred\u00a0(e.g. Digital Transformation,\u00a0eCommerce, Digital Marketing, O2O Digital Channels, etc.)\u00a0\nUnderstanding of design thinking\u00a0\nExperienced in executing implementation digital projects\u00a0\nStrong background in\u00a0digital\u00a0business analysis and/or system analysis\u00a0\nStrong analytical mind with excellent relationship management\u00a0\nExcellent verbal and written communication skills and the ability to interact professionally with diverse group of stakeholders\u00a0\nFluent Cantonese, English and Mandarin is a must\u00a0\nAble to legally work in\u00a0Hong Kong", "employment_types": ["Full Time", "Permanent"], "selling_points": ["4-5+ years of relevant experience", "Digital Transformation Projects", "IT Consulting"], "locations": ["Not Specified"], "categories": ["Information Technology (IT)", "IT Project Management / Team Lead", "Product Management / Business Analyst", "Technical / Functional Consulting"], "post_time": "2022-01-18T01:58:12Z", "salary": {"currency": null, "max": null, "min": null, "period": "monthly", "term": null}, "salary_visible": false, "title_keywords": ["business analyst"], "responsibilities": ["visualization", "consulting", "data", "operations", "business plans", "design", "communication", "business process", "maintain", "plan", "developing", "implementation", "reporting", "management", "specifications", "digital marketing", "executing", "tracking", "analysis", "business analysis"], "requirements": {"degrees": ["degree"], "majors": ["business", "computer science", "information technology"], "languages": ["cantonese", "english", "chinese", "mandarin"], "language_level": ["fluent"], "hard_skills": ["agile", "data analytics", "analysis", "make", "adobe", "data visualization", "workshops"], "soft_skills": ["productive", "communication skills", "advanced", "agile", "timely", "deep", "committed", "diverse", "analytical mind", "detailed"], "languages_combined": [{"language": "cantonese", "language_level": ["fluent"]}, {"language": "english", "language_level": []}, {"language": "chinese", "language_level": []}, {"language": "mandarin", "language_level": []}]}, "experience_required": {"duration": ["minimum of 2 years", "5+ years"], "field": ["management", "consulting", "design", "business", "relevant experience", "digital"]}}, {"job_id": "100003009055783", "location_code": "hk", "company": "Hong Kong Express Airways Limited", "job_title": "Assistant Manager, Infrastructure Operations", "description": "DEAR TALENT, YOUR MOVE!\n\nBeing the new rising airline since 2013, we are the Hong Kong\u2019s only Low Cost Carrier (LCC) offering you safe and flexible service options to Hong Kong and beyond.\n\nWe\u2019re on a mission to inspire you to be different, to shake things up, to inspire the spirit of adventure by bringing you to fascinating destinations that few others serve.\n\nSpread your wings and fly with us!\n\nWhat will you do?\u00a0\n\nLead a small team to maintain daily IT Infrastructure operation to support internal users within SLA under ITIL standard;\nSupport Security team to handle security events in IT infrastructure environment;\nSupport internal audit to assess different IT areas;\nDevelop and maintain formal guidelines, policies, and procedures to ensure the smooth operation;\nManage external vendor to provide technical support on corporate IT Infrastructure with emphasis on the internal network, servers, Microsoft office365 environment and cloud infrastructure;\nManage external vendor to provide technical support on Airport IT Infrastructure with emphasis on Express IP, AviNet, ACARS and EDI about Cargo / Crew / Passenger Information Filing;\nPlan, setup, lead and manage the IT Infrastructure and End-user Technology Strategy including disaster recovery planning;\nResearch on new technology, identify technology gaps, develop and deploy Infrastructure solutions;\nRemediate Risk & Vulnerability for Infrastructure and End-user computing;\nDrive the continuous improvement to all IT Infrastructure related services;\nDetermine how to leverage enabling technologies to implement innovative IT infrastructure solutions to support the business\nCoach and mentor team members;\nTravel occasionally for new station setup/support;\u00a0\nSupport ad-hoc duties as assigned.\n\nWe are a perfect match, if you are:\n\nUniversity graduate in Computer Technology or related discipline;\nMinimum 6 years of related working experiences in IT security with 2 years of supervisor post;\nStrong technical knowledge in all aspects of IT Infrastructure especially in Microsoft Office365, Fortinet, Azure/Alibaba cloud and End-user computing;\nSound Knowledgeable on SOC, DLP and SIEM;\nCertification on networking (such as CCNA, CCNP, CCIE);\nITILv3 Foundation Certification is a must;\nBasic knowledge of common information security management frameworks, such as ISO 27001, CobiT, ITIL, PCI DSS.\n\nYour Future Work Life?\n\nWork flexibly with staggered working hours and flexible workplace\nDress Casual and Smart everyday\nWork in a newly-designed office with open seating, stylish breakout areas, game room, gym and free coffee\u2026\nWork with a group of energetic and multicultural professionals (up to 50 nationalities!)\nHave great fun in Snack Friday, New Year Market, Fly with your Kids Day, Basketball Team\u2026\nHave your voice heard through Townhalls, Crew forums, CEO live sessions etc.\n\nWhat will you enjoy?\n\nFly anywhere we fly for free plus taxes during leisure with your friends and family\nSpecial privileges to buy duty free products\nCareer Express\n\n\nYou will be inspired by our core values.\nYou will be inspired by our vibrant, efficient and entrepreneurial spirit. Join our fun, collaborative and reliable team to ignite your dream!\n\n\nInterested? It\u2019s time to have YOUR MOVE!\nIf you're ready to embark your adventure, start by clicking the \u2018Apply now\u2019 and get on the plane to fly with HK Express!\u00a0", "employment_types": ["Full Time"], "selling_points": ["Flexible Working Practices, WFH, Travel Benefits", "Maintain daily IT infrastructure operations", "Microsoft Office365; Cloud Infrastructure"], "locations": ["Tung Chung"], "categories": ["Information Technology (IT)", "Hardware", "Network & System", "Technical / Functional Consulting"], "post_time": "2022-01-18T02:56:52Z", "salary": {"currency": null, "max": null, "min": null, "period": "monthly", "term": null}, "salary_visible": false, "title_keywords": ["operations", "assistant manager,"], "responsibilities": ["cost", "information security", "management", "it infrastructure", "internal audit", "recovery planning", "guidelines", "policies", "lead a small team", "technical support", "procedures", "infrastructure", "ad-hoc duties", "develop", "maintain", "plan", "deploy", "setup"], "requirements": {"degrees": ["university graduate"], "majors": [], "languages": [], "language_level": [], "hard_skills": ["small", "itil", "plus", "azure", "servers", "basic", "security management", "fun", "ccnp", "ccna", "airline", "vendor", "sla", "safe", "ip", "lcc"], "soft_skills": ["flexible", "efficient", "collaborative", "innovative", "smooth", "reliable", "ad-hoc duties", "energetic"], "languages_combined": []}, "experience_required": {"duration": ["2 years", "minimum 6 years"], "field": ["related", "it", "security"]}}, {"job_id": "100003009055176", "location_code": "hk", "company": "Win Hanverky Holdings Limited", "job_title": "IT Specialist", "description": "Responsibilities\n\n\nProvide technical support and troubleshooting to end users on hardware, software and computer services\u00a0\nPerform maintenance, configuration and monitoring of IT equipment\nPerform management of hardware and software inventory\nAssist in IT documentation, process improvement and equipment procurement\nAssist in project support and perform ad hoc duties as assigned\nRequirements:\n\n\nDegree in Information Technology, Computer Science or related disciplines\nCCNA/CCNP/MCSE certificate holder will be an advantage\n2 years experience in IT Support\nHands on experience in O365 (Teams/SharePoint Online), Win10, Active Directory, VMWare/Hyper-V\nKnowledge in TCP/IP, Wi-Fi, Firewall, network infrastructure and security technology\nA self-motivated and organized individual with good problem solving skills and strong sense of responsibility\nAbility to work independently, flexibly and positively\nGood command in both spoken and written English and Chinese (Cantonese and Mandarin)\u00a0\nApplicants with less experience will be considered as IT Officer.\u00a0 Fresh graduates is also welcomed\nInterested parties please send your resume with your\u00a0current and expected salary\u00a0to email:\u00a0hrd @ win-hanverky.com.hk\u00a0or click \"APPLY NOW\".\u00a0The closing date for application is 17 February 2022.\u00a0All information collected will be kept in strict confidence and will be used for recruitment purpose only.", "employment_types": ["Full Time", "Permanent"], "selling_points": [], "locations": ["Lai Chi Kok"], "categories": ["Information Technology (IT)", "Hardware", "Technical / Functional Consulting", "Others"], "post_time": "2022-01-18T01:38:51Z", "salary": {"currency": null, "max": null, "min": null, "period": "monthly", "term": null}, "salary_visible": false, "title_keywords": ["it specialist"], "responsibilities": ["ad hoc duties", "management", "software", "maintenance", "technical support", "configuration", "inventory", "computer services", "monitoring", "troubleshooting", "hardware", "documentation", "it equipment"], "requirements": {"degrees": ["certificate", "degree"], "majors": ["related disciplines", "computer science", "information technology"], "languages": ["cantonese", "english", "chinese", "mandarin"], "language_level": ["good command"], "hard_skills": ["mcse", "o365", "hyper-v", "vmware", "active directory", "tcp", "wi-fi", "ccnp", "ccna", "ip", "firewall", "problem solving skills"], "soft_skills": ["organized", "self-motivated", "work independently", "sense of responsibility", "hands on", "problem solving skills", "active"], "languages_combined": [{"language": "cantonese", "language_level": ["good command"]}, {"language": "english", "language_level": ["good command"]}, {"language": "chinese", "language_level": ["good command"]}, {"language": "mandarin", "language_level": ["good command"]}]}, "experience_required": {"duration": ["2 years"], "field": ["it", "it support"]}}, {"job_id": "100003009055833", "location_code": "hk", "company": "Ambition", "job_title": "Business Analyst - Commerce - Hong Kong", "description": "Business Analyst - Commerce - Hong Kong\n\nA MNC client on commerce side is now hiring a high calibre Business Analyst to join their team. The ideal candidate would have prior project experience around ERP system implementation/enhancement.\n\nResponsibilities:\n\nYou will support operations and functional teams to define problems or desired outcomes, determine required information, synthesize findings, and recommend action.\nYou will work closely with the IT application team throughout the system development life cycle to deliver product features and solutions.\nYou will also understand the business objectives and rationales behind high-level product features, analyse and translate them into detailed user project specifications and system configuration requirements.\n\nRequirements:\n\nExperienced in Agile/Scrum software development environment preferred\nExperienced in medium to large scale digital transformation and ERP implementation projects\nAnalytical thinking and strong communication skills\nExcellent communication skills in Cantonese and English\n\nPlease submit resume to jessie.rao@ambition.com.hk\n\nIf this job isn't quite right for you, but you know someone who would be great at this role, why not take advantage of our referral scheme? We offer HKD1000 in Apple gift cards for every referred candidate who we place in a role. Terms & Conditions Apply. https://www.ambition.com.hk/refer-a-friend", "employment_types": ["Full Time", "Permanent"], "selling_points": ["Business Analyst", "Commerce", "Based in Hong Kong"], "locations": ["Not Specified"], "categories": ["Information Technology (IT)", "Application Specialist - Software", "Product Management / Business Analyst", "Technical / Functional Consulting"], "post_time": "2022-01-18T02:59:42Z", "salary": {"currency": "HKD", "max": 29999, "min": 25000, "period": "monthly", "term": null}, "salary_visible": true, "title_keywords": ["business analyst"], "responsibilities": ["configuration", "operations", "teams", "specifications", "analyse"], "requirements": {"degrees": [], "majors": [], "languages": ["cantonese", "english"], "language_level": ["excellent"], "hard_skills": ["agile", "erp", "scheme"], "soft_skills": ["communication skills", "agile"], "languages_combined": [{"language": "cantonese", "language_level": ["excellent"]}, {"language": "english", "language_level": ["excellent"]}]}, "experience_required": {"duration": [], "field": []}}, {"job_id": "100003009051663", "location_code": "hk", "company": "Nikoyo (HK) Ltd", "job_title": "Systems Engineer", "description": "The Job\n\nResponsible for Presales consultancy,\nDesign infrastructure and create technical specifications to fulfil client requirements, specializing in Cloud Service, Server & Storage (Nutanix, Inspur, Netapp) , HCI and Backup solution (NetApp),\nConduct system operation training for system administrator and users,\nWork closely with sales team at presenting solutions to customer,\n\u00a0Analyze users\u2019 requirements and develop detailed solutions,\nPresent new products and services to enhance current customer relationship,\nCollaborate with end users, vendors and internal management team to process new solutions.\n\nThe Person\n\nDegree holder of Computer Science, Computer Engineering or related disciplines,\nAt least 2 years\u2019 working experience in infrastructure or system design,\nHolder of Professional Certificates such as NetApp, Commvault, AWS, Nutanix or VMware is an advantage,\n\u00a0Project experience on public cloud, SaaS or Backup solution is preferable,\n\u00a0Excellent communication and negotiation skills,\n\u00a0Proficient in both spoken and written English and Chinese,\n\u00a0Self-motivated and strong analytical skills.\n\nApplicant please send us your full resume, stating the date of availability, present and expected salary.\n\nYour application and personal information will be treated as strictly confidential and used only for purposes of recruitment and selection.\n\nApplicants who are not invited to interview within 8 weeks may consider their applications unsuccessful. All personal data of unsuccessful candidates will be destroyed after 6 months.", "employment_types": ["Full Time"], "selling_points": [], "locations": ["Quarry Bay"], "categories": ["Information Technology (IT)", "Product Management / Business Analyst", "Application Specialist - Network", "Technical / Functional Consulting"], "post_time": "2022-01-16T21:50:35Z", "salary": {"currency": null, "max": null, "min": null, "period": "monthly", "term": null}, "salary_visible": false, "title_keywords": ["systems engineer"], "responsibilities": ["collaborate with", "management team", "infrastructure", "design", "develop", "specifications", "sales team"], "requirements": {"degrees": ["degree holder"], "majors": ["related disciplines", "computer engineering", "computer science"], "languages": ["english", "chinese"], "language_level": ["proficient"], "hard_skills": ["system design", "vmware", "analytical skills", "aws"], "soft_skills": ["communication", "negotiation skills", "self-motivated", "analytical skills"], "languages_combined": [{"language": "english", "language_level": ["proficient"]}, {"language": "chinese", "language_level": ["proficient"]}]}, "experience_required": {"duration": ["at least 2 years"], "field": ["infrastructure", "system design"]}}, {"job_id": "100003009055648", "location_code": "hk", "company": "HKT Consumer Group", "job_title": "Relationship Account Manager - HKT Premier", "description": "Relationship Account Manager, HKT Premier\n\nYour role\n\nPromote and provide one-stop shop quadplay products and services to HKT\u2019s Premier customers\nUnderstand customer needs and promote customized home automation solutions to VIP residential projects through face-to-face consultations in Hong Kong, provide the highest level of personalized customer care service to develop and maintain relationship with potential and existing premium customers\nLiaise with external parties on potential partnership and identify business; Work closely with top tier architects, interior designers, contractors and IT managers and other internal & external professions to ensure project completion\nProject management in project schedule, cost, cash flow and profitability\nShift duty is required\n\nTo succeed in this role\n\nDiploma or above\nAt least 5 years related business development experience in consultancies, design & building firms, and contractors. Knowledge of design and maintenance of automation control systems is a must.\nExperience of High-end Home Theatre & Hi-Fi System business is a plus\nKnowledge of networking is preferable\nStrong network and contacts in residential projects\nPositive and customer oriented manner\nGood communication, negotiation and interpersonal skill\n\nWe offer you\n\nORSO/MPF retirement scheme\n16\u00a0days annual leave\nMedical and hospitalization insurance with dependent\nFull-paid sick leave\nExclusive staff discount plan and sales offer(i.e. CSL,1010,Now TV, nevigator and more)\nPre-sales on new product / service\nMarriage and compassionate leave\nSponsorship of external study\n\nApplication method\u00a0\n\nI want to make an interview appointment:\u00a06029 4292\u00a0\u00a0https://bit.ly/3tidcUa\u00a0\n\nEnquiry hotline:\u00a02888 1129\u00a0\n\nEmail:\u00a0career-consumer@pccw.com\u00a0", "employment_types": ["Full Time"], "selling_points": [], "locations": ["Quarry Bay"], "categories": ["Information Technology (IT)", "Network & System", "Technical / Functional Consulting", "Mobile / Wireless Communications"], "post_time": "2022-01-18T02:49:57Z", "salary": {"currency": null, "max": null, "min": null, "period": "monthly", "term": null}, "salary_visible": false, "title_keywords": ["account manager"], "responsibilities": ["understand customer needs", "cost", "control", "maintenance", "external parties", "systems", "design", "develop", "communication", "project management", "cash flow", "maintain", "schedule", "liaise with"], "requirements": {"degrees": ["diploma or above"], "majors": [], "languages": [], "language_level": [], "hard_skills": ["project management", "plus", "maintenance"], "soft_skills": ["negotiation", "interpersonal skill", "communication", "project management", "positive"], "languages_combined": []}, "experience_required": {"duration": ["at least 5 years"], "field": ["related", "business development", "design", "business"]}}, {"job_id": "100003009055311", "location_code": "hk", "company": "Aim System Ltd", "job_title": "ERP Project Consultant", "description": "Responsibilities:\n\nImplementation of ERP, provide training, UAT, Report Design with Business Intelligence Tools\nCollect user requirements, analysis and preparation in related documents\nSupport customers on using the system and work with the team to troubleshoot the problem\nAssist in the system development life cycle\nHandle any ad-hoc projects as assigned\n\nRequirements:\n\nDegree holder in Information Systems, Computing Science, Finance, Business Management or related disciplines\nFamiliar with ERP development or vendor experience is a definite advantage\nKnowledge in the financial systems, reporting tools, project management, database management or VBA will be an advantage\nExcellent communication, interpersonal skills and detail-minded\nProficient in both spoken and written English and Chinese (Cantonese & Mandarin are included)\nFresh graduates will be also considered\n\nInterested parties please apply with full resume stating availability, current and expected salaries by clicking \"APPLY NOW\".\n\nWe are an equal opportunity employer and welcome applications from qualified candidates.\u00a0 All information provided will be treated in strict confidence by authorized personnel and will be used only for recruitment related purpose.\u00a0 Applicants who do not hear from us within 6 weeks may consider their application unsuccessful.\u00a0 All personal data of unsuccessful applications will be destroyed after 6 months.\u00a0", "employment_types": ["Full Time", "Permanent"], "selling_points": [], "locations": ["Central & Western Area"], "categories": ["Information Technology (IT)", "Application Specialist - Software", "Support", "Technical / Functional Consulting"], "post_time": "2022-01-18T02:08:30Z", "salary": {"currency": null, "max": null, "min": null, "period": "monthly", "term": null}, "salary_visible": false, "title_keywords": ["consultant"], "responsibilities": ["provide training", "uat", "related documents", "analysis", "implementation", "design", "troubleshoot", "ad-hoc projects", "report"], "requirements": {"degrees": ["degree holder"], "majors": ["finance", "science", "related disciplines", "business"], "languages": ["cantonese", "english", "chinese", "mandarin"], "language_level": ["proficient"], "hard_skills": ["business management", "vba", "vendor", "erp", "project management"], "soft_skills": ["communication", "project management", "detail-minded", "interpersonal skills"], "languages_combined": [{"language": "cantonese", "language_level": ["proficient"]}, {"language": "english", "language_level": ["proficient"]}, {"language": "chinese", "language_level": ["proficient"]}, {"language": "mandarin", "language_level": ["proficient"]}]}, "experience_required": {"duration": [], "field": ["development"]}}, {"job_id": "100003009056109", "location_code": "hk", "company": "DHL EXPRESS (HONG KONG) LIMITED", "job_title": "Program Manager, Customer Facing IT", "description": "Working Location: Ngau Tau Kok\nReporting to Senior Manager, Customer Facing IT, you will be responsible for managing Global / Regional customer integration and other customer solutions programs or projects implemented in Hong Kong.\nResponsibilities:\nPlan, formulate and execute the implementation of various customer IT programs\nUnderstand thoroughly from IT perspective of customer needs (including networking and infrastructure requirements) and work out feasible information system (IS) or system integration solutions\nWork closely with customers and stakeholders to manage deployment of agreed IT integration solutions in timely and quality manner\nWork closely with Sales Team on pre-sales support of IS costing estimation, customer requirements as well as post- sales support of technical issues resolution, performance monitoring and recommendation on continuous improvement\nCoordinate and work with global/regional or related internal stakeholders to offer and deploy appropriate IT solutions and e-tools to satisfy customer needs, including participation of UAT of new initiatives\nManage and liaise with external suppliers, but not limited to selection of vendors, contract negotiation, establishment of service levels, and performance monitoring, etc.\nLeverage digitalization to cope with business challenges as well as to enhance customer experience\nRequirements:\nDegree holder in Information Technology or related disciplines\nAt\u00a0least 5 years\u2019 customer facing IT experience, preferably in logistics/ transportation industry or multinational companies\nStrong\u00a0technical background in electronic data interchange (EDI) and Application Interface (API) technology\nExcellent communications skills and good knowledge on market trends of IT Technology\nCustomer focused and good influencing skills\nStrong project management and analytical skills\nEmbrace Design Thinking mindset that enable digital transformation\nProven track record of leading and managing digitalization projects\nGood command of spoken and written English and Chinese (Cantonese and Mandarin)\nProficient PC skills in software and applications\nApplication:\nClick \"Apply Now\". Indicate your current and expected salary, and availability.\u00a0 For more job opportunities, please visit our website at https://www.dpdhl.jobs/\n\n\n\nPersonal Information Collection Statement pertaining to Recruitment\n\nDHL Express (Hong Kong) Limited / DHL Aviation (Hong Kong) Limited (\u201cDHL\u201d) is committed to protecting and respecting your privacy in accordance with the Personal Data (Privacy) Ordinance of Hong Kong (the \u201cOrdinance\u201d) and DHL\u2019s Personal Data Protection Policy (the \u201cPolicy\u201d) at\u00a0https://www.dhl.com/hk-en/home/footer/local-privacy-notice.html\n\nBy proceeding to respond to this recruitment advertisement, you consent that we may use, retain, process, transfer or otherwise handle the personal data that we collect from you for recruitment,\u00a0 application processing, assessment and communication purposes (including any other purposes directly related thereto) in accordance with the Policy.\n\nAll personal data of unsuccessful applicants will be retained for future recruitment purposes for a period of not more than two (2) years after which such data will be destroyed.\n\nYou have the right at any time to make a data access or correction request concerning your personal data held by us. In addition, you may request us to delete your personal data that is no longer required for the relevant purposes which you have given consent. Should you wish to exercise such rights or have any question in relation to your personal data or the Policy, please contact our Human Resources Division in writing.", "employment_types": ["Full Time", "Permanent"], "selling_points": ["Manage and liaise with external suppliers", "Degree holder in Information Technology", "At least 5 years\u2019 customer facing IT experience"], "locations": ["Ngau Tau Kok"], "categories": ["Sales, CS & Business Devpt", "Customer Service - Manager", "Information Technology (IT)", "Technical / Functional Consulting", "Others"], "post_time": "2022-01-18T03:19:57Z", "salary": {"currency": null, "max": null, "min": null, "period": "monthly", "term": null}, "salary_visible": false, "title_keywords": ["manager"], "responsibilities": ["uat", "infrastructure", "quality", "implementation", "monitoring", "resolution", "coordinate", "sales team", "plan", "deploy", "liaise with"], "requirements": {"degrees": ["degree holder"], "majors": ["related disciplines", "information technology"], "languages": ["cantonese", "english", "chinese", "mandarin"], "language_level": ["good command"], "hard_skills": ["pc skills", "no", "html", "analytical skills", "project management", "make", "processing"], "soft_skills": ["focused", "analytical skills", "communication", "project management", "committed"], "languages_combined": [{"language": "cantonese", "language_level": ["good command"]}, {"language": "english", "language_level": ["good command"]}, {"language": "chinese", "language_level": ["good command"]}, {"language": "mandarin", "language_level": ["good command"]}]}, "experience_required": {"duration": ["at least 5 years"], "field": ["logistics", "it experience"]}}, {"job_id": "100003009055564", "location_code": "hk", "company": "KOS International Limited", "job_title": "Account Manager(IT Solutions) - Microsoft Products focusing", "description": "About our client\n\nOur client is an international IT solution provider, specialized in Microsoft products, and they are looking for an Account Manager(IT Solution) with good knowledge of Microsoft products & solutions.\n\nAbout the role\n\n\nResponsible for maintaining relationships with clients and business development potential clients\n\nCommunicating and liaising with clients to identify and gather user's requirements\n\nManage business sales process by effective promotion, presentation, negotiation\n\nResponsible for negotiation and deal closing with clients\n\nWorking closely with IT teams(e.g., developers and presales ) to develop technical solutions\n\nReporting on pipeline and putting forward solutions on improving team and sales performance\n\n\n\n\nRequirements\n\n\nBachelor degree holder in Computer Science, Information Technology, Business Administration or related discipline\n\nMinimum 5 years working experience in IT sales, IT service delivery, IT consulting or relative sector\n\nPractical experience in key account management, consulting or solution sales to sizable organizations\n\nFamiliar with Microsoft products is a plus\n\nWith a track record on sales achievement or target fulfillment is a plus\n\nStrong in communication, negotiation, and interpersonal skills\n\nMotived, customer-orient person with good team spirit\n\nGood command of English and Chinese(Cantonese & Mandarin)\n\n\nClick \"Apply Now\" to apply for this position or call Harry Yau at +852 3180 4936 for a confidential discussion. All information collected will be kept in strict confidence and will be used for recruitment purpose only.", "employment_types": ["Full Time", "Permanent"], "selling_points": ["International working environment", "5+ years of relevant experience", "Attractive Package, Microsoft Solutions"], "locations": ["Not Specified"], "categories": ["Information Technology (IT)", "Technical / Functional Consulting"], "post_time": "2022-01-18T02:43:41Z", "salary": {"currency": null, "max": null, "min": null, "period": "monthly", "term": null}, "salary_visible": false, "title_keywords": [], "responsibilities": ["reporting", "management", "it service", "maintaining", "consulting", "sales performance", "fulfillment", "liaising with", "develop", "communication", "recruitment", "administration"], "requirements": {"degrees": ["bachelor degree holder"], "majors": ["business administration", "computer science", "information technology"], "languages": ["english", "mandarin"], "language_level": ["good command"], "hard_skills": ["plus"], "soft_skills": ["team spirit", "confidence", "negotiation", "responsible", "communication", "interpersonal skills", "presentation"], "languages_combined": [{"language": "english", "language_level": ["good command"]}, {"language": "mandarin", "language_level": ["good command"]}]}, "experience_required": {"duration": ["minimum 5 years"], "field": ["it sales", "it", "account management", "consulting"]}}, {"job_id": "100003009055869", "location_code": "hk", "company": "Manpower Services (Hong Kong) Limited", "job_title": "IT Support (Real Estate/Financial Industry, 35K)", "description": "Our client is a\u00a0global software company providing innovative property management solutions and services in every real estate market. They are focused on providing our customers with superior products and outstanding customer service.\n\nResponsibilities\n\n\nPerform complex system and business process reviews and other service reviews to identify inefficient processes and make sound recommendations for client productivity gains\nUse your strong teaching skills to effectively train clients, manage software integrations, maintenance and updates in collaboration in clients\nResearch, analyze and resolve software functionality and reporting problems for clients\nCollaborate with management and peers to address complex client requests and resolve issues\nPerform data mapping, conversions and provide other support aligned to successful software deployment\nFocus on best practices and provide recommendations to clients regarding ancillary products and services that align with our client\u2019s business and operational needs and goals\n\n\nRequirement\n\n\nBachelor\u2019s degree in Business, Finance, Math, or Computer Science or other equivalent degree or experience in the property management industry\n3-5 years of experience in software or business process consulting, or equivalent consulting experience interacting with customers\n3-5 years of experience managing projects on accounting, business process, property management, or real estate software\nPrior experience working with ERP systems\nAwesome written and verbal communication skills\nConfidence and the ability to positively influence clients, peers and management\n\n\u00a0*Aberdeen,\u00a0Real Estate/Financial Industry, up to 35K\n\nif you are interested in this position or any other IT related opportunities, please send your CV to luke.he@manpowergrc.hk for more information.\u00a0", "employment_types": ["Permanent"], "selling_points": ["Real Estate / Financial Industry", "Business Analysis", "Project implementation"], "locations": ["Central"], "categories": ["Accounting", "Consulting", "Information Technology (IT)", "Network & System", "Technical / Functional Consulting"], "post_time": "2022-01-18T03:01:58Z", "salary": {"currency": null, "max": null, "min": null, "period": "monthly", "term": null}, "salary_visible": false, "title_keywords": ["it support"], "responsibilities": ["collaborate with", "reporting", "management", "software", "maintenance", "data", "business process", "provide recommendations"], "requirements": {"degrees": ["degree", "bachelor"], "majors": ["finance", "business", "computer science", "math"], "languages": [], "language_level": [], "hard_skills": ["erp systems", "math"], "soft_skills": ["interested in", "communication skills", "confidence"], "languages_combined": []}, "experience_required": {"duration": ["3-5 years"], "field": ["management", "consulting", "finance", "business", "accounting"]}}, {"job_id": "100003009055968", "location_code": "hk", "company": "CL Technical Services Ltd.", "job_title": "Network Engineer (over $40K, Shatin)", "description": "Job Duties:\n\nTo provide technical support on WAN/LAN environment with specific focus on Metro-Ethernet network,\u00a0core routers, network switches, firewall appliances and load balancers;\nTo liaise with users and vendors for requirement study, implementation and on-going support activities;\nTo participate in technical specification development and proposal evaluation for new projects / enhancements;\nTo prepare test plan and conduct acceptance test;\nTo install security patches and upgrade on various hardware platforms and software applications;\nTo perform administration tasks and backup job related to various network and server platforms;\nTo update technical documents and prepare operation manual\n\nJob Requirements:\n\nHigher Diploma or above in IT related discipline\nAt least have 4 years\u2019 experience in IT field\nAt least 2 years of experience in network infrastructure support/ administration and configuration in the WAN/LAN environment\nSound knowledge in dynamic routing adopted in WAN/LAN environment\nHands on experience in firewall products\nKnowledge in Network monitoring and management tools is preferred\nPossession of certifications of CCNA or similar qualification is preferred\nIndependent, proactive and able to work under pressure\nGood communication skills\nProficient in both spoken and written English and Cantonese.\n\n\nFor more job opportunity, please visit our website: www.clts.com\n\nThe personal information collected is strictly for recruitment purpose only.", "employment_types": ["Full Time"], "selling_points": ["5 days work", "medical", "Stable working environment"], "locations": ["Shatin Area"], "categories": ["Information Technology (IT)", "Application Specialist - Network", "Network & System", "Technical / Functional Consulting"], "post_time": "2022-01-18T03:10:20Z", "salary": {"currency": null, "max": null, "min": null, "period": "monthly", "term": null}, "salary_visible": false, "title_keywords": ["engineer"], "responsibilities": ["software", "technical support", "implementation", "hardware", "plan", "evaluation", "liaise with", "administration"], "requirements": {"degrees": ["higher diploma or above"], "majors": ["it"], "languages": ["cantonese", "english"], "language_level": ["proficient"], "hard_skills": ["infrastructure support", "ccna", "dynamic", "firewall", "wan"], "soft_skills": ["communication skills", "independent", "hands on", "dynamic", "proactive", "work under pressure"], "languages_combined": [{"language": "cantonese", "language_level": ["proficient"]}, {"language": "english", "language_level": ["proficient"]}]}, "experience_required": {"duration": ["4 years", "at least 2 years"], "field": ["infrastructure", "it", "administration"]}}, {"job_id": "100003009051751", "location_code": "hk", "company": "Pinpoint Asia Limited", "job_title": "SOC Security Operations Manager - Enterprise Security Hub", "description": "Our client, a leading large enterprise with a large CyberSecurity Center and SOC in Hong Kong, is looking for a SOC Manager to comply with their increasing Cyber Security defense need. Great exposure and scale to work with one of the most prominent financial institutions in the region.\n\nResponsibilities:\n\nLead the SOC Operations in Hong Kong to monitor potential risks, threats, and attacks.\nReview and manage security systems including security log, user behavior analytics, vulnerability scanning, security playbook automation.\nMonitor suspicious cloud-based user activities, potential hazardous actions, malware, etc.\nWork with the IT and security teams in performing system and network vulnerability scanning. Advice development teams and technology product owners on security to withstand known attack vectors and prevalent threats.\nWork with the development and operations team on integrating security control policies and instructions into the CASB architecture.\nWork with the business stakeholders for user requirements and enable CASH security controls on business SaaS.\n\nRequirements:\n\nAt least 10 years of hands-on technical experience in the Information Security and/or Cyber Security area.\nExperience with vulnerability assessments, environment scanning, security controls, etc.\nExperience with Security Data Analytics technology in SIEM, UEBA, ELK, and SOAR.\nExperience in building secure network infrastructure including Anti-DDoS, NG Firewall, IDS/IPS, WAF, Secure MTA, Load Balancer, Internet Proxy, DNS hosting, etc.\nExperience in performing malware analysis and using the sandbox for detailed investigation.\nHands-on experience on endpoint whitelisting, web isolation, and or MSS handling.\nFamiliar with network and infrastructure design to adopt security controls.\nSecurity Certificates in CISSP, CISM, CISA, or equivalent.\nExcellent communication skills in English.\nBachelor's Degree in Computer Science or related field from a reputable University.\n\nIf this outstanding opportunity sounds like your next career move, please send your resume in Word format to Danny Kwan at resume(at)pinpointasia(dot)com and put SOC Security Operations Manager - Enterprise Security Hub\u00a0in the subject header.\n\nData provided is for recruitment purposes only.", "employment_types": ["Full Time", "Permanent"], "selling_points": ["Large Security Center", "Sophisticated Technology", "SOC Operations"], "locations": ["Not Specified"], "categories": ["Information Technology (IT)", "IT Management", "Security", "Technical / Functional Consulting"], "post_time": "2022-01-17T00:14:13Z", "salary": {"currency": "HKD", "max": 89999, "min": 70000, "period": "monthly", "term": null}, "salary_visible": true, "title_keywords": ["operations manager"], "responsibilities": ["scanning", "control", "operations", "policies", "review", "monitor", "systems", "teams", "architecture"], "requirements": {"degrees": ["degree", "bachelor"], "majors": ["computer science"], "languages": ["english"], "language_level": ["excellent"], "hard_skills": ["dns", "web", "cyber security", "data analytics", "analysis", "word", "firewall"], "soft_skills": ["communication skills", "hands-on", "detailed"], "languages_combined": [{"language": "english", "language_level": ["excellent"]}]}, "experience_required": {"duration": ["at least 10 years"], "field": ["infrastructure", "security"]}}, {"job_id": "100003009056071", "location_code": "hk", "company": "Tata Consultancy Services Limited", "job_title": "Senior RPA Technial Support", "description": "Desired Competencies (Technical/Behavioral Competency)\n\n\nMust-Have:\n\nUniversity Degree in Computer Science, Information Systems or related disciplines.\nMinimum 5 years of IT experience on application support and development.\nExperience with one or more RPA technologies.\nSolid technical knowledge of Microsoft Visual Studio.\nNET (ASP.NET and C#.NET) and SQL server.\nSolid technical knowledge of Java with Mybatis framework, and MongoDB/SQLite.\nFamiliar with RESTful/WebSocket network API development.\nFamiliar with HTML and JavaScript development.\nFamiliar with Linux command and shell script.\nFluent spoken and good written in Cantonese and English.\n\nGood-to-Have:\n\nRPA technologies -Blue Prism is plus.\nDocker experience is plus.\nExperience with chat bot development is plus.\n\n\n\nRole descriptions / Expectations from the Role\n\nProduction support for RPA BOT, Symphony BOT, Deployment, onsite support\nProvides production support and maintenance, including incident, problem, monitoring for RPA BOT and deployment for the BOT\nWorks with development team and clients to resolve incidents by analysing log and process workflows; provides work around and long term fix\nFollow procedure to deploy package to production, and verify\nWork with Support Manager to generate production status report\nParticipate in proactive maintenance and improvement abilities in RPA\n\n\n", "employment_types": ["Full Time"], "selling_points": ["Minimum 5 years of IT experience.", "NET (ASP.NET and C#.NET) and SQL server", "Experience with one or more RPA technologies."], "locations": ["Others"], "categories": ["Information Technology (IT)", "Technical / Functional Consulting"], "post_time": "2022-01-18T03:14:51Z", "salary": {"currency": null, "max": null, "min": null, "period": "monthly", "term": null}, "salary_visible": false, "title_keywords": [], "responsibilities": ["maintenance", "monitoring", "systems", "visual", "deploy", "report"], "requirements": {"degrees": ["university degree"], "majors": ["related disciplines", "computer science"], "languages": ["cantonese", "english"], "language_level": ["good", "fluent"], "hard_skills": ["linux", "java", "plus", "maintenance", "html", "rpa", "sql", "javascript", "deployment", "server", "c#"], "soft_skills": ["proactive"], "languages_combined": [{"language": "cantonese", "language_level": ["good", "fluent"]}, {"language": "english", "language_level": ["good", "fluent"]}]}, "experience_required": {"duration": ["minimum 5 years"], "field": ["development", "it experience"]}}, {"job_id": "100003009055607", "location_code": "hk", "company": "AXA Hong Kong", "job_title": "Senior Manager, Core systems", "description": "Solution Delivery\n\n\nCoordinate with Release Management to plan systems deployment to production.\nManage a group of application specialists and consultants to perform application analysis, design, development (where applicable) and quality assurance activities of all IT projects assigned.\nManage and engage the vendors to build, integrate and deliver RLS.\nMonitor daily activities to ensure application solutions meet AXA's policies, standards and quality requirement.\n\nProject Management\n\n\nManage projects throughout the delivery life cycle aim at controlling the scope, schedule and cost for IT projects.\n\nPeople Management\n\n\nDevelop and manage the performance of the team to ensure knowledge retention for key platforms via proper resource planning and backup.\nDrive capability development of the team to build specialization in their responsible application domain area.\n\nVendor Management\n\n\nFacilitate discussions and help vendors understand business requirements and improve vendor performance.\nReview and approve deliverables to ensure quality assurance.\nOversee the delivery of trainings and knowledge transfer to the production support teams to ensure necessary knowledge is transferred.\nManage vendor resources to ensure a right mix of external vendors to support multiple IT projects running in parallel, achieve utilization goal and on/offshore work ratio target.\nDefine, monitor and track overall vendor and project performance against SLA and KPIs to ensure value achievement.\n\nPlanning and Budgeting\n\n\nWith strong business acumen, negotiate and liaise with business divisions to define project scope and planning during project initiation phases with clarity on business objectives and outcomes.\nDefine the project timeline for the implementation approaches.\nMonitor the project costs against the budget.\n\nBusiness Advisory\n\n\nHelp customers fully understand the value of the applications to the business. Provide inputs to business proposals to ensure technical contents are covered correctly.\n\nSolution Architecture\n\n\nReview, challenge and contribute to the Solution Architect's proposed solution architecture to ensure the architecture meets the demand of applications.\n\nExperience and qualifications:\n\n\nUniversity degree in Computer Science or related fields.\nMinimum 13 years' experience in IT solution delivery, with at least 5 years' experience in the insurance/financial services field.\n\nSkills\n\n\nExperience in managing teams of technical professionals to evaluate solution on technical suitability, especially implementation and future maintenance, according to business requirements.\nIn-depth understanding of Insurance solution delivery\nIn-depth formal system development experience, preferably in AS400 RPGILE system development, Individual Life products, operations, finance and actuarial functional knowledge.\nSolid experience in large scale project delivery involving multiple teams, applications from both AS400 and non-AS400 platforms, and transition of the application implementation and maintenance to Delivery Centre / Vendor.\nExcellent analytical and problem-solving skills.\nExcellent written and verbal English communication skills.\nWorking experience in Asia countries, with understandings of the country characteristics, cultures and work style, is an advantage", "employment_types": ["Full Time", "Permanent"], "selling_points": ["AS400", "Solution Delivery", "Project Management"], "locations": ["Not Specified"], "categories": ["Information Technology (IT)", "IT Project Management / Team Lead", "Product Management / Business Analyst", "Technical / Functional Consulting"], "post_time": "2022-01-18T02:47:16Z", "salary": {"currency": null, "max": null, "min": null, "period": "monthly", "term": null}, "salary_visible": false, "title_keywords": ["senior manager"], "responsibilities": ["budgeting", "operations", "budget", "quality", "design", "communication", "manage projects", "plan", "liaise with", "costs", "monitor", "teams", "implementation", "develop", "schedule", "kpis", "architecture", "management", "cost", "review", "coordinate with", "contents", "maintenance", "policies", "analysis", "systems", "evaluate", "project management", "insurance", "planning"], "requirements": {"degrees": ["university degree"], "majors": ["computer science"], "languages": ["english"], "language_level": ["excellent"], "hard_skills": ["maintenance", "analysis", "vendor", "project management", "goal", "sla", "deployment", "problem-solving skills", "acumen"], "soft_skills": ["communication skills", "responsible", "project management", "business acumen", "problem-solving skills"], "languages_combined": [{"language": "english", "language_level": ["excellent"]}]}, "experience_required": {"duration": ["minimum 13 years", "at least 5 years"], "field": ["maintenance", "finance", "system development", "business", "it", "financial services", "insurance"]}}, {"job_id": "100003009053302", "location_code": "hk", "company": "SmarTone Telecommunications Limited", "job_title": "Consultant, Cyber Risk & Security Practice", "description": "Responsibilities:\n\n\nPre-sales - assist in qualifying sales leads from a technical standpoint\nAssist with performing security assessments, such as ethical hacking (i.e. vulnerability assessments and penetration tests), security governance reviews, threat hunting and SOC monitoring\nDesigning and Testing of new IT security solutions\n\n\nRequirements:\n\n\nBachelor\u2019s Degree in Computer Science, Information Systems or similar field is required\n1-4+ years of recent and focused experience securing networks\nKnowledge of networking protocols and operations such as LAN, WAN, VPN and Cloud technologies\nKnowledge of network attacks, detections, and defenses\nStrong analytic skill and robust problem solver needing new challenges and growth\nAbility to work independently and handle multiple tasks concurrently\nSuperior verbal and written communication skills in English and Cantonese are mandatory\nHolder of CCNA, CISSP, CISA, NSE4+ or Any security related Certification are strongly desired\n\nInterested parties please apply with full resume stating present and expected salary by clicking \"Apply Now\" or visiting our website:\u00a0www.smartone.com/tc/about_us/careers/\n\nSmarTone is an equal-opportunity employer.\u00a0 All data supplied will be kept in strict confidence and will be used for employment related purpose.\u00a0 We may transfer such data to any agent, contractor or third party who provides services to us with respect to matters relating to your application. Only short-listed candidates will be contacted.\n\nYou are welcome to visit our website:\u00a0smartone.com\u00a0", "employment_types": ["Full Time", "Permanent"], "selling_points": ["Security & networking application & solutions", "Support pre-sales activities", "Passionate about Cybersecurity"], "locations": ["Ngau Tau Kok"], "categories": ["Information Technology (IT)", "Security", "Network & System", "Technical / Functional Consulting"], "post_time": "2022-01-17T06:43:34Z", "salary": {"currency": null, "max": null, "min": null, "period": "monthly", "term": null}, "salary_visible": false, "title_keywords": ["consultant"], "responsibilities": ["testing", "monitoring", "designing"], "requirements": {"degrees": ["degree", "bachelor"], "majors": ["computer science"], "languages": ["cantonese", "english"], "language_level": [], "hard_skills": ["wan", "ccna", "vpn"], "soft_skills": ["communication skills", "work independently", "problem solver", "focused", "robust", "handle multiple tasks", "superior"], "languages_combined": [{"language": "cantonese", "language_level": []}, {"language": "english", "language_level": []}]}, "experience_required": {"duration": ["4+ years"], "field": []}}, {"job_id": "100003009054749", "location_code": "hk", "company": "EAB Systems", "job_title": "Software Developers / Analyst Programmer / Software Engineer \u2013 React.js (ReactJS) / Flutter", "description": "\u00a0What we offer:\u00a0\n\nSalary and bonus base on your contribution to the company's success.\nStable environment for growth - personal and career\nMultinational experience and scope to grow\nYou have a voice to contribute building a better product, a better customer service & delivery, a better company and a better you!\u00a0\n\n\u00a0\nYour Activities:\u00a0\n\n\nBuild new applications using react.js / react.native / flutter\nDesign new applications / components / microservice\nEnhancing existing enterprise applications\nProvide technical advise on technical resolution\nWorking on our core front end components across our\u00a0Insurtech\u00a0Platform, with\u00a0a focus on creating beautiful front end experiences and a best-in-class user experience.\u00a0\nWork closely\u00a0with product team and\u00a0UX\u00a0/ UI\u00a0creative team\u00a0to translate designs into web\u00a0/ mobile apps\u00a0that maintain the\u00a0platform\u2019s unique identity.\u00a0\n\nCreate self-contained, reusable, and testable modules and components.\u00a0\n\nWrite tested, idiomatic, and documented JavaScript, HTML, and CSS.\u00a0\nDefine\u00a0/ Adopt\u00a0best practices & solutions to improve the design QA process and communicate web\u00a0/ mobile apps\u00a0UX best practices to\u00a0UX\u00a0/ UI\u00a0creative team.\nInternal and external multinational client projects\u00a0\n\n\u00a0Ideal profile:\u00a0\n\n\nSolid\u00a0hands-on\u00a0experience in\u00a0HTML and CSS and at least one\u00a0front-end\u00a0UI / front-end\u00a0framework\u00a0such as\u00a0React.js (ReactJS)\u00a0/\u00a0Flutter\u00a0etc.\u00a0\n\nSolid\u00a0hands-on\u00a0experience\u00a0in JavaScript, and preferably with exposure to TypeScript\u00a0\n\nGood\u00a0programming practice in responsive and mobile first design\u00a0\n\nExperience with common front-end development tools such as\u00a0Git, Sass,\u00a0Material-UI\u00a0and\u00a0Chrome Dev Tools\u00a0etc.\u00a0\n\nExperience in managing complex asynchronous operations like concurrent RESTful API integration using JavaScript Promise\u00a0\n\nMin 3 years of professional experience\u00a0\n\n\nNice to haves:\u00a0\n\n\nKnowledge of cross-browser compatibility\u00a0\nPassion\u00a0for /\u00a0Good sense of the UX\u00a0/\u00a0UI design\u00a0\nExperience in front-end testing tools and testing frameworks\u00a0\n\n\nSound interesting? If you think you have the best composition of the above, send us your resume and let's chat!\u00a0\n\n\nApplicants with more experience will be considered for the position of Senior Software Engineer or Senior Systems Analyst Equivalent. Fresh graduates will be considered for an entry level position.\n\nTo apply, press the Apply Now button below and send us your CV with your availability and current and expected salary.\n\nInformation you provide will be treated in strict confidence and will only be used for recruitment purposes.", "employment_types": ["Full Time", "Permanent"], "selling_points": ["Team Collaboration", "Emphasis on self and team growth", "Insurtech web & mobile app solution"], "locations": ["Kowloon Bay"], "categories": ["Information Technology (IT)", "Application Specialist - Software", "Software Development", "Technical / Functional Consulting"], "post_time": "2022-01-17T16:21:08Z", "salary": {"currency": "HKD", "max": 44999, "min": 25000, "period": "monthly", "term": null}, "salary_visible": true, "title_keywords": ["analyst programmer", "software engineer"], "responsibilities": [], "requirements": {"degrees": [], "majors": [], "languages": [], "language_level": [], "hard_skills": [], "soft_skills": [], "languages_combined": []}, "experience_required": {"duration": [], "field": []}}, {"job_id": "100003009054667", "location_code": "hk", "company": "OPM Systems Company Limited", "job_title": "Consultant", "description": "This role is part of the project team members to perform user requirement study and to propose solution, prototyping and development. He or she has to be able to work independently and collaborate with external vendors, clients and internal teams to deliver success.\n\n\nJobs Duties\nConsult clients on solutions to meet clients\u2019 requirement\nStrong communication skill to working with external vendor\nAble to advise and being recognized on portal design, prototyping and development\nSoftware configuration on collaboration software\nWorking with project team members and client for the system integration\nSoftware enhancement of self-developed applications software that base on java programming language (such as identity management software, CMS)\nJob Requirements\n\nDegree holder or above major in Computer Science or equivalent\nWith minimum 3 years of experience of portal design, development, CMS and collaboration\nExperience with both Windows and Linux platform\nExperience on systems analysis role\u00a0\nHand-on experience on portal software customization such as liferay, sharepoint etc\nStrong knowledge on HTML5, CSS, JavaScript, Tomcat, MariDB/MySQL, Java, JQuery, Ajax\nAble to manage different collaboration software for configuration/customization\nExcellent communication skills in both verbal and written English and Chinese\nAble to solve problems independently, work under pressure and challenges and having good interpersonal skills\nTeam player and self-motivated\n5-Day work week\nA variety of company activities and training provided", "employment_types": ["Full Time"], "selling_points": ["Customization of Collaboration Software", "HTML5, CSS, Tomcat, MariDB, PHP, Linux, JAVA", "RestAPI, API, JavaScript"], "locations": ["Not Specified"], "categories": ["Information Technology (IT)", "IT Project Management / Team Lead", "Network & System", "Technical / Functional Consulting"], "post_time": "2022-01-17T10:27:49Z", "salary": {"currency": null, "max": null, "min": null, "period": "monthly", "term": null}, "salary_visible": false, "title_keywords": ["consultant"], "responsibilities": ["management", "software", "configuration", "design", "communication"], "requirements": {"degrees": ["degree holder"], "majors": ["computer science"], "languages": ["english", "chinese"], "language_level": ["excellent"], "hard_skills": ["linux", "java", "analysis", "jquery", "javascript", "ajax", "css"], "soft_skills": ["communication skills", "self-motivated", "independently", "solve problems", "interpersonal skills", "team player", "work under pressure"], "languages_combined": [{"language": "english", "language_level": ["excellent"]}, {"language": "chinese", "language_level": ["excellent"]}]}, "experience_required": {"duration": ["minimum 3 years"], "field": ["development", "design"]}}, {"job_id": "100003009055236", "location_code": "hk", "company": "ORIENTAL HUMAN RESOURCES LIMITED", "job_title": "Systems Engineer / Junior Systems Engineer", "description": "Responsibilities:\n\nMaintain Multi-network Antivirus Management System\nMaintain SIEM / CDN Alerting System\nManage and Coordinate Security Incident Response and Investigation Process\nResearch and satisfy security related requirements\nON-JOB TRAINING: Hacking & Virus Forensic / Linux / Bash / Python / Windows / MacOS/ Proxmox / Docker / ESMC / KSC / SIEM / Graylog / Elasticsearch / IDS / AlientVault / Encryption / HAProxy / MySQL / Zabbix / etc\n\nRequirements:\n\nDegree / Higher Diploma in Computer Science or related disciplines\nAt least 3 years of IT working experience\nKnowledge of Networking, Web Application Security, Instruction Detection Systems, Penetration Testing, Network Vulnerability Scanners and Scripting Languages (e.g Windows and Linux Platform)\nExperience in Security Systems, including Firewalls, Anti-Virus Software, Authentication System, Log Management, etc\nDedicated, initiative and self-motivated with strong analytical skills and good reporting skills\nGood command of written and spoken Chinese and English\n\n\u00a0(Candidate with less experience will be considered as Junior Systems Engineer)\n\n\nApplication Method\u00a0\n\nWe offer 5-day work week, free shuttle bus, free parking and fringe benefits including medical scheme, discretionary bonus, public holidays together with career growth opportunities to the right candidate. \u00a0Interested parties, please send full resume with expected salary to ORIENTAL\u00a0HUMAN RESOURCES LIMITED\u00a0by clicking \"Apply now\" ;\u00a0or fax to 3600 1900 ( Please quote reference on the application letter )\n\nPersonal Information Collection Statement\n\nPersonal data collected will be treated in accordance with our Personal Data Policy and handled in strict confidence by authorized personnel for recruitment related purpose only.\n\non.cc", "employment_types": ["Full Time", "Permanent"], "selling_points": [], "locations": ["Tai Po Area"], "categories": ["Information Technology (IT)", "IT Auditing", "Security", "Technical / Functional Consulting"], "post_time": "2022-01-18T01:53:56Z", "salary": {"currency": null, "max": null, "min": null, "period": "monthly", "term": null}, "salary_visible": false, "title_keywords": ["systems engineer", "junior"], "responsibilities": ["coordinate", "management", "maintain", "investigation"], "requirements": {"degrees": ["diploma", "degree"], "majors": ["related disciplines", "computer science"], "languages": ["english", "chinese"], "language_level": ["good command"], "hard_skills": ["linux", "web application security", "scheme", "analytical skills"], "soft_skills": ["self-motivated", "initiative", "analytical skills"], "languages_combined": [{"language": "english", "language_level": ["good command"]}, {"language": "chinese", "language_level": ["good command"]}]}, "experience_required": {"duration": ["at least 3 years"], "field": ["management", "it", "security"]}}, {"job_id": "100003009055001", "location_code": "hk", "company": "Smarthing Technology Co., Limited", "job_title": "Technical Account Manager", "description": "This position will own the company\u2019s global telecom carrier projects and provide professional advice on Telecom Billing Solution and maintain Long-term relationships with Customers.\n\nResponsibilities:\n\nProvide professional advice on telecom billing solution to our existing and new potential customers\nDevelop good and maintain long-term relationships with existing customers\nParticipate in the project management of current customer projects.\nAbility to operate under pressure in a dynamic environment\nWork in a team and be of good influence to others\nAd hoc duties as assigned\n\nRequirements:\n\nUniversity graduate in IT/Engineering discipline\n3 year working experience in system integrator/telecom carriers or relevant experience\nDegree in IT, Computer Science/Engineering or business-related disciplines is preferred.\nOutgoing, detail-minded, good problem-solving skills and presentation skills\nGood interpersonal skills and communication skills, fluent in Chinese, English and Cantonese\nStrong self-motivation and able to work independently and according to schedule\nGood knowledge of cloud technologies, telecom technologies is advanced\n\nIf you are interested in this position, please apply online by submitting your latest CV in\u00a0Word format\u00a0including current & expected salary. Kindly note that only shortlisted candidates will be notified.", "employment_types": ["Full Time"], "selling_points": ["University graduate in IT/Engineering discipline", "global telecom carrier", "3 year working experience"], "locations": ["Wan Chai Area"], "categories": ["Information Technology (IT)", "Product Management / Business Analyst", "Network & System", "Technical / Functional Consulting"], "post_time": "2022-01-17T16:22:54Z", "salary": {"currency": null, "max": null, "min": null, "period": "monthly", "term": null}, "salary_visible": false, "title_keywords": ["account manager"], "responsibilities": ["ad hoc duties", "project management", "maintain", "develop"], "requirements": {"degrees": ["university graduate", "degree"], "majors": ["engineering", "related disciplines", "business", "it", "computer science"], "languages": ["cantonese", "english", "chinese"], "language_level": ["fluent", "good"], "hard_skills": ["problem-solving skills", "word"], "soft_skills": ["outgoing", "detail-minded", "communication skills", "work independently", "advanced", "interested in", "presentation skills", "self-motivation", "interpersonal skills", "problem-solving skills"], "languages_combined": [{"language": "cantonese", "language_level": ["fluent", "good"]}, {"language": "english", "language_level": ["fluent", "good"]}, {"language": "chinese", "language_level": ["fluent", "good"]}]}, "experience_required": {"duration": ["3 year"], "field": ["relevant experience"]}}, {"job_id": "100003009051054", "location_code": "hk", "company": "The Wharf Group", "job_title": "HRIS Project Manager", "description": "Responsibilities:\n\nOversee the project progress and planning on digitalization related projects across the Group\nCraft out the implementation plan on various stages and follow through the implementation status with team members according to agreed timeline, quality and budget\nCommercial terms review, budget control and project P&L management\nIdentify and analyze business processes and requirements, and manage all stages of development including system design, technical specifications, system integration, testing and deployment of applications, and maintenance\nEvaluate technical architectures and solutions, evaluate potential risks and issues with recommendations, and report progress to stakeholders and management\nEvaluate proof-of-concept and new technology/solutions to integrate with existing systems / future systems \u00a0\nProvide training and briefing sessions to users on deployed systems and applications\nPerform vendor and contract management and review vendors\u2019 system documentation\nIT liaison and advisory on system security on various applications\n\nRequirements:\n\nDegree holders in Information Technology, Computer Science, Engineering or related disciplines; preferably with PMP or equivalent qualifications\u00a0\nAt least 12 years\u2019 relevant experience in IT system design, development and management of core projects; including not less than 3 years project management experience on tier one human resources systems.\nCompetence in managing the whole SDLC process including gathering of requirements, analysis, development, UAT, production release and maintenance; plus\u00a0good knowledge of MySQL, MS SQL, VB.Net, Crystal Report, Java, ASP. Net, HTML and PHP\nExperience in SAP SuccessFactors is highly preferred\nExperience with Cloud Computing platform, Business Intelligence System, Data Analytics would be an added advantage\nStrong ability and proven track record in designing and implementing pragmatic solutions under complex business requirements\nMature, detail-minded with strong communication and problem solving skills\nGood command of spoken and written English and Chinese (Cantonese and Putonghua)\n\nWe work 5 days per week.\n\nInterested parties, please click \"APPLY NOW\" and attach with your application letter and full resume.\n\nFor further information of the Wharf Group, please visit our website: www.wharfholdings.com\u00a0", "employment_types": ["Full Time", "Permanent"], "selling_points": [], "locations": ["Tsim Sha Tsui"], "categories": ["Information Technology (IT)", "IT Project Management / Team Lead", "IT Management", "Technical / Functional Consulting"], "post_time": "2022-01-15T19:11:48Z", "salary": {"currency": null, "max": null, "min": null, "period": null, "term": null}, "salary_visible": false, "title_keywords": ["hris project manager"], "responsibilities": ["provide training", "budget", "quality", "plan", "budget control", "system documentation", "implementation", "project progress", "p&l", "testing", "report", "management", "review", "specifications", "maintenance", "systems", "contract management", "evaluate", "system design", "system security", "planning"], "requirements": {"degrees": ["degree"], "majors": ["related disciplines", "engineering", "computer science", "information technology"], "languages": ["cantonese", "putonghua", "english", "chinese"], "language_level": ["good command"], "hard_skills": ["plus", "java", "maintenance", "php", "sap", "data analytics", "analysis", "html", "project management", "sdlc", "system design", "problem solving skills", "pmp", "business intelligence", "ms sql"], "soft_skills": ["detail-minded", "mature", "communication", "project management", "problem solving skills"], "languages_combined": [{"language": "cantonese", "language_level": ["good command"]}, {"language": "putonghua", "language_level": ["good command"]}, {"language": "english", "language_level": ["good command"]}, {"language": "chinese", "language_level": ["good command"]}]}, "experience_required": {"duration": ["3 years", "at least 12 years"], "field": ["management", "development", "project management", "business", "relevant experience", "it system design", "human resources systems"]}}, {"job_id": "100003009049050", "location_code": "hk", "company": "Karin Solutions and Services Limited", "job_title": "Unified Communication Engineer/Assistant Unified Communication Engineer", "description": "Understand customer requirement\nTranslate business needs into technical requirements\nPrepare technical proposal and product BOM\nConduct presentation and Proof-of-Concept of proposed solutions\nProvide solution consultations to our customer\nBe a Voice of Customer to share insights and best practices\n\n\u00a0Drive successful project delivery activities, include:\n\nInitiate kickoff meetings\nBuild solution implementation roadmaps\nCollaborate with project delivery team\nEnsure successful execution of project plans\nTechnology area focus (one of the following), include:\nIP telephony solution (e.g. Cisco, Avaya\u2026..etc.)\nCustomer meeting service and solution (e.g. Zoom, Microsoft Teams, Webex Meeting, etc.)\n\nRequirements:\n\nUniversity graduate in Computer Science, Information Engineering, Electronics Engineering or related disciplines, with at least 2-year work experiences\nDemonstrate a good learning track record and experience in solution design or implementation in complex projects\nSelf-motivated and interested to explore new technologies and solutions\nOther latest technical knowledge in unified communication solution\nGood command of both written and spoken English and Chinese\nLess experienced candidate will be considered as Assistant Unified Communication Engineer\n\nWe offer a competitive remuneration package to the right candidate. Interested parties please send your full resume with\u00a0present and expected salary\u00a0by clicking 'Apply Now'.\n\nCompany Address: 9/F, The Whitney, 183 Wai Yip Street, Kwun Tong, Hong Kong\n\n(We are an Equal Opportunity Employer and personal data collected would be used for recruitment purpose only.)", "employment_types": ["Full Time", "Permanent"], "selling_points": ["Conduct presentation and Proof-of-Concept", "Prepare technical proposal and product BOM", "IP telephony solution (e.g. Cisco, Avaya)"], "locations": ["Kwun Tong"], "categories": ["Engineering", "Telecommunication / Wireless / Radio", "Information Technology (IT)", "Network & System", "Technical / Functional Consulting"], "post_time": "2022-01-14T08:06:38Z", "salary": {"currency": null, "max": null, "min": null, "period": "monthly", "term": null}, "salary_visible": false, "title_keywords": ["engineer", "assistant"], "responsibilities": ["collaborate with", "teams", "implementation", "design", "communication", "plans"], "requirements": {"degrees": ["university graduate"], "majors": ["related disciplines", "engineering", "computer science"], "languages": ["english", "chinese"], "language_level": ["good command"], "hard_skills": ["unified communication", "ip", "focus"], "soft_skills": ["self-motivated", "communication", "learning", "focus", "presentation"], "languages_combined": [{"language": "english", "language_level": ["good command"]}, {"language": "chinese", "language_level": ["good command"]}]}, "experience_required": {"duration": ["at least 2-year"], "field": ["related", "engineering", "design"]}}, {"job_id": "100003009053066", "location_code": "hk", "company": "Orient Overseas Container Line Ltd (OOCL)", "job_title": "IT Graduate Trainee Program", "description": "We are offering you:\n\nAn experience of advanced technologies and working modules\u00a0\nGlobal exposure to work on innovative projects\u00a0\nCoaching and training to solidify your skill set throughout the trainee program\u00a0\nClear career road map & career advancement\nYoung, energetic & friendly work environment\nWork-life balance, fringe benefits with medical/dental insurance coverage, double pay, discretionary bonus, free meal & shuttle bus service\n\nData Science Trainee Program\n\nBe curious and passionate in developing or enhancing machine learning and artificial intelligence algorithms\u00a0\nBring up your insights to dedicated projects with strong analytical and logical thinking\u00a0\nTransform your knowledge and ideas into enterprise solutions\u00a0\n\nTechnical Analyst Trainee Program\n\nLearn and apply the new technologies in building enterprise software systems\nBy offering job rotation, you will experience different IT areas such as Cloud Engineering, Data Analytics, Software Development, Infrastructure & Networking, Cyber Security, Development Operations (DevOps), etc\nExperience the latest working models - Agile development and pair programming\n\nBusiness Analyst Trainee Program\n\nProvide analysis to create requirement specifications for in-house enterprise application systems and recommend solutions for future business processes\u00a0\nPerform business/functional analysis, recommend solutions and create product requirement specifications for in-house enterprise application systems to drive business improvement changes\u00a0\nParticipate in system roll out planning, coordinate with global IT teams, and conduct training to world-wide end users\u00a0\nCollaborate with world-wide business users and global IT teams in system development, implementation planning, acceptance testing, user training and post-implementation review\u00a0\n\nOperations Analyst Trainee Program\n\nIdentify and interpret trends and patterns in datasets to locate influences through simulations, algorithms, and machine learning\u00a0\nGet involved in various data analytics tools, methodologies, reports, and dashboard design and implementation processes\u00a0\n\nWho\u00a0we are\u00a0looking for\n\nBachelor\u2019s degree or above in Computer Science, Information Engineering, Information Systems, Business Analytics, Data Science, Operations Research, Statistics, Mathematics, International Shipping, Operations Management, Global Supply Chain Management or related disciplines\u00a0\nNumerically sensitive, creative aptitude and highly adaptable in a multicultural environment\u00a0\nGood team player with excellent analytical, communication and presentation skills\u00a0\nEmbrace challenge, enjoy team collaboration and an open organization\u00a0\nEager to learn in a fast-paced and dynamic environment\u00a0\nPassionate in pursuing IT professionalism\n\nInterested parties, please submit your application letter together with detailed resume and copies of your latest transcript\u00a0by clicking \u201cApply Now\u201d.\n\n(Data collected will be used for recruitment purpose only.)", "employment_types": ["Full Time", "Permanent"], "selling_points": ["2-year Fresh Graduate Program", "Become global expertise and shipping profession", "Team collaboration and open organization"], "locations": ["Shatin Area"], "categories": ["Professional Services", "Business Analysis / Data Analysis", "Information Technology (IT)", "Application Specialist - Software", "Technical / Functional Consulting"], "post_time": "2022-01-17T05:33:28Z", "salary": {"currency": null, "max": null, "min": null, "period": "monthly", "term": null}, "salary_visible": false, "title_keywords": ["graduate trainee"], "responsibilities": [], "requirements": {"degrees": [], "majors": [], "languages": [], "language_level": [], "hard_skills": [], "soft_skills": ["advanced", "innovative", "clear", "friendly", "energetic"], "languages_combined": []}, "experience_required": {"duration": [], "field": []}}, {"job_id": "100003009050680", "location_code": "hk", "company": "Hutchison Telecommunications (Hong Kong) Limited", "job_title": "Senior Solution Consultant", "description": "Responsibilities:\n\n\nProvide pre-sales solution consultation to corporate customers\nUnderstand customer\u2019s business requirements and translate them into technical\u00a0requirements\nDesign solution and prepare technical proposal and tender responses\nConduct presentation and Proof-Of-Concept demonstration of proposed solutions\nSource solutions from external parties\nPerform ad-hoc projects if required\n\nRequirements:\n\n\n\nBachelor holder in\u00a0IT, Engineering, or related disciplines\nAt least 5 years working experience\n\u00a0Demonstrate a good track record and experience in solution design or implementation in IT&T projects\nSelf-motivated and interested to explore new technologies and solutions\n\u00a0Technical knowledge in network & system architecture, mobile, IoT, cloud, AI, application development, is a plus\nAbility to work in a fast paced and dynamic environment\nStrong interpersonal and presentation skills\nHighly organized, very effective with time management skills\nGood command of both written and spoken English and Chinese\nLess experienced candidate will be considered as Solution Consultant\nApart from competitive remuneration package and exciting opportunity for career development within the Group, we provide attractive employee benefits such as free company shuttle, free company SIM card and preferential SIM plan offers, comprehensive medical & insurance schemes, as well as full range of other employee well-being provisions.\u00a0\n\nInterested parties, please apply with full resume, present and expected salary, by clicking \u201cAPPLY NOW\u201d. Please quote the reference number on the e-mail subject.\n\nWe are an equal opportunity employer and welcome applications from all qualified candidates. Personal data collected will be treated in the strictest confidence and handled confidentially by authorised personnel for recruitment-related purposes only within the CK Hutchison Group of companies. The personal data of unsuccessful applicants will be destroyed after the recruitment exercise pursuant to the requirements of the Personal Data (Privacy) Ordinance in Hong Kong.", "employment_types": ["Full Time", "Permanent"], "selling_points": [], "locations": ["Tsing Yi"], "categories": ["Information Technology (IT)", "Technical / Functional Consulting", "Others"], "post_time": "2022-01-14T11:10:24Z", "salary": {"currency": null, "max": null, "min": null, "period": "monthly", "term": null}, "salary_visible": false, "title_keywords": ["consultant"], "responsibilities": ["tender", "ad-hoc projects", "external parties", "design"], "requirements": {"degrees": ["bachelor"], "majors": ["related disciplines", "it", "engineering"], "languages": ["english", "chinese"], "language_level": ["good command"], "hard_skills": ["mobile", "plus", "dynamic", "ai"], "soft_skills": ["organized", "self-motivated", "dynamic environment", "time management skills", "presentation skills", "comprehensive", "interpersonal"], "languages_combined": [{"language": "english", "language_level": ["good command"]}, {"language": "chinese", "language_level": ["good command"]}]}, "experience_required": {"duration": ["at least 5 years"], "field": ["design"]}}, {"job_id": "100003009054061", "location_code": "hk", "company": "eCloudvalley Technology (HK) Limited", "job_title": "Cloud Solution Architect / Associate Solution Architect", "description": "Do you like helping enterprise clients implement innovative cloud solutions and solve technical problems? Do you want to be the leader and demonstrate how the emerging technologies (such as A.I., Big Data, Cloud, DevOps) can be applied to businesses? With business growth and global expansion opportunities, we are looking for a highly motivated Cloud Solution Architect\u00a0to help accelerate our growing technical team. This is an excellent opportunity to join a world class technical team, working with some of the best and brightest engineers and account managers while also developing your skills and furthering your career within one of the most innovative and progressive technology young companies in Hong Kong.\n\u00a0\nResponsibilities includes but is not limited to:\nUnderstanding clients\u2019 requirements and design technical solutions on AWS that address clients\u2019 requirements for scalability, reliability, security, and performance.\n\u00a0Work closely and support sales team from technical perspective.\nWork closely with a team of architects and engineers to create technical documents and proposals.\n\u00a0Conduct proof-of-concept demonstrations, technical presentations, and sharing.\n\u00a0Respond to technical issues in a professional and timely manner.\n\u00a0Maintain technical skills and knowledge of market trends and competitive insights; collaborate and share with the technical community.\n\nRequirements:\n\nBachelor's degree in Computer Science, Computer Engineering, Information Technology or relevant field.\n3+ years' experience on designing, executing and supporting IT cloud solutions.\n\u00a0Proven experience on architecting, designing and programming applications in an AWS Cloud environment.\n\u00a0Hands-on experience with cloud computing technologies in AWS is preferred.\n\u00a0Current AWS Certified Solutions Architect \u2013 Professional preferred.\n\u00a0Knowledge of cloud computing technologies on AWS and current computing trends.\n\u00a0Knowledge of cloud computing technologies on cloud platforms other than AWS (e.g. Azure, AliCloud) is advantageous.\n\u00a0Architectural knowledge of data centre infrastructure including networking, servers, storage infrastructure and virtualization ) is advantageous.\n\u00a0Positive attitude and a strong commitment to delivering quality work.\n\u00a0Effective communication skills (written and verbal) in English and Mandarin\nCandidate with less experience will be considered as Associate Solution Architect.", "employment_types": ["Full Time", "Permanent"], "selling_points": [], "locations": ["Wan Chai"], "categories": ["Information Technology (IT)", "Application Specialist - Software", "IT Project Management / Team Lead", "Technical / Functional Consulting"], "post_time": "2022-01-17T08:15:52Z", "salary": {"currency": null, "max": null, "min": null, "period": "monthly", "term": null}, "salary_visible": false, "title_keywords": ["associate"], "responsibilities": ["collaborate", "presentations", "design", "maintain", "sales team"], "requirements": {"degrees": ["degree", "bachelor"], "majors": ["computer engineering", "computer science", "information technology"], "languages": ["english", "mandarin"], "language_level": [], "hard_skills": ["azure", "servers", "computing technologies", "aws", "programming", "cloud environment"], "soft_skills": ["positive attitude", "communication skills", "hands-on"], "languages_combined": [{"language": "english", "language_level": []}, {"language": "mandarin", "language_level": []}]}, "experience_required": {"duration": ["3+ years"], "field": ["it", "programming", "solution architect"]}}, {"job_id": "100003009046003", "location_code": "hk", "company": "Acton Consulting Limited", "job_title": "Business Process Consultant - Outsourcing Services", "description": "Our client is a sizable organization. Due to the rapid growth of the company, they are now looking for talented individuals to join the professional team.\u00a0\u00a0\n\nRole:\n\nThe Business Process Outsourcing Consultant (Finance, Human Resources and Procurement) operates to support the organization in identifying, qualifying and implementing Business Process Outsourcing opportunities in the Hong Kong market\nInitiate, qualify, scope, and manage the delivery of Business Process Outsourcing projects for clients across different sectors.\n\nResponsibilities:\n\nPlan, lead and support marketing developments events to raise customer awareness of the services offerings and capabilities in the Business Process Outsourcing space.\nLead engagement with prospective clients and qualify their business needs in the operating model transformation area.\nLead the analysis and preparation of recommendations and business case for Business Process Outsourcing that will drive organizational effectiveness and cost optimization.\nPartner with business leaders to maintain ongoing communication regarding improvement opportunities, design and facilitate customer insight sessions, lead cross functional teams to generate ideas for solutions that enhance customer experience.\nDevelop compelling business cases, including gaining senior management buy-in, to accomplish business objectives. Identifies, assesses and mitigates business risks associated with the current operating model and/or desired target state operating models.\n\nRequirements:\n\nUniversity Degree or above in ICT, Business in IT or Business operation or related disciplines\nAt least 12+ years\u2019 experience in pre-sales support or identifying business opportunities\nWorking knowledge in common business processes or workflow design\nExperience / knowledge in Accounting operations will be a great advantage\nKnowledge in Payroll OR procurement operation is a plus\nExperience in the sales support and service delivery cycle of Business Processes outsourcing services\nProfessional qualifications in Accounting, PMP, Lean Six Sigma is an asset BUT not Essential\nStrong analytical ability, developed complex problem-solving ability, and creativity\nStrong interviewing and observation skills\nExcellent communication and customer service skills with the ability to focus on the details and to communicate effectively to both technical and non-technical teams\n\nInterested parties please send full resume in MS WORD format stating current salary, expected salary and availability to us.\n\nwww.ActonCL.com\u00a0\u00a0Unit 2302,\u00a023/F, New World Tower 1,\u00a018 Queen's Road Central.\u00a0Hong Kong\n\nAll information received will be kept in strict confidence and only for employment-related purposes.", "employment_types": ["Full Time", "Permanent", "Contract"], "selling_points": ["5 days\u2019 work with fringe benefits", "Outsource Service", "Business Process or Workflow"], "locations": ["Not Specified"], "categories": ["Professional Services", "Business Consultancy", "Sales, CS & Business Devpt", "Business Development", "Information Technology (IT)", "Technical / Functional Consulting"], "post_time": "2022-01-13T09:25:38Z", "salary": {"currency": null, "max": null, "min": null, "period": "monthly", "term": null}, "salary_visible": false, "title_keywords": ["consultant"], "responsibilities": ["cost optimization", "ideas", "analysis", "teams", "design", "develop", "communication", "maintain", "business process", "plan", "senior management"], "requirements": {"degrees": ["degree or above"], "majors": ["related disciplines", "business", "it"], "languages": [], "language_level": [], "hard_skills": ["plus", "lean", "sales support", "focus", "professional qualifications", "problem-solving", "six sigma", "pmp"], "soft_skills": ["communication", "customer service skills", "problem-solving", "focus"], "languages_combined": []}, "experience_required": {"duration": ["at least 12+ years"], "field": ["business", "sales support", "accounting"]}}, {"job_id": "100003009050056", "location_code": "hk", "company": "Career Search AP (Hong Kong) Company", "job_title": "Solution Consultant / Engineer  - IT, CCTV,  Camera 30-60K", "description": "Job Description\n\nDesign and Present Industry solutions to Channel, Vertical Market and Government Customers\nDevelop business contact with channel and government customers\nMake market analysis for industries such as Finance, Energy, and Security\nIntegrate Company solutions to match customer needs\nBusiness Development and Following-up\n\nJob Requirements\n\n3 years of work experience on CCTV project domain / SI in Hongkong market\n3 years of work experience on related domain in Hongkong market\nRich region / country Pre-sales experiences\nDegree or above of Telecommunications or Marketing\nExperience\u00a0in IT or communication department of industry, or worked in operator\u2019s channel or enterprise department\nExperience\u00a0in Enterprise sector of Axis, Pelco, Bosch\uff0cSamsung and Panasonic is a plus.\nCCTV background in IP, IT and Networking\nProfound Knowledge of local CCTV and Industry market", "employment_types": ["Full Time", "Permanent"], "selling_points": ["Experience in CCTV project", "Background in IP, IT and Networking", "solution consultant, pre-sales experiences"], "locations": ["Tsim Sha Tsui"], "categories": ["Information Technology (IT)", "Hardware", "Technical / Functional Consulting", "Marketing / Public Relations", "Marketing - Brand / Product Management"], "post_time": "2022-01-14T09:42:02Z", "salary": {"currency": null, "max": null, "min": null, "period": "monthly", "term": null}, "salary_visible": false, "title_keywords": ["engineer", "consultant"], "responsibilities": ["market analysis", "contact", "design", "develop"], "requirements": {"degrees": ["degree or above"], "majors": ["marketing"], "languages": [], "language_level": [], "hard_skills": ["ip", "cctv", "plus"], "soft_skills": ["communication"], "languages_combined": []}, "experience_required": {"duration": ["3 years"], "field": ["related", "it"]}}, {"job_id": "100003009051851", "location_code": "hk", "company": "Sinowittech (Hong Kong) Technology Co., Limited", "job_title": "System Analyst", "description": "This position will provide high quality services and technical support to customers and partners for the products.\u00a0 Main responsibilities include:\n\nResponsibilities\n\nPerform user requirements collection, system design & configuration and report design\nParticipate in testing of customers\u2019 systems performance\nEvaluate alternative solutions and make recommendation on system improvement\nProvide remote or onsite access support on customers\u2019 system environments\nPerform trouble shooting and implement solution to complex technical issues\nSupervises and provides direction to software engineers. Daily interaction with clients and stakeholders\nDeliver customer presentations, internal & external customers training\n\n\u00a0Requirements\n\nBachelor\u2019s Degree in Computer Science, Electrical Engineering or related discipline\nMinimum 6 years\u2019 relevant experience covering an entire software lifecycle in a team environment\nKnowledgeable in SQL, .Net , C# or JavaScript. Expertise in database applications, particularly in Oracle and/or MS SQL Server a plus\nKnowledge and experience in maintaining Windows Server cluster (VMware ESXi) and network configuration (firewall rules and DMZ) is a plus.\nCustomer-oriented with excellent interpersonal and communication skills\nFluency in oral and written English and Chinese communication\n\n\u00a0 \u00a0 \u00a0Please visit our website www.sinowittech.com for more information about our CompanyPersonal data collected will be used for recruitment purposes only.", "employment_types": ["Full Time"], "selling_points": ["Double pay", "Five-day work week", "Travel allowance"], "locations": ["Tai Po Area"], "categories": ["Information Technology (IT)", "Network & System", "Technical / Functional Consulting", "Others"], "post_time": "2022-01-17T01:22:34Z", "salary": {"currency": "HKD", "max": 44999, "min": 35000, "period": "monthly", "term": null}, "salary_visible": true, "title_keywords": ["system analyst"], "responsibilities": ["make recommendation", "software", "configuration", "systems", "design", "testing", "evaluate", "presentations", "system design", "report"], "requirements": {"degrees": ["degree", "bachelor"], "majors": ["electrical engineering", "computer science"], "languages": ["english", "chinese"], "language_level": ["fluency"], "hard_skills": ["plus", "vmware", "ms sql server", "c#", "sql", "javascript", "firewall", "windows server", "oracle"], "soft_skills": ["communication skills", "oral", "communication", "customer-oriented", "interpersonal"], "languages_combined": [{"language": "english", "language_level": ["fluency"]}, {"language": "chinese", "language_level": ["fluency"]}]}, "experience_required": {"duration": ["minimum 6 years"], "field": ["relevant experience", "team"]}}, {"job_id": "100003009052715", "location_code": "hk", "company": "Chinasoft International Technology Service (Hong Kong) Limited", "job_title": "IT Sales / Account Manager", "description": "Responsibilities:\n\nManage the customer relationship to ensure overall satisfaction, serve as a trusted advisor by understanding customer needs and building long term relationships\nWork closely with customers to identity business opportunities, with a clear target to expand service portfolio and uplift customer experience\nTake charge to the operation delivery\nAssist with business renewal documentations and offshore business related documents\nPrepare customer contract, agreement and related documents\n\nRequirements:\n\nDegree holder\n2+ years of experience in IT consulting / account management / project management / recruitment / service delivery is preferred\nCustomer oriented with strong sense of ownership and accountability\nAble to engage with senior management\nAble to propose and provide services based on client's project requirements\nMature and pleasant personality with good communication skill\nAbility to work under stress\nExcellent for both written and spoken Cantonese, Mandarin and English", "employment_types": ["Full Time", "Permanent"], "selling_points": ["2+ years of experience in IT sales / AM", "IT solutions sales / business development", "Energetic with excellent communication skill"], "locations": ["Mong Kok"], "categories": ["Sales, CS & Business Devpt", "Business Development", "Information Technology (IT)", "Technical / Functional Consulting", "Account Servicing"], "post_time": "2022-01-17T03:47:12Z", "salary": {"currency": null, "max": null, "min": null, "period": "monthly", "term": null}, "salary_visible": false, "title_keywords": ["account manager", "sales"], "responsibilities": ["related documents", "business opportunities"], "requirements": {"degrees": ["degree holder"], "majors": [], "languages": ["cantonese", "english", "mandarin"], "language_level": ["excellent"], "hard_skills": ["project management"], "soft_skills": ["accountability", "communication skill", "mature", "pleasant", "project management"], "languages_combined": [{"language": "cantonese", "language_level": ["excellent"]}, {"language": "english", "language_level": ["excellent"]}, {"language": "mandarin", "language_level": ["excellent"]}]}, "experience_required": {"duration": ["2+ years"], "field": ["consulting", "project management", "it", "recruitment", "account management"]}}, {"job_id": "100003009048305", "location_code": "hk", "company": "Perun Consultants Limited", "job_title": "Senior Management Consultant / IT Consultant", "description": "\nPerun Consultants is the leading independent advisory firm with offices in Hong Kong and Singapore. We specialise in provision of high quality services in the areas of forensic accounting, corporate advisory, restructuring, turnaround and liquidation appointments. At Perun, we promote a work-life balance, value individualism and embrace the differences.\n\nWe are recruiting an experienced Senior Management Consultant who is well-versed in project management and organisational governance to join our Hong Kong office.\n\nThe consultant will be responsible for the following duties:\n\nTo lead process improvement and transformation projects\nIdentify and define and quantify client\u2019s problems or potential for improvement\nWork with the team to implement solutions\nUnderstand the impact of change and digital transformation, lead team to help clients navigate the change in the organisation to achieve change targets.\nConduct Business Process Mapping, analyse the track business requirements\nA successful candidate will demonstrate the following qualities:\n\nDegree holder, preferably in Information Technology or Engineering or a relevant discipline\nFluent in English and Mandarin\nKnowledge in BPR, LEAN Manufacturing and Six Sigma\nGood knowledge of Enterprise Resource Planning (ERP) implementation\nAt least 3-5 years of Management/IT consulting experience with medium and large organizations\nExperience in running a key area of improvement in a project\nExperience in managing a team and clients to achieve set objectives\nDemonstrated experience in organisational change effort\nGood verbal and written communication skills in presentation and dealing with clients\nAbility to work in a multicultural setting\nMotivated and capable of tackling new problems\nIn addition to the above role, we are always interested in hearing from proactive, commercially minded, individuals at all levels of seniority and experience looking to work in a dynamic and flexible environment.\n\nWe offer a competitive remuneration package where you will be rewarded for your individual and team performance. We are committed to being an inclusive employer and are happy to consider flexible working arrangements.\nTo apply, contact us at Apply Now .", "employment_types": ["Full Time"], "selling_points": [], "locations": ["Central"], "categories": ["Professional Services", "Business Consultancy", "Information Technology (IT)", "Technical / Functional Consulting"], "post_time": "2022-01-14T06:12:04Z", "salary": {"currency": null, "max": null, "min": null, "period": "monthly", "term": null}, "salary_visible": false, "title_keywords": ["consultant"], "responsibilities": ["management", "consulting", "quality", "implementation", "communication", "project management", "business process", "planning", "senior management", "managing a team", "analyse"], "requirements": {"degrees": ["degree holder"], "majors": ["engineering", "information technology"], "languages": ["english", "mandarin"], "language_level": ["fluent"], "hard_skills": ["lean", "erp", "project management", "six sigma", "dynamic"], "soft_skills": ["flexible", "communication skills", "independent", "capable", "responsible", "interested in", "project management", "motivated", "dynamic", "organisation", "proactive", "presentation"], "languages_combined": [{"language": "english", "language_level": ["fluent"]}, {"language": "mandarin", "language_level": ["fluent"]}]}, "experience_required": {"duration": ["at least 3-5 years"], "field": ["managing a team", "management", "it", "consulting"]}}, {"job_id": "100003009053029", "location_code": "hk", "company": "PCCW Media", "job_title": "System Engineer / Cloud Engineer / DevOps Engineer (MOOV), Hong Kong", "description": "Your New Role\n\nYou will have the opportunities to manage various projects and work closely with the team to facilitate new initiatives.\n\nWork closely with internal teams to build and maintain infrastructure & best practice\nDesign and maintain hybrid cloud infrastructure in highly scalable, reliable, and cost-effective ways\nDesign and maintain CI/CD pipelines to maximize SDLC efficiency\nCreate and maintain DevOps guidelines & documentations\n\nWhat makes you succeed\n\nUniversity Graduate or High Diploma in Computer Science or related discipline\nMinimum 2+ years of relevant experience\nExperience in VM server management (VMWare, Linux, etc.)\nExperience in designing and implementing solution on AWS cloud\nKnowledge in containerization (i.e. Kubernetes, Docker)\nKnowledge in CI/CD using Jenkins and infrastructure as code\nKnowledge in network & infrastructure of on-premises is highly recommended\nKnowledge in programming and involving in SDLC is an advantage\u00a0\u00a0\u00a0\u00a0\u00a0\u00a0\u00a0\u00a0\nPassionate in learning and using new technologies\nCandidate with more experience will be considered as senior position\n\n\n\nWe offer attractive and competitive salary and benefits, an exciting work environment and excellent career development opportunities.\u00a0If you have the desire for an exciting and rewarding career, please send us your resume,\u00a0stating your present and expected salary to Human Resources Department by post, fax or clicking \"Apply Now\":\n\nPost:\u00a0\u00a0 \u00a0\u00a06/F, Goldin Financial Global Centre, 17 Kai Cheung Road, Kowloon Bay\u00a0\nFax:\u00a0\u00a0\u00a0\u00a0 (852) 2827 8322\u00a0\u00a0\n\nFor more information on other job opportunities of PCCW, please visit our website at <http://www.pccw.com/Careers/Job+Opportunities+&+Application/Current+Opportunities?language=en_US>\n\nPCCW is an equal opportunity employer and welcomes applications from all qualified candidates. Information provided will be treated in strict confidence and will only be used for recruitment-related purposes. Personal data provided by job applicants will be used strictly in accordance with the employer\u2019s privacy statement\u00a0(www.pccw.com/privacy-statement/index.page), a copy of which will be provided immediately upon request.", "employment_types": ["Full Time"], "selling_points": [], "locations": ["Kowloon Bay"], "categories": ["Information Technology (IT)", "Application Specialist - Software", "Software Development", "Technical / Functional Consulting"], "post_time": "2022-01-17T05:12:49Z", "salary": {"currency": null, "max": null, "min": null, "period": null, "term": null}, "salary_visible": false, "title_keywords": ["system engineer", "engineer"], "responsibilities": ["cost", "management", "guidelines", "infrastructure", "teams", "design", "maintain", "designing"], "requirements": {"degrees": ["high diploma", "university graduate"], "majors": ["computer science"], "languages": [], "language_level": [], "hard_skills": ["linux", "vmware", "jenkins", "pipelines", "devops", "aws", "sdlc", "programming", "server", "code", "documentations"], "soft_skills": ["passionate", "reliable", "learning"], "languages_combined": []}, "experience_required": {"duration": ["minimum 2+ years"], "field": ["management", "relevant experience"]}}, {"job_id": "100003009053018", "location_code": "hk", "company": "Viu", "job_title": "Senior Data Strategy Manager, Hong Kong", "description": "Your New Role\n\nWe are now looking for a\u00a0Senior Data Strategy Manager\u00a0to join our Data team in Hong Kong. The successful candidate will be responsible for designing and delivering data strategies and overseeing data platform within Viu.\n\nKey Responsibilities\n\n\nLead and set the roadmap of data-driven strategy and foster the use of data for analytics, monetize and explore business opportunities, make decisions and improve the user experience.\nImplementing data privacy policies and complying with data protection regulations.\nWork closely with senior business stakeholders and communicate with team members at any level of seniority.\nManage the team resources and schedule to ensure the data platform is delivered with effectiveness, high quality, accurate, secure, on time, budget, and cost control.\nKnowledge of relevant applications and big data solutions and tools.\n\nWhat makes you succeed\n\nTo be successful in your new position, it is important that you are forward-thinking and take initiative. Also, it is essential to have the following skills:\n\n5+ years related experience in a senior-level data management background.\nDegree holder, actuarial, mathematics, statistics, computer science, or related disciplines.\nBeing a visionary in improving the existing business as well as enabling new businesses.\nStrong leadership, communication, strong analytical and problem-solving skills.\nExperience in managing multiple projects and deliverables.\nKnowledge of machine learning, deep learning, and analytic techniques; capable to lead multiple data science work streams simultaneously in a fast-paced environment with multiple business stakeholders.\nKnowledge of cloud environments such as AWS, Google Cloud, or other public cloud platforms.\nWorking experience in the digital, e-commerce industry, mobile app, and web environment is highly desirable.\nFlexible and able to work in a dynamic environment and manage your own time and in a high-paced work environment and tight timeline.\nGood command of both written and spoken English and Chinese.", "employment_types": ["Full Time"], "selling_points": [], "locations": ["Kowloon Bay"], "categories": ["Information Technology (IT)", "Application Specialist - Software", "Technical / Functional Consulting", "Data Scientist"], "post_time": "2022-01-17T05:07:37Z", "salary": {"currency": null, "max": null, "min": null, "period": null, "term": null}, "salary_visible": false, "title_keywords": ["manager"], "responsibilities": ["regulations", "communicate with", "management", "mobile app", "data", "policies", "business opportunities", "budget", "quality", "user experience", "big data", "communication", "schedule", "cost control", "designing", "multiple projects", "team resources"], "requirements": {"degrees": ["degree holder"], "majors": ["related disciplines", "mathematics", "statistics", "computer science"], "languages": ["english", "chinese"], "language_level": ["good command"], "hard_skills": ["data management", "web", "e-commerce", "aws", "make", "mobile", "dynamic", "public cloud platforms", "problem-solving skills"], "soft_skills": ["flexible", "dynamic environment", "capable", "responsible", "fast-paced environment", "deep", "driven", "communication", "learning", "visionary", "problem-solving skills", "accurate", "leadership", "initiative"], "languages_combined": [{"language": "english", "language_level": ["good command"]}, {"language": "chinese", "language_level": ["good command"]}]}, "experience_required": {"duration": ["5+ years"], "field": ["management", "e-commerce", "related", "business", "digital"]}}, {"job_id": "100003009055757", "location_code": "hk", "company": "Robert Walters (HK)", "job_title": "Information Security Risk Manager", "description": "My reputable client is looking to expand their technology risk team, if you are keen to know more, please get in touch!\n\nAbout the responsibilities:\n\nReview and update technology and operational risk management framework, policies and controls taking into consideration the bank's strategy, current/future regulatory requirements and emerging risk scenarios.\nCommunicate T&O risk management standards, policies and procedures to stakeholders of bank\nIdentify control weaknesses in cybersecurity from a risk-based perspective\nAssist to define and review monitoring requirements and indicators for measuring technology and operational risk positions\nMonitor, review and update T&O risk profile and controls on a regular basis\nManage and conduct regular T&O key risk and control assessments (RCA) and ad-hoc independent assessments\n\nAbout the requirements:\n\n5 or more year of relevant experience in T&O Risk, Audit or Cybersecurity\nCertifications under ECF-C professional level highly desirable, e.g. CISA, CISSP, CISM, CRISC\nFamiliarity with HKMA SPM on E-banking (TM-E-1), Technology Risk Management (TM-G-1), BCP (TM-G-2), Outsourcing (SA-2)\nStrong communication skills and interpersonal skills to a wide range of individuals and at different levels of seniority\nSelf-starter who has experience in dealing with varieties of cultures and work in a dynamic environment", "employment_types": ["Full Time", "Permanent"], "selling_points": ["Reputable listed company", "Excellent project exposure", "Good team culture"], "locations": ["Not Specified"], "categories": ["Information Technology (IT)", "Security", "Technical / Functional Consulting"], "post_time": "2022-01-18T02:55:42Z", "salary": {"currency": "HKD", "max": 69999, "min": 45000, "period": "monthly", "term": null}, "salary_visible": true, "title_keywords": ["manager"], "responsibilities": ["ad-hoc", "management", "control", "policies", "regulatory requirements", "review", "procedures", "monitoring", "monitor"], "requirements": {"degrees": [], "majors": [], "languages": [], "language_level": [], "hard_skills": ["hkma", "dynamic", "c"], "soft_skills": ["communication skills", "dynamic environment", "interpersonal skills"], "languages_combined": []}, "experience_required": {"duration": [], "field": ["relevant experience", "audit"]}}, {"job_id": "100003009043679", "location_code": "hk", "company": "Legato Technologies Limited", "job_title": "Senior Project Executive / Project Executive", "description": "Responsibilities:\n\nPlanning and coordination of Web/Mobile application projects, ensuring project is on time, according to the specification and\u00a0delivery with quality standards\nRequirements gathering, documentations and be able to communicate with customers independently\nLiaise with internal external parties for project development\nCapable to handle customer's requests and expectation through out the development cycle\n\n\nRequirements:\n\nDegree holder with project experiences in Mobile/Web development\nExcellent interpersonal and analytical skills\nWell time management with multi-tasking skills\nAttention to details\nLess experienced candidate will be considered as Project Executive\nImmediate availability is preferred\n\n\nBenefits:\n\nFive-day work week (Flexible working hours)\nMedical allowance\nPerformance bonus\nBirthday leave\n\nInterested parties please send full resume with availability and expected salary to us by clicking \"Apply Now\"\n\nPersonal data will be used for recruitment purposes only.", "employment_types": ["Full Time", "Permanent"], "selling_points": [], "locations": ["Kowloon Bay"], "categories": ["Information Technology (IT)", "IT Project Management / Team Lead", "IT Management", "Technical / Functional Consulting"], "post_time": "2022-01-13T01:27:30Z", "salary": {"currency": null, "max": null, "min": null, "period": "monthly", "term": null}, "salary_visible": false, "title_keywords": ["senior project executive", "project executive"], "responsibilities": ["communicate with", "external parties", "quality", "coordination", "liaise with", "planning"], "requirements": {"degrees": ["degree holder"], "majors": [], "languages": [], "language_level": [], "hard_skills": ["mobile", "web development", "analytical skills"], "soft_skills": ["analytical skills", "attention to details", "multi-tasking skills", "time management", "interpersonal"], "languages_combined": []}, "experience_required": {"duration": [], "field": ["development"]}}, {"job_id": "100003009050877", "location_code": "hk", "company": "Integrated Solutions Ltd", "job_title": "Pre-Sales Consultant (5-Day Work)", "description": "-\u00a0 Identify and pursue sales opportunities for Enterprise Solutions (e.g. ERP, CRM and HRM Solutions);\n-\u00a0 Sales presentation, solution proposal and handling customers' enquiries would be required; and\n-\u00a0\u00a0Work with Sales team on solution design and provide suggestions to customers.\n\nQualifications:\n\n-\u00a0\u00a0Bachelor's degree or above in Business Administration, Information Technology or related disciplines;\n-\u00a0 3 to 5 years experience of selling business application software;\n-\u00a0 Excellent consultative selling skill and communication skill; and\n-\u00a0 \u00a0 Fluent in Cantonese, English and Mandarin.\n\nAll interested parties please apply with full confidence your resume, references, current (if possible, past), date of availability and expected salary by clicking \"Apply Now\".\n\nPersonal data collected will be used for recruitment purpose only.", "employment_types": ["Full Time", "Permanent"], "selling_points": [], "locations": ["Shatin Area"], "categories": ["Professional Services", "Business Consultancy", "Information Technology (IT)", "Technical / Functional Consulting"], "post_time": "2022-01-14T11:37:26Z", "salary": {"currency": null, "max": null, "min": null, "period": "monthly", "term": null}, "salary_visible": false, "title_keywords": ["sales consultant"], "responsibilities": ["software", "solution proposal", "design", "communication", "sales team", "administration"], "requirements": {"degrees": ["degree or above", "bachelor"], "majors": ["related disciplines", "business administration", "information technology"], "languages": ["cantonese", "english", "mandarin"], "language_level": ["fluent"], "hard_skills": ["erp"], "soft_skills": ["communication skill", "presentation"], "languages_combined": [{"language": "cantonese", "language_level": ["fluent"]}, {"language": "english", "language_level": ["fluent"]}, {"language": "mandarin", "language_level": ["fluent"]}]}, "experience_required": {"duration": ["3 to 5 years"], "field": ["business"]}}, {"job_id": "100003009049684", "location_code": "hk", "company": "Hong Kong Internet Registration Corporation Limited", "job_title": "Senior System Engineer", "description": "Responsibilities:\n\nl\u00a0\u00a0 Perform daily system monitoring and operation tasks, assist system administration, planning and technology evolution\n\nl\u00a0\u00a0 Experience in Linux (Redhat, Ubuntu & CentOS), Virtualization technologies (Oracle & RedHat), Monitoring / Operational intelligence products (Nagios, Graylog)\n\nl\u00a0\u00a0 Hands-on experience and Deep understand of DNS and DNSSEC technology\n\nl\u00a0\u00a0Experience with programming and/or scripting, task automation(e.g. Ansible), and best security practices for server installation and administration\n\nl\u00a0\u00a0 Undertake system infrastructure enhancements in-house and with outsourced vendors\n\nl\u00a0\u00a0 Set up and conduct proof-of-concept testing and evaluation on test-beds for assessing new technology, technical standards and products\n\nl\u00a0\u00a0 Maintain documentation and develop reports for system implementation and infrastructure changes\n\nl\u00a0\u00a0 Good analytical and problems solving skills with strong self-motivation and ability to work under pressure\n\nl\u00a0\u00a0 Candidates with less experience will also be considered as System Engineer\n\nRequirements:\n\nl\u00a0\u00a0 Degree holder in Computer Science, Computer Engineering, or equivalent\n\nl\u00a0\u00a0 5 years of experience in manage platform service over Cloud, Automation software (Ansible)\n\nl\u00a0\u00a0 Proficiency and knowledge in Linux platforms\n\nl\u00a0\u00a0 Knowledge of Container Orchestration tools (Kubernetes) is an advantage\n\nl\u00a0\u00a0 Familiarity with DNS and BIND is a definite advantage\n\nl\u00a0\u00a0 Certificate Holder of RHCSA/ LPIC-1 / CompTIA Linux+ / Cloud platform (e.g. Azure Administrator)\n\nl\u00a0\u00a0 Good communication and interpersonal skills\n\nl\u00a0\u00a0 Immediate availability preferred\n\n\n\nSalary range from HK$40,000/ monthly\n\n\nShuttle bus routes from Tai Wai, Mei Foo, Kowloon Tong, Lam Tin, Hang Hau and Sheung Wan to Cyberport are available\n\nInterested parties, please submit your application by click \"Apply Now\" plus providing us the full resume with your expected and current salary.\u00a0\u00a0", "employment_types": ["Full Time", "Permanent"], "selling_points": [], "locations": ["Pok Fu Lam"], "categories": ["Information Technology (IT)", "Security", "Network & System", "Technical / Functional Consulting"], "post_time": "2022-01-14T09:04:51Z", "salary": {"currency": null, "max": null, "min": null, "period": "monthly", "term": null}, "salary_visible": false, "title_keywords": ["senior system engineer"], "responsibilities": ["administration", "installation", "problems solving", "dns", "work under pressure", "monitoring", "infrastructure", "implementation", "testing", "develop", "reports", "evaluation", "maintain documentation", "planning"], "requirements": {"degrees": ["certificate", "degree holder"], "majors": ["computer engineering", "computer science"], "languages": [], "language_level": [], "hard_skills": ["azure", "dns", "linux platforms", "ansible", "container", "wan"], "soft_skills": ["communication and interpersonal skills"], "languages_combined": []}, "experience_required": {"duration": ["5 years"], "field": []}}, {"job_id": "100003009052487", "location_code": "hk", "company": "Ricoh Hong Kong Limited", "job_title": "Solution Engineer", "description": "The Job:\n\nResponsible for Document Management System (DMS) solution project deployment and post services\nConfirm user requirements, function specification and prepare related documentations for customer endorsement\nSelf-develop and/or coordinate with the team for the program coding (.NET & JavaScript)\nCollaborate with project manager / team lead with scheduling, resourcing and management of technical activities to ensure project accuracy and quality\nDetermines task details of projects by understanding the design overview and scope of work handed over by pre-sales team\nDetermines the time requirements of project task by liaison with pre-sales support and / or customers and technical studies\nPrepares project status reports and recommendations\n\nThe Person:\n\nHigher Diploma \u00a0in Computer Science or IT or related discipline\nAt least 3 years relevant working experience in DMS related industries\nProficient in programming with\u00a0.NET & JavaScript\nHolder of MTA, MCSA, Web Applications certificate or equivalent is an advantage\nStrong PC hardware & software, MS Windows, basic server & network knowledge\nGood communication skills in both written and spoken English\nGood team player, able to take ownership and can work independently\nWe offer 5-day work, attractive remuneration and benefits package to the right candidate.\n\nInterested parties please forward your full resume (in Microsoft Word or PDF format) with current and expect salary to the\u00a0Human Resources & Facilities Services, Ricoh Hong Kong Limited,\u00a0by clicking \"Apply Now\".\nInformation provided will be treated in strict confidence and only be used for recruitment related purposes. All personal data of unsuccessful candidates will be destroyed on completion of the recruitment exercise.\n", "employment_types": ["Full Time", "Permanent"], "selling_points": ["DMS Project deployment and post services", "Confirm user requirements for customer endorsement", "Familiar with .NET & JavaScript Framework"], "locations": ["Kowloon Bay"], "categories": ["Information Technology (IT)", "Application Specialist - Software", "Product Management / Business Analyst", "Technical / Functional Consulting"], "post_time": "2022-01-17T03:10:23Z", "salary": {"currency": null, "max": null, "min": null, "period": "monthly", "term": null}, "salary_visible": false, "title_keywords": ["engineer"], "responsibilities": ["collaborate with", "management", "coordinate with", "quality", "coding", "develop", "design", "scheduling", "sales team", "reports"], "requirements": {"degrees": ["certificate", "diploma"], "majors": ["it", "computer science"], "languages": ["english"], "language_level": ["good"], "hard_skills": ["web applications", "basic", "ms windows", "hardware", "javascript", "programming", "mcsa", "server", "pc"], "soft_skills": ["communication skills", "good team player", "work independently"], "languages_combined": [{"language": "english", "language_level": ["good"]}]}, "experience_required": {"duration": ["at least 3 years"], "field": ["related", "relevant working experience"]}}, {"job_id": "100003009051372", "location_code": "hk", "company": "Liberty International Insurance Limited", "job_title": "Assistant Manager, Technology-Application Delivery & Engineering", "description": "Job Summary:\n\nThis role will be acting as a Lead in Asia Markets engineering team, support the projects development across the countries.\u00a0 Especially with Hong Kong focused projects, working closely with different business units and drive the technical and architecture design to achieve the Company\u2019s goals.\n\nResponsibilities:\n\nLead the Asia Markets engineering team for technical and architecture design\nWork with Technology and business product owners on shaping project requirements and solutions and responsible for solution delivery\nUnderstand business requirements and how they translate in application features\nWork with business analysts to recommend updates to core systems to the team responsible for development\nCollaborate with a team of IT professionals to set specifications for new applications and develop user stories\nEvaluate existing applications to reprogram, update and add new features\nDevelop technical documents and handbooks to accurately represent application design and code\nIntegrate software components and third-party programs and libraries\nTroubleshoot, debug and upgrade existing software\nRecommend and execute improvements to programs, systems and processes\nCreate technical documentation for reference and reporting.\n\nRequirements:\n\n5+ years\u00a0of experience in software development\nSolid experience using for example\u00a0Java8, Spring Boot, Spring MVC\nKnowledge of object-oriented design and design patterns, and programming skills\nExperience in designing and implementing APIs and Microservices\nKnowledge of and experience with Frontend technologies is also desirable.\nStrong concepts of clean code principles\nExperience with relational/non-relational databases\nAble to understand and apply design patterns\nExperience with container technologies (Docker or similar)\u00a0 is also desirable.\nExperience of Cloud technology (AWS or similar)\nExperience in vendor management\nYou are interested in growing as a software engineer participating actively in the whole development cycle (frontend, backend, database, testing, DevOps...)\nBachelor\u2019s degree in management information systems, computer science, information technology or other related field required\nMust be driven and flexible enough to succeed in ambiguous and less structured situations\nFast-learner, analytical and problem solver, keen to adopt latest technologies in a challenging environment\nStrong communication skills\nProficient in English and Cantonese languages is a plus", "employment_types": ["Full Time", "Permanent"], "selling_points": ["Java8, Spring Boot, Spring MVC", "implementing APIs and Microservices", "driven and flexible in ambiguous environment"], "locations": ["Quarry Bay"], "categories": ["Information Technology (IT)", "Application Specialist - Software", "Software Development", "Technical / Functional Consulting"], "post_time": "2022-01-15T12:19:12Z", "salary": {"currency": null, "max": null, "min": null, "period": "monthly", "term": null}, "salary_visible": false, "title_keywords": ["assistant manager,"], "responsibilities": ["collaborate with", "project requirements", "reporting", "software", "systems", "design", "develop", "evaluate", "specifications", "troubleshoot", "documentation", "architecture"], "requirements": {"degrees": ["degree", "bachelor"], "majors": ["computer science", "information technology"], "languages": ["cantonese", "english"], "language_level": ["proficient"], "hard_skills": ["clean", "plus", "devops", "microservices", "vendor", "aws", "container", "programming", "spring", "databases", "code"], "soft_skills": ["flexible", "communication skills", "problem solver", "keen", "interested in", "structured", "driven"], "languages_combined": [{"language": "cantonese", "language_level": ["proficient"]}, {"language": "english", "language_level": ["proficient"]}]}, "experience_required": {"duration": ["5+ years"], "field": ["management", "software development"]}}, {"job_id": "100003009055917", "location_code": "hk", "company": "Ambition", "job_title": "SAP SD Analyst", "description": "Job Description\n\nProvide regional SAP SD technical support\nImplement new applications and assist in system upgrade\nResponsible for testing and report to management\nSupport solution implementation by actively reviewing within the team\n\nJob Requirements\n\nA minimum of 3 years' working experience in SAP SD operations and configuration\nExperience in using ABAP is a must\nKnowledge in S/4HANA will be a huge advantage\nGood communication skills with well spoken English and Mandarin\n\nIf this job isn't quite right for you, but you know someone who would be great at this role, why not take advantage of our referral scheme? We offer HKD1000 in Apple gift cards for every referred candidate who we place in a role. Terms & Conditions Apply. https://www.ambition.com.hk/refer-a-friend", "employment_types": ["Full Time", "Permanent"], "selling_points": ["Reputable International Appliance Manufacturer", "Regional Exposure", "Flexible Working Hours"], "locations": ["Not Specified"], "categories": ["Information Technology (IT)", "Technical / Functional Consulting", "Technical Writing", "Others"], "post_time": "2022-01-18T03:05:13Z", "salary": {"currency": null, "max": null, "min": null, "period": "monthly", "term": null}, "salary_visible": false, "title_keywords": ["analyst"], "responsibilities": ["management", "technical support", "implementation", "testing", "report"], "requirements": {"degrees": [], "majors": [], "languages": ["english", "mandarin"], "language_level": ["good"], "hard_skills": ["abap", "scheme", "sap"], "soft_skills": ["communication skills"], "languages_combined": [{"language": "english", "language_level": ["good"]}, {"language": "mandarin", "language_level": ["good"]}]}, "experience_required": {"duration": ["minimum of 3 years"], "field": []}}, {"job_id": "100003009046283", "location_code": "hk", "company": "Pinpoint Asia Limited", "job_title": "Senior Programme Manager (Executive Director) - Leading Investment Bank", "description": "Our client, a leading investment, is looking for a Senior Programme Manager in their Global Programme office to drive the effective management of their large-scale programme. The selected candidate will be working with senior stakeholders across the bank.\n\nResponsibilities\n\nProvide programme governance in maintaining the schedule, resources, quality, change, financial, and communications management.\nOversight of the programme portfolio management and project delivery.\nWork with the project teams across the bank spanning Front Office, Technology, Operations, Risk, Finance, etc.\nWork with different key stakeholders in resolving issues and provide solutions.\nHave an in-depth understanding of programme / project risks and dependencies. Ability to provide escalation if necessary.\nWork with the programme leads and project managers to ensure the project deliverables.\nProvide senior management reporting on the overall health and status of the programme.\nProvide project governance, monitoring, and reporting of the project lifecycle. Ensure there is sufficient project methodology and standards for the programme team.\nEstablish key programme KPIs to facilitate the monitoring and decision-making in supporting the programme delivery.\nTrack and monitor impacts and interdependencies between programmes.\n\nRequirements:\n\nUniversity graduate with Masters or Bachelors Degree preferably in Business, Finance, IT or other related disciplines\nProven experience in managing and delivering large transformational change programmes.\nExperience in a large programme environment delivering large scale IT projects / programme.\nWorking experience in an investment banking or financial services industry exposure.\nA good understanding of front-to-back office functions.\nExperience in tracking large-scale and complex projects with efficient management and implementation.\nStrong interpersonal skills with different senior stakeholders.\nExperience with China or Asia regulations with the financial industry is preferred.\nExcellent communication and interpersonal skills.\nFluency in verbal and written English and Chinese communications is essential.\n\nIf this outstanding opportunity sounds like your next career move, please send your resume in Word format to Danny Kwan at resume(at)pinpointasia(dot)com and put Senior Programme Manager (Executive Director) - Leading Investment Bank in the subject header.\n\nData provided is for recruitment purposes only.", "employment_types": ["Full Time"], "selling_points": ["Large Scale Programme Management", "Governance and Monitoring", "Cross Regional Project role"], "locations": ["Not Specified"], "categories": ["Information Technology (IT)", "IT Project Management / Team Lead", "IT Management", "Technical / Functional Consulting"], "post_time": "2022-01-13T10:15:33Z", "salary": {"currency": "HKD", "max": 159999, "min": 120000, "period": "monthly", "term": null}, "salary_visible": true, "title_keywords": ["executive director", "manager"], "responsibilities": ["reporting", "management", "maintaining", "project deliverables", "operations", "monitoring", "quality", "teams", "provide solutions", "monitor", "schedule", "kpis", "senior management"], "requirements": {"degrees": ["university graduate", "degree"], "majors": ["related disciplines", "finance", "business", "it"], "languages": ["english", "chinese"], "language_level": ["fluency"], "hard_skills": ["word"], "soft_skills": ["efficient", "communication and interpersonal skills", "interpersonal skills"], "languages_combined": [{"language": "english", "language_level": ["fluency"]}, {"language": "chinese", "language_level": ["fluency"]}]}, "experience_required": {"duration": [], "field": ["management", "financial industry", "it", "investment", "banking", "financial services industry"]}}, {"job_id": "100003009053030", "location_code": "hk", "company": "Moov", "job_title": "iOS Developer, Hong Kong", "description": "Your New Role\n\nResponsible for implementation, maintenance, and release of our iOS music service applications\nImplement app functionalities based on product requirements under iteration cycles and participate in R&D and prototyping\nEnsure that architectural design and solution can balance business needs and technical/security standards\n\nWhat makes you succeed\n\nUniversity Graduate or High Diploma in Computer Science or related discipline\nMinimum 2+ years of relevant experience\nStrong knowledge and hands-on experience in both Swift and Objective C\nSolid understanding of the full mobile development life cycle\nGood problem solving and analytical skills\nOrganized, self-motivated and teamwork oriented\nCandidate with more experience will be considered as senior position", "employment_types": ["Full Time"], "selling_points": [], "locations": ["Kowloon Bay"], "categories": ["Information Technology (IT)", "Application Specialist - Software", "Software Development", "Technical / Functional Consulting"], "post_time": "2022-01-17T05:13:27Z", "salary": {"currency": null, "max": null, "min": null, "period": null, "term": null}, "salary_visible": false, "title_keywords": ["developer"], "responsibilities": ["implementation", "maintenance", "design"], "requirements": {"degrees": ["high diploma", "university graduate"], "majors": ["computer science"], "languages": [], "language_level": [], "hard_skills": ["r&d", "maintenance", "analytical skills", "problem solving", "mobile", "c", "swift"], "soft_skills": ["organized", "self-motivated", "responsible", "teamwork", "problem solving and analytical skills", "hands-on"], "languages_combined": []}, "experience_required": {"duration": ["minimum 2+ years"], "field": ["relevant experience"]}}, {"job_id": "100003009053025", "location_code": "hk", "company": "PCCW Media", "job_title": "Senior System Analyst / System Analyst / Analyst Programmer (MOOV), Hong Kong", "description": "Your New Role\n\nYou will have the opportunities to manage various projects and work closely with the team to facilitate new initiatives.\n\n\nResponsible for backend system implementation, maintenance and release\nDevelop and maintain APIs to support mobile and web application functionalities based on product requirement under iteration cycles\nEnsure that architectural design and solution can balance business needs and technical/security standards\n\nWhat makes you succeed\n\nUniversity Graduate or High Diploma in Computer Science or related discipline\nMinimum 3+ years of relevant experience\nHands-on experience in Java / J2EE / Spring\nExperience in Spring Boot, API Microservice, CI/CD is an advantage\nExperience in Node.JS and/or PHP is an advantage\nFamiliar with SQL / NoSQL databases\nOrganized, self-motivated and teamwork oriented\nCandidate with more experience will be considered as senior position\n\nWe offer attractive and competitive salary and benefits, an exciting work environment and excellent career development opportunities.\u00a0If you have the desire for an exciting and rewarding career, please send us your resume,\u00a0stating your present and expected salary to Human Resources Department by post, fax or clicking \"Apply Now\":\n\nPost:\u00a0\u00a0 \u00a0\u00a06/F, Goldin Financial Global Centre, 17 Kai Cheung Road, Kowloon Bay\u00a0\nFax:\u00a0\u00a0\u00a0\u00a0 (852) 2827 8322\u00a0\u00a0\n\nFor more information on other job opportunities of PCCW, please visit our website at<http://www.pccw.com/Careers/Job+Opportunities+&+Application/Current+Opportunities?language=en_US>\n\nPCCW is an equal opportunity employer and welcomes applications from all qualified candidates. Information provided will be treated in strict confidence and will only be used for recruitment-related purposes. Personal data provided by job applicants will be used strictly in accordance with the employer\u2019s privacy statement\u00a0(www.pccw.com/privacy-statement/index.page), a copy of which will be provided immediately upon request.", "employment_types": ["Full Time"], "selling_points": [], "locations": ["Kowloon Bay"], "categories": ["Information Technology (IT)", "Application Specialist - Software", "Software Development", "Technical / Functional Consulting"], "post_time": "2022-01-17T05:11:52Z", "salary": {"currency": null, "max": null, "min": null, "period": "monthly", "term": null}, "salary_visible": false, "title_keywords": ["analyst programmer", "system analyst"], "responsibilities": ["maintenance", "implementation", "design", "develop", "maintain", "databases"], "requirements": {"degrees": ["high diploma", "university graduate"], "majors": ["computer science"], "languages": [], "language_level": [], "hard_skills": ["java", "web", "maintenance", "php", "sql", "mobile", "spring", "databases", "system implementation"], "soft_skills": ["organized", "self-motivated", "responsible", "teamwork", "hands-on"], "languages_combined": []}, "experience_required": {"duration": ["minimum 3+ years"], "field": ["relevant experience"]}}, {"job_id": "100003009045770", "location_code": "hk", "company": "TierONE Consultants", "job_title": "IT - Manager, Information Technology, Network & Infrastructure (HK$40000-HK$45000)", "description": "Our client, an financial institutions, with full SFC licenses, they are hiring an IT Manager for their IT team, the requirements is as follow:-\u00a0 \u00a0\nDegree holder + 5+years related IT network, technical supports from financial institutions;\u00a0\u00a0\nReport to IT Director,\u00a0work together with teammates to perform supporting for business users via email, telephone or in person;\u00a0\nExperience of technical,\u00a0infrastructure, network daily supports as well as to perform Level I scripting;\nDevelop operational, installation, configuration and upgrade documentation for relevant technology components;\nPerform regular tasks for computer operations, such as hardware, software installation, configuration on desktops, laptops, printers and mobile devices;\nFollow standard guidelines and procedures for incident management, problem management etc;\nIdentify, isolate, resolve, escalate and close incident/problem ticket according to incident/problem management process;\nTest all changes to networks, hardware, software, and hosted applications;\nExperience in provision computing resources, capacity planning for IT infrastructure and assist in IT procurement;\nMaintain IT inventory and ensure the services are renewed within timeframe;\nProvide the necessary report(s) with accuracy during regular reporting;\nAssist in special project when is needed;\u00a0\nGood English and Fluent Cantonese;\nIndependent and good communication skill;\n5 working days with full employee benefits.\u00a0\nInterested candidates, please send full resume\u00a0(in MS WORD format),\u00a0with\u00a0current and expected salary to us\u00a0or please click\u00a0APPLY NOW\u00a0to submit your application.\u00a0\n\nRef: IT- 30353\n\nInformation provided by candidates with be treated in strict confidence and will only be used for recruitment related purposes. All information on unsuccessful candidates with be deleted from our files within 6 months.", "employment_types": ["Full Time", "Permanent"], "selling_points": ["degree information technology infrastructure IT", "technical supports help desk network financial", "asset management brokerage investment english"], "locations": ["Others"], "categories": ["Information Technology (IT)", "Application Specialist - Network", "Network & System", "Technical / Functional Consulting"], "post_time": "2022-01-13T08:37:05Z", "salary": {"currency": "HKD", "max": 54999, "min": 45000, "period": "monthly", "term": null}, "salary_visible": true, "title_keywords": ["manager"], "responsibilities": ["technical supports", "software", "operations", "communication", "maintain", "mobile devices", "it procurement", "it infrastructure", "configuration", "infrastructure", "develop", "it inventory", "report", "installation", "management", "reporting", "procedures", "documentation", "guidelines", "hardware", "planning"], "requirements": {"degrees": ["degree holder"], "majors": ["it"], "languages": ["cantonese", "english"], "language_level": ["fluent", "good"], "hard_skills": ["documentation", "hardware", "mobile", "printers"], "soft_skills": ["communication skill", "independent"], "languages_combined": [{"language": "cantonese", "language_level": []}, {"language": "english", "language_level": ["good", "fluent"]}]}, "experience_required": {"duration": [], "field": ["infrastructure", "it", "procurement", "planning"]}}, {"job_id": "100003009054323", "location_code": "hk", "company": "MIT Technology System Limited", "job_title": "Jr. Oracle e-Business Technical Consultant", "description": "Responsibilities:\n\n\nDesign and develop technical solutions for Oracle EBS modules (mainly on Finance and Procurement)\nPerform unit, system and interface testing in support of Oracle EBS product\nDevelop technical and functional documentation such as requirements specifications, program designs, test plans and user guides\nTroubleshoot issues and provide supporting to our clients\n\n\u00a0Requirements:\n\n\nBachelor\u2019s Degree in Computer Science, Engineering, Information Technology or related disciplines\nMinimum 3 years of experience in IT profession with a minimum of 1 years\u2019 experience in the position of Oracle EBS Developer\nExperience in Oracle E-Business Suit R12.2 Finance and Procurement modules\nGood Knowledge of PL/SQL, Oracle Forms / Reports, Personalization, BI / XML Publisher and WebADI template development\nGood Knowledge of Oracle Open Interface, APIs and standard table structures\nExperienced with Workflow or OA Framework (customizations and extensions) development is a plus\nExperienced with Cloud integration is a plus\nGood command of spoken and written English and Chinese\nGood analytical, interpersonal and problem-solving skills\nPositive attitude, fast learning, energetic, able to perform in challenging environment\n\nWe offer a competitive remuneration package to the right candidate as well as an opportunity to grow within the Company. Interested parties should send us full resume with current & expected salary, and availability.\n\n*All personal data collected will be used for recruitment and employment related purpose only.", "employment_types": ["Full Time"], "selling_points": ["Min. 3 yr(s) experience in IT profession", "Min. 1 yr experience of Oracle EBS position", "Attractive salary, 5-day week,12 days annual leave"], "locations": ["Not Specified"], "categories": ["Information Technology (IT)", "Software Development", "Technical / Functional Consulting", "Others"], "post_time": "2022-01-17T09:09:34Z", "salary": {"currency": null, "max": null, "min": null, "period": "monthly", "term": null}, "salary_visible": false, "title_keywords": ["consultant"], "responsibilities": ["design and develop", "develop", "testing", "specifications", "troubleshoot", "documentation", "plans"], "requirements": {"degrees": ["degree", "bachelor"], "majors": ["related disciplines", "engineering", "computer science", "information technology"], "languages": ["english", "chinese"], "language_level": ["good command"], "hard_skills": ["plus", "bi", "problem-solving skills", "sql", "integration", "publisher", "pl", "oracle"], "soft_skills": ["positive attitude", "learning", "problem-solving skills", "energetic", "interpersonal"], "languages_combined": [{"language": "english", "language_level": ["good command"]}, {"language": "chinese", "language_level": ["good command"]}]}, "experience_required": {"duration": ["minimum of 1 years", "minimum 3 years"], "field": ["business", "developer", "it"]}}, {"job_id": "100003009045758", "location_code": "hk", "company": "Kepro Solutions Limited", "job_title": "Consultant/Associate Consultant - Data Services", "description": "Responsibilities:\u00a0\n\nBI, Data management project implementation (Data integration, Data Governance, Data security etc.).\nPrepare and conduct demonstration/presentation to clients and partners\nPrepare proposal and tender documents in response to clients\u2019 requirements (Construct, design, architect and describe a cost effective solution for potential customers; and\n\u00a0Involve in initial planning and design of projects and transform all business requirements into technical specifications.\n\n\u00a0Requirements:\n\nDegree in Computer Sciences / Information Technology / Data management or related discipline.\nMore than 3 year of experience on designing (scripting) and implementing schedule based ETL processes with ETL tools such as SSIS, Alteryx, Pentaho PDI, Informatica, DataStage, or other open source ETL tools such as Talend\nData Warehouse design and data mining knowledge\nExcellent presentation, communication, and interpersonal skills\nPrepare related documentations during the project life cycle\nAbility to provide efficient, timely, and reliable service to customers\u00a0\nSolid experience in BI, database management, data analyst and modeling.\nGood command of both written and spoken English and Chinese\nImmediate available in highly preferred\nWe offer a competitive remuneration package to the right candidate. Interested parties please send your full resume with\u00a0present and expected salary to us by\u00a0clicking 'Apply Now'.\n\n\nCompany Address: 9/F, The Whitney, 183 Wai Yip Street, Kwun Tong, Hong Kong\n\nKepro Solutions Website:\u00a0https://intranet.karingroup.com/IntranetApp/Default.aspx\n\n(We are an Equal Opportunity Employer and personal data collected would be used for recruitment purpose only.)", "employment_types": ["Full Time", "Permanent"], "selling_points": ["3+ years relating to data management solutions", "Provide efficient solutions in handling data", "5-day week, steady career path"], "locations": ["Kwun Tong"], "categories": ["Information Technology (IT)", "Product Management / Business Analyst", "Technical / Functional Consulting", "Data Scientist"], "post_time": "2022-01-15T03:49:31Z", "salary": {"currency": null, "max": null, "min": null, "period": "monthly", "term": null}, "salary_visible": false, "title_keywords": ["associate", "consultant"], "responsibilities": ["management", "cost", "tender documents", "data", "implementation", "design", "specifications", "planning"], "requirements": {"degrees": ["degree"], "majors": ["information technology"], "languages": ["english", "chinese"], "language_level": ["good command"], "hard_skills": ["bi", "data management", "data warehouse", "alteryx", "data mining", "documentations"], "soft_skills": ["efficient", "timely", "communication", "interpersonal skills", "reliable", "presentation"], "languages_combined": [{"language": "english", "language_level": ["good command"]}, {"language": "chinese", "language_level": ["good command"]}]}, "experience_required": {"duration": ["3 year"], "field": ["database management"]}}, {"job_id": "100003009043900", "location_code": "hk", "company": "Chandler Macleod Group (HK) Limited", "job_title": "VIP Support Engineer", "description": "Our client is a well-known global consumer product company with long history. They are in search for a VIP Support Engineer to join their growing business\n\nJob Responsibility\n\n\nProviding first line technical support to internal users - taking enquiries by phone and email\nDealing with problems for hardware, such as servers, computers and printers, and software programs\nHandling hardware service requests such as video conference setup, new hardware etc...\nTroubleshoot and identify technical issues and reporting to technical teams\nManaging junior support staff\n\nJob Requirements\n\n\nDegree in technology related studies\nMinimum 5 years of experience in Helpdesk/Service desk role with VIP support\nExcellent communication in spoken and written English is required\nStrong customer service mindset\nQuick reaction to problems and able to offer workaround solutions in short amount of time", "employment_types": ["Full Time", "Permanent"], "selling_points": ["Multinational company", "Generous salary package", "Convenient working location"], "locations": ["Not Specified"], "categories": ["Information Technology (IT)", "Support", "Application Specialist - Network", "Technical / Functional Consulting"], "post_time": "2022-01-13T02:22:51Z", "salary": {"currency": null, "max": null, "min": null, "period": "monthly", "term": null}, "salary_visible": false, "title_keywords": ["support engineer"], "responsibilities": ["reporting", "software", "technical support", "teams", "hardware", "troubleshoot", "setup"], "requirements": {"degrees": ["degree"], "majors": [], "languages": ["english"], "language_level": ["excellent"], "hard_skills": [], "soft_skills": ["communication", "customer service"], "languages_combined": [{"language": "english", "language_level": ["excellent"]}]}, "experience_required": {"duration": ["minimum 5 years"], "field": []}}, {"job_id": "100003009048750", "location_code": "hk", "company": "United Asia Finance Limited", "job_title": "Project Manager [new credit card business] (FinTech and Innovation)", "description": "Position Summary\n\nProject Manager is responsible for coordinating and completing FTD projects on time within budget and scope.\u00a0 Oversee all aspects of projects, monitor progress, control quality, assign resources and summarize progress of projects.\n\nJob Responsibilities\n\nCoordinate internal resources for the execution of projects\nEnsure that all projects are delivered on-time, within scope and within budget\nAssist in the definition of project scope and objectives, involving all relevant stakeholders and ensuring functional and non-functional feasibility\nDevelop a detailed project plan to monitor and track progress, and provide regular project status update\nMeasure project performance using appropriate tools and techniques\nCoordinate with BUSINESS USER to work out UAT schedule for the execution of user acceptance test.\nCoordinate with QA lead and Business Analyst to draw up the UAT test plan, test cases/scenarios and guide them to understand the UAT approach & objectives.\nMonitor the status and progress of UAT and ensure implementation can be arranged as scheduled.\nHelp BUSINESS USER to understand the change & impact of implementing the System Change and give them advice if they need to update/change related operational procedures and manuals.\n\nJob Requirements\n\nDegree holders or above major in Information System or Computer Science or related discipline preferable\nMinimal 8 years IT solid experience in application project management and business analysis in either finance, banking, or other financial sector related fields\nSolid experience in managing and liaison with IT people or software vendors\nLogical thinker, results-oriented and with excellent project management, communication, problem solving and analytical skills\nExcellent client-facing and internal communication skills\nExcellent written and verbal communication skills\nProject Management Professional (PMP) / PRINCE II certification is a plus\nAgile / Scrum experience\n\nWe offer attractive remuneration package which includes double pay and discretionary bonus. Interested parties please send your CV indicating your current salary, expected salary and availability to HR Department, by clicking \"Apply Now\"\n\n(Personal data collected will be treated in the strictest confidence and will be handled by authorized personnel for recruitment-related purposes only. Applicants who do not hear from us within 3 months may consider their application unsuccessful and their data will be destroyed within 24 months of receipt.)", "employment_types": ["Full Time"], "selling_points": ["Degree in Information System, Computer Science", "At least 8 yrs in application project management", "PMP a plus"], "locations": ["Wan Chai"], "categories": ["Information Technology (IT)", "IT Project Management / Team Lead", "Software Development", "Technical / Functional Consulting"], "post_time": "2022-01-14T07:12:59Z", "salary": {"currency": null, "max": null, "min": null, "period": "monthly", "term": null}, "salary_visible": false, "title_keywords": ["project manager"], "responsibilities": ["uat", "budget", "monitor", "project plan", "coordinate with", "develop", "coordinate", "implementation", "operational procedures", "schedule", "plan"], "requirements": {"degrees": ["degree"], "majors": ["computer science"], "languages": [], "language_level": [], "hard_skills": ["plus", "agile", "project management professional", "analysis", "information system", "analytical skills", "problem solving", "project management", "pmp"], "soft_skills": ["communication skills", "agile", "communication", "project management", "problem solving and analytical skills", "client-facing"], "languages_combined": []}, "experience_required": {"duration": ["8 years"], "field": ["related", "finance", "project management", "it", "banking", "business analysis", "financial"]}}, {"job_id": "100003009052005", "location_code": "hk", "company": "Giesecke & Devrient Asia Pacific Ltd", "job_title": "Senior Product Application Engineer / Product Application Engineer", "description": "MAJOR DUTIES AND RESPONSIBILITIES include the followings. Other duties may be assigned as necessary to fulfill optimum efficiency of this position:\n\nDesign and implement sensor decision algorithms for banknote products\nParticipate in product support and conduct User Acceptance Test with customers\nParticipate in project activities, e.g., collection of user requirements, and maintain all technical specifications\nWork closely with global and local support teams for any trouble-shooting in the diagnosis of technical issues experienced by the end users\nMaintain track record of reported incidents and provide regular updates to internal teams or end users\nIdentify problems and calibrate product configuration and application\u00a0\n\nREQUIREMENT:\n\nDegree holder in Computing, Electronics, Electrical, Mechanical Engineering or equivalent;\n2 years working experience in product support or development. Fresh graduate will also be considered as Junior Product Engineer.\nExcellent in problem solving and trouble shooting skills\u00a0\nKnowledge in Software Programming is plus\nGood command of both written and spoken English and Chinese\nWiling to work and travel globally\n\nAn attractive package that is commensurate with successful candidate's qualifications and experience will be offered. Please apply with detailed resume including availability, current & expected salary and contact number to HR Department, Giesecke & Devrient Asia Pacific Limited, Room 2901 Hysan Place, 500 Hennessy Road, Causeway Bay, Hong Kong or apply in JobsDB.com directly.\n\nAll information received will be kept in strict confidence and only for employment-related purpose.", "employment_types": ["Full Time", "Permanent"], "selling_points": ["Support and troubleshoot on products and solutions", "Communicate with software users and customer IT", "Software system deployment and configuration"], "locations": ["Causeway Bay"], "categories": ["Information Technology (IT)", "Application Specialist - Software", "Support", "Technical / Functional Consulting"], "post_time": "2022-01-17T01:48:38Z", "salary": {"currency": null, "max": null, "min": null, "period": "monthly", "term": null}, "salary_visible": false, "title_keywords": ["application engineer"], "responsibilities": ["other duties", "configuration", "teams", "design", "specifications", "maintain"], "requirements": {"degrees": ["fresh graduate", "degree holder"], "majors": ["mechanical engineering"], "languages": ["english", "chinese"], "language_level": ["good command"], "hard_skills": ["problem solving", "plus", "programming"], "soft_skills": ["problem solving", "confidence", "detailed"], "languages_combined": [{"language": "english", "language_level": ["good command"]}, {"language": "chinese", "language_level": ["good command"]}]}, "experience_required": {"duration": ["2 years"], "field": ["development"]}}, {"job_id": "100003009045820", "location_code": "hk", "company": "Kinetix Systems Ltd", "job_title": "Pre-sales Solution Manager / Consultant", "description": "Responsibilities\n\nTake lead on technical aspects of solutions, such as product and solution briefings, proposal preparations, pricing strategy, proof-of-concept work, coordination of supporting technical resources etc.\nEvaluate clients' project needs and propose the most optimal solutions and approaches\nGather user requirements and define scope of work\nCollaborate between professional services department and customers on-going project when required\nPrepare user guide and solution comparison reports\nWork with Sales Department to identify business opportunities\nRequirements\n\n5+ years of experience in pre-sales role\nEquip with commercial and business sense, experience in technical product management cycle\nEquip with presentation skills, with experience in presenting to senior management/client\u00a0\nUnderstand application development lifecycle, workflow, integration and infrastructure design\nAcquire and able to apply commercial and technical expertise by staying up-to-date in industry and market trends\nGood command of both spoken and written English and Cantonese, and Mandarin\nFamiliar with production solution will be a definite advantage\nIf you enjoy working in a friendly and challenging working environment, please send your full resume with your availability, last/current and expected salary by clicking \u201cApply Now\u201d.\n\n*All information collected will be used for recruitment purpose only and will be kept strictly confidential*", "employment_types": ["Full Time", "Permanent"], "selling_points": ["Excellent in client facing & communication skills", "Key person in Inter-departmental collaboration", "Comprehensive remuneration package"], "locations": ["Kwun Tong"], "categories": ["Information Technology (IT)", "IT Project Management / Team Lead", "Technical / Functional Consulting", "Others"], "post_time": "2022-01-13T08:48:45Z", "salary": {"currency": null, "max": null, "min": null, "period": "monthly", "term": null}, "salary_visible": false, "title_keywords": ["manager", "consultant", "sales"], "responsibilities": ["collaborate", "identify business opportunities", "evaluate", "reports", "coordination"], "requirements": {"degrees": [], "majors": [], "languages": ["cantonese", "english", "mandarin"], "language_level": ["good command"], "hard_skills": ["integration"], "soft_skills": ["enjoy working", "presentation skills", "friendly", "business sense"], "languages_combined": [{"language": "cantonese", "language_level": ["good command"]}, {"language": "english", "language_level": ["good command"]}, {"language": "mandarin", "language_level": ["good command"]}]}, "experience_required": {"duration": ["5+ years"], "field": ["product management", "commercial", "management", "business"]}}, {"job_id": "100003009054812", "location_code": "hk", "company": "EY Mtel Solutions Limited", "job_title": "Mobile Application Developer (iOS / Android / React Native)", "description": "Responsibilities:\n\nDevelop new mobile apps (iOS / Android / React Native)\nMaintain and enhance existing apps\nTroubleshoot and debug\nCollaborate with project managers, UX designers, backend developers and quality assurance to deliver client projects\n\nRequirements:\n\n\nTo qualify for the role you must have:\n\nHigher Diploma or Degree in Computer Science / IT or related disciplines\nGood communication and interpersonal skills\nResponsible and able to work under pressure\nProficiency in Objective-C / Swift / Java / Kotlin\nSolid experience in iOS / Android development\nKnowledge on cross platform development is an advantage\n1 - 2 year experience in mobile app development (Fresh graduates are also welcome)\n\nWhat working at EY offers:\n\nSupport, coaching and feedback from some of the most engaging colleagues around\nOpportunities to develop new skills and progress your career\nThe freedom and flexibility to handle your role in a way that\u2019s right for you\n\nIf you can confidently demonstrate that you meet the criteria above, please contact us as soon as possible.\n\nJoin us in building a better working world.\n\nApply now.", "employment_types": ["Full Time", "Permanent"], "selling_points": ["Develop and maintain cool mobile applications", "Work with a great team, for great brands", "Apply latest mobile technologies and techniques"], "locations": ["Kwun Tong"], "categories": ["Information Technology (IT)", "Software Development", "Technical / Functional Consulting", "Mobile / Wireless Communications"], "post_time": "2022-01-17T11:16:09Z", "salary": {"currency": null, "max": null, "min": null, "period": "monthly", "term": null}, "salary_visible": false, "title_keywords": ["developer"], "responsibilities": ["collaborate with", "quality", "develop", "maintain", "troubleshoot"], "requirements": {"degrees": ["diploma", "degree"], "majors": ["related disciplines", "it", "computer science"], "languages": [], "language_level": [], "hard_skills": ["android development", "java", "objective-c", "mobile", "swift", "kotlin"], "soft_skills": ["communication and interpersonal skills", "responsible", "work under pressure"], "languages_combined": []}, "experience_required": {"duration": ["1 - 2 year"], "field": ["development"]}}, {"job_id": "100003009039596", "location_code": "hk", "company": "HKBN Enterprise Solutions HK Limited (HKBNES)", "job_title": "Service Delivery Manager (ESSID)", "description": "You will create impact via...\n\nProvide deep-level support and IT architecture service to customers\nDesign, implement and support technology solutions and integrated systems solutions to customers\nProvide technical consultancy and prepare proposals/reports/documentations for solutions to meet customers\u2019 technology and service requirements\nPerform as Project Manager and assist in IT Service Management whenever needed\nProvide IT Infrastructure planning and consulting services to customers\nEnabler of ITIL Life Cycle and industrial and technology standards\n\nThe follow attributes will be valued...\n\nUniversity graduate with above 5 years in relevant IT infrastructure roles\nExperience in supporting and servicing core enterprise infrastructure environment in corporations\nSolid and hands-on knowledge in Wintel Solutions (e.g. operating systems, Active Directory, Exchange email with archiving solution, MS System Center, storage and backup solution, etc.)\nKnowledge in virtualization technology such as VMware and Hyper-V, and backup technology such as Veeam, Commvault and Symantec is preferred\nKnowledge/experience in other IT infrastructure areas (e.g. Infrastructure networking, heterogeneous IT environment with different Wintel/Unix/Linux platform, DR and virtualization, Oracle and SQL database clustering, infrastructure design, Data Centre, etc.) is an advantage\nStrong team player with strong verbal and written communication skills;\nStrong decision making, problem solving skills, project management skills,\u00a0highly organized, detail oriented and self-motivating\nAbility to work calmly under pressure, multitask, prioritize independently and within a team environment\nITIL Foundation/MCSE/CCNA certified\n\nWhat you get in return\u2026\n\nApart from competitive salary package and benefits, in HKBN, you will work flexibly under our Talent-first culture and we uphold Life-Work Priority. Examples of our flexible initiatives:\n\nFive-day work week and shorten working hours (8 hours including 1 hour 15 mins meal break)\nHalf Day Off Friday once a month (compensation leave for Talents who work on shift)\nHalf Day Off on Festival Eve (compensation leave for Talents who work on shift)\nUnique leaves arrangement: Family-care leave, Anniversary leave, Bonus leave, Volunteer leave, Sabbatical leave, etc.\nComprehensive medical and life insurance coverage\nUpgraded maternity leave and paternity leave\nDiscounted Talent plan offers including broadband and mobile plans and other promoted products\nEducation subsidies and Examination leave\nYear-end discretionary bonus", "employment_types": ["Full Time", "Permanent"], "selling_points": ["Provide strong support & IT architecture service", "IT Infrastructure planning and consulting services", "LIFE-Work Priority & Talent-First Culture"], "locations": ["Kowloon Bay"], "categories": ["Information Technology (IT)", "IT Project Management / Team Lead", "Support", "Technical / Functional Consulting"], "post_time": "2022-01-11T10:13:26Z", "salary": {"currency": null, "max": null, "min": null, "period": "monthly", "term": null}, "salary_visible": false, "title_keywords": ["manager"], "responsibilities": ["management", "clustering", "it service", "it infrastructure", "consulting", "active directory", "data", "systems", "infrastructure", "design", "communication", "project management", "reports", "database", "architecture", "operating systems", "planning"], "requirements": {"degrees": ["university graduate"], "majors": ["it"], "languages": [], "language_level": [], "hard_skills": ["itil", "hyper-v", "virtualization technology", "linux", "oracle", "vmware", "active directory", "mcse", "ccna", "sql", "project management", "problem solving skills", "documentations", "exchange"], "soft_skills": ["communication skills", "organized", "independently", "under pressure", "project management skills", "detail oriented", "deep", "prioritize", "multitask", "hands-on", "problem solving skills", "team player", "active", "decision making"], "languages_combined": []}, "experience_required": {"duration": [], "field": ["infrastructure", "it"]}}, {"job_id": "100003009048737", "location_code": "hk", "company": "Gimmick House Ltd", "job_title": "IT Project Executive / Assistant", "description": "Responsibilities:\nJoin the team to provide end-to-end IT Solution and digital related project delivery\u00a0\nProvide project assistance on project initiation including scoping, costing, planning and feasibility for products, platform and app development\nSupport project governance, risk management and change management\nWork closely with clients to gather requirements and technical details to fully scope out solution\nCollaborate with UX, marketing, creative, technical teams through all stages of project from strategy and concept, design, technical planning, prototyping, production, QA to deployment or other supporting activities\nSource, plan and manage both internal resources and external partners/vendors\u00a0\nMust posses an active understanding of digital including strategy, information and visual design, technology, social media and rich media\nAssist to prepare documents to pitch clients, e.g. marketing plan, schedule, budget etc.\nParticipate in ad-hoc projects and other assigned duties\nRequirements:\nBachelor's degree in Information Systems or related disciplines\nExecutive grade with 2+ years of experience in project management\nA recognised qualification such as CSM or PMP would be an advantage\nRelevant experience in website revamp and Digital project development\nAbility to follow and implement Agile project management methodologies\nExperience\u00a0managing large scale projects\nExperience running a variety of digital projects, from web apps, banners to platforms, using a variety of technologies and mediums\nExcellent communication skills with spoken and written English, Cantonese preferred\nImmediately available is highly preferred", "employment_types": ["Full Time", "Permanent"], "selling_points": ["IT Solution & Digital Projects Management", "Innovative, break non-rules, challenge yourself", "Work-life balance, Asia regional exposure"], "locations": ["Kwun Tong"], "categories": ["Information Technology (IT)", "IT Project Management / Team Lead", "IT Management", "Technical / Functional Consulting"], "post_time": "2022-01-14T09:04:34Z", "salary": {"currency": null, "max": null, "min": null, "period": "monthly", "term": null}, "salary_visible": false, "title_keywords": ["assistant", "it project executive"], "responsibilities": ["collaborate with", "social media", "management", "change management", "budget", "teams", "design", "marketing plan", "schedule", "plan", "visual", "ad-hoc projects", "prepare documents", "planning"], "requirements": {"degrees": ["degree", "bachelor"], "majors": ["related disciplines"], "languages": ["cantonese", "english"], "language_level": ["excellent"], "hard_skills": ["project management", "pmp", "web apps", "agile"], "soft_skills": ["communication skills", "project management", "agile"], "languages_combined": [{"language": "cantonese", "language_level": ["excellent"]}, {"language": "english", "language_level": ["excellent"]}]}, "experience_required": {"duration": ["2+ years"], "field": ["project management", "development", "relevant experience", "digital"]}}, {"job_id": "100003009050736", "location_code": "hk", "company": "Hutchison Telecommunications (Hong Kong) Limited", "job_title": "Digital Service Development Officer", "description": "Responsibilities:\n\n\nManage and design all Marketing programs roll out logistics and preparation in both Mass and Corp Business Lead key system customizations on business issue resolution and service improvement\nWork out the implementation of marketing policy and business requirement; and to define an effective frontend logistics flow\nManage end-to-end UAT/PAT to ensure the product, service and system enhancement is working properly before put live\nDevelop in-house service tool to uplift the customer experience and satisfaction\nStrive system enhancement to offload the backend manual process support\nCall center service system development & enhancement\nKey participant in Digital Transformation project to contribute towards mapping customer journeys and business\n\nRequirements:\n\n\nHigher Diploma or above in Business, Statistics, Marketing or related discipline\nMinimum 4 years or above working experiences in Customer Service, Marketing and Business Support preferably gained in online/ banking/ telecommunications industry\nGood Business and customer service sense, with strong negotiation, planning and organization skills\nStrong communication skill and able to distill complex information and translate into clear indicated actions and frontline information\nGood analytical thinking, self-motivated and independent judgment and able to deliver under tight timelines\nProficiency in Microsoft Offices and Chinese Word processing\nExcellent command of written & spoken in English and Chinese\u00a0\n\n\n\nApart from competitive remuneration package and exciting opportunity for career development within the Group, we provide attractive employee benefits such as free company shuttle, free company SIM card and preferential SIM plan offers, comprehensive medical & insurance schemes, as well as full range of other employee well-being provisions.\u00a0\n\nInterested parties, please apply with full resume, present and expected salary, by clicking \u201cAPPLY NOW\u201d. Please quote the reference number on the e-mail subject.\n\nWe are an equal opportunity employer and welcome applications from all qualified candidates. Personal data collected will be treated in the strictest confidence and handled confidentially by authorised personnel for recruitment-related purposes only within the CK Hutchison Group of companies. The personal data of unsuccessful applicants will be destroyed after the recruitment exercise pursuant to the requirements of the Personal Data (Privacy) Ordinance in Hong Kong.", "employment_types": ["Full Time", "Permanent"], "selling_points": [], "locations": ["Tsing Yi"], "categories": ["Information Technology (IT)", "Support", "Technical / Functional Consulting", "Marketing / Public Relations", "Marketing - General / Support"], "post_time": "2022-01-14T11:15:01Z", "salary": {"currency": null, "max": null, "min": null, "period": "monthly", "term": null}, "salary_visible": false, "title_keywords": ["service development officer"], "responsibilities": ["uat", "implementation", "design", "develop", "resolution", "logistics"], "requirements": {"degrees": ["higher diploma or above"], "majors": ["business", "statistics", "marketing"], "languages": ["english", "chinese"], "language_level": ["proficiency", "excellent"], "hard_skills": ["chinese word processing"], "soft_skills": ["self-motivated", "independent", "negotiation", "communication skill", "clear", "customer service", "comprehensive", "organization skills"], "languages_combined": [{"language": "english", "language_level": ["excellent"]}, {"language": "chinese", "language_level": ["proficiency", "excellent"]}]}, "experience_required": {"duration": ["minimum 4 years"], "field": ["business support", "customer service", "marketing", "banking", "telecommunications"]}}, {"job_id": "100003009050380", "location_code": "hk", "company": "GrammyTech Ltd", "job_title": "Pre Sales Manager", "description": "System Integrator is looking for a Pre Sales Manager in Hong Kong\u00a0\n\nRequirement :\n\n\nDegree holder\nAt least 3 years in pre sales support of IT infrastructure products\nHead a small consulting team for providing support to sales department\nExcellent interpersonal and communication skills\nGood presentation techniques especially in front of clients\n\nInterested parties, please send your full resume in word format together with current and expected salary to danielmo@ grammytech.com.\n\n(Personal data collected will be used for recruitment purposes only)", "employment_types": ["Full Time"], "selling_points": ["IT Pre Sales Support", "IT infrastructure, traditional and cloud platform", "People Manager"], "locations": ["Kwun Tong"], "categories": ["Information Technology (IT)", "Technical / Functional Consulting"], "post_time": "2022-01-14T10:15:34Z", "salary": {"currency": null, "max": null, "min": null, "period": "monthly", "term": null}, "salary_visible": false, "title_keywords": ["sales manager"], "responsibilities": ["communication", "providing support", "it infrastructure", "consulting"], "requirements": {"degrees": ["degree holder"], "majors": [], "languages": [], "language_level": [], "hard_skills": ["small", "sales support"], "soft_skills": ["communication skills", "presentation", "interpersonal"], "languages_combined": []}, "experience_required": {"duration": [], "field": []}}, {"job_id": "100003009049229", "location_code": "hk", "company": "4PX Express Co., Limited", "job_title": "IT Engineer/ IT \u5de5\u7a0b\u5e2b", "description": "System Integrator is looking for a IT Customer Service Manager in Hong Kong\u00a0\n\nRequirement :\n\n\nDegree holder\nAt least 10 years in support and customer service of IT infrastructure products\nHead a small consulting team for providing customer service to clients\nExcellent interpersonal and communication skills\nDeal with Tier 1, 2, 3 level of customer service\n\nInterested parties, please send your full resume in word format together with current and expected salary to danielmo@ grammytech.com.\n\n(Personal data collected will be used for recruitment purposes only)", "employment_types": ["Full Time"], "selling_points": ["IT helpdesk, user desktop problems", "equipment and related software maintenance", "installation and troubleshooting of office softwar"], "locations": ["Tin Shui Wai"], "categories": ["Information Technology (IT)", "Hardware", "Support", "Technical / Functional Consulting"], "post_time": "2022-01-14T08:17:37Z", "salary": {"currency": null, "max": null, "min": null, "period": "monthly", "term": null}, "salary_visible": false, "title_keywords": ["engineer"], "responsibilities": ["communication", "customer service", "it infrastructure", "consulting"], "requirements": {"degrees": ["degree holder"], "majors": [], "languages": [], "language_level": [], "hard_skills": ["small"], "soft_skills": ["communication skills", "customer service", "interpersonal"], "languages_combined": []}, "experience_required": {"duration": [], "field": []}}, {"job_id": "100003009051423", "location_code": "hk", "company": "Jardine Restaurant Group", "job_title": "IT Officer - (POS & CMS)", "description": "Our client, a leading bank, is looking for an experienced IT Audit Manager to join their Audit 3LOD team. The successful candidate will be bringing IT audits especially for their Cyber Security and new digital banking initiatives.\u00a0\n\nResponsibilities:\n\nLead the IT Audit across audit plans, and methods across various IT areas including Cyber Security, Digital, Banking Procedures and IT Controls.\nConduct risk assessment, audit planning, audit testings, control evaluation, etc. Provide audits finding reports, follow-up, and verifications.\nDevelop and monitor cybersecurity development initiatives, through design and perform of continuous risk assessment methodology\nPerform Investigation on technology-related frauds and incidents.\nWork closely with the management through tracking and reporting function, to ensure a timely response to executives, board, and regulators.\nStay up-to-date with evolving industry and regulatory change requirements which may impact the business and technology team.\nUpdate and maintain Audit systems and provide suggestions on efficiency and effectiveness improvement.\u00a0\n\n\u00a0Required Skills/Experience:\n\nAt least 4 years of experience in the IT Audit area, ideally with exposure to the banking / financial services industry.\nUnderstanding regulatory requirements including HKMA is highly preferable.\nUnderstanding of banking information security and information technology governance and assessment.\nOutstanding communication and interpersonal skills. Ability to work effectively with all levels of the organization.\nStrong analytical skills required to enable independent research and accurate assessments of risk management process effectiveness and adherence to regulatory requirements.\nCISA, CISM, CISSP, or equivalent industry certification is preferred.\n\nIf this outstanding opportunity sounds like your next career move, please send your resume in Word format to Danny Kwan at resume(at)pinpointasia(dot)com and put IT Audit Manager - Leading Bank in the subject header.\n\nData provided is for recruitment purposes only.", "employment_types": ["Full Time"], "selling_points": ["POS & CMS", "Technical Support", "Vendors Deployments"], "locations": ["Hung Hom"], "categories": ["Information Technology (IT)", "Support", "Network & System", "Technical / Functional Consulting"], "post_time": "2022-01-15T15:43:31Z", "salary": {"currency": null, "max": null, "min": null, "period": "monthly", "term": null}, "salary_visible": false, "title_keywords": ["it officer"], "responsibilities": ["information security", "cyber security", "data", "regulatory requirements", "audit", "design", "communication", "maintain", "evaluation", "plans", "control", "monitor", "develop", "reports", "banking", "reporting", "management", "procedures", "investigation", "audits", "tracking", "systems", "recruitment", "planning"], "requirements": {"degrees": [], "majors": [], "languages": [], "language_level": [], "hard_skills": ["hkma", "word", "analytical skills", "cyber security"], "soft_skills": ["work effectively", "independent", "timely", "analytical skills", "communication and interpersonal skills", "accurate"], "languages_combined": []}, "experience_required": {"duration": ["at least 4 years"], "field": ["financial services industry", "it", "audit", "banking"]}}, {"job_id": "100003009037326", "location_code": "hk", "company": "EonConnect Solutions Limited", "job_title": "Solution Consultant", "description": "Our clients, including World's leading ICT Solutions Vendors, System Integrators, Network Operators and Telecom Carriers are looking for various technical talents to join their team. If you are looking for a career move, please apply on this job advert and our consultants would contact you for a discussion\n\nResponsibilities:\u00a0\n\nIdentify, understand and define customer needs, objectives and business requirements.\nWork with the sales representative to design the IP network/ Network Infrastructure/ Cloud Virtualization/ Security solutions to clients included switches, routers, security gateway, Storage, Server, application systems, Data Center solutions etc.\nAlign with internal parties for\u00a0technical materials including sales presentations, proposals, demonstrations and tender bidding\nRequirements:\n\nBachelor\u2019s Degree in Computer Science, Business or other related fields.\nAround 3-5 years pre-sales experience in network services provider, SI or Vendors\nMore experience would be considered as Senior Consultant\nSolid technical hand-on experience in Security/ networking/ network infrastructure/ Cloud or Data Center Professionals\nAny of related technical certification holder would be an added advantages\n\nInterested parties please click \"APPLY NOW\", or send full resume with expected salary\u00a0to\u00a0hr2@premieraegis. com\n\nAll applications and data collected will be treated in strict confidence and used exclusively for recruitment purposes only \u00a0\u00a0", "employment_types": ["Full Time", "Permanent"], "selling_points": ["Cyber security & Advance Network Tech Exposure", "Varies Consultation & Project Exposure", "Excellent Career Development Opportunities"], "locations": ["Kwai Fong"], "categories": ["Information Technology (IT)", "Security", "Network & System", "Technical / Functional Consulting"], "post_time": "2022-01-11T02:29:09Z", "salary": {"currency": null, "max": null, "min": null, "period": "monthly", "term": null}, "salary_visible": false, "title_keywords": ["consultant"], "responsibilities": ["network infrastructure", "data", "design", "presentations", "tender", "application systems", "internal parties"], "requirements": {"degrees": ["degree", "bachelor"], "majors": ["business", "computer science"], "languages": [], "language_level": [], "hard_skills": [], "soft_skills": [], "languages_combined": []}, "experience_required": {"duration": ["3-5 years"], "field": ["infrastructure", "security"]}}, {"job_id": "100003009051464", "location_code": "hk", "company": "Apple Service Consultancy Co., Limited", "job_title": "Business Analyst / Application Consultant / Functional Consultant (ERP / HRMS / CRM / BPM)", "description": "Currently we are helping a listed company (In house Position) to look for Database Professional to join their team\n\n\n\nResponsibilities:\n\nResponsible for the DB Team and Whole SDLC\nResponsible for capacity planning & security compliance\nResponsible for the documentation such as technical and reference documents\nCooperating with internal and external parties\n\nRequirements:\n\nHD or above in Computer Science or other related\nHolder of Oracle certification will be advantage\nAt least 6-year experience in DBA\nMust experience in at least one of following:\nExperience in OEM would be big plus\nOracle RAC or\nDataGuard", "employment_types": ["Full Time", "Permanent"], "selling_points": ["Computer Science / Information Technology", "Minimum 1-2 years working experience", "Fresh Graduate will also be considered"], "locations": ["Kowloon Bay"], "categories": ["Information Technology (IT)", "Application Specialist - Software", "Support", "Technical / Functional Consulting"], "post_time": "2022-01-16T21:50:28Z", "salary": {"currency": null, "max": null, "min": null, "period": "monthly", "term": null}, "salary_visible": false, "title_keywords": ["business analyst", "consultant"], "responsibilities": ["documentation", "compliance", "internal and external parties", "planning"], "requirements": {"degrees": [], "majors": [], "languages": [], "language_level": [], "hard_skills": ["plus", "oracle"], "soft_skills": [], "languages_combined": []}, "experience_required": {"duration": ["at least 6-year"], "field": []}}, {"job_id": "100003009051039", "location_code": "hk", "company": "The Wharf Group", "job_title": "System Administrator", "description": "Responsibilities\n\n\u00a0\u00a0\u00a0\u00a0\u00a0\u00a0 Engage in advanced technology projects of AI, IoT, VR/AR/MR and Robotics;\n\u00a0\u00a0\u00a0\u00a0\u00a0\u00a0 Conduct functional design and development;\n\u00a0\u00a0\u00a0\u00a0\u00a0\u00a0 Research and participate in new technology development;\n\u00a0\u00a0\u00a0\u00a0\u00a0\u00a0 Responsible for development, enhancement and maintenance for applications\n\u00a0\u00a0\u00a0\u00a0\u00a0\u00a0 Provide support to application systems including trouble shooting, bug fixing and ad-hoc queries\n\u00a0\u00a0\u00a0\u00a0\u00a0\u00a0 Conduct research and evaluate emerging software technologies\n\nRequirements\n\n\u00a0\u00a0\u00a0\u00a0\u00a0\u00a0 Degree or above in IT, CS and Computing Engineering or equivalent;\n\u00a0\u00a0\u00a0\u00a0\u00a0\u00a0 1 year or above relevant experience in business analyst, advanced technology\u00a0analyst or equivalent;\u00a0\n\u00a0\u00a0\u00a0\u00a0\u00a0\u00a0 Passion in new advanced technology;\n\u00a0\u00a0\u00a0\u00a0\u00a0\u00a0 Well-developed analytical and problem solving skills;\n\u00a0\u00a0\u00a0\u00a0\u00a0\u00a0 Excellent interpersonal and communication skill;\n\u00a0\u00a0\u00a0\u00a0\u00a0\u00a0 Excellent verbal and written skill in English and Chinese;\n\u00a0\u00a0\u00a0\u00a0\u00a0\u00a0 Deep intellectual curiosity, detail-oriented and independently;\n\u00a0\u00a0\u00a0\u00a0\u00a0\u00a0 Knowledge in one or more of the following areas will be an advantage:\nFlutter / React Native / Swift / Kotlin\nLatest technology (e.g. IoT, AI, Robotics, Blockchain)\nAPI integrations\nEdge and Cloud computing\nUI / UX design concepts\n\u00a0Knowledge of Construction will be an advantage\n\nInterested parties please apply with a detailed resume stating expected salary and date of availability to the HR Manager through fax at 2833 5441 or e-mail by clicking \"APPLY NOW\".\n\nCompany Website:\u00a0https://xensetech.hk/\n\n\nAll personal data provided will be used strictly in accordance with our \u201cPersonal Information Collection Statement Pertaining to Recruitment\u201d, a copy of which is available upon written request to us by E-mail.", "employment_types": ["Full Time", "Permanent"], "selling_points": [], "locations": ["Tsim Sha Tsui"], "categories": ["Information Technology (IT)", "IT Project Management / Team Lead", "Network & System", "Technical / Functional Consulting"], "post_time": "2022-01-15T01:26:06Z", "salary": {"currency": null, "max": null, "min": null, "period": null, "term": null}, "salary_visible": false, "title_keywords": ["system administrator"], "responsibilities": ["ad-hoc", "provide support", "robotics", "ar", "maintenance", "software", "design", "evaluate", "application systems", "conduct research"], "requirements": {"degrees": ["degree or above"], "majors": ["it", "engineering"], "languages": ["english", "chinese"], "language_level": ["excellent"], "hard_skills": ["blockchain", "ai", "react native", "kotlin", "swift", "problem solving skills"], "soft_skills": ["independently", "advanced", "passion in", "communication skill", "deep", "detail-oriented", "analytical and problem solving skills", "interpersonal"], "languages_combined": [{"language": "english", "language_level": ["excellent"]}, {"language": "chinese", "language_level": ["excellent"]}]}, "experience_required": {"duration": ["1 year"], "field": ["business", "relevant experience"]}}, {"job_id": "100003009053027", "location_code": "hk", "company": "PCCW Media", "job_title": "Full Stack Developer (MOOV), Hong Kong", "description": "Responsibilities:\nSupport\u00a0direct sales force on enterprise solution\nProvide consultative service and technical advice to our business clients\u00a0\nGather customer requirements and prepare solution proposals\nProvide solution design, demonstration, POC, evaluation and documentation\nCommunicate between users and development team, liaise with the team on resource allocation\nKeep track on project status and provide professional recommendations\nProvide roll-out and post-implementation support\nExplore new business opportunities and achieve assigned target\nCoordinate with internal departments and vendors for order processing and logistic arrangement\nRequirements:\nDiploma\u00a0in Computer Science / Information Technology or relevant disciplines\nMinimum 2 years relevant working experiences, particular experience in IT Consulting, Pre-sales or related industry\nMCSE/ MCITP/ MCP, IT and networking are preferred\nSound knowledge on Print Management / Document Solution / Business Process Automation will be an advantage\nGood command of both spoken and written English, Cantonese and Mandarin\nIndependent and self-motivated\nGood team player with strong communication and analytical skills\nCandidate with more experience will be considered as\u00a0Senior Solution Consultant\n\nInterested parties, please click \"Apply Now\" to submit your application.\n\nPersonal data collected will be used for recruitment purpose only.\n", "employment_types": ["Full Time"], "selling_points": [], "locations": ["Kowloon Bay"], "categories": ["Information Technology (IT)", "Application Specialist - Software", "Software Development", "Technical / Functional Consulting"], "post_time": "2022-01-17T05:12:21Z", "salary": {"currency": null, "max": null, "min": null, "period": "monthly", "term": null}, "salary_visible": false, "title_keywords": ["developer"], "responsibilities": ["explore new business opportunities", "technical advice", "coordinate with", "implementation", "design", "logistic arrangement", "liaise with", "order processing", "evaluation", "documentation"], "requirements": {"degrees": ["diploma"], "majors": ["computer science", "information technology"], "languages": ["cantonese", "english", "mandarin"], "language_level": ["good command"], "hard_skills": ["mcse", "analytical skills"], "soft_skills": ["good team player", "self-motivated", "independent", "analytical skills", "communication"], "languages_combined": [{"language": "cantonese", "language_level": ["good command"]}, {"language": "english", "language_level": ["good command"]}, {"language": "mandarin", "language_level": ["good command"]}]}, "experience_required": {"duration": ["minimum 2 years"], "field": ["related", "it", "consulting"]}}, {"job_id": "100003009050771", "location_code": "hk", "company": "The Hong Kong Polytechnic University", "job_title": "Specialist / Assistant Specialist (System Infrastructure) (three posts)", "description": "Job Responsibilities:\n\nProvide the system development services for HKSARG projects and Supply Chain Management (SCM) Solution for customers of various industries.\nParticipate in the whole development life cycle including requirement study, design solution, prototyping, preparing specification, development, system testing and UAT support and production rollout.\nWork with Project Manager / Consultant / System Analyst / Analyst Programmer to deliver the System Solution.\n\n\u00a0Requirements:\n\nHolder of Higher Diploma or higher accreditation in IT or related disciplines\n4 Years IT experience with minimum 2 years SA / AP experience in Java web application development, implementation and system integration\nProficiency in J2EE, Struts, Spring, JSP, JSF, Hibernate, JavaScript, XML, HTML, CSS, JSON, RDBMS (Oracle / MSSQL), Application Servers (JBoss / Wildfly / Websphere).\nExperience on HKSARG projects / Agile development would be an advantage\nGood communication skills in English", "employment_types": ["Full Time"], "selling_points": [], "locations": ["Not Specified"], "categories": ["Information Technology (IT)", "Network & System", "Technical / Functional Consulting", "Others"], "post_time": "2022-01-14T11:21:41Z", "salary": {"currency": null, "max": null, "min": null, "period": "monthly", "term": null}, "salary_visible": false, "title_keywords": ["specialist", "assistant"], "responsibilities": ["management", "uat", "design", "testing"], "requirements": {"degrees": ["diploma"], "majors": ["related disciplines", "it"], "languages": ["english"], "language_level": ["good"], "hard_skills": ["ap", "java", "hibernate", "web application development", "servers", "agile", "struts", "jsf", "html", "mssql", "javascript", "spring", "integration", "css", "oracle"], "soft_skills": ["communication skills", "agile"], "languages_combined": [{"language": "english", "language_level": ["good"]}]}, "experience_required": {"duration": ["4 years", "minimum 2 years"], "field": ["development", "application development", "it experience"]}}, {"job_id": "100003009050810", "location_code": "hk", "company": "Ztore HK Limited", "job_title": "Devops Engineer", "description": "Microsoft is looking for the right candidate to fill in below position.\n\n\n\n**Job description and responsibility**\u00a0\n\nCloud Solution Architects (CSAs) play a critical role in working with Startups / ISV to provide deep technical support through solution build and first mile customer engagements such as Proof of Concepts, Architectural Design Sessions (ADS), and Hackathons. The CSAs build relationships with Startups, designing and architecting new solutions based on Microsoft\u2019s cloud platform and technologies. They deliver value via a portfolio of service delivery engagements optimized to accelerate partner solution builds.\n\nKey areas of responsibility:\u00a0\n\nBuild and Enhance Partner Capability and Capacity:\nBuild and enhance partner capability and capacity through delivering technical engagements such as Technical Briefings, Architectural Design Sessions, Hackathons, and Proof of Concepts.\nArchitecture Design & Deployment: Champions an existing architecture approach, synthesizes data about partner business, applies broad technical, industry, and enterprise knowledge, anticipates technical blockers and adapts methodology to minimize risks.\nDevelop partner engagements that can provide in-depth\u00a0technical skills and attach resulting greater impact for each build with engagement.\nSupport Partner Sales Success: Drive business impact through helping partners develop, launch, and publish offers to the Commercial Marketplace (Azure Marketplace, AppSource, etc.). Drive partner sales success through supporting initial 20 Startups.\n\n\u00a0**Post Requirement**\n\n2+ years of success in consultative/complex technical sales, technology solutions/practice development, architecture, design, implementation, and/or support of highly distributed applications\n\n\nArchitecture Design & Deployment: Skilled at proposing and developing high-value solutions to scale across multiple partners while demonstrating the business case and presenting alternative scenarios in collaboration with the partner, meeting business and IT requirements and constraints. Experience in enabling a breadth of highly advanced solutions using enterprise-scale technical experience with cloud and hybrid infrastructures, architecture designs, migrations and technology management that support the partner throughout pre-sales and/or implementation, resolving blockers and accelerating consumption while minimizing business and technical risks.\n\n\nTrusted Advisor: Skillfully provides direction to Startups technical decision-makers and builds the bridge between TDMs and business decision-makers (BDMs). Knows when to challenge partner decision and/or areas where they might do more and encourages alternative architectures and approaches.\n\n\nThought Leadership: Ability to share strong insights, and strategic, technical input with technical teams and internal communities\n\n\n2+ years\u2019 experience in the following technologies:\nCloud application design, development and deployment (e.g., IaaS, PaaS, Serverless, API Management);\nContinuous integration technologies (e.g., Jenkins, Spinnaker, Azure DevOps, Chef, Puppet).\nExperience with scalable architectures using Azure App Service, API management, serverless technologies, container orchestration (e.g., Kubernetes, Cloud Foundry etc.), microservice frameworks etc.\nFamiliar with one or more of the following programming languages: C++, C#, Java, Node.js, JSON, PHP, Perl, Python, Ruby on Rails, Pig/Hive; targeting Android, iOS, Linux or Windows in public clouds (i.e., Azure, AWS).\nKnowledge of infrastructure Technologies (e.g., Compute, Storage, Networking, etc.). Migration techniques, and resiliency design.\nAdditionally, good exposure in Application Security, GitHub, Databases or NoSQL.\n\u00a0 \u00a0 \u00a0 \u00a0 \u00a0 \u00a0 6. Collaboration: Acknowledged for driving decisions collaboratively, resolving conflicts and ensuring follow through with exceptional verbal and written communication skills\n\n\u00a0 \u00a0 \u00a0 \u00a0 \u00a0 \u00a0 7. Communication: Ability to orchestrate, lead, and influence virtual teams. Strong presentation skills with a high degree of comfort with both large and small audiences at different levels of organizations. \u00a0\u00a0\n\n\nEDUCATION\u00a0\n\nBachelor's degree in Computer Science, Information Technology, Engineering, or related field preferred\nCertification in one of the following technologies preferred: Cloud, mobile, web application development, cloud-native application architecture (i.e. containers, microservices, API management), modern software development techniques like DevOps and CI/CD tool chains (i.e. Jenkins, Spinnaker, Azure DevOps, GitHub) and container orchestration systems (i.e. Docker, Kubernetes, Cloud Foundry, Azure)\u00a0\n\nInterested parties please send the CV with expected salary and notice period.\u00a0 Thanks.", "employment_types": ["Full Time"], "selling_points": ["Auto CI/CD", "Terraform", "AWS"], "locations": ["Lai Chi Kok"], "categories": ["Information Technology (IT)", "Support", "Software Development", "Technical / Functional Consulting"], "post_time": "2022-01-14T11:26:50Z", "salary": {"currency": null, "max": null, "min": null, "period": "monthly", "term": null}, "salary_visible": false, "title_keywords": ["engineer"], "responsibilities": ["service delivery", "data", "technical support", "design", "develop", "designing", "architecture"], "requirements": {"degrees": ["degree", "bachelor"], "majors": ["engineering", "computer science", "information technology"], "languages": [], "language_level": [], "hard_skills": ["azure", "jenkins", "c++", "web application development", "ruby on rails", "c#", "java", "microservices", "integration", "perl", "small", "devops", "aws", "container", "python", "linux", "php", "mobile", "deployment", "programming", "databases", "android"], "soft_skills": ["communication skills", "advanced", "communication", "presentation skills", "leadership"], "languages_combined": []}, "experience_required": {"duration": ["2+ years"], "field": ["management", "business"]}}, {"job_id": "100003009048154", "location_code": "hk", "company": "Recruit Squad Limited", "job_title": "IT Project Manager (up to HK$70K)", "description": "Job Responsibilities\n\nResponsible for IT helpdesk work, quickly responding and dealing with user desktop problems and needs;\nResponsible for the daily maintenance of IT desktops and related equipment, including PCs, printers, scanners, electronic scales, and other equipment and related software maintenance;\nResponsible for the installation and distribution of IT desktop related equipment and systems;\nResponsible for the security and stability of the IT network (including wireless network) environment;\nResponsible for the management and maintenance of CCTV monitoring equipment;\nAssist the asset department in managing and updating assets. Including asset warehousing, issuance, inventory, maintenance, and scrap management.\n\nRequirements\n\nComputer-related major, with practical related work experience;\nPossess strong problem analysis and solving skills, high sense of responsibility, good professional ethics, a strong sense of service, and proactive;\nProficient in Windows, macOS, and other operating systems, proficient in the installation and troubleshooting of office software and common software;\nSkilled in solving the faults of terminal equipment such as PCs, printers, telephones, scanners, electronic scales, etc.;\nMaster the configuration, use, and policy formulation of mainstream VPN, online behavior management, access, firewall, and other security equipment;\nMaster the configuration, maintenance, fault diagnosis, and optimization of routers, switches, WLCs, APs, and other network equipment;\nMaster the basic use and maintenance of CCTV monitoring equipment;\nUnderstand enterprise IT infrastructure, and have a certain understanding of weak current integrated wiring, servers, virtualization, etc.\n\nInterested Parties please feel free to click the button above for APPLYING/ WhatsApp / call 6603 4144\n\n\u5d17\u4f4d\u8077\u8cac\n\n\u8ca0\u8cacIThelpdesk\u5de5\u4f5c\uff0c\u5feb\u901f\u76f8\u61c9\u548c\u8655\u7406\u7528\u6236\u684c\u9762\u7aef\u554f\u984c\u548c\u9700\u6c42\uff1b\n\u8ca0\u8cacIT\u684c\u9762\u53ca\u76f8\u95dc\u8a2d\u5099\u7684\u65e5\u5e38\u7dad\u8b77\u5de5\u4f5c\uff0c\u5305\u62ecPC\u3001\u6253\u5370\u6a5f\u3001\u6383\u63cf\u5100\u3001\u96fb\u5b50\u79e4\u7b49\u8a2d\u5099\u53ca\u76f8\u95dc\u8edf\u4ef6\u7dad\u8b77\uff1b\n\u8ca0\u8cacIT\u684c\u9762\u76f8\u95dc\u8a2d\u5099\u548c\u7cfb\u7d71\u7684\u5b89\u88dd\u3001\u914d\u767c\u5de5\u4f5c\uff1b\n\u8ca0\u8cacIT\u7db2\u7d61\uff08\u5305\u542b\u7121\u7dda\u7db2\u7d61\uff09\u74b0\u5883\u5b89\u5168\u7a69\u5b9a\uff1b\n\u8ca0\u8cacCCTV\u76e3\u63a7\u8a2d\u5099\u7ba1\u7406\u3001\u7dad\u8b77\u5de5\u4f5c\uff1b\n\u5354\u52a9\u8cc7\u7522\u90e8\u9580\u9032\u884c\u8cc7\u7522\u7684\u7ba1\u7406\u8207\u66f4\u65b0\u3002\u5305\u62ec\u8cc7\u7522\u5165\u5eab\u3001\u767c\u653e\u3001\u76e4\u9ede\u3001\u7dad\u4fee\u3001\u5831\u5ee2\u7ba1\u7406\u3002\n\n\u5165\u8077\u8981\u6c42\n\n\u8a08\u7b97\u6a5f\u76f8\u95dc\u5c08\u696d\uff0c\u5177\u6709\u5be6\u969b\u76f8\u95dc\u5de5\u4f5c\u7d93\u9a57\uff1b\n\u5177\u5099\u8f03\u5f37\u7684\u554f\u984c\u5206\u6790\u548c\u89e3\u6c7a\u80fd\u529b\uff0c\u9ad8\u5ea6\u8cac\u4efb\u611f\uff0c\u826f\u597d\u7684\u8077\u696d\u9053\u5fb7\uff0c\u670d\u52d9\u610f\u8b58\u5f37\uff0c\u7a4d\u6975\u9032\u53d6\uff1b\n\u719f\u7df4\u638c\u63e1Windows\u3001MacOS\u7b49\u64cd\u4f5c\u7cfb\u7d71\u76f8\u95dc\u77e5\u8b58\uff0c\u719f\u7df4office\u8fa6\u516c\u8edf\u4ef6\u53ca\u5e38\u7528\u8edf\u4ef6\u7684\u5b89\u88dd\u548c\u6545\u969c\u89e3\u6c7a\uff1b\n\u719f\u7df4\u89e3\u6c7aPC\u6a5f\u3001\u6253\u5370\u6a5f\u3001\u96fb\u8a71\u3001\u6383\u63cf\u5100\u3001\u96fb\u5b50\u79e4\u7b49\u7d42\u7aef\u8a2d\u5099\u7684\u6545\u969c\uff1b\n\u638c\u63e1\u4e3b\u6d41VPN\u3001\u4e0a\u7db2\u884c\u70ba\u7ba1\u7406\u3001\u51c6\u5165\u3001\u9632\u706b\u7246\u7b49\u5b89\u5168\u8a2d\u5099\u7684\u914d\u7f6e\u3001\u4f7f\u7528\u53ca\u7b56\u7565\u7684\u88fd\u5b9a\uff1b\n\u638c\u63e1\u8def\u7531\u5668\u3001\u4ea4\u63db\u6a5f\u3001WLC\u3001AP\u7b49\u7db2\u7d61\u8a2d\u5099\u7684\u914d\u7f6e\u3001\u7dad\u8b77\u3001\u6545\u969c\u8a3a\u65b7\u53ca\u512a\u5316\uff1b\n\u638c\u63e1CCTV\u76e3\u63a7\u8a2d\u5099\u7684\u57fa\u672c\u4f7f\u7528\u548c\u7dad\u8b77\uff1b\n\u4e86\u89e3\u4f01\u696dIT\u57fa\u790e\u67b6\u69cb\uff0c\u5c0d\u5f31\u96fb\u7d9c\u5408\u4f48\u7dda\u3001\u670d\u52d9\u5668\u3001\u865b\u64ec\u5316\u7b49\u65b9\u9762\u6709\u4e00\u5b9a\u8a8d\u8b58\u3002\n\n\u6709\u610f\u8005\u8acb\u96a8\u6642\u9ede\u64ca\u4e0a\u65b9\u6309\u9215\u7533\u8acb/whatsapp/\u81f4\u96fb6603 4144", "employment_types": ["Full Time", "Permanent"], "selling_points": ["IT Project Management Permanent Role", "Great Exposure on Digital Transformation, AL 20+", "Dynamic working environment, Bonus, Healthcare"], "locations": ["Not Specified"], "categories": ["Information Technology (IT)", "IT Project Management / Team Lead", "Software Development", "Technical / Functional Consulting"], "post_time": "2022-01-14T05:25:23Z", "salary": {"currency": null, "max": null, "min": null, "period": "monthly", "term": null}, "salary_visible": false, "title_keywords": ["it project manager"], "responsibilities": ["installation", "management", "warehousing", "software", "maintenance", "inventory", "pcs", "systems", "monitoring"], "requirements": {"degrees": ["master"], "majors": [], "languages": [], "language_level": [], "hard_skills": ["printers", "basic", "servers", "maintenance", "analysis", "cctv", "vpn", "firewall", "office software"], "soft_skills": ["high sense of responsibility", "proactive", "troubleshooting"], "languages_combined": []}, "experience_required": {"duration": [], "field": ["related"]}}, {"job_id": "100003009048827", "location_code": "hk", "company": "Hong Kong Air Cargo Terminals Ltd", "job_title": "Senior Business Analyst", "description": "Responsibilities:\n\nPerform timely POS and CMS System menu update, and testing\nProvide daily technical support and handle requests from key users\nSupport new implementation promotion campaign and technical issues\nWork with external service vendors to ensure vendor deployments and deliverables are in quality standard\nAssist in ad-hoc projects as assigned\n\nRequirements:\n\n\nHigher Diploma or above in Computer Science or related discipline\n3 years working experience in IT user support, experience in QSR is preferred\nMCP, MCSE or CCNA holder would be an advantage\n\nKnowledge, Skills & Abilities Required:\n\nSolid experience in helpdesk support, virus and spam control, PC disaster recovery and data migration\nHands-on experience in supporting Windows, MS Active Directory, Office 365, Sophos, POS and other Microsoft applications\nSelf-motivated, strong problem solving and analytical skills\nCan do attitude and willing to work under pressure and overtime\nCustomer focused attitude and dedicated to problem resolution\nAble to work shift duty in weekend and on public holidays (5-day work per week)\nMore experiences will be considered as Senior Officer", "employment_types": ["Full Time", "Permanent"], "selling_points": ["Experienced in IT application development", "Guarantee 13th month pay & discretionary bonus", "Free shuttle bus and traffic allowance"], "locations": ["Airport Area"], "categories": ["Information Technology (IT)", "Network & System", "Technical / Functional Consulting", "Data Scientist"], "post_time": "2022-01-14T07:21:55Z", "salary": {"currency": null, "max": null, "min": null, "period": "monthly", "term": null}, "salary_visible": false, "title_keywords": ["senior business analyst"], "responsibilities": ["technical support", "quality", "implementation", "testing", "ad-hoc projects"], "requirements": {"degrees": ["higher diploma or above"], "majors": ["computer science"], "languages": [], "language_level": [], "hard_skills": ["mcse", "office 365", "active directory", "pos", "microsoft applications", "ccna", "analytical skills", "problem solving", "pc"], "soft_skills": ["self-motivated", "focused", "problem solving and analytical skills", "hands-on", "active", "work under pressure"], "languages_combined": []}, "experience_required": {"duration": ["3 years"], "field": ["it", "disaster recovery"]}}, {"job_id": "100003009050684", "location_code": "hk", "company": "Hutchison Telecommunications (Hong Kong) Limited", "job_title": "System Development Manager / Consultant (1 year Contract)", "description": "\u00a0Job Responsibilities:\n\nParticipating in project implementations, providing professional services including Business requirement studies, system design, system testing, training, support and maintenance.\nSupport Senior Consultant in Project Implementation\nTroubleshoot Business Application, Enterprise Software, system/hardware issues\nPerform product testing before product release\nSoftware / System Configuration\nProvide customer service and hotline support to customers via telephone and email\nProvide support to any ad hoc events/activities assigned by supervisor/manager\n\nJob Requirements:\n\nDegree Holder (Business Administration / Computer Science / Information Technology / Accounting) holder or above\n1-2 years working experience in System implementation (requirement analysis, solutions design, testing, training\nApplicant with more experience will be considered as Senior Business Analyst / Senior\u00a0Application Consultant / Senior\u00a0Function\u00a0Consultant\u00a0\nFresh Graduate will also be considered\nOn-job training will be provided\nExperience in enterprise software\u00a0(ERP / HRMS / CRM / BPM / MRP) is an advantage\nKnowledge in MS SQL, reporting tools or light programing is an advantage\nSelf-motivated person with good analytical and problem-solving skills\nGood command of both spoken and written English, Cantonese and Mandarin\nGood communication, interpersonal and presentation skills\nDetail-minded and able to handle multi-task\n\nWe offer fringe remuneration package with 5-day work, medical insurance and 14 working day\u2019s\nannual leave.\u00a0Interested parties please send your detailed resume with current and expected salary email to us.\n\nData collected will be used for recruitment purpose only.\n\nFor the detailsof company information, please visit\u00a0www.solutionshouse.com.hk", "employment_types": ["Full Time", "Contract"], "selling_points": [], "locations": ["Tsing Yi"], "categories": ["Information Technology (IT)", "Application Specialist - Software", "Software Development", "Technical / Functional Consulting"], "post_time": "2022-01-14T11:10:26Z", "salary": {"currency": null, "max": null, "min": null, "period": "monthly", "term": null}, "salary_visible": false, "title_keywords": ["manager", "consultant"], "responsibilities": ["provide customer service", "provide support", "ad hoc", "software", "maintenance", "configuration", "implementation", "testing", "system design", "troubleshoot", "hardware issues"], "requirements": {"degrees": ["fresh graduate", "degree holder"], "majors": ["accounting", "business administration", "computer science", "information technology"], "languages": ["cantonese", "english", "mandarin"], "language_level": ["good command"], "hard_skills": ["analysis", "erp", "system implementation", "problem-solving skills", "ms sql"], "soft_skills": ["detail-minded", "self-motivated", "multi-task", "communication", "presentation skills", "problem-solving skills", "interpersonal"], "languages_combined": [{"language": "cantonese", "language_level": ["good command"]}, {"language": "english", "language_level": ["good command"]}, {"language": "mandarin", "language_level": ["good command"]}]}, "experience_required": {"duration": ["1-2 years"], "field": ["business", "training", "design", "testing"]}}, {"job_id": "100003009044405", "location_code": "hk", "company": "HKT Consumer Group", "job_title": "Technical Consultant, Premier Home Solutions", "description": "Responsibilities:\n\nhandle system installation, upgrade, configuration, administration, troubleshooting, patching, and monitoring of information systems including Microsoft AD, Exchange email, VM platform and endpoints system\nmanage system storage and backup, and restore the operations\nassist in planning and implementing systems and network integrations\nconfigure security settings or access permissions\nanalyze and report computer system security breaches or attempted breaches\nliaise and coordinate with vendors, suppliers, distributors, and contract consultants\nevaluate new technologies and platforms to determine applicability to resolve business challenges\nmentor and guide junior staff on operation and configuration of systems\nprepare reports, business correspondences, procedures and manuals as required\nTimely respond and handle urgent business requests/system support during normal and non-office hours with company-assigned facilities including phone and laptop\n\nRequirements:\n\nDegree holders in Information Technology / Computer Science or other related disciplines; VCP, MCSE, CCNA, ITIL would be an advantage\nminimum 5 years\u2019 experience in sizeable firm\nsolid hands-on experience in Microsoft Active Directory, Group Policy Objects (GPOs), Microsoft Exchange,\u00a0Office 365, WSUS / SCCM\nstrong infrastructure skills in Server, SAN, Windows, VMWare, SSLVPN and Veeam\nExperience in the administration of Azure Cloud, Office 365 and AWS is preferred\nexperience in Vendor Management especially in dealing with SI\ngood knowledge of enterprise Ethernet, VLANs, QOS, routing, switching and IP addressing\ndetail-minded, committed to work and able to prioritize effectively\nWell organized and able to work independently\u00a0under pressure and tight deadlines\ngood command of spoken and written English and Chinese, proficiency in Putonghua required\n\nCandidates with less experience will be considered as Assistant System Administrator.\n\nWe work 5 days per week.\n\n\nInterested parties, please click \"APPLY NOW\" and attach with your application letter and full resume.\u00a0\n\nFor further information of the Wharf Group, please visit our website: www.wharfholdings.com\u00a0\n", "employment_types": ["Full Time"], "selling_points": [], "locations": ["Causeway Bay"], "categories": ["Information Technology (IT)", "Support", "Technical / Functional Consulting"], "post_time": "2022-01-13T03:57:55Z", "salary": {"currency": null, "max": null, "min": null, "period": "monthly", "term": null}, "salary_visible": false, "title_keywords": ["consultant"], "responsibilities": ["liaise", "installation", "configuration", "operations", "monitoring", "systems", "troubleshooting", "coordinate with", "procedures", "evaluate", "planning", "system security", "prepare reports", "report", "administration"], "requirements": {"degrees": ["degree"], "majors": ["related disciplines", "computer science", "information technology"], "languages": ["putonghua", "english", "chinese"], "language_level": ["proficiency", "good command"], "hard_skills": ["itil", "mcse", "office 365", "azure", "vmware", "active directory", "sccm", "ccna", "vendor", "aws", "ip", "server", "microsoft exchange"], "soft_skills": ["detail-minded", "work independently", "under pressure", "able to prioritize", "well organized", "committed", "hands-on", "active"], "languages_combined": [{"language": "putonghua", "language_level": ["proficiency", "good command"]}, {"language": "english", "language_level": ["proficiency", "good command"]}, {"language": "chinese", "language_level": ["proficiency", "good command"]}]}, "experience_required": {"duration": ["minimum 5 years"], "field": ["management", "administration"]}}, {"job_id": "100003009048757", "location_code": "hk", "company": "United Asia Finance Limited", "job_title": "Senior Infrastructure Specialist (FinTech and Innovation Department)", "description": "Your New Role\n\nYou will have the opportunities to manage various projects and work closely with the team to facilitate new initiatives.\n\nResponsible for frontend & backend system implementation, maintenance and release\nDevelop and maintain APIs to support mobile and web application functionalities based on product requirement under iteration cycles\nEnsure that architectural design and solution can balance business needs and technical/security standards\n\nWhat makes you succeed\n\n\nUniversity Graduate or High Diploma in Computer Science or related discipline\nMinimum 2+ years of relevant experience\nHands-on experience in PHP Laravel framework, Node.Js, and Python\nFamiliar with MySQL & MongoDB\nExperience in API Microservice, CI/CD is an advantage\nExperience in Java and/or GoLang is an advantage\nOrganized, self-motivated and teamwork oriented\nCandidate with more experience will be considered as senior position\n\n\nWe offer attractive and competitive salary and benefits, an exciting work environment and excellent career development opportunities.\u00a0If you have the desire for an exciting and rewarding career, please send us your resume,\u00a0stating your present and expected salary to Human Resources Department by post, fax or clicking \"Apply Now\":\n\nPost:\u00a0\u00a0 \u00a0\u00a06/F, Goldin Financial Global Centre, 17 Kai Cheung Road, Kowloon Bay\u00a0\nFax:\u00a0\u00a0\u00a0\u00a0 (852) 2827 8322\u00a0\u00a0\n\nFor more information on other job opportunities of PCCW, please visit our website at <http://www.pccw.com/Careers/Job+Opportunities+&+Application/Current+Opportunities?language=en_US>\n\nPCCW is an equal opportunity employer and welcomes applications from all qualified candidates. Information provided will be treated in strict confidence and will only be used for recruitment-related purposes. Personal data provided by job applicants will be used strictly in accordance with the employer\u2019s privacy statement\u00a0(www.pccw.com/privacy-statement/index.page), a copy of which will be provided immediately upon request.", "employment_types": ["Full Time", "Permanent"], "selling_points": ["Double pay and discretionary bonus", "Perform system administration on Firewall", "Bachelor Degree in Computer Science"], "locations": ["Wan Chai"], "categories": ["Information Technology (IT)", "Network & System", "Technical / Functional Consulting", "Others"], "post_time": "2022-01-14T07:13:26Z", "salary": {"currency": null, "max": null, "min": null, "period": "monthly", "term": null}, "salary_visible": false, "title_keywords": ["specialist"], "responsibilities": ["maintenance", "implementation", "design", "develop", "maintain"], "requirements": {"degrees": ["high diploma", "university graduate"], "majors": ["computer science"], "languages": [], "language_level": [], "hard_skills": ["java", "web", "maintenance", "php", "python", "mobile", "system implementation"], "soft_skills": ["organized", "self-motivated", "responsible", "teamwork", "hands-on"], "languages_combined": []}, "experience_required": {"duration": ["minimum 2+ years"], "field": ["relevant experience"]}}, {"job_id": "100003009050556", "location_code": "hk", "company": "Ambition", "job_title": "Information Security Manager - Financial Services - Hong Kong", "description": "INFORMATION TECHNOLOGY SERVICES OFFICE\nSpecialist / Assistant Specialist (System Infrastructure) (three posts) (Ref. 22011410-E5)\nDuties\nThe appointees will work in the Systems Infrastructure Services Section and will be required to:\n(a)\u00a0\u00a0\u00a0\u00a0 support computer systems and facilities in Central Data Centres;\n(b)\u00a0\u00a0\u00a0\u00a0 support the University\u2019s cloud infrastructures;\n(c)\u00a0\u00a0\u00a0\u00a0 support service automation and streamlining of workflows;\n(d)\u00a0\u00a0\u00a0\u00a0 work outside normal office hours whenever necessary; and\n(e)\u00a0\u00a0\u00a0\u00a0 perform any other duties as assigned by the Director of the Office or his delegates.\nQualifications\nApplicants should:\n(a)\u00a0\u00a0\u00a0\u00a0 have a recognised degree or diploma\u00a0 in\u00a0 Computer\u00a0 Science, Information Technology or a related discipline;\n(b)\u00a0\u00a0\u00a0\u00a0 preferably have relevant working experience; and\n(c)\u00a0\u00a0\u00a0\u00a0 be able to communicate effectively in both written and spoken English and Chinese.\nApplicants with less experience or fresh graduates will also be considered.\nApplicants who have responded to the previous advertisements need not re-apply.\nRemuneration and Conditions of Service\nA highly competitive remuneration package will be offered.\u00a0 Initial appointment will be on a fixed-term gratuity-bearing contract.\u00a0 Re-engagement thereafter is subject to mutual agreement.\u00a0 Applicants should state their current and expected salary in the application.\nApplication\nPlease send a completed application form by post to Human Resources Office, 13/F, Li Ka Shing Tower, The Hong Kong Polytechnic University, Hung Hom, Kowloon, Hong Kong or via email by clicking \"Apply Now\".\u00a0 Application forms can be downloaded from https://www.polyu.edu.hk/hro/careers/guidelines_and_forms/forms.\u00a0 If\u00a0 a separate curriculum vitae is to be provided, please still complete the application form which will help speed up the recruitment process.\u00a0 The closing date for application is Monday, 14 February 2022.\u00a0 Applicants who are not invited to an interview within two months from the closing date should consider their applications unsuccessful.\u00a0 The University\u2019s Personal Information Collection Statement for recruitment can be found at https://www.polyu.edu.hk/hro/careers/guidelines_and_forms/pics_for_recruitment.\nPolyU is an equal opportunity employer committed to diversity and inclusivity.\u00a0 All qualified applicants will receive consideration for employment without regard to gender, ethnicity, nationality, family status or physical or mental disabilities.\u00a0\u00a0", "employment_types": ["Full Time", "Permanent"], "selling_points": ["Information Security Manager", "Financial Services", "Based in Hong Kong"], "locations": ["Not Specified"], "categories": ["Information Technology (IT)", "IT Management", "Security", "Technical / Functional Consulting"], "post_time": "2022-01-14T10:44:03Z", "salary": {"currency": "HKD", "max": 69999, "min": 55000, "period": "monthly", "term": null}, "salary_visible": true, "title_keywords": ["information security manager"], "responsibilities": ["any other duties", "systems infrastructure", "data", "advertisements", "infrastructure", "computer systems", "recruitment", "recruitment process"], "requirements": {"degrees": ["diploma", "degree"], "majors": ["science", "information technology"], "languages": ["english", "chinese"], "language_level": [], "hard_skills": ["c", "computer systems"], "soft_skills": ["committed"], "languages_combined": [{"language": "english", "language_level": []}, {"language": "chinese", "language_level": []}]}, "experience_required": {"duration": [], "field": ["relevant working experience"]}}, {"job_id": "100003009050378", "location_code": "hk", "company": "Conners Consulting Limited", "job_title": "Data Science / Data Analytics Manager (Leading bank with excellent package )", "description": "We are expanding our team and looking for a number of passionate and talented IT professionals to join us and support our business to grow innovatively. You will work will Product Team to study and analysis user requirement. You will experienced in how to handle high traffic application and make it stable.\n\nResponsibilities:\n\nMaintain and build new development tools and infrastructure such AWS, GCP\nAutomate and improve system and application monitoring\nWillingness take the initiatives to setup DevOps\nRequirement:\n\n\n1 - 3 years work experience\nStrong in either Python, Java, PHP\nHave exposure on DevOps in previous experience\nFamiliar with various IT Automation Tools/ Platform, such as Terraform, Ansible\nExperience on Linux infrastructure and shell script\nExperience with managing and troubleshooting at Linux servers\nGood written and verbal skills in both Chinese and English\nWhat you will learn:\n\n\nAuto CI/CD\nAutomation Tools such Terraform, Jenkins\nCloud-native/serverless architectures\nContainers (e.g. Docker, Kubernetes)", "employment_types": ["Full Time", "Permanent"], "selling_points": ["Permeant role", "Renewable contract with attractive package", "Fast expanding and leading commercial bank"], "locations": ["Kwun Tong Area"], "categories": ["Information Technology (IT)", "DBA", "Technical / Functional Consulting", "Data Scientist"], "post_time": "2022-01-15T03:51:03Z", "salary": {"currency": null, "max": null, "min": null, "period": "monthly", "term": null}, "salary_visible": false, "title_keywords": ["manager"], "responsibilities": ["infrastructure", "monitoring", "maintain", "setup"], "requirements": {"degrees": [], "majors": [], "languages": ["english", "chinese"], "language_level": ["good"], "hard_skills": ["linux", "java", "servers", "jenkins", "php", "devops", "ansible", "python"], "soft_skills": ["troubleshooting"], "languages_combined": [{"language": "english", "language_level": ["good"]}, {"language": "chinese", "language_level": ["good"]}]}, "experience_required": {"duration": ["1 - 3 years"], "field": ["devops", "infrastructure", "troubleshooting"]}}, {"job_id": "100003009045355", "location_code": "hk", "company": "Endeavour Search Limited", "job_title": "Senior IT Business Partner \u2013 Change Management & APAC Project Leadership", "description": "Our Clients are in the E-Commerce, Fintech and Commercial space. They're currently expanding their team and looking to hire IT Project Managers (Permanent Role) to join their progressive team!\u00a0\n\n\n\nResponsibilities:\n\nAnalyse project requirements and determine development scope and provide time estimates for completion.\nPerform System Design, Build and Test new Application\nProvide enhancement, improvements and maintenance tasks on existing applications\nProactively make recommendations for process improvement and automation\nMake decisions on appropriate design or development techniques\n\nRequirements:\n\nHigher Diploma or University Graduates in Computer Science or equivalent;\nGood experience in Java / .NET / Mobile (iOS, Android, ARVR) / PHP / Oracle EBS / Oracle Forms Reports / SAP / ABAP\nTeam Work and Good communication in Cantonese and English\n\n\n\n\n\u00a0We offer attractive remuneration and fringe benefits to the right candidates. Please send us the application by clicking the \"Apply Now\" button, together with a detailed resume, stating current and expected salary.\u00a0\n\n(All personal data provided by job applicants are used only for recruitment purpose and will be treated strictly confidential.)\u00a0", "employment_types": ["Full Time", "Permanent"], "selling_points": ["Report directly to C-Level Business leaders", "MNC APAC Regional exposure an advantage", "Enterprise CRM/ERP/ECOM experience a plus"], "locations": ["Kwai Tsing Area"], "categories": ["Information Technology (IT)", "IT Project Management / Team Lead", "IT Management", "Technical / Functional Consulting"], "post_time": "2022-01-13T18:55:07Z", "salary": {"currency": null, "max": null, "min": null, "period": "monthly", "term": null}, "salary_visible": false, "title_keywords": [], "responsibilities": ["make recommendations", "project requirements", "design", "maintenance tasks", "system design", "analyse"], "requirements": {"degrees": ["diploma"], "majors": ["computer science"], "languages": ["cantonese", "english"], "language_level": ["good"], "hard_skills": ["java", "abap", "sap", "php", "mobile", "android", "oracle"], "soft_skills": ["communication"], "languages_combined": [{"language": "cantonese", "language_level": ["good"]}, {"language": "english", "language_level": ["good"]}]}, "experience_required": {"duration": [], "field": []}}]