[{"job_id": "100003009055605", "location_code": "hk", "company": "Tofugear Limited", "job_title": "Project Assistant - Great Technology, Exciting Projects, Free Snacks", "description": "Job Highlights\n\ntechnical writer,project management\ncomfortable working environment\nWell-organized, mature, highly responsible\u2028\n\nJob Description\nJob Requirements\n\nWell-organized, mature, highly responsible and independent\nGood in spoken and writing English, Cantonese and Mandarin\nInterested in IT industry\u00a0\nWilling to build up and keep a good relationship with our clients and vendors\nDetailed-minded\nWilling to learn\nProactive with good communication skills\nHave basic understanding of retail/F&B businesses operation is a\u00a0plus\n\n\nJob Duties:\n\nReports to Project Manager\nCo-ordinate with development team to achieve project deliverables\nOperate and set up Omnitech system to cater for clients\u2019 operations, campaigns and promotions\napp testing and develop standardised test plans\nTroubleshoot for clients\u2019 technical problems\n\nWe offer you\n\nFlexible working hours\nComfortable working environment\nFree drinks and snacks\nChance to learn the coolest things in IT industryYou can find more in our website:\u00a0https://www.tofugear.com\n\nIf you are interested, please click apply now\u00a0with attached CV with expected salary\nAll personal information submitted by job applicants will be used for recruitment purposes and we reserve the rights to consider the applications for other positions in our\u00a0Group.", "employment_types": ["Full Time", "Permanent"], "selling_points": ["technical writer,project management", "comfortable working environment", "Well-organized, mature, highly responsible"], "locations": ["Wong Tai Sin Area"], "categories": ["Information Technology (IT)", "IT Management", "Technical / Functional Consulting", "Technical Writing"], "post_time": "2022-01-18T02:47:07Z", "salary": {"currency": null, "max": null, "min": null, "period": "monthly", "term": null}, "salary_visible": false, "title_keywords": ["project assistant"], "responsibilities": [], "requirements": {"degrees": [], "majors": [], "languages": ["cantonese", "english", "mandarin"], "language_level": ["good"], "hard_skills": ["plus", "basic"], "soft_skills": ["communication skills", "independent", "responsible", "interested in", "well-organized", "willing to learn", "mature", "troubleshoot", "proactive", "detailed"], "languages_combined": [{"language": "cantonese", "language_level": ["good"]}, {"language": "english", "language_level": ["good"]}, {"language": "mandarin", "language_level": ["good"]}]}, "experience_required": {"duration": [], "field": []}}, {"job_id": "100003009053179", "location_code": "hk", "company": "Haystar Consultant Limited", "job_title": "TRAINEE - In-house I.T. Support (\u65e5\u8cc7\u4e0a\u5e02\u516c\u53f8/ \u798f\u5229\u9f4a/ \u5c6f\u9580 & \u8343\u7063)", "description": "A well-established Japan-based distributor for supplying advanced electrical equipment accessories to the worldwide.\u00a0 Due to expansion, we are looking for several high calibre candidates to join its flexible team.\n\nDuties:\u00a0\n\nProvide daily operation on servers, pc, system and network support\nProvide technical support via phone, remote & helpdesk support\nProvide onsite / offsite troubleshooting, repairing, installation and maintenance\nHandle backend user inquiries, technical troubleshooting, repairing and support\n\nRequirements:\n\nKnowlege of LAN/WAN, TCP/IP networking, DNS, VPN, AP\nExperience in M365, Exchange, Google working space, window AD & VMware administration\nExperience in IT support and help desk services is preferred\n1-2 years of relevant working experience\nLess experience/ fresh graduate with high caliber is also welcome as a TRAINEE\nKnowledge of IT Systems and applications\nEager to look for a permanent job in a Japan-based company\n\nThe remuneration package is commensurate with competency & experience. Interested parties please send full resume (WORD format) with expected salary and availability.\n\n\nTo learn more about us, please visit our website: www.haystar.com.hk\n\nInformation provided by applicants will be treated in strict confidence and used for recruitment purposes only.", "employment_types": ["Full Time", "Permanent"], "selling_points": ["A Renowned Trading with head office in Japan", "No overtime work is essential.", "On-the-job training will be provided"], "locations": ["Tuen Mun Area"], "categories": ["Information Technology (IT)", "Support", "Network & System", "Technical Writing"], "post_time": "2022-01-17T06:21:42Z", "salary": {"currency": null, "max": null, "min": null, "period": "monthly", "term": null}, "salary_visible": false, "title_keywords": ["trainee"], "responsibilities": ["installation", "maintenance", "technical support", "daily operation", "troubleshooting"], "requirements": {"degrees": ["fresh graduate"], "majors": [], "languages": [], "language_level": [], "hard_skills": ["ap", "dns", "vmware", "tcp", "ip", "vpn", "wan", "exchange"], "soft_skills": [], "languages_combined": []}, "experience_required": {"duration": ["1-2 years"], "field": ["it support", "relevant working experience", "administration"]}}, {"job_id": "100003009054399", "location_code": "hk", "company": "Global eSolutions (HK) Limited", "job_title": "System Analyst", "description": "Duties:\n\nParticipate in application design and implementation, system enhancements, testing, and end-user training\nDevelopment of web-based management systems\nDaily system maintenance and troubleshooting and routinely software deployment\n\nRequirements:\n\nUniversity Graduate in Computer Science or related subject\n5-10 years experience\u00a0in coding and development using\u00a0Java, Spring Framework, SQL\nExperienced in DevOps, Git\nGood analytical and problem-solving skills, and capable of preparing technical and programming documentation\nPositive attitude\nSalary range depends on the\u00a0capability of the candidates\n\nWe offer 5-day work, public holidays, medical benefits, excellent career opportunities, considerable remuneration to the right candidates.\n\nInterested parties please send an email of a full resume and/or application letter, with current and expected salary to us.", "employment_types": ["Full Time", "Permanent"], "selling_points": ["Java, Spring, SQL", "Development", "5 Days, Medical Allowance"], "locations": ["Kwun Tong"], "categories": ["Information Technology (IT)", "IT Project Management / Team Lead", "Software Development", "Technical Writing"], "post_time": "2022-01-17T09:22:35Z", "salary": {"currency": null, "max": null, "min": null, "period": "monthly", "term": null}, "salary_visible": false, "title_keywords": ["system analyst"], "responsibilities": ["management", "software", "maintenance", "systems", "implementation", "design", "testing", "troubleshooting"], "requirements": {"degrees": ["university graduate"], "majors": ["computer science"], "languages": [], "language_level": [], "hard_skills": ["java", "git", "devops", "sql", "spring", "programming", "documentation", "problem-solving skills"], "soft_skills": ["positive attitude", "problem-solving skills", "capable"], "languages_combined": []}, "experience_required": {"duration": ["5-10 years"], "field": ["sql", "development"]}}, {"job_id": "100003009052817", "location_code": "hk", "company": "ELM Computer Technologies Ltd", "job_title": "Analyst Programmer", "description": "Responsibilities:\n\nInvolved in the entire system development life cycle (SDLC), including collection of user requirements, system analysis and design and system development and testing\nPerforming coding and system test\nPrepare technical documentation and provide user training\n\n\u00a0Requirements:\u00a0\n\nDiploma or above in IT related disciplines\nMinimum 2 years relevant working experience\nProficiency in Java and RDBMS\nWith knowledge in development frameworks, such as Spring Boot, Angular and Hibernate and system integration\nSelf-motivated, a team player, hardworking and able to work independently\nFresh graduate and candidate with less experience will be considered as Programmer", "employment_types": ["Temporary", "Contract"], "selling_points": ["Minimum 2 years relevant working experience", "Proficiency in Java and RDBMS", "Less experience will be considered as Programmer"], "locations": ["Shatin Area"], "categories": ["Information Technology (IT)", "Application Specialist - Software", "Software Development", "Technical Writing"], "post_time": "2022-01-17T04:09:39Z", "salary": {"currency": null, "max": null, "min": null, "period": "monthly", "term": null}, "salary_visible": false, "title_keywords": ["analyst programmer"], "responsibilities": ["analysis", "coding", "design", "testing", "documentation"], "requirements": {"degrees": ["fresh graduate", "diploma or above"], "majors": ["related disciplines", "it"], "languages": [], "language_level": [], "hard_skills": ["java", "hibernate", "angular", "spring", "integration"], "soft_skills": ["self-motivated", "team player", "work independently", "hardworking"], "languages_combined": []}, "experience_required": {"duration": ["minimum 2 years"], "field": ["relevant working experience"]}}, {"job_id": "100003009053951", "location_code": "hk", "company": "Accenture Company Limited", "job_title": "Interactive Industrie&Co \u2013  Full Stack Engineer", "description": "About Industrie&Co\n\nIndustrie&Co is an Accenture company specialising in building software-powered products and platforms for our clients. We have a strong reputation in the Financial Services sector and love solving complex problems. We are currently on the hunt for a passionate full stack engineer who will be based in our Hong Kong office working predominantly on FinTech and Digital Transformation projects.\n\nYour Role:\n\nWork alongside colleagues and client engineers as part of an agile team to deliver high quality solutions, primarily running on cloud services\nHands-on with technical tasks, with a focus on developing high quality end-to-end solutions using modern technology stacks\n\nExperience, Attributes and Qualifications:\n\nYou have good working knowledge of micro-services oriented architecture and REST APIs\nYou have a proven track record of building robust and scalable backend solutions\nYou are comfortable with one or more programming languages (Java, Python, Typescript...)\n\u00a0You are comfortable around SQL and NoSQL databases\nYou write maintainable, tested, and well documented code bases\nYou are comfortable with cloud infrastructures and relevant automation tools (AWS, Docker, CI/CD, K8s, ...)\nYou have used one or more front-end web frameworks (React, Vue, Angular, ...)\nYou understand how to configure and manage non-functional software aspects (logging, telemetry, security, ...)\nYou enjoy picking up new languages and technologies\nYou have experience working in an agile environment with fast paced / iterative development\nYou have experience with Test Driven Development (TDD) and / or Behaviour Driven Development (BDD)\nYou have a Bachelor's Degree in any technical Discipline\nYou have 5+ years\u2019 experience helping build great solutions end-to-end\n\nAdditional information\n\nAt Industrie&Co you will work in a collaborative, challenging and progressive environment. We are very much team players who work together to ensure we are achieving our individual and company goals every single day. We provide a very flexible work environment and ensure that an excellent work-life balance is achieved across the entire organisation. If you are looking for a workplace where you will have a significant impact and simultaneously grow your skills, Industrie&Co is the place for you.", "employment_types": ["Full Time"], "selling_points": ["Leadership - uplift others' capacity", "Passionate - helping with effectiveness", "Culture - Multi-Cultural Diverse Environment"], "locations": ["Not Specified"], "categories": ["Information Technology (IT)", "Application Specialist - Software", "Software Development", "Technical Writing"], "post_time": "2022-01-17T07:49:42Z", "salary": {"currency": null, "max": null, "min": null, "period": "monthly", "term": null}, "salary_visible": false, "title_keywords": ["engineer"], "responsibilities": ["software", "quality", "developing", "databases", "architecture"], "requirements": {"degrees": ["degree", "bachelor"], "majors": [], "languages": [], "language_level": [], "hard_skills": ["java", "agile", "web", "react", "aws", "sql", "typescript", "programming", "databases", "python", "code", "focus", "angular"], "soft_skills": ["passionate", "agile", "collaborative", "robust", "hands-on", "progressive", "focus", "driven"], "languages_combined": []}, "experience_required": {"duration": ["5+ years"], "field": ["development"]}}, {"job_id": "100003009053169", "location_code": "hk", "company": "Softcube Systems Limited", "job_title": "Programmer (5 days work)", "description": "Job Responsibilities\n\nParticipate in system design, development, testing and implementation of web-based applications\u00a0\nWork closely with developer and designer\u00a0to\u00a0meet the requirement and project schedule\nEnsure system performance and coding quality meeting latest standard\n\nJob Requirements\n\n\u00a0\u00a0\u00a0\u00a0\u00a0\u00a0\u00a0\u00a0 Experience in .Net framework, MSSQL, MYSQL, HTML, CSS, JQuery development\u00a0\n\u00a0\u00a0\u00a0\u00a0\u00a0\u00a0\u00a0\u00a0 Experience in CRM tools such as Magento, Shopify, Shopline, WooCommerce is an advantage\n\u00a0\u00a0\u00a0\u00a0\u00a0\u00a0\u00a0\u00a0 Self-motivation and a good team player\n\u00a0\u00a0\u00a0\u00a0\u00a0\u00a0\u00a0\u00a0 Willing to learn, able to work under pressure\u00a0and meet deadline\n\u00a0\u00a0\u00a0\u00a0\u00a0\u00a0\u00a0\u00a0 Well organized and responsible\n\u00a0\u00a0\u00a0\u00a0\u00a0\u00a0\u00a0\u00a0 Strong communication, analytic and problem-solving skills\n\u00a0\u00a0\u00a0\u00a0\u00a0\u00a0\u00a0\u00a0 Immediate availability is preferred\n\n\n", "employment_types": ["Full Time"], "selling_points": ["5-days work week", "Vibrant, Friendly and Diversify environment", "Performance bonus"], "locations": ["Ngau Tau Kok"], "categories": ["Information Technology (IT)", "Software Development", "Technical Writing", "Others"], "post_time": "2022-01-17T06:13:36Z", "salary": {"currency": null, "max": null, "min": null, "period": "monthly", "term": null}, "salary_visible": false, "title_keywords": ["programmer"], "responsibilities": ["quality", "implementation", "coding", "testing", "system design", "schedule"], "requirements": {"degrees": [], "majors": [], "languages": [], "language_level": [], "hard_skills": ["problem-solving skills", "shopify", "jquery", "html", "mssql", "css"], "soft_skills": ["good team player", "responsible", "willing to learn", "well organized", "communication", "self-motivation", "problem-solving skills", "work under pressure"], "languages_combined": []}, "experience_required": {"duration": [], "field": []}}, {"job_id": "100003009053178", "location_code": "hk", "company": "CL Technical Services Ltd.", "job_title": "Analyst Programmer (Java, Wanchai, over $40K)", "description": "Job details:\n\nResponsible for the system design, development and maintenance of\u00a0in-house developed Java applications\nAssist in collecting user requirements and transforming into functional requirements and technical specifications\nLiaise with and support users for system implementation, bug fixing, user acceptance test, deployment, training and related documentation\nCreate database tunneling via SQL\n\nRequirements:\n\nBachelor degree in Computer Science or a related discipline\nMinimum 3 years working experience in similar position\nSolid experience n Java,\u00a0Struts (Apache) and SQL\nGood command of spoken and written English and Chinese\n\nFor more job opportunity, please visit our website: www.clts.com\n\nThe personal information is collected strictly for recruitment purpose only.", "employment_types": ["Full Time"], "selling_points": ["Experience in Java, Struts (Apache) and SQL", "Stable working environment", "5-day work a week"], "locations": ["Wan Chai"], "categories": ["Information Technology (IT)", "Application Specialist - Software", "Software Development", "Technical Writing"], "post_time": "2022-01-17T06:18:40Z", "salary": {"currency": null, "max": null, "min": null, "period": "monthly", "term": null}, "salary_visible": false, "title_keywords": ["analyst programmer"], "responsibilities": ["related documentation", "maintenance", "implementation", "specifications", "system design", "database", "liaise with"], "requirements": {"degrees": ["degree", "bachelor"], "majors": ["computer science"], "languages": ["english", "chinese"], "language_level": ["good command"], "hard_skills": ["sql", "java", "apache", "struts"], "soft_skills": [], "languages_combined": [{"language": "english", "language_level": ["good command"]}, {"language": "chinese", "language_level": ["good command"]}]}, "experience_required": {"duration": ["minimum 3 years"], "field": ["sql"]}}, {"job_id": "100003009055568", "location_code": "hk", "company": "PeopleLink Services Limited", "job_title": "Business Analyst / Senior Business Analyst | Up to HK$60k + Bonus", "description": "\u00a0Responsibilities:\n\nUnderstand business and user requirement and translate to project scope and work closely with Product Owner, Project Managers and Development Teams\nLiaise and communicate with project stakeholders to ensure project deliverable meet user expectations\nTest deliverables regularly to ensure project on track and prepare document report to management\nQualifications\n\u00a0\n\nBachelor's degree in Computer Science, Information Technology, Business Analytics or equivalent\n5+ years of experience in business analyst on medium-sized to large projects involving multiple stakeholders. Experience in systems revamp in insurance business is preferred.\nSolid work experience in collect user requirements, change management, UAT\nParticipated in full SDLC for at least one of the projects below:\nArtificial Intelligence / Machine Learning application development\nData Management / Data Warehousing\nCloud Infrastructure\nAbility to work effectively with all levels of personnel across the organization\nEffective interpersonal skills with a clear, concise and relevant communication style, including excellent presentation skills.\nExperience in using project tools such as Jira, Confluence\nFluent English and excellent report writing skills", "employment_types": ["Full Time", "Permanent"], "selling_points": ["5+ yrs experience as Business Analyst", "Participate in AI/ML, Data, Cloud projects", "Large scale project exposure, Perm, Great Benefits"], "locations": ["Not Specified"], "categories": ["Information Technology (IT)", "IT Project Management / Team Lead", "Product Management / Business Analyst", "Technical Writing"], "post_time": "2022-01-18T02:43:58Z", "salary": {"currency": "HKD", "max": 54999, "min": 45000, "period": "monthly", "term": null}, "salary_visible": true, "title_keywords": ["senior business analyst", "business analyst"], "responsibilities": ["liaise", "user requirement", "communicate with", "management", "revamp", "change management", "uat", "data", "warehousing", "systems", "teams", "infrastructure", "communication", "application development", "insurance", "report"], "requirements": {"degrees": ["degree", "bachelor"], "majors": ["business analytics", "computer science", "information technology"], "languages": ["english"], "language_level": ["excellent", "fluent"], "hard_skills": ["sdlc", "data management", "writing skills"], "soft_skills": ["work effectively", "writing skills", "communication", "clear", "presentation skills", "learning", "interpersonal skills"], "languages_combined": [{"language": "english", "language_level": ["fluent", "excellent"]}]}, "experience_required": {"duration": ["5+ years"], "field": ["management", "business", "insurance"]}}, {"job_id": "100003009054253", "location_code": "hk", "company": "CHOW TAI FOOK JEWELLERY CO LTD", "job_title": "Business Intelligence Analyst", "description": "What You Do\n\n\nPerform ETL, Data modeling and Dashboard building\nWork closely with business analysis team and other stakeholders to develop end-to-end BI solutions and dashboards in order to facilitate business requirements that yield relevant business information\nMaintain, support and implement business intelligence platform\nTroubleshoot issues on BI reports & dashboards\nEnsure smooth data architecture and process for BI projects\nImprove data visualization by turning data into insights\nResponsible for data consolidation and ensure data quality is well maintained\nComplete jobs with good quality and within schedule\nProvide proper documentations, such as BRD and TDD\nPerform other ad-hoc management reports development as assigned\n\nWho Will Thrive\n\n\nBachelor Degree in Computer Science\u00a0/\u00a0Statistics /\u00a0Finance or other relevant quantitative disciplines\nAt least 3 years\u2019 solid working experiences in data analytics with exposure in business intelligence project\nFamiliar with Qlikview / Qlik Sense and\u00a0SQL Query or other data visualization tools\nCertified Qlik Data Architect is an advantage\nExperience in web development\u00a0is an\u00a0advantage but not essential\nExperience in\u00a0Supply\u00a0Chain\u00a0Management\u00a0/\u00a0jewelry industry is an advantage\nAble to work independently in\u00a0a\u00a0fast-paced environment with minimum supervision\nExcellent communication in English and Chinese\n\nBenefits\n\n5-day work\nCompetitive salary, staff meal, medical and dental insurance, life insurance\nVarious types of leave, e.g. Family-friendly leave, self-development leave,\u00a0Examination leave, marriage leave, birthday leave, volunteer service leave, etc\n\nWe offer excellent career opportunities, attractive remuneration package & benefits to the right candidate.\u00a0Interested parties please apply by clicking \"Apply Now\" with a full resume stating the latest and expected salary.\n\n\n\nAll information collected will be used for recruitment purposes only.", "employment_types": ["Full Time", "Contract"], "selling_points": ["Business Intelligence Analyst", "ETL, Data modeling and Dashboard building", "SQL Query / Qlikview / Qlik Sense / Python"], "locations": ["Kwai Hing"], "categories": ["Information Technology (IT)", "Software Development", "Technical Writing", "Others"], "post_time": "2022-01-17T08:58:11Z", "salary": {"currency": null, "max": null, "min": null, "period": "monthly", "term": null}, "salary_visible": false, "title_keywords": ["analyst"], "responsibilities": ["ad-hoc", "management", "visualization", "data", "quality", "develop", "communication", "management reports", "maintain", "reports", "troubleshoot", "schedule", "business analysis", "architecture"], "requirements": {"degrees": ["degree", "bachelor"], "majors": ["finance", "statistics", "computer science"], "languages": ["english", "chinese"], "language_level": ["excellent"], "hard_skills": ["qlikview", "web development", "bi", "data analytics", "analysis", "sql", "management reports", "data visualization", "business intelligence", "documentations"], "soft_skills": ["work independently", "responsible", "fast-paced environment", "communication", "troubleshoot", "smooth"], "languages_combined": [{"language": "english", "language_level": ["excellent"]}, {"language": "chinese", "language_level": ["excellent"]}]}, "experience_required": {"duration": ["at least 3 years"], "field": ["development", "management", "business", "supply chain"]}}, {"job_id": "100003009054153", "location_code": "hk", "company": "CHOW TAI FOOK JEWELLERY CO LTD", "job_title": "Analyst Programmer", "description": "What You Do\n\nHands-on for SDLC including design, coding, testing, implementation and maintenance of in-house systems\nInterface internal systems with other outsourced modules\nWork closely with business analysts to produce application design\nConduct feasibility study and analysis based on users' requirements and provide technical advice\nEnsure flexibility, stability, scalability, sustainability and performance of systems\nProvide system support on more complex user enquiries, production problems and troubleshooting\nProvide technical investigation and quick fix in case of encountering critical incident\nComplete jobs with good quality and within schedule\nMaintain awareness of new technologies and best practices for adoption\nEnsure all deliverables are in good quality and meeting requirements\nProvide database maintenance and data housekeeping\nWork closely with data quality team to align with SDLC on data governance related compliance\nPrepare technical documentations and system specifications\n\nWho Will Thrive\n\nBachelor Degree in Computer Science, Information System or equivalent with experience in supply chain management, jewelry industry is an advantage\nAt least 3 years of experience in web-based application development in .NET platform\nFamiliar with the ASP.NET framework, SQL Server and design/architectural patterns (e.g. MVC)\nFamiliar with .NET languages (e.g. C#, VB.NET), javascript, Ajax, jQuery, JSON, HTML5/CSS3, MSSQL\nGood analytical, problem solving and interpersonal skills\nAble to work independently in fast paced environment with minimum supervision\nComplete jobs with good quality and within schedule\n\nBenefits\n\n\n5-day work\nCompetitive salary, staff meal,\u00a0medical and dental insurance, life insurance\nVarious types of leave, e.g.\u00a0Family-friendly leave, self-development leave,\u00a0Examination leave, marriage leave, birthday\u00a0leave, volunteer service leave, etc\n\nWe offer excellent career opportunities, attractive remuneration package & benefits to the right candidate.\u00a0Interested parties please apply by clicking \"Apply Now\" with a full resume stating the latest and expected salary.\n\n\n\nAll information collected will be used for recruitment purposes only.", "employment_types": ["Full Time", "Permanent"], "selling_points": ["Application development and testing", "Application management", ".NET / ASP.NET / RPA / Git"], "locations": ["Kwai Hing"], "categories": ["Information Technology (IT)", "Software Development", "Technical Writing", "Others"], "post_time": "2022-01-17T08:35:31Z", "salary": {"currency": null, "max": null, "min": null, "period": "monthly", "term": null}, "salary_visible": false, "title_keywords": ["analyst programmer"], "responsibilities": ["data", "technical advice", "quality", "troubleshooting", "coding", "design", "maintain", "database", "application development", "compliance", "implementation", "testing", "schedule", "internal systems", "management", "investigation", "specifications", "maintenance", "housekeeping", "analysis", "systems"], "requirements": {"degrees": ["degree", "bachelor"], "majors": ["computer science"], "languages": [], "language_level": [], "hard_skills": ["maintenance", "web", "analysis", "jquery", "information system", "mssql", "sql", "problem solving", "sdlc", "javascript", "ajax", "server", "documentations", "c#"], "soft_skills": ["work independently", "troubleshooting", "problem solving", "hands-on", "interpersonal skills"], "languages_combined": []}, "experience_required": {"duration": ["at least 3 years"], "field": ["supply chain", "management", "application development"]}}, {"job_id": "100003009055917", "location_code": "hk", "company": "Ambition", "job_title": "SAP SD Analyst", "description": "Job Description\n\nProvide regional SAP SD technical support\nImplement new applications and assist in system upgrade\nResponsible for testing and report to management\nSupport solution implementation by actively reviewing within the team\n\nJob Requirements\n\nA minimum of 3 years' working experience in SAP SD operations and configuration\nExperience in using ABAP is a must\nKnowledge in S/4HANA will be a huge advantage\nGood communication skills with well spoken English and Mandarin\n\nIf this job isn't quite right for you, but you know someone who would be great at this role, why not take advantage of our referral scheme? We offer HKD1000 in Apple gift cards for every referred candidate who we place in a role. Terms & Conditions Apply. https://www.ambition.com.hk/refer-a-friend", "employment_types": ["Full Time", "Permanent"], "selling_points": ["Reputable International Appliance Manufacturer", "Regional Exposure", "Flexible Working Hours"], "locations": ["Not Specified"], "categories": ["Information Technology (IT)", "Technical / Functional Consulting", "Technical Writing", "Others"], "post_time": "2022-01-18T03:05:13Z", "salary": {"currency": null, "max": null, "min": null, "period": "monthly", "term": null}, "salary_visible": false, "title_keywords": ["analyst"], "responsibilities": ["management", "technical support", "implementation", "testing", "report"], "requirements": {"degrees": [], "majors": [], "languages": ["english", "mandarin"], "language_level": ["good"], "hard_skills": ["abap", "scheme", "sap"], "soft_skills": ["communication skills"], "languages_combined": [{"language": "english", "language_level": ["good"]}, {"language": "mandarin", "language_level": ["good"]}]}, "experience_required": {"duration": ["minimum of 3 years"], "field": []}}, {"job_id": "100003009051985", "location_code": "hk", "company": "Eclipse Options (HK) Limited", "job_title": "Java Software Engineer", "description": "Java Software Engineer\n\nEclipse Trading is one of Asia's leading proprietary derivatives trading firms. Founded in 2007, we have over a 100 staff across three office locations \u2013 Hong Kong (our HQ), Sydney, and Shanghai. Our trading expertise and strategies are deployed across several Asian markets and although we mainly specialise in equity derivatives, we also trade index derivatives, ETFs, commodity derivatives, and crypto currency products.\n\nTechnology is paramount to our business and our Trading Systems Development (TSD) team is responsible for the in-house derivatives trading system, spanning order execution, derivative pricing, risk management, and P&L. Due to organic growth, we are looking for a Java Software Engineer to join our growing TSD team in Hong Kong.\n\nResponsibilities and Duties\n\nDesign and implement solutions to manage orders, price derivatives, and manage risk\nParticipate in code reviews and provide constructive feedback to peers\nEngage with traders and quants on a regular basis to gather business and system requirements\nContribute to the next generation of our trading system to support growing volumes, increased automation and new asset classes, through green field development and refactoring of existing code bases with modern technologies (Java 11, Kafka, Kafka Streams)\nProvide Tier 3 support as needed\n\nWhat you offer\n\nExcellent core Java design and development skills\n3+ years of\u00a0relevant\u00a0experience in building distributed systems in Java\nStrong believer in automated testing and collaboration with colleagues\nUniversity Degree in Computer Science or related field\nExcellent command of spoken and written English\n\nWhat we offer\n\nAttractive benefits package with discretionary bonus\nWork/Life balance in a multi-cultural environment with reasonable work hours\nA fast-growing company, encouraging adoption of new technologies and ideas\nA flat management structure, where everyone's voice is valued\nA collaborative work environment with motivated, intelligent, and respectful colleagues\n\nAll information provided will be treated in strict confidence and used solely for recruitment purposes.\nDue to the high number of responses that we receive, we are only able to respond to successful applicants.", "employment_types": ["Full Time"], "selling_points": ["Excellent core Java design and development skills", "Build the next generation of our trading system", "3+ yrs exp in building distributed systems in Java"], "locations": ["Causeway Bay"], "categories": ["Information Technology (IT)", "Application Specialist - Software", "Software Development", "Technical Writing"], "post_time": "2022-01-17T01:45:21Z", "salary": {"currency": null, "max": null, "min": null, "period": "monthly", "term": null}, "salary_visible": false, "title_keywords": ["software engineer"], "responsibilities": ["design"], "requirements": {"degrees": [], "majors": [], "languages": [], "language_level": [], "hard_skills": [], "soft_skills": [], "languages_combined": []}, "experience_required": {"duration": [], "field": []}}, {"job_id": "100003009052001", "location_code": "hk", "company": "Automated Systems (HK) Ltd", "job_title": "QA Lead (Banking sector)", "description": "\nResponsibilities\nAnalyze business and system requirement and identify test solution.\nKeep track on change requirement.\nCollaborate with Manager and Engineer to develop test plan, test scenario, test cases and report.\nAct as main focal point for communicate, co-ordinate all testing tasks and communicate with stakeholders, infra-structure team, external party, if any\nIdentify and resolve test issues and conflicts regarding test execution.\nEscalate to QA Manager for unresolved issue.\nTrack tester's progress on test cases preparation and review.\nMonitor test cases execution progress, defect fixation progress on overall test execution.\nDevelop test progress and defect report.\u00a0Analyse, evaluate test result and provide recommendation.\n\nJob Requirements\n\nBachelor or above in Computer Science or related degree\nStrong understanding and experience on IT project management, Integration testing and/or Business application QA testing.\u00a0Banking industry experience is a plus.\nExperience in leading and managing test teams.\nFamiliar with languages such as Java, Python etc are advantage\nExperience in SQL/NoSQL databases are advantage\nStrong interpersonal, communication, collaboration and presentation skills.\nStrong analytical skill.\nProficient written and verbal communications skills\nWe offer 5-day week, public holidays, medical benefits, excellent career opportunities, considerable remuneration to the right candidates.\n\u201cIf you have the desire for an exciting and rewarding career, please send us your resume, stating your notice period, present and expected salary to Human Resources Department by clicking \"Apply Now\".\nTo learn us more, please visit our website: www.asl.com.hk\nWe are an equal opportunity employer. All applications will be treated in strict confidence. We regret that only shortlisted candidates will be notified. All personal data will be destroyed within six months after the selection process.", "employment_types": ["Full Time", "Permanent", "Contract"], "selling_points": ["Opportunities for your career promotion", "Will have opportunities to try different projects", "Become part of our talented and core team"], "locations": ["Quarry Bay"], "categories": ["Information Technology (IT)", "Software Development", "Testing / QA", "Technical Writing"], "post_time": "2022-01-17T01:48:18Z", "salary": {"currency": null, "max": null, "min": null, "period": "monthly", "term": null}, "salary_visible": false, "title_keywords": ["lead"], "responsibilities": [], "requirements": {"degrees": ["degree", "bachelor"], "majors": ["computer science"], "languages": [], "language_level": [], "hard_skills": ["plus", "java", "analytical skill", "focal", "python", "sql", "project management", "databases", "integration"], "soft_skills": ["analytical skill", "communication", "project management", "presentation skills", "interpersonal"], "languages_combined": []}, "experience_required": {"duration": [], "field": ["banking industry", "qa", "testing", "sql", "project management", "business", "it"]}}, {"job_id": "100003009051270", "location_code": "hk", "company": "Letlink Technology Limited", "job_title": "Full Set Magento2 Developer", "description": "Your Role\n\nDetermining the structure and design of Magento with ERP system.\nDeveloping features to enhance the user experiences to meet clients\u2019 requirements\nSourcing and working with suitable extensions for both Magento and eLearn Platform. \u00a0Building reusable code for future use.\nConfigure, design, and develop solutions including key integrations to 3rd party solutions\nCollaborate with other team members and stakeholders.\n\nRequirements for this role\n\nDegree in Computer Science or related field.\nStrong object-oriented programming knowledge\nVery good PHP knowledge\nExperience with Magento 2.\nGood problem-solving, verbal communication, interpersonal skills.", "employment_types": ["Full Time"], "selling_points": [], "locations": ["Shatin Area"], "categories": ["Information Technology (IT)", "Software Development", "Network & System", "Technical Writing"], "post_time": "2022-01-15T07:00:57Z", "salary": {"currency": null, "max": null, "min": null, "period": "monthly", "term": null}, "salary_visible": false, "title_keywords": ["developer"], "responsibilities": ["collaborate with", "developing", "design", "develop", "communication"], "requirements": {"degrees": ["degree"], "majors": ["computer science"], "languages": [], "language_level": [], "hard_skills": ["php", "problem-solving", "erp system", "programming", "code"], "soft_skills": ["communication", "problem-solving", "interpersonal skills"], "languages_combined": []}, "experience_required": {"duration": [], "field": ["developing"]}}, {"job_id": "100003009055566", "location_code": "hk", "company": "Hays", "job_title": "Information Security Manager / Specialist (50k-90k , Bank)", "description": "Information Security role 1.5 LOD\n\nYour new company\nMy client is one of the largest bank in the Asia region. They are looking to expand their cyber security team of 15.\n\nYour new role\n\nTo proactively mitigate technology, cyber and information security risks, as well as response to security incidents\nTo ensure the cyber and information security related projects is delivered on time & relevant controls are performed accurately & properly across the Bank Group according to the Bank's standard procedures and regulatory requirements\nTo act as liaison with relevant second line, third line, regulators and/or enforcement agencies in relation to information security matters\n\n\n\nWhat you'll need to succeed\n\nUniversity graduate in Information Technology, Computer Science or a related discipline\nMinimum of 5 years' experience in IT sector covering technology audit or cyber and information security\nIn-depth knowledge in cyber and information security operations, risk management and audits\nGood project management and leadership skill\nGood communication, interpersonal, and problem solving skills\nRisk awareness\nCertified in CISSP, CISA or ECF-Cybersecurity related professional certification\nGood command of both spoken and written English and Chinese, fluent in Putonghua is preferable\n\n\n\nWhat you need to do now\nIf you're interested in this role, click 'apply now' to forward an up-to-date copy of your CV, or send your CV in word format to kenneth.ling@hays.com.hk\n\nIf this job isn't quite right for you but you are looking for a new position, please contact us for a confidential discussion on your career.", "employment_types": ["Full Time", "Permanent"], "selling_points": ["Banking & Finance", "Information Security", "1.5 LOD"], "locations": ["Not Specified"], "categories": ["Information Technology (IT)", "IT Auditing", "IT Project Management / Team Lead", "Technical Writing"], "post_time": "2022-01-18T02:43:46Z", "salary": {"currency": "HKD", "max": 89999, "min": 55000, "period": "monthly", "term": null}, "salary_visible": true, "title_keywords": ["specialist", "information security manager"], "responsibilities": ["management", "information security", "cyber security", "regulatory requirements", "operations", "procedures", "audit", "communication", "project management", "contact", "audits"], "requirements": {"degrees": ["university graduate"], "majors": ["computer science", "information technology"], "languages": ["putonghua", "english", "chinese"], "language_level": ["good command", "fluent"], "hard_skills": ["project management", "problem solving skills", "word", "cyber security"], "soft_skills": ["interested in", "communication", "project management", "problem solving skills", "leadership skill", "interpersonal"], "languages_combined": [{"language": "putonghua", "language_level": ["fluent", "good command"]}, {"language": "english", "language_level": ["good command"]}, {"language": "chinese", "language_level": ["good command"]}]}, "experience_required": {"duration": ["minimum of 5 years"], "field": ["it", "security", "audit"]}}, {"job_id": "100003009049368", "location_code": "hk", "company": "HGC Global Communications Limited", "job_title": "IT Project Manager", "description": "Responsibilities:\u00a0\n\nManage and lead the planning and implementation of IT technical projects (e.g. Cloud implementation, IT infrastructure\u00a0projects);\nManage project schedule, resources\u00a0and risks. Perform proper\u00a0escalation to ensure project success;\nEnsure all the contractual\u00a0commitments and deliverable\u00a0are successfully delivered by vendors on time and within the budget;\nConduct system analysis, implementation, testing, user training and documentation\u00a0on IT systems;\nInterface with customers on system implementation for business systems projects;\nPerform product evaluation, vendor selection, and procurement of IT solutions / products.\u00a0\n\nRequirement:\n\nDegree in IT/ Computer Sciences/ Computer Engineering or related discipline\n5 years solid experience in IT project management with technical knowledge;\nCertified in any PMP, Agile, or Scrum Master is preferred\nKey competencies:\nLeading others\u00a0\nComposure\nInterpersonal Savvy\u00a0\nBusiness Acumen\nDealing with Ambiguity\n\nWe offer competitive salary package and career development opportunity. \u00a0Free company coach is provided. Interested parties, please quote our reference number and apply with full resume,\u00a0present and expected salary, by clicking \"APPLY NOW\".\u00a0\n\n\nWe are an equal opportunity employer and welcome applications from all qualified candidates. Information provided will be treated in strict confidence and only be used for consideration of your application for the relevant post within the HGC Global Communications Limited. Personal data provided by job applicants will be used strictly according to our Personal Information Collection Statement, a copy of which will be available upon written request. Information of unsuccessful candidates will be destroyed within six months.", "employment_types": ["Full Time", "Permanent"], "selling_points": ["IT Project Management permanent role", "Great exposure on technical transformation", "Dynamic working environment"], "locations": ["Tsing Yi"], "categories": ["Information Technology (IT)", "IT Project Management / Team Lead", "IT Management", "Technical Writing"], "post_time": "2022-01-14T08:31:44Z", "salary": {"currency": null, "max": null, "min": null, "period": "monthly", "term": null}, "salary_visible": false, "title_keywords": ["it project manager"], "responsibilities": ["it infrastructure", "analysis", "budget", "systems", "implementation", "testing", "schedule", "evaluation", "documentation", "planning"], "requirements": {"degrees": ["degree", "master"], "majors": ["it", "computer engineering"], "languages": [], "language_level": [], "hard_skills": ["project management", "pmp", "agile", "acumen"], "soft_skills": ["business acumen", "project management", "interpersonal", "agile"], "languages_combined": []}, "experience_required": {"duration": ["5 years"], "field": ["project management", "it"]}}, {"job_id": "100003009051461", "location_code": "hk", "company": "ADECCO", "job_title": "UI/UX Designer - 45-50k - Urgent Immediate Available - Global Media Powerhouse - Western Culture.", "description": "My Client is Asia Pacific\u2019s largest broadcast and media systems integrator. This role is within the special division of the firm that focuses on providing cloud integration and proprietary software solutions for media industry-based clientele as well as Audio-Visual Clients.\n\nJob Overview\u00a0\n\nThe UI/UX Designer is responsible for all the visual elements that users see and interact within company-wide suite of web applications. They will work with the product owners and software engineers in making improvements on current websites, as well as creating new ones from the ground up through developing prototypes and generating the code. They will be the core in creation of well-designed, user-centred, interfaces.\n\nResponsibilities and Duties\n\nLead all Web UI/UX design initiatives.\nWork with stakeholders in developing new user-facing features.\nBuilding high-quality mock-ups and design different wireframes and prototypes.\nStriking a balance between functional and aesthetic design.\nOptimizing web pages for maximum speed and scalability.\nWhere necessary be able to perform SEO.\nDesigning *GREENFIELD* mobile-based features.\nMaintaining brand consistency throughout design.\n\nSkills and Qualifications\u00a0Required:\n\nEither a related university degree or rich UI/UX design experience.\nExperience with the UI/UX workflow, from initial communication to final signoff is necessary.\nFamiliarity with tools such as Sketch, Adobe XD and Figma.\nKnowledge of usability principles across different platforms is important.\nStrong communication skills in English.\nExperience of working with cloud technology, such as AWS, particularly content delivery such as CloudFront and Route 53, is beneficial.\nWorking knowledge of HTML5, CSS3 and ES6 is especially useful.\nExpertise in JavaScript frameworks such as React and Material-UI is advantageous.\nExperience in working with source control, such has GitLab or GitHub.\nUnderstanding of Agile methods and developments tools such as Jira is valuable.\nStrong positive working attitude, quick-learner and able to work independently.\n\nPlease click the apply button or send through your updated CV direct to it.pl.hk (AT ) adecco.com.\u00a0 For more information feel free to call +852 28996179 and ask for Philip for a confidential discussions.", "employment_types": ["Full Time"], "selling_points": ["Lead all Web UI/UX design initiatives.", "Designing mobile-based features.", "Optimizing web pages for maximum speed and scalabi"], "locations": ["Central & Western Area"], "categories": ["Information Technology (IT)", "IT - Webmaster / SEO", "Technical Writing", "UI/UX Designer"], "post_time": "2022-01-16T03:00:57Z", "salary": {"currency": null, "max": null, "min": null, "period": "monthly", "term": null}, "salary_visible": false, "title_keywords": ["ux designer"], "responsibilities": ["control", "seo", "software", "systems", "quality", "developing", "design", "mock-ups", "designing", "communication", "maintaining brand consistency", "visual", "audio", "ui"], "requirements": {"degrees": ["university degree"], "majors": ["design"], "languages": ["english"], "language_level": [], "hard_skills": ["web applications", "seo", "web", "react", "adobe xd", "agile", "web pages", "aws", "mobile", "javascript", "integration", "code", "pl"], "soft_skills": ["communication skills", "work independently", "agile", "responsible", "communication", "positive working attitude"], "languages_combined": [{"language": "english", "language_level": []}]}, "experience_required": {"duration": [], "field": ["related", "design"]}}, {"job_id": "100003009048897", "location_code": "hk", "company": "GTS Platform Services Limited", "job_title": "C++ Developer", "description": "Responsibilities:\n\nParticipate in the development of the company\u2019s server, complete the design, development and programming tasks of the corresponding software with high quality;\nDevelop and improve the speed and scalability of existing trading systems;\nDaily maintenance of the existing system to ensure the safety and stability of the application system;\nAssist in providing training to juniors;\nReport to China team-lead.\n\n\u00a0Requirements:\n\nBachelor degree in Information Technology or related discipline.\n2 years\u2019 experience of C++ programming language development and related development and debugging tools;\nProficient in network protocol TCP, UDP, HTTP/WebSocket protocol, network programming and multi-threaded programming, with high concurrent service development experience;\nMaster MySQL, PostgreSQL, Redis and LevelDB, be able to design database tables independently and optimize SQL statements;\nProficient in Windows/Linux system, especially in C++11, with enthusiasm for solving practical business problems with new technical methods;\nHave strong sense of responsibility, good at logical and systematical thinking;\nExperience in large-scale financial transaction system development is highly preferred;\nGreat interest in exploring Fintech industry;\nEnergetic with can-do attitude and team spirit;\nStrong communication and presentation skills in Chinese and Mandarin.\nIANG is welcomed.\nWe provide competitive package to the right candidates:\n\n5 days work\nDiscretionary bonus\n13-21 days annual leave\nMarriage leave\nCompassionate leave\nMedical insurance\nDental scheme\nWFH policy\nUnlimited snacks and drinks provided\nPeriodic tea time gathering\nStaff team building activities\nand more...", "employment_types": ["Full Time", "Permanent"], "selling_points": ["Familiar with C++ language and Linux platform", "Familiar with MySQL, PostgreSQL, Redis and LevelDB", "Experience in fintech industry an advantage"], "locations": ["Tsim Sha Tsui"], "categories": ["Information Technology (IT)", "Software Development", "Technical Writing", "Sciences, Lab, R&D", "Research & Development (R&D)"], "post_time": "2022-01-14T07:38:16Z", "salary": {"currency": null, "max": null, "min": null, "period": "monthly", "term": null}, "salary_visible": false, "title_keywords": ["developer"], "responsibilities": ["software", "maintenance", "systems", "quality", "design", "develop", "application system", "report"], "requirements": {"degrees": ["degree", "bachelor", "master"], "majors": ["design", "information technology"], "languages": ["chinese", "mandarin"], "language_level": [], "hard_skills": ["linux", "c++", "tcp", "sql", "programming"], "soft_skills": ["independently", "team spirit", "can-do attitude", "sense of responsibility", "communication", "presentation skills", "energetic"], "languages_combined": [{"language": "chinese", "language_level": []}, {"language": "mandarin", "language_level": []}]}, "experience_required": {"duration": ["2 years"], "field": ["related", "development", "system development", "programming", "financial"]}}, {"job_id": "100003009048062", "location_code": "hk", "company": "EGUSI", "job_title": "Mobile & Web Application Programmer", "description": "To cope with our expansion, we are currently seeking a\u00a0Mobile & Web\u00a0Application Programmer\u00a0to join our software development team:\n\nJob Highlights\n\n0-3 year experiences on web/mobile application development\n5-days work, Work-Life Balance\nGood exposure to full software development cycle & pick up all-rounded programming skills\n\nResponsibilities:\n\nDesign, build and maintain web and mobile business applications for clients in various industries.\nParticipate in system design, programming, testing and system delivery\nMaintain and support the application services\nAnalyze and optimize program for efficiency and performance\n\nSkills & Qualifications:\n\nKnowledge or previous working experience on one of the programming languages such as Java, PHP, React, Nodejs, Python, C#\nGood working attitude, communication skills and problem-solving skills\nFresh graduates will be considered\nDiploma or University Graduate\nWe offer competitive remuneration packages to the right candidate. Interested parties please send full resume with expected salary and available date.", "employment_types": ["Full Time", "Part Time", "Permanent"], "selling_points": [], "locations": ["Yau Tsim Mong Area"], "categories": ["Information Technology (IT)", "Application Specialist - Software", "Software Development", "Technical Writing"], "post_time": "2022-01-14T04:38:02Z", "salary": {"currency": null, "max": null, "min": null, "period": "monthly", "term": null}, "salary_visible": false, "title_keywords": ["programmer"], "responsibilities": ["software", "system delivery", "design", "testing", "communication", "maintain", "system design", "application development"], "requirements": {"degrees": ["university graduate", "diploma"], "majors": [], "languages": [], "language_level": [], "hard_skills": ["java", "web", "php", "react", "mobile", "system design", "programming", "python", "problem-solving skills", "c#"], "soft_skills": ["communication skills", "good working attitude", "problem-solving skills"], "languages_combined": []}, "experience_required": {"duration": ["0-3 year"], "field": ["application development", "programming"]}}, {"job_id": "100003009047916", "location_code": "hk", "company": "Wings & Associates Consulting Engineers Limited", "job_title": "Senior Software Developer / Software Programmer", "description": "Requirements:\n\nDegree in Computer Science or related disciplines\n5 years of experience in software development\nSolid experience in program languages .NET (C#) and/or Python\nFamiliar with Microsoft Visual Studio and Excel VBA or other MS applications\nKnowledge in Dynamo Visual or Grasshopper Programming is a plus\nGood team player, self-motivated and strong sense of ownership\nGood communication and interpersonal skills\nPassionate about data analysis and improvement\nCandidates with less experience will be considered as Software Programmer\n\nResponsibilities:\n\nResponsible for the software development and programming of the software\nProvide technical solution in the system design, implement and features in framework\nPrepare technical specification for development and automation purpose\nPerform system testing and performance tuning\nWork with massive amount of data from various data sources and do analysis\n\nWe offer attractive remuneration and benefits including 5-day working week to the right candidates. Interested parties, please send your full resume including your\u00a0CURRENT\u00a0and\u00a0EXPECTED\u00a0salary to\u00a0our HR Manager by email.\u00a0\n\nPersonal data provided will be used by us for recruitment and related purposes, which is strictly in accordance with the Personal Data (Privacy) Ordinance (i.e. Cap. 486) for Applicants for Employment. Applicants who are not contacted within 6 weeks may consider your applications unsuccessful and the personal data collected will be destroyed after 6 months or such other period as prescribed by the applicable laws.", "employment_types": ["Full Time", "Permanent"], "selling_points": ["5-day work, Medical Allowance, Performance Bonus", "Happy Work Environment, Dynamic Team", "Good Career Prospect and Personal Development"], "locations": ["Kwun Tong"], "categories": ["Information Technology (IT)", "Application Specialist - Software", "Software Development", "Technical Writing"], "post_time": "2022-01-14T04:18:00Z", "salary": {"currency": null, "max": null, "min": null, "period": "monthly", "term": null}, "salary_visible": false, "title_keywords": ["developer", "programmer"], "responsibilities": ["software", "data", "analysis", "testing", "system design"], "requirements": {"degrees": ["degree"], "majors": ["related disciplines", "computer science"], "languages": [], "language_level": [], "hard_skills": ["excel", "vba", "plus", "ms applications", "analysis", "dynamo", "programming", "python", "c#"], "soft_skills": ["good team player", "communication and interpersonal skills", "passionate about", "self-motivated"], "languages_combined": []}, "experience_required": {"duration": ["5 years"], "field": ["software development"]}}, {"job_id": "100003009049071", "location_code": "hk", "company": "CL Technical Services Ltd.", "job_title": "Junior Programmer / Programmer (.Net C#, in-house)", "description": "Job Duties:\n\nInvolved in the full Software Development Lifecycle (\u201cSDLC\u201d) from performing business requirement study, documentation, analysis, design, development, testing, and user training to commissioning of the system\nConduct user requirement analysis for the development/implementation of new systems\nAssist in the integration testing, system testing, User Acceptance Test and implementation activities\nWork with business partners during system implementation and manage post implementation support\n\nRequirements:\n\nHigh Diploma or above in Computer Science or related discipline\nAt least 2 years proven experience in system development and maintenance (Less experience will be considered as Junior Programmer)\nFamiliar with C#, MSSQL, MVC, ASP.NET, HTML5, Javascript, Angular is required\nGood working attitude, presentation and communication skills\nHK Permanent Resident is required\n\nFor more job opportunity, please visit our website: www.clts.com\n\nThe personal information collected is strictly for recruitment purpose only.", "employment_types": ["Full Time"], "selling_points": ["5 days work", "Stable working environment", "Listed Company"], "locations": ["Kowloon Bay"], "categories": ["Information Technology (IT)", "Software Development", "Technical Writing", "Others"], "post_time": "2022-01-14T08:03:23Z", "salary": {"currency": null, "max": null, "min": null, "period": "monthly", "term": null}, "salary_visible": false, "title_keywords": ["programmer", "junior"], "responsibilities": ["user requirement", "commissioning", "software", "analysis", "systems", "implementation", "design", "testing", "documentation"], "requirements": {"degrees": ["high diploma or above"], "majors": ["computer science"], "languages": [], "language_level": [], "hard_skills": ["maintenance", "javascript", "angular", "mssql", "c#"], "soft_skills": ["communication skills", "good working attitude", "presentation"], "languages_combined": []}, "experience_required": {"duration": ["at least 2 years"], "field": ["maintenance", "system development"]}}, {"job_id": "100003009051043", "location_code": "hk", "company": "The Wharf Group", "job_title": "Network Engineer", "description": "Responsibilities:\n\nProvide support on the routine monitoring, configuration and maintenance of network devices\u00a0\nPerform first-tier end-user support on network connectivity problem\nPrepare and maintain documentation on network infrastructure, network setup, drawings, inventory and guidelines\nAssist to evaluate new technologies, plan and implement solutions to cope with\u00a0the business requirements\nHandle urgent business requests and network deployment duties timely during normal and non-office hours with company-assigned facilities including phone and laptop\n\nRequirements:\n\nDegree holder in Information Technology, Computer Science or related disciplines\nMinimum 2 years\u2019 experience in network implementations and operation, with strong technical exposure in LAN, WAN, switches, routers and firewall\nSolid experience in network infrastructure implementation projects with internal technical teams and external support partners\nHands-on experience in router & switch management for H3C/ Cisco/ Juniper; and firewall management on SonicWALL/ Palo Alto/ Checkpoint\nSelf-motivated, well-organized, good interpersonal skills, able to work independently or in a team\nGood command of both written and spoken English and Chinese\n\nWe work 5 days per week.\n\nInterested parties, please click \"APPLY NOW\" below and attach with your application letter and full resume.\u00a0\n\nFor further information of the Wharf Group, please visit our website: www.wharfholdings.com\n", "employment_types": ["Full Time", "Permanent"], "selling_points": [], "locations": ["Tsim Sha Tsui"], "categories": ["Information Technology (IT)", "Application Specialist - Network", "Network & System", "Technical Writing"], "post_time": "2022-01-15T01:26:08Z", "salary": {"currency": null, "max": null, "min": null, "period": null, "term": null}, "salary_visible": false, "title_keywords": ["engineer"], "responsibilities": ["network infrastructure", "provide support", "maintenance", "configuration", "guidelines", "inventory", "monitoring", "drawings", "evaluate", "plan", "maintain documentation", "setup"], "requirements": {"degrees": ["degree holder"], "majors": ["related disciplines", "computer science", "information technology"], "languages": ["english", "chinese"], "language_level": ["good command"], "hard_skills": ["router", "wan", "switch", "firewall"], "soft_skills": ["work independently", "self-motivated", "well-organized", "hands-on", "interpersonal skills"], "languages_combined": [{"language": "english", "language_level": ["good command"]}, {"language": "chinese", "language_level": ["good command"]}]}, "experience_required": {"duration": ["minimum 2 years"], "field": ["infrastructure", "management", "operation"]}}, {"job_id": "100003009051865", "location_code": "hk", "company": "Hong Kong Applied Science and Technology Research Institute Company Limited (ASTRI)", "job_title": "Computer Vision - Senior Lead Engineer / Lead Engineer", "description": "Reference #:\u00a0CTO/IOTSEN/07\nJob Responsibilities\n\nDevelopment of computer vision systems for industrial applications\nResearch on latest vision algorithms\nDesign and evaluation of vision software architecture\nSoftware integration of vision systems\nLiterature review and patent reading\nPreparation of technical documents\nOccasional business trips to other cities for onsite support\nRequirements\n\n\nPhD holder or Master\u2019s degree in Mathematics, Computer Science, Electronic Engineering or relevant disciplines with minimum 3 years of related experiences. Candidates with less experience may also be considered.\nStrong programming skills in C/C++ and Python\nExperience in GPU programming\nExpertise in:\n\nmachine-learning algorithms, including neural networks, optimizers,\u00a0etc., and\nimage-processing algorithms, including image feature extraction, registration, stereo vision,\u00a0etc.\nFamiliarity with TensorFlow, PyTorch, OpenCV or CUDA is a plus\nFluent in written and spoken English\n\nApplication\n\n\nThe appointment will be on renewable contract terms with a competitive salary and performance-linked variable pay. Fringe benefits include paid leave, medical and dental benefits, insurance coverage and contribution to MPF. The incumbent will normally work\u00a0a five-day week.\n\nInterested candidates, please send an application (quoting Ref. No.) with a detailed resume, current and expected salary to\u00a0Talent Acquisition by clicking \"APPLY NOW\".\u00a0The resume should\u00a0not\u00a0include any sensitive personal information such as HKID or passport number, photo, etc.\u00a0\n\nPosition offer is subject to the applicant\u2019s experience and academic qualification. The application will be open until the position is filled. Only short-listed candidates will be notified. ASTRI reserves the right not to fill the position.\n\nASTRI is an Equal Opportunities Employer. Personal data provided by job applicants will be used\u00a0exclusively\u00a0for recruitment\u00a0only. For details, please refer to\u00a0Privacy - ASTRI - Hong Kong Applied Science and Technology Research Institute Company Limited, in particular section 9.", "employment_types": ["Full Time", "Contract"], "selling_points": ["Development of computer vision systems", "Research on latest vision algorithms", "Preparation of technical documents"], "locations": ["Shatin Area"], "categories": ["Engineering", "Electrical / Electronics", "Information Technology (IT)", "Software Development", "Technical Writing"], "post_time": "2022-01-17T01:25:09Z", "salary": {"currency": null, "max": null, "min": null, "period": "monthly", "term": null}, "salary_visible": false, "title_keywords": ["engineer", "lead"], "responsibilities": ["software", "systems", "design", "evaluation", "literature review", "architecture"], "requirements": {"degrees": ["degree", "master"], "majors": ["mathematics", "engineering", "computer science"], "languages": ["english"], "language_level": ["fluent"], "hard_skills": ["plus", "c++", "cuda", "c", "programming", "python", "processing"], "soft_skills": ["learning"], "languages_combined": [{"language": "english", "language_level": ["fluent"]}]}, "experience_required": {"duration": ["minimum 3 years"], "field": ["related", "engineering", "programming"]}}, {"job_id": "100003009049107", "location_code": "hk", "company": "Hong Kong Interbank Clearing Ltd", "job_title": "Permanent/Contract Architect/Senior Specialist/Specialist I(Application Development)\u2013Web Application", "description": "Major Responsibilities\nResponsible for development of strategic business initiatives as well as maintenance of existing application systems\nParticipate in designing, coding, testing, debugging, documenting and implementing computer programs\nProduce necessary documentation whenever applicable\nAnalyse and define user requirements\nDesign and develop systems specifications\nOn call for emergency production incidents and provide fire fighting support\nRequirements\nUniversity education with over 10 years\u2019 mission-critical system development experience preferably in the financial sector for Architect (Application Development); over 5 years\u2019 experience for Senior Specialist (Application Development); over 3 years\u2019 experience for Specialist I (Application Development)\nProficient in Java EE technologies and web-based development, particularly in EJB, XML, XSL, Servlets, JMS, HTML, JQuery, JavaScript, and SQL. Prior working experience in Spring, Jasper Reports, Hibernate, Websphere MQ, WAS, DB2 and X.509 will be a definite advantage\nStrong schema design and DB2 DBA background are desirable for the roles related to database design\nGood technical writing skill and prior working experience in banking sector is preferable\nGood command of written and spoken English and Chinese\n\n\nHow to Apply\nInterested parties please send your curriculum vitae stating your current and expected salaries, and the contact phone number to the Human Resources Division, Unit B, 25/F, MG Tower, 133 Hoi Bun Road, Kwun Tong, Kowloon\u00a0 by clicking the \"Apply Now\" button below.\nAll applications and personal information collected will be treated in strict confidence and only be used for the purpose of recruitment and selection.\u00a0 The information collected will be accessed by our authorized personnel only.\u00a0 Those applicants not contacted by the Human Resources Division within two months from their application date should consider their applications filed for future reference which will be retained for one year for possible future job matching, and will be destroyed after the expiry of one year.", "employment_types": ["Full Time", "Permanent"], "selling_points": [], "locations": ["Ngau Tau Kok"], "categories": ["Information Technology (IT)", "Application Specialist - Software", "Software Development", "Technical Writing"], "post_time": "2022-01-14T08:08:13Z", "salary": {"currency": null, "max": null, "min": null, "period": null, "term": null}, "salary_visible": false, "title_keywords": ["specialist", "senior specialist"], "responsibilities": ["business initiatives", "maintenance", "coding", "testing", "designing", "documentation", "application systems"], "requirements": {"degrees": [], "majors": [], "languages": ["english", "chinese"], "language_level": ["good command"], "hard_skills": ["java", "hibernate", "web", "jquery", "html", "writing skill", "sql", "javascript", "spring"], "soft_skills": ["writing skill"], "languages_combined": [{"language": "english", "language_level": ["good command"]}, {"language": "chinese", "language_level": ["good command"]}]}, "experience_required": {"duration": ["5 years", "10 years", "3 years"], "field": ["system development", "education", "banking sector", "writing", "application development", "financial"]}}, {"job_id": "100003009048421", "location_code": "hk", "company": "Andrew Found Limited", "job_title": "System Analyst/ Full-stack Developer /Programmer - Web / Mobile  (Up to 60K)", "description": "Responsibilities:\n\nPerform as software engineer to handle on both front-end/ back-end development\nAnalyze project requirements wisely and achieve the project goals\nManage the development and maintenance on projects\u00a0\nEnsure smooth implementation and delivery of the projects\nAny ad-hoc job assigned\n\nRequirements:\n\nExperienced in software development is preferable\nDevelopment experience in Java/ NodeJS and related frameworks\nExperienced working in Web / Mobile Application development\u00a0\u00a0\nOther technical skills in one or more of the following areas would be an advantage: Spring framework, K8S technology, Docker, SQL, AWS\nFresh graduates are also welcomed*", "employment_types": ["Full Time", "Permanent"], "selling_points": ["Double Pay + Bonus, Dental & Medical cover", "Fin-tech / Payment / Web / Mobile Development", "Knowledge in Java / Javascript / NodeJS / React"], "locations": ["Not Specified"], "categories": ["Information Technology (IT)", "Application Specialist - Software", "Software Development", "Technical Writing"], "post_time": "2022-01-14T06:30:47Z", "salary": {"currency": null, "max": null, "min": null, "period": "monthly", "term": null}, "salary_visible": false, "title_keywords": ["developer", "system analyst", "programmer"], "responsibilities": ["ad-hoc", "project requirements", "software", "maintenance", "implementation"], "requirements": {"degrees": [], "majors": [], "languages": [], "language_level": [], "hard_skills": ["java", "web", "aws", "sql", "mobile", "spring"], "soft_skills": ["technical skills"], "languages_combined": []}, "experience_required": {"duration": [], "field": ["related", "development"]}}, {"job_id": "100003009049096", "location_code": "hk", "company": "CL Technical Services Ltd.", "job_title": "Programmer /Analyst Programmer (Java, in-house, Multiple Vacancies)", "description": "Job Duties:\n\nResponsible for development and maintenance of online portals and enterprise web applications\nGather users\u2019 requirements and translate users\u2019 requirements into system design\nInvolve in system testing and debugging\n\nJob Requirements:\n\nHigh Diploma in Computer Science, Information Technology or related discipline;\nProficient in at least one of the following programming languages: Java, Python and/or JavaScript;\nExperience in programming, preferably JAVA\nGood communication, analytical and problem-solving skills\nProficiency in both of English and Chinese\nHK Permanent Resident is required\n\nFor more job opportunity, please visit our website: www.clts.com\n\nThe personal information collected is strictly for recruitment purpose only.", "employment_types": ["Full Time"], "selling_points": ["Both commercial and gov\u2019t project", "Competitive pay", "Listed company"], "locations": ["Central & Western Area"], "categories": ["Information Technology (IT)", "Support", "Software Development", "Technical Writing"], "post_time": "2022-01-15T03:50:07Z", "salary": {"currency": null, "max": null, "min": null, "period": "monthly", "term": null}, "salary_visible": false, "title_keywords": ["analyst programmer", "programmer"], "responsibilities": ["system design", "maintenance", "testing"], "requirements": {"degrees": ["high diploma"], "majors": ["computer science", "information technology"], "languages": ["english", "chinese"], "language_level": ["proficiency"], "hard_skills": ["java", "javascript", "programming", "python", "problem-solving skills"], "soft_skills": ["communication", "problem-solving skills"], "languages_combined": [{"language": "english", "language_level": ["proficiency"]}, {"language": "chinese", "language_level": ["proficiency"]}]}, "experience_required": {"duration": [], "field": ["programming"]}}, {"job_id": "100003009050063", "location_code": "hk", "company": "Esri China (Hong Kong) Ltd", "job_title": "Programmer (Fresh Graduate)", "description": "Job Descriptions:\n\nDefine, document and translate business requirements into system specification;\nPerform analysis, design, programming and testing following system development life cycle (SDLC) methodology and adhering to corporate-wise technology standards;\nAdhere to the development processes including coding standards, technical; documentation standards, QA processes, configuration management;\nWork closely in team-environment and meet project schedules; and\nKeep good communication and coordination with team members.\n\nRequirements:\n\nDegree in Computer Science, Information Technology or related disciplines;\nKnowledge in Microsoft .NET Framework (C#) or JavaScript in Web programming;\nFluent in applying SQL statements for data manipulations;\nGood command of written and spoken in Chinese and English;\nFresh graduate is welcomed to apply; and\nImmediately available is highly preferable.\n\nWe offer five-day work week, attractive career opportunities, remuneration and benefits to the right candidates. Interested applicants, please submit detailed resume with current & expected salary and date of availability to Human Resources Department by clicking the below\u00a0Apply Now.\u00a0\n\n(For more information about our Company, please visit our website www.esrichina.hk)\n(Application received will be treated in strict confidence and will be used exclusively\u00a0for recruitment-related purposes.)", "employment_types": ["Full Time", "Permanent"], "selling_points": [], "locations": ["Lai Chi Kok"], "categories": ["Information Technology (IT)", "Support", "Network & System", "Technical Writing"], "post_time": "2022-01-14T09:42:52Z", "salary": {"currency": null, "max": null, "min": null, "period": "monthly", "term": null}, "salary_visible": false, "title_keywords": ["programmer"], "responsibilities": ["management", "configuration", "schedules", "analysis", "coordination with", "coding", "design", "testing", "communication", "documentation"], "requirements": {"degrees": ["degree", "fresh graduate"], "majors": ["related disciplines", "computer science", "information technology"], "languages": ["english", "chinese"], "language_level": ["good command"], "hard_skills": ["web", "sql", "javascript", "programming", "c#"], "soft_skills": [], "languages_combined": [{"language": "english", "language_level": ["good command"]}, {"language": "chinese", "language_level": ["good command"]}]}, "experience_required": {"duration": [], "field": []}}, {"job_id": "100003009049843", "location_code": "hk", "company": "Aloha Fintech Limited", "job_title": "Analyst Programmer (Ruby / Golang)", "description": "We are looking for a high-caliber talent to join our team. As an Analyst Programmer, \u00a0you will participate in crypto exchange project led by blockchain professionals.\u00a0\n\n\u00a0RESPONSIBILITIES\n\nTranslating business ideas into holistic and functional applications\nMaintaining code quality, organization and automatization\nMaintenance, development and enhancement of backend services\nManage any ad hoc tasks or projects as assigned\n\nREQUIREMENTS\n\nHigh Diploma or above in computer science, computing or other related discipline\u00a0\nProficient on programming with any of Ruby on Rails /\u00a0Golang / Javascript / Python / Flutter\n\u00a0Familiar with MySQL, Redis, NoSQL or other databases\nFamiliar with RabbitMQ / Kafka\n2 \u2013 5 years of relevant work experience\nExperience in Blockchain exchange and wallet project development will be an advantage\n\nIf you are interested in blockchain technology and want to start a new challenging job in the fintech industry, please don\u2019t hesitate to apply with your full resume, present/expected salary, and availability by click on the 'Apply' button.\n\n* Personal data provided are treated in strictest confidence and for recruitment purposes only. *", "employment_types": ["Full Time"], "selling_points": ["Young and dynamic team in blockchain industry", "Competitive remuneration package", "Work life balance"], "locations": ["Tsim Sha Tsui"], "categories": ["Information Technology (IT)", "Support", "Software Development", "Technical Writing"], "post_time": "2022-01-14T09:18:50Z", "salary": {"currency": null, "max": null, "min": null, "period": "monthly", "term": null}, "salary_visible": false, "title_keywords": ["analyst programmer"], "responsibilities": ["ideas", "maintenance", "maintaining", "quality", "ad hoc tasks"], "requirements": {"degrees": ["high diploma or above"], "majors": ["computer science"], "languages": [], "language_level": [], "hard_skills": ["blockchain", "ruby on rails", "javascript", "databases", "programming", "python", "exchange"], "soft_skills": ["interested in", "confidence"], "languages_combined": []}, "experience_required": {"duration": ["5 years"], "field": ["development"]}}, {"job_id": "100003009051862", "location_code": "hk", "company": "Hong Kong Applied Science and Technology Research Institute Company Limited (ASTRI)", "job_title": "Embedded System - Senior Lead Engineer / Lead Engineer", "description": "Reference #:\u00a0CTO/IOTSEN/08\n\nJob Responsibilities\n\nDevelopment system integration of embedded computer vision systems for industrial applications\nDesign and evaluation of FPGA/SoC architecture or embedded system\nResearch on point cloud processing algorithms or other latest 3D vision algorithms\nLiterature review and patent reading\nPreparation of technical documents\nRequirements\n\n\nPh.D. holder or Master\u2019s degree in Electronic Engineering, Computer Science or relevant disciplines with a minimum of 3 years of related experiences. Candidate with less experiences may also be considered.\nStrong programming skills in VHDL/Verilog, C/C++ and Python, experience in cross-platform programming.\nSolid understanding in FPGA programming / embedded system or SoC architecture, related firmware development, data structure, algorithms, and image processing.\nExperience in analogue & digital circuit design and signal processing is a plus.\nFluent in written and spoken English\nLive ASTRI values\nApplication\n\nThe appointment will be on renewable contract terms with a competitive salary and performance-linked variable pay. Fringe benefits include paid leave, medical and dental benefits, insurance coverage and contribution to MPF. The incumbent will normally work\u00a0a five-day week.\n\nInterested candidates, please send an application (quoting Ref. No.) with a detailed resume, current and expected salary to\u00a0Talent Acquisition by clicking \"APPLY NOW\".\u00a0The resume should\u00a0not\u00a0include any sensitive personal information such as HKID or passport number, photo, etc.\u00a0\n\nPosition offer is subject to the applicant\u2019s experience and academic qualification. The application will be open until the position is filled. Only short-listed candidates will be notified. ASTRI reserves the right not to fill the position.\n\nASTRI is an Equal Opportunities Employer. Personal data provided by job applicants will be used\u00a0exclusively\u00a0for recruitment\u00a0only. For details, please refer to\u00a0Privacy - ASTRI - Hong Kong Applied Science and Technology Research Institute Company Limited, in particular section 9.", "employment_types": ["Full Time", "Contract"], "selling_points": ["FPGA programming / embedded system", "Stable working environment with career path", "R&D projects with good exposure, 5 days work"], "locations": ["Shatin Area"], "categories": ["Engineering", "Electrical / Electronics", "Information Technology (IT)", "Application Specialist - Software", "Technical Writing"], "post_time": "2022-01-17T01:24:44Z", "salary": {"currency": null, "max": null, "min": null, "period": "monthly", "term": null}, "salary_visible": false, "title_keywords": ["engineer", "lead"], "responsibilities": ["systems", "design", "evaluation", "literature review", "architecture"], "requirements": {"degrees": ["degree", "master"], "majors": ["engineering", "computer science"], "languages": ["english"], "language_level": ["fluent"], "hard_skills": ["plus", "c++", "verilog", "c", "vhdl", "programming", "python", "processing", "signal"], "soft_skills": [], "languages_combined": [{"language": "english", "language_level": ["fluent"]}]}, "experience_required": {"duration": ["minimum of 3 years"], "field": ["engineering", "related", "design", "programming", "digital"]}}, {"job_id": "100003009049293", "location_code": "hk", "company": "Henderson Land Development Company Limited", "job_title": "ANALYST PROGRAMMER / SENIOR PROGRAMMER / PROGRAMMER", "description": "Ref. No.: JDB/HLD20/APSP\n\n\nDegree in IT or related discipline\nMinimum 1 year's solid experience in Web Development with HTML5, CSS3, .Net, JavaScript, Ionic, Cordova, node.js, Angular, Jquery and object oriented development experience of Delphi / C++\nExperience in Windows & MS SQL is a must\nFamiliar with mobile development, XCode is preferred\n\nAttractive salary and fringe benefits will be offered to the successful candidates. Please apply with full resume by mail to\u00a0Human Resources Department, Henderson Land Development Co. Ltd., 71/F, Two International Finance Centre, 8 Finance Street, Central, Hong Kong\u00a0or by fax at\u00a02905 1855\u00a0or visit our homepage at\u00a0http://www.hld.com\u00a0or\u00a0by clicking \"Apply Now\".\n\n(Please quote the ref. no. on letter)\u00a0\n\nPersonal data provided by job applicants will be used for recruitment purpose only.", "employment_types": ["Full Time", "Permanent"], "selling_points": ["Medical Allowance", "Education Allowance", "Free Lunch"], "locations": ["Central"], "categories": ["Information Technology (IT)", "Product Management / Business Analyst", "Technical Writing", "Others"], "post_time": "2022-01-14T08:23:37Z", "salary": {"currency": null, "max": null, "min": null, "period": "monthly", "term": null}, "salary_visible": false, "title_keywords": ["analyst programmer", "programmer", "senior programmer"], "responsibilities": [], "requirements": {"degrees": ["degree"], "majors": ["it"], "languages": [], "language_level": [], "hard_skills": ["web development", "no", "c++", "jquery", "mobile", "javascript", "angular", "delphi", "ms sql"], "soft_skills": [], "languages_combined": []}, "experience_required": {"duration": ["minimum 1 year"], "field": ["sql", "development"]}}, {"job_id": "100003009047741", "location_code": "hk", "company": "Leadership Solutions Limited", "job_title": "Application Support", "description": "Job Nature:\n\nInstall, configure and regular update software application and database\nProvide daily operation and technical applications & databases.\nConduct user, technical and support documents writing\nRender on-site or remote end user training or support service\nInteract with end-users directly for problem identification and resolution\nRespond to, prioritize, escalate as well as resolve variety of application or database issues\nWork closely with Development Team for project support\n\nRequirements:\n\nDiploma holder in Business, Information Systems, Computer Science or equivalent\nRelevant working experience in supporting Information Systems/Applications/Databases.\nExperience in using SQL for data management on Microsoft SQL Server\nWith strong analytical skills and able to liaise with users at different levels effectively\nAble to work independently and effectively as part of a team with multiple tasks simultaneously\nGood presentation and interpersonal communication skills\nGood command of written and spoken English and Cantonese", "employment_types": ["Full Time", "Permanent"], "selling_points": ["Diploma holder in Business, Information Systems", "Great Learning Platform", "5 working days, performance bonus, bank holiday"], "locations": ["Not Specified"], "categories": ["Information Technology (IT)", "Support", "Testing / QA", "Technical Writing"], "post_time": "2022-01-14T03:49:48Z", "salary": {"currency": null, "max": null, "min": null, "period": "monthly", "term": null}, "salary_visible": false, "title_keywords": ["application support"], "responsibilities": ["management", "software", "data", "systems", "daily operation", "resolution", "communication", "databases", "database", "liaise with"], "requirements": {"degrees": ["diploma holder"], "majors": ["business", "computer science"], "languages": ["cantonese", "english"], "language_level": ["good command"], "hard_skills": ["data management", "analytical skills", "sql", "databases", "microsoft sql server"], "soft_skills": ["communication skills", "work independently", "multiple tasks", "prioritize", "analytical skills", "interpersonal", "presentation"], "languages_combined": [{"language": "cantonese", "language_level": ["good command"]}, {"language": "english", "language_level": ["good command"]}]}, "experience_required": {"duration": [], "field": ["sql", "management", "relevant working experience"]}}, {"job_id": "100003009049109", "location_code": "hk", "company": "Hong Kong Interbank Clearing Ltd", "job_title": "Architect / Senior Specialist (Application Development) \u2013 Mainframe", "description": "Major Responsibilities\n\n\nResponsible for development of strategic business initiatives as well as maintenance of existing application systems\nParticipate in designing, coding, testing, debugging, documenting and implementing computer programs\nProduce necessary documentation whenever applicable\nAnalyse and define user requirements\nDesign and develop systems specifications\nOn call for emergency production incidents and provide fire fighting support\n\nRequirements\n\n\nUniversity education with over 10 years\u2019 mission-critical system development experience preferably in the financial sector for Architect (Application Development); over 5 years\u2019 experience for Senior Specialist (Application Development); over 3 years\u2019 experience for Specialist I (Application Development)\nProficient in z/OS, CICS, COBOL and VSAM\nKnowledge in Java EE technologies and web-based development, particularly in EJB, XML, XSL, Servlets, JMS, HTML, JQuery, JavaScript, Jasper Reports, WAS, Websphere MQ, Spring and SQL will be an advantage.\nGood technical writing skill and prior working experience in banking sector is preferable\nGood command of written and spoken English and Chinese\n\n\n\nHow to Apply\n\n\nInterested parties please send your curriculum vitae stating your current and expected salaries, and the contact phone number to the Human Resources Division, Unit B, 25/F, MG Tower, 133 Hoi Bun Road, Kwun Tong, Kowloon\u00a0\u00a0by clicking the \"Apply Now\" button below.\nAll applications and personal information collected will be treated in strict confidence and only be used for the purpose of recruitment and selection.\u00a0 The information collected will be accessed by our authorized personnel only.\u00a0 Those applicants not contacted by the Human Resources Division within two months from their application date should consider their applications filed for future reference which will be retained for one year for possible future job matching, and will be destroyed after the expiry of one year.", "employment_types": ["Full Time", "Permanent"], "selling_points": [], "locations": ["Ngau Tau Kok"], "categories": ["Banking / Finance", "Financial Services", "Information Technology (IT)", "Application Specialist - Software", "Technical Writing"], "post_time": "2022-01-14T08:08:14Z", "salary": {"currency": null, "max": null, "min": null, "period": null, "term": null}, "salary_visible": false, "title_keywords": ["senior specialist"], "responsibilities": ["business initiatives", "maintenance", "coding", "testing", "designing", "documentation", "application systems"], "requirements": {"degrees": [], "majors": [], "languages": ["english", "chinese"], "language_level": ["good command"], "hard_skills": ["java", "web", "jquery", "cics", "html", "writing skill", "sql", "os", "javascript", "spring", "cobol"], "soft_skills": ["writing skill"], "languages_combined": [{"language": "english", "language_level": ["good command"]}, {"language": "chinese", "language_level": ["good command"]}]}, "experience_required": {"duration": ["5 years", "10 years", "3 years"], "field": ["system development", "education", "banking sector", "writing", "application development", "financial"]}}, {"job_id": "100003009050069", "location_code": "hk", "company": "Esri China (Hong Kong) Ltd", "job_title": "Programmer (Non-degree Holder)", "description": "Job Descriptions:\n\nDefine, document and translate business requirements into system specification;\nPerform analysis, design, programming and testing following system development life cycle (SDLC) methodology and adhering to corporate-wise technology standards;\nAdhere to the development processes including coding standards, technical; documentation standards, QA processes, configuration management;\nWork closely in team-environment and meet project schedules; and\nKeep good communication and coordination with team members.\n\nRequirements:\n\nHigher Diploma in Computer Science, Information Technology or related disciplines;\nKnowledge in Microsoft .NET Framework (C#) or JavaScript in Web programming;\nFluent in applying SQL statements for data manipulations;\nGood command of written and spoken in Chinese and English;\nFresh graduate is welcomed to apply; and\nImmediately available is highly preferable.\n\nWe offer five-day work week, attractive career opportunities, remuneration and benefits to the right candidates. Interested applicants, please submit detailed resume with current & expected salary and date of availability to Human Resources Department by clicking the below\u00a0Apply Now.\u00a0\n\n(For more information about our Company, please visit our website www.esrichina.hk)\n(Application received will be treated in strict confidence and will be used exclusively\u00a0for recruitment-related purposes.)", "employment_types": ["Full Time", "Permanent"], "selling_points": [], "locations": ["Lai Chi Kok"], "categories": ["Information Technology (IT)", "Support", "Network & System", "Technical Writing"], "post_time": "2022-01-14T09:43:31Z", "salary": {"currency": null, "max": null, "min": null, "period": "monthly", "term": null}, "salary_visible": false, "title_keywords": ["programmer"], "responsibilities": ["management", "configuration", "schedules", "analysis", "coordination with", "coding", "design", "testing", "communication", "documentation"], "requirements": {"degrees": ["diploma", "fresh graduate"], "majors": ["related disciplines", "computer science", "information technology"], "languages": ["english", "chinese"], "language_level": ["good command"], "hard_skills": ["web", "sql", "javascript", "programming", "c#"], "soft_skills": [], "languages_combined": [{"language": "english", "language_level": ["good command"]}, {"language": "chinese", "language_level": ["good command"]}]}, "experience_required": {"duration": [], "field": []}}, {"job_id": "100003009048818", "location_code": "hk", "company": "Hong Kong Air Cargo Terminals Ltd", "job_title": "Team Lead (Application Development)", "description": "Hong Kong Air Cargo Terminals Limited (Hactl) is one of the world\u2019s leading air cargo terminals with the unique world-class facilities, highly efficient operation, and innovative technology.\n\nKey Responsibilities\n\nLead a development team to conduct production support and project delivery for our cargo handling systems\nConduct technical analysis and design\nProvide on-going support and maintenance for our mission critical systems\nManage external vendors and developers in offshore development center\n\nQualifications\n\nHigh Diploma / Bachelor degree holders in Information Technology, Computer Engineering, Computer Science or related disciplines\nMinimum 8 years\u2019 experience in application development where 3 years\u2019 experience as team leader role\nHands-on experience or good knowledge in the followings:\nJava, Spring Framework, WebLogic, Tomcat\nOracle RDBMS, SQL and RDBMS\nDevOps, version control system (e.g. GIT, SVN), maven, JIRA\nMulti-tier and high availability system architecture\nAbility to work independently and proactively in a flexible and dynamic environment\nGood analysis, problem solving and communication skills\nGood team player, strong self-initiative, and commit to achieve high quality results\nPrior working experience in cargo handling systems or at least 4 years\u2019 development experience in large-scale mission-critical system is definitely an advantage\nCandidate with less experience will be considered as IT specialist\n\nWe offer 5-Day work week with a competitive and comprehensive remuneration package including Chinese New Year bonus, discretionary bonus, transport subsidy, employer topped-up MPF contributions, medical benefits (including family members), voluntary dental coverage (including family members), life insurance, birthday leave, extra annual leave, marriage leave, maternity leave, paternity leave, newborn baby gift, sports centre and free shuttle bus.\n\nInterested parties please apply with full resume detailing experience, qualifications and expected salary by post, by e-mail or click \"Apply Now\".\n\nBy post: Human Resources, 6/F, North Office Block, SuperTerminal 1, Hong Kong International Airport, HK\n\nPlease quote the above reference in your application. To know more about our company, please visit our website https://careers.hactl.com/.\n\nApplicants not invited for interview within four weeks should consider their applications unsuccessful. Applicants\u2019 personal data collected will only be used for the sole purpose of recruitment. The data of unsuccessful applicants will be destroyed within six months.", "employment_types": ["Full Time", "Permanent"], "selling_points": ["Team leader", "Enterprise level JAVA application design", "Guarantee 13th month pay & discretionary bonus"], "locations": ["Airport Area"], "categories": ["Information Technology (IT)", "Support", "Technical Writing", "Others"], "post_time": "2022-01-14T07:21:52Z", "salary": {"currency": null, "max": null, "min": null, "period": "monthly", "term": null}, "salary_visible": false, "title_keywords": ["lead"], "responsibilities": ["control", "mpf", "maintenance", "analysis", "systems", "quality", "design", "communication", "application development", "insurance", "architecture"], "requirements": {"degrees": ["high diploma", "degree", "bachelor"], "majors": ["related disciplines", "computer engineering", "computer science", "information technology"], "languages": ["chinese"], "language_level": [], "hard_skills": ["java", "git", "maintenance", "devops", "analysis", "technical analysis", "sql", "problem solving", "dynamic", "spring", "oracle"], "soft_skills": ["efficient", "flexible", "work independently", "dynamic environment", "communication skills", "good team player", "unique", "problem solving", "hands-on", "comprehensive", "self-initiative", "innovative", "world-class"], "languages_combined": [{"language": "chinese", "language_level": []}]}, "experience_required": {"duration": ["3 years", "minimum 8 years", "at least 4 years"], "field": ["development", "application development", "it", "team"]}}, {"job_id": "100003009045769", "location_code": "hk", "company": "Kepro Solutions Limited", "job_title": "Analyst Programmer (1-Year Contract)", "description": "Participate in the whole Software Development Life Cycle including functional requirement collection, system analysis and design, data modelling, programming, system tests, user acceptance tests, user trainings, system promotion procedures and controls, batch job setup and scheduling, monitoring and control measurements.\u00a0\nCollaborate with project managers, business analyst, system analyst and quality assurance to implement and develop system/application for internal users and external clients.\nPerform R&D as needed.\n\nRequirement:\n\nDegree\u00a0or Diploma\u00a0in Computer Science, Information Technology or any related discipline with relevant experience.\nKnowledge on Java, J2EE, JavaScript, .NET, Python, HTML5.\n3 years or above related working experience.\nAbility to provide efficient, timely, and reliable service to customers.\nGood command of both written and spoken English and Chinese.\n\nWe offer a competitive remuneration package, career advancement opportunities and fringe benefits to the right candidate. Interested parties please send your full resume with\u00a0present and expected salary\u00a0to us by clicking \"Apply Now\".\u00a0\u00a0\n\nCompany Address: 9/F, The Whitney, 183 Wai Yip Street, Kwun Tong, Hong Kong\n\nCorporate Website:\u00a0http://www.kepro.com.hk/eng/index.php\n\n(We are an Equal Opportunity Employer and personal data collected would be used for recruitment purpose only.)", "employment_types": ["Full Time", "Contract"], "selling_points": ["Participate in the whole Software Development Life", "Project managers, business analyst, system analyst", "Knowledge on Java,J2EE,JavaScript,NET,Python,HTML5"], "locations": ["Kwun Tong"], "categories": ["Information Technology (IT)", "Product Management / Business Analyst", "Software Development", "Technical Writing"], "post_time": "2022-01-13T08:36:35Z", "salary": {"currency": null, "max": null, "min": null, "period": "monthly", "term": null}, "salary_visible": false, "title_keywords": ["analyst programmer"], "responsibilities": ["collaborate with", "control", "software", "data", "analysis", "monitoring", "procedures", "quality", "design", "develop", "scheduling", "setup"], "requirements": {"degrees": ["diploma", "degree"], "majors": ["computer science", "information technology"], "languages": ["english", "chinese"], "language_level": ["good command"], "hard_skills": ["r&d", "java", "analysis", "batch", "javascript", "programming", "python"], "soft_skills": ["efficient", "timely", "reliable"], "languages_combined": [{"language": "english", "language_level": ["good command"]}, {"language": "chinese", "language_level": ["good command"]}]}, "experience_required": {"duration": ["3 years"], "field": ["related", "relevant experience", "information technology"]}}, {"job_id": "100003009042038", "location_code": "hk", "company": "EC Healthcare", "job_title": "System Analyst", "description": "Job Highlights\n\nIn-house application development and documentation\nRequirements analysis, prototype, design, coding, testing\nCloud Solution Development\nJava, J2EE technology, Angular\n\nJob Responsibilities:\n\nPerform overall software development life cycle that meets user requirements and complies to standard;\nProvide leadership and clarity to programmer, review vendor work and challenge them on technical matters where necessary; and\nProvide on-going support to ensure service stability and availability for IT systems.\n\nRequirements:\n\nHigher Diploma / Bachelor Degree in Computer Science or any related disciplines;\n5+ years\u2019 work experience in IT development field, less experience may be considered as Senior Analyst Programmer;\nGood technical skills in one or more of the following areas would be an advantage: Kotlin, Spring framework, Hibernate, K8S technology, Docker, SQL, ETL;\nGood analytical and problem-solving skills;\nAggressive, self-motivated, result-orientated and able to work under pressure;\nExcellent interpersonal and communication skills; and\nGood command of Cantonese, English and Mandarin.", "employment_types": ["Full Time"], "selling_points": ["Java, J2EE technology, Angular", "Cloud Solution Development", "In-house application development and documentation"], "locations": ["Mong Kok"], "categories": ["Information Technology (IT)", "Application Specialist - Software", "Software Development", "Technical Writing"], "post_time": "2022-01-12T05:34:06Z", "salary": {"currency": null, "max": null, "min": null, "period": "monthly", "term": null}, "salary_visible": false, "title_keywords": ["system analyst"], "responsibilities": ["review", "software", "systems"], "requirements": {"degrees": ["diploma", "degree", "bachelor"], "majors": ["related disciplines", "computer science"], "languages": ["cantonese", "english", "mandarin"], "language_level": ["good command"], "hard_skills": ["hibernate", "sql", "spring", "problem-solving skills", "kotlin"], "soft_skills": ["communication skills", "self-motivated", "technical skills", "problem-solving skills", "interpersonal", "work under pressure"], "languages_combined": [{"language": "cantonese", "language_level": ["good command"]}, {"language": "english", "language_level": ["good command"]}, {"language": "mandarin", "language_level": ["good command"]}]}, "experience_required": {"duration": ["5+ years"], "field": ["it development"]}}, {"job_id": "100003009046235", "location_code": "hk", "company": "AXA Hong Kong", "job_title": "Senior Data and API Analyst", "description": "Your responsibilities\n\n\nOversight of Data Management requirements gathering, analysis and clarification\nOverall owner of design of Data Management components including Data Models, ETL, MDM and Data storage systems (including non-functional design)\nKey contact for engagement of Data Management vendors deliver to ensure delivery of high-quality Regional Data Solutions\nActively monitor the delivery life cycle and manage scope, schedule, quality and cost.\nOversee Data Quality review, definition of validation rules and exception handling\nLead Performance Tuning across Data technologies\nReview and signoff functional and technical designs and specifications\nReview test scope, test approach, and test strategies related to Data Management\nWork with vendor and internal teams to plan and complete production implementation\nOwn and maintain the application domain knowledge for Data Management applications, drive the team to maintain awareness of technology trends to ensure the delivery of best practice\n\nJob Requirements:\n\nTypically requires a tertiary qualification in an IT discipline or related field\nMinimum of 4-5 years of proven leadership and Business Intelligence experience in the financial services industry\nStrong analytical capability and skills related to business intelligence (i.e. - database architecture design, Data Services, etc.)\nCompetent delivering results through ownership & drive\nProven ability to lead, motivate and develop a team\nThe ability to think creatively and ensure services meets stakeholder needs and are fit for purpose.\nDemonstrated ability to create strong working relationships with others\nAbility to gather, synthesise and analyse data and draw logical conclusions", "employment_types": ["Full Time", "Permanent"], "selling_points": ["IT data & application development", "Exposure to Insurance products & industry", "Good working environment & culture"], "locations": ["Southern Area"], "categories": ["Information Technology (IT)", "Support", "Software Development", "Technical Writing"], "post_time": "2022-01-13T10:03:14Z", "salary": {"currency": null, "max": null, "min": null, "period": "monthly", "term": null}, "salary_visible": false, "title_keywords": ["analyst"], "responsibilities": ["management", "cost", "designs and specifications", "data", "production implementation", "analysis", "clarification", "systems", "quality", "design", "monitor", "review", "teams", "maintain", "contact", "schedule", "plan"], "requirements": {"degrees": [], "majors": [], "languages": [], "language_level": [], "hard_skills": ["business intelligence"], "soft_skills": ["leadership", "competent"], "languages_combined": []}, "experience_required": {"duration": ["minimum of 4-5 years"], "field": ["financial services industry", "business"]}}, {"job_id": "100003009046097", "location_code": "hk", "company": "Hoo Technology Limited", "job_title": "Development Engineer | Blockchain Related", "description": "Job description and responsibilities\n1. Design and implement smart contracts and related tools;\n2. Optimize the underlying code of the chain;\n3. Develop various public chain auxiliary tools and applications.\n\nJob requirements\n1. Proficient in Dapp development languages \u200b\u200band contract frameworks such as Solidity, react, Nodejs;\n2. Proficient in one or more languages of Golang / C++ / Rust;\n3. 3 years of blockchain related development experience;\n4. Good English reading ability;\n5. Good communication and presentation skills.", "employment_types": ["Full Time", "Contract"], "selling_points": ["3 year blockchain related development experience", "Good English reading ability", "Salary is negotiable"], "locations": ["Tsuen Wan Area"], "categories": ["Information Technology (IT)", "Technical Writing"], "post_time": "2022-01-13T09:36:34Z", "salary": {"currency": null, "max": null, "min": null, "period": "monthly", "term": null}, "salary_visible": false, "title_keywords": ["engineer"], "responsibilities": ["contracts", "design", "develop"], "requirements": {"degrees": [], "majors": [], "languages": ["english"], "language_level": ["good"], "hard_skills": ["blockchain", "c++", "react", "rust", "solidity"], "soft_skills": ["communication", "presentation skills"], "languages_combined": [{"language": "english", "language_level": ["good"]}]}, "experience_required": {"duration": ["3 years"], "field": ["related", "development"]}}, {"job_id": "100003009046151", "location_code": "hk", "company": "Eddid FinTech Limited", "job_title": "Java Developer (Payment & Settlement System)", "description": "To cope with rapid expansion in the Great China region, we are recruiting capable talent to join us.\n\nKey elements of the job will involve:\n\nPerform the tasks of coding, testing and deploying application programs\nImplement IT projects to enhance effectiveness of IT applications and to ensure the project deadlines are met\nPerform other duties assigned by supervisor\n\nThe ideal candidate should be a :\n\nBachelor degree in computer science or other related disciplines\n3-5 year experience of java programmer\nKnowledge in spring, springboot, mysql, redis, mybatis, linux, git\nKnowledge/ Experience in Agile would be an advantage\u00a0\nWork closely with both local and offshore teams on the development\ngood command of spoken Putonghua is an advantage\nA good team player with strong analytical/trouble shooting skills, and self-motivated\n\nWe offer an exciting career opportunity to the successful candidate. Please email your detailed resume with current and expected salary and availability by clicking \u201cApply Now\u201d.\n\nAll information provided will be treated in strict confidence and used solely for recruitment purposes.", "employment_types": ["Full Time", "Permanent"], "selling_points": ["3-5 year experience of java programmer", "Bachelor degree in computer science or others", "5 days work; Bonus; OT Pay, Medical Insurance"], "locations": ["Wan Chai"], "categories": ["Information Technology (IT)", "Application Specialist - Software", "Software Development", "Technical Writing"], "post_time": "2022-01-13T09:44:50Z", "salary": {"currency": null, "max": null, "min": null, "period": "monthly", "term": null}, "salary_visible": false, "title_keywords": ["developer"], "responsibilities": ["perform other duties", "teams", "coding", "testing"], "requirements": {"degrees": ["degree", "bachelor"], "majors": ["related disciplines", "computer science"], "languages": ["putonghua"], "language_level": ["advantage", "good command"], "hard_skills": ["linux", "java", "git", "agile", "spring", "rapid"], "soft_skills": ["self-motivated", "good team player", "capable", "agile", "ideal"], "languages_combined": [{"language": "putonghua", "language_level": ["advantage", "good command"]}]}, "experience_required": {"duration": ["3-5 year"], "field": []}}, {"job_id": "100003009048815", "location_code": "hk", "company": "Hong Kong Air Cargo Terminals Ltd", "job_title": "Senior IT Analyst (Application Development)", "description": "Key Responsibilities\n\nWork in a development team to conduct production support and project delivery for our cargo handling systems\nParticipate in application development and testing\nAssist IT specialist to conduct technical analysis and design\nProvide on-going support and maintenance for our mission critical systems\nWork with external vendors and developers in offshore development center\n\nRequirements\n\nHigh Diploma / Bachelor degree holders in Information Technology, Computer Engineering, Computer Science or related disciplines\nMinimum 4 years\u2019 experience in application development\nHands-on experience or good knowledge in the followings:\nJava, Spring Framework, WebLogic, Tomcat\nOracle RDBMS, SQL and RDBMS\nDevOps, version control system (e.g. GIT, SVN), maven, JIRA\nAbility to work independently and proactively in a flexible and dynamic environment\nGood analytical, problem solving and communication skills\nGood team player, strong self-initiative, and commit to achieve high quality results\nPrior working experience in cargo handling systems or at least 2 years\u2019 development experience in large-scale mission-critical system is definitely an advantage\nCandidates with less experience may be considered as IT Analyst\n\nWe offer 5-Day work week with a competitive and comprehensive remuneration package including Chinese New Year bonus, discretionary bonus, transport subsidy, employer topped-up MPF contributions, medical benefits (including family members), voluntary dental coverage (including family members), life insurance, birthday leave, extra annual leave, marriage leave, maternity leave, paternity leave, newborn baby gift, sports centre and free shuttle bus.\n\nInterested parties please apply with full resume detailing experience, qualifications and expected salary by post, by e-mail or click \"Apply Now\".\n\nBy post: Human Resources, 6/F, North Office Block, SuperTerminal 1, Hong Kong International Airport, HK\n\nPlease quote the above reference in your application. To know more about our company, please visit our website https://careers.hactl.com/.\n\nApplicants not invited for interview within four weeks should consider their applications unsuccessful. Applicants\u2019 personal data collected will only be used for the sole purpose of recruitment. The data of unsuccessful applicants will be destroyed within six months.", "employment_types": ["Full Time", "Permanent"], "selling_points": ["Enterprise level JAVA application design&develop't", "Guarantee 13th month pay & discretionary bonus", "Free shuttle bus and traffic allowance"], "locations": ["Airport Area"], "categories": ["Information Technology (IT)", "Application Specialist - Software", "Software Development", "Technical Writing"], "post_time": "2022-01-14T07:21:51Z", "salary": {"currency": null, "max": null, "min": null, "period": "monthly", "term": null}, "salary_visible": false, "title_keywords": ["senior it analyst"], "responsibilities": ["maintenance", "analysis", "systems", "design", "testing", "application development"], "requirements": {"degrees": ["high diploma", "degree", "bachelor"], "majors": ["related disciplines", "computer engineering", "computer science", "information technology"], "languages": ["chinese"], "language_level": [], "hard_skills": ["java", "git", "devops", "sql", "problem solving", "dynamic", "spring", "oracle"], "soft_skills": ["flexible", "communication skills", "work independently", "dynamic environment", "good team player", "problem solving", "hands-on", "comprehensive", "self-initiative"], "languages_combined": [{"language": "chinese", "language_level": []}]}, "experience_required": {"duration": ["minimum 4 years", "at least 2 years"], "field": ["development", "application development", "it"]}}, {"job_id": "100003009046858", "location_code": "hk", "company": "Cloud Light Technology Limited", "job_title": "Test Engineer - Firmware Validation and Software Development (Job Ref. No. Apply-HK-2109-TE)", "description": "Job Highlights\n\nOptical product engineer (R&D)\nModule firmware validation and Windows programming\nWorking Location in Hong Kong Science Park\n\nJob Role and Responsibilities\n\nThe successful candidates will join Hong Kong-based optical product R&D team and be involved in the development of high-speed fiber-optic transceiver products for data center applications.\n\nQualify each release of module firmware\nExecute the test cases manually/automatically based on the test plan and firmware release schedule\nMaintain a suite of regression test to ensure module firmware functionality for each release\nDevelop automation test infrastructure\nCreating and updating test cases for new features and products\nDevelop GUI for product evaluation and demonstration\nDevelop clear and concise test reports\nOccasional traveling is required\n\nRequirement:\n\nBachelor\u2019s degree or above in Computer-Science / Computer-Engineering / Electronic-Engineering discipline with 1+ year of related working experience\nCandidate with more experience will be considered as senior engineer\nExperience in GUI development using VB/C++/C/Python/LabVIEW or similar\nExperience in GUI design using Qt system is an advantage\nExperience with digital interfaces such as SPI/UART/I2C/MDIO is a plus\nKnowledge in embedded MCU programming is a plus\nFamiliarity with lab equipment such as oscilloscopes, multimeters, spectrum analyzers, signal generators, etc.\nKnowledge of optical transceiver, switch and electronic circuitry are preferred\nAbility to work independently and have good problem-solving skills\nAbility to summarize and communicate data and progress in a clear, understandable fashion\nA team player with great inter-personal skills and strong sense of ownership\nGood command of English and Chinese\nApplication:\n\nTo apply, please email\u00a0us your resume, your availability to report duty and quote the Job Ref.\nOnly short-listed candidates will be notified. Personal data provided by applicants will be used for consideration of an application only.\n\nApplication Deadline:\n\nUntil this position is filled.\nResumes received will strictly be used for recruitment-related purpose.", "employment_types": ["Full Time", "Permanent"], "selling_points": ["Module firmware validation and Windows programming", "Develop automation test infrastructure", "Computer-Science / Electronic-Engineering"], "locations": ["Shatin Area"], "categories": ["Engineering", "Electrical / Electronics", "Others", "Information Technology (IT)", "Technical Writing"], "post_time": "2022-01-14T01:29:29Z", "salary": {"currency": null, "max": null, "min": null, "period": "monthly", "term": null}, "salary_visible": false, "title_keywords": ["engineer"], "responsibilities": ["data", "infrastructure", "develop", "maintain", "reports", "schedule", "plan", "evaluation"], "requirements": {"degrees": ["degree or above", "bachelor"], "majors": ["science", "engineering"], "languages": ["english", "chinese"], "language_level": ["good command"], "hard_skills": ["plus", "c++", "switch", "c", "programming", "python", "problem-solving skills", "labview", "signal"], "soft_skills": ["work independently", "inter-personal skills", "clear", "problem-solving skills", "team player"], "languages_combined": [{"language": "english", "language_level": ["good command"]}, {"language": "chinese", "language_level": ["good command"]}]}, "experience_required": {"duration": ["1+ year"], "field": ["engineering", "related", "senior engineer", "development", "design", "digital"]}}, {"job_id": "100003009045491", "location_code": "hk", "company": "HKT Consumer Group", "job_title": "Software Engineer, DrGo & eSmartHealth", "description": "Your Role\n\nResponsible for mobile applications design, development, testing, implementation, enhancement and maintenance\nWork closely with clients and internal teams on project requirement and UX/UI design\nPrepare documentations including user requirements, functional specifications, test plans and user manuals\nWork with device vendors and external business partners to develop new products and enhance our product competitiveness\nProvide user support and on-site troubleshooting for our integrated solutions\n\nTo Succeed in this Role\n\nDegree holder in Computer Science, Information Technology, or related disciplines\nAt least 3 years solid experience in native iOS/Android development, or cross-platform solutions like React Native or Flutter\nExperience in graphic/artwork design and web programming is an advantage\nKnowledge of e-Health products/platforms and their integration via BLE/API is definitely an advantage\nUnderstanding of common data structures, cryptography, threading, RESTful APIs, etc\nCreative, self-motivated, and able to work independently and under tight schedule\nA good team player with excellent presentation and interpersonal skills\nGood command of written and spoken Chinese and English, Mandarin is an advantage", "employment_types": ["Full Time"], "selling_points": [], "locations": ["Quarry Bay"], "categories": ["Information Technology (IT)", "Application Specialist - Software", "Technical Writing", "Mobile / Wireless Communications"], "post_time": "2022-01-13T07:56:51Z", "salary": {"currency": null, "max": null, "min": null, "period": "monthly", "term": null}, "salary_visible": false, "title_keywords": ["software engineer"], "responsibilities": ["maintenance", "data", "teams", "implementation", "design", "testing", "develop", "troubleshooting", "specifications", "schedule", "plans", "ui"], "requirements": {"degrees": ["degree holder"], "majors": ["related disciplines", "computer science", "information technology"], "languages": ["english", "chinese", "mandarin"], "language_level": ["advantage", "good command"], "hard_skills": ["android development", "maintenance", "web", "mobile", "react native", "programming", "integration", "documentations"], "soft_skills": ["self-motivated", "work independently", "good team player", "responsible", "troubleshooting", "interpersonal skills", "creative", "presentation"], "languages_combined": [{"language": "english", "language_level": ["advantage", "good command"]}, {"language": "chinese", "language_level": ["advantage", "good command"]}, {"language": "mandarin", "language_level": ["advantage", "good command"]}]}, "experience_required": {"duration": ["at least 3 years"], "field": ["programming", "development", "graphic", "design"]}}, {"job_id": "100003009042037", "location_code": "hk", "company": "EC Healthcare", "job_title": "eCommerce Web Developer", "description": "Job Responsibilities:\n\nResponsible for development, implementation and testing of web application and responsive website with CMS backend;\nProvide support on user acceptance test and system maintenance;\nWork closely with UI/UX designer and eCommerce team to deliver the best experience on both web and mobile platforms; and\nTroubleshoot and resolve application production issues.\n\nRequirements:\n\nHigher Diploma / Associate Degree or above in Computer Science, Information Technology, or any related disciplines;\n2+ years\u2019 experience in web application development;\nStrong & hands-on development skills in WordPress, WooCommerce, PHP, CSS, JavaScript, MySQL, and responsive web;\nFamiliar with SEO, Google Analytics, Git, Bootstrap, Angular, Drupal, and Wix would be an advantage;\nGood analytical and problem-solving skills;\nAggressive, self-motivated, result-orientated, and able to work under pressure;\nExcellent interpersonal and communication skills; and\nGood command of Cantonese, English, and Mandarin.", "employment_types": ["Full Time", "Permanent"], "selling_points": ["Web Application Development", "WordPress, PHP", "Self-motivated, Result-orientated"], "locations": ["Mong Kok"], "categories": ["Information Technology (IT)", "Software Development", "Technical Writing", "E-commerce", "Software Development"], "post_time": "2022-01-12T05:33:08Z", "salary": {"currency": null, "max": null, "min": null, "period": "monthly", "term": null}, "salary_visible": false, "title_keywords": ["developer"], "responsibilities": ["provide support", "maintenance", "implementation", "website", "testing", "troubleshoot", "ui"], "requirements": {"degrees": ["diploma", "degree or above"], "majors": ["related disciplines", "computer science", "information technology"], "languages": ["cantonese", "english", "mandarin"], "language_level": ["good command"], "hard_skills": ["google analytics", "git", "web application development", "seo", "web", "php", "problem-solving skills", "wordpress", "javascript", "angular", "css"], "soft_skills": ["communication skills", "self-motivated", "hands-on", "problem-solving skills", "responsive", "interpersonal", "work under pressure"], "languages_combined": [{"language": "cantonese", "language_level": ["good command"]}, {"language": "english", "language_level": ["good command"]}, {"language": "mandarin", "language_level": ["good command"]}]}, "experience_required": {"duration": ["2+ years"], "field": ["application development"]}}, {"job_id": "100003009047405", "location_code": "hk", "company": "Tai Hing Catering Group Limited", "job_title": "IT Manager / Analyst Programmer \u2013 Application & System", "description": "Responsibilities:\n\nManage and monitor home-grown application / system aiming to maintain and enhance the company\u2019s effectiveness and efficiency;\nPerform application development, system testing, implementation, debugging and maintenance;\nConduct the review and establish operating support model in order to ensure a smooth transition to the application launch;\nLiaise with vendors and internal user for managing project schedule, work plan and expenditures;\nPrepare system documentation and online tutorials for user training;\nProvide technical support for ongoing operations and service enhancement;\nAssist in any ad-hoc duties as assigned\n\nRequirements:\n\nBachelor degree in Computer Science, Computer Engineering, Information System, Information technology or related disciplines;\n5-8 years of relevant working experience in IT application development, support and project management;\nKnowledge of web hosting and languages & web development frameworks, e.g. JavaScript, HTML, CSS, JQuery, JSON, Laravel, PHP, MVC;\nKnowledge in crystal report and database management system (MS-SQL, MySQL);\nSound knowledge in Node.js / React / Composer / NoSQL / PWA;\nKnowledge in Linux (Red Hat) will be an advantage;\nFamiliar with Bitbucket / Github, JIRA is a plus;\nStrong leadership, analytical and organizational skills\nImmediate available is highly preferred;\n\nWorking Location - Fotan\n\nWe offer\u00a0competitive\u00a0package and benefits:\n\n\u00a0\u00a0\u00a0\u00a0\u00a0\u00a0\u00a0\u00a0 Five-Day work week\n\u00a0\u00a0\u00a0\u00a0\u00a0\u00a0\u00a0\u00a0 3 Days Marriage Leave\n\u00a0\u00a0\u00a0\u00a0\u00a0\u00a0\u00a0\u00a0 5 Days Full Pay Paternity Leave\n\u00a0\u00a0\u00a0\u00a0\u00a0\u00a0\u00a0\u00a0 Family-Friendly Leave\n\u00a0\u00a0\u00a0\u00a0\u00a0\u00a0\u00a0\u00a0 Birthday Leave\n\u00a0\u00a0\u00a0\u00a0\u00a0\u00a0\u00a0\u00a0 Free Duty Meal\n\u00a0\u00a0\u00a0\u00a0\u00a0\u00a0\u00a0\u00a0 Staff Discount\n\u00a0\u00a0\u00a0\u00a0\u00a0\u00a0\u00a0\u00a0 Medical Benefits\n\u00a0 \u00a0 \u00a0 \u00a0 \u00a0Life Insurance Plan\n\u00a0\u00a0\u00a0\u00a0\u00a0\u00a0\u00a0\u00a0 Promotion Opportunities\n\nFor more company information, please visit our web site at\u00a0www.taihing.com\nInterested parties please send\u00a0full resume with expected salary\u00a0and availability\u00a0to the\u00a0Human Resources Department via email.\n\nAll information received will be kept in strict confidence and only used for employment-related purposes. Applicants who are not invited for interview within 6 weeks may consider their applications unsuccessful.", "employment_types": ["Full Time", "Permanent"], "selling_points": [], "locations": ["Shatin Area"], "categories": ["Information Technology (IT)", "IT Project Management / Team Lead", "Software Development", "Technical Writing"], "post_time": "2022-01-14T03:01:20Z", "salary": {"currency": null, "max": null, "min": null, "period": "monthly", "term": null}, "salary_visible": false, "title_keywords": ["analyst programmer", "it manager"], "responsibilities": ["system documentation", "maintenance", "technical support", "operations", "review", "monitor", "implementation", "testing", "maintain", "schedule", "plan", "ad-hoc duties", "liaise with", "application development"], "requirements": {"degrees": ["degree", "bachelor"], "majors": ["related disciplines", "computer engineering", "computer science", "information technology"], "languages": [], "language_level": [], "hard_skills": ["linux", "web development", "red hat", "plus", "php", "react", "jquery", "web hosting", "information system", "html", "project management", "javascript", "ms-sql", "css"], "soft_skills": ["project management", "leadership", "organizational skills"], "languages_combined": []}, "experience_required": {"duration": ["5-8 years"], "field": ["project management", "application development", "it", "relevant working experience"]}}, {"job_id": "100003009050568", "location_code": "hk", "company": "IT Solutions Ltd.", "job_title": "Phone Banking Projects: SA / AP / Senior Programmer - Major Bank", "description": "We are searching on behalf of a Major Bank\u00a0for a number of high-calibre System Analyst\u00a0/ Analyst Programmer / Senior Programmer to work on\u00a0Call Centre Systems enhancement projects.\n\nResponsibilities:\n\nSystem design and implementation in Call Centre Systems enhancement projects.\nWork through the software development lifecycle.\nAssist in project implementation.\nProvide solutions based on user requirements.\nLiaise with development team and external vendors.\nSystem rollout and support.\n\nRequirements:\n\nDegree in Computer Science or related discipline\n3 years+ experience in IT software / application development.\n\nExperience in Call Centre systems / Interactive Voice Response System (IVRS).\nExperience in Java, web programming are preferable but not mandatory.\nWith or without banking experience.\n\nBenefits:\n\nAttractive remunerations will be offered to the successful candidates.\nExcellent opportunity to further develop your professional skills on Phone Banking Systems Projects in a Major Bank.\n\n\n\nIf you are interested, please send your resume in MS Word format, specifying your availability, current and expected salaries to:\n\njobs @itsolutions.com.hk\n\nor\n\nPlease click the Apply Now button and attach your cv in MS Word Format, specifying your availability, current and expected salaries.\n\n\nPersonal data collected will be used for recruitment purposes only.\n\n\nIT Solutions Ltd.\nSuite 2102, 21st Floor\nLucky Building\n39 Wellington Street\nCentral, Hong Kong\n\n(P.S.\u00a0 We do not process applications from overseas for this position)", "employment_types": ["Full Time"], "selling_points": ["Experience in Call Centre Systems / IVRS System", "3 years+ of relevant IT experience", "Gain enterprise scale banking system experience"], "locations": ["Not Specified"], "categories": ["Information Technology (IT)", "Application Specialist - Software", "Software Development", "Technical Writing"], "post_time": "2022-01-15T05:20:25Z", "salary": {"currency": null, "max": null, "min": null, "period": "monthly", "term": null}, "salary_visible": false, "title_keywords": ["senior programmer"], "responsibilities": ["software", "systems", "implementation", "system design", "enhancement projects"], "requirements": {"degrees": ["degree"], "majors": ["computer science"], "languages": [], "language_level": [], "hard_skills": ["programming", "java", "web"], "soft_skills": [], "languages_combined": []}, "experience_required": {"duration": [], "field": ["application development", "it", "programming", "banking experience"]}}, {"job_id": "100003009043955", "location_code": "hk", "company": "Evergreen System Limited", "job_title": "Analyst Programmer", "description": "Job Highlights\n- 5-day Work Week, Flexible Working Hour\n- Medical allowance\n- Casual Dress Code\n- Competitive Pay\n- Performance Bonus\n\nResponsibilities:\n1. Perform technical microservice architecture design, development, unit testing and development integration testing to deliver high performance, flexible and reliable software systems\n2. Responsible for applications development and maintenance\n3. Working on design and development of the infrastructure\n4. Ensure code quality and operational efficiency, and have the ability to adjust and optimize project code.\n5. Willing to learn, hardworking, committed and proactive\n\nRequirements:\n- 2-3 years experience in software development\n- Higher diploma/certificate or above in Computer Science or other related disciplines\n- Familiar with java/golang development experience is preferred\n- Knowledge in SQL(MySQL), NoSQL(MongoDB, Redis)\n- Familiar with Git and/or GitHub\n- Experience in Docker / Kubernetes and CI/CD will be a plus\n- Good Logical-thinking, Research-spirit, Passion on technology\n- Fluent in English, good written and verbal communication skills\n\nBonus experience:\n- Flutter / Dart\n- Docker\n- Linux\n- Node.js\n\nLess relevant experienced candidates / Fresh graduate are welcome to apply.", "employment_types": ["Full Time"], "selling_points": ["Year and Performance Bonus", "5 working day per week", "Fresh graduate are welcome."], "locations": ["Hung Hom"], "categories": ["Information Technology (IT)", "Application Specialist - Software", "IT - Webmaster / SEO", "Technical Writing"], "post_time": "2022-01-13T02:35:25Z", "salary": {"currency": null, "max": null, "min": null, "period": "monthly", "term": null}, "salary_visible": false, "title_keywords": ["analyst programmer"], "responsibilities": ["software", "maintenance", "systems", "infrastructure", "quality", "design", "testing", "architecture"], "requirements": {"degrees": ["certificate", "diploma", "fresh graduate"], "majors": ["related disciplines", "computer science"], "languages": ["english"], "language_level": ["good", "fluent"], "hard_skills": ["linux", "java", "git", "plus", "dart"], "soft_skills": ["communication skills"], "languages_combined": [{"language": "english", "language_level": ["fluent", "good"]}]}, "experience_required": {"duration": ["2-3 years"], "field": ["development", "software development"]}}, {"job_id": "100003009048816", "location_code": "hk", "company": "Hong Kong Air Cargo Terminals Ltd", "job_title": "Linux System Engineer (Senior IT Analyst)", "description": "Duties\n\nPerform development, testing, installation and implementation of systems in virtualized Linux Platform (on premises & Cloud)\nParticipate in the feasibility study and proof-of-concept evaluation of new IT Infrastructure Technology & Solutions\nPrepare documentation system and operational support\nTake part in 7 x 24 on-call rotation for supporting on mission critical systems\nQualifications\n\nDegree or above in Computer Science or related discipline\n3 -5 years\u2019 solid experience in Linux administration, implementation and production support\nExperience in Linux (Oracle, Redhat, Ubuntu & CentOS), Virtualization technologies (Oracle & RedHat), Monitoring / Operational intelligence products (Nagios, Splunk or ELK) and Backup products (Veritas / NetBackup & Commvault)\nExperience with programming and/or scripting, task automation(e.g. Ansible), and best security practices for server installation and administration\nGood analytical and problems solving skills with strong self-motivation and ability to work under pressure\nCandidates with less experience will also be considered\n\nWe offer 5-Day work week with a competitive and comprehensive remuneration package including Chinese New Year bonus, discretionary bonus, transport subsidy, employer topped-up MPF contributions, medical benefits (including family members), voluntary dental coverage (including family members), life insurance, birthday leave, extra annual leave, marriage leave, maternity leave, paternity leave, newborn baby gift, sports centre and free shuttle bus.\nInterested parties please apply with full resume detailing experience, qualifications and expected salary by post, by e-mail or click \"Apply Now\".\nBy post: Human Resources, 6/F, North Office Block, SuperTerminal 1, Hong Kong International Airport, HK\nPlease quote the above reference in your application. To know more about our company, please visit our website https://careers.hactl.com/.\nApplicants not invited for interview within four weeks should consider their applications unsuccessful. Applicants\u2019 personal data collected will only be used for the sole purpose of recruitment. The data of unsuccessful applicants will be destroyed within six months.", "employment_types": ["Full Time", "Permanent"], "selling_points": ["Excellent career opportunity with attractive pay", "Guarantee 13th month pay & discretionary bonus", "Free Shuttle and Transport Subsidy"], "locations": ["Airport Area"], "categories": ["Information Technology (IT)", "Network & System", "Technical / Functional Consulting", "Technical Writing"], "post_time": "2022-01-14T07:21:51Z", "salary": {"currency": null, "max": null, "min": null, "period": "monthly", "term": null}, "salary_visible": false, "title_keywords": ["system engineer", "senior it analyst"], "responsibilities": ["installation", "problems solving", "operational support", "it infrastructure", "mpf", "work under pressure", "systems", "monitoring", "implementation", "testing", "evaluation", "documentation", "insurance", "administration"], "requirements": {"degrees": ["degree or above"], "majors": ["computer science"], "languages": ["chinese"], "language_level": [], "hard_skills": ["linux", "server", "centos", "ansible", "programming", "documentation", "oracle"], "soft_skills": ["comprehensive", "self-motivation", "work under pressure"], "languages_combined": [{"language": "chinese", "language_level": []}]}, "experience_required": {"duration": ["3 -5 years"], "field": ["programming", "administration"]}}, {"job_id": "100003009043425", "location_code": "hk", "company": "Cornerstone Global Partners", "job_title": "Python Developer - International Ecommerce Company (High Pay)", "description": "\nJob Summaries:\n1. We are looking for a Python Developer to help us develop and maintain commission and various software systems that align with our business needs.\n2. Writing and testing code, debugging programs, and integrating applications with third\u0002party web services.\n3.\u00a0Troubleshoot and perform fixing / data patching for operation issues\n\nResponsibilities:\u00a0\n\u2022 Write effective, scalable code\n\u2022 Develop back-end components to improve responsiveness and overall performance\n\u2022 Integrate user-facing elements into applications\n\u2022 Test and debug programs\n\u2022 Troubleshoot and perform fixing / data patching for operation issues\n\u2022 Improve functionality of existing systems\n\u2022 Implement security and data protection solutions\n\u2022 Assess and prioritize feature requests\n\u2022 Coordinate with internal teams to understand user requirements and provide technical solutions\n\nQualifications:\u00a0\n\u2022 BSc in Computer Science, Engineering, Statistics, or relevant field\n\u2022 2+ years relevant commercial development experience\n\u2022 Expertise in\u00a0Python, T-SQL, and Azure DataBricks\n\u2022 Good problem-solving skills\n\u2022 Experience on Azure storage / Azure SQL / Redis / Data factory / Synapse\n\u2022 Reporting relevant skill", "employment_types": ["Full Time", "Contract"], "selling_points": ["International E-commerce exposure", "Competitive Salary Package", "International Working Culture"], "locations": ["Kwun Tong"], "categories": ["Information Technology (IT)", "Application Specialist - Software", "Technical / Functional Consulting", "Technical Writing"], "post_time": "2022-01-12T11:39:40Z", "salary": {"currency": null, "max": null, "min": null, "period": "monthly", "term": null}, "salary_visible": false, "title_keywords": ["developer"], "responsibilities": ["reporting", "software", "data", "systems", "coordinate with", "teams", "testing", "develop", "maintain", "troubleshoot"], "requirements": {"degrees": ["bsc"], "majors": ["statistics", "engineering", "computer science"], "languages": [], "language_level": [], "hard_skills": ["azure", "problem-solving skills", "t-sql", "sql", "python", "code", "web services"], "soft_skills": ["problem-solving skills", "troubleshoot", "prioritize"], "languages_combined": []}, "experience_required": {"duration": ["2+ years"], "field": ["sql", "commercial", "development"]}}, {"job_id": "100003009041924", "location_code": "hk", "company": "iCON Business Systems Ltd", "job_title": "Programmer / Analyst Programmer / Software Engineer (Delphi, .Net C#)", "description": "Responsibilities:\n\nAssigned to complete programming tasks including coding, testing and documentation\nAssist in system design, collect user requirements and system design\nProvide user training, documentation and system support service\nWork according to management instructions and guidance\nCapable of providing high-quality, stable and professional programming services\nBe a matured and capable team member to accomplish software project\n\n\u00a0Requirements:\n\n2+ year solid experience of desktop or web application development\nCandidates with 4+ years solid development experiences will be considered at Analysis Programmer\nExperience in Delphi, C#, .NetCore and SQL would be an advantage\nExperience in software development using OOP, design patterns would be an advantage\nWilling to learn and aggressive - having ample opportunities to learn programming skill\nCan work independently and Be Self motivated\nSelf-learned programming skill will be an asset\nKnowledge / experience in database system development or ERP application is advantage\nBachelor Degree or Diploma in Computer Science, Information Technology or related disciplines\n\nWe offer comprehensive remuneration and benefits, and excellent career opportunities to the right candidates. Interested parties please state clearly the position you are applying to with reference no. if any in the subject line and email us a full resume with CURRENT & EXPECTED SALARY.\n\nAll applications will be treated in the strictest confidence. We regret that only shortlisted candidates will be notified. Personal data collected will be used for recruitment purpose only.", "employment_types": ["Full Time", "Permanent"], "selling_points": ["Desktop and Web development", "Knowledge in OOP / Design patterns / RDBMS", "5-day week; Bonus; Transportation allowance"], "locations": ["Cheung Sha Wan"], "categories": ["Information Technology (IT)", "Software Development", "Technical Writing"], "post_time": "2022-01-12T04:41:21Z", "salary": {"currency": "HKD", "max": 34999, "min": 20000, "period": "monthly", "term": null}, "salary_visible": true, "title_keywords": ["analyst programmer", "software engineer", "programmer"], "responsibilities": ["guidance", "management", "software", "quality", "coding", "testing", "system design", "documentation"], "requirements": {"degrees": ["diploma", "degree", "bachelor"], "majors": ["related disciplines", "computer science", "information technology"], "languages": [], "language_level": [], "hard_skills": ["web application development", "analysis", "erp", "sql", "programming", "delphi", "c#"], "soft_skills": ["self motivated", "work independently", "willing to learn"], "languages_combined": []}, "experience_required": {"duration": ["4+ years", "2+ year"], "field": ["development", "design", "system development", "database", "software development", "application development"]}}, {"job_id": "100003009035332", "location_code": "hk", "company": "\u601d\u8b00\u96c6\u5718\u6709\u9650\u516c\u53f8", "job_title": "Technical Writer", "description": "Responsibilities1. Participate in brainstorming sessions with management, business teams and R&D teams to develop creative ideas for technical and business document development that aligns with overall strategy and business needs\n2. Work closely with internal teams to collect the latest company technology trends, solutions, and product roadmap and understand complex concepts regarding products, projects, and documentation requirements to communicate the information in a way that is engaging and understood by end-users at various technical levels.\n3. Outline, write, edit, translate, and proofread new and existing product materials (i.e., brochures, leaflets, demos, introduction decks), technical/service manuals, work instructions, sales/business presentations, public materials such as press release, newsletters, reports, white papers etc. in sound English & Chinese\n4. Acting as an editor, produces high-quality, accurate documentation that meets applicable internal requirement, aligns terminology and style consistency, compiles with industry standards and countries regulations, and is appropriate for its intended audience and drives business opportunities.\n5. Get alignment and execute final changes on documentations to reduce correction loops before and after translations.\n6. Build and maintain content / translation library, templates, and instruction manuals for translation process for standardisation purposes.\n7. Work in ad-hoc project support and other duties as assigned.Requirements1. Bachelor\u2019s degree or above; major in Engineering, Technical Communication, Technical Translation, or an equivalent background / field of studies would be preferred.\n2. A minimum of 3 years' proven experience in technical documentation writing and translation, experience working in the manufacturing related industries is an advantage\n3. Strong interest and good knowledge of technologies, industry 4.0, smart manufacturing, digital transformation etc., and ability to explain and describe new technologies in a way that is concise and descriptive.\n4. Excellent writing skills in English and (simplified and traditional) Chinese, with strong background in editing and translation, and proven ability to communicate technical information in high professional standard and accuracy\n5. Responsible, self-motivated, and able to work in a fast-paced environment whilst under pressure to meet tight deadlines\n6. Detailed-oriented and with excellent organizational and project management skills\n7. Work independently on written assignments while be a dependable, strong team player with excellent interpersonal and communication skills\n8. Proficient in MS Word, Excel, PowerPoint", "employment_types": ["Full Time"], "selling_points": ["Technical Writer", "Outline, write, edit, translate", "instruction manuals for translation process"], "locations": ["Shatin Area"], "categories": ["Information Technology (IT)", "Technical Writing", "Others", "Professional Services", "Translation"], "post_time": "2022-01-10T06:51:01Z", "salary": {"currency": null, "max": null, "min": null, "period": "monthly", "term": null}, "salary_visible": false, "title_keywords": [], "responsibilities": ["regulations", "ad-hoc", "management", "other duties", "leaflets", "business opportunities", "teams", "quality", "presentations", "maintain", "reports", "documentation", "develop creative ideas"], "requirements": {"degrees": ["degree or above", "bachelor"], "majors": [], "languages": ["english", "chinese"], "language_level": ["excellent"], "hard_skills": ["excel", "writing skills", "powerpoint", "project management", "documentation", "translation", "ms word"], "soft_skills": ["communication skills", "self-motivated", "meet tight deadlines", "under pressure", "work independently", "responsible", "fast-paced environment", "organizational", "project management skills", "writing skills", "communication", "team player", "interpersonal", "detailed"], "languages_combined": [{"language": "english", "language_level": ["excellent"]}, {"language": "chinese", "language_level": ["excellent"]}]}, "experience_required": {"duration": ["minimum of 3 years"], "field": ["related", "manufacturing", "writing"]}}, {"job_id": "100003009043715", "location_code": "hk", "company": "Esri China (Hong Kong) Ltd", "job_title": "Analyst Programmer", "description": "Job Descriptions:\n\nDefine, document and translate business requirements into system specification;\nPerform analysis, design, programming and testing following system development life cycle (SDLC) methodology and adhering to corporate-wise technology standards;\nAdhere to the development processes including coding standards, technical; documentation standards, QA processes, configuration management;\nWork closely in team-environment and meet project schedules; and\nKeep good communication and coordination with team members.\n\nRequirements:\n\nDegree in Computer Science, Information Technology or related disciplines;\nKnowledge in Microsoft .NET Framework (C#) or JavaScript in Web programming;\nAt least 2 years relevant IT working experience;\nFluent in applying SQL statements for data manipulations;\nGood command of written and spoken in Chinese and English; and\nImmediately available is highly preferable.\n\nWe offer five-day work week, attractive career opportunities, remuneration and benefits to the right candidates. Interested applicants, please submit detailed resume with current & expected salary and date of availability to Human Resources Department by clicking the below\u00a0Apply Now.\u00a0\n\n(For more information about our Company, please visit our website www.esrichina.hk)\n(Application received will be treated in strict confidence and will be used exclusively\u00a0for recruitment-related purposes.)", "employment_types": ["Full Time", "Permanent"], "selling_points": [], "locations": ["Lai Chi Kok"], "categories": ["Information Technology (IT)", "Support", "Network & System", "Technical Writing"], "post_time": "2022-01-13T01:38:15Z", "salary": {"currency": null, "max": null, "min": null, "period": "monthly", "term": null}, "salary_visible": false, "title_keywords": ["analyst programmer"], "responsibilities": ["management", "configuration", "schedules", "analysis", "coordination with", "coding", "design", "testing", "communication", "documentation"], "requirements": {"degrees": ["degree"], "majors": ["related disciplines", "computer science", "information technology"], "languages": ["english", "chinese"], "language_level": ["good command"], "hard_skills": ["web", "sql", "javascript", "programming", "c#"], "soft_skills": [], "languages_combined": [{"language": "english", "language_level": ["good command"]}, {"language": "chinese", "language_level": ["good command"]}]}, "experience_required": {"duration": ["at least 2 years"], "field": ["it"]}}, {"job_id": "100003009039739", "location_code": "hk", "company": "BBPOS Limited", "job_title": "Cyber Security Manager", "description": "Responsibilities:\n\nLead cyber security team working closing with regional teams\nManage security operations in hybrid cloud environment\nDevelop and manage cyber security architecture design, framework, roadmap and policy\nResponsible for Security Risk Assessment and Vulnerability Management\nResponsible for 3rd party security management\nEvaluate and implement new security controls\nParticipate in various information security related audits/assessments\nProvide regular security awareness training to all staffs\nProvide security advice to software and infrastructure teams\n\nRequirements:\n\nDegree or above in Computer Science or related discipline\nA CISM, CISSP, GIAC, CEH or equivalent certification will be advantageous\n10 years+ experience in information security related area\nSolid experience in security risk management\nSolid experience in AWS and Azure\nExperience in designing, executing and supporting cyber security framework and policy development, preferably with exposure in the areas of network security, application security, endpoint security, data security, identity management, database and infrastructure security, container security or cloud security\nGood working knowledge of Windows, Linux, OSX and mobile operating systems\nExperience in cloud security will be advantageous\nFamiliar with ISO9001, ISO27001 and PCI related compliance will be advantageous\nFluent in both spoken and written English and Cantonese\nSelf-motivated, excited to learn\nLess experience candidate will be considered as Cyber Security Specialist\n\nWe offer career prospect, attractive remuneration, and benefits to the right candidate. To discuss this opportunity further, please send your full resume, present and expected salary to the\u00a0HR Department email\u00a0or\u00a0direct email to recruit @bbpos.com\n\nAll information provided will be treated in strict confidence and used for recruitment purposes only.", "employment_types": ["Full Time", "Permanent"], "selling_points": ["Rapidly growing Fintech company", "Max 18 days AL, Flexible hr, Performance bonus", "5 days work in HK"], "locations": ["Tsuen Wan Area"], "categories": ["Information Technology (IT)", "Security", "Network & System", "Technical Writing"], "post_time": "2022-01-11T10:48:12Z", "salary": {"currency": null, "max": null, "min": null, "period": "monthly", "term": null}, "salary_visible": false, "title_keywords": ["manager"], "responsibilities": ["management", "software", "information security", "cyber security", "operations", "infrastructure", "teams", "design", "develop", "evaluate", "audits", "vulnerability management", "architecture"], "requirements": {"degrees": ["degree or above"], "majors": ["computer science"], "languages": ["cantonese", "english"], "language_level": ["fluent"], "hard_skills": ["linux", "azure", "cyber security", "aws", "mobile", "container"], "soft_skills": ["self-motivated"], "languages_combined": [{"language": "cantonese", "language_level": ["fluent"]}, {"language": "english", "language_level": ["fluent"]}]}, "experience_required": {"duration": [], "field": ["risk management", "management", "related", "development", "infrastructure", "security", "database"]}}, {"job_id": "100003009046332", "location_code": "hk", "company": "IT Solutions Ltd.", "job_title": "Corporate Banking - Custody Services System: Java SA / AP / P", "description": "We are searching on behalf of a Major Bank\u00a0for a number of high-calibre J2EE Senior Systems Analysts & Systems Analysts & Analyst Programmers to work on\u00a0Corporate Banking Custody Services Systems projects.\n\nResponsibilities:\n\nCustody Services Systems\u00a0development and enhancement.\nWork through the whole software development lifecycle.\nSystem analysis and system design.\nDevelop and test applications using Java,\u00a0J2EE architecture, JSP, EJB, JavaScript, HTML, Web Services, Oracle, etc\nPrepare system documentation.\nSystem rollout and support\nLiaise with internal IT staff or external vendors\nSupport UAT.\n\nRequirements:\n\nDegree in Computer Science or related discipline\nExperience in software development using Java, .Net, Python or other programming languages.\n\nWith or without banking experience\nKnowledge of Aglie Development Process is an advantage but not mandatory.\nAnalytical and able to work under pressure\nFresh graduate with either hands-on Java programming experience OR formal education in Java are also welcome to apply\n\n\nBenefits:\n\nAttractive remunerations will be offered to the successful candidates.\nExcellent opportunity to further develop your professional skills on Corporate Banking Systems Projects in a Major Bank.\n\n\n\nIf you are interested, please send your resume in MS Word format, specifying your availability, current and expected salaries to:\n\njobs @itsolutions.com.hk\n\nor\n\nPlease click the Apply Now button and attach your cv in MS Word Format, specifying your availability, current and expected salaries.\n\n\nPersonal data collected will be used for recruitment purposes only.\n\n\nIT Solutions Ltd.\nSuite 2102, 21st Floor\nLucky Building\n39 Wellington Street\nCentral, Hong Kong\n\n(P.S.\u00a0 We do not process applications from overseas for this position)", "employment_types": ["Full Time"], "selling_points": ["Strong Knowledge in Java / J2EE", "Gain enterprise scale banking system experience", "Fresh Grad are welcome to apply"], "locations": ["Not Specified"], "categories": ["Information Technology (IT)", "Application Specialist - Software", "Software Development", "Technical Writing"], "post_time": "2022-01-13T10:31:58Z", "salary": {"currency": null, "max": null, "min": null, "period": "monthly", "term": null}, "salary_visible": false, "title_keywords": [], "responsibilities": ["software", "system documentation", "uat", "analysis", "systems", "develop", "system design", "liaise with", "architecture"], "requirements": {"degrees": ["degree", "fresh graduate"], "majors": ["computer science"], "languages": [], "language_level": [], "hard_skills": ["python", "java", "programming"], "soft_skills": ["hands-on", "work under pressure"], "languages_combined": []}, "experience_required": {"duration": [], "field": ["programming", "education", "banking experience", "software development"]}}, {"job_id": "100003009041683", "location_code": "hk", "company": "Pathos Consultancy Limited", "job_title": "Senior Analyst Programmer (C#.NET) \u2013 1 Year Contract Renewable", "description": "The Company\nOur client is a financial services firm growing within the market at a rapid speed. They promote work-life balance as one of their core values. Currently their IT department is expanding and looking for .NET programmers to join the team.\u00a0\n\nThe Role\n\n\nDevelop application code and modules for business and technical requirements.\nTune up design for maintainability, scalability, and efficiency.\nDevelop and implement programs, designs, and codes.\nResolve and troubleshoot problems and complex issues.\nPerform unit tests and fix bugs.\nIntegrate best qualitative practices in design and development aspects of programs.\u00a0\n\nYour Profile\n\n\nHigher Diploma in Computer Science or equivalent is preferred\nSolid experience on programming in .NET framework. e.g. C# and ASP.Net etc.\nGood command of both written and spoken Cantonese and English\nLess experienced ones will be considered as Analyst Programmer\u00a0\n\nApply Today\nTo apply online (Word attachment only), please click the 'Apply' button. Interested parties please apply with the most updated CV with expected salary and available date via JobsDB. Applicants who do not hear from us within 2 weeks may consider their applications unsuccessful.\u00a0\n\nAbout Pathos\nWe are Pathos Consultancy Limited, a boutique recruitment firm based in Hong Kong strategically placing our candidates across all levels in permanent, temporary and contract roles.\u00a0 We specialize in IT and finance roles for banking, financial services and listed MNC sectors.", "employment_types": ["Full Time", "Contract"], "selling_points": ["C#.NET and ASP.NET", "Solid career path and job exposures", "Stable working environment"], "locations": ["Central"], "categories": ["Information Technology (IT)", "Application Specialist - Software", "Software Development", "Technical Writing"], "post_time": "2022-01-12T04:12:46Z", "salary": {"currency": null, "max": null, "min": null, "period": "monthly", "term": null}, "salary_visible": false, "title_keywords": ["senior analyst programmer"], "responsibilities": ["troubleshoot", "design", "develop"], "requirements": {"degrees": ["diploma"], "majors": ["computer science"], "languages": ["cantonese", "english"], "language_level": ["good command"], "hard_skills": ["c#", "word", "programming", "rapid", "code", "codes"], "soft_skills": ["troubleshoot"], "languages_combined": [{"language": "cantonese", "language_level": ["good command"]}, {"language": "english", "language_level": ["good command"]}]}, "experience_required": {"duration": [], "field": ["programming"]}}, {"job_id": "100003009038311", "location_code": "hk", "company": "Nautilus Technology Limited", "job_title": "Front-end Web Developer \u524d\u7aef\u958b\u767c\u5de5\u7a0b\u5e2b", "description": "Job Responsibilities:\n\n1. Be responsible for acquiring user requirement, development to testing, maintenance, enhancements and system support of websites and front-end applications\n\n2. Optimize front-end for maximum speed and scalability\n\n3. Work closely with internal teams, such as back-end and infrastructure, on the assigned projects and conduct project implementation\n\n4. Provide support during system assurance and user acceptance tests\n\n5. Support ad-hoc tasks and requests by the management\n\n\n\nRequirements:\n\n1. Bachelor\u2019s Degree in Computer Science or relevant field\n\n2. At least 1 year of front-end project experience, able to independently undertake front-end development work\n\n3. Professional experience with Vue or React\n\n4. A solid understanding in core web and browser concepts (eg. how the browser parses and constructs a web page) - A solid understanding of semantic HTML, CSS, and core JavaScript concepts.\n\n5. Demonstrated capacity to clearly and concisely communicate about complex technical, architectural, and/or organizational problems and propose thorough iterative solutions\n\n6. Experience using Git in a professional/workplace environment\n\n7. Strong command of both written and spoken English and Chinese (Especially in Mandarin)", "employment_types": ["Full Time", "Permanent"], "selling_points": [], "locations": ["Tsim Sha Tsui"], "categories": ["Information Technology (IT)", "IT - Webmaster / SEO", "Network & System", "Technical Writing"], "post_time": "2022-01-11T06:35:07Z", "salary": {"currency": null, "max": null, "min": null, "period": "monthly", "term": null}, "salary_visible": false, "title_keywords": ["developer"], "responsibilities": ["user requirement", "provide support", "management", "maintenance", "ad-hoc tasks", "infrastructure", "teams", "implementation", "testing"], "requirements": {"degrees": ["degree", "bachelor"], "majors": ["computer science"], "languages": ["english", "chinese", "mandarin"], "language_level": [], "hard_skills": ["git", "web", "react", "html", "javascript", "css"], "soft_skills": ["organizational", "independently", "thorough"], "languages_combined": [{"language": "english", "language_level": []}, {"language": "chinese", "language_level": []}, {"language": "mandarin", "language_level": []}]}, "experience_required": {"duration": ["at least 1 year"], "field": ["development"]}}, {"job_id": "100003009038183", "location_code": "hk", "company": "Anywhere Everywhere Six Degrees Link Limited", "job_title": "IT Business Analyst ( Global IT Company )", "description": "Role & Responsibilities\n\nClosely work with the internal team, design and deliver a customized and comprehensive service for client's business\nCarry out system implementation work including installation, configuration and UAT\nProvide coaching and training to the end-users\nPrepare project documents including business requirements\nPrepare test cases and perform product testing before product release\nSoftware / System Configuration\nFollow-up with the clients, provide enhancement and upgrade advice to the clients from time to time\nRequirements\n\nDegree Holder (Business Administration / Computer Science / Information Technology) holder or above 2-3 years working experience in System implementation (requirement analysis, solutions design, testing, training)\nKnowledge in Trading System / HRMS / CRM is definitely a plus\nSelf-motivated person with good analytical and problem-solving skills\nGood command of both spoken and written English, Cantonese\nGood communication, interpersonal and presentation skills\nDetail-minded and able to handle multiple tasks\nBenefits\n\n14-Day ALs\nMedical\nMacBook Pro will be provided\nWork with International Team\u00a0\nYoung and Energetic Team\u00a0", "employment_types": ["Full Time"], "selling_points": ["Salary : 22K - 35K + Bonus ( 1 - 2 Months )", "Work in Young and Energetic Agile/Scrum Team", "Work Life Balance | 14 ALs | Bonus"], "locations": ["Wan Chai"], "categories": ["Information Technology (IT)", "Product Management / Business Analyst", "Technical Writing", "Others"], "post_time": "2022-01-11T05:56:43Z", "salary": {"currency": "HKD", "max": 34999, "min": 25000, "period": "monthly", "term": null}, "salary_visible": true, "title_keywords": ["business analyst"], "responsibilities": ["installation", "uat", "software", "configuration", "implementation", "design", "testing", "project documents"], "requirements": {"degrees": ["degree holder"], "majors": ["design", "business administration", "computer science", "information technology"], "languages": ["cantonese", "english"], "language_level": ["good command"], "hard_skills": ["system implementation", "problem-solving skills", "analysis", "plus"], "soft_skills": ["detail-minded", "self-motivated", "communication", "handle multiple tasks", "presentation skills", "problem-solving skills", "interpersonal"], "languages_combined": [{"language": "cantonese", "language_level": ["good command"]}, {"language": "english", "language_level": ["good command"]}]}, "experience_required": {"duration": ["2-3 years"], "field": ["business administration", "training", "design", "testing", "information technology"]}}, {"job_id": "100003009041130", "location_code": "hk", "company": "CL Technical Services Ltd.", "job_title": "Data Engineer / ETL Developer (BI, 5 Days Work, $25-30K)", "description": "Job details:\n\nWork closely with oversea partners and report to oversea team lead\nCollect user requirement, perform data engineering, system development, set up\nImplement software components from the specification and guidelines\nDevelop unit test cases, perform testing and record the results\nSupport UAT and system implementation\nPrepare system and operations documents\nAssist in developing data warehouse and AI\n\nRequirements:\n\nDegree holder in Computer Science / Data Science or equivalent\n3 years\u2019 experience with data including reporting, managing, and analysing\nHands on experience in Python / SAS and SQL\nGood communication and interpersonal skills\nProficient in both written and spoken English and Chinese\n\nFor more job opportunity, please visit our website: www.clts.com\n\nThe personal information is collected strictly for recruitment purpose only.", "employment_types": ["Full Time"], "selling_points": ["Several job vacancies", "Listed company", "Great learning opportunity"], "locations": ["Mong Kok"], "categories": ["Information Technology (IT)", "IT Management", "Technical Writing", "Data Scientist"], "post_time": "2022-01-12T03:29:12Z", "salary": {"currency": null, "max": null, "min": null, "period": "monthly", "term": null}, "salary_visible": false, "title_keywords": ["developer", "data engineer"], "responsibilities": ["user requirement", "software", "uat", "data", "guidelines", "operations", "implementation", "developing", "develop", "testing", "report"], "requirements": {"degrees": ["degree holder"], "majors": ["data science", "computer science"], "languages": ["english", "chinese"], "language_level": ["proficient"], "hard_skills": ["python", "sql", "sas"], "soft_skills": ["hands on", "communication and interpersonal skills"], "languages_combined": [{"language": "english", "language_level": ["proficient"]}, {"language": "chinese", "language_level": ["proficient"]}]}, "experience_required": {"duration": ["3 years"], "field": ["sql"]}}, {"job_id": "100003009037993", "location_code": "hk", "company": "China Construction Bank (Asia) Corporation Limited", "job_title": "OFC - Analyst Programmer (Investment Applications)", "description": "Main Responsibilities\n\n- Responsible for analysis, development, testing and technical specification delivery\n- Assist project manager/system analyst to co-ordinate and communicate with various stakeholders effectively in accordance with the project plan\n- Support system integration testing, user acceptance testing, system implementation as well as preparation of technical documentation\n- Co-ordinate with vendors and review vendor deliverables\n- Provide productions support and applications support\n\nRequirements\n\n- Degree holder in Information Technology, Computer Science or related disciplines\n- Minimum 3 years-experience application development, preferably gained from banking / finance industry\n- Fresh graduate with a degree in Computer Science or related disciplines will also be considered\n- Experience in following business background would be an advantage\nSecurities Trading, order placements systems, settlement system\nOR\nMutual funds, bonds, FX, derivatives, structured products\n- For candidates with working experiences, sound knowledge in ONE of the following technical areas:\n- VB.NET, ASP.NET, C#, Restful API/JASON, Java and Web Service\n- PL/SQL, T-SQL in Oracle and MSSQL database. (Crystal report is a plus)\n- Meticulous at work, excellent analytical and logical thinking skills\n- Good team player who is passionate in latest technology trend and eager to learn or develop new skills\n- Proactive, independent and able to work multi-tasking under pressure\n- Excellent communication in both spoken and written English and Chinese (including Mandarin)\n- Candidate with more experience will be considered as Senior Analyst Programmer\n- Business travel may be required", "employment_types": ["Full Time", "Permanent"], "selling_points": ["Analyst Programmer", "Investment Applications", "system integration testing"], "locations": ["Kowloon Bay"], "categories": ["Information Technology (IT)", "Testing / QA", "Technical Writing"], "post_time": "2022-01-11T04:30:25Z", "salary": {"currency": null, "max": null, "min": null, "period": "monthly", "term": null}, "salary_visible": false, "title_keywords": ["analyst programmer"], "responsibilities": ["communicate with", "co-ordinate with", "analysis", "review", "implementation", "project plan", "testing", "documentation"], "requirements": {"degrees": ["degree", "fresh graduate", "degree holder"], "majors": ["related disciplines", "computer science", "information technology"], "languages": ["english", "chinese", "mandarin"], "language_level": ["excellent"], "hard_skills": ["restful api", "java", "oracle", "plus", "web", "t-sql", "sql", "mssql", "pl", "c#"], "soft_skills": ["passionate", "meticulous", "good team player", "proactive", "independent", "under pressure", "communication", "eager to learn", "multi-tasking", "structured"], "languages_combined": [{"language": "english", "language_level": ["excellent"]}, {"language": "chinese", "language_level": ["excellent"]}, {"language": "mandarin", "language_level": ["excellent"]}]}, "experience_required": {"duration": ["minimum 3 years"], "field": ["application development", "business", "finance industry", "banking"]}}, {"job_id": "100003009037994", "location_code": "hk", "company": "China Construction Bank (Asia) Corporation Limited", "job_title": "OFC - Analyst Programmer (e-Channel)", "description": "Main Responsibilities\n\n- Responsible for analysis, development, testing and technical specification delivery\n- Co-ordinate and communicate with stakeholders effectively according to project plan\n- Support user acceptance testing and system implementation\n- Provide production support\n\nRequirements\n\n- Degree holder in Computer Science, Information Technology or related disciplines\n- Minimum 3 years experience on web/mobile application development, preferably in banking\n- Excellent in programming languages including JavaScript, Java, XML, HTML/CSS, webservice etc.\n- strong knowledge and hand-on experience of various mobile frameworks, e.g. React Native\n- Proficiency in JEE, Spring, Microservice\n- Good knowledge of DevOps & Agile development\n- Good analytical, inter-personal communication and problem-solving skills\n- Good team player who is passionate in latest technology trend and eager to learn or develop new skills\n- Proactive, independent and able to multi-tasking under pressure\n- Excellent language in both spoken and written English and Chinese (including Mandarin)\n- Business travel may be required", "employment_types": ["Full Time", "Permanent"], "selling_points": ["Analyst Programmer", "e-Channel", "user acceptance testing"], "locations": ["Kowloon Bay"], "categories": ["Information Technology (IT)", "Testing / QA", "Technical Writing"], "post_time": "2022-01-11T04:30:25Z", "salary": {"currency": null, "max": null, "min": null, "period": "monthly", "term": null}, "salary_visible": false, "title_keywords": ["analyst programmer"], "responsibilities": ["communicate with", "analysis", "implementation", "project plan", "testing"], "requirements": {"degrees": ["degree holder"], "majors": ["related disciplines", "computer science", "information technology"], "languages": ["english", "chinese", "mandarin"], "language_level": ["excellent"], "hard_skills": ["java", "agile", "web", "problem-solving skills", "devops", "html", "mobile", "javascript", "react native", "programming", "spring", "css"], "soft_skills": ["passionate", "good team player", "independent", "agile", "under pressure", "inter-personal", "communication", "eager to learn", "multi-tasking", "problem-solving skills", "proactive"], "languages_combined": [{"language": "english", "language_level": ["excellent"]}, {"language": "chinese", "language_level": ["excellent"]}, {"language": "mandarin", "language_level": ["excellent"]}]}, "experience_required": {"duration": ["minimum 3 years"], "field": ["application development", "banking"]}}, {"job_id": "100003009034857", "location_code": "hk", "company": "BGC Group (HK) Limited", "job_title": "Backend/ Frontend Developer (IoT, SaaS & Big Data Project)", "description": "Our client is an US Company which provides IoT Solutions. They are dedicated to deliver creative and professional solutions to clients in different sectors such as medical, retail and hospitality which improve lives and environment through AI and automation.\n\n\nATTRACTIVE remuneration with GENEROUS salary package and benefits\nGet connected with people all over the world; MNC\nFluent in both spoken and written English\n\nResponsibilities:\n\nWork closely with global team to implement and develop the projects\nResponsible for deployment and testing of cloud application\nWork closely with technical team to review operation processes and determine requirement\nParticipate in an integrated IoT platform which includes proprietary sensors, controls, software and AI to monitor, automate and optimize facilities, equipment and processes\nParticipate in demand research, project analysis, technical analysis and system development\nBe innovative and give ideas to growth hack the business metrics\n\nRequirements:\n\n3 years + working experience on related development field\nExperience in using\u00a0Experience in working with AWS cloud services and Google cloud will be a plus\nReactJS, AngularJS, NodeJS (Frontend)\nor Golang/Java and J2EE or Spring (Backend)\nCreative, proactive, and passionate with latest technologies\u00a0\u00a0\nGreat team player, independent, strong sense of responsibility and self-motivated\nProficient in written and spoken Chinese and English\n\nInterested candidates please click \"APPLY NOW\" or send your resume in WORD format enclosed with your current and expected salaries to\u00a0\u00a0Francis @bgc-group.com\n\n\u00a0*Personal data collected will be used for recruitment purpose only\n\n\n", "employment_types": ["Full Time", "Permanent"], "selling_points": ["Attractive and generous salary package", "Permanent offer; 5-day; Regular work schedule", "Open work environment & work life balance"], "locations": ["Ngau Tau Kok"], "categories": ["Information Technology (IT)", "Application Specialist - Software", "Software Development", "Technical Writing"], "post_time": "2022-01-10T04:26:09Z", "salary": {"currency": null, "max": null, "min": null, "period": "monthly", "term": null}, "salary_visible": false, "title_keywords": ["developer"], "responsibilities": [], "requirements": {"degrees": [], "majors": [], "languages": [], "language_level": [], "hard_skills": [], "soft_skills": [], "languages_combined": []}, "experience_required": {"duration": [], "field": []}}, {"job_id": "100003009038196", "location_code": "hk", "company": "Anywhere Everywhere Six Degrees Link Limited", "job_title": "QA Engineer, Automation/ Manual ( Fresh Graduates are welcome )", "description": "Manual\nJob Duties\n\nReview user requirements, functional specifications and prepare test specification/ plan\nPerform functional testing, regression testing, performance testing & exploratory testing and provide test report\nCollaborate with developers and reproduce defects for debug plan\nDesign contingency test case for unexpected scenarios\nParticipate in planning, design and testing phases of the application development\nProvide training materials and class for different parties\nRequirements\n\nRequirements Diploma or above, preferably in Computer Science, Information Technology or equivalent\nInterest and passion in new technology\n1 year related experience\nGood presentation skill on verbal and written English and Chinese\nFamiliar with translate User Stories into manual and automated test cases\nExperience in Agile / Scrum test environment procedures and processes is highly preferred\nFresh graduates would be considered\nAutomation\nJob Duties\n\nPartner with the development team to understand project objectives, gather automation requirements, design automated tests, troubleshoot issues, and implement scalable test automation\nExecute testing using both Manual and Automated testing Methods\nCompose test scripts for User Acceptance Testing from Business Analysis specification\nIdentify areas where automated testing can be applied\nParticipate in planning, design and testing phases of the application development\nReview Test scripts on a periodic basis to determine system efficiencies\nOther ad-hoc tasks as assigned\nRequirements\n\nDiploma or above, preferably in Computer Science, Information Technology or equivalent\nInterest and passion in new technology\n1 year related experience\nGood presentation skill on verbal and written English and Chinese\nFamiliar with translate User Stories into manual and automated test cases\nExperience in Agile / Scrum test environment procedures and processes is highly preferred\nProficient writing in Java / Python / JavaScript\nProficient writing Web / Mobile automation cases in Selenium / Appium ( either one is a big plus )\nFresh graduates would be considered\nBenefits\n5-day work week\nBirthday Leave\nDouble Paid\n14 ALs\nMedical Allowance with Dental\nYear-end Performance Bonus\nWorked with QA Team Size of 4", "employment_types": ["Full Time"], "selling_points": ["Salary : 25K - 40K + Bonus ( 1 - 2 Months )", "Automation : Selenium / Appium / Postman | Manual", "Work Life Balance | 14 ALs | Medical + Dental"], "locations": ["Yau Tsim Mong Area"], "categories": ["Information Technology (IT)", "Testing / QA", "Technical Writing", "Others"], "post_time": "2022-01-11T05:59:36Z", "salary": {"currency": "HKD", "max": 44999, "min": 25000, "period": "monthly", "term": null}, "salary_visible": true, "title_keywords": ["engineer"], "responsibilities": ["collaborate with", "provide training", "performance testing", "review", "design", "testing", "specifications", "planning", "plan", "application development", "report"], "requirements": {"degrees": ["diploma or above"], "majors": ["computer science", "information technology"], "languages": ["english", "chinese"], "language_level": ["good"], "hard_skills": ["presentation skill", "java", "plus", "agile", "web", "analysis", "mobile", "javascript", "python"], "soft_skills": ["presentation skill", "agile", "troubleshoot", "passion in"], "languages_combined": [{"language": "english", "language_level": ["good", "good"]}, {"language": "chinese", "language_level": ["good", "good"]}]}, "experience_required": {"duration": ["1 year"], "field": ["related"]}}, {"job_id": "100003009037083", "location_code": "hk", "company": "Cathay Pacific Airways Ltd", "job_title": "Digital Experience Executive \u2013 Chatbot", "description": "Responsibilities:\n\nDesign and implement Java applications using different frameworks;\nResponsible for development, maintenance of enterprise web applications and provide tier-3 support for business;\nGather users\u2019 requirements and translate it into system design;\nInvolve in development life cycle, debugging and enhancement.\n\nRequirement:\n\nBachelor Degree or above in Computer Science or related field;\nFamiliar with Core Java;\nFamiliar with Javascript / ES6 / Typescript;\nFamiliar with any of database (Oracle / SQL / MongoDb);\n\nAdded advantage:\n\nKnowledge of backend/frontend framework (Spring, Angular / React);\nExperience in mobile development (React Native / Flutter);\nKnowledge of microservice / container architecture;\nFamiliar with any of web application server (Weblogic/ Tomcat).\nCommitted, responsible, highly motivated and able to work independently;\n\nOur offer:\u00a0\n\nAttractive remuneration. We offer at least $25,000 for successful candidate;\nCareer development prospect;\n5-day working week;\n21+ days Annual Leave for all staff;\nPerformance bonus and company shares;\nMedical, Dental, Life Insurance;\nEducation allowance and monthly sports allowance.\n\nInterested parties please send your full resume by clicking \"APPLY NOW\".\n\nOur company is an equal opportunities employer and welcome application from all qualified candidates.\u00a0Information provided will be treated with strict confidential and be used for the purpose of selection only.\u00a0Applicants who are not invited for interview within 10 weeks may consider their applications unsuccessful. Personal data of unsuccessful applicant will be destroyed within 12 months.", "employment_types": ["Full Time", "Permanent"], "selling_points": ["2-3 years of experience in Digital", "Bachelor degree in Business, Computer Science", "Travel Benefits, 5-day work, Medical Benefits"], "locations": ["Lantau Island"], "categories": ["Information Technology (IT)", "Application Specialist - Network", "Technical Writing", "Others"], "post_time": "2022-01-11T01:39:29Z", "salary": {"currency": null, "max": null, "min": null, "period": "monthly", "term": null}, "salary_visible": false, "title_keywords": ["digital experience executive"], "responsibilities": ["maintenance", "system design", "design"], "requirements": {"degrees": ["degree or above", "bachelor"], "majors": ["computer science"], "languages": [], "language_level": [], "hard_skills": ["java", "web", "react", "sql", "mobile", "javascript", "typescript", "react native", "spring", "angular", "container", "application server", "oracle"], "soft_skills": ["committed", "work independently", "motivated", "responsible"], "languages_combined": []}, "experience_required": {"duration": [], "field": ["development"]}}, {"job_id": "100003009037995", "location_code": "hk", "company": "China Construction Bank (Asia) Corporation Limited", "job_title": "OFC - Analyst Programmer (Data & AML)", "description": "Main Responsibilities\n\n- To perform Data Analysis and Data Model design on Big Data Cloud Platform\n- Conduct system and report development based on user requirement, including requirement analysis, system design, coding and testing\n- Provide support and maintenance in production environments\n- Provide application support for in-house systems including training\n- Implement system testing to ensure quality of work\n- Prepare technical documentation\n\nRequirements\n\n- Degree holder in Information Technology, Computer Science or related disciplines\n- 3 years or above experience in application development, preferably gained from banking / finance industry\n- Experience in Data Analysis, Data Model design and ETL design\n- Knowledge and experience in Oracle PL/SQL, SQL, Java and Python\n- Knowledge and experience in Big Data Technology like Hadoop/Hive, GreenPlum;\n- Knowledge in report development with BI tools like Cognos\n- Knowledge in data analysis with strong ability in understanding business requirement; Strong ability in data modelling\n- Knowledge in VB.NET, ASP.NET, C#, SQL Server, Unix shell scripts and Web Service\n- Able to work independently with positive thinking; Good communication skills and able to work under pressure; Strong ability in learning new technology; Able to work in a team\n- Good command of written and spoken English and Chinese (including Putonghua)", "employment_types": ["Full Time", "Permanent"], "selling_points": ["Analyst Programmer", "Data Analysis", "Big Data"], "locations": ["Kowloon Bay"], "categories": ["Information Technology (IT)", "Technical Writing", "Data Scientist"], "post_time": "2022-01-11T04:30:25Z", "salary": {"currency": null, "max": null, "min": null, "period": "monthly", "term": null}, "salary_visible": false, "title_keywords": ["analyst programmer"], "responsibilities": ["user requirement", "provide support", "maintenance", "data", "analysis", "systems", "big data", "quality", "design", "coding", "data analysis", "testing", "system design", "documentation", "report"], "requirements": {"degrees": ["degree holder"], "majors": ["related disciplines", "computer science", "information technology"], "languages": ["putonghua", "english", "chinese"], "language_level": ["good command"], "hard_skills": ["server", "java", "bi", "web", "analysis", "unix shell", "c#", "sql", "python", "pl", "oracle"], "soft_skills": ["communication skills", "work independently", "positive thinking", "learning", "work under pressure"], "languages_combined": [{"language": "putonghua", "language_level": ["good command"]}, {"language": "english", "language_level": ["good command"]}, {"language": "chinese", "language_level": ["good command"]}]}, "experience_required": {"duration": ["3 years"], "field": ["banking", "design", "data analysis", "sql", "finance industry", "application development", "oracle pl"]}}, {"job_id": "100003009038757", "location_code": "hk", "company": "HomePlus (Hong Kong) Limited (HOME+)", "job_title": "Software QA Engineer - E-Commerce Platform", "description": "What efforts you need to make?\nReview requirements, specifications and technical design documents to provide timely and meaningful feedback\nCreate detailed, comprehensive and well-structured test plans and test cases\nEstimate, prioritize, plan and coordinate testing activities\nDesign, develop and execute automation scripts using open source tools\nIdentify, record, document thoroughly and track bugs\nPerform thorough regression testing when bugs are resolved\nDevelop and apply testing processes for new and existing products to meet client needs\nLiaise with internal teams (e.g. developers and product managers) to identify system requirements\nMonitor debugging process results\nInvestigate the causes of non-conforming software and train users to implement solutions\nTrack quality assurance metrics, like defect densities and open defect counts\nStay up-to-date with new testing tools and test strategies\nLet's check if you are/have\u2026\nProven work experience in software development\nProven work experience in software quality assurance\nStrong knowledge of software QA methodologies, tools and processes\nExperience in writing clear, concise and comprehensive test plans and test cases\nHands-on experience with both white box and black box testing\nHands-on experience with automated testing tools (e.g. Selenium, Appium)\nSolid knowledge of SQL and scripting (e.g. Python browser library, robot framework)\nExperience working in an Agile/Scrum development process\nExperience with performance and/or security testing is a plus\nBS/MS degree in Computer Science, Engineering or a related subject\n\nWhat you get in return\u2026\n\nApart from competitive salary package and benefits, in HKBN, you will work flexibly under our Talent-first\u00a0culture\u00a0and we uphold Life-Work Priority. Examples of our flexible initiatives:\n\nFive-day work week and shorten working hours (8 hours including 1 hour 15 mins meal break)\nHalf Day Off Friday once a month (compensation leave for Talents who work on shift)\nHalf Day Off on Festival Eve (compensation leave for Talents who work on shift)\nUnique leaves arrangement: Family-care leave, Anniversary leave, Bonus leave, Volunteer leave, Sabbatical leave, etc.\nComprehensive medical and life insurance coverage\nUpgraded maternity leave and paternity leave\nDiscounted Talent plan offers including broadband and mobile plans and other promoted products\nEducation subsidies and Examination leave\nYear-end discretionary bonus", "employment_types": ["Full Time", "Permanent"], "selling_points": ["Software QA methodologies", "SQL and scripting", "LIFE-Work Priority & Talent-first Culture"], "locations": ["Kwai Hing"], "categories": ["Information Technology (IT)", "Software Development", "Technical Writing", "E-commerce", "Software Development"], "post_time": "2022-01-11T07:45:11Z", "salary": {"currency": null, "max": null, "min": null, "period": "monthly", "term": null}, "salary_visible": false, "title_keywords": ["engineer"], "responsibilities": ["software", "review", "teams", "monitor", "design", "plan and coordinate", "testing activities", "develop", "testing", "specifications", "quality", "bs", "liaise with", "plans"], "requirements": {"degrees": ["degree"], "majors": ["engineering", "computer science"], "languages": [], "language_level": [], "hard_skills": ["plus", "agile", "sql", "make", "python"], "soft_skills": ["agile", "timely", "prioritize", "clear", "hands-on", "comprehensive", "thorough", "structured", "detailed"], "languages_combined": []}, "experience_required": {"duration": [], "field": ["development", "testing", "writing", "security", "software development", "quality assurance"]}}, {"job_id": "100003009040284", "location_code": "hk", "company": "Ai Pu Jing Software Technology (Hong Kong) Co Ltd", "job_title": "IT Solution Architect", "description": "APJ Hong Kong ( www.apjcorp.com.hk ) provides the highest quality software development, maintenance and testing services.\u00a0 We have cost effective service centers with highly qualified IT professionals in Hong Kong. Our clients include major enterprises and organizations in the Finance, Manufacturing, Public Utility, Retail, healthcare and Government sectors. We are looking for Solution Architect.\n\nYou will be involving\u2026\n\nTo act as the technical design leader for Azure cloud or other applications solution\nTo understand business objectives, user requirements and lead the team on solution architecture and design\nTo work closely with Solution team, IT Team and Sales Team to prepare business and technical proposals with viable solutions for clients\nTo perform system analysis, design and development of applications using Azure cloud or other technologies\nLead the PoC, technical assessment on solutions\n\nWe are looking for\u2026\n\nDegree holder in Computer Science/Computer Engineering or related discipline\nMinimum 6 years of solid experiences in application design and technical architecture, particularly Azure based cloud solutions\nStrong experience in design and implementing Webs, Mobile Applications, .NET, and DevOps\nExperience in migrating on-premise .Net solutions to Azure cloud would be an advantage\nExperience in Scaled agile framework would be an advantage\nProficient in written and spoken English and Chinese with strong communication skills\nResponsible, proactive and detail minded\n\nWe are offering\u2026\n\n5-day work\nAttractive package\nYear \u2013 end bonus\nMedical insurance\nFestival gifts\nExcellent project exposure and career development opportunities\n\nIf you are interested in sizable project and want to start a new challenging job into public institution industry, please feel free to apply with your full resume, present/expected salary, and availability by click on the 'Apply Now' button.", "employment_types": ["Full Time"], "selling_points": ["At least 6 years total relevant experience", "Lead the development team on solution development", "MS Azure experience"], "locations": ["Kowloon Bay"], "categories": ["Information Technology (IT)", "Application Specialist - Software", "Software Development", "Technical Writing"], "post_time": "2022-01-12T02:07:46Z", "salary": {"currency": null, "max": null, "min": null, "period": "monthly", "term": null}, "salary_visible": false, "title_keywords": [], "responsibilities": ["cost", "software", "maintenance", "analysis", "quality", "design", "testing", "communication", "sales team", "career development", "insurance", "architecture"], "requirements": {"degrees": ["degree holder"], "majors": ["computer engineering", "computer science"], "languages": ["english", "chinese"], "language_level": ["proficient"], "hard_skills": ["azure", "agile", "maintenance", "analysis", "devops", "mobile"], "soft_skills": ["communication skills", "agile", "responsible", "interested in", "proactive"], "languages_combined": [{"language": "english", "language_level": ["proficient"]}, {"language": "chinese", "language_level": ["proficient"]}]}, "experience_required": {"duration": ["minimum 6 years"], "field": ["design"]}}, {"job_id": "100003009037989", "location_code": "hk", "company": "China Construction Bank (Asia) Corporation Limited", "job_title": "OFC - Systems Analyst /Sr Analyst Programmer (Java)", "description": "Main Responsibilities\n\n- Conduct business analysis and applications programming for systems development projects\n- Act as project manager of projects assigned\n- Co-ordinate with vendors and collaborate with different business units to ensure the projects can be delivered on schedule\n- Prepare and execute test plan and scripts for system integration test\n- Provide user acceptance test and production support\n- Conduct project implementation\n- Prepare system documentation\n- Provide coaching to junior team members and lead programmers, contractors and/or vendors to complete assignments\n\nRequirements\n\n- University graduate preferably in Computer Science or related disciplines\n- Minimum 6 years of experience on application development, preferably in banking or finance industry with hands-on project management experience\n- Good understanding in user experience, systems, database design.\n- Proficiency in Spring frameworks, Java, HTML5, JavaScript, CSS, JSON, RESTful, SQL\n- Knowledgeable in Node.js, Git, NPM, Maven, Jenkins, Linux Shell, Microsoft Technology stack (e.g. C#,VB) is a plus\n- Good command of spoken and written English and Chinese (both Cantonese and Putonghua)\n- Solid interpersonal, communication and organizational skills\n- Strong self-motivation with good project management skills and able to work independently\n- Candidate with less experience would be considered as Senior Analyst Programmer", "employment_types": ["Full Time", "Permanent"], "selling_points": ["business analysis", "applications programming", "Java"], "locations": ["Kowloon Bay"], "categories": ["Information Technology (IT)", "Product Management / Business Analyst", "Technical Writing"], "post_time": "2022-01-11T04:30:24Z", "salary": {"currency": null, "max": null, "min": null, "period": "monthly", "term": null}, "salary_visible": false, "title_keywords": ["analyst programmer", "analyst"], "responsibilities": ["collaborate with", "system documentation", "co-ordinate with", "systems", "implementation", "schedule", "plan", "business analysis"], "requirements": {"degrees": ["university graduate"], "majors": ["related disciplines", "computer science"], "languages": ["cantonese", "putonghua", "english", "chinese"], "language_level": ["good command"], "hard_skills": ["linux", "java", "git", "plus", "jenkins", "sql", "project management", "javascript", "spring", "css"], "soft_skills": ["organizational skills", "work independently", "project management skills", "communication", "project management", "hands-on", "self-motivation", "interpersonal"], "languages_combined": [{"language": "cantonese", "language_level": ["good command"]}, {"language": "putonghua", "language_level": ["good command"]}, {"language": "english", "language_level": ["good command"]}, {"language": "chinese", "language_level": ["good command"]}]}, "experience_required": {"duration": ["minimum 6 years"], "field": ["banking", "design", "project management", "database", "finance industry", "application development"]}}, {"job_id": "100003009039720", "location_code": "hk", "company": "Morgan Half International (Hong Kong) Limited", "job_title": "IT Manager - Cloud Security (Microsoft 365, Aliyun/Azure/AWS)", "description": "Client Details:\n\nOur client is a reputable company. They are looking for a Cloud Security IT Manager. In this role you will accountable to develop the cloud security design framework.\n\nResponsibilities:\n\n\nAccountable for development of the Cloud Security Design framework for new technology solutions\nResponsible for embedding best practice security through the setup and maintenance of Cloud Landing Zones\nDevelop security hardening standard for AWS, Azure and Aliyun cloud platforms\nResponsible for leading cloud security project to automate cloud hardening compliance checking and remediation\nDevelop cloud security alert handling SOP for SOC to follow\nPerform security risk assessment on Cloud applications/IT systems to identify security weaknesses and non-compliance with IT Reference Architecture and IT security control matrix\nImplement RPA/automation to improve team efficiency\n\nRequirements:\n\nDegree holder/or above with IT related discipline\n5+ years of IT security experience\u00a0\nHolder of cloud security certification such as CCSP, Aliyun ACP, AWS Certified Security Specialty, Azure security certification\nManagerial grade experience with cyber and cloud security knowledge\nStrong knowledge of IT general controls, cybersecurity risks, technology risks (including infrastructure, cloud and application security)\nHand-on security assessment/implementation experience on Microsoft 365, Aliyun/Azure/AWS public cloud platforms.\nHand-on experience on cloud landing zone design and maintenance\nPractical skill on cloud configuration compliance checking automation\nA strong team player with good analytical and problem-solving skill\nProject management experience is preferred\nGood communication skill\nGood English and Chinese (including Mandarin) Language skill (both written & verbal)\n\nTo apply online, please press \"Apply Now\" button below. For any inquiries, please email info @morganhalf.com", "employment_types": ["Full Time"], "selling_points": ["CCSP, Aliyun ACP, AWS Certified Security Specialty", "Listed company, Cyber Security Team", "13 months salary plus bonus, stable environment"], "locations": ["Not Specified"], "categories": ["Information Technology (IT)", "Security", "Technical / Functional Consulting", "Technical Writing"], "post_time": "2022-01-11T10:40:42Z", "salary": {"currency": null, "max": null, "min": null, "period": "monthly", "term": null}, "salary_visible": false, "title_keywords": ["it manager"], "responsibilities": ["control", "maintenance", "compliance", "systems", "checking", "design", "develop", "architecture", "setup"], "requirements": {"degrees": ["degree holder"], "majors": ["it"], "languages": ["english", "chinese", "mandarin"], "language_level": ["good"], "hard_skills": ["azure", "maintenance", "problem-solving", "aws", "project management", "public cloud platforms"], "soft_skills": ["problem-solving", "project management", "team player", "communication skill"], "languages_combined": [{"language": "english", "language_level": ["good"]}, {"language": "chinese", "language_level": ["good"]}, {"language": "mandarin", "language_level": []}]}, "experience_required": {"duration": ["5+ years"], "field": ["managerial", "maintenance", "design", "project management", "it", "security"]}}, {"job_id": "100003009034945", "location_code": "hk", "company": "Pathsight Limited", "job_title": "Programmer / Senior Programmer up to 28k (FG welcome)", "description": "Exciting opportunities for IT professionals and FGs with passion to identify their career path\u00a0\n\nResponsibilities\n\n\nEnd-to-end system development from requirement collections, feasibility study, system design, implementation, to system deployment\nPerform quality assurance on project deliverable\nSupport and facilitate Project Manager in planning, executing, monitoring and reporting to ensure project success\n\nRequirements\n\nHD or above in Computer Science or IT related disciplines\nFor Programmer 0-1 year experience (FG welcome)\u00a0\nFor Senior Programmer 1\u00a0year or above\u00a0\nExperience in system integration related to the following:\u00a0\nJava / J2EE / Spring or,\nC# / VB.NET / ASP.NET\nJavaScipt/PHP\nReact.js, Node.js\nC/C++", "employment_types": ["Full Time", "Permanent"], "selling_points": ["5-day, Medical, Dental, Education Allowance", "Openings of different industries", "Bonus, Double Pay"], "locations": ["Not Specified"], "categories": ["Information Technology (IT)", "Application Specialist - Software", "Technical / Functional Consulting", "Technical Writing"], "post_time": "2022-01-10T04:47:42Z", "salary": {"currency": null, "max": null, "min": null, "period": "monthly", "term": null}, "salary_visible": false, "title_keywords": ["programmer", "senior programmer"], "responsibilities": ["reporting", "monitoring", "quality", "implementation", "system design", "executing", "planning"], "requirements": {"degrees": [], "majors": [], "languages": [], "language_level": [], "hard_skills": ["java", "c++", "php", "react", "c", "spring", "integration", "c#"], "soft_skills": [], "languages_combined": []}, "experience_required": {"duration": ["0-1 year"], "field": ["related"]}}, {"job_id": "100003009034787", "location_code": "hk", "company": "HomePlus (Hong Kong) Limited (HOME+)", "job_title": "AWS Engineer / AWS Administrator", "description": "This\u00a0position will be under HOME+ e-commerce platform.\n\nOur Vision of Home+ is to set up a merchant ecosystem of merchants with shared value, covering different aspects of our customers\u2019 daily household purchases. The mission is to provide customers with the best value for money for the promotional products and services offered, from time to time. For more information, please feel free to visit our website at\u00a0https://home-plus.hk/\n\nTo be part of our mission, we are looking for an AWS Engineer / AWS Administrator to\u2026\n\nAct as first contact person in case of alerts\nDesign and\u00a0maintain highly available, cloud-based infrastructures in AWS.\nUnderstand of auto-scaling technologies and high-throughput designs.\nMonitor and troubleshoot in case of alerts and manage incidents to closure.\nManage full AWS Lifecycle, Provisioning, Automation and Security.\nConfigure and fine-tune cloud infrastructure systems.\nPerform software upgrades. Kernel patching, errata patches.\nAutomate deployment of infrastructure through the use of Cloud Formation or Terraform.\nEnforce resource tagging to designate costs and for planning of budgeting, governance, and reporting.\nCommunicate with the Cloud team to manage network connections on VPCs, VPNs.\nMonitor billing and to develop cost optimization strategies.\nEnforce AWS best practice in managing infrastructure\nMaintain a backup plan for all resources used on AWS.\nManage disaster recovery and create backups.\n\nThe follow attributes will be valued\u2026\n\n0 -2 years of experience in building infrastructure for enterprise applications and solutions using AWS.\nExperience with AWS cloud-based architectures\nExperience on using metrics to monitor the health, utilization and availability of AWS resources on a full scale by Amazon CloudWatch, CloudTrail and third party tools such as NewRelic.\nVery strong skills on the basics (Route53, EC2, ACM, ELB, VPC and S3).\nHands on experience on overcoming and protecting against a DDoS attack.\nHands on implementing one or more CloudFront Distributions and the core use-cases for a CDN.\n\nWhat you get in return\u2026\n\nApart from competitive salary package and benefits, in HKBN, you will work flexibly under our Talent-first\u00a0culture\u00a0and we uphold Life-Work Priority. Examples of our flexible initiatives:\n\nFive-day work week and shorten working hours (8 hours including 1 hour 15 mins meal break)\nHalf Day Off Friday once a month (compensation leave for Talents who work on shift)\nHalf Day Off on Festival Eve (compensation leave for Talents who work on shift)\nUnique leaves arrangement: Family-care leave, Anniversary leave, Bonus leave, Volunteer leave, Sabbatical leave, etc.\nComprehensive medical and life insurance coverage\nUpgraded maternity leave and paternity leave\nDiscounted Talent plan offers including broadband and mobile plans and other promoted products\nEducation subsidies and Examination leave\nYear-end discretionary bonus\n\n\n", "employment_types": ["Full Time", "Permanent"], "selling_points": ["Maintain cloud-based infrastructure in AWS", "Manage full AWS Lifecycle/Provisioning/Automation", "Monitor health/utilization/AWS Resources"], "locations": ["Kwai Hing"], "categories": ["Information Technology (IT)", "Support", "Technical Writing", "E-commerce", "Software Development"], "post_time": "2022-01-10T04:14:54Z", "salary": {"currency": null, "max": null, "min": null, "period": "monthly", "term": null}, "salary_visible": false, "title_keywords": ["administrator", "engineer"], "responsibilities": ["software", "budgeting", "website", "design", "maintain", "troubleshoot", "plan", "costs", "infrastructure", "monitor", "develop", "reporting", "upgrades", "contact", "backups", "third party", "communicate with", "cost optimization", "systems", "e-commerce platform", "planning"], "requirements": {"degrees": [], "majors": [], "languages": [], "language_level": [], "hard_skills": ["plus", "amazon", "e-commerce", "aws", "deployment", "s3"], "soft_skills": ["hands on", "troubleshoot"], "languages_combined": []}, "experience_required": {"duration": ["0 -2 years"], "field": ["infrastructure"]}}, {"job_id": "100003009034889", "location_code": "hk", "company": "Top Executive Talent Engineering", "job_title": "Developer/ Programmer (Fresh Grad welcome) 19K+/- Top General Insurance Firm", "description": "GREAT STEPPING STONE FOR IT GRADUATES\n\nJob Descriptions:\n\nl\u00a0 Develop in-house finance and insurance services related application programs\n\nl\u00a0 Assist in program testing, modification and documentation\n\nl\u00a0 Provide technical support to end users\n\nl\u00a0 Compile regular reports\n\nRequirements:\n\nl\u00a0 \u00a0University graduate in computing, information technology or related disciplines\n\nl\u00a0 Knowledge of Java, Visual Basic and web application\n\nl\u00a0 Interested in financial industry is an advantage\n\nWe offer 5-day work, discretionary bonus, medical benefits, retirement fund and public holiday, etc\n\n\n\n", "employment_types": ["Full Time", "Permanent"], "selling_points": ["Fresh IT Grad, enjoy web/ app coding", "Full on the job training provided", "Great prospect, $$ and benefits"], "locations": ["Wan Chai"], "categories": ["Information Technology (IT)", "Application Specialist - Software", "Technical Writing", "Mobile / Wireless Communications"], "post_time": "2022-01-10T04:30:26Z", "salary": {"currency": null, "max": null, "min": null, "period": "monthly", "term": null}, "salary_visible": false, "title_keywords": ["developer", "programmer"], "responsibilities": ["technical support", "testing", "develop", "reports", "documentation", "insurance"], "requirements": {"degrees": ["university graduate"], "majors": ["related disciplines", "information technology"], "languages": [], "language_level": [], "hard_skills": ["java", "visual basic", "web"], "soft_skills": ["interested in"], "languages_combined": []}, "experience_required": {"duration": [], "field": []}}, {"job_id": "100003009039305", "location_code": "hk", "company": "IT Solutions Ltd.", "job_title": "New e-Banking System Project: Java Development Manager - Major Bank", "description": "We are searching on behalf of a Major Bank\u00a0for high-calibre IT Development Manager\u00a0to work on\u00a0New e-Banking System development project.\n\nResponsibilities:\n\nWork through the whole software development lifecycle\nSystem analysis and system design\nPlan and suggest for solutions to enhance user experience\nLead Analyst Programmer and Programmer to develop and test applications using Java,\u00a0Spring MVC, SQL, etc\nLiaise with internal IT staff and external vendors\nSystem rollout and support.\n\nRequirements:\n\nDegree in Computer Science or related discipline\nStrong knowledge in Java and SQL.\nKnowledge in TypeScript, Spring, React Native, React is an advantage but not mandatory.\nWith or without banking experience\nCandidates with less experience will be considered as AP or Programmer.\n\nBenefits:\n\nAttractive remunerations will be offered to the successful candidates.\nExcellent opportunity to further develop your professional skills on Corporate Banking Systems Projects in a Major Bank.\n\n\n\nIf you are interested, please send your resume in MS Word format, specifying your availability, current and expected salaries to:\n\njobs @itsolutions.com.hk\n\nor\n\nPlease click the Apply Now button and attach your cv in MS Word Format, specifying your availability, current and expected salaries.\n\n\nPersonal data collected will be used for recruitment purposes only.\n\n\nIT Solutions Ltd.\nSuite 2102, 21st Floor\nLucky Building\n39 Wellington Street\nCentral, Hong Kong\n\n(P.S.\u00a0 We do not process applications from overseas for this position)", "employment_types": ["Full Time"], "selling_points": ["Strong knowledge in Java, SQL", "Gain enterprise scale system development skills", "Good career prospect in a Major Bank"], "locations": ["Not Specified"], "categories": ["Information Technology (IT)", "Application Specialist - Software", "Software Development", "Technical Writing"], "post_time": "2022-01-11T09:46:16Z", "salary": {"currency": null, "max": null, "min": null, "period": "monthly", "term": null}, "salary_visible": false, "title_keywords": ["manager"], "responsibilities": ["software", "analysis", "user experience", "develop", "system design", "plan", "liaise with"], "requirements": {"degrees": ["degree"], "majors": ["computer science"], "languages": [], "language_level": [], "hard_skills": ["ap", "java", "react", "sql", "typescript", "react native", "spring"], "soft_skills": [], "languages_combined": []}, "experience_required": {"duration": [], "field": ["banking experience"]}}, {"job_id": "100003009034062", "location_code": "hk", "company": "Webs s'up Production Company Limited", "job_title": "Web Developer", "description": "We\u2019re Webs S\u2019 up, a digital consultancy with a singular mission \u2013 We Enhance Engagement.\n\nJoin us to become a Webs S\u2019 up family member!\n\nYou will be entitled to a competitive salary and attractive staff benefits including:\n\nAnnual leave, paid sick leave, compensation leave, marriage leave, maternity leave, paternity leave and compassionate leave\nFive-day work week in Kowloon Bay Office\nComprehensive medical and dental coverage\nProfessional training and career advancement opportunities\nFriendly working environment\u00a0and work-life balance culture\n\nWhat do you need to do?\n\nWork with a team of Web/App developers to develop and implement Web-based applications/services\nCreate and maintain web pages using HTML, CSS and JavaScript\nDevelop web-based application/service, database and APIs\n\nWhat do you need to have?\n\nDegree in Computer Science, Information Technology, or equivalent major\n1-2 years hands-on experience of web development\nFamiliar with web technologies, including RESTful API, GraphQL, OpenAPI and OAuth\nExperience in Node.js\nExperience in framework such as Nuxt.js and Laravel\nExperience in infrastructure such as AWS, GCP and Azure\nExperience in virtual machines and containers\nExperience in version control such as Git\nAbility to learn new technologies and integrate them effectively into the platform\nTeam player with strong analytical, problem-solving, and communication skills\nThe passion and ability to learn quickly and work with a team\nReasonable command of spoken and written English and Cantonese\n\nReady to join us? Apply now to submit your resume & expected salary to us!\n\n(Personal data will be used for Webs s\u2019 up Production Limited recruitment purposes only. We will retain the applications of candidates for no more than 12 months.)", "employment_types": ["Full Time", "Permanent"], "selling_points": ["Five-day work week in Kowloon Bay Office", "Open-minded and young working environment", "Competitive salary with attractive Talent Benefi"], "locations": ["Kowloon Bay"], "categories": ["Information Technology (IT)", "Application Specialist - Software", "Software Development", "Technical Writing"], "post_time": "2022-01-10T02:33:25Z", "salary": {"currency": null, "max": null, "min": null, "period": "monthly", "term": null}, "salary_visible": false, "title_keywords": ["developer"], "responsibilities": [], "requirements": {"degrees": [], "majors": [], "languages": [], "language_level": [], "hard_skills": [], "soft_skills": [], "languages_combined": []}, "experience_required": {"duration": [], "field": []}}, {"job_id": "100003009035745", "location_code": "hk", "company": "Hong Kong Technology Venture Company Limited", "job_title": "Programmer - Frontend / Backend (New Project)", "description": "You will work under a brand-new company and team with start-up culture. We have flexible and self-motivated working style and informal working environment.\n\nWhat You will be Doing\n\nFrontend-Web programmer:\n\nEngage in design, develop, implement, test and maintain a new era e-commerce web applications with reusable modules, automated testing, and continuous deployment.\nApply strong analytical and technical skills in application problems, system design and user experience.\nResearching and adopting the latest frontend/Backend and cloud related technologies and tools or\nWork with the team in the Agile approach.\n\nBackend programmer:\n\nEngage in design, develop, implement, test and maintain a new era e-commerce web applications with reusable modules, automated testing, and continuous deployment.\nApply strong analytical and technical skills in application problems, system design and user experience.\nResearching and adopting the latest backend and cloud related technologies and tools.\nWork with the team in the Agile approach.\n\nWho is Our Right Fit\n\nFrontend-Web programmer:\n\nDegree holder in IT related disciplines.\n2+ years of hands-on experience in web application development.\nSkilled in building frontends with React, Redux, HTML5, CSS3, CSS Modules, TypeScript/ES2017.\nFamiliar with testing, performance and optimization techniques.\nThorough understanding in RESTful API.\n\nBackend programmer:\n\nDegree holder in IT related disciplines.\n2+ years of hands-on experience in web application development.\nSkilled in building backends with Node.js and TypeScript (or proficient in other server-side languages such as Java, C# will also be considered).\nFamiliar with Event-Driven design and tools, such as Message Queue, Event Bus...etc.\nExcellent knowledge of Relational Databases, SQL.\nKnowledge of NoSQL Database.\nKnowledge and experience adhering to writing high-quality code with tests.\nThorough understanding in RESTful API.\nFamiliar with containers technology (i.e. Docker) and deployment.\u00a0\n\nAdvantage\n\nFrontend-Web programmer:\n\nFamiliar with SSR / SSG frameworks such as Next.js is a strong plus.\nExperience in WebSocket programming.\nThorough understanding of SEO implementation.\nFamiliar with Git, Docker, CI/CD tools and AWS.\n\nBackend programmer:\n\nExperience in using AWS cloud (e.g. Lambda, API Gateway...etc.).\nExperience in WebSocket programming.\nFamiliar with IaC such as Terraform, AWS CDK and Pulumi.\nFamiliar with Nest.js.\nFamiliar with K8S, Helm.\nFamiliar with Git, Docker, CI/CD tools.\nFamiliar with domain driven design.\n\nPersonal\n\nSelf-motivated with \u201ccan do\u201d attitude.\nGood team player.\nTo-the-point communication.\nTimely delivery of results.", "employment_types": ["Full Time", "Permanent"], "selling_points": ["Excellent career development in E-commerce", "2+ years exp in web application development", "Young & open-minded work environment"], "locations": ["Tseung Kwan O"], "categories": ["Information Technology (IT)", "Application Specialist - Software", "Software Development", "Technical Writing"], "post_time": "2022-01-10T08:21:13Z", "salary": {"currency": null, "max": null, "min": null, "period": "monthly", "term": null}, "salary_visible": false, "title_keywords": ["programmer"], "responsibilities": ["seo", "quality", "user experience", "design", "testing", "develop", "implementation", "communication", "maintain", "system design", "databases", "database", "application development"], "requirements": {"degrees": ["degree holder"], "majors": ["related disciplines", "it"], "languages": [], "language_level": [], "hard_skills": ["plus", "web application development", "agile", "web", "e-commerce", "server", "c#", "java", "git", "css", "restful api", "seo", "aws", "sql", "typescript", "web applications", "react", "system design", "deployment", "databases", "programming", "code"], "soft_skills": ["flexible", "self-motivated", "good team player", "agile", "timely", "communication", "hands-on", "thorough", "technical skills", "driven"], "languages_combined": []}, "experience_required": {"duration": ["2+ years"], "field": ["analytical", "system design", "writing", "programming", "application development"]}}, {"job_id": "100003009033956", "location_code": "hk", "company": "Seito Systems Ltd", "job_title": "Sales Engineer ( IT Applications )", "description": "\u00a0 \u00a0 \u00a0 \u00a0 \u00a0 \u00a0Job Description\n\nCollaborate with team-mates of Business Development, Marketing, and Sales Departments to demonstrate, prove of concept and deploy related I.T.\u00a0applications and solutions to Customers\nMarket research and technical evaluations to address requirements and needs.\nTeam up with RnD and Product Management Departments to provide solutions for Customers.\n\n\u00a0 \u00a0 \u00a0 \u00a0 \u00a0 \u00a0Job Requirements\n\nHigh Diploma or Degree holder in computer or related Professions\nMinimum 1-2 years of experience in a technical engineering role\nFamiliar with Windows server and Internet Applications\nKnowledge in MSSQL database administration is an advantage\nGood command of written and spoken English is a Must\nWork independently, self motivate and able to work under pressure\nWilling to travel and visit regional sites for sales and system implementations\nBenefits\nWe offer a competitive remuneration package and good prospects to the right candidate including\n5 days work week\nAnnual Leave\nBirthday Leave\nMarriage Leave\nExtra paternity leave\nCompassionate leave\nMedical insurance\nEducation allowance support\nPerformance bonus\nInterested parties please apply with a full resume and indicate your current and expected salary by clicking \"Apply Now\" or WhatsApp Ms. Shum on 93292895.\nAll Personal data collected will be used for recruitment purposes only.", "employment_types": ["Full Time", "Permanent"], "selling_points": ["High Diploma or above in Computer or related Prof.", "Working experience in POS solutions", "5 Days work,"], "locations": ["Kwun Tong"], "categories": ["Hospitality / F & B", "Food & Beverage", "Information Technology (IT)", "Technical Writing", "Sales, CS & Business Devpt", "Technical Sales / Sales Engineer"], "post_time": "2022-01-10T02:16:39Z", "salary": {"currency": null, "max": null, "min": null, "period": "monthly", "term": null}, "salary_visible": false, "title_keywords": ["sales engineer"], "responsibilities": ["collaborate with", "management", "market research", "provide solutions", "deploy"], "requirements": {"degrees": ["high diploma", "degree holder"], "majors": [], "languages": ["english"], "language_level": ["good command"], "hard_skills": ["mssql", "windows server"], "soft_skills": ["work independently", "work under pressure"], "languages_combined": [{"language": "english", "language_level": ["good command"]}]}, "experience_required": {"duration": ["minimum 1-2 years"], "field": ["engineering"]}}, {"job_id": "100003009034942", "location_code": "hk", "company": "Pathsight Limited", "job_title": "Junior / Mobile Developer (iOS / Android) - 40k", "description": "Requirement:\u00a0\nAssisting in the mobile application project(s)\u00a0\u00a0\nImplementing software component(s) based on the provided specification(s) and guidelines\nDeveloping, implementing and testing mobile application(s) - iOS / Android\u00a0\nAssisting in analyzing requirements and involve in system designation\u00a0\nDeveloping unit test case(s), and perform comprehensive unit testing\u00a0\nQualification\u00a0\nDegree / Diploma in Computer Science or any equivalent\n1 - 7 years in application development of iOS or Android platform\u00a0(Fresh Graduates are welcome to apply!)\u00a0\nKnowledge in\u00a0Swift / Objective-C / Xamarin, Java / Kotlin, C# / Unity, React Native\nCandidate with more experience will be considered for senior position(s)", "employment_types": ["Full Time", "Permanent"], "selling_points": ["5-day, Medical, Dental, Edu, Bonus, Double Pay", "Openings of different industries", "Android/iOS, Swift/Java/Kotlin, React Native"], "locations": ["Not Specified"], "categories": ["Information Technology (IT)", "Application Specialist - Software", "Technical / Functional Consulting", "Technical Writing"], "post_time": "2022-01-10T04:47:41Z", "salary": {"currency": null, "max": null, "min": null, "period": "monthly", "term": null}, "salary_visible": false, "title_keywords": ["developer", "junior"], "responsibilities": ["software", "guidelines", "developing", "testing", "application development"], "requirements": {"degrees": ["diploma", "degree"], "majors": ["computer science"], "languages": [], "language_level": [], "hard_skills": ["java", "objective-c", "mobile", "react native", "swift", "kotlin", "unity", "android", "c#"], "soft_skills": ["comprehensive"], "languages_combined": []}, "experience_required": {"duration": [], "field": []}}, {"job_id": "100003009036927", "location_code": "hk", "company": "Hong Kong Technology Venture Company Limited", "job_title": "Programmer - Frontend/ Backend", "description": "What You Will Be Doing\n\nEngage in design, develop, implement, test and maintain a new era e-commerce web applications with reusable modules, automated testing, and continuous deployment\nApply strong analytical and technical skills in application problems, system design and user experience\nResearching and adopting the latest frontend technologies and tools\nWork with the team in the Agile approach\n\nFrontend - Who is Our Right Fit\u00a0\n\nDegree holder in IT related disciplines\n2+ years of hands-on experience in web application development\nSkilled in building frontends with React, Redux, HTML5, CSS3, CSS Modules, TypeScript/ES2017\nFamiliar with testing, performance and optimization techniques\nThorough understanding in RESTful API\nCandidates with more experiences will consider as Senior Programmer\n\nAdvantage\n\nFamiliar with SSR / SSG frameworks such as Next.js is a strong plus\nExperience in WebSocket programming\nThorough understanding of SEO implementation\nFamiliar with Git, Docker, CI/CD tools and AWS\n\nBackend - Who is Our Right Fit\u00a0\u00a0\n\nDegree holder in IT related disciplines\n2+ years of hands-on experience in web application development\nSkilled in building backends with Node.js and TypeScript (or proficient in other server-side languages such as Java, C# will also be considered)\nFamiliar with Event-Driven design and tools, such as Message Queue, Event Bus...etc.\nExcellent knowledge of Relational Databases, SQL\nKnowledge of NoSQL Database\nKnowledge and experience adhering to writing high-quality code with tests\nThorough understanding in RESTful API\nFamiliar with containers technology (i.e. Docker) and deployment\nCandidates with more experiences will consider as Senior Programmer\n\nAdvantage\u00a0\n\nExperience in using AWS cloud (e.g. Lambda, API Gateway...etc.)\nExperience in WebSocket programming\nFamiliar with IaC such as Terraform, AWS CDK and Pulumi\nFamiliar with Nest.js\nFamiliar with K8S, Helm\nFamiliar with Git, Docker, CI/CD tools\nFamiliar with domain driven design", "employment_types": ["Full Time", "Permanent"], "selling_points": ["Excellent Career development in E-commerce", "Maintain a new era e-commerce web applications", "Experience in WebSocket programming"], "locations": ["Tseung Kwan O"], "categories": ["Information Technology (IT)", "Application Specialist - Software", "Software Development", "Technical Writing"], "post_time": "2022-01-11T00:42:16Z", "salary": {"currency": null, "max": null, "min": null, "period": "monthly", "term": null}, "salary_visible": false, "title_keywords": ["programmer"], "responsibilities": ["seo", "quality", "user experience", "design", "testing", "develop", "implementation", "maintain", "system design", "databases", "database", "application development"], "requirements": {"degrees": ["degree holder"], "majors": ["related disciplines", "it"], "languages": [], "language_level": [], "hard_skills": ["plus", "web application development", "agile", "e-commerce", "server", "c#", "java", "git", "code", "restful api", "seo", "aws", "sql", "typescript", "web applications", "react", "system design", "deployment", "programming", "databases", "css"], "soft_skills": ["agile", "hands-on", "thorough", "technical skills", "driven"], "languages_combined": []}, "experience_required": {"duration": ["2+ years"], "field": ["analytical", "system design", "writing", "programming", "application development"]}}, {"job_id": "100003009033735", "location_code": "hk", "company": "EAST ICT Limited", "job_title": "System Engineer / Server Engineer", "description": "Responsibilities:\n\nSupport sales team to drive infrastructure services business or opportunity, especially in\u00a0\u00a0Virtualization\u00a0,\u00a0\u00a0SAN Storage\u00a0\u00a0and\u00a0\u00a0Backup solutions\nResponsible for customer meeting, presentation, demo, proposal writing and preparing documentation\nProvide professional services on planning, design and integration services to fulfill customer's requirements\nBuild and maintain key customer technical operations relationships to facilitate the delivery of services.\nInput to development of process and procedures to facilitate the support of the customer.\nInput to the Service Transition process including the Planning, Change, Configuration, Release, Testing and Evaluation functions\nTechnical input to the Service Operation process including Event, Incident, Request and Problem management functions.\nTechnical input to the Continual Service Improvement process including operations Measurement and Reporting.\nAct as the Technical contact and escalation point in relation to delivery of all the client's Services at Customer site(s)\nReview operational data and compare it to design assumptions and make recommendations wherever appropriate.\nAble to communicate with customers and the client internal teams for technical service engagement and able to influence customer on the client's solutions and design\nMaintain technical documentation for the accounts\nParticipate on the customers Change Control Board as an expert storage advisor, including presentation and meeting with customer senior management.\nPerform other duties as required or directed by management\n\n\u00a0\u00a0Requirements:\n\nBachelor Degree holder in Computer Science or Information Technology, or relate discipline\nHolder of professional certifications is\u00a0PLUS\u00a0(e.g. VCP)\nITIL certified (preferred)\nMinimum 2 years working experience in System Integrator\u00a0\nPreviously worked for a technology vendor, software or Systems Integration Company or an IT Consultancy is an\u00a0advantage.\nTechnical knowledge on Virtualization, Server, SAN Storage and Backup Solutions\u00a0\nAdvanced Storage and Fabric Management experience\nOperating System Management experience (Windows, UNIX (HPUX, Solaris, Linux varieties) preferred), VMware and Hyper-V\nTrouble shooting skills related to connectivity and performance issues\nUnderstanding of virtualisation and replication\nUnderstand network presentation of storage, e.g. NAS, CIFS, NFS etc. and\u00a0multi-pathing software for each OS\nPossess the ability to resolve issues and conflicts, as well as be able to take ownership in challenging situations\nFluent spoken and written English and Chinese\nWilling to learn new technologies and strong problem solving skill\nGood communication skill and strong and strong inter-personal skills\nImmediately available is highly preferred\nLess experience will consider as\u00a0\u00a0System engineer\n\n\u00a0\u00a0If you are interested, please send your resume together with your current salary, expected salary, and date of availability to us via \u201cApply Now\u201d .\n\nOnly short-listed candidates will be notified. Personal data collected will be used for recruitment purpose only.\n\nAll applications applied through our system will be delivered directly to the advertiser and privacy of personal data of the applicant will be ensured with security.", "employment_types": ["Full Time"], "selling_points": [], "locations": ["Not Specified"], "categories": ["Information Technology (IT)", "Technical Writing", "Others"], "post_time": "2022-01-10T01:42:53Z", "salary": {"currency": null, "max": null, "min": null, "period": "monthly", "term": null}, "salary_visible": false, "title_keywords": ["server", "system engineer", "engineer"], "responsibilities": ["data", "operations", "design", "maintain", "evaluation", "senior management", "make recommendations", "control", "perform other duties", "configuration", "infrastructure", "measurement", "teams", "testing", "reporting", "management", "review", "procedures", "contact", "documentation", "communicate with", "sales team", "planning"], "requirements": {"degrees": ["bachelor degree holder"], "majors": ["computer science", "information technology"], "languages": ["english", "chinese"], "language_level": ["fluent"], "hard_skills": ["itil", "linux", "plus", "hyper-v", "vmware", "integration", "nas", "vendor", "problem solving", "os", "server"], "soft_skills": ["advanced", "communication skill", "willing to learn", "inter-personal skills", "problem solving skill", "presentation"], "languages_combined": [{"language": "english", "language_level": ["fluent"]}, {"language": "chinese", "language_level": ["fluent"]}]}, "experience_required": {"duration": ["minimum 2 years"], "field": ["management"]}}, {"job_id": "100003009033875", "location_code": "hk", "company": "CL Technical Services Ltd.", "job_title": "Vice President (Java, Banking, In-house)", "description": "Job Duties:\n\nSupervise Junior SA, SAP and AP to control the development process\nSurvey and analyze the business requirement to define the project segment and specification to design efficient system\nDesign efficient solutions and application systems\nTest the program and examine the test results to ensure they fulfill the system requirements\nPrepare and maintain system documentation\nProvide training to users in early stage of system implementation\nManage the application development and adhere to application methodology, rules, policies, procedures and deadlines\nProvide advice and guidance on complex matters from both technical and business perspectives\n\nJob Requirements:\n\nDegree holder in Computer science, information technology or related discipline\nAt least 7 years of relevant experience\nProven experience in system analysis and design\nProficient in Java, J2EE, Linux AIX, DB2, MongoDB and/or HTML5 environment\nPossession of banking business knowledge, various development tools (such as JUnit, UML, Gradle, SVN, Selenium, RAD, RTC) and/or Project management skills is an advantage\nSolid analytical and problem-solving skills\nGood communication in English and Chinese\n\nFor more job opportunity, please visit our website: www.clts.com\n\nThe personal information collected is strictly for recruitment purpose only.", "employment_types": ["Full Time"], "selling_points": ["Listed Company", "5 days work with stable working environment", "Competitive pay"], "locations": ["Central"], "categories": ["Information Technology (IT)", "IT Project Management / Team Lead", "IT Management", "Technical Writing"], "post_time": "2022-01-10T02:00:55Z", "salary": {"currency": null, "max": null, "min": null, "period": "monthly", "term": null}, "salary_visible": false, "title_keywords": ["vice president"], "responsibilities": ["ap", "provide training", "control", "guidance", "system documentation", "application development", "policies", "procedures", "implementation", "design", "maintain", "provide advice", "application systems"], "requirements": {"degrees": ["degree holder"], "majors": ["computer science", "information technology"], "languages": ["english", "chinese"], "language_level": ["good"], "hard_skills": ["linux", "java", "analysis", "project management", "problem-solving skills"], "soft_skills": ["problem-solving skills", "project management skills", "communication"], "languages_combined": [{"language": "english", "language_level": ["good"]}, {"language": "chinese", "language_level": ["good"]}]}, "experience_required": {"duration": ["at least 7 years"], "field": ["relevant experience", "design"]}}, {"job_id": "100003009028241", "location_code": "hk", "company": "CL Technical Services Ltd.", "job_title": "Junior Programmer / Programmer (.Net C#, in-house)", "description": "Job Duties:\n\nInvolved in the full Software Development Lifecycle (\u201cSDLC\u201d) from performing business requirement study, documentation, analysis, design, development, testing, and user training to commissioning of the system\nConduct user requirement analysis for the development/implementation of new systems\nAssist in the integration testing, system testing, User Acceptance Test and implementation activities\nWork with business partners during system implementation and manage post implementation support\n\nRequirements:\n\nHigh Diploma or above in Computer Science or related discipline\nAt least 2 years proven experience in system development and maintenance (Less experience will be considered as Junior Programmer)\nFamiliar with C#, MSSQL, MVC, ASP.NET, HTML5, Javascript, Excel Macro is required\nGood working attitude, presentation and communication skills\nHK Permanent Resident is required\n\nFor more job opportunity, please visit our website: www.clts.com\n\nThe personal information collected is strictly for recruitment purpose only.", "employment_types": ["Full Time"], "selling_points": ["Large scale project", "Multiple vacancies", "Competitive pay"], "locations": ["Kowloon Bay"], "categories": ["Information Technology (IT)", "Support", "Software Development", "Technical Writing"], "post_time": "2022-01-07T19:19:38Z", "salary": {"currency": null, "max": null, "min": null, "period": "monthly", "term": null}, "salary_visible": false, "title_keywords": ["programmer", "junior"], "responsibilities": ["user requirement", "commissioning", "software", "analysis", "systems", "implementation", "design", "testing", "documentation"], "requirements": {"degrees": ["high diploma or above"], "majors": ["computer science"], "languages": [], "language_level": [], "hard_skills": ["excel", "macro", "maintenance", "javascript", "mssql", "c#"], "soft_skills": ["communication skills", "good working attitude", "presentation"], "languages_combined": []}, "experience_required": {"duration": ["at least 2 years"], "field": ["maintenance", "system development"]}}, {"job_id": "100003009032776", "location_code": "hk", "company": "KOS International Limited", "job_title": "Research Analyst (Cryptocurrency)~Welcome Fresh Grad", "description": "About The Client\n\nOur client is a dynamic blockchain company which develops cutting-edge technology and they are looking for Research Analyst to join their team.\n\nJob Description\n\nDetermine, analyze, and interpret trends or patterns in complex data sets, and present findings as visualizations and reports\nCollaborate with the Product and Community Team to analyze user data and proactively provide actionable data insights to drive improvements\nSupport Product Managers to build knowledge base and conduct performance tracking of new features\nMonitor KPI and competitor movements to inform overall product strategy\nAssist with Business Development Team in liaising with external partners' collaboration and partnership\nStay informed on trends in DeFi and the crypto space, analyze product trends and conduct competitor research to formulate insights and strategies\n\n\nQualifications:\n\nDegree holder in Computer Science, Analytic, Finance, or related disciplines\nGood understanding of crypto-currency/blockchain-related terminologies and trends is a must\nAbility to synthesize data and develop meaningful conclusions and predictive insights\nUser-focused and product-driven mindset\nExcellent in presentation and good interpersonal skills\nExcellent command of English and Chinese with exceptional writing and research skills\nFresh graduate are welcome\n\nClick \"Apply Now\" to apply for this position or call Sharon Tsu at +852 3180 4950 for a confidential discussion. All information collected will be kept in strict confidence and will be used for recruitment purpose only.", "employment_types": ["Full Time", "Permanent"], "selling_points": ["Decentralized Finance", "Friendly Culture & Flexible Working Hours", "Competitive Salary"], "locations": ["Not Specified"], "categories": ["Information Technology (IT)", "Product Management / Business Analyst", "Technical Writing", "Others"], "post_time": "2022-01-07T16:37:47Z", "salary": {"currency": null, "max": null, "min": null, "period": "monthly", "term": null}, "salary_visible": false, "title_keywords": ["research analyst"], "responsibilities": ["collaborate with", "data", "monitor", "liaising with", "develop", "reports", "recruitment", "tracking"], "requirements": {"degrees": ["fresh graduate", "degree holder"], "majors": ["related disciplines", "finance", "computer science"], "languages": ["english", "chinese"], "language_level": ["excellent"], "hard_skills": ["blockchain", "inform", "dynamic", "crypto"], "soft_skills": ["confidence", "research skills", "focused", "cutting-edge", "driven", "dynamic", "interpersonal skills", "presentation"], "languages_combined": [{"language": "english", "language_level": ["excellent"]}, {"language": "chinese", "language_level": ["excellent"]}]}, "experience_required": {"duration": [], "field": []}}, {"job_id": "100003009032126", "location_code": "hk", "company": "JFE Consulting Limited", "job_title": "Java Analyst Programmer / System Analyst (up to $55K!!)", "description": "Exciting opportunities for IT professionals and FGs with passion to identify their career in the following industries:\u00a0\n\nBanking & Financial Services\nInsurTech\nInformation Technology\nTelecommunications\nProfessional Services\nShipping & Logistics\n\nResponsibilities\n\nInvolve in the Whole SDLC from requirement collection, system designation and implementation\nPrepare and maintain documentation(s)\nAssist in the quality assurance on project deliverable\nSupport System analyst and Project Manager\u00a0\n\nRequirements\n\nHD or above in Computer Science or IT related disciplines\nFor Analyst Programmer at least 2 years' experience\u00a0\nFor Senior Analyst Programmer 3 years' experience\u00a0\nWorking Experience in system integration:\nJava / J2EE / Spring\nPython, Node.js\nC# / VB.NET / ASP.NET\nReactjs, Angularjs, Vuejs\nReact Native, Flutter\nJava/Kotlin, Objective C, Swift\nPHP,\u00a0eCommerce", "employment_types": ["Full Time", "Permanent"], "selling_points": ["Generous Bonus, Double Pay, Annual leaves", "Competitive Salary and Great Benefits", "Awesome Opportunity and Career Path Development"], "locations": ["Not Specified"], "categories": ["Information Technology (IT)", "Application Specialist - Software", "Software Development", "Technical Writing"], "post_time": "2022-01-07T10:17:09Z", "salary": {"currency": null, "max": null, "min": null, "period": "monthly", "term": null}, "salary_visible": false, "title_keywords": ["analyst programmer", "system analyst"], "responsibilities": ["maintain", "quality", "implementation"], "requirements": {"degrees": [], "majors": [], "languages": [], "language_level": [], "hard_skills": ["java", "php", "swift", "python", "c", "react native", "spring", "integration", "kotlin", "c#"], "soft_skills": [], "languages_combined": []}, "experience_required": {"duration": ["at least 2 years", "3 years"], "field": []}}, {"job_id": "100003009032263", "location_code": "hk", "company": "Hong Kong Interbank Clearing Ltd", "job_title": "Permanent/Contract Architect/Senior Specialist/Specialist I(Application Development)\u2013Web Application", "description": "Major Responsibilities\nResponsible for development of strategic business initiatives as well as maintenance of existing application systems\nParticipate in designing, coding, testing, debugging, documenting and implementing computer programs\nProduce necessary documentation whenever applicable\nAnalyse and define user requirements\nDesign and develop systems specifications\nOn call for emergency production incidents and provide fire fighting support\nRequirements\nUniversity education with over 10 years\u2019 mission-critical system development experience preferably in the financial sector for Architect (Application Development); over 5 years\u2019 experience for Senior Specialist (Application Development); over 3 years\u2019 experience for Specialist I (Application Development)\nProficient in Java EE technologies and web-based development, particularly in EJB, XML, XSL, Servlets, JMS, HTML, JQuery, JavaScript, and SQL. Prior working experience in Spring, Jasper Reports, Hibernate, Websphere MQ, WAS, DB2 and X.509 will be a definite advantage\nStrong schema design and DB2 DBA background are desirable for the roles related to database design\nGood technical writing skill and prior working experience in banking sector is preferable\nGood command of written and spoken English and Chinese\n\n\nHow to Apply\nInterested parties please send your curriculum vitae stating your current and expected salaries, and the contact phone number to the Human Resources Division, Unit B, 25/F, MG Tower, 133 Hoi Bun Road, Kwun Tong, Kowloon\u00a0 by clicking the \"Apply Now\" button below.\nAll applications and personal information collected will be treated in strict confidence and only be used for the purpose of recruitment and selection.\u00a0 The information collected will be accessed by our authorized personnel only.\u00a0 Those applicants not contacted by the Human Resources Division within two months from their application date should consider their applications filed for future reference which will be retained for one year for possible future job matching, and will be destroyed after the expiry of one year.", "employment_types": ["Full Time", "Permanent"], "selling_points": [], "locations": ["Ngau Tau Kok"], "categories": ["Information Technology (IT)", "Application Specialist - Software", "Software Development", "Technical Writing"], "post_time": "2022-01-07T10:34:59Z", "salary": {"currency": null, "max": null, "min": null, "period": null, "term": null}, "salary_visible": false, "title_keywords": ["specialist", "senior specialist"], "responsibilities": ["business initiatives", "maintenance", "coding", "testing", "designing", "documentation", "application systems"], "requirements": {"degrees": [], "majors": [], "languages": ["english", "chinese"], "language_level": ["good command"], "hard_skills": ["java", "hibernate", "web", "jquery", "html", "writing skill", "sql", "javascript", "spring"], "soft_skills": ["writing skill"], "languages_combined": [{"language": "english", "language_level": ["good command"]}, {"language": "chinese", "language_level": ["good command"]}]}, "experience_required": {"duration": ["5 years", "10 years", "3 years"], "field": ["system development", "education", "banking sector", "writing", "application development", "financial"]}}, {"job_id": "100003009031020", "location_code": "hk", "company": "Andrew Found Limited", "job_title": "Mobile App / Full-stack Developer (20K-60K, Welcome Fresh Grad / Senior**)", "description": "Responsibilities:\n\nDevelop and handle on front-end/ back-end development\nCreate technical documentation and providing written knowledge transfer material\nAnalyze project requirements wisely and achieve the project goals\nMaintain and improve existing codebases and peer review code changes\n\nRequirements:\n\n\nHigh diploma or Degree in Computer Science / Engineering / related disciplines\nDevelopment experience in Java / JavaScript / NodeJS / React Native and related frameworks\nExperienced working in Web / Mobile development\u00a0\u00a0\nOther technical skills in one or more of the following areas would be advantageous: Kotlin, Spring framework, Hibernate framework, K8S technology, Docker, SQL, Magenta, Linux, AWS, hybrid\n*** Fresh graduates are also welcomed ***", "employment_types": ["Full Time", "Permanent"], "selling_points": ["Double Pay+Bonus, Dental & Medical Cover, 12AL UP", "Mobile/ Web Development in fin-tech firm/ projects", "Language of Java/ React Native/ NodeJS/ Javascript"], "locations": ["Wong Tai Sin Area"], "categories": ["Information Technology (IT)", "Application Specialist - Software", "Software Development", "Technical Writing"], "post_time": "2022-01-07T19:20:23Z", "salary": {"currency": null, "max": null, "min": null, "period": "monthly", "term": null}, "salary_visible": false, "title_keywords": ["developer"], "responsibilities": ["project requirements", "review", "develop", "maintain", "documentation"], "requirements": {"degrees": ["high diploma", "degree"], "majors": ["related disciplines", "engineering", "computer science"], "languages": [], "language_level": [], "hard_skills": ["linux", "java", "hibernate", "web", "aws", "sql", "mobile", "javascript", "react native", "spring", "kotlin"], "soft_skills": ["technical skills"], "languages_combined": []}, "experience_required": {"duration": [], "field": ["related", "development"]}}, {"job_id": "100003009032881", "location_code": "hk", "company": "IT Solutions Ltd.", "job_title": "Web Programmer - Government Department [Salary: $35K+] (T25)", "description": "We are searching\u00a0for high-calibre Web Programmers\u00a0to develop and manage the Government websites.\n\n\u00a0Responsibilities:\n\nImplement new Government websites and maintain existing websites.\nDevelop and manage thematic websites.\nManage and update web pages under government department purview.\nDesign and write small web application for web pages.\nHandle webcasting, blogs and other ad-hoc tasks.\nProvide technical support for using social media in publicity campaigns.\n\nRequirements:\u00a0\u00a0 \u00a0\n\nHighier Diploma or above in Computer Science or equivalent\n2 years+ IT work experience\n1 year experience in HTML, JavaScript and web programming.\n\nBenefits:\n\nAttractive remuneration will be offered to the successful candidates.\nExcellent opportunity to further develop your professional skills in the Public Sector.\n\nIf you are interested, please send your resume in MS Word format, specifying your availability, current and expected salaries to:\n\njobs @itsolutions.com.hk\n\nor\n\nPlease click the Apply Now button and attach your cv in MS Word Format, specifying your availability, current and expected salaries.\n\nPersonal data collected will be used for recruitment purposes only.\n\nIT Solutions Ltd.\n\nSuite 2102\n21/F Lucky Building\n39 Wellington Street\nCentral, Hong Kong\n\n(P.S. We do not process applications from overseas for this position)\u00a0", "employment_types": ["Full Time"], "selling_points": ["2 Years IT Experience with Salary $35+", "Web Programming: HTML, JavaScript", "Government Department"], "locations": ["North Point"], "categories": ["Information Technology (IT)", "Application Specialist - Software", "Software Development", "Technical Writing"], "post_time": "2022-01-08T04:00:27Z", "salary": {"currency": null, "max": null, "min": null, "period": "monthly", "term": null}, "salary_visible": false, "title_keywords": ["web programmer"], "responsibilities": ["social media", "technical support", "ad-hoc tasks", "design", "develop", "maintain"], "requirements": {"degrees": ["diploma or above"], "majors": ["computer science"], "languages": [], "language_level": [], "hard_skills": ["programming", "javascript", "web", "html"], "soft_skills": [], "languages_combined": []}, "experience_required": {"duration": ["1 year"], "field": ["it", "programming"]}}, {"job_id": "100003009025980", "location_code": "hk", "company": "BII Transit Systems (HK) Co., Limited", "job_title": "Software Engineer/ Programmer", "description": "What you will do\n\nYou will be working with our software team to participate in software development of our payment products and systems, as well as software maintenance of the existing systems of our customers.\u00a0 \u00a0\n\nResponsibilities:\n\nSoftware design and documentation\nSoftware implementation\nSystem integration and testing\n\n\u00a0To be considered for this role you will have:\n\nTertiary qualification in Computer Science or related discipline\nProficient in programming with C/C++, Python or other languages\nExperience in Linux is an advantage\nAble to write technical documentation\n\n\u00a0On a personal level you must also:\n\nBe self-motivated\nHave good problem-solving skill\nGood communication skill in both spoken and written English and Chinese\u00a0\n\nApplicant with less experiences will also be considered and graduates with programming experience are welcome to apply.\u00a0\n\nPlease send your full resume with current and expected salary, availability and contact numbers to the Human Resources Administrator, BII Transit Systems (HK) Co., Ltd. by clicking the \"Apply Now\" Bottom.\n\nWeb Site: www.biitt.hk\n\n\u00a0Personal data collected will be kept in strictly confidential and used for recruitment purpose only.", "employment_types": ["Full Time", "Permanent"], "selling_points": ["5-day work week, medical and dental insurance", "Double pay, 15 days annual leave", "Design and development"], "locations": ["Kowloon Bay"], "categories": ["Information Technology (IT)", "Software Development", "Technical Writing", "Others"], "post_time": "2022-01-06T06:57:34Z", "salary": {"currency": null, "max": null, "min": null, "period": "monthly", "term": null}, "salary_visible": false, "title_keywords": ["software engineer", "programmer"], "responsibilities": ["software", "maintenance", "systems", "implementation", "design", "testing", "communication", "payment", "recruitment", "contact", "documentation", "personal data"], "requirements": {"degrees": [], "majors": [], "languages": ["english", "chinese"], "language_level": ["good"], "hard_skills": ["linux", "integration", "maintenance", "c++", "web", "problem-solving", "python", "c", "programming", "documentation"], "soft_skills": ["problem-solving", "self-motivated", "communication skill"], "languages_combined": [{"language": "english", "language_level": ["good"]}, {"language": "chinese", "language_level": ["good"]}]}, "experience_required": {"duration": [], "field": ["programming"]}}, {"job_id": "100003009029999", "location_code": "hk", "company": "Sing Tao Management Services Limited", "job_title": "Senior Data Engineer / Data Engineer (New Media Business)", "description": "Responsibilities:\n\nImplement data platform architecture including big data, NoSQL and AI, and applications for providing data services to other systems and business users.\nGather business and data requirements\nResponsible for Data Ingestion\nTranslate requirements into data strategies and models\nWork closely with business / Technology teams to understand their needs and develop data-driven solutions\nDevelop reports, dashboards and other artifacts to communicate the analysis results to business users\nDevelop different data solutions as required by the business\nData warehouse architecture design\nETL development\nDefining data governance model to ensure data quality\n\nRequirements:\n\nBachelor in Computer Science, Engineering or Big Data or relevant disciplines\n2+ years of experience in data warehouse projects and development\nExperience with ETL development or Big Data Technologies, or Data Transformation, and modeling\nExperience in architecting and building scalable data platforms\nExperience in data governance\nExperience in Enterprise grade BI and reporting tools\nExperience with Cloud Technologies (Data Lake, Google, AWS etc.) or experience with open source technologies\nExperience with 2 of 4 - Java, Scala, R, and Python programming languages\nExperience with Big Query, SQL and/or NOSQL databases\nNeed to support the visualization e.g. DataStudio, Tabluea\nExperience in architecting and building scalable data platforms\nSelf-motivated,\u00a0able to work under dynamic work environment and flexible to changes\nWorking Location: Tseung Kwan O Industrial Estate\n\nInterested parties please click \u201cApply Now\" to submit your complete resume with\u00a0compensation history, expected salary and REFERENCE NUMBER or by\u00a0post to\u00a0Human Resources Department,\u00a03/F,\u00a0Sing Tao News Corporation Building, 7 Chun Cheong Street, Tseung Kwan O Industrial Estate, Tseung Kwan O, New Territories, Hong Kong\n\nWe are an equal opportunity employer and welcome applications from all qualified candidates. Information provided will be treated in strict confidence and only be used for recruitment related purpose. Applicant who is not invited for an interview within 6 weeks may consider their application not successful. All personal data of unsuccessful applicants will be destroyed within 6 months.\n\nwww.singtaonewscorp.com", "employment_types": ["Full Time", "Permanent"], "selling_points": [], "locations": ["Tseung Kwan O"], "categories": ["Information Technology (IT)", "Network & System", "Technical / Functional Consulting", "Technical Writing"], "post_time": "2022-01-07T06:35:09Z", "salary": {"currency": null, "max": null, "min": null, "period": "monthly", "term": null}, "salary_visible": false, "title_keywords": ["data engineer"], "responsibilities": ["systems", "architecture", "big data", "data"], "requirements": {"degrees": ["bachelor"], "majors": ["engineering", "computer science"], "languages": [], "language_level": [], "hard_skills": ["java", "bi", "data warehouse", "analysis", "aws", "scala", "sql", "dynamic", "programming", "databases", "python", "r"], "soft_skills": ["flexible", "self-motivated", "responsible", "dynamic", "driven"], "languages_combined": []}, "experience_required": {"duration": ["2+ years"], "field": ["sql", "development", "programming"]}}, {"job_id": "100003009030037", "location_code": "hk", "company": "Hong Kong Baptist University", "job_title": "Senior AI Research Engineer / AI Research Engineer (PR0443/21-22)", "description": "AUGMENTED CREATIVITY LAB\n\nSenior AI Research Engineer / AI Research Engineer (in the rank of Research Fellow / Senior Research Assistant / Research Assistant) (PR0443/21-22)\n\nThe Augmented Creativity Lab at Hong Kong Baptist University invites applications for the Senior AI Research Engineer / AI Research Engineer position. The selected candidates will work with a group of renowned interdisciplinary researchers, focusing on an AI-based Art Tech project addressing human-machine co-creativity research. More information about the project could be found at https://research.hkbu.edu.hk/highlighted-projects/building-platform-technologies-for-symbiotic-creativity-in-hong-kong.\n\nThe appointees are expected to perform the following roles:\nDevelop new algorithms for AI art content generation using Deep Learning;\nDevelop demo/system/platform of symbiotic performance incorporating with AI system engineer, AI scientist and artist; and\nWrite paper/patent and release open source code.\nPotential candidates should have/be:\n\nPhD or master\u2019s degree in Computer Science, Electronic Engineering, Information Engineering, Mathematics or relevant disciplines with substantial years of related experience. Candidates with less experience but with strong research record may also be considered;\nSolid R&D experience in one or more of the following domains: content generation, NLP, computer vision, etc.;\nFamiliar with deep learning/algorithms, especially on foundation model, transformer model, GANs, GNNs, RL, etc.;\nFamiliar with deep learning frameworks of PyTorch/TensorFlow, GPU programming of CUDA. Knowledge of Mindspore is a plus;\nSolid coding skills in Python/C/C++/Java;\nStrong self-motivation and be able to work independently;\nStrong communication skills, the ability to communicate effectively and manage relationships with stakeholders coming from both technical and non-technical backgrounds; and\nFluent in English, good written and oral communication skills.\nInitial appointment will be offered on a fixed-term contract of two years. Re-appointment thereafter will be subject to mutual agreement and availability of funding.\n\nRank and salary will be commensurate with qualifications and experience.\n\nApplication Procedure:\n\nApplications are invited to submit their applications at the HKBU e-Recruitment System (jobs.hkbu.edu.hk). Those not invited for interview 4 months after submission of application may consider their applications unsuccessful. Details of the University\u2019s Personal Information Collection Statement can be found at http://hro.hkbu.edu.hk/pics.\n\nThe University reserves the right not to make an appointment for the posts advertised, and the appointment will be made according to terms and conditions then applicable at the time of offer.\n\nReview of applications is ongoing until the positions are filled.", "employment_types": ["Full Time"], "selling_points": ["PhD or master\u2019s degree", "Solid R&D experience", "Develop new algorithms"], "locations": ["Kowloon City"], "categories": ["Information Technology (IT)", "DBA", "Technical Writing", "Data Scientist"], "post_time": "2022-01-07T06:39:58Z", "salary": {"currency": null, "max": null, "min": null, "period": "monthly", "term": null}, "salary_visible": false, "title_keywords": ["engineer"], "responsibilities": ["review", "coding", "develop", "communication", "recruitment"], "requirements": {"degrees": ["degree", "master"], "majors": ["mathematics", "engineering", "computer science"], "languages": ["english"], "language_level": ["good", "fluent"], "hard_skills": ["r&d", "plus", "java", "c++", "ai", "cuda", "make", "c", "programming", "python", "code"], "soft_skills": ["communication skills", "work independently", "oral", "deep", "self-motivation", "learning"], "languages_combined": [{"language": "english", "language_level": ["fluent", "good"]}]}, "experience_required": {"duration": [], "field": ["related", "research", "engineering"]}}, {"job_id": "100003009032883", "location_code": "hk", "company": "IT Solutions Ltd.", "job_title": "Risk Management Projects: Python Analyst Programmer / Programmer - Major Bank", "description": "We are searching\u00a0for a high-calibre Python\u00a0Analyst Programmers /\u00a0Programmers\u00a0 to work on Major Risk Management Projects - Anti-Money Laundering System (AML)\u00a0in a Major Bank.\n\nResponsibilities:\n\nSystem Analysis, Design and Programming of Anti Money Laundering Projects.\nManaging Data Warehouse analytics application using Python.\n\nRequirements:\n\nDegree in Computer Science or related fields.\n1-3 years experience in machine learning using Python or other similar tools.\nBanking experience is highly preferred.\nFresh Graduates are welcome to apply.\n\nBenefits:\n\nAttractive remuneration will be offered to the successful candidates.\nExcellent opportunity to further develop your professional skills in the Major Bank.\n\nIf you are interested, please send your resume in MS Word format, specifying your availability, current and expected salaries to:\n\njobs @itsolutions.com.hk\n\nor\n\nPlease click the Apply Now button and attach your cv in MS Word Format, specifying your availability, current and expected salaries.\n\n\n\nPersonal data collected will be used for recruitment purposes only.\n\n\n\nIT Solutions Ltd.\nSuite 2102\n21/F\u00a0Lucky Building\n39\u00a0Wellington Street\nCentral, Hong Kong\u00a0\n\n(P.S. We do not process applications from overseas for this position)", "employment_types": ["Full Time", "Contract"], "selling_points": ["Machine Learning using Python", "Anti-Money Laundering System (AML) Projects", "Develop professional IT skills in a Major Bank"], "locations": ["Not Specified"], "categories": ["Information Technology (IT)", "Application Specialist - Software", "Software Development", "Technical Writing"], "post_time": "2022-01-08T04:00:07Z", "salary": {"currency": null, "max": null, "min": null, "period": "monthly", "term": null}, "salary_visible": false, "title_keywords": ["analyst programmer", "programmer"], "responsibilities": ["analysis", "design", "data"], "requirements": {"degrees": ["degree"], "majors": ["computer science"], "languages": [], "language_level": [], "hard_skills": ["python"], "soft_skills": ["learning"], "languages_combined": []}, "experience_required": {"duration": ["1-3 years"], "field": ["banking experience"]}}, {"job_id": "100003009031901", "location_code": "hk", "company": "REC Engineering Company Limited", "job_title": "Analyst Programmer (Java, SQL Server) Over", "description": "Responsibilities\n\nTo provide technical support for the development of requirement specification and implementation proposal during the System Analysis Design and overall technical testing and deployment of application during the System implementation, on areas including coordination with user and other system support team on the system development, program coding, program bug fixing and unit testing, Quality assurance of deliverables from outsourcing vendors, inventory management, support User Acceptance Testing, etc.\nRequirement Details\n\nDegree or above in Information Technology / Computer Science\n3 years\u2019 experience in Application /System development\nSolid working experience in Java and SQL Server\nSelf motivated, good communication skill and able to work independently\nProficiency in both spoken and written English & Cantonese\nIf interested for the above position, please send detailed resume with current and expected salary as well as date of availability by sending email to\u00a0[via APPLY NOW]\n\nFor more job opportunity, please visit our website: www.clts.com\n\nThe personal information is collected strictly for recruitment purpose only.", "employment_types": ["Full Time"], "selling_points": ["To provide technical support", "Degree or above", "3 years\u2019 experience"], "locations": ["Not Specified"], "categories": ["Information Technology (IT)", "Support", "Technical / Functional Consulting", "Technical Writing"], "post_time": "2022-01-07T09:55:38Z", "salary": {"currency": null, "max": null, "min": null, "period": "monthly", "term": null}, "salary_visible": false, "title_keywords": ["analyst programmer", "server"], "responsibilities": ["technical support", "analysis", "coordination with", "quality", "implementation", "design", "testing", "coding", "inventory management"], "requirements": {"degrees": [], "majors": [], "languages": [], "language_level": [], "hard_skills": [], "soft_skills": [], "languages_combined": []}, "experience_required": {"duration": [], "field": []}}, {"job_id": "100003009024366", "location_code": "hk", "company": "LiquidStack Limited", "job_title": "Technical Writer (Liquid Immersion Cooling)", "description": "POSITION SUMMARY\n\nReporting to the Documentation and Electronics Engineer of LiquidStack, this role is responsible for the creation of standard technical documentation including but limited to operation manuals, service manuals, and work instructions. The individual will focus heavily on the drafting of patents and the overall IP/patent portfolio of the company. This role will work closely with the engineering team and cross-functionally with the legal team. The role will learn new technologies that will improve and shape the data center industry. We are looking for a passionate and driven individual within the profession who wants to be a key team member on one of the world\u2019s global leaders in liquid cooling for data centers, edge, and high-performance computing.\n\nESSENTIAL DUTIES AND RESPONSIBILITIES\n\nOutlines, writes, and edits new and existing technical/service manuals, presentations, and work instructions.\nDocuments test procedures and results. Works closely with internal teams to understand project and documentation requirements.\nProduces high-quality documentation that meets applicable standards and is appropriate for its intended audience.\nPrepares patent specifications and works with the legal team on patent drafts, art search and support other patent applications tasks.\nActs in a manner consistent with LiquidStack\u2019s core values and according to LiquidStack\u2019s Code of Business Conduct and Ethical Behavior.\nComplies with standards and procedures of LiquidStack\u2019s health and safety manual and Occupational Health and Safety regulations.\n\nSPECIFIC KNOWLEDGE, SKILLS AND ABILITIES\n\nBachelors degree in Engineering/Mechanical Engineering or an equivalent background would be preferred.\nA minimum of 5 years\u2019 proven work experience in technical documentation writing.\nWork experience or exposure in patent research and writing is an asset.\nAbility to explain and describe new technologies in a way that is concise and descriptive.\nSelf-starter that can be hands-on and work independently.\u00a0\nMust have strong planning, organizational, analytical and problem-solving skills.\nAble to prioritize completing tasks and keeping to critical deadlines.\nAttention to detail with the ability to see the bigger picture.\nMulticultural approach, comfortable working with diverse cultures and mind-sets.\nAppreciation to work in a global organization with teammates in different time zones/regions.\nExcellent communication (verbal & written) with proven ability of producing comprehensive documents with a focus on accuracy.\nProficient in English (native preferred), fluency in Cantonese is a strong plus.\nProficient in MS Word, Excel, Powerpoint, and Adobe illustrator and Photoshop is required.\nKnowledge in Adobe InDesign and SolidWorks eDrawings is preferred.", "employment_types": ["Full Time"], "selling_points": ["Exciting Climate Conscious Technology", "Company Equity (Restricted Share Units) Offered", "Annual Performance Incentive Plan"], "locations": ["Tsuen Wan Area"], "categories": ["Engineering", "Others", "Information Technology (IT)", "Technical Writing", "Sciences, Lab, R&D", "Research & Development (R&D)"], "post_time": "2022-01-05T18:02:22Z", "salary": {"currency": null, "max": null, "min": null, "period": "monthly", "term": null}, "salary_visible": false, "title_keywords": [], "responsibilities": ["regulations", "reporting", "data", "procedures", "teams", "presentations", "quality", "communication", "specifications", "documentation", "planning"], "requirements": {"degrees": ["degree"], "majors": ["engineering", "mechanical engineering"], "languages": ["cantonese", "english"], "language_level": ["fluency", "native", "proficient"], "hard_skills": ["excel", "plus", "problem-solving skills", "adobe indesign", "presentations", "powerpoint", "adobe illustrator", "ip", "photoshop", "documentation", "code", "focus", "solidworks", "ms word"], "soft_skills": ["passionate", "work independently", "responsible", "able to prioritize", "organizational", "communication", "diverse", "hands-on", "comprehensive", "ethical", "attention to detail", "problem-solving skills", "focus", "team member", "driven"], "languages_combined": [{"language": "cantonese", "language_level": ["fluency", "native", "proficient"]}, {"language": "english", "language_level": ["fluency", "native", "proficient"]}]}, "experience_required": {"duration": ["minimum of 5 years"], "field": ["research", "writing"]}}, {"job_id": "100003009026287", "location_code": "hk", "company": "MRC (HRMS) Limited", "job_title": "Backend Programmer / Analyst Programmer (.NET Core / MSSQL / C#) (Fresh graduates also welcome)", "description": "MRC\u00a0is looking for a resourceful, experienced Backend Programmer/Analyst Programmer to join our development team. The candidate will be responsible for development and enhancement of our HRMS products.\n\nJob Responsibilities:\n\nResponsible for development and enhancement on HRMS product and related tools.\nResponsible for 3rd\u00a0party integration and new feature development.\nCompile internal technical document and perform internal user training.\nWorking with system consultation team on technical assistance for client\u2019s requirement and bug fixing.\n\nJob Requirements\uff1a\n\nDiploma or above in Computer Science, Information Technology or equivalent discipline.\nSolid experience in C# and .NET Core framework.\nKnowledge in SQL server, Crystal Report, Stimulsoft Report or Angular is an advantage\nGood communication skill in both English and Chinese\nStrong interpersonal, analytical and independent problem-solving skills.\nMore than 3 years IT working experience will be considered as Analyst Programmer\nLess experience or fresh graduates also welcome and considered as Programmer)\n\n\n**Interested parties, please send\u00a0full resumes\u00a0with\u00a0current and expected salary\u00a0by clicking \u201cAPPLY NOW\u201d to apply.**\n\nAll Information collected will be treated in strict confidence and used solely for recruitment purpose only.\u00a0 Only shortlisted candidates will be notified.\u00a0 If candidates are not received our notification within 6 weeks, their application will be considered to be unsuccessful.\u00a0 All information of unsuccessful application will be destroyed within 6 months.", "employment_types": ["Full Time", "Permanent"], "selling_points": [], "locations": ["Lai Chi Kok"], "categories": ["Information Technology (IT)", "Software Development", "Network & System", "Technical Writing"], "post_time": "2022-01-06T07:52:56Z", "salary": {"currency": null, "max": null, "min": null, "period": "monthly", "term": null}, "salary_visible": false, "title_keywords": ["analyst programmer", "programmer"], "responsibilities": ["technical assistance"], "requirements": {"degrees": ["diploma or above"], "majors": ["computer science", "information technology"], "languages": ["english", "chinese"], "language_level": ["good"], "hard_skills": ["sql", "angular", "server", "problem-solving skills", "c#"], "soft_skills": ["problem-solving skills", "communication skill", "independent", "interpersonal"], "languages_combined": [{"language": "english", "language_level": ["good"]}, {"language": "chinese", "language_level": ["good"]}]}, "experience_required": {"duration": ["3 years"], "field": ["it"]}}, {"job_id": "100003009025444", "location_code": "hk", "company": "APRIL Hong Kong Limited", "job_title": "Regional Application System Analyst", "description": "For over 30 years, APRIL International Care has been specializing in international health insurance solutions. We design, distribute, and manage insurance plans and assistance services for individuals and businesses. With teams across Asia, Europe, and America, we look after our members wherever they are to make sure they access proper care. We are part of the APRIL Group, a global insurance specialist with 2,300 staff in 16 countries.\n\n\u00a0To sustain the growth of the company as the expansion of our services, we are currently looking for an\n\n\u00a0Application Support Analyst\n\nJob Description\n\nA self-starter who enjoys contributing to maintaining and improving the company\u2019s IT ecosystem and helping the company's operations run smoothly.\n\nThe APRIL Group is fast growing. This position is an ideal place to start with us and get a deep understanding of large-scale IT Insurance systems and evolve toward a wide array of both technical and project-based positions.\n\nMain Activities\n\nSupport of the configuration for the back-end system [training will be provided]\nFollow up of corrective and evolutive application update with the third-party provider (SDLC)\nSupport business needs, using scripting abilities\nWrite elementary database queries (advanced skills are welcomed)\n\nTo be successful in this role, you will need to be structured and organised to respond promptly to service issues and requests.\u00a0\n\nYou have the following profile:\n\nA bachelor\u2019s degree in IT or any related field.\nYou have a few years of programming.\nExperience supporting large scale, 24/7, real-time mission-critical systems.\nProven experience in System API Integration and EDI.\nPassion to experiment and learn new technologies (e.g., exposure to Python, GraphQL).\nGood Knowledge of MS SQL, GraphQL is a plus.\nOutstanding coding, debugging and analytical skills: Core problem-solving skills, ability to analyse available data and potential solutions.\nGreat communication skills. You will work closely with end-users to understand their needs and deliver the results. You are fluent in English.\n\nEven better if you have:\n\nUsed JIRA/ Jira service desk (or any Atlassian solutions)\nAn experience in source control systems such as Git\nWorking experience with insurance back-end system\n\n\u00a0Contact:\n\nIf you are interest in this\u00a0position, please send your\u00a0CV to us with expected salary by clicking APPLY NOW or\u00a0click this\u00a0link\u00a0to\u00a0https://aprilinternationalasia.bamboohr.com/jobs/view.php?id=131\n\nPersonal data collected will be used for recruitment purpose only.", "employment_types": ["Full Time", "Permanent"], "selling_points": [], "locations": ["Central"], "categories": ["Information Technology (IT)", "Software Development", "Technical Writing", "Insurance", "Others"], "post_time": "2022-01-06T04:33:09Z", "salary": {"currency": null, "max": null, "min": null, "period": "monthly", "term": null}, "salary_visible": false, "title_keywords": ["system analyst"], "responsibilities": ["control", "maintaining", "data", "configuration", "operations", "systems", "teams", "design", "coding", "communication", "recruitment", "contact", "database", "plans", "personal data", "insurance", "support business needs", "analyse"], "requirements": {"degrees": ["degree", "bachelor"], "majors": ["it"], "languages": ["english"], "language_level": ["fluent"], "hard_skills": ["plus", "git", "python", "analytical skills", "make", "sdlc", "programming", "integration", "problem-solving skills", "ms sql"], "soft_skills": ["communication skills", "advanced", "ability to analyse", "deep", "analytical skills", "organised", "problem-solving skills", "structured", "ideal"], "languages_combined": [{"language": "english", "language_level": ["fluent"]}]}, "experience_required": {"duration": [], "field": ["insurance"]}}, {"job_id": "100003009032133", "location_code": "hk", "company": "Michael Page", "job_title": "Analyst Programmer / System Analyst - Java ,Bank", "description": "One of most well-established banks is looking for a system analyst to be part of their IT Team and the key member in re-innovate their platform\n\nClient Details\n\nMy client is one of the most well-established banks in Hong Kong. They are at the critical phase of having active system innovation and transformation to handle their rapid expansion of user base. They are currently looking for Analyst Programmer/System Analyst with Banking experience to handle their transformation project.\n\nDescription\n\nCollaborate with cross functional teams, user experience designers, project managers, product managers, functional owners and engineers across the company, architect and building and enhance digital product on a project basis.\nHands on development on building scalable applications using RESTful Services, Java/J2EE, Oracle and related technologies\nResponsible for scalable, reusable highly available (Cloud-based) architecture that, with consideration to security and performance\nOverseeing the implementations of releases and to ensure a complete and on-time and on-quality build\n\nProfile\n\nDegree holder in IT, Computer Science or related discipline\nProven experience in System development\nExperience in Java, J2EE, Spring Boot\nFamiliar with Loan System\nGood command in English and Cantonese\n\nJob Offer\n\nCompetitive salary package\nStable Working Environment\nPerm Position\n\nTo apply online please click the 'Apply' button below. For a confidential discussion about this role please contact Astra To on +852 2848 9547.", "employment_types": ["Full Time", "Permanent"], "selling_points": ["Java ,Tier 1 Retail Bank", "Stable Working Environment , Perm", "Loan System"], "locations": ["Not Specified"], "categories": ["Information Technology (IT)", "Application Specialist - Software", "Software Development", "Technical Writing"], "post_time": "2022-01-07T10:17:51Z", "salary": {"currency": null, "max": null, "min": null, "period": "monthly", "term": null}, "salary_visible": false, "title_keywords": ["analyst programmer", "system analyst"], "responsibilities": ["collaborate with", "teams", "user experience", "quality", "contact", "banking", "architecture"], "requirements": {"degrees": ["degree holder"], "majors": ["it", "computer science"], "languages": ["cantonese", "english"], "language_level": ["good command"], "hard_skills": ["java", "oracle", "spring", "rapid"], "soft_skills": ["hands on", "active", "stable", "responsible"], "languages_combined": [{"language": "cantonese", "language_level": ["good command"]}, {"language": "english", "language_level": ["good command"]}]}, "experience_required": {"duration": [], "field": ["digital", "system analyst", "banking experience", "system development"]}}, {"job_id": "100003009023592", "location_code": "hk", "company": "TuoFan IT Limited", "job_title": "UI / UX Designer", "description": "Job Highlights\n2 years+ experience in a UI/UX-related field\nSocial Media, Blockchain, DeFi platform\nYoung & energetic team, innovative startup culture\n\nJob Description\n\nResponsibilities:\n\nMaintain the consistency and sustainability of our visual design system.\nCollaborate with product managers, developers, and cross-functional stakeholders to understand requirements, and provide creative, thoughtful solutions.\nCommunicate concepts with storyboards, wireframes. Guide design and development with high-fidelity phototype.Work with IT team.\n\nRequirements:\n\nMinimum2-year experience in UI/UX-related field, social media experience is an advantage.\nSolid UI design experience on cross platform, familiarity with technical constraints and limitations on Desktop, mobile web, android and IOS.\nProficiency in design tools, Adobe Creative Suite, figma etc.\nPragmatic Thinking.\nGood communication skills.\nSelf-motivated, Excellent problem-solving skills.\n\nInterested parties are invited to send full resume stating contact telephone number, date available, present and expected salary to our recruitment email address.", "employment_types": ["Full Time"], "selling_points": [], "locations": ["Tsuen Wan Area"], "categories": ["Information Technology (IT)", "Technical Writing", "Others", "UI/UX Designer"], "post_time": "2022-01-05T09:13:47Z", "salary": {"currency": null, "max": null, "min": null, "period": "monthly", "term": null}, "salary_visible": false, "title_keywords": ["ux designer"], "responsibilities": ["collaborate with", "design", "maintain", "visual", "storyboards"], "requirements": {"degrees": [], "majors": [], "languages": [], "language_level": [], "hard_skills": ["web", "mobile", "problem-solving skills", "adobe creative suite", "android"], "soft_skills": ["problem-solving skills", "communication skills", "self-motivated", "creative"], "languages_combined": []}, "experience_required": {"duration": [], "field": ["related", "social media", "design"]}}, {"job_id": "100003009024909", "location_code": "hk", "company": "Loscam (Asia Pacific) Co., Limited", "job_title": "Senior Technical Analyst", "description": "This role will work alongside the IT infrastructure team to provide technical support related to IT technologies across the business. The IT Operations Analyst is responsible for handling service desk tasks and maintaining ongoing availability of the computer and network environment.\n\nJob Responsibilities:-\n\nActively provide support to internal users and drive positive IT service culture and satisfaction\nMonitor IT infrastructure and ensure maximum availability of production environment by providing effective support\nMaintain and improve service desk system, documenting IT related problems and solutions on the technical database\nTroubleshooting and repairing hardware, software and infrastructure\nProvide Support and participate in IT projects including upgrades, migrations and outage.\nFollowing ITIL to define IT standards and processes\nProvide training to users\nImplementing and administering security systems\nJob Requirements:-\n\nDegree or relevant work experience\nMinimum of 5 years\u2019 relevant experience\nFluent in Chinese and English\nExcellent communication skills and demonstrate exceptional customer service\nCan work independently and as a good team player\nExperience with Azure cloud technologies, Windows infrastructure, virtual environment, MDM and FortiGate security devices\nExcellent diagnostic and resolution skills\nAbility to prioritize tasks and deliver within agreed timeline\nAbility to travel occasionally\nA competitive remuneration package including 5-day work, double pay, medical insurance and other employee benefits will be offered to the right candidate.\u00a0 Please send your detailed resume, current & expected salary by clicking \"Apply Now\".\n\n(All information received will be kept in strictly confidence and will be used for employment related purpose only.)", "employment_types": ["Permanent"], "selling_points": [], "locations": ["Sheung Wan"], "categories": ["Information Technology (IT)", "Support", "Network & System", "Technical Writing"], "post_time": "2022-01-06T02:53:22Z", "salary": {"currency": null, "max": null, "min": null, "period": "monthly", "term": null}, "salary_visible": false, "title_keywords": ["analyst"], "responsibilities": ["migrations", "provide training", "provide support", "it service", "it infrastructure", "software", "upgrades", "infrastructure", "monitor", "troubleshooting", "systems", "hardware", "maintain", "database"], "requirements": {"degrees": ["degree"], "majors": [], "languages": ["english", "chinese"], "language_level": ["fluent"], "hard_skills": ["azure"], "soft_skills": ["communication skills", "work independently", "good team player", "confidence", "prioritize", "customer service", "detailed"], "languages_combined": [{"language": "english", "language_level": ["fluent"]}, {"language": "chinese", "language_level": ["fluent"]}]}, "experience_required": {"duration": ["minimum of 5 years"], "field": ["infrastructure", "relevant experience", "security"]}}, {"job_id": "100003009023946", "location_code": "hk", "company": "Data World Solutions Limited", "job_title": "Analyst Programmer / Programmer (5 days)", "description": "Responsibilities\n\nManage and perform software development of business management applications (user requirements study, system analysis and design, programming, testing, documentation, report writing and support)\n\nGeneral Requirements\n\nDiploma, \u00a0Higher Certificate or Degree in Software Engineering, Computing, or related disciplines\nGood communication, \u00a0presentation and problem solving skills\nProficient in written and spoken English and Chinese (Cantonese)\nIndependent, initiative, mature, self-motivated, and result-oriented\n\nExperience Requirements\n\nMinimum 2 years of solid and relevant experience in software development\nFamiliar with SQL, Python, Excel VBA, C#, ASP.NET, JQuery, Ajax, Java Script, XML, HTML and Crystal Report\nKnowledge on ERP / CRM is preferrable.\nApplicant with less experience may be considered as Programmer\nInterested parties please apply with your full resume with expected salary and quote (Ref: DWS-APP-20211214-0501). For more information about us, please visit our website\u00a0dws.dataworld.com.hk\u00a0\n(Personal data collected will be used for recruitment purpose only)", "employment_types": ["Full Time", "Permanent"], "selling_points": ["Programmer", "Analyst Programmer", "Software Development, SDLC"], "locations": ["Kwai Hing"], "categories": ["Information Technology (IT)", "Software Development", "Testing / QA", "Technical Writing"], "post_time": "2022-01-05T10:05:24Z", "salary": {"currency": null, "max": null, "min": null, "period": "monthly", "term": null}, "salary_visible": false, "title_keywords": ["analyst programmer", "programmer"], "responsibilities": ["management", "software", "analysis", "design", "testing", "documentation", "report"], "requirements": {"degrees": ["diploma", "degree", "higher certificate"], "majors": ["related disciplines", "software engineering"], "languages": ["cantonese", "english", "chinese"], "language_level": ["proficient"], "hard_skills": ["excel", "vba", "java script", "jquery", "html", "erp", "sql", "ajax", "python", "problem solving skills", "c#"], "soft_skills": ["result-oriented", "self-motivated", "independent", "presentation", "mature", "communication", "problem solving skills", "initiative"], "languages_combined": [{"language": "cantonese", "language_level": ["proficient"]}, {"language": "english", "language_level": ["proficient"]}, {"language": "chinese", "language_level": ["proficient"]}]}, "experience_required": {"duration": ["minimum 2 years"], "field": ["relevant experience", "software development"]}}, {"job_id": "100003009022469", "location_code": "hk", "company": "Green Tomato Limited", "job_title": "Senior Business Designer (UX Writing)", "description": "We are hiring talents like you!\n\nWe are seeking an entrepreneurial Copywriter to join our rapidly growing clients in the Fintech Industry. You will work closely with the members of the project team at all levels to generate and execute concepts for digital experiences on mobile application and / or website. \u00a0You\u2019ll be expected to actively contribute to the development of original solutions and create polished, final deliverables. A solid familiarity with trends in online marketing and the interactive digital space is required. You\u2019ll work directly with senior level practitioners and collaborate with various disciplines\u2014including visual design, experience design, product, and development teams\u2014to drive a point of view for end-user facing solutions. We look for people who are passionate about what they do and thrive working with other smart people to solve the toughest design challenges.\n\n\n\nYou will do the following in this job:\u00a0\n\n\nCollaborating with creative team members to determine the conceptual and copy direction of digital products\nWorking with senior creative or project leads to ensure copy tone and style are consistent across the customer experience\nInteracting with project teams to understand business objectives and constraints.\nPartnering with a content strategist in reviewing and translating business requirements and technical mandatories into clear, concise, and actionable copy in English and Chinese that's enjoyable for readers\nCollaborating with experience designers on user flows and visual designers on page layouts, always advocating for best user experience for audiences\nTracking copy changes\u2014and across multiple projects\n\nWe are looking for you if you are:\n\n\n3+ years in an advertising or marketing agency or media (interactive, digital) are preferred\nExceptional portfolio that demonstrates conceptual thinking\nStrong understanding of UX principles and how it relates copy\nOutstanding writing skills, including the ability to write in a range of voices and styles\nFamiliar and successful in both marketing and transactional style writing\nAcute attention to detail within demanding deadlines\nExperience writing alt-text for screen readers\nPrevious experience creating digital experiences and/or experience in Financial Services a plus\nExperience working in structured, client-facing copy decks preferred\n\nYou will enjoy:\n\n5-day work week\nCompetitive remuneration\nDiscretionary Bonus\nBirthday Leave\nMedical Allowance\nHappy and harmonious working environment\nValuable working experience\n\nWe offer an attractive remuneration package, comprehensive on the job training on new technologies, and excellent career development opportunities to the right candidate.\u00a0\n\nFinal and Most Important Requirement\n\n\n\"Enjoy What You Do!!\"\u00a0\n\n\nInterested applicants, please click APPLY NOW\u00a0to submit your application.\n\n\nCandidates not contacted within 4 weeks may consider their application for this role unsuccessful. Unless advised otherwise, unsuccessful candidates will be kept on file for future job opportunities. Personal data collected will be used for recruitment-related purposes only and all personal data of applicants will be kept in strict accordance with the Personal Data Privacy Ordinance.\n\n", "employment_types": ["Full Time", "Permanent"], "selling_points": ["UX Copywriter in Fintech industry", "3+yrs exp in advertisement/mkt agency/media", "Good career development"], "locations": ["Kwun Tong"], "categories": ["Media & Advertising", "Editorial / Journalism", "Information Technology (IT)", "Technical Writing", "Marketing / Public Relations", "Public Relations - Copy-writing"], "post_time": "2022-01-05T05:39:43Z", "salary": {"currency": null, "max": null, "min": null, "period": "monthly", "term": null}, "salary_visible": false, "title_keywords": ["designer"], "responsibilities": ["collaborate with", "advertising", "teams", "website", "design", "user experience", "recruitment", "career development", "visual", "multiple projects", "personal data", "tracking"], "requirements": {"degrees": [], "majors": [], "languages": ["english", "chinese"], "language_level": [], "hard_skills": ["mobile", "visual design", "writing skills", "plus"], "soft_skills": ["harmonious", "writing skills", "clear", "comprehensive", "attention to detail", "structured", "creative", "client-facing", "passionate about"], "languages_combined": [{"language": "english", "language_level": []}, {"language": "chinese", "language_level": []}]}, "experience_required": {"duration": [], "field": ["development", "design", "financial services", "writing", "digital", "client-facing", "team"]}}, {"job_id": "100003009026565", "location_code": "hk", "company": "Page Group Hong Kong", "job_title": "Senior Business Analyst - Signature Cloud Program", "description": "It's an excellent opportunity to join in one of a top leader in its industry in the world. Due to a large revamp programme for cloud transformation, they are now looking for an experienced business analyst to acts as an intermediate between user and IT Team. Applicant should have strong business analyst skillset including user stories, requirement and so on. Meanwhile, applicants would also require solid cloud project experience.\n\n\u5ba2\u6237\u7b80\u4ecb\n\nOur client is one of a market dominant in the industries for its business. Currently, they are having cloud transformation projects. They are now seeking for a skillful business analyst to their IT team and acts as an intermediate between stakeholders. The candidate will have an excellent exposure on its challenging projects and roles.\n\n\u5de5\u4f5c\u5185\u5bb9\n\nResponsible for:\n\nGathering business requirement and analyst\nActs as liaison among stakeholders including IT and user\nDefining and documenting functional and non-functional requirement\nFully engage with agile/scrum project methodology\n\n\u7406\u60f3\u7684\u6c42\u804c\u8005\n\nQualifications:\n\nDegree holder in Computer Science or Information Technology\nMore than 5 years experience as business analyst, especially for cloud transformation projects\nAgile projects exposure is a must\nProficient in both written and spoken English\nEligible to work in Hong Kong\nImmediately available is preferred\n\n\u798f\u5229\u5f85\u9047\n\nLarge organisation exposure\nNice working environment\nTeam Spirit\nEngage with one of the signature projects in cloud\nGood atmosphere\n\nTo apply online please click the 'Apply' button below. For a confidential discussion about this role please contact Johnson Choy on +852 3602 2467.", "employment_types": ["Full Time", "Contract"], "selling_points": ["Joining signature cloud transformation project", "Large organization working environment", "Standardized Agile Exposure"], "locations": ["Not Specified"], "categories": ["Information Technology (IT)", "Product Management / Business Analyst", "Technical / Functional Consulting", "Technical Writing"], "post_time": "2022-01-06T08:19:31Z", "salary": {"currency": "HKD", "max": 69999, "min": 45000, "period": "monthly", "term": null}, "salary_visible": true, "title_keywords": ["senior business analyst"], "responsibilities": ["revamp", "contact"], "requirements": {"degrees": ["degree holder"], "majors": ["computer science", "information technology"], "languages": ["english"], "language_level": ["proficient"], "hard_skills": ["nice", "agile"], "soft_skills": ["organisation", "team spirit", "agile", "responsible"], "languages_combined": [{"language": "english", "language_level": ["proficient"]}]}, "experience_required": {"duration": ["5 years"], "field": ["business"]}}, {"job_id": "100003009023132", "location_code": "hk", "company": "JFE Consulting Limited", "job_title": "Programmer / Senior Programmer (C#/ .Net) - up to $35K  (Fresh Graduate Welcome)", "description": "Responsibilities\n\nInvolve end-to-end system development from requirement collections, feasibility study, system design, implementation, to system deployment\nPreparing and maintaining technical documentations\nPerform and assist in the quality assurance on project deliverable\nInvolve in the SDLC, and Project Management\n\n\u00a0Requirements\n\nHD or above in Computer Science or IT related disciplines\nFor\u00a0Programmer\u00a01-3 year IT experience\nFor\u00a0Senior Programmer\u00a01 year up experience\u00a0\nFamiliar with system development cycle, design methodology and documentation standard\nExperience in system integration related to the following:\u00a0\nJava / J2EE / Spring\u00a0 OR\u00a0\nC# / VB.NET / ASP.NET OR\u00a0\nJavaScript / PHP\u00a0 OR\u00a0\nC, C++\u00a0\nReactjs, angularjs, vuejs, nodejs\nMobile: Java, Kotlin, Objective-C, Swift, React native, Flutter", "employment_types": ["Full Time", "Permanent"], "selling_points": ["Different Industries' opportunities are open", "On-job training about new technologies", "Bonus, Medical, Dental, Life Insurance"], "locations": ["Not Specified"], "categories": ["Information Technology (IT)", "Application Specialist - Software", "Software Development", "Technical Writing"], "post_time": "2022-01-05T07:33:17Z", "salary": {"currency": null, "max": null, "min": null, "period": "monthly", "term": null}, "salary_visible": false, "title_keywords": ["programmer", "senior programmer"], "responsibilities": ["maintaining", "quality", "implementation", "project management", "system design"], "requirements": {"degrees": [], "majors": [], "languages": [], "language_level": [], "hard_skills": ["java", "integration", "php", "c++", "swift", "objective-c", "mobile", "javascript", "c", "react native", "spring", "documentation", "kotlin", "c#"], "soft_skills": [], "languages_combined": []}, "experience_required": {"duration": ["1-3 year", "1 year"], "field": ["related", "it experience"]}}, {"job_id": "100003009028438", "location_code": "hk", "company": "Page Group Hong Kong", "job_title": "Senior UX/UI Designer- Top insurance group", "description": "A leading insurance company is currently looking for an ambitious senior UX/UI designer to enhance customer experience and expand business opportunities. The successful candidate will be responsible for translating concepts into wire frames and mock ups that lead to intuitive user experiences.\n\nClient Details\n\nOur client is a one of the largest public listed group with a broad footprint spanning in Asia Pacific. Their service is not limited to insurance and financial services, but also life insurance for individuals and businesses, as well as retirement planning, wealth management services etc. They are looking for a determined candidate with around 5+ years' experience in Mobile app UI/UX design to join their expanding team.\n\nDescription\n\nResponsible for:\n\nWorking closely with development teams to deliver user-friendly digital output\nTranslating concepts into wire frames and mock ups that lead to intuitive user experiences.\nConducting research in the industry's latest trends and technologies\nEffectively communicate design processes, ideas, and solutions to teams and clients.\nDemonstrating high-quality design practices including in all aspect of UI and UX: research, interaction design and visual design\nAsking targeted questions to gather critical data, craft solutions and deliver validated automation solutions to our clients\nDriving ideas from start to finish and advocating for best practices through design architecture and live implementation\nOwning project vision and strategy for an end-to-end design process\n\nProfile\n\nQualifications:\n\nMinimum of 5 years' experience in UI/UX design, preferably in large corporations and involved in projects with many stakeholders from different functions\nBachelor's degree or more than 7 years of working experience\nAble to communicate in a clear, consistent, and transparent manner\nStrong organisational, time management skills\nPassionate in UI/UX and other areas of design and innovations\nStrong experience in desktop and mobile app design\nFamiliar with Agile environment\nGood command of English and Cantonese\n\nJob Offer\n\nWork-Life Balance\nSupportive and collaborative workplace\nGood Learning Platform\nCompetitive Package + Benefits\n\nTo apply online please click the 'Apply' button below. For a confidential discussion about this role please contact Crystal Cheuk on +852 2258 3536", "employment_types": ["Full Time", "Contract"], "selling_points": ["International working environment", "Great collaborative culture and people", "Positive work life balance"], "locations": ["Not Specified"], "categories": ["Information Technology (IT)", "Application Specialist - Software", "Technical Writing", "UI/UX Designer"], "post_time": "2022-01-07T02:18:39Z", "salary": {"currency": null, "max": null, "min": null, "period": "monthly", "term": null}, "salary_visible": false, "title_keywords": ["ui designer"], "responsibilities": ["management", "mobile app", "ideas", "data", "business opportunities", "teams", "quality", "design", "implementation", "architecture", "visual", "insurance", "mock ups", "ui", "planning"], "requirements": {"degrees": ["degree", "bachelor"], "majors": [], "languages": ["cantonese", "english"], "language_level": ["good command"], "hard_skills": ["mobile", "visual design", "agile"], "soft_skills": ["passionate", "supportive", "determined", "responsible", "agile", "time management skills", "collaborative", "clear", "learning", "friendly"], "languages_combined": [{"language": "cantonese", "language_level": ["good command"]}, {"language": "english", "language_level": ["good command"]}]}, "experience_required": {"duration": ["7 years", "5+ years", "minimum of 5 years"], "field": ["designer", "design", "business", "insurance", "team"]}}]