[{"job_id": "100003009050497", "location_code": "hk", "company": "LABS Group Limited", "job_title": "Game Editor/\u904a\u6232\u6e2c\u8a66\u54e1 (English and Chinese)", "description": "\u00a0Motto: Are you a hardcore Gamer? Into Blockchain? Come and talk to us!\n\n\u00a0Responsibilities include:\n\nReview Gamefi / NFT / Blockchain Projects for content quality based on company requirements..\nAble to provide data & reports through analysis on market trends for Gamefi / NFTs.\nThoroughly check ad content with quality and accuracy.\nAnalyze data and evaluate trends/ patterns.\nRecommend generic marketing patterns / buying insight\nEscalating questions/issues from the team regarding the process and cascading updates to the team.\nPreparing weekly process reports & sending out to the concerned people.\nBecome a key personality within the team to potentially become a crypto influencer.\n\n\u00a0Requirements:\n\nMinimum 1 years of experience in\u00a0game QA testing,\u00a0developing test plans and test cases\nAim to choose crypto as long-term career pathStrong sense of art or degen in NFT discord channels is a plus\nHeavy game player is a strong bonusFull-time analyst\u00a0\nStrong communication\u00a0and\u00a0analytical skills\nFamiliar with the popular games released in past 5 years\n\nApplication Requirement:\n\nA writing sample that introduce you as a hardcore mobile gamer and why you're a good fit for us\n\n\n\nWhat We Offer:\n\nAttractive remuneration package that includes 5-day work\nPrivilege insurance plan for group medical (covers clinical, hospitalization with supplementary major medical) & dental\nConvenient office location in TsimShaTsui\nWork with the young and energetic team\nFree snacks, coffee, and tea\nFestival cash and gifts\nRegular staff activities\n\nPlease send your full resume in English, stating present and expected salary by clicking APPLY NOW.\n\nWe are an equal opportunity employer and welcome applications from all qualified candidates.\u00a0 Personal data collected will be treated in strictest confidence and handled confidentially by authorized personnel for recruitment-related purposes within the Group.", "employment_types": ["Full Time", "Permanent"], "selling_points": ["Joyful working environment with free snacks/drinks", "Young & friendly working environment", "5 days work medical and Dental Insurance"], "locations": ["Tsim Sha Tsui"], "categories": ["Media & Advertising", "Editorial / Journalism", "Information Technology (IT)", "Software Development", "Testing / QA"], "post_time": "2022-01-17T10:52:26Z", "salary": {"currency": null, "max": null, "min": null, "period": "monthly", "term": null}, "salary_visible": false, "title_keywords": ["editor"], "responsibilities": ["data", "analysis", "review", "quality", "evaluate", "reports", "analyze data"], "requirements": {"degrees": [], "majors": [], "languages": [], "language_level": [], "hard_skills": ["mobile", "plus", "crypto", "analytical skills"], "soft_skills": ["communication", "analytical skills"], "languages_combined": []}, "experience_required": {"duration": ["minimum 1 years"], "field": ["developing", "qa", "testing"]}}, {"job_id": "100003009052698", "location_code": "hk", "company": "Global Logistics System (HK) Co Ltd", "job_title": "QUALITY ASSURANCE ANALYST (5-Day Work)", "description": "Responsibilities\n\nManage the QA testing process to ensure quality delivery of applications, ensuring the software applications or components are conformed to the IT Project Delivery Framework\nPrepare test plans and scripts, execute testing, and finalize the test report according to the schedule and to the defined best practices, standards and procedures\nLiaise with development team and decide the approach and strategy for the test\nAnalyze formal test results in order to discover and report any defects, bugs, errors and configuration issues\nExecute test scripts and documents defect, works with development team to analyze and resolve defects\u00a0\nInvolvement in varies of Infocast product testing including mobile solution, quote terminals, securities trading web page, core trading engine (OMS), settlement back office systems\nEstablish the test automation improving the efficiency of manual testing\n\nRequirements\n\nDegree holder or above in Information Technology / Business Administration\nExperience in financial industry /software testing will be an advantage\nGood communication skills in both English and Chinese\nAble to work under pressure and meet tight deadlines\nFresh graduates will also be considered\n\nWe Offer\n\n5-day work week\nDiscretionary Bonus\nMedical Insurance\nVariety of Leaves (e.g. Birthday, Marriage Leave etc.)\nVariety of company activities and training\n\nTo Apply:\nWe offer attractive package including medical insurance scheme and good career prospects to the right candidate. Interested parties please send your application via \"Apply Now\" button.\n\nFor more Company information, please feel free to visit our website at www.infocast.com.hk.\n\nAll information received will be kept in strict confidential and only for employment-related purposes.", "employment_types": ["Full Time", "Permanent"], "selling_points": ["Responsible to assure product quality", "Responsible to execute & conclude testings", "Medical insurance with attractive package"], "locations": ["Airport Area"], "categories": ["Information Technology (IT)", "Application Specialist - Software", "Support", "Testing / QA"], "post_time": "2022-01-17T03:44:15Z", "salary": {"currency": null, "max": null, "min": null, "period": "monthly", "term": null}, "salary_visible": false, "title_keywords": ["quality assurance analyst"], "responsibilities": ["software", "configuration", "systems", "quality", "procedures", "back office", "testing", "schedule", "liaise with", "plans", "report"], "requirements": {"degrees": ["degree holder"], "majors": ["business administration", "information technology"], "languages": ["english", "chinese"], "language_level": ["good"], "hard_skills": [], "soft_skills": ["communication skills", "meet tight deadlines", "work under pressure"], "languages_combined": [{"language": "english", "language_level": ["good"]}, {"language": "chinese", "language_level": ["good"]}]}, "experience_required": {"duration": [], "field": ["financial industry", "testing"]}}, {"job_id": "100003009053129", "location_code": "hk", "company": "Sunstar Tech Company Limited", "job_title": "Software Testing Engineer (Mobile App/Web, QA, UAT)", "description": "Responsibilities\nTo be a team member of Business Innovation & FinTech Department\nAssist Test Manager to complete all UAT related activities\nPrepare test cases and provide appropriate planning and execution in feature testing, regression testing, integration testing, performance testing, and another non-functional testing to ensure successful application/product deployment.\nPrepare and update training materials, user manuals.\nUpdate and maintain best QA procedures and standards, including test planning, test data preparation, and test automation.\nDesign and prepare Test plans, Test Scenarios, and Test Cases according to user requirements.\nReport any findings and prepare a testing report\nRequirements\nUniversity graduate with 1-2 years\u2019 working experience in IT industry is preferable\u00a0\nPrepare UAT test cases according to the user requirement and UI design\nExecute UAT test cases in regular or ad-hoc release cycles\nReport defect/issue clearly with detail steps using the provided bug tracking tools\nGenerate daily test report for management\nSolid experience in performing UAT\nExperience with performance and/or security testing is a plus\nStrong communication and presentation skill is an advantage\nFamiliar with Excel, HPQC, JIRA\nProficient in of both spoken and written English and Chinese", "employment_types": ["Full Time", "Permanent"], "selling_points": ["Flexible Working Hours;", "Start with 14 Days Annual Leave; 5-Day Work", "Competitive Pay; Performance Bonus"], "locations": ["Ngau Tau Kok"], "categories": ["Information Technology (IT)", "Application Specialist - Software", "Software Development", "Testing / QA"], "post_time": "2022-01-17T06:02:37Z", "salary": {"currency": null, "max": null, "min": null, "period": "monthly", "term": null}, "salary_visible": false, "title_keywords": ["engineer"], "responsibilities": ["uat", "performance testing", "data", "procedures", "design", "testing", "maintain", "plans", "report", "planning"], "requirements": {"degrees": ["university graduate"], "majors": ["it"], "languages": ["english", "chinese"], "language_level": ["proficient"], "hard_skills": ["presentation skill", "excel", "plus"], "soft_skills": ["communication", "presentation skill"], "languages_combined": [{"language": "english", "language_level": ["proficient"]}, {"language": "chinese", "language_level": ["proficient"]}]}, "experience_required": {"duration": ["1-2 years"], "field": ["it", "security", "testing"]}}, {"job_id": "100003009052330", "location_code": "hk", "company": "Capgemini Hong Kong Limited", "job_title": "QA Tester", "description": "Key Responsibilities:\n\n\u00a0 \u00a0 \u00a0Design and create test cases by analyzing and reviewing product requirements.\n\u00a0 \u00a0 \u00a0Execute test cases, record results and give feedback to relevant personnel in time.\n\u00a0 \u00a0 \u00a0Track bugs and prompt developers to follow up and modify the bugs so that the project can be delivered in a timely manner.\n\u00a0 \u00a0 \u00a0Analyze function testing results and write function testing reports.\n\nRequirements:\n\n\u00a0 \u00a0 Higher Diploma, Bachelor\u2019s degree or above in Computer Engineering / Computer Science / Information Technology or related discipline\n\u00a0 \u00a0 Minimum 3 years solid experience in software function testing and test case compiling.\n\u00a0 \u00a0 \u00a0Familiar with common software testing methods and tools, such as\u00a0black-box testing theory,\u00a0test metrics and etc.\n\u00a0 \u00a0 \u00a0Have ability to\u00a0apply unit testing, interface testing, system testing, performance testing and etc.\n\u00a0 \u00a0 \u00a0Have the ability to be in charge of the project testing independently, and improve R&D efficiency through technical means such as continuous integration or online quality monitoring.\n\u00a0 \u00a0 \u00a0Have a strong sense of responsibility and team spirit, good at communication and cooperation, self-motivated and well organised.\n\u00a0 \u00a0 Good communication skill in both spoken and written English and Chinese (Cantonese & Mandarin).\n\u00a0 \u00a0 Work experience in Agile development is a plus.\n\n\nBenefits\nPerformance Bonus\nGood work-life balance\nCommensurate with experience\nFlexible working arrangements\nWorking days: Monday \u2013 Friday\n\nIf you would like to apply for this role, please email your CV and expected salary to us\u00a0or click\u00a0'Apply Now'.", "employment_types": ["Full Time", "Contract"], "selling_points": ["Manual/Automated Testing", "ISTQB Certified", "Mobile Testing Experience"], "locations": ["Others"], "categories": ["Information Technology (IT)", "Testing / QA"], "post_time": "2022-01-17T02:47:14Z", "salary": {"currency": null, "max": null, "min": null, "period": "monthly", "term": null}, "salary_visible": false, "title_keywords": [], "responsibilities": ["a timely manner", "design", "testing", "reports", "give feedback"], "requirements": {"degrees": ["diploma", "degree or above", "bachelor"], "majors": ["computer engineering", "computer science", "information technology"], "languages": ["cantonese", "english", "chinese", "mandarin"], "language_level": ["good"], "hard_skills": ["r&d", "plus", "agile", "integration"], "soft_skills": ["self-motivated", "independently", "team spirit", "agile", "sense of responsibility", "communication skill", "communication", "organised"], "languages_combined": [{"language": "cantonese", "language_level": ["good"]}, {"language": "english", "language_level": ["good"]}, {"language": "chinese", "language_level": ["good"]}, {"language": "mandarin", "language_level": ["good"]}]}, "experience_required": {"duration": ["minimum 3 years"], "field": ["development", "testing"]}}, {"job_id": "100003009054289", "location_code": "hk", "company": "Tata Consultancy Services Limited", "job_title": "Performance Test Lead", "description": "Role descriptions\n\nWork as a Performance Test Lead\nWork on Performance test planning, Performance test script development. and Performance test execution\nMonitor Performance metrics, defects, and follow-up on defects closure\nPrepare Performance Test result\nCommunicate to all stakeholders on project progress and status.\nProvide support for checking test data and test environment\nParticipate in project status meetings including decision making and issue resolution.\nWork collaboratively with Client team involved in the program towards successful delivery\n\nMust-Have\n\nJmeter Solid understanding of Non Functional testing ( It includes how to capture non functional requirement, How prepare Script, Debugging, Monitoring, Result Analysis)\n\nGood-to-Have\n\nAutomation hands-on experience (Selenium)", "employment_types": ["Full Time"], "selling_points": ["Work as a Performance Test Lead", "Prepare Performance Test result", "Communicate to all stakeholders"], "locations": ["Others"], "categories": ["Information Technology (IT)", "Testing / QA"], "post_time": "2022-01-17T09:04:08Z", "salary": {"currency": null, "max": null, "min": null, "period": "monthly", "term": null}, "salary_visible": false, "title_keywords": ["lead"], "responsibilities": ["provide support", "data", "monitor performance", "analysis", "monitoring", "checking", "project progress", "testing", "resolution", "planning"], "requirements": {"degrees": [], "majors": [], "languages": [], "language_level": [], "hard_skills": ["analysis"], "soft_skills": ["hands-on", "decision making"], "languages_combined": []}, "experience_required": {"duration": [], "field": []}}, {"job_id": "100003009052001", "location_code": "hk", "company": "Automated Systems (HK) Ltd", "job_title": "QA Lead (Banking sector)", "description": "Konew Financial Express is one of the leading FinTech companies in money lending industry at Hong Kong, Taiwan and Mainland China. Konew aims to bring great customer experience to everyone\u2019s financial journey. We strive to improve people\u2019s lives by reinventing financial services through innovative digital technology. We put our people first, whether it\u2019s our customers or our employees.\n\nDue to expansion of the business, this is a new hiring position of\u00a0Quality Assurance Analyst to join our high growth and dynamic Digital team. You will be responsible for our FinTech product testing and rollout, as well as the quality of the overall process. To succeed in this role, you should be creative, willing to learn new technology and a problem-solver with passion for the FinTech industry.\n\nMain Duties & Responsibilities:\n\n\nCollaborate with project manager, product manager, development teams and other key stakeholders\nDesign and prepare Test plans, Test Scenarios, and Test Cases according to user requirements\nEnsure the deliverables meet the planned level of performance and comply with established quality standards\nIdentify application issues, report discrepancies, prepare test reports and recommend improvements\nIdentify areas for shift left and shift right as part of early testing and maximize reusability\nDue diligence of DEV and QA processes, identify gaps and suggest improvements\nReview / Prepare Playbook, Guideline, Standard and Templates\n\nRequirements:\n\n\nAt least 5 years of relevant experience in software testing and System Development Life Cycle\nStrong knowledge of QA methodologies, tools and processes\nExperience in performing testing of banking applications\nSolid experience in engaging in Testing (e.g. functional, Stress, UAT) for Mobile App/ Website/ System projects\n\u00a0Experience on test cases automation will be an advantage\nExperience in product lifecycle management, preferably in agile framework\nExcellent communication, interpersonal and presentation skills\n\u00a0Problem-solving aptitude, Well-organized, self-motivated and able to work under pressure\nExperience on financial institutes background will be an advantage\nExcellent command of spoken and written Chinese and English\n\nWe offer:\n\nDiscretionary bonus\nMedical insurance\nDental insurance\nHardship allowance\nCompetitive annual leave days\nBirthday leave\nAnniversary leave\nStudy leave\nMarriage leave\nCompassionate leave\n\nHow to apply:\n\nInterested parties, please send your resume stating your expected salary to Human Capital Department\u00a0by clicking \"APPLY NOW\".\n\n(We are an equal opportunity employer.\u00a0 Personal data collected will be used for recruitment purpose only.\u00a0 The unsuccessful applications will be destroyed after 6 months.)", "employment_types": ["Full Time", "Permanent", "Contract"], "selling_points": ["Opportunities for your career promotion", "Will have opportunities to try different projects", "Become part of our talented and core team"], "locations": ["Quarry Bay"], "categories": ["Information Technology (IT)", "Software Development", "Testing / QA", "Technical Writing"], "post_time": "2022-01-17T01:48:18Z", "salary": {"currency": null, "max": null, "min": null, "period": "monthly", "term": null}, "salary_visible": false, "title_keywords": ["lead"], "responsibilities": ["collaborate with", "due diligence", "review", "teams", "quality", "design", "testing", "reports", "suggest improvements", "plans", "report"], "requirements": {"degrees": [], "majors": [], "languages": ["english", "chinese"], "language_level": ["excellent"], "hard_skills": ["mobile", "problem-solving", "agile"], "soft_skills": ["self-motivated", "agile", "problem-solving", "well-organized", "communication", "presentation skills", "interpersonal", "work under pressure"], "languages_combined": [{"language": "english", "language_level": ["excellent"]}, {"language": "chinese", "language_level": ["excellent"]}]}, "experience_required": {"duration": ["at least 5 years"], "field": ["management", "system development", "testing", "relevant experience", "banking", "financial"]}}, {"job_id": "100003009053835", "location_code": "hk", "company": "Konew Financial Express Ltd", "job_title": "Quality Assurance Analyst", "description": "THE PERSON\n\n\n\nCreate, run, and document manual test scripts\nLearn from more senior resources how to create test scripts based on business requirements\nUtilizing UAT testing tools to log and track your scripts and requirements status\nCollaborate with other QA testers on the team and business users\nCommunicate your findings from test scripts with business users to ensure code is ready for production\nDocument test case execution, test results and defects in detail.\nProduce reports on User Acceptance Testing (UAT) and automation tesing by using Seleium with explanation of findings.\nCreate and document instructional documents (SOPs) as it relates to new, changed, or enhanced systems or processes.\nPerform continuous development, revision, and upkeep of test documentation for the purposes of improvement and addressing lessons learned.\nWork independently on multiple projects in a fast-paced environment.\nInteract with multiple teams to ensure project objectives are being attained.\n\n\nTHE PERSON\n\n\n\nDegree holder in Computer Science, Information Technology or related disciplines with minimum 2 years of manual testing experience\nStrong communication skills and ability to be proactive and collaborative with the testing team and business users\nAbility to work as an Individual Contributor\nEffective verbal and written communication in English and Chinese;\u00a0\n\nTo apply online please click the Apply button below. For a confidential discussion about this role please contact us on +852 2391 2813.\n\nAll personal data provided will be used for consideration of your job application only.", "employment_types": ["Full Time", "Permanent"], "selling_points": ["Design and execute functional test plans", "Prepare Project Test Strategy/Plan", "At least 5 years of relevant testing experience"], "locations": ["Central"], "categories": ["Information Technology (IT)", "IT Management", "Software Development", "Testing / QA"], "post_time": "2022-01-17T07:36:08Z", "salary": {"currency": null, "max": null, "min": null, "period": "monthly", "term": null}, "salary_visible": false, "title_keywords": ["quality assurance analyst"], "responsibilities": ["collaborate with", "uat", "systems", "uat testing", "teams", "testing", "communication", "reports", "contact", "sops", "documentation", "multiple projects", "personal data"], "requirements": {"degrees": ["degree holder"], "majors": ["related disciplines", "computer science", "information technology"], "languages": ["english", "chinese"], "language_level": [], "hard_skills": ["documentation", "code"], "soft_skills": ["communication skills", "work independently", "fast-paced environment", "collaborative", "communication", "proactive"], "languages_combined": [{"language": "english", "language_level": []}, {"language": "chinese", "language_level": []}]}, "experience_required": {"duration": ["minimum 2 years"], "field": ["related", "testing", "information technology"]}}, {"job_id": "100003009054595", "location_code": "hk", "company": "Linkers International Limited", "job_title": "QA Engineer (Manual / Automation) - 30k - 44k + bonus", "description": "Job Responsibilities:\nDesign and prepare test plan, test cases and test scenarios based on product requirement specification\nEstimate, prioritize, plan and coordinate testing activities\nPerform functional test and user test cases\nAutomation testing design implementation\nProvide testing report\nIssue tracking and management\nKnowledge of product quality assurance\nCollaborate with engineers and designers to ensure all products are completely compliant and no issues arise\nPrepare and present compliance reports with analysis of measurement, statistical, and other data\nDuties & Responsibilities:\nDesign and prepare test plan, test cases and test scenarios based on product requirement specification\nEstimate, prioritize, plan and coordinate testing activities\nPerform functional test and user test cases\nAutomation testing design implementation\nProvide testing report\nIssue tracking and management\nKnowledge of product quality assurance\nCollaborate with engineers and designers to ensure all products are completely compliant and no issues arise\nPrepare and present compliance reports with analysis of measurement, statistical, and other data\nBasic Qualifications:\nDegree in Electrical Engineering or related discipline required\nExperience in any one of the programming languages, python would be an advantage\nExperience in using auto-testing software would be an advantage\nExperience in mobile application testing distribution flow would be an advantage\nExperience in ISO27001 would be an advantage\nPreferred Qualifications:\nUnderstand the software development workflow\nWilling to learn new technologies\nSkilful on various software engineering tools\nGood analytical and problem-solving skill, results oriented attitude\nAble to communicate information in a clear & precise manner\nExcellent communication in both written and spoken English and Chinese (Mandarin an advantage)\nGood presentation skill", "employment_types": ["Full Time", "Permanent"], "selling_points": ["5 days work, work for a sizeable financial project", "30k - 44k + bonus +benefits, depends on experience", "Manual QA with a bit automation also welcome!"], "locations": ["Causeway Bay"], "categories": ["Information Technology (IT)", "Application Specialist - Software", "Testing / QA", "Others"], "post_time": "2022-01-17T10:10:32Z", "salary": {"currency": "HKD", "max": 44999, "min": 30000, "period": "monthly", "term": null}, "salary_visible": true, "title_keywords": ["engineer"], "responsibilities": ["tracking", "management", "collaborate with engineers", "software", "data", "analysis", "compliance", "quality", "implementation", "plan and coordinate", "testing", "testing activities", "design", "measurement", "communication", "reports", "plan", "report"], "requirements": {"degrees": ["degree"], "majors": ["electrical engineering"], "languages": ["english", "chinese", "mandarin"], "language_level": ["advantage", "excellent"], "hard_skills": ["presentation skill", "no", "basic", "analysis", "problem-solving", "mobile", "programming", "python"], "soft_skills": ["presentation skill", "problem-solving", "willing to learn", "prioritize", "clear", "communication", "precise"], "languages_combined": [{"language": "english", "language_level": ["excellent"]}, {"language": "chinese", "language_level": ["excellent"]}, {"language": "mandarin", "language_level": ["advantage", "excellent"]}]}, "experience_required": {"duration": [], "field": ["programming", "testing"]}}, {"job_id": "100003009052000", "location_code": "hk", "company": "Automated Systems (HK) Ltd", "job_title": "QA Engineer / Senior QA Engineer", "description": "Job Responsibilities:\n\nQuality Assurance of the product \u2013 responsible to assure product quality\nResponsible for analyze & review products\u2019 quality and system performance proactively\nBe proactive in provide suggestion, advice to project stakeholders for preventing repeated errors from the testing phase\nEnsure proper maintenance of test plan / test result and follow up the final testing after rectification made to the error\nMake use of automation testing and scripting to enhance repetitive & regression testing routines\nAdopt a mix of technical and operation perspective mindset to uncover and minimize potential defects\nStay updated in technology trends to provide precaution advice to assure GLS products usability\nTesting \u2013 being accountable / responsible to execute & conclude testing\nResponsible for the creation of testing artifacts including but not limited to test cases, test scripts, test conditions, and expected test results\nResponsible for day-to-day ad-hoc test execution activities\nResponsible for mapping of test cases with user requirements and functional designs\nDesign & conduct user acceptance testing (UAT), functional test, regression test, performance and destructive test to validate the end-to-end business flow to enhance the quality of deployment and provide trouble-shooting\nDocumentation of all tests, including progress and observations, and incorporate into a final test report\nSupport QA Lead and work closely with Project team/QA Analyst to handle project deliverables on time\n\nJob Requirements:\n\n\n\nDegree in Computer Science, E-Commerce or related data science disciplines\nMinimum 2 years of experience in software testing or information technology\nExperience in API/Web/Mobile automation testing\nAbility to execute test plans, test cases and test analysis independently\nDetailed-minded, customer centric and strong aptitude for learning new technologies\nTeam player with good communication skills collaborating with cross-department\nHighly independent with analytical mind and ability to work under pressure\nFluent in Cantonese, English and Putonghua\n\nWe offer 5-day work,\u00a0and attractive remuneration, medical and dental insurance, provident fund and other fringe benefits\u00a0including\u00a0discounted air tickets\u00a0on Cathay Pacific Airways,\u00a0recreation subsidy,\u00a0birthday leave,\u00a0Airport Express discount\u00a0and\u00a0shuttle bus\u00a0to the right candidate and his/her dependents etc.\u00a0 Interested parties, please submit your detailed CV, stating your present and\u00a0expected salary\u00a0and\u00a0availability\u00a0to us.\n\nWe are an equal opportunity Employer. All CVs and personal data collected are for recruitment purposes and the information will be kept confidential.", "employment_types": ["Full Time", "Contract"], "selling_points": ["Opportunities for your career promotion", "Will have opportunities to try different projects", "Become part of our talented and core team"], "locations": ["Shatin Area"], "categories": ["Information Technology (IT)", "Software Development", "Testing / QA", "Network & System"], "post_time": "2022-01-17T01:48:18Z", "salary": {"currency": null, "max": null, "min": null, "period": "monthly", "term": null}, "salary_visible": false, "title_keywords": ["engineer"], "responsibilities": ["ad-hoc", "uat", "maintenance", "project deliverables", "review", "quality", "rectification", "design", "testing", "plan", "documentation", "report"], "requirements": {"degrees": ["degree"], "majors": ["data science", "computer science", "e-commerce"], "languages": ["cantonese", "putonghua", "english"], "language_level": ["fluent"], "hard_skills": ["mobile", "analysis", "web", "e-commerce"], "soft_skills": ["communication skills", "highly independent", "independently", "work under pressure", "learning", "analytical mind", "team player", "detailed"], "languages_combined": [{"language": "cantonese", "language_level": ["fluent"]}, {"language": "putonghua", "language_level": ["fluent"]}, {"language": "english", "language_level": ["fluent"]}]}, "experience_required": {"duration": ["minimum 2 years"], "field": ["information technology", "testing"]}}, {"job_id": "100003009054823", "location_code": "hk", "company": "HALO Energy Limited, HKSTP Acceleration Programme", "job_title": "System Testing Engineer (Compliance)", "description": "Responsible to plan, execute and monitor the testing activities for different applications and systems Communicate with UAT Lead to clarify on project requirements and scope.\nDefined Testing Strategy and Policy;\n\n\u5ba2\u6237\u7b80\u4ecb\n\nOur client is a global technology leader investing in digital and innovations including AIML, connectivity and big data analytic technology - their mission is to build a better future which is vital to the development of our societies.\n\n\u5de5\u4f5c\u5185\u5bb9\n\nJob Responsibilities:\n\nYou will be involving in to plan, execute and monitor the testing activities for different mobile applications to clarify on project requirements and scope;\nSupport business with effective implementation of mobile applications;\nBusiness requirements review and User Acceptance Test (UAT);\nCollaborate with technology teams to ensure effective end to end testing is executed well;\nResponsible for managing end-to-end mobile UAT development and execution;\nDefine UAT plan, including objectives, scenarios, E2E scope, efforts, test scripts, entry and exit criteria;\nImplement and support UAT best practices and methodology;\nExecute test scripts, raise defects in tracking system and follow-through on defect resolution;\nEnsure appropriate engagement and oversight of testing quality.\n\n\u7406\u60f3\u7684\u6c42\u804c\u8005\n\nJob Requirements:\n\nMUST HAVE:\n\nBachelor's degree/ Higher Diploma in computer science or equivalent;\nAt least 5 years of good experience in (UAT) PPERFORMANCE TESTING;\nExperience in developing, documenting and implementing quality assurance standards;\n\nGOOD TO HAVE: (Optional)\n\nKnowledge of testing methodology and tools is essential, with experience in Agile methodology is plus;\nExperience in developing automation test for mobile application and website using tools such as Katalon, Selenium, etc; Experience with testing Web-based/ Mobile applications/ Web service;\nBasic knowledge on Performance Testing and/or Security Testing;\nExperience in developing, documenting and implementing quality assurance standards;\nImplementation Manager experience would be an added advantage;\nGood communications skills, able to speak both Cantonese and verbal English;\n\n\u798f\u5229\u5f85\u9047\n\n5-day week\nComprehensive Medical insurance Scheme (inclusive of dental care)\nRegular Birthday leave\nHappy Friday\nStaff Discount\n\nTo apply online please click the 'Apply' button below.\nFor a confidential discussion about this role please contact Joe Tsoi on +852 2848 9539.", "employment_types": ["Full Time"], "selling_points": ["At least 5 years relevant working experience", "System testing in an innovation way", "5 days per week working hours, performance bonus"], "locations": ["Shatin Area"], "categories": ["Engineering", "Electrical / Electronics", "Information Technology (IT)", "Testing / QA", "Others"], "post_time": "2022-01-17T11:27:30Z", "salary": {"currency": null, "max": null, "min": null, "period": "monthly", "term": null}, "salary_visible": false, "title_keywords": ["engineer"], "responsibilities": ["collaborate with", "project requirements", "uat", "review", "monitor", "implementation", "testing activities", "teams", "testing", "resolution", "quality", "plan", "tracking"], "requirements": {"degrees": ["diploma", "degree", "bachelor"], "majors": ["computer science"], "languages": ["cantonese", "english"], "language_level": ["good"], "hard_skills": ["plus", "basic", "agile", "web", "scheme", "mobile"], "soft_skills": ["comprehensive", "agile"], "languages_combined": [{"language": "cantonese", "language_level": ["good"]}, {"language": "english", "language_level": ["good"]}]}, "experience_required": {"duration": ["at least 5 years"], "field": ["quality assurance", "developing", "testing"]}}, {"job_id": "100003009052808", "location_code": "hk", "company": "ADECCO", "job_title": "Application Tester / Quality Assurance (Renewable Contract)", "description": "Our client is a developing tech corporation in Hong Kong, they are looking for an Application Tester with solid QA experience to join their projects.\n\nResponsibilities\n\nGather and understand user requirements\nConduct manual tests such as integration, functional, performance and regression tests for applications\nWork closely with internal and external teams to develop test strategy such as test plans and test cases\nRequirements\n\nAt least 1-year of experience in software QA and testing or relevant experience\nExperience in testing web, mobile applications, and API\nExperience in developing and executing frontend manual test suites\nFamiliar with bug tracking tools and test case management tools\nExcellent capability on analytical, writing and communication skills\nImmediately Available is preferred\u00a0\nInterested parties, please\u00a0CLICK HERE\u00a0to apply the position via Adecco website with your CV.\u00a0Please note that only shortlisted candidates will be notified. All information gathered will be treated in strict confidence and solely used for recruitment purposes.", "employment_types": ["Full Time", "Contract"], "selling_points": [], "locations": ["Shatin Area"], "categories": ["Information Technology (IT)", "Support", "Software Development", "Testing / QA"], "post_time": "2022-01-17T04:07:37Z", "salary": {"currency": null, "max": null, "min": null, "period": "monthly", "term": null}, "salary_visible": false, "title_keywords": [], "responsibilities": [], "requirements": {"degrees": [], "majors": [], "languages": [], "language_level": [], "hard_skills": ["integration", "mobile", "web"], "soft_skills": ["communication skills"], "languages_combined": []}, "experience_required": {"duration": ["at least 1-year"], "field": ["relevant experience", "developing", "qa", "testing"]}}, {"job_id": "100003009052965", "location_code": "hk", "company": "David James Recruitment Limited", "job_title": "Automation QA Engineer \u2013 Crypto/FX Trading Platforms \u2013 HKD$30k-60k", "description": "Job brief\nWe are looking for a QA Tester to assess software quality through manual and automated testing. You will be responsible for finding and reporting bugs and glitches.\nIn this role, you should have a keen eye for detail and excellent communication skills. If you are also competent in executing test cases and are passionate about quality, we\u2019d like to meet you.\nUltimately, you will ensure that our products, applications and systems work correctly.\nJob Description\nExperience in Manual and UAT testing\nIndividual contributor working in Agile development environment\nClosely working in a scrum team to identify- test- requirements.\nCreating- test- environment for functional and regression- tests.\nExecuting functional as well as regression- tests.\nBuild and release of- tested code to the QA as well as production environment.\nWork on automation project with the team whenever needed.\nProvide support during critical business months.\nStrong Understanding of SDLC and role of a QA Analyst.\nStrong Understanding of software testing techniques and tools.\nExperience in Mobile Testing is added advantage.", "employment_types": ["Full Time"], "selling_points": ["3-6 years in Automation QA", "Young and Energetic Working Environment", "Exposure to crypto exchange platform"], "locations": ["Not Specified"], "categories": ["Information Technology (IT)", "Application Specialist - Software", "Software Development", "Testing / QA"], "post_time": "2022-01-17T04:43:14Z", "salary": {"currency": null, "max": null, "min": null, "period": "monthly", "term": null}, "salary_visible": false, "title_keywords": ["engineer"], "responsibilities": ["reporting", "provide support", "software", "systems", "quality", "uat testing", "agile development", "testing", "communication", "executing"], "requirements": {"degrees": [], "majors": [], "languages": [], "language_level": [], "hard_skills": ["code", "sdlc", "mobile", "agile"], "soft_skills": ["communication skills", "agile", "responsible", "competent", "keen", "eye for detail", "passionate about"], "languages_combined": []}, "experience_required": {"duration": [], "field": ["testing"]}}, {"job_id": "100003009053989", "location_code": "hk", "company": "The Bank of East Asia, Limited", "job_title": "UAT Tester (Business Innovation & FinTech)", "description": "\nResponsibilities\nAnalyze business and system requirement and identify test solution.\nKeep track on change requirement.\nCollaborate with Manager and Engineer to develop test plan, test scenario, test cases and report.\nAct as main focal point for communicate, co-ordinate all testing tasks and communicate with stakeholders, infra-structure team, external party, if any\nIdentify and resolve test issues and conflicts regarding test execution.\nEscalate to QA Manager for unresolved issue.\nTrack tester's progress on test cases preparation and review.\nMonitor test cases execution progress, defect fixation progress on overall test execution.\nDevelop test progress and defect report.\u00a0Analyse, evaluate test result and provide recommendation.\n\nJob Requirements\n\nBachelor or above in Computer Science or related degree\nStrong understanding and experience on IT project management, Integration testing and/or Business application QA testing.\u00a0Banking industry experience is a plus.\nExperience in leading and managing test teams.\nFamiliar with languages such as Java, Python etc are advantage\nExperience in SQL/NoSQL databases are advantage\nStrong interpersonal, communication, collaboration and presentation skills.\nStrong analytical skill.\nProficient written and verbal communications skills\nWe offer 5-day week, public holidays, medical benefits, excellent career opportunities, considerable remuneration to the right candidates.\n\u201cIf you have the desire for an exciting and rewarding career, please send us your resume, stating your notice period, present and expected salary to Human Resources Department by clicking \"Apply Now\".\nTo learn us more, please visit our website: www.asl.com.hk\nWe are an equal opportunity employer. All applications will be treated in strict confidence. We regret that only shortlisted candidates will be notified. All personal data will be destroyed within six months after the selection process.", "employment_types": ["Full Time", "Permanent"], "selling_points": ["To be a team member of Business Innovation", "Assist Test Manager to complete all UAT related", "With 1-2 years\u2019 working experience in banking"], "locations": ["Not Specified"], "categories": ["Information Technology (IT)", "Testing / QA", "Others"], "post_time": "2022-01-17T07:56:47Z", "salary": {"currency": null, "max": null, "min": null, "period": "monthly", "term": null}, "salary_visible": false, "title_keywords": ["uat tester"], "responsibilities": [], "requirements": {"degrees": ["degree", "bachelor"], "majors": ["computer science"], "languages": [], "language_level": [], "hard_skills": ["plus", "java", "analytical skill", "focal", "python", "sql", "project management", "databases", "integration"], "soft_skills": ["analytical skill", "communication", "project management", "presentation skills", "interpersonal"], "languages_combined": []}, "experience_required": {"duration": [], "field": ["banking industry", "qa", "testing", "sql", "project management", "business", "it"]}}, {"job_id": "100003009042739", "location_code": "hk", "company": "Promise (Hong Kong) Co., Limited", "job_title": "IT Officer/Senior Officer (Software Quality Assurance)", "description": "Summary:\nYou will be responsible to manage and support on User Acceptance Test (UAT) for the rollout of Core Banking System and assist in designing UAT test cases and performing UAT testing according to the pre-defined test cases.\nKey Role and Responsibilities: \u00a0\nAssist in project management in terms of User Acceptance Testing (UAT) planning, UAT co-ordination, UAT environment setup, UAT test cases preparation and execution\nDesign test scenarios and test case based on business requirement, functional requirement specification (FRS), test plan and ensure comprehensive coverage of test cases\nManage execution of test case manually or using automated testing tools\nCompile test result to respective handling staff assigned by project team for upload to defect management system and monitor the defect fixing progress\nMonitor UAT schedule and progress and support the rollout of bank Teller systems\nUnderstand the limitations and issues of existing testing processes and recommend improvement initiatives\nProvide guidance and coaching to junior UAT tester of the team\nJob Requirements:\nMatriculated or degree holder\nAround 1 - 3 working experiences, preferably in IT/ Banking sectors\nExperience in performing testing of banking systems\nProduct Knowledge on Retail Banking / Corporate Banking is essential\nSelf-initiative, able to work independently and under pressure, and meet tight deadline\nMeticulous and well organized\nExcellent communication and interpersonal skills\nGood command of both written and spoken English and Chinese\nPlease note that only shortlisted candidates will be notified.", "employment_types": ["Full Time", "Permanent"], "selling_points": ["Perform unit test and integration test", "Assist in UAT", "Provide end-user support"], "locations": ["Wan Chai"], "categories": ["Information Technology (IT)", "Support", "Testing / QA", "Others"], "post_time": "2022-01-15T03:49:15Z", "salary": {"currency": null, "max": null, "min": null, "period": "monthly", "term": null}, "salary_visible": false, "title_keywords": ["senior officer", "it officer"], "responsibilities": ["management", "uat", "systems", "monitor", "design", "testing", "project management", "schedule", "plan", "provide guidance", "setup", "planning"], "requirements": {"degrees": ["degree holder"], "majors": [], "languages": ["english", "chinese"], "language_level": ["good command"], "hard_skills": [], "soft_skills": ["meticulous", "work independently", "under pressure", "well organized", "communication and interpersonal skills", "self-initiative", "meet tight deadline"], "languages_combined": [{"language": "english", "language_level": ["good command"]}, {"language": "chinese", "language_level": ["good command"]}]}, "experience_required": {"duration": [], "field": ["testing", "it", "banking"]}}, {"job_id": "100003009055269", "location_code": "hk", "company": "Infocast Limited", "job_title": "System Quality Officer", "description": "Responsibilities\n\nManage the QA testing process to ensure quality delivery of applications, ensuring the software applications or components are conformed to the IT Project Delivery Framework\nPrepare test plans and scripts, execute testing, and finalize the test report according to the schedule and to the defined best practices, standards and procedures\nLiaise with development team and decide the approach and strategy for the test\nAnalyze formal test results in order to discover and report any defects, bugs, errors and configuration issues\nExecute test scripts and documents defect, works with development team to analyze and resolve defects\u00a0\nInvolvement in varies of Infocast product testing including mobile solution, quote terminals, securities trading web page, core trading engine (OMS), settlement back office systems\nEstablish the test automation improving the efficiency of manual testing\n\nRequirements\n\nDegree holder or above in Information Technology / Business Administration\nExperience in financial industry /software testing will be an advantage\nGood communication skills in both English and Chinese\nAble to work under pressure and meet tight deadlines\nFresh graduates will also be considered\n\nWe Offer\n\n5-day work week\nDiscretionary Bonus\nMedical Insurance\nVariety of Leaves (e.g. Birthday, Marriage Leave etc.)\nVariety of company activities and training\n\nTo Apply:\nWe offer attractive package including medical insurance scheme and good career prospects to the right candidate. Interested parties please send your application via \"Apply Now\" button.\n\nFor more Company information, please feel free to visit our website at www.infocast.com.hk.\n\nAll information received will be kept in strict confidential and only for employment-related purposes.", "employment_types": ["Full Time", "Permanent"], "selling_points": ["Manage & analyze the QA testing process", "Establish the test automation", "Fresh graduates are welcome"], "locations": ["Hung Hom"], "categories": ["Information Technology (IT)", "Application Specialist - Software", "Testing / QA", "Network & System"], "post_time": "2022-01-18T01:59:19Z", "salary": {"currency": null, "max": null, "min": null, "period": "monthly", "term": null}, "salary_visible": false, "title_keywords": ["quality officer"], "responsibilities": ["software", "configuration", "systems", "quality", "procedures", "back office", "testing", "schedule", "liaise with", "plans", "report"], "requirements": {"degrees": ["degree holder"], "majors": ["business administration", "information technology"], "languages": ["english", "chinese"], "language_level": ["good"], "hard_skills": [], "soft_skills": ["communication skills", "meet tight deadlines", "work under pressure"], "languages_combined": [{"language": "english", "language_level": ["good"]}, {"language": "chinese", "language_level": ["good"]}]}, "experience_required": {"duration": [], "field": ["financial industry", "testing"]}}, {"job_id": "100003009056173", "location_code": "hk", "company": "Osmium Consulting Group Limited", "job_title": "Software QA Engineer / QA Tester ( Manual / Automation )", "description": "Responsibilities\nTo be a team member of Business Innovation & FinTech Department\nAssist Test Manager to complete all UAT related activities\nPrepare test cases and provide appropriate planning and execution in feature testing, regression testing, integration testing, performance testing, and another non-functional testing to ensure successful application/product deployment.\nPrepare and update training materials, user manuals.\nUpdate and maintain best QA procedures and standards, including test planning, test data preparation, and test automation.\nDesign and prepare Test plans, Test Scenarios, and Test Cases according to user requirements.\nReport any findings and prepare a testing report\nRequirements\nUniversity graduate with 1-2 years\u2019 working experience in IT industry is preferable\u00a0\nPrepare UAT test cases according to the user requirement and UI design\nExecute UAT test cases in regular or ad-hoc release cycles\nReport defect/issue clearly with detail steps using the provided bug tracking tools\nGenerate daily test report for management\nSolid experience in performing UAT\nExperience with performance and/or security testing is a plus\nStrong communication and presentation skill is an advantage\nFamiliar with Excel, HPQC, JIRA\nProficient in of both spoken and written English and Chinese", "employment_types": ["Full Time", "Permanent"], "selling_points": ["MNC | Global FinTech | Software Quality Assurance", "1 Years+ | Tester | Engineer | Large Scale Project", "5 Days Work | Bonus | Medical | Young Culture"], "locations": ["Tsim Sha Tsui"], "categories": ["Information Technology (IT)", "Application Specialist - Software", "IT Project Management / Team Lead", "Testing / QA"], "post_time": "2022-01-18T03:28:48Z", "salary": {"currency": "HKD", "max": 34999, "min": 25000, "period": "monthly", "term": null}, "salary_visible": true, "title_keywords": ["engineer"], "responsibilities": ["uat", "performance testing", "data", "procedures", "design", "testing", "maintain", "plans", "report", "planning"], "requirements": {"degrees": ["university graduate"], "majors": ["it"], "languages": ["english", "chinese"], "language_level": ["proficient"], "hard_skills": ["presentation skill", "excel", "plus"], "soft_skills": ["communication", "presentation skill"], "languages_combined": [{"language": "english", "language_level": ["proficient"]}, {"language": "chinese", "language_level": ["proficient"]}]}, "experience_required": {"duration": ["1-2 years"], "field": ["it", "security", "testing"]}}, {"job_id": "100003009055806", "location_code": "hk", "company": "Michael Page", "job_title": "Senior Software UAT Tester (Performance Test)", "description": "Responsible to plan, execute and monitor the testing activities for different applications and systems Communicate with UAT Lead to clarify on project requirements and scope.\nDefined Testing Strategy and Policy;\n\n\u5ba2\u6237\u7b80\u4ecb\n\nOur client is a global technology leader investing in digital and innovations including AIML, connectivity and big data analytic technology - their mission is to build a better future which is vital to the development of our societies.\n\n\u5de5\u4f5c\u5185\u5bb9\n\nJob Responsibilities:\n\nYou will be involving in to plan, execute and monitor the testing activities for different mobile applications to clarify on project requirements and scope;\nSupport business with effective implementation of mobile applications;\nBusiness requirements review and User Acceptance Test (UAT);\nCollaborate with technology teams to ensure effective end to end testing is executed well;\nResponsible for managing end-to-end mobile UAT development and execution;\nDefine UAT plan, including objectives, scenarios, E2E scope, efforts, test scripts, entry and exit criteria;\nImplement and support UAT best practices and methodology;\nExecute test scripts, raise defects in tracking system and follow-through on defect resolution;\nEnsure appropriate engagement and oversight of testing quality.\n\n\u7406\u60f3\u7684\u6c42\u804c\u8005\n\nJob Requirements:\n\nMUST HAVE:\n\nBachelor's degree/ Higher Diploma in computer science or equivalent;\nAt least 5 years of good experience in (UAT) PPERFORMANCE TESTING;\nExperience in developing, documenting and implementing quality assurance standards;\n\nGOOD TO HAVE: (Optional)\n\nKnowledge of testing methodology and tools is essential, with experience in Agile methodology is plus;\nExperience in developing automation test for mobile application and website using tools such as Katalon, Selenium, etc; Experience with testing Web-based/ Mobile applications/ Web service;\nBasic knowledge on Performance Testing and/or Security Testing;\nExperience in developing, documenting and implementing quality assurance standards;\nImplementation Manager experience would be an added advantage;\nGood communications skills, able to speak both Cantonese and verbal English;\n\n\u798f\u5229\u5f85\u9047\n\n5-day week\nComprehensive Medical insurance Scheme (inclusive of dental care)\nRegular Birthday leave\nHappy Friday\nStaff Discount\n\nTo apply online please click the 'Apply' button below.\nFor a confidential discussion about this role please contact Joe Tsoi on +852 2848 9539.", "employment_types": ["Full Time", "Permanent"], "selling_points": ["Defined Testing Strategy and Policy;", "UAT Test Process and Resource Management;", "HKD 45K - 50K Max Per Month"], "locations": ["Central & Western Area"], "categories": ["Information Technology (IT)", "Testing / QA"], "post_time": "2022-01-18T02:58:12Z", "salary": {"currency": "HKD", "max": 44999, "min": 35000, "period": "monthly", "term": null}, "salary_visible": true, "title_keywords": ["uat tester"], "responsibilities": ["collaborate with", "project requirements", "uat", "review", "monitor", "implementation", "testing activities", "teams", "testing", "resolution", "quality", "plan", "tracking"], "requirements": {"degrees": ["diploma", "degree", "bachelor"], "majors": ["computer science"], "languages": ["cantonese", "english"], "language_level": ["good"], "hard_skills": ["plus", "basic", "agile", "web", "scheme", "mobile"], "soft_skills": ["comprehensive", "agile"], "languages_combined": [{"language": "cantonese", "language_level": ["good"]}, {"language": "english", "language_level": ["good"]}]}, "experience_required": {"duration": ["at least 5 years"], "field": ["quality assurance", "developing", "testing"]}}, {"job_id": "100003009047870", "location_code": "hk", "company": "BGC Group (HK) Limited", "job_title": "Software Tester Lead / QA Manager (Manual / Automated)", "description": "Who are we?\nDavid James Recruitment is a leader in IT recruitment, with directors who have a long track record and great success in our field. Our goal is to be outstanding - for service, knowledge, network, and quality delivery to our candidates and clients.\u00a0 Our team combines IT recruitment experience from major global cities across APAC and Europe, coupled with excellent knowledge in the HK and Asia markets.\nAt David James we are regard ourselves as \u201cold school\u201d \u2013we are keen on training and building consultants from trainee level so that we are consistent with our methods, as well as encouraging loyalty, teamwork and promoting a positive company culture with a real sense of fun and humour.\nWith Directors that are hands on and having many years of genuine end to end recruitment experience, we will provide an in depth insight of the industry in a short time, helping you to learn and pick things up quickly. We want to encourage and support people into bigger roles and more money. There is no hire/fire mentality here - consultants are given fair chances to learn, try hard, and make it happen, with senior staff supporting you every step of the way.\nWe have a particularly strong emphasis on quality service, end to end recruitment, work hard play hard mentality, fairness, loyalty and teamwork.\nThe right candidate will be:\u00a0\n\n\nNaturally sales driven and customer driven\nFearless and outgoing\nPositive and passionate\nHave a great sense of humour\nAble to think outside the box\nBe a fantastic communicator\nFocused and disciplined\nFluent in English and preferably Chinese (Cantonese or Mandarin)\nAmbitious and impatient for success\nYou will not need knowledge of IT, with all training provided, and hard work and application, you will be able to pick things up quickly\nContact us now if you are keen to have an informal chat to hear more at +852 3619 9860 or send us your CV for our reference.", "employment_types": ["Full Time", "Permanent"], "selling_points": ["Perform QA/Testing duties with Top Listed IT firm", "Experience in project leading", "Attractive Remuneration Package & Fringe Benefits"], "locations": ["Not Specified"], "categories": ["Information Technology (IT)", "Software Development", "Testing / QA", "Technical / Functional Consulting"], "post_time": "2022-01-15T03:49:51Z", "salary": {"currency": null, "max": null, "min": null, "period": "monthly", "term": null}, "salary_visible": false, "title_keywords": ["manager", "lead"], "responsibilities": [], "requirements": {"degrees": [], "majors": [], "languages": [], "language_level": [], "hard_skills": [], "soft_skills": [], "languages_combined": []}, "experience_required": {"duration": [], "field": []}}, {"job_id": "100003009049716", "location_code": "hk", "company": "Teki'Spire Limited", "job_title": "(Senior) QA Engineers (Manual & Automation) x multiple openings | Perm | in-house", "description": "My client is a well-known eCommerce\u00a0conglomerate. Recently undergoing a great transformation, they are now looking for energetic data engineers to aid with their rapid growth. You will be working very closely with the product team and potentially owning the data products.\n\nIf you have been working in a traditional firm with standard working yet boring procedure, come join the team and expose in exciting projects.\n\n\nDuties:\u00a0\n\nBuild and optimise batch and streaming data pipelines to provide reliable and organised data products for downstream consumptions (e.g. analytics and machine learning applications)\n\nImprove the deployment of analytical applications utilizing cloud-native architectures and CI/CD tools\n\nRequirements:\u00a0\n\nBachelor\u2019s Degree in Computer Science or\u00a0related disciplines\n1-2 years of experience in data related development\nSolid experience in SQL\nProficiency in Python and at least one static-type programming language (e.g. Java, Scala, C++), especially on concurrency and OOP\n\nIf you are interested in please send us your CV or call us on +852 3619 9859 for a further discussion", "employment_types": ["Full Time", "Permanent"], "selling_points": ["QA, Quality Assurance, Testing, UAT", "Automation Testing, Selenium, Appium", "Manual Testing, JIRA, Test Management tools, Agile"], "locations": ["Central & Western Area"], "categories": ["Information Technology (IT)", "Testing / QA"], "post_time": "2022-01-14T09:10:31Z", "salary": {"currency": null, "max": null, "min": null, "period": "monthly", "term": null}, "salary_visible": false, "title_keywords": [], "responsibilities": ["data"], "requirements": {"degrees": ["degree", "bachelor"], "majors": ["related disciplines", "computer science"], "languages": [], "language_level": [], "hard_skills": ["java", "c++", "sql", "scala", "programming", "python"], "soft_skills": ["interested in"], "languages_combined": []}, "experience_required": {"duration": ["1-2 years"], "field": ["related", "development", "sql"]}}, {"job_id": "100003009047924", "location_code": "hk", "company": "Endeavour Search Limited", "job_title": "Test Manager - Perm Role / Investment Bank Project / Central Office Location", "description": "Our client is a sizable and stable international law firm with a friendly and dynamic working environment. They are recently seeking a receptionist to manage the front desk and support the general office administrative work.\n\nResponsibilities:\n\nSupporting the HR Manager and the Administrative Officer\nManaging the switchboard of the firm\nEnsuring the front desk area, meeting rooms and pantry are clean and tidy\nGreeting all incoming guests and providing professional customer services\nHandling all incoming mails and courier\nManaging the meeting rooms booking system\nClosely working with IT team to prepare the equipment and materials required for meetings and conference calls\nCatering ordering and breakfast / lunch meetings coordination\nStationery and other office supplies ordering\nPrepare the attendance report of internal staff\nLiaising with the building management office on office facilities maintenance\nAd hoc office administrative support\n\n\nRequirements:\n\nTertiary educated with fluency of spoken English\nAt least 1 years working experience in customer service / reception\nGood team player with excellent presentation and communication skills\nCandidates with legal / banking / finance / Big 4 / MNCs background will be considered first\n\nTo Apply\n\nInterested parties please send us your updated resume with your latest and expected salaries or please call +852 3619 9858 or email at legal\uff20djrecruit.com for a confidential discussion.", "employment_types": ["Full Time"], "selling_points": ["Fortune 500 Company / US NASDAQ Listed IT Company", "Wealth Management Project", "Very competitive compensation package"], "locations": ["Not Specified"], "categories": ["Information Technology (IT)", "IT Project Management / Team Lead", "Testing / QA", "Technical / Functional Consulting"], "post_time": "2022-01-14T04:16:23Z", "salary": {"currency": null, "max": null, "min": null, "period": "monthly", "term": null}, "salary_visible": false, "title_keywords": ["manager"], "responsibilities": ["attendance", "ad hoc", "maintenance", "administrative support", "office supplies", "hr", "stationery", "liaising with", "customer services", "building management", "booking", "coordination", "report", "catering"], "requirements": {"degrees": [], "majors": [], "languages": ["english"], "language_level": ["fluency"], "hard_skills": [], "soft_skills": ["communication skills", "good team player", "customer service", "presentation"], "languages_combined": [{"language": "english", "language_level": ["fluency"]}]}, "experience_required": {"duration": ["at least 1 years"], "field": ["customer service"]}}, {"job_id": "100003009053869", "location_code": "hk", "company": "iAsia Online Systems Limited", "job_title": "Project Officer (Project Management Office Team)", "description": "Responsibilities:\n\nReview and analyze system specifications\nCollaborate with Application Development team to develop effective strategies and test plans\nExecute test cases (manual or automated) and analyze results\nEvaluate product code according to specifications\nCreate logs to document testing phases and defects\nReport bugs and errors to development teams\nHelp troubleshoot issues\nConduct post-release/ post-implementation testing\nWork with cross-functional teams to ensure quality throughout the software development lifecycle\n\nRequirements:\n\nProven work experience in software development and\u00a0quality assurance\nAt least 3 years working experience of software quality assurance\nStrong knowledge of software QA methodologies, tools and processes\nExperience in writing clear, concise and comprehensive test plans and test cases.\nHands-on programming experience with automated testing tools\nSolid knowledge of SQL and scripting\nFamiliarity with Agile frameworks and regression testing is a plus\nDiploma in Computer Science, Engineering or a related subject\nCandidate with less experience will be considered as QA Tester\n\nApart from competitive remuneration package and exciting opportunity for career development within the Group, we provide attractive employee benefits such as free company shuttle, free company SIM card and preferential SIM plan offers, comprehensive medical & insurance schemes, as well as full range of other employee well-being provisions.\n\nInterested parties, please apply with full resume, present and expected salary, by clicking \u201cAPPLY NOW\u201d. Please quote the reference number on the e-mail subject.\n\nWe are an equal opportunity employer and welcome applications from all qualified candidates. Personal data collected will be treated in the strictest confidence and handled confidentially by authorised personnel for recruitment-related purposes only within the CK Hutchison Group of companies. The personal data of unsuccessful applicants will be destroyed after the recruitment exercise pursuant to the requirements of the Personal Data (Privacy) Ordinance in Hong Kong.\n", "employment_types": ["Full Time", "Permanent"], "selling_points": ["Experience in Project Mgt or Project Coordination", "Fresh graduate will also be considered", "Immediately available is preferred"], "locations": ["Yau Tsim Mong Area"], "categories": ["Information Technology (IT)", "Support", "Product Management / Business Analyst", "Testing / QA"], "post_time": "2022-01-17T07:39:30Z", "salary": {"currency": null, "max": null, "min": null, "period": "monthly", "term": null}, "salary_visible": false, "title_keywords": ["project officer"], "responsibilities": ["collaborate with", "software", "review", "teams", "implementation", "quality", "develop", "evaluate", "testing", "specifications", "troubleshoot", "plans", "application development", "cross-functional teams", "report"], "requirements": {"degrees": ["diploma"], "majors": ["engineering", "computer science"], "languages": [], "language_level": [], "hard_skills": ["sql", "plus", "agile", "programming"], "soft_skills": ["clear", "hands-on", "comprehensive", "agile"], "languages_combined": []}, "experience_required": {"duration": ["at least 3 years"], "field": ["qa", "testing", "writing", "programming", "software development", "quality assurance"]}}, {"job_id": "100003008998513", "location_code": "hk", "company": "SEEK Asia (JobsDB)", "job_title": "Quality Engineer", "description": "Our client, a leading financial institution, is looking for a\u00a0Head of Quality Assurance CoE\u00a0for their large technology delivery. The selected candidate will drive a high-quality testing delivery across core technology platforms, digital and cloud API services.\n\n\nRequirements:\n\nDevelop and build test strategies for manual, automated, and performance testing which assist the application teams to maintain high-quality software delivery.\nDefine and maintain quality assurance guidelines and standards across the whole firm.\nWork with the key business and technology stakeholders in building the required testing strategy and framework.\nManage the testing teams on building test plans, testing scripts, test reports.\nLead the testing function in the development division and drive testing governance plan for best practices.\nLead the testing in CI/CD environment.\nContributes to testing best practices across the firm.\nManage testing resources across the firm, including in-house testing teams, contractors, external vendors, and offshore resources.\n\nResponsibilities:\n\nExtensive experience in leading a testing function with leadership responsibilities.\nExperience in leading a testing functionality with testing strategy and direction.\nStrong understanding of QA including SAT, and UAT.\nExperience with at least one hybrid automation modern test framework.\nExperience using testing tools including Cucumber and JBehave is a great plus.\nHands-on experience using Atlassian Jira and Confluence.\nStrong knowledge of the Software Development Life Cycle with expertise in QA processes and methodology, specifically in Agile.\nExperience with various test methods, tools, and toolkits: Functional, Automated, Performance.\nStrong working experience in an Agile / DevOps environment.\nExcellent communication skills in English and Chinese (Mandarin & Cantonese)\nBachelor's degree from a reputed University.\n\nIf this outstanding opportunity sounds like your next career move, please send your resume in Word format to Danny Kwan at resume(at)pinpointasia(dot)com and put\u00a0Head of Quality Assurance CoE - Leading Financial Institution in\u00a0the subject header.\n\nData provided is for recruitment purposes only.", "employment_types": ["Full Time", "Permanent"], "selling_points": ["Our motto: Improving Lives through Better Careers", "Company Values: We Care, We Aim High, We Deliver", "Customized career development opportunities"], "locations": ["Quarry Bay"], "categories": ["Information Technology (IT)", "Testing / QA"], "post_time": "2022-01-13T18:48:24Z", "salary": {"currency": null, "max": null, "min": null, "period": "monthly", "term": null}, "salary_visible": false, "title_keywords": ["engineer"], "responsibilities": ["sat", "uat", "software", "data", "quality", "testing", "communication", "recruitment"], "requirements": {"degrees": [], "majors": [], "languages": [], "language_level": [], "hard_skills": [], "soft_skills": [], "languages_combined": []}, "experience_required": {"duration": [], "field": []}}, {"job_id": "100003009044226", "location_code": "hk", "company": "PERSOLKELLY Hong Kong Limited", "job_title": "UAT Tester (Banking)", "description": "The Role\nThe QA Engineer is an advocate for a whole-team approach to quality. They will embed within the development teams to define and execute appropriate strategies which support the functional and non-funtional quality of the Seek Asia mobile apps. This is an individual contributor who will collaborate with the team to build, enhance and execute automated tests. They will perfom manual and exploratory testing as required and will help drive quality engineering within the team.\nKey responsibilities include:\nOwning the test strategies for Seek Asia mobile apps.\nEvolving these test strategies to help continuously improve the Seek Asia mobile apps.\nAdvocating for a quality first approach.\nEnsuring systems are fit for purpose, well architected and follow current SEEK development practices.\nMaintaining platform health ensuring that our systems are secure, reliable, resilient, and cost effective.\nDriving best practice functional testing techniques.\nWorking closely with an agile development teams to build, enhance and execute automated tests.\nShare operational support duties.\nSo, what we are looking for?\nTest-driven development and agile software delivery methods. A familiarity with evolutionary architecture is an asset\nAn understanding of the common problems in software testing and the ability to offer better solutions.\nApplies relevant technologies knowledge to the development and improvement of software applications, being able to drive better technical decision at the team level.\nInvolve in collaboration with stakeholders to understand business challenges and customer needs, remove bottlenecks, and identify new opportunities for growth.\nKnowledge and experience with industry best practices, regulations and compliance (GDPR, PDPI), and quality assurance techniques.\nWorked in a Test Driven Agile Environment.\nExperience working with geo-distributed teams and external consultants.\nPositive attitude and a clear sense of initiative.\nHas a growth mindset - flexible, open, and actively seeking opportunities to improve.\nHighly self-motivated team player with good analytical and conceptual thinking, results-driven and customer focus.\nA solid understanding of software test and quality practices.\nThe ability to understand, navigate and use React Native code.\nExperience using some of Jest, Appium, WebDriver and Cucumber for test development\nKnowledge of CI-CD automation frameworks such as Buildkite and Jenkins\nKnowledge of iOS and Android tooling (Xcode, Apple Developer, Android Studio, Firebase, Playstore.)\nAn understanding of the AWS platform.\nDesired Values\nBelieved in aiming high to deliver world-class results and yet, not forgetting to care for others\nThe Team\nSeek Asia Apps provides products and services to candidates in job markets across the Asia region. We operate under the 3 brands of JobStreet, JobsDB and SEEK to help over 150 million candidates find employment.\nAdditional Information\n\nAt SEEK, the health and safety of our people is our highest priority. For this reason, SEEK has introduced a policy requiring all employees and visitors to be fully vaccinated for COVID-19 within our offices, unless a formal medical exemption applies. In addition, all employees attending in-person work related meetings or events outside the office will also need to be fully vaccinated.\u00a0 We have chosen to share this information early in our hiring process, so that candidates can make an informed choice. On this basis, as part of the application process you will be asked to confirm that you have read and understood this policy, and would like to continue with the hiring process.\u00a0 Further details about this policy will be shared during the hiring process, as required.", "employment_types": ["Full Time"], "selling_points": ["Banking experience in digital project testing", "Experience in performing UAT", "FG is also welcome"], "locations": ["Central & Western Area"], "categories": ["Information Technology (IT)", "Testing / QA"], "post_time": "2022-01-13T03:27:21Z", "salary": {"currency": null, "max": null, "min": null, "period": "monthly", "term": null}, "salary_visible": false, "title_keywords": ["uat tester"], "responsibilities": ["collaborate with", "regulations", "cost", "operational support", "software", "maintaining", "systems", "teams", "quality", "agile development", "testing", "compliance", "architecture"], "requirements": {"degrees": [], "majors": [], "languages": [], "language_level": [], "hard_skills": ["agile", "jenkins", "android studio", "aws", "reason", "mobile", "make", "react native", "code", "focus", "android"], "soft_skills": ["initiative", "flexible", "self-motivated", "agile", "positive attitude", "clear", "customer focus", "team player", "reliable", "driven", "world-class"], "languages_combined": []}, "experience_required": {"duration": [], "field": ["development", "compliance", "quality assurance"]}}, {"job_id": "100003009049648", "location_code": "hk", "company": "Hays", "job_title": "Project Executive (UAT) - Top tier Banking Institution", "description": "Job Responsibilities\n\nDesign and prepare test plan, scenarios and cases\nPerform functional, stability and performance testing on multiple platforms such as windows, web-based system and mobile app\nProvide clear and detailed test report\nProvide track bug fixing status\nEnsure product are delivered with approved quality and timeline\nComplete fast-pacing projects on time with strong sense of responsibility.\nDevelop test automation suite with development teams\nResponsible for system installation and manage the test environment\n\nJob Requirements:\n\nMinimum 1 years' of progressively related experience in relevant field\nDiploma or above in Information System, Computer Science or equivalent\nExperienced on using auto-testing software will be an advantage\nGood interpersonal skill and able to meet commitment and delivery quality service level\nDetail oriented, well organized and able to work independently\nIndependent, analytical, presentable, self-motivated with strong presentation and communication skills\nWorking experience in QA role is preferred\nImmediate availability is preferred\n\n\nUCR Technology\u00a0is an equal opportunity employer and welcomes applications from all qualified candidates. Information provided will be treated in strict confidence and will only be used for recruitment-related purposes.", "employment_types": ["Full Time", "Temporary"], "selling_points": ["Large reputable bank with great company culture", "1-2 years experience in UAT testing preferable", "Fresh Graduates are also welcome"], "locations": ["Not Specified"], "categories": ["Information Technology (IT)", "Support", "Testing / QA"], "post_time": "2022-01-14T09:01:03Z", "salary": {"currency": null, "max": null, "min": null, "period": "monthly", "term": null}, "salary_visible": false, "title_keywords": ["project executive"], "responsibilities": ["installation", "mobile app", "performance testing", "quality", "teams", "design", "develop", "plan", "report"], "requirements": {"degrees": ["diploma or above"], "majors": ["computer science"], "languages": [], "language_level": [], "hard_skills": ["information system"], "soft_skills": ["communication skills", "work independently", "self-motivated", "independent", "confidence", "detail oriented", "well organized", "interpersonal skill", "presentable", "presentation"], "languages_combined": []}, "experience_required": {"duration": ["minimum 1 years"], "field": ["related", "qa"]}}, {"job_id": "100003009050369", "location_code": "hk", "company": "Pathsight Limited", "job_title": "QA Lead / Manager up to 55k - MNC", "description": "Major Responsibilities\n\nPrepare test cases / test scripts and other relevant documents for conducting UAT, certification tests and simulation tests to facilitate a smooth implementation of business projects\nCo-ordinate, prepare, execute and follow up on test cases / scripts and document test results and problem logs\nAssist in maintaining UAT problem logs and coordinate with IT development team to identify the resolution\nManage UAT of small to medium sized projects and prepare relevant documents which include UAT plan\nPrepare and maintain comprehensive documentation for projects being implemented before, during and after testing\nCommunicate and liaise with users and IT teams in carrying out testing\nPromote quality assurance standard and best practices to the team\n\nRequirements\n\nUniversity/ Tertiary education with at least 4 years\u2019 quality assurance experience with exposure in financial sector\nHands-on testing experience in mobile and Web-based applications for financial systems as well as knowledge in ISO20022 message would be an advantage\nTechnical knowledge of SWIFT messages and XML would be preferred\nSolid experience in quality assurance process, competence in writing test plans and scripts preferably with knowledge of financial systems\nStrong logical and analytical mindset and capable of comprehending both business knowledge and technical knowledge\nGood command of written and spoken English and Chinese\nGood interpersonal, presentation and communication skills with sound business sense and detail-oriented\nIndependent, self-motivated, organized and able to work under pressure with tight schedules\n\n\nHow to Apply\nInterested parties please send your curriculum vitae stating your current and expected salaries, and the contact phone number to the Human Resources Division, Unit B, 25/F, MG Tower, 133 Hoi Bun Road, Kwun Tong, Kowloon\u00a0 by clicking the \"Apply Now\" button below.\nAll applications and personal information collected will be treated in strict confidence and only be used for the purpose of recruitment and selection.\u00a0 The information collected will be accessed by our authorized personnel only.\u00a0 Those applicants not contacted by the Human Resources Division within two months from their application date should consider their applications filed for future reference which will be retained for one year for possible future job matching, and will be destroyed after the expiry of one year.", "employment_types": ["Full Time", "Permanent"], "selling_points": ["International working culture, large organization", "5-day, Medical, Dental, Education Allowance, Bonus", "Develop Your Own Career Path"], "locations": ["Not Specified"], "categories": ["Information Technology (IT)", "IT Project Management / Team Lead", "IT Management", "Testing / QA"], "post_time": "2022-01-14T10:13:09Z", "salary": {"currency": null, "max": null, "min": null, "period": "monthly", "term": null}, "salary_visible": false, "title_keywords": ["manager", "lead"], "responsibilities": ["uat", "maintaining", "business projects", "coordinate with", "implementation", "teams", "testing", "resolution", "liaise with", "quality", "maintain", "plan", "documentation"], "requirements": {"degrees": [], "majors": [], "languages": ["english", "chinese"], "language_level": ["good command"], "hard_skills": ["swift", "mobile", "web-based applications"], "soft_skills": ["communication skills", "self-motivated", "organized", "independent", "capable", "business sense", "detail-oriented", "hands-on", "interpersonal", "presentation", "work under pressure"], "languages_combined": [{"language": "english", "language_level": ["good command"]}, {"language": "chinese", "language_level": ["good command"]}]}, "experience_required": {"duration": ["at least 4 years"], "field": ["financial", "testing", "education", "writing", "quality assurance"]}}, {"job_id": "100003009052080", "location_code": "hk", "company": "ADECCO", "job_title": "IT Helpdesk Administrator (General IT support, up to 22k)", "description": "Your new company\n\nYou'll be working in the team of Business Development department within a reputable bank. The team is expanding and aiming to grow a team of people who have strong passion to support UAT test cases.\n\n\n\nYour new role\n\nPrepare and execute UAT test cases according to the user requirements\nReport defect and issues clearly with detail steps using the provided bug tracking tools\nResponsible for BAU test, Production support and Ad-hot tasks\nAssist Test Manager to complete all UAT related activities and support tasks\nProvide assistant on admin tasks assign by management\n\n\nWhat you'll need to succeed\n\nSolid experience in performing UAT\nExperience with production case support\nExperience with performance and/or security testing is a plus\nStrong communication and presentation skill is an advantage\nFamiliar with Excel, HPQC, JIRA - Proficient in of both spoken and written English and Chinese\n\n\n\nWhat you'll get in return\n\nCompetitive benefits and rewards package\nGreat exposure to the banking industry\n\n\n\nWhat you need to do now\n\nIf you are interested in the above position or other project management opportunities, please send your updated CV to Heily Ho at Heily.Ho@hays.com.hk or reach me at +852 2230 7455 for a confidential discussion.", "employment_types": ["Full Time", "Permanent"], "selling_points": [], "locations": ["Pok Fu Lam"], "categories": ["Information Technology (IT)", "Support", "Testing / QA", "Others"], "post_time": "2022-01-17T02:03:02Z", "salary": {"currency": null, "max": null, "min": null, "period": "monthly", "term": null}, "salary_visible": false, "title_keywords": ["administrator", "it support"], "responsibilities": ["management", "uat", "testing", "communication", "report", "tracking"], "requirements": {"degrees": [], "majors": [], "languages": ["english", "chinese"], "language_level": ["proficient"], "hard_skills": ["presentation skill", "excel", "plus"], "soft_skills": ["communication", "presentation skill", "responsible"], "languages_combined": [{"language": "english", "language_level": ["proficient"]}, {"language": "chinese", "language_level": ["proficient"]}]}, "experience_required": {"duration": [], "field": ["security", "testing"]}}, {"job_id": "100003009046336", "location_code": "hk", "company": "IT Solutions Ltd.", "job_title": "UAT Tester (i-Bank - Treasury Products)", "description": "Duties:\n\nResponsible for designing and building the test case(s)\nSet up the testing requirement and objective(s)\nProject management\nCooperate with development lead in project testing issue\nInvolve in the Strategy planning including policies and procedures\nLead the QA Team\nSupport sales, support, and software development team\nIdentify the potential issue\n\n\u00a0Requirements:\n\nDegree or above in CS or other related disciplines\nAt least 6-year working experience in QA field\nExperience in Linux or Window would be advantage\nStrong knowledge in Hardware and Software\nExperience in Cloud / VMWare would be big plus\nKnowledge in networking technology and programming \u2013 JS / Python / JAVA", "employment_types": ["Full Time"], "selling_points": ["An entry position into i-Bank", "Fresh Graduates are also welcome", "Treasury Products"], "locations": ["Central"], "categories": ["Banking / Finance", "Others", "Information Technology (IT)", "Product Management / Business Analyst", "Testing / QA"], "post_time": "2022-01-13T10:35:01Z", "salary": {"currency": null, "max": null, "min": null, "period": "monthly", "term": null}, "salary_visible": false, "title_keywords": ["uat tester"], "responsibilities": ["software", "policies", "procedures", "testing", "project management", "designing", "cooperate with", "planning"], "requirements": {"degrees": ["degree or above"], "majors": ["related disciplines"], "languages": [], "language_level": [], "hard_skills": ["linux", "plus", "java", "vmware", "hardware", "programming", "python"], "soft_skills": [], "languages_combined": []}, "experience_required": {"duration": ["at least 6-year"], "field": ["qa"]}}, {"job_id": "100003009041412", "location_code": "hk", "company": "Osmium Consulting Group Limited", "job_title": "Software QA Engineer / QA Tester ( Manual / Automation )", "description": "We are searching for high-calibre UAT\u00a0Testers\u00a0to perform UAT\u00a0on the i-Bank Treasury Products for New Treasury System Implementation Project\u00a0in a Major Bank.\u00a0 It will be a good entry position into the world of i-Banks.\n\nResponsibilities:\n\nPerorm User Acceptance Test (UAT) for the i-Bank Treasury products.\nAssist to prepare the\u00a0testing report and UAT logs.\n\n\u00a0 \u00a0 \u00a0 ** Training will be provided for suitable candidates\n\nRequirements:\n\nDegree in Business Administration,\u00a0Banking & Finance, Computer Science or\u00a0related fields\nSelf-initiative, hardworking, independent and able to work under\u00a0pressure\nStrong writing & communication skills in English and Chinese (including Mandarin)\nProficiency in MS Excel\nFresh Graduates are also welcome**\n\nBenefits:\u00a0\n\nExcellent opportunity to gain experience\u00a0in Treasury & Capital Market\u00a0and further develop your professional skills in a major banking environment\nAttractive remuneration will be offered to the successful candidates\n\nIf you are interested, please send your resume in MS Word format, specifying your availability, current and expected salaries to:\n\njobs @itsolutions.com.hk\u00a0\n\nor\n\nPlease click the Apply Now button and attach your cv in MS Word Format, specifying your availability, current and expected salaries.\n\nPersonal data collected will be used for recruitment purposes only.\n\nIT Solutions Ltd.\nSuite 2102\n21/F Lucky Building\n39 Wellington Street\nCentral, Hong Kong\n\n(P.S. We do not process applications from overseas for this position)", "employment_types": ["Full Time"], "selling_points": ["MNC | Global FinTech | Software Quality Assurance", "1 Years+ | Tester | Engineer | Large Scale Project", "5 Days Work | Bonus | Medical | Young Culture"], "locations": ["Not Specified"], "categories": ["Information Technology (IT)", "Application Specialist - Software", "IT Project Management / Team Lead", "Testing / QA"], "post_time": "2022-01-12T03:51:23Z", "salary": {"currency": null, "max": null, "min": null, "period": "monthly", "term": null}, "salary_visible": false, "title_keywords": ["engineer"], "responsibilities": ["report", "uat", "testing"], "requirements": {"degrees": ["degree"], "majors": ["finance", "business administration", "computer science"], "languages": ["english", "chinese", "mandarin"], "language_level": [], "hard_skills": ["ms excel"], "soft_skills": ["communication skills", "independent", "self-initiative", "hardworking", "work under pressure"], "languages_combined": [{"language": "english", "language_level": []}, {"language": "chinese", "language_level": []}, {"language": "mandarin", "language_level": []}]}, "experience_required": {"duration": [], "field": []}}, {"job_id": "100003009040583", "location_code": "hk", "company": "Hillman Ross", "job_title": "Software QA Tester (perm, 5-day work)", "description": "Major Responsibilities\n\nDevelop driving and sensing systems of the new generation of robotic devices\nWrite specifications and/or instructions & test plans\nDesign & develop robot prototyping and testing\nSimulate testing environments of systems\nPerform supplier sourcing, engagement, and management\nManage critical components, platform selection, qualification and BOM establishment\n\nRequirements\n\nBachelor degree or above in Computer, Electronics Engineering or related discipline\nMinimum 1 year\u2019s experience in robotics industry\nStrong technical competency and knowledge in motor driving and control systems\nDemonstrate abilities in translating non-technical objectives into design requirements\nExperience in camera modelling, characterization and calibration\nExperience in FE analysis and design for production\nSelf-driven and passionate to learn new things and encounter challenges\nGood collaboration and effective problem-solving skills\nWilling to learn and able to work under pressure\nGood command of spoken English and Chinese (including Putonghua)\n\nInterested parties, please apply together with a detailed resume, stating current and expected salary, and send it via APPLY NOW.\u00a0 Attractive remuneration will be offered in commensurate with qualification and experience.\u00a0\n\nAll personal information received will be treated in strict confidence for employment purpose only.\u00a0 Your application can be considered as unsuccessful if you have not been reached within 3 months.\u00a0 On the other hand, it may be transferred to other companies of our group for job openings.\u00a0 Unsuccessful applications will be destroyed for a period not more than 12 months.\u00a0\n\nhttps://www.computime.com/\nhttps://salus-controls.com/", "employment_types": ["Full Time", "Permanent"], "selling_points": ["Web App, Mobile App and API", "Manual and Automation", "Attractive package"], "locations": ["Not Specified"], "categories": ["Information Technology (IT)", "Testing / QA"], "post_time": "2022-01-12T02:48:36Z", "salary": {"currency": null, "max": null, "min": null, "period": "monthly", "term": null}, "salary_visible": false, "title_keywords": [], "responsibilities": ["management", "systems", "design", "develop", "testing", "specifications", "plans"], "requirements": {"degrees": ["degree or above", "bachelor"], "majors": ["engineering"], "languages": ["putonghua", "english", "chinese"], "language_level": ["good command"], "hard_skills": ["problem-solving skills", "analysis"], "soft_skills": ["passionate", "willing to learn", "problem-solving skills", "driven", "work under pressure"], "languages_combined": [{"language": "putonghua", "language_level": ["good command"]}, {"language": "english", "language_level": ["good command"]}, {"language": "chinese", "language_level": ["good command"]}]}, "experience_required": {"duration": ["minimum 1 year"], "field": ["design"]}}, {"job_id": "100003009048747", "location_code": "hk", "company": "United Asia Finance Limited", "job_title": "Senior Officer, Project Management and Quality Assurance (FinTech and Innovation)", "description": "Job Responsibilities:\n\n\n\nActively initiate and drive continuous improvement of EzyCargo/CX Cargo.com and other distribution tools.\nConsolidate the user requirments from worldside outports to enhance existing booking engines/systems.\nCoordinate, conduct workshop and meetings to understand business nature, process flow.\nArticulate the requirements, implement and support distribution projects and being a business analyst to ensure vendor deliver planned projects in a timely and cost effective manner.\nPrepare testing plan and review test cases and scenarios and documented properly.\nParticipate in system testing cycle (UAT/PT/SIT) and complete the testing in timely & accurate manner.\nDesign, compile and distribute management reports for measuring the KPI/result/usage rate post cutover.\nMaintain user guide/business process for worldwide reservation team on e-booking/booking functions, so as to improve agent self-service functions and increase capacity for revenue generation.\nDesign solutions to cater the unique & special sales practice from different regions, and achieve the global standardization in ultimate goal.\nAssist to formulate worldwide GSA deployment strategies/contract renewal. Assess sales performance of GSA against commission pay-out to ensure commission payout generate the best possible revenue return.\nSupport in financial modelling, to prepare the cargo distribution cost budget and forecast.\n\nJob Requirements:\n\nUniversity degree (Preferably in related disciplines)\nResults-driven individual with proven analytical skills and commercial acumen.\nStrong command of analytical tools e.g. Excel, PowerPoint.\nEager to learn, easy adopt to change/new initiative and able to pick up the knowledge in a fast manner\nDeliver results in timely manner, able to work under high pressure\nStrong communication and presentation skills.\nSome experience in aviation industry is an advantage.\nExperienced candidate will be considered as senior position\n\nWe offer\u00a05-day work\u00a0and attractive remuneration,\u00a0medical and dental insurance,\u00a0provident fund\u00a0and other fringe benefits including\u00a0discounted air tickets\u00a0on Cathay Pacific Airways,\u00a0recreation subsidy,\u00a0birthday leave,\u00a0Airport Express discount\u00a0and\u00a0shuttle bus\u00a0to the right candidate and his/her dependents etc.\u00a0 Interested parties, please submit your detailed CV, stating your present and\u00a0expected salary\u00a0and\u00a0availability\u00a0to us.\n\nWe are an equal opportunity Employer. All CVs and personal data collected are for recruitment purposes and the information will be kept confidential.", "employment_types": ["Full Time"], "selling_points": ["Degree in Information System or related major", "At least 5 years IT solid exp in PM, BA and QA", "Double pay & discretionary bonus"], "locations": ["Wan Chai"], "categories": ["Information Technology (IT)", "IT Project Management / Team Lead", "Product Management / Business Analyst", "Testing / QA"], "post_time": "2022-01-14T07:12:58Z", "salary": {"currency": null, "max": null, "min": null, "period": "monthly", "term": null}, "salary_visible": false, "title_keywords": ["senior officer"], "responsibilities": ["cost", "uat", "design solutions", "sales performance", "workshop", "systems", "review", "budget", "design", "testing", "coordinate", "management reports", "maintain", "business process", "booking", "plan", "forecast"], "requirements": {"degrees": ["university degree"], "majors": ["related disciplines"], "languages": [], "language_level": [], "hard_skills": ["powerpoint", "excel", "acumen", "analytical skills"], "soft_skills": ["timely", "driven", "analytical skills", "communication", "eager to learn", "presentation skills", "work under high pressure", "initiative"], "languages_combined": []}, "experience_required": {"duration": [], "field": []}}, {"job_id": "100003009039850", "location_code": "hk", "company": "Accedo Broadband Asia Limited", "job_title": "Quality Assurance Engineer", "description": "Are you an expertise in testing? We are seeking a candidate who is familiar with testing, programming and who is able to work closely with the manager for duties such as, test program, functional and non-functional test. More information will be provide below.\n\n\u5ba2\u6237\u7b80\u4ecb\n\nMy client is one of the Japanese bank with more than 50 offices in overseas. They are seeking a candidate who has knowledge in programming such as Java and Python. In addition, it will be a benefit if you have previously experienced in a Unix working environment.\n\n\u5de5\u4f5c\u5185\u5bb9\n\nResponsible for programming duties\nYou are expected to assist with preparing programme\nAssisting with the development and implementation of e.g test program, test script etc\nHandling with test result and work closely with manager for enhancement\nDealing with ongoing process and management\n\n\u7406\u60f3\u7684\u6c42\u804c\u8005\n\nDegree holder in Computer science, information technology or any other related major\nFamiliar with Java/Python/Javescript/UNIX/UAT testing\nPreviously worked as a programmer or knowledge in automation will be a benefit\nProficiency in both Chinese and English\n\n\u798f\u5229\u5f85\u9047\n\nCompetitive salary package\nAnnual leave 16 days up\nGood working location\nGreat career progression\n\nTo apply online please click the 'Apply' button below. For a confidential discussion about this role please contact Kiki Chan on +852 3602 2433.", "employment_types": ["Full Time"], "selling_points": ["MNC culture", "APAC projects", "Diverse team members"], "locations": ["Kwun Tong"], "categories": ["Information Technology (IT)", "Testing / QA"], "post_time": "2022-01-11T12:26:12Z", "salary": {"currency": null, "max": null, "min": null, "period": "monthly", "term": null}, "salary_visible": false, "title_keywords": ["engineer"], "responsibilities": ["management", "uat testing", "implementation", "testing", "contact"], "requirements": {"degrees": ["degree holder"], "majors": ["computer science", "information technology"], "languages": ["japanese", "english", "chinese"], "language_level": ["proficiency"], "hard_skills": ["python", "java", "programming"], "soft_skills": ["responsible"], "languages_combined": [{"language": "japanese", "language_level": []}, {"language": "english", "language_level": ["proficiency"]}, {"language": "chinese", "language_level": ["proficiency"]}]}, "experience_required": {"duration": [], "field": []}}, {"job_id": "100003009037544", "location_code": "hk", "company": "Hong Kong Technology Venture Company Limited", "job_title": "Software Quality Assurance Assistant ($17k for Fresh Graduate)", "description": "Job Responsibilities:\n\nLead, manage and implement projects to ensure the timelines and quality of deliverables\nMonitor project budget and progress and maintain good relationship with users, IT and vendors\nManage project processes, documentation, progress reporting, status meeting and escalation effectively\nAssist users on UAT test plan, schedule and cases preparation\nAssist in UAT execution and problem diagnosis\nPrepare training materials, conduct training and assist in matters related to system implementation\nAdminister the entire software development life cycle based on Agile framework\nContribute to development and maintenance of project standards, processes, and best practices\n\nJob Requirements:\n\nDegree holders or above major in Information System or Computer Science or related discipline preferable\nAt least 5 years IT solid experience in application project management, business analysis and quality assurance in either finance, banking, or other financial sector related fields\nSolid experience in managing and liaison with IT people or software vendors\nStrong knowledge of QA methodologies, tools and processes\nLogical thinker, results-oriented and with excellent project management, communication, problem solving and analytical skills\nProficient in both spoken and written Chinese and English, with good spoken of Putonghua a must\nImmediate available or short notice period is highly desirable\n\nWe offer attractive remuneration package which includes double pay and discretionary bonus. Interested parties please send your CV indicating your current salary, expected salary and availability to HR Department, byclicking \u201cApply Now\u201d\n\n(Personal data collected will be treated in the strictest confidence and will be handled by authorized personnel for recruitment-related purposes only. Applicants who do not hear from us within 3 months may consider their application unsuccessful and their data will be destroyed within 24 months of receipt.)", "employment_types": ["Full Time"], "selling_points": ["Interested in mobile app and web", "Good knowledge on mobile application and web page", "Young & energetic work environment"], "locations": ["Tseung Kwan O"], "categories": ["Information Technology (IT)", "Product Management / Business Analyst", "Testing / QA"], "post_time": "2022-01-11T03:05:05Z", "salary": {"currency": null, "max": null, "min": null, "period": "monthly", "term": null}, "salary_visible": false, "title_keywords": ["quality assurance assistant"], "responsibilities": ["reporting", "uat", "software", "maintenance", "budget", "monitor", "quality", "implementation", "maintain good relationship", "schedule", "plan", "documentation"], "requirements": {"degrees": ["degree"], "majors": ["computer science"], "languages": ["putonghua", "english", "chinese"], "language_level": ["good", "proficient"], "hard_skills": ["analysis", "information system", "analytical skills", "problem solving", "project management"], "soft_skills": ["communication", "project management", "problem solving and analytical skills"], "languages_combined": [{"language": "putonghua", "language_level": ["good", "proficient"]}, {"language": "english", "language_level": ["good", "proficient"]}, {"language": "chinese", "language_level": ["good", "proficient"]}]}, "experience_required": {"duration": ["at least 5 years"], "field": ["financial", "related", "finance", "project management", "it", "banking", "business analysis", "quality assurance"]}}, {"job_id": "100003009042411", "location_code": "hk", "company": "Infocean Technology Co Ltd", "job_title": "Junior Business Analyst (5 day work)", "description": "Our client, a well-known bank in Hong Kong is looking for a UAT Tester for designing and executing test cases as well as to coordinate the setup of test environments for digital projects.\n\nMain responsibilities:\n\nPrepare and review accurate and complete test scripts through a detailed understanding of the business user requirements, and functional specification documents delivered for each project\nReport UAT testing progress/test results/issue logs to the project team in an efficient and detailed manner\nVerify defect fixes and report retest results\nEnsure the validated deliverables meet functional system specifications and requirements\nReviewing test scripts received from the offshore team and external parties for completeness and to ensure appropriate regression test scripts are available to test \u201caround\u201d enhancement areas as is appropriate\nWork with cross-functional teams to ensure system quality\nRequirements:\n\nDiploma graduate or above, preferably in Information Technology, Computer Science or equivalent\nExperience in performing UAT on digital platforms such as web, app, secure and insecure sites\nPrior experience in banking is preferable\nFresh graduates will also be considered\n\n\n\nTo apply for this position, please send your full r\u00e9sum\u00e9 to\u00a0Contract_hk @persolkelly.com\u00a0in word format indicating the reference number and title.\n\nIf you are not contacted by our consultants within 2 weeks, please consider your application unsuccessful. All applications will be treated in strict confidence, and used for recruitment purposes only in accordance with\u00a0PERSOLKELLY Hong Kong Limited\u2019s Privacy Notice.", "employment_types": ["Full Time", "Permanent"], "selling_points": [], "locations": ["Tsim Sha Tsui"], "categories": ["Information Technology (IT)", "Support", "Product Management / Business Analyst", "Testing / QA"], "post_time": "2022-01-12T07:22:12Z", "salary": {"currency": null, "max": null, "min": null, "period": "monthly", "term": null}, "salary_visible": false, "title_keywords": ["business analyst", "junior"], "responsibilities": ["external parties", "review", "uat testing", "quality", "specifications", "cross-functional teams", "report"], "requirements": {"degrees": ["diploma"], "majors": ["computer science", "information technology"], "languages": [], "language_level": [], "hard_skills": ["word", "web"], "soft_skills": ["confidence"], "languages_combined": []}, "experience_required": {"duration": [], "field": ["digital", "banking"]}}, {"job_id": "100003009038196", "location_code": "hk", "company": "Anywhere Everywhere Six Degrees Link Limited", "job_title": "QA Engineer, Automation/ Manual ( Fresh Graduates are welcome )", "description": "Responsibilities:\nConduct functional tests on software products based on test plans and coordinate with developers and project managers\nReproduce defects for investigation\nAssist design and create test plans, test scripts and other relevant documents\nRequirements\n\n\nTo qualify for the role you must have:\n\nHigher Diploma or above in Computer Science, Information Technology, Information System or equivalent\nGraduates from other disciplines, who are interested to develop career in tech industry would also be considered\nUnderstanding and use of testing techniques\nGood communication skills in both English and Chinese\nTeam player, self-motivated, well organized and ability to work under pressure\nFresh graduates would be considered\u00a0\u00a0\n\nWhat working at EY offers:\n\nSupport, coaching and feedback from some of the most engaging colleagues around\nOpportunities to develop new skills and progress your career\nThe freedom and flexibility to handle your role in a way that\u2019s right for you\n\nIf you can confidently demonstrate that you meet the criteria above, please contact us as soon as possible.\n\nJoin us in building a better working world.\n\nApply now.", "employment_types": ["Full Time"], "selling_points": ["Salary : 25K - 40K + Bonus ( 1 - 2 Months )", "Automation : Selenium / Appium / Postman | Manual", "Work Life Balance | 14 ALs | Medical + Dental"], "locations": ["Yau Tsim Mong Area"], "categories": ["Information Technology (IT)", "Testing / QA", "Technical Writing", "Others"], "post_time": "2022-01-11T05:59:36Z", "salary": {"currency": "HKD", "max": 44999, "min": 25000, "period": "monthly", "term": null}, "salary_visible": true, "title_keywords": ["engineer"], "responsibilities": ["software", "coordinate with", "investigation", "design", "plans"], "requirements": {"degrees": ["higher diploma or above"], "majors": ["computer science", "information technology"], "languages": ["english", "chinese"], "language_level": ["good"], "hard_skills": ["information system"], "soft_skills": ["communication skills", "self-motivated", "well organized", "team player", "work under pressure"], "languages_combined": [{"language": "english", "language_level": ["good"]}, {"language": "chinese", "language_level": ["good"]}]}, "experience_required": {"duration": [], "field": []}}, {"job_id": "100003009044118", "location_code": "hk", "company": "Seamatch Asia Limited", "job_title": "Project Manager/ Business Analyst/ Project officer/ QA Trainee/ UAT Tester (Welcome Fresh)", "description": "Responsibilities:\n\nParticipate in various life system projects; ensure the quality and timely delivery of admin system;\nCollect and analyse information from admin users for preparing user requirements;\nLiaise with admin users and MIS/IT in system design and enhancement;\nPerform User Acceptance Test;\nConduct end-user training;\nSupport ad hoc production problems.\n\n\n\nRequirements:\n\nUniversity graduates;\nExperience in system development projects or life insurance company is an advantage;\nGood analytical and problem solving skills;\nDetail-oriented and strong communication skill with different levels;\nGood command of both written and spoken English;\nGood team player and able to work independently;\nAble to work under pressure to meet tight deadlines;\nCandidates with\u00a0more experience will be considered as\u00a0Business Analyst\n\n\n\nInterested parties, please send your FULL RESUME with availability, current and expected salary by clicking \"Apply Now\".\n\nPersonal data collected will be used for recruitment purpose only.", "employment_types": ["Full Time"], "selling_points": ["Project Manager, Business analyst, QA", "Project Management", "SDLC, UAT, user requirement collection"], "locations": ["Not Specified"], "categories": ["Information Technology (IT)", "IT Project Management / Team Lead", "Product Management / Business Analyst", "Testing / QA"], "post_time": "2022-01-13T03:07:38Z", "salary": {"currency": null, "max": null, "min": null, "period": "monthly", "term": null}, "salary_visible": false, "title_keywords": ["trainee", "uat tester", "project officer", "project manager", "business analyst"], "responsibilities": ["ad hoc", "quality", "system design", "liaise with", "analyse"], "requirements": {"degrees": [], "majors": [], "languages": ["english"], "language_level": ["good command"], "hard_skills": ["problem solving skills"], "soft_skills": ["good team player", "work independently", "meet tight deadlines", "communication skill", "detail-oriented", "analytical and problem solving skills", "work under pressure"], "languages_combined": [{"language": "english", "language_level": ["good command"]}]}, "experience_required": {"duration": [], "field": ["life insurance company", "business", "system development"]}}, {"job_id": "100003009043186", "location_code": "hk", "company": "AEON CREDIT SERVICE (ASIA) CO., LTD.", "job_title": "QA Specialist \u2013 System Development, IT Division (Perm position)", "description": "Job Description:\n\nResponsible for the development of web applications including programming, testing, implementation, and other related support services\nPrepare design documentations, functional specifications and users guides related to the applications developed\nPerform system development, testing, implementation, maintenance support and user training\nDevelop, enhance, and provide supports to existing systems and applications\nProvide ad hoc support to daily operation\n\nRequirement:\n\nHigher Diploma/ Associate Degree/ Degree in Computer Science, Information Technology, or related disciplines.\n0-3 years experiences in software development and familiar with all aspects of software engineering and software development life cycle.\nHands-on front-end development by using Node.js, React Native, Angular, jQuery, JavaScript, HTML5, CSS, etc.\nExperience in software development team and systems analysis is a plus.\nGood interpersonal skills are also essential as a high level of teamwork is expected\nProactive, problem-solving and willing to learn new technologies\nFluent in English, and preferable if Cantonese and Mandarin too\nBootCamp graduated candidate is welcome.\nCandidate with less experience will be considered as Junior Programmer.", "employment_types": ["Full Time", "Permanent"], "selling_points": ["Degree holder in Computer Science", "Minimum 3 years or above relevant experience", "Apply unit testing, SIT and UAT, system testing"], "locations": ["Tsim Sha Tsui"], "categories": ["Information Technology (IT)", "Software Development", "Testing / QA", "Network & System"], "post_time": "2022-01-12T10:06:29Z", "salary": {"currency": null, "max": null, "min": null, "period": "monthly", "term": null}, "salary_visible": false, "title_keywords": ["specialist"], "responsibilities": ["ad hoc", "maintenance support", "support services", "systems", "implementation", "design", "testing", "develop", "daily operation", "specifications"], "requirements": {"degrees": ["associate degree", "diploma", "degree"], "majors": ["related disciplines", "computer science", "information technology"], "languages": ["cantonese", "english", "mandarin"], "language_level": ["fluent"], "hard_skills": ["plus", "jquery", "analysis", "problem-solving", "javascript", "react native", "angular", "css"], "soft_skills": ["problem-solving", "teamwork", "willing to learn", "hands-on", "interpersonal skills", "proactive"], "languages_combined": [{"language": "cantonese", "language_level": []}, {"language": "english", "language_level": ["fluent"]}, {"language": "mandarin", "language_level": []}]}, "experience_required": {"duration": ["0-3 years"], "field": ["engineering", "team", "software development"]}}, {"job_id": "100003009041380", "location_code": "hk", "company": "Osmium Consulting Group Limited", "job_title": "Automation QA Engineer - MNC", "description": "Senior Electronic Engineer / Electronic Engineer (NPI)\n\nJob responsibilities:\n\nDefine the test requirement and production flow of new production line.\nDevelop new production test methodology if necessary.\nWork with Contract Manufacturer to setup the production line per required timeline.\nQualify each test station and whole production line by using systematic quality tools.\nSupport continuous production improvement actions to increase the production yield and efficiency.\nProvide technical training of new technology to Contract Manufacturer if necessary.\n\nJob requirements:\u00a0\n\nBachelor\u2019s Degreein Electronic Engineering or related engineering\nOver 5 years\u2019 experience onwireless consumer electronics manufacturing industry such as Set Top Box, Wi-Fi router and power line modem, etc.\u00a0 Less experience will be considered as Electronic engineer.\nSound RF knowledge such as Wi-Fi, Bluetooth, LTE, or Zigbee technologies.\nStrong knowledge and experience with various RF test equipment\nFluent in English and Mandarin and good PC skills\nTeam player with well-developed interpersonal skills\nProactive, self-motivated and excellent communication skills\nFrequent travel to China and oversea", "employment_types": ["Full Time", "Permanent"], "selling_points": ["MNC", "good working location", "Attractive benefits & 5 day work week"], "locations": ["Wan Chai"], "categories": ["Information Technology (IT)", "Software Development", "Testing / QA", "E-commerce", "Software Development"], "post_time": "2022-01-12T03:49:21Z", "salary": {"currency": "HKD", "max": 44999, "min": 25000, "period": "monthly", "term": null}, "salary_visible": true, "title_keywords": ["engineer"], "responsibilities": ["quality", "setup", "develop"], "requirements": {"degrees": ["bachelor"], "majors": ["engineering"], "languages": ["english", "mandarin"], "language_level": ["good", "fluent"], "hard_skills": ["router", "pc skills", "wi-fi"], "soft_skills": ["communication skills", "self-motivated", "interpersonal skills", "team player", "proactive"], "languages_combined": [{"language": "english", "language_level": ["fluent", "good"]}, {"language": "mandarin", "language_level": ["fluent", "good"]}]}, "experience_required": {"duration": ["5 years"], "field": ["manufacturing industry"]}}, {"job_id": "100003009042283", "location_code": "hk", "company": "Global Talent Services Limited", "job_title": "UAT Tester (Large Bank, one-year contract, $16K) (Ref:GTS_JH_UAT)", "description": "Meta Air Labs Limited is an Enterprise-Grade Blockchain as a Solutions (BaaS) Service Provider based in Hong Kong. We are looking for talented candidates to join us . If you are passionate in blockchain technology and want a new fresh start for your career path, SEND US YOUR LATEST CV!\n\nYour role:\n\nResponsible for the e-wallet product, liaise with business users, vendor, and internal IT team to ensure smooth delivery of the project.\nGather\u00a0and\u00a0analyze user requirement into functional specifications\nExecute user acceptance testing including test planning, execution, and defect management\nConduct market research and analysis to identify business needs and opportunities\u00a0\n\nWe look for:\n\nDegree holder in Business Management, IT or related disciplines\n2 years or above in business analysis and/or system analysis experiences\nPrevious working in Fintech industry is preferred\nStrong business analysis skills on requirement gathering and documentation\nSolid experience in software testing including planning, execution, and result document\nStrong analytical and problem-solving skills with the ability to work under dynamic environment and multi-tasking\nProficiency in spoken and written English, Cantonese, and Mandarin\nImmediately available is highly preferred\n\u00a0#\u00a0Candidates with more experience will be considered as\u00a0Senior\u00a0Product Development Officer\n\n\nWe offer:\n\nAttractive remuneration package with performance bonus\nPrivilege insurance plan for group medical (covers clinical, hospitalization with supplementary major medical) & dental\n5-day work week, flexible working hours\nConvenient office location in Tsimshatsui\nWork with the young and energetic team\nOpportunities to participate in blockchain projects\nFree snacks, coffee, and tea\nFestival red packets and gifts\nEmployee referral bonus\nRegular staff activities\n\nIf you are interested in this position and want to get a new exposure in Fintech industry, please don\u2019t hesitate to apply with your full resume, present/expected salary and availability by click on the 'Apply Now' button.\u00a0\n\nAll personal data collected will be\u00a0treated in strict confidence\u00a0and used for recruitment purposes only.", "employment_types": ["Full Time", "Contract"], "selling_points": [], "locations": ["North Point"], "categories": ["Information Technology (IT)", "Application Specialist - Software", "Support", "Testing / QA"], "post_time": "2022-01-12T06:50:45Z", "salary": {"currency": null, "max": null, "min": null, "period": "monthly", "term": null}, "salary_visible": false, "title_keywords": ["uat tester"], "responsibilities": ["user requirement", "management", "documentation", "business analysis", "software", "conduct market research", "analysis", "testing", "specifications", "liaise with", "planning"], "requirements": {"degrees": ["degree holder"], "majors": ["related disciplines", "business", "it"], "languages": ["cantonese", "english", "mandarin"], "language_level": ["proficiency"], "hard_skills": ["blockchain", "business management", "analysis", "vendor", "dynamic", "documentation", "problem-solving skills"], "soft_skills": ["passionate", "dynamic environment", "responsible", "multi-tasking", "smooth", "problem-solving skills"], "languages_combined": [{"language": "cantonese", "language_level": ["proficiency"]}, {"language": "english", "language_level": ["proficiency"]}, {"language": "mandarin", "language_level": ["proficiency"]}]}, "experience_required": {"duration": ["2 years"], "field": ["business analysis", "product development", "planning", "testing"]}}, {"job_id": "100003009038473", "location_code": "hk", "company": "Seamatch Asia Limited", "job_title": "Business Analyst / Project Coordinator / QA Officer (Fresh is welcome)", "description": "Duties:\n\nDevelop, configure and implement system applications and external system interfaces in accordance to user requirements\nPerform unit testing, system integration testing and project implementation with knowledge of methodologies and procedures for application testing and quality assurance\nInvestigate into defects, research for problem resolution and implementation problem rectification\nPlan and assist in User Acceptance Testing\nAssist with application training for users\nParticipate in implementation roll-out\nProvide operational support and ongoing maintenance and enhancement after implementation, including troubleshooting of production issues\n\nRequirements:\n\nHigher Diploma or above in Computer Science / Information Technology or equivalent\nAt least 2 years solid experience in application development\nProficient in .NET framework and Angular\nStrong understanding of object-oriented programming\nCreating database schemas that represent and support business processes\nAble to work independently to meet project deadlines with minimum supervision, and a good team player\nGood interpersonal and communication skills\n\nFor more job opportunity, please visit our website: www.clts.com\n\nThe personal information collected is strictly for recruitment purpose only.", "employment_types": ["Full Time", "Permanent"], "selling_points": ["Junior BA, (Web/ Mobile/ Bank/ telecom projects)", "Project Coordinator, QA Officer (Junior & Senior)", "Large Corp/ Team exp, Good language/ Communication"], "locations": ["Central & Western Area"], "categories": ["Information Technology (IT)", "IT Project Management / Team Lead", "Product Management / Business Analyst", "Testing / QA"], "post_time": "2022-01-11T07:02:07Z", "salary": {"currency": null, "max": null, "min": null, "period": "monthly", "term": null}, "salary_visible": false, "title_keywords": ["officer", "business analyst", "project coordinator"], "responsibilities": ["operational support", "maintenance", "rectification", "procedures", "implementation", "quality", "testing", "develop", "resolution", "troubleshooting", "plan"], "requirements": {"degrees": ["higher diploma or above"], "majors": ["computer science", "information technology"], "languages": [], "language_level": [], "hard_skills": ["programming", "angular"], "soft_skills": ["communication skills", "good team player", "work independently", "interpersonal"], "languages_combined": []}, "experience_required": {"duration": ["at least 2 years"], "field": ["application development"]}}, {"job_id": "100003009041221", "location_code": "hk", "company": "Ai Pu Jing Software Technology (Hong Kong) Co Ltd", "job_title": "Software Test Analyst", "description": "What You Will Be Doing\n\n\nCollect and consolidate user requirements and turn them into structural system specifications\nDesign and create clear and detail-oriented test plans/cases\nExecute manual and automated test suites throughout projects\nReport discrepancies discovered and compose test reports\nReproduce defects for investigation\n\nWho is our Right Fit\n\n\nBachelor Degree in any discipline is welcomed. Candidates with Degree in Computer Science / Information Technology or equivalent will be an advantage.\n1 year working experience in software development related area, fresh grads are also welcome\nKnowledge in software development life cycle (SDLC) and agile development method\nQA experience is an asset\nGood knowledge on mobile application and web page\nInterested in playing around with mobile application and web page\nFast learner, logical thinking and pay attention to details\nGood communication and reporting skills in English and Chinese\nAble to handle multitasks in a fast-paced environment\nCandidates with programming background are welcomed", "employment_types": ["Full Time", "Permanent"], "selling_points": ["2 Years Related Experience", "Able to Manage testing lifecycle & deliverable", "U-Degree in Computer Science or related discipline"], "locations": ["Kowloon Bay"], "categories": ["Information Technology (IT)", "Software Development", "Testing / QA", "Others"], "post_time": "2022-01-12T03:36:46Z", "salary": {"currency": null, "max": null, "min": null, "period": "monthly", "term": null}, "salary_visible": false, "title_keywords": ["analyst"], "responsibilities": ["reporting", "software", "agile development", "design", "investigation", "communication", "specifications", "reports", "plans", "report"], "requirements": {"degrees": ["degree", "bachelor"], "majors": ["computer science", "information technology"], "languages": ["english", "chinese"], "language_level": ["good"], "hard_skills": ["agile", "web", "mobile", "sdlc", "programming"], "soft_skills": ["agile", "fast-paced environment", "interested in", "detail-oriented", "clear", "communication", "attention to details", "fast learner"], "languages_combined": [{"language": "english", "language_level": ["good"]}, {"language": "chinese", "language_level": ["good"]}]}, "experience_required": {"duration": ["1 year"], "field": ["related", "qa", "software development"]}}, {"job_id": "100003009037668", "location_code": "hk", "company": "GDC Technology Limited", "job_title": "Software Test Engineer", "description": "A large bank urgently requires following high calibre to join their team:\n\nResponsibilities and requirements:\n\nUAT testing\nSupport other business requirements\nPreferred Tester Experience\nHaving testing experience in banking system\nAttention to details, persistent and patient\n\nOur client offers attractive remuneration package to right candidates. Interested parties please send full resume with present and expected salary to us.\n\n(Data collected will be used for recruitment purpose only)", "employment_types": ["Full Time"], "selling_points": [], "locations": ["North Point"], "categories": ["Information Technology (IT)", "Software Development", "Testing / QA", "Others", "Student / Fresh Graduate / No Experience"], "post_time": "2022-01-11T03:25:55Z", "salary": {"currency": null, "max": null, "min": null, "period": "monthly", "term": null}, "salary_visible": false, "title_keywords": ["engineer"], "responsibilities": [], "requirements": {"degrees": [], "majors": [], "languages": [], "language_level": [], "hard_skills": [], "soft_skills": ["persistent", "patient", "attention to details"], "languages_combined": []}, "experience_required": {"duration": [], "field": ["banking", "testing"]}}, {"job_id": "100003009039451", "location_code": "hk", "company": "Ai Momentum Limited", "job_title": "Application Tester", "description": "We have a full-time position available, looking for a couple of talents to assist with tracking and reporting on progress and performance of projects.\n\nBusiness Analyst\n\nCommunicate with customers to analyze functional and nonfunctional requirements;\nPrepare system documentations including functional specification and system testing;\nConduct analysis on the existing systems and availability of solutions and technologies in the market;\nPrepare training materials and provide user training and implementation support;\nPerform\u00a0Quality Assurance and provide User Acceptance Testing (UAT) and production support of the application\nWork closely with project manager and software development team for project implementation & delivery\n\nGeneral Requirements:\n\nUniversity graduate preferably in Computer Science, Information System, Finance or related discipline\n2-3 years relevant working experience in business / finance / technology analysis\nAbility to deliver according to schedule and quality criteria\nExperience in Application development will be an advantage\nGood planning, time management and organizational skills\nProactive, fast-learning,\u00a0self-motivated\u00a0and able to work under pressure and independently;\nProficiency in English, Cantonese and Putonghua\nMore experience will be consider as Senior Business analyst/Project Manager\n\n\nProject Coordinator\n\n\nAssist Project Manager to prepare project proposal and planning\nGather project status information, preparing project status reports and budget usage reports\nOrganize project meeting by preparing agenda, issuing meeting notice and handling minutes and records\nCoordinate assigned projects by working closely with internal departments, project team members and third parties\nUnderstand customer business flow & perform system implementation\nApply quality assurance procedure and hold user acceptance test\nConduct user training on system usage\n\nGeneral Requirements:\n\nHigher Diploma or above in Computer Science, Information Technology, Business or related discipline\n1-2 years working experience in project execution activities, working with IT projects is desirable\nKnowledge of Software Development is preferred\nProficient in Microsoft Office (Word, Excel, PowerPoint) and Chinese input method\nGood problem solving skill and strong communication skill\nSelf-initiative, be able to work independently\n\n\nQuality Assurance Officer\n\nPrepare user requirements and specifications for system development\nReview user requirements, functional specifications and prepare test specification / plan\nPerform functional testing, regression testing, performance testing & exploratory testing and provide test report\nCollaborate with developers and reproduce defects for debug plan\nDesign contingency test case for unexpected scenarios\nParticipate in planning, design and testing phases of the application development\nFollow up with related parties to ensure the smooth implementation of the new products or services\n\nRequirements:\n\nDegree in computer science or software QA related disciplines\nMin 1 year related experience\nInterest and passion in new technology\nStrong in problem solving analysis, troubleshooting, web application testing, analytical thinking and communications skills\nTechnical background on Responsive Website, Mobile Apps and Software Test Tools is a plus\nExperience in using software test automation tools is a plus\nGood presentation skill on verbal and written English and Chinese\nLess experience or Fresh Graduate will be consider as Junior position", "employment_types": ["Full Time", "Contract"], "selling_points": [], "locations": ["Kowloon Bay"], "categories": ["Information Technology (IT)", "Application Specialist - Software", "Testing / QA"], "post_time": "2022-01-11T16:01:52Z", "salary": {"currency": null, "max": null, "min": null, "period": "monthly", "term": null}, "salary_visible": false, "title_keywords": [], "responsibilities": ["collaborate with", "software", "budget", "quality", "troubleshooting", "design", "website", "communication", "plan", "application development", "work under pressure", "uat", "implementation", "testing", "reports", "schedule", "report", "reporting", "management", "review", "specifications", "tracking", "communicate with", "performance testing", "analysis", "systems", "coordinate", "planning"], "requirements": {"degrees": ["university graduate", "higher diploma or above", "degree", "fresh graduate"], "majors": ["finance", "information technology", "related disciplines", "business", "computer science"], "languages": ["cantonese", "putonghua", "english", "chinese"], "language_level": ["good", "proficiency", "proficient"], "hard_skills": ["chinese input", "excel", "plus", "presentation skill", "web", "microsoft office", "analysis", "information system", "word", "powerpoint", "problem solving", "mobile", "system implementation", "documentations"], "soft_skills": ["presentation skill", "organizational skills", "self-motivated", "proactive", "independently", "work independently", "passion in", "communication skill", "troubleshooting", "fast-learning", "problem solving", "self-initiative", "smooth", "problem solving skill", "time management", "responsive", "work under pressure"], "languages_combined": [{"language": "cantonese", "language_level": ["proficiency"]}, {"language": "putonghua", "language_level": ["proficiency"]}, {"language": "english", "language_level": ["good", "proficiency"]}, {"language": "chinese", "language_level": ["good", "proficient"]}]}, "experience_required": {"duration": ["min 1 year", "1-2 years", "2-3 years"], "field": ["technology analysis", "related", "finance", "relevant working experience", "business", "it", "application development"]}}, {"job_id": "100003009046430", "location_code": "hk", "company": "BOC Credit Card (International) Limited", "job_title": "Contract Product Development Officer / Senior Product Development Officer \u2013 UAT (PDDCPDO-2201)", "description": "Responsibilities:\n\nReviewing software requirements and preparing test scenarios\nExecuting tests on software usability\nAnalyzing test results on application impacts, errors or bugs, and usability\nPreparing reports on all aspects related to the software testing carried out and reporting to the design team\nInteracting with team members to understand product requirements\nParticipating in design reviews and providing input on requirements, product design, and potential problems\n\nRequirements:\n\nDiploma or above in computer science, information technology or related field\nMinimum 1 year related working experience\nUp-to-date knowledge of software test design and testing methodologies\nKnowledge of test techniques and compatibility with various software programs is an advantage\nKnowledge of programming\nExcellent communication and critical thinking skills\nGood organizational skills and detail-oriented mindset\n\nWe offer 5 day work per week (except certain Saturdays according to specific project requirements), 12-months contract, medical plan, free shuttle bus, free snacks & beverages, happy & harmonious working environment.\n\nFor interested parties, please submit your full resume with current & expected salary, and state your availability in MS Word Format. Application without salary information will not be considered. All information provided will be treated in strict confidence and used solely for recruitment purposes.", "employment_types": ["Contract"], "selling_points": ["Formulate system test plan", "Post-secondary or above", "Preparation and execution of User Acceptance Test"], "locations": ["Not Specified"], "categories": ["Banking / Finance", "Others", "Information Technology (IT)", "Product Management / Business Analyst", "Testing / QA"], "post_time": "2022-01-13T11:37:23Z", "salary": {"currency": null, "max": null, "min": null, "period": "monthly", "term": null}, "salary_visible": false, "title_keywords": ["officer", "product development"], "responsibilities": ["reporting", "software", "design", "testing", "product design", "executing", "preparing reports"], "requirements": {"degrees": ["diploma or above"], "majors": ["computer science", "information technology"], "languages": [], "language_level": [], "hard_skills": ["programming"], "soft_skills": ["communication", "organizational skills", "harmonious", "detail-oriented"], "languages_combined": []}, "experience_required": {"duration": ["minimum 1 year"], "field": ["related"]}}, {"job_id": "100003009034860", "location_code": "hk", "company": "Osmium Consulting Group Limited", "job_title": "Software QA Engineer / QA Tester ( Manual / Automation )", "description": "Responsibilities:\n\nParticipate in the preparation and execution of User Acceptance Test (UAT) for various projects\nArrange and maintain the schedules of various teams and department meetings\nAssist in preparing PowerPoint presentations, Excel spreadsheets\n\n\nRequirements:\n\nHigher Diploma or Degree qualification in Business Administration, Secretarial Studies or related disciplines \uf06c\nExcellent interpersonal skills with an ability to meet and deal with all levels in a professional and courteous manner \uf06c\nGood ability to prioritize, multi-task and work flexibly and independently with high level of accuracy \uf06c\nHigh integrity in maintaining strict confidentiality when dealing with sensitive information and matters \uf06c\nExcellent proficiency in MS Office applications and English/Chinese word processing; solid experience in report preparation \uf06c\nGood proficiency of written and spoken English, Cantonese and Putonghua \uf06c\nRelevant working experience in card products /payment / banking industry is an added advantage skills\n\nApplicants for the above positions must be proficient in spoken and written Chinese (including Mandarin) and English, and be competent in MS Office applications.\n\nAttractive remuneration packages will be offered to suitable candidates. Interested parties please send full resume with present and expected salary to Adminstration Department, 20/F BOC Credit Card Centre, 68 Connaught Road West, H.K. (Please quote Ref. no.) OR email via \"Apply Now\".\n\n\u00a0**Data collected would be used for recruitment purposes only.\u00a0 Applicants who do not hear from us within 8 weeks may consider their application unsuccessful and their data will be destroyed within 12 months of receipt.\n", "employment_types": ["Full Time", "Permanent"], "selling_points": ["MNC | Global FinTech | Software Quality Assurance", "1 Years+ | Tester | Engineer | Large Scale Project", "5 Days Work | Bonus | Medical | Young Culture"], "locations": ["Tsim Sha Tsui"], "categories": ["Information Technology (IT)", "Application Specialist - Software", "IT Project Management / Team Lead", "Testing / QA"], "post_time": "2022-01-10T04:26:27Z", "salary": {"currency": "HKD", "max": 34999, "min": 25000, "period": "monthly", "term": null}, "salary_visible": true, "title_keywords": ["engineer"], "responsibilities": ["uat", "schedules", "teams", "presentations", "maintain"], "requirements": {"degrees": ["diploma", "degree"], "majors": ["related disciplines", "business administration"], "languages": ["cantonese", "english", "mandarin", "putonghua", "chinese"], "language_level": ["proficient", "excellent", "proficiency", "good"], "hard_skills": ["chinese word processing", "ms office"], "soft_skills": ["courteous", "independently", "multi-task", "competent", "integrity", "prioritize", "interpersonal skills", "sensitive"], "languages_combined": [{"language": "cantonese", "language_level": ["proficiency", "good"]}, {"language": "english", "language_level": ["proficient", "excellent", "proficiency", "proficiency", "good"]}, {"language": "mandarin", "language_level": ["proficient"]}, {"language": "putonghua", "language_level": ["proficiency", "good"]}, {"language": "chinese", "language_level": ["proficient", "excellent", "proficiency"]}]}, "experience_required": {"duration": [], "field": ["banking industry", "relevant working experience"]}}, {"job_id": "100003009043470", "location_code": "hk", "company": "Optimum Solutions (Hong Kong) Limited", "job_title": "Software Testing Engineer / Software Tester", "description": "Responsibilities\nTo be a team member of Business Innovation & FinTech Department\nAssist Test Manager to complete all UAT related activities\nPrepare test cases and provide appropriate planning and execution in feature testing, regression testing, integration testing, performance testing, and another non-functional testing to ensure successful application/product deployment.\nPrepare and update training materials, user manuals.\nUpdate and maintain best QA procedures and standards, including test planning, test data preparation, and test automation.\nDesign and prepare Test plans, Test Scenarios, and Test Cases according to user requirements.\nReport any findings and prepare a testing report\nRequirements\nUniversity graduate with 1-2 years\u2019 working experience in IT industry is preferable\u00a0\nPrepare UAT test cases according to the user requirement and UI design\nExecute UAT test cases in regular or ad-hoc release cycles\nReport defect/issue clearly with detail steps using the provided bug tracking tools\nGenerate daily test report for management\nSolid experience in performing UAT\nExperience with performance and/or security testing is a plus\nStrong communication and presentation skill is an advantage\nFamiliar with Excel, HPQC, JIRA\nProficient in of both spoken and written English and Chinese", "employment_types": ["Full Time", "Permanent", "Contract"], "selling_points": ["Min 1 to 3 years software testing exp", "Agile or Scrum testing approach", "Exp in Web and Mobile testing"], "locations": ["Others"], "categories": ["Information Technology (IT)", "Support", "Software Development", "Testing / QA"], "post_time": "2022-01-12T13:06:17Z", "salary": {"currency": null, "max": null, "min": null, "period": "monthly", "term": null}, "salary_visible": false, "title_keywords": ["engineer"], "responsibilities": ["uat", "performance testing", "data", "procedures", "design", "testing", "maintain", "plans", "report", "planning"], "requirements": {"degrees": ["university graduate"], "majors": ["it"], "languages": ["english", "chinese"], "language_level": ["proficient"], "hard_skills": ["presentation skill", "excel", "plus"], "soft_skills": ["communication", "presentation skill"], "languages_combined": [{"language": "english", "language_level": ["proficient"]}, {"language": "chinese", "language_level": ["proficient"]}]}, "experience_required": {"duration": ["1-2 years"], "field": ["it", "security", "testing"]}}, {"job_id": "100003009035437", "location_code": "hk", "company": "Global Logistics System (HK) Co Ltd", "job_title": "QUALITY ASSURANCE ANALYST (5-Day Work)", "description": "Requirements:\n\nMInimum 1 year of experience applying Agile (preferably Scrum) testing approaches (e.g., manual testing, unit testing, acceptance testing, test automation) using tools such as Jira, Confluence, Slack.\nExperience using some of the tools such as Zephyr Scale, Selenium, Appium, Espresso, Mocha, Postman.\nExposure working in a DevOps workflow (CI/CD) and Cloud environments.\nExperience working in a technical environment that makes use of languages, frameworks, techniques, and technologies such as HTML5, JavaScript, Node.js, Java, Spring, REST APIs, Git, GitLab, Docker.\nExperience in both Web and Mobile testing (Android/iOS/Hybrid).\n\nThe Ideal Candidate:\n\nAnalytical mindset and problem-solving aptitude\nKnowledge of engineering fundamentals and architecture\nAble to think holistically around engineering issues\nCan think critically and creatively around how to improve software quality through testing\nGood written and verbal communication skills in English", "employment_types": ["Full Time", "Permanent"], "selling_points": ["Responsible to assure product quality", "Responsible to execute & conclude testings", "Medical insurance with attractive package"], "locations": ["Airport Area"], "categories": ["Information Technology (IT)", "Application Specialist - Software", "Support", "Testing / QA"], "post_time": "2022-01-10T07:09:38Z", "salary": {"currency": null, "max": null, "min": null, "period": "monthly", "term": null}, "salary_visible": false, "title_keywords": ["quality assurance analyst"], "responsibilities": ["software", "quality", "testing", "communication", "architecture"], "requirements": {"degrees": [], "majors": [], "languages": ["english"], "language_level": ["good"], "hard_skills": ["java", "git", "agile", "web", "devops", "problem-solving", "mobile", "javascript", "spring", "android"], "soft_skills": ["communication skills", "problem-solving", "agile", "ideal"], "languages_combined": [{"language": "english", "language_level": ["good"]}]}, "experience_required": {"duration": ["minimum 1 year"], "field": ["testing"]}}, {"job_id": "100003009036224", "location_code": "hk", "company": "New World Construction Company Limited", "job_title": "Quality Assurance Engineer (Ref: NWCON/IT/20220110)", "description": "Job Responsibilities:\n\nQuality Assurance of the product \u2013 responsible to assure product quality\nResponsible for analyze & review products\u2019 quality and system performance proactively\nBe proactive in provide suggestion, advice to project stakeholders for preventing repeated errors from the testing phase\nEnsure proper maintenance of test plan / test result and follow up the final testing after rectification made to the error\nMake use of automation testing and scripting to enhance repetitive & regression testing routines\nAdopt a mix of technical and operation perspective mindset to uncover and minimize potential defects\nStay updated in technology trends to provide precaution advice to assure GLS products usability\nTesting \u2013 being accountable / responsible to execute & conclude testing\nResponsible for the creation of testing artifacts including but not limited to test cases, test scripts, test conditions, and expected test results\nResponsible for day-to-day ad-hoc test execution activities\nResponsible for mapping of test cases with user requirements and functional designs\nDesign & conduct user acceptance testing (UAT), functional test, regression test, performance and destructive test to validate the end-to-end business flow to enhance the quality of deployment and provide trouble-shooting\nDocumentation of all tests, including progress and observations, and incorporate into a final test report\nSupport QA Lead and work closely with Project team/QA Analyst to handle project deliverables on time\n\nJob Requirements:\n\n\n\nDegree in Computer Science, E-Commerce or related data science disciplines\nMinimum 2 years of experience in software testing or information technology\nExperience in API/Web/Mobile automation testing\nAbility to execute test plans, test cases and test analysis independently\nDetailed-minded, customer centric and strong aptitude for learning new technologies\nTeam player with good communication skills collaborating with cross-department\nHighly independent with analytical mind and ability to work under pressure\nFluent in Cantonese, English and Putonghua\n\nWe offer 5-day work, and attractive remuneration, medical and dental insurance, provident fund and other fringe benefits\u00a0including\u00a0discounted air tickets\u00a0on Cathay Pacific Airways,\u00a0recreation subsidy,\u00a0birthday leave,\u00a0Airport Express discount\u00a0and\u00a0shuttle bus\u00a0to the right candidate and his/her dependents etc.\u00a0 Interested parties, please submit your detailed CV, stating your present and\u00a0expected salary\u00a0and\u00a0availability\u00a0to us.\n\nWe are an equal opportunity Employer. All CVs and personal data collected are for recruitment purposes and the information will be kept confidential.", "employment_types": ["Full Time", "Permanent"], "selling_points": ["2-year experience in software quality assurance", "Competitive remuneration package", "5 days work, medical insurance, etc."], "locations": ["Kwun Tong"], "categories": ["Information Technology (IT)", "Application Specialist - Software", "Software Development", "Testing / QA"], "post_time": "2022-01-10T09:43:48Z", "salary": {"currency": null, "max": null, "min": null, "period": "monthly", "term": null}, "salary_visible": false, "title_keywords": ["engineer"], "responsibilities": ["ad-hoc", "uat", "maintenance", "project deliverables", "review", "quality", "rectification", "design", "testing", "plan", "documentation", "report"], "requirements": {"degrees": ["degree"], "majors": ["data science", "computer science", "e-commerce"], "languages": ["cantonese", "putonghua", "english"], "language_level": ["fluent"], "hard_skills": ["mobile", "analysis", "web", "e-commerce"], "soft_skills": ["communication skills", "highly independent", "independently", "work under pressure", "learning", "analytical mind", "team player", "detailed"], "languages_combined": [{"language": "cantonese", "language_level": ["fluent"]}, {"language": "putonghua", "language_level": ["fluent"]}, {"language": "english", "language_level": ["fluent"]}]}, "experience_required": {"duration": ["minimum 2 years"], "field": ["information technology", "testing"]}}, {"job_id": "100003009037645", "location_code": "hk", "company": "Joint Electronic Teller Services Limited (\u201cJETCO\u201d)", "job_title": "Senior QA Officer", "description": "Responsibilities\n\n\nDevelop and follow through end-to-end testing processes for new and existing products, from planning testing activities to monitoring debugging process results\nWork with internal teams, e.g. developers and product owner, to identify system requirements and provide timely feedback on specifications and technical design\nCreate comprehensive and well-structured test plans and test cases, and collaborate with stakeholders to exercise related testing activities, with proper documentations and records to closely monitor testing phrases and defects\nDesign and execute automation scripts to ensure bugs tracking, and perform thorough regression testing until bugs fixed\nInvestigate causes of non-conforming software and train users to implement solutions\n\nRequirements\n\n\nHigher Diploma or above in Computing, Computer Science, Information Systems or related disciplines\nAt least 2-year experience in software quality assurance; Knowledge of SQL is a plus\nWell versed in software QA methodologies, tools and processes, such as test plans and test cases, automated testing tools, white box and black box testing\nExperience with performance and/or security testing will be an advantage\nEnjoy working in an independent manner, tackling problems and able to articulate complicated technical scenarios\nCandidate with more experience will be considered as Senior Quality Assurance Engineer\nImmediate availability is highly preferred\n\nCompetitive remuneration package will be offered to successful candidates. To apply, please send your application with a full resume including\u00a0current\u00a0and\u00a0expected salary, and availability to\u00a0Corporate Human Services Department, 8/F,\u00a0KOHO, 73 - 75 Hung To Road, Kwun Tong, Kowloon, Hong\u00a0Kong\u00a0or by clicking\u00a0'Apply Now'\u00a0(Please quote the job reference number and job title on the subject).\n\nFor more details, please visit our company website\u00a0www.hipseng.com\n\nApplicants not invited for interview within 8 weeks may consider their applications unsuccessful. Personal data provided by job applicants will be used strictly in accordance with the company\u2019s personal data policy.", "employment_types": ["Full Time", "Permanent"], "selling_points": ["Business tasks to support project implementation", "4-6 years of QA or software testing experience", "5-day work week"], "locations": ["Wan Chai"], "categories": ["Information Technology (IT)", "Software Development", "Testing / QA", "Others"], "post_time": "2022-01-11T03:22:45Z", "salary": {"currency": null, "max": null, "min": null, "period": "monthly", "term": null}, "salary_visible": false, "title_keywords": ["officer"], "responsibilities": ["collaborate with", "tracking", "software", "monitoring", "teams", "monitor", "testing activities", "testing", "develop", "design", "specifications", "plans", "planning"], "requirements": {"degrees": ["higher diploma or above"], "majors": ["related disciplines", "computer science"], "languages": [], "language_level": [], "hard_skills": ["sql", "plus"], "soft_skills": ["enjoy working", "articulate", "independent"], "languages_combined": []}, "experience_required": {"duration": ["at least 2-year"], "field": ["testing", "security", "quality assurance"]}}, {"job_id": "100003009042637", "location_code": "hk", "company": "Openrice Limited", "job_title": "Junior Software Tester", "description": "Our client is a large\u00a0corporation, due to expansion, they need to\u00a0 \u00a0recruit many IT / project professionals to join their\u00a0IT team. (for both application and infrastructure team projects)\u00a0 \u00a0 \u00a0\u00a0\n\n\nProject Manager /\u00a0Business Analyst/ Project officer/ QA Trainee/ UAT Tester\n(Welcome Fresh)\u00a0 \u00a0\n\nResponsibilities:\n\nHandle user requirement collection, business analysis of\u00a0various\u00a0 \u00a0application, Project Management\nLiaise with business users on scope, testing plans\nPerform\u00a0Quality Assurance and provide User Acceptance Testing (UAT) and production support of the application\nPrepare System Specification and user documentation writing up\nProject coordination and management (application and / or infrastructure projects)\u00a0\nProper training will be provided to the junior / fresh\n\nRequirements:\n\nDegree in Business, Finance, Computer Science or related disciplines\nMin 2 years relevant experience in project management/ business analysis\nStrong communication skills\nProficiency in both English and Chinese\u00a0\nFresh graduate or less experience also considered and proper training will be provided\nMore experience will consider as Senior Business Analyst / Project Specialist\u00a0\nFocus on UAT/ Quality Assurance experience will be consider as QA specialist\n7 year or above experience will be considered as Project Manager / Business Analyst Lead", "employment_types": ["Full Time", "Permanent"], "selling_points": ["Utilize task management and bug reporting tools", "Fresh Graduate is also welcome", "Five days work with flexible working hours"], "locations": ["Quarry Bay"], "categories": ["Information Technology (IT)", "Testing / QA", "Others", "Others", "Student / Fresh Graduate / No Experience"], "post_time": "2022-01-12T08:14:59Z", "salary": {"currency": null, "max": null, "min": null, "period": "monthly", "term": null}, "salary_visible": false, "title_keywords": ["junior"], "responsibilities": ["user requirement", "management", "documentation", "uat", "project coordination", "infrastructure", "quality", "testing", "project management", "liaise with", "business analysis", "plans"], "requirements": {"degrees": ["degree", "fresh graduate"], "majors": ["related disciplines", "finance", "business", "computer science"], "languages": ["english", "chinese"], "language_level": ["proficiency"], "hard_skills": ["project management", "analysis", "focus"], "soft_skills": ["communication skills", "project management", "focus"], "languages_combined": [{"language": "english", "language_level": ["proficiency"]}, {"language": "chinese", "language_level": ["proficiency"]}]}, "experience_required": {"duration": ["min 2 years", "7 year"], "field": ["training", "qa", "project management", "business", "relevant experience", "business analysis", "quality assurance"]}}, {"job_id": "100003008993871", "location_code": "hk", "company": "Tranthink Technology Service Limited", "job_title": "Junior Backend Programmer (Java & Server-oriented)", "description": "JOIN OpenRice\u2026\u2026if you want to service our\n\n\u00a05 million App users with\n\n\u00a09 million pageviews per day in Hong Kong!\u00a0\u00a0\n\nOpenRice\u00a0is seeking an energetic and passionate individual\u00a0who interested in website and mobile apps testing.\u00a0 You will be part of the regional team to work with mobile / software engineers and product specialists to deliver top-notch e-products to\u00a0mass\u00a0market.\n\nJob Descriptions:\n\n\nExecutes test cases for software programs, apps, and websites\nDocuments and evaluates test results\nTracks defects and helps troubleshoot errors\nReport to Team lead on progress, status and other major issues of the project\n\nJob Requirements:\n\nHigh Diploma, Degree holder of Engineering, Computing, Mobile Application or equivalent\n1+ years\u00a0of relevant work experience\nHigh attention to detail and solid analytical skills.\nUtilize task management and bug reporting tools like JIRA\nAbility to plan, design and perform stress test using JMeter\u00a0/ Appium is a plus\nGood command of written and communication skill in both English and Cantonese\nFresh graduate is also\u00a0welcome\n\nWe offer a competitive remuneration package including excellent career prospects to the right candidate. Interested parties please submit your detailed resume with expected salary and available date by clicking the Quick Apply button.\n\nAll personal information submitted by job applicants will be used for recruitment purposes and we reserve the rights to consider the applications for other positions in our Group.", "employment_types": ["Full Time", "Permanent"], "selling_points": ["5 Days Work, Double Pay, Medical Insurance", "Flexible working hours, Free snack", "Server systems development, testing and bug fixing"], "locations": ["Lai Chi Kok"], "categories": ["Information Technology (IT)", "Software Development", "Testing / QA", "Network & System"], "post_time": "2022-01-16T21:50:01Z", "salary": {"currency": null, "max": null, "min": null, "period": "monthly", "term": null}, "salary_visible": false, "title_keywords": ["server", "programmer", "junior"], "responsibilities": ["software", "troubleshoot", "report"], "requirements": {"degrees": ["high diploma", "fresh graduate", "degree holder"], "majors": ["engineering"], "languages": ["cantonese", "english"], "language_level": ["good command"], "hard_skills": ["mobile", "plus", "analytical skills"], "soft_skills": ["communication skill", "attention to detail", "analytical skills"], "languages_combined": [{"language": "cantonese", "language_level": ["good command"]}, {"language": "english", "language_level": ["good command"]}]}, "experience_required": {"duration": ["1+ years"], "field": []}}, {"job_id": "100003009051932", "location_code": "hk", "company": "Octopus Holdings Limited", "job_title": "Senior System Engineer / System Engineer (Front-End) Ref: OCL/TEC/2021-235", "description": "Responsibilities\u00a0\nLead and drive the definition, preparation, and execution of testing strategies for client project engagements including Functional, System Integration and User Acceptance test phases according to the defined QA Test Strategy and Standards\nManage daily/weekly progress reporting and defect tracking and resolution progress\nReview and provide input to project schedule tasks, levels of effort, duration, testing risks and dependencies\nCreate requirements traceability matrices and conduct reviews with business analysts and technical development staff to ensure understanding of business requirements and complete test coverage\nCreate comprehensive test strategies and test plans and conduct reviews\nHands on execution of test cases, update documentation accordingly with results\nManage other QA analysts onshore/offshore for daily QA tasks\nDeveloping testing solutions that meet needs of clients and customers\nLead testing efforts for projects that impact their core area of testing responsibilities, which includes acting in a leadership role to acquire test data and ensuring proper tests are executed in all testing environments\nMust be able to work as a team to ensure execution of smoke, functional and regressions tests in all levels of the environments\nConduct testing post-mortems to define and document lessons learned and translate them to improvement to the QA test strategy and standards\nAbility to mine for data using SQL to validate test results\nMust have strong technical aptitude and analytic background needed to understand applications and data infrastructure\nBuild and drive Automation initiatives in the project\nSupport the Quality Assurance Manager as required.\nTeam player.\nDeliver on budget and on time!\nQualifications, Training and Experience\n\nA. Qualifications:\nBachelor\u2019s degree in a relevant field (e.g. Computer Science, Engineering, Marketing, Business Administration)\nPossesses 4 to 6 years of QA or software testing experience\nB. Requirements:\nAble to work independently with the least supervision, but always a team player\nWork collaboratively within a cross-functional team\nStrong aptitude for learning new technologies\nAttention to detail\nGood understanding of testing methodologies and testing processes\nUnderstand software development life cycle and various testing techniques including proficiency in systems testing\nGood documentation and communication skills\nFamiliar with testing tools and defects management tools like JIRA, Azure DevOps or HP\nAbility to work off-business hours as needed\nC. Preferences, Training and Experiences:\nExperience in medical, health, or life insurance\nExperience in test data management\nKnowledge of basic SQL\nHas prior experience in leading a team\nCantonese speaker preferred but not required.\u00a0 Excellent English is required if candidate is not a Chinese speaker\nBackground in business analysis\nExperience in testing API\u2019s (REST, SOAP, or application propriety API\u2019s)\nISTQB / QAI certifications\nBupa offers 5 days work per week and comprehensive remuneration packages including base salary, study assistance plan, life and medical benefit, dental benefit, annual leave, examination leave, etc.\nBupa is an equal opportunity employer and welcomes applications from qualified candidates. Information provided will be treated in strict confidential and only be used for consideration of application with Bupa.\u00a0\u00a0\u00a0\u00a0\u00a0\u00a0\u00a0\u00a0\u00a0\u00a0\u00a0\u00a0\u00a0\u00a0\nPersonal data collected will be used for recruitment purposes only. Only candidates selected for interviews will be contacted. Bupa will be in touch for any opportunities that matches your profile. All personal data of unsuccessful application will be destroyed 24 months from the date of receiving the application", "employment_types": ["Full Time", "Permanent"], "selling_points": ["Design and development life cycle of Octopus app", "University Degree in Computer Science", "Minimum 2 years of software development experience"], "locations": ["Kowloon Bay"], "categories": ["Information Technology (IT)", "Application Specialist - Software", "Software Development", "Testing / QA"], "post_time": "2022-01-17T01:32:44Z", "salary": {"currency": null, "max": null, "min": null, "period": null, "term": null}, "salary_visible": false, "title_keywords": ["system engineer", "senior system engineer"], "responsibilities": ["administration", "reporting", "software", "data", "review", "infrastructure", "developing", "quality", "testing", "resolution", "budget", "schedule", "documentation", "plans", "tracking"], "requirements": {"degrees": [], "majors": [], "languages": ["cantonese", "english", "chinese"], "language_level": ["excellent"], "hard_skills": ["azure", "data management", "basic", "devops", "analysis", "sql", "c", "documentation"], "soft_skills": ["communication skills", "work independently", "learning", "comprehensive", "attention to detail", "team player"], "languages_combined": [{"language": "cantonese", "language_level": []}, {"language": "english", "language_level": ["excellent"]}, {"language": "chinese", "language_level": []}]}, "experience_required": {"duration": [], "field": ["management", "training", "testing", "medical", "insurance", "team"]}}, {"job_id": "100003009032959", "location_code": "hk", "company": "Ringus Solution Enterprise Limited", "job_title": "Software Quality Assurance Engineer", "description": "Responsible for server systems development, testing and bug fixing\nWilling to learn new technologies (ELK, Dubbo, Docker..)\nMay perform other duties as assigned\nSkills & Requirements\nFoundation level in JAVA and SQL\nExperienced in version control tools (GIT/SVN)\nReliable and cooperative personalities\nWilling to learn and work with new technologies\nFresh Graduate will also be considered\nPriority considers:\nExperienced in Spring stack\nFoundation level in Microservices, Cache, Big Data and MQ\nPlease click \"Apply Now\" to submit your application.\n\nPersonal data collected will be used for recruitment purpose only.\n\n#JAVA #SQL #Spring #Dubbo #Microservices", "employment_types": ["Full Time", "Permanent"], "selling_points": ["Design and prepare Test Plan and Test Cases", "Test on web-based system and mobile app", "Provide clear and detail test report and track bug"], "locations": ["Sheung Wan"], "categories": ["Information Technology (IT)", "Application Specialist - Software", "Testing / QA", "Others"], "post_time": "2022-01-08T04:18:04Z", "salary": {"currency": null, "max": null, "min": null, "period": "monthly", "term": null}, "salary_visible": false, "title_keywords": ["engineer"], "responsibilities": ["perform other duties", "control", "systems", "big data", "testing", "recruitment", "personal data"], "requirements": {"degrees": ["fresh graduate"], "majors": [], "languages": [], "language_level": [], "hard_skills": ["java", "git", "microservices", "sql", "spring", "server"], "soft_skills": ["cooperative", "reliable", "willing to learn", "responsible"], "languages_combined": []}, "experience_required": {"duration": [], "field": []}}, {"job_id": "100003009037877", "location_code": "hk", "company": "China Construction Bank (Asia) Corporation Limited", "job_title": "UAT Test Process and Resource Management Professional", "description": "KEY RESPONSIBILITIES:\n\n\nBridge between business and IT on defining\u00a0business requirement and monitoring IT tasks/ projects delivery progress\nPerform UAT testing and support for various systems\nFacilitate and enable business to fully adopt new systems to improve productivity and efficiency\nEvaluate problems and risks on AS-IS process, recommend and implement solutions for improvement\nPrepare project plan and training materials and document requirements for new systems or enhancement.\n\nJOB REQUIREMENTS:\n\n\nBachelor degree in Computer Science, Information System or related discipline\n5 years or above working experience as Business Analyst in Retail Business. Candidate with more experience may be considered as Senior Business Analyst.\nSelf-motivated and ability to work independently\nExperience in SQL and/or programming languages is a plus\nExcellent interpersonal and problem-solving skills\nExcellent presentation and communication skills\n\nAn attractive remuneration package together with fringe benefits will be offered to the right candidate.\u00a0\u00a0Interested parties are invited to send your full resume with current and expected salary\u00a0by clicking \"Apply Now\".\n\nPersonal data collected will be used for recruitment purpose only.", "employment_types": ["Full Time", "Permanent"], "selling_points": ["User Acceptance Test", "Project Management", "Vendor Procurement"], "locations": ["Kowloon Bay"], "categories": ["Information Technology (IT)", "Testing / QA"], "post_time": "2022-01-11T04:06:49Z", "salary": {"currency": null, "max": null, "min": null, "period": "monthly", "term": null}, "salary_visible": false, "title_keywords": [], "responsibilities": ["monitoring", "uat testing", "project plan", "systems", "evaluate"], "requirements": {"degrees": ["degree", "bachelor"], "majors": ["computer science"], "languages": [], "language_level": [], "hard_skills": ["plus", "information system", "sql", "programming", "problem-solving skills"], "soft_skills": ["communication skills", "self-motivated", "work independently", "presentation", "problem-solving skills", "interpersonal"], "languages_combined": []}, "experience_required": {"duration": ["5 years"], "field": ["sql", "programming", "business", "retail"]}}, {"job_id": "100003009043169", "location_code": "hk", "company": "iFAST ePension Services Limited", "job_title": "Business Analyst (Pension)", "description": "Ref: OCL/TEC/2021-235 \u00a0\n\nJob Responsibilities:\nParticipate in firmware/software design and development life cycle of Octopus applications\nPrioritise tasks and complete works in accordance with planned schedule with high quality outputs and deliverables\nIdentify opportunities for improvement of future products\nRequirements:\nUniversity Degree in Computer Science, Computer Engineering or Electronic Engineering related disciplines\nMinimum 2 years of software development experience, preferably in Linux or other real-time operating system (RTOS) platforms\nProficiency in C/C++, knowledge of Java and Android will be an advantage\nAble to work under pressure, self-motivated to learn quickly and pick up new skills\nCapable of working independently in system design, development and testing\nA good team player with strong analytical, problem solving and troubleshooting skills\nProficient in written and spoken English and Chinese and with strong communication skills\nCandidate with less experience will be considered as System Engineer", "employment_types": ["Full Time", "Permanent"], "selling_points": ["Participate in the ePension platform setup", "Entitle performance bonus and company shares", "21+ days Annual Leave"], "locations": ["Tsim Sha Tsui"], "categories": ["Information Technology (IT)", "IT Project Management / Team Lead", "Product Management / Business Analyst", "Testing / QA"], "post_time": "2022-01-12T10:00:14Z", "salary": {"currency": null, "max": null, "min": null, "period": "monthly", "term": null}, "salary_visible": false, "title_keywords": ["business analyst"], "responsibilities": ["quality", "software", "design", "schedule"], "requirements": {"degrees": ["university degree"], "majors": ["related disciplines", "computer engineering", "engineering", "computer science"], "languages": ["english", "chinese"], "language_level": ["proficient"], "hard_skills": ["linux", "java", "c++", "problem solving", "c", "system design", "android"], "soft_skills": ["communication skills", "good team player", "self-motivated", "independently", "capable", "troubleshooting", "problem solving", "work under pressure"], "languages_combined": [{"language": "english", "language_level": ["proficient"]}, {"language": "chinese", "language_level": ["proficient"]}]}, "experience_required": {"duration": ["minimum 2 years"], "field": ["software development"]}}, {"job_id": "100003009048341", "location_code": "hk", "company": "ST Engineering Infa Systems Limited", "job_title": "System Engineer / Installation Engineer x 5", "description": "Job Responsibilities\n\nDesign and prepare Test Plan, Test Scenarios and Test Cases according to user requirements\n\nPerform functional test and user scenario test on web-based system and mobile app\nProvide clear and detail test report and track bug fixing status\n\nEnsure product are delivered with approved quality and timeline\n\n\nJob Requirements:\n\nMinimum 2 years of progressively related experience in relevant field\nDiploma or above in Information System, Computer Science or equivalent\nExperienced on using auto-testing software will be an advantage\nDetail oriented and well organized\nWorking experience in QA role is preferred\nImmediate availability is preferred\n\n\nWe offer attractive salary package and career advancement opportunities to the right candidates. Interested parties please send your detail resume with EXPECTED SALARY & AVAILABLE DATE in WORD FORMAT and portfolio (if any), by clicking \"Apply Now\".\n\n(Personal data collected will be Kept & used for recruitment purpose only)", "employment_types": ["Full Time", "Permanent", "Contract"], "selling_points": [], "locations": ["North Point"], "categories": ["Engineering", "Electrical / Electronics", "Information Technology (IT)", "Testing / QA", "Others", "Student / Fresh Graduate / No Experience"], "post_time": "2022-01-14T06:29:00Z", "salary": {"currency": null, "max": null, "min": null, "period": "monthly", "term": null}, "salary_visible": false, "title_keywords": ["system engineer", "engineer"], "responsibilities": ["mobile app", "quality", "design", "plan", "report"], "requirements": {"degrees": ["diploma or above"], "majors": ["computer science"], "languages": [], "language_level": [], "hard_skills": ["information system"], "soft_skills": ["detail oriented", "well organized"], "languages_combined": []}, "experience_required": {"duration": ["minimum 2 years"], "field": ["related", "qa"]}}, {"job_id": "100003009047420", "location_code": "hk", "company": "Tai Hing Catering Group Limited", "job_title": "Project Coordinator", "description": "Main Responsibilities\n- Support all aspects of User Acceptance Test (UAT) for a wide range of projects\n- Coordinate activities in relations to UAT to ensure the successful testing implementation and delivery\n- Work with internal stakeholders to understand the requirement for UAT on various projects\n- Monitor the UAT progress to ensure the projects are completed on-time, within budget and with desired quality\n- Assist supervisor to log and manage defects and incidents identified throughout the project testing phases\n- Arrange UAT testers Onboard/Offboard Logistics\n- Gather UAT project list and requirements from users\n- Prepare documents for Vendor Procurement\n\nRequirements\n- University degree in Computer Science, Information management, Business Administration or related disciplines\n- Minimum 1 years Project Management / UAT related work experience in banking or financial industry\n- Comprehensive understanding of PDLC, testing and quality assurance methodologies\n- Good command of spoken and written English and Chinese (including Putonghua)\n- Strong communication, interpersonal, negotiation, organizational skills and project management skills\n- Independent and able to manage multiple tasks\n- Result oriented, attention to details and able to motivate the UAT teams to achieve testing results within schedule and budget\n", "employment_types": ["Full Time", "Permanent"], "selling_points": [], "locations": ["Shatin Area"], "categories": ["Information Technology (IT)", "Software Development", "Testing / QA", "Technical / Functional Consulting"], "post_time": "2022-01-14T03:02:16Z", "salary": {"currency": null, "max": null, "min": null, "period": "monthly", "term": null}, "salary_visible": false, "title_keywords": ["project coordinator"], "responsibilities": ["uat", "budget", "monitor", "implementation", "quality", "testing", "coordinate", "logistics", "prepare documents"], "requirements": {"degrees": ["university degree"], "majors": ["related disciplines", "business administration", "computer science"], "languages": ["putonghua", "english", "chinese"], "language_level": ["good command"], "hard_skills": ["project management"], "soft_skills": ["organizational skills", "independent", "negotiation", "multiple tasks", "project management skills", "communication", "project management", "result oriented", "comprehensive", "attention to details", "interpersonal"], "languages_combined": [{"language": "putonghua", "language_level": ["good command"]}, {"language": "english", "language_level": ["good command"]}, {"language": "chinese", "language_level": ["good command"]}]}, "experience_required": {"duration": ["minimum 1 years"], "field": ["related", "project management", "financial industry", "banking"]}}, {"job_id": "100003009049112", "location_code": "hk", "company": "Hong Kong Interbank Clearing Ltd", "job_title": "Specialist (Clearing Operations) (Two-Year Programme)", "description": "One of the well-establish banking client is hiring for a specialist to assist supervisor(s) in product and system development processes, to perform quality assurance on digital products for customer channels and internal supporting platforms. Excellent exposure to\n\n\nAbout the role\n\nTo understand users requirements and complaints on using digital products\nTo verify customer's feedback and complaints in testing environment\nTo identify defects and work with technical teams to provide solutions of defects on various channels including Internet Banking, Mobile Banking, Phone Banking, ATM and Digital Branches, etc.\nTo conduct UAT and define testing scenario, test cases, test plans and produce testing reports\nTo review, close and report defects log to testing team lead, IT and other relevant department", "employment_types": ["Full Time", "Permanent"], "selling_points": [], "locations": ["Ngau Tau Kok"], "categories": ["Information Technology (IT)", "Testing / QA", "Banking / Finance", "Order Processing & Operation / Settlement", "Management", "Management Trainee"], "post_time": "2022-01-14T08:08:15Z", "salary": {"currency": null, "max": null, "min": null, "period": null, "term": null}, "salary_visible": false, "title_keywords": ["specialist", "operations"], "responsibilities": ["uat", "review", "teams", "quality", "provide solutions", "testing", "reports", "plans", "banking", "testing environment", "report"], "requirements": {"degrees": [], "majors": [], "languages": [], "language_level": [], "hard_skills": ["mobile"], "soft_skills": [], "languages_combined": []}, "experience_required": {"duration": [], "field": []}}, {"job_id": "100003009039580", "location_code": "hk", "company": "IT Solutions Ltd.", "job_title": "Major Bank (QA): Project Assistants / Admin Assistants (Treasury System Project)", "description": "Our client is a mobile trading platform focus in securities trading who is looking for a QA engineer.\n\nResponsibilities\n\nWork close with product and development teams on understanding requirements, identify testing needs\nDesign test plans, help execute tests, and report defects on assigned systems\nRequirements\n\nDegree holder or above preferably in Business or Information Technology; HD or AD graduates with solid experience will also be considered\n2-3 years experience in Quality Assurance / Business Analysis experience, candidates with Mobile Investment Application experience will be a plus\nExperience in UAT execution is highly preferred\nExperience in preparing Test Case / Scenario, Test Plan preferred\nAbility to work effectively with teams across different geographical locations.\nStrong attention to details with good command written and spoken English, Cantonese, Mandarin (is a plus but not a must)", "employment_types": ["Full Time"], "selling_points": ["Develop career in Banking & IT field", "Bank Operations", "Training will be provided"], "locations": ["Central"], "categories": ["Admin & HR", "Clerical / Admin Staff", "Banking / Finance", "Treasury", "Information Technology (IT)", "Testing / QA"], "post_time": "2022-01-11T10:09:37Z", "salary": {"currency": null, "max": null, "min": null, "period": "monthly", "term": null}, "salary_visible": false, "title_keywords": ["admin"], "responsibilities": ["systems", "teams", "design", "testing", "plans", "report"], "requirements": {"degrees": ["degree holder"], "majors": ["business", "information technology"], "languages": ["cantonese", "english", "mandarin"], "language_level": ["good command"], "hard_skills": ["mobile", "analysis", "plus"], "soft_skills": ["work effectively", "attention to details"], "languages_combined": [{"language": "cantonese", "language_level": ["good command"]}, {"language": "english", "language_level": ["good command"]}, {"language": "mandarin", "language_level": ["good command"]}]}, "experience_required": {"duration": ["2-3 years"], "field": ["business analysis", "investment", "quality assurance"]}}, {"job_id": "100003009034682", "location_code": "hk", "company": "Reticle Search International Limited", "job_title": "UAT Tester (Permanent)", "description": "Responsibilities:\n\nUnderstand the business objectives and rationales behind high-level product features, analyze and translate them into detailed functional requirement specifications of projects;\nDesign test scenarios and test cases based on business requirements, functional requirement specifications and ensure comprehensive coverage of test cases\nPerform execution of test case manually or using automated testing tools, compile test result and monitor the defect fixing progress\nUnderstand the limitations and issues of existing testing processes and recommend improvement initiatives\nWork closely with the business users and IT application team throughout the system development life cycle to deliver product features and solutions;\nCoordinate with users in integration and testing of new enhancements;\nAct as the key interface between the IT application team, relevant departments, and external vendors;\nPerform ad-hoc duties as and when required.\n\nRequirements:\n\nBachelor degree in Computer Science, IT, Business Information Systems or related field;\nMinimum\u00a01 year\u2019s\u00a0related experience in business analysis, solution design or project managements; preferably related experience in the pension or financial industry;\nExperience in performing testing of pension or financial application is an advantage\nCapacity to multi-task, manage time effectively and work under pressure and to fixed deadlines with attention to detail in a fast-paced environment;\nStrong analytical, interpersonal and communication skills;\nSelf-motivated, strong sense of responsibility and willing to learn;\nExcellent command in spoken and written English and Chinese.\n\nOur offer:\u00a0\n\nCareer development prospect;\nAttractive remuneration;\n5-day working week;\n21+ days Annual Leave;\nMedical, Dental, Life Insurance;\nPerformance bonus and shares;\nEducation, sports allowance.", "employment_types": ["Permanent"], "selling_points": ["A wholly owned by a Nasdaq-listed company", "Experience in UAT, Test Case/Scenario, Test Plan", "Attractive package with bonus"], "locations": ["Causeway Bay"], "categories": ["Information Technology (IT)", "Product Management / Business Analyst", "Testing / QA", "E-commerce", "Product Management / Business Analyst"], "post_time": "2022-01-10T04:01:00Z", "salary": {"currency": null, "max": null, "min": null, "period": "monthly", "term": null}, "salary_visible": false, "title_keywords": ["uat tester"], "responsibilities": ["coordinate with", "monitor", "design", "testing", "specifications", "ad-hoc duties"], "requirements": {"degrees": ["degree", "bachelor"], "majors": ["business", "it", "computer science"], "languages": ["english", "chinese"], "language_level": ["excellent"], "hard_skills": ["analysis"], "soft_skills": ["communication skills", "self-motivated", "multi-task", "sense of responsibility", "fast-paced environment", "willing to learn", "attention to detail", "interpersonal", "work under pressure"], "languages_combined": [{"language": "english", "language_level": ["excellent"]}, {"language": "chinese", "language_level": ["excellent"]}]}, "experience_required": {"duration": ["minimum 1 year"], "field": ["related", "financial industry", "design", "testing", "business analysis", "financial"]}}, {"job_id": "100003009034023", "location_code": "hk", "company": "Global Talent Services Limited", "job_title": "UAT Tester (Secondment, Banking, 3-month Contract) (Ref:GTS_UAT_HK)", "description": "Responsibilities:\n\n\nWorking in the Digital Products Group Department\nTesting AI, Cloud, IoT products\u00a0\nDesigning test plans, scenarios, scripts, and procedures.\nPerform UAT and SIT\nWorking with the development team to correct bugs and errors\nAgile working environment\nRequirements:\n\nMinimum of 3 years experience in QA with at least 2 years experience in Automation Testing\nA Bachelor's degree in Computer Science, Engineering, or related field\nSolid knowledge of SQL and scripting\nKnowledge of Java / Python / Node.js\u00a0\nKnowledge of Selenium\u00a0\u00a0\nGood team working and critical thinking skills.", "employment_types": ["Full Time", "Contract"], "selling_points": [], "locations": ["Quarry Bay"], "categories": ["Information Technology (IT)", "Application Specialist - Software", "Support", "Testing / QA"], "post_time": "2022-01-10T02:26:29Z", "salary": {"currency": "HKD", "max": 24999, "min": 17000, "period": "monthly", "term": null}, "salary_visible": true, "title_keywords": ["uat tester"], "responsibilities": ["uat", "procedures", "testing", "designing", "plans"], "requirements": {"degrees": ["degree", "bachelor"], "majors": ["engineering", "computer science"], "languages": [], "language_level": [], "hard_skills": ["sql", "java", "python"], "soft_skills": ["team working"], "languages_combined": []}, "experience_required": {"duration": ["at least 2 years", "minimum of 3 years"], "field": ["qa", "testing"]}}, {"job_id": "100003009036338", "location_code": "hk", "company": "Accenture Technology Solutions (HK) Ltd", "job_title": "Technology - Test Engineering Specialist", "description": "APJ Hong Kong (\u00a0www.apjcorp.com.hk\u00a0) provides the highest quality software development, maintenance and testing services.\u00a0 We have cost effective service centers with highly qualified IT professionals in Hong Kong. Our clients include major enterprises and organizations in the Finance, Manufacturing, Public Utility, Retail, healthcare and Government sectors.\u00a0\n\nYou will be involving\u2026\n\nReport to Quality Assurance Manager\nDevelop, implement, and maintain test plans, test scenarios, test cases, and test procedures for all levels of testing\nEnhance test methodologies that ensure exhaustive testing of all assigned systems\nEnsure all testing work is undertaken in accordance with the policies and procedures as described\nGather and analyze data in support of business cases, projects, process / system requirements\nHelp validate business requirements and processes through careful testing\nIdentify and manage project-level risks associated with/during testing and escalate as required.\nManage the end to end OAT lifecycle and deliverables for each project engagement.\n\nWe are looking for\u2026\n\n\nAt least 2 years of hands on related experience\u00a0\nExcellent in written and spoken English with the ability to articulate technical concepts to a range of audiences.\nStrong interpersonal and communication skills to promote healthy relationships and influence others.\nProactive and willing to drive changes to achieve positive outcomes.\nWell-developed analytical, problem-solving, and decision-making skills, leveraging both logic and creativity; strong troubleshooting skills; ability to identify patterns and generate ideas.\nValidating test results through diagnosis and analysis of various system/application error logs, transaction metrics, as well as database performance logs.\n\nWe are offering\u2026\n\n5-day work\nAttractive package\nYear \u2013 end bonus\nMedical insurance\nFestival gifts\nExcellent project exposure and career development opportunities", "employment_types": ["Full Time", "Permanent"], "selling_points": ["3 years or above in Quality Assurance & Testing", "Integration testing / Automation testing", "Excellent communication & interaction skills"], "locations": ["Not Specified"], "categories": ["Information Technology (IT)", "Software Development", "Testing / QA"], "post_time": "2022-01-10T10:04:19Z", "salary": {"currency": null, "max": null, "min": null, "period": "monthly", "term": null}, "salary_visible": false, "title_keywords": ["specialist"], "responsibilities": ["ideas", "software", "quality", "troubleshooting", "communication", "maintain", "database", "plans", "testing", "develop", "analyze data", "report", "cost", "procedures", "career development", "maintenance", "policies", "analysis", "systems", "insurance"], "requirements": {"degrees": [], "majors": [], "languages": ["english"], "language_level": ["excellent"], "hard_skills": ["problem-solving", "analysis", "maintenance"], "soft_skills": ["exhaustive", "communication skills", "careful", "problem-solving", "troubleshooting", "hands on", "articulate", "proactive", "interpersonal", "positive"], "languages_combined": [{"language": "english", "language_level": ["excellent"]}]}, "experience_required": {"duration": ["at least 2 years"], "field": ["related"]}}, {"job_id": "100003009040256", "location_code": "hk", "company": "iFAST Financial (HK) Limited", "job_title": "Project Analyst/ Business Analyst", "description": "This is a great opportunity for anyone with attention to details and logical thinking to join a young and dynamic team of engineers working on the latest technologies for the cinema industry. The candidate must have a desire to test systems like the end user and take pride in creating seamless experiences for customers. You will be working in a team of experts and developers and will be provided with all the domain knowledge needed.\n\n\u00a0Responsibilities:\n\nExecute functional test plans for existing and new features of our products\nMaintain test plan documentation\nMaintain testing process and systems for our products\n\nRequirements:\n\nGraduate degree in any discipline\n1+ years experience with functional testing of system hardware and software\nAnalytical and thorough with an understanding of test methodologies\nFamiliarity with Linux OS preferred\nKnowledge of automated software test systems and methodologies is useful\nFresh graduates/Entry level applicants with relevant skills will be considered\n\nAttractive remuneration package will be offered.\n\nAll information provided by applicants will be treated in strictest confidence and used only for processing their application.", "employment_types": ["Full Time", "Permanent"], "selling_points": ["testing of new enhancements", "21+ days Annual Leave for all staff", "Performance bonus and company shares"], "locations": ["Central"], "categories": ["Information Technology (IT)", "IT Project Management / Team Lead", "Product Management / Business Analyst", "Testing / QA"], "post_time": "2022-01-12T02:02:08Z", "salary": {"currency": null, "max": null, "min": null, "period": "monthly", "term": null}, "salary_visible": false, "title_keywords": ["analyst", "business analyst"], "responsibilities": ["systems", "testing", "maintain", "plan", "documentation", "plans"], "requirements": {"degrees": ["degree"], "majors": [], "languages": [], "language_level": [], "hard_skills": ["hardware", "os", "linux", "processing"], "soft_skills": ["confidence", "thorough"], "languages_combined": []}, "experience_required": {"duration": ["1+ years"], "field": ["testing"]}}, {"job_id": "100003009043170", "location_code": "hk", "company": "iFAST ePension Services Limited", "job_title": "Business Analyst (Frontend Pension Projects)", "description": "Responsibilities:\u00a0\n\nPerform all installation/ testing with users for customized software or hardware applications\nPrepare all necessary install/ test plans and procedures. Submit results and reports for user acceptance.\nCommunication among customers and sub-contractors for technical problem resolution\n\nRequirements:\u00a0\n\nDegree or above in IT/ Electronic/ Telecommunication/ Engineering \u00a0or related discipline.\nProcess valid HK class 1 driving license is an advantage.\nAble to communicate in Cantonese, Mandarin and English.\nGood analytical and problems solving skills with strong self-motivation.\nWelcome fresh graduate.\nWe offer excellent career opportunities and remuneration package. Interested parties, please send Full C.V. provided Date Available, Current and Expected Salary with Reference No. on the letter to the following address: 17/F, 169 Electric Road, North Point, Hong Kong OR you may reach us by fax/ email: 852-2231 0718/ Click \"Apply Now\". Attn to Ms Jacqueline Sy.", "employment_types": ["Full Time", "Permanent"], "selling_points": ["Digital pension platform and related applications", "Fresh graduates are welcome", "21 days+ annual leave and company shares (SGX:AIY)"], "locations": ["Tsim Sha Tsui"], "categories": ["Information Technology (IT)", "IT Project Management / Team Lead", "Product Management / Business Analyst", "Testing / QA"], "post_time": "2022-01-12T10:00:14Z", "salary": {"currency": null, "max": null, "min": null, "period": "monthly", "term": null}, "salary_visible": false, "title_keywords": ["business analyst"], "responsibilities": ["installation", "software", "procedures", "testing", "communication", "hardware", "resolution", "reports", "plans"], "requirements": {"degrees": ["degree or above", "fresh graduate"], "majors": ["it", "engineering"], "languages": ["cantonese", "english", "mandarin"], "language_level": [], "hard_skills": [], "soft_skills": ["self-motivation"], "languages_combined": [{"language": "cantonese", "language_level": []}, {"language": "english", "language_level": []}, {"language": "mandarin", "language_level": []}]}, "experience_required": {"duration": [], "field": []}}, {"job_id": "100003009042588", "location_code": "hk", "company": "ESD Services Limited (ESDlife)", "job_title": "Senior Project Executive (Digital Solutions)", "description": "Major Responsibilities\nExposure to interbank clearing operations in Hong Kong to acquire expertise in interbank paper cheque clearing and other electronic clearing systems.\nInvolve in new system design and development and assist in new project implementation for interbank clearing and settlement initiatives in Hong Kong.\nParticipate in preparing clearing and settlement documentation, such as rules and procedures.\nPrepare user testing documentations and conduct user acceptance tests on new systems.\nParticipate in the clearing operation of paper cheque, e-Cheque and other electronic clearing items.\nInvolve in the operation and monitoring of the Faster Payment System.\nRequirements\nTertiary education with good academic achievement, majoring in banking, finance, business management, information technology or related disciplines will be an advantage.\nOne to two years working experience preferred.\u00a0\nTarget driven with excellent ethics to maintain business quality.\nConfident, self-motivated and resilient, with strong interpersonal and organization skills.\nExcellent command of both written and spoken English and Chinese; fluency in Putonghua is an advantage.\nRequired to work at alternative sites and perform shift duties as well as provide operation support under adverse weather situations.\u00a0\nOur Benefits and Career Path\nAttractive remuneration package\nMedical and dental insurance\nLife insurance\n2-year talent development program incorporating on-the-job training, external training and job rotations\nTo be an Assistant Manager after the two-year programme\n\n\nHow to Apply\nInterested parties please send your curriculum vitae stating your current and expected salaries, and the contact phone number to the Human Resources Division, Unit B, 25/F, MG Tower, 133 Hoi Bun Road, Kwun Tong, Kowloon\u00a0 by clicking the \"Apply Now\" button below.\nAll applications and personal information collected will be treated in strict confidence and only be used for the purpose of recruitment and selection.\u00a0 The information collected will be accessed by our authorized personnel only.\u00a0 Those applicants not contacted by the Human Resources Division within two months from their application date should consider their applications filed for future reference which will be retained for one year for possible future job matching, and will be destroyed after the expiry of one year.", "employment_types": ["Full Time", "Permanent"], "selling_points": [], "locations": ["Hung Hom"], "categories": ["Information Technology (IT)", "Product Management / Business Analyst", "Testing / QA"], "post_time": "2022-01-12T08:06:01Z", "salary": {"currency": null, "max": null, "min": null, "period": "monthly", "term": null}, "salary_visible": false, "title_keywords": ["senior project executive"], "responsibilities": ["operations", "systems", "procedures", "implementation", "monitoring", "testing", "payment", "system design", "documentation"], "requirements": {"degrees": [], "majors": [], "languages": ["putonghua", "english", "chinese"], "language_level": ["fluency", "advantage", "excellent"], "hard_skills": ["business management", "operation support"], "soft_skills": ["confident", "self-motivated", "driven", "organization skills", "interpersonal"], "languages_combined": [{"language": "putonghua", "language_level": ["fluency", "advantage"]}, {"language": "english", "language_level": ["excellent"]}, {"language": "chinese", "language_level": ["excellent"]}]}, "experience_required": {"duration": ["one to two years"], "field": []}}, {"job_id": "100003009037195", "location_code": "hk", "company": "Hong Kong Aircraft Engineering Co Ltd", "job_title": "Assistant Solutions Analyst (Enterprise Solutions)", "description": "Responsibilities:\n\n\nCreate detailed, comprehensive and well-structured test plan and acceptance criteria according to business requirements and schedule\nAssist creation of requirements traceability matrices and conduct reviews with Business Analysts and Software Development teams to ensure understanding of business requirements and complete test coverage\nDesign, develop, execute test cases (manual and / or automated) and analysis of testing results\nPerform business tasks to support project implementation including system testing and overall user acceptance testing \u00a0\nEnsure that system changes are authorized, tested and implemented in a controlled manner prior to being introduced into the production environment\nPerform any other duties as assigned by superior from time to time\n\u00a0\n\nQualifications:\n\n\nBachelor\u2019s degree in Information Technology, Computer Science or related discipline\n4-6 years of QA or software testing experience\nStrong knowledge of software QA methodologies, tools and processes\nSolid experience in test automation.\nProven work experience in software development will be considered as a distinct advantage\nInitiative, independent and quality-driven\nGood analytical and communication skills\nProficient in MS Word, Excel and Power Point\nGood command of written English and Chinese\nWe offer competitive remuneration package and career prospects to the right candidate. Salary will be commensurate with qualifications and experience. Our attractive remuneration package includes 5-day work week, year-end bonus, performance bonus, dental and medical benefits, employer voluntary contributions to MPF, education allowance, staff well-being sponsorship, birthday leave, marriage leave, family care leave, etc.\n\nInterested candidates please send your full resume stating contact details, current and expected salary by clicking \u201cApply Now\u201d.\n\nPersonal data collected will be used for recruitment purpose only. We are an equal opportunity employer\n\n", "employment_types": ["Full Time", "Permanent"], "selling_points": ["User requirement collection and system analysis", "Degree holder in Computer Science, Engineering", "Experience in VB SQL,Power BI,MS Azure & REST API"], "locations": ["Airport Area"], "categories": ["Information Technology (IT)", "Product Management / Business Analyst", "Software Development", "Testing / QA"], "post_time": "2022-01-11T02:02:07Z", "salary": {"currency": null, "max": null, "min": null, "period": "monthly", "term": null}, "salary_visible": false, "title_keywords": ["analyst", "assistant"], "responsibilities": ["any other duties", "software", "analysis", "teams", "implementation", "design", "develop", "testing", "quality", "communication", "schedule", "plan", "system changes"], "requirements": {"degrees": ["degree", "bachelor"], "majors": ["computer science", "information technology"], "languages": ["english", "chinese"], "language_level": ["good command"], "hard_skills": ["power point", "excel", "analysis", "ms word"], "soft_skills": ["communication skills", "independent", "driven", "detailed", "comprehensive", "controlled", "structured", "initiative", "superior"], "languages_combined": [{"language": "english", "language_level": ["good command"]}, {"language": "chinese", "language_level": ["good command"]}]}, "experience_required": {"duration": ["4-6 years"], "field": ["software development", "qa", "testing"]}}, {"job_id": "100003009049567", "location_code": "hk", "company": "Build King Holdings Ltd", "job_title": "Project Engineer / Project Officer - Innovative Solutions (Ref: JD/PEPO-IS)", "description": "We are searching\u00a0on behalf of a\u00a0Major Bank\u00a0for a number of high-calibre Project Assistants / Admin Assistants\u00a0to work on Treasury System Software\u00a0related projects.\n\nResponsibilities:\n\nWork on QA of Treasury System Software.\nPerform administrative tasks.\nPrepare regular reports.\nTraining will be provided.\n\nRequirements:\n\nDegree in Finance, Business Administration, Computer Science or related disciplines.\nDesire to start a career in a major bank\u00a0\nGood knowledge in MS Excel and Chinese word processing\nStrong written Chinese and English.\nLocation: Central.\nFresh Graduates are also welcome**\n\nBenefits:\u00a0\n\nAttractive remuneration will be offered to the successful candidates.\n\u00a0Excellent opportunity to further develop your professional skills in Banking Sector.\n\nIf you are interested, please send your resume in MS Word format, specifying your availability, current and expected salaries to:\n\njobs @itsolutions.com.hk\u00a0\n\nor\n\nPlease click the Apply Now button and attach your cv in MS Word Format, specifying your availability, current and expected salaries.\n\nPersonal data collected will be used for recruitment purposes only.\n\nIT Solutions Ltd.\nSuite 2102\n21/F Lucky Building\n39 Wellington Street\nCentral, Hong Kong\n\n(P.S. We do not process applications from overseas for this position)", "employment_types": ["Full Time", "Permanent"], "selling_points": ["Station at Head Office", "5-day work", "Free shuttle bus"], "locations": ["Kwun Tong"], "categories": ["Building & Construction", "Building / Construction / QS", "Information Technology (IT)", "Testing / QA", "Marketing / Public Relations", "Marketing - Brand / Product Management"], "post_time": "2022-01-14T08:53:52Z", "salary": {"currency": null, "max": null, "min": null, "period": "monthly", "term": null}, "salary_visible": false, "title_keywords": ["project officer", "project engineer"], "responsibilities": ["administrative tasks", "reports", "software"], "requirements": {"degrees": ["degree"], "majors": ["related disciplines", "finance", "business administration", "computer science"], "languages": ["english", "chinese"], "language_level": ["good"], "hard_skills": ["ms excel", "chinese word processing"], "soft_skills": [], "languages_combined": [{"language": "english", "language_level": []}, {"language": "chinese", "language_level": ["good"]}]}, "experience_required": {"duration": [], "field": []}}, {"job_id": "100003009050518", "location_code": "hk", "company": "Manpower Services (Hong Kong) Limited", "job_title": "Junior Programmer/Senior Programmer/Analyst Programmer (Welcome IT Fresh Grads)", "description": "Responsibilities:\n\nLead the digital quality assurance for the entire Bank project\nImplement and maintain testing standards and automation procedures for digital platforms.\u00a0\nEngage with Release and Change Management teams for effective change delivery into the group digital platform production platform\nEngage with development teams to embed Agile best practices for the release of quality deliverables.\u00a0\n\nRequirements:\n\n5+ years of related experience in manual and automation test\u00a0\nExperience in digital solution testing delivery is absolutely advantage\nProven experience in managing and executing various types of testing, including SIT, UAT, load test, performance test, resilience test, regression test, etc.\nHands-on experience in test management software and issue management software\nGreat communicator that can bridge communications gaps between culturally diverse vendor(s) and internal stakeholders\nAnalytical mind and problem-solving aptitude.\nExcellent communication and interpersonal skills.", "employment_types": ["Contract"], "selling_points": ["Stable career", "Attractive salary package", "Chance for promotion"], "locations": ["Central & Western Area"], "categories": ["Information Technology (IT)", "Application Specialist - Software", "Testing / QA"], "post_time": "2022-01-14T10:36:22Z", "salary": {"currency": null, "max": null, "min": null, "period": "monthly", "term": null}, "salary_visible": false, "title_keywords": ["analyst programmer", "senior programmer", "programmer", "junior"], "responsibilities": ["change management", "quality", "procedures", "teams", "testing", "digital platform", "maintain"], "requirements": {"degrees": [], "majors": [], "languages": [], "language_level": [], "hard_skills": ["problem-solving"], "soft_skills": ["problem-solving", "diverse", "hands-on", "analytical mind", "communication and interpersonal skills", "communicator"], "languages_combined": []}, "experience_required": {"duration": ["5+ years"], "field": ["related", "digital", "management", "testing"]}}, {"job_id": "100003009046846", "location_code": "hk", "company": "Nexify Limited", "job_title": "System Analyst (Java)", "description": "About the company\n\n\n\n\nAt\u00a0VYOND, our mission is to put the power of video in the hands of everyone.\u00a0Vyond\u00a0allows people of all skill levels in all industries and job roles to create dynamic and powerful media. With features that go\u00a0beyond\u00a0moving text and images, you can build character-driven stories or compelling data visualizations that engage audiences and deliver results.\n\nFounded as GoAnimate in 2007,\u00a0Vyond\u00a0has helped Global 2000 organizations, small businesses, and individuals produce more than 30 million videos.\n\nWith offices in Silicon Valley, Hong Kong, and Taiwan,\u00a0Vyond\u00a0employs a team of people whose creativity extends well\u00a0beyond\u00a0our office walls. We are passionate about the power of video and how it makes the static dynamic and transforms the mundane into the captivating.\n\nAbout the role:\n\nYou are a Software Engineer in nature. A career as a Software Development Engineer in Test (SDET) is your preferred, but not the second-choice.\n\n\n\n\nAs a hands-on Senior SDET at Vyond, you will make real impact, and be the key player by working closely with the Development team, QA team as well as the DevOps team to ensure the continuous quality of the codes throughout the whole software development life cycle. As a role model, you will be the expert in the team to inspire the developers to implement tests and write high quality scripts.\u00a0\n\n\n\n\nYou will be responsible for:\n\n\n\n\nDriving and implementing the automation testing strategy to support the company initiatives and roadmaps.\n\nOwning and directly contributing to the improvement of quality, as well as the coverage of tests.\n\nBuilding up and maintaining the test frameworks which enables developers to write reliable and better tests.\n\nWorking closely with the DevOps team to improve the CI/CD flow for achieving faster and reliable releases.\n\n\n\n\nIf you are passionate about technology, detail-oriented and obsessed with quality, this will be the perfect stage for you to demonstrate your skills and utilize your experience.\n\n\n\n\n\u00a0Basic Requirements:\n\n\n\n\nBachelor degree or above in Computer Science, or equivalent working experience.\u00a0\n\nMinimum 3 years of trackable and proven experience in designing and implementing automation frameworks for large or enterprise scale applications.\n\nSolid experience with SaaS, and cloud platforms like AWS / Azure / GCP.\n\nKnowledge of at least one OOP language (e.g. Java or C++).\u00a0\n\nFamiliarity with the software engineering methodologies and practices.\n\nAble to work independently; A team player, self-motivated and well organised.\u00a0\n\nExcellent communication skills. Able to work with people from different teams, with technical or non-technical backgrounds.\u00a0\n\nGood command of English, both written and spoken.\u00a0\n\n\n\n\n\n\u00a0Preferred Requirements:\n\nFull stack understanding of web application systems, from user input to data persistence.\n\nExperience in implementing or developing test suites for complex cloud applications with large scale and high availability.\n\nKnowledge of Node.js or Python.\n\nPrevious leadership experience is a plus.", "employment_types": ["Full Time", "Permanent"], "selling_points": ["Analyze business processes, identify problem areas", "User requirements collection and systems design", "Attractive remuneration package & 5 days work"], "locations": ["Kwun Tong"], "categories": ["Information Technology (IT)", "Software Development", "Testing / QA", "Network & System"], "post_time": "2022-01-14T01:27:35Z", "salary": {"currency": null, "max": null, "min": null, "period": "monthly", "term": null}, "salary_visible": false, "title_keywords": ["system analyst"], "responsibilities": ["software", "maintaining", "data", "quality", "teams", "developing", "testing", "communication", "designing", "application systems"], "requirements": {"degrees": ["degree or above", "bachelor"], "majors": ["computer science"], "languages": ["english"], "language_level": ["good command"], "hard_skills": ["small", "java", "plus", "basic", "azure", "c++", "web", "devops", "aws", "make", "dynamic", "python", "go", "codes"], "soft_skills": ["communication skills", "work independently", "self-motivated", "responsible", "detail-oriented", "hands-on", "dynamic", "organised", "team player", "reliable", "leadership", "driven", "passionate about"], "languages_combined": [{"language": "english", "language_level": ["good command"]}]}, "experience_required": {"duration": ["minimum 3 years"], "field": ["developing"]}}, {"job_id": "100003009040806", "location_code": "hk", "company": "The Hong Kong Polytechnic University", "job_title": "Postdoctoral Fellow / Research Associate", "description": "For Direct Application, please click\u00a0here\u00a0\nWe are looking for a QA Automation Engineer with a passion to develop and deliver high-quality automation test coverage for setting up automation framework from scratch for existing\u00a0and new feature development and making sure the regression cases are up to date. In this role, you will be involved in the whole software development lifecycle, from requirements analysis, testplanning, test execution, defect tracking until product delivery and maintenance.\nWhat you will be delivering\nAccountable for setting up the end to end automation test framework for mobile\u00a0apps and web applications.\nWork closely with QA Manager, Product Managers, Product Designers, CTO, Tech Leads to understand the project details.\nAble to estimate , prioritize\u00a0, plan , document, coordinate and execute the testing effort for any given deliverables.\nAble to set goals and handle multiple tasks, stakeholders and projects simultaneously if required.\nAble to drive the adoption of current best practices and contribute to the ongoing improvement of QA methodologies and processes.\nWho you are:\nStrong handson experience in automation testing using Appium, Selenium and other automation tools for performing mobile app\u00a0test and integration test automation fully into the CI / CD pipeline.\nSolid hands on experience\u00a0in creating automation framework with developing test scripts, maintaining\u00a0and continuously evolving efficient test automation approach for full coverage.\nMobile testing and automation using Java with Appium experience in IOS and Android App testing.\nGood understanding software development process, software testing types, techniques, tools, processes, and QA methodologies and\u00a0familiarity with Jira.\nKnowledge on any test management tools (Zephyr, XRay, PractiTest, Testlink, Testrail, Testflow).\nAble to perform API Testing by using any of the tools (Postman, Swagger and rest assured).\nExperience in working in Agile SCRUM team would be a plus.\nExperience with performance and/or security testing is a plus not mandatory.\nKnowledge on Saucelabs ,\u00a0BrowserStack tools would be a plus\n\nPerks and Benefits\n\nBirthday Leave\nMedical and Dental insurance\nStart-up Work Environment\u00a0\nFlexible Work Arrangement\nFree flow of snacks and soft drinks\u00a0\nGOGOX New Joiner Kit", "employment_types": ["Full Time"], "selling_points": [], "locations": ["Not Specified"], "categories": ["Information Technology (IT)", "Software Development", "Testing / QA", "Sciences, Lab, R&D", "Research & Development (R&D)"], "post_time": "2022-01-12T03:07:00Z", "salary": {"currency": null, "max": null, "min": null, "period": null, "term": null}, "salary_visible": false, "title_keywords": ["research associate"], "responsibilities": ["coordinate", "plan", "testing"], "requirements": {"degrees": [], "majors": [], "languages": [], "language_level": [], "hard_skills": ["java", "plus", "agile", "mobile", "integration", "android"], "soft_skills": ["efficient", "hands on", "agile"], "languages_combined": []}, "experience_required": {"duration": [], "field": ["security", "developing", "team", "testing"]}}, {"job_id": "100003009030787", "location_code": "hk", "company": "Peplink International Limited", "job_title": "QA / Test Engineer", "description": "Our client is seeking a Junior Programmer/Senior Programmer/Analyst Programmer (Welcome IT Fresh Grads) to join their team.\n\n\nJob Description:\n\nResponsible for system testing, coding, and debug in different stages\nMaintain system, application design, analysis, programming and develop\nParticipate in support and enhancement: system & user\nPrepare documentation and technical specification\nConduct the system implementation and configuration\nSystem coaching and team lead for senior level \u00a0\n\nRequirement:\n\nHigher Diploma / Associate Degree/ Degree in Information Technology, Computer Science, or related disciplines\nSchool Project or Working experience in JavaScript/ Java web application design and development is highly preferable \u00a0\nExperience in some of the followings:\nJava Application Framework\nJavaScript Programming\nJ2EE Development\nSQL/MS Access/ Oracle/ jQuery/ HTML5\nSpring/Node.js/React JS/ Hibernate/ TypeScript/ Unix\nMobile app design or development in Android or IOS platform\nGood command of both spoken and written English is an advantage\nImmediate available is highly preferred\n3-5 years of experience or above will be considered as Analyst Programmer;\n2-3 years of experience or above will be considered as Programmer;\nFresh graduates will be considered as Junior Programmer", "employment_types": ["Full Time", "Permanent"], "selling_points": ["5 days work, 2-month discretionary bonus", "Passionate in technology and development", "Fresh graduate will be considered"], "locations": ["Lai Chi Kok"], "categories": ["Information Technology (IT)", "Testing / QA", "Network & System", "Others"], "post_time": "2022-01-07T08:19:35Z", "salary": {"currency": null, "max": null, "min": null, "period": "monthly", "term": null}, "salary_visible": false, "title_keywords": ["engineer"], "responsibilities": ["configuration", "analysis", "implementation", "design", "coding", "testing", "develop", "maintain", "documentation"], "requirements": {"degrees": ["associate degree", "diploma", "degree"], "majors": ["related disciplines", "computer science", "information technology"], "languages": ["english"], "language_level": ["advantage", "good command"], "hard_skills": ["web application design", "java", "hibernate", "react", "jquery", "sql", "mobile", "javascript", "typescript", "programming", "spring", "android", "oracle"], "soft_skills": [], "languages_combined": [{"language": "english", "language_level": ["advantage", "good command"]}]}, "experience_required": {"duration": ["2-3 years", "3-5 years"], "field": ["development", "design"]}}, {"job_id": "100003009046991", "location_code": "hk", "company": "Global Executive Consultants Ltd.", "job_title": "Systems Analyst / Senior Systems Analyst (HK$50K to $60K) (Ref. No.: 24764)", "description": "Responsibilities:\n\nWork closely with the IT application team throughout the system development life cycle to deliver product features and solutions;\nUnderstand the business objectives and rationales behind high-level product features, analyze and translate them into detailed user specifications of projects;\nCoordinate with users in integration and testing of new enhancements;\nWork closely with the business/ product owners to influence and understand the product vision, strategic product direction, and product roadmap;\nAct as the key interface between the IT application team, relevant departments, and external vendors;\nKeep abreast of the market, suggest and propose new business initiatives.\n\n\u00a0Requirements:\n\nBachelor degree in Computer Science, IT, Business Information Systems or related field;\n1-2 years of relevant working experience is required, preferably in the financial industry;\u00a0\nExperience working in an Agile/Scrum software development environment a plus;\nKnowledge of SQL / automated testing tools is added advantage;\nPassionate about supporting development of IT systems and applications;\nStrong interpersonal skills and ability to work in a team;\nAbility to multi-task and manage in a fast-paced, dynamic environment;\nGood command of written and spoken English, Cantonese and Mandarin.\n\n\u00a0Our offer:\u00a0\n\nAttractive remuneration;\nCareer development prospect;\n5-day working week;\n21+ days Annual Leave for all staff;\nPerformance bonus and company shares;\nMedical, dental, life insurance;\nStaff discount on securities tranactions;\nTraining allowance and monthly sports allowance.\n\nInterested parties please send your full resume by clicking \"APPLY NOW\".\nOur company is an equal opportunities employer and welcome application from all qualified candidates.\u00a0Information provided will be treated with strict confidential and be used for the purpose of selection only.\u00a0Applicants who are not invited for interview within 10 weeks may consider their applications unsuccessful. Personal data of unsuccessful applicants will be destroyed within 12 months.", "employment_types": ["Full Time", "Permanent", "Contract"], "selling_points": ["Java / J2EE", "Vendor management", "Conduct market research"], "locations": ["Not Specified"], "categories": ["Information Technology (IT)", "Application Specialist - Software", "Software Development", "Testing / QA"], "post_time": "2022-01-14T09:04:56Z", "salary": {"currency": null, "max": null, "min": null, "period": "monthly", "term": null}, "salary_visible": false, "title_keywords": ["analyst"], "responsibilities": ["business initiatives", "specifications", "coordinate with", "testing"], "requirements": {"degrees": ["degree", "bachelor"], "majors": ["business", "it", "computer science"], "languages": ["cantonese", "english", "mandarin"], "language_level": ["good command"], "hard_skills": ["sql", "plus", "dynamic", "agile"], "soft_skills": ["dynamic environment", "multi-task", "agile", "interpersonal skills", "passionate about"], "languages_combined": [{"language": "cantonese", "language_level": ["good command"]}, {"language": "english", "language_level": ["good command"]}, {"language": "mandarin", "language_level": ["good command"]}]}, "experience_required": {"duration": ["1-2 years"], "field": ["financial industry", "relevant working experience", "software development"]}}, {"job_id": "100003009031562", "location_code": "hk", "company": "Computer And Technologies Software Limited", "job_title": "Quality Assurance Engineer (Ref: JDB/ERM/QAE)", "description": "Responsibilities\n\nResponsible for multiple platform applications design, development, implementation, maintenance and enhancement using multiple frameworks and languages;\nImprove code quality through writing unit tests, automation and performing code reviews;\nCommunicate with product team and users to get user feedback on our platform;\nSupport users in using our system on our daily operation.\n\nRequirements\n\nBachelor Degree or above in Computer Science or related field with minimum 3 year relevant experience;\nAmbitious to develop both web and mobile app with excellent end-user experience;\nExperience on building your own native iOS app and understand deeply the design theory behind it would be great;\nExperience of using, Golang, PHP, gRPC, RESTful API architecture;\nKnowledge with versioning control tools such as Git is a plus;\nProactive in brainstorming and contributing in cutting-edge technology development;\nGood command of both spoken and written English and Mandarin;\nCommitted, responsible, highly motivated and able to work independently. \u00a0\n\nWe offer competitive remuneration package with comprehensive fringe benefits to the right candidates:\n\n- Birthday Leave / Marriage Leave / Paternity Leave / Examination Leave\n- Staff Care Programme\n- Career Development Programme\u00a0\n\nContact us\n\nQualified candidate, please email your full resume with academic credentials, working experience, expected salary and availability by clicking the \"apply now\" button as below.", "employment_types": ["Full Time", "Permanent"], "selling_points": ["Responsible on test design/ optimization/ strategy", "Exp. in System Testing & Test management software", "Birthday Leave & Transportation Subsidy & Time-off"], "locations": ["Pok Fu Lam"], "categories": ["Information Technology (IT)", "Application Specialist - Software", "Software Development", "Testing / QA"], "post_time": "2022-01-07T09:28:21Z", "salary": {"currency": null, "max": null, "min": null, "period": "monthly", "term": null}, "salary_visible": false, "title_keywords": ["engineer"], "responsibilities": ["communicate with", "maintenance", "quality", "implementation", "design", "daily operation"], "requirements": {"degrees": ["degree or above", "bachelor"], "majors": ["computer science"], "languages": ["english", "mandarin"], "language_level": ["good command"], "hard_skills": ["restful api", "git", "plus", "web", "php", "mobile"], "soft_skills": ["work independently", "responsible", "cutting-edge", "committed", "motivated", "proactive"], "languages_combined": [{"language": "english", "language_level": ["good command"]}, {"language": "mandarin", "language_level": ["good command"]}]}, "experience_required": {"duration": ["minimum 3 year"], "field": ["related", "it", "relevant experience", "design"]}}, {"job_id": "100003009037978", "location_code": "hk", "company": "China Construction Bank (Asia) Corporation Limited", "job_title": "Process Planning & Management Professional (Payment / Cash Management Focus)", "description": "Nexify Limited is one of the leading IT solution providers specialized in system integration in Hong Kong. We encourage innovation, teamwork and personal growth. With continuous business expansion, we need high calibre candidates to join our professional team and we offer exciting job opportunities to the right talents. If you want to work in a fun and energetic environment, please do not hesitate to apply!\n\n\u00a0Job Description\n\n\nAnalyze business processes, identify problem areas of systems and recommend solutions\nConduct user requirements gathering, system analysis, design and development\nPrepare systems design specifications in accordance with business needs\nPrepare project schedule and resources requirements; manage requirements and monitor the project progress throughout project life cycles\nConduct SIT and support UAT to ensure the enhanced systems meet the requirement specifications\nPrepare documentation and technical specifications\n\nJob Requirement\n\n\nDegree holder in Information Technology or related disciplines\nAt least 5 years' practical work experience in Information Technology\nExperience in Java/J2EE, XML, JSON, Spring, Hibernate, Angular, Jasper Report or Restful API and web-based software development\nFamiliar with MS SQL Server, Oracle, MySQL, MariaDB or other databases\nKnowledge of AIX, Websphere, JBoss EAP, MongoDB, Mobile App development will be an advantage\nGood analytical mind and problem-solving skills\nGood interpersonal, verbal and written communication skills\nGood command of written and spoken Chinese and English\nCandidate with less experience will be considered as Analyst Programmer\n\nBenefits:\n\n5-Day Work Week\nPerformance bonus\nMarriage Leave\nPaternity Leave\nBirthday Leave\nMedical allowance\nCompassionate Leave\nExamination Leave\nPromotion opportunities\nIn-service training course\n\nWe offer 5-day work with good career prospects and excellent fringe benefits to the right candidates. Different areas of IT solution training will be provided. Please send your full resume including current and expected salary by clicking \"Apply Now\"", "employment_types": ["Full Time", "Permanent"], "selling_points": ["Process Planning & Management", "Payment / Cash Management", "User Acceptance Test"], "locations": ["Kowloon Bay"], "categories": ["Information Technology (IT)", "Testing / QA", "Banking / Finance", "Order Processing & Operation / Settlement"], "post_time": "2022-01-11T04:28:49Z", "salary": {"currency": null, "max": null, "min": null, "period": "monthly", "term": null}, "salary_visible": false, "title_keywords": ["cash management"], "responsibilities": ["uat", "analysis", "systems", "monitor", "project progress", "design", "design specifications", "specifications", "schedule", "documentation"], "requirements": {"degrees": ["degree holder"], "majors": ["related disciplines", "information technology"], "languages": ["english", "chinese"], "language_level": ["good command"], "hard_skills": ["java", "hibernate", "restful api", "ms sql server", "web-based software development", "mobile", "angular", "spring", "databases", "problem-solving skills", "oracle"], "soft_skills": ["communication skills", "problem-solving skills", "analytical mind", "interpersonal"], "languages_combined": [{"language": "english", "language_level": ["good command"]}, {"language": "chinese", "language_level": ["good command"]}]}, "experience_required": {"duration": ["at least 5 years"], "field": ["software development", "information technology"]}}, {"job_id": "100003009031841", "location_code": "hk", "company": "Recruit Logic Limited", "job_title": "Senior QA Analyst / QA Analyst - 20k - 45k x 13 months, Perm", "description": "At Peplink, your expertise will be turned into wired and wireless SD-WAN routers, software and technologies, which form a unique ecosystem to deliver reliable connectivity to global customers. Currently, thousands of customers around the world are using Peplink solutions to increase bandwidth, enhance Internet reliability, reduce connectivity cost, and enable new deployment possibilities.\n\nThe team is now looking for QA / Test Engineers, who will be working with other engineers from the Software Engineering team and Hardware Engineering team respectively. To ensure the highest level of stability, performance and usability of Peplink\u2019s products, the QA / Test Engineers need to understand and translate the requirement specifications into test scenarios, test cases and test reports. Implementing test automation and performing network simulations are also required.\n\nVisit https://www.peplink.com/ to know more about what you can achieve with Peplink (brand under Plover Bay, stock code: 1523).\n\nWhat We Need\n\nBS degree in Engineering or other technical disciplines\n3 years of relevant work experience\nExperience in setting up wired and wireless network\nKnowledge of Linux, scripting languages and test automation\n\nWe Hope You Are\n\n\nPassionate in technology\u00a0\nDetail-oriented\nProactive and able to perform analytical skills in problem solving\nHigh-caliber fresh graduates are encouraged to apply.\u00a0\nWhat We Offer\n\n\nGlobal exposure in a fast-growing technology company.\nCompetitive package commensurate with your experience.\nTransparent and diverse working culture.\u00a0\n2-month discretionary bonus.\nStock options plan.\nFlexible working hours; casual work attire.\n12-16 days of annual leave.\nFree snacks.\n5-day work week.\nPeplink is a place where problem solvers come together, get things done, and make things work. Ideas are welcome, and talents are valued. Join this energetic team and open up more possibilities with us! The journey will be challenging, but extremely fun.\u00a0\u00a0\n\n\nPlease send your CV with present and expected salary to\u00a0hr\u200b@peplink.com.\u00a0\n\nPersonal data collected will be treated in the strictest confidence and will only be used for employment-related purpose.", "employment_types": ["Full Time", "Permanent"], "selling_points": ["(Senior) QA Analyst - perm, inhouse", "Auto + Manual testing, application testing", "Sitting at headquarter with international coverage"], "locations": ["Tsing Yi"], "categories": ["Information Technology (IT)", "Testing / QA"], "post_time": "2022-01-07T09:49:09Z", "salary": {"currency": null, "max": null, "min": null, "period": "monthly", "term": null}, "salary_visible": false, "title_keywords": ["analyst"], "responsibilities": ["cost", "software", "bs", "hardware", "specifications", "reports"], "requirements": {"degrees": ["degree"], "majors": ["engineering"], "languages": [], "language_level": [], "hard_skills": ["hope", "linux", "analytical skills", "problem solving", "hardware", "sd-wan", "deployment", "code"], "soft_skills": ["passionate", "proactive", "unique", "detail-oriented", "analytical skills", "problem solving", "reliable"], "languages_combined": []}, "experience_required": {"duration": ["3 years"], "field": []}}, {"job_id": "100003009043189", "location_code": "hk", "company": "\u773c\u93e188\u6709\u9650\u516c\u53f8 OPTICAL 88 Limited", "job_title": "Senior Analyst Programmer", "description": "Main Responsibilities\n\n- Responsible for analysis, development, testing and technical specification delivery\n- Co-ordinate and communicate with stakeholders effectively according to project plan\n- Support user acceptance testing and system implementation\n- Provide production support\n\nRequirements\n\n- Degree holder in Computer Science, Information Technology or related disciplines\n- Minimum 3 years experience on web/mobile application development, preferably in banking\n- Excellent in programming languages including JavaScript, Java, XML, HTML/CSS, webservice etc.\n- strong knowledge and hand-on experience of various mobile frameworks, e.g. React Native\n- Proficiency in JEE, Spring, Microservice\n- Good knowledge of DevOps & Agile development\n- Good analytical, inter-personal communication and problem-solving skills\n- Good team player who is passionate in latest technology trend and eager to learn or develop new skills\n- Proactive, independent and able to multi-tasking under pressure\n- Excellent language in both spoken and written English and Chinese (including Mandarin)\n- Business travel may be required", "employment_types": ["Full Time"], "selling_points": ["Perform ERP and POS implementation", "Handle system testing and problem identification", "Provide daily support to end users"], "locations": ["Wong Tai Sin Area"], "categories": ["Information Technology (IT)", "Support", "Software Development", "Testing / QA"], "post_time": "2022-01-12T10:08:28Z", "salary": {"currency": null, "max": null, "min": null, "period": null, "term": null}, "salary_visible": false, "title_keywords": ["senior analyst programmer"], "responsibilities": ["communicate with", "analysis", "implementation", "project plan", "testing"], "requirements": {"degrees": ["degree holder"], "majors": ["related disciplines", "computer science", "information technology"], "languages": ["english", "chinese", "mandarin"], "language_level": ["excellent"], "hard_skills": ["java", "agile", "web", "problem-solving skills", "devops", "html", "mobile", "javascript", "react native", "programming", "spring", "css"], "soft_skills": ["passionate", "good team player", "independent", "agile", "under pressure", "inter-personal", "communication", "eager to learn", "multi-tasking", "problem-solving skills", "proactive"], "languages_combined": [{"language": "english", "language_level": ["excellent"]}, {"language": "chinese", "language_level": ["excellent"]}, {"language": "mandarin", "language_level": ["excellent"]}]}, "experience_required": {"duration": ["minimum 3 years"], "field": ["application development", "banking"]}}, {"job_id": "100003009041961", "location_code": "hk", "company": "New Beauty Group Limited", "job_title": "Analyst Programmer (Front/ Back- End)", "description": "DEPARTMENT OF COMPUTING\n\nPostdoctoral Fellow / Research Associate (Ref.22011202)\n\n[Appointment period: twelve to thirty-six months]\n\nDuties\n\nThe appointee will assist the project leader in the research project - \u201cSecond phase of the Jockey Club diversity at schools project\u201d. \u00a0The project aims to transform local schools into self\u2010learning organizations that are capable to manage student diversity effectively and efficiently in their school-based contexts through the development and enhancement of school\u2010based diversity infrastructures in three domains: data\u2010driven / data\u2010informed school practice, learning and teaching activities, and close collaboration.\u00a0 He/She will act as AI Analyst and be required to:\n\n(a) carry out implementation and support tasks to ensure student data platform and associated systems being effectively implemented at schools, and quality support services being provided to enable adoption;\n\n(b) conduct trainings and coaching to schools, teachers and systems administrators/IT support to ensure that they can effectively use the platform and the data to enable appropriate profiling, reporting, analytics, and intervention for diversity management;\n\n(c) conduct trainings to schools, teachers, systems administrators on the use of data platform, associated systems, dash boards, AI tools, and the use and analysis of data;\n\n(d) assist schools in the use, processing, and analysis of data and the development of analytics reports or dash boards;\n\n(e) promote and facilitate deeper and wider adoption and use of the data platform and related solutions;\n\n(f) provide effective support services to schools and teachers on operational and functional matters related to student data platform and use of data;\n\n(g) investigate and follow\u2010up problems or incidents related to the use of the data platform;\n\n(h) communicate with schools and teachers on implementation, usage and adoption;\n\n(i) develop, maintain and support dashboards, analytics modules and reports;\n\n(j) assist in the tunning of AI and machine learning tools at school level;\n\n(k) assist in systems testing to ensure quality systems and services; and\n\n(l) assist in the organization of workshops, seminars, conferences and other events as needed.\n\nQualifications\n\nFor the post of Postdoctoral Fellow, applicants should have a doctoral degree or an equivalent qualification and must have no more than five years of post\u2010qualification experience at the time of application.\n\nFor the posts of Research Associate, applicants should have a master\u2019s degree or a good honours degree with three or more years of research/relevant work experience.\n\nFor both posts, applicants should also:\n\n(a) have at least 2 years\u2019 experience in software development, system support and training/teaching, preferably with some project management experience;\n\n(b) have excellent communications skills and be fluent in both written and spoken English and Chinese;\n\n(c) be proficient in using IT applications;\n\n(d) have some knowledge of the use of BI and AI tools; and\n\n(e) be familiar with school environment and use of data in education.\n\nApplicants are invited to contact Prof. Jiannong Cao at tel no. 2766 7275, fax no. 2774 0842 or email via \"Apply Now\"\u00a0for further information.\n\nRemuneration\n\nA highly competitive remuneration package will be offered.\u00a0 Applicants should state their current and expected salary in the application.\n\nApplication\n\nPlease send a completed application form by post to Human Resources Office, 13/F, Li Ka Shing Tower, The Hong Kong Polytechnic University, Hung Hom, Kowloon, Hong Kong or via email by clicking \"Apply Now\".\u00a0 Application forms can be downloaded from\u00a0 https://www.polyu.edu.hk/hro/careers/guidelines_and_forms/forms. If a separate curriculum vitae is to be provided, please still complete the application form which will help speed up the recruitment process. \u00a0The closing date for application is Thursday, 10 February 2022.\u00a0 Applicants who are not invited to an interview within two months from the closing date should consider their applications unsuccessful.\u00a0 Applications should be addressed directly to Prof. Jiannong Cao (please state Department ofComputing on the envelope).\u00a0 The University\u2019s Personal Information Collection Statement for recruitment can be found at https://www.polyu.edu.hk/hro/careers/guidelines_and_forms/pics_for_recruitment.\n\nPolyU is an equal opportunity employer committed to diversity and inclusivity.\u00a0 All qualified applicants will receive consideration for employment without regard to gender, ethnicity, nationality, family status or physical or mental disabilities.\u00a0", "employment_types": ["Full Time", "Permanent"], "selling_points": ["HTML, CSS, JavaScript, JQuery, AJAX, XML and MySQL", "2 - 3 years of experience", "Dynamic, young and supportive environment"], "locations": ["Mong Kok"], "categories": ["Information Technology (IT)", "Application Specialist - Software", "Software Development", "Testing / QA"], "post_time": "2022-01-12T05:56:16Z", "salary": {"currency": null, "max": null, "min": null, "period": "monthly", "term": null}, "salary_visible": false, "title_keywords": ["analyst programmer"], "responsibilities": ["software", "data", "quality", "maintain", "implementation", "develop", "testing", "conferences", "reports", "reporting", "management", "contact", "recruitment process", "communicate with", "analysis", "support services", "systems", "project management", "recruitment"], "requirements": {"degrees": ["degree", "master"], "majors": [], "languages": ["english", "chinese"], "language_level": ["excellent", "fluent"], "hard_skills": ["no", "bi", "ai", "analysis", "project management", "c", "workshops", "processing"], "soft_skills": ["project management", "learning", "capable", "committed"], "languages_combined": [{"language": "english", "language_level": ["fluent", "excellent"]}, {"language": "chinese", "language_level": ["fluent", "excellent"]}]}, "experience_required": {"duration": ["at least 2 years", "five years"], "field": ["research", "training", "system support", "project management", "software development", "teaching"]}}, {"job_id": "100003009035429", "location_code": "hk", "company": "Global Logistics System (HK) Co Ltd", "job_title": "AUTOMATED CARGO DISTRIBUTION ANALYST (5-Day Work)", "description": "More than 1 location (will be assigned to 1 location):\n\n\nFotan (will move to Hung Hom in Q1 2022)\nLai Chi Kok\nKwun Tong\nWong Chuk Hang\nQuarry Bay\n\n\nResponsibilities\n\nCreating test plan, test cases based on user stories\nSetup testing environment and test preparation.\nReport any finding in bug tracking system and prepare a testing report\nLiaise with users and development teams\n\n\nRequirements\n\nMinimum 6 months application testing experience\nPreferably Higher Diploma in Information Technology or related discipline\nWork independent, analytical, good problem solving skills, and must be able to cope with tight project schedule\nGood communication skill in both spoken and written English and Chinese.\nFresh graduates are welcomed.\n\n\nInterested parties please send your resume by Apply Now.\n\n", "employment_types": ["Full Time"], "selling_points": ["Large-scale air cargo industry project", "Work-life balance", "Medical insurance with attractive package"], "locations": ["Airport Area"], "categories": ["Information Technology (IT)", "IT Project Management / Team Lead", "Product Management / Business Analyst", "Testing / QA"], "post_time": "2022-01-10T07:07:43Z", "salary": {"currency": null, "max": null, "min": null, "period": "monthly", "term": null}, "salary_visible": false, "title_keywords": ["analyst"], "responsibilities": ["teams", "testing", "plan", "liaise with", "testing environment", "report", "setup", "tracking"], "requirements": {"degrees": ["diploma"], "majors": ["information technology"], "languages": ["english", "chinese"], "language_level": ["good"], "hard_skills": ["problem solving skills"], "soft_skills": ["problem solving skills", "communication skill", "independent"], "languages_combined": [{"language": "english", "language_level": ["good"]}, {"language": "chinese", "language_level": ["good"]}]}, "experience_required": {"duration": [], "field": ["testing"]}}, {"job_id": "100003009043529", "location_code": "hk", "company": "Mirum Hong Kong", "job_title": "Senior Developer / Analyst Programmer", "description": "Let\u2019s work together\n\n\nPerform ERP and POS implementation\nHandle system testing, problem identification and bug fixing\nCollect user requirements\nDevelop user reports using reporting tools\nProvide daily support to end users\nResponsible for system documentation and user training\n\u00a0We are looking for\n\n\nHigher Diploma or above in Computer Science or related disciplines\nMinimum 4 years of ERP support experience\nHands-on experience in retail systems such as BOSS SIS & POS\nFamiliar with RDMBS (Sybase, MS Access, SQL Server, MySQL, etc)\nExperience in Java, VBScript, PowerBuilder, C++ or VB preferred\nAttention to details and strong sense of responsibility\nStrong analytical and problem solving skills\nGood interpersonal and communication skills\n\nJoin us now:\n\nPlease send\u00a0full resume stating your academic qualifications, career history, availability with current and expected salary\u00a0to: The\u00a0Human Resources Manager\n\u00a0\nOn offer is a competitive package\nAttractive\u00a0Remuneration\n5 Days Work\nAnnual Leave\nFamily Leave\nMonthly Early Release\n\n\nBirthday Leave with gifts\nMarriage Leave with red packets\nExamination Leave\nMedical Scheme\nStaff Discount\n\n\u00a0Website: www.optical88.com.hk", "employment_types": ["Full Time", "Part Time", "Permanent", "Contract", "Freelance"], "selling_points": ["Attractive package and career growth", "Participate in a large, young fast-growing team", "Experience to work with well-known enterprises"], "locations": ["Quarry Bay"], "categories": ["Information Technology (IT)", "Application Specialist - Software", "Software Development", "Testing / QA"], "post_time": "2022-01-12T16:32:38Z", "salary": {"currency": null, "max": null, "min": null, "period": "monthly", "term": null}, "salary_visible": false, "title_keywords": ["analyst programmer", "developer"], "responsibilities": ["communication", "website"], "requirements": {"degrees": ["higher diploma or above"], "majors": ["related disciplines", "computer science"], "languages": [], "language_level": [], "hard_skills": ["server", "java", "pos", "c++", "erp", "sql", "powerbuilder", "documentation"], "soft_skills": ["hands-on", "attention to details", "responsible", "sense of responsibility"], "languages_combined": []}, "experience_required": {"duration": ["minimum 4 years"], "field": ["retail"]}}, {"job_id": "100003009034888", "location_code": "hk", "company": "ConnectedGroup Limited", "job_title": "Senior IT Business Analyst, Financial Services", "description": "Pursue a Career with Impact\n\nAt New Beauty, we dare to envision, and we strive for perfection.\n\nNew Beauty is under a leading Medical Beauty Group, Perfect Medical,\u00a0 which has over 100 treatment centers worldwide. With our passion for innovation and breakthroughs, our group business\u2019 global footprint has been extending from Hong Kong Headquarter to China, Macau, Australia and Singapore with over 2,000 employees across regions.\n\nTo cope with the Company\u2019s rapid expansion, we are currently looking for high caliber and visionary candidates to join our team as Analyst Programmer\n\nResponsibilities:\n\nDesign, develop, implement and maintain web based applications and services\nGather and refine specifications and requirements based on technical needs\nRevise, edit, proofread & optimize web content\nWork with cross-functionally to enhance overall user experience of our platforms\nOwn various design tasks involved in the web development life cycle from start to finish\n\nRequirements:\n\nHigh Diploma or above in Computer Science or related disciplines\nAt least 1-2 years' solid experience in website development\nExperience on using HTML, CSS, JavaScript, JQuery, AJAX, XML and MySQL\nKnowledge of responsive design and cross-browser compatibility\nSelf-motivated with can do attitude and timely delivery of results\nAbility to multi-task, organize and prioritize work\nWe offer competitive remuneration package and good prospects to the right candidates.\u00a0Interested parties please send your full resume with expected salary to apply.\u00a0Data collected will be kept confidential and used for recruitment purposes only.", "employment_types": ["Full Time", "Permanent"], "selling_points": ["Digital Solutions", "Agile", "Business Analyst/ Project Manager"], "locations": ["Not Specified"], "categories": ["Information Technology (IT)", "IT Project Management / Team Lead", "Product Management / Business Analyst", "Testing / QA"], "post_time": "2022-01-10T04:30:15Z", "salary": {"currency": null, "max": null, "min": null, "period": "monthly", "term": null}, "salary_visible": false, "title_keywords": ["business analyst"], "responsibilities": ["user experience", "design", "develop", "specifications", "maintain"], "requirements": {"degrees": ["high diploma or above"], "majors": ["related disciplines", "computer science"], "languages": [], "language_level": [], "hard_skills": ["jquery", "html", "javascript", "ajax", "css"], "soft_skills": ["self-motivated", "multi-task", "timely", "prioritize", "responsive"], "languages_combined": []}, "experience_required": {"duration": ["at least 1-2 years"], "field": ["development"]}}, {"job_id": "100003009031306", "location_code": "hk", "company": "EY Mtel Solutions Limited", "job_title": "Test Engineer / Senior Test Engineer", "description": "Job Responsibilities:\n\n\n\nActively initiate and drive continuous improvement of EzyCargo/CX Cargo.com and other distribution tools.\nConsolidate the user requirments from worldside outports to enhance existing booking engines/systems.\nCoordinate, conduct workshop and meetings to understand business nature, process flow.\nArticulate the requirements, implement and support distribution projects and being a business analyst to ensure vendor deliver planned projects in a timely and cost effective manner.\nPrepare testing plan and review test cases and scenarios and documented properly.\nParticipate in system testing cycle (UAT/PT/SIT) and complete the testing in timely & accurate manner.\nDesign, compile and distribute management reports for measuring the KPI/result/usage rate post cutover.\nMaintain user guide/business process for worldwide reservation team on e-booking/booking functions, so as to improve agent self-service functions and increase capacity for revenue generation.\nDesign solutions to cater the unique & special sales practice from different regions, and achieve the global standardization in ultimate goal.\nAssist to formulate worldwide GSA deployment strategies/contract renewal. Assess sales performance of GSA against commission pay-out to ensure commission payout generate the best possible revenue return.\nSupport in financial modelling, to prepare the cargo distribution cost budget and forecast.\n\nJob Requirements:\n\nUniversity degree (Preferably in related disciplines)\nResults-driven individual with proven analytical skills and commercial acumen.\nStrong command of analytical tools e.g. Excel, PowerPoint.\nEager to learn, easy adopt to change/new initiative and able to pick up the knowledge in a fast manner\nDeliver results in timely manner, able to work under high pressure\nStrong communication and presentation skills.\nSome experience in aviation industry is an advantage.\nExperienced candidate will be considered as senior position\n\nWe offer\u00a05-day work\u00a0and attractive remuneration,\u00a0medical and dental insurance,\u00a0provident fund\u00a0and other fringe benefits including\u00a0discounted air tickets\u00a0on Cathay Pacific Airways,\u00a0recreation subsidy,\u00a0birthday leave,\u00a0Airport Express discount\u00a0and\u00a0shuttle bus\u00a0to the right candidate and his/her dependents etc.\u00a0 Interested parties, please submit your detailed CV, stating your present and\u00a0expected salary\u00a0and\u00a0availability\u00a0to us.\n\nWe are an equal opportunity Employer. All CVs and personal data collected are for recruitment purposes and the information will be kept confidential.", "employment_types": ["Full Time", "Permanent"], "selling_points": ["Higher Diploma or Degree in Computer Science / IT", "1 year or above relevant experience", "Design and create test plans/ test scripts"], "locations": ["Kwun Tong"], "categories": ["Information Technology (IT)", "Support", "Software Development", "Testing / QA"], "post_time": "2022-01-07T09:10:49Z", "salary": {"currency": null, "max": null, "min": null, "period": "monthly", "term": null}, "salary_visible": false, "title_keywords": ["engineer"], "responsibilities": ["cost", "uat", "design solutions", "sales performance", "workshop", "systems", "review", "budget", "design", "testing", "coordinate", "management reports", "maintain", "business process", "booking", "plan", "forecast"], "requirements": {"degrees": ["university degree"], "majors": ["related disciplines"], "languages": [], "language_level": [], "hard_skills": ["powerpoint", "excel", "acumen", "analytical skills"], "soft_skills": ["timely", "driven", "analytical skills", "communication", "eager to learn", "presentation skills", "work under high pressure", "initiative"], "languages_combined": []}, "experience_required": {"duration": [], "field": []}}, {"job_id": "100003009038725", "location_code": "hk", "company": "China Construction Bank (Asia) Corporation Limited", "job_title": "Business Analyst, Commercial Banking (Ref no: IT/CMB/JDB)", "description": "Job Highlights\n\n\nAttractive package and career growth\nParticipate in a large, young fast-growing team\nExperience to work with well-known enterprises\nJob Description\n\n\nRole and Responsibilities\n\n\nResponsible for technology development and maintenance of web applications\nParticipate in the entire software development life cycle\nCollaborate with project and creative teams to define, design, and implement digital solutions\nPerform website and system optimization and quality assurance\nCommunicate with client's IT teams and prepare technical documentation\nEmbrace large scale development\n\nRequirement\n\nDegree/Higher Diploma in Computer Science/IT or equivalent but not entirely necessary based on the skillset\n3+ years of experience in web development\nExperience in .NET(C#, ASP.NET), JAVA, PHP, Node.js, HTML, JavaScript, React.JS, Vue, CSS, etc.\nStrong knowledge of Database, e.g. MySQL, MSSQL, Oracle\nFamiliar with web servers or development tools, e.g. IIS, Apache, Git\nExperience in enterprise solutions such as Sitecore, Umbraco, Kentico, MS Sharepoint or Drupal is a plus\nKnowledge about AWS, Azure or other cloud technology is an advantage\nExperience in DevOps, CI/CD, Docker, networking, automated test is an advantage\nDemonstrate positive and can-do attitude to provide alternatives and solutions\nAct as a strong team player and proactive to resolve problem as a team\nStrong sense of responsibility and self-motivated to embrace challenges\nGood analytical and problem-solving skills\nCandidate with more experience will be considered as Analyst Programmer\n\n\u00a0What we can offer:\n\nAn attractive salary and benefits package, a long-term career prospect to the right talents\nParticipate in a large, young and fast-growing technical team which allows the right candidates to contribute and learn with the team.\nExperience to work with the well-known enterprise clients\nOpportunities to involve in large variety of digital projects (e.g. website and mobile development, system integration, AR/VR innovations)\nState of the art office and an innovation centre\u00a0", "employment_types": ["Full Time", "Permanent"], "selling_points": ["Project Management, UAT, IT background", "Commercial Banking", "Bachelor degree with min. 3 yrs of experience"], "locations": ["Kowloon Bay"], "categories": ["Banking / Finance", "Corporate Banking", "Information Technology (IT)", "Product Management / Business Analyst", "Testing / QA"], "post_time": "2022-01-11T07:41:22Z", "salary": {"currency": null, "max": null, "min": null, "period": "monthly", "term": null}, "salary_visible": false, "title_keywords": ["business analyst"], "responsibilities": ["collaborate with", "communicate with client", "software", "maintenance", "teams", "website", "design", "quality", "documentation"], "requirements": {"degrees": ["diploma", "degree"], "majors": ["it", "computer science"], "languages": [], "language_level": [], "hard_skills": ["web development", "java", "apache", "git", "plus", "php", "react", "azure", "devops", "problem-solving skills", "iis", "html", "aws", "javascript", "mssql", "css", "web servers", "oracle"], "soft_skills": ["self-motivated", "sense of responsibility", "can-do attitude", "problem-solving skills", "team player", "proactive", "positive"], "languages_combined": []}, "experience_required": {"duration": ["3+ years"], "field": ["development", "devops"]}}, {"job_id": "100003009034714", "location_code": "hk", "company": "Peoplehub Limited", "job_title": "Product Business Analyst - Oversea project [Perm, up to 40k]", "description": "A well-established Financial Institution is currently looking for multiple Senior IT Business Analysts to join their digital team to focus on transformation projects, this particular individual will be expected to act as BA/ PM and work closely with different senior stakeholders for projects delivery.\n\nResponsibilities:\n\nOversee projects planning, scope; schedule, resources, cost, budgeting and quality\nLeading ongoing reviews of business processes and developing optimization strategies.\nWriting functional specification for larger scale projects, and engaging technical teammates to ensure the solution remains technically feasible.\nParticipate in test plans and performance UAT\nConducting meetings and presentations to share ideas and findings.\nEffectively communicating your insights and plans to cross-functional team members and management.\nServing as a liaison between stakeholders and users.\n\nRequirements:\n\nBachelor degree in Information Technology or related discipline\nMore than 3-year working experience as Business Analyst\nCandidates with more experience might be considered as (Senior) Manager\nPreferably working experience within banking/ insurance sector\nCreative, innovative and well-organised personnel with strong communication and interpersonal skills\nSelf-motivated, independent, diligent and able to work under pressure and overtime to execute projects\nExcellent command of written and spoken English and Chinese\n\nInterested individuals can click apply now and send updated resume (in WORD format) to Mannie CHIU for further information.", "employment_types": ["Full Time", "Permanent"], "selling_points": ["Global project", "Good English Speaking", "Western style management"], "locations": ["Not Specified"], "categories": ["Professional Services", "Business Analysis / Data Analysis", "Information Technology (IT)", "Product Management / Business Analyst", "Testing / QA"], "post_time": "2022-01-10T04:02:36Z", "salary": {"currency": null, "max": null, "min": null, "period": "monthly", "term": null}, "salary_visible": false, "title_keywords": ["business analyst"], "responsibilities": ["cost", "management", "ideas", "uat", "budgeting", "quality", "developing", "presentations", "schedule", "plans", "planning"], "requirements": {"degrees": ["degree", "bachelor"], "majors": ["information technology"], "languages": ["english", "chinese"], "language_level": ["excellent"], "hard_skills": ["word"], "soft_skills": ["self-motivated", "independent", "diligent", "innovative", "communication and interpersonal skills", "well-organised", "creative", "work under pressure"], "languages_combined": [{"language": "english", "language_level": ["excellent"]}, {"language": "chinese", "language_level": ["excellent"]}]}, "experience_required": {"duration": ["3-year"], "field": ["business", "insurance", "banking"]}}, {"job_id": "100003009025083", "location_code": "hk", "company": "Q P Group Holdings Limited", "job_title": "Senior System Quality Assurance Engineer/ Manager", "description": "Responsibilities:\n\nDevelop and maintain home-grown application / system under the coordination with team members and users;\nAssist in application development, system testing, implementation, debugging and maintenance;\nPrepare system documentation and online tutorials for user training;\nAssist in any ad-hoc duties as assigned\n\nRequirements:\n\nHigher Diploma or above in Computer Science or related field, in which with solid application support experience is an advantage;\nKnowledge of web development & frameworks, e.g. PHP, JavaScript, HTML5, CSS, JQuery, AJAX;\nKnowledge with MSSQL and MySQL database;\nGood interpersonal and communication skills;\nEager to learn and take on challenges;\nCandidate with more experience will be considered as Senior Programmer\nWorking Location - Fotan\n\n\nWe offer\u00a0competitive\u00a0package and benefits:\n\n\u00a0\u00a0\u00a0\u00a0\u00a0\u00a0\u00a0\u00a0 Five-Day work week\n\u00a0\u00a0\u00a0\u00a0\u00a0\u00a0\u00a0\u00a0 3 Days Marriage Leave\n\u00a0\u00a0\u00a0\u00a0\u00a0\u00a0\u00a0\u00a0 5 Days Full Pay Paternity Leave\n\u00a0\u00a0\u00a0\u00a0\u00a0\u00a0\u00a0\u00a0 Family-Friendly Leave\n\u00a0\u00a0\u00a0\u00a0\u00a0\u00a0\u00a0\u00a0 Birthday Leave\n\u00a0\u00a0\u00a0\u00a0\u00a0\u00a0\u00a0\u00a0 Free Duty Meal\n\u00a0\u00a0\u00a0\u00a0\u00a0\u00a0\u00a0\u00a0 Staff Discount\n\u00a0\u00a0\u00a0\u00a0\u00a0\u00a0\u00a0\u00a0 Medical Benefits\n\u00a0 \u00a0 \u00a0 \u00a0 \u00a0Life Insurance Plan\n\u00a0\u00a0\u00a0\u00a0\u00a0\u00a0\u00a0\u00a0 Promotion Opportunities\n\nFor more company information, please visit our web site at\u00a0www.taihing.com\nInterested parties please send\u00a0full resume with expected salary\u00a0and availability\u00a0to the\u00a0Human Resources Department via email.\n\nAll information received will be kept in strict confidence and only used for employment-related purposes. Applicants who are not invited for interview within 6 weeks may consider their applications unsuccessful.", "employment_types": ["Full Time"], "selling_points": ["Perform manual and automated testing", "Output document with relevant tools", "5 years+ experience on relevant field"], "locations": ["Shatin Area"], "categories": ["Engineering", "Others", "Information Technology (IT)", "IT Management", "Testing / QA"], "post_time": "2022-01-06T03:24:43Z", "salary": {"currency": null, "max": null, "min": null, "period": "monthly", "term": null}, "salary_visible": false, "title_keywords": ["manager", "engineer"], "responsibilities": ["system documentation", "maintenance", "coordination with", "implementation", "testing", "develop", "maintain", "ad-hoc duties", "application development"], "requirements": {"degrees": ["higher diploma or above"], "majors": ["computer science"], "languages": [], "language_level": [], "hard_skills": ["web development", "php", "jquery", "javascript", "ajax", "mssql", "css"], "soft_skills": ["communication skills", "interpersonal", "eager to learn"], "languages_combined": []}, "experience_required": {"duration": [], "field": ["related"]}}, {"job_id": "100003009029223", "location_code": "hk", "company": "Dah Sing Financial Group", "job_title": "Project Assistant, Testing (12 months Contract)", "description": "Responsibilities:\nDesign and create test plans, test scripts and other relevant documents\nDesign and implement automated tests\nReproduce defects for investigation\nRequirements\n\n\nTo qualify for the role you must have:\n\nHigher Diploma or above in Computer Science, Information Technology or equivalent\n1 year or above experience in software testing\nUnderstanding and use of testing techniques\nGood communication skills in both English and Chinese\nTeam player, self-motivated, well organized and ability to work under pressure\nExperience in automatic test framework such as Appium or Selenium\nFresh graduates would be considered\u00a0\u00a0\n\nWhat working at EY offers:\n\nSupport, coaching and feedback from some of the most engaging colleagues around\nOpportunities to develop new skills and progress your career\nThe freedom and flexibility to handle your role in a way that\u2019s right for you\n\nIf you can confidently demonstrate that you meet the criteria above, please contact us as soon as possible.\n\nJoin us in building a better working world.\n\nApply now.", "employment_types": ["Contract"], "selling_points": ["Assist in project management in terms of UAT", "Matriculated or degree holder", "Around 1 - 3 working experiences"], "locations": ["North Point"], "categories": ["Information Technology (IT)", "IT Project Management / Team Lead", "Testing / QA", "Network & System"], "post_time": "2022-01-07T04:41:07Z", "salary": {"currency": null, "max": null, "min": null, "period": "monthly", "term": null}, "salary_visible": false, "title_keywords": ["project assistant"], "responsibilities": ["plans", "investigation", "design"], "requirements": {"degrees": ["higher diploma or above"], "majors": ["computer science", "information technology"], "languages": ["english", "chinese"], "language_level": ["good"], "hard_skills": [], "soft_skills": ["communication skills", "self-motivated", "well organized", "team player", "work under pressure"], "languages_combined": [{"language": "english", "language_level": ["good"]}, {"language": "chinese", "language_level": ["good"]}]}, "experience_required": {"duration": ["1 year"], "field": ["testing"]}}, {"job_id": "100003009025251", "location_code": "hk", "company": "PCCW Solutions", "job_title": "Quality Assurance Specialist / Analyst", "description": "Job Descriptions:\n\n\n\nProvide project management support for the implementation of banking systems in Commercial Banking Division.\nConduct user requirement analysis for the automation of banking operations as well as regulatory and MIS reporting.\nCoordinate the conduct of user acceptance testing and test cases planning\n\nRequirements:\n\n\nUniversity graduate preferably in Computer Science, Banking and Finance, Business Management or related disciplines\nAt least 3 years of IT related working experience in banking or finance industry is preferred\nExperience in analysing user requirements for automation and implementing automation projects of different banking business areas, including regulatory reporting, treasury system, risk management system and trade finance system.\nThorough working knowledge of banking operations and computer technology.\nProject management experience is required.\nGood command of written and spoken English and Chinese (including Putonghua). Ability in other languages would be an advantage.\nEnthusiastic and self-motivated.\n\nTo apply, please send the detailed resume to the designated email address or by fax at 3718 2910.\n\nApplicants who are not contacted within 8 weeks may consider their applications unsuccessful and their personal data will be retained by the bank for a period up to two years.\n\nAll information provided by applicants will be used for recruitment purposes only and will be used strictly in accordance with the bank\u2019s personal data policies, a copy of which will be provided upon request.", "employment_types": ["Full Time"], "selling_points": [], "locations": ["Mong Kok"], "categories": ["Information Technology (IT)", "Testing / QA"], "post_time": "2022-01-06T03:56:44Z", "salary": {"currency": null, "max": null, "min": null, "period": "monthly", "term": null}, "salary_visible": false, "title_keywords": ["specialist", "analyst"], "responsibilities": ["user requirement", "reporting", "operations", "analysis", "systems", "implementation", "testing", "coordinate", "project management", "banking", "planning"], "requirements": {"degrees": ["university graduate"], "majors": ["related disciplines", "finance", "business", "computer science"], "languages": ["putonghua", "english", "chinese"], "language_level": ["good command"], "hard_skills": ["business management", "project management"], "soft_skills": ["self-motivated", "project management", "thorough", "enthusiastic", "detailed"], "languages_combined": [{"language": "putonghua", "language_level": ["good command"]}, {"language": "english", "language_level": ["good command"]}, {"language": "chinese", "language_level": ["good command"]}]}, "experience_required": {"duration": ["at least 3 years"], "field": ["risk management", "related", "finance", "banking", "project management", "it", "business", "finance industry"]}}, {"job_id": "100003009027397", "location_code": "hk", "company": "JFE Consulting Limited", "job_title": "QA Analyst/ Tester", "description": "Summary:\nYou will be responsible to manage and support on User Acceptance Test (UAT) for the rollout of Core Banking System and assist in designing UAT test cases and performing UAT testing according to the pre-defined test cases.\nKey Role and Responsibilities:\nAssist in project management in terms of User Acceptance Testing (UAT) planning, UAT co-ordination, UAT environment setup, UAT test cases preparation and execution\nDesign test scenarios and test case based on business requirement, functional requirement specification (FRS), test plan and ensure comprehensive coverage of test cases\nManage execution of test case manually or using automated testing tools\nCompile test result to respective handling staff assigned by project team for upload to defect management system and monitor the defect fixing progress\nMonitor UAT schedule and progress and support the rollout of bank Teller systems\nUnderstand the limitations and issues of existing testing processes and recommend improvement initiatives\nProvide guidance and coaching to junior UAT tester of the team\nJob Requirements:\nMatriculated or degree holder\nAround 1 - 3 working experiences, preferably in IT/ Banking sectors\nExperience in performing testing of banking systems\nProduct Knowledge on Retail Banking / Corporate Banking is essential\nSelf-initiative, able to work independently and under pressure, and meet tight deadline\nMeticulous and well organized\nExcellent communication and interpersonal skills\nGood command of both written and spoken English and Chinese\nPlease note that only shortlisted candidates will be notified.", "employment_types": ["Full Time", "Permanent"], "selling_points": ["Opportunity to involve large scale project", "On Job Training ,coordinate and prepare test plans", "Perm role, 13 month guarantee + Bonus,Medical"], "locations": ["Not Specified"], "categories": ["Information Technology (IT)", "Application Specialist - Software", "Product Management / Business Analyst", "Testing / QA"], "post_time": "2022-01-06T09:53:08Z", "salary": {"currency": null, "max": null, "min": null, "period": "monthly", "term": null}, "salary_visible": false, "title_keywords": ["analyst"], "responsibilities": ["management", "uat", "systems", "monitor", "design", "testing", "project management", "schedule", "plan", "provide guidance", "setup", "planning"], "requirements": {"degrees": ["degree holder"], "majors": [], "languages": ["english", "chinese"], "language_level": ["good command"], "hard_skills": [], "soft_skills": ["meticulous", "work independently", "under pressure", "well organized", "communication and interpersonal skills", "self-initiative", "meet tight deadline"], "languages_combined": [{"language": "english", "language_level": ["good command"]}, {"language": "chinese", "language_level": ["good command"]}]}, "experience_required": {"duration": [], "field": ["testing", "it", "banking"]}}, {"job_id": "100003009037993", "location_code": "hk", "company": "China Construction Bank (Asia) Corporation Limited", "job_title": "OFC - Analyst Programmer (Investment Applications)", "description": "Key Responsibilities\n\n\nAct as a quality champion and empower teams to create highly performant and secure systems.\nAct entrepreneurially to try unhappy paths and edge cases in performance /security testing to create a highly resilient system\nDefine procedures for specific products by writing test plans and creating test cases based on requirements and design documentation\nDevelop automated systems to make tests reusable.\nMaintain systems to be completely error-free and in line with specifications by performing various kinds of testing, including quality assurance and design reviews\nAnalyze any detected issues, and track down the root cause.\nConfigure necessary hardware and operating environments as needed to complete assigned testing and providing technical know-how on particular products, operating systems and specialized environments\nPrepare reports on test results and problems, monitoring and updating test processes, assisting in the review of test processes as they are developed, and performing other test-related tasks.\nEnsure development work follow department standard and guideline\nEnsure the software development progress according to schedule\n\nRequirements\n\n\nMinimum 6 years of experience as an exploratory/hands-on tester with multiple platforms and testing techniques\nSolid experience with implementing automated end-to-end tests, experience with frameworks and tools such as BDD, Selenium, Appium and the ability to code in common languages such as Java or JavaScript\nHands on experience in Mobile Automation Testing, Mobile Web Testing and API testing\nExperience with manual acceptance testing at story level, exploratory and creative testing, and within fast-paced sprint cycles\nPreferable with experience in managing multiple and complex testing involving multiple critical banking applications\n\nFor more details about career opportunities with the Bank, please visit our website http://www.cncbinternational.com/careers/en/index.jsp. Please apply with full resume stating current and expected salaries.\nPersonal data collected will be used for recruitment related purposes only. Applicants not invited for interview within 6 weeks may consider their applications unsuccessful. However, applicants may be considered for other suitable positions within the Group for a period of not more than 2 years. Personal data will be destroyed at any time after 3 months.\n\nChina CITIC Bank International is committed to being an equal opportunities employer and intends to provide a work environment free of unlawful discrimination or harassment. All employment decisions will be made in a non-discriminatory manner.", "employment_types": ["Full Time", "Permanent"], "selling_points": ["Analyst Programmer", "Investment Applications", "system integration testing"], "locations": ["Kowloon Bay"], "categories": ["Information Technology (IT)", "Testing / QA", "Technical Writing"], "post_time": "2022-01-11T04:30:25Z", "salary": {"currency": null, "max": null, "min": null, "period": "monthly", "term": null}, "salary_visible": false, "title_keywords": ["analyst programmer"], "responsibilities": ["prepare reports", "software", "monitoring", "systems", "teams", "quality", "procedures", "testing", "design", "develop", "hardware", "maintain", "specifications", "review", "schedule", "documentation", "plans", "operating systems"], "requirements": {"degrees": [], "majors": [], "languages": [], "language_level": [], "hard_skills": ["java", "mobile", "javascript", "code", "web testing"], "soft_skills": ["committed", "hands-on", "hands on", "creative"], "languages_combined": []}, "experience_required": {"duration": ["minimum 6 years"], "field": ["banking", "testing"]}}, {"job_id": "100003009041200", "location_code": "hk", "company": "Taylor Coulter", "job_title": "Programmer/ Analyst Programmer - banking applications", "description": "Our client is an award-winning MNC and a revolutionary market leader that is seeking for a high calibre\u00a0QA Analyst/ Tester to join their expanding team in the Hong Kong office.\n\n\n\nYou will be:\n\nTo coordinate and prepare test plans in order to fulfill the test requirements\nDevelop and execute testing scripts to automate tests;\u00a0\nDefine product test cases and criteria for acceptance\nResponsible for test standard & procedures\nTo resolve the problem / potential issue of test process\nOrganize test cases and report testing progress to supervisors\n\n\u00a0We need you:\n\nDiploma or above in Information Technology or Business Management\n1 to 2-year QA / Tester working experience\nExperience in conduct testing\u00a0\nGood command of spoken and written English and Chinese", "employment_types": ["Full Time"], "selling_points": ["Java, Spring boot; C# is an advantage", "interested in banking & financial industry", "More experience will be considered as AP"], "locations": ["Quarry Bay"], "categories": ["Information Technology (IT)", "Application Specialist - Software", "Software Development", "Testing / QA"], "post_time": "2022-01-12T03:35:17Z", "salary": {"currency": null, "max": null, "min": null, "period": "monthly", "term": null}, "salary_visible": false, "title_keywords": ["analyst programmer", "programmer"], "responsibilities": ["management", "procedures", "testing", "coordinate", "develop", "plans", "report"], "requirements": {"degrees": ["diploma or above"], "majors": ["business", "information technology"], "languages": ["english", "chinese"], "language_level": ["good command"], "hard_skills": ["business management"], "soft_skills": ["revolutionary", "responsible"], "languages_combined": [{"language": "english", "language_level": ["good command"]}, {"language": "chinese", "language_level": ["good command"]}]}, "experience_required": {"duration": ["2-year"], "field": ["qa", "testing"]}}, {"job_id": "100003009033804", "location_code": "hk", "company": "Nixon Technology Co Ltd", "job_title": "Web Developer / Senior Web Developer", "description": "Accelerate your career\n\n\nYou will be a core member of our System Support Team to implement & support the mission critical Enterprise System and Infrastructures\u00a0including Oracle DB, Exadata,\u00a0ZDLRA, Mongo, Hadoop and DBF platforms in both Hong Kong and Shanghai office.\nThis is an excellent opportunity to participate in our most challenging project of Enterprise system implementation, supporting and new technologies evaluations.\nYour role\nEvaluate and implement efficient and scalable system management and automation tools to support our Enterprise Applications on Linux & Windows platforms.\u00a0On Job Training will be provided where applicable.\n\nProvide timely support, trouble shooting and implement the fixing in related platforms.\nProvide the Disaster Recovery environment implementation and support.\n\nWho we are looking for\n\nUniversity graduate in Information Technology or related disciplines.\nAdequate and related IT experiences and exposures to Oracle technology e.g. Oracle DB 10g or above.\nJunior IT graduate with strong willingness to learn and to implement new technologies is also welcome.\nProficient spoken and written English, Cantonese and Mandarin is advantage.\n\nInterested parties please send your application letter with detailed resume and expected salary by clicking \"Apply Now\" and quote the reference number on the subject\n\n(Data collected will be used for recruitment purpose only.)", "employment_types": ["Full Time"], "selling_points": ["Experience in Java/Cloud-based development", "Familiar with frontend build, unit testing and CI", "Knowledge in UX/UI design skill"], "locations": ["Kwun Tong"], "categories": ["Information Technology (IT)", "IT - Webmaster / SEO", "Software Development", "Testing / QA"], "post_time": "2022-01-10T01:49:16Z", "salary": {"currency": null, "max": null, "min": null, "period": "monthly", "term": null}, "salary_visible": false, "title_keywords": ["developer"], "responsibilities": ["evaluate", "management", "implementation"], "requirements": {"degrees": ["university graduate"], "majors": ["related disciplines", "information technology"], "languages": ["cantonese", "english", "mandarin"], "language_level": ["advantage", "proficient"], "hard_skills": ["system implementation", "linux", "oracle"], "soft_skills": ["efficient", "timely"], "languages_combined": [{"language": "cantonese", "language_level": ["advantage", "proficient"]}, {"language": "english", "language_level": ["advantage", "proficient"]}, {"language": "mandarin", "language_level": ["advantage", "proficient"]}]}, "experience_required": {"duration": [], "field": ["related", "it"]}}, {"job_id": "100003009039369", "location_code": "hk", "company": "iTalent Company", "job_title": "Quantitative Developer - Crypto Trading Platform / Multiple openings", "description": "Job duties:\n\nResponsible for designing, developing and supporting scalable web-based applications in a collaborative team\nConduct system tests to ensure systems operate accurately\nPrepare necessary documentation and maintaining proper record of documents\nProvide daily support services for application\n\nJob Requirements:\n\nBachelor or above in Computer Science / Information Technology or related discipline\nExperience/ Knowledge in web programming\nKnowledge in Java / JavaScript / NodeJS / AngularJS / React is highly advantage\nFresh graduates will also be considered", "employment_types": ["Full Time", "Permanent"], "selling_points": ["Crypto / Blockchain, Java is preferred", "Quantitative Trading", "Competitive package and flexi-working environment"], "locations": ["Not Specified"], "categories": ["Information Technology (IT)", "Application Specialist - Software", "Software Development", "Testing / QA"], "post_time": "2022-01-11T09:32:29Z", "salary": {"currency": "HKD", "max": 119999, "min": 35000, "period": "monthly", "term": null}, "salary_visible": true, "title_keywords": ["developer"], "responsibilities": ["maintaining", "systems", "support services", "developing", "designing", "documentation"], "requirements": {"degrees": ["bachelor"], "majors": ["computer science", "information technology"], "languages": [], "language_level": [], "hard_skills": ["java", "web", "react", "javascript", "programming"], "soft_skills": [], "languages_combined": []}, "experience_required": {"duration": [], "field": ["programming"]}}, {"job_id": "100003009031008", "location_code": "hk", "company": "Page Group Hong Kong", "job_title": "IT Test Analyst - Fast-Growing Insurance Firm", "description": "CISD (Asia) Co., Ltd. is a system integrator and is now seeking high caliber\napplicants to join us.\n\nSkills:\n\nSAP ERP System Administrator will share the responsibility of the design,\nconfiguration and\u00a0management of ERP and peripheral system for 1000+ Users.\nBasis team member not only will\u00a0manage SAP Basis layer but also be in charge of the\nwhole underlying infrastructure hosted in\u00a0data center.\n\nRequirement\n\n- Applicant must be the Hong Kong resident or with Hong Kong\n\u00a0 \u00a0work permit\n- Diploma in Computer Science or related discipline\n- Good command of English and Cantonese\n- Must be independent, responsible and punctual\n- Good communication skill with team mates and related project members\n- Solid troubleshooting skill and can maintain emotion and patience\n\u00a0 \u00a0under situations\n- Must be organized, pay attentions and recognize tasks followed by\n\u00a0 \u00a0other mates.\n- Must be able to prepare material to propose solutions and procedures\n\u00a0 \u00a0as necessary.\n- Good documentation skill is necessary\n- Be responsible for maintaining ledgers and critical documents.\n- Experience with SAP R/3, SAP ECC or SAP S/4\n- Experience with SAP Solution Manager and SAP Router\n- Experience with (SAP) database administration of Microsoft SQL Server\n\u00a0 \u00a0and/or SAP\u00a0HANA1/2\n- At least 3 years relevant experience in Windows server system\n- Experience with Active Directory / LDAP is welcome\n- Experience with Enterprise Linux server administration is preferable\n- Network knowledge is preferable\n- Experience with enterprise virtualization platform such as VMware,\n\u00a0 \u00a0Hyper-V is preferable\n- Solid experience in setup and administration of proprietary server\n\u00a0 \u00a0vendor hardware\u00a0(HPE,DELL, Lenovo etc)\n- Experience with scripting for server administration\n\u00a0 \u00a0(VBS/.NET/PowerShell/Linux batch\u00a0script etc) is welcome\n- Experience with administering Microsoft cloud services (M365, Azure etc)\n\u00a0 \u00a0are preferred.\n\n\nJob Duties\n\n- Manage and operate multi-layer aspects of global SAP system infrastructure.\n- Inspect and monitor status of services and underlying infrastructure.\n- Troubleshooting within SAP, operating system and hardware layer as necessary.\n- Interact with SAP and other vendors to acquire official support information.\n- Interact with other non-Basis SAP teams to provide access and solution for them.\n- ID administration of end users and other SAP support teams.\n- Support headquarter office's requests for audit related information gathering.\n- Regular system maintenance (monthly in one weekend)\n\n\nWe offer a 5-day work with an attractive package to the right candidate.\nInterested parties please click \"APPLY NOW\"\u00a0\u00a0or fax: 2865 1218.\n\nVisit us at www.cisd.com.hk for more information.\n\nAll information provided by applicants will be treated in strict confidence and will only be used for recruitment related purposes. All unsuccessful applications will be destroyed within 6 months.", "employment_types": ["Full Time", "Permanent"], "selling_points": ["Career Opportunity in a Fast-Growing Firm", "Exposure to Various Insurance Projects", "Dynamic and Friendly Working Environment"], "locations": ["Not Specified"], "categories": ["Information Technology (IT)", "Testing / QA"], "post_time": "2022-01-07T08:48:43Z", "salary": {"currency": null, "max": null, "min": null, "period": "monthly", "term": null}, "salary_visible": false, "title_keywords": ["analyst"], "responsibilities": ["maintenance", "infrastructure", "teams", "monitor", "troubleshooting", "audit", "hardware", "administration"], "requirements": {"degrees": ["diploma"], "majors": ["computer science"], "languages": ["cantonese", "english"], "language_level": ["good command"], "hard_skills": ["linux", "hyper-v", "server", "azure", "vmware", "sap", "ecc", "active directory", "server administration", "vendor", "router", "hardware", "batch", "powershell", "microsoft sql server", "documentation", "r", "windows server"], "soft_skills": ["organized", "independent", "responsible", "communication skill", "troubleshooting", "patience", "active"], "languages_combined": [{"language": "cantonese", "language_level": ["good command"]}, {"language": "english", "language_level": ["good command"]}]}, "experience_required": {"duration": ["at least 3 years"], "field": ["server administration", "sql", "relevant experience", "database", "administration"]}}, {"job_id": "100003009024632", "location_code": "hk", "company": "Robert Walters (HK)", "job_title": "Quality Assurance/ UAT Tester - Digital Banking ~30K", "description": "Our client:\n\nOur client is a well-funded fintech company with an open-source blockchain-based operating system with smart contract functionality. With headquarter in Beijing and regional office in HK and Singapore. They are now looking for Quantitative Developers to join their development team. Candidate with working experience or who is enthusiastic in Blockchain / Crypto is a big plus.\n\nYour role:\n\nMaintain and optimize order management system, market tick data capture, exchange API connectivity, etc.\nExpand automated trading business to new trading products and venues, calibrate and fine tune the performance\nTake lead in idea generation, alpha research, trading strategy formulation, back-testing and implementation\nParticipate in strategy research using deep learning and reinforcement learning\nCollaborate with quant trading teams to implement market making / delta-1 strategies\nImprovement of existing strategies, portfolio optimization and evaluating new datasets for alpha potential\nDevelop models and tools to automate daily tasks\nConduct post trade analysis of trading strategies and algo performance\n\nRequirements:\n\nBachelor in EE/CS or relevant engineering/quantitative fields\n1+ years\u2019 exp. Fresh welcome\nProficiency in python. C++/Java is plus\nExperience in exchange gateway/data feed handler\nGood knowledge in multithreading, networking and data structure\nHands on restful/websocket experience is preferred\nCrypto experience is preferred, but not a must\nFrontend experience is welcome, but not a must\nFluent in Chinese and English\nProblem solver, self-motivated, open-minded and responsible\n\nClick \"Apply Now\" to apply for this position or\u00a0call\u00a0us\u00a0at\u00a0+852 2762 4829\u00a0for a confidential discussion. All information collected will be kept in strict confidence and will be used for recruitment purposes only.\u00a0", "employment_types": ["Full Time", "Contract"], "selling_points": ["Gather User Requirement, set up test bed", "Participate UAT and regression test", "Experience on UAT and / or systems design"], "locations": ["Not Specified"], "categories": ["Banking / Finance", "Others", "Information Technology (IT)", "Product Management / Business Analyst", "Testing / QA"], "post_time": "2022-01-06T02:00:43Z", "salary": {"currency": "HKD", "max": 34999, "min": 20000, "period": "monthly", "term": null}, "salary_visible": true, "title_keywords": ["uat tester"], "responsibilities": ["collaborate with", "order management", "data", "analysis", "teams", "implementation", "testing", "develop", "maintain", "recruitment"], "requirements": {"degrees": ["bachelor"], "majors": ["engineering"], "languages": ["english", "chinese"], "language_level": ["fluent"], "hard_skills": ["blockchain", "plus", "java", "crypto", "c++", "analysis", "python", "exchange"], "soft_skills": ["self-motivated", "confidence", "problem solver", "responsible", "open-minded", "deep", "learning", "hands on", "enthusiastic"], "languages_combined": [{"language": "english", "language_level": ["fluent"]}, {"language": "chinese", "language_level": ["fluent"]}]}, "experience_required": {"duration": [], "field": []}}, {"job_id": "100003009014218", "location_code": "hk", "company": "Capgemini Hong Kong Limited", "job_title": "Test Lead/Manager", "description": "Our client is currently handling multiple projects for their insurance direct channels. The successful candidates will work with different stakeholders within and outside of the company throughout the UAT activities. Candidates must have proven experience in dealing with banking or insurance-related products. Fluency in both English and Cantonese are mandatory.\n\nClient Details\n\nOur client is a well-known financial services company with strong business focus in Hong Kong. With more than 50 years of history operating in major financial hubs, the firm has continued to provide top-notch insurance & investment product to their global clients.\n\nThey are currently running different on-going projects under their insurance division. The successful candidates will work with different stakeholders for the UAT processes of the insurance products. Candidates must have proven experience dealing with insurance, banking, or investment products. Fluency in both English and Cantonese are mandatory.\n\nDescription\n\nResponsibilities:\n\nCoordinate with different stakeholders and project teams for the testing activities\nForm test scenarios and cases based on the business requirements\nCollaborate with QA/ Development team members in executing UAT\nConduct timely and accurate fulfillment and business reports\nPrepare necessary project documents for reporting and user training purposes\n\nProfile\n\nRequirements:\n\nBachelor's degree holder in Business Administration, Information System, Statistic or related disciplines\nAt least 2 years of banking/insurance experience, preferably with exposure to testing or UAT experience\nSolid understanding in Life Insurance, General Insurance or Employee Benefit\nExperience in Agile/ Scrum projects would be an advantage\nProficient in English and Chinese communication, both in written and spoken\n\nJob Offer\n\nCareer Progression in a Sizeable Company\nExposure to Large Scale Projects\nExposure to Various Insurance Products\nExperience in Standardized UAT Workflow\nSolid IT Infrastructure with Updated Applications\nDynamic Working Environment\nCompetitive Salary with Bonuses\nGenerous Balance of Annual Leaves\nConvenient Working Location\n\nTo apply online please click the 'Apply' button below. For a confidential discussion about this role please contact Sedrick Chan on +852 2258 3417.", "employment_types": ["Full Time", "Permanent", "Contract"], "selling_points": ["Test Management", "Team Leading", "Manual & Automation Testing"], "locations": ["Others"], "categories": ["Information Technology (IT)", "Testing / QA"], "post_time": "2022-01-03T03:10:03Z", "salary": {"currency": "HKD", "max": 69999, "min": 45000, "period": "monthly", "term": null}, "salary_visible": true, "title_keywords": ["manager", "lead"], "responsibilities": ["collaborate with", "reporting", "uat", "fulfillment", "teams", "coordinate with", "testing activities", "project documents", "executing", "reports"], "requirements": {"degrees": ["bachelor", "degree holder"], "majors": ["related disciplines", "business administration"], "languages": ["english", "chinese"], "language_level": ["proficient"], "hard_skills": ["dynamic", "information system", "agile"], "soft_skills": ["communication", "dynamic", "agile"], "languages_combined": [{"language": "english", "language_level": ["proficient"]}, {"language": "chinese", "language_level": ["proficient"]}]}, "experience_required": {"duration": ["at least 2 years"], "field": ["testing", "insurance", "banking"]}}, {"job_id": "100003009014524", "location_code": "hk", "company": "Osmium Consulting Group Limited", "job_title": "Senior/QA Analyst ( Manual Testing | Automation Testing )", "description": "Main Duties & Responsibilities:\n\nProvide high quality application support to business, fulfilling requests accurately and in a timely manner\nDiagnose and resolve application incidents and problems in Loan System and a range of critical software applications for back-office\nMonitor high priority incidents and performance problems, conduct root cause analysis, and deliver resolution to avoid recurrence\nCode development for complete change management assessments at the organizational level\nPerform stakeholder management, particularly in supporting and engaging internal stakeholders\nAssist in developing support processes and ensure up-to-date documentation is available for cross team knowledge sharing and development\nTest software components to ensure enhancements and patches delivered to customers are in full working order\nSystems management and monitoring of server tasks to ensure incoming and outgoing data is processed reliably on schedule\nEnsure the system design reflects user requirements by conducting system design review with business user\nAssist development team in deployment of applications\nConduct System Integration Testing (SIT) and coordinate User Acceptance Test (UAT)\nDocument project artifacts and deliverables such as test cases and test results\n\nRequirements:\n\nDegree in Computer Science or relevant disciplines\nAt least 3 years of solid experience in C# application development\nFamiliar with entity Framework, .Net MVC, C#, SQL, JavaScript and HTML\nFamiliar with configuration of Window Servers environment\nFamiliar with development/task management/version control tools: Visual Studio, Jira, Git, SourceTree, etc\nExperience in end-to-end system development lifecycle (SDLC) from analysis, development, testing, deployment, to maintenance\nExcellent communication, team spirit and problem-solving skill\nExcellent command of spoken and written Chinese and English\n\nWe offer:\n\nDiscretionary bonus\nMedical insurance\nDental insurance\nHardship allowance\nCompetitive annual leave days\nBirthday leave\nAnniversary leave\nStudy leave\nMarriage leave\nCompassionate leave\n\nHow to apply:\n\nInterested parties, please send your resume stating your expected salary\u00a0to\u00a0Human Capital Department\u00a0by clicking\u00a0\"APPLY NOW\".\n\n(We are an equal opportunity employer.\u00a0 Personal data collected will be used for recruitment purpose only.\u00a0 The unsuccessful applications will be destroyed after 6 months.)", "employment_types": ["Full Time", "Permanent"], "selling_points": ["Attractive Bonus! No OT!", "Competitive Salary and Benefits", "Work from Home Plan"], "locations": ["Tsim Sha Tsui"], "categories": ["Information Technology (IT)", "Application Specialist - Software", "Testing / QA", "Others"], "post_time": "2022-01-03T03:34:58Z", "salary": {"currency": "HKD", "max": 44999, "min": 25000, "period": "monthly", "term": null}, "salary_visible": true, "title_keywords": ["analyst"], "responsibilities": ["software", "data", "quality", "uat", "monitor", "diagnose", "developing", "testing", "resolution", "schedule", "management", "change management", "monitoring", "review", "documentation", "analysis", "systems", "a timely manner", "coordinate", "system design"], "requirements": {"degrees": ["degree"], "majors": ["computer science"], "languages": ["english", "chinese"], "language_level": ["excellent"], "hard_skills": ["git", "servers", "maintenance", "analysis", "problem-solving", "html", "sql", "sdlc", "javascript", "deployment", "c#"], "soft_skills": ["communication", "problem-solving", "team spirit"], "languages_combined": [{"language": "english", "language_level": ["excellent"]}, {"language": "chinese", "language_level": ["excellent"]}]}, "experience_required": {"duration": ["at least 3 years"], "field": ["maintenance", "development", "testing", "system development", "application development"]}}, {"job_id": "100003009035027", "location_code": "hk", "company": "Delken Group Limited", "job_title": "Associate (Treasury Operations)", "description": "Our client is a Financial Institution, they are currently seeking for an Associate (Treasury Operations) to join their team.\n\n\nResponsibilities\n\n\nTo support treasury operations and settlements for all treasury activities, including documentation review and payment execution;\nTo participate in designing, developing and testing application systems;\nTo design and construct ad-hoc data analysis and reporting;\nTo recommend and implement new systems and processes, business process reengineering initiatives and procedural manuals maintenance; and\nThe employment will be on contract basis subject to renewal.\n\nRequirements:\n\nBachelor degree in Finance, Accounting, Business Administration, Information Systems or related discipline. \u00a0Candidates with dual degree in business and IT would be preferable;\nPreferably with 1 year of working experience in commercial banks or financial institutions;\nSolid knowledge in banking products, system development cycle and UAT would be an advantage;\nAttention to details, high degree of accuracy, able to work independently, under pressure and meet tight deadlines;\nSelf-motivated, proactive working attitude, eager to learn and willing to take up new responsibilities;\nExcellent command of written and spoken English and Chinese;\nProficient in computer operation including MS Word and MS Excel, knowledge in MS Access an added advantage; and\nFresh graduates will also be considered\n\nInterested candidates, please send your resume (MS Word document) including employment history, present and expected salary to us.\n\nFor more jobs, please visit our website:\u00a0www.delken.com.hk.\u00a0\n\n(All personal data submitted will be treated in strict confidential and used for recruitment purposes only.)\u00a0", "employment_types": ["Full Time", "Contract"], "selling_points": ["1 yr exp in Comm'l bank or finance/Fresh grad.", "Data analysis & reporting, UAT knowledge an advan.", "5-days, 15AL, Med, Immediate Available preferable"], "locations": ["Kwun Tong"], "categories": ["Accounting", "Accounting Clerk / Supervisor", "Banking / Finance", "Treasury", "Information Technology (IT)", "Testing / QA"], "post_time": "2022-01-10T05:24:04Z", "salary": {"currency": null, "max": null, "min": null, "period": "monthly", "term": null}, "salary_visible": false, "title_keywords": ["operations", "associate"], "responsibilities": ["ad-hoc", "reporting", "maintenance", "operations", "review", "systems", "developing", "design", "testing", "data analysis", "payment", "business process", "designing", "documentation", "application systems"], "requirements": {"degrees": ["degree", "bachelor"], "majors": ["business administration", "finance", "business", "it", "accounting"], "languages": ["english", "chinese"], "language_level": ["excellent"], "hard_skills": ["ms excel", "ms word"], "soft_skills": ["work independently", "self-motivated", "under pressure", "meet tight deadlines", "eager to learn", "attention to details", "proactive"], "languages_combined": [{"language": "english", "language_level": ["excellent"]}, {"language": "chinese", "language_level": ["excellent"]}]}, "experience_required": {"duration": ["1 year"], "field": ["commercial", "financial institutions"]}}, {"job_id": "100003009026945", "location_code": "hk", "company": "Wistron Information Technology and Services Limited", "job_title": "Testing Engineer", "description": "The Job:\n\nPropose feasible business solutions and optimize solution delivery for projects\nProvide business analysis service and/or process review to support business initiatives\nLead the collection functional & non-functional analysis and/or documenting business needs and requirements in a complex environment\nLiaise with end-users and IT delivery partners to facilitate alignment of understanding of requirements between business and IT\nConduct gap analysis and support IT feasibility study from business perspective\nEngage in business solution design and apply operation knowledge to contribute alternative solutions.\nDrive requirement gathering activities via interviews, workshops and meetings with stakeholders\nPrepare test plan and script for developer\n\nThe Candidate:\n\nBachelor degree with 2 years of experience with a focus on business analysis and/or system analysis\nPrevious project management / Agile experience will be an advantage\nGood Communication skill in English\u00a0\n\nFor interested parties, please send your full resume and expected salary to\u00a0cv@ peoplehub.hk\n\nPersonal data will be treated with strict confidential and used for recruitment purpose only", "employment_types": ["Full Time", "Permanent"], "selling_points": ["Testing experience preferred", "Preference for existing HK visa", "Telematics Testing"], "locations": ["Tsuen Wan Area"], "categories": ["Information Technology (IT)", "Testing / QA"], "post_time": "2022-01-06T08:55:38Z", "salary": {"currency": null, "max": null, "min": null, "period": "monthly", "term": null}, "salary_visible": false, "title_keywords": ["engineer"], "responsibilities": ["business initiatives", "analysis", "review", "design", "communication", "liaise with", "project management", "plan", "business analysis"], "requirements": {"degrees": ["degree", "bachelor"], "majors": ["business"], "languages": ["english"], "language_level": ["good"], "hard_skills": ["agile", "analysis", "gap", "project management", "workshops", "focus"], "soft_skills": ["project management", "focus", "communication skill", "agile"], "languages_combined": [{"language": "english", "language_level": ["good"]}]}, "experience_required": {"duration": ["2 years"], "field": ["business analysis", "project management"]}}, {"job_id": "100003009034106", "location_code": "hk", "company": "iAsia Online Systems Limited", "job_title": "Project Manager (Project Management Office Team)", "description": "Senior System Quality Assurance Engineer/ Manager\n\nJob Responsibilities:\n\nPerform manual and automated testing\nReview web product GUI, web API & draft all relevant test cases/test plans, well documents\nOutput document with relevant tools to illustrate the findings and methods\nAlign with all departments and define the structure on quality assurance @ software & release readiness\nAs a key stakeholder in Bugs review meeting & explain all levels of bugs\nBugs Report with summary which aligned with statistic figures\nManage on QA Automation, release notes and related release actions\nTarget to achieve Excellence in Code (SAFECode)\nPerform ad hoc assignment assigned by management\n\nRequirements:\n\nBachelor Degree in Computer Science or related discipline\n5 years+ experience on relevant field with Ecommerce website experience\nProgramming knowledge in Python, HTML/2.X, ASP.NET, JS & JSP. Knowledge on MS SQL/ MongoDB is a plus\nBasic knowledge in web server such as IIS & APACHE, STATEFUL/STATELESS web platform\nExperience on CI/CD pipeline workflow, SDLC, QA Automation\nSolid experience in Bitbucket, Github, JIRA & JENKIN\nUnderstand Hardware/Software requirements of the automation tool\nNice if ever worked with Agile development, any automation software testing tools for VS IDE\nGood communication skill, problem solving skill and project management skill\n\nApplication:\n\nPlease send your CV, recent salary & expected salary in word file to\n[via APPLY NOW]\n\n*** All personal information collected will be kept for employment related purposes only ***\n\n\n\nSummary\nIndustry:\nManufacturing / Industrial\nJob Category / Function:\nIT (IT Auditing)\nIT (Software / Web Developer)\nIT (Network & System)\nIT (Others)\nJob Position Level:\nMiddle\nEmployment Term:\nFull Time / Permanent\nMin. Edu. Level Req:\nBachelor\nMinimum QF Level attained:\n-\nTotal Working Exp:\n5\nSalary(HKD):\n-\nLocation:\nShatin District / Shatin\nBenefits:\nDental Insurance\nDouble Pay\nEducation Allowance\nFive-Day Work\nLife Insurance\nMedical Insurance\nPerformance Bonus\n\n\n\nInterested candidates, please click APPLY NOW \u00a0to apply.", "employment_types": ["Full Time", "Permanent"], "selling_points": ["Experience in Project Mgt or Project Coordination", "Detail-minded and self-motivated", "Attractive remuneration package"], "locations": ["Yau Tsim Mong Area"], "categories": ["Information Technology (IT)", "IT Project Management / Team Lead", "Product Management / Business Analyst", "Testing / QA"], "post_time": "2022-01-10T02:42:17Z", "salary": {"currency": null, "max": null, "min": null, "period": "monthly", "term": null}, "salary_visible": false, "title_keywords": ["project manager"], "responsibilities": ["management", "software", "ad hoc assignment", "review", "quality", "testing", "plans", "report"], "requirements": {"degrees": ["degree", "bachelor"], "majors": ["computer science"], "languages": [], "language_level": [], "hard_skills": ["web server", "plus", "apache", "basic", "agile", "web", "nice", "iis", "html", "word", "problem solving", "hardware", "sdlc", "vs", "project management", "programming", "python", "ms sql"], "soft_skills": ["problem solving skill", "communication skill", "agile", "project management skill"], "languages_combined": []}, "experience_required": {"duration": [], "field": ["ecommerce", "qa"]}}, {"job_id": "100003009034481", "location_code": "hk", "company": "Object Valley (Asia Pacific) Limited", "job_title": "Programmers / Senior Programmers / Analyst Programmers", "description": "Summary\n\nThe successful candidate will participate in a Digital Transformation Project for the largest telecommunications company in Hong Kong \u2013 by transforming the legacy systems through the latest digital solution on agile architecture to support the next generation of CRM & Billing systems.\u00a0 The new CRM & Billing Systems will provide the first class Customer Experience via innovative functions and features.\n\nJob Duties\n\nHe / She will be responsible for performing quality assurance activities with the following scope of duties:\n\nLead and coordinate testing / quality activities to promote delivery excellence\nConduct data collection / analysis and produce various analytical reports relating to dynamic business needs\nProactively manage testing and quality tasks with stamina on risk-based thinking\nAssist in the development of Test Cases and make suggestions on testing scenarios to achieve high quality testing results\nCandidates with less experience will be considered as QA Assistant\n\nThe Person\n\nDegree holder in Business Administration, Computer Science, Information Technology or related disciplines\nMinimum 3 years of experience in IT profession / Quality Assurance\nKnowledgeable of testing tools, concepts and methodologies of QA\nKnowledge/Experience in RPA Robotic Process Automation tool is an advantage, such as Selenium, Uipath, etc.\nKnowledgeable in SDLC, end-to-end testing and agile methodologies\nExperience in developing testing plan\nExperience in ISO standards, risk management is a definite advantage\nExperience in automate a test by multiple RPA tools or programming\u00a0(such as Macro, Shell script, SQL and Java) is required\nPreferred working experience in BSS/OSS systems or software product development\nA self-starter with good analytical and problem solving skills to manage and organise multiple tasks\nGood leadership, analytical, inter-personal and problem solving skills\nPositive attitude, fast-learning, energetic, able to perform in challenging environment\nGood command of spoken and written English is a must", "employment_types": ["Full Time", "Permanent"], "selling_points": ["Opportunities\u00a0to\u00a0develop\u00a0your\u00a0career\u00a0with\u00a0us", "5 days work week", "Fresh graduate will also be considered"], "locations": ["Airport Area"], "categories": ["Information Technology (IT)", "Software Development", "Testing / QA", "Others", "Student / Fresh Graduate / No Experience"], "post_time": "2022-01-10T03:28:56Z", "salary": {"currency": null, "max": null, "min": null, "period": "monthly", "term": null}, "salary_visible": false, "title_keywords": ["analyst"], "responsibilities": ["analysis", "quality", "testing", "coordinate", "reports", "data collection"], "requirements": {"degrees": ["degree holder"], "majors": ["related disciplines", "business administration", "computer science", "information technology"], "languages": ["english"], "language_level": ["good command"], "hard_skills": ["macro", "java", "agile", "rpa", "sql", "sdlc", "programming", "problem solving skills"], "soft_skills": ["agile", "inter-personal", "multiple tasks", "fast-learning", "positive attitude", "analytical and problem solving skills", "problem solving skills", "energetic", "leadership"], "languages_combined": [{"language": "english", "language_level": ["good command"]}]}, "experience_required": {"duration": ["minimum 3 years"], "field": ["risk management", "developing", "testing", "sql", "it", "programming", "product development", "quality assurance"]}}, {"job_id": "100003009033896", "location_code": "hk", "company": "Evangelical Lutheran Church Social Service - Hong Kong", "job_title": "Analyst Programmer  (\u8077\u4f4d\u7de8\u865f\uff1aAP-HO-DD)", "description": "CISD (Asia) Co., Ltd. is a system integrator and is now seeking high caliber\napplicants to join us.\n\nSkills:\n\nThe ideal candidate will possess experience with designing specifications and\ndeveloping functions for SAP and user training. In the near future, our new SAP\nplatform will shift to S/4 HANA hence experience with such platform is highly\nfavorable.\n\n\n\nRequirement\n\nApplicant must be the Hong Kong resident or with Hong Kong work permit\n\u00a0High Diploma/University graduate in accounting or computer related discipline\n\u00a0Solid Knowledge and configuration experience with SAP FICO and FSCM\n\u00a0Understanding of Accounting rules and principles is a must\n\u00a0Knowledge with SAP S4/HANA is preferred\n\u00a0Good command of written and spoken English and Cantonese, speaking of Mandarin and/or Japanese will be an advantage\n\u00a0Good communication skill and Interpersonal skill\n\u00a0Pleasant characters with strong team spirit and good personal attitude\n\u00a0Must be well organized and able to work both independently and in a team\u00a0environment\nWilling to travel\n\nJob Duties\n\n\u00a0Review business processes, interpret system requirements and recommend SAP\nbased solutions.\n\u00a0Develop functional specifications and system design specifications for SAP.\n\u00a0Work with ABAP team where necessary to realize solutions.\n\u00a0Perform system testing and documentation\n\u00a0Conduct system trainings for users on SAP operation (include oversea end-users)\n\u00a0Proactive and result-oriented team player\n\u00a0SAP Support to regional offices\n\nWe offer a 5-day work with an attractive package to the right candidate.\nInterested parties please click \"APPLY NOW\"\u00a0\u00a0or fax: 2865 1218.\n\nVisit us at www.cisd.com.hk for more information.\n\nAll information provided by applicants will be treated in strict confidence and will only be used for recruitment related purposes. All unsuccessful applications will be destroyed within 6 months.", "employment_types": ["Full Time", "Contract"], "selling_points": [], "locations": ["Yau Ma Tei"], "categories": ["Information Technology (IT)", "IT Management", "Application Specialist - Network", "Testing / QA"], "post_time": "2022-01-10T02:04:41Z", "salary": {"currency": null, "max": null, "min": null, "period": "monthly", "term": null}, "salary_visible": false, "title_keywords": ["analyst programmer"], "responsibilities": ["review", "testing", "develop", "specifications", "system design", "documentation"], "requirements": {"degrees": ["high diploma", "university graduate"], "majors": ["computer related", "accounting"], "languages": ["cantonese", "japanese", "english", "mandarin"], "language_level": ["advantage", "good command"], "hard_skills": ["sap"], "soft_skills": ["team spirit", "independently", "communication skill", "well organized", "pleasant", "interpersonal skill"], "languages_combined": [{"language": "cantonese", "language_level": ["advantage", "good command"]}, {"language": "japanese", "language_level": ["advantage", "good command"]}, {"language": "english", "language_level": ["advantage", "good command"]}, {"language": "mandarin", "language_level": ["advantage", "good command"]}]}, "experience_required": {"duration": [], "field": []}}, {"job_id": "100003009039053", "location_code": "hk", "company": "CISD (Asia) Co., Ltd.", "job_title": "SAP Application Specialist", "description": "Our client is a forward thinking tech-savvy financial services company that provides credit and risk related services to individuals and banks. They are looking for junior, mid and senior level Java software developers to help build out an internal system. Database knowledge (SQL, MongoDB, etc.) is required as well. Successful candidates must have excellent communication skills in both Cantonese and English.\n\nClient Details\n\nOur client is a forward thinking tech-savvy financial services company that provides credit and risk related services to individuals and banks.\n\nWith a further expansion of the company and subsequently the usage of internal systems, they are currently looking for several (junior to senior) hands-on Java developers to help build out and enhance their internal systems. Database knowledge (SQL server, MongoDB and etc.) and RESTful API /Linux is required as well. Knowledge in Spring would be a definite advantage.\n\nPrior experience in financial services in an advantage but not mandatory. Computer Science degree candidates are highly preferred but is not a must.\n\nExcellent communication skills in Cantonese and English is required.\n\nDescription\n\nResponsibilities:\n\nsystem architecture design\nimplement, maintain and release internal systems\nresolve and mitigate any system risks and issues\nSIT, unit testing\nadd new modules and system enhancements\ndraft system documentations\n\nProfile\n\nRequirements:\n\nBachelor's degree in Computer Science (most preferred), or any other related technical degrees\n2+ years of hands-on Java development experience\nExperience in databases (SQL server, Mongo and etc.)\nExperience in Linux and RESTful API is highly preferred\nKnowledge in Spring is a definite plus\nGood communication skills (written and spoken) Cantonese and English is a must\nProactiveness, analytic and team working mindset is required\n\nJob Offer\n\n18 days of annual leave\nGroup medical covering spouse and dependants\nNear the MTR station\nTeam working environment\nForward-thinking company\nOpen to using new technologies\nGrowing company\n\nTo apply online please click the 'Apply' button below. For a confidential discussion about this role please contact Jacqueline Lung on +852 3602 2471", "employment_types": ["Permanent"], "selling_points": [], "locations": ["Admiralty"], "categories": ["Information Technology (IT)", "Support", "Testing / QA"], "post_time": "2022-01-11T08:32:45Z", "salary": {"currency": null, "max": null, "min": null, "period": "monthly", "term": null}, "salary_visible": false, "title_keywords": ["application specialist"], "responsibilities": ["design", "testing", "maintain", "architecture", "internal systems"], "requirements": {"degrees": ["degree", "bachelor"], "majors": ["computer science"], "languages": ["cantonese", "english"], "language_level": ["good"], "hard_skills": ["linux", "java", "restful api", "plus", "sql", "databases", "spring", "server"], "soft_skills": ["communication skills", "hands-on", "team working"], "languages_combined": [{"language": "cantonese", "language_level": ["good"]}, {"language": "english", "language_level": ["good"]}]}, "experience_required": {"duration": ["2+ years"], "field": ["sql", "development"]}}]