[{"job_id": "100003009054790", "location_code": "hk", "company": "EY Mtel Solutions Limited", "job_title": "UI / UX Designer", "description": "Our client is a listed company and established a global presence with a variety of businesses around the world.\u00a0 Reporting to Head and Creative Director, candidate will take the ownership and be the go-to person of the website and mobile app.\n\nKey Responsibilities:\u00a0\n\nRedesign the current the website and build a new app from scratch for new business direction and enhanced backend technology\nDeliver CRO, UX, and UI ideas and solutions\u00a0to optimize the results and performance\nDrive A/B tests to improve conversion funnels and user engagement\nEnsure the highest standard and keep improving the design based on new business requirements and changes\n\nKey Requirements:\n\n\nDegree holder in Multimedia Design, Arts, Visual Arts or any related disciplines\nMinimum 3 years\u2019 relevant working experience, preferably gained in\u00a0advertising / creative / branding agency with UX/UI focused experience\u00a0\nProficient in Adobe Creative Suite, Photoshop, Illustrator and InDesign\nHands-on experience in UX design software such as Adobe XD, InVision and UXPin. Knowledge and experience in After Effects and Premiere Pro a bonus\nGood command of both written and spoken English and Chinese\nStrong sense of responsibility, self-motivated, eager to learn and a good team player\nPortfolio is required for application\nCandidate with more experience will be considered as Senior UX/UI Designer\u00a0\n\nInterested parties please send your application with full career history, current & expected salary and portfolio by clicking Apply Now button. Applications will be treated in strict confidence. Personal data collected will be used for recruitment purposes only.", "employment_types": ["Full Time", "Permanent"], "selling_points": ["Diploma/Degree in Design or a related field", "Photoshop, Illustrator, Sketch, Figma", "Knowledge of prototyping, HTML/CSS, JavaScript"], "locations": ["Kwun Tong"], "categories": ["Design", "Graphics", "Web Designer", "Information Technology (IT)", "UI/UX Designer"], "post_time": "2022-01-17T11:05:27Z", "salary": {"currency": null, "max": null, "min": null, "period": "monthly", "term": null}, "salary_visible": false, "title_keywords": ["ux designer"], "responsibilities": ["ui", "ideas", "website", "design"], "requirements": {"degrees": ["degree holder"], "majors": ["multimedia design", "related disciplines"], "languages": ["english", "chinese"], "language_level": ["good command"], "hard_skills": ["adobe xd", "indesign", "illustrator", "after effects", "multimedia", "premiere pro", "adobe creative suite", "photoshop"], "soft_skills": ["self-motivated", "good team player", "focused", "sense of responsibility", "eager to learn", "hands-on", "creative"], "languages_combined": [{"language": "english", "language_level": ["good command"]}, {"language": "chinese", "language_level": ["good command"]}]}, "experience_required": {"duration": ["minimum 3 years"], "field": ["designer", "advertising", "agency", "relevant working experience", "design"]}}, {"job_id": "100003009053082", "location_code": "hk", "company": "BDO Financial Services Limited", "job_title": "UX/UI Designer", "description": "My client is from well-known cryptocurrency platform with global exposure.\u00a0\n\n\nResponsibilities:\n\nCreate compelling mobile app & Website user interface designs\nWork closely with product managers, project manager and engineers to validate, iterate and execute designs on time\nResponsible for all design process, from initial concept discovery, user journey mapping, and usability testing through to the execution of final UI design details\nProduce high quality UX design solutions through wireframes, visual and graphic designs, flow diagrams, storyboards, site maps, and prototypes\n\n\u00a0Requirements:\n\nHigher Diploma or above in Web Design / Multimedia Design / Graphic Design or related discipline.\nAt least 3 years solid experience in UI / UX design work, with experience of a full cycle project\nExperience in digital assets and cryptocurrency industry and basic knowledge in stock market would be an advantage\nKnowledgeable in design and wireframe tools like Adobe Creative Suite, Sketch, InVision or related UX/UI software\nA portfolio of professional UI/UX design work for mobile platforms\nUp to date with current trends and information within UI knowledge\nGood communication, detail orientated and organizational skill\nGood spoken and written English", "employment_types": ["Full Time", "Permanent"], "selling_points": ["Listed Company", "Exp from advertising / creative / branding agency", "Westernize team culture"], "locations": ["Not Specified"], "categories": ["Media & Advertising", "Creative / Design", "Marketing / Public Relations", "Digital Marketing", "Information Technology (IT)", "UI/UX Designer"], "post_time": "2022-01-17T05:41:29Z", "salary": {"currency": null, "max": null, "min": null, "period": "monthly", "term": null}, "salary_visible": false, "title_keywords": ["ui designer"], "responsibilities": ["mobile app", "design solutions", "quality", "website", "design", "testing", "graphic designs", "user interface", "visual", "ui", "storyboards"], "requirements": {"degrees": ["higher diploma or above"], "majors": ["multimedia design", "web design", "graphic design"], "languages": ["english"], "language_level": ["good"], "hard_skills": ["web design", "basic", "mobile", "multimedia", "cryptocurrency", "adobe creative suite"], "soft_skills": ["communication", "creative", "organizational skill", "detail orientated"], "languages_combined": [{"language": "english", "language_level": ["good"]}]}, "experience_required": {"duration": ["at least 3 years"], "field": ["digital", "design"]}}, {"job_id": "100003009053147", "location_code": "hk", "company": "One Arrow Consulting Asia Limited", "job_title": "UI Designer - Cryptocurrency", "description": "Responsibilities:\n\nConducting user research, testing and report\nDeveloping wireframes and user flows based on user needs\nCollaborating with product management and engineering to define and implement innovative solutions for the product direction, visuals and experience\nExecuting all visual design stages from concept to final hand-off to engineering\nConduct user research and evaluate user feedback\n\nRequirements:\n\nTo qualify for the role you must have:\n\n\nProven experience as a UX Designer, UI Designer or similar role\nPortfolio of related design projects is a must\nFamiliarity with interaction design and information architecture\nFamiliarity with design software and technologies (e.g. Photoshop, Illustrator, Sketch, Figma... etc.)\nAbility to work methodically and meet deadlines\nKnowledge of prototyping\nKnowledge of HTML/CSS; JavaScript is a plus\nExcellent communication skills in English and Chinese.\nDegree in Design or a related field\n\nWhat working at EY offers:\n\nSupport, coaching and feedback from some of the most engaging colleagues around\nOpportunities to develop new skills and progress your career\nThe freedom and flexibility to handle your role in a way that\u2019s right for you\n\nIf you can confidently demonstrate that you meet the criteria above, please contact us as soon as possible.\n\nJoin us in building a better working world.\n\nApply now.", "employment_types": ["Full Time", "Permanent"], "selling_points": ["Global Exposure", "Digital Assets", "Attractive Package"], "locations": ["Central & Western Area"], "categories": ["Design", "Others", "Information Technology (IT)", "UI/UX Designer"], "post_time": "2022-01-17T06:07:13Z", "salary": {"currency": null, "max": null, "min": null, "period": "monthly", "term": null}, "salary_visible": false, "title_keywords": ["ui designer"], "responsibilities": ["management", "developing", "design", "testing", "evaluate", "executing", "visual", "report"], "requirements": {"degrees": ["degree"], "majors": ["design"], "languages": ["english", "chinese"], "language_level": ["excellent"], "hard_skills": ["plus", "illustrator", "html", "javascript", "css", "photoshop"], "soft_skills": ["communication skills", "meet deadlines"], "languages_combined": [{"language": "english", "language_level": ["excellent"]}, {"language": "chinese", "language_level": ["excellent"]}]}, "experience_required": {"duration": [], "field": ["designer"]}}, {"job_id": "100003009047350", "location_code": "hk", "company": "YOOV Internet Technology (HK) Limited", "job_title": "UI/UX Designer (5-day work)", "description": "Big Leap Global - Your Trusted Partner in Blockchain APP Development\n\nIf the internet revolutionized the world in the 2000s, social media changed the game in 2010s, then in 2020s, blockchain and internet will be the winning factor for those adopt it to eliminate those do not.\u00a0\n\nWe are a blockchain and game mobile application firm with user-oriented mindsets.\n\nWith our expertise in UI/UX design, blockchain software development and marketing & user penetration, we provide solutions to CEO, CTO or product managers who are looking to outsource their blockchain development. We help companies not just to design and build great social media and blockchain apps but we help them to take it to the world!\n\nIf you see the future of technology like we do, and you are determined to fast track your career by entering one of the most rapidly growing industries in the 2020s, come join us.\u00a0\n\nWe are sure you can design something even nicer than a Shiba Inu on a coin. How about Corgi?\n\n\n\n\n\nHow you can create the next big thing:\n\nYou will be reporting to the senior designer and will be contributing your highly usable and intuitive interface creation for our mobile app and mobile game projects. Your design shall be easy for users to digest and trigger users to share the product with their friends.\u00a0\n\n\n\nDevelop intuitive, usable, and engaging interactions and visual designs for mobile.\nCreate wireframes, page flows, mockup / interactive prototypes across mobile and desktop to communicate interaction and design ideas\nCollaborate with cross-functional teams (executive suite, marketing, engineering, operation) throughout the design process\nParticipate in the full-cycle development process from definition, through design, build, test, release, and maintenance.\nResearch and track advancements in latest mobile application design patterns in the blockchain field and the several key competitors of each project.\u00a0\n\nWhat makes you a game changer:\n\n\n\n2-years or above solid experience in designing UI of mobile applications and mobile web pages.\u00a0\nDiploma or above in Web Design / Graphic / Multimedia design or related discipline\nExperience working with blockchain startup will be an advantage\nExperience in unity\u00a0\nIntermediate to knowledge of relevant technologies and tools (e.g., HTML/CSS,Photoshop, Illustrator)\nAble to work under pressure with tight deadlines with a strong sense of responsibility\nWhat\u2019s next?\n\n\nTo facilitate the recruitment process, remember to insert the followings in your resume,\u00a0\n\n\nLinks to your design portfolio\nYour current salary and expected salary\nYour availability for reporting duties\nThis will help us to choose your profile easier among the numerous applications.\u00a0\n", "employment_types": ["Full Time", "Permanent"], "selling_points": ["User experience and interface design", "Excellent Career Development Opportunity", "Work-Life Balance Fast Growing IT Company"], "locations": ["Kwun Tong"], "categories": ["Design", "Web Designer", "Information Technology (IT)", "Software Development", "UI/UX Designer"], "post_time": "2022-01-14T02:52:55Z", "salary": {"currency": null, "max": null, "min": null, "period": "monthly", "term": null}, "salary_visible": false, "title_keywords": ["ux designer"], "responsibilities": ["collaborate with", "social media", "reporting", "multimedia design", "mobile app", "software", "ideas", "maintenance", "designing", "provide solutions", "design", "develop", "visual", "recruitment process", "ui", "cross-functional teams", "work under pressure"], "requirements": {"degrees": ["diploma or above"], "majors": ["multimedia design", "web design"], "languages": [], "language_level": [], "hard_skills": ["blockchain", "web design", "maintenance", "illustrator", "web pages", "html", "mobile", "factor", "multimedia", "css", "unity", "photoshop"], "soft_skills": ["sense of responsibility", "determined", "work under pressure"], "languages_combined": []}, "experience_required": {"duration": [], "field": []}}, {"job_id": "100003009051461", "location_code": "hk", "company": "ADECCO", "job_title": "UI/UX Designer - 45-50k - Urgent Immediate Available - Global Media Powerhouse - Western Culture.", "description": "To cope with our business growth, we are currently looking for a high calibre candidate to join us as an UI/UX Designer, mainly focus on the product design of our cloud-based low code system.\n\n\n\nResponsibilities\n\n\nIllustrate and present design ideas using storyboards, flow maps, and wireframes\nDesign delightful interactions and intuitive user interface that help our users accomplish their tasks efficiently and effectively\nCreate high-quality user interface designs for different devices that elevate the user experience and achieve business requirements\nBuild high fidelity prototypes for review and usability testing\nHelp the team develop and maintain the design system\nAssist the product team prepare and conduct usability testing and user research\n\nRequirements\n\nDegree or diploma holder in Interaction Design, Communication Design, HCI, or related disciplines\n1-2 years experience working as a UI/UX Designer or related fields\nProficient with design tools such as Figma and Sketch\nExcellent communication, presentation, and interpersonal skills\nFundamental understanding of web design standards and best practices\nExperience in HTML/CSS, app development, and B2B products is an advantage\nMust submit a soft copy or a link of your portfolio (Candidates with no portfolio will not be considered)\nInterested candidates please send your job application to our HR Department by \u201cAPPLY NOW\u201d. Please indicate the details of your working experience, current and expected salary, and your date of availability in your CV.\n\n(Only shortlisted candidates will be contacted)\n\nPersonal Information Collection Statement (PICS)\n\nThe personal data collected will be used by our member(s) of the recruitment team for recruitment purpose only. It is our policy to retain the personal data of unsuccessful applicants for future recruitment purposes for a period of 3 months. When there are vacancies in our subsidiary or associate companies during that period, we may transfer the candidate\u2019s application to them for consideration of employment. And, all information will be kept confidential during that period and be destroyed after use.\n", "employment_types": ["Full Time"], "selling_points": ["Lead all Web UI/UX design initiatives.", "Designing mobile-based features.", "Optimizing web pages for maximum speed and scalabi"], "locations": ["Central & Western Area"], "categories": ["Information Technology (IT)", "IT - Webmaster / SEO", "Technical Writing", "UI/UX Designer"], "post_time": "2022-01-16T03:00:57Z", "salary": {"currency": null, "max": null, "min": null, "period": "monthly", "term": null}, "salary_visible": false, "title_keywords": ["ux designer"], "responsibilities": ["ideas", "review", "quality", "user experience", "design", "testing", "develop", "user interface", "maintain", "storyboards"], "requirements": {"degrees": ["diploma holder", "degree"], "majors": ["related disciplines", "design"], "languages": [], "language_level": [], "hard_skills": ["css", "web design", "no", "html"], "soft_skills": ["communication", "interpersonal skills", "presentation"], "languages_combined": []}, "experience_required": {"duration": ["1-2 years"], "field": ["related", "development", "designer"]}}, {"job_id": "100003009053039", "location_code": "hk", "company": "Tech Nine Limited", "job_title": "Graphic Designer (Mobile App/Web) (5 days work)", "description": "Got tired of your boring work?\n\nWe have cool people. We deliver cool design. We are not a machine to work under long hours everyday with strict rules. We are not someone\u2019s pair of hands. We work in a creative, fun and flexible environment with no pressure.\n\nIf you think you are cool enough and ready to overcome challenges with supportive teammates to break your boundaries. Join us now!\n\nCheck out our new promotional video to find out who we are & why Digi is with Salad!\n\nResponsibilities:\n\nUtilize industry design standards and best practices to define and implement design criteria by a variety of methods to convey ideas and concepts (e.g. personas, user flow diagrams, wireframes, design prototypes, etc)\nDesign and specify UX and UI design for Responsive Web and Mobile application (iOS & Android)\nDeliver inventive, durable and thoughtful, solutions from concept to launch\nApply conceptual thinking to create desirable and feasible digital solutions across multiple platforms\nWork closely with a blended cross-functional team and tackle all aspects of the design process\nMaintain knowledge of design trends and assist with implementation of design innovations\u00a0\nLess Experience will be considered as Senior UX & UI Designer or UX & UI Designer\n\nRequirements:\n\nDegree or Diploma holder in visual design, interactive design, creative media or relevant discipline\nMinimum 3 years of experience in App and Responsive Web design\nStrong portfolio demonstrating proven UX workflow and strong design techniques\nProven ability in a variety of design tools such as Figma, Sketch, Invision, Photoshop, Illustrator and a bonus if you have experience with Adobe After Effects/ Flinto/ Principle\nBasic Knowledge in HTML production, HTML5, CSS3, JavaScript\nEffectively communicate research findings, conceptual ideas, detailed design, and design rationale both verbally and visually\nWilling to learn new trends and technology\nPositive attitude and motivation to deliver highest quality work\nDigital Agency Background is preferable but not a must\u00a0\n\nBenefit We Offer:\n\n5 days\u2019 work\nPerformance Bonus\nMedical Coverage\nFlexible Working Hours\nBirthday, Wedding, Maternity and Paternity leaves\nFun, young and joyful environment\u00a0\n\nWe're looking for talented individuals that want to do great work in a fun, creative, young and smart place. Attractive long term career prospect, along with competitive remuneration package and fringe benefits will be offered to the right candidate.\n\nJoin Us and Be a Cool People Now!\n\nInterested parties please click \"Apply Now\" to send a cover letter stating your expected salary, resume and a full set of your portfolio to us.\n\n*All information will be treated as confidential and used solely for recruitment purposes.\n", "employment_types": ["Full Time", "Permanent"], "selling_points": ["Looking for passionate and talented designer", "Website, Mobile Application, Marketing Collateral", "Friendly and energetic working environment"], "locations": ["Lai Chi Kok"], "categories": ["Design", "Graphics", "Multi-media", "Information Technology (IT)", "UI/UX Designer"], "post_time": "2022-01-17T16:20:58Z", "salary": {"currency": null, "max": null, "min": null, "period": "monthly", "term": null}, "salary_visible": false, "title_keywords": ["graphic designer"], "responsibilities": ["ideas", "implementation", "design", "maintain", "design trends", "ui"], "requirements": {"degrees": ["diploma holder", "degree"], "majors": ["creative media", "design"], "languages": [], "language_level": [], "hard_skills": ["web design", "basic", "illustrator", "html", "adobe after effects", "visual design", "javascript", "photoshop"], "soft_skills": ["willing to learn", "positive attitude", "creative", "responsive", "detailed"], "languages_combined": []}, "experience_required": {"duration": ["minimum 3 years"], "field": ["design"]}}, {"job_id": "100003009051331", "location_code": "hk", "company": "Big Leap Global Limited", "job_title": "APP UI/UX Designer", "description": "Snapshot\n\nMy client is under global expansion and looking for a Senior UXUI designer to join the team.\u00a0\nSuccessful candidate will be working with the ecommerce team to build up a next generation web/mobile applications.\u00a0\n\nCompany Profile\n\nA fast growing and reputable global tech accessories brand based in US.\u00a0\n\nExciting new role for you\n\n\nPrepare UX/UI design and materials including wire framing, mockup and rapid prototyping for various interfaces, including websites, mobile devices and apps for ecommerce site\nAnalyze current user journey to understand motivation, expose pain points, issues and improvement opportunities\nConduct user research, A/B testing, and propose solutions to optimize customer experience\nCommunicate concepts and work collaboratively with project team / Tech team in order to develop the most efficient design schemas\nSit with developers to do pixel-perfect reviews of frontend products before they are pushed in production.\nRequirements:\n\n\nBachelor Degree in Creative Media / Interactive Design / Web Design / Web Development;\n5+ years of experience building transactional website\nSpecific experience in a fast growing ecommerce company\nAbility to solve problems of complexity through smart design\nBeing data-driven, and be able to back up your assertions with data, with proficiency in analytic tools - Hotjar, Google Analytics, Optimizely etc\nStrong understanding of web grids and browser limitations\nFamiliarity with usability testing, A/B testing methods\nProficiency with Photoshop, Adobe XD, Webflow, HTML, CSS, PHP\nExperience with Shopify site designs / SDK is highly preferred\nRewards\n\n\nYou will be working at a high-performing energetic team with great career progression. Attractive remuneration and package. Opportunity to join a leading company with a fast-growing business.\n\n\u00a0Action Now\n\nPlease send your CV via \"APPLY NOW\" to have a confidential discussion about this role and other exciting opportunities with you.", "employment_types": ["Full Time", "Permanent"], "selling_points": ["Acquire valuable blockchain exposure", "Global projects", "Work closely within small teams"], "locations": ["Central & Western Area"], "categories": ["Design", "Multi-media", "Web Designer", "Information Technology (IT)", "UI/UX Designer"], "post_time": "2022-01-15T09:22:20Z", "salary": {"currency": null, "max": null, "min": null, "period": "monthly", "term": null}, "salary_visible": false, "title_keywords": ["ux designer"], "responsibilities": ["data", "website", "design", "develop", "testing", "mobile devices", "ui"], "requirements": {"degrees": ["degree", "bachelor"], "majors": ["creative media", "web design", "design"], "languages": [], "language_level": [], "hard_skills": ["web design", "web development", "google analytics", "web", "php", "adobe xd", "shopify", "html", "mobile", "rapid", "css", "photoshop"], "soft_skills": ["efficient", "creative", "solve problems", "energetic", "driven"], "languages_combined": []}, "experience_required": {"duration": ["5+ years"], "field": ["ecommerce", "research", "testing"]}}, {"job_id": "100003009052930", "location_code": "hk", "company": "DigiSalad Solutions Limited", "job_title": "UX Lead / (Senior) UX & UI Designer", "description": "My Client is Asia Pacific\u2019s largest broadcast and media systems integrator. This role is within the special division of the firm that focuses on providing cloud integration and proprietary software solutions for media industry-based clientele as well as Audio-Visual Clients.\n\nJob Overview\u00a0\n\nThe UI/UX Designer is responsible for all the visual elements that users see and interact within company-wide suite of web applications. They will work with the product owners and software engineers in making improvements on current websites, as well as creating new ones from the ground up through developing prototypes and generating the code. They will be the core in creation of well-designed, user-centred, interfaces.\n\nResponsibilities and Duties\n\nLead all Web UI/UX design initiatives.\nWork with stakeholders in developing new user-facing features.\nBuilding high-quality mock-ups and design different wireframes and prototypes.\nStriking a balance between functional and aesthetic design.\nOptimizing web pages for maximum speed and scalability.\nWhere necessary be able to perform SEO.\nDesigning *GREENFIELD* mobile-based features.\nMaintaining brand consistency throughout design.\n\nSkills and Qualifications\u00a0Required:\n\nEither a related university degree or rich UI/UX design experience.\nExperience with the UI/UX workflow, from initial communication to final signoff is necessary.\nFamiliarity with tools such as Sketch, Adobe XD and Figma.\nKnowledge of usability principles across different platforms is important.\nStrong communication skills in English.\nExperience of working with cloud technology, such as AWS, particularly content delivery such as CloudFront and Route 53, is beneficial.\nWorking knowledge of HTML5, CSS3 and ES6 is especially useful.\nExpertise in JavaScript frameworks such as React and Material-UI is advantageous.\nExperience in working with source control, such has GitLab or GitHub.\nUnderstanding of Agile methods and developments tools such as Jira is valuable.\nStrong positive working attitude, quick-learner and able to work independently.\n\nPlease click the apply button or send through your updated CV direct to it.pl.hk (AT ) adecco.com.\u00a0 For more information feel free to call +852 28996179 and ask for Philip for a confidential discussions.", "employment_types": ["Full Time", "Permanent"], "selling_points": ["UX-Driven Digital Agency", "Fun and Young Working Environment", "Birthday Leave and Medical Coverage"], "locations": ["Tsuen Wan Area"], "categories": ["Design", "Multi-media", "Web Designer", "Information Technology (IT)", "UI/UX Designer"], "post_time": "2022-01-17T04:34:39Z", "salary": {"currency": null, "max": null, "min": null, "period": "monthly", "term": null}, "salary_visible": false, "title_keywords": ["ui designer", "lead"], "responsibilities": ["control", "seo", "software", "systems", "quality", "developing", "design", "mock-ups", "designing", "communication", "maintaining brand consistency", "visual", "audio", "ui"], "requirements": {"degrees": ["university degree"], "majors": ["design"], "languages": ["english"], "language_level": [], "hard_skills": ["web applications", "seo", "web", "react", "adobe xd", "agile", "web pages", "aws", "mobile", "javascript", "integration", "code", "pl"], "soft_skills": ["communication skills", "work independently", "agile", "responsible", "communication", "positive working attitude"], "languages_combined": [{"language": "english", "language_level": []}]}, "experience_required": {"duration": [], "field": ["related", "design"]}}, {"job_id": "100003009054498", "location_code": "hk", "company": "PERSOLKELLY Hong Kong Limited", "job_title": "Senior UXUI designer (Up to 37K x 13 Months)", "description": "Responsibilities\n\nDevelopment of iOS/ Android mobile application\nTechnical system design, development and UAT\nRequirement analysis and documentation\nCoordinate with offshore team on system development and implementation\nWork closely with internal & external parties to collect and analyze their requirements\n\nRequirements\n\nHigher Diploma or above in Technology, Computer Science, Engineering or related disciplines\nSolid experience in mobile software development on iOS or Android platform\nExperience in Kotlin, Java - Android / Swift - iOS platform / Flutter, React Native - Hybrid\nFresh graduates with programming background and strong motivation to learn will be considered\nExperienced candidates will be considered for a senior position\nFamiliar with Agile development methodology is a definite advantage\n\nWhat we can provide\n\nDouble Pay\nDiscretionary Performance Bonus\nLife Insurance\nMedical insurance\nFree Snacks and Drinks", "employment_types": ["Full Time", "Permanent"], "selling_points": ["Exp in large ecommerce & retail company", "MNC culture & global exposure", "Photoshop, Adobe XD, Webflow, HTML, CSS, PHP"], "locations": ["Others"], "categories": ["Information Technology (IT)", "UI/UX Designer"], "post_time": "2022-01-17T09:47:41Z", "salary": {"currency": null, "max": null, "min": null, "period": "monthly", "term": null}, "salary_visible": false, "title_keywords": ["designer"], "responsibilities": ["system design", "uat"], "requirements": {"degrees": ["higher diploma or above"], "majors": ["related disciplines", "engineering", "computer science"], "languages": [], "language_level": [], "hard_skills": ["java", "agile", "analysis", "swift", "mobile", "react native", "programming", "documentation", "kotlin", "android"], "soft_skills": ["agile"], "languages_combined": []}, "experience_required": {"duration": [], "field": ["software development"]}}, {"job_id": "100003009055716", "location_code": "hk", "company": "AXA Hong Kong", "job_title": "User Experience Researcher", "description": "You should keep watching...\n\nIf you are interested in the website and mobile app graphic design, enjoying a flexible culture and would like to join an energetic team, which is led and supervised by IT experts and to work with Millennial professionals, this is exactly what you are looking for!\nYou'll responsible for...\n\nHandle design project, including mobile and web application graphics, icons and\u00a0 UI elements\nWork independently to develop and produce artwork for mobile application, desktop application & website\nBrainstorm innovative ideas and prepare proposal/presentation materials\nWork with design managers to ensure timely completion and quality of design elements\nClosely communicate with the project team and product team to ensure final graphics and layouts aligns with project requirements\nSupport projects' task assigned by Manager & Director\nRight fit if you are...\n\nDiploma or above in Graphic Design or related disciplines\n3 year or above working experience in Graphic Design\nProficiency in using Photoshop & Illustrator, Figma and Sketch\nExperience in Website/ Mobile App graphic design is a plus\nWith strong creative and design sense\nAble to work independently, willing to meet new challenges under a tight schedule\nImmediately available is highly preferred\nWe offer...\n\nProject Bonus\n5-days Work + Bank Holiday\nEducation Allowance, Medical Allowance\nSnacks and drinks\nLess than 5 mins walk from Lai Chi Kok MTR Station\nGood Career Prospect in the growing IT Industry\n\nApply now! Do not miss this opportunity to join us!\n\nInterested parties, please apply with full resume, portfolio that will demonstrate our required fields as mentioned above, current and expected salary.\n\nRemarks: Data collected would be used for recruitment purposes only. Applicants who do not hear from us within 8 weeks may consider their application unsuccessful and their data will be destroyed within 24 months of receipt.", "employment_types": ["Full Time", "Permanent"], "selling_points": ["user research", "UX workshop", "customer interview"], "locations": ["Not Specified"], "categories": ["Design", "Multi-media", "Web Designer", "Information Technology (IT)", "UI/UX Designer"], "post_time": "2022-01-18T02:52:52Z", "salary": {"currency": null, "max": null, "min": null, "period": "monthly", "term": null}, "salary_visible": false, "title_keywords": ["researcher"], "responsibilities": ["graphics", "communicate with", "project requirements", "support projects", "mobile app", "ideas", "graphic design", "quality", "website", "design", "develop", "schedule", "ui"], "requirements": {"degrees": ["diploma or above"], "majors": ["related disciplines", "graphic design"], "languages": [], "language_level": [], "hard_skills": ["graphics", "plus", "web", "illustrator", "mobile", "photoshop"], "soft_skills": ["flexible", "work independently", "creative", "responsible", "timely", "interested in", "innovative", "energetic", "presentation"], "languages_combined": []}, "experience_required": {"duration": ["3 year"], "field": ["graphic design"]}}, {"job_id": "100003009043951", "location_code": "hk", "company": "IT Channel (Asia) Limited", "job_title": "UI/UX Designer", "description": "As our User Researcher of our Design Hub team in Hong Kong, your primary mission will be to understand the needs and product requirements and transform that understanding into user-focused and intuitive products and services.\n\nYou will:\n\nmanage and run all forms of requirement gathering, user research, UX workshop, customer interview, usability testing, focus group etc.\nfacilitate the product vision by researching, sketching, prototyping and user-testing experiences for digital products\ndesign experiences through human-centred-design\nensure that research findings and insights are translated into actionable product goals and direction and sharing insights with stakeholders\ncreate wireframes (from sketches to high-fidelity ones)\ntranslate concepts into user flows & wireframes\ncreate rapid prototypes to validate design concepts with stakeholders and customers\nrun workshops and other group activities\nContributing to on-going enhancement of customer experience and user experience methodologies\nstay abreast of UX and technology trends and look for inspiration\n\nRequirements:\n\nMinimum of 5 years relevant experience as a User Researcher, interaction designer or similar roles\nnative Cantonese speaker with strong local cultural understanding. Fluent and comfortable in English\nexperienced in user research, prototyping and user testing methodologies\nunderstand Agile / iterative project management methodologies\nable to handle a Mac and the usual tools (Adobe, Sketch)\nbe a self-motivated and resilient team player driving collaboration\nwith strong sense of personal accountability", "employment_types": ["Full Time", "Contract"], "selling_points": ["UX/UI", "Travelling Benefit", "Web/Mobile Apps Design"], "locations": ["Airport Area"], "categories": ["Information Technology (IT)", "Application Specialist - Software", "Others", "UI/UX Designer"], "post_time": "2022-01-13T02:34:44Z", "salary": {"currency": null, "max": null, "min": null, "period": "monthly", "term": null}, "salary_visible": false, "title_keywords": ["ux designer"], "responsibilities": ["design concepts", "workshop", "user experience", "sketches", "design", "testing", "project management"], "requirements": {"degrees": [], "majors": [], "languages": ["cantonese", "english"], "language_level": ["native", "fluent"], "hard_skills": ["agile", "project management", "adobe", "rapid", "workshops", "focus"], "soft_skills": ["self-motivated", "agile", "focused", "accountability", "project management", "team player", "focus"], "languages_combined": [{"language": "cantonese", "language_level": ["native"]}, {"language": "english", "language_level": ["fluent"]}]}, "experience_required": {"duration": ["minimum of 5 years"], "field": ["designer", "design", "testing", "relevant experience", "digital"]}}, {"job_id": "100003009049406", "location_code": "hk", "company": "Midland Holdings Limited", "job_title": "Web Designer", "description": "We are looking for the suitable candidate to join our client's project!\n\nJob Description:\n\nDevelop UX/UI Design Prototype:\n\nDevelop prototype as a standard for those digital channels to follow. The prototype will be illustrated by (include but not limited to) application flows, features, wireframes and clickable prototypes.\nTo make sure the prototype is practical and workable; the components below must be included in the project.\n\nDevelop UX/UI Design Standard and Guideline:\n\nWork with the team members to review and update the personas of users of various digital channels.\nReview the latest version of the existing App, analyze its usage data and identify user pain points to complete analysis of existing UX/UI.\nPerform end user study including surveys, interviews and/or focus groups to validate the persona and UX/UI analysis results.\nPerform stakeholder analysis with representatives from various departments to establish stakeholder requirements on the App, including but limited to on-site workshops and meetings.\nBased on the above analysis, develop the standard and guideline of UX/UI design which includes style, font, color and reference layout templates for the Authority and its assigned contractors to develop the App or other interfaces.\nDesign pitching with management team.\nOversee multiple web and mobile application features, interfaces, and experiences\n\nQualifications:\n\nBachelor\u2019s degree in interaction design, user-centered design, or a design-related field\n2 to 5 years experiences in related field\nFamiliar with UX/UI design tools such as Sketch, Adobe Illustrator, Adobe Dreamweaver, Adobe Photoshop, Adobe XD, InVision, etc.\nStrong communication, presentation, and interpersonal skills and ability to analytically defend design decisions\nA self-motivated team player who excels in a collaborative environment\nProject management in managing UI/UX to coding execution is a plus\nFluent in Cantonese and English both written and verbally\n\nInterested parties, please click \"Apply Now\" to send us your resume\n\n", "employment_types": ["Temporary", "Contract"], "selling_points": ["5 days work with discretionary bonus", "Web UI/UX and Banner Design", "Familiar in HTML5, JAVASCRIPT, CSS, bootstrap"], "locations": ["Admiralty"], "categories": ["Design", "Web Designer", "Information Technology (IT)", "Others", "UI/UX Designer"], "post_time": "2022-01-15T19:11:38Z", "salary": {"currency": null, "max": null, "min": null, "period": "monthly", "term": null}, "salary_visible": false, "title_keywords": ["designer"], "responsibilities": ["management team", "data", "analysis", "review", "design", "develop", "communication", "project management", "coding", "ui"], "requirements": {"degrees": ["degree", "bachelor"], "majors": ["design"], "languages": ["cantonese", "english"], "language_level": ["fluent"], "hard_skills": ["plus", "web", "adobe xd", "analysis", "adobe photoshop", "adobe illustrator", "make", "mobile", "adobe", "dreamweaver", "project management", "workshops", "focus"], "soft_skills": ["self-motivated", "collaborative", "communication", "project management", "team player", "interpersonal skills", "focus", "presentation"], "languages_combined": [{"language": "cantonese", "language_level": ["fluent"]}, {"language": "english", "language_level": ["fluent"]}]}, "experience_required": {"duration": ["2 to 5 years"], "field": ["related"]}}, {"job_id": "100003009042072", "location_code": "hk", "company": "Osmium Consulting Group Limited", "job_title": "UI / UX Designer | 38k-48k", "description": "Responsibilities:\n\nWeb UI/UX and Banner Design\n\nOnline campaigns development and maintenance\nWork closely with Web Developer/ Programmer on web development\n\nRequirements:\n\nDegree or Diploma in Web Design, Creative/ Interactive Media or related disciplines\n\nFamiliar in HTML5, JAVASCRIPT, CSS, bootstrap\nAdobe Creative Cloud, MS Powerpoint, Apple Keynote\n1-3 years of experience in web design\n\nCompetitive Salary will be offered to the right candidate. \u00a0For application, please update your resume by clicking \"APPLY NOW\" or complete the online application form which is available at\u00a0https://www.midland.com.hk/joinus/\u00a0and sent to the corresponding email address together with your full resume, present & expected salary.\u00a0\n\nAll personal data collected will be used for recruitment purpose only. Applicants not hearing from us within 2 months may consider their applications unsuccessful. \u00a0All personal data supplied will be kept for a reasonable period in accordance with the legal requirements.\n\nAs an Equal Opportunities Employer, we are committed to eliminating discrimination in employment. Our vacancy is open to all applicants meeting the basic entry requirement irrespective of their disability, sex, marital status, pregnancy, age, family status, sexual orientation and race.", "employment_types": ["Full Time"], "selling_points": ["UX UI Designer | In House | Rare Opportunity", "5 Days Work | Bouns | Med", "Work From Home"], "locations": ["Not Specified"], "categories": ["Media & Advertising", "Creative / Design", "Design", "Web Designer", "Information Technology (IT)", "UI/UX Designer"], "post_time": "2022-01-12T05:54:06Z", "salary": {"currency": null, "max": null, "min": null, "period": "monthly", "term": null}, "salary_visible": false, "title_keywords": ["ux designer"], "responsibilities": ["maintenance", "ui", "design"], "requirements": {"degrees": ["diploma", "degree"], "majors": ["related disciplines", "web design"], "languages": [], "language_level": [], "hard_skills": ["web design", "basic", "javascript", "adobe", "css", "ms powerpoint"], "soft_skills": ["committed", "creative"], "languages_combined": []}, "experience_required": {"duration": ["1-3 years"], "field": ["design"]}}, {"job_id": "100003009053342", "location_code": "hk", "company": "Endeavour Search Limited", "job_title": "Full Stack Developer \u2013 Corporate Communication Projects / Interactive app/web design / MNC", "description": "\u00a0Responsibilities :\nDesign product flows and journeys that optimize user experience based on the acquired insights as well as business and technical requirements.\u00a0\nFollow through product from concept development, artwork design\u00a0and production\nExecute creative solutions to meet the client needs\nDevelop pixel-perfect UI components that are ready for production and ensure design consistency across different app and web platforms.\nDevelop pixel-perfect UI components that are ready for production and ensure design consistency across different app and web platforms.\nCreate compelling user interface designs for Mobile apps and\nwebsites\n\n\u00a0Requirements :\n\nDiploma or above in Graphic / Multimedia Design or related\u00a0disciplines\n3+ years of UX and UI design experience and have experience designing for large customer-facing platforms.\nUnderstanding of UI/UX design methodologies on mobile and desktop platform\nStrong skilled in Figma, Adobe, Sketch, etc.\n\nStrong self-motivation to start and run the work individually and with the teams.\n\nGood understanding of interaction, journeys and prototyping is an advantage\nSelf-motivated, willing to learn, and a strong sense of responsibility and commitment\nExperienced in the Website interface will be an advantag\nMore experience shall be considered as a Senior\u00a0UI / UX Designer", "employment_types": ["Full Time", "Permanent"], "selling_points": ["In-House Perm Role; MNC", "Interactive web/app design for the group image", "Long term career development & training provided"], "locations": ["Kwai Tsing Area"], "categories": ["Design", "Web Designer", "Information Technology (IT)", "Software Development", "UI/UX Designer"], "post_time": "2022-01-17T06:48:41Z", "salary": {"currency": null, "max": null, "min": null, "period": "monthly", "term": null}, "salary_visible": false, "title_keywords": ["developer"], "responsibilities": ["user experience", "design", "develop", "user interface", "ui"], "requirements": {"degrees": ["diploma or above"], "majors": ["multimedia design", "related disciplines"], "languages": [], "language_level": [], "hard_skills": ["mobile", "adobe", "multimedia"], "soft_skills": ["self-motivated", "self-motivation", "willing to learn", "sense of responsibility"], "languages_combined": []}, "experience_required": {"duration": ["3+ years"], "field": ["designer", "design"]}}, {"job_id": "100003009045500", "location_code": "hk", "company": "Ambition", "job_title": "UIUX designer, Insurance, 30k", "description": "Our client is a Financial Services Firm who are hiring a\u00a0Lead UI/UX Product Designer (Manager) to continually drive the companies Platform Product Expansion and to manage a team of 4 UI/UX Designers. The ideal candidate will be from a solid UI/UX Product Design background and have several years of Manager / Team Leadership experience. This role will still require hands on work.\u00a0\n\nRole & Responsibilities:\n\nMust have a updated Portfolio / Showcase of previous projects.\u00a0\nMinimum 5+ years of\u00a0UI/UX Design Product experience.\u00a0\nMust be leading a current Product Design Team / have previous Team Lead experience.\u00a0\nTechnology Stack:\u00a0Figma, Invision, Adobe Creative, Visio, Web, iOS.\nAbility to work with multiple stakeholders including Clients, Product Team and Developers.\nRole involves Produce Personas, Wireframes, Flow Diagrams and Low High Fidelity Mockups.\nSmart / Startup / Adaptable / Self Research Mindset.\nFluent English Speaking Required.\nIf you would like to find out more, please submit your CV or call us on 3619 2365.", "employment_types": ["Full Time", "Contract"], "selling_points": ["international team", "great career prospects", "digital projects"], "locations": ["Not Specified"], "categories": ["Information Technology (IT)", "UI/UX Designer"], "post_time": "2022-01-13T07:57:51Z", "salary": {"currency": null, "max": null, "min": null, "period": "monthly", "term": null}, "salary_visible": false, "title_keywords": ["designer"], "responsibilities": ["product design", "ui", "design"], "requirements": {"degrees": [], "majors": [], "languages": ["english"], "language_level": ["fluent"], "hard_skills": ["adobe", "web"], "soft_skills": ["adaptable", "hands on", "creative", "leadership", "ideal"], "languages_combined": [{"language": "english", "language_level": ["fluent"]}]}, "experience_required": {"duration": ["minimum 5+ years"], "field": ["product design", "design", "team"]}}, {"job_id": "100003009043245", "location_code": "hk", "company": "Labs Property Limited", "job_title": "UX/UI Designer (Blockchain)", "description": "The Senior UI / Frontend Software Engineer will provide efficient UX to clients' digital platforms.\n\nResponsibilities\n\nDesign and implement products and platforms to provide highly efficient user experiences for all functionalities\nPassionate about using the latest frontend technologies to tackle complex business problems\nCollaborate with product design, product manager and other software engineer to deliver high quality code\nDevelop the mobile App and Web browser site\nParticipate in extensive and candid code review peers\nMentor junior developers\n\nRequirements\n\nSc or high degree in computer science and related fields.\nMore than 3 years of front-end experience.\nStrong JavaScript/HTML/CSS frontend engineering experience.\nDeep understanding of underlying design philosophy and implementation of common web frameworks, including React/Vue.\nExperience with Babel, Webpack, Rollup, or other JavaScript building tools\nExperience in building large-scale web applications and optimizing front-end performance in fast-moving team environment.\n\nApplication\n\nDon't miss out on this exciting opportunity to work in a fast-growing fintech companys! To apply, click 'Apply Now' to submit your resume to us.\n\nAny questions, please feel free to contact Yvonne Hung at +852 3907 3977 or email your inquiry to yhung@morganmckinley.com.", "employment_types": ["Full Time", "Permanent"], "selling_points": ["Crypto knowledge is an advantage", "Creative and strong design sense", "At least 2 years experience"], "locations": ["Tsim Sha Tsui"], "categories": ["Information Technology (IT)", "UI/UX Designer"], "post_time": "2022-01-12T10:21:00Z", "salary": {"currency": null, "max": null, "min": null, "period": "monthly", "term": null}, "salary_visible": false, "title_keywords": ["ui designer"], "responsibilities": ["collaborate with", "mobile app", "software", "review", "quality", "design", "develop", "product design"], "requirements": {"degrees": ["degree"], "majors": ["computer science"], "languages": [], "language_level": [], "hard_skills": ["web applications", "web", "react", "html", "javascript", "css"], "soft_skills": ["deep"], "languages_combined": []}, "experience_required": {"duration": ["3 years"], "field": ["web applications", "engineering", "team"]}}, {"job_id": "100003009047625", "location_code": "hk", "company": "Welab Bank Limited", "job_title": "UI/UX Designer (Virtual Bank)", "description": "Job Highlights\n\nWebsite and mobile app user interface designs\nGraphic and digital design for banner\nWork with project and development team\n\nJob Responsibilities\n\nWebsite and mobile app user interface designs;\nProduce all kind of graphic and digital design for banner and other presentation materials;\nWork with project and development team; and\nManage any ad-hoc tasks or projects as assigned.\n\nJob Requirements:\n\nHigher Diploma or above in digital design, multimedia design, graphic communications or related field;\nMinimum 1 years' of working experience in design related field\nHands on skills in Adobe Photoshop, Illustrator, Sketch;\nKnowledge of UI design principles and techniques;\nDetail minded with can-do attitude and ability to multitask;\nProvide online portfolio link in addition to resume. *Immediate availability is preferred\n\nWorking location & hours\n\n5-days work\nWork in Kwun Tong", "employment_types": ["Full Time", "Permanent"], "selling_points": ["Take ownership of the entire user experience", "Develop and prototype design solutions", "Work with the team in strategic development"], "locations": ["Quarry Bay"], "categories": ["Banking / Finance", "Financial Services", "Design", "Others", "Information Technology (IT)", "UI/UX Designer"], "post_time": "2022-01-14T03:36:28Z", "salary": {"currency": null, "max": null, "min": null, "period": "monthly", "term": null}, "salary_visible": false, "title_keywords": ["ux designer"], "responsibilities": ["mobile app", "ad-hoc tasks", "website", "design", "user interface"], "requirements": {"degrees": ["higher diploma or above"], "majors": ["multimedia design", "communications", "design"], "languages": [], "language_level": [], "hard_skills": ["illustrator", "adobe photoshop", "multimedia"], "soft_skills": ["ability to multitask", "hands on", "can-do attitude"], "languages_combined": []}, "experience_required": {"duration": ["minimum 1 years"], "field": ["related", "design"]}}, {"job_id": "100003009042882", "location_code": "hk", "company": "XDynamics Limited", "job_title": "UX/UI  Designer", "description": "Job duties\n\nWorking closely with business stakeholders, product owners and business analysts to translate user stories/business requirements into digital experiences.\nChampion human-centered design practices when solving design requests and challenges\nDriving user research activities such as stakeholder interview, survey, A/B testing, usability testing, learning about user behavior and translating research findings into possible solutions.\nBeing responsible for providing high-quality deliverables such as user journeys, user flows, wireframes, UI mock-ups and prototypes.\nDeveloping pixel-perfect UI and ensuring design consistency between digital products.\n\nRequirements\n\n3+ years of experience as a user experience designer, professional experience in advertising, design, interaction designer, Web/graphic design or similar roles.\nDiploma graduate or above in graphic design or related disciplines such as Industrial Design, Communication Arts, Information Design, human-computer interaction (HCI).\nA portfolio demonstrating a clean visual aesthetic and a strong eye for detail.\nGood command in English and interpersonal skills. Cantonese and/or Mandarin-speaking skill is a plus.\n\nIf this job isn't quite right for you, but you know someone who would be great at this role, why not take advantage of our referral scheme? We offer HKD1000 in Apple gift cards for every referred candidate who we place in a role. Terms & Conditions Apply. https://www.ambition.com.hk/refer-a-friend", "employment_types": ["Full Time"], "selling_points": ["UX, Drones, High Tech, Designer", "Adobe XD, Wireframe, HTML/CSS", "Indesign, Interface wireframes, Android, IOS"], "locations": ["Shatin Area"], "categories": ["Design", "Graphics", "Information Technology (IT)", "UI/UX Designer"], "post_time": "2022-01-12T09:07:09Z", "salary": {"currency": null, "max": null, "min": null, "period": "monthly", "term": null}, "salary_visible": false, "title_keywords": ["designer"], "responsibilities": ["mock-ups", "quality", "developing", "design", "testing", "ui"], "requirements": {"degrees": ["diploma"], "majors": ["related disciplines", "graphic design", "design"], "languages": ["cantonese", "english", "mandarin"], "language_level": ["good command"], "hard_skills": ["clean", "plus", "scheme", "web"], "soft_skills": ["communication", "interpersonal skills", "eye for detail"], "languages_combined": [{"language": "cantonese", "language_level": []}, {"language": "english", "language_level": ["good command"]}, {"language": "mandarin", "language_level": []}]}, "experience_required": {"duration": ["3+ years"], "field": ["graphic design", "advertising", "designer", "design"]}}, {"job_id": "100003009043228", "location_code": "hk", "company": "David James Recruitment Limited", "job_title": "Lead UI/UX Product Designer (Manager) - Financial Services - $60k", "description": "We are currently looking for an INSURANCE - GRAPHIC, UX/UI DESIGNER (MANAGER)\u00a0\n\n\n\nRESPONSIBILITIES\n\n\nLead creative strategies, concepts, and content that meet business objectives\nDrive design innovation across all the design disciplines,\u00a0 including design innovation, leading the creation of new design patterns and thought leadership of design evolution in the external context\nDevelop clear and impactful digital content and messages\nIdeate and execute on compelling digital communications and campaigns to drive customer engagement and customer stickiness\nLead content standards across different digital channels & platforms and be a champion for best practices\n\nREQUIREMENTS\u00a0\n\nUniversity degree, with at least 8 years\u2019 relevant experience\nHands on experiences of developing and implementing digital customer communication and campaign\nWell versed in all disciplines of design (UI/UX, Research, Animation, Motion)\nProven experience in managing and measuring digital content marketing is a plus\nCulturally sensitive and understanding of global and local customer needs.\nStrong marketing sense, business acumen, excellent leadership and communication skills\nExcellent English , Mandarin and Cantonese\nAPPLY FOR THE JOB\n\nInterested candidate please\u00a0CLICK\u00a0apply button to apply online or send your resume in MS word format to\u00a0Jobson Mores Recruitment\n\nPlease note that only shortlisted candidate will be notified. All information will be treated in strict confidence and solely used for recruitment purposes.", "employment_types": ["Full Time", "Permanent"], "selling_points": ["Figma, Invision, Adobe Creative, Visio", "Manager / Team Leadership Experience", "Competitive Salary Package"], "locations": ["Central & Western Area"], "categories": ["Information Technology (IT)", "UI/UX Designer"], "post_time": "2022-01-12T10:17:57Z", "salary": {"currency": "HKD", "max": 54999, "min": 45000, "period": "monthly", "term": null}, "salary_visible": true, "title_keywords": ["product designer", "manager", "lead"], "responsibilities": ["design", "develop"], "requirements": {"degrees": ["university degree"], "majors": [], "languages": ["cantonese", "english", "mandarin"], "language_level": ["excellent"], "hard_skills": ["ms word", "plus", "acumen"], "soft_skills": ["communication skills", "confidence", "marketing sense", "communication", "hands on", "sensitive", "business acumen", "leadership"], "languages_combined": [{"language": "cantonese", "language_level": ["excellent"]}, {"language": "english", "language_level": ["excellent"]}, {"language": "mandarin", "language_level": ["excellent"]}]}, "experience_required": {"duration": ["at least 8 years"], "field": ["digital content", "developing", "marketing", "relevant experience", "digital"]}}, {"job_id": "100003009042121", "location_code": "hk", "company": "W Consulting Company Limited", "job_title": "Senior UI/UX Designer for Software", "description": "Duties:\n\nServe a contract assignment under InfoTech's headcount, full-time second to a statutory body;\nRun a small development team to deliver customer-facing websites or applications;\nWork closely with business and IT teams to manage and deliver web projects;\nCustomize and enhance the Council's CMS solution, TeamSite and WordPress;\nManage external vendors to fulfil integration requirements when necessary;\nParticipate in IT project activities, such as system design, feasibility study, effort estimation and scheduling.\nRequirements:\n\n5 years' or above experience in web development, including 2 years' or more experience in leading a development team; candidate with less experience may be considered as Senior Analyst Programmer;\nHigher Diploma or above in Computer Science, IT or a related discipline preferred;\nStrong in front-end development such as HTML5, CSS3 and JavaScript; knowledge and experience in RWD (Responsive Web Design), SPA (Single-page Application), e.g. ReactJS is a must;\nKnowledge and experience in back-end development technology stack, e.g. Windows, Linux, Apache, NginX, MariaDB and Node.js;\nExperience in cloud such as AWS and CMS such as TeamSite and WordPress is a bonus;\nKnowledge of project management methodology. Holder of PMP, Agile, Scrum or equivalent qualifications is an advantage;\nAbility to work independently or with a team to meet tight project deadlines.\nOriginal JD\u00a0 \u00a0 \u00a0 Direct: 3978 8032", "employment_types": ["Full Time", "Permanent"], "selling_points": [], "locations": ["Central"], "categories": ["Information Technology (IT)", "UI/UX Designer"], "post_time": "2022-01-12T06:17:43Z", "salary": {"currency": null, "max": null, "min": null, "period": "monthly", "term": null}, "salary_visible": false, "title_keywords": ["ux designer"], "responsibilities": ["scheduling", "system design", "teams"], "requirements": {"degrees": ["higher diploma or above"], "majors": ["it", "computer science"], "languages": [], "language_level": [], "hard_skills": ["web design", "web development", "linux", "apache", "agile", "aws", "project management", "wordpress", "javascript", "pmp"], "soft_skills": ["project management", "work independently", "responsive", "agile"], "languages_combined": []}, "experience_required": {"duration": ["5 years", "2 years"], "field": ["development", "design", "team"]}}, {"job_id": "100003009043467", "location_code": "hk", "company": "Jobson Mores Limited", "job_title": "Insurance - Graphic, UX/UI Designer (Manager)", "description": "Job Responsibilities\nDesign/develop Mobile and Website UI with good sense of user experience and creativity\nPrepare prototypes for all new digital product applications and features\nHandle multiple projects, work under tight schedule and meet deadlines\nResponsible and creative, work well independently and also with teammates\n\nJob Requirements\n\n\nHigher Diploma or above in Digital Product/Interaction/Multimedia Design or other related discipline\nMinimum of 2 year working experience\nExperience in application UI/UX design via the APP or Web is preferred\nStrong sense of composition, space, color management, deep appreciation for clean, fresh and usable interfaces\nProficiency in using graphic & photo imaging software and web design tools is MUST (e.g. Adobe Photoshop, Illustrator, XD, After Effects, etc.)\nCreative, well-organized, detail-minded, independent, self-initiate, hardworking, aggressive and good personality\nKnowledge in HTML5, CSS, Action script will be an advantage\nGood command of both written and spoken English and Chinese\nInterested parties, please click \"Apply Now\" to submit your application.\nPersonal data collected will be used for recruitment purpose only.", "employment_types": ["Full Time"], "selling_points": ["Lead Creative Strategies, Concepts, and Content", "Well versd in UI/UX, Research, Animation, Motion", "Strong marketing sense & Business Acumen,"], "locations": ["Wan Chai"], "categories": ["Insurance", "Others", "Marketing / Public Relations", "Digital Marketing", "Information Technology (IT)", "UI/UX Designer"], "post_time": "2022-01-12T12:55:55Z", "salary": {"currency": null, "max": null, "min": null, "period": "monthly", "term": null}, "salary_visible": false, "title_keywords": ["ui designer", "manager"], "responsibilities": ["user experience", "website", "design", "develop", "schedule", "multiple projects", "ui"], "requirements": {"degrees": ["higher diploma or above"], "majors": ["multimedia design"], "languages": ["english", "chinese"], "language_level": ["good command"], "hard_skills": ["clean", "web design", "web", "adobe photoshop", "illustrator", "after effects", "multimedia", "css"], "soft_skills": ["detail-minded", "independent", "deep", "well-organized", "creative", "hardworking"], "languages_combined": [{"language": "english", "language_level": ["good command"]}, {"language": "chinese", "language_level": ["good command"]}]}, "experience_required": {"duration": ["minimum of 2 year"], "field": ["design"]}}, {"job_id": "100003009036158", "location_code": "hk", "company": "Landcrowd Limited", "job_title": "UI designer - Recent Grads Welcome", "description": "Job Highlights\u00a0\n\nDigital Media (DL.theVOC) + Technical Creative Projects + UI / UX Design\n\nGood sense of art direction, graphic sense\n\nWorking with Award winning Creatives\n\nJob Description:\u00a0\n\nProvide full creative, design, project art direction and production support;\n\nResponsible for social media OG design, GDN banner, graphics design, video editing, animation and other marketing materials;\n\nCreating different designs for marketing use purpose in different platform such as desktop, mobile as well as kiosk;\n\nKnowledge & experience in digital media industry is a plus;\u00a0\n\nRequirements:\n\nDiploma or above in Graphic / Multimedia / Web design or related fields;\n\nMinimum 2 years\u2019 relevant experience in graphic design, web design or advertising;\n\nPhotography and photo retouching, video post production, sound editing skills\n\nProficient in using PC / Mac Systems, Adobe Creative Cloud specifically Photoshop, Illustrator, Premiere, After Effects and other essential multimedia, interactive softwares, WordPress, Microsoft Office and other relevant software applications, familiar with HTML / HTML5 / CSS / JS is a plus;\n\nWorking knowledge of SEO best practice, GDN Display Ads, familiar with UI / UX design (Adobe XD, Figma, Sketch) is a big plus;\n\nStrong multimedia and web sense and understanding of digital technology trends;\n\nCreative, detail-oriented, enthusiastic, independent and self-motivated;\n\nGood written and spoken in English and Chinese;\n\nA perfect team player;\n\nPortfolio attachment is a MUST;\n\nCandidates with less experience would also be considered as Associate Art Director;\n\n\u00a0Benefits:\n\nAnnual Leave\n\nBirthday Leave\n\nPerformance Bonus\n\nMedical Insurance\n\nWe offer 5\u2013day work week, competitive salary and fringe benefits to the right candidate. For interested parties please send a cover letter stating your current salary and expected salary with Resume, Graduation Certification and Transcript to us.\n\nCandidates who are not contacted within 1 month from sending the resume should consider your applications filed for future opportunities. All applications will be treated in strict confidentiality and used for recruitment purpose only", "employment_types": ["Full Time"], "selling_points": ["Fast-growing, profitable, exciting tech startup", "Friendly design-focused startup team/mentorship", "Strong career development, continuous learning"], "locations": ["Sheung Wan"], "categories": ["Media & Advertising", "Creative / Design", "Design", "Web Designer", "Information Technology (IT)", "UI/UX Designer"], "post_time": "2022-01-10T09:31:12Z", "salary": {"currency": "HKD", "max": 24999, "min": 17000, "period": "monthly", "term": null}, "salary_visible": true, "title_keywords": ["ui designer"], "responsibilities": ["graphics", "social media", "design", "video editing", "marketing materials", "animation"], "requirements": {"degrees": ["diploma or above"], "majors": ["web design"], "languages": ["english", "chinese"], "language_level": ["good"], "hard_skills": ["web design", "plus", "seo", "web", "microsoft office", "adobe xd", "css", "illustrator", "premiere", "html", "after effects", "wordpress", "adobe", "multimedia", "pc", "photoshop"], "soft_skills": ["self-motivated", "independent", "detail-oriented", "enthusiastic", "team player", "creative"], "languages_combined": [{"language": "english", "language_level": ["good"]}, {"language": "chinese", "language_level": ["good"]}]}, "experience_required": {"duration": ["minimum 2 years"], "field": ["art director", "advertising", "graphic design", "design", "relevant experience"]}}, {"job_id": "100003009054919", "location_code": "hk", "company": "Oslo Environmental Innovation Limited", "job_title": "Programmer (Web and Mobile Application)", "description": "Our client is a global software consultancy company, recently listed on NASDAQ.\u00a0 They are now expanding their business in Hong Kong and Macau and looking for passionate technical talents to join their team to cope with the fast-growing business needs.\n\nResponsibilities:\n\n\u00a0\u00a0\u00a0\u00a0\u00a0\u00a0 Develop modern data architecture to meet clients\u2019 business objectives and provide end-to-end data solutions\n\u00a0\u00a0\u00a0\u00a0\u00a0\u00a0 Assist clients in realizing the additional business value that brings to them with data solutions\n\u00a0\u00a0\u00a0\u00a0\u00a0\u00a0 Implementation of projects\n\u00a0\u00a0\u00a0\u00a0\u00a0\u00a0 Work on mass data collection and big data storage components\n\u00a0\u00a0\u00a0\u00a0\u00a0\u00a0 Perform big data related tasks, including data cleaning, integration, visualization, drilling, and analytics\n\u00a0\u00a0\u00a0\u00a0\u00a0\u00a0 Monitor results and conduct performance tuning\n\nRequirements:\n\n\u00a0\u00a0\u00a0\u00a0\u00a0\u00a0 3+ years of experience big data-related areas, proficiency in at least one of the programming languages: Java, Scala, or Python\n\u00a0\u00a0\u00a0\u00a0\u00a0\u00a0 Experience with distributed computer frameworks like Spark, Flink, Mapreduce, or others\n\u00a0\u00a0\u00a0\u00a0\u00a0\u00a0 Experience with streaming processing frameworks like Storm, SparkStreaming, or others\n\u00a0\u00a0\u00a0\u00a0\u00a0\u00a0 Experience with MPP and search engines like Impala, Preso, Elasticsearch, etc.\n\u00a0\u00a0\u00a0\u00a0\u00a0\u00a0 Experience in distributed storage systems like HDFS, Ceph, etc.\n\u00a0\u00a0\u00a0\u00a0\u00a0\u00a0 Experience in NoSQL DBs like HBase, MongoDB, CouchDB, etc.\n\u00a0\u00a0\u00a0\u00a0\u00a0\u00a0 Experience in cloud based Hadoop distribution like MapR, Cloudera, Hortonworks, etc.\n\u00a0\u00a0\u00a0\u00a0\u00a0\u00a0 Knowledge in PowerBI, Tableau, and other data visualization tools is preferred\n\u00a0\u00a0\u00a0\u00a0\u00a0\u00a0 Knowledge in big data component tuning and machine learning would be a big plus.", "employment_types": ["Full Time", "Part Time", "Permanent", "Internship"], "selling_points": ["5-day work", "Support digital business", "Fresh grad also welcome"], "locations": ["Tuen Mun Area"], "categories": ["Information Technology (IT)", "Application Specialist - Software", "Software Development", "UI/UX Designer"], "post_time": "2022-01-17T13:51:39Z", "salary": {"currency": null, "max": null, "min": null, "period": "monthly", "term": null}, "salary_visible": false, "title_keywords": ["programmer"], "responsibilities": ["visualization", "data", "big data", "monitor", "develop", "implementation of projects", "data collection", "cleaning", "architecture"], "requirements": {"degrees": [], "majors": [], "languages": [], "language_level": [], "hard_skills": ["java", "plus", "tableau", "scala", "programming", "data visualization", "python", "spark", "processing"], "soft_skills": ["learning"], "languages_combined": []}, "experience_required": {"duration": ["3+ years"], "field": ["related", "programming"]}}, {"job_id": "100003009042115", "location_code": "hk", "company": "\u91ab\u7d50\u6709\u9650\u516c\u53f8", "job_title": "UI/UX Designer (App & Web)", "description": "WHO WE ARE AND WHAT WE DO:\n\nSpacious, Hong Kong's #1 internet property platform, is looking for a UI Designer, with a good sense of UX, to join our best-in-class Hong Kong based product team. You will work with a high-quality technology team of veterans and seasoned developers\u00a0to create amazing user experiences.\u00a0\n\nSpacious helps\u00a0to\u00a0make finding a property online\u00a0to\u00a0buy or rent easier and more efficient. Spacious has been providing the best-in-class search experience for property hunters in Greater China with its premium user interface, offering the highest quality listings and data comparisons for more than half a decade. This focus enables Spacious\u00a0to\u00a0generate the highest quality enquiries for property agents, developers, etc., who\u00a0pay\u00a0to\u00a0list.\n\nSpacious is a profitable, self-sustaining and proven business that is growing very quickly. We have over 1,000,000+ monthly high-value property searchers visiting our website/mobile app.\u00a0\n\nWe are a design-focused startup with a highly technical team with a technical founder who has coded various technologies for more than a decade.\u00a0UI/UX and technology are at the core of what we do and how we differentiate ourselves from our competition.\n\nFinding a home is one of life's most important (and stressful) events; by making the process easier, we positively impact people's lives every day with our work. Friends, family and strangers who have used Spacious to find a home often tell us how grateful they are for Spacious.\n\nWe are an international team with team members from the UK, USA, India and of course, Hong Kong.\nRoughly half our team are women.\nWe operate a friendly, collaborative company with diverse opinions in an environment that respects diversity and inclusion, from a top-quality office in the heart of Hong Kong.\nWe operate a flat organization with no strict reporting lines, open communication, and we trust our employees to manage their own time, offering a high degree of autonomy.\n\nThis is our website:\u00a0www.spacious.hk\nSpacious mobile apps are award winning on both Android and iOS apps.\n\nWHO WE ARE LOOKING FOR:\n\nDuties:\n(a)\u00a0Execute all visual design stages from concept to final hand-off to software engineering (50%)\n(b)\u00a0Collaborate with product management and engineering to define and implement innovative solutions for the product direction, visuals and experience (10%)\n(c)\u00a0Conceptualize original ideas that bring simplicity and user-friendliness to complex design roadblocks\u00a0(10%)\n(d)\u00a0Create wireframes, storyboards, user flows, process flows, and site maps to communicate interaction and design ideas effectively\u00a0(10%)\n(e)\u00a0Conduct user research and evaluate user feedback\u00a0(10%)\n(f)\u00a0Establish and promote design guidelines, best practices and standards (5%)\n(g) Help to create creative materials for paid ads, blog posts, social media,\u00a0clients content, offline banners when required (5%)\n\nRecent Grads welcome. This role is a fantastic opportunity to learn from one of Hong Kong's most experienced and highly skilled startup teams.\n\nThe ideal candidate should have an eye for clean and artful design, possess superior UI skills, translate high-level requirements into interaction flows and artefacts and transform them into beautiful, intuitive, and functional user interfaces.\n\nIf the challenge of working in an exciting, fast-paced startup that is growing quickly appeals to you, then get in touch.\n\nQualifications:\n\nDegree in design related subject.\nPrevious experience of UI Design for web and mobile App design or wireframing\nA portfolio of relevant design work (please attach samples as a cover letter or provide a link to your portfolio)\nPassionate about details and have a pixel-perfect obsession\nCareer Path\nSenior UI/UX Designer\nAs you gain experience and knowledge from the rest of the team - you will naturally move to more senior UX/UI roles with greater ownership levels. We have annual salary reviews and have quarterly catchups to offer feedback on how you are doing.\nUltimately this leads to a career path with people management leadership responsibilities.\n\nExperience\nRecent Grads Welcome\n\nWHY YOU SHOULD JOIN US:\n\nWe work in a fun, collaborative open space where we encourage creativity and ideas to flow freely.\u00a0\nYou'll be able to steer the future roadmap to improve our products, big or small, and see the results of your products reach our customers.\nGet to work with flexible working hours. Our priority is on getting the job done.\nFlat structure environment, you will be able to work independently and make your own choices.\nWe provide guidance and mentorship to polish your technical skills, business skills and entrepreneurship mindset.\nWe are one of the standout tech startups in Hong Kong, targeting a huge opportunity in Asia.\nBenefits\nExcellent monthly salary\nMPF\nMedical Insurance\n18 days annual leave\nA budget for continual learning", "employment_types": ["Full Time", "Permanent"], "selling_points": ["Leading Insurtech Company", "Energetic company", "Young and Passionate Team"], "locations": ["Kwun Tong"], "categories": ["Design", "Web Designer", "Information Technology (IT)", "UI/UX Designer"], "post_time": "2022-01-12T06:16:19Z", "salary": {"currency": null, "max": null, "min": null, "period": "monthly", "term": null}, "salary_visible": false, "title_keywords": ["ux designer"], "responsibilities": ["collaborate with", "ideas", "software", "data", "quality", "website", "design", "communication", "user interface", "banners", "storyboards", "mobile app", "teams", "visual", "ui", "reporting", "management", "social media", "design work", "guidelines", "evaluate"], "requirements": {"degrees": ["degree", "recent grads"], "majors": ["design"], "languages": [], "language_level": [], "hard_skills": ["clean", "small", "no", "web", "fun", "make", "mobile", "visual design", "c", "focus", "android"], "soft_skills": ["efficient", "flexible", "work independently", "creative", "focused", "collaborative", "communication", "diverse", "friendly", "leadership", "focus", "innovative", "superior", "passionate about", "ideal"], "languages_combined": []}, "experience_required": {"duration": [], "field": ["product management", "engineering", "design", "team"]}}, {"job_id": "100003009038685", "location_code": "hk", "company": "", "job_title": "UI/UX Design Supervisor", "description": "Responsible for the design, development, implementation, enhancement, testing and maintenance of web and mobile systems/applications\nProvide user support and conduct system analysis; propose, develop and implement IT solutions\nDesign and complete requirement specifications for different components for application systems\nParticipate in new product development projects and support digital marketing related projects\n\nRequirement\n\nDegree in Computer Science / Information Technology or equivalent\nHands-on experience in Web and Mobile application development is preferable\nGood communication and reporting skills in English and Chinese\nA self-motivated team player with good interpersonal and communication skills;\nAble to work independently to meet project deadlines;", "employment_types": ["Full Time", "Permanent"], "selling_points": ["Being a UI/UX design lead of company interaction", "Higher Diploma or above in Digital Product/", "Minimum of 3 years working experience"], "locations": ["Kwun Tong"], "categories": ["Information Technology (IT)", "Application Specialist - Software", "Others", "UI/UX Designer"], "post_time": "2022-01-11T07:38:13Z", "salary": {"currency": null, "max": null, "min": null, "period": "monthly", "term": null}, "salary_visible": false, "title_keywords": ["supervisor"], "responsibilities": ["reporting", "maintenance", "application development", "analysis", "systems", "implementation", "design", "testing", "develop", "communication", "specifications", "digital marketing", "application systems"], "requirements": {"degrees": ["degree"], "majors": ["computer science", "information technology"], "languages": ["english", "chinese"], "language_level": ["good"], "hard_skills": ["mobile", "analysis", "web", "maintenance"], "soft_skills": ["communication skills", "self-motivated", "work independently", "responsible", "communication", "hands-on", "team player", "interpersonal"], "languages_combined": [{"language": "english", "language_level": ["good"]}, {"language": "chinese", "language_level": ["good"]}]}, "experience_required": {"duration": [], "field": ["application development"]}}, {"job_id": "100003009056170", "location_code": "hk", "company": "Osmium Consulting Group Limited", "job_title": "Senior/Mobile Developer ( iOS/ Android/Flutter/React Native ) | FinTech", "description": "Responsibilities\n\nDevelopment of iOS/ Android mobile application\nTechnical system design, development and UAT\nRequirement analysis and documentation\nCoordinate with offshore team on system development and implementation\nWork closely with internal & external parties to collect and analyze their requirements\n\nRequirements\n\nHigher Diploma or above in Technology, Computer Science, Engineering or related disciplines\nSolid experience in mobile software development on iOS or Android platform\nExperience in Kotlin, Java - Android / Swift - iOS platform / Flutter, React Native - Hybrid\nFresh graduates with programming background and strong motivation to learn will be considered\nExperienced candidates will be considered for a senior position\nFamiliar with Agile development methodology is a definite advantage\n\nWhat we can provide\n\nDouble Pay\nDiscretionary Performance Bonus\nLife Insurance\nMedical insurance\nFree Snacks and Drinks", "employment_types": ["Full Time", "Permanent"], "selling_points": ["FinTech/Crypto industry", "Fully work form home plan", "New Tech & Technical"], "locations": ["Tsim Sha Tsui"], "categories": ["Information Technology (IT)", "Application Specialist - Software", "Software Development", "UI/UX Designer"], "post_time": "2022-01-18T03:28:29Z", "salary": {"currency": "HKD", "max": 54999, "min": 30000, "period": "monthly", "term": null}, "salary_visible": true, "title_keywords": ["developer"], "responsibilities": ["system design", "uat"], "requirements": {"degrees": ["higher diploma or above"], "majors": ["related disciplines", "engineering", "computer science"], "languages": [], "language_level": [], "hard_skills": ["java", "agile", "analysis", "swift", "mobile", "react native", "programming", "documentation", "kotlin", "android"], "soft_skills": ["agile"], "languages_combined": []}, "experience_required": {"duration": [], "field": ["software development"]}}, {"job_id": "100003009049628", "location_code": "hk", "company": "TecPal Limited", "job_title": "UX / UI Designer", "description": "Responsibilities:\n\n\nCreate innovative user experiences and user interfaces for mobile apps and smart home devices\nIntegrate design features, wireframes, sketches, flow diagrams, style guides and user research into the product development process\nCollaborate with product development and engineering team\nStay up-to-date with the latest UX/UI design trends, tools, best practices\nRequirements:\n\nDiploma or above in Visual Design, interactive Design or similar disciplines\nMore than 3 years of related work experience\nGood knowledge of UX design techniques\nProficiency in Sketch and/or Adobe CS\nGood command in written and spoken English\nSelf-starter, independent and well-organized\nCome and join us in a multi-cultural, dynamic and stable work environment, experience the opportunity to develop your career and to work in different exciting projects in an nicely decorated office.\n\nWe are an Equal Opportunity Employer. Interested parties, please send us your job application, the position you apply, together with Current and Expected Salary. We look forward to your application.", "employment_types": ["Full Time"], "selling_points": ["Multicultural Workplace", "15-day Annual Leave", "Excellent Career Development"], "locations": ["Hung Hom"], "categories": ["Media & Advertising", "Creative / Design", "Design", "Web Designer", "Information Technology (IT)", "UI/UX Designer"], "post_time": "2022-01-14T08:59:43Z", "salary": {"currency": null, "max": null, "min": null, "period": "monthly", "term": null}, "salary_visible": false, "title_keywords": ["ui designer"], "responsibilities": ["collaborate with", "sketches", "design", "design trends", "ui"], "requirements": {"degrees": ["diploma or above"], "majors": ["design"], "languages": ["english"], "language_level": ["good command"], "hard_skills": ["visual design", "adobe cs"], "soft_skills": ["independent", "well-organized"], "languages_combined": [{"language": "english", "language_level": ["good command"]}]}, "experience_required": {"duration": ["3 years"], "field": ["related"]}}, {"job_id": "100003009048924", "location_code": "hk", "company": "Morgan McKinley", "job_title": "Senior UI/ Frontend Software Engineer (React.JS), Fintech", "description": "The Senior UI / Frontend Software Engineer will provide efficient UX to clients' digital platforms.\n\nResponsibilities\n\nDesign and implement products and platforms to provide highly efficient user experiences for all functionalities\nPassionate about using the latest frontend technologies to tackle complex business problems\nCollaborate with product design, product manager and other software engineer to deliver high quality code\nDevelop the mobile App and Web browser site\nParticipate in extensive and candid code review peers\nMentor junior developers\n\nRequirements\n\nSc or high degree in computer science and related fields.\nMore than 3 years of front-end experience.\nStrong JavaScript/HTML/CSS frontend engineering experience.\nDeep understanding of underlying design philosophy and implementation of common web frameworks, including React/Vue.\nExperience with Babel, Webpack, Rollup, or other JavaScript building tools\nExperience in building large-scale web applications and optimizing front-end performance in fast-moving team environment.\n\nApplication\n\nDon't miss out on this exciting opportunity to work in a fast-growing fintech companys! To apply, click 'Apply Now' to submit your resume to us.\n\nAny questions, please feel free to contact Yvonne Hung at +852 3907 3977 or email your inquiry to yhung@morganmckinley.com.", "employment_types": ["Full Time", "Permanent"], "selling_points": ["Multicultural environment & convenient location", "Work with experts from financial services", "5-day work week, medical insurance and more"], "locations": ["Not Specified"], "categories": ["Information Technology (IT)", "Software Development", "E-commerce", "Software Development", "UI/UX Designer"], "post_time": "2022-01-14T07:43:01Z", "salary": {"currency": "HKD", "max": 54999, "min": 45000, "period": "monthly", "term": null}, "salary_visible": true, "title_keywords": ["software engineer"], "responsibilities": ["collaborate with", "mobile app", "software", "review", "quality", "design", "develop", "product design"], "requirements": {"degrees": ["degree"], "majors": ["computer science"], "languages": [], "language_level": [], "hard_skills": ["web applications", "web", "react", "html", "javascript", "css"], "soft_skills": ["deep"], "languages_combined": []}, "experience_required": {"duration": ["3 years"], "field": ["web applications", "engineering", "team"]}}, {"job_id": "100003009044129", "location_code": "hk", "company": "Goodbye Dear Company Limited", "job_title": "UI UX designer", "description": "Job Highlights\n\nWebsite and mobile app user interface designs\nGraphic and digital design for banner\nWork with project and development team\n\nJob Responsibilities\n\nWebsite and mobile app user interface designs;\nProduce all kind of graphic and digital design for banner and other presentation materials;\nWork with project and development team; and\nManage any ad-hoc tasks or projects as assigned.\n\nJob Requirements:\n\nHigher Diploma or above in digital design, multimedia design, graphic communications or related field;\nMinimum 1 years' of working experience in design related field\nHands on skills in Adobe Photoshop, Illustrator, Sketch;\nKnowledge of UI design principles and techniques;\nDetail minded with can-do attitude and ability to multitask;\nProvide online portfolio link in addition to resume. *Immediate availability is preferred\n\nWorking location & hours\n\n5-days work\nWork in Kwun Tong", "employment_types": ["Full Time", "Contract"], "selling_points": [], "locations": ["Kwun Tong"], "categories": ["Design", "Multi-media", "Web Designer", "Information Technology (IT)", "UI/UX Designer"], "post_time": "2022-01-13T03:09:46Z", "salary": {"currency": null, "max": null, "min": null, "period": "monthly", "term": null}, "salary_visible": false, "title_keywords": ["ux designer"], "responsibilities": ["mobile app", "ad-hoc tasks", "website", "design", "user interface"], "requirements": {"degrees": ["higher diploma or above"], "majors": ["multimedia design", "communications", "design"], "languages": [], "language_level": [], "hard_skills": ["illustrator", "adobe photoshop", "multimedia"], "soft_skills": ["ability to multitask", "hands on", "can-do attitude"], "languages_combined": []}, "experience_required": {"duration": ["minimum 1 years"], "field": ["related", "design"]}}, {"job_id": "100003009051487", "location_code": "hk", "company": "InfoTech Services ( HK ) Ltd. \u8cc7\u8a0a\u79d1\u6280\u670d\u52d9(\u9999\u6e2f)\u6709\u9650\u516c\u53f8", "job_title": "System Analyst / Senior Analyst Programmer - Front-end Lead", "description": "Duties:\n\nServe a contract assignment under InfoTech's headcount, full-time second to a statutory body;\nRun a small development team to deliver customer-facing websites or applications;\nWork closely with business and IT teams to manage and deliver web projects;\nCustomize and enhance the Council's CMS solution, TeamSite and WordPress;\nManage external vendors to fulfil integration requirements when necessary;\nParticipate in IT project activities, such as system design, feasibility study, effort estimation and scheduling.\nRequirements:\n\n5 years' or above experience in web development, including 2 years' or more experience in leading a development team; candidate with less experience may be considered as Senior Analyst Programmer;\nHigher Diploma or above in Computer Science, IT or a related discipline preferred;\nStrong in front-end development such as HTML5, CSS3 and JavaScript; knowledge and experience in RWD (Responsive Web Design), SPA (Single-page Application), e.g. ReactJS is a must;\nKnowledge and experience in back-end development technology stack, e.g. Windows, Linux, Apache, NginX, MariaDB and Node.js;\nExperience in cloud such as AWS and CMS such as TeamSite and WordPress is a bonus;\nKnowledge of project management methodology. Holder of PMP, Agile, Scrum or equivalent qualifications is an advantage;\nAbility to work independently or with a team to meet tight project deadlines.\nOriginal JD\u00a0 \u00a0 \u00a0 Direct: 3978 8032", "employment_types": ["Full Time", "Contract"], "selling_points": ["Attractive salary package, 5-day work", "3 - 5 years' web development exp, a statutory body", "HTML5, CSS3, React.js, RWD, SPA, Node.js, Linux"], "locations": ["Wan Chai"], "categories": ["Information Technology (IT)", "IT Project Management / Team Lead", "Software Development", "UI/UX Designer"], "post_time": "2022-01-16T04:15:06Z", "salary": {"currency": null, "max": null, "min": null, "period": "monthly", "term": null}, "salary_visible": false, "title_keywords": ["system analyst", "senior analyst programmer", "lead"], "responsibilities": ["scheduling", "system design", "teams"], "requirements": {"degrees": ["higher diploma or above"], "majors": ["it", "computer science"], "languages": [], "language_level": [], "hard_skills": ["web design", "web development", "linux", "apache", "agile", "aws", "project management", "wordpress", "javascript", "pmp"], "soft_skills": ["project management", "work independently", "responsive", "agile"], "languages_combined": []}, "experience_required": {"duration": ["5 years", "2 years"], "field": ["development", "design", "team"]}}, {"job_id": "100003009038684", "location_code": "hk", "company": "AAStocks.com Limited", "job_title": "UI/UX Designer (5-day work)", "description": "Job Responsibilities\nDesign/develop Mobile and Website UI with good sense of user experience and creativity\nPrepare prototypes for all new digital product applications and features\nHandle multiple projects, work under tight schedule and meet deadlines\nResponsible and creative, work well independently and also with teammates\n\nJob Requirements\n\n\nHigher Diploma or above in Digital Product/Interaction/Multimedia Design or other related discipline\nMinimum of 2 year working experience\nExperience in application UI/UX design via the APP or Web is preferred\nStrong sense of composition, space, color management, deep appreciation for clean, fresh and usable interfaces\nProficiency in using graphic & photo imaging software and web design tools is MUST (e.g. Adobe Photoshop, Illustrator, XD, After Effects, etc.)\nCreative, well-organized, detail-minded, independent, self-initiate, hardworking, aggressive and good personality\nKnowledge in HTML5, CSS, Action script will be an advantage\nGood command of both written and spoken English and Chinese\nInterested parties, please click \"Apply Now\" to submit your application.\nPersonal data collected will be used for recruitment purpose only.", "employment_types": ["Full Time", "Permanent"], "selling_points": ["Design/develop Mobile and Website UI", "Handle multiple projects", "Minimum of 2 year working experience"], "locations": ["Kwun Tong"], "categories": ["Design", "Multi-media", "Information Technology (IT)", "Others", "UI/UX Designer"], "post_time": "2022-01-11T07:38:12Z", "salary": {"currency": null, "max": null, "min": null, "period": "monthly", "term": null}, "salary_visible": false, "title_keywords": ["ux designer"], "responsibilities": ["user experience", "website", "design", "develop", "schedule", "multiple projects", "ui"], "requirements": {"degrees": ["higher diploma or above"], "majors": ["multimedia design"], "languages": ["english", "chinese"], "language_level": ["good command"], "hard_skills": ["clean", "web design", "web", "adobe photoshop", "illustrator", "after effects", "multimedia", "css"], "soft_skills": ["detail-minded", "independent", "deep", "well-organized", "creative", "hardworking"], "languages_combined": [{"language": "english", "language_level": ["good command"]}, {"language": "chinese", "language_level": ["good command"]}]}, "experience_required": {"duration": ["minimum of 2 year"], "field": ["design"]}}, {"job_id": "100003009051349", "location_code": "hk", "company": "3T6B Limited", "job_title": "Creative Director (Art) / Art Director (Digital)", "description": "Job Highlights\u00a0\n\nDigital Media (DL.theVOC) + Technical Creative Projects + UI / UX Design\n\nGood sense of art direction, graphic sense\n\nWorking with Award winning Creatives\n\nJob Description:\u00a0\n\nProvide full creative, design, project art direction and production support;\n\nResponsible for social media OG design, GDN banner, graphics design, video editing, animation and other marketing materials;\n\nCreating different designs for marketing use purpose in different platform such as desktop, mobile as well as kiosk;\n\nKnowledge & experience in digital media industry is a plus;\u00a0\n\nRequirements:\n\nDiploma or above in Graphic / Multimedia / Web design or related fields;\n\nMinimum 2 years\u2019 relevant experience in graphic design, web design or advertising;\n\nPhotography and photo retouching, video post production, sound editing skills\n\nProficient in using PC / Mac Systems, Adobe Creative Cloud specifically Photoshop, Illustrator, Premiere, After Effects and other essential multimedia, interactive softwares, WordPress, Microsoft Office and other relevant software applications, familiar with HTML / HTML5 / CSS / JS is a plus;\n\nWorking knowledge of SEO best practice, GDN Display Ads, familiar with UI / UX design (Adobe XD, Figma, Sketch) is a big plus;\n\nStrong multimedia and web sense and understanding of digital technology trends;\n\nCreative, detail-oriented, enthusiastic, independent and self-motivated;\n\nGood written and spoken in English and Chinese;\n\nA perfect team player;\n\nPortfolio attachment is a MUST;\n\nCandidates with less experience would also be considered as Associate Art Director;\n\n\u00a0Benefits:\n\nAnnual Leave\n\nBirthday Leave\n\nPerformance Bonus\n\nMedical Insurance\n\nWe offer 5\u2013day work week, competitive salary and fringe benefits to the right candidate. For interested parties please send a cover letter stating your current salary and expected salary with Resume, Graduation Certification and Transcript to us.\n\nCandidates who are not contacted within 1 month from sending the resume should consider your applications filed for future opportunities. All applications will be treated in strict confidentiality and used for recruitment purpose only", "employment_types": ["Full Time"], "selling_points": ["Digital Media(\uff20DL.theVOC) + UI/UX \uff06 Graphic Design", "Good sense of art direction, graphic sense", "Working with Award winning Creatives"], "locations": ["Kwun Tong"], "categories": ["Design", "Graphics", "Multi-media", "Information Technology (IT)", "UI/UX Designer"], "post_time": "2022-01-15T10:39:17Z", "salary": {"currency": null, "max": null, "min": null, "period": "monthly", "term": null}, "salary_visible": false, "title_keywords": ["art director", "creative director"], "responsibilities": ["graphics", "social media", "design", "video editing", "marketing materials", "animation"], "requirements": {"degrees": ["diploma or above"], "majors": ["web design"], "languages": ["english", "chinese"], "language_level": ["good"], "hard_skills": ["web design", "plus", "seo", "web", "microsoft office", "adobe xd", "css", "illustrator", "premiere", "html", "after effects", "wordpress", "adobe", "multimedia", "pc", "photoshop"], "soft_skills": ["self-motivated", "independent", "detail-oriented", "enthusiastic", "team player", "creative"], "languages_combined": [{"language": "english", "language_level": ["good"]}, {"language": "chinese", "language_level": ["good"]}]}, "experience_required": {"duration": ["minimum 2 years"], "field": ["art director", "advertising", "graphic design", "design", "relevant experience"]}}, {"job_id": "100003009044964", "location_code": "hk", "company": "Well In Technology Development Limited", "job_title": "Art Director / Senior Designer", "description": "Responsibilities:\n\nResponsible for UI and UX design of applications including mobile apps and responsive website\nNeed to participate\u00a0in product design and creating the design guidelines\nWork closely with internal stakeholder to gather requirement and present the design concept\nCreate UI mock-ups, components and prototypes\nIdentify and troubleshoot UI/UX problems\n\nRequirements:\n\nDiploma or above in Graphic Design, Multimedia or related disciplines\n\nExperience in designing web/mobile products or commercial products\nProficient in UI/UX design software (e.g. Figma, Adobe XD)\nBasic knowledge in HTML, CSS, JavaScript is a must\nBasic knowledge in Vue is a plus\nUpdate-to-date with latest trends and technique in design UI & UX\n\nCreativity and Flexibility\nSelf-motivated, a team player, hardworking and able to work independently\n\nBenefits:\u00a0 \u00a0\u00a0\n\nAnnual Leave 12-18 days\nBirthday Leave\nMarriage Leave\nCompassionate Leave\nFull Paid Paternity Leave\u00a0\nMaternity Leave\u00a0\nNotebook Subsidy\nEducation\u00a0Subsidy\nExamination Time-off\u00a0\nGraduation\u00a0Time-off\nAs a caring company, staff development is one of our top priorities.\u00a0We offer attractive\u00a0remuneration packages with a wide range of fringe benefits include medical & dental insurance, education allowance, performance bonus and excellent career prospect to the right candidate.\u00a0We also offer on-the-job training and specialized training programme to uplift the potential of our staff.\u00a0\n\nInterested parties please send your detailed resume\u00a0with\u00a0current and expected salary\u00a0by email\u00a0to:\u00a0hr_manager @ctil.com\u00a0or by mail to \"Human Resources Department, Computer And Technologies\u00a0Resources Limited, Level 10, Cyberport 2, 100 Cyberport Road, Hong Kong\".\u00a0Please quote the employer reference number in the application.\u00a0\nIn order to explore more about our growth initiatives and other job opportunities, please visit our website\u00a0https://www.ctil.com/.\u00a0\nMore job openings in our C&T group can be viewed in our website\u00a0https://careers.ctil.com/index.php?page=en_Job+Openings.\u00a0\nAll personal data collected will be kept in strict confidence and would only be used for recruitment purpose.", "employment_types": ["Full Time"], "selling_points": ["Work with a team of developers", "Deliver the UI/UX experience for Web & iOS/Android", "Portfolio is a must"], "locations": ["Mong Kok"], "categories": ["Design", "Others", "Information Technology (IT)", "UI/UX Designer"], "post_time": "2022-01-13T06:47:16Z", "salary": {"currency": null, "max": null, "min": null, "period": "monthly", "term": null}, "salary_visible": false, "title_keywords": ["art director", "senior designer"], "responsibilities": ["guidelines", "design concept", "mock-ups", "website", "design", "product design", "troubleshoot", "ui"], "requirements": {"degrees": ["diploma or above"], "majors": ["related disciplines", "graphic design"], "languages": [], "language_level": [], "hard_skills": ["plus", "basic", "web", "adobe xd", "html", "mobile", "javascript", "multimedia", "css"], "soft_skills": ["self-motivated", "team player", "work independently", "hardworking"], "languages_combined": []}, "experience_required": {"duration": [], "field": ["commercial"]}}, {"job_id": "100003009042421", "location_code": "hk", "company": "CITIC Telecom International CPC Limited", "job_title": "Digital Product Designer/Manager", "description": "The Job Scope\nYou will:\n\nSupport Customer Digital Experience Development Manager in delivering user centred digital application projects across the Club\u2019s range of digital channels, including mobile app, website, e-commerce and cross-media platforms.\nTransform business analysis, customer feedback and/or market research outcomes in to digital business insights and product requirement.\nResponsible for interaction design of various digital channels in the Club\u2019s\nExpert in user experience design from user\u2019s requirement analysis, through information architecture, wireframes, user flow, behavioural design and prototype for a variety of mobile/web products.\nHaving sophisticated experience in conducting agile research, including needs finding research, conceptual validation, usability testing etc.\nPassionate and skilful for translating research findings into tangible designs\nBe part of the scrum team, work closely with development team to maximize value of sprint deliveries\nDemonstrable experience with Agile methodologies such as Kanban, Scrum and tools such as Jira, Confluence and Slack.\n\nAbout You\nYou should have:\n\nA bachelor degree or above in interaction design, industrial design, computer science, psychology or other relevant disciplines.\nAt least 6 years of proven working experience in Consulting / Digital Solution / Technology project management\nSolid working experience within an agile team on digital products implementation\nStrong interpersonal skills with internal and external stakeholders. Easily understand people idea and turn it into action.\nExcellent written and verbal communication (English and Chinese).\nAn excellent working attitude, self-motivated and being a team player.\nProficiency in design and prototyping software (e.g. Adobe Creative Suite, Sketch, Axure) is a must\nKnowledge in Horse Racing and/or Football betting is a definite advantage\nUnderstanding in latest digital trend, including Gamification and Artificial Intelligence is a plus\nA portfolio demonstration during the interview.\nCandidate with less experience may consider as Senior Officer\n\n\nTerms of Employment\nThe level of appointment will be commensurate with qualifications and experience.\n\nHow to Apply\nPlease send your resume, complete with expected salary and job reference by clicking the Apply Now button\n\nWe are an equal opportunity employer. Personal data provided by job applicants will be used strictly in accordance with the Club's notice to employees and prospective employees relating to the Personal Data (Privacy) Ordinance. A copy of which will be provided immediately upon request.", "employment_types": ["Full Time", "Permanent"], "selling_points": ["Develop customer journeys in Telco products", "IT, Telco or related industry experience", "Min. 5 years UX design experience"], "locations": ["Quarry Bay"], "categories": ["Information Technology (IT)", "Product Management / Business Analyst", "UI/UX Designer"], "post_time": "2022-01-12T07:24:57Z", "salary": {"currency": null, "max": null, "min": null, "period": "monthly", "term": null}, "salary_visible": false, "title_keywords": ["product designer", "manager"], "responsibilities": ["mobile app", "software", "consulting", "analysis", "website", "design", "market research", "user experience", "testing", "project management", "implementation", "communication", "business analysis", "personal data", "architecture"], "requirements": {"degrees": ["degree or above", "bachelor"], "majors": ["psychology", "computer science", "design"], "languages": ["english", "chinese"], "language_level": ["excellent"], "hard_skills": ["plus", "agile", "e-commerce", "analysis", "web products", "mobile", "project management", "adobe creative suite"], "soft_skills": ["sophisticated", "passionate", "self-motivated", "agile", "responsible", "communication", "project management", "interpersonal skills", "team player", "creative"], "languages_combined": [{"language": "english", "language_level": ["excellent"]}, {"language": "chinese", "language_level": ["excellent"]}]}, "experience_required": {"duration": ["at least 6 years"], "field": ["research", "consulting", "e-commerce", "development", "design", "testing", "project management", "digital", "media", "team"]}}, {"job_id": "100003009036186", "location_code": "hk", "company": "Computer And Technologies Resources Limited", "job_title": "UI/ UX Designer (Ref: JDB/PRD/UIUXD)", "description": "Duties and Responsibilities\n\nDesign and construct the user interface for our platform\nCollaborate with product management and engineering to define and implement innovative solutions for the product/platform direction, visuals, and experience\nExecute all visual design stages from concept to final hand-off to engineering\nCreate user-centered designs by understanding business requirements, the voice of the customer, user journeys, customer feedback, and usability findings\nConceptualize original ideas that bring simplicity and user-friendliness to complex design roadblocks\nGenerate an effective range of layouts for all elements of the creative solution (e.g. wireframes, storyboards, user flows, process flows, and site maps)\nProvide direction and feedback to teams on their work to ensure achievement of objectives\nConduct user research and competitor analysis and evaluate user feedback\nEstablish and promote design guidelines, best practices, and standards that consistently scale across platforms\n\nRequirement\n\n3 years or above of UI/UX design experience and a proven track record\nPreferably holding a Bachelor\u2019s degree in Multimedia Design or equivalent\nProficiency in industry tools such as Figma, Sketch, InVision, Adobe InDesign, Illustrator, or comparable design programs\nSolid experience in creating wireframes, storyboards, user flows, process flows, and site maps\nExcellent written and verbal communication skills in English and Chinese.\nSelf-motivated, dedicated with strong problem solving and communications skills, good team player, and can work independently.\nExcellent command in both spoken and written English, Cantonese, and Putonghua\nImmediate available or short notice period is highly preferable", "employment_types": ["Full Time", "Permanent"], "selling_points": ["Responsible for UI and UX design of applications", "Participate in product design & creating guideline", "Birthday Leave & Transportation Subsidy & Time-off"], "locations": ["Pok Fu Lam"], "categories": ["Design", "Web Designer", "Information Technology (IT)", "Software Development", "UI/UX Designer"], "post_time": "2022-01-10T09:36:02Z", "salary": {"currency": null, "max": null, "min": null, "period": "monthly", "term": null}, "salary_visible": false, "title_keywords": ["ux designer"], "responsibilities": ["collaborate with", "management", "ideas", "provide direction", "guidelines", "analysis", "teams", "design", "evaluate", "user interface", "visual", "storyboards"], "requirements": {"degrees": ["degree", "bachelor"], "majors": ["multimedia design"], "languages": ["cantonese", "putonghua", "english", "chinese"], "language_level": ["excellent"], "hard_skills": ["problem solving", "illustrator", "adobe indesign", "multimedia"], "soft_skills": ["communication skills", "self-motivated", "work independently", "good team player", "problem solving"], "languages_combined": [{"language": "cantonese", "language_level": ["excellent"]}, {"language": "putonghua", "language_level": ["excellent"]}, {"language": "english", "language_level": ["excellent", "excellent"]}, {"language": "chinese", "language_level": ["excellent"]}]}, "experience_required": {"duration": ["3 years"], "field": ["design"]}}, {"job_id": "100003009042083", "location_code": "hk", "company": "Osmium Consulting Group Limited", "job_title": "Senior UI/UX Designer - Solid UX Experience Required", "description": "Responsibilities :\nGather and evaluate user requirements in collaboration with product managers and engineers\nIllustrate design ideas using storyboards, process flows and sitemaps\nDevelop UI mockups and prototypes that clearly illustrate how sites function and look like\nPrepare and present rough drafts to internal teams and key stakeholders\nIdentify and troubleshoot UX problems\u00a0\nConduct layout adjustments based on user feedback\nRequirements :\nMinimum 3 years\u2019 solid experience on UI/UX design of web application and mobile app\nExperience with large customer facing platform preferred\u00a0\nExtensive knowledge of wireframing and prototyping tools such as Sketch, Figma, and Adobe Xd\nExperience in user testing and usability analysis\nExcellent verbal and written communication skills\nImmediate availability is highly preferred\u00a0", "employment_types": ["Full Time", "Permanent"], "selling_points": ["Work From Home", "Large Media Platform", "In-House"], "locations": ["Wong Tai Sin Area"], "categories": ["Information Technology (IT)", "Software Development", "UI/UX Designer"], "post_time": "2022-01-12T05:59:31Z", "salary": {"currency": "HKD", "max": 54999, "min": 35000, "period": "monthly", "term": null}, "salary_visible": true, "title_keywords": ["ux designer"], "responsibilities": ["ideas", "teams", "design", "develop", "evaluate", "troubleshoot", "ui", "storyboards"], "requirements": {"degrees": [], "majors": [], "languages": [], "language_level": [], "hard_skills": ["adobe xd", "mobile", "analysis", "web"], "soft_skills": ["communication skills", "extensive"], "languages_combined": []}, "experience_required": {"duration": ["minimum 3 years"], "field": ["design", "testing"]}}, {"job_id": "100003009034022", "location_code": "hk", "company": "AXA Hong Kong", "job_title": "UI/UX Architect/Designer", "description": "Front End Platform Engineer\n\nEclipse Trading is one of Asia's leading proprietary derivatives trading firms, specialising in options market making. Technology is at the core of our business, and our trading expertise and strategies are deployed across several Asian markets. Founded in 2007, we have approximately 100 staff across our three office locations \u2013 Hong Kong (our HQ), Sydney, and Shanghai.\n\nThe successful candidate will join the UI development team, building out the company\u2019s next generation derivative trading and risk management UIs.\n\nOur team builds tools that allow traders, quants and other developers create their own applications. We have created an in-house platform to combine, transform, and\u00a0visualize\u00a0real time data streams from multiple sources. We also provide added functionality so that users can change and interact with that data.\u00a0\u00a0\n\nWe mostly work in C# and TypeScript and use a variety of technologies including: React, Redux, WPF, Plotly, ReactiveX, GraphQL, Monaco, Docker, C# Source Generators, SignalR, Kafka, Avro, RethinkDb, Clickhouse, and Timescale. The unique nature of our work gives us the opportunity to take on many different kinds of challenge, like real time stream processing, language parsing, code generation, and dynamically creating complex UIs that look and feel purpose built.\u00a0\n\nPerformance management is also a major part of our work. We deal with tens of thousands of updates streaming onto our platform every second. The flexibility of our system means that\u00a0we need to build components that can perform optimally under a range of different scenarios. We need to ensure we can handle the load and get that data to users without delays, while also maintaining a high level of functionality.\n\nEveryone in our team owns their own projects from beginning to end - from finding out what's needed and proposing a design to implementation and follow up. Each member of\u00a0our\u00a0team has a voice in shaping the future of our platform, and\u00a0we're looking for\u00a0individuals\u00a0who can offer new ideas and help drive our platform forward. We work directly with other teams and with our users, and every member of\u00a0our\u00a0team\u00a0has the opportunity\u00a0to\u00a0build relationships with our users and with developer from other teams.\u00a0\n\nIf you're an engineer who thrives on challenging work,\u00a0and is passionate about learning new technologies, we'd love to hear from you.\n\nWhat we offer\n\nA dynamic work environment where the focus is on getting things done efficiently instead of working long hours every day\nA flat management structure, where everyone's voice is valued\nHands-on experience in the most exciting part of the financial industry\nCompetitive salary and discretionary performance-related bonus.\n\nAll information provided will be treated in strict confidence and used solely for recruitment purposes.\nDue to the high number of responses that we receive, we are only able to respond to successful applicants.", "employment_types": ["Full Time", "Permanent"], "selling_points": ["design wireframes, user journeys", "develop pixel perfect UI", "deliver design consistency"], "locations": ["Not Specified"], "categories": ["Design", "Multi-media", "E-commerce", "Product Management / Business Analyst", "Information Technology (IT)", "UI/UX Designer"], "post_time": "2022-01-10T02:26:15Z", "salary": {"currency": null, "max": null, "min": null, "period": "monthly", "term": null}, "salary_visible": false, "title_keywords": ["designer"], "responsibilities": ["management", "ideas", "maintaining", "data", "teams", "implementation", "design", "ui"], "requirements": {"degrees": [], "majors": [], "languages": [], "language_level": [], "hard_skills": ["react", "typescript", "code", "processing", "c#"], "soft_skills": ["passionate about", "unique", "learning"], "languages_combined": []}, "experience_required": {"duration": [], "field": []}}, {"job_id": "100003009034509", "location_code": "hk", "company": "Reel Fintech Limited", "job_title": "UI/UX Designer", "description": "Responsibilities:\n\nSupport the entire application lifecycle (concept, design, deployment, testing, implementation, enhancement, and maintenance)\nResponsible for full lifecycle of web-based business solutions\nEngage in both front-end and back-end development\nDeliver beautiful interfaces that improve user experience\nTroubleshoot and debug to optimize\u00a0the app\u00a0performance\n\nRequirements:\n\nDegree/Higher Diploma in Computer Science, Computer Engineering or equivalent disciplines\nDemonstrable experience in web development and data visualisation (e.g. GitHub projects, degree coursework, UI/UX design portfolio on Codepen or JSFiddle)\nUnderstanding of at least one Python web framework (Django, Flask)\nProficiency in at least one JavaScript framework (React.js or Vue.js)\nWorking experience with Git version control\nAbility to learn new technologies and integrate them effectively into the platform\nKnowledge about AWS, Azure or other cloud technology is an advantage\nGood analytical, problem solving, communication and presentation skills\nGood sense of UI / UX design is a plus\n\nInterested parties, please send full resume with last & expected salary and date of available by clicking \u2018Apply Now\u2019.\u00a0 All information received will be kept in strict confidential and only for recruitment purpose.", "employment_types": ["Full Time", "Permanent"], "selling_points": ["Website and mobile app user interface designs", "Graphic and digital design for banner", "Work with project and development team"], "locations": ["Tsim Sha Tsui"], "categories": ["Information Technology (IT)", "UI/UX Designer"], "post_time": "2022-01-10T03:32:53Z", "salary": {"currency": null, "max": null, "min": null, "period": "monthly", "term": null}, "salary_visible": false, "title_keywords": ["ux designer"], "responsibilities": ["maintenance", "user experience", "implementation", "design", "testing", "troubleshoot"], "requirements": {"degrees": ["diploma", "degree"], "majors": ["computer engineering", "computer science", "design"], "languages": [], "language_level": [], "hard_skills": ["web development", "git", "azure", "plus", "react", "aws", "problem solving", "javascript", "python", "web framework"], "soft_skills": ["problem solving", "presentation skills", "communication"], "languages_combined": []}, "experience_required": {"duration": [], "field": ["development"]}}, {"job_id": "100003009039255", "location_code": "hk", "company": "Capmi Technology Limited", "job_title": "UX/UI Software Developer", "description": "Job Description\n\nSoftware Development will be responsible for the UI and UX design of applications including mobile apps and responsive website. Also, materials for online promotion with our motion capture technology.\n\n*Show us your work. Attach your work in the CV.*\n\nResponsibilities\nResponsible for UI and UX design of applications including mobile apps and responsive website\nUse 3D modelling, texture, mapping and other techniques to create graphics, visual effects, and animations\nDesigning conceptual wireframes, high-fidelity mockups, interaction specifications and pixel-perfect UI for web and app product\nWork independently and also as part of a team with engineers to resolve technical issues and provide solutions to achieve product goals and meet deadlines\nRequirements\nImaginative and Creative\nBachelors Degree in Computer Science / Computer Engineering / in Graphic Design, Multimedia or related disciplines or Equivalent\n1-3 years or more experience in frontend application development and design\nJavaScript and TypeScript (Mainly) /Python/Java/C/C++\nSolid experience in development using NodeJS, React.js, React Native, Material UI, Three.js\nProficiency in relevant design software (Figma, Adobe, etc.)\nKnowledge in modern frontend framework and methodologies\nExperienced in Mobile Apps and Web development\nWill be a plus: Knowledge in 3D graphics, computer vision, and relevant areas\nGreat passion of program development, programming visual and animation\nAre excited to work in a startup environment, not afraid to roll up your sleeves and to be proactive\nWilling to learn, being flexible with can-do attitude\nFresh Graduates are welcomed to apply", "employment_types": ["Full Time"], "selling_points": ["CSS, Javascript, Node.js, ReactJS, React Native", "5-day work, fun and relaxed office environment", "Fresh Graduates are welcomed to apply"], "locations": ["Shatin Area"], "categories": ["Information Technology (IT)", "Software Development", "UI/UX Designer"], "post_time": "2022-01-11T09:11:30Z", "salary": {"currency": null, "max": null, "min": null, "period": "monthly", "term": null}, "salary_visible": false, "title_keywords": ["developer"], "responsibilities": ["graphics", "software", "designing", "website", "design", "provide solutions", "specifications", "animations", "visual", "ui", "online promotion"], "requirements": {"degrees": ["degree"], "majors": ["related disciplines", "graphic design", "computer engineering", "computer science"], "languages": [], "language_level": [], "hard_skills": ["graphics", "java", "web development", "plus", "c++", "react", "mobile", "typescript", "javascript", "multimedia", "c", "react native", "python", "adobe", "programming"], "soft_skills": ["flexible", "creative", "can-do attitude", "willing to learn", "imaginative", "proactive"], "languages_combined": []}, "experience_required": {"duration": ["1-3 years"], "field": ["development", "application development", "design"]}}, {"job_id": "100003009037153", "location_code": "hk", "company": "Centaline Data Technology Limited", "job_title": "UX / UI Designer (5-day work)", "description": "Responsibility:\u00a0\n\nDevelop UI mockups, prototypes that clearly illustrate how sites function and look like (including wireframes)\nIdentify and troubleshoot UX problems (e.g. responsiveness)\nAdvocate for the end user, always seeking ways to improve and innovate\nCreate key visuals\nConduct adjustments based on user feedback\nIllustrating design ideas using storyboards, process flows and sitemaps\nDesigning graphic user interface elements, like menus, tabs and widgets\nAssist in setting up brand guidelines to create layouts that reinforce a brand\u2019s style\n\n\u00a0Qualification:\u00a0\u00a0\n\nDegree in design or related field a plus\n5+ years in digital User Experience and Interface design (Candidate with less experience is also welcomed)\nA portfolio showcasing ideas is a must\nExperience with B2B design and iteration, preferably in an agile development environment\nA user-centric mindset; understand business and user needs\nTeam spirit, strong soft skills to collaborate with various stakeholders\nGood time-management skills\nPrevious experience in financial services, Fintech (blockchain, digital assets) a plus\nCreative, paastionate about new technologies and trends\nStrong communication skills in English, Cantonese, and conversational Mandarin\nCandidates possessing skills in only UI or UX would still be considered\n\nWe offer competitive remuneration package and excellent career prospects to qualified candidates. \u00a0Interested parties please send your\u00a0full\u00a0resumes with present and expected salaries to us.\n\nAll applications will be treated in the strictest confidence and personal data collected will be used for recruitment purposes only.", "employment_types": ["Full Time", "Permanent"], "selling_points": ["Diploma in Web / Multimedia / Graphics design", "Solid exp in Web/App/Multimedia design", "Quaterly Bonus / Medical & Study Allowance, etc"], "locations": ["Tsim Sha Tsui"], "categories": ["Design", "Multi-media", "E-commerce", "Software Development", "Information Technology (IT)", "UI/UX Designer"], "post_time": "2022-01-11T01:55:07Z", "salary": {"currency": null, "max": null, "min": null, "period": "monthly", "term": null}, "salary_visible": false, "title_keywords": ["ui designer"], "responsibilities": ["collaborate with", "management", "key visuals", "ideas", "user experience", "design", "develop", "agile development", "user interface", "create layouts", "communication", "brand guidelines", "troubleshoot", "designing", "ui", "storyboards"], "requirements": {"degrees": ["degree"], "majors": ["design"], "languages": ["cantonese", "english", "mandarin"], "language_level": ["conversational"], "hard_skills": ["blockchain", "plus", "agile"], "soft_skills": ["communication skills", "team spirit", "agile", "troubleshoot", "creative"], "languages_combined": [{"language": "cantonese", "language_level": []}, {"language": "english", "language_level": ["conversational"]}, {"language": "mandarin", "language_level": []}]}, "experience_required": {"duration": ["5+ years"], "field": ["digital", "development", "financial services", "design"]}}, {"job_id": "100003009048074", "location_code": "hk", "company": "Centre for Intelligent Multidimensional Data Analysis Limited", "job_title": "Computer Programmer (Post A) /  Engineer (Post B) / IT Systems Officer (Post C)", "description": "You will:\u00a0\n\nDevelop creative concepts, artworks, design layout, animation for promotional & marketing materials on websites, social media, EDM, etc.\nFrontend related design/development works on other digital platforms such as eDM, webpage\nWork closely with Marketing Team to ensure all outputs are on brand and in line with commercial objectives\n\nYou should have / be:\u00a0\n\n\nCREATIVE MIND with STRONG AESTHETIC SENSE\nDegree holder in Advertising, Creative Media, Graphic Design or related disciplines\n2-3 years\u2019 experience in related area with eCommerce knowledge\nCreative mind with strong aesthetic sense\nProficiency in Adobe Photoshop & Illustrator\nGood knowledge in HTML5, CSS & UI/UX design. Knowledge of related frameworks like bootstrap would be an advantage\nPassionate, self-motivated, responsible, able to work independently but also a great team player\nGood at communicating in English and Cantonese\nCandidate with more experience will be considered as 'Senior Web Designer'\nPortfolio links should be provided in the resume\n\n\u00a0In addition, you will be able to:\u00a0\u00a0\u00a0\n\nEnjoy an attractive and competitive remuneration package\nReceive training and development opportunities\n\nPlease send in your\u00a0full resume, portfolio links and expected salary by \u201cApply Now\u201d.\n\nTo know more about us, please visit our website at\u00a0https://corporate.esdlife.com/\u00a0and\u00a0https://health.esdlife.com/shop/hk/\n\n\nWe are an equal opportunity employer and welcome applications from all qualified candidates. The information provided will be treated in strict confidence and used only for consideration of application for relevant/similar post(s) within the Hutchison Group of Companies.\n\nApplicants not having heard from us within four weeks from the date of this advertisement may consider their application unsuccessful. All personal data of unsuccessful applicants will be destroyed after the recruitment exercise when no longer required.", "employment_types": ["Full Time"], "selling_points": ["18 AL, Medical and Dental Insurance, friendly team", "Programmer, IT Officer, Engineer", "Artificial intelligence & Big Data Analysis"], "locations": ["Shatin Area"], "categories": ["Information Technology (IT)", "IT Management", "Software Development", "UI/UX Designer"], "post_time": "2022-01-14T04:41:39Z", "salary": {"currency": null, "max": null, "min": null, "period": "monthly", "term": null}, "salary_visible": false, "title_keywords": ["officer", "programmer", "engineer"], "responsibilities": ["social media", "advertising", "edm", "graphic design", "website", "design", "recruitment", "marketing materials", "personal data", "develop creative concepts", "ui", "animation"], "requirements": {"degrees": ["degree holder"], "majors": ["related disciplines", "creative media", "graphic design"], "languages": ["cantonese", "english"], "language_level": ["good"], "hard_skills": ["no", "web", "adobe photoshop", "illustrator", "css"], "soft_skills": ["passionate", "self-motivated", "work independently", "confidence", "responsible", "team player", "creative"], "languages_combined": [{"language": "cantonese", "language_level": ["good"]}, {"language": "english", "language_level": ["good"]}]}, "experience_required": {"duration": ["2-3 years"], "field": ["related", "ecommerce", "designer"]}}, {"job_id": "100003009035913", "location_code": "hk", "company": "Hong Kong Digital Asset Ex Limited", "job_title": "UI/UX Designer", "description": "Job Responsibilities:\nMaintain, troubleshoot and develop features on web-based applications.\nWork closely with the QA team and backend developers.\nFollower the requirements and implement creativity from the Product team.\nDeliver quality work under the right schedules.\nJob Requirements:\nGood technical skills in Javascript(ES5/ES6), HTML, CSS.\nFamiliar with MVVM/MVP/MVC frameworks such as Vue/Angular/React will be an advantage.\nKnowledge of frontend system architecture and common design patterns will be an advantage.\nExperience on Vue3.0/Typescript is a big plus.\nSelf-motivated, responsible and a good team player.\nInterested parties, please click \"Apply Now\" for application.\nPersonal data collected will be used for recruitment purpose only.", "employment_types": ["Full Time", "Permanent"], "selling_points": ["UI/UX Design", "Crypto", "Fintech"], "locations": ["Central"], "categories": ["Banking / Finance", "Financial Services", "Design", "Web Designer", "Information Technology (IT)", "UI/UX Designer"], "post_time": "2022-01-10T08:45:43Z", "salary": {"currency": null, "max": null, "min": null, "period": "monthly", "term": null}, "salary_visible": false, "title_keywords": ["ux designer"], "responsibilities": ["schedules", "quality", "develop", "maintain", "troubleshoot"], "requirements": {"degrees": [], "majors": [], "languages": [], "language_level": [], "hard_skills": ["plus", "react", "html", "typescript", "angular", "css"], "soft_skills": ["technical skills", "good team player", "self-motivated", "responsible"], "languages_combined": []}, "experience_required": {"duration": [], "field": []}}, {"job_id": "100003009042608", "location_code": "hk", "company": "ESD Services Limited (ESDlife)", "job_title": "Web Designer", "description": "As the UI/UX Designer of our Design Hub team in Hong Kong, you will advocate for design driven project execution in a stimulating environment to unleash the potential of our business.\n\n\nwork closely with business stakeholders, product owners and business analyst to translate user stories/business requirements into user flows & wireframes\ndesign wireframes, user journeys, UI mock-ups, components and prototypes for our Emma platform or other digital platforms for stakeholders and customers validation\ndevelop pixel perfect UI and adjust design layouts based on user feedback\nidentify design & technical problems and devise elegant human-centred solutions\nensure design consistency within and between AXA digital platforms\nability to collaborate effectively, working in agile delivery teams with developers, other designers, UX researchers, PM, business analyst, product owners and developers\nResponsible for Emma's design deliverable, feature, end to end customer journey\nstrong creative design energy, with effective stakeholder management skills\nadhere to style and branding standards and be detail focused\n\nRequirements:\n\nfluent in Cantonese and English both written and verbally.\nminimum of 6 years relevant experience as a UX/UI designer with strong digital platform experience\nstrong story-telling skills on layout presentation and strong learning attitude\nable to define UX research hypophysis and topics\nable to handle a Mac and the usual tools (Sketch, InVision, Zeplin, Adobe Creative Suite)\nconversant with cross-browser, as well as native and cross-platform mobile design best practice\nproven work portfolio\nexperienced with Agile / iterative project management methodologies\nbasic knowledge on coding and grid system, e.g. html, CSS, react-native, bootstrap\nable to analyze complex problems, propose and implement exceptional solutions\na self-motivated team player who excels in a collaborative environment\nproactive, with a strong sense of personal accountability\nexperience with the China market would be an advantage\nKnowledge or working experience in insurance related field is preferred.", "employment_types": ["Full Time", "Permanent"], "selling_points": [], "locations": ["Hung Hom"], "categories": ["Design", "Web Designer", "Information Technology (IT)", "UI/UX Designer"], "post_time": "2022-01-12T08:09:09Z", "salary": {"currency": null, "max": null, "min": null, "period": "monthly", "term": null}, "salary_visible": false, "title_keywords": ["designer"], "responsibilities": ["collaborate", "management", "mock-ups", "teams", "design", "develop", "digital platform", "project management", "coding", "design layouts", "insurance", "ui"], "requirements": {"degrees": [], "majors": [], "languages": ["cantonese", "english"], "language_level": ["fluent"], "hard_skills": ["creative design", "basic", "agile", "react", "html", "mobile", "project management", "css", "adobe creative suite"], "soft_skills": ["self-motivated", "proactive", "agile", "focused", "responsible", "accountability", "presentation", "collaborative", "project management", "learning", "team player", "creative", "driven"], "languages_combined": [{"language": "cantonese", "language_level": ["fluent"]}, {"language": "english", "language_level": ["fluent"]}]}, "experience_required": {"duration": ["minimum of 6 years"], "field": ["designer", "related", "relevant experience", "digital", "insurance"]}}, {"job_id": "100003008993902", "location_code": "hk", "company": "Tranthink Technology Service Limited", "job_title": "Web Frontend Programmer", "description": "Responsibilities:\n\nResponsive Web UI implementation for E-learning platform (mainly in JavaScript)\nUpdate dynamic client content via AJAX query and JSON respond\nDesign and build JS reusable Classes object with decent interface\nClearly state inline comments and overall documentation\nPerform other ad-hoc projects and tasks as assigned\nRequirements:\n\nDegree in Computer Science, Information System or other related disciplines, qualification in\u00a0Artificial intelligence will be an advantage\n2 years or above web development related experience\nProficiency in HTML5, CSS, JavaScript (DOM, Classes, and Regular Expression)\nExperience in responsive and mobile-first web design development\nHigh diploma level in Computer Science, or other related disciplines\nFamiliar Photoshop, Illustrator, Dreamweaver with good sense in graphic design will be an advantage\nGood command in written English and/or Chinese\nWe offer 5-day-work week with competitive remuneration packages to the right candidate.\u00a0 Interested parties please send your CV with EXPECTED SALARY through the below application procedure.\n\n(Personal data will be used by Chow Sang Sang (CSS) for recruitment only.\u00a0 CSS may refer suitable applications to other vacancies within CSS and its associated companies.\u00a0 We will retain unsuccessful applications for a maximum period of 24 months)", "employment_types": ["Full Time", "Permanent"], "selling_points": ["5 Days Work, Double Pay, Medical Insurance", "Flexible working hours, Free snack", "Javascript(ES5/ES6), HTML, CSS"], "locations": ["Lai Chi Kok"], "categories": ["Information Technology (IT)", "Application Specialist - Software", "Software Development", "UI/UX Designer"], "post_time": "2022-01-16T21:50:02Z", "salary": {"currency": null, "max": null, "min": null, "period": "monthly", "term": null}, "salary_visible": false, "title_keywords": ["programmer"], "responsibilities": ["comments", "implementation", "design", "documentation", "ad-hoc projects", "ui"], "requirements": {"degrees": ["high diploma", "degree"], "majors": ["related disciplines", "computer science"], "languages": ["english", "chinese"], "language_level": ["good command"], "hard_skills": ["web design", "web development", "information system", "illustrator", "mobile", "javascript", "dreamweaver", "css", "photoshop"], "soft_skills": ["responsive"], "languages_combined": [{"language": "english", "language_level": ["good command"]}, {"language": "chinese", "language_level": ["good command"]}]}, "experience_required": {"duration": ["2 years"], "field": ["related", "development", "design"]}}, {"job_id": "100003009053016", "location_code": "hk", "company": "JFE Consulting Limited", "job_title": "Systems Specialist (Unix/Linux)", "description": "The Senior UX/UI Designer will oversee a team to develop and deliver UX/UI solutions for designated client projects, ensuring quality experiences consistently.\n\nResponsibilities:\n\n- Build and foster relationships with designated clients, ensuring their understanding of the role of User Experience\n\n- Work with Account and Production team to enhance quality, productivity, and profitability of designated account\n\n- Participate in workshops alongside Strategy to help define user needs, gather clients' requirements and input to prioritise functionality and content to address client and user needs\n\n- Collaborate with multidiscipline team members including design, copy and tech to provide creative solutions that address the client and user needs\n\n- Create written and visual documentation outlining user experience requirements for client and internal teams, including user journeys, site maps, user-flows, wireframes, functional specifications and prototypes\n\n- Communicate user requirements to clients and internal team\n\n- Work with Account & Production team to define the user experience approach and timings for account projects and ensure all deliverables and deadlines are met within budget\n\n- Validate assumptions by conducting user testing where appropriate\n\n- Keep up-to-date with user experience trends and share this knowledge with the team\n\nRequirements:\n\n- At least 4 years previous experience in a User Experience role\n\n- Experience overseeing junior team members\n\n- Proven experience of developing User Experience deliverables for a range of projects from discrete Campaigns and apps through to large-scale ongoing platform projects\n\n- Extensive proven knowledge of user-centred design methodologies and tools\n\n- Extensive proven knowledge of user experience visualization and prototyping tools such as Omnigraffle\n\n- Ability to define and employ user-centred methodology definition on small to large-scale projects\n\n- Ability to accurately provide timings for deliverables\n\n- Hands-on ability to visualise and document User Experience concepts and detailed specifications\n\n- Excellent communication and presentation skills, with ability to communicate user experience recommendations in a clear, concise manner.\n\nApplication:\n\nDon't miss out on this great opportunity to work in a world-class digital agency! To apply, click 'Apply Now' to submit your resume to us.\n\nAny questions, please feel free to contact Yvonne Hung at +852 3907 3977 or email your inquiry to yhung@morganmckinley.com.", "employment_types": ["Full Time", "Permanent"], "selling_points": ["Unix/Linux", "Holder of RHCE, LPI or SAN certification", "Technical project implementation"], "locations": ["Quarry Bay"], "categories": ["Information Technology (IT)", "Support", "Others", "UI/UX Designer"], "post_time": "2022-01-17T05:04:58Z", "salary": {"currency": null, "max": null, "min": null, "period": "monthly", "term": null}, "salary_visible": false, "title_keywords": ["specialist"], "responsibilities": ["collaborate with", "budget", "quality", "user experience", "design", "teams", "testing", "specifications", "visual", "documentation"], "requirements": {"degrees": [], "majors": [], "languages": [], "language_level": [], "hard_skills": ["small"], "soft_skills": ["world-class", "communication", "clear", "hands-on", "presentation skills", "extensive", "detailed"], "languages_combined": []}, "experience_required": {"duration": ["at least 4 years"], "field": ["developing", "team"]}}, {"job_id": "100003009049609", "location_code": "hk", "company": "Chow Sang Sang Holdings International Limited", "job_title": "Executive - Web Development", "description": "Job Responsibilities:\n\nWebsite and mobile app user interface designs;\nProduce all kind of graphic and digital design for banner and other presentation materials;\nWork with project and development team; and\nManage any ad-hoc tasks or projects as assigned.\n\nJob Requirements:\n\nHigher Diploma or above in digital design, multimedia design, graphic communications or related field;\nMinimum 3-4 years' of working experience in design related field, preferable with\u00a0exposure in mobile / web product / financial or banking products;\nHands on skills in Adobe Photoshop, Illustrator, Sketch;\nKnowledge of UI design principles and techniques;\nDetail minded with can-do attitude and ability to multitask;\nHigh level of initiative and ability to work under tight deadlines in a fast-paced, team-oriented environment; and\nProvide online portfolio link in addition to resume.", "employment_types": ["Full Time", "Permanent"], "selling_points": ["Web UI implementation for E-learning platform", "Update dynamic client content via AJAX query", "2 yrs or above web development related experience"], "locations": ["Cheung Sha Wan"], "categories": ["Design", "Web Designer", "Information Technology (IT)", "Application Specialist - Software", "UI/UX Designer"], "post_time": "2022-01-14T08:57:43Z", "salary": {"currency": null, "max": null, "min": null, "period": "monthly", "term": null}, "salary_visible": false, "title_keywords": ["executive"], "responsibilities": ["mobile app", "ad-hoc tasks", "website", "design", "user interface"], "requirements": {"degrees": ["higher diploma or above"], "majors": ["multimedia design", "communications", "design"], "languages": [], "language_level": [], "hard_skills": ["web", "adobe photoshop", "illustrator", "mobile", "multimedia"], "soft_skills": ["ability to multitask", "hands on", "initiative", "can-do attitude"], "languages_combined": []}, "experience_required": {"duration": ["minimum 3-4 years"], "field": ["related", "banking", "design", "financial"]}}, {"job_id": "100003009051234", "location_code": "hk", "company": "Achiever Technology Limited", "job_title": ".Net Programmer/ Programmer Trainee", "description": "As a UX/UI Designer, you will advocate for design-driven project execution in a stimulating environment to unleash the potential of our business.\n\nWork closely with business stakeholders, product owners, and business analysts, understand the business metrics and be able to translate the company\u2019s and business\u2019 goals.\nDesign wireframes, user journeys, UI mock-ups, components and prototypes or other digital forms for stakeholders and customers\u2019 validation.\nDevelop pixel perfect UI and adjust design layouts based on user and stakeholders\u2019 feedback.\nAbility to collaborate effectively, working in agile delivery teams with developers, PM, business analysts, product owners, and business owners.\nContribute to usability testing planning activities and be able to understand usability testing insights.\n\nDuties & Responsibilities\n\nYou\u2019re highly flexible, and able to refocus your output and direction based on emerging business trends and creative decisions.\nUnderstand users\u2019 thinking and design user-friendly UX/UI flows.\nDesign from concept to completion all facets of the User Interface including: mock-ups, wireframes, and prototypes to communicate interactions and features effectively.\nReview existing products and perform product testing and improvement reports.\nWorking with the development team to identify, estimate, schedule and track UX/UI tasks.\u00a0\n\nExperience & Requirements\n\nMinimum 2-3 years\u2019 experience focusing on UX and UI. (Candidates with less experience can also be considered)\nHigher Diploma or above in Mobile App development / Web / Multimedia / Graphic design or related fields.\nStrong sense of responsive design, UX/UI and technology trends.\nExpert with UI tools, Figma, Sketch, or similar.\nAbility to conduct user research, A/B testing and iteration usability testing.\nKnowledge of any scripting languages.\nUnderstanding of \u201cfreemium\u201d business model, including customer acquisition, retention, and monetization", "employment_types": ["Full Time", "Permanent"], "selling_points": [], "locations": ["Lai Chi Kok"], "categories": ["Information Technology (IT)", "Application Specialist - Software", "Software Development", "UI/UX Designer"], "post_time": "2022-01-15T05:29:40Z", "salary": {"currency": null, "max": null, "min": null, "period": "monthly", "term": null}, "salary_visible": false, "title_keywords": ["programmer", "trainee"], "responsibilities": ["review", "mock-ups", "design", "testing", "user interface", "reports", "schedule", "ui"], "requirements": {"degrees": ["higher diploma or above"], "majors": ["graphic design"], "languages": [], "language_level": [], "hard_skills": ["mobile", "multimedia", "web"], "soft_skills": ["responsive"], "languages_combined": []}, "experience_required": {"duration": ["minimum 2-3 years"], "field": []}}, {"job_id": "100003009043959", "location_code": "hk", "company": "Aecom Asia Company Limited", "job_title": "RPA Solution Analyst / Developer [Robotic Process Automation]", "description": "To cope with our continuous growth and business expansion, we are looking for energetic and high calibre of candidates to join.\u00a0\n\nDuties:\n\n\nResponsible for user interface design of system, mobile apps and websites\nBanner, image retouch and other graphics design\n\n\nRequirements:\n\n\nDiploma holder or above in Web / Multimedia / Graphics design or related discipline;\nAt least\u00a03 years\u2019 solid experience in Web/App/Multimedia design;\nProficiency in graphics & web design tools such as Adobe Photoshop,\u00a0 Illustrator, XD or Sketch;\nKnowledge of design, prototyping tools and usability best practices in wire frames and prototypes;\nStrong sense on responsive design, UI/UX and technology trends;\nKnowledge of iOS & Android app official UI guideline;\nKnowledge of JavaScript, HTML5, CSS3\u00a0is a plus;\nResponsible, detail-minded, have good interpersonal and communication skills;\nImmediately available is preferable;\nCandidates with more experience will be considered as Senior UX/UI Designer\n\nAt least\u00a03 portfolios provided\u00a0for review is a must\n\nInterested parties, please send full resume with CURRENT & EXPECTED SALARY to Centaline Data Technology Limited.", "employment_types": ["Full Time", "Permanent"], "selling_points": ["Fresh Graduates will also be considered", "Experienced in UiPath", "Interested in process automation or AI application"], "locations": ["Shatin Area"], "categories": ["Information Technology (IT)", "Application Specialist - Software", "Software Development", "UI/UX Designer"], "post_time": "2022-01-13T02:36:21Z", "salary": {"currency": null, "max": null, "min": null, "period": "monthly", "term": null}, "salary_visible": false, "title_keywords": ["developer", "solution analyst"], "responsibilities": ["graphics", "user interface", "design"], "requirements": {"degrees": ["diploma holder"], "majors": ["design"], "languages": [], "language_level": [], "hard_skills": ["graphics", "web design", "plus", "web", "adobe photoshop", "illustrator", "javascript", "multimedia", "android"], "soft_skills": ["detail-minded", "communication skills", "responsible", "responsive", "interpersonal"], "languages_combined": []}, "experience_required": {"duration": ["at least 3 years"], "field": ["designer", "design"]}}, {"job_id": "100003009031979", "location_code": "hk", "company": "Viu", "job_title": "UX/UI Designer, Hong Kong", "description": "Your Mission:\u00a0\n\nIt is NOT a solely individual contributing role: you will work closely with the TEAM. Start your adventure with us! We're looking for you to join our 5-star team!\n\nWhat you'll do:\n\n-\u00a0 Create user-centered designs by understanding business requirements, and user feedback\n\n- Create sitemap, user flows, wireframes, prototypes ,and mockups for web and mobile applications\n\n- Translate requirements into style guides, design systems, design patterns, and attractive user interfaces\n\n- Illustrate design ideas using storyboards, process flows, and sitemaps\n\n- Participate in graphic design for marketing materials, website, presentation and social media pages etc\n\n- Participate in user research, usage metrics, and usability findings into design in order to enhance user experience\n\n- Responsible for the creation, design, development, and maintenance of the corporate websites of individual businesses\n\n- Create graphic and animated design for our website, social media, and branding assets for marketing campaigns\n\n- Apply best practices to increase page speed & ratings, and SEO ranking\n\nWhat you\u2019ll enjoy:\n\n- Fun workspace\n\n- Work experience in a multinational startup company\n\n- Open-minded and eager to learn new technologies\n\nWhat you'll need:\n\n- Diploma holder or above in web, graphic design, or related field\n\n- At least 2 years of relevant working experience\n\n- Knowledge in SEO, CSS, HTML5, Java and WordPress\n\n- Knowledge in Adobe Photoshop, Fireworks, Illustrator, Flash, Dreamweaver\n\n- Experience in video shooting and production is an advantage (not a must)\n\n- Strong sense of responsibility, able to work independently to meet project deadlines\n\n- Knowledge in a website or mobile application development\n\n- Strong experience in responsive, mobile, and app design\n\n- Crypto knowledge is definitely an advantage\n\n- Interest in Sports is a must\n\n- Candidate with more experiences would also be considered as Senior UX/UI Designer\n\n- Candidates please attached your portfolio when you submit your application\n\nWhat we offer attractive remuneration package with fringe benefits to right candidates:\n\n- Casual working environment\n\n- Gym facilities / workout classes\n\n- Snackbar (Snacks and drinks)\n\n- Medical insurance covered", "employment_types": ["Full Time"], "selling_points": [], "locations": ["Kowloon Bay"], "categories": ["Design", "Multi-media", "Web Designer", "Information Technology (IT)", "UI/UX Designer"], "post_time": "2022-01-07T10:04:14Z", "salary": {"currency": null, "max": null, "min": null, "period": null, "term": null}, "salary_visible": false, "title_keywords": ["ui designer"], "responsibilities": ["social media", "ideas", "seo", "maintenance", "graphic design", "systems", "website", "design", "user experience", "video shooting", "marketing campaigns", "marketing materials", "application development", "ui", "storyboards"], "requirements": {"degrees": ["diploma holder"], "majors": ["graphic design"], "languages": [], "language_level": [], "hard_skills": ["java", "seo", "crypto", "maintenance", "web", "fun", "adobe photoshop", "illustrator", "mobile", "wordpress", "flash", "dreamweaver", "css"], "soft_skills": ["work independently", "responsible", "sense of responsibility", "open-minded", "eager to learn", "responsive", "presentation"], "languages_combined": []}, "experience_required": {"duration": ["at least 2 years"], "field": ["research", "designer", "relevant working experience", "design", "video shooting"]}}, {"job_id": "100003009031527", "location_code": "hk", "company": "Chow Sang Sang Holdings International Limited", "job_title": "UX/UI Manager - Omnichannel Applications", "description": "Your New Role\n\nDesign and refine beautiful user interfaces, scalable UI components and related interactions\nDeep understanding of design systems architecture\u00a0\nConfident and able to communicate design decisions and constructive feedback\nCreate meaningful and elegant interactive interfaces that exceed the needs of our targeted audience\nMaintain a high level of user interface quality\nImprove the look and feel of the overall product\nExecute all visual design stages from sketches to interactive prototypes to final hand-off to Engineers teams\nDesign scalable UI elements and components and all related interactions\nSpecify and define guidelines to the related UI components and interactions\nPartner and support UX and UI designers to provide the best visual and interactive experiences\nEnsure visual consistency across features, products, branding and other related assets\n\nWhat makes you succeed\n\nTo be successful in your new position, it is essential to have the following skills:\n\nBS or MS degree in Human-Computer Interaction, Interaction Design, or other related areas\n3+ years of demonstrable experience in designing User Interface and Interaction Design\nA strong portfolio demonstrating deep interaction and great visual design skills\nKnowledgeable about usability and visual design principles, composition, colours psychology, accessibility\nHigh ability to quickly produce a wide range of user interfaces and user interaction concepts\u00a0\nHigh ability to rationalise and build components of a design system\nKnowledgeable about product stories, journey maps, storyboards and personas\nAbility to give and receive constructive feedback\nAbility to communicate and explain design decisions\nGreat sense of aesthetics is critical\nExcellent communication skill and presentation skills in English, Mandarin and Cantonese\nUsing Figma, Principles, Miro and other tools to design and share artifacts\nMotion design skills is a plus\nSelf-motivated, detail-oriented and deadline-oriented\nPassionate about emerging design trends and interactive experiences\u00a0\nEager to learn and share with the design team", "employment_types": ["Full Time", "Permanent"], "selling_points": ["Deliver consumer centric application for all brand", "Conduct a variety of UX research", "Minimum 6 years of experience in UI/UX Design"], "locations": ["Cheung Sha Wan"], "categories": ["Design", "Graphics", "Web Designer", "Information Technology (IT)", "UI/UX Designer"], "post_time": "2022-01-07T09:25:16Z", "salary": {"currency": null, "max": null, "min": null, "period": "monthly", "term": null}, "salary_visible": false, "title_keywords": ["manager"], "responsibilities": ["guidelines", "systems", "quality", "teams", "design", "sketches", "bs", "user interface", "designing", "maintain", "communication", "visual", "design trends", "architecture", "ui", "storyboards"], "requirements": {"degrees": ["degree"], "majors": ["design"], "languages": ["cantonese", "english", "mandarin"], "language_level": ["excellent"], "hard_skills": ["visual design", "plus"], "soft_skills": ["confident", "self-motivated", "communication skill", "deep", "detail-oriented", "eager to learn", "presentation skills", "constructive", "passionate about"], "languages_combined": [{"language": "cantonese", "language_level": ["excellent"]}, {"language": "english", "language_level": ["excellent"]}, {"language": "mandarin", "language_level": ["excellent"]}]}, "experience_required": {"duration": ["3+ years"], "field": ["design"]}}, {"job_id": "100003009031925", "location_code": "hk", "company": "CBX Software Limited", "job_title": "Product Designer (UI focus) (Five-day work)", "description": "Looking for a passionate service designer who has experience/ able to lead a team.\n\nYour new company\nThis is a well known bank who is expanding their Service Design teams in Hong Kong.\n\nYour new role\n\nProvide support, training and coaching on design thinking and design methodologies/standards to teams across the organization\nGood stakeholder management\nPlan, manage and execute the design research activities (strategy, user research, secondary research etc.) collaboratively with other team members\nFacilitate workshops to identify and redesign priority customer journeys with different stakeholders from across the organization\nAnalyze and synthetize research data to identify and generate meaningful insights and behavioral patterns that inform the new user experience\nTranslate insights and research into user stories, wireframes, mockups and prototypes that allow the development and validation of user experiences\n\n\nWhat you'll need to succeed\n\n\nBachelor's or equivalent degree required; and a current online portfolio\nWith 5+ years experience in service design roles; success driving mindset changes in organizations and Manager titles or equivalent\nWell verse in skills like Sketch, Photoshop and prototyping tools (e.g., Flinto, Principle, Axure RP)\nDigital experience and proficiency with ethnographic research techniques, usability testing, UX/UI, rapid prototyping and agile method\nStrong customer-experienced oriented mindset to rapidly identify core needs of customer\nExcellent written and verbal communication skills to collaborate with stakeholders, coach internal teams, and run research activities and workshops\n\n\nWhat you need to do now\nIf you're interested in this role, click \"apply now\" or for more information and a confidential discussion this role or to find out more about IT and Digital opportunities contact Carina Choi at +852-2230-7437 or Carina.Choi@hays.com.hk Follow Hays for the most up-to-date career advice and insights on the world of work: https://www.linkedin.com/company/hays", "employment_types": ["Full Time", "Permanent"], "selling_points": ["Convert requirements into Wireframes & Visual UI", "Participate full design lifecycle with UX desiger", "Fluent in Figma, Adobe PS/AI/XD and Sketch"], "locations": ["Lai Chi Kok"], "categories": ["Design", "Multi-media", "Web Designer", "Information Technology (IT)", "UI/UX Designer"], "post_time": "2022-01-07T09:58:39Z", "salary": {"currency": null, "max": null, "min": null, "period": "monthly", "term": null}, "salary_visible": false, "title_keywords": ["product designer"], "responsibilities": ["collaborate with", "provide support", "management", "data", "teams", "user experience", "design", "testing", "communication", "lead a team", "contact", "plan", "ui"], "requirements": {"degrees": ["degree", "bachelor"], "majors": [], "languages": [], "language_level": [], "hard_skills": ["inform", "agile", "customer journeys", "rapid", "workshops", "photoshop"], "soft_skills": ["passionate", "communication skills", "interested in", "agile"], "languages_combined": []}, "experience_required": {"duration": ["5+ years"], "field": ["research", "designer", "development", "design", "testing", "digital", "team"]}}, {"job_id": "100003009028438", "location_code": "hk", "company": "Page Group Hong Kong", "job_title": "Senior UX/UI Designer- Top insurance group", "description": "Responsibilities\n\nConvert requirements into Wireframes & Visual UI\nMaintain consist brand image in the form of UI\nParticipate on full design lifecycle - user research (primary and secondary), ideation, design execution and user testing.\nCollaborate with UX designer, product managers, engineers, stakeholders and teams to deliver end-to-end product experiences\nWork closely with product, data science and engineering to ensure design execution is in line with strategy, vision and timeframes\nCollaborate and present ideas, concepts, and design solutions to peers and stakeholders in a clear, confident and persuasive manner.\nIdentify and troubleshoot UI/UX problems and constantly seek to improve the user\u2019s experience of the platform.\nParticipate on co-creation and ideation with other stakeholders on various initiatives, collaborate and contribute to strategies to support overall company growth.\nWork together with the design team to define and improve new and existing processes to support structured and efficient product design.\nGetting things done in a fast-paced environment.\n\nRequirements\n\nBachelor\u2019s degree in a relevant field\nAt least 4 years experience in visual UI / digital design\nStrong background in visual design and passionate about digital design\nExperience of creating and using Design systems- animation skills would be beneficial.\nA blend of product, UX and UI\nStrong team player, self-motivated, enthusiastic and fast learner\nFluent in using tools such as Figma, Adobe PS/AI/XD and Sketch\nFluency in both Cantonese and English is essential\nA self-starter who is energetic, pragmatic and welcoming of new challenges\n\nBenefits\n\nFriendly and collaborative work environment with diverse and inclusive international teams\nExcellent career development opportunities\nAttractive remuneration packages\nOn-job training\n5 minute walk to MTR from office\nMonthly fun activities\nMedical insurances\nPerformance bonuses\nReferral bonuses\nEmployment visa sponsorship (if required)\n\nInterested parties, please apply together with resume, stating current and expected salary, and send it via\u00a0APPLY NOW.\n\nWe are an equal opportunity employer and welcome applications from all qualified candidates. All information provided by applicants will be treated in strictest confidence and handled confidentially for recruitment-related purposes within the company and our associated company. Applicants may be considered for other suitable positions within the company over a one-year period, after which their personal data will be destroyed.", "employment_types": ["Full Time", "Contract"], "selling_points": ["International working environment", "Great collaborative culture and people", "Positive work life balance"], "locations": ["Not Specified"], "categories": ["Information Technology (IT)", "Application Specialist - Software", "Technical Writing", "UI/UX Designer"], "post_time": "2022-01-07T02:18:39Z", "salary": {"currency": null, "max": null, "min": null, "period": "monthly", "term": null}, "salary_visible": false, "title_keywords": ["ui designer"], "responsibilities": ["collaborate with", "collaborate", "ideas", "data", "design solutions", "teams", "design", "testing", "maintain", "product design", "troubleshoot", "visual", "ui"], "requirements": {"degrees": ["degree", "bachelor"], "majors": [], "languages": ["cantonese", "english"], "language_level": ["fluency"], "hard_skills": ["visual design", "adobe", "ai"], "soft_skills": ["self-motivated", "enthusiastic", "team player", "energetic", "fast learner", "passionate about"], "languages_combined": [{"language": "cantonese", "language_level": ["fluency"]}, {"language": "english", "language_level": ["fluency"]}]}, "experience_required": {"duration": ["at least 4 years"], "field": ["digital", "design"]}}, {"job_id": "100003008754190", "location_code": "hk", "company": "New iMedia Solutions Limited", "job_title": "Programmer / Software Developer (Welcome Fresh Graduate) | Support AI Project", "description": "\u00a0Responsibilities :\nDesign product flows and journeys that optimize user experience based on the acquired insights as well as business and technical requirements.\u00a0\nFollow through product from concept development, artwork design\u00a0and production\nExecute creative solutions to meet the client needs\nDevelop pixel-perfect UI components that are ready for production and ensure design consistency across different app and web platforms.\nDevelop pixel-perfect UI components that are ready for production and ensure design consistency across different app and web platforms.\nCreate compelling user interface designs for Mobile apps and\nwebsites\n\n\u00a0Requirements :\n\nDiploma or above in Graphic / Multimedia Design or related\u00a0disciplines\n3+ years of UX and UI design experience and have experience designing for large customer-facing platforms.\nUnderstanding of UI/UX design methodologies on mobile and desktop platform\nStrong skilled in Figma, Adobe, Sketch, etc.\n\nStrong self-motivation to start and run the work individually and with the teams.\n\nGood understanding of interaction, journeys and prototyping is an advantage\nSelf-motivated, willing to learn, and a strong sense of responsibility and commitment\nExperienced in the Website interface will be an advantag\nMore experience shall be considered as a Senior\u00a0UI / UX Designer", "employment_types": ["Full Time"], "selling_points": ["Welcome Fresh Grad. Young & Energetic Workplace", "Flexi-Hour, Monthly Early-off, 12 AL+2 Extra Leave", "Solid Knowledge in Java or PHP and REST API"], "locations": ["Kwun Tong"], "categories": ["Information Technology (IT)", "IT Project Management / Team Lead", "Software Development", "UI/UX Designer"], "post_time": "2022-01-11T02:41:59Z", "salary": {"currency": null, "max": null, "min": null, "period": "monthly", "term": null}, "salary_visible": false, "title_keywords": ["developer", "programmer"], "responsibilities": ["user experience", "design", "develop", "user interface", "ui"], "requirements": {"degrees": ["diploma or above"], "majors": ["multimedia design", "related disciplines"], "languages": [], "language_level": [], "hard_skills": ["mobile", "adobe", "multimedia"], "soft_skills": ["self-motivated", "self-motivation", "willing to learn", "sense of responsibility"], "languages_combined": []}, "experience_required": {"duration": ["3+ years"], "field": ["designer", "design"]}}, {"job_id": "100003009047393", "location_code": "hk", "company": "Aerosim (HK) Limited, HKSTP Acceleration Programme", "job_title": "Software Developer", "description": "Responsible for full-stack development of multiple application.\nDesign, develop, implement, test and maintain apps and websites application with reusable modules, automated testing, and continuous deployment.\nApply strong analytical and technical skills in application problems, system design and user experience.\nWork closely with internal teams or vendors in driving business goals.\nParticipate in any ad hoc tasks as assigned.\n\nQualification\n\n\nHigh Diploma or above in computer science, information technology, creative media, multimedia, interface design or related disciplines.\n2+ years of hands-on experience in app and web application development.\nFamiliar with UI / UX design and coding, e.g. Java / .NET / Angular JS/React JS/NodeJS, HTML/HTML5, CSS, JavaScript, XML, SQL.\nGood command of written and spoken English & Chinese.\nStrong proven problem-solving and communication skills.\nSelf-driven, motivated, well-organized, goal-oriented, positive thinking and able to work independently.", "employment_types": ["Full Time"], "selling_points": ["Develop and maintain native iOS mobile app", "Maintain and update corporate website", "Degree in Computer Science, Information Technology"], "locations": ["Shatin Area"], "categories": ["Information Technology (IT)", "Software Development", "Others", "UI/UX Designer"], "post_time": "2022-01-14T02:59:04Z", "salary": {"currency": null, "max": null, "min": null, "period": "monthly", "term": null}, "salary_visible": false, "title_keywords": ["developer"], "responsibilities": ["business goals", "teams", "user experience", "design", "testing", "develop", "ad hoc tasks", "coding", "maintain", "system design", "communication", "application development", "ui"], "requirements": {"degrees": ["high diploma or above"], "majors": ["creative media", "design", "information technology", "related disciplines", "computer science"], "languages": ["english", "chinese"], "language_level": ["good command"], "hard_skills": ["java", "web application development", "react", "problem-solving", "html", "sql", "goal", "system design", "javascript", "multimedia", "deployment", "angular", "css"], "soft_skills": ["communication skills", "work independently", "responsible", "problem-solving", "well-organized", "positive thinking", "hands-on", "motivated", "technical skills", "creative", "driven"], "languages_combined": [{"language": "english", "language_level": ["good command"]}, {"language": "chinese", "language_level": ["good command"]}]}, "experience_required": {"duration": ["2+ years"], "field": ["application development", "system design", "analytical"]}}, {"job_id": "100003009025431", "location_code": "hk", "company": "Osmium Consulting Group Limited", "job_title": "UI / UX Designer", "description": "We are looking for programmers\u00a0who will be assigned to\u00a0work in Government/ public sector.\u00a0\u00a0\n\nPost 1\n\nWorking location: North Point\n\nJob Description\n\nTo continuously provide support to in-house web Geographical Information Systems (GIS) applications and mobile map apps\nTo provide helpdesk service to handle public enquires\nTo provide first line help service to users and perform associated help desk activities using tools provided, if any and carry out on-site inspection and take recovery action according to prescribed procedures;\nTo fulfil logging and administrative reporting requirements and assist in preparing statistics and reports; and\nTo perform any other duties assigned by supervisor\n\nJob Requirement\n\nGrade E/ Level 2 or above in five subjects including Chinese Language and English Language in HKCEE/ HKDSEE\nBe familiar with the use of computer in Microsoft Windows 10 Operating System and use of Microsoft Office Professional software;\nExperience in Adobe Illustrator and website maintenance\nHave solid working experience in handling public enquires and complaint\nHave good verbal/written and interpersonal communication skills in both Chinese and English\n\nPost 2\n\nWorking location: Wanchai and Yau Ma Tei\n\nJob Description\n\nTo provide web design and support on various systems.\nGraphic and animation design and web development\nReports Checking\nAssist in system and application testing\nData entry (Both English and Chinese input)\nMaintain inventory records\nProvide on-call support for urgent production system incidents during non-office hours\nAny other duties appointed by the supervisors\n\nJob Requirement\n\nDiploma Holder in Design or equivalent is a mandatory\nWorking experience on web development & maintenance using HTML, Adobe Photoshop, Adobe Illustrator and Adobe Premiere is a must\nAble to handle general office duties\nGood typing skill and Chinese character processing\nGood command of both written & spoken English & Chinese\n\nTo apply for this role, please click the\u00a0\u201cApply Now\u201d\u00a0below or send your full resume by MS word format.\nOnly shortlisted candidate will be notified.\n\nPersonal data collected by job applicants will be kept in strict confidence and used for recruitment purpose only", "employment_types": ["Full Time"], "selling_points": ["UX UI Designer | In House | Rare Opportunity", "5 Days Work | Bouns | Med", "Work From Home"], "locations": ["Not Specified"], "categories": ["Media & Advertising", "Creative / Design", "Design", "Web Designer", "Information Technology (IT)", "UI/UX Designer"], "post_time": "2022-01-06T04:30:15Z", "salary": {"currency": null, "max": null, "min": null, "period": "monthly", "term": null}, "salary_visible": false, "title_keywords": ["ux designer"], "responsibilities": ["reporting", "provide support", "any other duties", "systems", "procedures", "site inspection", "reports"], "requirements": {"degrees": ["diploma holder"], "majors": ["design"], "languages": ["english", "chinese"], "language_level": ["good command", "good"], "hard_skills": ["chinese input", "web design", "web development", "maintenance", "microsoft office", "adobe photoshop", "typing", "html", "adobe illustrator", "windows 10", "adobe premiere", "processing", "ms word"], "soft_skills": ["communication skills", "confidence", "interpersonal"], "languages_combined": [{"language": "english", "language_level": ["good command", "good", "good"]}, {"language": "chinese", "language_level": ["good command", "good", "good", "good"]}]}, "experience_required": {"duration": [], "field": ["development", "maintenance"]}}, {"job_id": "100003009024560", "location_code": "hk", "company": "Prenetics Limited", "job_title": "UX/UI Designer", "description": "Job Responsibilities\n- Responsible for UI and UX design for applications including mobile apps, responsive website, console/dashboard.\n- Contribute new ideas, translate concepts into user-friendly design.\n- Identify and troubleshoot UX problems;\n- Create user flow with details of all possible user scenarios;\n- Follow up the development schedule with Project Manager and Developers;\n- Work with Development Team and Designers to deliver the best UX and beautiful UI.\n- Create pixel detailed graphics such as icons, banners, gif animation etc;\n- Prepare necessary graphic materials for marketing purpose;\n\u00a0\u00a0 \u00a0\nJob Requirements\n- Higher Diploma, Associate Degree or Bachelor Degree Holder;\n- Proficient in design software like Adobe Photoshop, XD/Sketch, Illustrator;\n- At least 2-3 years of experience in UI and graphic design;\n- Responsible, Self-starter, Attention to details, Independent and Well-Organized Team Player;\n- Knowledge in HTML, CSS, Javascript is an advantage;\n- Experience in video editing or motion graphics is an advantage;\n- Good command of written and spoken English and Cantonese", "employment_types": ["Full Time"], "selling_points": ["Excellent in Communication", "Experienced in UX/UI design", "Fluent in graphics design"], "locations": ["Quarry Bay"], "categories": ["Information Technology (IT)", "UI/UX Designer"], "post_time": "2022-01-06T01:43:53Z", "salary": {"currency": null, "max": null, "min": null, "period": "monthly", "term": null}, "salary_visible": false, "title_keywords": ["ui designer"], "responsibilities": ["graphics", "ideas", "website", "design", "banners", "troubleshoot", "schedule", "ui", "animation"], "requirements": {"degrees": ["associate degree", "diploma", "bachelor degree holder"], "majors": [], "languages": ["cantonese", "english"], "language_level": ["good command"], "hard_skills": ["graphics", "adobe photoshop", "illustrator", "html", "video editing", "javascript", "css"], "soft_skills": ["independent", "responsible", "well-organized", "attention to details", "team player"], "languages_combined": [{"language": "cantonese", "language_level": ["good command"]}, {"language": "english", "language_level": ["good command"]}]}, "experience_required": {"duration": ["at least 2-3 years"], "field": ["graphic design", "editing", "video"]}}, {"job_id": "100003009024849", "location_code": "hk", "company": "Master Dynamic Limited", "job_title": "UI/UX Designer", "description": "A leading insurance company is currently looking for an ambitious senior UX/UI designer to enhance customer experience and expand business opportunities. The successful candidate will be responsible for translating concepts into wire frames and mock ups that lead to intuitive user experiences.\n\nClient Details\n\nOur client is a one of the largest public listed group with a broad footprint spanning in Asia Pacific. Their service is not limited to insurance and financial services, but also life insurance for individuals and businesses, as well as retirement planning, wealth management services etc. They are looking for a determined candidate with around 5+ years' experience in Mobile app UI/UX design to join their expanding team.\n\nDescription\n\nResponsible for:\n\nWorking closely with development teams to deliver user-friendly digital output\nTranslating concepts into wire frames and mock ups that lead to intuitive user experiences.\nConducting research in the industry's latest trends and technologies\nEffectively communicate design processes, ideas, and solutions to teams and clients.\nDemonstrating high-quality design practices including in all aspect of UI and UX: research, interaction design and visual design\nAsking targeted questions to gather critical data, craft solutions and deliver validated automation solutions to our clients\nDriving ideas from start to finish and advocating for best practices through design architecture and live implementation\nOwning project vision and strategy for an end-to-end design process\n\nProfile\n\nQualifications:\n\nMinimum of 5 years' experience in UI/UX design, preferably in large corporations and involved in projects with many stakeholders from different functions\nBachelor's degree or more than 7 years of working experience\nAble to communicate in a clear, consistent, and transparent manner\nStrong organisational, time management skills\nPassionate in UI/UX and other areas of design and innovations\nStrong experience in desktop and mobile app design\nFamiliar with Agile environment\nGood command of English and Cantonese\n\nJob Offer\n\nWork-Life Balance\nSupportive and collaborative workplace\nGood Learning Platform\nCompetitive Package + Benefits\n\nTo apply online please click the 'Apply' button below. For a confidential discussion about this role please contact Crystal Cheuk on +852 2258 3536", "employment_types": ["Full Time", "Permanent"], "selling_points": ["UI/UX Design", "Graphics & Innovative Design", "Multimedia"], "locations": ["Shatin Area"], "categories": ["Information Technology (IT)", "UI/UX Designer"], "post_time": "2022-01-06T02:42:42Z", "salary": {"currency": null, "max": null, "min": null, "period": "monthly", "term": null}, "salary_visible": false, "title_keywords": ["ux designer"], "responsibilities": ["management", "mobile app", "ideas", "data", "business opportunities", "teams", "quality", "design", "implementation", "architecture", "visual", "insurance", "mock ups", "ui", "planning"], "requirements": {"degrees": ["degree", "bachelor"], "majors": [], "languages": ["cantonese", "english"], "language_level": ["good command"], "hard_skills": ["mobile", "visual design", "agile"], "soft_skills": ["passionate", "supportive", "determined", "responsible", "agile", "time management skills", "collaborative", "clear", "learning", "friendly"], "languages_combined": [{"language": "cantonese", "language_level": ["good command"]}, {"language": "english", "language_level": ["good command"]}]}, "experience_required": {"duration": ["7 years", "5+ years", "minimum of 5 years"], "field": ["designer", "design", "business", "insurance", "team"]}}, {"job_id": "100003009041759", "location_code": "hk", "company": "Taylor Coulter", "job_title": "IT Support/ Application Support - Website maintenance", "description": "The UX Project Manager will oversee designated UX projects end-to-end, responsible for scoping, prioritization, and estimation with the project teams, mitigating risks while ensuring all requirements are met with less than a 10% variance from the agreed estimate.\n\nResponsibilities:\n\nManage a collaborative project team to ensure excellence and quality deliverables, to produce work that is effective and award winning\nDisplay a very good understanding of project methodologies and implement best practice across a full range of projects\nShowcase fantastic adaptability skills and willingness to flex, learn and problem solve for a broad range of new projects\nSupport your line manager to assess all new briefs to ensure they meet business needs; validate the commercial viability and suggest the delivery approach / methodology accordingly\nHelp lead and manage the operational infrastructure of your portfolio. You will demonstrate control to clients and internal stakeholders through strong financial tracking (recovery rate and revenue forecasting), effectively manage change requests / scope creep, develop status and risk documentation templates and team resourcing\nBe a trusted and respected partner to clients. You will continue to add value throughout the project lifecycle by continuing to problem solve and demonstrating a strong level of control and production knowledge to drive creative solutions and maintain excellent client satisfaction rates\nDrive successful team collaboration and bring together multiple specialist disciplines\nActively manage communication tools across your portfolio and mediate against any conflict to ensure productive morale and clear direction on the common objective\nWork with the wider delivery team to improve the delivery process\n\nRequirements:\n\nExamples of having delivered a range of projects that is over HKD1m in value including experience design, innovation, web/app development, content production, strategic and creative development\n3 years+ experience working within a top digital agency (ideally global or regional) or digital communications agency in a production or project management (or equivalent) role\nAn outstanding level of clear documentation (SoW, Budget, Project Plan)\nDemonstrate problem solving abilities and a can-do attitude\nHighly motivated, collaborative and entrepreneurial\nStrong ethos to deliver innovative, creative solutions that have the client's needs at heart\nHighly articulate communication skills (verbal and written) and excellent presentation skills\nAbility to communicate with authority, good negotiation and influencing skills\nUnderstanding of processes, workflows, tools and methodologies, including Agile\nManagement of multidisciplinary teams, including: Strategy, UX, Creative, Copy, Design, Data, Technology and QA\n\nApplication:\n\nDon't miss out on this great opportunity to work in a world-class digital agency! To apply, click 'Apply Now' to submit your resume to us.\n\nAny questions, please feel free to contact Yvonne Hung at +852 3907 3977 or email your inquiry to yhung@morganmckinley.com.", "employment_types": ["Full Time"], "selling_points": ["Post 1: IT Support/ application support", "Post 2: more on Web design & application support", "Familiar in Windows 10 & HTML, Adobe product"], "locations": ["Not Specified"], "categories": ["Information Technology (IT)", "Support", "Software Development", "UI/UX Designer"], "post_time": "2022-01-12T04:19:35Z", "salary": {"currency": null, "max": null, "min": null, "period": "monthly", "term": null}, "salary_visible": false, "title_keywords": ["application support", "it support"], "responsibilities": ["control", "communication tools", "infrastructure", "quality", "develop", "maintain", "documentation", "forecasting", "tracking"], "requirements": {"degrees": [], "majors": [], "languages": [], "language_level": [], "hard_skills": ["agile", "web", "problem solving", "project management", "documentation"], "soft_skills": ["communication skills", "negotiation", "agile", "can-do attitude", "collaborative", "innovative", "clear", "project management", "problem solving", "motivated", "presentation skills", "articulate", "creative", "world-class"], "languages_combined": []}, "experience_required": {"duration": [], "field": ["agency", "development", "design", "project management", "digital"]}}, {"job_id": "100003009033269", "location_code": "hk", "company": "IT Solutions Ltd.", "job_title": "Programmers: Government Departments (T25 Contract), 35K+", "description": "Reports to:\u00a0Digital Experience Manager \u2013 Self Service\nDepartment:\u00a0Customer Experience and Design\n\n\nThe job holder is responsible for supporting the development and management of Cathay Pacific self-services, servicing communication and disruption management on digital channels.\n\nKey Responsibilities\n\n\nWork with design team and technical team to deliver and manage servicing communication initiatives based on the roadmaps\nAssist in designing servicing communication opportunities across digital touchpoints (including but not limited to Email, SMS, Social media channel) that improve customer experience and drive conversion\nCoordinate and collaborate with Commercial, Operation and other Customer Experience teams on new initiatives\nResponsible for end-to-end process from business requirements gathering to design, content and deployment for any servicing communications\nAnalyse product and channel performance and prepare regular performance report that support continuous improvement\nDevelop and execute customer communications through self-services platform to support daily operations and disruptions\nProactively uses data, reporting and industry benchmarks to provide thoughtful analytics, actionable insights and recommendations\n\nRequirements\n\n\nBachelor degree in Business, Computer Science or related subjects\nRelevant working experience preferably in airlines or travel industry\nStrong e-commerce background in driving user engagement and conversion across online channels\nAble to generate insights and understand trends from data analysis\nExcellent problem solving skills - able to identify, analyze and propose solutions to various technical and business issues\nProficient in web development skill (HTML, CSS)\nExperience in agile development preferred\nWorking knowledge of a CRM, Digital Asset/Content Management platform required\nSelf-\u2010motivated, independent, organized and proactive, highly responsive, flexible and adaptable when working across multiple product teams\n\nApplication deadline: 27 January 2022\n\n\nCathay Pacific is an Equal Opportunities Employer. Personal data provided by job applicants will be used strictly in accordance with our personal data policy and for recruitment purposes only. Candidates not notified within eight weeks may consider their application unsuccessful. All related information will be kept in our file for up to 24 months. A copy of our Personal Information Collection Statement will be provided upon request by contacting our Data Protection Officer.\n\nPlease note that with effect from 1 December 2021, all employees must be vaccinated in order to access Cathay City and all other Cathay Group Company premises in Hong Kong. Consideration will be given to those who are unable to get vaccinated for valid medical reasons.", "employment_types": ["Full Time", "Contract"], "selling_points": ["T-25, CP, Contract Programmer (T25)", "Government Departments", "$35,250 per mth, 10 days annual leave, 5 days work"], "locations": ["Not Specified"], "categories": ["Information Technology (IT)", "Software Development", "Network & System", "UI/UX Designer"], "post_time": "2022-01-09T03:11:08Z", "salary": {"currency": null, "max": null, "min": null, "period": "monthly", "term": null}, "salary_visible": false, "title_keywords": [], "responsibilities": ["collaborate with", "social media", "reporting", "data", "teams", "design", "develop", "communication", "coordinate", "daily operations", "designing", "report", "analyse"], "requirements": {"degrees": ["degree", "bachelor"], "majors": ["business", "computer science"], "languages": [], "language_level": [], "hard_skills": ["web development", "agile", "e-commerce", "analysis", "html", "airlines", "css", "problem solving skills"], "soft_skills": ["flexible", "organized", "independent", "agile", "adaptable", "problem solving skills", "proactive", "responsive"], "languages_combined": []}, "experience_required": {"duration": [], "field": ["development", "relevant working experience"]}}, {"job_id": "100003009022310", "location_code": "hk", "company": "Ahsay Systems Corporation Limited", "job_title": "UX/UI Graphics Designer", "description": "You will enjoy our attractive benefits:\n\nCompetitive remuneration package\u00a0\nPerformance Bonus\u00a0\nMedical Insurance\u00a0\n5-day work per week\u00a0\nFlexi-working hour\u00a0\nGeneral Holiday, Annual Leave, Family Care Leave and Anniversary Leave\u00a0\nCasual wear in office\u00a0\nFriendly working environment\n\nThe Job\n\nAct as both front-end and back-end developer to cooperate with designers and other stakeholders to design, implement, test and document the web based applications and services;\nDevelop trendy features and user interfaces from wireframe models;\nEnsure the best performance and user experience of the application, e.g. UAT, bug fixing and web speed;\nProvide technical support to users;\nTake up projects and other duties as assigned by supervisor;\nEngage in AI Project;\n\nThe Person\n\nBachelor Degree in Computer Science / Information Technology or related discipline;\n1 year hands-on internship experience in web application development and/or project experience;\nSolid knowledge in Java or PHP and REST API;\nDatabase systems' knowledge in MySQL or MSSQL or Oracle;\nKnowledge in Python, Tensorflow, AI, React / Angular, JavaScript, CSS and HTML is an advantage;\nExperience in Python and machine learning programming languages is a plus;\nExperience in common machine learning or deep learning model is a plus\n\nPlease send your application with full resume as well as portfolio stating\u00a0your present and expected salary\u00a0to the Company by clicking\u00a0on the\u00a0\"Apply now\".\u00a0Please also quote the\u00a0reference number\u00a0of the applied position in the subject field.", "employment_types": ["Full Time"], "selling_points": ["UX/UI design for mobile apps, responsive website", "Fast track of promotion opportunities", "Working location : Lai Chi Kok"], "locations": ["Lai Chi Kok"], "categories": ["Information Technology (IT)", "UI/UX Designer"], "post_time": "2022-01-05T05:23:47Z", "salary": {"currency": null, "max": null, "min": null, "period": "monthly", "term": null}, "salary_visible": false, "title_keywords": ["designer"], "responsibilities": [], "requirements": {"degrees": [], "majors": [], "languages": [], "language_level": [], "hard_skills": [], "soft_skills": [], "languages_combined": []}, "experience_required": {"duration": [], "field": []}}, {"job_id": "100003009043431", "location_code": "hk", "company": "Cathay Pacific Airways Ltd", "job_title": "Digital Experience Executive - Travel Service", "description": "Key Responsibilities\n\nConduct the global product features design on all platforms to maximise the organic performance and usage\nConduct the behaviour data analysis and the user researches to enhance the user journeys and improve the funnel conversion\nWork closely with the Product / UX/UI / Data Teams to optimize every touchpoint from awareness to winback and unconditional scenarios for high value personas and segments with leveraging analytics insight and data models\nCollaborate with sales and marketing teams to provide the product / digital solutions and strengthen the framework for penetration, retention and monetisation strategy\nCreate and improve design system guidelines and benchmarks to measure the product features and UX quality for the continuous improvement plan.\nTranslate the requirements into epic, user story, sketches, flow diagrams, wireframes, prototypes that lead to intuitive user experiences\n\nRequirements:\n\nExcellent communication skill and presentation skills in English, Mandarin and Cantonese\nBS or MS degree in Human-Computer Interaction, Interaction Design, or other related areas\nAt least 5 years of user design experience and managing products in the digital industry\nStrong portfolio demonstrating proven user-centred design (UCD), planning and conducting user research, user testing, A/B testing, rapid prototyping, heuristic analysis, usability and accessibility concerns.\nIn-depth knowledge across UX design skills and experience in using the digital optimisation tools for experiments and hypothesis testing\nProficiency in Figma, Miro or other popular UI/UX design tools\nKnowledge in designing platform including modular architecture design, data analytics and visual design\nDigital-savvy and knowledgeable on the latest digital trends preferred\nAggressive, self-motivated with excellent communication and presentation skills\nExcellent communication skill and presentation skills in English, Mandarin and Cantonese\nCandidates with less experience will be considered as UX Designer\n\nWe offer attractive and competitive salary and benefits, an exciting work environment and excellent career development opportunities.\u00a0If you have the desire for an exciting and rewarding career, please send us your resume,\u00a0stating your present and expected salary to Human Resources Department by post, fax or clicking \"Apply Now\":\n\nPost:\u00a0\u00a0 \u00a0\u00a06/F, Goldin Financial Global Centre, 17 Kai Cheung Road, Kowloon Bay\u00a0\n\nFax:\u00a0\u00a0\u00a0\u00a0 (852) 2827 8322\u00a0\u00a0\n\nFor more information on other job opportunities of PCCW, please visit our website at\u00a0<http://www.pccw.com/Careers/Job+Opportunities+&+Application/Current+Opportunities?language=en_US>\n\nPCCW is an equal opportunity employer and welcomes applications from all qualified candidates. Information provided will be treated in strict confidence and will only be used for recruitment-related purposes. Personal data provided by job applicants will be used strictly in accordance with the employer\u2019s privacy statement\u00a0(www.pccw.com/privacy-statement/index.page), a copy of which will be provided immediately upon request.", "employment_types": ["Full Time", "Permanent"], "selling_points": ["Minimum 3 years of relevant experiences", "Strong e-commerce background", "Travel Benefits, 5-day work, Medical Benefits"], "locations": ["Lantau Island"], "categories": ["Information Technology (IT)", "Software Development", "E-commerce", "Product Management / Business Analyst", "UI/UX Designer"], "post_time": "2022-01-13T01:38:36Z", "salary": {"currency": null, "max": null, "min": null, "period": "monthly", "term": null}, "salary_visible": false, "title_keywords": ["digital experience executive"], "responsibilities": ["collaborate with", "data", "guidelines", "teams", "quality", "design", "sketches", "data analysis", "plan", "ui"], "requirements": {"degrees": ["degree"], "majors": ["design"], "languages": ["cantonese", "english", "mandarin"], "language_level": ["excellent"], "hard_skills": ["visual design", "data analytics", "analysis", "rapid"], "soft_skills": ["communication", "presentation skills", "communication skill", "self-motivated"], "languages_combined": [{"language": "cantonese", "language_level": ["excellent", "excellent"]}, {"language": "english", "language_level": ["excellent", "excellent"]}, {"language": "mandarin", "language_level": ["excellent", "excellent"]}]}, "experience_required": {"duration": ["at least 5 years"], "field": ["designer", "design", "testing", "digital industry", "digital"]}}, {"job_id": "100003009031978", "location_code": "hk", "company": "Viu", "job_title": "Senior UX/UI Designer", "description": "Molecule financial\u00a0is a HONG KONG Home-grown fintech platform. We are looking for a UXUI designer to be a part of our star team. You will be bringing new visual elements into our application and creating an extraordinary\u00a0experience for the fintech world.\n\nResponsibilities:\n\nDesign graphic user interface elements\nIllustrate design ideas process flows and sitemaps or mock up\nIdentify and troubleshoot UX problems\nEnhance user experience by adjusting layouts based on users\u2019 feedback\nDevelop UI mock-ups and prototypes that clearly illustrate how sites function and look like\n\nRequirements:\n\n1-2 years of demonstrated experience in creating and implementing UXUI design\nUnderstanding of UI/UX design methodologies on mobile and desktop platform\nProficient with relevant design software ( such as Figma, Adobe Photoshop, illustrator and sketch etc)\nCollaborate closely with senior UI/UX designer, product team and technical team to create the best user experience\nMulti-tasking and time-management skills, with the ability to prioritise tasks\nExcellent collaboration and communication skills\nStrong sense of ownership and eager to learn\n\nPlease send us your\u00a0detailed resume with\u00a0current and expected salary,\u00a0earliest availability\u00a0and your project portfolio by clicking 'Apply Now'.\u00a0 \u00a0\n\nData collected will be used for recruitment purpose only.\u00a0", "employment_types": ["Full Time"], "selling_points": [], "locations": ["Kowloon Bay"], "categories": ["Information Technology (IT)", "Others", "UI/UX Designer"], "post_time": "2022-01-07T10:04:13Z", "salary": {"currency": null, "max": null, "min": null, "period": null, "term": null}, "salary_visible": false, "title_keywords": ["ui designer"], "responsibilities": ["ideas", "mock-ups", "user experience", "design", "develop", "user interface", "troubleshoot", "ui"], "requirements": {"degrees": [], "majors": [], "languages": [], "language_level": [], "hard_skills": ["mobile", "adobe photoshop", "illustrator"], "soft_skills": ["communication skills", "prioritise", "eager to learn", "multi-tasking", "detailed"], "languages_combined": []}, "experience_required": {"duration": ["1-2 years"], "field": ["designer", "design", "team"]}}, {"job_id": "100003009025241", "location_code": "hk", "company": "StockViva", "job_title": "Junior UIUX Designer (Fintech)", "description": "Founded in 2014, Prenetics is a major global diagnostics and genetic testing company with the mission to bring health closer to millions of people globally and decentralize healthcare by making the three pillars \u2014 Prevention, Diagnostics and Personalized Care \u2014 comprehensive and accessible to anyone, at anytime and anywhere. Prenetics is led by visionary entrepreneur, Danny Yeung, with a team of over 800 employees and operations across 9 locations, including United Kingdom, Hong Kong, India, South Africa, and Southeast Asia. Prenetics develops consumer genetic testing and early colorectal cancer screening; provides COVID-19 testing, rapid point of care and at-home diagnostic testing and medical genetic testing.\n\nMost recently, Prenetics made international headlines to become the first Unicorn in Hong Kong to publicly list on the Nasdaq via merger with 2021 Adrian Cheng's Artisan Acquisition Corp, valuing Prenetics at approximately US $1.7b.\n\nResponsibilities\n\nFundamentals.\u00a0You conceptualise, iterate, and execute on thoughtful and comprehensive designs that drive delightful experiences for our users.\nCommunicate.\u00a0You engage cross functional stakeholders and communicate designs and experiences at varying level of fidelity, from sketches on paper to pixel-perfect wireframes.\nUsability.\u00a0You research,study, and conduct market analysis to explore the many different approaches to improve user experience.\nCollaboration.\u00a0You work closely with design, product, marketing, and engineering to ensure final product reflects design vision.\nOrganisation.\u00a0You develop and maintain product design library for both existing and new products.\n\nRequirements\n\nExperience.\u00a0You are experienced in UX/UI design across multiple platforms (print, web, mobile).\nGraphics Chops.\u00a0You are fully fluent in graphics design.\nPortfolio.\u00a0You maintain an online portfolio which demonstrates your experience creating great end-to-end, user-centered experiences across print, web and mobile platforms.\nTraits.\u00a0You are highly organised, possess extreme attention to detail, and have a keen sense for aesthetics, including layout, grid system, color usage, and typography.\nAdaptability.\u00a0You are flexible, can multi-task, and are able to deal with ambiguity and changes intrinsic to the business as Prenetics scales.\nCollaboration.\u00a0You enjoy working in a collaborative team and working directly with Product Managers and developers for implementation of designs.\nCommunication.\u00a0You communicate clearly and thoughtfully and possess the ability to articulate product flows to non-designers.\nTools.\u00a0You are proficient designing and prototyping with a variety of tools such as Adobe XD, Sketch, Invision, Photoshop, Illustrator, InDesign.\n\nOur DNA is P-R-E-N-E-T-I-C-S. See what each word of our company name means:\n\nPassion\n\nYou love what you do and accomplish amazing result\nYou spread positivity, bring enthusiasm to work and inspire team members\nYou drive team toward specific goals, even when they seem unlikely or difficult\n\nResilience\n\nYou embrace changes and be able to drive through uncertainty, ambiguity and uncomfortable situations\nYou bounce back quickly from setbacks and challenges\nYou are persistent and determined to achieve the desired outcome\n\nEmpowerment\n\nYou trust others to play their positions well like an elite sports team\nYou foster a strong team spirit while encouraging others to take initiatives and risks\nYou create a space to allow team to grow and hold each other accountable\n\niNtegrity\n\nYou are trustworthy and lead by example\nYou are consistent in your message and action all the times\nYou deliver what you have promised\n\nEpic\n\nYou challenge your own comfort zone and always outperform yourself\nYou make meaningful and amazing impact to the world\nYou dare to take risks and you move fast\n\nTransparency\n\nYou are completely honest and committed to giving candid feedbacks, no matter how challenging it might be\nYou share ideas, knowledge and skills that empower others and create access to information with the wider team\nYou share wins and failures openly\n\nIngenuity\n\nYou make sound judgement and come up with solutions that are creative and smart. Copy when feasible\nYou challenge the status quo and question things that could be done differently for better. Modify the wheel if you can\u2019t change it\nYou think outside of the box and make value-based innovation\n\nCommunications\n\nYou articulate your thoughts and ideas effectively and respectfully\nYou know your audience and talk in a way they want to be told\nYou make sure communications happens, no matter where you are\n\nSelflessness\n\nYou put the needs of others before one's own and find ways in helping other to succeed\nYou focus on team wins than personal wins and share credits\nYou act in the company's best interest\nWe are Prenetics, our people make us who we are.", "employment_types": ["Full Time"], "selling_points": ["Market leading financial social platform", "Creative fintech start-up environment", "Free snacks and drinks"], "locations": ["Lai Chi Kok"], "categories": ["Design", "Graphics", "Web Designer", "Information Technology (IT)", "UI/UX Designer"], "post_time": "2022-01-06T10:00:05Z", "salary": {"currency": null, "max": null, "min": null, "period": "monthly", "term": null}, "salary_visible": false, "title_keywords": ["designer", "junior"], "responsibilities": ["user experience", "sketches", "develop", "design", "market analysis", "maintain", "product design"], "requirements": {"degrees": [], "majors": [], "languages": [], "language_level": [], "hard_skills": ["graphics", "no", "web", "adobe xd", "indesign", "illustrator", "word", "mobile", "make", "c", "r", "focus", "photoshop"], "soft_skills": ["team spirit", "trustworthy", "enjoy working", "persistent", "collaborative", "communication", "articulate", "focus", "determined", "keen", "integrity", "committed", "adaptability", "honest", "creative", "attention to detail", "flexible", "multi-task", "accountable", "organised"], "languages_combined": []}, "experience_required": {"duration": [], "field": ["print"]}}, {"job_id": "100003009025910", "location_code": "hk", "company": "MegaHub Limited", "job_title": "UI / UX Designer", "description": "Our mission: \"Connecting people by one APP\"\n\nAs a young and energetic start-up focusing on e-commerce platform services, iHK places its focus on the \u201cFood+Fun\u201d strategy and firstly takes \u201ceating\u201d as the core of its businesses in 2022. To strive for continuous improvement on both user experience and service quality, we are looking for talented UI Designers to grow our business with us.\n\nResponsibilities\n\nUnderstand users\u2019\u00a0thinking and design user-friendly UX/UI flows\nDesign from concept to completion all facets of the UI including wireframes, mock-ups, and prototypes\nFlexible, multi-task, handle ad hoc tasks and projects when required\nDesign/develop mobile App and Website with a good sense of user experience and creativity\nCollaborate closely with senior UI/UX designer, project management team, and developers to iterate on the design artwork to deliver the best user experience\n\nRequirements\n\nDegree/Higher Diploma holder in Web, Multimedia and Graphic Design or related disciplines\nMinimum 1-year relevant working experience in UI/UX design\nUp-to-date with the latest UI trends, techniques, and technologies\nProficiency in relevant design software (such as Figma, Adobe CC, etc.)\nKnowledge of UI/UX design work and skills in HTML/CSS/JavaScript is a plus\nProactive, creative, independent, strong sense of integrity and able to work under pressure to meet deadlines;\nStrong presentation skills with good verbal skills in Cantonese and Mandarin\nExperience in developing user-friendly UI for the local life service platform industry would be an advantage", "employment_types": ["Full Time"], "selling_points": ["Fin-tech Co./ 5-day work/ Flexible work & lunch hr", "Young & energetic Co./ Joining bonus/ Warm culture", "UI UX Web design/ Developing wire-frames & flows"], "locations": ["Wan Chai"], "categories": ["Design", "Industrial / Product", "Web Designer", "Information Technology (IT)", "UI/UX Designer"], "post_time": "2022-01-06T06:45:32Z", "salary": {"currency": null, "max": null, "min": null, "period": "monthly", "term": null}, "salary_visible": false, "title_keywords": ["ux designer"], "responsibilities": ["collaborate", "mobile app", "mock-ups", "ad hoc tasks", "website", "design", "develop", "user experience", "project management", "ui"], "requirements": {"degrees": ["degree", "higher diploma holder"], "majors": ["related disciplines", "graphic design"], "languages": ["cantonese", "mandarin"], "language_level": ["good"], "hard_skills": ["plus", "web", "html", "javascript", "multimedia", "adobe cc", "css"], "soft_skills": ["independent", "creative", "integrity", "presentation skills", "friendly", "meet deadlines", "proactive", "work under pressure"], "languages_combined": [{"language": "cantonese", "language_level": ["good"]}, {"language": "mandarin", "language_level": ["good"]}]}, "experience_required": {"duration": ["minimum 1-year"], "field": ["relevant working experience", "design", "developing"]}}, {"job_id": "100003009024132", "location_code": "hk", "company": "\u661f\u6cb3\u4fe1\u606f\u6280\u8853\u6709\u9650\u516c\u53f8", "job_title": "UI/UX Designer", "description": "Responsibilities:\n\nDeveloping wire-frames and user flows based on user needs.\nCollaborating with product management and engineering to define and implement innovative solutions for the product direction, visuals and experience.\nExecuting all visual design stages from concept to final hand-off to engineering.\n\nRequirements:\n\nMinimum of 5 years as a UX Designer, UI Designer or similar role.\nDegree in Design or a related field.\nPortfolio of related design projects is a must.\nFamiliarity with interaction design and information architecture.\nHighly proficient with design tools such as Sketch/Figma, InVision, Zeplin, Adobe Creative Suite.\nKnowledge of prototyping.\nPrevious experience in financial services, Fintech (blockchain, digital assets) is a plus.\nKnowledge of HTML/CSS; JavaScript is a plus.\nExcellent communication skills in English and Chinese.\n\nTo know more about us, please visit our website:\nhttps://www.megahubhk.com/\n\nWe offer 5-day work week, flexible working hours and good career development opportunities in a young and dynamic environment.\u00a0 Interested parties, please send your PORTFOLIO, resume and stating your current & expected salary to MegaHub Limited by clicking \"Apply Now\".\n(Personal data collected will be used for recruitment purpose only)\n\n\n\n", "employment_types": ["Full Time", "Permanent"], "selling_points": ["Five-day work week, Bank Holiday, Annual Leave", "Double pay, Salary+Remuneration", "Chances of in-charge UI development from 0-1"], "locations": ["Tsuen Wan Area"], "categories": ["Design", "Graphics", "Web Designer", "Information Technology (IT)", "UI/UX Designer"], "post_time": "2022-01-05T10:59:34Z", "salary": {"currency": null, "max": null, "min": null, "period": "monthly", "term": null}, "salary_visible": false, "title_keywords": ["ux designer"], "responsibilities": ["management", "developing", "design", "executing", "visual"], "requirements": {"degrees": ["degree"], "majors": ["design"], "languages": ["english", "chinese"], "language_level": ["excellent"], "hard_skills": ["blockchain", "plus", "html", "javascript", "css", "adobe creative suite"], "soft_skills": ["communication skills", "creative"], "languages_combined": [{"language": "english", "language_level": ["excellent"]}, {"language": "chinese", "language_level": ["excellent"]}]}, "experience_required": {"duration": [], "field": ["digital", "financial services"]}}, {"job_id": "100003009027752", "location_code": "hk", "company": "The Block Soho Limited", "job_title": "UI / UX DESIGNER", "description": "Responsibilities\n\nResponsible to the UI/UX design of the digital products, taking ideas from product vision to create flow diagrams, storyboards and high-fidelity prototypes.\nWorking closely with the product team and development team, you will produce innovative and intuitive design with high quality to achieve business goal.\nProvide graphics support and innovative design across multimedia for wide range of projects, technologies and devices.\nCreating\u00a0design artifacts for web, tablet and mobile interfaces.\nCreating user-centered designs by understanding business requirements, and user feedback.\nCreating user flows, wireframes, prototypes and mockups.\nTranslating requirements into style guides, design systems, design patterns and attractive user interfaces.\nAny ad-hoc assignments as requested by the supervisor.\n\n\u00a0Requirements\n\nBachelor Degree in Multimedia Design, Multimedia Web Design & Development, Visual Design or related disciplines.\nRelevant knowledge or experience in UI/UX design.\nHands-on working experience in graphic, artwork, and output production design.\nHands-on working experience in UI/UX in corporate level of web portal, mobile app design.\nAbility to multi-task and work under tight timeline.\nA good team player, innovative with strong problem-solving and presentation skills.\nFamiliar with Adobe Illustrator, Adobe Photoshop. Knowledge of video editing is an advantage.\nGood command of both verbal and written English and Chinese.\nImmediate available would be an advantage.\n\nWe offer attractive remuneration with excellent opportunities to the right\u00a0candidate.\u00a0 Interested parties please apply with detailed resume stating present and expected salary, and date of availability to us. All personal information is collected for recruitment purpose solely.", "employment_types": ["Full Time"], "selling_points": ["3 years + UI/UX experience", "Figma, Sketch, IN Vision, Adobe InDesign, etc.", "High degree of autonomy"], "locations": ["Central"], "categories": ["Information Technology (IT)", "UI/UX Designer"], "post_time": "2022-01-06T12:35:08Z", "salary": {"currency": null, "max": null, "min": null, "period": "monthly", "term": null}, "salary_visible": false, "title_keywords": ["ux designer"], "responsibilities": ["graphics support", "ideas", "ad-hoc assignments", "systems", "quality", "design", "ui", "storyboards"], "requirements": {"degrees": ["degree", "bachelor"], "majors": ["multimedia design", "web design", "related disciplines", "design"], "languages": ["english", "chinese"], "language_level": ["good command"], "hard_skills": ["web design", "web", "problem-solving", "adobe photoshop", "adobe illustrator", "video editing", "mobile", "visual design", "multimedia"], "soft_skills": ["good team player", "multi-task", "problem-solving", "hands-on", "presentation skills", "innovative"], "languages_combined": [{"language": "english", "language_level": ["good command"]}, {"language": "chinese", "language_level": ["good command"]}]}, "experience_required": {"duration": [], "field": ["graphic", "design"]}}, {"job_id": "100003009023592", "location_code": "hk", "company": "TuoFan IT Limited", "job_title": "UI / UX Designer", "description": "Duties and Responsibilities\nDesign and construct the user interface for our platform\nCollaborate with product management and engineering to define and implement innovative solutions for the product/platform direction, visuals, and experience\nExecute all visual design stages from concept to final hand-off to engineering\nCreate user-centered designs by understanding business requirements, the voice of the customer, user journeys, customer feedback, and usability findings\nConceptualize original ideas that bring simplicity and user-friendliness to complex design roadblocks\nGenerate an effective range of layouts for all elements of the creative solution (e.g. wireframes, storyboards, user flows, process flows, and site maps)\nProvide direction and feedback to teams on their work to ensure achievement of objectives\nConduct user research and competitor analysis and evaluate user feedback\nEstablish and promote design guidelines, best practices, and standards that consistently scale across platforms\n\nRequirement\n\n3 years or above of UI/UX design experience and a proven track record\nPreferably holding a Bachelor\u2019s degree in Multimedia Design or equivalent\nProficiency in industry tools such as Figma, Sketch, InVision, Adobe InDesign, Illustrator, or comparable design programs\nSolid experience in creating wireframes, storyboards, user flows, process flows, and site maps\nExcellent written and verbal communication skills in English and Chinese.\nSelf-motivated, dedicated with strong problem solving and communications skills, good team player, and can work independently.\nExcellent command in both spoken and written English, Cantonese, and Putonghua\nImmediate available or short notice period is highly preferable", "employment_types": ["Full Time"], "selling_points": [], "locations": ["Tsuen Wan Area"], "categories": ["Information Technology (IT)", "Technical Writing", "Others", "UI/UX Designer"], "post_time": "2022-01-05T09:13:47Z", "salary": {"currency": null, "max": null, "min": null, "period": "monthly", "term": null}, "salary_visible": false, "title_keywords": ["ux designer"], "responsibilities": ["collaborate with", "management", "ideas", "provide direction", "guidelines", "analysis", "teams", "design", "evaluate", "user interface", "visual", "storyboards"], "requirements": {"degrees": ["degree", "bachelor"], "majors": ["multimedia design"], "languages": ["cantonese", "putonghua", "english", "chinese"], "language_level": ["excellent"], "hard_skills": ["problem solving", "illustrator", "adobe indesign", "multimedia"], "soft_skills": ["communication skills", "self-motivated", "work independently", "good team player", "problem solving"], "languages_combined": [{"language": "cantonese", "language_level": ["excellent"]}, {"language": "putonghua", "language_level": ["excellent"]}, {"language": "english", "language_level": ["excellent", "excellent"]}, {"language": "chinese", "language_level": ["excellent"]}]}, "experience_required": {"duration": ["3 years"], "field": ["design"]}}, {"job_id": "100003009020253", "location_code": "hk", "company": "Cornerstone Global Partners", "job_title": "UX/UI Designer (Leading Insurance firm)", "description": "Job Highlights\n2 years+ experience in a UI/UX-related field\nSocial Media, Blockchain, DeFi platform\nYoung & energetic team, innovative startup culture\n\nJob Description\n\nResponsibilities:\n\nMaintain the consistency and sustainability of our visual design system.\nCollaborate with product managers, developers, and cross-functional stakeholders to understand requirements, and provide creative, thoughtful solutions.\nCommunicate concepts with storyboards, wireframes. Guide design and development with high-fidelity phototype.Work with IT team.\n\nRequirements:\n\nMinimum2-year experience in UI/UX-related field, social media experience is an advantage.\nSolid UI design experience on cross platform, familiarity with technical constraints and limitations on Desktop, mobile web, android and IOS.\nProficiency in design tools, Adobe Creative Suite, figma etc.\nPragmatic Thinking.\nGood communication skills.\nSelf-motivated, Excellent problem-solving skills.\n\nInterested parties are invited to send full resume stating contact telephone number, date available, present and expected salary to our recruitment email address.", "employment_types": ["Full Time"], "selling_points": ["Design/develop Mobile and Website UI", "UX/UI Development | Mobile Apps focus", "At least 5 years of relevant experience"], "locations": ["Central & Western Area"], "categories": ["Design", "Industrial / Product", "Web Designer", "Information Technology (IT)", "UI/UX Designer"], "post_time": "2022-01-04T10:17:11Z", "salary": {"currency": null, "max": null, "min": null, "period": "monthly", "term": null}, "salary_visible": false, "title_keywords": ["ui designer"], "responsibilities": ["collaborate with", "design", "maintain", "visual", "storyboards"], "requirements": {"degrees": [], "majors": [], "languages": [], "language_level": [], "hard_skills": ["web", "mobile", "problem-solving skills", "adobe creative suite", "android"], "soft_skills": ["problem-solving skills", "communication skills", "self-motivated", "creative"], "languages_combined": []}, "experience_required": {"duration": [], "field": ["related", "social media", "design"]}}, {"job_id": "100003009040917", "location_code": "hk", "company": "ACT Solutions Ltd.", "job_title": "Analyst Programmer - C#, Java,.NET", "description": "Responsibilities:\n\nFundamentals. You conceptualise, iterate, and execute on thoughtful and comprehensive designs that drive delightful experiences for our users.\nCommunicate. You engage cross functional stakeholders and communicate designs and experiences at varying level of fidelity, from sketches on paper to pixel-perfect wireframes.\nUsability. You research, study, and conduct market analysis to explore the many different approaches to improve user experience.\nCollaboration. You work closely with design, product, marketing, and engineering to ensure final product reflects design vision.\nOrganisation. You develop and maintain product design library for both existing and new products.\n\nWho You Are:\n\n5 years of experience up. You are experienced in UX/UI design across multiple platforms (print, web, mobile).\nGraphics Chops. You are fully fluent in graphics design.\nPortfolio. You maintain an online portfolio which demonstrates your experience creating great end-to-end, user-centered experiences across print, web and mobile platforms.\nTraits. You are highly organised, possess extreme attention to detail, and have a keen sense for aesthetics, including layout, grid system, color usage, and typography.\nAdaptability. You are flexible, can multi-task, and are able to deal with ambiguity and changes intrinsic to the business\nCollaboration. You enjoy working in a collaborative team and working directly with Product Managers and developers for implementation of designs.\nCommunication. You communicate clearly and thoughtfully and possess the ability to articulate product flows to non-designers.\nTools. You are proficient designing and prototyping with a variety of tools such as Adobe XD, Sketch, Invision, Photoshop, Illustrator, InDesign.", "employment_types": ["Full Time", "Permanent"], "selling_points": ["Eager to learn Microsoft new technologies", "Solid Development skills in .Net and C#", "Building application for multi-national companies."], "locations": ["Southern Area"], "categories": ["Information Technology (IT)", "Application Specialist - Software", "Software Development", "UI/UX Designer"], "post_time": "2022-01-12T03:13:12Z", "salary": {"currency": null, "max": null, "min": null, "period": "monthly", "term": null}, "salary_visible": false, "title_keywords": ["analyst programmer"], "responsibilities": ["user experience", "sketches", "develop", "design", "market analysis", "maintain", "product design"], "requirements": {"degrees": [], "majors": [], "languages": [], "language_level": [], "hard_skills": ["graphics", "web", "adobe xd", "indesign", "illustrator", "mobile", "photoshop"], "soft_skills": ["flexible", "multi-task", "keen", "enjoy working", "collaborative", "communication", "adaptability", "attention to detail", "organised", "articulate"], "languages_combined": []}, "experience_required": {"duration": ["5 years"], "field": ["print"]}}, {"job_id": "100003009038694", "location_code": "hk", "company": "AAStocks.com Limited", "job_title": "Business Analyst (5-day work)", "description": "Contract Programmers to work for Government Departments:\n\nT25-CP\n\nResponsibilities:\n\nDevelop, enhance and maintain enterprise application systems\nConduct program testing, system testing and support user acceptance test\nPrepare and maintain program documentation\nHandle users and answer their inquiries\nProvide System support\n\nRequirements:\n\nApplication development experiences of 2 or more years, using software tools such as:\nJAVA, J2EE, WEBSPHERE, XML\nHTML, HTML5\nJavaScript, PHP\nSQL\nC#, C++\nVisual Basic\n.Net, Web Services, Oracle, etc\nCandidates who are not experienced in application development but possess professional experiences in Network or System Support will also be considered\nBachelor Degree, Higher Diploma or Associate Degree in information technology or related disciplines\nCandidates who do not have the above academic qualifications but with 2 extra years of proven relevant IT experience will also be qualified\n\n\nBenefits:\n\n$35,250 per month\n10 days annual leave\n5 days work per week\nComprehensive Medical Insurances\n\n\n\nIf you are interested, please send your resume in MS Word format, specifying your availability, current and expected salaries to:\n\njobs @itsolutions.com.hk\n(Tel: 2866 8676)\n\nor\n\nPlease click the Apply Now button and attach your cv in MS Word Format, specifying your availability, current and expected salaries.\n\n\n\nPersonal data collected will be used for recruitment purposes only.\n\nIT Solutions Ltd.\nSuite 2102\n21/F Lucky Building\n39 Wellington Street\nCentral, Hong Kong\n\n(P.S. We do not process applications from overseas for this position)", "employment_types": ["Full Time", "Permanent"], "selling_points": ["Working closely with Design team", "Provide project rollout presentation", "2+ years\u2019 expin digital product development"], "locations": ["Kwun Tong"], "categories": ["Information Technology (IT)", "IT Project Management / Team Lead", "Product Management / Business Analyst", "UI/UX Designer"], "post_time": "2022-01-11T07:39:00Z", "salary": {"currency": null, "max": null, "min": null, "period": "monthly", "term": null}, "salary_visible": false, "title_keywords": ["business analyst"], "responsibilities": ["testing", "develop", "maintain", "documentation", "application systems"], "requirements": {"degrees": ["associate degree", "diploma", "degree", "bachelor"], "majors": ["related disciplines", "information technology"], "languages": [], "language_level": [], "hard_skills": ["java", "oracle", "c++", "php", "html", "sql", "javascript", "visual basic", "web services", "c#"], "soft_skills": [], "languages_combined": []}, "experience_required": {"duration": [], "field": ["application development", "system support", "it experience"]}}, {"job_id": "100003009034061", "location_code": "hk", "company": "Webs s'up Production Company Limited", "job_title": "Frontend Developer", "description": "Responsibilities\n\nAs a project manager to take care of the overall digital product development (Website, Mobile/Tablet APP, Desktop Applications)\nWorking closely with Design team, Development team and Quality Assurance team for ensuring product/project can be rollout on schedule with good quality and appropriate UI/UX design\nPreparing the functional specification for product development\nProvide project rollout presentation to related parties\nIdentify and troubleshoot product problems\n\nRequirements\n\n2+ years\u2019 experience in digital product development (candidate with less experience will also be considered)\nPassion for customer-centric and aesthetic, pixel perfect design\nDegree in Finance, Information Technology or related field\nGood project management and communication skills\nPlease click \"Apply Now\" to submit your application.\n\nPersonal data collected will be used for recruitment purpose only.", "employment_types": ["Full Time", "Permanent"], "selling_points": ["Competitive salary with attractive Talent Benefits", "Javascript / jQuery / Vue / API integration", "Zurb Foundation / Bootstrap / UIUX principles"], "locations": ["Kowloon Bay"], "categories": ["Information Technology (IT)", "Application Specialist - Software", "Software Development", "UI/UX Designer"], "post_time": "2022-01-10T02:33:25Z", "salary": {"currency": null, "max": null, "min": null, "period": "monthly", "term": null}, "salary_visible": false, "title_keywords": ["developer"], "responsibilities": ["quality", "website", "design", "schedule", "troubleshoot", "ui"], "requirements": {"degrees": ["degree"], "majors": ["finance", "information technology"], "languages": [], "language_level": [], "hard_skills": ["project management"], "soft_skills": ["communication skills", "project management", "passion for"], "languages_combined": []}, "experience_required": {"duration": ["2+ years"], "field": ["digital", "product development"]}}, {"job_id": "100003009038695", "location_code": "hk", "company": "AAStocks.com Limited", "job_title": "Assistant Business Analyst", "description": "Responsibilities\nAssist Manager to evaluate areas for improvement and develop/ implement digit product development projects\nPerform product research for supporting digital product development (Website, Mobile/Tablet APP, Desktop Applications)\nWorking closely with Design team, Development team and Quality Assurance team for ensuring product/project can be rollout on schedule with good quality and appropriate UI/UX design\nPreparing the functional specification for product development\nProvide project rollout presentation to related parties\nGather user comments and feedbacks\nIdentify and troubleshoot product problems\nRequirements\n1+ years\u2019 experience in digital product development preferred (candidate with less experience will also be considered)\nPassion for customer-centric and aesthetic, pixel perfect design\nDegree in Finance or Information Technology or related field\nGood project management and communication skills\nDetail-minded and good team player", "employment_types": ["Full Time", "Permanent"], "selling_points": ["Identify and troubleshoot product problems", "Degree in Finance or Information Technology", "Fresh graduates are welcomed"], "locations": ["Kwun Tong"], "categories": ["Information Technology (IT)", "IT Project Management / Team Lead", "Product Management / Business Analyst", "UI/UX Designer"], "post_time": "2022-01-11T07:39:00Z", "salary": {"currency": null, "max": null, "min": null, "period": "monthly", "term": null}, "salary_visible": false, "title_keywords": ["business analyst", "assistant"], "responsibilities": ["comments", "quality", "website", "design", "develop", "evaluate", "schedule", "troubleshoot", "ui"], "requirements": {"degrees": ["degree"], "majors": ["finance", "information technology"], "languages": [], "language_level": [], "hard_skills": ["project management"], "soft_skills": ["detail-minded", "communication skills", "good team player", "passion for", "project management"], "languages_combined": []}, "experience_required": {"duration": ["1+ years"], "field": ["digital", "product development"]}}, {"job_id": "100003009029156", "location_code": "hk", "company": "Money Plaza Hong Kong Limited", "job_title": "Web app Developer/ Programmer", "description": "Responsible for design, development, implementation, testing & tuning and bug fixing of web cloud applications\nCollaborate with project team to new cloud solutions developments\nConduct UAT, Program tunning and stability analysis\nNew cloud technologies implementation and tests\nLeading Junior Staff in program development\n\nREQUIREMENTS\n\nHigh Diploma or above in Computer Science, Computer Engineering or related disciplines\nExperience in frontend & backend programming skills is a must (such as PHP, JavaScript, MySQL and commonly used libraries)\nExperience in cloud programming framework & security\nKnowledge on Amazon Web Services (AWS) is preferred (such as EC2, S3, Route53, RDS, Lamda, Athena, etc)\nEager to learn new things and technologies\nFresh graduate or with less experience will be considered as Junior Web Developer\n\nInterested parties, please click\u00a0\"Apply Now\"\u00a0to apply for this position.\u00a0All information collected will be kept in strict confidence and will be used for recruitment purpose only.", "employment_types": ["Full Time", "Part Time", "Permanent", "Contract", "Freelance"], "selling_points": ["Passionate in a highly growth industry", "Flexible employment terms - project based possible", "Great Compensation with performance bonus"], "locations": ["Tsuen Wan Area"], "categories": ["Information Technology (IT)", "Application Specialist - Software", "E-commerce", "Software Development", "UI/UX Designer"], "post_time": "2022-01-10T02:50:26Z", "salary": {"currency": null, "max": null, "min": null, "period": "monthly", "term": null}, "salary_visible": false, "title_keywords": ["developer", "programmer"], "responsibilities": ["collaborate with", "uat", "analysis", "implementation", "design", "testing"], "requirements": {"degrees": ["high diploma or above", "fresh graduate"], "majors": ["related disciplines", "computer engineering", "computer science"], "languages": [], "language_level": [], "hard_skills": ["web", "php", "analysis", "amazon web services (aws)", "javascript", "programming", "s3"], "soft_skills": ["eager to learn", "responsible"], "languages_combined": []}, "experience_required": {"duration": [], "field": ["developer", "security", "programming"]}}, {"job_id": "100003009034896", "location_code": "hk", "company": "O-Dynamic Visual Studio Company Limited", "job_title": "Senior Web Developer / Web Developer", "description": "Job duties\n\nCollaborate with peer designers, product managers, engineers, business stakeholders and other teams to deliver end-to-end UX and VD experiences.\nInitiate design process, from concept development, UI & VD design, prototype to production with guidance from peers and colleagues.\nDesign user-focused wireframes, hi-fidelity mockups, interaction models, specifications, style guides and prototypes that illustrate a deep understanding of the user's needs and business requirements.\nUse wireframes, prototypes, style guides, user flows, mocks to communicate one's interaction and design ideas\nPresent one's designs to a group and conduct design validation exercises for feedback to improve the design and overall client experience.\n\nRequirements\n\n3+ years of experience as a user experience designer, professional experience in advertising, design, interaction designer, Web/graphic design or similar roles.\nDiploma graduate or above in graphic design or related disciplines such as Industrial Design, Communication Arts, Information Design, human-computer interaction (HCI).\nA portfolio demonstrating a clean visual aesthetic and a strong eye for detail.\nGood command in English and interpersonal skills. Cantonese and/or Mandarin-speaking skill is a plus.\n\nIf this job isn't quite right for you, but you know someone who would be great at this role, why not take advantage of our referral scheme? We offer HKD1000 in Apple gift cards for every referred candidate who we place in a role. Terms & Conditions Apply. https://www.ambition.com.hk/refer-a-friend", "employment_types": ["Full Time"], "selling_points": [], "locations": ["Wong Tai Sin Area"], "categories": ["Information Technology (IT)", "Application Specialist - Software", "Software Development", "UI/UX Designer"], "post_time": "2022-01-10T04:33:39Z", "salary": {"currency": null, "max": null, "min": null, "period": "monthly", "term": null}, "salary_visible": false, "title_keywords": ["developer"], "responsibilities": ["collaborate with", "guidance", "ideas", "teams", "design", "specifications", "ui"], "requirements": {"degrees": ["diploma"], "majors": ["related disciplines", "graphic design", "design"], "languages": ["cantonese", "english", "mandarin"], "language_level": ["good command"], "hard_skills": ["clean", "plus", "scheme", "web"], "soft_skills": ["communication", "interpersonal skills", "eye for detail"], "languages_combined": [{"language": "cantonese", "language_level": []}, {"language": "english", "language_level": ["good command"]}, {"language": "mandarin", "language_level": []}]}, "experience_required": {"duration": ["3+ years"], "field": ["graphic design", "advertising", "designer", "design"]}}, {"job_id": "100003009034435", "location_code": "hk", "company": "Azeus Systems Ltd", "job_title": "Android Mobile App Developer", "description": "Responsibilities:\n\nDevelop systems/functions according to the customers' requirements.\nPerform project implementation including documentation, coding, testing,\u00a0 and user support.\n\n\u00a0Requirements:\n\nEnergetic, self-motivated, a good team player, eager to learn new technologies including D365, AI, Cloud, Power BI, Power Apps etc.\nHands-on development experience\u00a0in .NET and\u00a0 C#.\n\n\u00a0Benefits:\n\nFive-day work\nAttractive bonus and compensation package\nMedical", "employment_types": ["Full Time"], "selling_points": [], "locations": ["North Point"], "categories": ["Information Technology (IT)", "Application Specialist - Software", "Software Development", "UI/UX Designer"], "post_time": "2022-01-10T03:23:11Z", "salary": {"currency": null, "max": null, "min": null, "period": "monthly", "term": null}, "salary_visible": false, "title_keywords": ["developer"], "responsibilities": ["systems", "implementation", "coding", "develop", "testing", "documentation"], "requirements": {"degrees": [], "majors": [], "languages": [], "language_level": [], "hard_skills": ["bi", "c#", "ai"], "soft_skills": ["good team player", "self-motivated", "eager to learn", "hands-on", "energetic"], "languages_combined": []}, "experience_required": {"duration": [], "field": ["development"]}}, {"job_id": "100003009024983", "location_code": "hk", "company": "Pathsight Limited", "job_title": "(Senior) UI/UX Designer", "description": "We\u2019re Webs S\u2019 up, a digital consultancy with a singular mission \u2013 We Enhance Engagement.\u00a0\n\nJoin us to become a Webs S\u2019 up family member!\n\nYou will be entitled to a competitive salary and attractive staff benefits including:\n\nAnnual leave, paid sick leave, compensation leave, marriage leave, maternity leave, paternity leave and compassionate leave\nFive-day work week in Kowloon Bay Office\nComprehensive medical and dental coverage\nProfessional training and career advancement opportunities\nFriendly working environment\u00a0and work-life balance culture\n\nWhat do you need to do?\n\nDevelop mobile/web app frontend targeted for thousands of users\nApply best industry practice & setup with HTML5/CSS3/JS standard\nAs a quality gatekeeper for front end\u00a0deliverables\nAn in-house resource to identify and provide quick fix for front end coding problem\nWork closely with the design and development team\n\nWhat do you need to have?\n\nA strong knowledge and experience of HTML5 / CSS3 (SASS)\nStrong experience of Javascript with ability to handcode\nExperience of Reactjs, jQuery, Vue and API integration\nExperience of Zurb Foundation / Bootstrap\nA good knowledge and experience of Responsive Web Build\nAn understanding of design and UI / UX principles\nUse of version control tools like GIT\nGood command of written and spoken English & Chinese\nCandidates with more experience will be considered for the senior position\n\nReady to join us? Apply now to submit your resume & expected salary to us!\n\n(Personal data will be used for Webs s\u2019 up Production Limited recruitment purposes only. We will retain the applications of candidates for no more than 12 months.)", "employment_types": ["Full Time", "Permanent"], "selling_points": ["UI / UX design (Web, APP)", "Project exp in Bank&Finance/Public Sector/Retail", "Attractive salary package; Friendly environment"], "locations": ["Not Specified"], "categories": ["Design", "Web Designer", "Others", "Information Technology (IT)", "UI/UX Designer"], "post_time": "2022-01-06T03:02:44Z", "salary": {"currency": null, "max": null, "min": null, "period": "monthly", "term": null}, "salary_visible": false, "title_keywords": ["ux designer"], "responsibilities": [], "requirements": {"degrees": [], "majors": [], "languages": [], "language_level": [], "hard_skills": [], "soft_skills": [], "languages_combined": []}, "experience_required": {"duration": [], "field": []}}, {"job_id": "100003009022641", "location_code": "hk", "company": "Ambition", "job_title": "UX designer, Insurance, 40 - 50K", "description": "Job Descriptions:\n\nParticipate in development of applications and microservices\nAssist in requirements gathering and systems analysis & design\nInvolve in implementation, application testing, prepare test cases, UAT & user training\nSupport application deployment in container platform\nEvaluate new technologies and solutions\nRequirements:\u00a0\n\nHigh Diploma / Degree holders in Computer Science or Software Engineering related disciplines\nAt least 2 years solid experience in C#, .Net/.Net Core, React, web and database application\nKnowledge or experience in Git, Kubernetes, React Native, Jenkins will be an advantage\nGood in both spoken and written Cantonese and English\nA self-motivated team player with good interpersonal and communication skills\nAble to work independently\nCandidates with less experience will be considered for the Senior Programmer position", "employment_types": ["Full Time", "Contract"], "selling_points": ["international team", "great career prospects", "hybrid UX-VD designer"], "locations": ["Not Specified"], "categories": ["Information Technology (IT)", "UI/UX Designer"], "post_time": "2022-01-05T06:02:24Z", "salary": {"currency": null, "max": null, "min": null, "period": "monthly", "term": null}, "salary_visible": false, "title_keywords": ["ux designer"], "responsibilities": ["uat", "analysis", "systems", "implementation", "design", "testing", "evaluate"], "requirements": {"degrees": ["high diploma", "degree"], "majors": ["related disciplines", "software engineering", "computer science"], "languages": ["cantonese", "english"], "language_level": ["good"], "hard_skills": ["git", "jenkins", "web", "react", "react native", "c#"], "soft_skills": ["communication skills", "self-motivated", "work independently", "team player", "interpersonal"], "languages_combined": [{"language": "cantonese", "language_level": ["good"]}, {"language": "english", "language_level": ["good"]}]}, "experience_required": {"duration": ["at least 2 years"], "field": []}}, {"job_id": "100003009028916", "location_code": "hk", "company": "Viu", "job_title": "Multimedia Design Manager, Hong Kong", "description": "The incumbent will be responsible for assisting Head of Digital Innovation & Growth to drive user-centered UXUI design of the digital projects, including the interface design of website, new wellness campaign, wellness application, and a seamless cross-platform user experience. In addition, he/she will be an important part of the digital strategic project team to formulate program proposition, customer flow, wireframes, and prototypes.\u00a0\n\nJob Responsibilities:\n\nProduce interface wireframes and prototype for customer validation\nFacilitate user research and usability test\nTransform customers insights and business requirements from stakeholders into seamless user work flow and desirable user interface\nManage and liaise with IT and external vendor on requirements, specifications, timeline, costing, testing and related deliverables\nParticipate in ad hoc projects as required\n\nJob Requirements:\n\nBachelor degree or above in Information Technology, Interaction Design, Business Information System, Computer Science or other relevant disciplines\n5+ years of digital product design experience and preferable in management level\nPassionate in new technologies - UI/UX with exceptional wireframing skills\nFamiliar with various design tools including Invision, Axuro, Omni Gaffle, Google Analytics, Mix Panel, Adobe, Creative Suite, Photoshop, Illustrator, Sketch is highly desirable\nKnowledge about HTML/CSS and app development will be an advantage\nExcellent presentation, communications and interpersonal skills\nCandidates with less experience will be considered as Assistant Manager.", "employment_types": ["Full Time"], "selling_points": [], "locations": ["Kowloon Bay"], "categories": ["Design", "Multi-media", "Web Designer", "Information Technology (IT)", "UI/UX Designer"], "post_time": "2022-01-07T03:57:20Z", "salary": {"currency": null, "max": null, "min": null, "period": null, "term": null}, "salary_visible": false, "title_keywords": ["design manager"], "responsibilities": ["testing", "user interface", "specifications", "ad hoc projects", "liaise with"], "requirements": {"degrees": ["degree or above", "bachelor"], "majors": ["computer science", "business", "design", "information technology"], "languages": [], "language_level": [], "hard_skills": ["google analytics", "css", "information system", "illustrator", "html", "adobe", "creative suite", "photoshop"], "soft_skills": ["passionate", "creative", "interpersonal skills", "presentation"], "languages_combined": []}, "experience_required": {"duration": ["5+ years"], "field": ["digital", "management", "product design"]}}, {"job_id": "100003009035800", "location_code": "hk", "company": "Macroview Telecom Limited", "job_title": "Analyst Programmer / Senior Analyst Programmer", "description": "You will be part of the Android development team to develop the award-winning Board Management Software being used in 100+ countries. You will write high-quality and maintainable codes to enhance to product features according to design specifications. You may use state-of-the-art Android technologies and coding styles and enhance the apps better.\n\nYou will also investigate support cases that are related to the Android App and provide bug fixes.\n\nTraining will be provided for newcomers. We have senior developers to guide your tasks and work together on the same product.\n\nAs we have offices around the world, our staff have chances to work with people from different countries and to experience different cultures.\u00a0\n\nJob Responsibilities\u00a0 \u00a0\u00a0\n\nInvestigate existing codes\nImplement fixes and enhancements in Java/Kotlin with quality\nResponse fast when there are issues reported\nCorporate with other staff for aligned solutions\nKeep learning and touching new Android technologies\n\nJob Requirements\n\n\nDiploma/Degree Holder in Information Technology, Computer Engineering, Computer Science, or related disciplines\nExperience on coding mobile app / Android app preferable\nExperience and knowledge in embedded database system (e.g. SQLite) and operating systems (e.g. Linux, Windows)\nGood troubleshooting, communication, and interpersonal skill\nGood in spoken and written English\nFresh graduates will also be considered.\n\nInterested individuals please email your full CV stating your academic result and qualifications, career history and availability with current and expected salary to HR department by email or via \"Apply Now\" button.\n\nPersonal data collected will be used for recruitment purpose only.", "employment_types": ["Full Time", "Permanent"], "selling_points": ["Container,Microservice,Kubernetes,C#,React,API", "2 years web application experience", "Experience in Git, Kubernetes, React Native, Jenki"], "locations": ["Quarry Bay"], "categories": ["Information Technology (IT)", "IT - Webmaster / SEO", "Others", "UI/UX Designer"], "post_time": "2022-01-10T08:27:05Z", "salary": {"currency": null, "max": null, "min": null, "period": "monthly", "term": null}, "salary_visible": false, "title_keywords": ["analyst programmer", "senior analyst programmer"], "responsibilities": ["quality"], "requirements": {"degrees": ["diploma", "degree holder"], "majors": ["related disciplines", "computer engineering", "computer science", "information technology"], "languages": ["english"], "language_level": ["good"], "hard_skills": ["mobile", "linux", "android"], "soft_skills": ["communication", "troubleshooting", "interpersonal skill"], "languages_combined": [{"language": "english", "language_level": ["good"]}]}, "experience_required": {"duration": [], "field": ["database"]}}, {"job_id": "100003009033684", "location_code": "hk", "company": "BOC Group Life Assurance Company Ltd", "job_title": "UXUI Manager (1-year Contract)", "description": "Responsibilities:\n\n\nResponsible for Web and APPs\u2019 UI / UX design\nCreate design deliverables (wireframes, mockups, prototyteps, flows etc.)\u00a0\nCreate user-centred designs by understanding business requirements, the voice of the customer, user journeys, customer feedback, and usability findings\u00a0\n\nRequirements:\n\n\nWith 1-8 years experience in UI/UX Design\nProject experience in banking & financial/ Public sector, retail is preferable but not a must\u00a0\nFamiliarity with design tools (e.g. Sketch/ Photoshop/ Figma/ Illustrator/InVision/Zeplin/ Overflow/ AdobeXd etc.)\nDetail-oriented, self-motivated, able to work independently\nCandidate with more experience will be consider as Senior UI/UX Designer", "employment_types": ["Contract"], "selling_points": [], "locations": ["Tai Koo"], "categories": ["Information Technology (IT)", "UI/UX Designer"], "post_time": "2022-01-10T01:36:20Z", "salary": {"currency": null, "max": null, "min": null, "period": "monthly", "term": null}, "salary_visible": false, "title_keywords": ["manager"], "responsibilities": ["ui", "design"], "requirements": {"degrees": [], "majors": [], "languages": [], "language_level": [], "hard_skills": ["illustrator", "photoshop"], "soft_skills": ["self-motivated", "work independently", "detail-oriented"], "languages_combined": []}, "experience_required": {"duration": ["1-8 years"], "field": ["designer", "design", "banking", "retail", "financial"]}}, {"job_id": "100003009014522", "location_code": "hk", "company": "Osmium Consulting Group Limited", "job_title": "UX/UI Designer ( Inhouse/MNC/FinTech )", "description": "As a UX/UI Designer, you will advocate for design-driven project execution in a stimulating environment to unleash the potential of our business.\n\nWork closely with business stakeholders, product owners, and business analysts, understand the business metrics and be able to translate the company\u2019s and business\u2019 goals.\nDesign wireframes, user journeys, UI mock-ups, components and prototypes or other digital forms for stakeholders and customers\u2019 validation.\nDevelop pixel perfect UI and adjust design layouts based on user and stakeholders\u2019 feedback.\nAbility to collaborate effectively, working in agile delivery teams with developers, PM, business analysts, product owners, and business owners.\nContribute to usability testing planning activities and be able to understand usability testing insights.\n\nDuties & Responsibilities\n\nYou\u2019re highly flexible, and able to refocus your output and direction based on emerging business trends and creative decisions.\nUnderstand users\u2019 thinking and design user-friendly UX/UI flows.\nDesign from concept to completion all facets of the User Interface including: mock-ups, wireframes, and prototypes to communicate interactions and features effectively.\nReview existing products and perform product testing and improvement reports.\nWorking with the development team to identify, estimate, schedule and track UX/UI tasks.\u00a0\n\nExperience & Requirements\n\nMinimum 2-3 years\u2019 experience focusing on UX and UI. (Candidates with less experience can also be considered)\nHigher Diploma or above in Mobile App development / Web / Multimedia / Graphic design or related fields.\nStrong sense of responsive design, UX/UI and technology trends.\nExpert with UI tools, Figma, Sketch, or similar.\nAbility to conduct user research, A/B testing and iteration usability testing.\nKnowledge of any scripting languages.\nUnderstanding of \u201cfreemium\u201d business model, including customer acquisition, retention, and monetization", "employment_types": ["Full Time", "Permanent"], "selling_points": ["Work Life Balance | Career Growth Opportunities", "UX/UI Development | Mobile Apps focus", "Bonus | Medical + Dental | Attractive Package"], "locations": ["Tsim Sha Tsui"], "categories": ["Design", "Graphics", "Multi-media", "Information Technology (IT)", "UI/UX Designer"], "post_time": "2022-01-03T03:34:58Z", "salary": {"currency": "HKD", "max": 34999, "min": 20000, "period": "monthly", "term": null}, "salary_visible": true, "title_keywords": ["ui designer"], "responsibilities": ["review", "mock-ups", "design", "testing", "user interface", "reports", "schedule", "ui"], "requirements": {"degrees": ["higher diploma or above"], "majors": ["graphic design"], "languages": [], "language_level": [], "hard_skills": ["mobile", "multimedia", "web"], "soft_skills": ["responsive"], "languages_combined": []}, "experience_required": {"duration": ["minimum 2-3 years"], "field": []}}, {"job_id": "100003009014794", "location_code": "hk", "company": "Talent Fields Hong Kong Company Limited", "job_title": "Junior UX/UI Designer - Fintech", "description": "KEY RESPONSIBILITIES AND ACCOUNTABILITIES\n\nTo lead a regional team around 10 persons of all multimedia design works of a pan-regional OTT video platform\u00a0\nTo support the Content Management team head quarter to manage all multi-media design project requirements from different regions\nTo monitor the daily workflow and ad-hoc projects to achieve quality, effectiveness and efficiency\u00a0\nTo coordinate with different parties, including content acquisition, content production, editorial curation, marketing promotion & sales, UX & UI team and corporate branding teams\u00a0on different KPIs\nTo work closely with the video production team to resolve technical or design issues\nTo help on the progress of provide visual elements for motion graphics, VFX and compositing, e.g. main titles, billboards, bumpers, ID tags, lower 3rds, etc.\u00a0\nTo lead the quality check of all the design process and finished product of the local outputs\u00a0\nTo study design briefs, conceptualize visuals based on requirements\u00a0\nTo help on the progress on develop illustrations, logos, typefaces, banners and other designs\nTo help build the brand and image of the platform\u00a0\nLess experienced candidates will be considered as Assistant, Multimedia Design Manager\n\nSKILLS AND COMPETENCIESILLS AND COMETENCIES\n\nUniversity graduated in Graphic / Multimedia Design or related disciplines\nAt least 10 years solid leading and management experience in multi-media design team / creative team\nStrong project management experience is crucial\u00a0\nTeam leader with regional exposure is a MUST\nWorking experience in regional OTT platform with multicultural mind set is\u00a0highly preferred\nKnowledge of content consumption, internet and mobile applications as well as design trends\nMulti-media design experience in graphic, typography, photo retouch, branding, online ads, video and website, etc.\nProficient in Photoshop, Illustrator and InDesign\nKnowledge of GDN banner, social media and video editing will be an advantage\nUnderstanding UI & UX design software is an advantage\nUnderstanding of video production is an advantage\nGood command in both English and Chinese are essential", "employment_types": ["Full Time", "Permanent"], "selling_points": ["Strong in developing UI/UX Strategy with data", "Knowledge in UI/UX design,app,web preferred", "Minimum 2 years of working experience"], "locations": ["Others"], "categories": ["Information Technology (IT)", "UI/UX Designer"], "post_time": "2022-01-03T04:10:28Z", "salary": {"currency": null, "max": null, "min": null, "period": "monthly", "term": null}, "salary_visible": false, "title_keywords": ["ui designer", "junior"], "responsibilities": ["multimedia design", "project requirements", "software", "quality", "website", "design", "video editing", "banners", "ad-hoc projects", "management team", "video production", "monitor", "teams", "develop", "motion graphics", "photo retouch", "visual", "kpis", "ui", "social media", "quality check", "management", "coordinate with", "project management", "design briefs", "design trends"], "requirements": {"degrees": [], "majors": [], "languages": ["english", "chinese"], "language_level": ["good command"], "hard_skills": ["graphics", "id", "indesign", "illustrator", "video editing", "project management", "mobile", "multimedia", "photoshop"], "soft_skills": ["project management", "creative"], "languages_combined": [{"language": "english", "language_level": ["good command"]}, {"language": "chinese", "language_level": ["good command"]}]}, "experience_required": {"duration": ["at least 10 years"], "field": ["management", "photo", "video", "design", "project management", "graphic", "media", "team"]}}, {"job_id": "100003009031569", "location_code": "hk", "company": "Centre for Intelligent Multidimensional Data Analysis Limited", "job_title": "Computer Programmer (Post A) /  Engineer (Post B) / IT Systems Officer (Post C)", "description": "Responsibilities:\n\nResponsible for develop and maintain web-based e-shop systems\nFollow the requirements and implement creativity from in-house team\nPerform other ad-hoc duties as required\n\n\u00a0Requirements:\n\n1-2 years relevant experience in programming and development (Fresh graduates are also welcome)\nFamiliar with programming languages, .NET framework (C#, ASP.NET)\nSolid experience in HTML, Database, JavaScript, HTML5, Bootstrap, jQuery, Ajax etc.\nExperience in cross browser compatibility and responsive designs\nGood sense of UI / UX design\nMobile apps development is an advantage\n\n\u00a0\u00a0Benefits:\n\n\u00a0\u00a0We offer attractive remuneration package and fringe benefits to suitable candidates including:\n\n5-Day Work Week (Monday to Friday)\nBank Holiday\nBirthday Leave, Marriage Leave, Compassionate Leave\nMedical & Life Insurance\nPerformance Bonus\nStaff Shopping Discount\nCareer advancement opportunities\n\nApply Method:\n\nInterest parties, please apply together with resume, stating current and expected salary, and send it via\u00a0APPLY NOW.\n\nIf you do not want to apply as JobsDB member, you may send your full resume with your availability, current and expected salaries to personnel at wellent.com.\n\n*Personal data collected will be used for recruitment purpose only and all application will be treated in strict confidence.", "employment_types": ["Full Time"], "selling_points": ["18 AL, Medical and Dental Insurance, friendly team", "Programmer, IT Officer, Engineer", "Artificial intelligence & Big Data Analysis"], "locations": ["Shatin Area"], "categories": ["Information Technology (IT)", "IT Management", "Software Development", "UI/UX Designer"], "post_time": "2022-01-07T09:29:10Z", "salary": {"currency": null, "max": null, "min": null, "period": "monthly", "term": null}, "salary_visible": false, "title_keywords": ["officer", "programmer", "engineer"], "responsibilities": ["e-shop", "systems", "develop", "maintain", "ad-hoc duties"], "requirements": {"degrees": [], "majors": [], "languages": [], "language_level": [], "hard_skills": ["jquery", "html", "mobile", "javascript", "programming", "ajax", "c#"], "soft_skills": ["responsive"], "languages_combined": []}, "experience_required": {"duration": ["1-2 years"], "field": ["development", "relevant experience", "programming", "database"]}}, {"job_id": "100003008993900", "location_code": "hk", "company": "Tranthink Technology Service Limited", "job_title": "Web Frontend Programmer", "description": "Duties\nPost A and B\nPerform and maintain application development\nIdentify user requirement and propose solution alternatives\nResponsible for system design, programming, testing and system delivery\nPrepare system documentation and deliver training and support to users\nWork on ad-hoc projects and perform any other duties as assigned\nPost C\nOversees the IT Service Management, Email communication and Special Projects\nDrive project management framework and manage projects life cycle\nResponsible for the implementation of software and hardware asset management\nDrive digital transformations\nDesign, build, and implement enterprise IT architecture\nResponsible for root cause analysis and keep track of corrective actions status\nManage IT budget and procurement\nWork on ad-hoc projects and perform any other duties as assigned\nRequirements\nPost A and B\nHigher Diploma or above in\u00a0Computer Science, Information System or a related discipline with 1-3 years\u2019 relevant working experience\nSolid experience in C/C++, Python, Django and Javascript or other programming languages\nProcess data structure, networking and algorithm knowledge\nPost C\nHigher Diploma or above\u00a0in Computer Science, Computer Engineering, Information Technology or a relevant discipline\nExperience with computer and network management and/or AI and data analysis application software instalments and maintenance\nProgramming and software development skills on desktop and mobile platforms and parallel processors will be an advantage\nAll posts\nGood command of written and spoken English\nExcellent analytical, problem-solving and communication skills\nGood organisational and interpersonal skills\nSelf-motivated, attentive to details and multi-task oriented\nAbility to work under tight schedule is essential\nSalary and Conditions of Service\nRemuneration package will be highly competitive, commensurate with qualifications and experience.\u00a0 Initial appointment will be made on a fixed-term contract.\nWhat you enjoy\n5-day work with stable hours\n18 days annual leave\nMedical and Dental Insurance\nPublic holidays\nCompensation leave\nMPF scheme\nGreat platform to learn and develop new skills in an encouraging environment\nFriendly team\nExcellent office environment (Newly renovated)\nShuttle bus from various locations in Hong Kong\nRecreational facilities in Science Park\nInformation and Application\nInterested parties please apply with full resume including expected salary and available date through email.\nApplications will receive full consideration and only shortlisted and selected applicants will be contacted.\nAn applicant who does not hear from us within 1 month after an interview may assume his/her application is not selected.\nAll information provided by applicants will be treated in strict confidence and used for recruitment purpose only. All personal data of unsuccessful applicants will be retained for 12 months for future recruitment purpose and will then be destroyed.", "employment_types": ["Full Time", "Permanent"], "selling_points": ["5 Days Work, Double Pay, Medical Insurance", "Flexible working hours, Free snack", "Javascript(ES5/ES6), HTML, CSS"], "locations": ["Lai Chi Kok"], "categories": ["Information Technology (IT)", "Application Specialist - Software", "Software Development", "UI/UX Designer"], "post_time": "2022-01-09T16:25:33Z", "salary": {"currency": null, "max": null, "min": null, "period": "monthly", "term": null}, "salary_visible": false, "title_keywords": ["programmer"], "responsibilities": ["any other duties", "it service", "software", "system delivery", "design", "communication", "maintain", "manage projects", "ad-hoc projects", "application development", "user requirement", "system documentation", "implementation", "testing", "architecture", "management", "it budget", "analysis", "project management", "hardware", "system design", "asset management"], "requirements": {"degrees": ["higher diploma or above"], "majors": ["computer engineering", "computer science", "information technology"], "languages": ["english"], "language_level": ["good command"], "hard_skills": ["network management", "c++", "ai", "maintenance", "analysis", "problem-solving", "information system", "scheme", "mobile", "c", "javascript", "programming", "python"], "soft_skills": ["communication skills", "self-motivated", "attentive to details", "multi-task oriented", "problem-solving", "interpersonal skills", "friendly", "stable"], "languages_combined": [{"language": "english", "language_level": ["good command"]}]}, "experience_required": {"duration": ["1-3 years"], "field": ["management", "maintenance", "related", "relevant working experience", "data analysis", "programming"]}}, {"job_id": "100003009014639", "location_code": "hk", "company": "Prenetics Limited", "job_title": "UX/UI Intern", "description": "Job Responsibilities:\nMaintain, troubleshoot and develop features on web-based applications.\nWork closely with the QA team and backend developers.\nFollower the requirements and implement creativity from the Product team.\nDeliver quality work under the right schedules.\nJob Requirements:\nGood technical skills in Javascript(ES5/ES6), HTML, CSS.\nFamiliar with MVVM/MVP/MVC frameworks such as Vue/Angular/React will be an advantage.\nKnowledge of frontend system architecture and common design patterns will be an advantage.\nExperience on Vue3.0/Typescript is a big plus.\nSelf-motivated, responsible and a good team player.\nInterested parties, please click \"Apply Now\" for application.\nPersonal data collected will be used for recruitment purpose only.", "employment_types": ["Internship"], "selling_points": ["UX/UI design", "Graphics Chops", "Communication"], "locations": ["Quarry Bay"], "categories": ["Information Technology (IT)", "UI/UX Designer"], "post_time": "2022-01-03T03:52:07Z", "salary": {"currency": null, "max": null, "min": null, "period": "monthly", "term": null}, "salary_visible": false, "title_keywords": ["intern"], "responsibilities": ["schedules", "quality", "develop", "maintain", "troubleshoot"], "requirements": {"degrees": [], "majors": [], "languages": [], "language_level": [], "hard_skills": ["plus", "react", "html", "typescript", "angular", "css"], "soft_skills": ["technical skills", "good team player", "self-motivated", "responsible"], "languages_combined": []}, "experience_required": {"duration": [], "field": []}}, {"job_id": "100003009022472", "location_code": "hk", "company": "Green Tomato Limited", "job_title": "Senior UI/UX Designer", "description": "We are hiring talent like you!\n\n\nSenior UI/UX Designer is a key member for us. He/ She is responsible for designing projects from ideas to finished products and Mobile App Creative & Design.\n\n\nYour role will include the following duties:\u00a0\n\nWorking closely with business stakeholders, product owners and business analysts to translate user stories/business requirements into digital experiences.\n\nDriving user research activities such as stakeholder interview, survey, A/B testing, usability testing, learn about user behavior and translate research findings into possible solutions.\n\nBeing responsible for providing high quality deliverables such as user journeys, user flows, wireframes, UI mock-ups and prototypes for digital platforms and products.\n\nDeveloping pixel-perfect UI and ensuring design consistency between digital platforms.\n\nCollaborating closely in agile delivery teams with business analysts, developers, quality assurance analysts, product owners and other designers.\n\nIdentifying design issues within the development team while tracking and providing solutions to design issues\n\nPresenting ideas to stakeholders and making recommendations in accordance to\u00a0 feedback\n\nLeading and managing junior designers by reviewing their work quality and maintaining company standards.\u00a0\n\nWe are very interested if..\n\nYou possess a diploma or above in Interactive / Multimedia / Visual Design or related disciplines.\n\nYou have a minimum of 3 years of experience in UI/UX design, Interaction Design or equivalent experience.\n\nYou have a well established knowledge in user-centered design (UCD), design language system, visual design principle and interaction design.\n\nYou possess strong presentation skills.\n\nYou have excellent oral and written communication skills in English and Cantonese.\n\nYou are highly proficient with design tools such as Sketch/Figma, InVision, Zeplin, Adobe Creative Suite.\n\nYou have some basic knowledge of programming (HTML/CSS & Javascript is an advantage).\n\nYou have experience working in banking, financial, and/or insurance industries using \u2018Agile\u2019 or similar project methodologies.\u00a0\n\nYou have an advantage by having experience in contributing to thought leadership in UI/UX.\u00a0\n\nYou are an experienced problem solver and can adapt to a fast-paced ever-changing environment.\u00a0\n\nYou are able to work independently, self-motivated and have a strong sense of responsibility.\u00a0\u00a0\n\nYou are willing to learn and explore new design trends, technologies and tools.\u00a0\n\nYou can provide a design portfolio with proven work.\n\nCandidate with more experience will consider as Assistant UI/UX Manager or above\n\nWhat we offer:\n\n5-day working week\n\nHappy and harmonious working environment.\u00a0\n\nCompetitive remuneration\n\nMedical Allowance\n\nBirthday Leave\n\nValuable working experience\n\nInternal training support.\u00a0\n\nYear-end Performance Bonus\n\nWe offer attractive remuneration packages and excellent career development opportunities to the right candidate.\u00a0\n\nFinal and Most Important Requirement\n\n\"Enjoy What You Do!!\"\u00a0\n\nCandidates not contacted within 4 weeks may consider their application for this role unsuccessful. Unless advised otherwise, unsuccessful candidates will be kept on file for future job opportunities. Personal data collected will be used for recruitment related purposes only and all personal data of applicants will be kept in strict accordance to the Personal Data Privacy Ordinance.", "employment_types": ["Full Time", "Permanent"], "selling_points": ["Mobile Application or Web UI/UX Design", "Birthday Leave", "Happy and harmonious working environment"], "locations": ["Kwun Tong"], "categories": ["Design", "Graphics", "Web Designer", "Information Technology (IT)", "UI/UX Designer"], "post_time": "2022-01-05T05:39:44Z", "salary": {"currency": null, "max": null, "min": null, "period": "monthly", "term": null}, "salary_visible": false, "title_keywords": ["ux designer"], "responsibilities": ["ideas", "mock-ups", "quality", "design", "communication", "designing", "mobile app", "maintaining", "teams", "developing", "testing", "banking", "visual", "ui", "presenting ideas", "tracking", "work quality", "design trends", "insurance"], "requirements": {"degrees": ["diploma or above"], "majors": ["related disciplines", "design"], "languages": ["cantonese", "english"], "language_level": ["excellent"], "hard_skills": ["basic", "agile", "html", "mobile", "visual design", "javascript", "multimedia", "programming", "css", "adobe creative suite"], "soft_skills": ["communication skills", "oral", "work independently", "self-motivated", "agile", "responsible", "problem solver", "sense of responsibility", "willing to learn", "presentation skills", "creative", "leadership"], "languages_combined": [{"language": "cantonese", "language_level": ["excellent"]}, {"language": "english", "language_level": ["excellent"]}]}, "experience_required": {"duration": ["minimum of 3 years"], "field": ["design", "business", "banking", "digital", "insurance", "financial"]}}, {"job_id": "100003009016496", "location_code": "hk", "company": "HANSEL INTERNATIONAL Executive Search Limited", "job_title": "Internet Broker - UI/UX Designer (Team Lead Role)", "description": "Our client is a a fast growing internet broker recently launched their stock trading APP.\u00a0 To cope with their rapid expansion, they are currently looking for an UI/UX Designer to join their team.\n\n\n\nResponsibilities\uff1a\n\nResponsible for the product UI/UX design, including the development and refining of front-end and back-end UI\nWork closely with Product development and front-end developers to deliver UI within schedule\nProvide UI/UX design for business needs and be able to present it by leveraging visualization tools\nKeep refining and improving UI/UX based on market feedbacks\nExplore emerging UI/UX capabilities that can be used for our product iterations\n\nRequirements:\n\nAt least 5 years work experience in UI/UX design\nProficient skills on graphic design software of Photoshop, Adobe Illustrator, Adobe After Effects\nFamiliar with designs in Web, iOS, and Android\nExcellent understanding of UI design principles and methodologies, especially on business-use UI/UX\nBe able to understand and think from the perspective of overall products, and design by focusing on product details\nGood command of English and Chinese, Mandarin is a huge plus\nFor interested candidates, please send us your updated resume with your 1) current salary 2) expected salary 3)notice period.\u00a0 All personal information collected will be strictly used for recruitment purpose only.\u00a0", "employment_types": ["Full Time"], "selling_points": ["UI/UX Designer, APP & Website", "Global Stock Trading Platform", "At least 5 years of relevant experience"], "locations": ["Tin Hau"], "categories": ["Information Technology (IT)", "Others", "UI/UX Designer"], "post_time": "2022-01-03T09:12:32Z", "salary": {"currency": null, "max": null, "min": null, "period": "monthly", "term": null}, "salary_visible": false, "title_keywords": ["ux designer", "lead"], "responsibilities": ["visualization", "ui", "design", "schedule"], "requirements": {"degrees": [], "majors": [], "languages": ["english", "chinese", "mandarin"], "language_level": ["good command"], "hard_skills": ["plus", "web", "adobe illustrator", "adobe after effects", "android", "photoshop"], "soft_skills": [], "languages_combined": [{"language": "english", "language_level": ["good command"]}, {"language": "chinese", "language_level": ["good command"]}, {"language": "mandarin", "language_level": ["good command"]}]}, "experience_required": {"duration": ["at least 5 years"], "field": ["design"]}}, {"job_id": "100003009030646", "location_code": "hk", "company": "Cyber Universal Company Limited", "job_title": "Programmer (5 Days work, TST East)", "description": "Responsibilities:\nWork with designers and teams to understand application requirements, design program changes / enhancements and prepare design specification\nDevelop programs and enhancements in web/android application of Traveling and POS systems\nOversee project timelines and schedule, ensuring all deadlines are met\nFollow up programming / technical issue, propose and implement bug fixing duties\nEvaluate and implement new technologies to maximize development efficiency\nAssist in analyzing and optimizing UI to enhance efficiency and performance\nDevelop and maintain proper programming documentation\nPerform and support various testing activities including unit testing, integration testing and user acceptance testing\nWilling to learn and have a strong sense of responsibility\nJob Requirements:\nFamiliarity with CSS, HTML, JAVASCRIPT or ANDROID development\nSpecific Angular2/4/6/8/10, XML and PostgreSQL knowledge is an advantage\nExcellent analytical and problem solving skills\nAbility to handle multiple projects simultaneously\nAble and willing to quickly learn new technologies and languages when necessary\nAble to work under pressure, good communication skill, cooperative, good team work and able to work independently\nFresh graduate will be considered\nImmediate available is preferred", "employment_types": ["Full Time", "Permanent"], "selling_points": [], "locations": ["Not Specified"], "categories": ["Information Technology (IT)", "Application Specialist - Software", "Software Development", "UI/UX Designer"], "post_time": "2022-01-07T07:59:24Z", "salary": {"currency": null, "max": null, "min": null, "period": "monthly", "term": null}, "salary_visible": false, "title_keywords": ["programmer"], "responsibilities": ["systems", "teams", "design", "develop", "evaluate", "testing activities", "testing", "maintain", "schedule", "documentation", "ui"], "requirements": {"degrees": ["fresh graduate"], "majors": [], "languages": [], "language_level": [], "hard_skills": ["android development", "html", "javascript", "css", "problem solving skills"], "soft_skills": ["good team work", "work independently", "cooperative", "communication skill", "analytical and problem solving skills", "work under pressure"], "languages_combined": []}, "experience_required": {"duration": [], "field": []}}, {"job_id": "100003009029355", "location_code": "hk", "company": "Tab Next Limited", "job_title": "IT Business Analyst (Healthcare)", "description": "Job descriptions:\n\nAssist project manager to collect users requirement\nAnalyze and design software from users operation workflow\nFocus on healthcare industry\nFull spectrum of documentations for project management\nProvide screen design and user interface design with or without the assistance of graphic designer\nPrepare presentation materials for end-users\nIn-depth understanding of user operation workflow\nStay at end-users side for quality control perspective\nWork collaboratively with programmers and end-users\nAttention to details and strong analytical and logical skills\nAccountability, be a good learner and team player\n\nJob requirement:\n\nTertiary education (IVE or above) in related disciplines such as CE, CS, BBA, BBA IS, IM or working experience as equivalent\u00a0 \u00a0\nKnowledge/ Experience in programming is definitely an advantage\nKnowledge/ Experience in healthcare industry is definitely an advantage\nUX/ UI designers are also welcomed\nGood communication in both verbal and written Chinese and English\nGood team players and willing to listen and learn\nSelf-motivated, work independently\n\nBenefits\n\n5-day work week\nFlexible working hour\nCareer coaching and development\nPerformance bonus via season or projects\n\nFor better understanding of our company, you can visit our Website.\n\nhttps://www.tabnext.asia", "employment_types": ["Full Time", "Permanent", "Contract"], "selling_points": ["Analyze & design software from operation workflow", "Keen to build career in Healthcare industry", "Career coaching, training and development"], "locations": ["Lai Chi Kok"], "categories": ["Information Technology (IT)", "Product Management / Business Analyst", "Technical Writing", "UI/UX Designer"], "post_time": "2022-01-07T04:51:37Z", "salary": {"currency": null, "max": null, "min": null, "period": "monthly", "term": null}, "salary_visible": false, "title_keywords": ["business analyst"], "responsibilities": ["software", "design", "project management", "user interface", "quality control"], "requirements": {"degrees": [], "majors": [], "languages": ["english", "chinese"], "language_level": ["good"], "hard_skills": ["programming"], "soft_skills": ["communication", "self-motivated", "work independently"], "languages_combined": [{"language": "english", "language_level": ["good"]}, {"language": "chinese", "language_level": ["good"]}]}, "experience_required": {"duration": [], "field": ["related", "education", "cs", "programming", "healthcare industry"]}}, {"job_id": "100003009014100", "location_code": "hk", "company": "Alfred24 Holdings Limited", "job_title": "Product Design Lead (UI/UX)", "description": "Job Responsibilities:\n\nDevelop business model by adopting innovative technology, enhance customer journeys and customer experience\n\nStay abreast of the FinTech development and market trends around the globe, research and create feasible solutions\n\nCollect and analyse customer needs, design UX/UI for digital platforms in agile approach\n\nAssist in formulating system requirements and UAT to ensure the customer experience up to standard\n\nMonitor and analyse customer satisfaction level and propose optimization suggestions\n\nRequirements:\n\nDegree or above with major in eCommerce, Innovative Technology, Business Administration, Information Technology, or related disciplines\n\nAt least 8 years relevant working experience\n\nDemonstrates innovative and out-of-the-box thinking\n\nAble to collaborate and maintain good relationships with both internal and external stakeholders and teamwork sprit\n\nStrong sense of responsibility and be used to accept challenges\n\nStrong knowledge and experience in using Microsoft Office Software and Chinese input\n\nCandidate with less experience will be considered as UI/UX Designer, Deputy UI/UX Designer or Assistant UI/UX Designer\n\nContract period is subject to renewal or conversion to permanent employment", "employment_types": ["Full Time", "Permanent"], "selling_points": ["Product Design Lead (UI/UX)", "Happy work culture", "Global team work environment"], "locations": ["Kwai Hing"], "categories": ["Information Technology (IT)", "UI/UX Designer"], "post_time": "2022-01-03T03:33:41Z", "salary": {"currency": null, "max": null, "min": null, "period": "monthly", "term": null}, "salary_visible": false, "title_keywords": ["lead"], "responsibilities": ["uat", "monitor", "design", "develop", "ui", "analyse"], "requirements": {"degrees": ["degree or above"], "majors": ["ecommerce", "related disciplines", "business administration", "information technology"], "languages": ["chinese"], "language_level": [], "hard_skills": ["chinese input", "microsoft office software"], "soft_skills": ["innovative", "sense of responsibility", "teamwork"], "languages_combined": [{"language": "chinese", "language_level": []}]}, "experience_required": {"duration": ["at least 8 years"], "field": ["designer", "relevant working experience"]}}, {"job_id": "100003009019310", "location_code": "hk", "company": "Bank of China (Hong Kong) Limited", "job_title": "Senior UI/UX Designer \u2013 Digital Project (1-year contract)", "description": "Our client is a Fintech company based in Hong Kong, focusing on mobile applications and web applications. Equipped with a well-structured digitalization plan, they are currently looking for a UXUI Designer to join the development team.\n\nJob Duties:\n\nCommunicate closely with business stakeholders and understand business goals & directions\nParticipate in market research and analysis to identify new opportunities\nStudy on different users behaviours, market & cultural factors\nCreate user stories, wireframes, flow diagrams and other design documents\nDefine, align and execute digital strategies and road map\nSupport application development team in project management, UAT and product launch\n\nJob Requirements:\n\nBachelor degree holder\nOver 1 years experience in UX/UI design or digital product design\nSolid experience in managing SDLC methodologies and tools\nWith a fundamental understanding of responsive web design standard methodologies;\nHigh proficiency in design software applications like Figma, Adobe Creative Suite e.g. Xd, Photoshop, illustrator, AE,", "employment_types": ["Contract"], "selling_points": ["-", "-", "-"], "locations": ["Admiralty"], "categories": ["Information Technology (IT)", "UI/UX Designer"], "post_time": "2022-01-04T07:17:36Z", "salary": {"currency": null, "max": null, "min": null, "period": "monthly", "term": null}, "salary_visible": false, "title_keywords": ["ux designer"], "responsibilities": ["business goals", "uat", "analysis", "market research", "design", "project management", "digital strategies", "application development"], "requirements": {"degrees": ["bachelor degree holder"], "majors": [], "languages": [], "language_level": [], "hard_skills": ["web design", "illustrator", "sdlc", "adobe creative suite", "photoshop"], "soft_skills": ["creative", "responsive"], "languages_combined": []}, "experience_required": {"duration": ["1 years"], "field": ["digital", "product design", "design"]}}, {"job_id": "100003009028510", "location_code": "hk", "company": "\u8b7d\u7043\u570b\u969b\u6709\u9650\u516c\u53f8", "job_title": "Frontend Developer", "description": "Founded in 2014, Prenetics is a major global diagnostics and genetic testing company with the mission to bring health closer to millions of people globally and decentralize healthcare by making the three pillars \u2014 Prevention, Diagnostics and Personalized Care \u2014 comprehensive and accessible to anyone, at anytime and anywhere. Prenetics is led by visionary entrepreneur, Danny Yeung, with a team of over 800 employees and operations across 9 locations, including United Kingdom, Hong Kong, India, South Africa, and Southeast Asia. Prenetics develops consumer genetic testing and early colorectal cancer screening; provides COVID-19 testing, rapid point of care and at-home diagnostic testing and medical genetic testing.\n\nMost recently, Prenetics made international headlines to become the first Unicorn in Hong Kong to publicly list on the Nasdaq via merger with 2021 Adrian Cheng's Artisan Acquisition Corp, valuing Prenetics at approximately US $1.7b.\n\n\nWe are currently looking for a creative and passionate young individual to join the team as our Visual Design Intern! If you think you\u2019re a curios, detail-oriented and has the ability to think critically kind of person, come join us now!\n\n\n\nYour Responsibilities:\n\n\n\nFundamentals.\u00a0You conceptualize, iterate, and execute thoughtful and comprehensive designs that drive delightful experiences for our users.\nCommunicate.\u00a0You engage cross-functional stakeholders and communicate designs and experiences at varying levels of fidelity, from sketches on paper to pixel-perfect wireframes.\nUsability.\u00a0You research, study, and conduct market analysis to explore the many different approaches to improve user experience.\nCollaboration.\u00a0You work closely with design, product, marketing, and engineering to ensure the final product reflects the design vision.\nOrganization.\u00a0You develop and maintain product design\u00a0libraries for both existing and new products.\n\nWho You Are:\n\nExperience.\u00a0You are knowledgeable in UX/UI design across multiple platforms (print, web, mobile)\nGraphics Chops.\u00a0You are fully fluent in graphics design.\nPortfolio.\u00a0You maintain an online portfolio that demonstrates your experience creating great end-to-end, user-centered experiences across web and mobile platforms.\nTraits.\u00a0You are highly organised, possess extreme attention to detail, and have a keen sense for aesthetics, including layout, grid system, color usage, and typography.\nAdaptability.\u00a0You are flexible, can multi-task, and are able to deal with ambiguity and changes intrinsic to the business as Prenetics scales.\nCollaboration.\u00a0You enjoy working in a collaborative team and working directly with Design Lead, Product Managers, Product Owner, and developers for implementation of designs.\nCommunication.\u00a0You communicate clearly and thoughtfully and possess the ability to articulate product flows to non-designers.\nTools.\u00a0You are proficient in designing and prototyping with a variety of tools such as Figma, Adobe XD, Sketch, Invision, Photoshop, Illustrator, InDesign.\n\n\n\nOur DNA is\u00a0P-R-E-N-E-T-I-C-S.\u00a0See what each word of our company name means:\n\nPassion\n\nYou love what you do and accomplish amazing result\nYou spread positivity, bring enthusiasm to work and inspire team members\nYou drive team toward specific goals, even when they seem unlikely or difficult\n\nResilience\n\nYou embrace changes and be able to drive through uncertainty, ambiguity and uncomfortable situations\nYou bounce back quickly from setbacks and challenges\nYou are persistent and determined to achieve the desired outcome\n\nEmpowerment\n\nYou trust others to play their positions well like an elite sports team\nYou foster a strong team spirit while encouraging others to take initiatives and risks\nYou create a space to allow team to grow and hold each other accountable\n\niNtegrity\n\nYou are trustworthy and lead by example\nYou are consistent in your message and action all the times\nYou deliver what you have promised\n\nEpic\n\nYou challenge your own comfort zone and always outperform yourself\nYou make meaningful and amazing impact to the world\nYou dare to take risks and you move fast\n\nTransparency\n\nYou are completely honest and committed to giving candid feedbacks, no matter how challenging it might be\nYou share ideas, knowledge and skills that empower others and create access to information with the wider team\nYou share wins and failures openly\n\nIngenuity\n\nYou make sound judgement and come up with solutions that are creative and smart. Copy when feasible\nYou challenge the status quo and question things that could be done differently for better. Modify the wheel if you can\u2019t change it\nYou think outside of the box and make value-based innovation\n\nCommunications\n\nYou articulate your thoughts and ideas effectively and respectfully\nYou know your audience and talk in a way they want to be told\nYou make sure communications happens, no matter where you are\n\nSelflessness\n\nYou put the needs of others before one's own and find ways in helping other to succeed\nYou focus on team wins than personal wins and share credits\nYou act in the company's best interest\nWe are Prenetics, our people make us who we are.", "employment_types": ["Full Time", "Permanent"], "selling_points": ["Programming skills in HTML5, CSS3, JavaScript", "Experience in Node.js, React.js/Vue.js", "12 Days AL, Performance Bonus,near Kwai Fong MTR"], "locations": ["Kwai Fong"], "categories": ["Information Technology (IT)", "IT - Webmaster / SEO", "Software Development", "UI/UX Designer"], "post_time": "2022-01-07T02:27:32Z", "salary": {"currency": null, "max": null, "min": null, "period": "monthly", "term": null}, "salary_visible": false, "title_keywords": ["developer"], "responsibilities": ["user experience", "sketches", "develop", "design", "market analysis", "maintain", "product design"], "requirements": {"degrees": [], "majors": [], "languages": [], "language_level": [], "hard_skills": ["graphics", "no", "web", "adobe xd", "indesign", "illustrator", "word", "mobile", "make", "c", "r", "focus", "photoshop"], "soft_skills": ["team spirit", "trustworthy", "enjoy working", "persistent", "collaborative", "communication", "articulate", "focus", "determined", "keen", "integrity", "committed", "adaptability", "honest", "creative", "attention to detail", "flexible", "multi-task", "accountable", "organised"], "languages_combined": []}, "experience_required": {"duration": [], "field": []}}, {"job_id": "100003009022755", "location_code": "hk", "company": "Randstad Hong Kong Limited", "job_title": "User Experience (UX) Researcher - Banking / Financial", "description": "about the company.\n\nOur client is a leading private bank providing a vast array of services that is one of the finest in the industry, serving high net worth individuals and wealthy families in its key markets of Asia, Greater China, India, Dubai and other international markets. With its successful business model, our client is currently looking for a User Experience / UX Researcher to join their dynamic team\n\nabout the team.\n\nReport to the Head of the team\nWork closely with other regions and other teams\nDynamic and vibrant working environment with work-life balance\n\nabout the job.\n\nYou will be responsible for the user experience research process, including customer experience, employee experience, product development cycle, etc.\nYou will apply suitable research methods to improve the user experience, methodology including qualitative and/or quantitative research, such as A/B testing, data analysis, testing across desktop and mobile, usability testing, survey evaluation, etc.\nYou will be able to understand users' needs, explaining to stakeholders in business context\nYou will work with different stakeholders across multiple product teams to determine user research needs and questions, and outline research plans\nYou will drive written report and presentation after the research findings\n\nskills & experiences required.\n\nYou are a Bachelor's Degree Holder of HCI, human factors engineering, related field or equivalent practical experience\nYou have 3 years of experience in user research and usability testing / analysis\nExcellent in verbal and written presentation\nExcellent in communication and interpersonal skills\nYou are a Native / Nearly Native English speaker, excellent in written and verbal English\nIf you have experience in financial services / ibank / banking / securities, that would be a big plus\nYou are fluent in Cantonese, Mandarin and English\n\nInterested candidates, please click APPLY NOW or send your updated resume with your portfolio to Vinnie Chan at vinnie.chan@randstad.com.hk", "employment_types": ["Full Time", "Permanent"], "selling_points": [], "locations": ["Causeway Bay"], "categories": ["Design", "Web Designer", "Marketing / Public Relations", "Marketing - Market Research", "Information Technology (IT)", "UI/UX Designer"], "post_time": "2022-01-05T06:27:26Z", "salary": {"currency": "HKD", "max": 44999, "min": 30000, "period": "monthly", "term": null}, "salary_visible": true, "title_keywords": ["researcher"], "responsibilities": ["analysis", "teams", "user experience", "banking", "testing", "data analysis", "communication", "evaluation", "research plans", "report"], "requirements": {"degrees": ["bachelor", "degree holder"], "majors": ["engineering"], "languages": ["cantonese", "english", "mandarin"], "language_level": ["native", "excellent", "fluent"], "hard_skills": ["mobile", "analysis", "dynamic", "plus"], "soft_skills": ["responsible", "communication and interpersonal skills", "dynamic", "vast", "presentation"], "languages_combined": [{"language": "cantonese", "language_level": ["fluent"]}, {"language": "english", "language_level": ["fluent", "native", "excellent"]}, {"language": "mandarin", "language_level": ["fluent"]}]}, "experience_required": {"duration": ["3 years"], "field": ["research", "engineering", "related", "securities", "testing", "data analysis", "business", "financial services", "banking", "product development", "team"]}}, {"job_id": "100003009031161", "location_code": "hk", "company": "Ztore HK Limited", "job_title": "Product Specialist (E-commerce, Web/ App)", "description": "Responsibilities:\n\nCommunicate with stakeholders across the company to gather and shape feature requests, translate business needs into user requirements.\nCollaborate with product design & product development team to deliver curated user requirements.\nManage product development cycle and release timeline, ensure timely and successful launch\nMeasure and analyze launched product features and feed insights to stakeholders and product development team\nUnderstand product goals, take part in developing and executing product roadmap\nTrack data, conduct analysis and develop insight to optimize customer journey and user experience in app and website\nTake initiative to carry out quantitative & qualitative survey to empower a customer centric mentality as a product owner\n\nRequirements:\n\n1+ year in project management/ product management/ product design or relevant work experience.\nBachelor's Degree in any discipline is welcomed, bachelor\u2019s degree in technical areas will be a plus. Fresh graduates are also welcome\nProactive and impact oriented individuals with strong sense of ownership and passion in developing career in e-commerce/retail/startup industry\nStrong communication, collaboration, organizational and interpersonal skills\nMotivated to grow and learn. Able to work independently and as a team.\nGood command of written and spoken English and Chinese\nAble to work under high pressure and fast-paced working environment", "employment_types": ["Full Time"], "selling_points": ["Collaborate with Product designers & developers", "eCommerce project & product management", "Good product sense and strong interpersonal skil"], "locations": ["Lai Chi Kok"], "categories": ["Information Technology (IT)", "Product Management / Business Analyst", "Marketing / Public Relations", "Marketing - Brand / Product Management", "UI/UX Designer"], "post_time": "2022-01-07T09:01:18Z", "salary": {"currency": null, "max": null, "min": null, "period": "monthly", "term": null}, "salary_visible": false, "title_keywords": ["product specialist"], "responsibilities": ["communicate with", "collaborate with", "data", "analysis", "developing", "user experience", "develop", "website", "product design", "executing"], "requirements": {"degrees": ["degree", "bachelor"], "majors": [], "languages": ["english", "chinese"], "language_level": ["good command"], "hard_skills": ["project management", "plus", "e-commerce"], "soft_skills": ["work independently", "passion in", "organizational", "communication", "project management", "motivated", "interpersonal skills", "work under high pressure", "proactive"], "languages_combined": [{"language": "english", "language_level": ["good command"]}, {"language": "chinese", "language_level": ["good command"]}]}, "experience_required": {"duration": ["1+ year"], "field": ["product management", "project management", "product design"]}}, {"job_id": "100003009016992", "location_code": "hk", "company": "Ucollex International Limited", "job_title": "Senior Product Designer (NFT Platform)", "description": "About UCOLLEX:\nWe have a message for the world. UCOLLEX is the future of digital art and toys. We are an innovative collectibles platform merging the physical collectibles market with digital asset creation.\nWe offer an extensive range of digital art and toys in form of NFT, made by the most creative minds in the world. From 3D models to augmented reality games, we are in the path of disrupting the globe with a bang and have awesome collectibles for everyone around the world!\n\nIf you want your voice to be heard, creative ideas come to live, acquire latest tech gadgets within the most disruptive digital space, please read on. Oh, read about our home and offerings too, and the perks!\n\nAbout the role and what\u2019s involved:\nWe are now looking for an experienced Product Designer to join our rapidly growing team and disrupt the NFT & Digital Collectible space!\n\nYou will be responsible for leading and managing the creative design of products that are not only beautiful, but also intuitive and useful. You\u2019ll own and be responsible for end-to-end user experiences and interfaces, from onboarding to member management. The role will also involve designing the entire process of acquiring and integrating the product, including aspects of branding, design, usability and function.\n\nAre you highly skilled in user experience and interface design, a motivational leader, and enjoy working in a collaborative, fast-paced, entrepreneurial environment? If so, we want to hear from you!\n\nHow you will add value:\nCreate and manage meaningful experiences, journeys and interfaces across our brands, while maintaining an intense focus on simplicity and usability.\n\nCollect behavioural data from user/market research, focus groups, surveys, feasibility & usability studies, to translate insights into designs that solve key journey pain points\nDevelop and manage high-quality, pixel-perfect designs that balance user needs, design priorities, and business objectives\nCollaborate with Product, Growth, and Brand teams throughout the design process to drive product iteration and innovation, influencing stakeholders at all levels\nPartner closely with our Engineering team to ensure designs pushed to market delight our customers\nInstill\u00a0Design Thinking principles across the organisation and help shape the Product vision\n\n\u00a0We are excited about you because you have:\n\n5+ years of experience designing captivating journeys and experiences\nExpert knowledge of responsive design principles across mobile, desktop and web technologies\nExperience creating, managing and communicating multi-input interactions, experiences and end-to-end flows, wireframes, prototypes, in both low and high-fidelity\nPrevious experience developing, owning and maintaining a Design System Manager (DSM)\nPrevious experience driving qualitative and quantitative user research and insights through modern UX research methods such as Usability Testing, A/B Testing, Clickstream Analysis etc.\nStrong working knowledge of Human-Centered Design (HCD) and Service Design principles\nProficiency in modern design and prototyping software (e.g. Figma, Adobe XD, Photoshop, Illustrator) and other design tools\nExcellent collaboration skills with the ability to work independently and cross-functionally in a team environment\nExcellent communication and presentation skills in English\nAn exceptional online portfolio showcasing UI and visual design work\nAn inherent passion for designing simple journeys around complex business problems\n\n\u00a0Nice to have\n\nKnowledge of Webflow\nPrevious experience working in e-commerce or a fast-paced start-up is a plus\nPassion for the Web 3 revolution and the disruptive technologies enabling it (Blockchain, NFTs)\n\n\u00a0What\u2019s in it for you?\n(Don\u2019t forget to checkout our perks in the employer profile page)\nCompetitive salary & equity grants / Medical, dental & vision insurance / Annual bonus program / Paid time off & work from home flexibility / Free Glam Bag Plus subscription / Learning & development programs\n\nSo go ahead and make the important choice to be part of an organisation working together for a better future please submit your application, including a cover letter and current resume to\u00a0careers @ucollex.io (no spacing)\n\nUcollex use technology to create an alternative world where people can discover, nurture and develop their passion.\n\nEmployer Profile\nThe perks of choosing us:\n\n\nUnder our rapidly expanding global startup, you will be rewarded with flexible Hours start of the working day, attractive package to include base equity and/or tokens, equity as well as health benefits, flat organization structure, as much responsibility as you\u2019re able to handle (just put your hand up), challenging work with exposure to cutting edge technologies dedicated to NFT and crypto world, growth in line with rapid scaling of the company, and most importantly, being surrounded with cool-positive and like-minded individuals\nWe guarantee that you\u2019ll be supported by a great team of agile experts in a can-do and supportive environment, where change and innovative thinking is encouraged!\nSo go ahead and make the important choice to be part of an organisation working together for a better future please click \u2018Apply\u2019 and submit your application, including a cover letter and current resume.\n\n\u00a0What is our home look like?\n\nWe are a band of brothers and sisters of bright, talented, collaborative members who love to evolve and jump on new opportunities.\nPeople who care about your growth and career development.\nCross-functional teams who value teamwork - from Hackathon to team off-sites, to Product roadshows, you get to experience it all.\n\n\u00a0If you are highly passionate about the digital environment and love the challenge of building a revolutionized collectibles platform, apply and let us know more about you!", "employment_types": ["Full Time", "Permanent"], "selling_points": ["Most disruptive Fintech in the digital world", "Forward thinking and outgoing team culture", "Collaborative and Open-space environment"], "locations": ["Wan Chai"], "categories": ["Information Technology (IT)", "UI/UX Designer"], "post_time": "2022-01-03T10:17:53Z", "salary": {"currency": null, "max": null, "min": null, "period": "monthly", "term": null}, "salary_visible": false, "title_keywords": ["senior product designer"], "responsibilities": [], "requirements": {"degrees": [], "majors": [], "languages": [], "language_level": [], "hard_skills": [], "soft_skills": ["innovative"], "languages_combined": []}, "experience_required": {"duration": [], "field": []}}, {"job_id": "100003009015216", "location_code": "hk", "company": "Jobslink Limited", "job_title": "UXUI Designer / Senior UXUI Designer (Position 1. Blockchain / Position 2. Ecommerce)", "description": "ROLES & RESPONSIBILITIES:\nAdvise on the creation of UX/UI assets (sketches, user flows, wireframes & prototypes) based on limitations of tech stack\nTrack and perform analysis on business results, analytics, customer behavior, and campaign effectiveness\nResponsible for product function design, write PRD and promote product development and testing online, and control the progress of product construction\nCoordinate and participate in multifaceted projects \u2013 involving both internal and external parties. Resolving conflicting interests and competing priorities of different stakeholders\nAnalyse analytics, user feedback and research findings to refine design decisions and product strategies\nAnalyse user feedback and find research to refine design decisions and product strategies\n\nSKILLS & EXPERIENCES REQUIRED\n\nDiploma or degree in Graphic Design, UI/UX Design, Multimedia or related major;\n3+ years of relevant experience as a Product Designer (UI/UX) for mobile and web customer facing products.\nExperience with defining product requirements, tracking performance, exploring drivers, diagnosing issues, etc.\nIn-depth knowledge and experience of user interface design with SaaS products;\nAbility to visualize and execute design concepts and ideas quickly, from ideation to prototyping, to user testing/validation, to execution;\nProficient in a variety of methods to convey ideas and concepts (e.g. storyboards, wireframes, prototypes, etc) to product owners and business stakeholders;\nA portfolio that demonstrates an ability to turn ideas into a strong and unique creative vision. A portfolio that provides insights into the candidate\u2019s design thinking process is a must;\nProficient with design and prototyping tools, i.e. Sketch, InVision, Zeplin, Overflow, Marvel, Framer, Figma, Adobe XD;\nExcellent communication skills, cross-team collaboration skill and ability to make compelling and clear design presentations for varied audiences;\nGood command of written & spoken English, Mandarin and Cantonese;\u00a0\n\nBENEFIT\u00a0\n\n5-days work\nBank Holiday\nFree snack and drink\nHappy team culture\nFlexible work environment\nSmart work from home\nMedical insurance", "employment_types": ["Full Time", "Permanent"], "selling_points": ["UI/UX", "Blockchain / Ecommerce", "Website, Mobile App, System, POS and Digital"], "locations": ["Not Specified"], "categories": ["Information Technology (IT)", "UI/UX Designer"], "post_time": "2022-01-03T06:10:34Z", "salary": {"currency": null, "max": null, "min": null, "period": "monthly", "term": null}, "salary_visible": false, "title_keywords": ["designer"], "responsibilities": ["design concepts", "control", "tracking", "ideas", "graphic design", "analysis", "internal and external parties", "sketches", "design", "testing", "coordinate", "user interface", "communication", "storyboards", "presentations", "promote product", "ui", "analyse"], "requirements": {"degrees": ["diploma", "degree"], "majors": ["graphic design", "design"], "languages": ["cantonese", "english", "mandarin"], "language_level": ["good command"], "hard_skills": ["web", "adobe xd", "analysis", "presentations", "mobile", "make", "multimedia"], "soft_skills": ["communication skills", "responsible", "unique", "clear", "multifaceted", "creative"], "languages_combined": [{"language": "cantonese", "language_level": ["good command"]}, {"language": "english", "language_level": ["good command"]}, {"language": "mandarin", "language_level": ["good command"]}]}, "experience_required": {"duration": ["3+ years"], "field": ["relevant experience", "designer", "design"]}}, {"job_id": "100003009029924", "location_code": "hk", "company": "Bolttech Management Limited", "job_title": "Senior Customer Experience Specialist", "description": "We have been working hard on leveraging technology to facilitate transactions of business of all sizes, and improve end consumer\u2019s quality of life. Right now, RichFame is providing applications and services across different sectors, from e-commerce, e-logistics.\n\nWe\u2019re a small, focused, and rapidly growing team with an abundance of opportunities. If you want to make a real impact and you\u2019re up for challenges, RichFame is the ideal place for you.\n\nHighlight of Benefits\uff1a\n12 Days annual leave\nFriendly, open and complaisant working environment\nPerformance Bonus\nGreat Career Exposure\nComprehensive medical Coverage\nOn Job training\n\n\nResponsibilities\n\n\nCollaborate with Frontend Team Lead and other teammates in development team to design and develop a well-structured front-end architecture for the in-house products in an agile approach\nCollaborate with Backend developers to integrate new features and unique consumer-facing products\nResearch and provide suggestions for product development strategies\nRequirement\n\nProgramming skills in HTML5, CSS3, JavaScript\nExperience in Node.js, React.js/Vue.js is a plus\nProficient in web development on WordPress\nExperience in open-source control systems such as Git and automated testing suites such as Jest\nStrong analytical, problem-solving skill and able to pick up new technologies\nGood understanding in TDD mindset and functional programming\nGood sense of UI / UX design\nLocation: near Kwai Fong MTR Station\n\nInterested parties please send your resume with your current and expected salary by clicking the Apply Now.\nPlease visit our website at: www.richfame.hk for more information about us", "employment_types": ["Full Time"], "selling_points": ["Dynamic team", "Exciting opportunity", "Global presence"], "locations": ["Sheung Wan"], "categories": ["Merchandising & Purchasing", "Others", "Public / Civil", "Others", "Information Technology (IT)", "UI/UX Designer"], "post_time": "2022-01-07T06:27:01Z", "salary": {"currency": null, "max": null, "min": null, "period": "monthly", "term": null}, "salary_visible": false, "title_keywords": ["specialist"], "responsibilities": [], "requirements": {"degrees": [], "majors": [], "languages": [], "language_level": [], "hard_skills": [], "soft_skills": [], "languages_combined": []}, "experience_required": {"duration": [], "field": []}}, {"job_id": "100003009015808", "location_code": "hk", "company": "Motherapp Limited", "job_title": "Senior UX Designer", "description": "Responsibilities:\n\nDesign user interface for Portal, POS, Customer Frontends (Mobile Apps, Tablet, PC);\nDesign for UI and UX;\nCollaborate with our development team to bring your designs to live;\nCommunicate with clients to gather requirements and present design concept.\n\nRequirements:\n\nDegree Holder in digital design or related disciplines;\nMinimum 2 year of UI /UX design experience (especially on web and Mobile App), or equivalent experience;\nExperience designing intuitive user experiences based on requirements;\nProficiency in graphic design - familiar with Photoshop or AI;\nProficiency in prototyping tools like Sketch, Figma;\nPassionate to provide innovative, creative and reliable digital business solutions (web, app, system) to our clients;\nGood team player with strong growth mindset, excellent communication, work with strict deadlines and under high-pressure situations;\nGood command of spoken and written English, Chinese and Mandarin;\nCandidate with more experience will be considered as Senior UX/UI Designer;\n\nInterested parties please submit your application to our mailbox by clicking Apply Now.\n\nPersonal data provided in the employment applications will be treated in strict confidence and used only for recruitment purpose.", "employment_types": ["Full Time"], "selling_points": ["Great promotion ladder", "Supportive teamwork environment", "Work from home arrangement"], "locations": ["Shatin Area"], "categories": ["Information Technology (IT)", "Application Specialist - Software", "Software Development", "UI/UX Designer"], "post_time": "2022-01-03T07:39:58Z", "salary": {"currency": null, "max": null, "min": null, "period": "monthly", "term": null}, "salary_visible": false, "title_keywords": ["ux designer"], "responsibilities": ["collaborate with", "communicate with", "design concept", "design", "user interface", "ui"], "requirements": {"degrees": ["degree holder"], "majors": ["related disciplines", "design"], "languages": ["english", "chinese", "mandarin"], "language_level": ["good command"], "hard_skills": ["ai", "mobile", "web", "photoshop"], "soft_skills": ["passionate", "good team player", "creative", "innovative", "communication", "reliable"], "languages_combined": [{"language": "english", "language_level": ["good command"]}, {"language": "chinese", "language_level": ["good command"]}, {"language": "mandarin", "language_level": ["good command"]}]}, "experience_required": {"duration": ["minimum 2 year"], "field": ["designer", "design"]}}, {"job_id": "100003009022894", "location_code": "hk", "company": "Popular e-Learning (H.K.) Limited", "job_title": "Project Management Officer, Multimedia", "description": "In this position you will...\n\nBuild a customer experience that is connecting people with more ways to protect the things they love. Our CX mission is to provide Fast, Easy, and Flexible customer experiences powered by technology. By making it easier for people to protect the things they love, we want to change the way customers feel about insurance. You will work collaboratively across the organization to support development of customer strategies including value proposition, product offerings, customer journeys and supporting services which can lead to increased customer acquisition, customer retention and customer lifetime value through up-sell and cross sell.\u00a0You will be part of a customer-first cultural at bolttech, focused on aligning the business to create and shape an outside-in perspective on services and offerings. You are responsible to drive initiatives within customer experience measurement (NPS and customer feedback), customer research, customer journey mapping/design and implementation of enhancements to our customer experiences. You will have the opportunity to engage with all individuals who either directly or indirectly impact our customers. It is crucial to provide insights on how to improve our customer experience based on customer data, market trends and technology innovation.\n\nYou will be responsible for\u2026\n\nCustomer Experience Strategy\n\nWork together with Group CX Leadership and Business Executives on continuous evolvement of bolttech\u2019s Group Customer Experience Strategy supported by Quarterly/Annually Missions and Prioritized Roadmap for Implementation.\n\nCustomer Journey Review\n\nOversee the customer experience across channels, platforms, and partnerships.\nConduct customer journey mapping review to identify actionable recommendations on how to improve and work closely with various internal teams and external partners to deliver requirements and target state design.\n\nCustomer Experience Measurement\n\nSupport and drive implementation of Customer Experience Measurement and Customer Feedback tools (e.g. Qualtrics, Meltwater etc.) across key customer touchpoints.\nAnalyze customer feedback leveraging implemented company-controlled or non-company-controlled tools.\nTrack customer experience performance, identify actionable insights and work with cross-functional group teams and business stakeholders on how to improve the experience and feedback scores.\n\nCustomer Research\n\nSupport and drive customer research (e.g. customer surveys, desktop research, qualitative research) for deeper understanding of customer behaviors, preferences and needs. \u00a0\u00a0\u00a0\nIdentify opportunities and initiate steps that will enhance customer experience and business value from research findings.\n\nCustomer Complaints\n\nSupport review of customer complaints summaries from business stakeholders on quarterly basis\nUnderstand key trends in customer complaints and work with business stakeholders on enhancements and how to prevent identified complaints.\n\nProject Management and Group CX Leadership\n\nLead and drive Group CX project teams including junior Group CX resources and resources from cross functional teams\nCoach and support development of junior Group CX resources\n\nFor you to be successful\u2026\n\n\u00a0 We expect you to be able to demonstrate the following key competencies\u00a0\n\nCustomer focus:\n\nChampions a customer-centric environment and helps teams to see the world from their customers\u2019 points of view and empathise with their needs\nIn touch with customer needs and trends and uses these to shape our strategy and approach in order to constantly improve customer experience\nDrives a culture focused on creating compelling customer experiences based on simplified and digitised customer journeys\n\nImpactful:\n\nCommitted to delivering strategically aligned objectives, creates plan to achieve with key milestones and measures\nPerseveres, tries new approaches to reach challenging goals and persists until outcomes and commitments are met.\nHolds high standards for delivery of outcomes with a lens of continuous improvement.\n\nCurious:\n\nMotivated and self-directed, identifying opportunities to grow and acquire new knowledge from a range of sources.\u00a0\nActively keeps abreast of industry trends and research and shares learnings with team\n\nCollaborative:\n\nDevelops strategic relationships and networks across the organization and shares with others for mutual benefit\n\nCommunication:\n\nShares accurate, timely information with the right people in an appropriate format for the audience\n\nYou will require the following qualifications and skills\n\nMinimum\u00a06 years of relevant career experience, preferably within customer experience, management consulting or insurance / financial services\nExperience in transformation of customer operations and services, leading to measurable improvement \u00a0\u00a0\nExperience working on successful customer-centric work across physical and digital channels.\nExperience in research and analytical skills with great comfort in analyzing/ modelling data in Microsoft suite tools\u00a0\nExperience in stakeholder management, project management, meeting presentations and workshop facilitation\nUnderstanding of insurance products, market trends, customer demands \u00a0\nUnderstanding of Agile teams, processes, principles and ways of working\nProficient in Microsoft suite (e.g. Power Point, Excel, Word, MS Project)\nHolds a Diploma or University Degree", "employment_types": ["Full Time", "Permanent"], "selling_points": ["multimedia project planning,scheduling,monitoring", "with relevant project management experience", "5-day work, Tsuen Wan"], "locations": ["Tsuen Wan Area"], "categories": ["Information Technology (IT)", "IT Project Management / Team Lead", "Product Management / Business Analyst", "UI/UX Designer"], "post_time": "2022-01-05T06:48:48Z", "salary": {"currency": null, "max": null, "min": null, "period": "monthly", "term": null}, "salary_visible": false, "title_keywords": ["officer"], "responsibilities": ["provide insights", "management", "consulting", "customer complaints", "data", "operations", "workshop", "review", "measurement", "implementation", "design", "teams", "communication", "project management", "presentations", "plan", "customer data", "insurance"], "requirements": {"degrees": ["diploma", "university degree"], "majors": [], "languages": [], "language_level": [], "hard_skills": ["excel", "agile", "customer journeys", "word", "presentations", "analytical skills", "project management", "power point", "focus"], "soft_skills": ["flexible", "agile", "focused", "responsible", "accurate", "timely", "collaborative", "analytical skills", "communication", "project management", "committed", "motivated", "controlled", "customer focus", "leadership"], "languages_combined": []}, "experience_required": {"duration": ["minimum 6 years"], "field": ["management", "research", "consulting", "analytical", "design", "project management", "business", "it", "financial services", "digital", "insurance"]}}, {"job_id": "100003009031165", "location_code": "hk", "company": "Ztore HK Limited", "job_title": "Associate Product Manager", "description": "As the Senior UX Designer, you will be working with a team of designers and engineers to understand clients\u2019 requirements, to propose design solutions and to create remarkable apps and websites that deliver both business goals & user experience.\n\nWork Experience\nAt least 5 years of work experience in digital interaction design, encompassing websites as well as mobile app design.\n\nPractical UX know-how\nHave solid knowledge in the design process and ability to practice qualitative and quantitative design research, insights defining, persona modeling, customer journey and wireframe creation, as well as rapid prototyping.\n\nMobile User Interface & Interaction Design\nFigma and Adobe suite mastering is a must. Ability to apply mobile design patterns with platform-specific design consideration.\n\nEffective Communicator\nAbility to bring about effective & pleasant collaborations among clients, design and engineering team members.\n\nAbout Motherapp\u00a0\nWe\u2019re helping people live better lives \u2014 One digital experience at a time.\nFounded in 2008 by an original Google employee, we are one of the most experienced digital innovation and solution development companies in Hong Kong. Over the years, Motherapp has established a solid UX centric process and culture; Together with our mobile and AI expertise, Motherapp has been delighting our customers and delivering creative digital solutions that excel both in user experience and business results.\n\nApply Now\nAll candidates are requested to send a design portfolio along with their applications.\nLearn more about us at:\u00a0https://motherapp.com\nMotherapp\nMobile App Development, AI Application Hong Kong | Motherapp HK\nMotherapp offers smart mobile app development and AI application solutions in Hong Kong (HK). From apps to digital consulting, Motherapp has got your back.", "employment_types": ["Full Time"], "selling_points": ["Collaborate with Product designers & developers", "eCommerce project & product management", "Good product sense and strong interpersonal skill"], "locations": ["Lai Chi Kok"], "categories": ["Information Technology (IT)", "IT Project Management / Team Lead", "Marketing / Public Relations", "Marketing - Brand / Product Management", "UI/UX Designer"], "post_time": "2022-01-07T09:01:20Z", "salary": {"currency": null, "max": null, "min": null, "period": "monthly", "term": null}, "salary_visible": false, "title_keywords": ["associate", "product manager"], "responsibilities": ["business goals", "mobile app", "consulting", "design solutions", "user experience", "design", "user interface"], "requirements": {"degrees": [], "majors": [], "languages": [], "language_level": [], "hard_skills": ["excel", "ai", "mobile", "adobe", "rapid"], "soft_skills": ["communicator", "creative", "pleasant"], "languages_combined": []}, "experience_required": {"duration": ["at least 5 years"], "field": ["designer", "design", "business", "digital", "team"]}}]