[{"job_id": "100003009053647", "location_code": "hk", "company": "Arup", "job_title": "Resident Engineer", "description": "Qualifications & Experience required:\n\n\nDegree in Civil/Geotechnical/Structural engineering or related discipline\nRecognized engineering chartered qualification with 2 years of post-chartered experience\nFamiliar with common practice in foundation, site formation, reinforced concrete and structural steel construction for private development projects\nBe adaptable and able to work independently with strong interpersonal skills\nProficient in both written and spoken English and Chinese\n\n\n\nThe above positions based in Macau will be on contract basis to work on a big building project. The contract is approximately 12 months which may be lengthened or shortened subject to project development. Standard working hours will be 6 days per week, shift work may be required. Attractive remuneration package with gratuity will be offered to the successful candidate.\n\nFor interested applicants, please click \"Apply Now\" \u00a0to submit your online application.\nTo explore more job opportunities in Arup, please visit our website at http://www.arup.com/Careers/Experienced_Hires/ApplyForAJob\n\u00a0\nPersonal data collected will be used for recruitment purpose only. Applicants not contacted within 8 weeks may consider their applications unsuccessful.", "employment_types": ["Full Time", "Contract"], "selling_points": [], "locations": ["Others - Macau"], "categories": ["Building & Construction", "Civil / Structural", "Engineering", "Others", "Others"], "post_time": "2022-01-17T07:17:54Z", "salary": {"currency": null, "max": null, "min": null, "period": null, "term": null}, "salary_visible": false, "title_keywords": ["resident engineer"], "responsibilities": ["personal data", "recruitment", "website"], "requirements": {"degrees": ["degree"], "majors": ["structural engineering"], "languages": ["english", "chinese"], "language_level": ["proficient"], "hard_skills": [], "soft_skills": ["adaptable", "work independently", "interpersonal skills"], "languages_combined": [{"language": "english", "language_level": ["proficient"]}, {"language": "chinese", "language_level": ["proficient"]}]}, "experience_required": {"duration": ["2 years"], "field": ["engineering"]}}, {"job_id": "100003009052958", "location_code": "hk", "company": "David S. K. Au & Associates Ltd", "job_title": "Assistant Engineer (Civil/Geotechnical)", "description": "Degree holder in Civil/Geotechnical Engineering\n2 year's post graduate experience for the position of Assistant Engineer\nFresh Graduates will also be considered\u00a0", "employment_types": ["Full Time", "Permanent"], "selling_points": [], "locations": ["North Point"], "categories": ["Building & Construction", "Civil / Structural"], "post_time": "2022-01-17T04:42:23Z", "salary": {"currency": null, "max": null, "min": null, "period": "monthly", "term": null}, "salary_visible": false, "title_keywords": ["assistant engineer"], "responsibilities": [], "requirements": {"degrees": ["degree holder"], "majors": ["engineering"], "languages": [], "language_level": [], "hard_skills": [], "soft_skills": [], "languages_combined": []}, "experience_required": {"duration": ["2 year"], "field": []}}, {"job_id": "100003009048792", "location_code": "hk", "company": "Active Way Ltd", "job_title": "Design Engineer / Assistant Design Engineer/ Draftsman", "description": "Responsibilities:\n\nCollaborate and coordinate design issues with various departments and parties;\nLiaise with architects, consultants and contractors to produce CSD, CBWD and related drawings;\nReporting to management team regarding BIM coordination progress, drawing production progress and BIM generated data;\nImplement BIM standards and processes;\nConduct BIM coordination meetings;\nAdhere to BIM execution plan and BIM project workflow criteria;\nEnsure accuracy of construction documents.\n\nRequirements:\n\nHigher diploma or above in Building Services Engineering or equivalent;\nAt Least 5 years with M&E CSD coordination experience is a must;\nProfessional Membership of HKIBIM is preferable;\nKnowledge of BIM (Revit) and experience in executing BIM-enabled projects will be a plus;\nCommercial experience regarding MEP work trades procurement and execution is preferred;\nExperience in implementing new technologies to construction work and experience with AEC design professions will be a plus;\nIndependent, able to work under pressure and adapt to site working environment;\nGood command of spoken and written in English, Chinese and Putonghua.\n\nCompetitive remuneration package will be offered to successful candidates.\u00a0 To apply, please send your application with a full resume including current and expected salary, and availability to Corporate Human Services Department, 8/F, KOHO, 73-75 Hung To Road, Kwun Tong, Kowloon, Hong Kong or by clicking 'Apply Now' (Please quote the job reference number and job title on the subject).\n\nFor more details, please visit our company website www.hipseng.com\n\nApplicants not invited for interview within 8 weeks may consider their applications unsuccessful. Personal data provided by job applicants will be used strictly in accordance with the company\u2019s personal data policy.", "employment_types": ["Full Time"], "selling_points": ["Knowledge in fabrication, installation, coordinate", "2 years of experience in Structural Steel, Glazing", "Graduate of B.Sc/ Dip in Civil/ Mech &Engineering"], "locations": ["Quarry Bay"], "categories": ["Design", "Others", "Building & Construction", "Civil / Structural", "Engineering", "Manufacturing & Production"], "post_time": "2022-01-14T07:24:57Z", "salary": {"currency": null, "max": null, "min": null, "period": "monthly", "term": null}, "salary_visible": false, "title_keywords": ["draftsman", "assistant", "design engineer"], "responsibilities": ["collaborate", "reporting", "management team", "data", "design", "drawings", "coordinate", "coordination", "plan", "liaise with"], "requirements": {"degrees": ["higher diploma or above"], "majors": ["building services", "engineering"], "languages": ["putonghua", "english", "chinese"], "language_level": ["good command"], "hard_skills": ["bim", "plus", "revit"], "soft_skills": ["independent", "coordination", "work under pressure"], "languages_combined": [{"language": "putonghua", "language_level": ["good command"]}, {"language": "english", "language_level": ["good command"]}, {"language": "chinese", "language_level": ["good command"]}]}, "experience_required": {"duration": ["at least 5 years"], "field": ["commercial", "construction", "procurement", "design"]}}, {"job_id": "100003009052351", "location_code": "hk", "company": "K. H. Foundations Ltd.", "job_title": "Assistant Engineer", "description": "Responsibilities:\n\nResponsible for interpreting and raising issues regarding the implementation and construct ability\u00a0of design;\nExecute day-to-day engineering work, supervision of work progress and co-ordination of various activities at construction projects;\nProvide on-site engineering and coordination support during the construction phase, prepare construction method for various site activities, write method statements, monitor and manage the progress of works and provide regular progress reports.\n\nRequirements:\n\nDegree in Building / Structural Engineering or equivalent;\nMinimum\u00a05 years\u2019 site working experience in building projects ranging from commercial high-rise to hotel and retail structures;\nExperience in building / structural work co-ordination will be an advantage;\u00a0\nFlexible, self-motivated and able to work under pressure;\nExcellent command of spoken and written English and Chinese.\u00a0\n\n** Candidates with\u00a0more experience will be considered as Project Engineer.\n\nCompetitive remuneration package will be offered to successful candidates. To apply, please send your application with a full resume including current and expected salary, and availability to\u00a0Corporate Human Services Department, 8/F,\u00a0KOHO, 73 - 75 Hung To Road, Kwun Tong, Kowloon, Hong Kong\u00a0or by clicking\u00a0'Apply Now'\u00a0(Please quote the job reference number and job title on the subject).\n\nFor more details, please visit our company website\u00a0\u00a0www.hipseng.com\n\nApplicants not invited for interview within 8 weeks may consider their applications unsuccessful. Personal data provided by job applicants will be used strictly in accordance with the company\u2019s personal data policy.", "employment_types": ["Full Time", "Permanent"], "selling_points": [], "locations": ["Not Specified"], "categories": ["Building & Construction", "Building / Construction / QS", "Civil / Structural", "Engineering", "Engineering Project Management"], "post_time": "2022-01-17T02:50:00Z", "salary": {"currency": null, "max": null, "min": null, "period": "monthly", "term": null}, "salary_visible": false, "title_keywords": ["assistant engineer"], "responsibilities": ["site activities", "progress reports", "monitor", "implementation", "design", "coordination"], "requirements": {"degrees": ["degree"], "majors": ["structural engineering"], "languages": ["english", "chinese"], "language_level": ["excellent"], "hard_skills": [], "soft_skills": ["flexible", "self-motivated", "work under pressure"], "languages_combined": [{"language": "english", "language_level": ["excellent"]}, {"language": "chinese", "language_level": ["excellent"]}]}, "experience_required": {"duration": ["minimum 5 years"], "field": ["commercial", "structural", "retail"]}}, {"job_id": "100003009054992", "location_code": "hk", "company": "BeFrank Engineering Consultant Limited", "job_title": "Assistant Structural Engineer", "description": "Responsibilities:\n\n\nAssist in project research and case studies;\n\nData / information collection from different fields of knowledge to support the need of assigned projects;\n\nAssist in data analyzing, writing proposal/report and preparing PowerPoint presentation;\n\nPrepare executive summary of specific documentation for management;\n\nProvide administrative support to the department;\n\nHandle ad hoc duties as assigned.\n\nRequirements:\n\nDegree in Business Studies / Social Sciences / Humanitiesor others related discipline;\n\nInquisitive in research, excellent analytical and organization skills;\n\nCreative, innovative, open-minded and passionate to learn new thing;\n\nGood communication and presentation skill;\n\nGood command of written and spoken English and Chinese.\n\n\n\nCompetitive remuneration package will be offered to successful candidates. To apply, please send your application with a full resume including\u00a0current and expected salary, and availability to\u00a0Corporate Human Services Department, 8/F,\u00a0KOHO, 73 - 75 Hung To Road, Kwun Tong, Kowloon, Hong Kong\u00a0or by clicking\u00a0'Apply Now'\u00a0(Please quote the job reference number and job title on the subject).\n\nFor more details, please visit our company website www.hipseng.com\n\nApplicants not invited for interview within 8 weeks may consider their applications unsuccessful. Personal data provided by job applicants will be used strictly in accordance with the company\u2019s personal data policy.", "employment_types": ["Full Time"], "selling_points": ["HD / Degree in Structural or Civil Engineering", "Competitive salary, medical insurance, bonus", "1 year or above experience in structural design"], "locations": ["Central"], "categories": ["Building & Construction", "Civil / Structural", "Engineering", "Engineering Project Management", "Others"], "post_time": "2022-01-17T16:22:49Z", "salary": {"currency": null, "max": null, "min": null, "period": "monthly", "term": null}, "salary_visible": false, "title_keywords": ["engineer", "assistant"], "responsibilities": ["ad hoc duties", "management", "data", "documentation", "provide administrative support", "report"], "requirements": {"degrees": ["degree"], "majors": ["business", "social sciences"], "languages": ["english", "chinese"], "language_level": ["good command"], "hard_skills": ["presentation skill"], "soft_skills": ["passionate", "presentation skill", "open-minded", "innovative", "communication", "organization skills", "creative"], "languages_combined": [{"language": "english", "language_level": ["good command"]}, {"language": "chinese", "language_level": ["good command"]}]}, "experience_required": {"duration": [], "field": []}}, {"job_id": "100003009048307", "location_code": "hk", "company": "Wings & Associates Consulting Engineers Limited", "job_title": "Engineer / Assistant Engineer", "description": "Responsibilities:\n\nPrepare structural designs for fa\u00e7ade system and related structure\nProvide befitting structural calculation and analysis\nClosely work with Hong Kong & PRC team in carrying out structural designs and other works\nPerform ad-hoc assignments as required\nRequirements:\n\nHigher Diploma or above, major in Civil and Structural Engineering or equivalent\n\n3 years or above relevant experience in fa\u00e7ade design, aluminium\u00a0structure and construction of curtain wall and other fa\u00e7ade elements\nKnowledgeable in structural analysis, fa\u00e7ade systems and materials such as glass, aluminium, steel etc.\n\nProficiency in SAP2000/ Strand7 and knowledge in AutoCAD is preferred\nMore experience will be considered as Structural Manager or Assistant Structural Manager", "employment_types": ["Full Time", "Permanent"], "selling_points": ["5-day work, Medical Allowance, Performance Bonus", "Happy Work Environment, Dynamic Team", "Good Career Prospects and Personal Development"], "locations": ["Kwun Tong"], "categories": ["Building & Construction", "Building / Construction / QS", "Civil / Structural", "Engineering", "Engineering Project Management"], "post_time": "2022-01-14T06:12:10Z", "salary": {"currency": null, "max": null, "min": null, "period": "monthly", "term": null}, "salary_visible": false, "title_keywords": ["assistant engineer", "engineer"], "responsibilities": ["ad-hoc assignments", "analysis"], "requirements": {"degrees": ["higher diploma or above"], "majors": ["structural engineering"], "languages": [], "language_level": [], "hard_skills": ["analysis", "sap2000", "autocad"], "soft_skills": [], "languages_combined": []}, "experience_required": {"duration": ["3 years"], "field": ["structural", "relevant experience", "construction", "design"]}}, {"job_id": "100003009053373", "location_code": "hk", "company": "Able Engineering Company Limited", "job_title": "Assistant Resident Engineer", "description": "Responsibilities:\n\n\nBuild up BIM database (Revit) from design drawings for construction;\nGenerate 2D ISD, CSD and various construction drawing (ACAD dwg) and data (e.g. xls) from BIM;\nAssist BIM engineer to resolve design/build problems identified within the BIM platform;\nPrepare materials (e.g. model, ppt, reports) to assist BIM engineer to fulfill coordination and collaboration processes;\nProvide hands-off training to general user in reviewing BIM contents;\nAssist BIM engineer to manage BIM data input/output through in-house propriety online collaboration platforms.\n\nRequirements:\n\n\nHigher Certificate or above in Building Services Engineering or Mechanical Engineering;\nExperience of MEP BIM (Revit) modeling will be a must;\nExperience with M&E CSD coordination and/or AutoCAD is a plus;\u00a0\u00a0\u00a0\u00a0\u00a0\nWilling to learn and use new tools;\nIndependent and be able to work under pressure;\nGood command of spoken and written in English and Chinese.\n\nCompetitive remuneration package will be offered to successful candidates. To apply, please send your application to \u00a0Corporate Human Services Department, 8/F,\u00a0KOHO, 73 - 75 Hung To Road, Kwun Tong, Kowloon, Hong Kong\u00a0or by clicking\u00a0'Apply Now'\u00a0(Please quote the job reference number and job title on the subject).\n\nFor more details, please visit our company website\u00a0www.hipseng.com\u00a0.\n\nApplicants not invited for interview within 8 weeks may consider their applications unsuccessful.\u00a0Personal data provided by job applicants will be used strictly in accordance with the company\u2019s personal data policy.\n\n", "employment_types": ["Full Time", "Permanent"], "selling_points": [], "locations": ["Not Specified"], "categories": ["Building & Construction", "Civil / Structural", "Engineering", "Others", "Others"], "post_time": "2022-01-17T06:52:31Z", "salary": {"currency": null, "max": null, "min": null, "period": "monthly", "term": null}, "salary_visible": false, "title_keywords": ["assistant resident engineer"], "responsibilities": ["data", "design drawings", "data input", "design", "contents", "reports", "database", "coordination"], "requirements": {"degrees": ["higher certificate"], "majors": ["building services", "engineering", "mechanical engineering"], "languages": ["english", "chinese"], "language_level": ["good command"], "hard_skills": ["bim", "autocad", "plus", "revit"], "soft_skills": ["independent", "willing to learn", "coordination", "work under pressure"], "languages_combined": [{"language": "english", "language_level": ["good command"]}, {"language": "chinese", "language_level": ["good command"]}]}, "experience_required": {"duration": [], "field": []}}, {"job_id": "100003009053264", "location_code": "hk", "company": "Arup", "job_title": "Senior Resident Engineer/ Resident Engineer/Assistant Resident Engineer", "description": "Responsibilities\n\nPerform system architecture & functional designs by providing seasoned technical advices with high level of technical competency on system development\nSupervise and motivate a team of Software Engineers to deliver in-house and outsource projects throughout whole System Development Life Cycle (SDLC) on time and in a good quality\nManage project resources, schedules, risks, changes requests, and UAT\nDevelop related technical designs, standards, best practices, policies and procedures to ensure\u00a0software quality\nProvide on-going system support, maintenance and incident management\nKeep abreast of\u00a0new technologies and solutions to add value for business\n\nRequirements\n\nDegree or above in Computer Engineering / Computer Science / Information Technology or related discipline\nMinimum 7 years solid\u00a0experience in system development and project management\nExperience in web front-end / server-side / API development\nWorking knowledge of enterprise high-availability applications, mobile application, Linux system administration, database design, Docker, Kubernetes, DevOps and CI/CD would be an advantages\nProgramming skills: C#, JavaScript, HTML5, jQuery, Restful API, AJAX, JSON, XML, MS SQL, and MySQL\nProactive, independent and well organized with strong business sense\n\nCompetitive remuneration package will be offered to successful candidates. To apply, please send your application with a full resume including\u00a0current\u00a0and\u00a0expected salary, and availability to\u00a0Corporate Human Services Department, 8/F,\u00a0KOHO, 73 - 75 Hung To Road, Kwun Tong, Kowloon, Hong\u00a0Kong\u00a0or by clicking\u00a0'Apply Now'\u00a0(Please quote the job reference number and job title on the subject).\n\nFor more details, please visit our company website\u00a0www.hipseng.com\n\nApplicants not invited for interview within 8 weeks may consider their applications unsuccessful. Personal data provided by job applicants will be used strictly in accordance with the company\u2019s personal data policy.", "employment_types": ["Full Time", "Contract"], "selling_points": [], "locations": ["Not Specified"], "categories": ["Building & Construction", "Building / Construction / QS", "Civil / Structural"], "post_time": "2022-01-17T06:36:57Z", "salary": {"currency": null, "max": null, "min": null, "period": null, "term": null}, "salary_visible": false, "title_keywords": ["assistant resident engineer", "resident engineer"], "responsibilities": ["management", "software", "uat", "maintenance", "schedules", "policies", "quality", "procedures", "develop", "architecture"], "requirements": {"degrees": ["degree or above"], "majors": ["computer engineering", "computer science", "information technology"], "languages": [], "language_level": [], "hard_skills": ["linux", "restful api", "web", "devops", "jquery", "project management", "mobile", "javascript", "programming", "ajax", "server", "ms sql", "c#"], "soft_skills": ["independent", "business sense", "well organized", "project management", "proactive"], "languages_combined": []}, "experience_required": {"duration": ["minimum 7 years"], "field": ["project management", "development", "system development"]}}, {"job_id": "100003009052180", "location_code": "hk", "company": "Aecom Asia Company Limited", "job_title": "Assistant Resident Engineer (Shau Kei Wan \u2013 TCP T3-DW/GIFW)", "description": "Responsibilities\n\nDevelop, maintain and support the websites and/or web-based application for desktop and mobile (front-end)\nWork closely with a team of UX/UI Designer, Software and Web Developer, as well as external vendors, to deliver best-in-class user experience\nCollect and analyze user requirements and ensure standards, procedures, and methodologies in the development life cycle are followed\nIdentify front-end coding issues and provide quick fix solutions\nApply industry best practice & setup the HTML5 / CSS3 / JavaScript standard\nDesign, document, and recommend technical solutions to facilitate sharing of the IT resources wherever feasible\n\nRequirements\n\nHigher Diploma or above in Computing / Computer Science / Information Systems or related disciplines\nRelated experience in web application and mobile app development (iOS / Android)\nWell-versed programming skills on HTML5, JavaScript, CSS3, JQuery, Bootstrap, Vue.js, React, Angular or other popular JS framework; have native or hybrid App development experience is a plus\nExperience in web services using markup languages like JSON and REST API or Android app development, Java / C#, CI/CD and DevOps is a plus\nStrong OOP skills with intention to write clean and maintainable code\nEnergetic and passionate; Willing to stay up-to-date on new technologies and advancements\n\nCompetitive remuneration package will be offered to successful candidates. To apply, please send your application with a full resume including\u00a0current\u00a0and\u00a0expected salary, and availability to\u00a0Corporate Human Services Department, 8/F,\u00a0KOHO, 73 - 75 Hung To Road, Kwun Tong, Kowloon, Hong\u00a0Kong\u00a0or by clicking\u00a0'Apply Now'\u00a0(Please quote the job reference number and job title on the subject).\n\nFor more details, please visit our company website\u00a0www.hipseng.com\n\nApplicants not invited for interview within 8 weeks may consider their applications unsuccessful. Personal data provided by job applicants will be used strictly in accordance with the company\u2019s personal data policy.\n", "employment_types": ["Full Time", "Contract"], "selling_points": ["Min. 5 years for HD/2 years for Bachelor candidate", "Exp. in Demolition Works", "RSE/RGE T3 and both the RSE/RGE\u2019s representative"], "locations": ["Shatin Area"], "categories": ["Building & Construction", "Civil / Structural", "Engineering", "Others"], "post_time": "2022-01-17T02:22:00Z", "salary": {"currency": null, "max": null, "min": null, "period": "monthly", "term": null}, "salary_visible": false, "title_keywords": ["assistant resident engineer"], "responsibilities": ["software", "procedures", "user experience", "coding", "develop", "design", "maintain", "ui", "setup"], "requirements": {"degrees": ["higher diploma or above"], "majors": ["related disciplines", "computer science"], "languages": [], "language_level": [], "hard_skills": ["clean", "plus", "java", "web", "react", "jquery", "devops", "mobile", "javascript", "programming", "angular", "code", "web services", "android", "c#"], "soft_skills": ["passionate", "energetic"], "languages_combined": []}, "experience_required": {"duration": [], "field": ["related", "development", "devops"]}}, {"job_id": "100003009055325", "location_code": "hk", "company": "Unistress Building Construction Limited", "job_title": "Assistant Project Coordinator / Assistant Engineer", "description": "Responsibilities\n\nAssess and analyze business requirements and ensure proper application technical documentations\nTake the lead among programmers, by demonstrating strong hands-on programming skills and conducting design and code review, to design and build advanced, scalable applications for web and mobile applications\nIntegrate with backend services (JSON, REST etc.) to ensure high quality of application deliverable\nProvide supports on UAT and perform program unit testing\nProvide user trainings and application supports.\n\n\u00a0Requirements\n\nHigher Diploma or above in Computer Science/ Software Engineering /IT related disciplines\nMinimum 5 years of hands-on experiences in large-scale system\u2019s analysis, design and development\nWell-versed programming skills on C#, ASP.NET MVC/Core framework about Win Application, Web Form and API development\nExperience in development database solution by using SQL Queries, Stored Procedures programming on RDBMS (MSSQL/MySQL) and NoSQL; SSRS knowledge will be an advantage\nSelf-driven, proactive, with strong sense of responsibility and able to work independently\n\nCompetitive remuneration package will be offered to successful candidates. To apply, please send your application with a full resume including\u00a0current\u00a0and\u00a0expected salary, and availability to\u00a0Corporate Human Services Department, 8/F,\u00a0KOHO, 73 - 75 Hung To Road, Kwun Tong, Kowloon, Hong\u00a0Kong\u00a0or by clicking\u00a0'Apply Now'\u00a0(Please quote the job reference number and job title on the subject).\n\nFor more details, please visit our company website\u00a0www.hipseng.com\n\nApplicants not invited for interview within 8 weeks may consider their applications unsuccessful. Personal data provided by job applicants will be used strictly in accordance with the company\u2019s personal data policy.", "employment_types": ["Full Time", "Permanent"], "selling_points": ["High Cert / Higher Dip / Degree in BuildingStudies", "Relevant 2 years site working experience", "Hard working and good interpersonal skill"], "locations": ["Not Specified"], "categories": ["Building & Construction", "Building / Construction / QS", "Civil / Structural", "Engineering", "Engineering Project Management"], "post_time": "2022-01-18T02:11:33Z", "salary": {"currency": null, "max": null, "min": null, "period": "monthly", "term": null}, "salary_visible": false, "title_keywords": ["assistant project coordinator", "assistant engineer"], "responsibilities": ["uat", "review", "quality", "design", "testing"], "requirements": {"degrees": ["higher diploma or above"], "majors": ["related disciplines", "it", "software engineering", "computer science"], "languages": [], "language_level": [], "hard_skills": ["web", "analysis", "sql", "programming", "mssql", "c#"], "soft_skills": ["work independently", "sense of responsibility", "hands-on", "proactive", "driven"], "languages_combined": []}, "experience_required": {"duration": ["minimum 5 years"], "field": ["development", "design", "sql", "programming", "database"]}}, {"job_id": "100003009052071", "location_code": "hk", "company": "Meinhardt Consulting Engineers", "job_title": "Site Supervision Engineer (Ref: 88088T6)", "description": "Responsibilities:\n\n\n\nDay-to-day site inspections and checks on compliance with drawings, specifications and working procedures as necessary\nCarry out relevant design checking and method statement checking\nLiaise with internal design team and external clients\n\nQualifications & Requirements:\n\n\nDegree holder in Geotechnical / Civil Engineering with 2+ years of relevant working experience\nFamiliar with Technically Competent Persons (TCP) requirements and duties\nLooking for progressive challenges and opportunities\nStrong analytical mind set and problem solving skills\nGood command of written English\nShould be detail-oriented, discipline and self-motivated\nGood team player with high degree of commitment to complete works\nFamiliar with structural design software is an advantage\n\n\u00a0Please send your full resume with expected salary and availability(quoting reference number) to:\n\nHuman Resources Manager\nMeinhardt Consulting Engineers\n10/F Genesis, 33-35 Wong Chuk Hang Road, Hong Kong\n\nOR send e-mail by clicking \"Apply Now\" \u00a0\u00a0\u00a0 http://www.meinhardtgroup.com\n\nCandidates who have not been contacted within 8 weeks of their date of application may assume their application has been unsuccessful. Data collected will be used for recruitment purpose only and will be destroyed after six months from date of application.", "employment_types": ["Full Time", "Permanent"], "selling_points": [], "locations": ["Not Specified"], "categories": ["Building & Construction", "Civil / Structural", "Engineering", "Engineering Project Management", "Others"], "post_time": "2022-01-17T02:01:43Z", "salary": {"currency": null, "max": null, "min": null, "period": "monthly", "term": null}, "salary_visible": false, "title_keywords": ["engineer"], "responsibilities": ["compliance", "procedures", "checking", "design", "drawings", "specifications", "site inspections", "liaise with"], "requirements": {"degrees": ["degree", "degree holder"], "majors": ["civil engineering"], "languages": ["english"], "language_level": ["good command"], "hard_skills": ["problem solving skills", "tcp"], "soft_skills": ["self-motivated", "good team player", "competent", "detail-oriented", "analytical mind", "progressive", "problem solving skills"], "languages_combined": [{"language": "english", "language_level": ["good command"]}]}, "experience_required": {"duration": ["2+ years"], "field": ["relevant working experience", "engineering"]}}, {"job_id": "100003009051383", "location_code": "hk", "company": "Aecom Asia Company Limited", "job_title": "Associate/Sr Engineer/Project Engineer/Engineer -Land Supply Municipal", "description": "Job Duties\n\n\nProject management and co-ordination of civil infrastructure projects\nPrepare engineering design including roadworks, utilities, drainage / sewerage / water supply, etc.\nConduct technical assessments and report preparation\nCoordinate amongst project teams and clients to facilitate project implementation\nSupervise junior engineers in terms of work allocation, training, and problem resolution\nParticipate in technical proposal preparation, prepare tender documents and tendering assistance\nParticipate in interdisciplinary review of project deliverables.\nCarry out duties in accordance with quality and environmental management system, health and safety policies and procedures, report any potential risk and problem to immediate supervisor\n\n\nJob Requirements\n\n\nA recognized degree in Civil / Structural Engineering or equivalent\nCorporate member of the Hong Kong Institution of Engineers or equivalent in relevant disciplines or equivalent\nMinimum 10 and 5 years post-qualification experience in project management / design of civil infrastructure projects for Associate and Senior Engineer respectively. Candidates with less experience may be considered for a Project Engineer or Engineer position.\nStrong oral and writing abilities in both Chinese (Cantonese and / or Putonghua) and English\nStrong sense of leadership and accountability\nStrong analytical skills, ability to identify problems and propose solutions\nSelf-motivated with high personal drive for achieving targets and business goals\nTeam player with excellent interpersonal and communication skills\nCandidate with no professional qualification would be considered as Assistant Engineer\n\nAECOM is a place where you can put your innovative thinking and business skills into high gear and work alongside other highly intelligent and motivated people. It's a place where you can apply your skills to some of the world's most challenging, interesting, and meaningful projects worldwide. It's a place that values the diversity of our areas of practice and our people. It's what makes AECOM a great place to work and grow. AECOM is an Equal Opportunity Employer.\n\n\nFor more information on AECOM, please visit our website at www.aecom.com.\u00a0", "employment_types": ["Full Time", "Permanent"], "selling_points": ["Co-ordination of civil infrastructure projects", "A recognized degree in Civil Engineer", "Chartered Status to HKIE or equivalent"], "locations": ["Shatin Area"], "categories": ["Building & Construction", "Building / Construction / QS", "Civil / Structural", "Engineering", "Engineering Project Management"], "post_time": "2022-01-15T13:17:05Z", "salary": {"currency": null, "max": null, "min": null, "period": "monthly", "term": null}, "salary_visible": false, "title_keywords": ["associate", "engineer", "project engineer"], "responsibilities": ["management", "engineering design", "project deliverables", "prepare tender documents", "policies", "infrastructure", "teams", "implementation", "tendering", "review", "coordinate", "project management", "resolution", "quality", "procedures", "report"], "requirements": {"degrees": ["degree"], "majors": ["structural engineering"], "languages": ["cantonese", "putonghua", "english", "chinese"], "language_level": [], "hard_skills": ["project management", "no", "the hong kong institution of engineers", "analytical skills"], "soft_skills": ["communication skills", "oral", "self-motivated", "accountability", "analytical skills", "project management", "motivated", "team player", "innovative", "leadership", "interpersonal"], "languages_combined": [{"language": "cantonese", "language_level": []}, {"language": "putonghua", "language_level": []}, {"language": "english", "language_level": []}, {"language": "chinese", "language_level": []}]}, "experience_required": {"duration": ["5 years"], "field": ["post-qualification", "senior engineer", "infrastructure", "design", "project management"]}}, {"job_id": "100003009047803", "location_code": "hk", "company": "New World Construction Company Limited", "job_title": "Project Engineer / Engineer (Ref: JDB/PE/E/20220114)", "description": "Responsibilities:\n\nResponsible for interpreting and raising issues regarding the implementation and construct ability\u00a0of design;\nExecute day-to-day engineering work, supervision of work progress and co-ordination of various activities at construction projects;\nProvide on-site engineering and coordination support during the construction phase, prepare construction method for various site activities, write method statements, monitor and manage the progress of works and provide regular progress reports.\n\nRequirements:\n\nDegree in Building / Structural Engineering or equivalent;\nMinimum\u00a05 years\u2019 site working experience in building projects ranging from commercial high-rise to hotel and retail structures;\nExperience in building / structural work co-ordination will be an advantage;\u00a0\nFlexible, self-motivated and able to work under pressure;\nExcellent command of spoken and written English and Chinese.\u00a0\n\n** Candidates with\u00a0more experience will be considered as Project Engineer.\n\nCompetitive remuneration package will be offered to successful candidates. To apply, please send your application with a full resume including current and expected salary, and availability to\u00a0Corporate Human Services Department, 8/F,\u00a0KOHO, 73 - 75 Hung To Road, Kwun Tong, Kowloon, Hong Kong\u00a0or by clicking\u00a0'Apply Now'\u00a0(Please quote the job reference number and job title on the subject).\n\nFor more details, please visit our company website\u00a0\u00a0www.hipseng.com\n\nApplicants not invited for interview within 8 weeks may consider their applications unsuccessful. Personal data provided by job applicants will be used strictly in accordance with the company\u2019s personal data policy.", "employment_types": ["Full Time", "Permanent"], "selling_points": ["Building / Structural Engineering", "Building / Structural work coordination", "5 years\u2019 on site experience in building projects"], "locations": ["Not Specified"], "categories": ["Building & Construction", "Building / Construction / QS", "Civil / Structural", "Others"], "post_time": "2022-01-14T03:56:28Z", "salary": {"currency": null, "max": null, "min": null, "period": "monthly", "term": null}, "salary_visible": false, "title_keywords": ["engineer", "project engineer"], "responsibilities": ["site activities", "progress reports", "monitor", "implementation", "design", "coordination"], "requirements": {"degrees": ["degree"], "majors": ["structural engineering"], "languages": ["english", "chinese"], "language_level": ["excellent"], "hard_skills": [], "soft_skills": ["flexible", "self-motivated", "work under pressure"], "languages_combined": [{"language": "english", "language_level": ["excellent"]}, {"language": "chinese", "language_level": ["excellent"]}]}, "experience_required": {"duration": ["minimum 5 years"], "field": ["commercial", "structural", "retail"]}}, {"job_id": "100003009049587", "location_code": "hk", "company": "Build King Holdings Ltd", "job_title": "Senior Site Engineer / Site Engineer - Civil (Ref:JD/SSE)", "description": "Degree holder in Civil Engineering\u00a0or related disciplines;\nChartered Engineer with Corporate membership of HKIE in Civil Discipline is an advantage;\nMinimum 4-7 years' practical experience in civil projects;\nCommitted to the achievement of the highest standards in all construction activities including safety and quality assurance;\nProven team leadership and contractual awareness;\nGood communication skills;\nCandidates with less experience will be considered\u00a0as Site Engineer.\n\nPlease send your application with full resume and expected salary to\u00a0Human Resources Department, Units 601-605A, 6/F,\u00a0Tower\u00a0B, Manulife Financial Centre, 223 Wai\u00a0Yip Street, Kwun Tong, Kowloon,\u00a0Hong Kong\u00a0(please quote the job reference number and job title on the subject)\u00a0or\u00a0by clicking\u00a0Job Application\u00a0or \"APPLY NOW\".\n\nPlease visit our website\u00a0http://www.buildking.hk/eng/whats-new/#whats-new/2021/1\u00a0for more details.\n\n(Personal data collected will be used for recruitment-related purposes only.)", "employment_types": ["Full Time", "Permanent"], "selling_points": ["Large-scale civil project", "Good career progression", "Performance bonus"], "locations": ["Not Specified"], "categories": ["Building & Construction", "Building / Construction / QS", "Civil / Structural"], "post_time": "2022-01-14T08:54:37Z", "salary": {"currency": null, "max": null, "min": null, "period": "monthly", "term": null}, "salary_visible": false, "title_keywords": ["site engineer"], "responsibilities": ["quality", "website", "communication", "recruitment", "personal data"], "requirements": {"degrees": ["degree holder"], "majors": ["related disciplines", "civil engineering"], "languages": [], "language_level": [], "hard_skills": ["hkie"], "soft_skills": ["communication skills", "committed", "leadership"], "languages_combined": []}, "experience_required": {"duration": ["minimum 4-7 years"], "field": ["civil projects"]}}, {"job_id": "100003009048539", "location_code": "hk", "company": "Kum Shing Group", "job_title": "Site Agent / Senior Project Engineer - Civil (Power Plant)", "description": "Reporting to the direct supervisor, the appointee will be responsible for but not limited to the following:\n\nResponsibilities:\n\nAssist Project Leader(s) on project planning, execution, monitoring and coordination;\nPrepare tender / project reports and technical submissions;\nRecord and report contractual disputes and variation orders;\nSupervise site safety and work quality to ensure meeting SHEQ standard of client and other regulatory authorities;\nLiaise with relevant authorities, clients, stakeholders and sub-contractors to ensure smooth and timely completion of projects;\nManage the necessary statutory permit application process.\n\nRequirements - Qualification:\n\nHigher diploma holder or above in Civil Engineering disciplines;\nMinimum 4 years of relevant working experience;\nCandidates with less experiences could be considered as Assistant Engineer;\nHolder of Valid green card;\nWith driving license (Class 1 and 2) is preferred;\nProficiency in Microsoft Office, Microsoft Project, Chinese word processing and AutoCAD;\nGood command of both written and spoken English and Chinese.\n\n\u00a0Requirements \u2013 Competences:\n\n\u00a0Good communication and interpersonal skills.\n\nBenefits:\n\nEmployee and dependent medical & dental plan;\nDiscretionary\u00a0Performance bonus;\nContinuing Education Allowance;\nLeave for special occasions (e.g. Examination, Volunteering, Marriage).\n\nWe look forward to receiving your application with detailed resume stating\u00a0working experience,\u00a0academic and language qualifications, existing and EXPECTED SALARY\u00a0as well as\u00a0availability.\u00a0All applications will be kept strictly confidential.\n\nWe offer promising professional career and exposure\u00a0to right candidate, together with attractive remuneration package including\u00a0discretionary bonus, continuing education allowance, medical and dental coverage.\n\nPersonal Data collected will be used for recruitment-related purposes only.", "employment_types": ["Full Time", "Permanent"], "selling_points": ["Performance bonus, education subsidy, medical plan", "Excellent career path", "Participate in project planning & site supervision"], "locations": ["Tuen Mun Area"], "categories": ["Building & Construction", "Building / Construction / QS", "Civil / Structural", "Engineering", "Others"], "post_time": "2022-01-14T06:45:25Z", "salary": {"currency": null, "max": null, "min": null, "period": "monthly", "term": null}, "salary_visible": false, "title_keywords": ["site agent", "senior project engineer"], "responsibilities": ["project planning", "monitoring", "permit application process", "project reports", "supervise site safety", "work quality", "tender", "coordination", "liaise with", "report"], "requirements": {"degrees": ["higher diploma holder"], "majors": ["civil engineering"], "languages": ["english", "chinese"], "language_level": ["proficiency", "good command"], "hard_skills": ["microsoft project", "chinese word processing", "microsoft office", "green card", "autocad"], "soft_skills": ["communication and interpersonal skills"], "languages_combined": [{"language": "english", "language_level": ["good command"]}, {"language": "chinese", "language_level": ["proficiency", "good command"]}]}, "experience_required": {"duration": ["minimum 4 years"], "field": ["relevant working experience"]}}, {"job_id": "100003009052069", "location_code": "hk", "company": "Meinhardt Consulting Engineers", "job_title": "Senior Engineer  (Ref: 88082T2)", "description": "Degree holder in Civil Engineering or equivalent with relevant professional qualification such as MHKIE / MICE\nMinimum 5 years\u2019 working experience in drainage / sewerage / waterworks projects for public and private projects\nSelf-motivated, logical and systematic thinkers\nGood communication skills and proficient in written and spoken English and Chinese\nPlease send your full resume with expected salary and availability(quoting reference number) to:\n\n\nHuman Resources Manager\nMeinhardt Consulting Engineers\n10/F Genesis, 33-35 Wong Chuk Hang Road, Hong Kong\n\nOR send e-mail by clicking \"Apply Now\" \u00a0\u00a0\u00a0 http://www.meinhardtgroup.com\n\nCandidates who have not been contacted within 8 weeks of their date of application may assume their application has been unsuccessful. Data collected will be used for recruitment purpose only and will be destroyed after six months from date of application.", "employment_types": ["Full Time", "Permanent"], "selling_points": [], "locations": ["Not Specified"], "categories": ["Building & Construction", "Civil / Structural", "Engineering", "Engineering Project Management", "Others"], "post_time": "2022-01-17T02:01:21Z", "salary": {"currency": null, "max": null, "min": null, "period": "monthly", "term": null}, "salary_visible": false, "title_keywords": ["senior engineer"], "responsibilities": ["communication", "recruitment", "consulting", "data"], "requirements": {"degrees": ["degree holder"], "majors": ["civil engineering"], "languages": ["english", "chinese"], "language_level": ["proficient", "good"], "hard_skills": ["mhkie"], "soft_skills": ["communication skills", "self-motivated", "systematic"], "languages_combined": [{"language": "english", "language_level": ["proficient", "good"]}, {"language": "chinese", "language_level": ["proficient", "good"]}]}, "experience_required": {"duration": ["minimum 5 years"], "field": ["drainage"]}}, {"job_id": "100003009044720", "location_code": "hk", "company": "Sunley Engineering & Construction Company Limited", "job_title": "Site Agent", "description": "-\u00a0Higher Diploma or Degree Holder in Structural/Civil Engineering or equivalent;\n\n-\u00a0Holder of TCP1/2 qualification;\n\n-\u00a07 years or above relevant experience in Foundation/Civil projects is preferred;\n\n-\u00a0Strong communication, well organization & energetic;\n\n-\u00a0Good command of both written & spoken English and Chinese;\n\n-\u00a0Proficiency in MS Office, AutoCAD and MS Project;", "employment_types": ["Full Time"], "selling_points": [], "locations": ["Not Specified"], "categories": ["Building & Construction", "Civil / Structural"], "post_time": "2022-01-13T05:41:34Z", "salary": {"currency": null, "max": null, "min": null, "period": "monthly", "term": null}, "salary_visible": false, "title_keywords": ["site agent"], "responsibilities": ["communication"], "requirements": {"degrees": ["diploma", "degree holder"], "majors": ["civil engineering"], "languages": ["english", "chinese"], "language_level": ["good command"], "hard_skills": ["autocad", "ms office"], "soft_skills": ["communication", "energetic"], "languages_combined": [{"language": "english", "language_level": ["good command"]}, {"language": "chinese", "language_level": ["good command"]}]}, "experience_required": {"duration": ["7 years"], "field": ["relevant experience", "civil projects"]}}, {"job_id": "100003009052490", "location_code": "hk", "company": "Union Contractors Limited", "job_title": "Project Coordinator / Assistant Project Coordinator", "description": "Job Requirements:\nDiploma or above of building / civil related institute or equivalent\nAt least 3 years\u2019 experience in participating for projects with Large Scale A&A Works\nAble to liaise and co-ordinate with the employers, consultants, sub-contractors and suppliers for developing construction details, monitoring site progress and conducting site co-ordination works.\nFamiliar with Auto-CAD or Micro-Station or BIM and MS Project\nImmediate available is definitely an advantage\nCandidate with less experience and / or qualification will be considered as Assistant Project Co-ordinator.\n\n\nWe offer attractive remuneration package with competitive fringe benefits to the right candidates..\n\nInterested parties please send your full resume with current and expected salary via email by clicking \"Apply Now\".\nPersonal data will be used for recruitment purpose only", "employment_types": ["Full Time", "Permanent"], "selling_points": ["Familiar with Auto-CAD or Micro-Station", "At least 3 years\u2019 experience", "Liaise and co-ordinate with the employers"], "locations": ["Not Specified"], "categories": ["Building & Construction", "Building / Construction / QS", "Civil / Structural", "Engineering", "Engineering Project Management"], "post_time": "2022-01-17T03:10:33Z", "salary": {"currency": null, "max": null, "min": null, "period": "monthly", "term": null}, "salary_visible": false, "title_keywords": ["assistant project coordinator", "project coordinator"], "responsibilities": ["liaise", "co-ordinate with", "site co-ordination", "monitoring", "developing"], "requirements": {"degrees": ["diploma or above"], "majors": [], "languages": [], "language_level": [], "hard_skills": ["cad", "bim"], "soft_skills": [], "languages_combined": []}, "experience_required": {"duration": ["at least 3 years"], "field": ["co-ordinator"]}}, {"job_id": "100003009052057", "location_code": "hk", "company": "Meinhardt Consulting Engineers", "job_title": "Technical Director / Executive Engineer / Senior Engineer (Ref: 88072T6)", "description": "Degree in civil / structural engineering or equivalent;\nQualified Engineer / Registered Professional Engineer (Civil / Structural / Bridge) with 8 to 20 years of relevant working experience including consulting engineering experience\n\nExtensive and proven with leading technical ability in the bridges and civil structures discipline;\nStrong management skills;\nSelf-motivated, logical and systematic thinkers;\nGood communication skills and proficient in written and spoken English and Chinese.\n\n\u00a0Please send your full resume with expected salary and availability(quoting reference number) to:\n\nHuman Resources Manager\nMeinhardt Consulting Engineers\n10/F Genesis, 33-35 Wong Chuk Hang Road, Hong Kong\n\nOR send e-mail by clicking \"Apply Now\" \u00a0\u00a0\u00a0 http://www.meinhardtgroup.com\n\nCandidates who have not been contacted within 8 weeks of their date of application may assume their application has been unsuccessful. Data collected will be used for recruitment purpose only and will be destroyed after six months from date of application.", "employment_types": ["Full Time", "Permanent"], "selling_points": [], "locations": ["Not Specified"], "categories": ["Building & Construction", "Civil / Structural", "Engineering", "Engineering Project Management", "Others"], "post_time": "2022-01-17T01:59:13Z", "salary": {"currency": null, "max": null, "min": null, "period": "monthly", "term": null}, "salary_visible": false, "title_keywords": ["senior engineer", "executive engineer", "director"], "responsibilities": ["management", "consulting", "data", "communication", "recruitment"], "requirements": {"degrees": ["degree"], "majors": ["structural engineering"], "languages": ["english", "chinese"], "language_level": ["proficient", "good"], "hard_skills": [], "soft_skills": ["communication skills", "self-motivated", "extensive", "systematic"], "languages_combined": [{"language": "english", "language_level": ["proficient", "good"]}, {"language": "chinese", "language_level": ["proficient", "good"]}]}, "experience_required": {"duration": ["8 to 20 years"], "field": ["structural", "engineering", "relevant working experience", "consulting"]}}, {"job_id": "100003009053806", "location_code": "hk", "company": "Liantronics (Hong Kong) Co., Limited", "job_title": "\u5de5\u7a0b\u5e2b", "description": "\n\u8077\u8cac :\u8ca0\u8cac\u8ddf\u9032\u9805\u76ee\u5de5\u7a0b,\u5354\u52a9\u92b7\u552e\u540c\u4e8b\u63a8\u5ee3LED,\u8207\u5de5\u5ee0\u7dad\u6301\u826f\u597d\u6e9d\u901a\u7b49\n\n\u8cc7\u6b77 :\u5c08\u4e0a\u6559\u80b2\uff1a\u6587\u6191/\u8b49\u66f8; 2\u5e74\u7d93\u9a57; \u826f\u597d\u7cb5\u8a9e; \u4e00\u822c\u666e\u901a\u8a71; \u826f\u597d\u82f1\u8a9e; \u61c2\u8b80\u5beb\u4e2d\u6587; \u61c2\u8b80\u5beb\u82f1\u6587; \u61c2Microsoft Office; \u61c2MS Word; \u61c2MS Excel; \u61c2\u4e2d\u82f1\u6587\u96fb\u8166\u64cd\u4f5c; \u61c2\u4e2d\u6587\u6253\u5b57; \u5177\u6709\u57fa\u672c\u96fb\u8166\u64cd\u4f5c\u77e5\u8b58; \u61c2AutoCAD; \u5177\u826f\u597d\u6e9d\u901a\u6280\u5de7,\u80fd\u7368\u7acb\u53ca\u5728\u58d3\u529b\u4e0b\u5de5\u4f5c\n\n\u5f85\u9047 :\u6bcf\u6708$16,000 - $20,000, \u6709\u96d9\u7ce7, \u661f\u671f\u4e00\u81f3\u4e94: \u4e0a\u53489\u6642\u81f3\u4e0b\u53486\u6642, \u6bcf\u9031\u5de5\u4f5c5\u5929, \u6bcf\u5929\u5de5\u4f5c 9 \u5c0f\u6642\n\n\u7533\u8acb\u9808\u77e5 :\u6c42\u8077\u8005\u53ef\u96fb\u90f5(Apply Now)\u5c65\u6b77\u8868\u7d66\u806f\u5efa\u5149\u96fb\uff08\u9999\u6e2f\uff09\u6709\u9650\u516c\u53f8\u3002\u5982\u8981\u7d22\u53d6\u6536\u96c6\u500b\u4eba\u8cc7\u6599\u8072\u660e, \u8acb\u8207\u856d\u5c0f\u59d0(Email)\u806f\u7d61\u3002\n\n", "employment_types": ["Full Time"], "selling_points": [], "locations": ["Shatin Area"], "categories": ["Building & Construction", "Architectural Services", "Building / Construction / QS", "Civil / Structural"], "post_time": "2022-01-17T07:32:53Z", "salary": {"currency": null, "max": null, "min": null, "period": "monthly", "term": null}, "salary_visible": false, "title_keywords": [], "responsibilities": [], "requirements": {"degrees": [], "majors": [], "languages": [], "language_level": [], "hard_skills": ["excel", "word"], "soft_skills": [], "languages_combined": []}, "experience_required": {"duration": [], "field": []}}, {"job_id": "100003009053463", "location_code": "hk", "company": "Able Engineering Company Limited", "job_title": "Works Supervisor (Building Works)", "description": "Certificate in Building or Building Studies from a Hong Kong Polytechnic University / Polytechnic or Hong Kong Institute of Vocational Education / technical institute / technical college or equivalent;\nAttainment of a level of proficiency in Chinese and English Languages equivalent to Form 5 standard;\n3 years relevant post-qualification experience of site supervision;\nWork on Construction Site in Hong Kong or Pre-fabrication Factory in PRC.\n\nWe offer competitive salary package and career development opportunity to the successful candidate. Interested parties may send your full resume, present and expected salary, available date and contact number by email by clicking \"Apply Now\".\n\nTo visit our website for more information: www.ableeng.com.hk\n\n(As an Equal Opportunities Employer, Able is committed to eliminating discrimination in employment. The vacancy advertised is open to all applicants meeting the basic entry requirement irrespective of their disability, sex, marital status, pregnancy, age, family status, sexual orientation or race etc. Applicants not hearing from us within 6 months may consider their applications unsuccessful. Personal data collected will be used for recruitment related purposes only.)", "employment_types": ["Full Time", "Permanent"], "selling_points": [], "locations": ["Not Specified"], "categories": ["Building & Construction", "Building / Construction / QS", "Civil / Structural", "Others"], "post_time": "2022-01-17T07:00:51Z", "salary": {"currency": null, "max": null, "min": null, "period": "monthly", "term": null}, "salary_visible": false, "title_keywords": ["supervisor"], "responsibilities": ["site supervision"], "requirements": {"degrees": ["certificate", "form 5"], "majors": ["building studies"], "languages": ["english", "chinese"], "language_level": ["proficiency"], "hard_skills": [], "soft_skills": [], "languages_combined": [{"language": "english", "language_level": ["proficiency"]}, {"language": "chinese", "language_level": ["proficiency"]}]}, "experience_required": {"duration": ["3 years"], "field": ["post-qualification"]}}, {"job_id": "100003009051037", "location_code": "hk", "company": "Shui On Building Contractors Ltd", "job_title": "Senior Engineer (QCM)", "description": "The Job:\n\nOrganize,\u00a0 plan\u00a0 and\u00a0 supervise\u00a0 Quality\u00a0 Control\u00a0 Coordinators\u00a0 (QCCs)\u00a0 in checking, endorsing and inspecting works in their relevant disciplines;\nCarry out inspection, checking and endorse on works;\nEnsure works were inspected by the respective QCCs in accordance with the\u00a0 Quality\u00a0 Control\u00a0 System,\u00a0 and\u00a0 are\u00a0 in\u00a0 accordance\u00a0 with\u00a0 the\u00a0 Specification and Drawings before seeking Approval from the CM\nCertify photocopies of the ISO certificates for materials or components as true copies of the original certificates when circumstances warranted;\nSubmit relevant forms to the CM as required by the contract;\nDevelop and oversee the control measures to ensure material compliance at all stages in the progress of the Works including purchase, delivery, storage and use of materials;\nAny other duties as required in the Specification.\n\nRequirement:\n\nDegree in Civil or Structural Engineering / Building Studies with minimum 4 years post-qualification working experience, and preferably with professional membership\nPrevious experience in HKHA building projects is an advantage;\nGood communication and interpersonal skills;\nGood command of English and Chinese.\n\nInterested parties please send full resume stating your current and expected salary with contact number via click \"Apply Now\" below.\n\nFor more information about our company, please visit our website at\u00a0http://www.socam.com/\n\nPersonal data provided by applicants will be used strictly in accordance with our Company's personal data policies, a copy of which is available upon request. You may consider your application unsuccessful if you are not contacted within 8 weeks.", "employment_types": ["Full Time", "Permanent"], "selling_points": [], "locations": ["Not Specified"], "categories": ["Building & Construction", "Building / Construction / QS", "Civil / Structural", "Engineering", "Others"], "post_time": "2022-01-15T19:11:46Z", "salary": {"currency": null, "max": null, "min": null, "period": "monthly", "term": null}, "salary_visible": false, "title_keywords": ["senior engineer"], "responsibilities": ["any other duties", "control", "compliance", "quality", "checking", "inspection", "drawings", "develop", "purchase", "plan"], "requirements": {"degrees": ["degree"], "majors": ["structural engineering", "building studies"], "languages": ["english", "chinese"], "language_level": ["good command"], "hard_skills": [], "soft_skills": ["communication and interpersonal skills"], "languages_combined": [{"language": "english", "language_level": ["good command"]}, {"language": "chinese", "language_level": ["good command"]}]}, "experience_required": {"duration": ["minimum 4 years"], "field": ["structural", "post-qualification", "engineering"]}}, {"job_id": "100003009049565", "location_code": "hk", "company": "Build King Holdings Ltd", "job_title": "Assistant Engineer - Civil  (Ref:JD/AE)", "description": "Higher Diploma or above in Civil Engineering\u00a0or related disciplines;\n1 year practical experience in construction;\nGood command of written and spoken English and Chinese;\nGood communication skills;\nFresh Graduate / IANG Holder will also be considered.\n\nPlease send your application with full resume and expected salary to\u00a0Human Resources Department, Units 601-605A, 6/F,\u00a0Tower\u00a0B, Manulife Financial Centre, 223 Wai\u00a0Yip Street, Kwun Tong, Kowloon,\u00a0Hong Kong\u00a0(please quote the job reference number and job title on the subject)\u00a0or\u00a0by clicking\u00a0Job Application\u00a0or \"APPLY NOW\".\n\nPlease visit our website\u00a0www.buildking.hk\u00a0for more details.\n\n(Personal data collected will be used for recruitment-related purposes only.)", "employment_types": ["Full Time", "Permanent"], "selling_points": ["For Civil projects", "Year-end bonus", "Fresh Graduate / IANG Holder is welcome"], "locations": ["Not Specified"], "categories": ["Building & Construction", "Building / Construction / QS", "Civil / Structural"], "post_time": "2022-01-14T08:53:51Z", "salary": {"currency": null, "max": null, "min": null, "period": "monthly", "term": null}, "salary_visible": false, "title_keywords": ["assistant engineer"], "responsibilities": ["communication", "personal data", "recruitment", "website"], "requirements": {"degrees": ["higher diploma or above", "fresh graduate"], "majors": ["related disciplines", "civil engineering"], "languages": ["english", "chinese"], "language_level": ["good command"], "hard_skills": [], "soft_skills": ["communication skills"], "languages_combined": [{"language": "english", "language_level": ["good command"]}, {"language": "chinese", "language_level": ["good command"]}]}, "experience_required": {"duration": ["1 year"], "field": ["construction"]}}, {"job_id": "100003009053402", "location_code": "hk", "company": "Prudential Surveyors International Ltd", "job_title": "Registered Structural Engineer/Structural Engineer (Civil/Structural/Geotechnical)", "description": "\u00a0Requirements:\n\n\u00a0For Registered Structural Engineer\n\nDegree\u00a0holder in Civil / Structural / Geotechnical\u00a0Engineering\nChartered Engineer / Registered Professional Engineer\nAt least 3 years' relevant\u00a0 experience in Civil / Structural project\nAbility to work\u00a0in a team with self-discipline and strong communication skills\nProficient in Microsoft Office Application, including Words, Excel, etc.\u00a0\nGood command in\u00a0both\u00a0English and Chinese\nImmediate or short notice available is highly preferred\nOur company is on AACSB and EACSB consultant list\n\n\u00a0\u00a0For Structural Engineer\n\nDegree\u00a0holder in Civil / Structural /\u00a0Geotechnical\u00a0Engineering\n2-3\u00a0years' relevant\u00a0 experience in Civil / Structural projects\nAbility to work\u00a0in a team with self-discipline and strong communication skills\nProficient in Microsoft Office Application, including Words, Excel, etc.\u00a0\nGood command in\u00a0both\u00a0English and Chinese\nImmediate or short notice available is highly preferred\nOur company is on AACSB and EACSB consultant list\n\nWe offer excellent career prospect and competitive package to the right candidate.\n\nPlease send your application with detailed resume stating your salary expected and availability.\n\nPersonal data collected will be used for recruitment purpose only.\n\n(Company web-site:\u00a0http://www.pruden.com.hk/", "employment_types": ["Full Time", "Permanent"], "selling_points": [], "locations": ["Sheung Wan"], "categories": ["Building & Construction", "Building / Construction / QS", "Civil / Structural", "Others"], "post_time": "2022-01-17T06:55:38Z", "salary": {"currency": null, "max": null, "min": null, "period": "monthly", "term": null}, "salary_visible": false, "title_keywords": ["engineer"], "responsibilities": ["communication"], "requirements": {"degrees": ["degree holder"], "majors": ["engineering"], "languages": ["english", "chinese"], "language_level": ["good command"], "hard_skills": ["excel", "words", "microsoft office"], "soft_skills": ["communication skills"], "languages_combined": [{"language": "english", "language_level": ["good command", "good command"]}, {"language": "chinese", "language_level": ["good command", "good command"]}]}, "experience_required": {"duration": ["at least 3 years", "2-3 years"], "field": ["structural"]}}, {"job_id": "100003009051082", "location_code": "hk", "company": "JMK Consulting Engineers Limited", "job_title": "Resident Engineer", "description": "Degree Holder in Civil, Structural or Geotechnical Engineering\nQualified to act as RGE T3 and/or RSE T3\nHKD35,000 \u2013 45,000 depend on working experience\nMHKIE (Structural) is preferable and salary negotiable\u00a0\n\n", "employment_types": ["Full Time", "Permanent", "Temporary", "Contract"], "selling_points": ["Min 3 years relevant working experience", "HKD35,000 \u2013 45,000 depend on working experience", "Medical Insurance, Bonus/Gratuity"], "locations": ["Not Specified"], "categories": ["Building & Construction", "Civil / Structural", "Engineering", "Others"], "post_time": "2022-01-15T01:56:44Z", "salary": {"currency": "HKD", "max": 44999, "min": 35000, "period": "monthly", "term": null}, "salary_visible": true, "title_keywords": ["resident engineer"], "responsibilities": [], "requirements": {"degrees": ["degree holder"], "majors": ["engineering"], "languages": [], "language_level": [], "hard_skills": ["mhkie"], "soft_skills": [], "languages_combined": []}, "experience_required": {"duration": [], "field": []}}, {"job_id": "100003009049300", "location_code": "hk", "company": "Fugro Geotechnical Services Limited", "job_title": "Assistant Geologist / Assistant Engineer", "description": "Job Responsibilities:\n\n\nCoordinate and monitor Site Investigation works (land and marine) to ensure the technical, quality, safety and progress of the projects in alignment with standards;\nHandle various field testing and assist in preparing factual reports;\nPrepare daily site reports and other related documentation;\nPerform project management duties as directed by the manager;\nHandle ad-hoc duties as required.\nJob Requirements:\n\n\nHigher Diploma or above in Civil Engineering, Earth Science or related disciplines;\nA good team player with good communication and interpersonal skills;\nGood command of written and spoken English and Chinese;\nValid Green card and CWRA holder, valid Blue card is a plus.\nFresh Graduates are welcome to apply for this position.\n\n\nHow to Apply\n\nInterested parties, please click the \u201cApply Now\u201d button below to upload your resume, stating the date of availability, the current and expected salary to The Human Resources Department, Fugro Geotechnical Services Limited or by email at\u00a0fgs.hr @fugro.com\u00a0for application.\u00a0\n\nAttractive remuneration package will be offered to suitable candidates,\u00a0inclusive 14 days of Annual Leave, Public Holidays, Group Medical Plan (covered dependents), Life & Accidental Insurance, Performance Bonus, Training Subsidy, Special Allowance and long-term career development opportunities.\n\nAll applications and personal information data provided will be treated in strict confidence and only be used for recruitment purposes.\u00a0\u00a0\u00a0", "employment_types": ["Full Time", "Permanent"], "selling_points": [], "locations": ["Kwai Hing"], "categories": ["Building & Construction", "Civil / Structural", "Engineering", "Engineering Project Management"], "post_time": "2022-01-14T08:24:19Z", "salary": {"currency": null, "max": null, "min": null, "period": "monthly", "term": null}, "salary_visible": false, "title_keywords": ["assistant engineer", "assistant geologist"], "responsibilities": ["related documentation", "quality", "monitor", "investigation", "testing", "coordinate", "project management", "reports", "ad-hoc duties"], "requirements": {"degrees": ["higher diploma or above"], "majors": ["related disciplines", "science", "civil engineering"], "languages": ["english", "chinese"], "language_level": ["good command"], "hard_skills": ["plus", "green card"], "soft_skills": ["good team player", "communication and interpersonal skills"], "languages_combined": [{"language": "english", "language_level": ["good command"]}, {"language": "chinese", "language_level": ["good command"]}]}, "experience_required": {"duration": [], "field": []}}, {"job_id": "100003009048964", "location_code": "hk", "company": "Wings & Associates Consulting Engineers Limited", "job_title": "Surveying Officer (Building Surveying) / Technical Officer (Civil/Structural)", "description": "Requirements:\n\nHigher Diploma or High Certificate in Building Surveying or Civil / Structural Engineering or other related discipline\nGood interpersonal and communication skills\nProactive and responsible\nFresh Graduate is welcomed\n\nResponsibilities:\n\nTo assist in checking structural design and details, test reports and construction records, and in witnessing and carrying out of tests on foundation and structural elements;\nTo assist in carrying out inspection of buildings and slopes, surveying defects, repair works and unauthorised building works, investigating sources of water seepage, arranging issue of statutory orders/notices/directions, and supervising works, including emergency cases, carried out by the government contractors;\nTo assist in preparing documents for Minor Works Control System, Mandatory Building Inspection Scheme and Mandatory Window Inspection Scheme submissions.\n\nWe offer attractive remuneration and benefits including 5-day working week to the right candidates. Interested parties, please send your full resume including your\u00a0CURRENT\u00a0and\u00a0EXPECTED\u00a0salary to\u00a0our HR Manager by email.\u00a0\n\nPersonal data provided will be used by us for recruitment and related purposes, which is strictly in accordance with the Personal Data (Privacy) Ordinance (i.e. Cap. 486) for Applicants for Employment. Applicants who are not contacted within 6 weeks may consider your applications unsuccessful and the personal data collected will be destroyed after 6 months or such other period as prescribed by the applicable laws.", "employment_types": ["Full Time", "Permanent"], "selling_points": ["5-day work, Medical Allowance, Performance Bonus", "Happy Work Environment, Dynamic Team", "new to work force"], "locations": ["Kwun Tong"], "categories": ["Building & Construction", "Civil / Structural", "Engineering", "Others", "Others", "Technician"], "post_time": "2022-01-14T07:48:40Z", "salary": {"currency": null, "max": null, "min": null, "period": "monthly", "term": null}, "salary_visible": false, "title_keywords": ["technical officer", "officer"], "responsibilities": ["control", "supervising", "checking", "design", "inspection", "repair", "reports"], "requirements": {"degrees": ["certificate", "diploma", "fresh graduate"], "majors": ["building surveying", "structural engineering"], "languages": [], "language_level": [], "hard_skills": [], "soft_skills": ["communication skills", "proactive", "interpersonal", "responsible"], "languages_combined": []}, "experience_required": {"duration": [], "field": []}}, {"job_id": "100003009049912", "location_code": "hk", "company": "Paul Y. Engineering Group", "job_title": "Assistant Engineer/ Project Engineer - Building", "description": "Job Description\n\nCoordinate and monitor the progress of the project to fulfill the contractual schedule and quality standards;\nPrepare the site progress report for inspection of works;\nConduct regular meetings to identify and resolve problems in respect of technical, safety and environmental issues etc.;\u00a0\nLiaise with clients, consultants and sub-contractors for technical issues; and\nTake part in day-to-day site activities including drawing design, programming and structural calculation.\n\nJob Requirement\n\n\nHD or above in\u00a0Building / Civil\u00a0Engineering or equivalent;\n1 year or above of construction experience in consultant or contractor;\nConversant in\u00a0BIM\u00a0application is an advantage;\nGood command of written and spoken English and Chinese;\nTeam player and willing to learn;\nIANG is also welcome; and\nCandidates with more experience will be considered as Project Engineer.\n\n***What we offer?\n\nCompetitive remuneration package\nOT Allowance\nAdditional leave (Family Care Leave, Exam Leave, Qualification Leave, etc.)\nDiscretionary bonus\nStudy Subsidies\nComprehensive training and professional career development\n\nInterested parties please apply by clicking \"APPLY NOW\"\u00a0with detailed CV stating\u00a0expected salary\u00a0and\u00a0date of availability.\n\nCompany Website:\u00a0http://www.pyengineering.com/\n\nAll personal data provided will be used strictly in accordance with our \u201cPersonal Information Collection Statement Pertaining to Recruitment\u201d, a copy of which is available upon written request to us by E-mail.", "employment_types": ["Full Time", "Permanent"], "selling_points": ["HD or above in Building/ Civil", "1 yr or above relevant exp. in contractors", "Comprehensive training & study sponsorship"], "locations": ["Yuen Long"], "categories": ["Building & Construction", "Building / Construction / QS", "Civil / Structural", "Engineering", "Engineering Project Management"], "post_time": "2022-01-15T03:50:40Z", "salary": {"currency": null, "max": null, "min": null, "period": "monthly", "term": null}, "salary_visible": false, "title_keywords": ["assistant engineer", "project engineer"], "responsibilities": ["liaise with clients", "site activities", "quality", "monitor", "environmental issues", "design", "coordinate", "inspection of works", "schedule", "report"], "requirements": {"degrees": [], "majors": [], "languages": ["english", "chinese"], "language_level": ["good command"], "hard_skills": ["bim"], "soft_skills": ["team player", "willing to learn"], "languages_combined": [{"language": "english", "language_level": ["good command"]}, {"language": "chinese", "language_level": ["good command"]}]}, "experience_required": {"duration": ["1 year"], "field": ["construction"]}}, {"job_id": "100003009047157", "location_code": "hk", "company": "Yee Hop Engineering Company Limited", "job_title": "Site Engineer / Assistant Site Engineer", "description": "Requirements:\n\nHigher Certificate / Higher Diploma or above in Civil / Structural Engineering / Building Studies or equivalent;\nMinimum 3 years\u2019\u00a0relevant site working experience;\nAble to work independently, self-motivated and responsible;\nApplicant with less qualification / experience will be considered as Assistant Site Engineer.\n\nInterested parties please apply with detailed resume stating expected salary and date of availability to Ms. Louise Loo\u00a0via email by clicking \"Apply Now\"\u00a0or fax to 2635 0611.\u00a0\u00a0\n\n[ Personal data collected will be used for recruitment-related purposes only. ]", "employment_types": ["Full Time", "Permanent"], "selling_points": [], "locations": ["Not Specified"], "categories": ["Building & Construction", "Building / Construction / QS", "Civil / Structural", "Others"], "post_time": "2022-01-15T03:49:35Z", "salary": {"currency": null, "max": null, "min": null, "period": "monthly", "term": null}, "salary_visible": false, "title_keywords": ["site engineer", "assistant"], "responsibilities": [], "requirements": {"degrees": ["higher diploma or above", "higher certificate"], "majors": ["structural engineering", "building studies"], "languages": [], "language_level": [], "hard_skills": [], "soft_skills": ["work independently", "self-motivated", "responsible"], "languages_combined": []}, "experience_required": {"duration": ["minimum 3 years"], "field": []}}, {"job_id": "100003009051382", "location_code": "hk", "company": "Aecom Asia Company Limited", "job_title": "Engineer / Project Engineer / Senior Engineer, Transportation", "description": "Job Requirements\u00a0\n\n\nA recognized degree in Civil Engineering or equivalent\nA minimum 4 years of relevant work experience in the design or construction or project co-ordination of civil infrastructure projects such as railway, bridges, aviation, utilities, marine works.\nChartered Status to HKIE or equivalent.\nFluent in spoken and written Chinese (Cantonese and/or Putonghua) and English\nFor senior engineer, the professional maturity to mentor junior engineers.\nTeam player with excellent interpersonal and communication skills\nFamiliarity and understanding of Hong Kong design codes and standards is an advantage.\n\nJob Duties\n\n\nDesign of civil structures and/or project management for major infrastructure projects in Hong Kong\nParticipate in interdisciplinary co-ordination of project deliverables.\nPrepare study reports, design reports, technical notes and specific project deliverables.\nFor senior engineers, assist the project managers in the management of specific projects and liaison with clients.\u00a0\n\nAECOM is a place where you can put your innovative thinking and business skills into high gear and work alongside other highly intelligent and motivated people. It's a place where you can apply your skills to some of the world's most challenging, interesting, and meaningful projects worldwide. It's a place that values the diversity of our areas of practice and our people. It's what makes AECOM a great place to work and grow. AECOM is an Equal Opportunity Employer.\n\n\nFor more information on AECOM, please visit our website at www.aecom.com.\u00a0", "employment_types": ["Full Time", "Permanent"], "selling_points": ["A minimum 4 years of experience", "A recognized degree in Civil Engineer", "Chartered Status to HKIE or equivalent"], "locations": ["Shatin Area"], "categories": ["Building & Construction", "Building / Construction / QS", "Civil / Structural", "Engineering", "Engineering Project Management"], "post_time": "2022-01-15T13:16:41Z", "salary": {"currency": null, "max": null, "min": null, "period": "monthly", "term": null}, "salary_visible": false, "title_keywords": ["senior engineer", "engineer", "project engineer"], "responsibilities": ["management", "project deliverables", "infrastructure", "website", "design", "project management", "reports"], "requirements": {"degrees": ["degree"], "majors": ["civil engineering"], "languages": ["cantonese", "putonghua", "english", "chinese"], "language_level": ["fluent"], "hard_skills": ["hkie", "codes"], "soft_skills": ["communication skills", "team player", "interpersonal"], "languages_combined": [{"language": "cantonese", "language_level": ["fluent"]}, {"language": "putonghua", "language_level": ["fluent"]}, {"language": "english", "language_level": ["fluent"]}, {"language": "chinese", "language_level": ["fluent"]}]}, "experience_required": {"duration": ["minimum 4 years"], "field": ["infrastructure", "construction", "design"]}}, {"job_id": "100003009043646", "location_code": "hk", "company": "Kwan On Construction Company Limited", "job_title": "Site Agent /Project Manager", "description": "Job Description:\n\nCivil engineering construction management and planning\nContract administration\nSite coordination and control\nMonitor the construction progress, execution of works to ensure the works can be completed within the required time, budget and quality.\n\nJob Requirements:\n\nDegree or above in Civil Engineering, Structural Engineering or Building disciplines\nMinimum 4 years post professional qualification experience for roadworks, geotechnical works, drainage works and pilling works\nKnowledge of safety and environment management\nCandidates with more experience will be considered as Project Manager\n\nWorking Location:\u00a0 Kwai Chung /\u00a0Kwun Tong / Sham Shui Po\n\n\n\nInterested parties please send your CV with current / last & expected salary by clicking \"Apply Now\"\n\n(All information provided will only be used for recruitment related purpose.)", "employment_types": ["Full Time", "Permanent"], "selling_points": [], "locations": ["Not Specified"], "categories": ["Building & Construction", "Building / Construction / QS", "Civil / Structural", "Others", "Security / Safety Control"], "post_time": "2022-01-13T01:17:14Z", "salary": {"currency": null, "max": null, "min": null, "period": "monthly", "term": null}, "salary_visible": false, "title_keywords": ["site agent", "project manager"], "responsibilities": ["control", "construction management", "contract administration", "budget", "monitor", "quality", "site coordination", "planning"], "requirements": {"degrees": ["degree or above"], "majors": ["structural engineering", "civil engineering"], "languages": [], "language_level": [], "hard_skills": [], "soft_skills": [], "languages_combined": []}, "experience_required": {"duration": ["minimum 4 years"], "field": ["drainage"]}}, {"job_id": "100003009044852", "location_code": "hk", "company": "Airport Authority Hong Kong", "job_title": "Assistant Engineer", "description": "This is a fixed-term contract position of minimum 2 years with possibility for renewal subject to organization need and individual performance.\n\nResponsibilities:\n\nProviding technical assistance in the design and site supervision of civil and building works;\nEnsuring that the consultants'/ contractors' proposals and works are in compliance with sound engineering principles and required standards in terms of quality and safety;\nUndertaking interface/coordination related civil/ building/ structural works;\nReviewing design submissions and technical reports;\nMonitoring statutory submission of the consultants' design works\nProviding technical support to site supervision teams including responding to request for information and preparing design change documents;\nCollaboratively working with the Contractors to ensure the works are completed on time and budget to a high level of quality.\n\nRequirements:\n\nBachelor's degree in Civil/ Structural Engineering or other related disciplines\nAt least 3 years' relevant experience in design, construction, project management of civil/ structural projects\nGood command of spoken and written English and Chinese. Knowledge of Putonghua is an advantage.\nProficient in MS Office applications", "employment_types": ["Full Time"], "selling_points": ["Degree holder in Civil / Structural Engineering", "At least 3 years' relevant working experience", "Experience in civil / structural projects"], "locations": ["Airport Area"], "categories": ["Engineering", "Building & Construction", "Civil / Structural", "Engineering Project Management"], "post_time": "2022-01-13T06:27:33Z", "salary": {"currency": null, "max": null, "min": null, "period": "monthly", "term": null}, "salary_visible": false, "title_keywords": ["assistant engineer"], "responsibilities": ["site supervision", "technical support", "compliance", "quality", "monitoring", "design", "teams", "budget", "reports", "coordination", "technical assistance"], "requirements": {"degrees": ["degree", "bachelor"], "majors": ["related disciplines", "structural engineering"], "languages": ["putonghua", "english", "chinese"], "language_level": ["advantage", "good command"], "hard_skills": ["project management", "ms office"], "soft_skills": ["project management"], "languages_combined": [{"language": "putonghua", "language_level": ["advantage"]}, {"language": "english", "language_level": ["good command"]}, {"language": "chinese", "language_level": ["good command"]}]}, "experience_required": {"duration": ["at least 3 years"], "field": ["structural", "design", "project management", "relevant experience", "construction"]}}, {"job_id": "100003009053933", "location_code": "hk", "company": "Able Engineering Company Limited", "job_title": "Technical Coordinator (Architectural)", "description": "Certificate / Diploma in Architectural Studies/Building Studies and have minimum 3 years drafting experience related to architectural works; or\nHigher Diploma in Architectural Studies and have 2 years relevant experience; or\nPossessing 5 years drafting experience in an architectural firm;\nAdequate Microsoft Office, AutoCAD and Revit; PhotoShop, Coreldraw and Google SketchUp knowledge;\nEmployment Period: 10 months.\n\nWe offer competitive salary package and career development opportunity to the successful candidate. Interested parties may send your full resume, present and expected salary, available date and contact number by email by clicking \"Apply Now\".\n\nTo visit our website for more information: www.ableeng.com.hk\n\n(As an Equal Opportunities Employer, Able is committed to eliminating discrimination in employment. The vacancy advertised is open to all applicants meeting the basic entry requirement irrespective of their disability, sex, marital status, pregnancy, age, family status, sexual orientation or race etc. Applicants not hearing from us within 6 months may consider their applications unsuccessful. Personal data collected will be used for recruitment related purposes only.)", "employment_types": ["Full Time"], "selling_points": [], "locations": ["Not Specified"], "categories": ["Building & Construction", "Architectural Services", "Building / Construction / QS", "Civil / Structural"], "post_time": "2022-01-17T07:47:50Z", "salary": {"currency": null, "max": null, "min": null, "period": "monthly", "term": null}, "salary_visible": false, "title_keywords": ["coordinator"], "responsibilities": [], "requirements": {"degrees": ["certificate", "diploma"], "majors": ["building studies"], "languages": [], "language_level": [], "hard_skills": ["microsoft office", "sketchup", "autocad", "photoshop", "revit"], "soft_skills": [], "languages_combined": []}, "experience_required": {"duration": ["5 years", "2 years", "minimum 3 years"], "field": ["related", "relevant experience"]}}, {"job_id": "100003009043360", "location_code": "hk", "company": "Sun Hung Kai Properties Ltd", "job_title": "STRUCTURAL ENGINEER /  ASSISTANT STRUCTURAL ENGINEER", "description": "Requirements:\n\nBachelor\u2019s degree in civil and structural engineering or related discipline\nMHKIE (in Structural Discipline) or equivalent preferable\nMinimum 2 years\u2019 post qualification experience in structural engineering\nProven English proficiency and good command of Putonghua\nCapable to handle projects independently\nExperience in China projects is an advantage\nResponsibilities:\n\nProvide structural engineering services include carrying of structural design and site supervision for Hong Kong projects, structural project management for Hong Kong and PRC projects\n\n(Candidates with less experience will be considered for Assistant Structural Engineer)\n\nGood remuneration and attractive fringe benefits will be offered to the successful applicant. Interested parties please apply with full resume, present and expected salary, available date by clicking \"Apply Now\".\n\nFor further information, please visit our company website: http://www.shkp.com/.\n\nWe are an equal opportunity employer and welcome applications from all qualified candidates. All personal data collected will be used for recruitment purpose only.\u00a0 Applicants not hearing from us within 3 months may consider their applications unsuccessful.\u00a0 All personal data collected will be destroyed within 24 months.", "employment_types": ["Full Time", "Permanent"], "selling_points": ["Degree in civil & structural eng with 2 yrs' exp", "MHKIE (in Structural Discipline) preferable", "Structural design and site supervision"], "locations": ["Wan Chai"], "categories": ["Building & Construction", "Civil / Structural", "Engineering", "Draftsman", "Engineering Project Management"], "post_time": "2022-01-12T11:00:14Z", "salary": {"currency": null, "max": null, "min": null, "period": null, "term": null}, "salary_visible": false, "title_keywords": ["engineer", "assistant"], "responsibilities": ["project management", "site supervision", "design"], "requirements": {"degrees": ["degree", "bachelor"], "majors": ["structural engineering"], "languages": ["putonghua", "english"], "language_level": ["proficiency", "good command"], "hard_skills": ["mhkie"], "soft_skills": ["independently", "capable"], "languages_combined": [{"language": "putonghua", "language_level": ["proficiency", "good command"]}, {"language": "english", "language_level": ["proficiency", "good command"]}]}, "experience_required": {"duration": ["minimum 2 years"], "field": ["structural", "engineering"]}}, {"job_id": "100003009047076", "location_code": "hk", "company": "Arup", "job_title": "Engineer / Project Engineer (Civil Engineering)", "description": "Degree in Civil Engineering or related discipline\nCorporate member of relevant professional institution(s)\nFresh chartered for the position of Engineer and at least 1 year of post chartered experience for the position of Project Engineer\nGood experience and skills in project management and civil engineering designs of infrastructure projects and familiar with local procedures of HKSAR Government in the implementation of infrastructure projects\nBe dynamic, proactive and able to work independently\nProficiency in both written and spoken English and Chinese\nFamiliar with AutoCAD or MicroStation and BIM applications will be an advantage\n\nWe offer a competitive remuneration package commensurate with qualifications and experience to the right candidate including Global Profit Share scheme, additional fringe benefits of maternity/paternity leave and long-term career development opportunities.\u00a0\n\nFor interested applicants, please click \u201cApply Now\" to submit your online application.\n\n\nTo explore more job opportunities in Arup, please visit our website at http://www.arup.com/Careers/Experienced_Hires/ApplyForAJob\n\u00a0\nPersonal data collected will be used for recruitment purpose only. Applicants not contacted within 8 weeks may consider their applications unsuccessful.", "employment_types": ["Full Time", "Permanent"], "selling_points": [], "locations": ["Kowloon City Area"], "categories": ["Building & Construction", "Civil / Structural", "Engineering", "Engineering Project Management", "Others"], "post_time": "2022-01-14T02:15:44Z", "salary": {"currency": null, "max": null, "min": null, "period": null, "term": null}, "salary_visible": false, "title_keywords": ["engineer", "project engineer"], "responsibilities": ["infrastructure", "procedures", "implementation", "website", "project management", "recruitment", "career development", "personal data"], "requirements": {"degrees": ["degree"], "majors": ["civil engineering"], "languages": ["english", "chinese"], "language_level": ["proficiency"], "hard_skills": ["scheme", "project management", "bim", "dynamic", "autocad"], "soft_skills": ["project management", "work independently", "dynamic", "proactive"], "languages_combined": [{"language": "english", "language_level": ["proficiency"]}, {"language": "chinese", "language_level": ["proficiency"]}]}, "experience_required": {"duration": ["at least 1 year"], "field": ["project management", "development", "infrastructure", "engineering"]}}, {"job_id": "100003009047458", "location_code": "hk", "company": "Leighton Contractors (Asia) Ltd", "job_title": "Graduate Engineer / Trainee - 2022 intake", "description": "Leighton Asia recognize that having dedicated training is a key part of building and managing a sustainable pipeline of talent for the future.\u00a0\n\nBeing a part of the CIMIC Group Graduate program, our dedicated graduate training program aims to build and manage a sustainable pipeline of talent for the future.\u00a0\n\nEach year, we recruit a number of high-calibre graduates, who undergo comprehensive training and career development program through on-the-job training, job rotations, secondments, in-house and external continuous professional development seminars, site visits and activities organised through our Young Professional Club peer group.\n\nWe invite high-calibre\u00a0graduates to join our 2022 Graduate Program in Hong Kong.\u00a0\n\nGraduate Positions:\n\nCivil Graduate Engineer\nBuilding Graduate Engineer\nMechanical\u00a0& Electrical Graduate Engineer\nBuilding Services Graduate Engineer\nQuantity Surveying Trainee\nSafety Officer Trainee\nDigital Engineering (BIM) Trainee\u00a0\n\nQualification:\n\nDegree / Higher Diploma in the following disciplines:\n\n\nArchitectural Studies\nAccounting, Finance or Business Administration\u00a0\nBuilding Engineering & Management\nConstruction Engineering & Management\nCivil & Environmental Engineering\nCivil & Structural Engineering\nDigital Engineering\u00a0\nElectrical / Mechanical or Building Services Engineering\nOccupation Health & Safety Management\nQuantity Surveying or related disciplines\n\nRequirement:\n\nHigher Diploma or Degree in related disciplines\nStrong Communication skills - both written and spoken in English and Chinese\nEnergetic, flexible, good problem-solving ability and strong communication skill\nEnjoy working in mixed cultural environment\n\nCome to join us and experience a fun,\u00a0challenging and energetic culture.\u00a0\u00a0\nWe offer\u00a0HKIE Scheme A Training, CPD seminar\u00a0& professional training course\u00a0sponsorship, study leave to eligible graduates\n\nDeadline of application: 28 February 2022\n\nFor application, please submit\u00a0your\u00a0full resume, latest academic transcripts, educational qualifications\u00a0(e.g. HKDSE/HKAL/HKCEE), other relevant awards/ certificates. Also, please\u00a0indicate your latest GPA\u00a0before submission.\n\nFor more information, please visit\u00a0Leighton Graduate Program", "employment_types": ["Full Time", "Permanent"], "selling_points": ["Comprehensive training and career development", "Professional development seminars", "HKIE Scheme \"A\" Training Program"], "locations": ["Not Specified"], "categories": ["Building & Construction", "Building / Construction / QS", "Civil / Structural", "Engineering", "Others"], "post_time": "2022-01-14T05:23:50Z", "salary": {"currency": null, "max": null, "min": null, "period": null, "term": null}, "salary_visible": false, "title_keywords": ["graduate engineer", "trainee"], "responsibilities": ["administration", "management", "communication", "career development"], "requirements": {"degrees": ["diploma", "degree"], "majors": ["related disciplines"], "languages": ["english", "chinese"], "language_level": [], "hard_skills": ["problem-solving", "bim", "fun"], "soft_skills": ["flexible", "communication skills", "enjoy working", "problem-solving", "communication skill", "comprehensive", "organised", "energetic"], "languages_combined": [{"language": "english", "language_level": []}, {"language": "chinese", "language_level": []}]}, "experience_required": {"duration": [], "field": []}}, {"job_id": "100003009052668", "location_code": "hk", "company": "Hong Kong Interior Design Architecture Limited", "job_title": "BIM Instructor (Part time)", "description": "Job responsibilities:\n\n\nConduct tutorial lessons\nPrepare materials for classes\nJob requirements:\n\nCCBC/CCBM holder is a must\nAt least three years working experenice in the field\nGood knowlege in BIM softwares\nPatient, positive and passionate about education\nBe enthusiastic and dynamic\nExcellent presentation and communication skill\nAble to teaching in English or Mandarin is a plus\nImmediate availability is preferred\nCampus:\nMongkok Campus\n\nWebsite:\nhttps://www.hkiai.com.hk/CCBM.php\n", "employment_types": ["Full Time", "Part Time"], "selling_points": [], "locations": ["Mong Kok"], "categories": ["Building & Construction", "Architectural Services", "Building / Construction / QS", "Civil / Structural"], "post_time": "2022-01-17T03:40:52Z", "salary": {"currency": null, "max": null, "min": null, "period": "hourly", "term": null}, "salary_visible": false, "title_keywords": [], "responsibilities": [], "requirements": {"degrees": [], "majors": [], "languages": ["english", "mandarin"], "language_level": [], "hard_skills": ["bim", "dynamic", "php", "plus"], "soft_skills": ["communication skill", "dynamic", "positive", "enthusiastic", "patient", "presentation", "passionate about"], "languages_combined": [{"language": "english", "language_level": []}, {"language": "mandarin", "language_level": []}]}, "experience_required": {"duration": [], "field": []}}, {"job_id": "100003009044717", "location_code": "hk", "company": "Sunley Engineering & Construction Company Limited", "job_title": "Engineer / Assistant Engineer", "description": "Job Responsibilities:\n-\u00a0 \u00a0 \u00a0 \u00a0 \u00a0 To supervise on-site daily routine works\n\u00a0 \u00a0 \u00a0 \u00a0 \u00a0 \u00a0(curtain wall / windows installation,etc)\n-\u00a0 \u00a0 \u00a0 \u00a0 \u00a0 To control and report the quality and progress\n-\u00a0 \u00a0 \u00a0 \u00a0 \u00a0 To make documentary records of the site\n-\u00a0 \u00a0 \u00a0 \u00a0 \u00a0 To monitor an effective control of material usage and to ensure work\n\u00a0 \u00a0 \u00a0 \u00a0 \u00a0 \u00a0 safety\n-\u00a0 \u00a0 \u00a0 \u00a0 \u00a0 To attend site meeting with clients & consultants\n\n\u8077\u8cac:\n-\u00a0 \u00a0 \u00a0 \u00a0 \u00a0 \u8ddf\u9032\u5730\u76e4\u65e5\u5e38\u5de5\u4f5c\n-\u00a0 \u00a0 \u00a0 \u00a0 \u00a0 \u76e3\u63a7\u53ca\u5831\u544a\u8cea\u91cf\u548c\u9032\u5ea6\n-\u00a0 \u00a0 \u00a0 \u00a0 \u00a0 \u8ca0\u8cac\u5730\u76e4\u7684\u6587\u4ef6\u8a18\u9304\n-\u00a0 \u00a0 \u00a0 \u00a0 \u00a0 \u76e3\u63a7\u7269\u8cc7\u904b\u7528\u548c\u78ba\u4fdd\u5730\u76e4\u8cea\u5b89\u74b0\n-\u00a0 \u00a0 \u00a0 \u00a0 \u00a0 \u53c3\u8207\u5ba2\u6236\u548c\u9867\u554f\u5728\u5730\u76e4\u7684\u6703\u8b70\n\nJob Requirements:\n-\u00a0 \u00a0 \u00a0 \u00a0 \u00a0 Diploma / Certificate in Engineering, Building Management or\n\u00a0 \u00a0 \u00a0 \u00a0 \u00a0 \u00a0equivalent\n-\u00a0 \u00a0 \u00a0 \u00a0 \u00a0 3-5 years' working experience in related to fa\u00e7ade works/curtain wall\n-\u00a0 \u00a0 \u00a0 \u00a0 \u00a0 Holder of TCP T1 Certificate\n-\u00a0 \u00a0 \u00a0 \u00a0 \u00a0 Able to read shop drawings\n\n\u5de5\u4f5c\u8981\u6c42:\n-\u00a0 \u00a0 \u00a0 \u00a0 \u00a0 \u6301\u5efa\u7bc9\u5de5\u7a0b\u6216\u76f8\u95dc\u5c08\u696d\u8b49\u66f8\u6216\u6587\u6191\n-\u00a0 \u00a0 \u00a0 \u00a0 \u00a0 3-5\u5e74\u5e55\u7246\u5de5\u7a0b\u5de5\u4f5c\u7d93\u9a57\n-\u00a0 \u00a0 \u00a0 \u00a0 \u00a0 \u6301\u6709\u9069\u4efb\u6280\u8853\u4eba\u54e1T1\u8b49\u66f8\n-\u00a0 \u00a0 \u00a0 \u00a0 \u00a0 \u61c2\u5f97\u95b1\u8b80\u5716\u5247\n\nInterested parties please send your full resume with current and expected salary by clicking \"Apply\".\n\n\u6709\u610f\u61c9\u5fb5\u8005\u8acb\u9644\u4e0a\u5c65\u6b77\u8868(\u5305\u62ec\u73fe\u6642\u53ca\u671f\u671b\u85aa\u91d1)\u53ca\u9ede\u64ca\u201cApply\u201d\u7533\u8acb\u3002", "employment_types": ["Full Time", "Permanent"], "selling_points": [], "locations": ["Not Specified"], "categories": ["Building & Construction", "Civil / Structural", "Engineering", "Others", "Others"], "post_time": "2022-01-13T05:40:48Z", "salary": {"currency": null, "max": null, "min": null, "period": "monthly", "term": null}, "salary_visible": false, "title_keywords": ["assistant engineer", "engineer"], "responsibilities": ["installation", "control", "quality", "monitor", "report"], "requirements": {"degrees": ["certificate", "diploma"], "majors": ["building management", "engineering"], "languages": [], "language_level": [], "hard_skills": ["tcp"], "soft_skills": [], "languages_combined": []}, "experience_required": {"duration": ["3-5 years"], "field": ["related"]}}, {"job_id": "100003009048265", "location_code": "hk", "company": "Polyfair Construction & Engineering Limited", "job_title": "Senior Site Supervisor / Site Supervisor (Fa\u00e7ade / Curtain Wall) (\u9ad8\u7d1a\u5730\u76e4\u76e3\u7763 / \u5730\u76e4\u76e3\u7763) (\u5e55\u7246\u5de5\u7a0b)", "description": "Requirements:-\n\nHigher Diploma or Degree Holder in Structural/Civil Engineering or equivalent;\n2-5 years or above relevant experience in Foundation/Civil projects is preferred;\nStrong communication and organization skills\nStrong command of both written & spoken English and Chinese\nImmediate available is preferred.\nProficiency in Microsoft Office and Project. Knowledge in AutoCAD operation is a must.\nCandidates with less experience and / or qualifications may apply for Assistant Engineer\n\nAttractive salary and fringe benefits will be offered to the successful candidates. Please apply with full resume, available date, present and expected salary to THE HUMAN RESOURCES DEPARTMENT, e-mail by clicking \"Apply Now\".\n\nAll Personal data collected will be used for recruitment purpose only.", "employment_types": ["Full Time"], "selling_points": ["3-5 Years' Experience", "Certificate or above", "Double Pay, Medical Insurance, Bank Holiday"], "locations": ["North Point"], "categories": ["Building & Construction", "Building / Construction / QS", "Civil / Structural", "Engineering", "Others"], "post_time": "2022-01-14T06:05:49Z", "salary": {"currency": null, "max": null, "min": null, "period": "monthly", "term": null}, "salary_visible": false, "title_keywords": ["site supervisor"], "responsibilities": ["communication"], "requirements": {"degrees": ["diploma", "degree holder"], "majors": ["civil engineering"], "languages": ["english", "chinese"], "language_level": [], "hard_skills": ["autocad", "microsoft office"], "soft_skills": ["communication", "organization skills"], "languages_combined": [{"language": "english", "language_level": []}, {"language": "chinese", "language_level": []}]}, "experience_required": {"duration": ["2-5 years"], "field": ["relevant experience", "civil projects"]}}, {"job_id": "100003009053438", "location_code": "hk", "company": "Able Engineering Company Limited", "job_title": "Assistant Clerk of Works", "description": "Job Description\n\nManage and supervise the QA/QC Team of the project to perform their duties;\nLiaise with Project Manager and Site Agent on all quality-related issues;\nConduct and prepare Quality Audit Reports;\nConduct site inspections and mitigate any potential quality problems to make sure the construction is performed in a quality manner;\nParticipate in site meetings to report the quality performance of the project timely; and\nCollect and analyze the date to drive continuous improvements.\n\nJob\u00a0Requirement\n\nHigh Diploma or above in Duilding Studies / Civil / Structural Engineering or related disciplines;\nMinimum 2 years of relevant working experience in QA/ QC;\nExperience in ISO9001 or relevant quality standards;\nExperience in the management of construction works and site supervisor;\nWith construction experience in ISO Audit and AAHK is an advantage;\nWith strong communication , analytical and negotiation skills;\nGood command of written and spoken English and Chinese;\nProficient in project management software tools such as Aconex and SnagR is an advantage; and\nImmediate available is an advantage.\n\n***What we offer?\n\nCompetitive remuneration package\nAdditional leave (Family Care Leave, Exam Leave, Qualification Leave, etc.)\nDiscretionary bonus\nStudy Subsidies\nComprehensive training and professional career development\n\nInterested parties please apply by clicking \"APPLY NOW\" with detailed CV stating expected salary and date of availability.\n\nCompany Website: \u00a0http://www.pyengineering.com/\n\nAll personal data provided will be used strictly in accordance with our \u201cPersonal Information Collection Statement Pertaining to Recruitment\u201d, a copy of which is available upon written request to us by E-mail.", "employment_types": ["Full Time", "Permanent"], "selling_points": [], "locations": ["Not Specified"], "categories": ["Building & Construction", "Building / Construction / QS", "Civil / Structural", "Others"], "post_time": "2022-01-17T06:59:11Z", "salary": {"currency": null, "max": null, "min": null, "period": "monthly", "term": null}, "salary_visible": false, "title_keywords": ["clerk", "assistant"], "responsibilities": ["continuous improvements", "site meetings", "quality", "audit", "reports", "site inspections", "liaise with", "report"], "requirements": {"degrees": ["high diploma or above"], "majors": ["related disciplines", "structural engineering"], "languages": ["english", "chinese"], "language_level": ["good command"], "hard_skills": ["project management"], "soft_skills": ["communication", "project management", "negotiation skills"], "languages_combined": [{"language": "english", "language_level": ["good command"]}, {"language": "chinese", "language_level": ["good command"]}]}, "experience_required": {"duration": ["minimum 2 years"], "field": ["management", "qa", "relevant working experience", "audit", "construction"]}}, {"job_id": "100003009049942", "location_code": "hk", "company": "Paul Y. Engineering Group", "job_title": "Quality Control Engineer", "description": "Job\u00a0Responsibilities:\n\nAssistant to Qualified Building Surveyor / Qualified Construction Manager to inter alia :-\n\n\nPrepare master and interim programmes and update the programmes from time to time on a bi-weekly basis\nPrepare shop drawings for the approval of Architect and Consultants\nPrepare Notification of Delays (NODs)\nTogether with the in-house QS to prepare the VOs\nManage the ordering of materials, in particular those require long lead-time\nCarry out regular site inspection with Safety Officer\nInspect works to ensure good workmanship\nAttend site meeting and prepare the minutes of meeting accordingly\nRequirements:\n\nA good Non-cognate Degree (2nd upper honoured degree or above) recognised by the government of HKSAR\nA construction related Cognate Degree in Building Surveying or Construction Management would be an advantage\nconversant in using word, excel and powerpoint, knowledge of computer aided design (CAD) would be an advantage\nGood command of spoken and written Chinese and English\nSelf-motivated, energetic and composed team player\n\nWe will provide : (1) mentorship and guidance (through qualified professionals) to selected candidates so that they can learn through on-the-job training; and (2) subject to conditions, assistance to selected candidates to enrol for construction related part-time studies and we shall pay for the tuition fees involved.\u00a0\u00a0 In addition, we offer attractive remuneration package with medical benefits to the right candidate.\u00a0 The incumbent will become part of the in-house project management team which consists of authorized person, qualified quantity surveyor and other construction professionals.\n\n\n\n\nFor those who are holding higher qualifications and more experience mentioned hereinabove, we may consider them for the post of \u201cProject Coordinator I\u201d.", "employment_types": ["Full Time", "Permanent"], "selling_points": ["Min 2 years of relevant working exp. in QA/QC", "HD or above in related disciplines", "Immediate available is an advantage"], "locations": ["Airport Area"], "categories": ["Building & Construction", "Building / Construction / QS", "Civil / Structural", "Engineering", "Engineering Project Management"], "post_time": "2022-01-15T03:50:44Z", "salary": {"currency": null, "max": null, "min": null, "period": "monthly", "term": null}, "salary_visible": false, "title_keywords": ["engineer"], "responsibilities": ["site inspection", "drawings"], "requirements": {"degrees": ["degree or above", "degree"], "majors": ["building surveying", "construction management"], "languages": ["english", "chinese"], "language_level": ["good command"], "hard_skills": ["excel", "word", "powerpoint", "cad"], "soft_skills": ["self-motivated", "energetic", "team player"], "languages_combined": [{"language": "english", "language_level": ["good command"]}, {"language": "chinese", "language_level": ["good command"]}]}, "experience_required": {"duration": [], "field": []}}, {"job_id": "100003009054355", "location_code": "hk", "company": "Shun Shing Contractors Limited", "job_title": "Project Coordinator II", "description": "We are one of the market leaders for premium architectural products in Hong Kong, seeking for right sales candidates to cope with the expanding business.\n\n\nDuties & Responsibilities:\u00a0\nTaking full\u00a0responsibility for managing\u00a0the implementation of construction activities\nLeading the operation team and sub-contractors to complete construction works within the target\nLiaising with Contractors, Consultants and Sub-Contractors\nSolving site problems with strategy development\n\nJobs Requirements\n\nHigh Certificate / High Diploma holder in Building, Civil / Structural Engineering or other construction related subject;\nAt least 10 years experience;\nPrevious experience with a main contractor is essential;\nGood command of Cantonese and English;\nGood knowledge of building and construction regulations and requirements in Hong Kong;\nGood command of computer software including MS Project, MS Excel and AutoCAD;\nHolder of valid Hong Kong driving license is preferred;\nMature, independent, initiative, co-operation and positive working attitude;\nSupervisions & Management skill;\nWorking experience in managing A&A, renovation and fitting out works with practical construction detail is required;\nSafety Supervisor Certificate holder;\nImmediate available is preferred\u00a0 \u00a0\n\nInterested parties please send your full resume with your availability, current and\u00a0expected salary\u00a0by\u00a0clicking\u00a0 \u201cAPPLY NOW\u201d.\n\n*Data collected will be used for recruitment purpose only*", "employment_types": ["Full Time"], "selling_points": [], "locations": ["Kwun Tong"], "categories": ["Building & Construction", "Building / Construction / QS", "Civil / Structural", "Engineering", "Engineering Project Management"], "post_time": "2022-01-17T09:25:48Z", "salary": {"currency": null, "max": null, "min": null, "period": "monthly", "term": null}, "salary_visible": false, "title_keywords": ["project coordinator"], "responsibilities": ["liaising with", "implementation"], "requirements": {"degrees": ["high diploma", "certificate"], "majors": ["structural engineering"], "languages": ["cantonese", "english"], "language_level": ["good command"], "hard_skills": ["ms excel", "autocad"], "soft_skills": ["positive working attitude", "independent", "initiative", "mature"], "languages_combined": [{"language": "cantonese", "language_level": ["good command"]}, {"language": "english", "language_level": ["good command"]}]}, "experience_required": {"duration": ["at least 10 years"], "field": ["construction"]}}, {"job_id": "100003009041261", "location_code": "hk", "company": "Lap Kai Engineering Company Limited", "job_title": "Site Engineer", "description": "Responsibilities:\n\nAssisting site team to prepare design and construction drawings for major construction projects.\n\n\u00a0Requirements:\n\nMinimum 5 years of relevant experience in preparation of 2D/ 3D drawings and familiar with CAD modeling, preferably with civil projector building services project experience (construction industry).\nProficiency in AutoCAD, MicroStation and other relevant computer software.\n\n\nWe offer attractive remuneration package with comprehensive fringe benefits to the right candidates. Interested parties please send resume with\u00a0day time contact number, expected salary and quoting Ref. No.\u00a0to the Human Resources Manager, 29/F., China Overseas Building, 139 Hennessy Road, Wanchai, Hong Kong or e-mail or fax to 2528 2840.\n\nInterested parties are invited to visit our website (www.cohl.com) for more information about us.\n\nApplicants who are not invited within 2 months may consider their applications unsuccessful. All information provided by applicants will be treated in strict confidence and used only for recruitment purposes. Applicants may be considered for other suitable positions within the China Overseas Group and its related companies over a one-year period, after which their personal data will be destroyed.\n\nServing The Community \u3002 Prospering Hong Kong", "employment_types": ["Full Time"], "selling_points": [], "locations": ["Not Specified"], "categories": ["Building & Construction", "Building / Construction / QS", "Civil / Structural", "Engineering", "Others"], "post_time": "2022-01-12T23:26:12Z", "salary": {"currency": null, "max": null, "min": null, "period": "monthly", "term": null}, "salary_visible": false, "title_keywords": ["site engineer"], "responsibilities": ["design", "drawings"], "requirements": {"degrees": [], "majors": [], "languages": [], "language_level": [], "hard_skills": ["cad", "autocad"], "soft_skills": [], "languages_combined": []}, "experience_required": {"duration": ["minimum 5 years"], "field": ["building services", "construction industry", "relevant experience"]}}, {"job_id": "100003009047163", "location_code": "hk", "company": "Hip Hing Construction Co Ltd", "job_title": "Project Engineer", "description": "Responsibility\n\nCommunicate and coordinate with the client, other contractors, and vendor\u2019s site personnel.\nTo liaise with client for collection of relevant information/cost to ease the potential\u00a0tender and quotation for fitting out works.\nTo supervise daily fitting out work progress, arrange worker schedule and fitting out site arrangements, company safety working practices.\nTo prepare the relevant site working progress report and daily fitting out work site working schedule.\nTo support all aspects of fitting out site works such as material handling and site co-ordination.\nAssist to solve on-site problems and report to the company\n\nRequirements:\n\nCertificate in Civil / Building Engineering/Architectural\u00a0Studies with 3 years relevant experience in project management, design and fitting out co-ordination and construction supervision in building works.\nGood command of both written and spoken English and Chinese.\nProficient in computer applications will be advantage, e.g., MS Word and MS Excel, Auto CAD etc.\nSelf-motivated and able to work under pressure.\nHolder of TCP T1 or equivalent.\nHigher priority with Holder of Safety Supervisor\u00a0\u00a0\nImmediate available is preferred.\n\nWe offer competitive package and attractive employee benefits including 5-day work\u00a0/ 5.5-day work (2 ex-gratia Sat-off per month),\u00a0ex-gratia rest day, birthday holiday,\u00a0All-in-One Flexible Benefit Plan,\u00a0training sponsorship and discretionary bonus.\n\nApplication with full resume, current and expected salary, and available date should be sent through email to The Human Resources Manager, quoting the appropriate reference number via email to\u00a0hr @chunwo.com\u00a0write to 5C, Hong Kong Spinners Industrial Building, 601-603 Tai Nan West Street, Cheung Sha Wan, Kowloon, Hong Kong.\n\nFor more information, please visit our website at www.chunwo.com\nPersonal data provided by job applicants would be used for recruitment purposes only.", "employment_types": ["Full Time", "Permanent"], "selling_points": ["Degree in Building/Civil/Structural Engineering", "Minimum 5 years' relevant working experience.", "Chartered, MHKIE, RPE, MIStructE, Building Project"], "locations": ["Not Specified"], "categories": ["Building & Construction", "Building / Construction / QS", "Civil / Structural", "Engineering", "Engineering Project Management"], "post_time": "2022-01-14T02:29:59Z", "salary": {"currency": null, "max": null, "min": null, "period": null, "term": null}, "salary_visible": false, "title_keywords": ["project engineer"], "responsibilities": ["cost", "site co-ordination", "quotation", "coordinate with", "liaise with client", "schedule", "tender", "report"], "requirements": {"degrees": ["certificate"], "majors": ["project management", "engineering", "design"], "languages": ["english", "chinese"], "language_level": ["good command"], "hard_skills": ["tcp", "auto cad", "project management", "ms excel", "ms word"], "soft_skills": ["project management", "self-motivated", "work under pressure"], "languages_combined": [{"language": "english", "language_level": ["good command"]}, {"language": "chinese", "language_level": ["good command"]}]}, "experience_required": {"duration": ["3 years"], "field": ["design", "project management", "relevant experience", "building engineering", "construction"]}}, {"job_id": "100003009050320", "location_code": "hk", "company": "Jibpool International Ltd", "job_title": "Site/Project Manager", "description": "Job Responsibilities:\n\nThird Runway Project in Hong Kong Airport;\nAttend regular meetings and prepare documents submissions;\nMonitor works progress and supervise various site works;\nProvide onsite engineering support during the construction phase, propose construction methods for various site activities;\nMonitor & supervise of work progress and co-ordinate of various activities at construction site;\nCoordinate with construction team or sub-contractor to ensure technical, quality and safety standards.\nJob Requirements:\n\nDegree/Diploma in Civil Engineering or equivalent\u00a0or other related disciplines;\nMinimum\u00a03 years\u2019 relevant experience in civil project with road, drainage, Underground Utilities\u00a0works is an advantage;\nChartered Engineer with Corporate membership of HKIE in Civil Discipline is an advantage;\nGood knowledge of BIM model software applications and experience in New Engineering Contract (NEC) are preferred;\nProficiency in AutoCAD drawing and MS Office;\nGood command of written English and Chinese and fluent in English and Cantonese;\nWith a high sense of responsibility, good communication, organizational and time management skills;\nCandidates with less experience/Fresh Graduates will be considered as Assistant Engineer.\nSAPRJV is one of contractor in Third Runway Project. The related project details are presented in HKAA website (https://www.threerunwaysystem.com/en/three-runway-system/project-overview/\u00a0)\n\nWe provide attractive remuneration package and fringe benefits for the right candidate.\u00a0 Interested parties please send detailed resume with current & expected salaries via\u00a0\u201cApply Now\u201d.", "employment_types": ["Full Time", "Permanent"], "selling_points": ["5 days work", "Performance bonus", "Medical insurance"], "locations": ["Quarry Bay"], "categories": ["Building & Construction", "Building / Construction / QS", "Civil / Structural", "Engineering", "Engineering Project Management"], "post_time": "2022-01-14T10:06:53Z", "salary": {"currency": null, "max": null, "min": null, "period": "monthly", "term": null}, "salary_visible": false, "title_keywords": ["project manager"], "responsibilities": ["site activities", "quality", "monitor", "coordinate with", "safety standards", "prepare documents"], "requirements": {"degrees": ["diploma", "degree"], "majors": ["related disciplines", "civil engineering"], "languages": ["cantonese", "english", "chinese"], "language_level": ["good command", "fluent"], "hard_skills": ["ms office", "bim", "hkie", "autocad"], "soft_skills": ["communication", "organizational", "high sense of responsibility", "time management skills"], "languages_combined": [{"language": "cantonese", "language_level": ["good command"]}, {"language": "english", "language_level": ["fluent", "good command"]}, {"language": "chinese", "language_level": ["fluent", "good command"]}]}, "experience_required": {"duration": ["minimum 3 years"], "field": ["relevant experience", "engineering", "drainage"]}}, {"job_id": "100003009047160", "location_code": "hk", "company": "Hip Hing Construction Co Ltd", "job_title": "Senior Engineer", "description": "Diploma or Higher Certificate in Building or Building Studies from a Hong Kong Polytechnic University / Polytechnic or Hong Kong Institute of Vocational Education / technical institute / technical college or equivalent;\nGrade E (Level 2) or above in Chinese Language and English Language in HKCEE/HKDSE or equivalent;\nAt least 10 years site experience including 6 years post qualification experience in the capacity of Clerk of Works;\nStrong interpersonal communication skills;\nWork on Pre-fabrication Factory in PRC.\n\nWe offer competitive salary package and career development opportunity to the successful candidate. Interested parties may send your full resume, present and expected salary, available date and contact number by email by clicking \"Apply Now\".\n\nTo visit our website for more information: www.ableeng.com.hk\n\n(As an Equal Opportunities Employer, Able is committed to eliminating discrimination in employment. The vacancy advertised is open to all applicants meeting the basic entry requirement irrespective of their disability, sex, marital status, pregnancy, age, family status, sexual orientation or race etc. Applicants not hearing from us within 6 months may consider their applications unsuccessful. Personal data collected will be used for recruitment related purposes only.)", "employment_types": ["Full Time", "Permanent"], "selling_points": ["Degree in Building/Civil/Structural Engineering", "Minimum 8 years' relevant working experience.", "Chartered, MHKIE, RPE, MIStructE, Building Project"], "locations": ["Not Specified"], "categories": ["Building & Construction", "Building / Construction / QS", "Civil / Structural", "Engineering", "Engineering Project Management"], "post_time": "2022-01-14T02:29:40Z", "salary": {"currency": null, "max": null, "min": null, "period": null, "term": null}, "salary_visible": false, "title_keywords": ["senior engineer"], "responsibilities": ["communication"], "requirements": {"degrees": ["diploma", "higher certificate", "hkdse"], "majors": ["building studies"], "languages": ["english", "chinese"], "language_level": [], "hard_skills": [], "soft_skills": ["communication skills", "interpersonal"], "languages_combined": [{"language": "english", "language_level": []}, {"language": "chinese", "language_level": []}]}, "experience_required": {"duration": ["at least 10 years", "6 years"], "field": []}}, {"job_id": "100003009047148", "location_code": "hk", "company": "David S. K. Au & Associates Ltd", "job_title": "Chartered Engineer (Geotechnical)", "description": "\u9435\u5668, \u92c1\u98fe\u9762\u677f, \u73bb\u7483\u5de5\u7a0b\u516c\u53f8\u8aa0\u8058 :\n\n\u5de5\u7a0b\u7d93\u7406\u2013 10\u5e74\u7d93\u9a57\u6216\u4ee5\u4e0a, \u6709\u9435\u5650, \u92c1\u98fe\u677f, \u6216\u73bb\u7483\u5de5\u7a0b\u7d93\u9a57\u512a\u5148\n\n\u00a0\u6709\u610f\u8005\u8acb\u8207Irene Chan \u806f\u7d612393 1112", "employment_types": ["Full Time", "Permanent"], "selling_points": [], "locations": ["North Point"], "categories": ["Building & Construction", "Civil / Structural"], "post_time": "2022-01-14T02:28:00Z", "salary": {"currency": null, "max": null, "min": null, "period": "monthly", "term": null}, "salary_visible": false, "title_keywords": ["engineer"], "responsibilities": [], "requirements": {"degrees": [], "majors": [], "languages": [], "language_level": [], "hard_skills": [], "soft_skills": [], "languages_combined": []}, "experience_required": {"duration": [], "field": []}}, {"job_id": "100003009048504", "location_code": "hk", "company": "Chun Wo Group", "job_title": "Site Supervisor", "description": "Qualifications & Experience required:\n\n\nRecognized engineering chartered qualification with at least 8 years of post chartered experience for the position of Senior Resident Engineer\nFamiliar with common practice in foundation, site formation, reinforced concrete and structural steel construction for private development projects\nBe adaptable and able to work independently coupled with strong interpersonal skills\nProficient in both written and spoken English and Chinese\n\n\nThe above positions based in Macau will be on contract basis to work on a big building project. The contract is approximately 12 months which may be lengthened or shortened subject to project development. Standard working hours will be 6 days per week, shift work may be required. Attractive remuneration package with gratuity will be offered to the successful candidate.\nFor interested applicants, please click \"Apply Now\" \u00a0to submit your online application.\nTo explore more job opportunities in Arup, please visit our website at http://www.arup.com/Careers/Experienced_Hires/ApplyForAJob\n\u00a0\nPersonal data collected will be used for recruitment purpose only. Applicants not contacted within 8 weeks may consider their applications unsuccessful.", "employment_types": ["Full Time", "Permanent"], "selling_points": ["Site working progress", "Project management", "TCP T1"], "locations": ["Not Specified"], "categories": ["Building & Construction", "Civil / Structural"], "post_time": "2022-01-14T06:41:50Z", "salary": {"currency": null, "max": null, "min": null, "period": null, "term": null}, "salary_visible": false, "title_keywords": ["site supervisor"], "responsibilities": ["personal data", "recruitment", "website"], "requirements": {"degrees": [], "majors": [], "languages": ["english", "chinese"], "language_level": ["proficient"], "hard_skills": [], "soft_skills": ["adaptable", "work independently", "interpersonal skills"], "languages_combined": [{"language": "english", "language_level": ["proficient"]}, {"language": "chinese", "language_level": ["proficient"]}]}, "experience_required": {"duration": ["at least 8 years"], "field": ["engineering"]}}, {"job_id": "100003009053961", "location_code": "hk", "company": "Able Engineering Company Limited", "job_title": "Clerk of Works", "description": "Responsible for technical submissions involving in design, drawings, specifications, contracts and reports, etc. to client\nResponsible for temporary works design\nCoordinate amongst design consultants, project team, government authorities and client in terms of design submission and approval to facilitate project implement\n\nJob Requirements:\n\nDegree in Civil / Geotechnical / Structural Engineering\nAt least 5 years' relevant post-qualification experience including experience in a key position on site for supervision or construction of works\nProficient in AutoCAD\nAble to work under pressure\nCandidate with less experience or qualification will be considered as Assistant Engineer\n\nWork location: Tung Chung\n\nPublic Holiday, Medical Insurance, Annual Leave, 5.5-days works, Saturday off at alternative week", "employment_types": ["Full Time", "Permanent"], "selling_points": [], "locations": ["Not Specified"], "categories": ["Building & Construction", "Building / Construction / QS", "Civil / Structural", "Others"], "post_time": "2022-01-17T07:52:49Z", "salary": {"currency": null, "max": null, "min": null, "period": "monthly", "term": null}, "salary_visible": false, "title_keywords": ["clerk"], "responsibilities": ["contracts", "design", "drawings", "coordinate", "specifications", "reports", "work under pressure"], "requirements": {"degrees": ["degree"], "majors": ["structural engineering"], "languages": [], "language_level": [], "hard_skills": ["autocad"], "soft_skills": ["responsible", "work under pressure"], "languages_combined": []}, "experience_required": {"duration": ["at least 5 years"], "field": ["post-qualification", "construction"]}}, {"job_id": "100003009054228", "location_code": "hk", "company": "Hop Fat Structural Steel Engineering Company Limited", "job_title": "\u5de5\u7a0b\u7d93\u7406", "description": "Degree in Civil or Geotechnical Engineering or equivalent\nCorporate membership of HKIE (Geotechnical Discipline)\nRegistered Professional Engineer (Geotechnical Discipline) with at least 3 years post-professional qualification experiences in the supervision and co-ordination of geotechnical elements of construction projects\nCandidates with previous experiences in working as resident engineer on foundation and excavation and lateral support works will be an advantage\nBe adaptable and able to work independently coupled with strong interpersonal skills\nGood command of both written and spoken English and Chinese\nThe above position will be on contract basis to work on foundation, excavation and site formation related works. The contract will be 12 months initially and may be lengthened subject to the performance and the project development.\u00a0 Standard working hours will be 6 days per week. Attractive remuneration package will be offered to the successful candidates.\n\nFor interested applicants, please click \"Apply Now\" \u00a0to submit your online application.\n\nTo explore more job opportunities in Arup, please visit our website at http://www.arup.com/Careers/Experienced_Hires/ApplyForAJob\n\nPersonal data collected will be used for recruitment purpose only. Applicants not contacted within 8 weeks may consider their applications unsuccessful.", "employment_types": ["Full Time"], "selling_points": [], "locations": ["Not Specified"], "categories": ["Building & Construction", "Civil / Structural"], "post_time": "2022-01-17T08:51:34Z", "salary": {"currency": null, "max": null, "min": null, "period": "monthly", "term": null}, "salary_visible": false, "title_keywords": [], "responsibilities": ["lateral support works", "recruitment", "website", "personal data"], "requirements": {"degrees": ["degree"], "majors": ["engineering"], "languages": ["english", "chinese"], "language_level": ["good command"], "hard_skills": ["hkie"], "soft_skills": ["adaptable", "work independently", "interpersonal skills"], "languages_combined": [{"language": "english", "language_level": ["good command"]}, {"language": "chinese", "language_level": ["good command"]}]}, "experience_required": {"duration": ["at least 3 years"], "field": ["construction"]}}, {"job_id": "100003009052062", "location_code": "hk", "company": "WECON LIMITED", "job_title": "\u9ad8\u7d1a\u7ba1\u5de5/\u5730\u76e4\u7ba1\u5de5/\u52a9\u7406\u7ba1\u5de5 (Sr. Foreman/Foreman/Asst. Foreman)", "description": "Degree in Structural Engineering / Civil Engineering or construction related discipline.\nAssist the project team to liaise and co-ordinate with consultants, sub-contractors and suppliers for developing construction details, monitoring site progress and conducting of site co-ordination works.\nNew graduates are welcome to apply for this position.\n\n\nInterested candidates please contact us by \"Apply Now\" for job information if you have any further enquiry.\n\n", "employment_types": ["Full Time", "Permanent"], "selling_points": [], "locations": ["Not Specified"], "categories": ["Building & Construction", "Building / Construction / QS", "Civil / Structural", "Engineering", "Engineering Project Management"], "post_time": "2022-01-17T02:00:31Z", "salary": {"currency": null, "max": null, "min": null, "period": "monthly", "term": null}, "salary_visible": false, "title_keywords": ["foreman"], "responsibilities": ["liaise", "co-ordinate with", "site co-ordination", "monitoring", "developing"], "requirements": {"degrees": ["degree"], "majors": ["structural engineering", "civil engineering"], "languages": [], "language_level": [], "hard_skills": [], "soft_skills": [], "languages_combined": []}, "experience_required": {"duration": [], "field": []}}, {"job_id": "100003009044703", "location_code": "hk", "company": "China Railway Engineering (Hong Kong) Limited", "job_title": "Engineer / Assistant Engineer", "description": "MHKIE (Structural) or (Civil)\n\nDegree Holder in Civil & Structural Engineering\n\nMin 4 years relevant working experience with 2 years experience at Consultant Firm is preferable.\n\nSalary \u2013to be negotiable\n\n5-day work\n\nAnnual leave \u00a0+ Medical Insurance + Performance Bonus", "employment_types": ["Full Time", "Permanent"], "selling_points": [], "locations": ["Tung Chung"], "categories": ["Building & Construction", "Civil / Structural"], "post_time": "2022-01-13T05:36:50Z", "salary": {"currency": null, "max": null, "min": null, "period": "monthly", "term": null}, "salary_visible": false, "title_keywords": ["assistant engineer", "engineer"], "responsibilities": ["insurance"], "requirements": {"degrees": ["degree holder"], "majors": ["civil & structural engineering"], "languages": [], "language_level": [], "hard_skills": ["mhkie"], "soft_skills": [], "languages_combined": []}, "experience_required": {"duration": ["2 years", "min 4 years"], "field": ["relevant working experience"]}}, {"job_id": "100003009047330", "location_code": "hk", "company": "Arup", "job_title": "Resident Engineer (Geotechnical)", "description": "Duties:\n\nProvide engineering design/drawing and calculation and implement the design of the projects in those civil and structural works;\nAssist the Design Manager on all aspects of geotechnical engineering design works\nIdentify possible design and construction issues\u00a0\nManage design submissions from sub-contractors including site visits to review design proposals\nCoordinate between construction team, clients, government agencies, design institutes, and other stakeholders to facilitate project implementation;\nAssist in technical proposal preparation, prepare design documents and assessment report;\nRequirements:\n\nHigher Diploma or Bachelor Degree in Civil / Structural Engineering or or equivalent\nGood experience in management Civil/ Structural design and statutory approvals;\nMinimum 3 years of relevant design experience in relevant sector(s)\nFamiliar with latest design standards/codes and government submission procedures;\nGood command of both written and spoken English while Chinese language skills are preferred\nCandidates with professional qualification(s) are preferred", "employment_types": ["Full Time", "Contract"], "selling_points": [], "locations": ["Kowloon City Area"], "categories": ["Building & Construction", "Civil / Structural", "Engineering", "Others", "Others"], "post_time": "2022-01-14T02:54:58Z", "salary": {"currency": null, "max": null, "min": null, "period": null, "term": null}, "salary_visible": false, "title_keywords": ["resident engineer"], "responsibilities": ["engineering design", "review", "implementation", "design", "coordinate", "report"], "requirements": {"degrees": ["diploma", "degree", "bachelor"], "majors": ["structural engineering"], "languages": ["english", "chinese"], "language_level": ["good command"], "hard_skills": ["codes"], "soft_skills": [], "languages_combined": [{"language": "english", "language_level": ["good command"]}, {"language": "chinese", "language_level": ["good command"]}]}, "experience_required": {"duration": ["minimum 3 years"], "field": ["management", "structural design", "design"]}}, {"job_id": "100003009052254", "location_code": "hk", "company": "Spring Professional (Hong Kong) Limited", "job_title": "Project Manager (Residential and commercial building) (HK and China project)", "description": "Responsibilities:\n\nCoordinate with clients and sub-contractors to facilitate site progress, safety and quality control.\nAttend site visits and meetings.\nPrepare and regularly review short term program, master program, materials and shop drawings submission schedule.\nPlan, prepare, organize and maintain project documentations\nPerform ad hoc duties as assigned\n\nRequirements:\n\nDegree/ Diploma in Building Studies or equivalent\nMin. 5 years relevant working experience\n2 years in maintenance work in the capacity of site representative or working experience in the government maintenance work is an advantage\nGood command of both written and spoken English and Chinese\nKnowledge of AutoCad and MS office\nStrong communication and problem solving skill.\nImmediate available is an advantage\n\nCandidates with less experience will be considered as\n\n\u00a0\u201cAssistant Project Coordinator \".\n\n\u00a0We offer a competitive remuneration package\uff1a\n\n14 Days Annual Leave\nBirthday Leave\nEducation Allowance\nPerformance Bonus\nMedical Insurance\n\nInterested parties, please send full resume with\u00a0expected salary\u00a0and\u00a0available date by clicking \" Apply Now\"\n\n\n(Data collected will be used for recruitment purpose only.)\n", "employment_types": ["Full Time"], "selling_points": ["Luxury Residential building (HK)", "High Rise Commercial Building (China)", "Developer in Hong Kong"], "locations": ["Tsim Sha Tsui"], "categories": ["Building & Construction", "Architectural Services", "Building / Construction / QS", "Civil / Structural"], "post_time": "2022-01-17T02:34:59Z", "salary": {"currency": null, "max": null, "min": null, "period": "monthly", "term": null}, "salary_visible": false, "title_keywords": ["project manager"], "responsibilities": ["ad hoc duties", "review", "drawings", "coordinate with clients", "maintain", "schedule", "quality control", "plan"], "requirements": {"degrees": ["diploma", "degree"], "majors": ["building studies"], "languages": ["english", "chinese"], "language_level": ["good command"], "hard_skills": ["problem solving", "ms office", "maintenance", "autocad"], "soft_skills": ["communication", "problem solving skill"], "languages_combined": [{"language": "english", "language_level": ["good command"]}, {"language": "chinese", "language_level": ["good command"]}]}, "experience_required": {"duration": ["5 years", "2 years"], "field": ["relevant working experience", "maintenance"]}}, {"job_id": "100003009049068", "location_code": "hk", "company": "TalentQuest HR Limited", "job_title": "Design Engineer / Senior Design Engineer - Building / Civil", "description": "Job Highlights\n- Degree in Structural Engineering or related\n- 2 years relevant experience or fresh graduates\n- immediate availability preferred\n\nRequirements\n\nBachelor Degree or above in Structural Engineering\u00a0or related disciplines\nWith 2 years or above relevant working experiences in Structural/Geotechnical Engineering design, Modular Integrated Construction (MiC) design will be consider for position of Assistant Engineer\nFresh Graduates are also welcome for position of Graduate Engineer\nProficiency in Structural/Geotechnical software\nGood command of both Chinese and English language\nGood communication and presentation skills\nEager to learn and hardworking\nAttractive package will be offer to the right candidate\nImmediate availability will be an advantage\n\nWe offer a competitive remuneration package commensurate\u00a0e.g.\u00a05 days work, year-end bonus, medical insurance and transportation allowance, etc.,\u00a0to the\u00a0right candidate and long-term career development opportunities.\n\nPlease send full\u00a0resume and employment references, state availability, expected salary package and contact telephone number\u00a0by clicking\u00a0\"Apply Now\".\nFor more information, please visit our website at:\u00a0https://www.wil.com.hk/\n(All personal data collected is only used for recruitment purpose only)", "employment_types": ["Full Time"], "selling_points": ["Hands-on experience in a mega civil / building pro", "Good project reference", "13 - 14 months salary"], "locations": ["Not Specified"], "categories": ["Building & Construction", "Building / Construction / QS", "Civil / Structural", "Engineering", "Engineering Project Management"], "post_time": "2022-01-14T08:02:30Z", "salary": {"currency": null, "max": null, "min": null, "period": "monthly", "term": null}, "salary_visible": false, "title_keywords": ["design engineer"], "responsibilities": ["communication", "engineering design", "software", "design"], "requirements": {"degrees": ["degree or above", "degree", "bachelor"], "majors": ["related disciplines", "structural engineering"], "languages": ["english", "chinese"], "language_level": ["good command"], "hard_skills": [], "soft_skills": ["communication", "eager to learn", "presentation skills", "hardworking"], "languages_combined": [{"language": "english", "language_level": ["good command"]}, {"language": "chinese", "language_level": ["good command"]}]}, "experience_required": {"duration": ["2 years"], "field": ["engineering", "structural", "design", "relevant experience", "construction"]}}, {"job_id": "100003009046771", "location_code": "hk", "company": "Jumbo Orient Contracting Limited", "job_title": "Structural Engineer", "description": "Responsibilities\n\nLead a team of design management engineers to manage and collaborate with design consultants and internal designers, as well as review design and statutory submissions\nAchieve an integrated and coordinated design and programme with other disciplines and provide directions on key design issues to meet the objectives of the new projects\nAssist in coordinating with stakeholders and senior officials of related government departments to resolve all technical, interface and statutory issues\n\nRequirement\n\nDegree in Civil Engineering or a related discipline\nA minimum of 10 years' experience in managing the design of large-scale infrastructure projects in a multi-disciplinary environment\nExperience in managing projects with Building Information Management and interfacing works with operating railway is preferred\nPossession of Corporate Membership of a recognised professional institution is preferred\nExcellent interpersonal, communication and leadership skills\nGood command of both written and spoken English\n\nRemarks\n\nAppointment will be made on two-year renewable contract terms\n\nApplications\nYou are invited to apply online via\u00a0http://www.mtr.com.hk/mtr_job_en\u00a0or send in your CV stating the position (with reference number) you are applying for by mail to Human Resource Management Department, MTR Corporation, G.P.O. Box 9916, Hong Kong on or before 27\u00a0January 2022.\n\u00a0\nFor other job openings, please visit MTR Corporation\u2019s website for more details.\n\u00a0\nAll information provided by applicants will be treated in strict confidence and used for recruitment purpose only. All personal data of unsuccessful applicants will be retained for 12 months for future recruitment purpose and will then be destroyed.", "employment_types": ["Full Time", "Permanent"], "selling_points": [], "locations": ["Lai Chi Kok"], "categories": ["Building & Construction", "Civil / Structural"], "post_time": "2022-01-14T01:00:17Z", "salary": {"currency": null, "max": null, "min": null, "period": "monthly", "term": null}, "salary_visible": false, "title_keywords": ["engineer"], "responsibilities": ["collaborate with", "review", "design", "lead a team", "design management"], "requirements": {"degrees": ["degree"], "majors": ["civil engineering"], "languages": ["english"], "language_level": ["good command"], "hard_skills": [], "soft_skills": ["communication", "leadership skills", "confidence", "interpersonal"], "languages_combined": [{"language": "english", "language_level": ["good command"]}]}, "experience_required": {"duration": ["minimum of 10 years"], "field": ["management", "infrastructure", "design"]}}, {"job_id": "100003009047449", "location_code": "hk", "company": "Wilson & Associates Limited", "job_title": "Assistant Engineer / Graduate Engineer (Structural)", "description": "The successful candidate will be responsible for supervising and monitoring the construction site works to ensure timely completion of projects with high quality standard.\nRequirements:\nFor New Built project \u2013 Minimum 6 years of proven site experience in residential building construction\nFor Fitting-out project - Minimum 6 years of proven site experience in hospitality or commercial building construction, preferably in large-scaled fitting-out projects\nDiploma / Higher Certificate in Building Studies / Building Engineering or equivalent\nSound technical and management knowledge gained with building contractors or developers\nWell organized and self-motivated with strong integrity, interpersonal and communication skills\nExperienced candidates but with lower academic qualifications will also be considered\nWe offer attractive remuneration packages commensurate with experience and qualifications. If you aspire to an exciting and rewarding career, send your resume immediately, quoting your present and expected salaries by clicking the button \u201cApply Now\u201d.\nIf the applicant does not receive a response by 13 February 2022, the application will be considered unsuccessful. Please read our Personal Information Collection Statement at https://www.sino.com/en-US/Careers/Personal-Information-Collection-Statement before submitting your application. Information provided by applicants will be treated in strict confidence and used for recruitment purposes only.", "employment_types": ["Full Time"], "selling_points": [], "locations": ["Wong Tai Sin Area"], "categories": ["Building & Construction", "Civil / Structural"], "post_time": "2022-01-14T03:07:11Z", "salary": {"currency": null, "max": null, "min": null, "period": "monthly", "term": null}, "salary_visible": false, "title_keywords": ["graduate engineer", "assistant engineer"], "responsibilities": ["management", "supervising", "monitoring", "quality", "communication"], "requirements": {"degrees": ["diploma", "higher certificate"], "majors": ["building studies", "engineering"], "languages": [], "language_level": [], "hard_skills": [], "soft_skills": ["communication skills", "self-motivated", "responsible", "timely", "integrity", "well organized", "interpersonal"], "languages_combined": []}, "experience_required": {"duration": ["minimum 6 years"], "field": ["commercial", "construction"]}}, {"job_id": "100003009050573", "location_code": "hk", "company": "Sino Group", "job_title": "Owner\u2019s Site Representative (For New Built/ Fitting-out project) (Ref: OSR/JDB)", "description": "Responsibilities:\n\nSupervise and monitor the subcontractors and suppliers performance;\nLiaise with client/consultant on points requiring clarification;\nAssist Project Manager for day-to-day operation, prepare method statement and shop drawings;\nAttend weekly, monthly meets with client and subcontractors;\nHandle and resolve site constrain and site problem.\n\n\u00a0Requirements - Qualification:\n\nDegree holder or above in Civil / Building Engineering disciplines;\nMinimum 5 years of A&A works site experience; preferably with experience in HKIA or MTR projects;\nHolder of Valid green card;\nProficiency in Microsoft Office, Microsoft Project and Chinese word processing;\nGood command of both written and spoken English and Chinese.\nCandidates with less experiences will be considered as Senior Project Engineer.\n\n\u00a0Requirements \u2013 Competences:\n\n\u00a0Good communication and interpersonal skills.\n\nWe look forward to receiving your application with detailed resume stating\u00a0working experience,\u00a0academic and language qualifications, existing and EXPECTED SALARY\u00a0as well as\u00a0availability.\u00a0All applications will be kept strictly confidential.\n\nWe offer promising professional career and exposure\u00a0to right candidate, together with attractive remuneration package including\u00a0discretionary bonus, continuing education allowance, medical and dental coverage.\n\nPersonal Data collected will be used for recruitment-related purposes only.", "employment_types": ["Full Time"], "selling_points": [], "locations": ["Not Specified"], "categories": ["Building & Construction", "Building / Construction / QS", "Civil / Structural", "Others"], "post_time": "2022-01-14T10:48:04Z", "salary": {"currency": null, "max": null, "min": null, "period": null, "term": null}, "salary_visible": false, "title_keywords": ["representative"], "responsibilities": ["clarification", "monitor", "drawings", "liaise with client", "day-to-day operation"], "requirements": {"degrees": ["degree holder"], "majors": ["engineering"], "languages": ["english", "chinese"], "language_level": ["proficiency", "good command"], "hard_skills": ["microsoft office", "microsoft project", "chinese word processing", "green card"], "soft_skills": ["communication and interpersonal skills", "detailed"], "languages_combined": [{"language": "english", "language_level": ["good command"]}, {"language": "chinese", "language_level": ["proficiency", "good command"]}]}, "experience_required": {"duration": ["minimum 5 years"], "field": []}}, {"job_id": "100003009046881", "location_code": "hk", "company": "LIEBHERR-SINGAPORE PTE LTD.", "job_title": "Assistant Project Engineer", "description": "Responsibility\n\n\nCommunicate and coordinate with the client, other contractors and vendor\u2019s site personnel;\nTo liaise with client for collection of relevant information/cost to ease the potential\u00a0 tender and quotation for fitting out works;\nTo supervise daily fitting out work progress, arrange worker schedule and fitting out site arrangements, company safety working practices;\nTo prepare the relevant site working progress report and daily fitting out work site working schedule;\nTo support all aspects of fitting out site works such as material handling and site co-ordination;\nAssist to solve on-site problems and report to the company\n\nRequirements:\n\nCertificate in Civil / Building Engineering/Architectural\u00a0Studies with 3 years relevant experience in project management, design and fitting out co-ordination and construction supervision in building works.\nGood command of both written and spoken English and Chinese;\nProficient in computer applications will be advantage, e.g. MS Word and MS Excel, Auto CAD etc;\nSelf-motivated and able to work under pressure;\nHolder of TCP T1 or equivalent .\nHigher priority with Holder of Safety Supervisor\u00a0\u00a0\nLess experience will be considered for the position of Foreman.\nImmediate available is preferred.", "employment_types": ["Full Time"], "selling_points": [], "locations": ["Shatin Area"], "categories": ["Building & Construction", "Civil / Structural", "Engineering", "Others"], "post_time": "2022-01-14T01:36:51Z", "salary": {"currency": null, "max": null, "min": null, "period": "monthly", "term": null}, "salary_visible": false, "title_keywords": ["assistant project engineer"], "responsibilities": ["cost", "site co-ordination", "quotation", "coordinate with", "liaise with client", "schedule", "tender", "report"], "requirements": {"degrees": ["certificate"], "majors": ["project management", "engineering", "design"], "languages": ["english", "chinese"], "language_level": ["good command"], "hard_skills": ["tcp", "auto cad", "project management", "ms excel", "ms word"], "soft_skills": ["project management", "self-motivated", "work under pressure"], "languages_combined": [{"language": "english", "language_level": ["good command"]}, {"language": "chinese", "language_level": ["good command"]}]}, "experience_required": {"duration": ["3 years"], "field": ["design", "project management", "relevant experience", "building engineering", "construction"]}}, {"job_id": "100003009048620", "location_code": "hk", "company": "Kum Shing Group", "job_title": "Senior Manager - Civil / Building (Major Projects)", "description": "Requirements\nFresh graduate with degree or equivalent in Civil Engineering or related disciplines\nGood command of both written and spoken Chinese and English\nWell versed in MS Office applications\nGood analytical and problem solving skills\nExcellent interpersonal and communication skills\nAble to work efficiently under pressure\nKnowledge / Experience in projects relating water / wastewater treatment plant, pumping stations, service reservoirs and pipelines would be an advantage\nImmediate Available is an advantage\n\nWe offer:\n\nScheme \u201cA\u201d Training accredited by HKIE\nCompetitive salary commensurate with qualifications and experience\n5-day work\nMedical & life insurance scheme coverage\n\nPersonal information contained in applications received will be used for employment-related purposes and, in respect of the successful appointee only, also for business-related purposes.\u00a0Please send full resume, availability, present and expected salaries and daytime contact telephone number quoting reference code to:\u00a0Human Resources Department, Binnies Hong Kong Limited, 43/F, AIA Kowloon Tower, 100 How Ming Street, Kowloon, Hong Kong or by clicking 'Apply Now'.", "employment_types": ["Full Time", "Permanent"], "selling_points": ["Capital construction projects of public works", "Degree in Civil / Building Engineering disciplines", "Performance bonus, education subsidy, medical plan"], "locations": ["To Kwa Wan"], "categories": ["Building & Construction", "Civil / Structural", "Engineering", "Engineering Project Management", "Others"], "post_time": "2022-01-14T06:54:40Z", "salary": {"currency": null, "max": null, "min": null, "period": "monthly", "term": null}, "salary_visible": false, "title_keywords": ["senior manager"], "responsibilities": ["communication"], "requirements": {"degrees": ["degree", "fresh graduate"], "majors": ["related disciplines", "civil engineering"], "languages": ["english", "chinese"], "language_level": ["good command"], "hard_skills": ["pipelines", "problem solving skills", "ms office"], "soft_skills": ["communication skills", "analytical and problem solving skills", "under pressure", "interpersonal"], "languages_combined": [{"language": "english", "language_level": ["good command"]}, {"language": "chinese", "language_level": ["good command"]}]}, "experience_required": {"duration": [], "field": []}}, {"job_id": "100003009048535", "location_code": "hk", "company": "Kum Shing Group", "job_title": "Assistant Manager \u2013 Civil / Building", "description": "Degree/ Diploma in Building Studies, Structural, Civil, Construction Management or related\n2 years' or above relevant working experience in\u00a0 Building Construction\nExperienced in Residential, HKHA, ASD, A&A and Fit Out projects is preferred\u00a0\u00a0\nGood command in both Chinese and English.\u00a0\n\nIf interested, please send us CV to talent@ awclhk.com or click \"APPLY NOW\". For more information, please call +852 37528883", "employment_types": ["Full Time", "Permanent"], "selling_points": ["Performance bonus, education subsidy, medical plan", "Excellent career path", "Minimum 5 years of A&A works site experience"], "locations": ["To Kwa Wan"], "categories": ["Building & Construction", "Building / Construction / QS", "Civil / Structural", "Engineering", "Engineering Project Management"], "post_time": "2022-01-14T06:45:23Z", "salary": {"currency": null, "max": null, "min": null, "period": "monthly", "term": null}, "salary_visible": false, "title_keywords": ["assistant manager"], "responsibilities": ["construction management"], "requirements": {"degrees": ["diploma", "degree"], "majors": ["construction management", "building studies"], "languages": ["english", "chinese"], "language_level": ["good command"], "hard_skills": [], "soft_skills": [], "languages_combined": [{"language": "english", "language_level": ["good command"]}, {"language": "chinese", "language_level": ["good command"]}]}, "experience_required": {"duration": ["2 years"], "field": ["construction", "relevant working experience"]}}, {"job_id": "100003009046243", "location_code": "hk", "company": "Sang Fai Construction Engineering Company Limited", "job_title": "Site Foreman/Site Supervisor", "description": "Degree in Materials / Civil / Structural Engineering or related discipline\nCorporate membership of relevant professional institution(s)\nAt least 2 years of practical experience for the position of Assistant Engineer; at least 3 years of practical experience for the position of Engineer\nPractical application of materials engineering in construction including condition survey, rehabilitation, renovation and repair is highly preferred\nGood technical experience on structural rehabilitation and maintenance of infrastructures and buildings\nExperience in project management of rehabilitation projects\nStrong interest and skill in the application and testing of construction materials, condition survey, durability and deterioration assessment, failure investigation and corrosion engineering\nExcellent written and spoken English and Chinese\n\nWe offer a competitive remuneration package commensurate with qualifications and experience to the right candidate including Global Profit Share scheme, additional fringe benefits of maternity/paternity leave and long-term career development opportunities.\u00a0\n\nFor interested applicants, please click \u201cApply Now\" to submit your online application.\n\n\nTo explore more job opportunities in Arup, please visit our website at http://www.arup.com/Careers/Experienced_Hires/ApplyForAJob\n\u00a0\nPersonal data collected will be used for recruitment purpose only. Applicants not contacted within 8 weeks may consider their applications unsuccessful.", "employment_types": ["Full Time"], "selling_points": [], "locations": ["Wan Chai Area"], "categories": ["Building & Construction", "Architectural Services", "Building / Construction / QS", "Civil / Structural"], "post_time": "2022-01-13T10:04:58Z", "salary": {"currency": null, "max": null, "min": null, "period": "monthly", "term": null}, "salary_visible": false, "title_keywords": ["site foreman", "site supervisor"], "responsibilities": ["rehabilitation", "maintenance", "renovation", "website", "investigation", "testing", "condition survey", "repair", "project management", "recruitment", "career development", "personal data"], "requirements": {"degrees": ["degree"], "majors": ["structural engineering"], "languages": ["english", "chinese"], "language_level": ["excellent"], "hard_skills": ["project management", "scheme", "maintenance"], "soft_skills": ["project management"], "languages_combined": [{"language": "english", "language_level": ["excellent"]}, {"language": "chinese", "language_level": ["excellent"]}]}, "experience_required": {"duration": ["at least 2 years", "at least 3 years"], "field": ["project management", "structural", "maintenance", "development"]}}, {"job_id": "100003009050938", "location_code": "hk", "company": "Chevalier Group -  Aluminium Windows & Curtain Walls", "job_title": "Structural Engineer/ Assistant Structural Engineer", "description": "Responsibilities:\n\n-\u00a0 Overall construction management of a residential property development project from initial to handover stage\n\n-\u00a0 Manage and coordinate with internal and external stakeholders including (project team, consultants, contractors and government authorities)\n\nRequirements:\n\n-\u00a0 Degree holder in Architecture/Building Studies/Structural Engineering/Civil Engineering, E&M Engineering or related disciplines\n\n-\u00a0 Chartered engineer and/or membership of recognized professional bodies.\n\n-\u00a0 Solid knowledge in statutory regulations compliance\n\n-\u00a0 Minimum 10 years relevant working experience in large scale construction projects\n\n-\u00a0 Working with consultancy firm or property developers preferred\n\n-\u00a0 Strong leadership, planning and management skills\n\n-\u00a0 Proficient both in written and spoken English and Chinese (including Mandarin)\n\n\nInterested parties please send full resume with salary expected and date available by clicking\u00a0APPLY NOW\n\n(All information received will be kept in strict confidence and for recruitment purpose only)", "employment_types": ["Full Time", "Permanent"], "selling_points": ["Perform structural calculation", "Higher Diploma or above in relevant disciplines", "Fresh graduates are welcome"], "locations": ["Kowloon Bay"], "categories": ["Building & Construction", "Building / Construction / QS", "Civil / Structural", "Engineering", "Engineering Project Management"], "post_time": "2022-01-14T11:51:58Z", "salary": {"currency": null, "max": null, "min": null, "period": null, "term": null}, "salary_visible": false, "title_keywords": ["engineer", "assistant"], "responsibilities": ["construction management", "coordinate with"], "requirements": {"degrees": ["degree holder"], "majors": ["engineering", "building studies", "related disciplines", "structural engineering", "architecture", "civil engineering"], "languages": ["english", "chinese", "mandarin"], "language_level": ["proficient"], "hard_skills": [], "soft_skills": ["leadership"], "languages_combined": [{"language": "english", "language_level": ["proficient"]}, {"language": "chinese", "language_level": ["proficient"]}, {"language": "mandarin", "language_level": ["proficient"]}]}, "experience_required": {"duration": ["minimum 10 years"], "field": ["construction", "relevant working experience"]}}, {"job_id": "100003009052404", "location_code": "hk", "company": "K. H. Foundations Ltd.", "job_title": "Safety Officer / Assistant Safety Officer / Safety Supervisor", "description": "Job Description:\n\nReporting to the manager of Engineering Section,\u00a0assist in structural analysis, stress calculation of aluminum and steel works\nSupport the Project Manager in the daily operations of the projects\nHandle basic modeling, analysis, and design\nSupervise and provide guidance to junior engineer\nLiaise with clients, consultants and sub-contractors for drawing submission and structural related documents\nLiaise and communicate with the Building Department, HKSAR on project issues.\nReview existing designs\u00a0and provide enhancements whenever necessary\u00a0\n\nQualification:\n\nPost-secondary education or above in Structural Engineering or relevant discipline\n3-5 years of experience in structural design and calculation and reinforced concrete structure\nExperience in temporary works design in metal industry preferred\nGood IT skills, AutoCAD, Microsoft office, SAP2000, MathCAD\u00a0\nFamiliar with procedures of Government projects\nFamiliar with design standards, regulations, and codes\nKnowledge in BIM will be an advantage\nNovative, proactive, and good at managing tasks with a tight schedule\nGood team player, resourceful and be able to work well with people at all levels\nImmediate available preferred\u00a0\nCandidate with more experience will be considered for the position of Senior Structural Engineer\u00a0\nWe offer a variety of staff benefits including double pay, bonus, medical insurance, birthday leave, education subsidies, and provide a stable work environment to create opportunities for development.\n\nInterested parties please send resume with day time contact number and expected salary through APPLY NOW We are an equal opportunity employer and welcome application from all qualified candidates.\n\nAll information provided by applicants will be treated in strict confidence and used only for recruitment purposes.\u00a0", "employment_types": ["Full Time", "Permanent"], "selling_points": [], "locations": ["Not Specified"], "categories": ["Building & Construction", "Building / Construction / QS", "Civil / Structural", "Engineering", "Engineering Project Management"], "post_time": "2022-01-17T02:57:57Z", "salary": {"currency": null, "max": null, "min": null, "period": "monthly", "term": null}, "salary_visible": false, "title_keywords": ["assistant safety officer", "safety officer", "safety supervisor"], "responsibilities": ["liaise with clients", "reporting", "liaise", "communicate with", "regulations", "related documents", "analysis", "review", "procedures", "design", "daily operations", "schedule", "insurance", "provide guidance"], "requirements": {"degrees": ["secondary education"], "majors": ["structural engineering"], "languages": [], "language_level": [], "hard_skills": ["basic", "sap2000", "microsoft office", "analysis", "mathcad", "codes", "bim", "autocad"], "soft_skills": ["good team player", "proactive", "stable", "resourceful"], "languages_combined": []}, "experience_required": {"duration": ["3-5 years"], "field": ["structural", "structural design", "design"]}}, {"job_id": "100003009048527", "location_code": "hk", "company": "Kum Shing (KF) Construction Co Ltd", "job_title": "Project Manager \u2013 Power Systems (Trenchless Projects)", "description": "\u8077\u8cac\n\u5354\u52a9\u5efa\u7bc9\u5730\u76e4\u65bd\u5de5\u7ba1\u7406\n\u719f\u6089\u5efa\u7bc9\u5730\u76e4\u904b\u4f5c\u53ca\u7d71\u7c4c\u5de5\u4f5c\n\u8981\u6c42\n\u6301\u6709\u5efa\u9020\u6587\u6191\u6216\u76f8\u7b49\u5b78\u6b77\n\u81f3\u5c119\u5e74\u6216\u4ee5\u4e0a\u5efa\u7bc9\u5730\u76e4\u7ba1\u7406\u7d93\u9a57\n\u9700\u6301\u670942\u621643\u5c0f\u6642\u5efa\u9020\u696d\u5b89\u5168\u7763\u5c0e\u54e1\u8ab2\u7a0b\n\u6301\u6709\u5de5\u7a0b\u76e3\u5de5\u9069\u4efb\u6280\u8853\u4eba\u54e1T1, T2, T3\u8b49\u66f8\u512a\u5148\u8003\u616e\n\u672c\u516c\u53f8\u8a2d\u6709\u5b8c\u5584\u798f\u5229\u53ca\u6649\u5347\u6a5f\u6703\uff0c\u6709\u610f\u8005\u8acb\u5c07\u5c65\u6b77\u9023\u540c\u8981\u6c42\u5f85\u9047\u3001\u73fe\u6642\u85aa\u91d1\u53ca\u5230\u8077\u65e5\u671f\u5230\u4ee5\u4e0b\u806f\u7d61\u65b9\u6cd5:\n\u5730\u5740: \u4e5d\u9f8d\u4e5d\u9f8d\u7063\u5b8f\u958b\u90538\u865f\u5176\u58eb\u5546\u696d\u4e2d\u5fc311\u6a13\u5354\u8208\u5efa\u7bc9\u6709\u9650\u516c\u53f8\u4eba\u529b\u8cc7\u6e90\u53ca\u57f9\u8a13\u90e8\u6536 \u6216 \"\u6309\u6b64\u7533\u8acb\" \u6216 \u50b3\u771f: 25304360\n\n\n\u516c\u53f8\u7db2\u5740: www.hiphing.com.hk\n\n\n\u6240\u6709\u500b\u4eba\u8cc7\u6599\u53ea\u4f5c\u62db\u8058\u7528\u9014\u3002\n\u5982\u7533\u8acb\u4eba\u5728\u516b\u661f\u671f\u5167\u672a\u7372\u901a\u77e5\u9762\u8a66\uff0c\u5373\u5176\u7533\u8acb\u4e0d\u7372\u63a5\u7d0d\u3002\n\u8acb\u958b\u555f\u700f\u89bd\u5668\u300c\u5f48\u51fa\u5f0f\u8996\u7a97 \u300d\u7684\u8a2d\u5b9a\uff0c\u6309\u6b64\u67e5\u770b\u6b65\u9a5f\u3002", "employment_types": ["Full Time", "Permanent"], "selling_points": ["Construction work for Trenchless Outline", "Excellent career path", "Performance bonus, education subsidy, medical plan"], "locations": ["To Kwa Wan"], "categories": ["Building & Construction", "Building / Construction / QS", "Civil / Structural", "Others"], "post_time": "2022-01-14T06:45:20Z", "salary": {"currency": null, "max": null, "min": null, "period": "monthly", "term": null}, "salary_visible": false, "title_keywords": ["project manager"], "responsibilities": [], "requirements": {"degrees": [], "majors": [], "languages": [], "language_level": [], "hard_skills": [], "soft_skills": [], "languages_combined": []}, "experience_required": {"duration": [], "field": []}}, {"job_id": "100003009054022", "location_code": "hk", "company": "Spencer Ogden (Hong Kong) Limited", "job_title": "Project Manager (Architect) - (New Built Residential Project - Property Developer)", "description": "4 years practical experience (for RSO) or 2 years for ASO;\nLittle site experience\u00a0can be applied as Safety Supervisor;\nDiploma in Occupational Safety and Health;\nSelf motivated and initiative;\nOpen minded;\nHave foundations experience is an advantage but not must;\nRSO will be stationed at Anderson Road Choi Hung; shuttle bus is provided.\n\n\u00a0We offer attractive remuneration package. Interested parties please send resume with present and expected salary to Human Resources Department.\u00a0\n\nAll information collected will be kept in strictly confidential and used for recruitment purpose only.", "employment_types": ["Full Time", "Permanent"], "selling_points": ["Registered Architect, Prestigious Projects", "Well known Developer, Attractive Package", "Excellent Career Prospect & Stability"], "locations": ["Not Specified"], "categories": ["Building & Construction", "Architectural Services", "Building / Construction / QS", "Civil / Structural"], "post_time": "2022-01-17T08:07:06Z", "salary": {"currency": null, "max": null, "min": null, "period": "monthly", "term": null}, "salary_visible": false, "title_keywords": ["developer", "project manager"], "responsibilities": [], "requirements": {"degrees": ["diploma"], "majors": [], "languages": [], "language_level": [], "hard_skills": [], "soft_skills": ["self motivated", "initiative", "open minded"], "languages_combined": []}, "experience_required": {"duration": ["4 years", "2 years"], "field": []}}, {"job_id": "100003009048350", "location_code": "hk", "company": "Minmetals Land Limited", "job_title": "Project Manager (Construction)", "description": "Responsibilities\n\nDelivering of trenchless project services to client\nLeading, controlling and management of project team and subcontractor workforce to meet relevant performance pledges, safety, quality and services targets\nCoordinating with designers for detailed study and\u00a0evaluating trenchless project schemes\nScheduling of detailed work program, road works permit application and design of TTA for execution including liaison with government authorities, developers, client and other stakeholders\nReviewing and certifying reports and records for invoicing and follow up on the payment from client and to subcontractors\n\nRequirements- Qualification:\n\nDegree in Civil or related engineering discipline;\nMinimum 8 years of relevant experience in which at least 3 years in supervisory position, preferably with main contractors or consultancy firms;\nCorporate Membership of the Hong Kong Institute of Engineers or Institute of Civil Engineering, or equivalent;\nWith driving license (Class 1 and 2) is preferred;\nHolder of valid Construction Workers Registration Card & Green Card\nSolid writing and presentation skills in both English and Chinese.\nCandidate with less qualification and experience will be considered as Assistant Project Manager.\n\nRequirements \u2013 Competences:\n\nStrong analytical and problem solving skills;\nProven leadership and interpersonal skills;\n\nWe look forward to receiving your application with detailed resume stating\u00a0working experience,\u00a0academic and language qualifications, existing and EXPECTED SALARY\u00a0as well as\u00a0availability.\u00a0All applications will be kept strictly confidential.\n\nWe offer promising professional career and exposure\u00a0to right candidate, together with attractive remuneration package including\u00a0discretionary bonus, continuing education allowance, medical and dental coverage.", "employment_types": ["Full Time", "Permanent"], "selling_points": ["Residential property development project", "Chartered engineer", "Minimum 10 years relevant working experience"], "locations": ["Tsim Sha Tsui"], "categories": ["Building & Construction", "Architectural Services", "Building / Construction / QS", "Civil / Structural"], "post_time": "2022-01-14T06:24:12Z", "salary": {"currency": null, "max": null, "min": null, "period": "monthly", "term": null}, "salary_visible": false, "title_keywords": ["project manager"], "responsibilities": ["management", "quality", "design", "invoicing", "scheduling", "payment", "reports"], "requirements": {"degrees": ["degree"], "majors": ["engineering"], "languages": ["english", "chinese"], "language_level": [], "hard_skills": ["construction workers registration card", "problem solving skills", "green card"], "soft_skills": ["analytical and problem solving skills", "presentation skills", "interpersonal skills", "leadership", "detailed"], "languages_combined": [{"language": "english", "language_level": []}, {"language": "chinese", "language_level": []}]}, "experience_required": {"duration": ["at least 3 years", "minimum 8 years"], "field": ["supervisory", "relevant experience"]}}, {"job_id": "100003009048637", "location_code": "hk", "company": "Kum Shing (KF) Construction Co Ltd", "job_title": "Senior Project Engineer/ Project Engineer / Assistant Engineer - Electrical (CCGT Plant)", "description": "Responsibilities:\n\n\nPerform overall quality control of the work (budget, schedule, plans, personnel's performance) and report regularly on project status\nMeeting with client and stakeholders on an ongoing basis regarding project objectives and progress;\nAssign project responsibilities to development team;\nEnsure compliance to applicable codes, practices, QA/QC policies, performance standards and specifications;\nDetermines project schedule and monitor project progression;\nResolves any issues that arise and coordinate team activities to maintain approved schedule;\nControls project pace and suggest schedule changes as needed;\nControls project costs by approving expenditures and administering contractor contracts;\nPrepares project status report and updates management team on project progression, completion and any necessary updates regularly;\nCooperate and communicate effectively with project manager and other project participants to provide assistance and technical support;\nMaintains safe and clean working environment;\nMaintains project data base.\n\nRequirements:\n\nHigher diploma or above in Mechanical or Control / Instrumentation Engineering;\nMinimum 5 years of related work experience in construction; preferably in Process / Industrial plant such as power plant, chemical/waste treatment plant or any infrastructure projects;\nCandidate with less experience will be considered as Assistant Engineer, candidate with more experience will be considered as Senior Project Engineer;\nProficient in MS Office;\nGood command of both written and spoken English and Chinese;", "employment_types": ["Full Time"], "selling_points": ["Iconic Prj \u2013Combined Cycle Gas Turbine Power Plant", "Good Career Prospects and Personal Development", "Happy Work Environment, Dynamic Team"], "locations": ["Tuen Mun Area"], "categories": ["Building & Construction", "Building / Construction / QS", "Civil / Structural", "Others"], "post_time": "2022-01-14T06:56:28Z", "salary": {"currency": null, "max": null, "min": null, "period": "monthly", "term": null}, "salary_visible": false, "title_keywords": ["senior project engineer", "assistant engineer", "project engineer"], "responsibilities": ["management team", "data", "technical support", "policies", "contracts", "budget", "monitor", "ensure compliance", "coordinate", "specifications", "maintain", "schedule", "quality control", "plans", "provide assistance", "costs", "report"], "requirements": {"degrees": ["higher diploma or above"], "majors": ["engineering"], "languages": ["english", "chinese"], "language_level": ["good command"], "hard_skills": ["ms office"], "soft_skills": [], "languages_combined": [{"language": "english", "language_level": ["good command"]}, {"language": "chinese", "language_level": ["good command"]}]}, "experience_required": {"duration": ["minimum 5 years"], "field": ["related", "construction"]}}, {"job_id": "100003009047206", "location_code": "hk", "company": "Yee Hop Engineering Company Limited", "job_title": "Project Coordinator", "description": "Currently looking for engineer's with 5-10 years of structural design experience, with an exciting opportunity to work for multiple iconic building and infrastructure projects.\u00a0\n\n5-10 years\u2019 experience in the design of high-rise buildings or infrastructure projects\u00a0\nCEng or MHKIE preferred\u00a0\nWell experienced in structural modelling\nConversant with the application of various structural software such as ETABS, SADS, SAFE, SAP2000, NIDA etc.\nMotivated and able to work hard\nIf you are interested to\u00a0find out more,\u00a0please send your updated resume to henri.chan\u00a0@ spencer-ogden.com", "employment_types": ["Full Time", "Permanent"], "selling_points": [], "locations": ["Not Specified"], "categories": ["Building & Construction", "Building / Construction / QS", "Civil / Structural", "Engineering", "Engineering Project Management"], "post_time": "2022-01-15T03:49:37Z", "salary": {"currency": null, "max": null, "min": null, "period": "monthly", "term": null}, "salary_visible": false, "title_keywords": ["project coordinator"], "responsibilities": ["infrastructure", "software", "design"], "requirements": {"degrees": [], "majors": [], "languages": [], "language_level": [], "hard_skills": ["etabs", "sap2000", "sads", "safe", "mhkie"], "soft_skills": ["motivated"], "languages_combined": []}, "experience_required": {"duration": ["5-10 years"], "field": ["infrastructure", "structural design", "design"]}}, {"job_id": "100003009049205", "location_code": "hk", "company": "China Harbour Engineering Company Ltd. (CHEC)", "job_title": "Foreman (Civil / Building)", "description": "Requirements:\nAssist tender submission, works programme, method statement, site layout plan, etc.;\nDegree holder in Civil / Structural Engineering;\nMinimum 2 years\u2019 relevant working experience in Site Formation / Foundation / ELS works;\nSite planning and project programming experience;\nGood computer knowledge and proficient in project-planning applications including Microsoft Project;\nGood communication and presentation skills;\nGood command of Chinese and English;\nLess experienced candidates will be considered as Assistant Planning Engineer.\nInterested parties please apply with detailed resume stating expected salary\u00a0and\u00a0date of availability to Mr. Henry Fu\u00a0via email by clicking \"Apply Now\"\u00a0or fax to 2635 0611.\u00a0\n[ Personal data collected will be used for recruitment-related purposes only. ]", "employment_types": ["Full Time"], "selling_points": ["General site operations", "Diploma or above", "Civil/ Structural/ Geotechnical Engineering"], "locations": ["Not Specified"], "categories": ["Building & Construction", "Building / Construction / QS", "Civil / Structural", "Others"], "post_time": "2022-01-14T08:15:59Z", "salary": {"currency": null, "max": null, "min": null, "period": "monthly", "term": null}, "salary_visible": false, "title_keywords": ["foreman"], "responsibilities": ["communication", "planning", "tender", "plan"], "requirements": {"degrees": ["degree holder"], "majors": ["structural engineering"], "languages": ["english", "chinese"], "language_level": ["good command"], "hard_skills": ["microsoft project", "programming"], "soft_skills": ["communication", "presentation skills"], "languages_combined": [{"language": "english", "language_level": ["good command"]}, {"language": "chinese", "language_level": ["good command"]}]}, "experience_required": {"duration": ["minimum 2 years"], "field": ["relevant working experience", "programming", "planning"]}}, {"job_id": "100003009047351", "location_code": "hk", "company": "Hip Hing Construction Co Ltd", "job_title": "Assistant Clerk of Works", "description": "Job Duties:\n\n\nEngineering design coordination\nContract administration\n\nRequirements:\n\nDegree holder in Civil Engineering or relevant disciplines\nSenior Engineer : over 4 years post-chartership experience with corporate membership from HKIE / ICE or equivalent\nEngineer : preferably with corporate membership from HKIE / ICE or equivalent\nAble to work under pressure efficiently and independently, and a team player\nGood interpersonal and communication skills\nProficient in written and spoken English & Chinese\n\nWe offer 5-day work and competitive salary commensurate with qualifications and experience.\n\nPersonal information contained in applications received will be used for employment-related purposes and, in respect of the successful appointee only, also for business-related purposes.\u00a0Please send full resume, availability, present and expected salaries and daytime contact telephone number quoting reference code to:\u00a0Human Resources Department, Binnies Hong Kong Limited, 43/F, AIA Kowloon Tower, 100 How Ming Street, Kowloon, Hong Kong\u00a0or by clicking 'Apply Now'.", "employment_types": ["Full Time"], "selling_points": ["Liaise with government departments", "Diploma in Building or Building Studies", "Experience in clerk of works"], "locations": ["Not Specified"], "categories": ["Building & Construction", "Building / Construction / QS", "Civil / Structural", "Others"], "post_time": "2022-01-14T02:53:10Z", "salary": {"currency": null, "max": null, "min": null, "period": null, "term": null}, "salary_visible": false, "title_keywords": ["clerk", "assistant"], "responsibilities": ["contract administration", "engineering design", "coordination"], "requirements": {"degrees": ["degree holder"], "majors": ["civil engineering"], "languages": ["english", "chinese"], "language_level": ["proficient"], "hard_skills": ["hkie"], "soft_skills": ["communication skills", "independently", "team player", "interpersonal", "work under pressure"], "languages_combined": [{"language": "english", "language_level": ["proficient"]}, {"language": "chinese", "language_level": ["proficient"]}]}, "experience_required": {"duration": ["4 years"], "field": ["senior engineer"]}}, {"job_id": "100003009043907", "location_code": "hk", "company": "David S. K. Au & Associates Ltd", "job_title": "Technical Officer (Structural)", "description": "\nWe\u2019re the leader in our industry because of our people and our suppliers. Given the importance of the procurement and supply chain capability to our success, we want to take it to the next level so we\u2019re investing in several way: we\u2019re growing the team, developing world class processes and finding new and better ways to use technology and data.\n\nWe\u2019ve created a new role at the core of our business to work with our consultants and suppliers on the most cutting-edge and innovative projects and programs of our time, addressing the big challenges of today and shaping the built environment for generations to come. We\u2019re looking for someone who has experience in procuring planning, design, engineering, program and construction management services. The role will suit someone who is a natural leader with an entrepreneurial spirit. The person will also enjoy working in teams comprising people from different countries and diverse backgrounds. The role reports to the Procurement Director - International and has line management responsibility for another member of staff.\n\nKey responsibilities of the role:\n\n\u00b7 Develop category management plans based on a detailed knowledge of demand, supply and market analysis across multiple countries\n\u00b7 Deliver sourcing strategies to meet business requirements including drafting tenders, evaluating offers, negotiation, contract drafting and implementation\n\u00b7 Manage contracts including the use of key performance indicators and escalation of performance issues where necessary\n\u00b7 Implement supplier relationship management with strategic suppliers to deliver greater value\n\u00b7 Review end to end processes to improve management of supplier base, channel management, contract management, enable and improve purchase order compliance and adoption, workflow and approvals, payment processes and data and analytics\n\u00b7 Utilise procurement technology and data to improve efficiency and achieve high levels of compliance to the procurement policy and processes, for example, through the implementation of the no PO no pay policy and the use of catalogues\n\u00b7 Where necessary, support key work winning activities, providing procurement expertise to the bid teams\n\u00b7 Develop change and project management plans to support new ways of working\n\u00b7 Support the development and capability of the Procurement and Supply Chain team by demonstrating high standard of delivery and sharing best practice\n\nSpecific technical knowledge/skills:\n\n\u00b7 CIPS qualified or equivalent professional procurement and supply chain qualification\n\u00b7 Degree or above along with 12-15+ years of relevant procurement / supply chain experience for MNC international firms. Prior experience working for a professional consultancy or in engineering/transport/utilities would be advantageous\n\u00b7 Interpersonal and influencing skills. Leadership techniques and staff development methods\n\u00b7 Category management tools and techniques\n\u00b7 Strategic sourcing tools and techniques\n\u00b7 Tender and contract drafting\n\u00b7 Tactical cost reduction expertise\n\u00b7 Supplier performance improvement tools & techniques\n\u00b7 Negotiation skills, strong contractual and commercial competence\n\u00b7 Analytical skills\n\u00b7 Change and project management tools and techniques\n\u00b7 Savings forecasting and recording experience\n\u00b7 Experience of procurement of planning, design, engineering, program and construction management services\n\u00b7 Bid winning support activity expertise would be an advantage\n\u00b7 Excellent verbal and written English and Mandarin\n\nIn addition to a competitive salary and benefits, the successful candidate will join a team that is sociable and supportive, a workplace that encourages growth, flexibility and creativity, as well as a company culture that champions inclusion, diversity and overall employee well-being through programs supported by company leadership. Our core values define who we are, how we act and what we aspire to, which comes down to not only delivering a better world but working to \u201cmake amazing happen\u201d in each neighbourhood, community and city we touch. We are the environmental, social, and corporate governance (ESG) leader in our industry and the Procurement and Supply Chain team are central to that achievement. As an Equal Opportunity Employer, we believe in each person\u2019s potential, and we\u2019ll help you reach yours.\n\n", "employment_types": ["Full Time", "Contract"], "selling_points": [], "locations": ["Not Specified"], "categories": ["Building & Construction", "Civil / Structural"], "post_time": "2022-01-13T02:25:03Z", "salary": {"currency": null, "max": null, "min": null, "period": "monthly", "term": null}, "salary_visible": false, "title_keywords": ["technical officer"], "responsibilities": ["data", "design", "purchase", "payment", "plans", "contracts", "compliance", "teams", "developing", "implementation", "develop", "reports", "tender", "forecasting", "management", "construction management", "cost", "review", "market analysis", "meet business requirements", "contract management", "project management", "planning"], "requirements": {"degrees": ["degree or above"], "majors": [], "languages": ["english", "mandarin"], "language_level": ["excellent"], "hard_skills": ["no", "analysis", "analytical skills", "project management", "make"], "soft_skills": ["supportive", "negotiation", "cutting-edge", "enjoy working", "sociable", "analytical skills", "diverse", "project management", "negotiation skills", "innovative", "leadership", "interpersonal", "detailed"], "languages_combined": [{"language": "english", "language_level": ["excellent"]}, {"language": "mandarin", "language_level": ["excellent"]}]}, "experience_required": {"duration": ["15+ years"], "field": ["management", "engineering", "procurement", "supply chain", "design", "construction", "planning"]}}, {"job_id": "100003009023304", "location_code": "hk", "company": "ScanTech (HK) Limited", "job_title": "Technical Assistant (Civil / Building Services)", "description": "AECOM has an immediate requirement for a Work Supervisor I to work on a large multi-disciplinary private project in Hong Kong. The project is located at Sai Sha, Shap Sze Heung, Sai Kung. The general nature of the proposed works include widening of Sai Sha Road between Sai O Village and Tai Tung Village from a 2-lane carriageway to a dual 2-lane carriageway; construction of a new carriageway from Tai Tung Village to Tseng Tau Village; construction of three footbridges near Nai Chung, Kwan Hang and Ma Kwu Lam Village; construction of footpaths and cycle tracks; and ancillary works including earthworks, drainage works, sewage and sewerage works, landscaping works, construction of box culverts, retaining walls, reconstruction of existing open space public carpark and public bus terminus and construction of noise barriers;\n\nThe works have commenced in 2018 with anticipated completion date in 4th quarter of Year 2024.\n\nThe successful applicant would be offered a 24-month contract initially and subject to renewal depending on the project\u2019s ongoing needs.\n\u00a0\nResponsibilities:\n\n\nAssist in supervising site works carried out by the Contractor;\nTake site measurements;\nEnsure the site works are constructed in accordance with Contract specifications, drawings and site instructions;\nCheck material quality and workmanship;\nKeep sites records, diary, weather chart, progress report, piling records, material delivery records etc.;\nCheck that all Contractor's site staff observe safety precautions for the Works to be carried out;\nKeep and update site records;\nDeal with any other duties as may be assigned from time to time by the superior.\n\u00a0\n\nRequirements:\n\nCertificate from a Hong Kong Polytechnic/ Polytechnic University, the Hong Kong Institute of Vocational Education or HKSAR technical institute or equivalent in an appropriate discipline or completed a technician apprenticeship; and\n\nAt least 3 years relevant post-qualification experience\n\n\u00a0Location:\u00a0\n\nSai Sha Road, Shap Sze Heung, Sai Kung, N.T.\n\nAECOM is a place where you can put your innovative thinking and business skills into high gear and work alongside other highly intelligent and motivated people. It's a place where you can apply your skills to some of the world's most challenging, interesting, and meaningful projects worldwide. It's a place that values the diversity of our areas of practice and our people. It's what makes AECOM a great place to work and grow.\n\nAECOM is an Equal Opportunity Employer.\n\nFor more information on AECOM, please visit our website at www.aecom.com.", "employment_types": ["Full Time", "Permanent"], "selling_points": ["2 Years Working Experience", "Civil / Technical Support", "Discretionary Bonus"], "locations": ["Lai Chi Kok"], "categories": ["Building & Construction", "Building / Construction / QS", "Civil / Structural", "Engineering", "Electrical / Electronics"], "post_time": "2022-01-13T18:54:41Z", "salary": {"currency": null, "max": null, "min": null, "period": "monthly", "term": null}, "salary_visible": false, "title_keywords": ["technical assistant"], "responsibilities": ["any other duties", "supervising", "quality", "drawings", "specifications", "report"], "requirements": {"degrees": ["certificate"], "majors": [], "languages": [], "language_level": [], "hard_skills": [], "soft_skills": ["motivated", "innovative"], "languages_combined": []}, "experience_required": {"duration": ["at least 3 years"], "field": ["post-qualification"]}}, {"job_id": "100003009050937", "location_code": "hk", "company": "Chevalier Group - Aluminium Windows & Curtain Walls", "job_title": "Site Supervisor / Site Foreman", "description": "AECOM Support/ Cross Services comprises a number of important functions which develop and implement solutions to support our businesses and to help them meet the needs of clients.\u00a0 Its role is to ensure that the Business Lines operate effectively, in alignment with AECOM\u2019s overall corporate goals.\u00a0 The activities cover Finance and Accounting, Human Resources, Information Technology, Legal, Compliance, Marketing and Communications, and Administration.\n\nResponsibilities:\n\n\u2022\u00a0 Support HR administrative services for large scale Resident Site Staff business units in Hong Kong\n\u2022\u00a0 Providing support services, including but not limited to recruitment, contracts preparation, handling employee issues, etc\n\u2022\u00a0 Ensure the delivery of HR services in line with overall HR policies and statutory compliance.\n\u2022\u00a0 Act as the point-of-contact for staff on matters relating to HR.\n\u2022\u00a0 Maintain and update HR reports, maintain personnel data integrity\n\u2022\u00a0 Any other duties as assigned\n\nRequirements:\n\n\u2022\u00a0 Higher Diploma holder in any disciplines\n\u2022\u00a0 Solid Administrative Operations or HR Support experience would be an advantage\n\u2022\u00a0 Good knowledge in HK Labour law and previous exposure in handling government documents will be assets.\n\u2022\u00a0 Well organized, detailed orientated and self motivated; pleasant, committed and positive working attitude\n\u2022\u00a0 \u00a0Strong sense of responsibility and willing to learn\n\u2022\u00a0 \u00a0Proficiency in MS Office (Word, Excel and PowerPoint)\n\u2022\u00a0 \u00a0Good command of spoken and written English", "employment_types": ["Full Time", "Permanent"], "selling_points": ["Form 5", "At least 1 year's working experience", "Holder of TCP T1"], "locations": ["Not Specified"], "categories": ["Building & Construction", "Building / Construction / QS", "Civil / Structural"], "post_time": "2022-01-14T11:51:57Z", "salary": {"currency": null, "max": null, "min": null, "period": null, "term": null}, "salary_visible": false, "title_keywords": ["site foreman", "site supervisor"], "responsibilities": ["any other duties", "data", "statutory compliance", "contracts", "hr", "policies", "hr reports", "maintain", "recruitment", "contact", "providing support"], "requirements": {"degrees": ["higher diploma holder"], "majors": ["any disciplines"], "languages": ["english"], "language_level": ["good command"], "hard_skills": ["excel", "word", "powerpoint", "ms office"], "soft_skills": ["sense of responsibility", "well organized", "willing to learn", "pleasant", "self motivated", "committed", "positive working attitude", "detailed"], "languages_combined": [{"language": "english", "language_level": ["good command"]}]}, "experience_required": {"duration": [], "field": ["hr", "administrative"]}}, {"job_id": "100003009047325", "location_code": "hk", "company": "Hip Hing Construction Co Ltd", "job_title": "\u52a9\u7ba1\u5de5", "description": "Job Duties\n\nAECOM\u00a0is seeking a\u00a0Resident Engineer to be based in Hong Kong.\nAct as RSE T5 & RSE/RGE T3 and both the RSE/RGE\u2019s Representative full time on site;\nAccountable and report to the AP/RSE/RGE and take-in-charge of the RE Site Office for implementing the RSE/RGE\u2019s supervision;\nTake overall responsibility to check the site safety measures in compliance with requirements of supervision plans;\nCarry out specific tasks as per requirements and checklist devised from RSE/RGE and representative of Client;\nSupervise the junior TCPs comprising Assistant Resident Engineers to check the essential items for specified tasks, including but not limited to demolition works;\nCoordinate and compile reports on supervision activities including reports on non-conformities, to deal with non-conformities, and to report to RSE/RGE;\nCheck the works in compliance with the approved plans, the approved temporary works, method statements, precautionary and protective measures;\nReview Contractor\u2019s submissions;\nMonitor the work of the Registered Contractor\u2019s TCPs;\nAttend the site meetings and project meetings, and assist and coordinate with the design office for all site works/matters.\nCheck the contractor\u2019s structural works are in compliance with the statutory and contractual requirements.\nEnforce ethics and compliance policy including Third Party payment, Sub-consultancy engagement process and Gift and Entertainment policy.\nAt AECOM, we\u2019re delivering a better world.\n\nWe believe infrastructure creates opportunity for everyone. Whether it\u2019s improving your commute, keeping the lights on, providing access to clean water or transforming skylines, our work helps people and communities thrive.\n\nOur clients trust us to bring together the best people, ideas, technical expertise and digital solutions to our work in transportation, buildings, water, the environment and new energy. We\u2019re one global team \u2013 47,000 strong \u2013 driven by a common purpose to deliver a better world.\n\n\nRequirements\n\nBachelor or Master degree in Civil/Structural Engineering;\nMHKIE or equivalent and RPE (Structural/Civil)\nMinimum 5 years of relevant experience with Demolition Works and ground investigation field works;\nRelevant experience with Foundation Works, and Building Works with significant geotechnical content would be an advantage;\nAbility to coordinate with other parties in the construction site environment;\nAbility to lead the site office and supervise the site team;\nExperience and awareness in contractual issues in construction, and\nFluency in written and spoken English and Cantonese.\nProject Brief\n\nThe project site is located in Shau Kei Wan\nThe project includes demolition of residential blocks and ground investigation field works\nTentative Contract period of employment:\u00a0 Around 17 months\n\n", "employment_types": ["Full Time", "Permanent"], "selling_points": ["2 \u5e74\u5efa\u7bc9\u5730\u76e4\u7ba1\u7406\u7d93\u9a57", "\u5efa\u9020\u696d\u5b89\u5168\u7763\u5c0e\u54e1\u8ab2\u7a0b", "T1, T2, T3\u8b49\u66f8"], "locations": ["Not Specified"], "categories": ["Building & Construction", "Architectural Services", "Building / Construction / QS", "Civil / Structural"], "post_time": "2022-01-14T02:49:59Z", "salary": {"currency": null, "max": null, "min": null, "period": null, "term": null}, "salary_visible": false, "title_keywords": [], "responsibilities": ["ap", "ideas", "site meetings", "compile reports", "compliance", "review", "monitor", "coordinate with", "design", "coordinate", "infrastructure", "payment", "reports", "plans", "third party", "report"], "requirements": {"degrees": ["bachelor", "master degree"], "majors": ["structural engineering"], "languages": ["cantonese", "english"], "language_level": ["fluency"], "hard_skills": ["wan", "mhkie"], "soft_skills": [], "languages_combined": [{"language": "cantonese", "language_level": ["fluency"]}, {"language": "english", "language_level": ["fluency"]}]}, "experience_required": {"duration": ["minimum 5 years"], "field": ["relevant experience", "construction"]}}, {"job_id": "100003009044721", "location_code": "hk", "company": "China Railway Engineering (Hong Kong) Limited", "job_title": "Superintendent", "description": "Job Summary:\n\nAccountable to the RSE/RGE for implementing the RSE/RGE\u2019s supervision\nAct as the RSE/RGE T5 and RSE/RGE\u2019s Representative on site;\nTake overall responsibility to check if the safety measures on site meet with requirements of supervision plans;\nAccountable to the RSE/RGE for the satisfactory execution of the specific tasks, and for responsibilities of the junior TCPs including checking of the essential items for specified tasks;\nCarry out specific tasks as per requirements and checklist devised from RSE/RGE;\nCoordinate and compile reports on supervision activities including reports on non-conformities, to deal with non-conformities, and to report to RSE/RGE;\nChecking that the works comply with the approved plans, method statements, precautionary and protective measures;\nReview Contractor\u2019s submissions;\nMonitor the work of the Registered Contractor\u2019s TCPs;\nActing as the office-in-charge of the RE office and supervise the Assistant Resident Engineers;\nRepresent AECOM to attend the site meetings and project meetings, and\nAssist and coordinate with the design office for all site works/matters\n\n\u00a0Minimum Requirements:\n\nCorporate member of HKIE (Civil or Structural or Geotechnical Engineering Discipline)\nCandidate with lesser experience or qualification will be considered for Assistant Resident Engineer post\nRegistered Professional Engineer (Civil or Structural or Geotechnical Discipline in Hong Kong under the Engineers Registration Ordinance)\n5 to 10 years of experience in design and/or site supervision of building foundation, basement excavation and construction, and structural works;\nAbility to coordinate with other parties in the construction site environment;\nAbility to lead the site office and supervise the site team;\nExperience and awareness in contractual issues in construction, and\nFluency in written and spoken English and Cantonese are required\n\nTo apply for the position, please submit full CV, academic and professional certifications, reference letters, and current and expected salary.", "employment_types": ["Full Time", "Permanent"], "selling_points": [], "locations": ["Tung Chung"], "categories": ["Building & Construction", "Civil / Structural"], "post_time": "2022-01-13T05:42:27Z", "salary": {"currency": null, "max": null, "min": null, "period": "monthly", "term": null}, "salary_visible": false, "title_keywords": [], "responsibilities": ["site supervision", "site meetings", "compile reports", "review", "monitor", "checking", "coordinate with", "design", "coordinate", "letters", "reports", "plans", "report"], "requirements": {"degrees": [], "majors": [], "languages": ["cantonese", "english"], "language_level": ["fluency"], "hard_skills": ["hkie"], "soft_skills": ["accountable"], "languages_combined": [{"language": "cantonese", "language_level": ["fluency"]}, {"language": "english", "language_level": ["fluency"]}]}, "experience_required": {"duration": ["5 to 10 years"], "field": ["structural", "construction", "design"]}}, {"job_id": "100003009036648", "location_code": "hk", "company": "Metrochain Limited", "job_title": "Assistant Project Manager / Project Manager", "description": "As part of the growth of the Talent Acquisition team, the Talent Acquisition\u00a0Senior Specialist / Assistant Manager\u00a0will support the recruitment campaigns primarily in Hong Kong. This will involve planning, managing, execution and delivery of these recruitment activities whilst working together with other TA Team Leads in those regions in APAC. Other key mandates include promoting the AECOM brand internally and externally in order to attract young and emerging talent and helping to improve the candidate experience.\n\n\n\nResponsibilities\n\nLiaise with hiring managers of the various business lines across AECOM to understand position requirements and provide advice on the Graduate and Intern recruitment process\nRecruitment Operations\nAssist in application form and job advertising design\n\u00a0Short-list candidates by paper and phone screening\n\u00a0Coordinate assessment centers and business line interviews\nCommunicate offer and onboarding process to selected candidates as well as dispositioning unsuccessful applicants once the recruitment campaign is\u00a0completed\u00a0\nHandle full cycle recruitment process, including ad posting, screening CV, shortlisting candidates and salary negotiation\nUtilize a number of sourcing methods including cold-approach (call or email), Linkedin, market-mapping, internet search, networking and related media\nRequirements\n6-8+ years of recruitment experience of which Recruitment Agency exposure is welcome in a MNC and dynamic recruitment environment. Candidates with less experience (3-5 years) may be considered as Specialist\nExperience and knowledge of the Engineering or Technical sectors would be an advantage\nHeadhunt, market-map whilst targeting high performing candidates in rival firms\nProactive and creative sourcing and research techniques on hard-to-fill assignments\nExceptional organizational skills and attention to detail\nAbility to record and present data accurately and with impact; strong Excel and Powerpoint skills\nExcellent verbal and written communication skills in English. Cantonese would be advantageous but not necessary\nExperience working with geographically-dispersed virtual teams, as well as having the ability to work both independently and in a team environment", "employment_types": ["Full Time"], "selling_points": ["Building Services", "Management and Coordination of projects", "Design, project planning & management"], "locations": ["Kowloon Bay"], "categories": ["Building & Construction", "Building / Construction / QS", "Civil / Structural", "Engineering", "Engineering Project Management"], "post_time": "2022-01-10T11:41:49Z", "salary": {"currency": null, "max": null, "min": null, "period": "monthly", "term": null}, "salary_visible": false, "title_keywords": ["assistant project manager", "project manager"], "responsibilities": ["advertising", "operations", "design", "coordinate", "provide advice", "recruitment", "liaise with", "recruitment process"], "requirements": {"degrees": [], "majors": [], "languages": ["cantonese", "english"], "language_level": ["excellent"], "hard_skills": ["excel", "dynamic", "powerpoint"], "soft_skills": ["organizational skills", "communication skills", "proactive", "independently", "dynamic", "attention to detail", "creative"], "languages_combined": [{"language": "cantonese", "language_level": []}, {"language": "english", "language_level": ["excellent"]}]}, "experience_required": {"duration": ["8+ years", "3-5 years"], "field": ["agency", "recruitment", "engineering", "team"]}}, {"job_id": "100003009048619", "location_code": "hk", "company": "Kum Shing (KF) Construction Co Ltd", "job_title": "Project Planner", "description": "Job Summary:\n\nWe are looking for high caliber professional to join our Hong Kong Business in Building Engineering. To be successful in the role, you will be required to:\n\n\nDemonstrate design and project management for geotechnical works on building projects.\nLead a team to complete designs in timely manner or/and carry out RGE/RGE-T5 TCP supervision.\nDealing with Geotechnical Engineering Office, Buildings Department, Housing Authority and Architectural\u00a0Services Department.\nUndertake and project-manage Geotechnical/Structural/Civil\u00a0engineering schemes from feasibility through to detailed design.\nBe a client liaison involved in the production of tenders, including quality documentation and costings.\nHave knowledge in the use of geotechnical/structural software.\nBe creative and understand the architectural and client drivers.\nPart Time applicants will also be considered.\n\nMinimum Requirements:\n\nRGE and/or RPE(G). Candidate with lesser experience or qualification will be considered for Geotechnical Professional Engineer post.\nProven design and project management experience delivering to quality, time and budget\nPrevious exposure with clients of both private and public sectors, together with major contractors\nGood understanding of local authorities\u2019 procedures and requirements\nGood personal effectiveness and time management\nOverseas project experience would also be an advantage\nExperience in BIM (Revit) is an advantage\nFluency in written and spoken English, Cantonese and Mandarin required.", "employment_types": ["Full Time"], "selling_points": ["Develop & maintain schedules of construction prj.", "Develop and maintain summary level schedule report", "Support the project management team"], "locations": ["Tuen Mun Area"], "categories": ["Building & Construction", "Building / Construction / QS", "Civil / Structural", "Others"], "post_time": "2022-01-14T06:54:39Z", "salary": {"currency": null, "max": null, "min": null, "period": "monthly", "term": null}, "salary_visible": false, "title_keywords": [], "responsibilities": ["management", "software", "budget", "quality", "procedures", "design", "project management", "lead a team", "documentation", "geotechnical works"], "requirements": {"degrees": [], "majors": [], "languages": ["cantonese", "english", "mandarin"], "language_level": ["fluency"], "hard_skills": ["tcp", "project management", "bim", "documentation", "revit"], "soft_skills": ["creative", "timely", "project management", "time management", "detailed"], "languages_combined": [{"language": "cantonese", "language_level": ["fluency"]}, {"language": "english", "language_level": ["fluency"]}, {"language": "mandarin", "language_level": ["fluency"]}]}, "experience_required": {"duration": [], "field": ["project management", "design"]}}, {"job_id": "100003009047340", "location_code": "hk", "company": "Vibro (H.K.) Limited", "job_title": "Assistant Geologist (Ref: V-AG/JDB)", "description": "Job Summary:\n\nPerform clerical and administrative support to project teams\nCoordinate with both internal and external parties to ensure efficient projects\u2019 operation\nMaintain and update the project files, documents, database / library with high accuracy\nAssist the project teams to prepare proposal / tender submission\nSupport projects\u2019 financial updates\nEnforce ethics and compliance policy including Third Party payment, Sub-consultancy engagement process and Gift and Entertainment policy\n\nMinimum Requirements:\n\nCompletion of Secondary / High School Education or above\nKnowledgeable in business tools including MS Office Suite (e.g. Excel, Word, PowerPoint, Outlook)\nGood communication, organizing and problem-solving skills\nSelf-motivated and able to work under pressure\nA good team player and can work well in a team\nGood command of both written and spoken English while Chinese language skills are preferred", "employment_types": ["Full Time", "Permanent"], "selling_points": ["Degree in Earth Sciences/ Geology or equivalent", "Fresh graduate will also be considered", "Good command of both English and Chinese"], "locations": ["Not Specified"], "categories": ["Building & Construction", "Civil / Structural"], "post_time": "2022-01-14T02:51:49Z", "salary": {"currency": null, "max": null, "min": null, "period": null, "term": null}, "salary_visible": false, "title_keywords": ["assistant geologist"], "responsibilities": ["support projects", "administrative support", "internal and external parties", "coordinate with", "teams", "compliance", "communication", "payment", "maintain", "database", "tender", "third party", "work under pressure"], "requirements": {"degrees": ["high school"], "majors": [], "languages": ["english", "chinese"], "language_level": ["good command"], "hard_skills": ["excel", "word", "powerpoint", "outlook", "problem-solving skills", "ms office"], "soft_skills": ["efficient", "self-motivated", "good team player", "communication", "problem-solving skills", "work under pressure"], "languages_combined": [{"language": "english", "language_level": ["good command"]}, {"language": "chinese", "language_level": ["good command"]}]}, "experience_required": {"duration": [], "field": []}}, {"job_id": "100003009045738", "location_code": "hk", "company": "Macdonald & Company Limited", "job_title": "(Senior) Structural Engineer", "description": "Job Duties:\nClosely work with the engineering teams for preparation of photomontages, artworks, publicity materials for the projects\nProvide creative design idea and support to the engineering teams\nPhoto shooting and re-touching for project publicity materials\nDesign and prepare layout and artwork in various channels, including printing graphic, digital platform, event and video production\nMinimum Requirements:\n\nHave Diploma or above in Multimedia Design or related disciplines\nAt least 3-year experience in graphic design\nProficient in QuarkXpress, Adobe InDesign, Illustrator, Photoshop, Dreamweaver and MS Office", "employment_types": ["Full Time", "Permanent"], "selling_points": ["Structural design in Building", "Good career path", "Leading Contractor"], "locations": ["Not Specified"], "categories": ["Building & Construction", "Building / Construction / QS", "Civil / Structural"], "post_time": "2022-01-13T08:29:41Z", "salary": {"currency": null, "max": null, "min": null, "period": "monthly", "term": null}, "salary_visible": false, "title_keywords": ["engineer"], "responsibilities": ["video production", "teams", "digital platform", "design", "re-touching"], "requirements": {"degrees": ["diploma or above"], "majors": ["multimedia design", "related disciplines"], "languages": [], "language_level": [], "hard_skills": ["adobe indesign", "illustrator", "multimedia", "dreamweaver", "ms office", "photoshop"], "soft_skills": [], "languages_combined": []}, "experience_required": {"duration": ["at least 3-year"], "field": ["graphic design"]}}, {"job_id": "100003009049067", "location_code": "hk", "company": "Urban Renewal Authority", "job_title": "Senior Officer, Building Rehabilitation (3-year contract) (Ref. SO(BR))", "description": "We' re the leader in our industry because of our people and our suppliers. Given the importance of the procurement and supply chain capability to our success, we want to take it to the next level so we\u2019re investing in several way: we\u2019re growing the team, developing world class processes and finding new and better ways to use technology and data.\n\nWe\u2019ve created several new roles at the core of our business to work with our consultants and suppliers on the most cutting-edge and innovative projects and programs of our time, addressing the big challenges of today and shaping the built environment for generations to come. \u00a0\n\nWe\u2019re looking for someone who has previous procurement, commercial and/or project management and wants to develop their category and sourcing knowledge of planning, design, engineering, program and construction management services. The role will suit someone who enjoys a challenge and wants to build a career in procurement and supply chain. The person will also enjoy working in teams comprising people from different countries and diverse backgrounds. The role reports to the Senior Procurement and Supply Chain Manager for Engineering in Asia and is based in Hong Kong.\n\nIn addition to a competitive salary and benefits, the successful candidate will join a team that is sociable and supportive, a workplace that encourages growth, flexibility and creativity, as well as a company culture that champions inclusion, diversity and overall employee well-being through programs supported by company leadership. Our core values define who we are, how we act and what we aspire to, which comes down to not only delivering a better world but working to \u201cmake amazing happen\u201d in each neighbourhood, community and city we touch. We are the environmental, social, and corporate governance (ESG) leader in our industry and the Procurement and Supply Chain team are central to that achievement. As an Equal Opportunity Employer, we believe in each person\u2019s potential, and we\u2019ll help you reach yours.\n\n\nKey responsibilities of the role:\n\n\nSupport the Senior Procurement and Supply Chain Manager to understand the business requirements across the region\nInput into the develop category management plans including details on demand, supply and market analysis\nManage sourcing strategies to meet business requirements including drafting tenders, evaluating offers, contract drafting and implementation\nManage contracts including the use of key performance indicators and escalation of performance issues where necessary\nSupport supplier relationship management to deliver greater value\nUtilise procurement technologies such as Coupa to improve efficiency and achieve high levels of compliance to the procurement policy and processes, for example, the implementation of use of catalogues to achieve the no PO no pay policy including the use of catalogues supported by Coupa\nUtilise business analytics tools like Microsoft Power BI to review data\nSupport the development and capability of the Asia Procurement and Supply Chain team by demonstrating high standard of delivery and improving procurement resources\nDevelop and maintain strong relationships at all levels within the organisation to ensure that procurement is seen as a valued contributor to the success of the business\nReview end to end process to improve management of supplier base, channel management, contract management, enable and improve PO compliance and adoption, workflow and approvals, payment processes and data and analytics\nWork with communication and change management teams to build effective plans when required\nSpecific technical knowledge/skills:\n\nStrong interpersonal and influencing skills\nStrong analytical skills\nNegotiation skills including contractual and commercial competence\nProject management skills\nCategory management tools and techniques would be an advantage\nStrategic sourcing tools and techniques such as tender and contract drafting would be an advantage\nTactical cost reduction expertise would be an advantage\nSupplier performance improvement tools & techniques would be an advantage\nExperience of managing the tender process including managing suppliers would be an advantage\nExcellent verbal and written English and Mandarin\n\nPreferred Qualifications:\n\nCIPS qualified or working towards qualification or equivalent would be an advantage\nDegree would be an advantage\n\n\u00a0At AECOM, we\u2019re delivering a better world.\n\nWe believe infrastructure creates opportunity for everyone. Whether it\u2019s improving your commute, keeping the lights on, providing access to clean water or transforming skylines, our work helps people and communities thrive.\n\nOur clients trust us to bring together the best people, ideas, technical expertise and digital solutions to our work in transportation, buildings, water, the environment and new energy. We\u2019re one global team \u2013 47,000 strong \u2013 driven by a common purpose to deliver a better world.", "employment_types": ["Full Time", "Contract"], "selling_points": ["To support on building rehabilitation", "To facilitate implementation of Rehab Schemes", "Minimum 3 years\u2019 experience"], "locations": ["Not Specified"], "categories": ["Building & Construction", "Building / Construction / QS", "Civil / Structural", "Others"], "post_time": "2022-01-14T08:02:39Z", "salary": {"currency": null, "max": null, "min": null, "period": "monthly", "term": null}, "salary_visible": false, "title_keywords": ["senior officer"], "responsibilities": ["ideas", "data", "design", "communication", "payment", "maintain", "plans", "contracts", "compliance", "teams", "developing", "implementation", "develop", "infrastructure", "reports", "tender", "management", "construction management", "change management", "cost", "review", "market analysis", "meet business requirements", "analytics tools", "power bi", "contract management", "project management", "planning"], "requirements": {"degrees": ["degree"], "majors": [], "languages": ["english", "mandarin"], "language_level": ["excellent"], "hard_skills": ["clean", "analytics tools", "no", "bi", "analysis", "analytical skills", "project management", "make"], "soft_skills": ["supportive", "cutting-edge", "enjoy working", "project management skills", "driven", "sociable", "analytical skills", "communication", "project management", "diverse", "negotiation skills", "organisation", "innovative", "leadership", "interpersonal"], "languages_combined": [{"language": "english", "language_level": ["excellent"]}, {"language": "mandarin", "language_level": ["excellent"]}]}, "experience_required": {"duration": [], "field": []}}, {"job_id": "100003009046231", "location_code": "hk", "company": "Arup", "job_title": "Engineer (Designer) / Project Engineer (Designer) / Senior Engineer (Designer) (Fa\u00e7ade Engineering)", "description": "Responsibilities:\n\nSuccessor role to lead a sizable payroll team, oversee the payroll and pension for Hong Kong, China, Taiwan, and other Asia regions as required\nSupervise and liaise with the payroll teams in AECOM Global Business Services Centers in Manila and Shanghai\nSupport in global payroll system transformation, implementation, and enhancement\nTransform and modernize the existing payroll function\nSupport the Employer\u2019s Returns\u00a0and correspond with the IRD enquiry letters\nEnsure full compliance of local employment and taxation law requirement across Asia\nInvolve in people costing analysis and accounting ledger posting\nStrictly follow the payroll payment schedule deadline for weekly and month pay cycle\nEnhance the payroll team meet all respective deadlines as defined in AECOM\nPerform and completion of all kinds of reconciliation and reports on time\nPartner with other teams to ensure payroll is processed accurately and effectively\nProcess review and ensure the payroll processes are satisfied with SOX requirement\nAny ad-hoc assignment when and as required\n\nRequirements:\n\nStrong payroll experience in Asia includes but not limited to Hong Kong, China, Taiwan and other Asia regions\nBachelor\u2019s degree or above, Accounting or Human Resources background\nMinimum of 5-year solid payroll supervisory experience from sizeable MNC\nStrong leadership and able to work under pressure\nKnowledge and experience of ORACLE, Workday, Yonyou, SQL and payroll system implementation are preferred\nBe precise, willing to deal with detail, sensitive with figures\nGood command of both written and spoken English and Mandarin\nSelf-initiative, proactive and\u00a0independent.\nPleasant personality with strong interpersonal, presentation and communication skills\nKnowledge of Government Resident Site Staff (\u201cRSS\u201d) Pay Scale Backpay Arrangement (is a plus)\n\nWork Location: Shatin\n\n", "employment_types": ["Full Time", "Permanent"], "selling_points": [], "locations": ["Kowloon City Area"], "categories": ["Building & Construction", "Architectural Services", "Civil / Structural", "Engineering", "Mechanical"], "post_time": "2022-01-13T10:04:25Z", "salary": {"currency": null, "max": null, "min": null, "period": null, "term": null}, "salary_visible": false, "title_keywords": ["senior engineer", "engineer", "designer", "project engineer"], "responsibilities": ["ad-hoc", "taxation", "compliance", "teams", "implementation", "letters", "review", "payment", "costing analysis", "reports", "schedule", "liaise with", "payroll"], "requirements": {"degrees": ["degree or above", "bachelor"], "majors": ["accounting"], "languages": ["english", "mandarin"], "language_level": ["good command"], "hard_skills": ["sql", "plus", "system implementation", "oracle"], "soft_skills": ["communication skills", "independent", "presentation", "pleasant", "self-initiative", "sensitive", "precise", "proactive", "leadership", "interpersonal", "work under pressure"], "languages_combined": [{"language": "english", "language_level": ["good command"]}, {"language": "mandarin", "language_level": ["good command"]}]}, "experience_required": {"duration": ["minimum of 5-year"], "field": ["sql", "payroll", "supervisory experience"]}}, {"job_id": "100003009050841", "location_code": "hk", "company": "Chevalier Group - Building Construction", "job_title": "BIM Technician", "description": "AECOM\u00a0is recruiting self-motivated, proactive and high caliber individual to join our sustainability team to provide professional services to both our local and international clients:\n\n\nResponsibilities:\nUndertake green building certification projects.\nCarry out building sustainability and microclimate studies (MCS) including computational fluid dynamics (CFD) simulations, air ventilation assessments (AVA), energy simulation, natural and artificial lighting simulations, etc.\nMinimum Requirements:\n\nDegree holder or above in Environmental / Mechanical / Building Services Engineering, Environmental Science, or related subjects.\nGood knowledge on Green Building certification schemes such as BEAM Plus, LEED, WELL, CGBL; CFD modelling; carbon study is preferred;\nBEAM/LEED accreditation (BEAM Affiliate, LEED AP, etc) is preferred;\nGood team player with strong influencing, planning and organizing skills.\nBe able to work independently with strong interpersonal and communication skills.\nExcellent in both written and spoken English and Mandarin. Good command of Putonghua would be an advantage.\n\n", "employment_types": ["Full Time", "Permanent"], "selling_points": ["BIM Technician", "Coordinate with the project team for drawings", "Prepare BIM drawings, clash analysis and animation"], "locations": ["Not Specified"], "categories": ["Building & Construction", "Building / Construction / QS", "Civil / Structural", "Engineering", "Draftsman"], "post_time": "2022-01-14T11:32:21Z", "salary": {"currency": null, "max": null, "min": null, "period": null, "term": null}, "salary_visible": false, "title_keywords": ["technician"], "responsibilities": [], "requirements": {"degrees": ["degree holder"], "majors": ["environmental science", "building services", "engineering"], "languages": ["putonghua", "english", "mandarin"], "language_level": ["advantage", "excellent", "good command"], "hard_skills": ["ap", "plus"], "soft_skills": ["communication skills", "good team player", "interpersonal", "work independently"], "languages_combined": [{"language": "putonghua", "language_level": ["advantage", "good command"]}, {"language": "english", "language_level": ["excellent"]}, {"language": "mandarin", "language_level": ["excellent"]}]}, "experience_required": {"duration": [], "field": []}}, {"job_id": "100003009054076", "location_code": "hk", "company": "Jetline Construction Co., Limited", "job_title": "Building Services Coordinator / Assistant Building Services Coordinator", "description": "Main Duties:\n\n\nResponsible for supervising contractor\u2019s works\nCarry out maintenance work for civil engineering facilities and building structures\n\nRequirements:\n\nCIC or VTC Certificate in Construction or above\n2 years or above relevant working experience\nHolder of valid driving license Class 1 & 2 is preferred\nOutdoor work is required\nGood learning and cooperative working attitude\nCandidates with less experience but with Higher Diploma in Civil Engineering will be considered as Technician Trainee\n\nPlease apply through our Career Centre at\u00a0https://www.hit.com.hk/cn/Career-With-Us/Career-Oppotunities.html. You may also apply the job\u00a0by sending your\u00a0full resume with current and expected salary to Human Resources Manager, Terminal 4, Container Port Road South, Kwai Chung.\n\nFor further information, please visit our website at http://www.hit.com.hk/.\n\nPlease read the Personal Information Collection Statement before submitting your application.\n\nWe are an equal opportunity employer and welcome applications from all qualified candidates. The information provided will be treated in strict confidence and used only for consideration of application for relevant/similar positions within the Hutchison Group of Companies. Applicants not invited for interview in 6 weeks after job posting may consider their application unsuccessful and your personal data will be destroyed after a period of\u00a06 months.", "employment_types": ["Full Time", "Permanent"], "selling_points": ["Bonus twice a year", "11 days Annual Leave, 5.5 days, bank holiday", "Work life balance"], "locations": ["Not Specified"], "categories": ["Building & Construction", "Building / Construction / QS", "Civil / Structural", "Engineering", "Engineering Project Management"], "post_time": "2022-01-17T08:19:28Z", "salary": {"currency": null, "max": null, "min": null, "period": "monthly", "term": null}, "salary_visible": false, "title_keywords": ["coordinator", "assistant"], "responsibilities": ["supervising", "maintenance"], "requirements": {"degrees": ["certificate", "diploma"], "majors": ["civil engineering"], "languages": [], "language_level": [], "hard_skills": ["container", "html"], "soft_skills": ["cooperative", "learning", "confidence"], "languages_combined": []}, "experience_required": {"duration": ["2 years"], "field": ["engineering", "relevant working experience"]}}, {"job_id": "100003009046158", "location_code": "hk", "company": "Arup", "job_title": "BIM Coordinator (Civil Engineering)", "description": "Responsibilities:\n\nCoordinate with E&M and work activities on sites as required.\nFollowing up project details and monitor project progress.\n\nRequirements:\n\nHigh Diploma or above in Building Services / Engineering / Electrical & Mechanical Engineering or related disciplines.\n3-10 years relevant experience, 0-3 years' will be considered as Assistant Building Services Coordinator.\n\nComputer knowledge for ACAD, MS Office, MS Project.\nWilling to learn and work hard.\nImmediate availability is highly preferable\u00a0.\n\nInterest parties, please send your detailed CV with expected salary by clicking \u201cApply Now\u201d.\u00a0\n\nAll Personal data collected will be used for recruitment purpose only.", "employment_types": ["Full Time", "Permanent"], "selling_points": [], "locations": ["Kowloon City Area"], "categories": ["Building & Construction", "Civil / Structural", "Engineering", "Draftsman", "Others"], "post_time": "2022-01-13T09:46:09Z", "salary": {"currency": null, "max": null, "min": null, "period": null, "term": null}, "salary_visible": false, "title_keywords": ["bim coordinator"], "responsibilities": ["monitor project progress", "coordinate with"], "requirements": {"degrees": ["high diploma or above"], "majors": ["related disciplines", "building services", "engineering", "mechanical engineering"], "languages": [], "language_level": [], "hard_skills": ["ms office"], "soft_skills": ["willing to learn", "detailed"], "languages_combined": []}, "experience_required": {"duration": ["0-3 years", "3-10 years"], "field": ["building services", "relevant experience"]}}, {"job_id": "100003009042809", "location_code": "hk", "company": "Able Engineering Holdings Limited", "job_title": "Graduate Engineer / Assistant Engineer", "description": "Diploma / Certificate in Civil Engineering from Technical Institute(s) or equivalent\nBIM professional certificates / training courses from Technical Institute(s) / software companies are required\nAt least 2 years of relevant experience in using computer tools for BIM modelling and / or drafting, e.g. AutoCAD, Autodesk Civil 3D / Revit / Dynamo / Navisoworks / Bentley MicroStation / Rhino /\u00a0 Grasshopper or equivalent\nGood command in both written and spoken English and Chinese\nCandidates with less experience will be considered for the position of BIM Modeller.\nWe offer a competitive remuneration package commensurate with qualifications and experience to the right candidate including Global Profit Share scheme, additional fringe benefits of maternity/paternity leave and long-term career development opportunities.\u00a0\n\nFor interested applicants, please click \u201cApply Now\" to submit your online application.\n\nTo explore more job opportunities in Arup, please visit our website at http://www.arup.com/Careers/Experienced_Hires/ApplyForAJob\n\nPersonal data collected will be used for recruitment purpose only. Applicants not contacted within 8 weeks may consider their applications unsuccessful.\n", "employment_types": ["Full Time"], "selling_points": [], "locations": ["Not Specified"], "categories": ["Building & Construction", "Building / Construction / QS", "Civil / Structural", "Others"], "post_time": "2022-01-12T08:53:23Z", "salary": {"currency": null, "max": null, "min": null, "period": "monthly", "term": null}, "salary_visible": false, "title_keywords": ["graduate engineer", "assistant engineer"], "responsibilities": ["software", "website", "recruitment", "career development", "personal data"], "requirements": {"degrees": ["certificate", "diploma"], "majors": ["civil engineering"], "languages": ["english", "chinese"], "language_level": ["good command"], "hard_skills": ["rhino", "bim modelling", "scheme", "dynamo", "bim", "autocad", "revit"], "soft_skills": [], "languages_combined": [{"language": "english", "language_level": ["good command"]}, {"language": "chinese", "language_level": ["good command"]}]}, "experience_required": {"duration": ["at least 2 years"], "field": ["development", "relevant experience"]}}, {"job_id": "100003009051386", "location_code": "hk", "company": "Esky Consultancy Limited", "job_title": "Project Manager /Quantity Surveyor / Site Supervisor  (Fitting Out)", "description": "Qualification\n\n\n\u00a0Higher Dip in Civil Engineering or equivalent\n\nRequirement\n\n\u00a02 years of hydraulic modelling with proficiency in InfoWater or equivalent\n\n\n\n\nWe offer 5-day work and competitive salary commensurate with qualifications and experience.\n\nPersonal information contained in applications received will be used for employment-related purposes and, in respect of the successful appointee only, also for business-related purposes.\u00a0Please send full resume, availability, present and expected salaries and daytime contact telephone number quoting reference code to:\u00a0Human Resources Department, Binnies Hong Kong Limited, 43/F, AIA Kowloon Tower, 100 How Ming Street, Kowloon, Hong Kong\u00a0or by clicking 'Apply Now'.", "employment_types": ["Full Time", "Permanent"], "selling_points": ["3 yrs exp in fitting out in commercial/ retail", "Project Manager/Quantity Surveyor /Site Supervisor", "Attractive salary package"], "locations": ["Central"], "categories": ["Building & Construction", "Architectural Services", "Building / Construction / QS", "Civil / Structural"], "post_time": "2022-01-15T13:30:20Z", "salary": {"currency": null, "max": null, "min": null, "period": "monthly", "term": null}, "salary_visible": false, "title_keywords": ["project manager", "site supervisor", "quantity surveyor"], "responsibilities": [], "requirements": {"degrees": ["dip"], "majors": ["civil engineering"], "languages": [], "language_level": [], "hard_skills": [], "soft_skills": [], "languages_combined": []}, "experience_required": {"duration": [], "field": []}}, {"job_id": "100003009046203", "location_code": "hk", "company": "Atkins China Ltd", "job_title": "Senior Geologist / Geologist", "description": "Following several recent successes in the region, we are expanding our energy business through targeted recruitment of capable and independent individuals with a background in energy. The candidate should have an out-going personality with drive and ambition to effectively promote and support the company\u2019s global energy business skills. The successful candidates will be based in our Hong Kong office but will be expected to travel.\nRelevant engineering related degree holder or equivalent\nPossesses or working towards professional membership of a recognised institution in\u00a0 the Civil/Mechanical/Industrial field\nAt least 8 years of post graduation experience and track record in delivering renewable and low carbon energy projects\nWith knowledge of technologies, including wind, solar photovoltaic, biomass, Combined Heat & Power (CHP) and geothermal in the East Asia region to complement the existing team\nFluency in both written and spoken English\nCandidates with less experience will be considered for the position of Renewable Energy Specialist.\n\nWe offer a competitive remuneration package commensurate with qualifications and experience to the right candidate including Global Profit Share scheme, additional fringe benefits of maternity/paternity leave and long-term career development opportunities.\n\nFor interested applicants, please click \"Apply Now\" to submit your online application.\n\nTo explore more job opportunities in Arup, please visit our website at http://www.arup.com/Careers/Experienced_Hires/ApplyForAJob\n\nPersonal data collected will be used for recruitment purpose only. Applicants not contacted within 8 weeks may consider their applications unsuccessful.", "employment_types": ["Full Time", "Permanent"], "selling_points": ["Chartered Geologist", "Open to consider Geologist to Principal Geologist", "International Design Engineering Consultant"], "locations": ["Tsim Sha Tsui"], "categories": ["Building & Construction", "Civil / Structural", "Engineering", "Engineering Project Management", "Others"], "post_time": "2022-01-13T09:56:12Z", "salary": {"currency": null, "max": null, "min": null, "period": "monthly", "term": null}, "salary_visible": false, "title_keywords": [], "responsibilities": ["personal data", "recruitment", "website", "career development"], "requirements": {"degrees": ["degree holder"], "majors": ["engineering"], "languages": ["english"], "language_level": ["fluency"], "hard_skills": ["scheme"], "soft_skills": ["independent", "capable"], "languages_combined": [{"language": "english", "language_level": ["fluency"]}]}, "experience_required": {"duration": ["at least 8 years"], "field": ["development"]}}, {"job_id": "100003009037116", "location_code": "hk", "company": "Wo Hing Construction Company Ltd", "job_title": "Engineer / Graduate Engineer", "description": "Degree in Building Engineering or equivalent;\nStrong interpersonal communication skills;\nResponsible, well-organized and self-motivated;\nFresh Graduate in 2022.\n\nWe offer competitive salary package and career development opportunity to the successful candidate. Interested parties may send your full resume, present and expected salary, available date and contact number by clicking \"Apply Now\"\n\nTo visit our website for more information:\u00a0www.ableeng.com.hk\n\n(As an Equal Opportunities Employer, Able is committed to eliminating discrimination in employment. The vacancy advertised is open to all applicants meeting the basic entry requirement irrespective of their disability, sex, marital status, pregnancy, age, family status, sexual orientation or race etc. Applicants not hearing from us within 6 months may consider their applications unsuccessful. Personal data collected will be used for recruitment related purposes only.)", "employment_types": ["Full Time"], "selling_points": [], "locations": ["Kowloon Bay"], "categories": ["Building & Construction", "Civil / Structural"], "post_time": "2022-01-11T01:45:31Z", "salary": {"currency": null, "max": null, "min": null, "period": "monthly", "term": null}, "salary_visible": false, "title_keywords": ["graduate engineer", "engineer"], "responsibilities": ["communication"], "requirements": {"degrees": ["degree", "fresh graduate"], "majors": ["engineering"], "languages": [], "language_level": [], "hard_skills": [], "soft_skills": ["communication skills", "self-motivated", "responsible", "well-organized", "interpersonal"], "languages_combined": []}, "experience_required": {"duration": [], "field": []}}, {"job_id": "100003009047051", "location_code": "hk", "company": "Yee Hop Engineering Company Limited", "job_title": "Building Services Coordinator", "description": "Diploma Holder or above in Building\u00a0 / Construction studies or equivalent\u00a0\nMin. 3 years in Interior Fitting-out or construction industry\nManage the project\u00a0\u00a0coordination, including progress, quality, cost and client relation\nStrong leadership management with good communication skills\nGood\u00a0PC knowledge of MS Office, Auto CAD", "employment_types": ["Full Time", "Permanent"], "selling_points": [], "locations": ["Not Specified"], "categories": ["Building & Construction", "Building / Construction / QS", "Civil / Structural", "Engineering", "Others"], "post_time": "2022-01-15T03:49:34Z", "salary": {"currency": null, "max": null, "min": null, "period": "monthly", "term": null}, "salary_visible": false, "title_keywords": ["coordinator"], "responsibilities": ["cost", "management", "quality", "communication", "coordination"], "requirements": {"degrees": ["diploma holder"], "majors": [], "languages": [], "language_level": [], "hard_skills": ["pc knowledge", "auto cad", "ms office"], "soft_skills": ["communication skills", "leadership", "coordination"], "languages_combined": []}, "experience_required": {"duration": [], "field": []}}, {"job_id": "100003009044656", "location_code": "hk", "company": "Chi Wo Contractors Limited", "job_title": "Site Engineers / Assistant Site Engineers", "description": "We are seeking a high-calibre staff to join our Ground Engineering department.\n\nResponsibilities:\n\nEngineering geological and geomorphological interpretation from both aerial photograph interpretation and field mapping;\nNumerical analysis of soil and rock slopes;\nPlanning and supervision of site investigations, including in situ and laboratory testing;\nLogging of trial pits, trial trenches and drillholes as well as rock faces; and\nDevelopment of ground model and technical report writing.\n\nJob Requirements:\n\nBachelor / Master Degree in Earth Science, Geology or related disciplines;\nChartered Geologist qualification is required, with minimum of 7 years of relevant experience;\nSolid experience in geohazard assessments in Hong Kong, including natural landslide hazard assessments and man-made slope stability investigations;\nAble to work independently and meet project deadline;\nResponsible, hardworking and self-motivated; and\nGood command of written and spoken English.\nCandidates with more experience can be considered as Principal Geologist\n\n\nFor interested parties, please submit your application with detailed resume, current and expected salary by clicking \"Apply Now\".\n\nApplications will be treated in confidence and only be used for recruitment purposes. Those not being invited for interview within 3 months may consider their applications unsuccessful.", "employment_types": ["Full Time", "Permanent"], "selling_points": [], "locations": ["Not Specified"], "categories": ["Building & Construction", "Building / Construction / QS", "Civil / Structural", "Engineering", "Others"], "post_time": "2022-01-13T06:56:58Z", "salary": {"currency": null, "max": null, "min": null, "period": "monthly", "term": null}, "salary_visible": false, "title_keywords": ["assistant"], "responsibilities": ["testing", "analysis", "report", "planning"], "requirements": {"degrees": ["bachelor", "master degree"], "majors": ["related disciplines", "science"], "languages": ["english"], "language_level": ["good command"], "hard_skills": [], "soft_skills": ["work independently", "hardworking", "self-motivated", "responsible"], "languages_combined": [{"language": "english", "language_level": ["good command"]}]}, "experience_required": {"duration": ["minimum of 7 years"], "field": ["relevant experience"]}}, {"job_id": "100003009049807", "location_code": "hk", "company": "Jibpool International Ltd", "job_title": "DRAFTSMAN (5 days work)", "description": "Requirements:\nHigher Diploma or above in Building Services / Electrical Engineering / Mechanical Engineering or equivalent discipline;\u00a0\nMinimum 3 years relevant experience in building services;\nGood IT skills, familiar with MS Office / AutoCAD / MS Project;\nInitiative and good communication skills;\nImmediate available is highly preferred.\nInterested parties please apply with detailed resume stating expected salary and date of availability to Mr. Henry Fu via email by clicking \"Apply Now\"\u00a0or fax to 2635 0611.\n[ Personal data collected will be used for recruitment-related purposes only. ]", "employment_types": ["Full Time", "Permanent"], "selling_points": ["5 days work", "Performance bonus", "Medical insurance"], "locations": ["Quarry Bay"], "categories": ["Building & Construction", "Civil / Structural", "Engineering", "Draftsman"], "post_time": "2022-01-14T09:15:23Z", "salary": {"currency": null, "max": null, "min": null, "period": "monthly", "term": null}, "salary_visible": false, "title_keywords": ["draftsman"], "responsibilities": ["communication"], "requirements": {"degrees": ["higher diploma or above"], "majors": ["building services", "electrical engineering", "mechanical engineering"], "languages": [], "language_level": [], "hard_skills": ["autocad", "ms office"], "soft_skills": ["communication skills", "initiative"], "languages_combined": []}, "experience_required": {"duration": ["minimum 3 years"], "field": ["building services", "relevant experience"]}}, {"job_id": "100003009035356", "location_code": "hk", "company": "Jacobs China Limited", "job_title": "Assistant Engineer (Audit Assistant)", "description": "Diploma /Higher Diploma / Degree in Building Studies or Building Engineering;\nAble to work independently with good problem-solving skills;\nFresh graduate are welcomed.\nInterested candidates please contact us by \"Apply Now\" for job information if you have any further enquiry.", "employment_types": ["Full Time", "Permanent"], "selling_points": ["Higher Certificate in Civil Engineering", "5 years of experience", "Undertake on site audit"], "locations": ["North Point"], "categories": ["Building & Construction", "Civil / Structural"], "post_time": "2022-01-10T06:55:26Z", "salary": {"currency": null, "max": null, "min": null, "period": "monthly", "term": null}, "salary_visible": false, "title_keywords": ["assistant engineer", "assistant"], "responsibilities": [], "requirements": {"degrees": ["diploma", "degree", "fresh graduate"], "majors": ["building studies", "engineering"], "languages": [], "language_level": [], "hard_skills": ["problem-solving skills"], "soft_skills": ["problem-solving skills", "work independently"], "languages_combined": []}, "experience_required": {"duration": [], "field": []}}, {"job_id": "100003009019374", "location_code": "hk", "company": "Mott MacDonald Hong Kong Limited", "job_title": "Technical Director (Civil)", "description": "We are one of the market leaders for premium architectural products in Hong Kong, seeking for right sales candidates to cope with the expanding business.\n\nRequirements\n\n\nF.5 or above;\n3 years relevant working experience or above;\nExcellent skills in AutoCad is a MUST;\nWorking experience in site progress inspection & monitoring or materials/cost sheet calculation is an advantage.\n\nInterested parties please send your full resume with your availability, current and expected salary by clicking\u00a0 \u201cAPPLY NOW\u201d.\n\n*Data collected will be used for recruitment purpose only*", "employment_types": ["Full Time", "Permanent"], "selling_points": ["Degree in civil engineering or related disciplines", "Around 18 years or more of relevant experience", "Good commercial awareness, 13th month salary"], "locations": ["Ngau Tau Kok"], "categories": ["Building & Construction", "Building / Construction / QS", "Civil / Structural", "Engineering", "Engineering Project Management"], "post_time": "2022-01-12T23:26:04Z", "salary": {"currency": null, "max": null, "min": null, "period": "monthly", "term": null}, "salary_visible": false, "title_keywords": ["director"], "responsibilities": ["cost", "monitoring", "inspection"], "requirements": {"degrees": [], "majors": [], "languages": [], "language_level": [], "hard_skills": ["autocad"], "soft_skills": [], "languages_combined": []}, "experience_required": {"duration": ["3 years"], "field": ["relevant working experience"]}}, {"job_id": "100003009045697", "location_code": "hk", "company": "J Pai Engineering Company Limited", "job_title": "\u9053\u8def\u6cb9\u6f06\u5b78\u5f92", "description": "Diploma or Higher Certificate in Civil or Structural Engineering from a Hong Kong Polytechnic/Polytechnic\u00a0University or Technical Institute, or equivalent;\nPost-qualification experience in structural analysis/design and/or computer drafting experience in preparation of structural drawings and/or structural maintenance aspects; and\nSecondment contract to Hong Kong Housing Authority.\n\nPlease send application with detailed resume, recent photo, familiarity with software programs, references, availability, present and expected salary by Email/mail to 15/F, 633 King\u2019s Road,\u00a0North Point, Hong Kong Website:\u00a0 www.daal.com.hk\n\n\n", "employment_types": ["Full Time"], "selling_points": [], "locations": ["Kwai Tsing Area"], "categories": ["Building & Construction", "Building / Construction / QS", "Civil / Structural", "Others"], "post_time": "2022-01-13T08:22:57Z", "salary": {"currency": null, "max": null, "min": null, "period": "hourly", "term": null}, "salary_visible": false, "title_keywords": [], "responsibilities": ["software", "maintenance", "analysis", "website", "design", "drawings"], "requirements": {"degrees": ["diploma", "higher certificate"], "majors": ["structural engineering"], "languages": [], "language_level": [], "hard_skills": ["analysis", "maintenance"], "soft_skills": ["detailed"], "languages_combined": []}, "experience_required": {"duration": [], "field": ["maintenance", "structural", "post-qualification", "design"]}}, {"job_id": "100003009045643", "location_code": "hk", "company": "\u6210\u8000(\u9999\u6e2f)\u5de5\u7a0b\u6709\u9650\u516c\u53f8", "job_title": "\u51b7\u96fb\u6c23\u5b78\u5f92", "description": "Our People & Places Solutions business \u2013 reinforces our drive to improve the lives of people everywhere and epitomizes the \"why\" of what we do \u2013 the tremendous positive impact and value our solutions bring to our communities and\u00a0society as a whole. From facilities delivering life-saving therapies and ensuring clean water to enabling the connection of people through all modes of transportation and providing access to technology \u2013 we're integrating a multitude of these solution elements to build the smart environments of tomorrow.\u00a0 \u00a0\n\nAt Jacobs, we\u2019re not just building structures, we\u2019re helping our clients innovate and grow by designing, engineering, and executing the construction of their various facilities that are changing our world.\n\nAssistant Engineer, Structural under Building section performs a variety of engineering work in the initial planning and design phase of a project. Specifications are prepared, and necessary subcontracts and requisitions are defined. The incumbent has basic knowledge of concepts, principles, and theories in the subject area or discipline. The person has a general understanding of the role of the team/department and industry practice and standards.\n\nJob Description :\n\n\n\nAssist Project Manager/RSE to undertake structural engineering works and also precast concrete production auditing work\nInclude precast concrete production auditing on site and precast factories\n\nQualifications:\u00a0\n\nHigher Certificate in Civil Engineering Construction / Building Studies or Approved equivalent.\nMinimum of five years\u2019 experience in building construction.\nPreferably one year experience in auditing a precast concrete production factory.\nApply through\u00a0Home - Jacobs Careers\u00a0with ref no.\u00a0Ref: ID: ASI0002M1 or Location \"Hong Kong\" or click 'Apply Now'.\u00a0\n\n\nJacobs. A world where you can.\u00a0\n\nFrom our inclusive employee networks, to our positive mental health champions \u2013 we\u2019re committed to driving a culture of caring where you can be you. Joining Jacobs not only connects you locally but globally - and together, our diverse perspectives and unique backgrounds power our collective strength. We collaborate and share! By supporting one another, we all succeed.\n\nWith safety and flexibility always top of mind, we\u2019ve gone beyond traditional ways of working so you have the support, means and space to maximise your potential. You\u2019ll uncover flexible working arrangements, benefits and opportunities to do good too \u2013 from participating in our global giving and volunteering program, to exploring new and inventive ways to help our clients make the world a better place. No matter what drives you, you\u2019ll discover how you can cultivate, nurture and achieve your goals \u2013 all at a single global company.\n\nStart your Jacobs career with a company that inspires and empowers you to deliver your best work so you can evolve, grow and succeed \u2013 today and into tomorrow.\u202f\u202f\u00a0\n\nPlease note: If you are being represented by a recruitment agency you will not be considered, to be considered you will need to apply directly to Jacobs.", "employment_types": ["Full Time"], "selling_points": [], "locations": ["Chai Wan"], "categories": ["Building & Construction", "Building / Construction / QS", "Civil / Structural", "Others"], "post_time": "2022-01-13T08:16:21Z", "salary": {"currency": null, "max": null, "min": null, "period": "monthly", "term": null}, "salary_visible": false, "title_keywords": [], "responsibilities": ["collaborate", "design", "specifications", "executing", "recruitment", "designing", "auditing", "planning"], "requirements": {"degrees": ["higher certificate"], "majors": ["building studies", "civil engineering"], "languages": [], "language_level": [], "hard_skills": ["clean", "no", "basic", "id", "make"], "soft_skills": ["flexible", "unique", "committed", "diverse", "positive"], "languages_combined": []}, "experience_required": {"duration": ["minimum of five years", "one year"], "field": ["construction"]}}, {"job_id": "100003009048547", "location_code": "hk", "company": "Kum Shing Group", "job_title": "Traffic / XP Coordinator", "description": "Job Description\n\nReporting to the Head of Transport, you will be responsible for providing technical leadership and project management for our multi-disciplinary infrastructure projects. You will thrive on technical challenge. You will embrace both developing solutions for unique conditions and in achieving cost-effective quality designs through efficient deployment of professional staff and software in the more commonplace or repetitive situations.\n\nPrimarily, you will be project manager in government infrastructure projects; you will nevertheless have sound experience of the whole life cycle of the projects, from feasibility study to design and construction, and operation and maintenance.\u00a0 Your primary focus will be on ensuring technical deliverables meet the client requirements and are produced on time and budget. In addition, you will assist develop client relationships, attend business related functions and actively participate in acquiring new work, as both participant and bid leader.\n\n\nAs a leader, you will demonstrate high technical standards and will have the ambition to be recognised for technical excellence within Mott MacDonald and among our client base. You will enjoy developing a strong team spirit among fellow professionals. Importantly, you will have a passion to help develop the skills and capabilities of colleagues, from graduate level up, as well as having a collaborative approach to multi-disciplinary design.\u00a0 This will be matched by good commercial awareness and a client-focused outward looking attitude.\n\nWhat You'll Need\n\n\nDegree in civil engineering or related disciplines\nExperience in Bridges design is preferred\u00a0\nChartered member of Hong Kong Institution of Engineers or equivalent with minimum of 18 years\u2019 post-chartered experience in infrastructure and other development in Hong Kong.\nA Registered Professional Engineer is preferred\nProactive and quality oriented, with a client-centric outlook, together with a high sense of accountability.\nA demonstrable track record of meeting exacting technical standards\nA team player with good communication, analytical and negotiation skills. Able to work with a range of project stakeholders, contractors and clients\nGood command of spoken and written English and ideally Cantonese\n\nWe offer competitive remuneration package including\u00a0top-up MPF plan\u00a0and\u00a0group medical insurance for dependents and 13th month salary.\u00a0\n\nInterested parties, please click 'Apply now' to submit your application with full resume including your current and expected salary, or send your full resume to\u00a0recruitment.MMHK @mottmac.com\u00a0\n\nTo explore more opportunities with us, please visit www.mottmac.com/careers.\u00a0\n\nAll personal data collected will be treated in strict confidence and be used for recruitment purpose only.\u00a0\n\nWe are an equal opportunity employer and value diversity at our company.\u00a0We do not discriminate, and take positive steps to create an inclusive culture.", "employment_types": ["Full Time", "Permanent"], "selling_points": ["Performance bonus, education subsidy, medical plan", "Excellent career path, friendly company culture", "Experience in road works and XPMS system"], "locations": ["To Kwa Wan"], "categories": ["Building & Construction", "Civil / Structural", "Engineering", "Others", "Transportation & Logistics", "Public Transportation"], "post_time": "2022-01-14T06:46:05Z", "salary": {"currency": null, "max": null, "min": null, "period": "monthly", "term": null}, "salary_visible": false, "title_keywords": ["coordinator"], "responsibilities": ["reporting", "cost", "software", "maintenance", "infrastructure", "quality", "developing", "design", "budget", "develop", "project management", "communication", "client base"], "requirements": {"degrees": ["degree"], "majors": ["related disciplines", "civil engineering"], "languages": ["cantonese", "english"], "language_level": ["good command"], "hard_skills": ["maintenance", "project management", "outlook", "deployment", "focus"], "soft_skills": ["efficient", "team spirit", "responsible", "focused", "accountability", "collaborative", "unique", "communication", "project management", "negotiation skills", "team player", "focus", "proactive", "leadership"], "languages_combined": [{"language": "cantonese", "language_level": ["good command"]}, {"language": "english", "language_level": ["good command"]}]}, "experience_required": {"duration": ["minimum of 18 years"], "field": ["maintenance", "development", "infrastructure", "design", "operation", "construction"]}}, {"job_id": "100003009046267", "location_code": "hk", "company": "Chelsea Consultancy Company Limited", "job_title": "Assistant Structural Engineer", "description": "\n\u8077\u8cac :\u8ca0\u8cac\u4fee\u88dc\u9053\u8def\u6a19\u8a18\u6cb9\u6f06\u5de5\u4f5c, \u5de5\u4f5c\u9700\u99d5\u99db, \u65bc\u8475\u6d8c\u53d6\u8eca\n\n\u8cc7\u6b77 :\u6c92\u6709\u5b78\u6b77\u8981\u6c42; \u826f\u597d\u7cb5\u8a9e; \u61c2\u8b80\u5beb\u4e2d\u6587; \u6301\u6709\u8f15\u578b\u8ca8\u8eca\u99d5\u99db\u57f7\u7167\n\n\u5f85\u9047 :\u6bcf\u65e5$700.00 - $750.00, \u4e0b\u53488\u6642\u81f3\u4e0a\u53486\u6642, \u6bcf\u9031\u5de5\u4f5c6\u5929,\u8f2a\u4f11, \u6bcf\u5929\u5de5\u4f5c 10 \u5c0f\u6642\n\n\u7533\u8acb\u9808\u77e5 :\u6c42\u8077\u8005\u53ef\u81f4\u96fb52868886\u8207\u7ae3\u67cf\u5de5\u7a0b\u6709\u9650\u516c\u53f8\u66fe\u5c0f\u59d0\u806f\u7d61\u3002\n\n", "employment_types": ["Full Time", "Permanent"], "selling_points": ["Friendly Culture/ Simple & Direct Communication", "5 Days/ 13 Months' Salary/ Near MTR Station", "New Building and A&A Works"], "locations": ["Tai Koo"], "categories": ["Building & Construction", "Civil / Structural"], "post_time": "2022-01-13T10:10:02Z", "salary": {"currency": null, "max": null, "min": null, "period": "monthly", "term": null}, "salary_visible": false, "title_keywords": ["engineer", "assistant"], "responsibilities": [], "requirements": {"degrees": [], "majors": [], "languages": [], "language_level": [], "hard_skills": [], "soft_skills": [], "languages_combined": []}, "experience_required": {"duration": [], "field": []}}, {"job_id": "100003009048628", "location_code": "hk", "company": "Allworth Consultants Limited", "job_title": "Building Surveyor / Senior Building Surveyor", "description": "\n\u8077\u8cac :\u4e00\u822c\u51b7\u96fb\u6c23\u5b78\u5f92\u5de5\u4f5c\n\n\u8cc7\u6b77 :\u6c92\u6709\u5b78\u6b77\u8981\u6c42; \u4e00\u822c\u7cb5\u8a9e; \u61c2\u8b80\u5beb\u4e2d\u6587; \u6301\u6709\u5efa\u9020\u696d\u5de5\u4eba\u8a3b\u518a\u8b49\n\n\u5f85\u9047 :\u6bcf\u6708$11,500, \u661f\u671f\u4e00\u81f3\u516d: \u4e0a\u53489\u6642\u81f3\u4e0b\u53486\u6642, \u6bcf\u9031\u5de5\u4f5c6\u5929\n\n\u7533\u8acb\u9808\u77e5 :\u6c42\u8077\u8005\u53ef\u81f4\u96fb25054854\u8207\u4f51\u8aa0\u5de5\u7a0b\u6709\u9650\u516c\u53f8\u83ab\u5c0f\u59d0\u806f\u7d61\u3002\n\n", "employment_types": ["Full Time"], "selling_points": ["ASD, BD, HKHA", "Building Surveyor", "HKIS"], "locations": ["Others"], "categories": ["Building & Construction", "Architectural Services", "Building / Construction / QS", "Civil / Structural"], "post_time": "2022-01-14T06:55:29Z", "salary": {"currency": null, "max": null, "min": null, "period": "monthly", "term": null}, "salary_visible": false, "title_keywords": ["surveyor"], "responsibilities": [], "requirements": {"degrees": [], "majors": [], "languages": [], "language_level": [], "hard_skills": [], "soft_skills": [], "languages_combined": []}, "experience_required": {"duration": [], "field": []}}, {"job_id": "100003009041136", "location_code": "hk", "company": "Lap Kai Engineering Company Limited", "job_title": "\u5730\u76e4\u7ba1\u5de5 (Site Foreman)", "description": "Responsibilities:\n\n\nDesign and prepare TTMs submission;\nManage of XP application system;\nCoordinate of XP application and temporary traffic arrangement;\nPlanning and monitoring of site works.\n\nRequirements - Qualification:\n\nForm 5 or above;\nMinimum 1-3 years of relevant working experience; preferably in road works and XPMS system;\nHolder of Valid green card;\nWith driving license (Class 1);\nProficiency in Microsoft Office, Chinese word processing and AutoCAD;\nGood command of both written and spoken English and Chinese.\n\nRequirements \u2013 Competences:\n\nGood interpersonal and communications skills.\n\nWe look forward to receiving your application with detailed resume stating\u00a0working experience,\u00a0academic and language qualifications, existing and EXPECTED SALARY\u00a0as well as\u00a0availability.\u00a0All applications will be kept strictly confidential.\n\nWe offer promising professional career and exposure\u00a0to right candidate, together with attractive remuneration package including\u00a0discretionary bonus, continuing education allowance, medical and dental coverage.\n\nPersonal Data collected will be used for recruitment-related purposes only.", "employment_types": ["Full Time"], "selling_points": [], "locations": ["Not Specified"], "categories": ["Building & Construction", "Building / Construction / QS", "Civil / Structural", "Engineering", "Others"], "post_time": "2022-01-12T23:26:12Z", "salary": {"currency": null, "max": null, "min": null, "period": "monthly", "term": null}, "salary_visible": false, "title_keywords": ["site foreman"], "responsibilities": ["monitoring", "application system", "design", "coordinate", "planning"], "requirements": {"degrees": ["form 5 or above"], "majors": [], "languages": ["english", "chinese"], "language_level": ["proficiency", "good command"], "hard_skills": ["microsoft office", "autocad", "chinese word processing", "green card"], "soft_skills": ["interpersonal", "detailed"], "languages_combined": [{"language": "english", "language_level": ["good command"]}, {"language": "chinese", "language_level": ["proficiency", "good command"]}]}, "experience_required": {"duration": ["minimum 1-3 years"], "field": ["relevant working experience"]}}]